{
  "type": "Feature",
  "properties": {
    "gn:admin1_code":"8.0",
    "gn:asciiname":"Kiwembo",
    "gn:country_code":"CD",
    "gn:dem":579,
    "gn:feature_class":"P",
    "gn:feature_code":"PPL",
    "gn:name":"Kiwembo",
    "gn:population":0,
    "gn:timezone":"Africa/Kinshasa",
    "iso:country":"CD",
    "wof:name":"Kiwembo",
    "wof:placetype":"locality"
},
  "geometry": {"coordinates":[15.2433,-5.40899],"type":"Point"}
}