{
  "type": "Feature",
  "properties": {
    "gn:admin1_code":"10.0",
    "gn:asciiname":"Iwe",
    "gn:country_code":"CD",
    "gn:dem":540,
    "gn:feature_class":"P",
    "gn:feature_code":"PPL",
    "gn:name":"Iwe",
    "gn:population":0,
    "gn:timezone":"Africa/Lubumbashi",
    "iso:country":"CD",
    "name:und_x_variant":[
        "Iwa",
        "Iwe"
    ],
    "wof:name":"Iwe",
    "wof:placetype":"locality"
},
  "geometry": {"coordinates":[25.83628,-3.94847],"type":"Point"}
}