{
  "type": "Feature",
  "properties": {
    "gn:admin1_code":"18.0",
    "gn:asciiname":"Mpala",
    "gn:country_code":"CD",
    "gn:dem":591,
    "gn:feature_class":"P",
    "gn:feature_code":"PPL",
    "gn:name":"Mpala",
    "gn:population":0,
    "gn:timezone":"Africa/Lubumbashi",
    "iso:country":"CD",
    "name:nld_x_preferred":[
        "Mpala"
    ],
    "wof:name":"Mpala",
    "wof:placetype":"locality"
},
  "geometry": {"coordinates":[20.9616,-6.48878],"type":"Point"}
}