{
  "type": "Feature",
  "properties": {
    "gn:admin1_code":"26.0",
    "gn:asciiname":"Boyawuku Deuxieme",
    "gn:country_code":"CD",
    "gn:dem":468,
    "gn:feature_class":"P",
    "gn:feature_code":"PPL",
    "gn:name":"Boyawuku Deuxi\u00e8me",
    "gn:population":0,
    "gn:timezone":"Africa/Kinshasa",
    "iso:country":"CD",
    "name:und_x_variant":[
        "Boyawuku Deuxi\u00e8me",
        "Boyawuku II"
    ],
    "wof:name":"Boyawuku Deuxieme",
    "wof:placetype":"locality"
},
  "geometry": {"coordinates":[20.51156,3.59054],"type":"Point"}
}