{
  "type": "Feature",
  "properties": {
    "gn:admin1_code":"27.0",
    "gn:asciiname":"Dikoti",
    "gn:country_code":"CD",
    "gn:dem":541,
    "gn:feature_class":"P",
    "gn:feature_code":"PPL",
    "gn:name":"Dikoti",
    "gn:population":0,
    "gn:timezone":"Africa/Lubumbashi",
    "iso:country":"CD",
    "name:und_x_variant":[
        "Dikati",
        "Dikoti"
    ],
    "wof:name":"Dikoti",
    "wof:placetype":"locality"
},
  "geometry": {"coordinates":[22.71667,-2.93333],"type":"Point"}
}