{
  "type": "Feature",
  "properties": {
    "gn:admin1_code":"18.0",
    "gn:asciiname":"Esanga-Djale",
    "gn:country_code":"CD",
    "gn:dem":473,
    "gn:feature_class":"P",
    "gn:feature_code":"PPL",
    "gn:name":"Esanga-Djale",
    "gn:population":0,
    "gn:timezone":"Africa/Lubumbashi",
    "iso:country":"CD",
    "name:und_x_variant":[
        "Esanga",
        "Esanga-Djale"
    ],
    "wof:name":"Esanga-Djale",
    "wof:placetype":"locality"
},
  "geometry": {"coordinates":[21.99808,-2.84368],"type":"Point"}
}