{
  "type": "Feature",
  "properties": {
    "gn:admin1_code":"14.0",
    "gn:asciiname":"Mumbombo",
    "gn:country_code":"CD",
    "gn:dem":1458,
    "gn:feature_class":"P",
    "gn:feature_code":"PPL",
    "gn:name":"Mumbombo",
    "gn:population":0,
    "gn:timezone":"Africa/Lubumbashi",
    "iso:country":"CD",
    "wof:name":"Mumbombo",
    "wof:placetype":"locality"
},
  "geometry": {"coordinates":[26.01667,-11.43333],"type":"Point"}
}