{
  "type": "Feature",
  "properties": {
    "gn:admin1_code":"8.0",
    "gn:asciiname":"Nianga",
    "gn:country_code":"CD",
    "gn:dem":576,
    "gn:feature_class":"P",
    "gn:feature_code":"PPL",
    "gn:name":"Nianga",
    "gn:population":0,
    "gn:timezone":"Africa/Kinshasa",
    "iso:country":"CD",
    "wof:name":"Nianga",
    "wof:placetype":"locality"
},
  "geometry": {"coordinates":[14.53464,-4.8963],"type":"Point"}
}