{
  "type": "Feature",
  "properties": {
    "gn:admin1_code":"8.0",
    "gn:asciiname":"Mfuatu",
    "gn:country_code":"CD",
    "gn:dem":544,
    "gn:feature_class":"P",
    "gn:feature_code":"PPL",
    "gn:name":"Mfuatu",
    "gn:population":0,
    "gn:timezone":"Africa/Kinshasa",
    "iso:country":"CD",
    "wof:name":"Mfuatu",
    "wof:placetype":"locality"
},
  "geometry": {"coordinates":[14.85215,-4.934],"type":"Point"}
}