{
  "type": "Feature",
  "properties": {
    "gn:admin1_code":"16.0",
    "gn:asciiname":"Tambuluka",
    "gn:country_code":"CD",
    "gn:dem":660,
    "gn:feature_class":"P",
    "gn:feature_code":"PPL",
    "gn:name":"Tambuluka",
    "gn:population":0,
    "gn:timezone":"Africa/Lubumbashi",
    "iso:country":"CD",
    "wof:name":"Tambuluka",
    "wof:placetype":"locality"
},
  "geometry": {"coordinates":[27.52036,3.9031],"type":"Point"}
}