{
  "type": "Feature",
  "properties": {
    "gn:admin1_code":"27.0",
    "gn:asciiname":"Ihambi",
    "gn:country_code":"CD",
    "gn:dem":581,
    "gn:feature_class":"P",
    "gn:feature_code":"PPL",
    "gn:name":"Ihambi",
    "gn:population":0,
    "gn:timezone":"Africa/Lubumbashi",
    "iso:country":"CD",
    "name:und_x_variant":[
        "Ehambi",
        "Ehampi",
        "Ihambi"
    ],
    "wof:name":"Ihambi",
    "wof:placetype":"locality"
},
  "geometry": {"coordinates":[23.82543,-3.24689],"type":"Point"}
}