{
  "type": "Feature",
  "properties": {
    "gn:admin1_code":"13.0",
    "gn:asciiname":"Kaningbi",
    "gn:country_code":"CD",
    "gn:dem":513,
    "gn:feature_class":"P",
    "gn:feature_code":"PPL",
    "gn:name":"Kaningbi",
    "gn:population":0,
    "gn:timezone":"Africa/Lubumbashi",
    "iso:country":"CD",
    "wof:name":"Kaningbi",
    "wof:placetype":"locality"
},
  "geometry": {"coordinates":[23.10677,4.13754],"type":"Point"}
}