{
  "type": "Feature",
  "properties": {
    "gn:admin1_code":"16.0",
    "gn:asciiname":"Ndavo",
    "gn:country_code":"CD",
    "gn:dem":878,
    "gn:feature_class":"P",
    "gn:feature_code":"PPL",
    "gn:name":"Ndavo",
    "gn:population":0,
    "gn:timezone":"Africa/Lubumbashi",
    "iso:country":"CD",
    "wof:name":"Ndavo",
    "wof:placetype":"locality"
},
  "geometry": {"coordinates":[29.55863,3.27588],"type":"Point"}
}