{
  "type": "Feature",
  "properties": {
    "gn:admin1_code":"29.0",
    "gn:asciiname":"Kakulu Maziba",
    "gn:country_code":"CD",
    "gn:dem":1021,
    "gn:feature_class":"P",
    "gn:feature_code":"PPL",
    "gn:name":"Kakulu Maziba",
    "gn:population":0,
    "gn:timezone":"Africa/Lubumbashi",
    "iso:country":"CD",
    "wof:name":"Kakulu Maziba",
    "wof:placetype":"locality"
},
  "geometry": {"coordinates":[27.92204000000001,-5.28017],"type":"Point"}
}