{
  "type": "Feature",
  "properties": {
    "gn:admin1_code":"21.0",
    "gn:asciiname":"Goye",
    "gn:country_code":"CD",
    "gn:dem":817,
    "gn:feature_class":"P",
    "gn:feature_code":"PPL",
    "gn:name":"Goye",
    "gn:population":0,
    "gn:timezone":"Africa/Lubumbashi",
    "iso:country":"CD",
    "wof:name":"Goye",
    "wof:placetype":"locality"
},
  "geometry": {"coordinates":[23.86394,-6.97416],"type":"Point"}
}