{
  "type": "Feature",
  "properties": {
    "gn:admin1_code":"16.0",
    "gn:asciiname":"Saki",
    "gn:country_code":"CD",
    "gn:dem":721,
    "gn:feature_class":"P",
    "gn:feature_code":"PPL",
    "gn:name":"Saki",
    "gn:population":0,
    "gn:timezone":"Africa/Lubumbashi",
    "iso:country":"CD",
    "name:ara_x_preferred":[
        "\u0633\u0627\u0643\u064a"
    ],
    "name:azb_x_preferred":[
        "\u0633\u0627\u06a9\u06cc"
    ],
    "name:bel_x_preferred":[
        "\u0421\u0430\u043a\u0456"
    ],
    "name:bre_x_preferred":[
        "Saki"
    ],
    "name:bul_x_preferred":[
        "\u0421\u0430\u043a\u0438"
    ],
    "name:deu_x_preferred":[
        "Saki"
    ],
    "name:epo_x_preferred":[
        "Saki"
    ],
    "name:fas_x_preferred":[
        "\u0633\u0627\u06a9\u06cc"
    ],
    "name:fin_x_preferred":[
        "Saki"
    ],
    "name:fra_x_preferred":[
        "Saki"
    ],
    "name:glv_x_preferred":[
        "Saki"
    ],
    "name:heb_x_preferred":[
        "\u05e1\u05d0\u05e7\u05d9"
    ],
    "name:ind_x_preferred":[
        "Saki"
    ],
    "name:ita_x_preferred":[
        "Saki"
    ],
    "name:jpn_x_preferred":[
        "\u30b5\u30ad"
    ],
    "name:lat_x_preferred":[
        "Saki"
    ],
    "name:lfn_x_preferred":[
        "Saki"
    ],
    "name:mal_x_preferred":[
        "\u0d38\u0d3e\u0d15\u0d3f"
    ],
    "name:nld_x_preferred":[
        "Saki"
    ],
    "name:pan_x_preferred":[
        "\u0a38\u0a3e\u0a15\u0a40"
    ],
    "name:pol_x_preferred":[
        "Saki"
    ],
    "name:por_x_preferred":[
        "Saki"
    ],
    "name:ron_x_preferred":[
        "Saki"
    ],
    "name:rus_x_preferred":[
        "\u0421\u0430\u043a\u0438"
    ],
    "name:slk_x_preferred":[
        "Saki"
    ],
    "name:swe_x_preferred":[
        "Saki"
    ],
    "name:tam_x_preferred":[
        "\u0b9a\u0bbe\u0b95\u0bbf"
    ],
    "name:ukr_x_preferred":[
        "\u0421\u0430\u043a\u0456"
    ],
    "name:zho_x_preferred":[
        "\u8d6b\u514b\u6258\u00b7\u4f11\u00b7\u8292\u7f57"
    ],
    "wof:name":"Saki",
    "wof:placetype":"locality"
},
  "geometry": {"coordinates":[27.42276,2.53375],"type":"Point"}
}