{
  "type": "Feature",
  "properties": {
    "gn:admin1_code":"16.0",
    "gn:asciiname":"Saki",
    "gn:country_code":"CD",
    "gn:dem":721,
    "gn:feature_class":"P",
    "gn:feature_code":"PPL",
    "gn:name":"Saki",
    "gn:population":0,
    "gn:timezone":"Africa/Lubumbashi",
    "iso:country":"CD",
    "wof:name":"Saki",
    "wof:placetype":"locality"
},
  "geometry": {"coordinates":[27.42276,2.53375],"type":"Point"}
}