{
  "type": "Feature",
  "properties": {
    "gn:admin1_code":"21.0",
    "gn:asciiname":"Tshimangala",
    "gn:country_code":"CD",
    "gn:dem":960,
    "gn:feature_class":"P",
    "gn:feature_code":"PPL",
    "gn:name":"Tshimangala",
    "gn:population":0,
    "gn:timezone":"Africa/Lubumbashi",
    "iso:country":"CD",
    "wof:name":"Tshimangala",
    "wof:placetype":"locality"
},
  "geometry": {"coordinates":[23.70475,-7.6342],"type":"Point"}
}