{
  "type": "Feature",
  "properties": {
    "gn:admin1_code":"17.0",
    "gn:asciiname":"Djarara",
    "gn:country_code":"CD",
    "gn:dem":1978,
    "gn:feature_class":"P",
    "gn:feature_code":"PPL",
    "gn:name":"Djarara",
    "gn:population":0,
    "gn:timezone":"Africa/Lubumbashi",
    "iso:country":"CD",
    "wof:name":"Djarara",
    "wof:placetype":"locality"
},
  "geometry": {"coordinates":[30.80949,2.10147],"type":"Point"}
}