{
  "type": "Feature",
  "properties": {
    "gn:admin1_code":"22.0",
    "gn:asciiname":"Mwene-Biji",
    "gn:country_code":"CD",
    "gn:dem":1030,
    "gn:feature_class":"P",
    "gn:feature_code":"PPL",
    "gn:name":"Mwene-Biji",
    "gn:population":0,
    "gn:timezone":"Africa/Lubumbashi",
    "iso:country":"CD",
    "name:und_x_variant":[
        "Mwin Mbij"
    ],
    "wof:name":"Mwene-Biji",
    "wof:placetype":"locality"
},
  "geometry": {"coordinates":[22.11225,-8.43509],"type":"Point"}
}