{
  "type": "Feature",
  "properties": {
    "gn:admin1_code":"21.0",
    "gn:asciiname":"Kaunda",
    "gn:country_code":"CD",
    "gn:dem":816,
    "gn:feature_class":"P",
    "gn:feature_code":"PPL",
    "gn:name":"Kaunda",
    "gn:population":0,
    "gn:timezone":"Africa/Lubumbashi",
    "iso:country":"CD",
    "name:deu_x_preferred":[
        "Kaunda"
    ],
    "name:und_x_variant":[
        "Kanda"
    ],
    "wof:name":"Kaunda",
    "wof:placetype":"locality"
},
  "geometry": {"coordinates":[24.16093,-6.32469],"type":"Point"}
}