{
  "type": "Feature",
  "properties": {
    "gn:admin1_code":"19.0",
    "gn:asciiname":"Nzofu-Baholo",
    "gn:country_code":"CD",
    "gn:dem":865,
    "gn:feature_class":"P",
    "gn:feature_code":"PPL",
    "gn:name":"Nzofu-Baholo",
    "gn:population":0,
    "gn:timezone":"Africa/Kinshasa",
    "iso:country":"CD",
    "wof:name":"Nzofu-Baholo",
    "wof:placetype":"locality"
},
  "geometry": {"coordinates":[18.13341,-6.36474],"type":"Point"}
}