{
  "type": "Feature",
  "properties": {
    "gn:admin1_code":"8.0",
    "gn:asciiname":"Mavuama",
    "gn:country_code":"CD",
    "gn:dem":207,
    "gn:feature_class":"P",
    "gn:feature_code":"PPL",
    "gn:name":"Mavuama",
    "gn:population":0,
    "gn:timezone":"Africa/Kinshasa",
    "iso:country":"CD",
    "name:und_x_variant":[
        "Mavuma",
        "Mavuama"
    ],
    "wof:name":"Mavuama",
    "wof:placetype":"locality"
},
  "geometry": {"coordinates":[12.98333,-5.08333],"type":"Point"}
}