{
  "type": "Feature",
  "properties": {
    "gn:admin1_code":"30.0",
    "gn:asciiname":"Bangwaze",
    "gn:country_code":"CD",
    "gn:dem":472,
    "gn:feature_class":"P",
    "gn:feature_code":"PPL",
    "gn:name":"Bangwaze",
    "gn:population":0,
    "gn:timezone":"Africa/Lubumbashi",
    "iso:country":"CD",
    "wof:name":"Bangwaze",
    "wof:placetype":"locality"
},
  "geometry": {"coordinates":[25.39929,1.89449],"type":"Point"}
}