{
  "type": "Feature",
  "properties": {
    "gn:admin1_code":"12.0",
    "gn:asciiname":"Bitobolo",
    "gn:country_code":"CD",
    "gn:dem":817,
    "gn:feature_class":"P",
    "gn:feature_code":"PPL",
    "gn:name":"Bitobolo",
    "gn:population":0,
    "gn:timezone":"Africa/Lubumbashi",
    "iso:country":"CD",
    "wof:name":"Bitobolo",
    "wof:placetype":"locality"
},
  "geometry": {"coordinates":[29.10639,-3.95222],"type":"Point"}
}