{
  "type": "Feature",
  "properties": {
    "gn:admin1_code":"18.0",
    "gn:asciiname":"Ngome",
    "gn:country_code":"CD",
    "gn:dem":551,
    "gn:feature_class":"P",
    "gn:feature_code":"PPL",
    "gn:name":"Ngome",
    "gn:population":0,
    "gn:timezone":"Africa/Lubumbashi",
    "iso:country":"CD",
    "name:ceb_x_preferred":[
        "Ngome"
    ],
    "name:swe_x_preferred":[
        "Ngome"
    ],
    "wof:name":"Ngome",
    "wof:placetype":"locality"
},
  "geometry": {"coordinates":[21.39819,-5.23106],"type":"Point"}
}