{
  "type": "Feature",
  "properties": {
    "gn:admin1_code":"23.0",
    "gn:asciiname":"Ngufulu",
    "gn:country_code":"CD",
    "gn:dem":804,
    "gn:feature_class":"P",
    "gn:feature_code":"PPL",
    "gn:name":"Ngufulu",
    "gn:population":0,
    "gn:timezone":"Africa/Lubumbashi",
    "iso:country":"CD",
    "wof:name":"Ngufulu",
    "wof:placetype":"locality"
},
  "geometry": {"coordinates":[22.92101,-6.08651],"type":"Point"}
}