{
  "type": "Feature",
  "properties": {
    "gn:admin1_code":"21.0",
    "gn:asciiname":"Keta",
    "gn:country_code":"CD",
    "gn:dem":909,
    "gn:feature_class":"P",
    "gn:feature_code":"PPL",
    "gn:name":"Keta",
    "gn:population":0,
    "gn:timezone":"Africa/Lubumbashi",
    "iso:country":"CD",
    "name:cat_x_preferred":[
        "Keta"
    ],
    "name:ceb_x_preferred":[
        "Keta"
    ],
    "name:deu_x_preferred":[
        "Keta"
    ],
    "name:ewe_x_preferred":[
        "Keta"
    ],
    "name:fra_x_preferred":[
        "Keta"
    ],
    "name:ind_x_preferred":[
        "Keta"
    ],
    "name:lit_x_preferred":[
        "Keta"
    ],
    "name:pol_x_preferred":[
        "Keta"
    ],
    "name:swe_x_preferred":[
        "Keta"
    ],
    "name:urd_x_preferred":[
        "\u06a9\u06cc\u0679\u0627"
    ],
    "wof:name":"Keta",
    "wof:placetype":"locality"
},
  "geometry": {"coordinates":[23.73275,-7.39508],"type":"Point"}
}