{
  "type": "Feature",
  "properties": {
    "gn:admin1_code":"19.0",
    "gn:asciiname":"Ka-Keti",
    "gn:country_code":"CD",
    "gn:dem":1029,
    "gn:feature_class":"P",
    "gn:feature_code":"PPL",
    "gn:name":"Ka-Keti",
    "gn:population":0,
    "gn:timezone":"Africa/Kinshasa",
    "iso:country":"CD",
    "wof:name":"Ka-Keti",
    "wof:placetype":"locality"
},
  "geometry": {"coordinates":[18.81364,-7.16998],"type":"Point"}
}