{
  "type": "Feature",
  "properties": {
    "gn:admin1_code":"22.0",
    "gn:asciiname":"Sambembe Premiere",
    "gn:country_code":"CD",
    "gn:dem":1024,
    "gn:feature_class":"P",
    "gn:feature_code":"PPL",
    "gn:name":"Sambembe Premi\u00e8re",
    "gn:population":0,
    "gn:timezone":"Africa/Lubumbashi",
    "iso:country":"CD",
    "wof:name":"Sambembe Premiere",
    "wof:placetype":"locality"
},
  "geometry": {"coordinates":[22.81936,-10.64472],"type":"Point"}
}