{
  "type": "Feature",
  "properties": {
    "gn:admin1_code":"23.0",
    "gn:asciiname":"Kaluendu",
    "gn:country_code":"CD",
    "gn:dem":824,
    "gn:feature_class":"P",
    "gn:feature_code":"PPL",
    "gn:name":"Kaluendu",
    "gn:population":0,
    "gn:timezone":"Africa/Lubumbashi",
    "iso:country":"CD",
    "name:und_x_variant":[
        "Kaluenda"
    ],
    "wof:name":"Kaluendu",
    "wof:placetype":"locality"
},
  "geometry": {"coordinates":[21.93812,-7.14939],"type":"Point"}
}