{
  "type": "Feature",
  "properties": {
    "gn:admin1_code":"20.0",
    "gn:asciiname":"Bwanzono",
    "gn:country_code":"CD",
    "gn:dem":344,
    "gn:feature_class":"P",
    "gn:feature_code":"PPL",
    "gn:name":"Bwanzono",
    "gn:population":0,
    "gn:timezone":"Africa/Kinshasa",
    "iso:country":"CD",
    "wof:name":"Bwanzono",
    "wof:placetype":"locality"
},
  "geometry": {"coordinates":[17.88663,-3.80452],"type":"Point"}
}