{
  "type": "Feature",
  "properties": {
    "gn:admin1_code":"22.0",
    "gn:asciiname":"Mwene-Itondo",
    "gn:country_code":"CD",
    "gn:dem":1023,
    "gn:feature_class":"P",
    "gn:feature_code":"PPL",
    "gn:name":"Mwene-Itondo",
    "gn:population":0,
    "gn:timezone":"Africa/Lubumbashi",
    "iso:country":"CD",
    "wof:name":"Mwene-Itondo",
    "wof:placetype":"locality"
},
  "geometry": {"coordinates":[23.55093,-8.66388],"type":"Point"}
}