{
  "type": "Feature",
  "properties": {
    "gn:admin1_code":"25.0",
    "gn:asciiname":"Longole",
    "gn:country_code":"CD",
    "gn:dem":404,
    "gn:feature_class":"P",
    "gn:feature_code":"PPL",
    "gn:name":"Longole",
    "gn:population":0,
    "gn:timezone":"Africa/Kinshasa",
    "iso:country":"CD",
    "name:und_x_variant":[
        "Sungole",
        "Longole"
    ],
    "wof:name":"Longole",
    "wof:placetype":"locality"
},
  "geometry": {"coordinates":[21.28666,1.41121],"type":"Point"}
}