{
  "type": "Feature",
  "properties": {
    "gn:admin1_code":"23.0",
    "gn:asciiname":"Kafundanga",
    "gn:country_code":"CD",
    "gn:dem":814,
    "gn:feature_class":"P",
    "gn:feature_code":"PPL",
    "gn:name":"Kafundanga",
    "gn:population":0,
    "gn:timezone":"Africa/Lubumbashi",
    "iso:country":"CD",
    "wof:name":"Kafundanga",
    "wof:placetype":"locality"
},
  "geometry": {"coordinates":[23.02448,-6.37861],"type":"Point"}
}