{
  "type": "Feature",
  "properties": {
    "gn:admin1_code":"22.0",
    "gn:asciiname":"Mupamba",
    "gn:country_code":"CD",
    "gn:dem":935,
    "gn:feature_class":"P",
    "gn:feature_code":"PPL",
    "gn:name":"Mupamba",
    "gn:population":0,
    "gn:timezone":"Africa/Lubumbashi",
    "iso:country":"CD",
    "wof:name":"Mupamba",
    "wof:placetype":"locality"
},
  "geometry": {"coordinates":[22.77557,-9.64413],"type":"Point"}
}