{
  "type": "Feature",
  "properties": {
    "gn:admin1_code":"17.0",
    "gn:asciiname":"Kambutso",
    "gn:country_code":"CD",
    "gn:dem":1625,
    "gn:feature_class":"P",
    "gn:feature_code":"PPL",
    "gn:name":"Kambutso",
    "gn:population":0,
    "gn:timezone":"Africa/Lubumbashi",
    "iso:country":"CD",
    "wof:name":"Kambutso",
    "wof:placetype":"locality"
},
  "geometry": {"coordinates":[30.31667,1.48333],"type":"Point"}
}