{
  "type": "Feature",
  "properties": {
    "gn:admin1_code":"19.0",
    "gn:asciiname":"Mukalukiya",
    "gn:country_code":"CD",
    "gn:dem":990,
    "gn:feature_class":"P",
    "gn:feature_code":"PPL",
    "gn:name":"Mukalukiya",
    "gn:population":0,
    "gn:timezone":"Africa/Kinshasa",
    "iso:country":"CD",
    "wof:name":"Mukalukiya",
    "wof:placetype":"locality"
},
  "geometry": {"coordinates":[19.29843,-7.40341],"type":"Point"}
}