{
  "type": "Feature",
  "properties": {
    "gn:admin1_code":"29.0",
    "gn:asciiname":"Benze",
    "gn:country_code":"CD",
    "gn:dem":792,
    "gn:feature_class":"P",
    "gn:feature_code":"PPL",
    "gn:name":"Benze",
    "gn:population":0,
    "gn:timezone":"Africa/Lubumbashi",
    "iso:country":"CD",
    "wof:name":"Benze",
    "wof:placetype":"locality"
},
  "geometry": {"coordinates":[28.24455,-5.99168],"type":"Point"}
}