{
  "type": "Feature",
  "properties": {
    "gn:admin1_code":"26.0",
    "gn:asciiname":"Baya",
    "gn:country_code":"CD",
    "gn:dem":464,
    "gn:feature_class":"P",
    "gn:feature_code":"PPL",
    "gn:name":"Baya",
    "gn:population":0,
    "gn:timezone":"Africa/Kinshasa",
    "iso:country":"CD",
    "wof:name":"Baya",
    "wof:placetype":"locality"
},
  "geometry": {"coordinates":[19.72444,4.94087],"type":"Point"}
}