{
  "type": "Feature",
  "properties": {
    "gn:admin1_code":"15.0",
    "gn:asciiname":"Kapundwe",
    "gn:country_code":"CD",
    "gn:dem":1043,
    "gn:feature_class":"P",
    "gn:feature_code":"PPL",
    "gn:name":"Kapundwe",
    "gn:population":0,
    "gn:timezone":"Africa/Lubumbashi",
    "iso:country":"CD",
    "wof:name":"Kapundwe",
    "wof:placetype":"locality"
},
  "geometry": {"coordinates":[25.45,-8.45],"type":"Point"}
}