{
  "type": "Feature",
  "properties": {
    "gn:admin1_code":"27.0",
    "gn:asciiname":"Bafeko",
    "gn:country_code":"CD",
    "gn:dem":506,
    "gn:feature_class":"P",
    "gn:feature_code":"PPL",
    "gn:name":"Bafeko",
    "gn:population":0,
    "gn:timezone":"Africa/Lubumbashi",
    "iso:country":"CD",
    "wof:name":"Bafeko",
    "wof:placetype":"locality"
},
  "geometry": {"coordinates":[24.13333,-2.08333],"type":"Point"}
}