{
  "type": "Feature",
  "properties": {
    "gn:admin1_code":"22.0",
    "gn:asciiname":"Mangenda",
    "gn:country_code":"CD",
    "gn:dem":1215,
    "gn:feature_class":"P",
    "gn:feature_code":"PPL",
    "gn:name":"Mangenda",
    "gn:population":0,
    "gn:timezone":"Africa/Lubumbashi",
    "iso:country":"CD",
    "wof:name":"Mangenda",
    "wof:placetype":"locality"
},
  "geometry": {"coordinates":[23.84741,-10.46006],"type":"Point"}
}