{
  "type": "Feature",
  "properties": {
    "gn:admin1_code":"19.0",
    "gn:asciiname":"Maziamu",
    "gn:country_code":"CD",
    "gn:dem":840,
    "gn:feature_class":"P",
    "gn:feature_code":"PPL",
    "gn:name":"Maziamu",
    "gn:population":0,
    "gn:timezone":"Africa/Kinshasa",
    "iso:country":"CD",
    "name:und_x_variant":[
        "Maziamo",
        "Maziamu"
    ],
    "wof:name":"Maziamu",
    "wof:placetype":"locality"
},
  "geometry": {"coordinates":[18.35791,-6.23175],"type":"Point"}
}