{
  "type": "Feature",
  "properties": {
    "gn:admin1_code":"15.0",
    "gn:asciiname":"Mwitombwe",
    "gn:country_code":"CD",
    "gn:dem":1083,
    "gn:feature_class":"P",
    "gn:feature_code":"PPL",
    "gn:name":"Mwitombwe",
    "gn:population":0,
    "gn:timezone":"Africa/Lubumbashi",
    "iso:country":"CD",
    "name:und_x_variant":[
        "Mwitobwe",
        "Mwitombwe"
    ],
    "wof:name":"Mwitombwe",
    "wof:placetype":"locality"
},
  "geometry": {"coordinates":[25.11944,-8.66111],"type":"Point"}
}