{
  "type": "Feature",
  "properties": {
    "gn:admin1_code":"18.0",
    "gn:asciiname":"Tshimabele",
    "gn:country_code":"CD",
    "gn:dem":653,
    "gn:feature_class":"P",
    "gn:feature_code":"PPL",
    "gn:name":"Tshimabele",
    "gn:population":0,
    "gn:timezone":"Africa/Lubumbashi",
    "iso:country":"CD",
    "wof:name":"Tshimabele",
    "wof:placetype":"locality"
},
  "geometry": {"coordinates":[21.20718,-6.56854],"type":"Point"}
}