{
  "type": "Feature",
  "properties": {
    "gn:admin1_code":"21.0",
    "gn:asciiname":"Kasengu",
    "gn:country_code":"CD",
    "gn:dem":603,
    "gn:feature_class":"P",
    "gn:feature_code":"PPL",
    "gn:name":"Kasengu",
    "gn:population":0,
    "gn:timezone":"Africa/Lubumbashi",
    "iso:country":"CD",
    "wof:name":"Kasengu",
    "wof:placetype":"locality"
},
  "geometry": {"coordinates":[25.90084,-6.10682],"type":"Point"}
}