{
  "type": "Feature",
  "properties": {
    "gn:admin1_code":"18.0",
    "gn:asciiname":"Kayembe-Kumbi",
    "gn:country_code":"CD",
    "gn:dem":671,
    "gn:feature_class":"P",
    "gn:feature_code":"PPL",
    "gn:name":"Kayembe-Kumbi",
    "gn:population":0,
    "gn:timezone":"Africa/Lubumbashi",
    "iso:country":"CD",
    "name:und_x_variant":[
        "Kayembe",
        "Kayembe-Kumbi"
    ],
    "wof:name":"Kayembe-Kumbi",
    "wof:placetype":"locality"
},
  "geometry": {"coordinates":[21.03705,-6.39799],"type":"Point"}
}