{
  "type": "Feature",
  "properties": {
    "gn:admin1_code":"14.0",
    "gn:asciiname":"Mubambi",
    "gn:country_code":"CD",
    "gn:dem":1525,
    "gn:feature_class":"P",
    "gn:feature_code":"PPL",
    "gn:name":"Mubambi",
    "gn:population":0,
    "gn:timezone":"Africa/Lubumbashi",
    "iso:country":"CD",
    "wof:name":"Mubambi",
    "wof:placetype":"locality"
},
  "geometry": {"coordinates":[26.28178,-11.09619],"type":"Point"}
}