{
  "type": "Feature",
  "properties": {
    "gn:admin1_code":"31.0",
    "gn:asciiname":"Boleko",
    "gn:country_code":"CD",
    "gn:dem":350,
    "gn:feature_class":"P",
    "gn:feature_code":"PPL",
    "gn:name":"Boleko",
    "gn:population":0,
    "gn:timezone":"Africa/Kinshasa",
    "iso:country":"CD",
    "wof:name":"Boleko",
    "wof:placetype":"locality"
},
  "geometry": {"coordinates":[20.04841,-1.53876],"type":"Point"}
}