{
  "type": "Feature",
  "properties": {
    "gn:admin1_code":"23.0",
    "gn:asciiname":"Mazala",
    "gn:country_code":"CD",
    "gn:dem":812,
    "gn:feature_class":"P",
    "gn:feature_code":"PPL",
    "gn:name":"Mazala",
    "gn:population":0,
    "gn:timezone":"Africa/Lubumbashi",
    "iso:country":"CD",
    "wof:name":"Mazala",
    "wof:placetype":"locality"
},
  "geometry": {"coordinates":[21.82507,-7.21287],"type":"Point"}
}