{
  "type": "Feature",
  "properties": {
    "gn:admin1_code":"23.0",
    "gn:asciiname":"Tshipepeie",
    "gn:country_code":"CD",
    "gn:dem":597,
    "gn:feature_class":"P",
    "gn:feature_code":"PPL",
    "gn:name":"Tshipepeie",
    "gn:population":0,
    "gn:timezone":"Africa/Lubumbashi",
    "iso:country":"CD",
    "wof:name":"Tshipepeie",
    "wof:placetype":"locality"
},
  "geometry": {"coordinates":[21.8856,-5.06997],"type":"Point"}
}