{
  "type": "Feature",
  "properties": {
    "gn:admin1_code":"30.0",
    "gn:asciiname":"Bangwade",
    "gn:country_code":"CD",
    "gn:dem":441,
    "gn:feature_class":"P",
    "gn:feature_code":"PPL",
    "gn:name":"Bangwade",
    "gn:population":0,
    "gn:timezone":"Africa/Lubumbashi",
    "iso:country":"CD",
    "name:und_x_variant":[
        "Bangwande",
        "Bangwade"
    ],
    "wof:name":"Bangwade",
    "wof:placetype":"locality"
},
  "geometry": {"coordinates":[25.24025,0.99648],"type":"Point"}
}