{
  "type": "Feature",
  "properties": {
    "gn:admin1_code":"15.0",
    "gn:asciiname":"Busaba",
    "gn:country_code":"CD",
    "gn:dem":954,
    "gn:feature_class":"P",
    "gn:feature_code":"PPL",
    "gn:name":"Busaba",
    "gn:population":0,
    "gn:timezone":"Africa/Lubumbashi",
    "iso:country":"CD",
    "wof:name":"Busaba",
    "wof:placetype":"locality"
},
  "geometry": {"coordinates":[25.89676,-6.58675],"type":"Point"}
}