{
  "type": "Feature",
  "properties": {
    "gn:admin1_code":"24.0",
    "gn:asciiname":"Sandy-Beach",
    "gn:country_code":"CD",
    "gn:dem":296,
    "gn:feature_class":"P",
    "gn:feature_code":"PPL",
    "gn:name":"Sandy-Beach",
    "gn:population":0,
    "gn:timezone":"Africa/Kinshasa",
    "iso:country":"CD",
    "wof:name":"Sandy-Beach",
    "wof:placetype":"locality"
},
  "geometry": {"coordinates":[16.23936,-2.51918],"type":"Point"}
}