{
  "type": "Feature",
  "properties": {
    "gn:admin1_code":"4.0",
    "gn:asciiname":"Kalongi",
    "gn:country_code":"CD",
    "gn:dem":769,
    "gn:feature_class":"P",
    "gn:feature_code":"PPL",
    "gn:name":"Kalongi",
    "gn:population":0,
    "gn:timezone":"Africa/Lubumbashi",
    "iso:country":"CD",
    "name:und_x_variant":[
        "Kalondji",
        "Kalonji",
        "Kalongi"
    ],
    "wof:name":"Kalongi",
    "wof:placetype":"locality"
},
  "geometry": {"coordinates":[23.3732,-6.24524],"type":"Point"}
}