{
  "type": "Feature",
  "properties": {
    "gn:admin1_code":"22.0",
    "gn:asciiname":"Bwamuyembe",
    "gn:country_code":"CD",
    "gn:dem":948,
    "gn:feature_class":"P",
    "gn:feature_code":"PPL",
    "gn:name":"Bwamuyembe",
    "gn:population":0,
    "gn:timezone":"Africa/Lubumbashi",
    "iso:country":"CD",
    "wof:name":"Bwamuyembe",
    "wof:placetype":"locality"
},
  "geometry": {"coordinates":[23.14848,-8.16024],"type":"Point"}
}