{
  "type": "Feature",
  "properties": {
    "gn:admin1_code":"15.0",
    "gn:asciiname":"Kaloko",
    "gn:country_code":"CD",
    "gn:dem":1018,
    "gn:feature_class":"P",
    "gn:feature_code":"PPL",
    "gn:name":"Kaloko",
    "gn:population":0,
    "gn:timezone":"Africa/Lubumbashi",
    "iso:country":"CD",
    "name:ceb_x_preferred":[
        "Kaloko"
    ],
    "name:swe_x_preferred":[
        "Kaloko"
    ],
    "wof:name":"Kaloko",
    "wof:placetype":"locality"
},
  "geometry": {"coordinates":[25.79549,-6.79811],"type":"Point"}
}