{
  "type": "Feature",
  "properties": {
    "gn:admin1_code":"23.0",
    "gn:asciiname":"Kongolo-Kakese",
    "gn:country_code":"CD",
    "gn:dem":810,
    "gn:feature_class":"P",
    "gn:feature_code":"PPL",
    "gn:name":"Kongolo-Kakese",
    "gn:population":0,
    "gn:timezone":"Africa/Lubumbashi",
    "iso:country":"CD",
    "name:und_x_variant":[
        "Kongolo-Kasese"
    ],
    "wof:name":"Kongolo-Kakese",
    "wof:placetype":"locality"
},
  "geometry": {"coordinates":[21.836,-6.88128],"type":"Point"}
}