{
  "type": "Feature",
  "properties": {
    "gn:admin1_code":"17.0",
    "gn:asciiname":"Tiko",
    "gn:country_code":"CD",
    "gn:dem":918,
    "gn:feature_class":"P",
    "gn:feature_code":"PPL",
    "gn:name":"Tiko",
    "gn:population":0,
    "gn:timezone":"Africa/Lubumbashi",
    "iso:country":"CD",
    "name:ceb_x_preferred":[
        "Tiko"
    ],
    "name:dan_x_preferred":[
        "Tiko"
    ],
    "name:fra_x_preferred":[
        "Tiko"
    ],
    "name:ind_x_preferred":[
        "Tiko"
    ],
    "name:ita_x_preferred":[
        "Tiko"
    ],
    "name:msa_x_preferred":[
        "Tiko"
    ],
    "name:nld_x_preferred":[
        "Tiko"
    ],
    "name:pol_x_preferred":[
        "Tiko"
    ],
    "name:por_x_preferred":[
        "Tiko"
    ],
    "name:ron_x_preferred":[
        "Tiko"
    ],
    "name:slv_x_preferred":[
        "Tiko"
    ],
    "name:swe_x_preferred":[
        "Tiko"
    ],
    "wof:name":"Tiko",
    "wof:placetype":"locality"
},
  "geometry": {"coordinates":[28.48333,1.83333],"type":"Point"}
}