{
  "type": "Feature",
  "properties": {
    "gn:admin1_code":"23.0",
    "gn:asciiname":"Bena-Kalombo",
    "gn:country_code":"CD",
    "gn:dem":658,
    "gn:feature_class":"P",
    "gn:feature_code":"PPL",
    "gn:name":"Bena-Kalombo",
    "gn:population":0,
    "gn:timezone":"Africa/Lubumbashi",
    "iso:country":"CD",
    "wof:name":"Bena-Kalombo",
    "wof:placetype":"locality"
},
  "geometry": {"coordinates":[22.86845,-5.01957],"type":"Point"}
}