{
  "type": "Feature",
  "properties": {
    "gn:admin1_code":"15.0",
    "gn:asciiname":"Lukunga-Bukunga",
    "gn:country_code":"CD",
    "gn:dem":789,
    "gn:feature_class":"P",
    "gn:feature_code":"PPL",
    "gn:name":"Lukunga-Bukunga",
    "gn:population":0,
    "gn:timezone":"Africa/Lubumbashi",
    "iso:country":"CD",
    "name:und_x_variant":[
        "Bakunga",
        "Bukunga",
        "Lukunga-Bukunga"
    ],
    "wof:name":"Lukunga-Bukunga",
    "wof:placetype":"locality"
},
  "geometry": {"coordinates":[25.75139,-7.68233],"type":"Point"}
}