{
  "type": "Feature",
  "properties": {
    "gn:admin1_code":"20.0",
    "gn:asciiname":"Nianga-Kikuka",
    "gn:country_code":"CD",
    "gn:dem":647,
    "gn:feature_class":"P",
    "gn:feature_code":"PPL",
    "gn:name":"Nianga-Kikuka",
    "gn:population":0,
    "gn:timezone":"Africa/Kinshasa",
    "iso:country":"CD",
    "wof:name":"Nianga-Kikuka",
    "wof:placetype":"locality"
},
  "geometry": {"coordinates":[19.87481,-5.77921],"type":"Point"}
}