{
  "type": "Feature",
  "properties": {
    "gn:admin1_code":"14.0",
    "gn:asciiname":"Luishia",
    "gn:country_code":"CD",
    "gn:dem":1256,
    "gn:feature_class":"P",
    "gn:feature_code":"PPL",
    "gn:name":"Luishia",
    "gn:population":0,
    "gn:timezone":"Africa/Lubumbashi",
    "iso:country":"CD",
    "wof:name":"Luishia",
    "wof:placetype":"locality"
},
  "geometry": {"coordinates":[27.01797,-11.17303],"type":"Point"}
}