{
  "type": "Feature",
  "properties": {
    "gn:admin1_code":"20.0",
    "gn:asciiname":"Kiniboyama",
    "gn:country_code":"CD",
    "gn:dem":452,
    "gn:feature_class":"P",
    "gn:feature_code":"PPL",
    "gn:name":"Kiniboyama",
    "gn:population":0,
    "gn:timezone":"Africa/Kinshasa",
    "iso:country":"CD",
    "wof:name":"Kiniboyama",
    "wof:placetype":"locality"
},
  "geometry": {"coordinates":[17.87017,-4.56051],"type":"Point"}
}