{
  "type": "Feature",
  "properties": {
    "gn:admin1_code":"22.0",
    "gn:asciiname":"Sakatota",
    "gn:country_code":"CD",
    "gn:dem":1036,
    "gn:feature_class":"P",
    "gn:feature_code":"PPL",
    "gn:name":"Sakatota",
    "gn:population":0,
    "gn:timezone":"Africa/Lubumbashi",
    "iso:country":"CD",
    "wof:name":"Sakatota",
    "wof:placetype":"locality"
},
  "geometry": {"coordinates":[22.42714,-10.51928],"type":"Point"}
}