{
  "type": "Feature",
  "properties": {
    "gn:admin1_code":"24.0",
    "gn:asciiname":"Boondo",
    "gn:country_code":"CD",
    "gn:dem":380,
    "gn:feature_class":"P",
    "gn:feature_code":"PPL",
    "gn:name":"Boondo",
    "gn:population":0,
    "gn:timezone":"Africa/Kinshasa",
    "iso:country":"CD",
    "wof:name":"Boondo",
    "wof:placetype":"locality"
},
  "geometry": {"coordinates":[20.23333,-2.28333],"type":"Point"}
}