{
  "type": "Feature",
  "properties": {
    "gn:admin1_code":"6.0",
    "gn:asciiname":"Lopes",
    "gn:country_code":"CD",
    "gn:dem":304,
    "gn:feature_class":"P",
    "gn:feature_code":"PPL",
    "gn:name":"Lopes",
    "gn:population":0,
    "gn:timezone":"Africa/Kinshasa",
    "iso:country":"CD",
    "wof:name":"Lopes",
    "wof:placetype":"locality"
},
  "geometry": {"coordinates":[15.5457,-4.07911],"type":"Point"}
}