{
  "type": "Feature",
  "properties": {
    "gn:admin1_code":"19.0",
    "gn:asciiname":"Shakabuma",
    "gn:country_code":"CD",
    "gn:dem":1060,
    "gn:feature_class":"P",
    "gn:feature_code":"PPL",
    "gn:name":"Shakabuma",
    "gn:population":0,
    "gn:timezone":"Africa/Kinshasa",
    "iso:country":"CD",
    "name:und_x_variant":[
        "Shakatema"
    ],
    "wof:name":"Shakabuma",
    "wof:placetype":"locality"
},
  "geometry": {"coordinates":[18.87293,-7.50423],"type":"Point"}
}