{
  "type": "Feature",
  "properties": {
    "gn:admin1_code":"22.0",
    "gn:asciiname":"Kayeye",
    "gn:country_code":"CD",
    "gn:dem":877,
    "gn:feature_class":"P",
    "gn:feature_code":"PPL",
    "gn:name":"Kayeye",
    "gn:population":0,
    "gn:timezone":"Africa/Lubumbashi",
    "iso:country":"CD",
    "wof:name":"Kayeye",
    "wof:placetype":"locality"
},
  "geometry": {"coordinates":[24.74995,-10.06114],"type":"Point"}
}