{
  "type": "Feature",
  "properties": {
    "gn:admin1_code":"20.0",
    "gn:asciiname":"Yasa",
    "gn:country_code":"CD",
    "gn:dem":425,
    "gn:feature_class":"P",
    "gn:feature_code":"PPL",
    "gn:name":"Yasa",
    "gn:population":0,
    "gn:timezone":"Africa/Kinshasa",
    "iso:country":"CD",
    "name:fra_x_preferred":[
        "Yasa"
    ],
    "name:hun_x_preferred":[
        "Jasza"
    ],
    "name:tha_x_preferred":[
        "\u0e1e\u0e23\u0e30\u0e22\u0e2a\u0e40\u0e16\u0e23\u0e30"
    ],
    "wof:name":"Yasa",
    "wof:placetype":"locality"
},
  "geometry": {"coordinates":[17.97405,-4.50788],"type":"Point"}
}