{
  "type": "Feature",
  "properties": {
    "gn:admin1_code":"19.0",
    "gn:asciiname":"Gulu",
    "gn:country_code":"CD",
    "gn:dem":877,
    "gn:feature_class":"P",
    "gn:feature_code":"PPL",
    "gn:name":"Gulu",
    "gn:population":0,
    "gn:timezone":"Africa/Kinshasa",
    "iso:country":"CD",
    "wof:name":"Gulu",
    "wof:placetype":"locality"
},
  "geometry": {"coordinates":[17.88723,-6.25838],"type":"Point"}
}