{
  "type": "Feature",
  "properties": {
    "gn:admin1_code":"13.0",
    "gn:asciiname":"Gambavuru",
    "gn:country_code":"CD",
    "gn:dem":434,
    "gn:feature_class":"P",
    "gn:feature_code":"PPL",
    "gn:name":"Gambavuru",
    "gn:population":0,
    "gn:timezone":"Africa/Lubumbashi",
    "iso:country":"CD",
    "wof:name":"Gambavuru",
    "wof:placetype":"locality"
},
  "geometry": {"coordinates":[24.03225,3.42508],"type":"Point"}
}