{
  "type": "Feature",
  "properties": {
    "gn:admin1_code":"15.0",
    "gn:asciiname":"Kamalondo",
    "gn:country_code":"CD",
    "gn:dem":1017,
    "gn:feature_class":"P",
    "gn:feature_code":"PPL",
    "gn:name":"Kamalondo",
    "gn:population":0,
    "gn:timezone":"Africa/Lubumbashi",
    "iso:country":"CD",
    "name:fra_x_preferred":[
        "Kamalondo"
    ],
    "wof:name":"Kamalondo",
    "wof:placetype":"locality"
},
  "geometry": {"coordinates":[23.8537,-8.02544],"type":"Point"}
}