{
  "type": "Feature",
  "properties": {
    "gn:admin1_code":"19.0",
    "gn:asciiname":"Mulopo",
    "gn:country_code":"CD",
    "gn:dem":721,
    "gn:feature_class":"P",
    "gn:feature_code":"PPL",
    "gn:name":"Mulopo",
    "gn:population":0,
    "gn:timezone":"Africa/Kinshasa",
    "iso:country":"CD",
    "name:und_x_variant":[
        "Mulopo-Pelende"
    ],
    "wof:name":"Mulopo",
    "wof:placetype":"locality"
},
  "geometry": {"coordinates":[17.31862000000001,-6.45342],"type":"Point"}
}