{
  "type": "Feature",
  "properties": {
    "gn:admin1_code":"23.0",
    "gn:asciiname":"Mukenge",
    "gn:country_code":"CD",
    "gn:dem":646,
    "gn:feature_class":"P",
    "gn:feature_code":"PPL",
    "gn:name":"Mukenge",
    "gn:population":0,
    "gn:timezone":"Africa/Lubumbashi",
    "iso:country":"CD",
    "wof:name":"Mukenge",
    "wof:placetype":"locality"
},
  "geometry": {"coordinates":[22.91961,-5.64965],"type":"Point"}
}