{
  "type": "Feature",
  "properties": {
    "gn:admin1_code":"17.0",
    "gn:asciiname":"Kanga",
    "gn:country_code":"CD",
    "gn:dem":1057,
    "gn:feature_class":"P",
    "gn:feature_code":"PPL",
    "gn:name":"Kanga",
    "gn:population":0,
    "gn:timezone":"Africa/Lubumbashi",
    "iso:country":"CD",
    "wof:name":"Kanga",
    "wof:placetype":"locality"
},
  "geometry": {"coordinates":[30.38294,2.89269],"type":"Point"}
}