{
  "type": "Feature",
  "properties": {
    "gn:admin1_code":"12.0",
    "gn:asciiname":"Mikamba",
    "gn:country_code":"CD",
    "gn:dem":905,
    "gn:feature_class":"P",
    "gn:feature_code":"PPL",
    "gn:name":"Mikamba",
    "gn:population":0,
    "gn:timezone":"Africa/Lubumbashi",
    "iso:country":"CD",
    "wof:name":"Mikamba",
    "wof:placetype":"locality"
},
  "geometry": {"coordinates":[29.15694,-3.15417],"type":"Point"}
}