{
  "type": "Feature",
  "properties": {
    "gn:admin1_code":"8.0",
    "gn:asciiname":"Kimbaoka",
    "gn:country_code":"CD",
    "gn:dem":632,
    "gn:feature_class":"P",
    "gn:feature_code":"PPL",
    "gn:name":"Kimbaoka",
    "gn:population":0,
    "gn:timezone":"Africa/Brazzaville",
    "iso:country":"CD",
    "wof:name":"Kimbaoka",
    "wof:placetype":"locality"
},
  "geometry": {"coordinates":[14.19653,-4.3904],"type":"Point"}
}