{
  "type": "Feature",
  "properties": {
    "gn:admin1_code":"20.0",
    "gn:asciiname":"Misale",
    "gn:country_code":"CD",
    "gn:dem":314,
    "gn:feature_class":"P",
    "gn:feature_code":"PPL",
    "gn:name":"Misale",
    "gn:population":0,
    "gn:timezone":"Africa/Kinshasa",
    "iso:country":"CD",
    "wof:name":"Misale",
    "wof:placetype":"locality"
},
  "geometry": {"coordinates":[17.62516,-3.51228],"type":"Point"}
}