{
  "type": "Feature",
  "properties": {
    "gn:admin1_code":"22.0",
    "gn:asciiname":"Ijidij",
    "gn:country_code":"CD",
    "gn:dem":1095,
    "gn:feature_class":"P",
    "gn:feature_code":"PPL",
    "gn:name":"Ijidij",
    "gn:population":0,
    "gn:timezone":"Africa/Lubumbashi",
    "iso:country":"CD",
    "wof:name":"Ijidij",
    "wof:placetype":"locality"
},
  "geometry": {"coordinates":[23.23656,-8.7727],"type":"Point"}
}