{
  "type": "Feature",
  "properties": {
    "gn:admin1_code":"30.0",
    "gn:asciiname":"Yokoko",
    "gn:country_code":"CD",
    "gn:dem":443,
    "gn:feature_class":"P",
    "gn:feature_code":"PPL",
    "gn:name":"Yokoko",
    "gn:population":0,
    "gn:timezone":"Africa/Lubumbashi",
    "iso:country":"CD",
    "name:und_x_variant":[
        "Yotoko",
        "Yokoko"
    ],
    "wof:name":"Yokoko",
    "wof:placetype":"locality"
},
  "geometry": {"coordinates":[24.10375,-0.36454],"type":"Point"}
}