{
  "type": "Feature",
  "properties": {
    "gn:admin1_code":"8.0",
    "gn:asciiname":"Kondo-Kibunzi",
    "gn:country_code":"CD",
    "gn:dem":211,
    "gn:feature_class":"P",
    "gn:feature_code":"PPL",
    "gn:name":"Kondo-Kibunzi",
    "gn:population":0,
    "gn:timezone":"Africa/Kinshasa",
    "iso:country":"CD",
    "wof:name":"Kondo-Kibunzi",
    "wof:placetype":"locality"
},
  "geometry": {"coordinates":[13.76225,-5.22311],"type":"Point"}
}