{
  "type": "Feature",
  "properties": {
    "gn:admin1_code":"23.0",
    "gn:asciiname":"Tshinyama",
    "gn:country_code":"CD",
    "gn:dem":637,
    "gn:feature_class":"P",
    "gn:feature_code":"PPL",
    "gn:name":"Tshinyama",
    "gn:population":0,
    "gn:timezone":"Africa/Lubumbashi",
    "iso:country":"CD",
    "wof:name":"Tshinyama",
    "wof:placetype":"locality"
},
  "geometry": {"coordinates":[22.40052,-5.70098],"type":"Point"}
}