{
  "type": "Feature",
  "properties": {
    "gn:admin1_code":"28.0",
    "gn:asciiname":"Busu-Sanimi",
    "gn:country_code":"CD",
    "gn:dem":378,
    "gn:feature_class":"P",
    "gn:feature_code":"PPL",
    "gn:name":"Busu-Sanimi",
    "gn:population":0,
    "gn:timezone":"Africa/Kinshasa",
    "iso:country":"CD",
    "wof:name":"Busu-Sanimi",
    "wof:placetype":"locality"
},
  "geometry": {"coordinates":[18.99631,2.49993],"type":"Point"}
}