{
  "type": "Feature",
  "properties": {
    "gn:admin1_code":"10.0",
    "gn:asciiname":"Lubinga",
    "gn:country_code":"CD",
    "gn:dem":693,
    "gn:feature_class":"P",
    "gn:feature_code":"PPL",
    "gn:name":"Lubinga",
    "gn:population":0,
    "gn:timezone":"Africa/Lubumbashi",
    "iso:country":"CD",
    "name:und_x_variant":[
        "Lubingo"
    ],
    "wof:name":"Lubinga",
    "wof:placetype":"locality"
},
  "geometry": {"coordinates":[27.59072,-4.93331],"type":"Point"}
}