{
  "type": "Feature",
  "properties": {
    "gn:admin1_code":"12.0",
    "gn:asciiname":"Kibumba",
    "gn:country_code":"CD",
    "gn:dem":1387,
    "gn:feature_class":"P",
    "gn:feature_code":"PPL",
    "gn:name":"Kibumba",
    "gn:population":0,
    "gn:timezone":"Africa/Lubumbashi",
    "iso:country":"CD",
    "wof:name":"Kibumba",
    "wof:placetype":"locality"
},
  "geometry": {"coordinates":[29.02861,-3.70111],"type":"Point"}
}