{
  "type": "Feature",
  "properties": {
    "gn:admin1_code":"14.0",
    "gn:asciiname":"Puta",
    "gn:country_code":"CD",
    "gn:dem":1598,
    "gn:feature_class":"P",
    "gn:feature_code":"PPL",
    "gn:name":"Puta",
    "gn:population":0,
    "gn:timezone":"Africa/Lubumbashi",
    "iso:country":"CD",
    "wof:name":"Puta",
    "wof:placetype":"locality"
},
  "geometry": {"coordinates":[29.26571,-8.2898],"type":"Point"}
}