{
  "type": "Feature",
  "properties": {
    "gn:admin1_code":"22.0",
    "gn:asciiname":"Ngulungu",
    "gn:country_code":"CD",
    "gn:dem":1029,
    "gn:feature_class":"P",
    "gn:feature_code":"PPL",
    "gn:name":"Ngulungu",
    "gn:population":0,
    "gn:timezone":"Africa/Lubumbashi",
    "iso:country":"CD",
    "wof:name":"Ngulungu",
    "wof:placetype":"locality"
},
  "geometry": {"coordinates":[23.94908,-9.50255],"type":"Point"}
}