{
  "type": "Feature",
  "properties": {
    "gn:admin1_code":"24.0",
    "gn:asciiname":"Pembe",
    "gn:country_code":"CD",
    "gn:dem":345,
    "gn:feature_class":"P",
    "gn:feature_code":"PPL",
    "gn:name":"Pembe",
    "gn:population":0,
    "gn:timezone":"Africa/Kinshasa",
    "iso:country":"CD",
    "wof:name":"Pembe",
    "wof:placetype":"locality"
},
  "geometry": {"coordinates":[19.13333,-0.86667],"type":"Point"}
}