{
  "type": "Feature",
  "properties": {
    "gn:admin1_code":"11.0",
    "gn:asciiname":"Nyabondo",
    "gn:country_code":"CD",
    "gn:dem":1237,
    "gn:feature_class":"P",
    "gn:feature_code":"PPL",
    "gn:name":"Nyabondo",
    "gn:population":0,
    "gn:timezone":"Africa/Lubumbashi",
    "iso:country":"CD",
    "name:und_x_variant":[
        "Nyabiondo"
    ],
    "wof:name":"Nyabondo",
    "wof:placetype":"locality"
},
  "geometry": {"coordinates":[28.73109,-1.31237],"type":"Point"}
}