{
  "type": "Feature",
  "properties": {
    "gn:admin1_code":"14.0",
    "gn:asciiname":"Kikangi",
    "gn:country_code":"CD",
    "gn:dem":1729,
    "gn:feature_class":"P",
    "gn:feature_code":"PPL",
    "gn:name":"Kikangi",
    "gn:population":0,
    "gn:timezone":"Africa/Lubumbashi",
    "iso:country":"CD",
    "wof:name":"Kikangi",
    "wof:placetype":"locality"
},
  "geometry": {"coordinates":[29.46114,-7.96332],"type":"Point"}
}