{
  "type": "Feature",
  "properties": {
    "gn:admin1_code":"18.0",
    "gn:asciiname":"Tshimbundu",
    "gn:country_code":"CD",
    "gn:dem":740,
    "gn:feature_class":"P",
    "gn:feature_code":"PPL",
    "gn:name":"Tshimbundu",
    "gn:population":0,
    "gn:timezone":"Africa/Lubumbashi",
    "iso:country":"CD",
    "wof:name":"Tshimbundu",
    "wof:placetype":"locality"
},
  "geometry": {"coordinates":[21.5477,-6.59333],"type":"Point"}
}