{
  "type": "Feature",
  "properties": {
    "gn:admin1_code":"22.0",
    "gn:asciiname":"Satshihuta",
    "gn:country_code":"CD",
    "gn:dem":924,
    "gn:feature_class":"P",
    "gn:feature_code":"PPL",
    "gn:name":"Satshihuta",
    "gn:population":0,
    "gn:timezone":"Africa/Lubumbashi",
    "iso:country":"CD",
    "wof:name":"Satshihuta",
    "wof:placetype":"locality"
},
  "geometry": {"coordinates":[23.35893,-9.65994],"type":"Point"}
}