{
  "type": "Feature",
  "properties": {
    "gn:admin1_code":"28.0",
    "gn:asciiname":"Yanga-Libenge",
    "gn:country_code":"CD",
    "gn:dem":437,
    "gn:feature_class":"P",
    "gn:feature_code":"PPL",
    "gn:name":"Yanga-Libenge",
    "gn:population":0,
    "gn:timezone":"Africa/Kinshasa",
    "iso:country":"CD",
    "name:und_x_variant":[
        "Libenge",
        "Yanga-Libenge"
    ],
    "wof:name":"Yanga-Libenge",
    "wof:placetype":"locality"
},
  "geometry": {"coordinates":[20.0514,2.53283],"type":"Point"}
}