{
  "type": "Feature",
  "properties": {
    "gn:admin1_code":"28.0",
    "gn:asciiname":"Mokiri",
    "gn:country_code":"CD",
    "gn:dem":364,
    "gn:feature_class":"P",
    "gn:feature_code":"PPL",
    "gn:name":"Mokiri",
    "gn:population":0,
    "gn:timezone":"Africa/Kinshasa",
    "iso:country":"CD",
    "wof:name":"Mokiri",
    "wof:placetype":"locality"
},
  "geometry": {"coordinates":[20.14551,2.68857],"type":"Point"}
}