{
  "type": "Feature",
  "properties": {
    "gn:admin1_code":"14.0",
    "gn:asciiname":"Jaboka",
    "gn:country_code":"CD",
    "gn:dem":1165,
    "gn:feature_class":"P",
    "gn:feature_code":"PPL",
    "gn:name":"Jaboka",
    "gn:population":0,
    "gn:timezone":"Africa/Lubumbashi",
    "iso:country":"CD",
    "wof:name":"Jaboka",
    "wof:placetype":"locality"
},
  "geometry": {"coordinates":[26.8376,-11.22596],"type":"Point"}
}