{
  "type": "Feature",
  "properties": {
    "gn:admin1_code":"14.0",
    "gn:asciiname":"Kiea",
    "gn:country_code":"CD",
    "gn:dem":999,
    "gn:feature_class":"P",
    "gn:feature_code":"PPL",
    "gn:name":"Kiea",
    "gn:population":0,
    "gn:timezone":"Africa/Lubumbashi",
    "iso:country":"CD",
    "wof:name":"Kiea",
    "wof:placetype":"locality"
},
  "geometry": {"coordinates":[27.16849,-10.64835],"type":"Point"}
}