{
  "type": "Feature",
  "properties": {
    "gn:admin1_code":"14.0",
    "gn:asciiname":"Kiula",
    "gn:country_code":"CD",
    "gn:dem":1386,
    "gn:feature_class":"P",
    "gn:feature_code":"PPL",
    "gn:name":"Kiula",
    "gn:population":0,
    "gn:timezone":"Africa/Lubumbashi",
    "iso:country":"CD",
    "wof:name":"Kiula",
    "wof:placetype":"locality"
},
  "geometry": {"coordinates":[27.92241,-9.4905],"type":"Point"}
}