{
  "type": "Feature",
  "properties": {
    "gn:admin1_code":"23.0",
    "gn:asciiname":"Mulolo",
    "gn:country_code":"CD",
    "gn:dem":810,
    "gn:feature_class":"P",
    "gn:feature_code":"PPL",
    "gn:name":"Mulolo",
    "gn:population":0,
    "gn:timezone":"Africa/Lubumbashi",
    "iso:country":"CD",
    "wof:name":"Mulolo",
    "wof:placetype":"locality"
},
  "geometry": {"coordinates":[22.32757,-6.62228],"type":"Point"}
}