{
  "type": "Feature",
  "properties": {
    "gn:admin1_code":"20.0",
    "gn:asciiname":"Nsalwo",
    "gn:country_code":"CD",
    "gn:dem":400,
    "gn:feature_class":"P",
    "gn:feature_code":"PPL",
    "gn:name":"Nsalwo",
    "gn:population":0,
    "gn:timezone":"Africa/Kinshasa",
    "iso:country":"CD",
    "wof:name":"Nsalwo",
    "wof:placetype":"locality"
},
  "geometry": {"coordinates":[18.3434,-3.98833],"type":"Point"}
}