{
  "type": "Feature",
  "properties": {
    "gn:admin1_code":"20.0",
    "gn:asciiname":"Bitshambele",
    "gn:country_code":"CD",
    "gn:dem":745,
    "gn:feature_class":"P",
    "gn:feature_code":"PPL",
    "gn:name":"Bitshambele",
    "gn:population":0,
    "gn:timezone":"Africa/Kinshasa",
    "iso:country":"CD",
    "wof:name":"Bitshambele",
    "wof:placetype":"locality"
},
  "geometry": {"coordinates":[19.27913,-5.45685],"type":"Point"}
}