{
  "type": "Feature",
  "properties": {
    "gn:admin1_code":"2.0",
    "gn:asciiname":"Bakungu",
    "gn:country_code":"CD",
    "gn:dem":338,
    "gn:feature_class":"P",
    "gn:feature_code":"PPL",
    "gn:name":"Bakungu",
    "gn:population":0,
    "gn:timezone":"Africa/Kinshasa",
    "iso:country":"CD",
    "wof:name":"Bakungu",
    "wof:placetype":"locality"
},
  "geometry": {"coordinates":[19.69505,1.24729],"type":"Point"}
}