{
  "type": "Feature",
  "properties": {
    "gn:admin1_code":"22.0",
    "gn:asciiname":"Kanza",
    "gn:country_code":"CD",
    "gn:dem":1135,
    "gn:feature_class":"P",
    "gn:feature_code":"PPL",
    "gn:name":"Kanza",
    "gn:population":0,
    "gn:timezone":"Africa/Lubumbashi",
    "iso:country":"CD",
    "wof:name":"Kanza",
    "wof:placetype":"locality"
},
  "geometry": {"coordinates":[24.1018,-10.18592],"type":"Point"}
}