{
  "type": "Feature",
  "properties": {
    "gn:admin1_code":"16.0",
    "gn:asciiname":"Biku",
    "gn:country_code":"CD",
    "gn:dem":773,
    "gn:feature_class":"P",
    "gn:feature_code":"PPL",
    "gn:name":"Biku",
    "gn:population":0,
    "gn:timezone":"Africa/Lubumbashi",
    "iso:country":"CD",
    "name:ara_x_preferred":[
        "\u0628\u064a\u06a9\u0648"
    ],
    "name:fas_x_preferred":[
        "\u0628\u06cc\u06a9\u0648"
    ],
    "wof:name":"Biku",
    "wof:placetype":"locality"
},
  "geometry": {"coordinates":[27.64035,2.31714],"type":"Point"}
}