{
  "type": "Feature",
  "properties": {
    "gn:admin1_code":"8.0",
    "gn:asciiname":"Kiniambi",
    "gn:country_code":"CD",
    "gn:dem":582,
    "gn:feature_class":"P",
    "gn:feature_code":"PPL",
    "gn:name":"Kiniambi",
    "gn:population":0,
    "gn:timezone":"Africa/Kinshasa",
    "iso:country":"CD",
    "wof:name":"Kiniambi",
    "wof:placetype":"locality"
},
  "geometry": {"coordinates":[15.08883,-4.76727],"type":"Point"}
}