{
  "type": "Feature",
  "properties": {
    "gn:admin1_code":"23.0",
    "gn:asciiname":"Sabo",
    "gn:country_code":"CD",
    "gn:dem":944,
    "gn:feature_class":"P",
    "gn:feature_code":"PPL",
    "gn:name":"Sabo",
    "gn:population":0,
    "gn:timezone":"Africa/Lubumbashi",
    "iso:country":"CD",
    "name:ceb_x_preferred":[
        "Sabo"
    ],
    "name:ces_x_preferred":[
        "Sabo"
    ],
    "name:deu_x_preferred":[
        "Sabo"
    ],
    "name:fra_x_preferred":[
        "Sabo"
    ],
    "name:ita_x_preferred":[
        "Sabo"
    ],
    "name:pol_x_preferred":[
        "Sabo"
    ],
    "name:por_x_preferred":[
        "Sabo"
    ],
    "name:ron_x_preferred":[
        "Sabo"
    ],
    "name:slk_x_preferred":[
        "Sabo"
    ],
    "name:spa_x_preferred":[
        "Sabo"
    ],
    "name:sqi_x_preferred":[
        "Sabo"
    ],
    "name:swe_x_preferred":[
        "Sabo"
    ],
    "name:ukr_x_preferred":[
        "\u0421\u0430\u0431\u043e"
    ],
    "name:uzb_x_preferred":[
        "Sabo"
    ],
    "wof:name":"Sabo",
    "wof:placetype":"locality"
},
  "geometry": {"coordinates":[22.41275,-7.48502],"type":"Point"}
}