{
  "type": "Feature",
  "properties": {
    "gn:admin1_code":"22.0",
    "gn:asciiname":"Samayo",
    "gn:country_code":"CD",
    "gn:dem":1222,
    "gn:feature_class":"P",
    "gn:feature_code":"PPL",
    "gn:name":"Samayo",
    "gn:population":0,
    "gn:timezone":"Africa/Lubumbashi",
    "iso:country":"CD",
    "wof:name":"Samayo",
    "wof:placetype":"locality"
},
  "geometry": {"coordinates":[23.60693,-10.90586],"type":"Point"}
}