{
  "type": "Feature",
  "properties": {
    "gn:admin1_code":"18.0",
    "gn:asciiname":"Kankundji",
    "gn:country_code":"CD",
    "gn:dem":726,
    "gn:feature_class":"P",
    "gn:feature_code":"PPL",
    "gn:name":"Kankundji",
    "gn:population":0,
    "gn:timezone":"Africa/Lubumbashi",
    "iso:country":"CD",
    "wof:name":"Kankundji",
    "wof:placetype":"locality"
},
  "geometry": {"coordinates":[20.03772,-6.5803],"type":"Point"}
}