{
  "type": "Feature",
  "properties": {
    "gn:admin1_code":"31.0",
    "gn:asciiname":"Nongo",
    "gn:country_code":"CD",
    "gn:dem":485,
    "gn:feature_class":"P",
    "gn:feature_code":"PPL",
    "gn:name":"Nongo",
    "gn:population":0,
    "gn:timezone":"Africa/Kinshasa",
    "iso:country":"CD",
    "wof:name":"Nongo",
    "wof:placetype":"locality"
},
  "geometry": {"coordinates":[23.98441,-1.41028],"type":"Point"}
}