{
  "type": "Feature",
  "properties": {
    "gn:admin1_code":"29.0",
    "gn:asciiname":"Luala",
    "gn:country_code":"CD",
    "gn:dem":714,
    "gn:feature_class":"P",
    "gn:feature_code":"PPL",
    "gn:name":"Luala",
    "gn:population":0,
    "gn:timezone":"Africa/Lubumbashi",
    "iso:country":"CD",
    "name:und_x_variant":[
        "Lula",
        "Luala"
    ],
    "wof:name":"Luala",
    "wof:placetype":"locality"
},
  "geometry": {"coordinates":[27.45916,-6.47545],"type":"Point"}
}