{
  "type": "Feature",
  "properties": {
    "gn:admin1_code":"13.0",
    "gn:asciiname":"Sikima",
    "gn:country_code":"CD",
    "gn:dem":659,
    "gn:feature_class":"P",
    "gn:feature_code":"PPL",
    "gn:name":"Sikima",
    "gn:population":0,
    "gn:timezone":"Africa/Lubumbashi",
    "iso:country":"CD",
    "wof:name":"Sikima",
    "wof:placetype":"locality"
},
  "geometry": {"coordinates":[26.87098,3.77669],"type":"Point"}
}