{
  "type": "Feature",
  "properties": {
    "gn:admin1_code":"8.0",
    "gn:asciiname":"Bulanda Mambu",
    "gn:country_code":"CD",
    "gn:dem":598,
    "gn:feature_class":"P",
    "gn:feature_code":"PPL",
    "gn:name":"Bulanda Mambu",
    "gn:population":0,
    "gn:timezone":"Africa/Kinshasa",
    "iso:country":"CD",
    "wof:name":"Bulanda Mambu",
    "wof:placetype":"locality"
},
  "geometry": {"coordinates":[14.08333,-4.43798],"type":"Point"}
}