{
  "type": "Feature",
  "properties": {
    "gn:admin1_code":"24.0",
    "gn:asciiname":"Tikolemba",
    "gn:country_code":"CD",
    "gn:dem":328,
    "gn:feature_class":"P",
    "gn:feature_code":"PPL",
    "gn:name":"Tikolemba",
    "gn:population":0,
    "gn:timezone":"Africa/Kinshasa",
    "iso:country":"CD",
    "wof:name":"Tikolemba",
    "wof:placetype":"locality"
},
  "geometry": {"coordinates":[19.21667,-1.61667],"type":"Point"}
}