{
  "type": "Feature",
  "properties": {
    "gn:admin1_code":"13.0",
    "gn:asciiname":"Efulu",
    "gn:country_code":"CD",
    "gn:dem":549,
    "gn:feature_class":"P",
    "gn:feature_code":"PPL",
    "gn:name":"Efulu",
    "gn:population":0,
    "gn:timezone":"Africa/Lubumbashi",
    "iso:country":"CD",
    "wof:name":"Efulu",
    "wof:placetype":"locality"
},
  "geometry": {"coordinates":[24.72839,3.55726],"type":"Point"}
}