{
  "type": "Feature",
  "properties": {
    "gn:admin1_code":"23.0",
    "gn:asciiname":"Ntambwe-Kankonde",
    "gn:country_code":"CD",
    "gn:dem":597,
    "gn:feature_class":"P",
    "gn:feature_code":"PPL",
    "gn:name":"Ntambwe-Kankonde",
    "gn:population":0,
    "gn:timezone":"Africa/Lubumbashi",
    "iso:country":"CD",
    "name:und_x_variant":[
        "Ntambwe-Kakonde"
    ],
    "wof:name":"Ntambwe-Kankonde",
    "wof:placetype":"locality"
},
  "geometry": {"coordinates":[22.36802,-5.84778],"type":"Point"}
}