{
  "type": "Feature",
  "properties": {
    "gn:admin1_code":"26.0",
    "gn:asciiname":"Bobusu",
    "gn:country_code":"CD",
    "gn:dem":396,
    "gn:feature_class":"P",
    "gn:feature_code":"PPL",
    "gn:name":"Bobusu",
    "gn:population":0,
    "gn:timezone":"Africa/Kinshasa",
    "iso:country":"CD",
    "wof:name":"Bobusu",
    "wof:placetype":"locality"
},
  "geometry": {"coordinates":[20.65,3.43333],"type":"Point"}
}