{
  "type": "Feature",
  "properties": {
    "gn:admin1_code":"14.0",
    "gn:asciiname":"Mulemba",
    "gn:country_code":"CD",
    "gn:dem":1140,
    "gn:feature_class":"P",
    "gn:feature_code":"PPL",
    "gn:name":"Mulemba",
    "gn:population":0,
    "gn:timezone":"Africa/Lubumbashi",
    "iso:country":"CD",
    "name:und_x_variant":[
        "Mulembo",
        "Mulemba"
    ],
    "wof:name":"Mulemba",
    "wof:placetype":"locality"
},
  "geometry": {"coordinates":[26.72333,-10.72556],"type":"Point"}
}