{
  "type": "Feature",
  "properties": {
    "gn:admin1_code":"20.0",
    "gn:asciiname":"Kazamba",
    "gn:country_code":"CD",
    "gn:dem":763,
    "gn:feature_class":"P",
    "gn:feature_code":"PPL",
    "gn:name":"Kazamba",
    "gn:population":0,
    "gn:timezone":"Africa/Kinshasa",
    "iso:country":"CD",
    "name:fra_x_preferred":[
        "Kazamba"
    ],
    "wof:name":"Kazamba",
    "wof:placetype":"locality"
},
  "geometry": {"coordinates":[17.8776,-5.37334],"type":"Point"}
}