{
  "type": "Feature",
  "properties": {
    "gn:admin1_code":"18.0",
    "gn:asciiname":"Katende",
    "gn:country_code":"CD",
    "gn:dem":588,
    "gn:feature_class":"P",
    "gn:feature_code":"PPL",
    "gn:name":"Katende",
    "gn:population":0,
    "gn:timezone":"Africa/Lubumbashi",
    "iso:country":"CD",
    "name:und_x_variant":[
        "Katendi",
        "Katende"
    ],
    "wof:name":"Katende",
    "wof:placetype":"locality"
},
  "geometry": {"coordinates":[21.72942,-5.5007],"type":"Point"}
}