{
  "type": "Feature",
  "properties": {
    "gn:admin1_code":"27.0",
    "gn:asciiname":"Tshunga-Shilu",
    "gn:country_code":"CD",
    "gn:dem":538,
    "gn:feature_class":"P",
    "gn:feature_code":"PPL",
    "gn:name":"Tshunga-Shilu",
    "gn:population":0,
    "gn:timezone":"Africa/Lubumbashi",
    "iso:country":"CD",
    "name:und_x_variant":[
        "Shunga",
        "Tshunga-Shilu"
    ],
    "wof:name":"Tshunga-Shilu",
    "wof:placetype":"locality"
},
  "geometry": {"coordinates":[24.78173,-4.03538],"type":"Point"}
}