{
  "type": "Feature",
  "properties": {
    "gn:admin1_code":"22.0",
    "gn:asciiname":"Imazo",
    "gn:country_code":"CD",
    "gn:dem":1124,
    "gn:feature_class":"P",
    "gn:feature_code":"PPL",
    "gn:name":"Imazo",
    "gn:population":0,
    "gn:timezone":"Africa/Lubumbashi",
    "iso:country":"CD",
    "wof:name":"Imazo",
    "wof:placetype":"locality"
},
  "geometry": {"coordinates":[22.30128,-11.22418],"type":"Point"}
}