{
  "type": "Feature",
  "properties": {
    "gn:admin1_code":"19.0",
    "gn:asciiname":"Buatundu-Kabela",
    "gn:country_code":"CD",
    "gn:dem":516,
    "gn:feature_class":"P",
    "gn:feature_code":"PPL",
    "gn:name":"Buatundu-Kabela",
    "gn:population":0,
    "gn:timezone":"Africa/Kinshasa",
    "iso:country":"CD",
    "wof:name":"Buatundu-Kabela",
    "wof:placetype":"locality"
},
  "geometry": {"coordinates":[17.59393,-4.30367],"type":"Point"}
}