{
  "type": "Feature",
  "properties": {
    "gn:admin1_code":"0.0",
    "gn:asciiname":"Swana-Mune",
    "gn:country_code":"CD",
    "gn:dem":1468,
    "gn:feature_class":"P",
    "gn:feature_code":"PPL",
    "gn:name":"Swana-Mune",
    "gn:population":0,
    "gn:timezone":"Africa/Lubumbashi",
    "iso:country":"CD",
    "wof:name":"Swana-Mune",
    "wof:placetype":"locality"
},
  "geometry": {"coordinates":[26.56667,-11.36667],"type":"Point"}
}