{
  "type": "Feature",
  "properties": {
    "gn:admin1_code":"11.0",
    "gn:asciiname":"Mumbembi",
    "gn:country_code":"CD",
    "gn:dem":1238,
    "gn:feature_class":"P",
    "gn:feature_code":"PPL",
    "gn:name":"Mumbembi",
    "gn:population":0,
    "gn:timezone":"Africa/Lubumbashi",
    "iso:country":"CD",
    "wof:name":"Mumbembi",
    "wof:placetype":"locality"
},
  "geometry": {"coordinates":[29.09586,0.05565],"type":"Point"}
}