{
  "type": "Feature",
  "properties": {
    "gn:admin1_code":"20.0",
    "gn:asciiname":"Zanga",
    "gn:country_code":"CD",
    "gn:dem":825,
    "gn:feature_class":"P",
    "gn:feature_code":"PPL",
    "gn:name":"Zanga",
    "gn:population":0,
    "gn:timezone":"Africa/Kinshasa",
    "iso:country":"CD",
    "wof:name":"Zanga",
    "wof:placetype":"locality"
},
  "geometry": {"coordinates":[17.79786,-5.37053],"type":"Point"}
}