{
  "type": "Feature",
  "properties": {
    "gn:admin1_code":"19.0",
    "gn:asciiname":"Kisiama",
    "gn:country_code":"CD",
    "gn:dem":806,
    "gn:feature_class":"P",
    "gn:feature_code":"PPL",
    "gn:name":"Kisiama",
    "gn:population":0,
    "gn:timezone":"Africa/Kinshasa",
    "iso:country":"CD",
    "wof:name":"Kisiama",
    "wof:placetype":"locality"
},
  "geometry": {"coordinates":[16.95246,-6.30015],"type":"Point"}
}