{
  "type": "Feature",
  "properties": {
    "gn:admin1_code":"22.0",
    "gn:asciiname":"Kawewe",
    "gn:country_code":"CD",
    "gn:dem":1034,
    "gn:feature_class":"P",
    "gn:feature_code":"PPL",
    "gn:name":"Kawewe",
    "gn:population":0,
    "gn:timezone":"Africa/Lubumbashi",
    "iso:country":"CD",
    "wof:name":"Kawewe",
    "wof:placetype":"locality"
},
  "geometry": {"coordinates":[24.47252000000001,-10.13972],"type":"Point"}
}