{
  "type": "Feature",
  "properties": {
    "gn:admin1_code":"28.0",
    "gn:asciiname":"Bogbali-Buyakamba",
    "gn:country_code":"CD",
    "gn:dem":387,
    "gn:feature_class":"P",
    "gn:feature_code":"PPL",
    "gn:name":"Bogbali-Buyakamba",
    "gn:population":0,
    "gn:timezone":"Africa/Kinshasa",
    "iso:country":"CD",
    "name:und_x_variant":[
        "Bogbwali",
        "Bogbali-Buyakamba"
    ],
    "wof:name":"Bogbali-Buyakamba",
    "wof:placetype":"locality"
},
  "geometry": {"coordinates":[19.04543,3.76485],"type":"Point"}
}