{
  "type": "Feature",
  "properties": {
    "gn:admin1_code":"20.0",
    "gn:asciiname":"Binga Vula",
    "gn:country_code":"CD",
    "gn:dem":743,
    "gn:feature_class":"P",
    "gn:feature_code":"PPL",
    "gn:name":"Binga Vula",
    "gn:population":0,
    "gn:timezone":"Africa/Kinshasa",
    "iso:country":"CD",
    "wof:name":"Binga Vula",
    "wof:placetype":"locality"
},
  "geometry": {"coordinates":[19.09799,-5.46061],"type":"Point"}
}