{
  "type": "Feature",
  "properties": {
    "gn:admin1_code":"18.0",
    "gn:asciiname":"Bakwa-Mukamba",
    "gn:country_code":"CD",
    "gn:dem":516,
    "gn:feature_class":"P",
    "gn:feature_code":"PPL",
    "gn:name":"Bakwa-Mukamba",
    "gn:population":0,
    "gn:timezone":"Africa/Lubumbashi",
    "iso:country":"CD",
    "wof:name":"Bakwa-Mukamba",
    "wof:placetype":"locality"
},
  "geometry": {"coordinates":[21.34528,-5.2611],"type":"Point"}
}