{
  "type": "Feature",
  "properties": {
    "gn:admin1_code":"19.0",
    "gn:asciiname":"Pulumba Deuxieme",
    "gn:country_code":"CD",
    "gn:dem":793,
    "gn:feature_class":"P",
    "gn:feature_code":"PPL",
    "gn:name":"Pulumba Deuxi\u00e8me",
    "gn:population":0,
    "gn:timezone":"Africa/Kinshasa",
    "iso:country":"CD",
    "wof:name":"Pulumba Deuxieme",
    "wof:placetype":"locality"
},
  "geometry": {"coordinates":[18.18561,-6.21494],"type":"Point"}
}