{
  "type": "Feature",
  "properties": {
    "gn:admin1_code":"19.0",
    "gn:asciiname":"Tshengeshi",
    "gn:country_code":"CD",
    "gn:dem":765,
    "gn:feature_class":"P",
    "gn:feature_code":"PPL",
    "gn:name":"Tshengeshi",
    "gn:population":0,
    "gn:timezone":"Africa/Kinshasa",
    "iso:country":"CD",
    "wof:name":"Tshengeshi",
    "wof:placetype":"locality"
},
  "geometry": {"coordinates":[16.78976,-5.75129],"type":"Point"}
}