{
  "type": "Feature",
  "properties": {
    "gn:admin1_code":"10.0",
    "gn:asciiname":"Kihila",
    "gn:country_code":"CD",
    "gn:dem":541,
    "gn:feature_class":"P",
    "gn:feature_code":"PPL",
    "gn:name":"Kihila",
    "gn:population":0,
    "gn:timezone":"Africa/Lubumbashi",
    "iso:country":"CD",
    "wof:name":"Kihila",
    "wof:placetype":"locality"
},
  "geometry": {"coordinates":[27.27443,-4.66135],"type":"Point"}
}