{
  "type": "Feature",
  "properties": {
    "gn:admin1_code":"23.0",
    "gn:asciiname":"Mangande",
    "gn:country_code":"CD",
    "gn:dem":774,
    "gn:feature_class":"P",
    "gn:feature_code":"PPL",
    "gn:name":"Mangande",
    "gn:population":0,
    "gn:timezone":"Africa/Lubumbashi",
    "iso:country":"CD",
    "wof:name":"Mangande",
    "wof:placetype":"locality"
},
  "geometry": {"coordinates":[21.68943,-7.09933],"type":"Point"}
}