{
  "type": "Feature",
  "properties": {
    "gn:admin1_code":"18.0",
    "gn:asciiname":"Tshisemasema",
    "gn:country_code":"CD",
    "gn:dem":739,
    "gn:feature_class":"P",
    "gn:feature_code":"PPL",
    "gn:name":"Tshisemasema",
    "gn:population":0,
    "gn:timezone":"Africa/Lubumbashi",
    "iso:country":"CD",
    "wof:name":"Tshisemasema",
    "wof:placetype":"locality"
},
  "geometry": {"coordinates":[21.50563,-6.41361],"type":"Point"}
}