{
  "type": "Feature",
  "properties": {
    "gn:admin1_code":"22.0",
    "gn:asciiname":"Sakai",
    "gn:country_code":"CD",
    "gn:dem":1075,
    "gn:feature_class":"P",
    "gn:feature_code":"PPL",
    "gn:name":"Sakai",
    "gn:population":0,
    "gn:timezone":"Africa/Lubumbashi",
    "iso:country":"CD",
    "wof:name":"Sakai",
    "wof:placetype":"locality"
},
  "geometry": {"coordinates":[22.30836,-9.90358],"type":"Point"}
}