{
  "type": "Feature",
  "properties": {
    "gn:admin1_code":"19.0",
    "gn:asciiname":"Kambwandji",
    "gn:country_code":"CD",
    "gn:dem":957,
    "gn:feature_class":"P",
    "gn:feature_code":"PPL",
    "gn:name":"Kambwandji",
    "gn:population":0,
    "gn:timezone":"Africa/Kinshasa",
    "iso:country":"CD",
    "wof:name":"Kambwandji",
    "wof:placetype":"locality"
},
  "geometry": {"coordinates":[18.51389,-7.83427],"type":"Point"}
}