{
  "type": "Feature",
  "properties": {
    "gn:admin1_code":"29.0",
    "gn:asciiname":"Mbuli",
    "gn:country_code":"CD",
    "gn:dem":704,
    "gn:feature_class":"P",
    "gn:feature_code":"PPL",
    "gn:name":"Mbuli",
    "gn:population":0,
    "gn:timezone":"Africa/Lubumbashi",
    "iso:country":"CD",
    "wof:name":"Mbuli",
    "wof:placetype":"locality"
},
  "geometry": {"coordinates":[27.5881,-5.39996],"type":"Point"}
}