{
  "type": "Feature",
  "properties": {
    "gn:admin1_code":"12.0",
    "gn:asciiname":"Luandjofu",
    "gn:country_code":"CD",
    "gn:dem":1659,
    "gn:feature_class":"P",
    "gn:feature_code":"PPL",
    "gn:name":"Luandjofu",
    "gn:population":0,
    "gn:timezone":"Africa/Lubumbashi",
    "iso:country":"CD",
    "wof:name":"Luandjofu",
    "wof:placetype":"locality"
},
  "geometry": {"coordinates":[29.02291,-1.80577],"type":"Point"}
}