{
  "type": "Feature",
  "properties": {
    "gn:admin1_code":"22.0",
    "gn:asciiname":"Koni",
    "gn:country_code":"CD",
    "gn:dem":1277,
    "gn:feature_class":"P",
    "gn:feature_code":"PPL",
    "gn:name":"Koni",
    "gn:population":0,
    "gn:timezone":"Africa/Lubumbashi",
    "iso:country":"CD",
    "wof:name":"Koni",
    "wof:placetype":"locality"
},
  "geometry": {"coordinates":[26.03425,-10.81569],"type":"Point"}
}