{
  "type": "Feature",
  "properties": {
    "gn:admin1_code":"23.0",
    "gn:asciiname":"Kaulu",
    "gn:country_code":"CD",
    "gn:dem":881,
    "gn:feature_class":"P",
    "gn:feature_code":"PPL",
    "gn:name":"Kaulu",
    "gn:population":0,
    "gn:timezone":"Africa/Lubumbashi",
    "iso:country":"CD",
    "name:und_x_variant":[
        "Kaula",
        "Kaulu"
    ],
    "wof:name":"Kaulu",
    "wof:placetype":"locality"
},
  "geometry": {"coordinates":[22.86498,-6.61589],"type":"Point"}
}