{
  "type": "Feature",
  "properties": {
    "gn:admin1_code":"2.0",
    "gn:asciiname":"Kelengo",
    "gn:country_code":"CD",
    "gn:dem":327,
    "gn:feature_class":"P",
    "gn:feature_code":"PPL",
    "gn:name":"Kelengo",
    "gn:population":0,
    "gn:timezone":"Africa/Kinshasa",
    "iso:country":"CD",
    "wof:name":"Kelengo",
    "wof:placetype":"locality"
},
  "geometry": {"coordinates":[19.08333,-0.36667],"type":"Point"}
}