{
  "type": "Feature",
  "properties": {
    "gn:admin1_code":"23.0",
    "gn:asciiname":"Kalemba",
    "gn:country_code":"CD",
    "gn:dem":719,
    "gn:feature_class":"P",
    "gn:feature_code":"PPL",
    "gn:name":"Kalemba",
    "gn:population":0,
    "gn:timezone":"Africa/Lubumbashi",
    "iso:country":"CD",
    "wof:name":"Kalemba",
    "wof:placetype":"locality"
},
  "geometry": {"coordinates":[22.26976,-6.08803],"type":"Point"}
}