{
  "type": "Feature",
  "properties": {
    "gn:admin1_code":"21.0",
    "gn:asciiname":"Kilungu",
    "gn:country_code":"CD",
    "gn:dem":801,
    "gn:feature_class":"P",
    "gn:feature_code":"PPL",
    "gn:name":"Kilungu",
    "gn:population":0,
    "gn:timezone":"Africa/Lubumbashi",
    "iso:country":"CD",
    "wof:name":"Kilungu",
    "wof:placetype":"locality"
},
  "geometry": {"coordinates":[24.30607,-6.11892],"type":"Point"}
}