{
  "type": "Feature",
  "properties": {
    "gn:admin1_code":"21.0",
    "gn:asciiname":"Dihumba",
    "gn:country_code":"CD",
    "gn:dem":711,
    "gn:feature_class":"P",
    "gn:feature_code":"PPL",
    "gn:name":"Dihumba",
    "gn:population":0,
    "gn:timezone":"Africa/Lubumbashi",
    "iso:country":"CD",
    "name:und_x_variant":[
        "Dipumba",
        "Dihumba"
    ],
    "wof:name":"Dihumba",
    "wof:placetype":"locality"
},
  "geometry": {"coordinates":[23.92367,-6.65005],"type":"Point"}
}