{
  "type": "Feature",
  "properties": {
    "gn:admin1_code":"16.0",
    "gn:asciiname":"Makombo",
    "gn:country_code":"CD",
    "gn:dem":693,
    "gn:feature_class":"P",
    "gn:feature_code":"PPL",
    "gn:name":"Makombo",
    "gn:population":0,
    "gn:timezone":"Africa/Lubumbashi",
    "iso:country":"CD",
    "name:und_x_variant":[
        "Mokambo",
        "Magambo",
        "Mokombo",
        "Makombo"
    ],
    "wof:name":"Makombo",
    "wof:placetype":"locality"
},
  "geometry": {"coordinates":[27.44793,3.65968],"type":"Point"}
}