{
  "type": "Feature",
  "properties": {
    "gn:admin1_code":"22.0",
    "gn:asciiname":"Noushi",
    "gn:country_code":"CD",
    "gn:dem":1110,
    "gn:feature_class":"P",
    "gn:feature_code":"PPL",
    "gn:name":"Noushi",
    "gn:population":0,
    "gn:timezone":"Africa/Kinshasa",
    "iso:country":"CD",
    "wof:name":"Noushi",
    "wof:placetype":"locality"
},
  "geometry": {"coordinates":[22.33139,-11.20172],"type":"Point"}
}