{
  "type": "Feature",
  "properties": {
    "gn:admin1_code":"16.0",
    "gn:asciiname":"Ngilima",
    "gn:country_code":"CD",
    "gn:dem":691,
    "gn:feature_class":"P",
    "gn:feature_code":"PPL",
    "gn:name":"Ngilima",
    "gn:population":0,
    "gn:timezone":"Africa/Lubumbashi",
    "iso:country":"CD",
    "name:und_x_variant":[
        "Gilima"
    ],
    "wof:name":"Ngilima",
    "wof:placetype":"locality"
},
  "geometry": {"coordinates":[28.25535,3.83169],"type":"Point"}
}