{
  "type": "Feature",
  "properties": {
    "gn:admin1_code":"29.0",
    "gn:asciiname":"Kangelwe",
    "gn:country_code":"CD",
    "gn:dem":1630,
    "gn:feature_class":"P",
    "gn:feature_code":"PPL",
    "gn:name":"Kangelwe",
    "gn:population":0,
    "gn:timezone":"Africa/Lubumbashi",
    "iso:country":"CD",
    "wof:name":"Kangelwe",
    "wof:placetype":"locality"
},
  "geometry": {"coordinates":[29.56667,-7.75],"type":"Point"}
}