{
  "type": "Feature",
  "properties": {
    "gn:admin1_code":"20.0",
    "gn:asciiname":"Kilwamba",
    "gn:country_code":"CD",
    "gn:dem":784,
    "gn:feature_class":"P",
    "gn:feature_code":"PPL",
    "gn:name":"Kilwamba",
    "gn:population":0,
    "gn:timezone":"Africa/Kinshasa",
    "iso:country":"CD",
    "wof:name":"Kilwamba",
    "wof:placetype":"locality"
},
  "geometry": {"coordinates":[18.16674,-5.48243],"type":"Point"}
}