{
  "type": "Feature",
  "properties": {
    "gn:admin1_code":"30.0",
    "gn:asciiname":"Bondomba",
    "gn:country_code":"CD",
    "gn:dem":424,
    "gn:feature_class":"P",
    "gn:feature_code":"PPL",
    "gn:name":"Bondomba",
    "gn:population":0,
    "gn:timezone":"Africa/Lubumbashi",
    "iso:country":"CD",
    "wof:name":"Bondomba",
    "wof:placetype":"locality"
},
  "geometry": {"coordinates":[23.59043,-0.55257],"type":"Point"}
}