{
  "type": "Feature",
  "properties": {
    "gn:admin1_code":"15.0",
    "gn:asciiname":"Lupafui",
    "gn:country_code":"CD",
    "gn:dem":958,
    "gn:feature_class":"P",
    "gn:feature_code":"PPL",
    "gn:name":"Lupafui",
    "gn:population":0,
    "gn:timezone":"Africa/Lubumbashi",
    "iso:country":"CD",
    "wof:name":"Lupafui",
    "wof:placetype":"locality"
},
  "geometry": {"coordinates":[24.46667,-9.88333],"type":"Point"}
}