{
  "type": "Feature",
  "properties": {
    "gn:admin1_code":"29.0",
    "gn:asciiname":"Sombwela",
    "gn:country_code":"CD",
    "gn:dem":649,
    "gn:feature_class":"P",
    "gn:feature_code":"PPL",
    "gn:name":"Sombwela",
    "gn:population":0,
    "gn:timezone":"Africa/Lubumbashi",
    "iso:country":"CD",
    "name:und_x_variant":[
        "Songwela",
        "Sombwela"
    ],
    "wof:name":"Sombwela",
    "wof:placetype":"locality"
},
  "geometry": {"coordinates":[26.36667000000001,-5.63333],"type":"Point"}
}