{
  "type": "Feature",
  "properties": {
    "gn:admin1_code":"22.0",
    "gn:asciiname":"Mungomba",
    "gn:country_code":"CD",
    "gn:dem":1051,
    "gn:feature_class":"P",
    "gn:feature_code":"PPL",
    "gn:name":"Mungomba",
    "gn:population":0,
    "gn:timezone":"Africa/Lubumbashi",
    "iso:country":"CD",
    "wof:name":"Mungomba",
    "wof:placetype":"locality"
},
  "geometry": {"coordinates":[23.20198,-9.53166],"type":"Point"}
}