{
  "type": "Feature",
  "properties": {
    "gn:admin1_code":"21.0",
    "gn:asciiname":"Keshi-Ngoie",
    "gn:country_code":"CD",
    "gn:dem":762,
    "gn:feature_class":"P",
    "gn:feature_code":"PPL",
    "gn:name":"Keshi-Ngoie",
    "gn:population":0,
    "gn:timezone":"Africa/Lubumbashi",
    "iso:country":"CD",
    "wof:name":"Keshi-Ngoie",
    "wof:placetype":"locality"
},
  "geometry": {"coordinates":[24.5437,-6.00295],"type":"Point"}
}