{
  "type": "Feature",
  "properties": {
    "gn:admin1_code":"13.0",
    "gn:asciiname":"Sangola",
    "gn:country_code":"CD",
    "gn:dem":604,
    "gn:feature_class":"P",
    "gn:feature_code":"PPL",
    "gn:name":"Sangola",
    "gn:population":0,
    "gn:timezone":"Africa/Lubumbashi",
    "iso:country":"CD",
    "wof:name":"Sangola",
    "wof:placetype":"locality"
},
  "geometry": {"coordinates":[25.08451,4.44952],"type":"Point"}
}