{
  "type": "Feature",
  "properties": {
    "gn:admin1_code":"8.0",
    "gn:asciiname":"Kimbundu",
    "gn:country_code":"CD",
    "gn:dem":445,
    "gn:feature_class":"P",
    "gn:feature_code":"PPL",
    "gn:name":"Kimbundu",
    "gn:population":0,
    "gn:timezone":"Africa/Kinshasa",
    "iso:country":"CD",
    "name:afr_x_preferred":[
        "Kimbundu"
    ],
    "name:ast_x_preferred":[
        "Kimbundu"
    ],
    "name:cat_x_preferred":[
        "Kimbundu"
    ],
    "name:deu_x_preferred":[
        "Kimbundu"
    ],
    "name:epo_x_preferred":[
        "Kimbunda lingvo"
    ],
    "name:eus_x_preferred":[
        "Kinbundu"
    ],
    "name:fin_x_preferred":[
        "Kimbundu"
    ],
    "name:fra_x_preferred":[
        "Kimbundu"
    ],
    "name:frr_x_preferred":[
        "Nuurd Mbundu"
    ],
    "name:glg_x_preferred":[
        "Lingua kimbundu"
    ],
    "name:hif_x_preferred":[
        "Kimbundu bhasa"
    ],
    "name:jpn_x_preferred":[
        "\u30ad\u30f3\u30d6\u30f3\u30c9\u8a9e"
    ],
    "name:kon_x_preferred":[
        "Kimbundu"
    ],
    "name:pms_x_preferred":[
        "Lenga Mbundu"
    ],
    "name:pol_x_preferred":[
        "J\u0119zyk mbundu"
    ],
    "name:por_x_preferred":[
        "Kimbundu"
    ],
    "name:rus_x_preferred":[
        "\u0421\u0435\u0432\u0435\u0440\u043d\u044b\u0439 \u043c\u0431\u0443\u043d\u0434\u0443"
    ],
    "name:sin_x_preferred":[
        "\u0d9a\u0dd2\u0db8\u0dca\u0db6\u0dd4\u0db1\u0dca\u0da9\u0dd4"
    ],
    "name:spa_x_preferred":[
        "Kimbundu"
    ],
    "name:swa_x_preferred":[
        "Kimbundu"
    ],
    "name:swe_x_preferred":[
        "Kimbundu"
    ],
    "name:tgl_x_preferred":[
        "Wikang Kimbundu"
    ],
    "name:ukr_x_preferred":[
        "\u041f\u0456\u0432\u043d\u0456\u0447\u043d\u0430 \u043c\u0431\u0443\u043d\u0434\u0443"
    ],
    "name:und_x_variant":[
        "Kimbunda"
    ],
    "name:zho_x_preferred":[
        "\u91d1\u90a6\u675c\u8bed"
    ],
    "wof:name":"Kimbundu",
    "wof:placetype":"locality"
},
  "geometry": {"coordinates":[15.61667,-5.06667],"type":"Point"}
}