{
  "type": "Feature",
  "properties": {
    "gn:admin1_code":"22.0",
    "gn:asciiname":"Samujimu",
    "gn:country_code":"CD",
    "gn:dem":1108,
    "gn:feature_class":"P",
    "gn:feature_code":"PPL",
    "gn:name":"Samujimu",
    "gn:population":0,
    "gn:timezone":"Africa/Lubumbashi",
    "iso:country":"CD",
    "wof:name":"Samujimu",
    "wof:placetype":"locality"
},
  "geometry": {"coordinates":[22.32706,-11.19744],"type":"Point"}
}