{
  "type": "Feature",
  "properties": {
    "gn:admin1_code":"8.0",
    "gn:asciiname":"Kinkabanga",
    "gn:country_code":"CD",
    "gn:dem":802,
    "gn:feature_class":"P",
    "gn:feature_code":"PPL",
    "gn:name":"Kinkabanga",
    "gn:population":0,
    "gn:timezone":"Africa/Kinshasa",
    "iso:country":"CD",
    "wof:name":"Kinkabanga",
    "wof:placetype":"locality"
},
  "geometry": {"coordinates":[16.13247,-5.55612],"type":"Point"}
}