{
  "type": "Feature",
  "properties": {
    "gn:admin1_code":"24.0",
    "gn:asciiname":"Pondu Deuxieme",
    "gn:country_code":"CD",
    "gn:dem":407,
    "gn:feature_class":"P",
    "gn:feature_code":"PPL",
    "gn:name":"Pondu Deuxi\u00e8me",
    "gn:population":0,
    "gn:timezone":"Africa/Kinshasa",
    "iso:country":"CD",
    "wof:name":"Pondu Deuxieme",
    "wof:placetype":"locality"
},
  "geometry": {"coordinates":[18.87778,-3.55622],"type":"Point"}
}