{
  "type": "Feature",
  "properties": {
    "gn:admin1_code":"15.0",
    "gn:asciiname":"Djobo",
    "gn:country_code":"CD",
    "gn:dem":734,
    "gn:feature_class":"P",
    "gn:feature_code":"PPL",
    "gn:name":"Djobo",
    "gn:population":0,
    "gn:timezone":"Africa/Lubumbashi",
    "iso:country":"CD",
    "wof:name":"Djobo",
    "wof:placetype":"locality"
},
  "geometry": {"coordinates":[27.21562,-8.18811],"type":"Point"}
}