{
  "type": "Feature",
  "properties": {
    "gn:admin1_code":"15.0",
    "gn:asciiname":"Kamutolo",
    "gn:country_code":"CD",
    "gn:dem":935,
    "gn:feature_class":"P",
    "gn:feature_code":"PPL",
    "gn:name":"Kamutolo",
    "gn:population":0,
    "gn:timezone":"Africa/Lubumbashi",
    "iso:country":"CD",
    "wof:name":"Kamutolo",
    "wof:placetype":"locality"
},
  "geometry": {"coordinates":[25.25993,-9.18802],"type":"Point"}
}