{
  "type": "Feature",
  "properties": {
    "gn:admin1_code":"9.0",
    "gn:asciiname":"Kpaika",
    "gn:country_code":"CD",
    "gn:dem":708,
    "gn:feature_class":"P",
    "gn:feature_code":"PPL",
    "gn:name":"Kpaika",
    "gn:population":0,
    "gn:timezone":"Africa/Lubumbashi",
    "iso:country":"CD",
    "wof:name":"Kpaika",
    "wof:placetype":"locality"
},
  "geometry": {"coordinates":[28.67,4.07],"type":"Point"}
}