{
  "type": "Feature",
  "properties": {
    "gn:admin1_code":"2.0",
    "gn:asciiname":"Ifuwa",
    "gn:country_code":"CD",
    "gn:dem":358,
    "gn:feature_class":"P",
    "gn:feature_code":"PPL",
    "gn:name":"Ifuwa",
    "gn:population":0,
    "gn:timezone":"Africa/Kinshasa",
    "iso:country":"CD",
    "wof:name":"Ifuwa",
    "wof:placetype":"locality"
},
  "geometry": {"coordinates":[19.73333,0.23333],"type":"Point"}
}