{
  "type": "Feature",
  "properties": {
    "gn:admin1_code":"17.0",
    "gn:asciiname":"Yazo",
    "gn:country_code":"CD",
    "gn:dem":1267,
    "gn:feature_class":"P",
    "gn:feature_code":"PPL",
    "gn:name":"Yazo",
    "gn:population":0,
    "gn:timezone":"Africa/Lubumbashi",
    "iso:country":"CD",
    "wof:name":"Yazo",
    "wof:placetype":"locality"
},
  "geometry": {"coordinates":[30.68957,3.17365],"type":"Point"}
}