{
  "type": "Feature",
  "properties": {
    "gn:admin1_code":"8.0",
    "gn:asciiname":"Mafiela",
    "gn:country_code":"CD",
    "gn:dem":441,
    "gn:feature_class":"P",
    "gn:feature_code":"PPL",
    "gn:name":"Mafiela",
    "gn:population":0,
    "gn:timezone":"Africa/Kinshasa",
    "iso:country":"CD",
    "wof:name":"Mafiela",
    "wof:placetype":"locality"
},
  "geometry": {"coordinates":[14.44482,-4.92261],"type":"Point"}
}