{
  "type": "Feature",
  "properties": {
    "gn:admin1_code":"21.0",
    "gn:asciiname":"Malenga",
    "gn:country_code":"CD",
    "gn:dem":922,
    "gn:feature_class":"P",
    "gn:feature_code":"PPL",
    "gn:name":"Malenga",
    "gn:population":0,
    "gn:timezone":"Africa/Lubumbashi",
    "iso:country":"CD",
    "wof:name":"Malenga",
    "wof:placetype":"locality"
},
  "geometry": {"coordinates":[23.23997,-7.74624],"type":"Point"}
}