{
  "type": "Feature",
  "properties": {
    "gn:admin1_code":"31.0",
    "gn:asciiname":"Ingandu",
    "gn:country_code":"CD",
    "gn:dem":356,
    "gn:feature_class":"P",
    "gn:feature_code":"PPL",
    "gn:name":"Ingandu",
    "gn:population":0,
    "gn:timezone":"Africa/Kinshasa",
    "iso:country":"CD",
    "name:und_x_variant":[
        "Inganda",
        "Ingandu"
    ],
    "wof:name":"Ingandu",
    "wof:placetype":"locality"
},
  "geometry": {"coordinates":[20.83333,-0.56667],"type":"Point"}
}