{
  "type": "Feature",
  "properties": {
    "gn:admin1_code":"27.0",
    "gn:asciiname":"Ulungu-Lukutu",
    "gn:country_code":"CD",
    "gn:dem":532,
    "gn:feature_class":"P",
    "gn:feature_code":"PPL",
    "gn:name":"Ulungu-Lukutu",
    "gn:population":0,
    "gn:timezone":"Africa/Lubumbashi",
    "iso:country":"CD",
    "wof:name":"Ulungu-Lukutu",
    "wof:placetype":"locality"
},
  "geometry": {"coordinates":[24.45,-3.93333],"type":"Point"}
}