{
  "type": "Feature",
  "properties": {
    "gn:admin1_code":"26.0",
    "gn:asciiname":"Kolekpwa",
    "gn:country_code":"CD",
    "gn:dem":457,
    "gn:feature_class":"P",
    "gn:feature_code":"PPL",
    "gn:name":"Kolekpwa",
    "gn:population":0,
    "gn:timezone":"Africa/Kinshasa",
    "iso:country":"CD",
    "name:und_x_variant":[
        "Kulekpwa"
    ],
    "wof:name":"Kolekpwa",
    "wof:placetype":"locality"
},
  "geometry": {"coordinates":[20.67876,4.3218],"type":"Point"}
}