{
  "type": "Feature",
  "properties": {
    "gn:admin1_code":"20.0",
    "gn:asciiname":"Pondji",
    "gn:country_code":"CD",
    "gn:dem":458,
    "gn:feature_class":"P",
    "gn:feature_code":"PPL",
    "gn:name":"Pondji",
    "gn:population":0,
    "gn:timezone":"Africa/Kinshasa",
    "iso:country":"CD",
    "wof:name":"Pondji",
    "wof:placetype":"locality"
},
  "geometry": {"coordinates":[18.50737,-5.37806],"type":"Point"}
}