{
  "type": "Feature",
  "properties": {
    "gn:admin1_code":"31.0",
    "gn:asciiname":"Djuevo",
    "gn:country_code":"CD",
    "gn:dem":350,
    "gn:feature_class":"P",
    "gn:feature_code":"PPL",
    "gn:name":"Djuevo",
    "gn:population":0,
    "gn:timezone":"Africa/Kinshasa",
    "iso:country":"CD",
    "wof:name":"Djuevo",
    "wof:placetype":"locality"
},
  "geometry": {"coordinates":[20.30874,-0.60225],"type":"Point"}
}