{
  "type": "Feature",
  "properties": {
    "gn:admin1_code":"12.0",
    "gn:asciiname":"Kilingitshi",
    "gn:country_code":"CD",
    "gn:dem":767,
    "gn:feature_class":"P",
    "gn:feature_code":"PPL",
    "gn:name":"Kilingitshi",
    "gn:population":0,
    "gn:timezone":"Africa/Lubumbashi",
    "iso:country":"CD",
    "wof:name":"Kilingitshi",
    "wof:placetype":"locality"
},
  "geometry": {"coordinates":[29.10167,-4.82333],"type":"Point"}
}