{
  "type": "Feature",
  "properties": {
    "gn:admin1_code":"18.0",
    "gn:asciiname":"Muniama",
    "gn:country_code":"CD",
    "gn:dem":659,
    "gn:feature_class":"P",
    "gn:feature_code":"PPL",
    "gn:name":"Muniama",
    "gn:population":0,
    "gn:timezone":"Africa/Lubumbashi",
    "iso:country":"CD",
    "wof:name":"Muniama",
    "wof:placetype":"locality"
},
  "geometry": {"coordinates":[20.58848,-6.33628],"type":"Point"}
}