{
  "type": "Feature",
  "properties": {
    "gn:admin1_code":"19.0",
    "gn:asciiname":"Kambangu",
    "gn:country_code":"CD",
    "gn:dem":947,
    "gn:feature_class":"P",
    "gn:feature_code":"PPL",
    "gn:name":"Kambangu",
    "gn:population":0,
    "gn:timezone":"Africa/Kinshasa",
    "iso:country":"CD",
    "wof:name":"Kambangu",
    "wof:placetype":"locality"
},
  "geometry": {"coordinates":[18.423,-7.56095],"type":"Point"}
}