{
  "type": "Feature",
  "properties": {
    "gn:admin1_code":"28.0",
    "gn:asciiname":"Bombawuli-Moke",
    "gn:country_code":"CD",
    "gn:dem":460,
    "gn:feature_class":"P",
    "gn:feature_code":"PPL",
    "gn:name":"Bombawuli-Moke",
    "gn:population":0,
    "gn:timezone":"Africa/Kinshasa",
    "iso:country":"CD",
    "wof:name":"Bombawuli-Moke",
    "wof:placetype":"locality"
},
  "geometry": {"coordinates":[19.84837000000001,3.23935],"type":"Point"}
}