{
  "type": "Feature",
  "properties": {
    "gn:admin1_code":"13.0",
    "gn:asciiname":"Libazu",
    "gn:country_code":"CD",
    "gn:dem":466,
    "gn:feature_class":"P",
    "gn:feature_code":"PPL",
    "gn:name":"Libazu",
    "gn:population":0,
    "gn:timezone":"Africa/Lubumbashi",
    "iso:country":"CD",
    "wof:name":"Libazu",
    "wof:placetype":"locality"
},
  "geometry": {"coordinates":[23.88987,3.53024],"type":"Point"}
}