{
  "type": "Feature",
  "properties": {
    "gn:admin1_code":"20.0",
    "gn:asciiname":"Malundu",
    "gn:country_code":"CD",
    "gn:dem":738,
    "gn:feature_class":"P",
    "gn:feature_code":"PPL",
    "gn:name":"Malundu",
    "gn:population":0,
    "gn:timezone":"Africa/Kinshasa",
    "iso:country":"CD",
    "name:und_x_variant":[
        "Kalundu",
        "Malundu"
    ],
    "wof:name":"Malundu",
    "wof:placetype":"locality"
},
  "geometry": {"coordinates":[19.7202,-5.72146],"type":"Point"}
}