{
  "type": "Feature",
  "properties": {
    "gn:admin1_code":"8.0",
    "gn:asciiname":"Sumba",
    "gn:country_code":"CD",
    "gn:dem":294,
    "gn:feature_class":"P",
    "gn:feature_code":"PPL",
    "gn:name":"Sumba",
    "gn:population":0,
    "gn:timezone":"Africa/Kinshasa",
    "iso:country":"CD",
    "wof:name":"Sumba",
    "wof:placetype":"locality"
},
  "geometry": {"coordinates":[14.04284,-5.62561],"type":"Point"}
}