{
  "type": "Feature",
  "properties": {
    "gn:admin1_code":"12.0",
    "gn:asciiname":"Lungungu",
    "gn:country_code":"CD",
    "gn:dem":645,
    "gn:feature_class":"P",
    "gn:feature_code":"PPL",
    "gn:name":"Lungungu",
    "gn:population":0,
    "gn:timezone":"Africa/Lubumbashi",
    "iso:country":"CD",
    "wof:name":"Lungungu",
    "wof:placetype":"locality"
},
  "geometry": {"coordinates":[28.01667,-3.38333],"type":"Point"}
}