{
  "type": "Feature",
  "properties": {
    "gn:admin1_code":"19.0",
    "gn:asciiname":"Mulopo-Kazanga",
    "gn:country_code":"CD",
    "gn:dem":677,
    "gn:feature_class":"P",
    "gn:feature_code":"PPL",
    "gn:name":"Mulopo-Kazanga",
    "gn:population":0,
    "gn:timezone":"Africa/Kinshasa",
    "iso:country":"CD",
    "wof:name":"Mulopo-Kazanga",
    "wof:placetype":"locality"
},
  "geometry": {"coordinates":[17.40947,-7.00985],"type":"Point"}
}