{
  "type": "Feature",
  "properties": {
    "gn:admin1_code":"17.0",
    "gn:asciiname":"Jiba",
    "gn:country_code":"CD",
    "gn:dem":1852,
    "gn:feature_class":"P",
    "gn:feature_code":"PPL",
    "gn:name":"Jiba",
    "gn:population":0,
    "gn:timezone":"Africa/Lubumbashi",
    "iso:country":"CD",
    "name:ceb_x_preferred":[
        "Jiba"
    ],
    "name:swe_x_preferred":[
        "Jiba"
    ],
    "wof:name":"Jiba",
    "wof:placetype":"locality"
},
  "geometry": {"coordinates":[30.69988,1.8713],"type":"Point"}
}