{
  "type": "Feature",
  "properties": {
    "gn:admin1_code":"19.0",
    "gn:asciiname":"Mandamba",
    "gn:country_code":"CD",
    "gn:dem":843,
    "gn:feature_class":"P",
    "gn:feature_code":"PPL",
    "gn:name":"Mandamba",
    "gn:population":0,
    "gn:timezone":"Africa/Kinshasa",
    "iso:country":"CD",
    "wof:name":"Mandamba",
    "wof:placetype":"locality"
},
  "geometry": {"coordinates":[17.42178,-6.89406],"type":"Point"}
}