{
  "type": "Feature",
  "properties": {
    "gn:admin1_code":"10.0",
    "gn:asciiname":"Ugandula",
    "gn:country_code":"CD",
    "gn:dem":570,
    "gn:feature_class":"P",
    "gn:feature_code":"PPL",
    "gn:name":"Ugandula",
    "gn:population":0,
    "gn:timezone":"Africa/Lubumbashi",
    "iso:country":"CD",
    "wof:name":"Ugandula",
    "wof:placetype":"locality"
},
  "geometry": {"coordinates":[26.83333,-1.41667],"type":"Point"}
}