{
  "type": "Feature",
  "properties": {
    "gn:admin1_code":"31.0",
    "gn:asciiname":"Konga",
    "gn:country_code":"CD",
    "gn:dem":379,
    "gn:feature_class":"P",
    "gn:feature_code":"PPL",
    "gn:name":"Konga",
    "gn:population":0,
    "gn:timezone":"Africa/Kinshasa",
    "iso:country":"CD",
    "name:ceb_x_preferred":[
        "Konga"
    ],
    "name:ita_x_preferred":[
        "Konga"
    ],
    "name:nld_x_preferred":[
        "Konga"
    ],
    "name:nno_x_preferred":[
        "Konga"
    ],
    "name:nor_x_preferred":[
        "Konga"
    ],
    "name:sme_x_preferred":[
        "Konga"
    ],
    "name:swe_x_preferred":[
        "Konga"
    ],
    "name:und_x_variant":[
        "Kongo",
        "Konga"
    ],
    "wof:name":"Konga",
    "wof:placetype":"locality"
},
  "geometry": {"coordinates":[20.65,0.98333],"type":"Point"}
}