{
  "type": "Feature",
  "properties": {
    "gn:admin1_code":"16.0",
    "gn:asciiname":"Misakale",
    "gn:country_code":"CD",
    "gn:dem":939,
    "gn:feature_class":"P",
    "gn:feature_code":"PPL",
    "gn:name":"Misakale",
    "gn:population":0,
    "gn:timezone":"Africa/Lubumbashi",
    "iso:country":"CD",
    "wof:name":"Misakale",
    "wof:placetype":"locality"
},
  "geometry": {"coordinates":[30.11261,3.14175],"type":"Point"}
}