{
  "type": "Feature",
  "properties": {
    "gn:admin1_code":"26.0",
    "gn:asciiname":"Botola",
    "gn:country_code":"CD",
    "gn:dem":393,
    "gn:feature_class":"P",
    "gn:feature_code":"PPL",
    "gn:name":"Botola",
    "gn:population":0,
    "gn:timezone":"Africa/Kinshasa",
    "iso:country":"CD",
    "name:deu_x_preferred":[
        "Botola"
    ],
    "name:fin_x_preferred":[
        "Botola"
    ],
    "name:hun_x_preferred":[
        "Marokk\u00f3i labdar\u00fag\u00f3-bajnoks\u00e1g"
    ],
    "name:ind_x_preferred":[
        "Botola"
    ],
    "name:jpn_x_preferred":[
        "\u30dc\u30c8\u30e9"
    ],
    "name:kor_x_preferred":[
        "\ubcf4\ud1a8\ub77c"
    ],
    "name:ron_x_preferred":[
        "Botola"
    ],
    "name:tur_x_preferred":[
        "Botola Pro"
    ],
    "name:zho_x_preferred":[
        "\u6469\u6d1b\u54e5\u8db3\u7403\u7532\u7d1a\u806f\u8cfd"
    ],
    "wof:name":"Botola",
    "wof:placetype":"locality"
},
  "geometry": {"coordinates":[21.10957,3.42233],"type":"Point"}
}