{
  "type": "Feature",
  "properties": {
    "gn:admin1_code":"26.0",
    "gn:asciiname":"Botola",
    "gn:country_code":"CD",
    "gn:dem":393,
    "gn:feature_class":"P",
    "gn:feature_code":"PPL",
    "gn:name":"Botola",
    "gn:population":0,
    "gn:timezone":"Africa/Kinshasa",
    "iso:country":"CD",
    "wof:name":"Botola",
    "wof:placetype":"locality"
},
  "geometry": {"coordinates":[21.10957,3.42233],"type":"Point"}
}