{
  "type": "Feature",
  "properties": {
    "gn:admin1_code":"18.0",
    "gn:asciiname":"Tshindinda",
    "gn:country_code":"CD",
    "gn:dem":657,
    "gn:feature_class":"P",
    "gn:feature_code":"PPL",
    "gn:name":"Tshindinda",
    "gn:population":0,
    "gn:timezone":"Africa/Lubumbashi",
    "iso:country":"CD",
    "name:und_x_variant":[
        "Tshidinda",
        "Tshindinda",
        "Tshibinda"
    ],
    "wof:name":"Tshindinda",
    "wof:placetype":"locality"
},
  "geometry": {"coordinates":[21.34714,-5.78856],"type":"Point"}
}