{
  "type": "Feature",
  "properties": {
    "gn:admin1_code":"15.0",
    "gn:asciiname":"Tshibui",
    "gn:country_code":"CD",
    "gn:dem":970,
    "gn:feature_class":"P",
    "gn:feature_code":"PPL",
    "gn:name":"Tshibui",
    "gn:population":0,
    "gn:timezone":"Africa/Lubumbashi",
    "iso:country":"CD",
    "name:und_x_variant":[
        "Tshibui Luania"
    ],
    "wof:name":"Tshibui",
    "wof:placetype":"locality"
},
  "geometry": {"coordinates":[24.17998,-7.69378],"type":"Point"}
}