{
  "type": "Feature",
  "properties": {
    "gn:admin1_code":"0.0",
    "gn:asciiname":"Kuhuha",
    "gn:country_code":"CD",
    "gn:dem":857,
    "gn:feature_class":"P",
    "gn:feature_code":"PPL",
    "gn:name":"Kuhuha",
    "gn:population":0,
    "gn:timezone":"Africa/Lubumbashi",
    "iso:country":"CD",
    "wof:name":"Kuhuha",
    "wof:placetype":"locality"
},
  "geometry": {"coordinates":[28.78333,-4.98333],"type":"Point"}
}