{
  "type": "Feature",
  "properties": {
    "gn:admin1_code":"20.0",
    "gn:asciiname":"Pani",
    "gn:country_code":"CD",
    "gn:dem":359,
    "gn:feature_class":"P",
    "gn:feature_code":"PPL",
    "gn:name":"Pani",
    "gn:population":0,
    "gn:timezone":"Africa/Kinshasa",
    "iso:country":"CD",
    "wof:name":"Pani",
    "wof:placetype":"locality"
},
  "geometry": {"coordinates":[18.10973,-3.80748],"type":"Point"}
}