{
  "type": "Feature",
  "properties": {
    "gn:admin1_code":"17.0",
    "gn:asciiname":"Katsolo",
    "gn:country_code":"CD",
    "gn:dem":1568,
    "gn:feature_class":"P",
    "gn:feature_code":"PPL",
    "gn:name":"Katsolo",
    "gn:population":0,
    "gn:timezone":"Africa/Lubumbashi",
    "iso:country":"CD",
    "wof:name":"Katsolo",
    "wof:placetype":"locality"
},
  "geometry": {"coordinates":[30.41753,1.70684],"type":"Point"}
}