{
  "type": "Feature",
  "properties": {
    "gn:admin1_code":"19.0",
    "gn:asciiname":"Muboti",
    "gn:country_code":"CD",
    "gn:dem":773,
    "gn:feature_class":"P",
    "gn:feature_code":"PPL",
    "gn:name":"Muboti",
    "gn:population":0,
    "gn:timezone":"Africa/Kinshasa",
    "iso:country":"CD",
    "wof:name":"Muboti",
    "wof:placetype":"locality"
},
  "geometry": {"coordinates":[17.28392,-5.70812],"type":"Point"}
}