{
  "type": "Feature",
  "properties": {
    "gn:admin1_code":"2.0",
    "gn:asciiname":"Bongondo",
    "gn:country_code":"CD",
    "gn:dem":317,
    "gn:feature_class":"P",
    "gn:feature_code":"PPL",
    "gn:name":"Bongondo",
    "gn:population":0,
    "gn:timezone":"Africa/Kinshasa",
    "iso:country":"CD",
    "wof:name":"Bongondo",
    "wof:placetype":"locality"
},
  "geometry": {"coordinates":[18.75,1.31667],"type":"Point"}
}