{
  "type": "Feature",
  "properties": {
    "gn:admin1_code":"12.0",
    "gn:asciiname":"Lukayo",
    "gn:country_code":"CD",
    "gn:dem":1703,
    "gn:feature_class":"P",
    "gn:feature_code":"PPL",
    "gn:name":"Lukayo",
    "gn:population":0,
    "gn:timezone":"Africa/Lubumbashi",
    "iso:country":"CD",
    "wof:name":"Lukayo",
    "wof:placetype":"locality"
},
  "geometry": {"coordinates":[28.82502,-2.17975],"type":"Point"}
}