{
  "type": "Feature",
  "properties": {
    "gn:admin1_code":"22.0",
    "gn:asciiname":"Fwawinwa-Kasongo",
    "gn:country_code":"CD",
    "gn:dem":1138,
    "gn:feature_class":"P",
    "gn:feature_code":"PPL",
    "gn:name":"Fwawinwa-Kasongo",
    "gn:population":0,
    "gn:timezone":"Africa/Lubumbashi",
    "iso:country":"CD",
    "wof:name":"Fwawinwa-Kasongo",
    "wof:placetype":"locality"
},
  "geometry": {"coordinates":[26.27686,-9.94276],"type":"Point"}
}