{
  "type": "Feature",
  "properties": {
    "gn:admin1_code":"13.0",
    "gn:asciiname":"Poko",
    "gn:country_code":"CD",
    "gn:dem":634,
    "gn:feature_class":"P",
    "gn:feature_code":"PPL",
    "gn:name":"Poko",
    "gn:population":0,
    "gn:timezone":"Africa/Lubumbashi",
    "iso:country":"CD",
    "name:ceb_x_preferred":[
        "Poko"
    ],
    "name:deu_x_preferred":[
        "Poko"
    ],
    "name:ita_x_preferred":[
        "Poko"
    ],
    "name:nld_x_preferred":[
        "Poko"
    ],
    "name:swe_x_preferred":[
        "Poko"
    ],
    "wof:name":"Poko",
    "wof:placetype":"locality"
},
  "geometry": {"coordinates":[26.89631,3.15772],"type":"Point"}
}