{
  "type": "Feature",
  "properties": {
    "gn:admin1_code":"20.0",
    "gn:asciiname":"Lumbi Nzinda",
    "gn:country_code":"CD",
    "gn:dem":535,
    "gn:feature_class":"P",
    "gn:feature_code":"PPL",
    "gn:name":"Lumbi Nzinda",
    "gn:population":0,
    "gn:timezone":"Africa/Kinshasa",
    "iso:country":"CD",
    "wof:name":"Lumbi Nzinda",
    "wof:placetype":"locality"
},
  "geometry": {"coordinates":[18.75869,-5.04823],"type":"Point"}
}