{
  "type": "Feature",
  "properties": {
    "gn:admin1_code":"29.0",
    "gn:asciiname":"Kiombe",
    "gn:country_code":"CD",
    "gn:dem":715,
    "gn:feature_class":"P",
    "gn:feature_code":"PPL",
    "gn:name":"Kiombe",
    "gn:population":0,
    "gn:timezone":"Africa/Lubumbashi",
    "iso:country":"CD",
    "wof:name":"Kiombe",
    "wof:placetype":"locality"
},
  "geometry": {"coordinates":[26.76476,-7.39168],"type":"Point"}
}