{
  "type": "Feature",
  "properties": {
    "gn:admin1_code":"22.0",
    "gn:asciiname":"Nawej",
    "gn:country_code":"CD",
    "gn:dem":912,
    "gn:feature_class":"P",
    "gn:feature_code":"PPL",
    "gn:name":"Nawej",
    "gn:population":0,
    "gn:timezone":"Africa/Lubumbashi",
    "iso:country":"CD",
    "wof:name":"Nawej",
    "wof:placetype":"locality"
},
  "geometry": {"coordinates":[22.37019,-8.17731],"type":"Point"}
}