{
  "type": "Feature",
  "properties": {
    "gn:admin1_code":"17.0",
    "gn:asciiname":"Marikandi",
    "gn:country_code":"CD",
    "gn:dem":1271,
    "gn:feature_class":"P",
    "gn:feature_code":"PPL",
    "gn:name":"Marikandi",
    "gn:population":0,
    "gn:timezone":"Africa/Lubumbashi",
    "iso:country":"CD",
    "wof:name":"Marikandi",
    "wof:placetype":"locality"
},
  "geometry": {"coordinates":[30.40862000000001,2.54774],"type":"Point"}
}