{
  "type": "Feature",
  "properties": {
    "gn:admin1_code":"22.0",
    "gn:asciiname":"Sambinga",
    "gn:country_code":"CD",
    "gn:dem":1096,
    "gn:feature_class":"P",
    "gn:feature_code":"PPL",
    "gn:name":"Sambinga",
    "gn:population":0,
    "gn:timezone":"Africa/Lubumbashi",
    "iso:country":"CD",
    "wof:name":"Sambinga",
    "wof:placetype":"locality"
},
  "geometry": {"coordinates":[22.77834,-9.228],"type":"Point"}
}