{
  "type": "Feature",
  "properties": {
    "gn:admin1_code":"15.0",
    "gn:asciiname":"Luba",
    "gn:country_code":"CD",
    "gn:dem":1040,
    "gn:feature_class":"P",
    "gn:feature_code":"PPL",
    "gn:name":"Luba",
    "gn:population":0,
    "gn:timezone":"Africa/Lubumbashi",
    "iso:country":"CD",
    "name:bel_x_preferred":[
        "\u041b\u0443\u0431\u0430"
    ],
    "name:ceb_x_preferred":[
        "Luba"
    ],
    "name:deu_x_preferred":[
        "Luba"
    ],
    "name:eus_x_preferred":[
        "Luba"
    ],
    "name:fin_x_preferred":[
        "Luba"
    ],
    "name:fra_x_preferred":[
        "Luba"
    ],
    "name:ita_x_preferred":[
        "Luba"
    ],
    "name:nld_x_preferred":[
        "Luba"
    ],
    "name:pol_x_preferred":[
        "Luba"
    ],
    "name:rus_x_preferred":[
        "\u041b\u0443\u0431\u0430"
    ],
    "name:spa_x_preferred":[
        "Luba"
    ],
    "name:swe_x_preferred":[
        "Luba"
    ],
    "name:war_x_preferred":[
        "Luba"
    ],
    "wof:name":"Luba",
    "wof:placetype":"locality"
},
  "geometry": {"coordinates":[27.63063,-7.88645],"type":"Point"}
}