{
  "type": "Feature",
  "properties": {
    "gn:admin1_code":"23.0",
    "gn:asciiname":"Lubwelu",
    "gn:country_code":"CD",
    "gn:dem":784,
    "gn:feature_class":"P",
    "gn:feature_code":"PPL",
    "gn:name":"Lubwelu",
    "gn:population":0,
    "gn:timezone":"Africa/Lubumbashi",
    "iso:country":"CD",
    "wof:name":"Lubwelu",
    "wof:placetype":"locality"
},
  "geometry": {"coordinates":[22.97653,-6.184],"type":"Point"}
}