{
  "type": "Feature",
  "properties": {
    "gn:admin1_code":"10.0",
    "gn:asciiname":"Mikeke",
    "gn:country_code":"CD",
    "gn:dem":593,
    "gn:feature_class":"P",
    "gn:feature_code":"PPL",
    "gn:name":"Mikeke",
    "gn:population":0,
    "gn:timezone":"Africa/Lubumbashi",
    "iso:country":"CD",
    "wof:name":"Mikeke",
    "wof:placetype":"locality"
},
  "geometry": {"coordinates":[26.59018,-3.82891],"type":"Point"}
}