{
  "type": "Feature",
  "properties": {
    "gn:admin1_code":"21.0",
    "gn:asciiname":"Ganza",
    "gn:country_code":"CD",
    "gn:dem":989,
    "gn:feature_class":"P",
    "gn:feature_code":"PPL",
    "gn:name":"Ganza",
    "gn:population":0,
    "gn:timezone":"Africa/Lubumbashi",
    "iso:country":"CD",
    "wof:name":"Ganza",
    "wof:placetype":"locality"
},
  "geometry": {"coordinates":[23.34081,-7.77379],"type":"Point"}
}