{
  "type": "Feature",
  "properties": {
    "gn:admin1_code":"17.0",
    "gn:asciiname":"Buenza",
    "gn:country_code":"CD",
    "gn:dem":1381,
    "gn:feature_class":"P",
    "gn:feature_code":"PPL",
    "gn:name":"Buenza",
    "gn:population":0,
    "gn:timezone":"Africa/Lubumbashi",
    "iso:country":"CD",
    "wof:name":"Buenza",
    "wof:placetype":"locality"
},
  "geometry": {"coordinates":[30.04444,2.01564],"type":"Point"}
}