{
  "type": "Feature",
  "properties": {
    "gn:admin1_code":"13.0",
    "gn:asciiname":"Yambo",
    "gn:country_code":"CD",
    "gn:dem":557,
    "gn:feature_class":"P",
    "gn:feature_code":"PPL",
    "gn:name":"Yambo",
    "gn:population":0,
    "gn:timezone":"Africa/Lubumbashi",
    "iso:country":"CD",
    "name:ceb_x_preferred":[
        "Yambo"
    ],
    "name:fra_x_preferred":[
        "Yambo"
    ],
    "name:spa_x_preferred":[
        "Yambo"
    ],
    "name:swe_x_preferred":[
        "Yambo"
    ],
    "wof:name":"Yambo",
    "wof:placetype":"locality"
},
  "geometry": {"coordinates":[24.19453,4.44366],"type":"Point"}
}