{
  "type": "Feature",
  "properties": {
    "gn:admin1_code":"4.0",
    "gn:asciiname":"Kaninda-Pania",
    "gn:country_code":"CD",
    "gn:dem":758,
    "gn:feature_class":"P",
    "gn:feature_code":"PPL",
    "gn:name":"Kaninda-Pania",
    "gn:population":0,
    "gn:timezone":"Africa/Lubumbashi",
    "iso:country":"CD",
    "wof:name":"Kaninda-Pania",
    "wof:placetype":"locality"
},
  "geometry": {"coordinates":[22.98164,-6.01448],"type":"Point"}
}