{
  "type": "Feature",
  "properties": {
    "gn:admin1_code":"13.0",
    "gn:asciiname":"Kaibi",
    "gn:country_code":"CD",
    "gn:dem":639,
    "gn:feature_class":"P",
    "gn:feature_code":"PPL",
    "gn:name":"Kaibi",
    "gn:population":0,
    "gn:timezone":"Africa/Lubumbashi",
    "iso:country":"CD",
    "wof:name":"Kaibi",
    "wof:placetype":"locality"
},
  "geometry": {"coordinates":[25.82098,3.39989],"type":"Point"}
}