{
  "type": "Feature",
  "properties": {
    "gn:admin1_code":"13.0",
    "gn:asciiname":"Bawea",
    "gn:country_code":"CD",
    "gn:dem":605,
    "gn:feature_class":"P",
    "gn:feature_code":"PPL",
    "gn:name":"Bawea",
    "gn:population":0,
    "gn:timezone":"Africa/Lubumbashi",
    "iso:country":"CD",
    "wof:name":"Bawea",
    "wof:placetype":"locality"
},
  "geometry": {"coordinates":[25.67683,3.15016],"type":"Point"}
}