{
  "type": "Feature",
  "properties": {
    "gn:admin1_code":"18.0",
    "gn:asciiname":"Kalembe-Mpata",
    "gn:country_code":"CD",
    "gn:dem":505,
    "gn:feature_class":"P",
    "gn:feature_code":"PPL",
    "gn:name":"Kalembe-Mpata",
    "gn:population":0,
    "gn:timezone":"Africa/Lubumbashi",
    "iso:country":"CD",
    "wof:name":"Kalembe-Mpata",
    "wof:placetype":"locality"
},
  "geometry": {"coordinates":[20.39466,-4.39897],"type":"Point"}
}