{
  "type": "Feature",
  "properties": {
    "gn:admin1_code":"18.0",
    "gn:asciiname":"Banga-Ibundula",
    "gn:country_code":"CD",
    "gn:dem":716,
    "gn:feature_class":"P",
    "gn:feature_code":"PPL",
    "gn:name":"Banga-Ibundula",
    "gn:population":0,
    "gn:timezone":"Africa/Lubumbashi",
    "iso:country":"CD",
    "name:und_x_variant":[
        "Banga Ibundola",
        "Banga-Ibundula"
    ],
    "wof:name":"Banga-Ibundula",
    "wof:placetype":"locality"
},
  "geometry": {"coordinates":[20.52679,-5.45572],"type":"Point"}
}