{
  "type": "Feature",
  "properties": {
    "gn:admin1_code":"2.0",
    "gn:asciiname":"Ilanga Premiere",
    "gn:country_code":"CD",
    "gn:dem":320,
    "gn:feature_class":"P",
    "gn:feature_code":"PPL",
    "gn:name":"Ilanga Premi\u00e8re",
    "gn:population":0,
    "gn:timezone":"Africa/Kinshasa",
    "iso:country":"CD",
    "wof:name":"Ilanga Premiere",
    "wof:placetype":"locality"
},
  "geometry": {"coordinates":[18.23591,-0.2431],"type":"Point"}
}