{
  "type": "Feature",
  "properties": {
    "gn:admin1_code":"18.0",
    "gn:asciiname":"Shamuhele",
    "gn:country_code":"CD",
    "gn:dem":734,
    "gn:feature_class":"P",
    "gn:feature_code":"PPL",
    "gn:name":"Shamuhele",
    "gn:population":0,
    "gn:timezone":"Africa/Lubumbashi",
    "iso:country":"CD",
    "name:und_x_variant":[
        "Shamuele",
        "Shamuhele"
    ],
    "wof:name":"Shamuhele",
    "wof:placetype":"locality"
},
  "geometry": {"coordinates":[20.78176,-7.06919],"type":"Point"}
}