{
  "type": "Feature",
  "properties": {
    "gn:admin1_code":"8.0",
    "gn:asciiname":"Mbemba",
    "gn:country_code":"CD",
    "gn:dem":746,
    "gn:feature_class":"P",
    "gn:feature_code":"PPL",
    "gn:name":"Mbemba",
    "gn:population":0,
    "gn:timezone":"Africa/Kinshasa",
    "iso:country":"CD",
    "name:ceb_x_preferred":[
        "Mbemba"
    ],
    "name:deu_x_preferred":[
        "Mbemba"
    ],
    "name:fra_x_preferred":[
        "Mbemba"
    ],
    "name:swe_x_preferred":[
        "Mbemba"
    ],
    "wof:name":"Mbemba",
    "wof:placetype":"locality"
},
  "geometry": {"coordinates":[15.37431,-5.66621],"type":"Point"}
}