{
  "type": "Feature",
  "properties": {
    "gn:admin1_code":"16.0",
    "gn:asciiname":"Mandoro",
    "gn:country_code":"CD",
    "gn:dem":759,
    "gn:feature_class":"P",
    "gn:feature_code":"PPL",
    "gn:name":"Mandoro",
    "gn:population":0,
    "gn:timezone":"Africa/Lubumbashi",
    "iso:country":"CD",
    "name:und_x_variant":[
        "Tongatanga",
        "Mandoro"
    ],
    "wof:name":"Mandoro",
    "wof:placetype":"locality"
},
  "geometry": {"coordinates":[28.46188,4.18613],"type":"Point"}
}