{
  "type": "Feature",
  "properties": {
    "gn:admin1_code":"22.0",
    "gn:asciiname":"Mwin Mbiji",
    "gn:country_code":"CD",
    "gn:dem":988,
    "gn:feature_class":"P",
    "gn:feature_code":"PPL",
    "gn:name":"Mwin Mbiji",
    "gn:population":0,
    "gn:timezone":"Africa/Lubumbashi",
    "iso:country":"CD",
    "name:und_x_variant":[
        "Mwana Bishi",
        "Bezi",
        "Mwin Mbiji"
    ],
    "wof:name":"Mwin Mbiji",
    "wof:placetype":"locality"
},
  "geometry": {"coordinates":[23.85275,-9.20956],"type":"Point"}
}