{
  "type": "Feature",
  "properties": {
    "gn:admin1_code":"11.0",
    "gn:asciiname":"Ngoma",
    "gn:country_code":"CD",
    "gn:dem":993,
    "gn:feature_class":"P",
    "gn:feature_code":"PPL",
    "gn:name":"Ngoma",
    "gn:population":0,
    "gn:timezone":"Africa/Lubumbashi",
    "iso:country":"CD",
    "name:bar_x_preferred":[
        "Ngoma"
    ],
    "name:ceb_x_preferred":[
        "Ngoma"
    ],
    "name:deu_x_preferred":[
        "Ngoma"
    ],
    "name:est_x_preferred":[
        "Ngoma"
    ],
    "name:fra_x_preferred":[
        "Ngoma"
    ],
    "name:ita_x_preferred":[
        "Ngoma"
    ],
    "name:pol_x_preferred":[
        "Ngoma"
    ],
    "name:swa_x_preferred":[
        "Ngoma"
    ],
    "name:swe_x_preferred":[
        "Ngoma"
    ],
    "wof:name":"Ngoma",
    "wof:placetype":"locality"
},
  "geometry": {"coordinates":[28.76148,0.3502],"type":"Point"}
}