{
  "type": "Feature",
  "properties": {
    "gn:admin1_code":"19.0",
    "gn:asciiname":"Kambundi-Ndindi",
    "gn:country_code":"CD",
    "gn:dem":781,
    "gn:feature_class":"P",
    "gn:feature_code":"PPL",
    "gn:name":"Kambundi-Ndindi",
    "gn:population":0,
    "gn:timezone":"Africa/Kinshasa",
    "iso:country":"CD",
    "name:und_x_variant":[
        "Ndindi",
        "Kambundi-Ndindi"
    ],
    "wof:name":"Kambundi-Ndindi",
    "wof:placetype":"locality"
},
  "geometry": {"coordinates":[17.45734,-6.23479],"type":"Point"}
}