{
  "type": "Feature",
  "properties": {
    "gn:admin1_code":"13.0",
    "gn:asciiname":"Gobela",
    "gn:country_code":"CD",
    "gn:dem":626,
    "gn:feature_class":"P",
    "gn:feature_code":"PPL",
    "gn:name":"Gobela",
    "gn:population":0,
    "gn:timezone":"Africa/Lubumbashi",
    "iso:country":"CD",
    "wof:name":"Gobela",
    "wof:placetype":"locality"
},
  "geometry": {"coordinates":[26.34072,2.48875],"type":"Point"}
}