{
  "type": "Feature",
  "properties": {
    "gn:admin1_code":"18.0",
    "gn:asciiname":"Mukalenge",
    "gn:country_code":"CD",
    "gn:dem":632,
    "gn:feature_class":"P",
    "gn:feature_code":"PPL",
    "gn:name":"Mukalenge",
    "gn:population":0,
    "gn:timezone":"Africa/Lubumbashi",
    "iso:country":"CD",
    "wof:name":"Mukalenge",
    "wof:placetype":"locality"
},
  "geometry": {"coordinates":[20.46991,-5.90504],"type":"Point"}
}