{
  "type": "Feature",
  "properties": {
    "gn:admin1_code":"24.0",
    "gn:asciiname":"Onkwankus",
    "gn:country_code":"CD",
    "gn:dem":330,
    "gn:feature_class":"P",
    "gn:feature_code":"PPL",
    "gn:name":"Onkwankus",
    "gn:population":0,
    "gn:timezone":"Africa/Kinshasa",
    "iso:country":"CD",
    "name:und_x_variant":[
        "Onkwankusu"
    ],
    "wof:name":"Onkwankus",
    "wof:placetype":"locality"
},
  "geometry": {"coordinates":[19.54116,-1.9851],"type":"Point"}
}