{
  "type": "Feature",
  "properties": {
    "gn:admin1_code":"18.0",
    "gn:asciiname":"Shayaluya",
    "gn:country_code":"CD",
    "gn:dem":810,
    "gn:feature_class":"P",
    "gn:feature_code":"PPL",
    "gn:name":"Shayaluya",
    "gn:population":0,
    "gn:timezone":"Africa/Lubumbashi",
    "iso:country":"CD",
    "wof:name":"Shayaluya",
    "wof:placetype":"locality"
},
  "geometry": {"coordinates":[20.32172000000001,-6.52591],"type":"Point"}
}