{
  "type": "Feature",
  "properties": {
    "gn:admin1_code":"18.0",
    "gn:asciiname":"Muamushiku",
    "gn:country_code":"CD",
    "gn:dem":759,
    "gn:feature_class":"P",
    "gn:feature_code":"PPL",
    "gn:name":"Muamushiku",
    "gn:population":0,
    "gn:timezone":"Africa/Lubumbashi",
    "iso:country":"CD",
    "wof:name":"Muamushiku",
    "wof:placetype":"locality"
},
  "geometry": {"coordinates":[21.14515,-7.21402],"type":"Point"}
}