{
  "type": "Feature",
  "properties": {
    "gn:admin1_code":"27.0",
    "gn:asciiname":"Awango",
    "gn:country_code":"CD",
    "gn:dem":494,
    "gn:feature_class":"P",
    "gn:feature_code":"PPL",
    "gn:name":"Awango",
    "gn:population":0,
    "gn:timezone":"Africa/Lubumbashi",
    "iso:country":"CD",
    "wof:name":"Awango",
    "wof:placetype":"locality"
},
  "geometry": {"coordinates":[22.23333,-3.36667],"type":"Point"}
}