{
  "type": "Feature",
  "properties": {
    "gn:admin1_code":"13.0",
    "gn:asciiname":"Zoza",
    "gn:country_code":"CD",
    "gn:dem":686,
    "gn:feature_class":"P",
    "gn:feature_code":"PPL",
    "gn:name":"Zoza",
    "gn:population":0,
    "gn:timezone":"Africa/Lubumbashi",
    "iso:country":"CD",
    "name:cat_x_preferred":[
        "Zoza"
    ],
    "name:ceb_x_preferred":[
        "Zoza"
    ],
    "name:cos_x_preferred":[
        "Zoza"
    ],
    "name:deu_x_preferred":[
        "Zoza"
    ],
    "name:eus_x_preferred":[
        "Zoza"
    ],
    "name:fra_x_preferred":[
        "Zoza"
    ],
    "name:hun_x_preferred":[
        "Zoza"
    ],
    "name:hye_x_preferred":[
        "\u0536\u0578\u0566\u0561"
    ],
    "name:ind_x_preferred":[
        "Zoza"
    ],
    "name:ita_x_preferred":[
        "Zoza"
    ],
    "name:kaz_x_preferred":[
        "\u0426\u043e\u0446\u0430"
    ],
    "name:lat_x_preferred":[
        "Zoza"
    ],
    "name:lmo_x_preferred":[
        "Zoza"
    ],
    "name:msa_x_preferred":[
        "Zoza"
    ],
    "name:nld_x_preferred":[
        "Zoza"
    ],
    "name:nor_x_preferred":[
        "Zoza"
    ],
    "name:oci_x_preferred":[
        "Zoza"
    ],
    "name:pms_x_preferred":[
        "Zoza"
    ],
    "name:pol_x_preferred":[
        "Zoza"
    ],
    "name:por_x_preferred":[
        "Zoza"
    ],
    "name:rus_x_preferred":[
        "\u0414\u0437\u043e\u0434\u0437\u0430"
    ],
    "name:slk_x_preferred":[
        "Zoza"
    ],
    "name:slv_x_preferred":[
        "Zoza"
    ],
    "name:spa_x_preferred":[
        "Zoza"
    ],
    "name:swe_x_preferred":[
        "Zoza"
    ],
    "name:ukr_x_preferred":[
        "\u0426\u043e\u0446\u0430"
    ],
    "name:vie_x_preferred":[
        "Zoza"
    ],
    "name:vol_x_preferred":[
        "Zoza"
    ],
    "name:war_x_preferred":[
        "Zoza"
    ],
    "wof:name":"Zoza",
    "wof:placetype":"locality"
},
  "geometry": {"coordinates":[27.04513,3.16836],"type":"Point"}
}