{
  "type": "Feature",
  "properties": {
    "gn:admin1_code":"13.0",
    "gn:asciiname":"Zoza",
    "gn:country_code":"CD",
    "gn:dem":686,
    "gn:feature_class":"P",
    "gn:feature_code":"PPL",
    "gn:name":"Zoza",
    "gn:population":0,
    "gn:timezone":"Africa/Lubumbashi",
    "iso:country":"CD",
    "wof:name":"Zoza",
    "wof:placetype":"locality"
},
  "geometry": {"coordinates":[27.04513,3.16836],"type":"Point"}
}