{
  "type": "Feature",
  "properties": {
    "gn:admin1_code":"19.0",
    "gn:asciiname":"Kangu",
    "gn:country_code":"CD",
    "gn:dem":978,
    "gn:feature_class":"P",
    "gn:feature_code":"PPL",
    "gn:name":"Kangu",
    "gn:population":0,
    "gn:timezone":"Africa/Kinshasa",
    "iso:country":"CD",
    "wof:name":"Kangu",
    "wof:placetype":"locality"
},
  "geometry": {"coordinates":[17.68631,-6.88604],"type":"Point"}
}