{
  "type": "Feature",
  "properties": {
    "gn:admin1_code":"30.0",
    "gn:asciiname":"Bolika",
    "gn:country_code":"CD",
    "gn:dem":480,
    "gn:feature_class":"P",
    "gn:feature_code":"PPL",
    "gn:name":"Bolika",
    "gn:population":0,
    "gn:timezone":"Africa/Lubumbashi",
    "iso:country":"CD",
    "wof:name":"Bolika",
    "wof:placetype":"locality"
},
  "geometry": {"coordinates":[24.18593,1.80184],"type":"Point"}
}