{
  "type": "Feature",
  "properties": {
    "gn:admin1_code":"18.0",
    "gn:asciiname":"Shamukumbi",
    "gn:country_code":"CD",
    "gn:dem":636,
    "gn:feature_class":"P",
    "gn:feature_code":"PPL",
    "gn:name":"Shamukumbi",
    "gn:population":0,
    "gn:timezone":"Africa/Lubumbashi",
    "iso:country":"CD",
    "wof:name":"Shamukumbi",
    "wof:placetype":"locality"
},
  "geometry": {"coordinates":[20.96709,-6.90798],"type":"Point"}
}