{
  "type": "Feature",
  "properties": {
    "gn:admin1_code":"24.0",
    "gn:asciiname":"Mosebwaka",
    "gn:country_code":"CD",
    "gn:dem":288,
    "gn:feature_class":"P",
    "gn:feature_code":"PPL",
    "gn:name":"Mosebwaka",
    "gn:population":0,
    "gn:timezone":"Africa/Kinshasa",
    "iso:country":"CD",
    "name:und_x_variant":[
        "Moseboaka",
        "Mosebwaka"
    ],
    "wof:name":"Mosebwaka",
    "wof:placetype":"locality"
},
  "geometry": {"coordinates":[16.20739,-2.75742],"type":"Point"}
}