{
  "type": "Feature",
  "properties": {
    "gn:admin1_code":"20.0",
    "gn:asciiname":"Mpo",
    "gn:country_code":"CD",
    "gn:dem":373,
    "gn:feature_class":"P",
    "gn:feature_code":"PPL",
    "gn:name":"Mpo",
    "gn:population":0,
    "gn:timezone":"Africa/Kinshasa",
    "iso:country":"CD",
    "wof:name":"Mpo",
    "wof:placetype":"locality"
},
  "geometry": {"coordinates":[18.59067000000001,-3.73088],"type":"Point"}
}