{
  "type": "Feature",
  "properties": {
    "gn:admin1_code":"30.0",
    "gn:asciiname":"Yafakituru",
    "gn:country_code":"CD",
    "gn:dem":432,
    "gn:feature_class":"P",
    "gn:feature_code":"PPL",
    "gn:name":"Yafakituru",
    "gn:population":0,
    "gn:timezone":"Africa/Lubumbashi",
    "iso:country":"CD",
    "wof:name":"Yafakituru",
    "wof:placetype":"locality"
},
  "geometry": {"coordinates":[24.16667,-0.21667],"type":"Point"}
}