{
  "type": "Feature",
  "properties": {
    "gn:admin1_code":"8.0",
    "gn:asciiname":"Kikangaya",
    "gn:country_code":"CD",
    "gn:dem":546,
    "gn:feature_class":"P",
    "gn:feature_code":"PPL",
    "gn:name":"Kikangaya",
    "gn:population":0,
    "gn:timezone":"Africa/Kinshasa",
    "iso:country":"CD",
    "wof:name":"Kikangaya",
    "wof:placetype":"locality"
},
  "geometry": {"coordinates":[14.2492,-4.47766],"type":"Point"}
}