{
  "type": "Feature",
  "properties": {
    "gn:admin1_code":"21.0",
    "gn:asciiname":"Bena",
    "gn:country_code":"CD",
    "gn:dem":823,
    "gn:feature_class":"P",
    "gn:feature_code":"PPL",
    "gn:name":"Bena",
    "gn:population":0,
    "gn:timezone":"Africa/Lubumbashi",
    "iso:country":"CD",
    "name:cat_x_preferred":[
        "Bena"
    ],
    "name:ceb_x_preferred":[
        "Bena"
    ],
    "name:deu_x_preferred":[
        "Bena"
    ],
    "name:fra_x_preferred":[
        "Bena"
    ],
    "name:hun_x_preferred":[
        "Bena"
    ],
    "name:nld_x_preferred":[
        "Bena"
    ],
    "name:pol_x_preferred":[
        "Bena"
    ],
    "name:por_x_preferred":[
        "Bena"
    ],
    "name:rus_x_preferred":[
        "\u0411\u0438\u043d\u0430"
    ],
    "name:swe_x_preferred":[
        "Bena"
    ],
    "wof:name":"Bena",
    "wof:placetype":"locality"
},
  "geometry": {"coordinates":[23.23745,-6.62978],"type":"Point"}
}