{
  "type": "Feature",
  "properties": {
    "gn:admin1_code":"19.0",
    "gn:asciiname":"Tsakala-Tutu",
    "gn:country_code":"CD",
    "gn:dem":711,
    "gn:feature_class":"P",
    "gn:feature_code":"PPL",
    "gn:name":"Tsakala-Tutu",
    "gn:population":0,
    "gn:timezone":"Africa/Kinshasa",
    "iso:country":"CD",
    "wof:name":"Tsakala-Tutu",
    "wof:placetype":"locality"
},
  "geometry": {"coordinates":[16.90449,-5.43785],"type":"Point"}
}