{
  "type": "Feature",
  "properties": {
    "gn:admin1_code":"31.0",
    "gn:asciiname":"Liombo",
    "gn:country_code":"CD",
    "gn:dem":395,
    "gn:feature_class":"P",
    "gn:feature_code":"PPL",
    "gn:name":"Liombo",
    "gn:population":0,
    "gn:timezone":"Africa/Kinshasa",
    "iso:country":"CD",
    "wof:name":"Liombo",
    "wof:placetype":"locality"
},
  "geometry": {"coordinates":[20.76667,-1.56667],"type":"Point"}
}