{
  "type": "Feature",
  "properties": {
    "gn:admin1_code":"22.0",
    "gn:asciiname":"Wifika",
    "gn:country_code":"CD",
    "gn:dem":940,
    "gn:feature_class":"P",
    "gn:feature_code":"PPL",
    "gn:name":"Wifika",
    "gn:population":0,
    "gn:timezone":"Africa/Lubumbashi",
    "iso:country":"CD",
    "wof:name":"Wifika",
    "wof:placetype":"locality"
},
  "geometry": {"coordinates":[24.8517,-10.09686],"type":"Point"}
}