{
  "type": "Feature",
  "properties": {
    "gn:admin1_code":"30.0",
    "gn:asciiname":"Bandjambo",
    "gn:country_code":"CD",
    "gn:dem":465,
    "gn:feature_class":"P",
    "gn:feature_code":"PPL",
    "gn:name":"Bandjambo",
    "gn:population":0,
    "gn:timezone":"Africa/Lubumbashi",
    "iso:country":"CD",
    "wof:name":"Bandjambo",
    "wof:placetype":"locality"
},
  "geometry": {"coordinates":[25.4176,1.44389],"type":"Point"}
}