{
  "type": "Feature",
  "properties": {
    "gn:admin1_code":"31.0",
    "gn:asciiname":"Besongote",
    "gn:country_code":"CD",
    "gn:dem":375,
    "gn:feature_class":"P",
    "gn:feature_code":"PPL",
    "gn:name":"Besongote",
    "gn:population":0,
    "gn:timezone":"Africa/Kinshasa",
    "iso:country":"CD",
    "name:und_x_variant":[
        "Bosongote",
        "Besongote",
        "Besongole"
    ],
    "wof:name":"Besongote",
    "wof:placetype":"locality"
},
  "geometry": {"coordinates":[21.09907,-0.58575],"type":"Point"}
}