{
  "type": "Feature",
  "properties": {
    "gn:admin1_code":"24.0",
    "gn:asciiname":"Bokoliwango",
    "gn:country_code":"CD",
    "gn:dem":324,
    "gn:feature_class":"P",
    "gn:feature_code":"PPL",
    "gn:name":"Bokoliwango",
    "gn:population":0,
    "gn:timezone":"Africa/Kinshasa",
    "iso:country":"CD",
    "wof:name":"Bokoliwango",
    "wof:placetype":"locality"
},
  "geometry": {"coordinates":[19.43333,-2.28333],"type":"Point"}
}