{
  "type": "Feature",
  "properties": {
    "gn:admin1_code":"4.0",
    "gn:asciiname":"Nkole-Mayombo",
    "gn:country_code":"CD",
    "gn:dem":653,
    "gn:feature_class":"P",
    "gn:feature_code":"PPL",
    "gn:name":"Nkole-Mayombo",
    "gn:population":0,
    "gn:timezone":"Africa/Lubumbashi",
    "iso:country":"CD",
    "wof:name":"Nkole-Mayombo",
    "wof:placetype":"locality"
},
  "geometry": {"coordinates":[23.52612,-6.23343],"type":"Point"}
}