{
  "type": "Feature",
  "properties": {
    "gn:admin1_code":"22.0",
    "gn:asciiname":"Salupepa",
    "gn:country_code":"CD",
    "gn:dem":1040,
    "gn:feature_class":"P",
    "gn:feature_code":"PPL",
    "gn:name":"Salupepa",
    "gn:population":0,
    "gn:timezone":"Africa/Lubumbashi",
    "iso:country":"CD",
    "wof:name":"Salupepa",
    "wof:placetype":"locality"
},
  "geometry": {"coordinates":[22.5229,-10.19315],"type":"Point"}
}