{
  "type": "Feature",
  "properties": {
    "gn:admin1_code":"13.0",
    "gn:asciiname":"Nabulangwe",
    "gn:country_code":"CD",
    "gn:dem":650,
    "gn:feature_class":"P",
    "gn:feature_code":"PPL",
    "gn:name":"Nabulangwe",
    "gn:population":0,
    "gn:timezone":"Africa/Lubumbashi",
    "iso:country":"CD",
    "wof:name":"Nabulangwe",
    "wof:placetype":"locality"
},
  "geometry": {"coordinates":[26.37456,2.47185],"type":"Point"}
}