{
  "type": "Feature",
  "properties": {
    "gn:admin1_code":"22.0",
    "gn:asciiname":"Mwant Kanzal",
    "gn:country_code":"CD",
    "gn:dem":1057,
    "gn:feature_class":"P",
    "gn:feature_code":"PPL",
    "gn:name":"Mwant Kanzal",
    "gn:population":0,
    "gn:timezone":"Africa/Lubumbashi",
    "iso:country":"CD",
    "name:und_x_variant":[
        "Mwata-Kansele"
    ],
    "wof:name":"Mwant Kanzal",
    "wof:placetype":"locality"
},
  "geometry": {"coordinates":[23.01634,-8.34586],"type":"Point"}
}