{
  "type": "Feature",
  "properties": {
    "gn:admin1_code":"14.0",
    "gn:asciiname":"Kapolowe",
    "gn:country_code":"CD",
    "gn:dem":1177,
    "gn:feature_class":"P",
    "gn:feature_code":"PPL",
    "gn:name":"Kapolowe",
    "gn:population":0,
    "gn:timezone":"Africa/Lubumbashi",
    "iso:country":"CD",
    "wof:name":"Kapolowe",
    "wof:placetype":"locality"
},
  "geometry": {"coordinates":[26.971,-11.06125],"type":"Point"}
}