{
  "type": "Feature",
  "properties": {
    "gn:admin1_code":"23.0",
    "gn:asciiname":"Mbaie",
    "gn:country_code":"CD",
    "gn:dem":661,
    "gn:feature_class":"P",
    "gn:feature_code":"PPL",
    "gn:name":"Mbaie",
    "gn:population":0,
    "gn:timezone":"Africa/Lubumbashi",
    "iso:country":"CD",
    "wof:name":"Mbaie",
    "wof:placetype":"locality"
},
  "geometry": {"coordinates":[22.56619,-5.91564],"type":"Point"}
}