{
  "type": "Feature",
  "properties": {
    "gn:admin1_code":"8.0",
    "gn:asciiname":"Kinzila",
    "gn:country_code":"CD",
    "gn:dem":456,
    "gn:feature_class":"P",
    "gn:feature_code":"PPL",
    "gn:name":"Kinzila",
    "gn:population":0,
    "gn:timezone":"Africa/Kinshasa",
    "iso:country":"CD",
    "wof:name":"Kinzila",
    "wof:placetype":"locality"
},
  "geometry": {"coordinates":[15.19513,-4.63107],"type":"Point"}
}