{
  "type": "Feature",
  "properties": {
    "gn:admin1_code":"19.0",
    "gn:asciiname":"Mwana-Uta_Kambundi",
    "gn:country_code":"CD",
    "gn:dem":813,
    "gn:feature_class":"P",
    "gn:feature_code":"PPL",
    "gn:name":"Mwana-Uta_Kambundi",
    "gn:population":0,
    "gn:timezone":"Africa/Kinshasa",
    "iso:country":"CD",
    "wof:name":"Mwana-Uta_Kambundi",
    "wof:placetype":"locality"
},
  "geometry": {"coordinates":[18.17087,-7.54109],"type":"Point"}
}