{
  "type": "Feature",
  "properties": {
    "gn:admin1_code":"19.0",
    "gn:asciiname":"Mokwenge",
    "gn:country_code":"CD",
    "gn:dem":535,
    "gn:feature_class":"P",
    "gn:feature_code":"PPL",
    "gn:name":"Mokwenge",
    "gn:population":0,
    "gn:timezone":"Africa/Luanda",
    "iso:country":"CD",
    "wof:name":"Mokwenge",
    "wof:placetype":"locality"
},
  "geometry": {"coordinates":[16.72846,-6.43199],"type":"Point"}
}