{
  "type": "Feature",
  "properties": {
    "gn:admin1_code":"22.0",
    "gn:asciiname":"Liatemuna",
    "gn:country_code":"CD",
    "gn:dem":1181,
    "gn:feature_class":"P",
    "gn:feature_code":"PPL",
    "gn:name":"Liatemuna",
    "gn:population":0,
    "gn:timezone":"Africa/Lubumbashi",
    "iso:country":"CD",
    "wof:name":"Liatemuna",
    "wof:placetype":"locality"
},
  "geometry": {"coordinates":[23.22086,-10.84662],"type":"Point"}
}