{
  "type": "Feature",
  "properties": {
    "gn:admin1_code":"15.0",
    "gn:asciiname":"Maucha",
    "gn:country_code":"CD",
    "gn:dem":917,
    "gn:feature_class":"P",
    "gn:feature_code":"PPL",
    "gn:name":"Maucha",
    "gn:population":0,
    "gn:timezone":"Africa/Lubumbashi",
    "iso:country":"CD",
    "wof:name":"Maucha",
    "wof:placetype":"locality"
},
  "geometry": {"coordinates":[25.2337,-7.31508],"type":"Point"}
}