{
  "type": "Feature",
  "properties": {
    "gn:admin1_code":"24.0",
    "gn:asciiname":"Bokobomo",
    "gn:country_code":"CD",
    "gn:dem":469,
    "gn:feature_class":"P",
    "gn:feature_code":"PPL",
    "gn:name":"Bokobomo",
    "gn:population":0,
    "gn:timezone":"Africa/Kinshasa",
    "iso:country":"CD",
    "wof:name":"Bokobomo",
    "wof:placetype":"locality"
},
  "geometry": {"coordinates":[16.50392,-2.82287],"type":"Point"}
}