{
  "type": "Feature",
  "properties": {
    "gn:admin1_code":"10.0",
    "gn:asciiname":"Katako Kombe",
    "gn:country_code":"CD",
    "gn:dem":499,
    "gn:feature_class":"P",
    "gn:feature_code":"PPL",
    "gn:name":"Katako Kombe",
    "gn:population":0,
    "gn:timezone":"Africa/Lubumbashi",
    "iso:country":"CD",
    "wof:name":"Katako Kombe",
    "wof:placetype":"locality"
},
  "geometry": {"coordinates":[25.871,-2.97185],"type":"Point"}
}