{
  "type": "Feature",
  "properties": {
    "gn:admin1_code":"19.0",
    "gn:asciiname":"Gunda",
    "gn:country_code":"CD",
    "gn:dem":825,
    "gn:feature_class":"P",
    "gn:feature_code":"PPL",
    "gn:name":"Gunda",
    "gn:population":0,
    "gn:timezone":"Africa/Kinshasa",
    "iso:country":"CD",
    "name:ceb_x_preferred":[
        "Gunda"
    ],
    "name:hun_x_preferred":[
        "Gunda"
    ],
    "name:lat_x_preferred":[
        "Gunda"
    ],
    "name:por_x_preferred":[
        "Gunda"
    ],
    "name:swe_x_preferred":[
        "Gunda"
    ],
    "name:vie_x_preferred":[
        "Gunda"
    ],
    "name:war_x_preferred":[
        "Gunda"
    ],
    "wof:name":"Gunda",
    "wof:placetype":"locality"
},
  "geometry": {"coordinates":[19.23413,-6.23141],"type":"Point"}
}