{
  "type": "Feature",
  "properties": {
    "gn:admin1_code":"19.0",
    "gn:asciiname":"Kingulu-Dunga",
    "gn:country_code":"CD",
    "gn:dem":357,
    "gn:feature_class":"P",
    "gn:feature_code":"PPL",
    "gn:name":"Kingulu-Dunga",
    "gn:population":0,
    "gn:timezone":"Africa/Kinshasa",
    "iso:country":"CD",
    "wof:name":"Kingulu-Dunga",
    "wof:placetype":"locality"
},
  "geometry": {"coordinates":[17.67078,-4.54666],"type":"Point"}
}