{
  "type": "Feature",
  "properties": {
    "gn:admin1_code":"8.0",
    "gn:asciiname":"Kimpemba",
    "gn:country_code":"CD",
    "gn:dem":654,
    "gn:feature_class":"P",
    "gn:feature_code":"PPL",
    "gn:name":"Kimpemba",
    "gn:population":0,
    "gn:timezone":"Africa/Kinshasa",
    "iso:country":"CD",
    "name:und_x_variant":[
        "Kimpamba",
        "Kimpemba"
    ],
    "wof:name":"Kimpemba",
    "wof:placetype":"locality"
},
  "geometry": {"coordinates":[15.30604,-5.48557],"type":"Point"}
}