{
  "type": "Feature",
  "properties": {
    "gn:admin1_code":"19.0",
    "gn:asciiname":"Kiala-Longo",
    "gn:country_code":"CD",
    "gn:dem":832,
    "gn:feature_class":"P",
    "gn:feature_code":"PPL",
    "gn:name":"Kiala-Longo",
    "gn:population":0,
    "gn:timezone":"Africa/Kinshasa",
    "iso:country":"CD",
    "wof:name":"Kiala-Longo",
    "wof:placetype":"locality"
},
  "geometry": {"coordinates":[16.93533,-6.13387],"type":"Point"}
}