{
  "type": "Feature",
  "properties": {
    "gn:admin1_code":"10.0",
    "gn:asciiname":"Shabani",
    "gn:country_code":"CD",
    "gn:dem":644,
    "gn:feature_class":"P",
    "gn:feature_code":"PPL",
    "gn:name":"Shabani",
    "gn:population":0,
    "gn:timezone":"Africa/Lubumbashi",
    "iso:country":"CD",
    "wof:name":"Shabani",
    "wof:placetype":"locality"
},
  "geometry": {"coordinates":[27.24275,-4.37995],"type":"Point"}
}