{
  "type": "Feature",
  "properties": {
    "gn:admin1_code":"10.0",
    "gn:asciiname":"Shabani",
    "gn:country_code":"CD",
    "gn:dem":644,
    "gn:feature_class":"P",
    "gn:feature_code":"PPL",
    "gn:name":"Shabani",
    "gn:population":0,
    "gn:timezone":"Africa/Lubumbashi",
    "iso:country":"CD",
    "name:bar_x_preferred":[
        "Shabani"
    ],
    "name:deu_x_preferred":[
        "Shabani"
    ],
    "name:fas_x_preferred":[
        "\u0634\u0639\u0628\u0627\u0646\u06cc"
    ],
    "name:sqi_x_preferred":[
        "Shabani"
    ],
    "wof:name":"Shabani",
    "wof:placetype":"locality"
},
  "geometry": {"coordinates":[27.24275,-4.37995],"type":"Point"}
}