{
  "type": "Feature",
  "properties": {
    "gn:admin1_code":"18.0",
    "gn:asciiname":"Ekumbi",
    "gn:country_code":"CD",
    "gn:dem":439,
    "gn:feature_class":"P",
    "gn:feature_code":"PPL",
    "gn:name":"Ekumbi",
    "gn:population":0,
    "gn:timezone":"Africa/Lubumbashi",
    "iso:country":"CD",
    "wof:name":"Ekumbi",
    "wof:placetype":"locality"
},
  "geometry": {"coordinates":[21.24883,-4.69851],"type":"Point"}
}