{
  "type": "Feature",
  "properties": {
    "gn:admin1_code":"27.0",
    "gn:asciiname":"Kasumbi",
    "gn:country_code":"CD",
    "gn:dem":561,
    "gn:feature_class":"P",
    "gn:feature_code":"PPL",
    "gn:name":"Kasumbi",
    "gn:population":0,
    "gn:timezone":"Africa/Lubumbashi",
    "iso:country":"CD",
    "wof:name":"Kasumbi",
    "wof:placetype":"locality"
},
  "geometry": {"coordinates":[23.26942,-4.98813],"type":"Point"}
}