{
  "type": "Feature",
  "properties": {
    "gn:admin1_code":"23.0",
    "gn:asciiname":"Tshimana Mashole",
    "gn:country_code":"CD",
    "gn:dem":802,
    "gn:feature_class":"P",
    "gn:feature_code":"PPL",
    "gn:name":"Tshimana Mashole",
    "gn:population":0,
    "gn:timezone":"Africa/Lubumbashi",
    "iso:country":"CD",
    "wof:name":"Tshimana Mashole",
    "wof:placetype":"locality"
},
  "geometry": {"coordinates":[22.76437,-6.45409],"type":"Point"}
}