{
  "type": "Feature",
  "properties": {
    "gn:admin1_code":"13.0",
    "gn:asciiname":"Dusio",
    "gn:country_code":"CD",
    "gn:dem":609,
    "gn:feature_class":"P",
    "gn:feature_code":"PPL",
    "gn:name":"Dusio",
    "gn:population":0,
    "gn:timezone":"Africa/Lubumbashi",
    "iso:country":"CD",
    "wof:name":"Dusio",
    "wof:placetype":"locality"
},
  "geometry": {"coordinates":[25.46323,3.65704],"type":"Point"}
}