{
  "type": "Feature",
  "properties": {
    "gn:admin1_code":"8.0",
    "gn:asciiname":"Kiloango",
    "gn:country_code":"CD",
    "gn:dem":765,
    "gn:feature_class":"P",
    "gn:feature_code":"PPL",
    "gn:name":"Kiloango",
    "gn:population":0,
    "gn:timezone":"Africa/Kinshasa",
    "iso:country":"CD",
    "wof:name":"Kiloango",
    "wof:placetype":"locality"
},
  "geometry": {"coordinates":[15.21327,-5.8497],"type":"Point"}
}