{
  "type": "Feature",
  "properties": {
    "gn:admin1_code":"22.0",
    "gn:asciiname":"Tshilanda",
    "gn:country_code":"CD",
    "gn:dem":1014,
    "gn:feature_class":"P",
    "gn:feature_code":"PPL",
    "gn:name":"Tshilanda",
    "gn:population":0,
    "gn:timezone":"Africa/Lubumbashi",
    "iso:country":"CD",
    "wof:name":"Tshilanda",
    "wof:placetype":"locality"
},
  "geometry": {"coordinates":[23.67115,-9.68717],"type":"Point"}
}