{
  "type": "Feature",
  "properties": {
    "gn:admin1_code":"2.0",
    "gn:asciiname":"Sikoro",
    "gn:country_code":"CD",
    "gn:dem":325,
    "gn:feature_class":"P",
    "gn:feature_code":"PPL",
    "gn:name":"Sikoro",
    "gn:population":0,
    "gn:timezone":"Africa/Kinshasa",
    "iso:country":"CD",
    "wof:name":"Sikoro",
    "wof:placetype":"locality"
},
  "geometry": {"coordinates":[18.29653,1.37745],"type":"Point"}
}