{
  "type": "Feature",
  "properties": {
    "gn:admin1_code":"8.0",
    "gn:asciiname":"Mbanza Mboma",
    "gn:country_code":"CD",
    "gn:dem":506,
    "gn:feature_class":"P",
    "gn:feature_code":"PPL",
    "gn:name":"Mbanza Mboma",
    "gn:population":0,
    "gn:timezone":"Africa/Kinshasa",
    "iso:country":"CD",
    "wof:name":"Mbanza Mboma",
    "wof:placetype":"locality"
},
  "geometry": {"coordinates":[15.15158,-4.94238],"type":"Point"}
}