{
  "type": "Feature",
  "properties": {
    "gn:admin1_code":"29.0",
    "gn:asciiname":"Lusonde",
    "gn:country_code":"CD",
    "gn:dem":697,
    "gn:feature_class":"P",
    "gn:feature_code":"PPL",
    "gn:name":"Lusonde",
    "gn:population":0,
    "gn:timezone":"Africa/Lubumbashi",
    "iso:country":"CD",
    "wof:name":"Lusonde",
    "wof:placetype":"locality"
},
  "geometry": {"coordinates":[26.79386,-7.15661],"type":"Point"}
}