{
  "type": "Feature",
  "properties": {
    "gn:admin1_code":"31.0",
    "gn:asciiname":"Bongulu",
    "gn:country_code":"CD",
    "gn:dem":358,
    "gn:feature_class":"P",
    "gn:feature_code":"PPL",
    "gn:name":"Bongulu",
    "gn:population":0,
    "gn:timezone":"Africa/Kinshasa",
    "iso:country":"CD",
    "wof:name":"Bongulu",
    "wof:placetype":"locality"
},
  "geometry": {"coordinates":[20.60149,0.8397],"type":"Point"}
}