{
  "type": "Feature",
  "properties": {
    "gn:admin1_code":"22.0",
    "gn:asciiname":"Kabwiz",
    "gn:country_code":"CD",
    "gn:dem":940,
    "gn:feature_class":"P",
    "gn:feature_code":"PPL",
    "gn:name":"Kabwiz",
    "gn:population":0,
    "gn:timezone":"Africa/Lubumbashi",
    "iso:country":"CD",
    "name:und_x_variant":[
        "Kabuiza"
    ],
    "wof:name":"Kabwiz",
    "wof:placetype":"locality"
},
  "geometry": {"coordinates":[22.45526,-8.42403],"type":"Point"}
}