{
  "type": "Feature",
  "properties": {
    "gn:admin1_code":"19.0",
    "gn:asciiname":"Tshambula",
    "gn:country_code":"CD",
    "gn:dem":893,
    "gn:feature_class":"P",
    "gn:feature_code":"PPL",
    "gn:name":"Tshambula",
    "gn:population":0,
    "gn:timezone":"Africa/Kinshasa",
    "iso:country":"CD",
    "wof:name":"Tshambula",
    "wof:placetype":"locality"
},
  "geometry": {"coordinates":[19.71566,-6.85002],"type":"Point"}
}