{
  "type": "Feature",
  "properties": {
    "gn:admin1_code":"22.0",
    "gn:asciiname":"Kabamba",
    "gn:country_code":"CD",
    "gn:dem":1052,
    "gn:feature_class":"P",
    "gn:feature_code":"PPL",
    "gn:name":"Kabamba",
    "gn:population":0,
    "gn:timezone":"Africa/Lubumbashi",
    "iso:country":"CD",
    "wof:name":"Kabamba",
    "wof:placetype":"locality"
},
  "geometry": {"coordinates":[22.4599,-9.93517],"type":"Point"}
}