{
  "type": "Feature",
  "properties": {
    "gn:admin1_code":"18.0",
    "gn:asciiname":"Kasoba",
    "gn:country_code":"CD",
    "gn:dem":656,
    "gn:feature_class":"P",
    "gn:feature_code":"PPL",
    "gn:name":"Kasoba",
    "gn:population":0,
    "gn:timezone":"Africa/Lubumbashi",
    "iso:country":"CD",
    "wof:name":"Kasoba",
    "wof:placetype":"locality"
},
  "geometry": {"coordinates":[21.51313,-6.20468],"type":"Point"}
}