{
  "type": "Feature",
  "properties": {
    "gn:admin1_code":"12.0",
    "gn:asciiname":"Mukuku",
    "gn:country_code":"CD",
    "gn:dem":774,
    "gn:feature_class":"P",
    "gn:feature_code":"PPL",
    "gn:name":"Mukuku",
    "gn:population":0,
    "gn:timezone":"Africa/Lubumbashi",
    "iso:country":"CD",
    "wof:name":"Mukuku",
    "wof:placetype":"locality"
},
  "geometry": {"coordinates":[29.09822,-4.12782],"type":"Point"}
}