{
  "type": "Feature",
  "properties": {
    "gn:admin1_code":"19.0",
    "gn:asciiname":"Mulopo",
    "gn:country_code":"CD",
    "gn:dem":819,
    "gn:feature_class":"P",
    "gn:feature_code":"PPL",
    "gn:name":"Mulopo",
    "gn:population":0,
    "gn:timezone":"Africa/Kinshasa",
    "iso:country":"CD",
    "wof:name":"Mulopo",
    "wof:placetype":"locality"
},
  "geometry": {"coordinates":[17.83626,-6.03918],"type":"Point"}
}