{
  "type": "Feature",
  "properties": {
    "gn:admin1_code":"14.0",
    "gn:asciiname":"Katanga",
    "gn:country_code":"CD",
    "gn:dem":1034,
    "gn:feature_class":"P",
    "gn:feature_code":"PPL",
    "gn:name":"Katanga",
    "gn:population":0,
    "gn:timezone":"Africa/Lubumbashi",
    "iso:country":"CD",
    "name:ara_x_preferred":[
        "\u0643\u0627\u062a\u0627\u0646\u063a\u0627 "
    ],
    "name:ben_x_preferred":[
        "\u0995\u09be\u09a4\u09be\u0982\u0997\u09be"
    ],
    "name:ceb_x_preferred":[
        "Katanga"
    ],
    "name:ces_x_preferred":[
        "Katanga"
    ],
    "name:deu_x_preferred":[
        "Katanga"
    ],
    "name:ell_x_preferred":[
        "\u039a\u03b1\u03c4\u03ac\u03bd\u03b3\u03ba\u03b1"
    ],
    "name:est_x_preferred":[
        "Katanga"
    ],
    "name:fra_x_preferred":[
        "Katanga"
    ],
    "name:heb_x_preferred":[
        "\u05e7\u05d8\u05e0\u05d2\u05d4"
    ],
    "name:hin_x_preferred":[
        "\u0915\u091f\u0902\u0917\u093e"
    ],
    "name:ina_x_preferred":[
        "Katanga"
    ],
    "name:ind_x_preferred":[
        "Katanga"
    ],
    "name:ita_x_preferred":[
        "Katanga"
    ],
    "name:kor_x_preferred":[
        "\uce74\ud0d5\uac00"
    ],
    "name:nld_x_preferred":[
        "Katanga"
    ],
    "name:nor_x_preferred":[
        "Katanga"
    ],
    "name:pol_x_preferred":[
        "Katanga"
    ],
    "name:por_x_preferred":[
        "Katanga"
    ],
    "name:rus_x_preferred":[
        "\u041a\u0430\u0442\u0430\u043d\u0433\u0430"
    ],
    "name:slk_x_preferred":[
        "Katanga"
    ],
    "name:spa_x_preferred":[
        "Katanga"
    ],
    "name:swe_x_preferred":[
        "Katanga"
    ],
    "name:tur_x_preferred":[
        "Katanga"
    ],
    "name:urd_x_preferred":[
        "\u06a9\u0627\u0679\u0627\u0646\u06af\u0627"
    ],
    "wof:name":"Katanga",
    "wof:placetype":"locality"
},
  "geometry": {"coordinates":[28.65,-10.63333],"type":"Point"}
}