{
  "type": "Feature",
  "properties": {
    "gn:admin1_code":"12.0",
    "gn:asciiname":"Mugeri",
    "gn:country_code":"CD",
    "gn:dem":1558,
    "gn:feature_class":"P",
    "gn:feature_code":"PPL",
    "gn:name":"Mugeri",
    "gn:population":0,
    "gn:timezone":"Africa/Lubumbashi",
    "iso:country":"CD",
    "wof:name":"Mugeri",
    "wof:placetype":"locality"
},
  "geometry": {"coordinates":[28.84841,-2.20083],"type":"Point"}
}