{
  "type": "Feature",
  "properties": {
    "gn:admin1_code":"30.0",
    "gn:asciiname":"Bahanga",
    "gn:country_code":"CD",
    "gn:dem":389,
    "gn:feature_class":"P",
    "gn:feature_code":"PPL",
    "gn:name":"Bahanga",
    "gn:population":0,
    "gn:timezone":"Africa/Lubumbashi",
    "iso:country":"CD",
    "wof:name":"Bahanga",
    "wof:placetype":"locality"
},
  "geometry": {"coordinates":[23.99046,1.44673],"type":"Point"}
}