{
  "type": "Feature",
  "properties": {
    "gn:admin1_code":"4.0",
    "gn:asciiname":"Konko",
    "gn:country_code":"CD",
    "gn:dem":762,
    "gn:feature_class":"P",
    "gn:feature_code":"PPL",
    "gn:name":"Konko",
    "gn:population":0,
    "gn:timezone":"Africa/Lubumbashi",
    "iso:country":"CD",
    "wof:name":"Konko",
    "wof:placetype":"locality"
},
  "geometry": {"coordinates":[23.08038,-6.26334],"type":"Point"}
}