{
  "type": "Feature",
  "properties": {
    "gn:admin1_code":"26.0",
    "gn:asciiname":"Badja",
    "gn:country_code":"CD",
    "gn:dem":504,
    "gn:feature_class":"P",
    "gn:feature_code":"PPL",
    "gn:name":"Badja",
    "gn:population":0,
    "gn:timezone":"Africa/Kinshasa",
    "iso:country":"CD",
    "wof:name":"Badja",
    "wof:placetype":"locality"
},
  "geometry": {"coordinates":[19.69964,4.9493],"type":"Point"}
}