{
  "type": "Feature",
  "properties": {
    "gn:admin1_code":"15.0",
    "gn:asciiname":"Mwilambwe",
    "gn:country_code":"CD",
    "gn:dem":1040,
    "gn:feature_class":"P",
    "gn:feature_code":"PPL",
    "gn:name":"Mwilambwe",
    "gn:population":0,
    "gn:timezone":"Africa/Lubumbashi",
    "iso:country":"CD",
    "wof:name":"Mwilambwe",
    "wof:placetype":"locality"
},
  "geometry": {"coordinates":[24.9983,-8.1042],"type":"Point"}
}