{
  "type": "Feature",
  "properties": {
    "gn:admin1_code":"23.0",
    "gn:asciiname":"Kayenge",
    "gn:country_code":"CD",
    "gn:dem":788,
    "gn:feature_class":"P",
    "gn:feature_code":"PPL",
    "gn:name":"Kayenge",
    "gn:population":0,
    "gn:timezone":"Africa/Lubumbashi",
    "iso:country":"CD",
    "wof:name":"Kayenge",
    "wof:placetype":"locality"
},
  "geometry": {"coordinates":[21.74997,-6.74789],"type":"Point"}
}