{
  "type": "Feature",
  "properties": {
    "gn:admin1_code":"25.0",
    "gn:asciiname":"Busu-Adula",
    "gn:country_code":"CD",
    "gn:dem":354,
    "gn:feature_class":"P",
    "gn:feature_code":"PPL",
    "gn:name":"Busu-Adula",
    "gn:population":0,
    "gn:timezone":"Africa/Kinshasa",
    "iso:country":"CD",
    "name:und_x_variant":[
        "Boso-Adula"
    ],
    "wof:name":"Busu-Adula",
    "wof:placetype":"locality"
},
  "geometry": {"coordinates":[21.6659,2.0822],"type":"Point"}
}