{
  "type": "Feature",
  "properties": {
    "gn:admin1_code":"8.0",
    "gn:asciiname":"Pangala",
    "gn:country_code":"CD",
    "gn:dem":578,
    "gn:feature_class":"P",
    "gn:feature_code":"PPL",
    "gn:name":"Pangala",
    "gn:population":0,
    "gn:timezone":"Africa/Kinshasa",
    "iso:country":"CD",
    "name:ceb_x_preferred":[
        "P\u0101ng\u0101la"
    ],
    "name:swe_x_preferred":[
        "P\u0101ng\u0101la"
    ],
    "wof:name":"Pangala",
    "wof:placetype":"locality"
},
  "geometry": {"coordinates":[16.1154,-5.82873],"type":"Point"}
}