{
  "type": "Feature",
  "properties": {
    "gn:admin1_code":"12.0",
    "gn:asciiname":"Mumusho",
    "gn:country_code":"CD",
    "gn:dem":1627,
    "gn:feature_class":"P",
    "gn:feature_code":"PPL",
    "gn:name":"Mumusho",
    "gn:population":0,
    "gn:timezone":"Africa/Lubumbashi",
    "iso:country":"CD",
    "wof:name":"Mumusho",
    "wof:placetype":"locality"
},
  "geometry": {"coordinates":[28.87805,-2.62058],"type":"Point"}
}