{
  "type": "Feature",
  "properties": {
    "gn:admin1_code":"16.0",
    "gn:asciiname":"Makusa",
    "gn:country_code":"CD",
    "gn:dem":699,
    "gn:feature_class":"P",
    "gn:feature_code":"PPL",
    "gn:name":"Makusa",
    "gn:population":0,
    "gn:timezone":"Africa/Lubumbashi",
    "iso:country":"CD",
    "wof:name":"Makusa",
    "wof:placetype":"locality"
},
  "geometry": {"coordinates":[27.94652,4.35241],"type":"Point"}
}