{
  "type": "Feature",
  "properties": {
    "gn:admin1_code":"22.0",
    "gn:asciiname":"Kivumbu",
    "gn:country_code":"CD",
    "gn:dem":1106,
    "gn:feature_class":"P",
    "gn:feature_code":"PPL",
    "gn:name":"Kivumbu",
    "gn:population":0,
    "gn:timezone":"Africa/Lubumbashi",
    "iso:country":"CD",
    "name:und_x_variant":[
        "Kavumbi",
        "Kuvumbi",
        "Kivumbu",
        "Kuvimbi"
    ],
    "wof:name":"Kivumbu",
    "wof:placetype":"locality"
},
  "geometry": {"coordinates":[26.44204,-10.50353],"type":"Point"}
}