{
  "type": "Feature",
  "properties": {
    "gn:admin1_code":"15.0",
    "gn:asciiname":"Lubango",
    "gn:country_code":"CD",
    "gn:dem":901,
    "gn:feature_class":"P",
    "gn:feature_code":"PPL",
    "gn:name":"Lubango",
    "gn:population":0,
    "gn:timezone":"Africa/Lubumbashi",
    "iso:country":"CD",
    "wof:name":"Lubango",
    "wof:placetype":"locality"
},
  "geometry": {"coordinates":[25.41104,-9.71703],"type":"Point"}
}