{
  "type": "Feature",
  "properties": {
    "gn:admin1_code":"18.0",
    "gn:asciiname":"Musemvu",
    "gn:country_code":"CD",
    "gn:dem":654,
    "gn:feature_class":"P",
    "gn:feature_code":"PPL",
    "gn:name":"Musemvu",
    "gn:population":0,
    "gn:timezone":"Africa/Lubumbashi",
    "iso:country":"CD",
    "wof:name":"Musemvu",
    "wof:placetype":"locality"
},
  "geometry": {"coordinates":[19.82165,-6.19785],"type":"Point"}
}