{
  "type": "Feature",
  "properties": {
    "gn:admin1_code":"23.0",
    "gn:asciiname":"Biteka",
    "gn:country_code":"CD",
    "gn:dem":811,
    "gn:feature_class":"P",
    "gn:feature_code":"PPL",
    "gn:name":"Biteka",
    "gn:population":0,
    "gn:timezone":"Africa/Lubumbashi",
    "iso:country":"CD",
    "wof:name":"Biteka",
    "wof:placetype":"locality"
},
  "geometry": {"coordinates":[21.85338,-7.12921],"type":"Point"}
}