{
  "type": "Feature",
  "properties": {
    "gn:admin1_code":"2.0",
    "gn:asciiname":"Wetsimbola",
    "gn:country_code":"CD",
    "gn:dem":346,
    "gn:feature_class":"P",
    "gn:feature_code":"PPL",
    "gn:name":"Wetsimbola",
    "gn:population":0,
    "gn:timezone":"Africa/Kinshasa",
    "iso:country":"CD",
    "wof:name":"Wetsimbola",
    "wof:placetype":"locality"
},
  "geometry": {"coordinates":[19.40073,-0.80216],"type":"Point"}
}