{
  "type": "Feature",
  "properties": {
    "gn:admin1_code":"19.0",
    "gn:asciiname":"Kitsuaka",
    "gn:country_code":"CD",
    "gn:dem":865,
    "gn:feature_class":"P",
    "gn:feature_code":"PPL",
    "gn:name":"Kitsuaka",
    "gn:population":0,
    "gn:timezone":"Africa/Kinshasa",
    "iso:country":"CD",
    "wof:name":"Kitsuaka",
    "wof:placetype":"locality"
},
  "geometry": {"coordinates":[17.42906,-6.33353],"type":"Point"}
}