{
  "type": "Feature",
  "properties": {
    "gn:admin1_code":"20.0",
    "gn:asciiname":"Mungamba",
    "gn:country_code":"CD",
    "gn:dem":724,
    "gn:feature_class":"P",
    "gn:feature_code":"PPL",
    "gn:name":"Mungamba",
    "gn:population":0,
    "gn:timezone":"Africa/Kinshasa",
    "iso:country":"CD",
    "wof:name":"Mungamba",
    "wof:placetype":"locality"
},
  "geometry": {"coordinates":[18.56444,-5.46972],"type":"Point"}
}