{
  "type": "Feature",
  "properties": {
    "gn:admin1_code":"28.0",
    "gn:asciiname":"Bobambe Deuxieme",
    "gn:country_code":"CD",
    "gn:dem":380,
    "gn:feature_class":"P",
    "gn:feature_code":"PPL",
    "gn:name":"Bobambe Deuxi\u00e8me",
    "gn:population":0,
    "gn:timezone":"Africa/Kinshasa",
    "iso:country":"CD",
    "name:und_x_variant":[
        "Bobambe Deuxi\u00e8me",
        "Bobambe II"
    ],
    "wof:name":"Bobambe Deuxieme",
    "wof:placetype":"locality"
},
  "geometry": {"coordinates":[19.72176,3.61806],"type":"Point"}
}