{
  "type": "Feature",
  "properties": {
    "gn:admin1_code":"31.0",
    "gn:asciiname":"Isekolokoto",
    "gn:country_code":"CD",
    "gn:dem":349,
    "gn:feature_class":"P",
    "gn:feature_code":"PPL",
    "gn:name":"Isekolokoto",
    "gn:population":0,
    "gn:timezone":"Africa/Kinshasa",
    "iso:country":"CD",
    "wof:name":"Isekolokoto",
    "wof:placetype":"locality"
},
  "geometry": {"coordinates":[20.92823,0.55424],"type":"Point"}
}