{
  "type": "Feature",
  "properties": {
    "gn:admin1_code":"28.0",
    "gn:asciiname":"Sandzala",
    "gn:country_code":"CD",
    "gn:dem":346,
    "gn:feature_class":"P",
    "gn:feature_code":"PPL",
    "gn:name":"Sandzala",
    "gn:population":0,
    "gn:timezone":"Africa/Kinshasa",
    "iso:country":"CD",
    "wof:name":"Sandzala",
    "wof:placetype":"locality"
},
  "geometry": {"coordinates":[18.1704,2.05745],"type":"Point"}
}