{
  "type": "Feature",
  "properties": {
    "gn:admin1_code":"10.0",
    "gn:asciiname":"Lukulunga",
    "gn:country_code":"CD",
    "gn:dem":563,
    "gn:feature_class":"P",
    "gn:feature_code":"PPL",
    "gn:name":"Lukulunga",
    "gn:population":0,
    "gn:timezone":"Africa/Lubumbashi",
    "iso:country":"CD",
    "wof:name":"Lukulunga",
    "wof:placetype":"locality"
},
  "geometry": {"coordinates":[26.36041,-3.64648],"type":"Point"}
}