{
  "type": "Feature",
  "properties": {
    "gn:admin1_code":"2.0",
    "gn:asciiname":"Waka Bofonge",
    "gn:country_code":"CD",
    "gn:dem":358,
    "gn:feature_class":"P",
    "gn:feature_code":"PPL",
    "gn:name":"Waka Bofonge",
    "gn:population":0,
    "gn:timezone":"Africa/Kinshasa",
    "iso:country":"CD",
    "wof:name":"Waka Bofonge",
    "wof:placetype":"locality"
},
  "geometry": {"coordinates":[20.15,-0.75],"type":"Point"}
}