{
  "type": "Feature",
  "properties": {
    "gn:admin1_code":"12.0",
    "gn:asciiname":"Katembo",
    "gn:country_code":"CD",
    "gn:dem":2075,
    "gn:feature_class":"P",
    "gn:feature_code":"PPL",
    "gn:name":"Katembo",
    "gn:population":0,
    "gn:timezone":"Africa/Lubumbashi",
    "iso:country":"CD",
    "wof:name":"Katembo",
    "wof:placetype":"locality"
},
  "geometry": {"coordinates":[29.05889,-3.20639],"type":"Point"}
}