{
  "type": "Feature",
  "properties": {
    "gn:admin1_code":"29.0",
    "gn:asciiname":"Muswe",
    "gn:country_code":"CD",
    "gn:dem":641,
    "gn:feature_class":"P",
    "gn:feature_code":"PPL",
    "gn:name":"Muswe",
    "gn:population":0,
    "gn:timezone":"Africa/Lubumbashi",
    "iso:country":"CD",
    "name:und_x_variant":[
        "Mubwe",
        "Muswe"
    ],
    "wof:name":"Muswe",
    "wof:placetype":"locality"
},
  "geometry": {"coordinates":[26.6762,-6.71923],"type":"Point"}
}