{
  "type": "Feature",
  "properties": {
    "gn:admin1_code":"23.0",
    "gn:asciiname":"Satuboko",
    "gn:country_code":"CD",
    "gn:dem":848,
    "gn:feature_class":"P",
    "gn:feature_code":"PPL",
    "gn:name":"Satuboko",
    "gn:population":0,
    "gn:timezone":"Africa/Lubumbashi",
    "iso:country":"CD",
    "wof:name":"Satuboko",
    "wof:placetype":"locality"
},
  "geometry": {"coordinates":[22.62739,-7.36305],"type":"Point"}
}