{
  "type": "Feature",
  "properties": {
    "gn:admin1_code":"21.0",
    "gn:asciiname":"Kabamba-Gombe",
    "gn:country_code":"CD",
    "gn:dem":676,
    "gn:feature_class":"P",
    "gn:feature_code":"PPL",
    "gn:name":"Kabamba-Gombe",
    "gn:population":0,
    "gn:timezone":"Africa/Lubumbashi",
    "iso:country":"CD",
    "name:und_x_variant":[
        "Kabambo",
        "Kabamba-Gombe"
    ],
    "wof:name":"Kabamba-Gombe",
    "wof:placetype":"locality"
},
  "geometry": {"coordinates":[25.16667,-5.85],"type":"Point"}
}