{
  "type": "Feature",
  "properties": {
    "gn:admin1_code":"10.0",
    "gn:asciiname":"Kayombo",
    "gn:country_code":"CD",
    "gn:dem":930,
    "gn:feature_class":"P",
    "gn:feature_code":"PPL",
    "gn:name":"Kayombo",
    "gn:population":0,
    "gn:timezone":"Africa/Lubumbashi",
    "iso:country":"CD",
    "wof:name":"Kayombo",
    "wof:placetype":"locality"
},
  "geometry": {"coordinates":[27.96837,-4.85426],"type":"Point"}
}