{
  "type": "Feature",
  "properties": {
    "gn:admin1_code":"17.0",
    "gn:asciiname":"Wawa",
    "gn:country_code":"CD",
    "gn:dem":1261,
    "gn:feature_class":"P",
    "gn:feature_code":"PPL",
    "gn:name":"Wawa",
    "gn:population":0,
    "gn:timezone":"Africa/Lubumbashi",
    "iso:country":"CD",
    "wof:name":"Wawa",
    "wof:placetype":"locality"
},
  "geometry": {"coordinates":[30.69017,3.18295],"type":"Point"}
}