{
  "type": "Feature",
  "properties": {
    "gn:admin1_code":"17.0",
    "gn:asciiname":"Wawa",
    "gn:country_code":"CD",
    "gn:dem":1261,
    "gn:feature_class":"P",
    "gn:feature_code":"PPL",
    "gn:name":"Wawa",
    "gn:population":0,
    "gn:timezone":"Africa/Lubumbashi",
    "iso:country":"CD",
    "name:ceb_x_preferred":[
        "Wawa"
    ],
    "name:deu_x_preferred":[
        "Wawa"
    ],
    "name:fin_x_preferred":[
        "Wawa"
    ],
    "name:fra_x_preferred":[
        "Wawa"
    ],
    "name:hye_x_preferred":[
        "\u054e\u0561\u057e\u0561"
    ],
    "name:ita_x_preferred":[
        "Wawa"
    ],
    "name:pol_x_preferred":[
        "Wawa"
    ],
    "name:rus_x_preferred":[
        "\u0412\u0430\u0432\u0430"
    ],
    "name:swe_x_preferred":[
        "Wawa"
    ],
    "name:ukr_x_preferred":[
        "\u0412\u0430\u0432\u0430"
    ],
    "wof:name":"Wawa",
    "wof:placetype":"locality"
},
  "geometry": {"coordinates":[30.69017,3.18295],"type":"Point"}
}