{
  "type": "Feature",
  "properties": {
    "gn:admin1_code":"14.0",
    "gn:asciiname":"Kienge",
    "gn:country_code":"CD",
    "gn:dem":931,
    "gn:feature_class":"P",
    "gn:feature_code":"PPL",
    "gn:name":"Kienge",
    "gn:population":0,
    "gn:timezone":"Africa/Lubumbashi",
    "iso:country":"CD",
    "wof:name":"Kienge",
    "wof:placetype":"locality"
},
  "geometry": {"coordinates":[27.55546,-10.56794],"type":"Point"}
}