{
  "type": "Feature",
  "properties": {
    "gn:admin1_code":"8.0",
    "gn:asciiname":"Temvo",
    "gn:country_code":"CD",
    "gn:dem":270,
    "gn:feature_class":"P",
    "gn:feature_code":"PPL",
    "gn:name":"Temvo",
    "gn:population":0,
    "gn:timezone":"Africa/Kinshasa",
    "iso:country":"CD",
    "wof:name":"Temvo",
    "wof:placetype":"locality"
},
  "geometry": {"coordinates":[13.00643,-5.49571],"type":"Point"}
}