{
  "type": "Feature",
  "properties": {
    "gn:admin1_code":"19.0",
    "gn:asciiname":"Shatshishima",
    "gn:country_code":"CD",
    "gn:dem":934,
    "gn:feature_class":"P",
    "gn:feature_code":"PPL",
    "gn:name":"Shatshishima",
    "gn:population":0,
    "gn:timezone":"Africa/Kinshasa",
    "iso:country":"CD",
    "wof:name":"Shatshishima",
    "wof:placetype":"locality"
},
  "geometry": {"coordinates":[19.52128,-7.08178],"type":"Point"}
}