{
  "type": "Feature",
  "properties": {
    "gn:admin1_code":"13.0",
    "gn:asciiname":"Manzaka",
    "gn:country_code":"CD",
    "gn:dem":604,
    "gn:feature_class":"P",
    "gn:feature_code":"PPL",
    "gn:name":"Manzaka",
    "gn:population":0,
    "gn:timezone":"Africa/Lubumbashi",
    "iso:country":"CD",
    "wof:name":"Manzaka",
    "wof:placetype":"locality"
},
  "geometry": {"coordinates":[25.88379,4.07827],"type":"Point"}
}