{
  "type": "Feature",
  "properties": {
    "gn:admin1_code":"19.0",
    "gn:asciiname":"Mwatshilombe",
    "gn:country_code":"CD",
    "gn:dem":1125,
    "gn:feature_class":"P",
    "gn:feature_code":"PPL",
    "gn:name":"Mwatshilombe",
    "gn:population":0,
    "gn:timezone":"Africa/Kinshasa",
    "iso:country":"CD",
    "wof:name":"Mwatshilombe",
    "wof:placetype":"locality"
},
  "geometry": {"coordinates":[19.09418,-7.90837],"type":"Point"}
}