{
  "type": "Feature",
  "properties": {
    "gn:admin1_code":"8.0",
    "gn:asciiname":"Maduda",
    "gn:country_code":"CD",
    "gn:dem":281,
    "gn:feature_class":"P",
    "gn:feature_code":"PPL",
    "gn:name":"Maduda",
    "gn:population":0,
    "gn:timezone":"Africa/Kinshasa",
    "iso:country":"CD",
    "wof:name":"Maduda",
    "wof:placetype":"locality"
},
  "geometry": {"coordinates":[13.07863,-4.91955],"type":"Point"}
}