{
  "type": "Feature",
  "properties": {
    "gn:admin1_code":"14.0",
    "gn:asciiname":"Kamilimba",
    "gn:country_code":"CD",
    "gn:dem":1034,
    "gn:feature_class":"P",
    "gn:feature_code":"PPL",
    "gn:name":"Kamilimba",
    "gn:population":0,
    "gn:timezone":"Africa/Lubumbashi",
    "iso:country":"CD",
    "wof:name":"Kamilimba",
    "wof:placetype":"locality"
},
  "geometry": {"coordinates":[28.50387000000001,-8.9293],"type":"Point"}
}