{
  "type": "Feature",
  "properties": {
    "gn:admin1_code":"11.0",
    "gn:asciiname":"Kawa",
    "gn:country_code":"CD",
    "gn:dem":1795,
    "gn:feature_class":"P",
    "gn:feature_code":"PPL",
    "gn:name":"Kawa",
    "gn:population":0,
    "gn:timezone":"Africa/Lubumbashi",
    "iso:country":"CD",
    "name:ceb_x_preferred":[
        "Kawa"
    ],
    "name:deu_x_preferred":[
        "Kawa"
    ],
    "name:fra_x_preferred":[
        "Kawa"
    ],
    "name:kur_x_preferred":[
        "Kawa"
    ],
    "name:pol_x_preferred":[
        "Kawa"
    ],
    "name:swe_x_preferred":[
        "Kawa"
    ],
    "wof:name":"Kawa",
    "wof:placetype":"locality"
},
  "geometry": {"coordinates":[28.96347,-0.84935],"type":"Point"}
}