{
  "type": "Feature",
  "properties": {
    "gn:admin1_code":"11.0",
    "gn:asciiname":"Nabura",
    "gn:country_code":"CD",
    "gn:dem":2051,
    "gn:feature_class":"P",
    "gn:feature_code":"PPL",
    "gn:name":"Nabura",
    "gn:population":0,
    "gn:timezone":"Africa/Lubumbashi",
    "iso:country":"CD",
    "wof:name":"Nabura",
    "wof:placetype":"locality"
},
  "geometry": {"coordinates":[28.86861,-1.2065],"type":"Point"}
}