{
  "type": "Feature",
  "properties": {
    "gn:admin1_code":"15.0",
    "gn:asciiname":"Kayembe",
    "gn:country_code":"CD",
    "gn:dem":619,
    "gn:feature_class":"P",
    "gn:feature_code":"PPL",
    "gn:name":"Kayembe",
    "gn:population":0,
    "gn:timezone":"Africa/Lubumbashi",
    "iso:country":"CD",
    "wof:name":"Kayembe",
    "wof:placetype":"locality"
},
  "geometry": {"coordinates":[26.39812,-8.91978],"type":"Point"}
}