{
  "type": "Feature",
  "properties": {
    "gn:admin1_code":"4.0",
    "gn:asciiname":"Bakwa-Masela",
    "gn:country_code":"CD",
    "gn:dem":574,
    "gn:feature_class":"P",
    "gn:feature_code":"PPL",
    "gn:name":"Bakwa-Masela",
    "gn:population":0,
    "gn:timezone":"Africa/Lubumbashi",
    "iso:country":"CD",
    "wof:name":"Bakwa-Masela",
    "wof:placetype":"locality"
},
  "geometry": {"coordinates":[23.91223,-6.35312],"type":"Point"}
}