{
  "type": "Feature",
  "properties": {
    "gn:admin1_code":"13.0",
    "gn:asciiname":"Yombio-Moke",
    "gn:country_code":"CD",
    "gn:dem":416,
    "gn:feature_class":"P",
    "gn:feature_code":"PPL",
    "gn:name":"Yombio-Moke",
    "gn:population":0,
    "gn:timezone":"Africa/Lubumbashi",
    "iso:country":"CD",
    "name:und_x_variant":[
        "Yombio",
        "Yombio-Moke"
    ],
    "wof:name":"Yombio-Moke",
    "wof:placetype":"locality"
},
  "geometry": {"coordinates":[24.34457,2.90575],"type":"Point"}
}