{
  "type": "Feature",
  "properties": {
    "gn:admin1_code":"8.0",
    "gn:asciiname":"Tsuku-Tadi",
    "gn:country_code":"CD",
    "gn:dem":167,
    "gn:feature_class":"P",
    "gn:feature_code":"PPL",
    "gn:name":"Tsuku-Tadi",
    "gn:population":0,
    "gn:timezone":"Africa/Kinshasa",
    "iso:country":"CD",
    "wof:name":"Tsuku-Tadi",
    "wof:placetype":"locality"
},
  "geometry": {"coordinates":[12.93333,-4.76667],"type":"Point"}
}