{
  "type": "Feature",
  "properties": {
    "gn:admin1_code":"18.0",
    "gn:asciiname":"Bomba-Kayenga",
    "gn:country_code":"CD",
    "gn:dem":697,
    "gn:feature_class":"P",
    "gn:feature_code":"PPL",
    "gn:name":"Bomba-Kayenga",
    "gn:population":0,
    "gn:timezone":"Africa/Lubumbashi",
    "iso:country":"CD",
    "wof:name":"Bomba-Kayenga",
    "wof:placetype":"locality"
},
  "geometry": {"coordinates":[21.47612,-6.65949],"type":"Point"}
}