{
  "type": "Feature",
  "properties": {
    "gn:admin1_code":"18.0",
    "gn:asciiname":"Lukangala",
    "gn:country_code":"CD",
    "gn:dem":816,
    "gn:feature_class":"P",
    "gn:feature_code":"PPL",
    "gn:name":"Lukangala",
    "gn:population":0,
    "gn:timezone":"Africa/Lubumbashi",
    "iso:country":"CD",
    "wof:name":"Lukangala",
    "wof:placetype":"locality"
},
  "geometry": {"coordinates":[21.48858,-7.14908],"type":"Point"}
}