{
  "type": "Feature",
  "properties": {
    "gn:admin1_code":"11.0",
    "gn:asciiname":"Mitwa Deuxieme",
    "gn:country_code":"CD",
    "gn:dem":1357,
    "gn:feature_class":"P",
    "gn:feature_code":"PPL",
    "gn:name":"Mitwa Deuxi\u00e8me",
    "gn:population":0,
    "gn:timezone":"Africa/Lubumbashi",
    "iso:country":"CD",
    "name:und_x_variant":[
        "Mitwa Deuxi\u00e8me",
        "Mitwa II"
    ],
    "wof:name":"Mitwa Deuxieme",
    "wof:placetype":"locality"
},
  "geometry": {"coordinates":[28.58545,-1.43083],"type":"Point"}
}