{
  "type": "Feature",
  "properties": {
    "gn:admin1_code":"28.0",
    "gn:asciiname":"Djepere",
    "gn:country_code":"CD",
    "gn:dem":369,
    "gn:feature_class":"P",
    "gn:feature_code":"PPL",
    "gn:name":"Djepere",
    "gn:population":0,
    "gn:timezone":"Africa/Kinshasa",
    "iso:country":"CD",
    "wof:name":"Djepere",
    "wof:placetype":"locality"
},
  "geometry": {"coordinates":[18.78322,3.74251],"type":"Point"}
}