{
  "type": "Feature",
  "properties": {
    "gn:admin1_code":"13.0",
    "gn:asciiname":"Masipiri",
    "gn:country_code":"CD",
    "gn:dem":414,
    "gn:feature_class":"P",
    "gn:feature_code":"PPL",
    "gn:name":"Masipiri",
    "gn:population":0,
    "gn:timezone":"Africa/Lubumbashi",
    "iso:country":"CD",
    "wof:name":"Masipiri",
    "wof:placetype":"locality"
},
  "geometry": {"coordinates":[24.12315,3.05875],"type":"Point"}
}