{
  "type": "Feature",
  "properties": {
    "gn:admin1_code":"28.0",
    "gn:asciiname":"Busu-Bombo",
    "gn:country_code":"CD",
    "gn:dem":349,
    "gn:feature_class":"P",
    "gn:feature_code":"PPL",
    "gn:name":"Busu-Bombo",
    "gn:population":0,
    "gn:timezone":"Africa/Kinshasa",
    "iso:country":"CD",
    "name:fra_x_preferred":[
        "Busu-Bombo"
    ],
    "wof:name":"Busu-Bombo",
    "wof:placetype":"locality"
},
  "geometry": {"coordinates":[19.01148,2.39994],"type":"Point"}
}