{
  "type": "Feature",
  "properties": {
    "gn:admin1_code":"19.0",
    "gn:asciiname":"Magueni",
    "gn:country_code":"CD",
    "gn:dem":549,
    "gn:feature_class":"P",
    "gn:feature_code":"PPL",
    "gn:name":"Magueni",
    "gn:population":0,
    "gn:timezone":"Africa/Kinshasa",
    "iso:country":"CD",
    "wof:name":"Magueni",
    "wof:placetype":"locality"
},
  "geometry": {"coordinates":[17.28343,-4.68178],"type":"Point"}
}