{
  "type": "Feature",
  "properties": {
    "gn:admin1_code":"12.0",
    "gn:asciiname":"Kisoshi",
    "gn:country_code":"CD",
    "gn:dem":779,
    "gn:feature_class":"P",
    "gn:feature_code":"PPL",
    "gn:name":"Kisoshi",
    "gn:population":0,
    "gn:timezone":"Africa/Lubumbashi",
    "iso:country":"CD",
    "wof:name":"Kisoshi",
    "wof:placetype":"locality"
},
  "geometry": {"coordinates":[29.10372000000001,-4.75693],"type":"Point"}
}