{
  "type": "Feature",
  "properties": {
    "gn:admin1_code":"11.0",
    "gn:asciiname":"Malubo",
    "gn:country_code":"CD",
    "gn:dem":1382,
    "gn:feature_class":"P",
    "gn:feature_code":"PPL",
    "gn:name":"Malubo",
    "gn:population":0,
    "gn:timezone":"Africa/Lubumbashi",
    "iso:country":"CD",
    "wof:name":"Malubo",
    "wof:placetype":"locality"
},
  "geometry": {"coordinates":[28.73056,-0.47167],"type":"Point"}
}