{
  "type": "Feature",
  "properties": {
    "gn:admin1_code":"21.0",
    "gn:asciiname":"Loanga-Kapongo",
    "gn:country_code":"CD",
    "gn:dem":753,
    "gn:feature_class":"P",
    "gn:feature_code":"PPL",
    "gn:name":"Loanga-Kapongo",
    "gn:population":0,
    "gn:timezone":"Africa/Lubumbashi",
    "iso:country":"CD",
    "wof:name":"Loanga-Kapongo",
    "wof:placetype":"locality"
},
  "geometry": {"coordinates":[24.70998,-5.88501],"type":"Point"}
}