{
  "type": "Feature",
  "properties": {
    "gn:admin1_code":"20.0",
    "gn:asciiname":"Makoto",
    "gn:country_code":"CD",
    "gn:dem":634,
    "gn:feature_class":"P",
    "gn:feature_code":"PPL",
    "gn:name":"Makoto",
    "gn:population":0,
    "gn:timezone":"Africa/Kinshasa",
    "iso:country":"CD",
    "name:deu_x_preferred":[
        "Makoto"
    ],
    "name:kor_x_preferred":[
        "\ub9c8\ucf54\ud1a0"
    ],
    "name:nld_x_preferred":[
        "Makoto"
    ],
    "name:pol_x_preferred":[
        "Makoto"
    ],
    "name:por_x_preferred":[
        "Makoto"
    ],
    "wof:name":"Makoto",
    "wof:placetype":"locality"
},
  "geometry": {"coordinates":[18.77939,-5.77294],"type":"Point"}
}