{
  "type": "Feature",
  "properties": {
    "gn:admin1_code":"15.0",
    "gn:asciiname":"Lukushi",
    "gn:country_code":"CD",
    "gn:dem":889,
    "gn:feature_class":"P",
    "gn:feature_code":"PPL",
    "gn:name":"Lukushi",
    "gn:population":0,
    "gn:timezone":"Africa/Lubumbashi",
    "iso:country":"CD",
    "wof:name":"Lukushi",
    "wof:placetype":"locality"
},
  "geometry": {"coordinates":[25.64365,-7.61784],"type":"Point"}
}