{
  "type": "Feature",
  "properties": {
    "gn:admin1_code":"19.0",
    "gn:asciiname":"Kidiaki",
    "gn:country_code":"CD",
    "gn:dem":708,
    "gn:feature_class":"P",
    "gn:feature_code":"PPL",
    "gn:name":"Kidiaki",
    "gn:population":0,
    "gn:timezone":"Africa/Kinshasa",
    "iso:country":"CD",
    "wof:name":"Kidiaki",
    "wof:placetype":"locality"
},
  "geometry": {"coordinates":[17.23961,-5.40781],"type":"Point"}
}