{
  "type": "Feature",
  "properties": {
    "gn:admin1_code":"22.0",
    "gn:asciiname":"Walengolo",
    "gn:country_code":"CD",
    "gn:dem":1182,
    "gn:feature_class":"P",
    "gn:feature_code":"PPL",
    "gn:name":"Walengolo",
    "gn:population":0,
    "gn:timezone":"Africa/Lubumbashi",
    "iso:country":"CD",
    "wof:name":"Walengolo",
    "wof:placetype":"locality"
},
  "geometry": {"coordinates":[26.28333,-10.41667],"type":"Point"}
}