{
  "type": "Feature",
  "properties": {
    "gn:admin1_code":"8.0",
    "gn:asciiname":"Kinlumbu",
    "gn:country_code":"CD",
    "gn:dem":674,
    "gn:feature_class":"P",
    "gn:feature_code":"PPL",
    "gn:name":"Kinlumbu",
    "gn:population":0,
    "gn:timezone":"Africa/Kinshasa",
    "iso:country":"CD",
    "wof:name":"Kinlumbu",
    "wof:placetype":"locality"
},
  "geometry": {"coordinates":[15.30877,-5.41522],"type":"Point"}
}