{
  "type": "Feature",
  "properties": {
    "gn:admin1_code":"31.0",
    "gn:asciiname":"Yasala",
    "gn:country_code":"CD",
    "gn:dem":383,
    "gn:feature_class":"P",
    "gn:feature_code":"PPL",
    "gn:name":"Yasala",
    "gn:population":0,
    "gn:timezone":"Africa/Kinshasa",
    "iso:country":"CD",
    "wof:name":"Yasala",
    "wof:placetype":"locality"
},
  "geometry": {"coordinates":[22.55,-0.68333],"type":"Point"}
}