{
  "type": "Feature",
  "properties": {
    "gn:admin1_code":"18.0",
    "gn:asciiname":"Bakwa-Kwanga",
    "gn:country_code":"CD",
    "gn:dem":562,
    "gn:feature_class":"P",
    "gn:feature_code":"PPL",
    "gn:name":"Bakwa-Kwanga",
    "gn:population":0,
    "gn:timezone":"Africa/Lubumbashi",
    "iso:country":"CD",
    "wof:name":"Bakwa-Kwanga",
    "wof:placetype":"locality"
},
  "geometry": {"coordinates":[21.52982,-5.02658],"type":"Point"}
}