{
  "type": "Feature",
  "properties": {
    "gn:admin1_code":"8.0",
    "gn:asciiname":"Samba",
    "gn:country_code":"CD",
    "gn:dem":438,
    "gn:feature_class":"P",
    "gn:feature_code":"PPL",
    "gn:name":"Samba",
    "gn:population":0,
    "gn:timezone":"Africa/Kinshasa",
    "iso:country":"CD",
    "wof:name":"Samba",
    "wof:placetype":"locality"
},
  "geometry": {"coordinates":[14.37974,-5.69936],"type":"Point"}
}