{
  "type": "Feature",
  "properties": {
    "gn:admin1_code":"19.0",
    "gn:asciiname":"Mukukulu-Tseke",
    "gn:country_code":"CD",
    "gn:dem":700,
    "gn:feature_class":"P",
    "gn:feature_code":"PPL",
    "gn:name":"Mukukulu-Tseke",
    "gn:population":0,
    "gn:timezone":"Africa/Kinshasa",
    "iso:country":"CD",
    "wof:name":"Mukukulu-Tseke",
    "wof:placetype":"locality"
},
  "geometry": {"coordinates":[16.86326,-5.33519],"type":"Point"}
}