{
  "type": "Feature",
  "properties": {
    "gn:admin1_code":"22.0",
    "gn:asciiname":"Kabola",
    "gn:country_code":"CD",
    "gn:dem":1055,
    "gn:feature_class":"P",
    "gn:feature_code":"PPL",
    "gn:name":"Kabola",
    "gn:population":0,
    "gn:timezone":"Africa/Lubumbashi",
    "iso:country":"CD",
    "wof:name":"Kabola",
    "wof:placetype":"locality"
},
  "geometry": {"coordinates":[23.09786,-9.56845],"type":"Point"}
}