{
  "type": "Feature",
  "properties": {
    "gn:admin1_code":"8.0",
    "gn:asciiname":"Sonso",
    "gn:country_code":"CD",
    "gn:dem":370,
    "gn:feature_class":"P",
    "gn:feature_code":"PPL",
    "gn:name":"Sonso",
    "gn:population":0,
    "gn:timezone":"Africa/Kinshasa",
    "iso:country":"CD",
    "wof:name":"Sonso",
    "wof:placetype":"locality"
},
  "geometry": {"coordinates":[14.23351,-4.83784],"type":"Point"}
}