{
  "type": "Feature",
  "properties": {
    "gn:admin1_code":"22.0",
    "gn:asciiname":"Poyo",
    "gn:country_code":"CD",
    "gn:dem":1161,
    "gn:feature_class":"P",
    "gn:feature_code":"PPL",
    "gn:name":"Poyo",
    "gn:population":0,
    "gn:timezone":"Africa/Lubumbashi",
    "iso:country":"CD",
    "wof:name":"Poyo",
    "wof:placetype":"locality"
},
  "geometry": {"coordinates":[23.93801,-10.29654],"type":"Point"}
}