{
  "type": "Feature",
  "properties": {
    "gn:admin1_code":"19.0",
    "gn:asciiname":"Kalenge",
    "gn:country_code":"CD",
    "gn:dem":707,
    "gn:feature_class":"P",
    "gn:feature_code":"PPL",
    "gn:name":"Kalenge",
    "gn:population":0,
    "gn:timezone":"Africa/Kinshasa",
    "iso:country":"CD",
    "wof:name":"Kalenge",
    "wof:placetype":"locality"
},
  "geometry": {"coordinates":[16.87222,-5.38093],"type":"Point"}
}