{
  "type": "Feature",
  "properties": {
    "gn:admin1_code":"13.0",
    "gn:asciiname":"Yengeyine",
    "gn:country_code":"CD",
    "gn:dem":675,
    "gn:feature_class":"P",
    "gn:feature_code":"PPL",
    "gn:name":"Yengeyine",
    "gn:population":0,
    "gn:timezone":"Africa/Lubumbashi",
    "iso:country":"CD",
    "name:und_x_variant":[
        "Yengeyne",
        "Yengeyime",
        "Yengeyine"
    ],
    "wof:name":"Yengeyine",
    "wof:placetype":"locality"
},
  "geometry": {"coordinates":[26.65,3.11667],"type":"Point"}
}