{
  "type": "Feature",
  "properties": {
    "gn:admin1_code":"15.0",
    "gn:asciiname":"Kanzandu",
    "gn:country_code":"CD",
    "gn:dem":938,
    "gn:feature_class":"P",
    "gn:feature_code":"PPL",
    "gn:name":"Kanzandu",
    "gn:population":0,
    "gn:timezone":"Africa/Lubumbashi",
    "iso:country":"CD",
    "name:und_x_variant":[
        "Kangandu"
    ],
    "wof:name":"Kanzandu",
    "wof:placetype":"locality"
},
  "geometry": {"coordinates":[25.2461,-9.09558],"type":"Point"}
}