{
  "type": "Feature",
  "properties": {
    "gn:admin1_code":"23.0",
    "gn:asciiname":"Tshelatsha",
    "gn:country_code":"CD",
    "gn:dem":714,
    "gn:feature_class":"P",
    "gn:feature_code":"PPL",
    "gn:name":"Tshelatsha",
    "gn:population":0,
    "gn:timezone":"Africa/Lubumbashi",
    "iso:country":"CD",
    "wof:name":"Tshelatsha",
    "wof:placetype":"locality"
},
  "geometry": {"coordinates":[22.53065,-6.26466],"type":"Point"}
}