{
  "type": "Feature",
  "properties": {
    "gn:admin1_code":"31.0",
    "gn:asciiname":"Yayongo",
    "gn:country_code":"CD",
    "gn:dem":500,
    "gn:feature_class":"P",
    "gn:feature_code":"PPL",
    "gn:name":"Yayongo",
    "gn:population":0,
    "gn:timezone":"Africa/Kinshasa",
    "iso:country":"CD",
    "wof:name":"Yayongo",
    "wof:placetype":"locality"
},
  "geometry": {"coordinates":[22.80996,0.68335],"type":"Point"}
}