{
  "type": "Feature",
  "properties": {
    "gn:admin1_code":"19.0",
    "gn:asciiname":"Luzau",
    "gn:country_code":"CD",
    "gn:dem":626,
    "gn:feature_class":"P",
    "gn:feature_code":"PPL",
    "gn:name":"Luzau",
    "gn:population":0,
    "gn:timezone":"Africa/Kinshasa",
    "iso:country":"CD",
    "name:und_x_variant":[
        "Lusaw",
        "Luzau"
    ],
    "wof:name":"Luzau",
    "wof:placetype":"locality"
},
  "geometry": {"coordinates":[16.77383,-4.85176],"type":"Point"}
}