{
  "type": "Feature",
  "properties": {
    "gn:country":"CD",
    "gn:fcode":"ADM4",
    "gn:pop":150319,
    "iso:country":"CD",
    "qs:name":"commune de Barumbu",
    "qs:photos_9r":0,
    "qs:photos_sr":0,
    "qs:pop_sr":"9",
    "wof:name":"commune de Barumbu",
    "wof:placetype":"localadmin",
    "wof:population":150319
},
  "geometry": {"coordinates":[15.3279,-4.31783],"type":"Point"}
}