{
  "type": "Feature",
  "properties": {
    "gn:admin1_code":"27.0",
    "gn:asciiname":"Oyokenie",
    "gn:country_code":"CD",
    "gn:dem":501,
    "gn:feature_class":"P",
    "gn:feature_code":"PPL",
    "gn:name":"Oyokenie",
    "gn:population":0,
    "gn:timezone":"Africa/Lubumbashi",
    "iso:country":"CD",
    "wof:name":"Oyokenie",
    "wof:placetype":"locality"
},
  "geometry": {"coordinates":[23.28649,-4.14887],"type":"Point"}
}