{
  "type": "Feature",
  "properties": {
    "gn:admin1_code":"22.0",
    "gn:asciiname":"Samulelu",
    "gn:country_code":"CD",
    "gn:dem":1170,
    "gn:feature_class":"P",
    "gn:feature_code":"PPL",
    "gn:name":"Samulelu",
    "gn:population":0,
    "gn:timezone":"Africa/Lubumbashi",
    "iso:country":"CD",
    "wof:name":"Samulelu",
    "wof:placetype":"locality"
},
  "geometry": {"coordinates":[24.07446,-10.29359],"type":"Point"}
}