{
  "type": "Feature",
  "properties": {
    "gn:admin1_code":"22.0",
    "gn:asciiname":"Samakuku",
    "gn:country_code":"CD",
    "gn:dem":1042,
    "gn:feature_class":"P",
    "gn:feature_code":"PPL",
    "gn:name":"Samakuku",
    "gn:population":0,
    "gn:timezone":"Africa/Lubumbashi",
    "iso:country":"CD",
    "wof:name":"Samakuku",
    "wof:placetype":"locality"
},
  "geometry": {"coordinates":[23.86722,-9.53999],"type":"Point"}
}