{
  "type": "Feature",
  "properties": {
    "gn:admin1_code":"23.0",
    "gn:asciiname":"Supanti Kesu",
    "gn:country_code":"CD",
    "gn:dem":881,
    "gn:feature_class":"P",
    "gn:feature_code":"PPL",
    "gn:name":"Supanti Kesu",
    "gn:population":0,
    "gn:timezone":"Africa/Lubumbashi",
    "iso:country":"CD",
    "wof:name":"Supanti Kesu",
    "wof:placetype":"locality"
},
  "geometry": {"coordinates":[22.39926,-7.26444],"type":"Point"}
}