{
  "type": "Feature",
  "properties": {
    "gn:admin1_code":"22.0",
    "gn:asciiname":"Tshikula",
    "gn:country_code":"CD",
    "gn:dem":1077,
    "gn:feature_class":"P",
    "gn:feature_code":"PPL",
    "gn:name":"Tshikula",
    "gn:population":0,
    "gn:timezone":"Africa/Lubumbashi",
    "iso:country":"CD",
    "wof:name":"Tshikula",
    "wof:placetype":"locality"
},
  "geometry": {"coordinates":[23.5109,-10.16484],"type":"Point"}
}