{
  "type": "Feature",
  "properties": {
    "gn:admin1_code":"10.0",
    "gn:asciiname":"Kabundi-Mwamba Kisi",
    "gn:country_code":"CD",
    "gn:dem":513,
    "gn:feature_class":"P",
    "gn:feature_code":"PPL",
    "gn:name":"Kabundi-Mwamba Kisi",
    "gn:population":0,
    "gn:timezone":"Africa/Lubumbashi",
    "iso:country":"CD",
    "wof:name":"Kabundi-Mwamba Kisi",
    "wof:placetype":"locality"
},
  "geometry": {"coordinates":[26.9216,-4.93069],"type":"Point"}
}