{
  "type": "Feature",
  "properties": {
    "gn:admin1_code":"22.0",
    "gn:asciiname":"Kingamyambo",
    "gn:country_code":"CD",
    "gn:dem":1438,
    "gn:feature_class":"P",
    "gn:feature_code":"PPL",
    "gn:name":"Kingamyambo",
    "gn:population":0,
    "gn:timezone":"Africa/Lubumbashi",
    "iso:country":"CD",
    "wof:name":"Kingamyambo",
    "wof:placetype":"locality"
},
  "geometry": {"coordinates":[25.39139,-10.66056],"type":"Point"}
}