{
  "type": "Feature",
  "properties": {
    "gn:admin1_code":"12.0",
    "gn:asciiname":"Bilembo",
    "gn:country_code":"CD",
    "gn:dem":1026,
    "gn:feature_class":"P",
    "gn:feature_code":"PPL",
    "gn:name":"Bilembo",
    "gn:population":0,
    "gn:timezone":"Africa/Lubumbashi",
    "iso:country":"CD",
    "wof:name":"Bilembo",
    "wof:placetype":"locality"
},
  "geometry": {"coordinates":[28.33108,-2.98986],"type":"Point"}
}