{
  "type": "Feature",
  "properties": {
    "gn:admin1_code":"8.0",
    "gn:asciiname":"Kiluaka",
    "gn:country_code":"CD",
    "gn:dem":644,
    "gn:feature_class":"P",
    "gn:feature_code":"PPL",
    "gn:name":"Kiluaka",
    "gn:population":0,
    "gn:timezone":"Africa/Kinshasa",
    "iso:country":"CD",
    "wof:name":"Kiluaka",
    "wof:placetype":"locality"
},
  "geometry": {"coordinates":[14.06607,-4.45262],"type":"Point"}
}