{
  "type": "Feature",
  "properties": {
    "gn:admin1_code":"23.0",
    "gn:asciiname":"Luatshi",
    "gn:country_code":"CD",
    "gn:dem":907,
    "gn:feature_class":"P",
    "gn:feature_code":"PPL",
    "gn:name":"Luatshi",
    "gn:population":0,
    "gn:timezone":"Africa/Lubumbashi",
    "iso:country":"CD",
    "name:und_x_variant":[
        "Luashi",
        "Luatshi"
    ],
    "wof:name":"Luatshi",
    "wof:placetype":"locality"
},
  "geometry": {"coordinates":[22.46667,-7.58333],"type":"Point"}
}