{
  "type": "Feature",
  "properties": {
    "gn:admin1_code":"11.0",
    "gn:asciiname":"Shekatiti",
    "gn:country_code":"CD",
    "gn:dem":1174,
    "gn:feature_class":"P",
    "gn:feature_code":"PPL",
    "gn:name":"Shekatiti",
    "gn:population":0,
    "gn:timezone":"Africa/Lubumbashi",
    "iso:country":"CD",
    "wof:name":"Shekatiti",
    "wof:placetype":"locality"
},
  "geometry": {"coordinates":[28.37934000000001,-1.51311],"type":"Point"}
}