{
  "type": "Feature",
  "properties": {
    "gn:admin1_code":"22.0",
    "gn:asciiname":"Saseya",
    "gn:country_code":"CD",
    "gn:dem":1048,
    "gn:feature_class":"P",
    "gn:feature_code":"PPL",
    "gn:name":"Saseya",
    "gn:population":0,
    "gn:timezone":"Africa/Lubumbashi",
    "iso:country":"CD",
    "wof:name":"Saseya",
    "wof:placetype":"locality"
},
  "geometry": {"coordinates":[22.46728,-9.9445],"type":"Point"}
}