{
  "type": "Feature",
  "properties": {
    "gn:admin1_code":"13.0",
    "gn:asciiname":"Mbomoke",
    "gn:country_code":"CD",
    "gn:dem":477,
    "gn:feature_class":"P",
    "gn:feature_code":"PPL",
    "gn:name":"Mbomoke",
    "gn:population":0,
    "gn:timezone":"Africa/Lubumbashi",
    "iso:country":"CD",
    "wof:name":"Mbomoke",
    "wof:placetype":"locality"
},
  "geometry": {"coordinates":[23.94093,3.55566],"type":"Point"}
}