{
  "type": "Feature",
  "properties": {
    "gn:admin1_code":"23.0",
    "gn:asciiname":"Tshionza",
    "gn:country_code":"CD",
    "gn:dem":774,
    "gn:feature_class":"P",
    "gn:feature_code":"PPL",
    "gn:name":"Tshionza",
    "gn:population":0,
    "gn:timezone":"Africa/Lubumbashi",
    "iso:country":"CD",
    "wof:name":"Tshionza",
    "wof:placetype":"locality"
},
  "geometry": {"coordinates":[21.62975,-6.90404],"type":"Point"}
}