{
  "type": "Feature",
  "properties": {
    "gn:admin1_code":"18.0",
    "gn:asciiname":"Kadiangika",
    "gn:country_code":"CD",
    "gn:dem":807,
    "gn:feature_class":"P",
    "gn:feature_code":"PPL",
    "gn:name":"Kadiangika",
    "gn:population":0,
    "gn:timezone":"Africa/Lubumbashi",
    "iso:country":"CD",
    "wof:name":"Kadiangika",
    "wof:placetype":"locality"
},
  "geometry": {"coordinates":[19.91591,-6.42948],"type":"Point"}
}