{
  "type": "Feature",
  "properties": {
    "gn:admin1_code":"22.0",
    "gn:asciiname":"Muvunda",
    "gn:country_code":"CD",
    "gn:dem":1422,
    "gn:feature_class":"P",
    "gn:feature_code":"PPL",
    "gn:name":"Muvunda",
    "gn:population":0,
    "gn:timezone":"Africa/Lubumbashi",
    "iso:country":"CD",
    "name:und_x_variant":[
        "Nuvunda",
        "Mavunda Tshiwewe",
        "Muvunda Tshiwewe",
        "Muvunda"
    ],
    "wof:name":"Muvunda",
    "wof:placetype":"locality"
},
  "geometry": {"coordinates":[25.21667,-10.88333],"type":"Point"}
}