{
  "type": "Feature",
  "properties": {
    "gn:admin1_code":"20.0",
    "gn:asciiname":"Banzama",
    "gn:country_code":"CD",
    "gn:dem":445,
    "gn:feature_class":"P",
    "gn:feature_code":"PPL",
    "gn:name":"Banzama",
    "gn:population":0,
    "gn:timezone":"Africa/Kinshasa",
    "iso:country":"CD",
    "wof:name":"Banzama",
    "wof:placetype":"locality"
},
  "geometry": {"coordinates":[17.68834,-4.10406],"type":"Point"}
}