{
  "type": "Feature",
  "properties": {
    "gn:admin1_code":"15.0",
    "gn:asciiname":"Kapiri",
    "gn:country_code":"CD",
    "gn:dem":1004,
    "gn:feature_class":"P",
    "gn:feature_code":"PPL",
    "gn:name":"Kapiri",
    "gn:population":0,
    "gn:timezone":"Africa/Lubumbashi",
    "iso:country":"CD",
    "wof:name":"Kapiri",
    "wof:placetype":"locality"
},
  "geometry": {"coordinates":[24.98374,-10.09399],"type":"Point"}
}