{
  "type": "Feature",
  "properties": {
    "gn:admin1_code":"22.0",
    "gn:asciiname":"Mwamwaku",
    "gn:country_code":"CD",
    "gn:dem":966,
    "gn:feature_class":"P",
    "gn:feature_code":"PPL",
    "gn:name":"Mwamwaku",
    "gn:population":0,
    "gn:timezone":"Africa/Lubumbashi",
    "iso:country":"CD",
    "wof:name":"Mwamwaku",
    "wof:placetype":"locality"
},
  "geometry": {"coordinates":[22.97418,-9.8601],"type":"Point"}
}