{
  "type": "Feature",
  "properties": {
    "gn:admin1_code":"4.0",
    "gn:asciiname":"Tsbibadik",
    "gn:country_code":"CD",
    "gn:dem":566,
    "gn:feature_class":"P",
    "gn:feature_code":"PPL",
    "gn:name":"Tsbibadik",
    "gn:population":0,
    "gn:timezone":"Africa/Lubumbashi",
    "iso:country":"CD",
    "name:und_x_variant":[
        "Tsbibadeka"
    ],
    "wof:name":"Tsbibadik",
    "wof:placetype":"locality"
},
  "geometry": {"coordinates":[23.78165,-6.04038],"type":"Point"}
}