{
  "type": "Feature",
  "properties": {
    "gn:admin1_code":"23.0",
    "gn:asciiname":"Lueta",
    "gn:country_code":"CD",
    "gn:dem":927,
    "gn:feature_class":"P",
    "gn:feature_code":"PPL",
    "gn:name":"Lueta",
    "gn:population":0,
    "gn:timezone":"Africa/Lubumbashi",
    "iso:country":"CD",
    "name:ceb_x_preferred":[
        "Comuna Lueta"
    ],
    "name:epo_x_preferred":[
        "Lueta"
    ],
    "name:fra_x_preferred":[
        "Lueta"
    ],
    "name:ita_x_preferred":[
        "Lueta"
    ],
    "name:msa_x_preferred":[
        "Lueta"
    ],
    "name:nld_x_preferred":[
        "Lueta"
    ],
    "name:por_x_preferred":[
        "Lueta"
    ],
    "name:ron_x_preferred":[
        "Comuna Lueta"
    ],
    "name:srp_x_preferred":[
        "\u041e\u043f\u0448\u0442\u0438\u043d\u0430 \u041b\u0443\u0435\u0442\u0430"
    ],
    "name:ukr_x_preferred":[
        "\u041b\u0443\u0435\u0442\u0430"
    ],
    "name:vie_x_preferred":[
        "Lueta"
    ],
    "name:vol_x_preferred":[
        "Lueta"
    ],
    "name:zho_x_preferred":[
        "\u76e7\u57c3\u5854\u9109"
    ],
    "wof:name":"Lueta",
    "wof:placetype":"locality"
},
  "geometry": {"coordinates":[22.09618,-7.30996],"type":"Point"}
}