{
  "type": "Feature",
  "properties": {
    "gn:admin1_code":"23.0",
    "gn:asciiname":"Shawanga",
    "gn:country_code":"CD",
    "gn:dem":853,
    "gn:feature_class":"P",
    "gn:feature_code":"PPL",
    "gn:name":"Shawanga",
    "gn:population":0,
    "gn:timezone":"Africa/Lubumbashi",
    "iso:country":"CD",
    "wof:name":"Shawanga",
    "wof:placetype":"locality"
},
  "geometry": {"coordinates":[21.81762,-6.98499],"type":"Point"}
}