{
  "type": "Feature",
  "properties": {
    "gn:admin1_code":"20.0",
    "gn:asciiname":"Nsualala",
    "gn:country_code":"CD",
    "gn:dem":620,
    "gn:feature_class":"P",
    "gn:feature_code":"PPL",
    "gn:name":"Nsualala",
    "gn:population":0,
    "gn:timezone":"Africa/Kinshasa",
    "iso:country":"CD",
    "wof:name":"Nsualala",
    "wof:placetype":"locality"
},
  "geometry": {"coordinates":[20.04027,-5.11738],"type":"Point"}
}