{
  "type": "Feature",
  "properties": {
    "gn:admin1_code":"25.0",
    "gn:asciiname":"Yasono",
    "gn:country_code":"CD",
    "gn:dem":415,
    "gn:feature_class":"P",
    "gn:feature_code":"PPL",
    "gn:name":"Yasono",
    "gn:population":0,
    "gn:timezone":"Africa/Kinshasa",
    "iso:country":"CD",
    "wof:name":"Yasono",
    "wof:placetype":"locality"
},
  "geometry": {"coordinates":[21.89054,2.7471],"type":"Point"}
}