{
  "type": "Feature",
  "properties": {
    "gn:admin1_code":"8.0",
    "gn:asciiname":"Gongo",
    "gn:country_code":"CD",
    "gn:dem":102,
    "gn:feature_class":"P",
    "gn:feature_code":"PPL",
    "gn:name":"Gongo",
    "gn:population":0,
    "gn:timezone":"Africa/Kinshasa",
    "iso:country":"CD",
    "wof:name":"Gongo",
    "wof:placetype":"locality"
},
  "geometry": {"coordinates":[13.05435,-5.75107],"type":"Point"}
}