{
  "type": "Feature",
  "properties": {
    "gn:admin1_code":"29.0",
    "gn:asciiname":"Leya",
    "gn:country_code":"CD",
    "gn:dem":673,
    "gn:feature_class":"P",
    "gn:feature_code":"PPL",
    "gn:name":"Leya",
    "gn:population":0,
    "gn:timezone":"Africa/Lubumbashi",
    "iso:country":"CD",
    "name:deu_x_preferred":[
        "Leya"
    ],
    "wof:name":"Leya",
    "wof:placetype":"locality"
},
  "geometry": {"coordinates":[26.74383,-5.557],"type":"Point"}
}