{
  "type": "Feature",
  "properties": {
    "gn:admin1_code":"12.0",
    "gn:asciiname":"Kalungwe",
    "gn:country_code":"CD",
    "gn:dem":808,
    "gn:feature_class":"P",
    "gn:feature_code":"PPL",
    "gn:name":"Kalungwe",
    "gn:population":0,
    "gn:timezone":"Africa/Lubumbashi",
    "iso:country":"CD",
    "wof:name":"Kalungwe",
    "wof:placetype":"locality"
},
  "geometry": {"coordinates":[29.13222,-3.46472],"type":"Point"}
}