{
  "type": "Feature",
  "properties": {
    "gn:admin1_code":"28.0",
    "gn:asciiname":"Taba",
    "gn:country_code":"CD",
    "gn:dem":380,
    "gn:feature_class":"P",
    "gn:feature_code":"PPL",
    "gn:name":"Taba",
    "gn:population":0,
    "gn:timezone":"Africa/Kinshasa",
    "iso:country":"CD",
    "name:ceb_x_preferred":[
        "Taba"
    ],
    "name:deu_x_preferred":[
        "Taba"
    ],
    "name:fra_x_preferred":[
        "Taba"
    ],
    "name:nld_x_preferred":[
        "Taba"
    ],
    "name:spa_x_preferred":[
        "Taba"
    ],
    "name:swe_x_preferred":[
        "Taba"
    ],
    "wof:name":"Taba",
    "wof:placetype":"locality"
},
  "geometry": {"coordinates":[18.88355,4.38778],"type":"Point"}
}