{
  "type": "Feature",
  "properties": {
    "gn:admin1_code":"30.0",
    "gn:asciiname":"Ilota",
    "gn:country_code":"CD",
    "gn:dem":442,
    "gn:feature_class":"P",
    "gn:feature_code":"PPL",
    "gn:name":"Ilota",
    "gn:population":0,
    "gn:timezone":"Africa/Lubumbashi",
    "iso:country":"CD",
    "wof:name":"Ilota",
    "wof:placetype":"locality"
},
  "geometry": {"coordinates":[24.43333,0.26667],"type":"Point"}
}