{
  "type": "Feature",
  "properties": {
    "gn:admin1_code":"11.0",
    "gn:asciiname":"Mumo",
    "gn:country_code":"CD",
    "gn:dem":1716,
    "gn:feature_class":"P",
    "gn:feature_code":"PPL",
    "gn:name":"Mumo",
    "gn:population":0,
    "gn:timezone":"Africa/Lubumbashi",
    "iso:country":"CD",
    "name:ell_x_preferred":[
        "\u039c\u03bf\u03cd\u03bc\u03bf"
    ],
    "wof:name":"Mumo",
    "wof:placetype":"locality"
},
  "geometry": {"coordinates":[28.85214,-1.01846],"type":"Point"}
}