{
  "type": "Feature",
  "properties": {
    "gn:admin1_code":"2.0",
    "gn:asciiname":"Boso-Ebangulu",
    "gn:country_code":"CD",
    "gn:dem":359,
    "gn:feature_class":"P",
    "gn:feature_code":"PPL",
    "gn:name":"Boso-Ebangulu",
    "gn:population":0,
    "gn:timezone":"Africa/Kinshasa",
    "iso:country":"CD",
    "wof:name":"Boso-Ebangulu",
    "wof:placetype":"locality"
},
  "geometry": {"coordinates":[19.26667,0.86667],"type":"Point"}
}