{
  "type": "Feature",
  "properties": {
    "gn:admin1_code":"23.0",
    "gn:asciiname":"Isuku",
    "gn:country_code":"CD",
    "gn:dem":857,
    "gn:feature_class":"P",
    "gn:feature_code":"PPL",
    "gn:name":"Isuku",
    "gn:population":0,
    "gn:timezone":"Africa/Lubumbashi",
    "iso:country":"CD",
    "wof:name":"Isuku",
    "wof:placetype":"locality"
},
  "geometry": {"coordinates":[22.51022,-7.15487],"type":"Point"}
}