{
  "type": "Feature",
  "properties": {
    "gn:admin1_code":"14.0",
    "gn:asciiname":"Simpoka",
    "gn:country_code":"CD",
    "gn:dem":1281,
    "gn:feature_class":"P",
    "gn:feature_code":"PPL",
    "gn:name":"Simpoka",
    "gn:population":0,
    "gn:timezone":"Africa/Lubumbashi",
    "iso:country":"CD",
    "wof:name":"Simpoka",
    "wof:placetype":"locality"
},
  "geometry": {"coordinates":[27.3078,-11.79223],"type":"Point"}
}