{
  "type": "Feature",
  "properties": {
    "gn:admin1_code":"15.0",
    "gn:asciiname":"Kakombo",
    "gn:country_code":"CD",
    "gn:dem":591,
    "gn:feature_class":"P",
    "gn:feature_code":"PPL",
    "gn:name":"Kakombo",
    "gn:population":0,
    "gn:timezone":"Africa/Lubumbashi",
    "iso:country":"CD",
    "wof:name":"Kakombo",
    "wof:placetype":"locality"
},
  "geometry": {"coordinates":[26.81667,-7.73333],"type":"Point"}
}