{
  "type": "Feature",
  "properties": {
    "gn:admin1_code":"22.0",
    "gn:asciiname":"Fumabanda",
    "gn:country_code":"CD",
    "gn:dem":914,
    "gn:feature_class":"P",
    "gn:feature_code":"PPL",
    "gn:name":"Fumabanda",
    "gn:population":0,
    "gn:timezone":"Africa/Lubumbashi",
    "iso:country":"CD",
    "wof:name":"Fumabanda",
    "wof:placetype":"locality"
},
  "geometry": {"coordinates":[22.84012,-9.71678],"type":"Point"}
}