{
  "type": "Feature",
  "properties": {
    "gn:admin1_code":"19.0",
    "gn:asciiname":"Shamwako",
    "gn:country_code":"CD",
    "gn:dem":1069,
    "gn:feature_class":"P",
    "gn:feature_code":"PPL",
    "gn:name":"Shamwako",
    "gn:population":0,
    "gn:timezone":"Africa/Kinshasa",
    "iso:country":"CD",
    "wof:name":"Shamwako",
    "wof:placetype":"locality"
},
  "geometry": {"coordinates":[18.52296,-7.1536],"type":"Point"}
}