{
  "type": "Feature",
  "properties": {
    "gn:admin1_code":"18.0",
    "gn:asciiname":"Kasonga",
    "gn:country_code":"CD",
    "gn:dem":628,
    "gn:feature_class":"P",
    "gn:feature_code":"PPL",
    "gn:name":"Kasonga",
    "gn:population":0,
    "gn:timezone":"Africa/Lubumbashi",
    "iso:country":"CD",
    "wof:name":"Kasonga",
    "wof:placetype":"locality"
},
  "geometry": {"coordinates":[21.19772,-5.4703],"type":"Point"}
}