{
  "type": "Feature",
  "properties": {
    "gn:admin1_code":"13.0",
    "gn:asciiname":"Balanga",
    "gn:country_code":"CD",
    "gn:dem":698,
    "gn:feature_class":"P",
    "gn:feature_code":"PPL",
    "gn:name":"Balanga",
    "gn:population":0,
    "gn:timezone":"Africa/Lubumbashi",
    "iso:country":"CD",
    "name:ceb_x_preferred":[
        "Balanga"
    ],
    "name:ilo_x_preferred":[
        "Balanga"
    ],
    "name:ita_x_preferred":[
        "Balanga"
    ],
    "name:swe_x_preferred":[
        "Balanga"
    ],
    "wof:name":"Balanga",
    "wof:placetype":"locality"
},
  "geometry": {"coordinates":[27.28309,3.61094],"type":"Point"}
}