{
  "type": "Feature",
  "properties": {
    "gn:admin1_code":"14.0",
    "gn:asciiname":"Loweshia",
    "gn:country_code":"CD",
    "gn:dem":1400,
    "gn:feature_class":"P",
    "gn:feature_code":"PPL",
    "gn:name":"Loweshia",
    "gn:population":0,
    "gn:timezone":"Africa/Lubumbashi",
    "iso:country":"CD",
    "wof:name":"Loweshia",
    "wof:placetype":"locality"
},
  "geometry": {"coordinates":[26.53333,-11.48333],"type":"Point"}
}