{
  "type": "Feature",
  "properties": {
    "gn:admin1_code":"19.0",
    "gn:asciiname":"Ngi-Muwandaka",
    "gn:country_code":"CD",
    "gn:dem":523,
    "gn:feature_class":"P",
    "gn:feature_code":"PPL",
    "gn:name":"Ngi-Muwandaka",
    "gn:population":0,
    "gn:timezone":"Africa/Kinshasa",
    "iso:country":"CD",
    "wof:name":"Ngi-Muwandaka",
    "wof:placetype":"locality"
},
  "geometry": {"coordinates":[17.46414,-4.30585],"type":"Point"}
}