{
  "type": "Feature",
  "properties": {
    "gn:admin1_code":"20.0",
    "gn:asciiname":"Kipata",
    "gn:country_code":"CD",
    "gn:dem":534,
    "gn:feature_class":"P",
    "gn:feature_code":"PPL",
    "gn:name":"Kipata",
    "gn:population":0,
    "gn:timezone":"Africa/Kinshasa",
    "iso:country":"CD",
    "wof:name":"Kipata",
    "wof:placetype":"locality"
},
  "geometry": {"coordinates":[17.83256,-4.82154],"type":"Point"}
}