{
  "type": "Feature",
  "properties": {
    "gn:admin1_code":"19.0",
    "gn:asciiname":"Tunganene",
    "gn:country_code":"CD",
    "gn:dem":587,
    "gn:feature_class":"P",
    "gn:feature_code":"PPL",
    "gn:name":"Tunganene",
    "gn:population":0,
    "gn:timezone":"Africa/Kinshasa",
    "iso:country":"CD",
    "wof:name":"Tunganene",
    "wof:placetype":"locality"
},
  "geometry": {"coordinates":[19.58285,-6.37089],"type":"Point"}
}