{
  "type": "Feature",
  "properties": {
    "gn:admin1_code":"13.0",
    "gn:asciiname":"Mabede",
    "gn:country_code":"CD",
    "gn:dem":622,
    "gn:feature_class":"P",
    "gn:feature_code":"PPL",
    "gn:name":"Mabede",
    "gn:population":0,
    "gn:timezone":"Africa/Lubumbashi",
    "iso:country":"CD",
    "wof:name":"Mabede",
    "wof:placetype":"locality"
},
  "geometry": {"coordinates":[25.96667,2.83333],"type":"Point"}
}