{
  "type": "Feature",
  "properties": {
    "gn:admin1_code":"17.0",
    "gn:asciiname":"Mayaribu",
    "gn:country_code":"CD",
    "gn:dem":1024,
    "gn:feature_class":"P",
    "gn:feature_code":"PPL",
    "gn:name":"Mayaribu",
    "gn:population":0,
    "gn:timezone":"Africa/Lubumbashi",
    "iso:country":"CD",
    "name:fra_x_preferred":[
        "Mayaribu"
    ],
    "name:fra_x_variant":[
        "Marabu"
    ],
    "name:und_x_variant":[
        "Marabu"
    ],
    "wof:name":"Mayaribu",
    "wof:placetype":"locality"
},
  "geometry": {"coordinates":[29.96883,1.47641],"type":"Point"}
}