{
  "type": "Feature",
  "properties": {
    "gn:admin1_code":"24.0",
    "gn:asciiname":"Tito",
    "gn:country_code":"CD",
    "gn:dem":320,
    "gn:feature_class":"P",
    "gn:feature_code":"PPL",
    "gn:name":"Tito",
    "gn:population":0,
    "gn:timezone":"Africa/Kinshasa",
    "iso:country":"CD",
    "name:und_x_variant":[
        "Itito",
        "Tito"
    ],
    "wof:name":"Tito",
    "wof:placetype":"locality"
},
  "geometry": {"coordinates":[18.06667,-1.26667],"type":"Point"}
}