{
  "type": "Feature",
  "properties": {
    "gn:admin1_code":"20.0",
    "gn:asciiname":"Balibi",
    "gn:country_code":"CD",
    "gn:dem":377,
    "gn:feature_class":"P",
    "gn:feature_code":"PPL",
    "gn:name":"Balibi",
    "gn:population":0,
    "gn:timezone":"Africa/Kinshasa",
    "iso:country":"CD",
    "wof:name":"Balibi",
    "wof:placetype":"locality"
},
  "geometry": {"coordinates":[18.48097000000001,-3.86914],"type":"Point"}
}