{
  "type": "Feature",
  "properties": {
    "gn:admin1_code":"18.0",
    "gn:asciiname":"Malembe-Kakese",
    "gn:country_code":"CD",
    "gn:dem":621,
    "gn:feature_class":"P",
    "gn:feature_code":"PPL",
    "gn:name":"Malembe-Kakese",
    "gn:population":0,
    "gn:timezone":"Africa/Lubumbashi",
    "iso:country":"CD",
    "wof:name":"Malembe-Kakese",
    "wof:placetype":"locality"
},
  "geometry": {"coordinates":[20.25605,-4.63622],"type":"Point"}
}