{
  "type": "Feature",
  "properties": {
    "gn:admin1_code":"19.0",
    "gn:asciiname":"Munanga",
    "gn:country_code":"CD",
    "gn:dem":1080,
    "gn:feature_class":"P",
    "gn:feature_code":"PPL",
    "gn:name":"Munanga",
    "gn:population":0,
    "gn:timezone":"Africa/Kinshasa",
    "iso:country":"CD",
    "wof:name":"Munanga",
    "wof:placetype":"locality"
},
  "geometry": {"coordinates":[19.33982,-7.96917],"type":"Point"}
}