{
  "type": "Feature",
  "properties": {
    "gn:admin1_code":"21.0",
    "gn:asciiname":"Bena-Kabala",
    "gn:country_code":"CD",
    "gn:dem":651,
    "gn:feature_class":"P",
    "gn:feature_code":"PPL",
    "gn:name":"Bena-Kabala",
    "gn:population":0,
    "gn:timezone":"Africa/Lubumbashi",
    "iso:country":"CD",
    "name:und_x_variant":[
        "Kabala",
        "Bena-Kabala"
    ],
    "wof:name":"Bena-Kabala",
    "wof:placetype":"locality"
},
  "geometry": {"coordinates":[23.99831,-6.50221],"type":"Point"}
}