{
  "type": "Feature",
  "properties": {
    "gn:admin1_code":"20.0",
    "gn:asciiname":"Mantshiene",
    "gn:country_code":"CD",
    "gn:dem":358,
    "gn:feature_class":"P",
    "gn:feature_code":"PPL",
    "gn:name":"Mantshiene",
    "gn:population":0,
    "gn:timezone":"Africa/Kinshasa",
    "iso:country":"CD",
    "name:und_x_variant":[
        "Mantsiene",
        "Mantshiene",
        "Mantiene"
    ],
    "wof:name":"Mantshiene",
    "wof:placetype":"locality"
},
  "geometry": {"coordinates":[17.71517,-3.81559],"type":"Point"}
}