{
  "type": "Feature",
  "properties": {
    "gn:admin1_code":"20.0",
    "gn:asciiname":"Mutobolo",
    "gn:country_code":"CD",
    "gn:dem":769,
    "gn:feature_class":"P",
    "gn:feature_code":"PPL",
    "gn:name":"Mutobolo",
    "gn:population":0,
    "gn:timezone":"Africa/Kinshasa",
    "iso:country":"CD",
    "wof:name":"Mutobolo",
    "wof:placetype":"locality"
},
  "geometry": {"coordinates":[19.07487,-5.79701],"type":"Point"}
}