{
  "type": "Feature",
  "properties": {
    "gn:admin1_code":"22.0",
    "gn:asciiname":"Tshajimbo",
    "gn:country_code":"CD",
    "gn:dem":1024,
    "gn:feature_class":"P",
    "gn:feature_code":"PPL",
    "gn:name":"Tshajimbo",
    "gn:population":0,
    "gn:timezone":"Africa/Lubumbashi",
    "iso:country":"CD",
    "wof:name":"Tshajimbo",
    "wof:placetype":"locality"
},
  "geometry": {"coordinates":[22.71166,-9.87284],"type":"Point"}
}