{
  "type": "Feature",
  "properties": {
    "gn:admin1_code":"22.0",
    "gn:asciiname":"Lutongo",
    "gn:country_code":"CD",
    "gn:dem":958,
    "gn:feature_class":"P",
    "gn:feature_code":"PPL",
    "gn:name":"Lutongo",
    "gn:population":0,
    "gn:timezone":"Africa/Lubumbashi",
    "iso:country":"CD",
    "wof:name":"Lutongo",
    "wof:placetype":"locality"
},
  "geometry": {"coordinates":[22.66141,-9.39768],"type":"Point"}
}