{
  "type": "Feature",
  "properties": {
    "gn:admin1_code":"14.0",
    "gn:asciiname":"Kiniama",
    "gn:country_code":"CD",
    "gn:dem":1083,
    "gn:feature_class":"P",
    "gn:feature_code":"PPL",
    "gn:name":"Kiniama",
    "gn:population":0,
    "gn:timezone":"Africa/Lubumbashi",
    "iso:country":"CD",
    "name:und_x_variant":[
        "Kaniama",
        "Shiniama",
        "Kiniama"
    ],
    "wof:name":"Kiniama",
    "wof:placetype":"locality"
},
  "geometry": {"coordinates":[28.33931,-11.48375],"type":"Point"}
}