{
  "type": "Feature",
  "properties": {
    "gn:admin1_code":"21.0",
    "gn:asciiname":"Kabwe Deuxieme",
    "gn:country_code":"CD",
    "gn:dem":742,
    "gn:feature_class":"P",
    "gn:feature_code":"PPL",
    "gn:name":"Kabwe Deuxi\u00e8me",
    "gn:population":0,
    "gn:timezone":"Africa/Lubumbashi",
    "iso:country":"CD",
    "name:und_x_variant":[
        "Kabwe Deuxi\u00e8me",
        "Kabwe II"
    ],
    "wof:name":"Kabwe Deuxieme",
    "wof:placetype":"locality"
},
  "geometry": {"coordinates":[25.3261,-6.20706],"type":"Point"}
}