{
  "type": "Feature",
  "properties": {
    "gn:admin1_code":"6.0",
    "gn:asciiname":"Ngombe",
    "gn:country_code":"CD",
    "gn:dem":299,
    "gn:feature_class":"P",
    "gn:feature_code":"PPL",
    "gn:name":"Ngombe",
    "gn:population":0,
    "gn:timezone":"Africa/Kinshasa",
    "iso:country":"CD",
    "name:ceb_x_preferred":[
        "Ngombe"
    ],
    "name:deu_x_preferred":[
        "Ngombe"
    ],
    "name:fra_x_preferred":[
        "Ngombe"
    ],
    "name:swa_x_preferred":[
        "Kingombe"
    ],
    "name:swe_x_preferred":[
        "Ngombe"
    ],
    "wof:name":"Ngombe",
    "wof:placetype":"locality"
},
  "geometry": {"coordinates":[15.17905,-4.39993],"type":"Point"}
}