{
  "type": "Feature",
  "properties": {
    "gn:admin1_code":"15.0",
    "gn:asciiname":"Kabelwe",
    "gn:country_code":"CD",
    "gn:dem":567,
    "gn:feature_class":"P",
    "gn:feature_code":"PPL",
    "gn:name":"Kabelwe",
    "gn:population":0,
    "gn:timezone":"Africa/Lubumbashi",
    "iso:country":"CD",
    "wof:name":"Kabelwe",
    "wof:placetype":"locality"
},
  "geometry": {"coordinates":[26.13394,-8.69199],"type":"Point"}
}