{
  "type": "Feature",
  "properties": {
    "gn:admin1_code":"27.0",
    "gn:asciiname":"Malela",
    "gn:country_code":"CD",
    "gn:dem":720,
    "gn:feature_class":"P",
    "gn:feature_code":"PPL",
    "gn:name":"Malela",
    "gn:population":0,
    "gn:timezone":"Africa/Lubumbashi",
    "iso:country":"CD",
    "wof:name":"Malela",
    "wof:placetype":"locality"
},
  "geometry": {"coordinates":[23.87568,-5.60018],"type":"Point"}
}