{
  "type": "Feature",
  "properties": {
    "gn:admin1_code":"22.0",
    "gn:asciiname":"Kahuna",
    "gn:country_code":"CD",
    "gn:dem":1044,
    "gn:feature_class":"P",
    "gn:feature_code":"PPL",
    "gn:name":"Kahuna",
    "gn:population":0,
    "gn:timezone":"Africa/Lubumbashi",
    "iso:country":"CD",
    "wof:name":"Kahuna",
    "wof:placetype":"locality"
},
  "geometry": {"coordinates":[22.38603,-10.60674],"type":"Point"}
}