{
  "type": "Feature",
  "properties": {
    "gn:admin1_code":"22.0",
    "gn:asciiname":"Kahuna",
    "gn:country_code":"CD",
    "gn:dem":1044,
    "gn:feature_class":"P",
    "gn:feature_code":"PPL",
    "gn:name":"Kahuna",
    "gn:population":0,
    "gn:timezone":"Africa/Lubumbashi",
    "iso:country":"CD",
    "name:deu_x_preferred":[
        "Kahuna"
    ],
    "name:epo_x_preferred":[
        "Kahuna"
    ],
    "name:eus_x_preferred":[
        "Kahuna"
    ],
    "name:hrv_x_preferred":[
        "Kahuna"
    ],
    "name:ita_x_preferred":[
        "Kahuna"
    ],
    "name:jpn_x_preferred":[
        "\u30ab\u30d5\u30ca"
    ],
    "name:lat_x_preferred":[
        "Kahuna"
    ],
    "name:pol_x_preferred":[
        "Kahuna"
    ],
    "name:por_x_preferred":[
        "Kahuna"
    ],
    "name:spa_x_preferred":[
        "Kahuna"
    ],
    "name:tur_x_preferred":[
        "Kahuna"
    ],
    "name:zho_x_preferred":[
        "\u5361\u80e1\u7d0d"
    ],
    "wof:name":"Kahuna",
    "wof:placetype":"locality"
},
  "geometry": {"coordinates":[22.38603,-10.60674],"type":"Point"}
}