{
  "type": "Feature",
  "properties": {
    "gn:admin1_code":"22.0",
    "gn:asciiname":"Tshingand Deuxieme",
    "gn:country_code":"CD",
    "gn:dem":1087,
    "gn:feature_class":"P",
    "gn:feature_code":"PPL",
    "gn:name":"Tshingand Deuxi\u00e8me",
    "gn:population":0,
    "gn:timezone":"Africa/Lubumbashi",
    "iso:country":"CD",
    "name:und_x_variant":[
        "Tshingand Deuxi\u00e8me",
        "Tshinganda"
    ],
    "wof:name":"Tshingand Deuxieme",
    "wof:placetype":"locality"
},
  "geometry": {"coordinates":[23.21133,-8.5699],"type":"Point"}
}