{
  "type": "Feature",
  "properties": {
    "gn:admin1_code":"8.0",
    "gn:asciiname":"Banza-Nzadi",
    "gn:country_code":"CD",
    "gn:dem":285,
    "gn:feature_class":"P",
    "gn:feature_code":"PPL",
    "gn:name":"Banza-Nzadi",
    "gn:population":0,
    "gn:timezone":"Africa/Kinshasa",
    "iso:country":"CD",
    "name:und_x_variant":[
        "Banza-Gombe",
        "Banza-Nzadi"
    ],
    "wof:name":"Banza-Nzadi",
    "wof:placetype":"locality"
},
  "geometry": {"coordinates":[13.98053,-5.10247],"type":"Point"}
}