{
  "type": "Feature",
  "properties": {
    "gn:admin1_code":"30.0",
    "gn:asciiname":"Etutu",
    "gn:country_code":"CD",
    "gn:dem":476,
    "gn:feature_class":"P",
    "gn:feature_code":"PPL",
    "gn:name":"Etutu",
    "gn:population":0,
    "gn:timezone":"Africa/Lubumbashi",
    "iso:country":"CD",
    "name:und_x_variant":[
        "Etutu Simbele"
    ],
    "wof:name":"Etutu",
    "wof:placetype":"locality"
},
  "geometry": {"coordinates":[24.21339,-0.66364],"type":"Point"}
}