{
  "type": "Feature",
  "properties": {
    "gn:admin1_code":"12.0",
    "gn:asciiname":"Muikabila",
    "gn:country_code":"CD",
    "gn:dem":1944,
    "gn:feature_class":"P",
    "gn:feature_code":"PPL",
    "gn:name":"Muikabila",
    "gn:population":0,
    "gn:timezone":"Africa/Lubumbashi",
    "iso:country":"CD",
    "wof:name":"Muikabila",
    "wof:placetype":"locality"
},
  "geometry": {"coordinates":[29.01361,-3.8525],"type":"Point"}
}