{
  "type": "Feature",
  "properties": {
    "gn:admin1_code":"29.0",
    "gn:asciiname":"Dilenge",
    "gn:country_code":"CD",
    "gn:dem":736,
    "gn:feature_class":"P",
    "gn:feature_code":"PPL",
    "gn:name":"Dilenge",
    "gn:population":0,
    "gn:timezone":"Africa/Lubumbashi",
    "iso:country":"CD",
    "wof:name":"Dilenge",
    "wof:placetype":"locality"
},
  "geometry": {"coordinates":[26.63916,-7.43534],"type":"Point"}
}