{
  "type": "Feature",
  "properties": {
    "gn:admin1_code":"17.0",
    "gn:asciiname":"Mandro",
    "gn:country_code":"CD",
    "gn:dem":1406,
    "gn:feature_class":"P",
    "gn:feature_code":"PPL",
    "gn:name":"Mandro",
    "gn:population":0,
    "gn:timezone":"Africa/Lubumbashi",
    "iso:country":"CD",
    "wof:name":"Mandro",
    "wof:placetype":"locality"
},
  "geometry": {"coordinates":[30.35416,1.57462],"type":"Point"}
}