{
  "type": "Feature",
  "properties": {
    "gn:admin1_code":"16.0",
    "gn:asciiname":"Apodo",
    "gn:country_code":"CD",
    "gn:dem":858,
    "gn:feature_class":"P",
    "gn:feature_code":"PPL",
    "gn:name":"Apodo",
    "gn:population":0,
    "gn:timezone":"Africa/Lubumbashi",
    "iso:country":"CD",
    "wof:name":"Apodo",
    "wof:placetype":"locality"
},
  "geometry": {"coordinates":[28.64419,2.59761],"type":"Point"}
}