{
  "type": "Feature",
  "properties": {
    "gn:admin1_code":"0.0",
    "gn:asciiname":"Kabongo",
    "gn:country_code":"CD",
    "gn:dem":1013,
    "gn:feature_class":"P",
    "gn:feature_code":"PPL",
    "gn:name":"Kabongo",
    "gn:population":0,
    "gn:timezone":"Africa/Lubumbashi",
    "iso:country":"CD",
    "wof:name":"Kabongo",
    "wof:placetype":"locality"
},
  "geometry": {"coordinates":[25.58333,-7.31667],"type":"Point"}
}