{
  "type": "Feature",
  "properties": {
    "gn:admin1_code":"19.0",
    "gn:asciiname":"Shakalongo",
    "gn:country_code":"CD",
    "gn:dem":1112,
    "gn:feature_class":"P",
    "gn:feature_code":"PPL",
    "gn:name":"Shakalongo",
    "gn:population":0,
    "gn:timezone":"Africa/Kinshasa",
    "iso:country":"CD",
    "wof:name":"Shakalongo",
    "wof:placetype":"locality"
},
  "geometry": {"coordinates":[18.66447,-7.57798],"type":"Point"}
}