{
  "type": "Feature",
  "properties": {
    "gn:admin1_code":"8.0",
    "gn:asciiname":"Nkolo",
    "gn:country_code":"CD",
    "gn:dem":451,
    "gn:feature_class":"P",
    "gn:feature_code":"PPL",
    "gn:name":"Nkolo",
    "gn:population":0,
    "gn:timezone":"Africa/Kinshasa",
    "iso:country":"CD",
    "name:und_x_variant":[
        "Kolo",
        "Nkolo"
    ],
    "wof:name":"Nkolo",
    "wof:placetype":"locality"
},
  "geometry": {"coordinates":[14.87339,-5.44493],"type":"Point"}
}