{
  "type": "Feature",
  "properties": {
    "gn:admin1_code":"20.0",
    "gn:asciiname":"Sekwa-Kiloka",
    "gn:country_code":"CD",
    "gn:dem":744,
    "gn:feature_class":"P",
    "gn:feature_code":"PPL",
    "gn:name":"Sekwa-Kiloka",
    "gn:population":0,
    "gn:timezone":"Africa/Kinshasa",
    "iso:country":"CD",
    "name:und_x_variant":[
        "Sekwa-Kitoka",
        "Sekwa-Kiloka"
    ],
    "wof:name":"Sekwa-Kiloka",
    "wof:placetype":"locality"
},
  "geometry": {"coordinates":[17.73803999999999,-5.6002],"type":"Point"}
}