{
  "type": "Feature",
  "properties": {
    "gn:admin1_code":"31.0",
    "gn:asciiname":"Wanga",
    "gn:country_code":"CD",
    "gn:dem":448,
    "gn:feature_class":"P",
    "gn:feature_code":"PPL",
    "gn:name":"Wanga",
    "gn:population":0,
    "gn:timezone":"Africa/Kinshasa",
    "iso:country":"CD",
    "wof:name":"Wanga",
    "wof:placetype":"locality"
},
  "geometry": {"coordinates":[22.09277,1.44972],"type":"Point"}
}