{
  "type": "Feature",
  "properties": {
    "gn:admin1_code":"23.0",
    "gn:asciiname":"Katombe-Muleba",
    "gn:country_code":"CD",
    "gn:dem":793,
    "gn:feature_class":"P",
    "gn:feature_code":"PPL",
    "gn:name":"Katombe-Muleba",
    "gn:population":0,
    "gn:timezone":"Africa/Lubumbashi",
    "iso:country":"CD",
    "wof:name":"Katombe-Muleba",
    "wof:placetype":"locality"
},
  "geometry": {"coordinates":[22.91013,-6.12027],"type":"Point"}
}