{
  "type": "Feature",
  "properties": {
    "gn:admin1_code":"29.0",
    "gn:asciiname":"Kinsukulu",
    "gn:country_code":"CD",
    "gn:dem":916,
    "gn:feature_class":"P",
    "gn:feature_code":"PPL",
    "gn:name":"Kinsukulu",
    "gn:population":0,
    "gn:timezone":"Africa/Lubumbashi",
    "iso:country":"CD",
    "wof:name":"Kinsukulu",
    "wof:placetype":"locality"
},
  "geometry": {"coordinates":[28.40797,-6.43224],"type":"Point"}
}