{
  "type": "Feature",
  "properties": {
    "gn:admin1_code":"17.0",
    "gn:asciiname":"Djida",
    "gn:country_code":"CD",
    "gn:dem":1736,
    "gn:feature_class":"P",
    "gn:feature_code":"PPL",
    "gn:name":"Djida",
    "gn:population":0,
    "gn:timezone":"Africa/Lubumbashi",
    "iso:country":"CD",
    "wof:name":"Djida",
    "wof:placetype":"locality"
},
  "geometry": {"coordinates":[30.597,1.93451],"type":"Point"}
}