{
  "type": "Feature",
  "properties": {
    "gn:admin1_code":"15.0",
    "gn:asciiname":"Tanganika",
    "gn:country_code":"CD",
    "gn:dem":581,
    "gn:feature_class":"P",
    "gn:feature_code":"PPL",
    "gn:name":"Tanganika",
    "gn:population":0,
    "gn:timezone":"Africa/Lubumbashi",
    "iso:country":"CD",
    "wof:name":"Tanganika",
    "wof:placetype":"locality"
},
  "geometry": {"coordinates":[25.8897,-9.18957],"type":"Point"}
}