{
  "type": "Feature",
  "properties": {
    "gn:admin1_code":"10.0",
    "gn:asciiname":"Unguo",
    "gn:country_code":"CD",
    "gn:dem":466,
    "gn:feature_class":"P",
    "gn:feature_code":"PPL",
    "gn:name":"Unguo",
    "gn:population":0,
    "gn:timezone":"Africa/Lubumbashi",
    "iso:country":"CD",
    "name:und_x_variant":[
        "Ungwo",
        "Unguo"
    ],
    "wof:name":"Unguo",
    "wof:placetype":"locality"
},
  "geometry": {"coordinates":[24.80408,-3.67209],"type":"Point"}
}