{
  "type": "Feature",
  "properties": {
    "gn:admin1_code":"8.0",
    "gn:asciiname":"Kinyembela",
    "gn:country_code":"CD",
    "gn:dem":626,
    "gn:feature_class":"P",
    "gn:feature_code":"PPL",
    "gn:name":"Kinyembela",
    "gn:population":0,
    "gn:timezone":"Africa/Kinshasa",
    "iso:country":"CD",
    "wof:name":"Kinyembela",
    "wof:placetype":"locality"
},
  "geometry": {"coordinates":[15.14725,-5.36181],"type":"Point"}
}