{
  "type": "Feature",
  "properties": {
    "gn:admin1_code":"10.0",
    "gn:asciiname":"Lubombola",
    "gn:country_code":"CD",
    "gn:dem":602,
    "gn:feature_class":"P",
    "gn:feature_code":"PPL",
    "gn:name":"Lubombola",
    "gn:population":0,
    "gn:timezone":"Africa/Lubumbashi",
    "iso:country":"CD",
    "name:und_x_variant":[
        "Lobombola",
        "Lubombola"
    ],
    "wof:name":"Lubombola",
    "wof:placetype":"locality"
},
  "geometry": {"coordinates":[27.12819,-4.45935],"type":"Point"}
}