{
  "type": "Feature",
  "properties": {
    "gn:admin1_code":"20.0",
    "gn:asciiname":"Gunga-Munene",
    "gn:country_code":"CD",
    "gn:dem":328,
    "gn:feature_class":"P",
    "gn:feature_code":"PPL",
    "gn:name":"Gunga-Munene",
    "gn:population":0,
    "gn:timezone":"Africa/Kinshasa",
    "iso:country":"CD",
    "wof:name":"Gunga-Munene",
    "wof:placetype":"locality"
},
  "geometry": {"coordinates":[17.41052,-3.73253],"type":"Point"}
}