{
  "type": "Feature",
  "properties": {
    "gn:admin1_code":"19.0",
    "gn:asciiname":"Muari",
    "gn:country_code":"CD",
    "gn:dem":657,
    "gn:feature_class":"P",
    "gn:feature_code":"PPL",
    "gn:name":"Muari",
    "gn:population":0,
    "gn:timezone":"Africa/Kinshasa",
    "iso:country":"CD",
    "name:und_x_variant":[
        "Nzashi-Muari",
        "Nzadi-Muari",
        "Muari"
    ],
    "wof:name":"Muari",
    "wof:placetype":"locality"
},
  "geometry": {"coordinates":[17.27079,-7.57812],"type":"Point"}
}