{
  "type": "Feature",
  "properties": {
    "gn:admin1_code":"20.0",
    "gn:asciiname":"Kilala",
    "gn:country_code":"CD",
    "gn:dem":695,
    "gn:feature_class":"P",
    "gn:feature_code":"PPL",
    "gn:name":"Kilala",
    "gn:population":0,
    "gn:timezone":"Africa/Kinshasa",
    "iso:country":"CD",
    "wof:name":"Kilala",
    "wof:placetype":"locality"
},
  "geometry": {"coordinates":[18.74302,-5.74545],"type":"Point"}
}