{
  "type": "Feature",
  "properties": {
    "gn:admin1_code":"8.0",
    "gn:asciiname":"Kisungani Premiere",
    "gn:country_code":"CD",
    "gn:dem":539,
    "gn:feature_class":"P",
    "gn:feature_code":"PPL",
    "gn:name":"Kisungani Premi\u00e8re",
    "gn:population":0,
    "gn:timezone":"Africa/Kinshasa",
    "iso:country":"CD",
    "wof:name":"Kisungani Premiere",
    "wof:placetype":"locality"
},
  "geometry": {"coordinates":[16.15047,-5.62941],"type":"Point"}
}