{
  "type": "Feature",
  "properties": {
    "gn:admin1_code":"20.0",
    "gn:asciiname":"Lungwama",
    "gn:country_code":"CD",
    "gn:dem":389,
    "gn:feature_class":"P",
    "gn:feature_code":"PPL",
    "gn:name":"Lungwama",
    "gn:population":0,
    "gn:timezone":"Africa/Kinshasa",
    "iso:country":"CD",
    "wof:name":"Lungwama",
    "wof:placetype":"locality"
},
  "geometry": {"coordinates":[18.84889,-3.88189],"type":"Point"}
}