{
  "type": "Feature",
  "properties": {
    "gn:admin1_code":"10.0",
    "gn:asciiname":"Kakunga",
    "gn:country_code":"CD",
    "gn:dem":501,
    "gn:feature_class":"P",
    "gn:feature_code":"PPL",
    "gn:name":"Kakunga",
    "gn:population":0,
    "gn:timezone":"Africa/Lubumbashi",
    "iso:country":"CD",
    "wof:name":"Kakunga",
    "wof:placetype":"locality"
},
  "geometry": {"coordinates":[25.55,-2.55],"type":"Point"}
}