{
  "type": "Feature",
  "properties": {
    "gn:admin1_code":"18.0",
    "gn:asciiname":"Shamasangu",
    "gn:country_code":"CD",
    "gn:dem":705,
    "gn:feature_class":"P",
    "gn:feature_code":"PPL",
    "gn:name":"Shamasangu",
    "gn:population":0,
    "gn:timezone":"Africa/Lubumbashi",
    "iso:country":"CD",
    "wof:name":"Shamasangu",
    "wof:placetype":"locality"
},
  "geometry": {"coordinates":[20.55836,-6.65953],"type":"Point"}
}