{
  "type": "Feature",
  "properties": {
    "gn:admin1_code":"10.0",
    "gn:asciiname":"Ulumba",
    "gn:country_code":"CD",
    "gn:dem":530,
    "gn:feature_class":"P",
    "gn:feature_code":"PPL",
    "gn:name":"Ulumba",
    "gn:population":0,
    "gn:timezone":"Africa/Lubumbashi",
    "iso:country":"CD",
    "wof:name":"Ulumba",
    "wof:placetype":"locality"
},
  "geometry": {"coordinates":[25.05793,-4.04344],"type":"Point"}
}