{
  "type": "Feature",
  "properties": {
    "gn:admin1_code":"8.0",
    "gn:asciiname":"Banza",
    "gn:country_code":"CD",
    "gn:dem":461,
    "gn:feature_class":"P",
    "gn:feature_code":"PPL",
    "gn:name":"Banza",
    "gn:population":0,
    "gn:timezone":"Africa/Kinshasa",
    "iso:country":"CD",
    "name:ceb_x_preferred":[
        "Banza"
    ],
    "name:swe_x_preferred":[
        "Banza"
    ],
    "wof:name":"Banza",
    "wof:placetype":"locality"
},
  "geometry": {"coordinates":[14.85203,-5.37883],"type":"Point"}
}