{
  "type": "Feature",
  "properties": {
    "gn:admin1_code":"20.0",
    "gn:asciiname":"Lusemfu",
    "gn:country_code":"CD",
    "gn:dem":801,
    "gn:feature_class":"P",
    "gn:feature_code":"PPL",
    "gn:name":"Lusemfu",
    "gn:population":0,
    "gn:timezone":"Africa/Kinshasa",
    "iso:country":"CD",
    "wof:name":"Lusemfu",
    "wof:placetype":"locality"
},
  "geometry": {"coordinates":[18.98512,-5.74692],"type":"Point"}
}