{
  "type": "Feature",
  "properties": {
    "gn:admin1_code":"17.0",
    "gn:asciiname":"Tshibi-Tshibi",
    "gn:country_code":"CD",
    "gn:dem":1318,
    "gn:feature_class":"P",
    "gn:feature_code":"PPL",
    "gn:name":"Tshibi-Tshibi",
    "gn:population":0,
    "gn:timezone":"Africa/Lubumbashi",
    "iso:country":"CD",
    "wof:name":"Tshibi-Tshibi",
    "wof:placetype":"locality"
},
  "geometry": {"coordinates":[30.06724,2.02893],"type":"Point"}
}