{
  "type": "Feature",
  "properties": {
    "gn:admin1_code":"19.0",
    "gn:asciiname":"Sha-Muhembo",
    "gn:country_code":"CD",
    "gn:dem":1014,
    "gn:feature_class":"P",
    "gn:feature_code":"PPL",
    "gn:name":"Sha-Muhembo",
    "gn:population":0,
    "gn:timezone":"Africa/Kinshasa",
    "iso:country":"CD",
    "wof:name":"Sha-Muhembo",
    "wof:placetype":"locality"
},
  "geometry": {"coordinates":[18.02851,-7.17834],"type":"Point"}
}