{
  "type": "Feature",
  "properties": {
    "gn:admin1_code":"14.0",
    "gn:asciiname":"Latente",
    "gn:country_code":"CD",
    "gn:dem":1353,
    "gn:feature_class":"P",
    "gn:feature_code":"PPL",
    "gn:name":"Latente",
    "gn:population":0,
    "gn:timezone":"Africa/Lubumbashi",
    "iso:country":"CD",
    "wof:name":"Latente",
    "wof:placetype":"locality"
},
  "geometry": {"coordinates":[27.00614,-11.5678],"type":"Point"}
}