{
  "type": "Feature",
  "properties": {
    "gn:admin1_code":"20.0",
    "gn:asciiname":"Dondo",
    "gn:country_code":"CD",
    "gn:dem":360,
    "gn:feature_class":"P",
    "gn:feature_code":"PPL",
    "gn:name":"Dondo",
    "gn:population":0,
    "gn:timezone":"Africa/Kinshasa",
    "iso:country":"CD",
    "name:ceb_x_preferred":[
        "Dondo"
    ],
    "name:deu_x_preferred":[
        "Dondo"
    ],
    "name:fra_x_preferred":[
        "Dondo"
    ],
    "name:ita_x_preferred":[
        "Dondo"
    ],
    "name:jpn_x_preferred":[
        "\u30c9\u30f3\u30c9"
    ],
    "name:pol_x_preferred":[
        "Dondo"
    ],
    "name:por_x_preferred":[
        "Dondo"
    ],
    "name:swe_x_preferred":[
        "Dondo"
    ],
    "name:und_x_variant":[
        "Kandondo",
        "Donda"
    ],
    "wof:name":"Dondo",
    "wof:placetype":"locality"
},
  "geometry": {"coordinates":[17.88266,-4.61058],"type":"Point"}
}