{
  "type": "Feature",
  "properties": {
    "gn:admin1_code":"19.0",
    "gn:asciiname":"Sefu",
    "gn:country_code":"CD",
    "gn:dem":474,
    "gn:feature_class":"P",
    "gn:feature_code":"PPL",
    "gn:name":"Sefu",
    "gn:population":0,
    "gn:timezone":"Africa/Kinshasa",
    "iso:country":"CD",
    "wof:name":"Sefu",
    "wof:placetype":"locality"
},
  "geometry": {"coordinates":[17.17065,-7.30175],"type":"Point"}
}