{
  "type": "Feature",
  "properties": {
    "gn:admin1_code":"2.0",
    "gn:asciiname":"Bombembo",
    "gn:country_code":"CD",
    "gn:dem":334,
    "gn:feature_class":"P",
    "gn:feature_code":"PPL",
    "gn:name":"Bombembo",
    "gn:population":0,
    "gn:timezone":"Africa/Kinshasa",
    "iso:country":"CD",
    "name:fra_x_preferred":[
        "Bombembo"
    ],
    "wof:name":"Bombembo",
    "wof:placetype":"locality"
},
  "geometry": {"coordinates":[19.13016,2.04205],"type":"Point"}
}