{
  "type": "Feature",
  "properties": {
    "gn:admin1_code":"8.0",
    "gn:asciiname":"Kimbungu",
    "gn:country_code":"CD",
    "gn:dem":555,
    "gn:feature_class":"P",
    "gn:feature_code":"PPL",
    "gn:name":"Kimbungu",
    "gn:population":0,
    "gn:timezone":"Africa/Kinshasa",
    "iso:country":"CD",
    "wof:name":"Kimbungu",
    "wof:placetype":"locality"
},
  "geometry": {"coordinates":[15.18604,-4.92359],"type":"Point"}
}