{
  "type": "Feature",
  "properties": {
    "gn:admin1_code":"16.0",
    "gn:asciiname":"Laso",
    "gn:country_code":"CD",
    "gn:dem":910,
    "gn:feature_class":"P",
    "gn:feature_code":"PPL",
    "gn:name":"Laso",
    "gn:population":0,
    "gn:timezone":"Africa/Lubumbashi",
    "iso:country":"CD",
    "name:ceb_x_preferred":[
        "Laso"
    ],
    "name:deu_x_preferred":[
        "Laso"
    ],
    "name:rus_x_preferred":[
        "\u041b\u0430\u0441\u043e"
    ],
    "name:swe_x_preferred":[
        "Laso"
    ],
    "name:und_x_variant":[
        "Lasso",
        "Laso"
    ],
    "wof:name":"Laso",
    "wof:placetype":"locality"
},
  "geometry": {"coordinates":[30.26667,3.91667],"type":"Point"}
}