{
  "type": "Feature",
  "properties": {
    "gn:admin1_code":"15.0",
    "gn:asciiname":"Kalondwa",
    "gn:country_code":"CD",
    "gn:dem":975,
    "gn:feature_class":"P",
    "gn:feature_code":"PPL",
    "gn:name":"Kalondwa",
    "gn:population":0,
    "gn:timezone":"Africa/Lubumbashi",
    "iso:country":"CD",
    "wof:name":"Kalondwa",
    "wof:placetype":"locality"
},
  "geometry": {"coordinates":[25.89306,-8.58599],"type":"Point"}
}