{
  "type": "Feature",
  "properties": {
    "gn:admin1_code":"15.0",
    "gn:asciiname":"Songe",
    "gn:country_code":"CD",
    "gn:dem":734,
    "gn:feature_class":"P",
    "gn:feature_code":"PPL",
    "gn:name":"Songe",
    "gn:population":0,
    "gn:timezone":"Africa/Lubumbashi",
    "iso:country":"CD",
    "name:ceb_x_preferred":[
        "Songe"
    ],
    "name:jav_x_preferred":[
        "Songe"
    ],
    "name:msa_x_preferred":[
        "Songe"
    ],
    "name:nno_x_preferred":[
        "Songe"
    ],
    "name:nor_x_preferred":[
        "Songe"
    ],
    "wof:name":"Songe",
    "wof:placetype":"locality"
},
  "geometry": {"coordinates":[26.24235,-7.29181],"type":"Point"}
}