{
  "type": "Feature",
  "properties": {
    "gn:admin1_code":"25.0",
    "gn:asciiname":"Yakaisa",
    "gn:country_code":"CD",
    "gn:dem":438,
    "gn:feature_class":"P",
    "gn:feature_code":"PPL",
    "gn:name":"Yakaisa",
    "gn:population":0,
    "gn:timezone":"Africa/Kinshasa",
    "iso:country":"CD",
    "wof:name":"Yakaisa",
    "wof:placetype":"locality"
},
  "geometry": {"coordinates":[22.51337,2.52153],"type":"Point"}
}