{
  "type": "Feature",
  "properties": {
    "gn:admin1_code":"19.0",
    "gn:asciiname":"Tsako",
    "gn:country_code":"CD",
    "gn:dem":854,
    "gn:feature_class":"P",
    "gn:feature_code":"PPL",
    "gn:name":"Tsako",
    "gn:population":0,
    "gn:timezone":"Africa/Kinshasa",
    "iso:country":"CD",
    "wof:name":"Tsako",
    "wof:placetype":"locality"
},
  "geometry": {"coordinates":[17.7128,-6.34117],"type":"Point"}
}