{
  "type": "Feature",
  "properties": {
    "gn:admin1_code":"18.0",
    "gn:asciiname":"Mokonienge",
    "gn:country_code":"CD",
    "gn:dem":552,
    "gn:feature_class":"P",
    "gn:feature_code":"PPL",
    "gn:name":"Mokonienge",
    "gn:population":0,
    "gn:timezone":"Africa/Lubumbashi",
    "iso:country":"CD",
    "name:und_x_variant":[
        "Mokomiymba",
        "Mokomyimba",
        "Mokonienge"
    ],
    "wof:name":"Mokonienge",
    "wof:placetype":"locality"
},
  "geometry": {"coordinates":[22.03366,-5.00584],"type":"Point"}
}