{
  "type": "Feature",
  "properties": {
    "gn:admin1_code":"18.0",
    "gn:asciiname":"Shatanda",
    "gn:country_code":"CD",
    "gn:dem":748,
    "gn:feature_class":"P",
    "gn:feature_code":"PPL",
    "gn:name":"Shatanda",
    "gn:population":0,
    "gn:timezone":"Africa/Lubumbashi",
    "iso:country":"CD",
    "wof:name":"Shatanda",
    "wof:placetype":"locality"
},
  "geometry": {"coordinates":[20.01324,-6.59013],"type":"Point"}
}