{
  "type": "Feature",
  "properties": {
    "gn:admin1_code":"18.0",
    "gn:asciiname":"Mombo",
    "gn:country_code":"CD",
    "gn:dem":485,
    "gn:feature_class":"P",
    "gn:feature_code":"PPL",
    "gn:name":"Mombo",
    "gn:population":0,
    "gn:timezone":"Africa/Lubumbashi",
    "iso:country":"CD",
    "name:und_x_variant":[
        "Mombo-Munene"
    ],
    "wof:name":"Mombo",
    "wof:placetype":"locality"
},
  "geometry": {"coordinates":[21.35683,-5.16877],"type":"Point"}
}