{
  "type": "Feature",
  "properties": {
    "gn:admin1_code":"13.0",
    "gn:asciiname":"Palapa",
    "gn:country_code":"CD",
    "gn:dem":697,
    "gn:feature_class":"P",
    "gn:feature_code":"PPL",
    "gn:name":"Palapa",
    "gn:population":0,
    "gn:timezone":"Africa/Lubumbashi",
    "iso:country":"CD",
    "name:und_x_variant":[
        "Balapa",
        "Palapa"
    ],
    "wof:name":"Palapa",
    "wof:placetype":"locality"
},
  "geometry": {"coordinates":[27.21009,3.00713],"type":"Point"}
}