{
  "type": "Feature",
  "properties": {
    "gn:admin1_code":"13.0",
    "gn:asciiname":"Palapa",
    "gn:country_code":"CD",
    "gn:dem":697,
    "gn:feature_class":"P",
    "gn:feature_code":"PPL",
    "gn:name":"Palapa",
    "gn:population":0,
    "gn:timezone":"Africa/Lubumbashi",
    "iso:country":"CD",
    "name:ara_x_preferred":[
        "\u0628\u0644\u0628\u0627"
    ],
    "name:deu_x_preferred":[
        "Palapa"
    ],
    "name:fin_x_preferred":[
        "Palapa"
    ],
    "name:fra_x_preferred":[
        "Palapa"
    ],
    "name:ind_x_preferred":[
        "Satelit Palapa"
    ],
    "name:jpn_x_preferred":[
        "\u30d1\u30e9\u30d1"
    ],
    "name:por_x_preferred":[
        "Palapa"
    ],
    "name:slk_x_preferred":[
        "Palapa"
    ],
    "name:tam_x_preferred":[
        "\u0baa\u0bb2\u0baa\u0bbe \u0b9a\u0bc6\u0baf\u0bb1\u0bcd\u0b95\u0bc8\u0b95\u0bcd\u0b95\u0bcb\u0bb3\u0bcd"
    ],
    "name:und_x_variant":[
        "Balapa"
    ],
    "wof:name":"Palapa",
    "wof:placetype":"locality"
},
  "geometry": {"coordinates":[27.21009,3.00713],"type":"Point"}
}