{
  "type": "Feature",
  "properties": {
    "gn:admin1_code":"13.0",
    "gn:asciiname":"Lemengu",
    "gn:country_code":"CD",
    "gn:dem":676,
    "gn:feature_class":"P",
    "gn:feature_code":"PPL",
    "gn:name":"Lemengu",
    "gn:population":0,
    "gn:timezone":"Africa/Lubumbashi",
    "iso:country":"CD",
    "wof:name":"Lemengu",
    "wof:placetype":"locality"
},
  "geometry": {"coordinates":[26.21783,3.20973],"type":"Point"}
}