{
  "type": "Feature",
  "properties": {
    "gn:admin1_code":"11.0",
    "gn:asciiname":"Kirima",
    "gn:country_code":"CD",
    "gn:dem":1683,
    "gn:feature_class":"P",
    "gn:feature_code":"PPL",
    "gn:name":"Kirima",
    "gn:population":0,
    "gn:timezone":"Africa/Lubumbashi",
    "iso:country":"CD",
    "wof:name":"Kirima",
    "wof:placetype":"locality"
},
  "geometry": {"coordinates":[29.11667000000001,0.18333],"type":"Point"}
}