{
  "type": "Feature",
  "properties": {
    "gn:admin1_code":"27.0",
    "gn:asciiname":"Samangwa",
    "gn:country_code":"CD",
    "gn:dem":584,
    "gn:feature_class":"P",
    "gn:feature_code":"PPL",
    "gn:name":"Samangwa",
    "gn:population":0,
    "gn:timezone":"Africa/Lubumbashi",
    "iso:country":"CD",
    "name:und_x_variant":[
        "Esamangwa",
        "Samangua",
        "Somangwa",
        "Samangwa",
        "Samangwe"
    ],
    "wof:name":"Samangwa",
    "wof:placetype":"locality"
},
  "geometry": {"coordinates":[24.1501,-4.32818],"type":"Point"}
}