{
  "type": "Feature",
  "properties": {
    "gn:admin1_code":"25.0",
    "gn:asciiname":"Gwemba",
    "gn:country_code":"CD",
    "gn:dem":333,
    "gn:feature_class":"P",
    "gn:feature_code":"PPL",
    "gn:name":"Gwemba",
    "gn:population":0,
    "gn:timezone":"Africa/Kinshasa",
    "iso:country":"CD",
    "wof:name":"Gwemba",
    "wof:placetype":"locality"
},
  "geometry": {"coordinates":[20.14924,2.02214],"type":"Point"}
}