{
  "type": "Feature",
  "properties": {
    "gn:admin1_code":"19.0",
    "gn:asciiname":"Sha-Tshiemfu",
    "gn:country_code":"CD",
    "gn:dem":1057,
    "gn:feature_class":"P",
    "gn:feature_code":"PPL",
    "gn:name":"Sha-Tshiemfu",
    "gn:population":0,
    "gn:timezone":"Africa/Kinshasa",
    "iso:country":"CD",
    "wof:name":"Sha-Tshiemfu",
    "wof:placetype":"locality"
},
  "geometry": {"coordinates":[18.17804,-7.38397],"type":"Point"}
}