{
  "type": "Feature",
  "properties": {
    "gn:admin1_code":"28.0",
    "gn:asciiname":"Mokanza",
    "gn:country_code":"CD",
    "gn:dem":334,
    "gn:feature_class":"P",
    "gn:feature_code":"PPL",
    "gn:name":"Mokanza",
    "gn:population":0,
    "gn:timezone":"Africa/Kinshasa",
    "iso:country":"CD",
    "wof:name":"Mokanza",
    "wof:placetype":"locality"
},
  "geometry": {"coordinates":[18.68809,2.14526],"type":"Point"}
}