{
  "type": "Feature",
  "properties": {
    "gn:admin1_code":"25.0",
    "gn:asciiname":"Ndeke-Ndombe",
    "gn:country_code":"CD",
    "gn:dem":385,
    "gn:feature_class":"P",
    "gn:feature_code":"PPL",
    "gn:name":"Ndeke-Ndombe",
    "gn:population":0,
    "gn:timezone":"Africa/Kinshasa",
    "iso:country":"CD",
    "wof:name":"Ndeke-Ndombe",
    "wof:placetype":"locality"
},
  "geometry": {"coordinates":[21.14504,2.21636],"type":"Point"}
}