{
  "type": "Feature",
  "properties": {
    "gn:admin1_code":"14.0",
    "gn:asciiname":"Kayumine",
    "gn:country_code":"CD",
    "gn:dem":1161,
    "gn:feature_class":"P",
    "gn:feature_code":"PPL",
    "gn:name":"Kayumine",
    "gn:population":0,
    "gn:timezone":"Africa/Lubumbashi",
    "iso:country":"CD",
    "wof:name":"Kayumine",
    "wof:placetype":"locality"
},
  "geometry": {"coordinates":[26.82947,-11.12793],"type":"Point"}
}