{
  "type": "Feature",
  "properties": {
    "gn:admin1_code":"15.0",
    "gn:asciiname":"Lusola",
    "gn:country_code":"CD",
    "gn:dem":1041,
    "gn:feature_class":"P",
    "gn:feature_code":"PPL",
    "gn:name":"Lusola",
    "gn:population":0,
    "gn:timezone":"Africa/Lubumbashi",
    "iso:country":"CD",
    "wof:name":"Lusola",
    "wof:placetype":"locality"
},
  "geometry": {"coordinates":[24.95,-9.18333],"type":"Point"}
}