{
  "type": "Feature",
  "properties": {
    "gn:admin1_code":"15.0",
    "gn:asciiname":"Koi",
    "gn:country_code":"CD",
    "gn:dem":1033,
    "gn:feature_class":"P",
    "gn:feature_code":"PPL",
    "gn:name":"Koi",
    "gn:population":0,
    "gn:timezone":"Africa/Lubumbashi",
    "iso:country":"CD",
    "name:afr_x_preferred":[
        "Koi"
    ],
    "name:ara_x_preferred":[
        "\u0643\u0648\u064a"
    ],
    "name:aze_x_preferred":[
        "Koi"
    ],
    "name:bel_x_preferred":[
        "\u041a\u0430\u0440\u043f"
    ],
    "name:bul_x_preferred":[
        "\u041a\u043e\u0438"
    ],
    "name:ceb_x_preferred":[
        "Koi"
    ],
    "name:ces_x_preferred":[
        "Kapr koi"
    ],
    "name:deu_x_preferred":[
        "Koi"
    ],
    "name:epo_x_preferred":[
        "Koi"
    ],
    "name:fas_x_preferred":[
        "\u06a9\u067e\u0648\u0631 \u06af\u0644\u06af\u0648\u0646"
    ],
    "name:fin_x_preferred":[
        "Koikarppi"
    ],
    "name:fra_x_preferred":[
        "Ko\u00ef"
    ],
    "name:heb_x_preferred":[
        "\u05e7\u05d5\u05d9"
    ],
    "name:hin_x_preferred":[
        "\u0915\u0935\u0908"
    ],
    "name:hun_x_preferred":[
        "Koi ponty"
    ],
    "name:ind_x_preferred":[
        "Koi"
    ],
    "name:isl_x_preferred":[
        "Koi"
    ],
    "name:ita_x_preferred":[
        "Carpa koi"
    ],
    "name:jav_x_preferred":[
        "Iwak koi"
    ],
    "name:jpn_x_preferred":[
        "\u30cb\u30b7\u30ad\u30b4\u30a4"
    ],
    "name:kor_x_preferred":[
        "\ube44\ub2e8\uc789\uc5b4"
    ],
    "name:lit_x_preferred":[
        "Koi"
    ],
    "name:mkd_x_preferred":[
        "\u0408\u0430\u043f\u043e\u043d\u0441\u043a\u0438 \u043a\u0440\u0430\u043f"
    ],
    "name:msa_x_preferred":[
        "Ikan Koi"
    ],
    "name:nld_x_preferred":[
        "Koi"
    ],
    "name:nor_x_preferred":[
        "Koi"
    ],
    "name:pol_x_preferred":[
        "Karp koi"
    ],
    "name:por_x_preferred":[
        "Nishikigoi"
    ],
    "name:rus_x_preferred":[
        "\u041a\u0430\u0440\u043f\u044b \u043a\u043e\u0438"
    ],
    "name:sco_x_preferred":[
        "Koi"
    ],
    "name:srp_x_preferred":[
        "Japanski \u0161aran"
    ],
    "name:sun_x_preferred":[
        "Koi"
    ],
    "name:tam_x_preferred":[
        "\u0b95\u0bca\u0baf\u0bcd"
    ],
    "name:tha_x_preferred":[
        "\u0e1b\u0e25\u0e32\u0e41\u0e1f\u0e19\u0e0b\u0e35\u0e04\u0e32\u0e23\u0e4c\u0e1b"
    ],
    "name:tur_x_preferred":[
        "Koi"
    ],
    "name:ukr_x_preferred":[
        "\u041f\u0430\u0440\u0447\u0435\u0432\u0438\u0439 \u043a\u043e\u0440\u043e\u043f"
    ],
    "name:und_x_variant":[
        "Koye"
    ],
    "name:vie_x_preferred":[
        "Koi"
    ],
    "wof:name":"Koi",
    "wof:placetype":"locality"
},
  "geometry": {"coordinates":[25.09503,-9.04211],"type":"Point"}
}