{
  "type": "Feature",
  "properties": {
    "gn:admin1_code":"15.0",
    "gn:asciiname":"Koi",
    "gn:country_code":"CD",
    "gn:dem":1033,
    "gn:feature_class":"P",
    "gn:feature_code":"PPL",
    "gn:name":"Koi",
    "gn:population":0,
    "gn:timezone":"Africa/Lubumbashi",
    "iso:country":"CD",
    "name:und_x_variant":[
        "Koye"
    ],
    "wof:name":"Koi",
    "wof:placetype":"locality"
},
  "geometry": {"coordinates":[25.09503,-9.04211],"type":"Point"}
}