{
  "type": "Feature",
  "properties": {
    "gn:admin1_code":"23.0",
    "gn:asciiname":"Mbote",
    "gn:country_code":"CD",
    "gn:dem":862,
    "gn:feature_class":"P",
    "gn:feature_code":"PPL",
    "gn:name":"Mbote",
    "gn:population":0,
    "gn:timezone":"Africa/Lubumbashi",
    "iso:country":"CD",
    "wof:name":"Mbote",
    "wof:placetype":"locality"
},
  "geometry": {"coordinates":[22.3898,-7.15829],"type":"Point"}
}