{
  "type": "Feature",
  "properties": {
    "gn:admin1_code":"27.0",
    "gn:asciiname":"Pungu-Djuki",
    "gn:country_code":"CD",
    "gn:dem":504,
    "gn:feature_class":"P",
    "gn:feature_code":"PPL",
    "gn:name":"Pungu-Djuki",
    "gn:population":0,
    "gn:timezone":"Africa/Lubumbashi",
    "iso:country":"CD",
    "name:und_x_variant":[
        "Pungu",
        "Pungu-Djuki"
    ],
    "wof:name":"Pungu-Djuki",
    "wof:placetype":"locality"
},
  "geometry": {"coordinates":[23.74371,-2.77255],"type":"Point"}
}