{
  "type": "Feature",
  "properties": {
    "gn:admin1_code":"30.0",
    "gn:asciiname":"Bapele Deuxieme",
    "gn:country_code":"CD",
    "gn:dem":468,
    "gn:feature_class":"P",
    "gn:feature_code":"PPL",
    "gn:name":"Bapele Deuxi\u00e8me",
    "gn:population":0,
    "gn:timezone":"Africa/Lubumbashi",
    "iso:country":"CD",
    "name:und_x_variant":[
        "Bapele Deuxi\u00e8me",
        "Bapele II"
    ],
    "wof:name":"Bapele Deuxieme",
    "wof:placetype":"locality"
},
  "geometry": {"coordinates":[25.95024,2.01287],"type":"Point"}
}