{
  "type": "Feature",
  "properties": {
    "gn:admin1_code":"13.0",
    "gn:asciiname":"Soa",
    "gn:country_code":"CD",
    "gn:dem":526,
    "gn:feature_class":"P",
    "gn:feature_code":"PPL",
    "gn:name":"Soa",
    "gn:population":0,
    "gn:timezone":"Africa/Lubumbashi",
    "iso:country":"CD",
    "name:swe_x_preferred":[
        "Soa"
    ],
    "wof:name":"Soa",
    "wof:placetype":"locality"
},
  "geometry": {"coordinates":[22.81974,4.66094],"type":"Point"}
}