{
  "type": "Feature",
  "properties": {
    "gn:admin1_code":"26.0",
    "gn:asciiname":"Bodorofio",
    "gn:country_code":"CD",
    "gn:dem":402,
    "gn:feature_class":"P",
    "gn:feature_code":"PPL",
    "gn:name":"Bodorofio",
    "gn:population":0,
    "gn:timezone":"Africa/Kinshasa",
    "iso:country":"CD",
    "name:und_x_variant":[
        "Botorofio"
    ],
    "wof:name":"Bodorofio",
    "wof:placetype":"locality"
},
  "geometry": {"coordinates":[20.44984,3.52305],"type":"Point"}
}