{
  "type": "Feature",
  "properties": {
    "gn:admin1_code":"17.0",
    "gn:asciiname":"Langbe",
    "gn:country_code":"CD",
    "gn:dem":1874,
    "gn:feature_class":"P",
    "gn:feature_code":"PPL",
    "gn:name":"Langbe",
    "gn:population":0,
    "gn:timezone":"Africa/Lubumbashi",
    "iso:country":"CD",
    "wof:name":"Langbe",
    "wof:placetype":"locality"
},
  "geometry": {"coordinates":[30.64958,1.79279],"type":"Point"}
}