{
  "type": "Feature",
  "properties": {
    "gn:admin1_code":"15.0",
    "gn:asciiname":"Gombe",
    "gn:country_code":"CD",
    "gn:dem":767,
    "gn:feature_class":"P",
    "gn:feature_code":"PPL",
    "gn:name":"Gombe",
    "gn:population":0,
    "gn:timezone":"Africa/Lubumbashi",
    "iso:country":"CD",
    "name:ara_x_preferred":[
        "\u063a\u0648\u0645\u0628\u064a"
    ],
    "name:ben_x_preferred":[
        "\u0997\u09cb\u09ae\u09cd\u09ac\u09c7"
    ],
    "name:cat_x_preferred":[
        "Gombe"
    ],
    "name:ceb_x_preferred":[
        "Gombe"
    ],
    "name:dan_x_preferred":[
        "Gombe"
    ],
    "name:deu_x_preferred":[
        "Gombe"
    ],
    "name:ell_x_preferred":[
        "\u0393\u03ba\u03cc\u03bc\u03c0\u03b5"
    ],
    "name:fas_x_preferred":[
        "\u06af\u0627\u0645\u0628"
    ],
    "name:fra_x_preferred":[
        "Gombe"
    ],
    "name:glg_x_preferred":[
        "Gombe"
    ],
    "name:hau_x_preferred":[
        "Gombe"
    ],
    "name:heb_x_preferred":[
        "\u05d2\u05d5\u05de\u05d1\u05bc\u05d4"
    ],
    "name:hin_x_preferred":[
        "\u0917\u094b\u092e\u094d\u092c\u0947"
    ],
    "name:hun_x_preferred":[
        "Gombe"
    ],
    "name:ind_x_preferred":[
        "Gombe"
    ],
    "name:ita_x_preferred":[
        "Gombe"
    ],
    "name:jpn_x_preferred":[
        "\u30b4\u30f3\u30d6\u5ddd"
    ],
    "name:kor_x_preferred":[
        "\uacf0\ubca0"
    ],
    "name:lug_x_preferred":[
        "Gombe"
    ],
    "name:mlg_x_preferred":[
        "Gombe"
    ],
    "name:nld_x_preferred":[
        "Gombe"
    ],
    "name:pol_x_preferred":[
        "Gombe"
    ],
    "name:por_x_preferred":[
        "Gombe"
    ],
    "name:rus_x_preferred":[
        "\u0440\u0435\u043a\u0430 \u0413\u043e\u043c\u0431"
    ],
    "name:spa_x_preferred":[
        "Gombe"
    ],
    "name:swe_x_preferred":[
        "Gombe"
    ],
    "name:tur_x_preferred":[
        "Gombe"
    ],
    "name:ukr_x_preferred":[
        "\u0413\u043e\u043c\u0431\u0435"
    ],
    "name:urd_x_preferred":[
        "\u06af\u0648\u0645\u0628\u06d2"
    ],
    "name:vie_x_preferred":[
        "S\u00f4ng Gombe"
    ],
    "name:zho_cn_x_preferred":[
        "\u8d21\u8d1d\u6cb3"
    ],
    "name:zho_tw_x_preferred":[
        "\u8ca2\u8c9d\u6cb3"
    ],
    "wof:name":"Gombe",
    "wof:placetype":"locality"
},
  "geometry": {"coordinates":[26.12329,-7.29028],"type":"Point"}
}