{
  "type": "Feature",
  "properties": {
    "gn:admin1_code":"19.0",
    "gn:asciiname":"Munzinga-Mfumu",
    "gn:country_code":"CD",
    "gn:dem":712,
    "gn:feature_class":"P",
    "gn:feature_code":"PPL",
    "gn:name":"Munzinga-Mfumu",
    "gn:population":0,
    "gn:timezone":"Africa/Kinshasa",
    "iso:country":"CD",
    "name:und_x_variant":[
        "Muzinga-Mfumu",
        "Munzinga-Mfumu"
    ],
    "wof:name":"Munzinga-Mfumu",
    "wof:placetype":"locality"
},
  "geometry": {"coordinates":[16.31667,-5.48333],"type":"Point"}
}