{
  "type": "Feature",
  "properties": {
    "gn:admin1_code":"21.0",
    "gn:asciiname":"Eshimba",
    "gn:country_code":"CD",
    "gn:dem":787,
    "gn:feature_class":"P",
    "gn:feature_code":"PPL",
    "gn:name":"Eshimba",
    "gn:population":0,
    "gn:timezone":"Africa/Lubumbashi",
    "iso:country":"CD",
    "wof:name":"Eshimba",
    "wof:placetype":"locality"
},
  "geometry": {"coordinates":[24.80295,-5.95573],"type":"Point"}
}