{
  "type": "Feature",
  "properties": {
    "gn:admin1_code":"17.0",
    "gn:asciiname":"Nderi",
    "gn:country_code":"CD",
    "gn:dem":1273,
    "gn:feature_class":"P",
    "gn:feature_code":"PPL",
    "gn:name":"Nderi",
    "gn:population":0,
    "gn:timezone":"Africa/Lubumbashi",
    "iso:country":"CD",
    "wof:name":"Nderi",
    "wof:placetype":"locality"
},
  "geometry": {"coordinates":[30.77084,3.12012],"type":"Point"}
}