{
  "type": "Feature",
  "properties": {
    "gn:admin1_code":"25.0",
    "gn:asciiname":"Yangonzi",
    "gn:country_code":"CD",
    "gn:dem":406,
    "gn:feature_class":"P",
    "gn:feature_code":"PPL",
    "gn:name":"Yangonzi",
    "gn:population":0,
    "gn:timezone":"Africa/Kinshasa",
    "iso:country":"CD",
    "wof:name":"Yangonzi",
    "wof:placetype":"locality"
},
  "geometry": {"coordinates":[21.7904,2.77751],"type":"Point"}
}