{
  "type": "Feature",
  "properties": {
    "gn:admin1_code":"25.0",
    "gn:asciiname":"Gwanga",
    "gn:country_code":"CD",
    "gn:dem":376,
    "gn:feature_class":"P",
    "gn:feature_code":"PPL",
    "gn:name":"Gwanga",
    "gn:population":0,
    "gn:timezone":"Africa/Kinshasa",
    "iso:country":"CD",
    "wof:name":"Gwanga",
    "wof:placetype":"locality"
},
  "geometry": {"coordinates":[20.91597,2.9125],"type":"Point"}
}