{
  "type": "Feature",
  "properties": {
    "gn:admin1_code":"11.0",
    "gn:asciiname":"Bilundule",
    "gn:country_code":"CD",
    "gn:dem":2219,
    "gn:feature_class":"P",
    "gn:feature_code":"PPL",
    "gn:name":"Bilundule",
    "gn:population":0,
    "gn:timezone":"Africa/Lubumbashi",
    "iso:country":"CD",
    "wof:name":"Bilundule",
    "wof:placetype":"locality"
},
  "geometry": {"coordinates":[29.13333,-0.35],"type":"Point"}
}