{
  "type": "Feature",
  "properties": {
    "gn:admin1_code":"22.0",
    "gn:asciiname":"Musepe",
    "gn:country_code":"CD",
    "gn:dem":1100,
    "gn:feature_class":"P",
    "gn:feature_code":"PPL",
    "gn:name":"Musepe",
    "gn:population":0,
    "gn:timezone":"Africa/Lubumbashi",
    "iso:country":"CD",
    "name:und_x_variant":[
        "Musepa",
        "Musepe"
    ],
    "wof:name":"Musepe",
    "wof:placetype":"locality"
},
  "geometry": {"coordinates":[22.7217,-10.7496],"type":"Point"}
}