{
  "type": "Feature",
  "properties": {
    "gn:admin1_code":"14.0",
    "gn:asciiname":"Kisabi",
    "gn:country_code":"CD",
    "gn:dem":966,
    "gn:feature_class":"P",
    "gn:feature_code":"PPL",
    "gn:name":"Kisabi",
    "gn:population":0,
    "gn:timezone":"Africa/Lubumbashi",
    "iso:country":"CD",
    "name:und_x_variant":[
        "Kizabi",
        "Kazabi-Kasabi"
    ],
    "wof:name":"Kisabi",
    "wof:placetype":"locality"
},
  "geometry": {"coordinates":[29.18746,-8.03372],"type":"Point"}
}