{
  "type": "Feature",
  "properties": {
    "gn:admin1_code":"16.0",
    "gn:asciiname":"Alulembane",
    "gn:country_code":"CD",
    "gn:dem":1215,
    "gn:feature_class":"P",
    "gn:feature_code":"PPL",
    "gn:name":"Alulembane",
    "gn:population":0,
    "gn:timezone":"Africa/Lubumbashi",
    "iso:country":"CD",
    "wof:name":"Alulembane",
    "wof:placetype":"locality"
},
  "geometry": {"coordinates":[29.95127,2.61709],"type":"Point"}
}