{
  "type": "Feature",
  "properties": {
    "gn:admin1_code":"13.0",
    "gn:asciiname":"Dianingala",
    "gn:country_code":"CD",
    "gn:dem":679,
    "gn:feature_class":"P",
    "gn:feature_code":"PPL",
    "gn:name":"Dianingala",
    "gn:population":0,
    "gn:timezone":"Africa/Lubumbashi",
    "iso:country":"CD",
    "wof:name":"Dianingala",
    "wof:placetype":"locality"
},
  "geometry": {"coordinates":[27.25809000000001,3.15587],"type":"Point"}
}