{
  "type": "Feature",
  "properties": {
    "gn:admin1_code":"28.0",
    "gn:asciiname":"Lilemba",
    "gn:country_code":"CD",
    "gn:dem":341,
    "gn:feature_class":"P",
    "gn:feature_code":"PPL",
    "gn:name":"Lilemba",
    "gn:population":0,
    "gn:timezone":"Africa/Kinshasa",
    "iso:country":"CD",
    "name:fra_x_preferred":[
        "Lilemba"
    ],
    "wof:name":"Lilemba",
    "wof:placetype":"locality"
},
  "geometry": {"coordinates":[19.19044,2.30056],"type":"Point"}
}