{
  "type": "Feature",
  "properties": {
    "gn:admin1_code":"8.0",
    "gn:asciiname":"Nganda-Tsundi",
    "gn:country_code":"CD",
    "gn:dem":224,
    "gn:feature_class":"P",
    "gn:feature_code":"PPL",
    "gn:name":"Nganda-Tsundi",
    "gn:population":0,
    "gn:timezone":"Africa/Kinshasa",
    "iso:country":"CD",
    "name:und_x_variant":[
        "Ganda",
        "Ganda-Sundi",
        "Nganda-Tsundi"
    ],
    "wof:name":"Nganda-Tsundi",
    "wof:placetype":"locality"
},
  "geometry": {"coordinates":[12.88837,-4.78288],"type":"Point"}
}