{
  "type": "Feature",
  "properties": {
    "gn:admin1_code":"14.0",
    "gn:asciiname":"Mwepo",
    "gn:country_code":"CD",
    "gn:dem":1490,
    "gn:feature_class":"P",
    "gn:feature_code":"PPL",
    "gn:name":"Mwepo",
    "gn:population":0,
    "gn:timezone":"Africa/Lubumbashi",
    "iso:country":"CD",
    "wof:name":"Mwepo",
    "wof:placetype":"locality"
},
  "geometry": {"coordinates":[26.18779,-11.92695],"type":"Point"}
}