{
  "type": "Feature",
  "properties": {
    "gn:admin1_code":"24.0",
    "gn:asciiname":"Ibalingongo",
    "gn:country_code":"CD",
    "gn:dem":301,
    "gn:feature_class":"P",
    "gn:feature_code":"PPL",
    "gn:name":"Ibalingongo",
    "gn:population":0,
    "gn:timezone":"Africa/Kinshasa",
    "iso:country":"CD",
    "wof:name":"Ibalingongo",
    "wof:placetype":"locality"
},
  "geometry": {"coordinates":[18.65476,-1.88989],"type":"Point"}
}