{
  "type": "Feature",
  "properties": {
    "gn:admin1_code":"4.0",
    "gn:asciiname":"Luese-Maboie",
    "gn:country_code":"CD",
    "gn:dem":632,
    "gn:feature_class":"P",
    "gn:feature_code":"PPL",
    "gn:name":"Luese-Maboie",
    "gn:population":0,
    "gn:timezone":"Africa/Lubumbashi",
    "iso:country":"CD",
    "wof:name":"Luese-Maboie",
    "wof:placetype":"locality"
},
  "geometry": {"coordinates":[23.23224,-6.12016],"type":"Point"}
}