{
  "type": "Feature",
  "properties": {
    "gn:admin1_code":"21.0",
    "gn:asciiname":"Tshinene",
    "gn:country_code":"CD",
    "gn:dem":818,
    "gn:feature_class":"P",
    "gn:feature_code":"PPL",
    "gn:name":"Tshinene",
    "gn:population":0,
    "gn:timezone":"Africa/Lubumbashi",
    "iso:country":"CD",
    "wof:name":"Tshinene",
    "wof:placetype":"locality"
},
  "geometry": {"coordinates":[23.745,-6.94204],"type":"Point"}
}