{
  "type": "Feature",
  "properties": {
    "gn:admin1_code":"13.0",
    "gn:asciiname":"Ngulo",
    "gn:country_code":"CD",
    "gn:dem":602,
    "gn:feature_class":"P",
    "gn:feature_code":"PPL",
    "gn:name":"Ngulo",
    "gn:population":0,
    "gn:timezone":"Africa/Lubumbashi",
    "iso:country":"CD",
    "wof:name":"Ngulo",
    "wof:placetype":"locality"
},
  "geometry": {"coordinates":[24.67946,4.78099],"type":"Point"}
}