{
  "type": "Feature",
  "properties": {
    "gn:admin1_code":"23.0",
    "gn:asciiname":"Namutaka",
    "gn:country_code":"CD",
    "gn:dem":902,
    "gn:feature_class":"P",
    "gn:feature_code":"PPL",
    "gn:name":"Namutaka",
    "gn:population":0,
    "gn:timezone":"Africa/Lubumbashi",
    "iso:country":"CD",
    "wof:name":"Namutaka",
    "wof:placetype":"locality"
},
  "geometry": {"coordinates":[22.40942,-7.45967],"type":"Point"}
}