{
  "type": "Feature",
  "properties": {
    "gn:admin1_code":"19.0",
    "gn:asciiname":"Kusu-Bakali",
    "gn:country_code":"CD",
    "gn:dem":817,
    "gn:feature_class":"P",
    "gn:feature_code":"PPL",
    "gn:name":"Kusu-Bakali",
    "gn:population":0,
    "gn:timezone":"Africa/Kinshasa",
    "iso:country":"CD",
    "wof:name":"Kusu-Bakali",
    "wof:placetype":"locality"
},
  "geometry": {"coordinates":[17.48211,-6.23666],"type":"Point"}
}