{
  "type": "Feature",
  "properties": {
    "gn:admin1_code":"22.0",
    "gn:asciiname":"Kaulu",
    "gn:country_code":"CD",
    "gn:dem":1116,
    "gn:feature_class":"P",
    "gn:feature_code":"PPL",
    "gn:name":"Kaulu",
    "gn:population":0,
    "gn:timezone":"Africa/Lubumbashi",
    "iso:country":"CD",
    "name:und_x_variant":[
        "Kutala"
    ],
    "wof:name":"Kaulu",
    "wof:placetype":"locality"
},
  "geometry": {"coordinates":[22.7483,-10.6258],"type":"Point"}
}