{
  "type": "Feature",
  "properties": {
    "gn:admin1_code":"18.0",
    "gn:asciiname":"Tshembe",
    "gn:country_code":"CD",
    "gn:dem":715,
    "gn:feature_class":"P",
    "gn:feature_code":"PPL",
    "gn:name":"Tshembe",
    "gn:population":0,
    "gn:timezone":"Africa/Lubumbashi",
    "iso:country":"CD",
    "wof:name":"Tshembe",
    "wof:placetype":"locality"
},
  "geometry": {"coordinates":[21.2229,-6.88576],"type":"Point"}
}