{
  "type": "Feature",
  "properties": {
    "gn:admin1_code":"25.0",
    "gn:asciiname":"Kenza",
    "gn:country_code":"CD",
    "gn:dem":472,
    "gn:feature_class":"P",
    "gn:feature_code":"PPL",
    "gn:name":"Kenza",
    "gn:population":0,
    "gn:timezone":"Africa/Kinshasa",
    "iso:country":"CD",
    "wof:name":"Kenza",
    "wof:placetype":"locality"
},
  "geometry": {"coordinates":[22.87372,2.89608],"type":"Point"}
}