{
  "type": "Feature",
  "properties": {
    "gn:admin1_code":"25.0",
    "gn:asciiname":"Kenza",
    "gn:country_code":"CD",
    "gn:dem":472,
    "gn:feature_class":"P",
    "gn:feature_code":"PPL",
    "gn:name":"Kenza",
    "gn:population":0,
    "gn:timezone":"Africa/Kinshasa",
    "iso:country":"CD",
    "name:ara_x_preferred":[
        "\u0643\u0646\u0632\u0629"
    ],
    "name:ceb_x_preferred":[
        "Kenza"
    ],
    "name:fra_x_preferred":[
        "Kenza"
    ],
    "name:swe_x_preferred":[
        "Kenza"
    ],
    "wof:name":"Kenza",
    "wof:placetype":"locality"
},
  "geometry": {"coordinates":[22.87372,2.89608],"type":"Point"}
}