{
  "type": "Feature",
  "properties": {
    "gn:admin1_code":"20.0",
    "gn:asciiname":"Nenga",
    "gn:country_code":"CD",
    "gn:dem":700,
    "gn:feature_class":"P",
    "gn:feature_code":"PPL",
    "gn:name":"Nenga",
    "gn:population":0,
    "gn:timezone":"Africa/Kinshasa",
    "iso:country":"CD",
    "name:ceb_x_preferred":[
        "Nenga"
    ],
    "name:fra_x_preferred":[
        "Nenga"
    ],
    "name:por_x_preferred":[
        "Nenga"
    ],
    "name:spa_x_preferred":[
        "Nenga"
    ],
    "name:swe_x_preferred":[
        "Nenga"
    ],
    "name:war_x_preferred":[
        "Nenga"
    ],
    "wof:name":"Nenga",
    "wof:placetype":"locality"
},
  "geometry": {"coordinates":[19.63665,-5.27592],"type":"Point"}
}