{
  "type": "Feature",
  "properties": {
    "gn:admin1_code":"19.0",
    "gn:asciiname":"Shamuhangenu",
    "gn:country_code":"CD",
    "gn:dem":1103,
    "gn:feature_class":"P",
    "gn:feature_code":"PPL",
    "gn:name":"Shamuhangenu",
    "gn:population":0,
    "gn:timezone":"Africa/Kinshasa",
    "iso:country":"CD",
    "wof:name":"Shamuhangenu",
    "wof:placetype":"locality"
},
  "geometry": {"coordinates":[18.66564,-7.59214],"type":"Point"}
}