{
  "type": "Feature",
  "properties": {
    "gn:admin1_code":"20.0",
    "gn:asciiname":"Yu",
    "gn:country_code":"CD",
    "gn:dem":722,
    "gn:feature_class":"P",
    "gn:feature_code":"PPL",
    "gn:name":"Yu",
    "gn:population":0,
    "gn:timezone":"Africa/Kinshasa",
    "iso:country":"CD",
    "wof:name":"Yu",
    "wof:placetype":"locality"
},
  "geometry": {"coordinates":[19.82553,-5.54843],"type":"Point"}
}