{
  "type": "Feature",
  "properties": {
    "gn:admin1_code":"20.0",
    "gn:asciiname":"Yu",
    "gn:country_code":"CD",
    "gn:dem":722,
    "gn:feature_class":"P",
    "gn:feature_code":"PPL",
    "gn:name":"Yu",
    "gn:population":0,
    "gn:timezone":"Africa/Kinshasa",
    "iso:country":"CD",
    "name:ara_x_preferred":[
        "\u064a\u0648"
    ],
    "name:ben_x_preferred":[
        "\u0987\u0989"
    ],
    "name:ell_x_preferred":[
        "\u0393\u03b9\u03bf\u03c5"
    ],
    "name:fas_x_preferred":[
        "\u06cc\u0648"
    ],
    "name:heb_x_preferred":[
        "\u05d9\u05d5\u05bc"
    ],
    "name:hin_x_preferred":[
        "\u092f\u0942"
    ],
    "name:hun_x_preferred":[
        "Yu"
    ],
    "name:ind_x_preferred":[
        "Yu"
    ],
    "name:ita_x_preferred":[
        "Yu"
    ],
    "name:kor_x_preferred":[
        "\uc720"
    ],
    "name:por_x_preferred":[
        "Yu"
    ],
    "name:spa_x_preferred":[
        "Yu"
    ],
    "name:tur_x_preferred":[
        "Yu"
    ],
    "name:ukr_x_preferred":[
        "\u042e"
    ],
    "name:urd_x_preferred":[
        "\u06cc\u0648"
    ],
    "wof:name":"Yu",
    "wof:placetype":"locality"
},
  "geometry": {"coordinates":[19.82553,-5.54843],"type":"Point"}
}