{
  "type": "Feature",
  "properties": {
    "gn:admin1_code":"18.0",
    "gn:asciiname":"Sungi-Kakese",
    "gn:country_code":"CD",
    "gn:dem":501,
    "gn:feature_class":"P",
    "gn:feature_code":"PPL",
    "gn:name":"Sungi-Kakese",
    "gn:population":0,
    "gn:timezone":"Africa/Lubumbashi",
    "iso:country":"CD",
    "wof:name":"Sungi-Kakese",
    "wof:placetype":"locality"
},
  "geometry": {"coordinates":[21.3988,-5.15335],"type":"Point"}
}