{
  "type": "Feature",
  "properties": {
    "gn:admin1_code":"28.0",
    "gn:asciiname":"Bogbasiko-Kaimba",
    "gn:country_code":"CD",
    "gn:dem":384,
    "gn:feature_class":"P",
    "gn:feature_code":"PPL",
    "gn:name":"Bogbasiko-Kaimba",
    "gn:population":0,
    "gn:timezone":"Africa/Kinshasa",
    "iso:country":"CD",
    "wof:name":"Bogbasiko-Kaimba",
    "wof:placetype":"locality"
},
  "geometry": {"coordinates":[19.04327,3.76798],"type":"Point"}
}