{
  "type": "Feature",
  "properties": {
    "gn:admin1_code":"18.0",
    "gn:asciiname":"Kasanji",
    "gn:country_code":"CD",
    "gn:dem":657,
    "gn:feature_class":"P",
    "gn:feature_code":"PPL",
    "gn:name":"Kasanji",
    "gn:population":0,
    "gn:timezone":"Africa/Lubumbashi",
    "iso:country":"CD",
    "wof:name":"Kasanji",
    "wof:placetype":"locality"
},
  "geometry": {"coordinates":[21.15708,-5.79602],"type":"Point"}
}