{
  "type": "Feature",
  "properties": {
    "gn:admin1_code":"14.0",
    "gn:asciiname":"Kasonkama",
    "gn:country_code":"CD",
    "gn:dem":1169,
    "gn:feature_class":"P",
    "gn:feature_code":"PPL",
    "gn:name":"Kasonkama",
    "gn:population":0,
    "gn:timezone":"Africa/Lubumbashi",
    "iso:country":"CD",
    "wof:name":"Kasonkama",
    "wof:placetype":"locality"
},
  "geometry": {"coordinates":[26.83806,-10.65556],"type":"Point"}
}