{
  "type": "Feature",
  "properties": {
    "gn:admin1_code":"11.0",
    "gn:asciiname":"Kahindi",
    "gn:country_code":"CD",
    "gn:dem":1663,
    "gn:feature_class":"P",
    "gn:feature_code":"PPL",
    "gn:name":"Kahindi",
    "gn:population":0,
    "gn:timezone":"Africa/Lubumbashi",
    "iso:country":"CD",
    "wof:name":"Kahindi",
    "wof:placetype":"locality"
},
  "geometry": {"coordinates":[29.19589,0.2981],"type":"Point"}
}