{
  "type": "Feature",
  "properties": {
    "gn:admin1_code":"26.0",
    "gn:asciiname":"Sidi",
    "gn:country_code":"CD",
    "gn:dem":383,
    "gn:feature_class":"P",
    "gn:feature_code":"PPL",
    "gn:name":"Sidi",
    "gn:population":0,
    "gn:timezone":"Africa/Kinshasa",
    "iso:country":"CD",
    "name:deu_x_preferred":[
        "Sidi"
    ],
    "name:fra_x_preferred":[
        "Sid"
    ],
    "name:por_x_preferred":[
        "Sidi"
    ],
    "name:spa_x_preferred":[
        "Sidi"
    ],
    "wof:name":"Sidi",
    "wof:placetype":"locality"
},
  "geometry": {"coordinates":[19.86947,5.01756],"type":"Point"}
}