{
  "type": "Feature",
  "properties": {
    "gn:admin1_code":"15.0",
    "gn:asciiname":"Kama-Mwadi",
    "gn:country_code":"CD",
    "gn:dem":1090,
    "gn:feature_class":"P",
    "gn:feature_code":"PPL",
    "gn:name":"Kama-Mwadi",
    "gn:population":0,
    "gn:timezone":"Africa/Lubumbashi",
    "iso:country":"CD",
    "wof:name":"Kama-Mwadi",
    "wof:placetype":"locality"
},
  "geometry": {"coordinates":[24.23402,-9.35213],"type":"Point"}
}