{
  "type": "Feature",
  "properties": {
    "gn:admin1_code":"16.0",
    "gn:asciiname":"Anzata",
    "gn:country_code":"CD",
    "gn:dem":786,
    "gn:feature_class":"P",
    "gn:feature_code":"PPL",
    "gn:name":"Anzata",
    "gn:population":0,
    "gn:timezone":"Africa/Lubumbashi",
    "iso:country":"CD",
    "wof:name":"Anzata",
    "wof:placetype":"locality"
},
  "geometry": {"coordinates":[27.84139,2.27229],"type":"Point"}
}