{
  "type": "Feature",
  "properties": {
    "gn:admin1_code":"19.0",
    "gn:asciiname":"Nakapinga",
    "gn:country_code":"CD",
    "gn:dem":1053,
    "gn:feature_class":"P",
    "gn:feature_code":"PPL",
    "gn:name":"Nakapinga",
    "gn:population":0,
    "gn:timezone":"Africa/Kinshasa",
    "iso:country":"CD",
    "wof:name":"Nakapinga",
    "wof:placetype":"locality"
},
  "geometry": {"coordinates":[19.30628,-7.74007],"type":"Point"}
}