{
  "type": "Feature",
  "properties": {
    "gn:admin1_code":"14.0",
    "gn:asciiname":"Petro",
    "gn:country_code":"CD",
    "gn:dem":1107,
    "gn:feature_class":"P",
    "gn:feature_code":"PPL",
    "gn:name":"Petro",
    "gn:population":0,
    "gn:timezone":"Africa/Lubumbashi",
    "iso:country":"CD",
    "name:epo_x_preferred":[
        "Petro"
    ],
    "name:ukr_x_preferred":[
        "\u041f\u0435\u0442\u0440\u043e"
    ],
    "wof:name":"Petro",
    "wof:placetype":"locality"
},
  "geometry": {"coordinates":[28.29794,-11.45742],"type":"Point"}
}