{
  "type": "Feature",
  "properties": {
    "gn:admin1_code":"28.0",
    "gn:asciiname":"Bomele",
    "gn:country_code":"CD",
    "gn:dem":393,
    "gn:feature_class":"P",
    "gn:feature_code":"PPL",
    "gn:name":"Bomele",
    "gn:population":0,
    "gn:timezone":"Africa/Kinshasa",
    "iso:country":"CD",
    "name:fra_x_preferred":[
        "Bomele"
    ],
    "wof:name":"Bomele",
    "wof:placetype":"locality"
},
  "geometry": {"coordinates":[18.99756,2.82508],"type":"Point"}
}