{
  "type": "Feature",
  "properties": {
    "gn:admin1_code":"9.0",
    "gn:asciiname":"Nayule",
    "gn:country_code":"CD",
    "gn:dem":735,
    "gn:feature_class":"P",
    "gn:feature_code":"PPL",
    "gn:name":"Nayule",
    "gn:population":0,
    "gn:timezone":"Africa/Lubumbashi",
    "iso:country":"CD",
    "wof:name":"Nayule",
    "wof:placetype":"locality"
},
  "geometry": {"coordinates":[28.46138,4.23287],"type":"Point"}
}