{
  "type": "Feature",
  "properties": {
    "gn:admin1_code":"10.0",
    "gn:asciiname":"Saramabila",
    "gn:country_code":"CD",
    "gn:dem":602,
    "gn:feature_class":"P",
    "gn:feature_code":"PPL",
    "gn:name":"Saramabila",
    "gn:population":0,
    "gn:timezone":"Africa/Lubumbashi",
    "iso:country":"CD",
    "wof:name":"Saramabila",
    "wof:placetype":"locality"
},
  "geometry": {"coordinates":[27.11667000000001,-1.66667],"type":"Point"}
}