{
  "type": "Feature",
  "properties": {
    "gn:admin1_code":"30.0",
    "gn:asciiname":"Bolinga",
    "gn:country_code":"CD",
    "gn:dem":386,
    "gn:feature_class":"P",
    "gn:feature_code":"PPL",
    "gn:name":"Bolinga",
    "gn:population":0,
    "gn:timezone":"Africa/Lubumbashi",
    "iso:country":"CD",
    "wof:name":"Bolinga",
    "wof:placetype":"locality"
},
  "geometry": {"coordinates":[24.17136,0.45668],"type":"Point"}
}