{
  "type": "Feature",
  "properties": {
    "gn:admin1_code":"25.0",
    "gn:asciiname":"Yakombe",
    "gn:country_code":"CD",
    "gn:dem":408,
    "gn:feature_class":"P",
    "gn:feature_code":"PPL",
    "gn:name":"Yakombe",
    "gn:population":0,
    "gn:timezone":"Africa/Kinshasa",
    "iso:country":"CD",
    "wof:name":"Yakombe",
    "wof:placetype":"locality"
},
  "geometry": {"coordinates":[22.02589,2.01998],"type":"Point"}
}