{
  "type": "Feature",
  "properties": {
    "gn:admin1_code":"28.0",
    "gn:asciiname":"Bopurumu",
    "gn:country_code":"CD",
    "gn:dem":430,
    "gn:feature_class":"P",
    "gn:feature_code":"PPL",
    "gn:name":"Bopurumu",
    "gn:population":0,
    "gn:timezone":"Africa/Kinshasa",
    "iso:country":"CD",
    "name:und_x_variant":[
        "Bapuruma",
        "Bopurumu"
    ],
    "wof:name":"Bopurumu",
    "wof:placetype":"locality"
},
  "geometry": {"coordinates":[20.06019,3.60052],"type":"Point"}
}