{
  "type": "Feature",
  "properties": {
    "gn:admin1_code":"27.0",
    "gn:asciiname":"Imbogunda",
    "gn:country_code":"CD",
    "gn:dem":521,
    "gn:feature_class":"P",
    "gn:feature_code":"PPL",
    "gn:name":"Imbogunda",
    "gn:population":0,
    "gn:timezone":"Africa/Lubumbashi",
    "iso:country":"CD",
    "wof:name":"Imbogunda",
    "wof:placetype":"locality"
},
  "geometry": {"coordinates":[24.93421,-4.23504],"type":"Point"}
}