{
  "type": "Feature",
  "properties": {
    "gn:admin1_code":"23.0",
    "gn:asciiname":"Kibondo",
    "gn:country_code":"CD",
    "gn:dem":809,
    "gn:feature_class":"P",
    "gn:feature_code":"PPL",
    "gn:name":"Kibondo",
    "gn:population":0,
    "gn:timezone":"Africa/Lubumbashi",
    "iso:country":"CD",
    "wof:name":"Kibondo",
    "wof:placetype":"locality"
},
  "geometry": {"coordinates":[22.67724,-6.38355],"type":"Point"}
}