{
  "type": "Feature",
  "properties": {
    "gn:admin1_code":"25.0",
    "gn:asciiname":"Libela",
    "gn:country_code":"CD",
    "gn:dem":392,
    "gn:feature_class":"P",
    "gn:feature_code":"PPL",
    "gn:name":"Libela",
    "gn:population":0,
    "gn:timezone":"Africa/Kinshasa",
    "iso:country":"CD",
    "wof:name":"Libela",
    "wof:placetype":"locality"
},
  "geometry": {"coordinates":[22.10549,2.48845],"type":"Point"}
}