{
  "type": "Feature",
  "properties": {
    "gn:admin1_code":"8.0",
    "gn:asciiname":"Bibanga",
    "gn:country_code":"CD",
    "gn:dem":474,
    "gn:feature_class":"P",
    "gn:feature_code":"PPL",
    "gn:name":"Bibanga",
    "gn:population":0,
    "gn:timezone":"Africa/Kinshasa",
    "iso:country":"CD",
    "wof:name":"Bibanga",
    "wof:placetype":"locality"
},
  "geometry": {"coordinates":[15.59219,-4.86064],"type":"Point"}
}