{
  "type": "Feature",
  "properties": {
    "gn:admin1_code":"27.0",
    "gn:asciiname":"Ombedi",
    "gn:country_code":"CD",
    "gn:dem":512,
    "gn:feature_class":"P",
    "gn:feature_code":"PPL",
    "gn:name":"Ombedi",
    "gn:population":0,
    "gn:timezone":"Africa/Lubumbashi",
    "iso:country":"CD",
    "wof:name":"Ombedi",
    "wof:placetype":"locality"
},
  "geometry": {"coordinates":[23.82485,-3.72355],"type":"Point"}
}