{
  "type": "Feature",
  "properties": {
    "gn:admin1_code":"30.0",
    "gn:asciiname":"Yalaki",
    "gn:country_code":"CD",
    "gn:dem":545,
    "gn:feature_class":"P",
    "gn:feature_code":"PPL",
    "gn:name":"Yalaki",
    "gn:population":0,
    "gn:timezone":"Africa/Lubumbashi",
    "iso:country":"CD",
    "name:und_x_variant":[
        "Yaolaki"
    ],
    "wof:name":"Yalaki",
    "wof:placetype":"locality"
},
  "geometry": {"coordinates":[23.41365,0.57898],"type":"Point"}
}