{
  "type": "Feature",
  "properties": {
    "gn:admin1_code":"0.0",
    "gn:asciiname":"Bokondo",
    "gn:country_code":"CD",
    "gn:dem":443,
    "gn:feature_class":"P",
    "gn:feature_code":"PPL",
    "gn:name":"Bokondo",
    "gn:population":0,
    "gn:timezone":"Africa/Kinshasa",
    "iso:country":"CD",
    "wof:name":"Bokondo",
    "wof:placetype":"locality"
},
  "geometry": {"coordinates":[22.53333,0.25],"type":"Point"}
}