{
  "type": "Feature",
  "properties": {
    "gn:admin1_code":"15.0",
    "gn:asciiname":"Bitupu",
    "gn:country_code":"CD",
    "gn:dem":961,
    "gn:feature_class":"P",
    "gn:feature_code":"PPL",
    "gn:name":"Bitupu",
    "gn:population":0,
    "gn:timezone":"Africa/Lubumbashi",
    "iso:country":"CD",
    "name:und_x_variant":[
        "Bituhu"
    ],
    "wof:name":"Bitupu",
    "wof:placetype":"locality"
},
  "geometry": {"coordinates":[24.09412,-7.90921],"type":"Point"}
}