{
  "type": "Feature",
  "properties": {
    "gn:admin1_code":"24.0",
    "gn:asciiname":"Semendua",
    "gn:country_code":"CD",
    "gn:dem":401,
    "gn:feature_class":"P",
    "gn:feature_code":"PPL",
    "gn:name":"Semendua",
    "gn:population":0,
    "gn:timezone":"Africa/Kinshasa",
    "iso:country":"CD",
    "wof:name":"Semendua",
    "wof:placetype":"locality"
},
  "geometry": {"coordinates":[18.11658,-3.23375],"type":"Point"}
}