{
  "type": "Feature",
  "properties": {
    "gn:admin1_code":"24.0",
    "gn:asciiname":"Bopaka-Pentana",
    "gn:country_code":"CD",
    "gn:dem":328,
    "gn:feature_class":"P",
    "gn:feature_code":"PPL",
    "gn:name":"Bopaka-Pentana",
    "gn:population":0,
    "gn:timezone":"Africa/Kinshasa",
    "iso:country":"CD",
    "name:und_x_variant":[
        "Pentana",
        "Bopaka",
        "Bopaka-Pentana"
    ],
    "wof:name":"Bopaka-Pentana",
    "wof:placetype":"locality"
},
  "geometry": {"coordinates":[17.36969,-2.49416],"type":"Point"}
}