{
  "type": "Feature",
  "properties": {
    "gn:admin1_code":"13.0",
    "gn:asciiname":"Bobeme",
    "gn:country_code":"CD",
    "gn:dem":425,
    "gn:feature_class":"P",
    "gn:feature_code":"PPL",
    "gn:name":"Bobeme",
    "gn:population":0,
    "gn:timezone":"Africa/Lubumbashi",
    "iso:country":"CD",
    "wof:name":"Bobeme",
    "wof:placetype":"locality"
},
  "geometry": {"coordinates":[23.34,2.63699],"type":"Point"}
}