{
  "type": "Feature",
  "properties": {
    "gn:admin1_code":"16.0",
    "gn:asciiname":"Basia",
    "gn:country_code":"CD",
    "gn:dem":731,
    "gn:feature_class":"P",
    "gn:feature_code":"PPL",
    "gn:name":"Basia",
    "gn:population":0,
    "gn:timezone":"Africa/Lubumbashi",
    "iso:country":"CD",
    "name:bre_x_preferred":[
        "Basia"
    ],
    "name:deu_x_preferred":[
        "Basia Trzetrzelewska"
    ],
    "name:fra_x_preferred":[
        "Basia Trzetrzelewska"
    ],
    "name:ita_x_preferred":[
        "Basia Trzetrzelewska"
    ],
    "name:jpn_x_preferred":[
        "\u30d0\u30fc\u30b7\u30a2"
    ],
    "name:nld_x_preferred":[
        "Basia Trzetrzelewska"
    ],
    "name:pol_x_preferred":[
        "Basia"
    ],
    "name:por_x_preferred":[
        "Basia"
    ],
    "name:spa_x_preferred":[
        "Basia Trzetrzelewska"
    ],
    "name:zho_x_preferred":[
        "Basia"
    ],
    "wof:name":"Basia",
    "wof:placetype":"locality"
},
  "geometry": {"coordinates":[28.7557,4.26488],"type":"Point"}
}