{
  "type": "Feature",
  "properties": {
    "gn:admin1_code":"18.0",
    "gn:asciiname":"Anga",
    "gn:country_code":"CD",
    "gn:dem":490,
    "gn:feature_class":"P",
    "gn:feature_code":"PPL",
    "gn:name":"Anga",
    "gn:population":0,
    "gn:timezone":"Africa/Lubumbashi",
    "iso:country":"CD",
    "wof:name":"Anga",
    "wof:placetype":"locality"
},
  "geometry": {"coordinates":[21.57628,-3.14018],"type":"Point"}
}