{
  "type": "Feature",
  "properties": {
    "gn:admin1_code":"12.0",
    "gn:asciiname":"Kisanga",
    "gn:country_code":"CD",
    "gn:dem":1766,
    "gn:feature_class":"P",
    "gn:feature_code":"PPL",
    "gn:name":"Kisanga",
    "gn:population":0,
    "gn:timezone":"Africa/Lubumbashi",
    "iso:country":"CD",
    "wof:name":"Kisanga",
    "wof:placetype":"locality"
},
  "geometry": {"coordinates":[28.66667,-4.41667],"type":"Point"}
}