{
  "type": "Feature",
  "properties": {
    "gn:admin1_code":"13.0",
    "gn:asciiname":"Bela",
    "gn:country_code":"CD",
    "gn:dem":451,
    "gn:feature_class":"P",
    "gn:feature_code":"PPL",
    "gn:name":"Bela",
    "gn:population":0,
    "gn:timezone":"Africa/Lubumbashi",
    "iso:country":"CD",
    "wof:name":"Bela",
    "wof:placetype":"locality"
},
  "geometry": {"coordinates":[22.73799,4.21124],"type":"Point"}
}