{
  "type": "Feature",
  "properties": {
    "gn:admin1_code":"15.0",
    "gn:asciiname":"Pasu",
    "gn:country_code":"CD",
    "gn:dem":780,
    "gn:feature_class":"P",
    "gn:feature_code":"PPL",
    "gn:name":"Pasu",
    "gn:population":0,
    "gn:timezone":"Africa/Lubumbashi",
    "iso:country":"CD",
    "wof:name":"Pasu",
    "wof:placetype":"locality"
},
  "geometry": {"coordinates":[26.03335,-7.44791],"type":"Point"}
}