{
  "type": "Feature",
  "properties": {
    "gn:admin1_code":"19.0",
    "gn:asciiname":"Kasindji",
    "gn:country_code":"CD",
    "gn:dem":738,
    "gn:feature_class":"P",
    "gn:feature_code":"PPL",
    "gn:name":"Kasindji",
    "gn:population":0,
    "gn:timezone":"Africa/Kinshasa",
    "iso:country":"CD",
    "wof:name":"Kasindji",
    "wof:placetype":"locality"
},
  "geometry": {"coordinates":[18.14399,-7.55951],"type":"Point"}
}