{
  "type": "Feature",
  "properties": {
    "gn:admin1_code":"16.0",
    "gn:asciiname":"Adala-Ole",
    "gn:country_code":"CD",
    "gn:dem":853,
    "gn:feature_class":"P",
    "gn:feature_code":"PPL",
    "gn:name":"Adala-Ole",
    "gn:population":0,
    "gn:timezone":"Africa/Lubumbashi",
    "iso:country":"CD",
    "wof:name":"Adala-Ole",
    "wof:placetype":"locality"
},
  "geometry": {"coordinates":[30.05699000000001,3.95342],"type":"Point"}
}