{
  "type": "Feature",
  "properties": {
    "gn:admin1_code":"26.0",
    "gn:asciiname":"Lite-Sobe",
    "gn:country_code":"CD",
    "gn:dem":476,
    "gn:feature_class":"P",
    "gn:feature_code":"PPL",
    "gn:name":"Lite-Sobe",
    "gn:population":0,
    "gn:timezone":"Africa/Kinshasa",
    "iso:country":"CD",
    "wof:name":"Lite-Sobe",
    "wof:placetype":"locality"
},
  "geometry": {"coordinates":[22.929,3.74853],"type":"Point"}
}