{
  "type": "Feature",
  "properties": {
    "gn:admin1_code":"18.0",
    "gn:asciiname":"Muakanangu",
    "gn:country_code":"CD",
    "gn:dem":656,
    "gn:feature_class":"P",
    "gn:feature_code":"PPL",
    "gn:name":"Muakanangu",
    "gn:population":0,
    "gn:timezone":"Africa/Lubumbashi",
    "iso:country":"CD",
    "name:und_x_variant":[
        "Mwakahangu",
        "Muakanangu"
    ],
    "wof:name":"Muakanangu",
    "wof:placetype":"locality"
},
  "geometry": {"coordinates":[20.84127,-7.25383],"type":"Point"}
}