{
  "type": "Feature",
  "properties": {
    "gn:admin1_code":"18.0",
    "gn:asciiname":"Lukadi-Mpaye",
    "gn:country_code":"CD",
    "gn:dem":596,
    "gn:feature_class":"P",
    "gn:feature_code":"PPL",
    "gn:name":"Lukadi-Mpaye",
    "gn:population":0,
    "gn:timezone":"Africa/Lubumbashi",
    "iso:country":"CD",
    "wof:name":"Lukadi-Mpaye",
    "wof:placetype":"locality"
},
  "geometry": {"coordinates":[20.71124,-5.95171],"type":"Point"}
}