{
  "type": "Feature",
  "properties": {
    "gn:admin1_code":"29.0",
    "gn:asciiname":"Kifundulu",
    "gn:country_code":"CD",
    "gn:dem":737,
    "gn:feature_class":"P",
    "gn:feature_code":"PPL",
    "gn:name":"Kifundulu",
    "gn:population":0,
    "gn:timezone":"Africa/Lubumbashi",
    "iso:country":"CD",
    "wof:name":"Kifundulu",
    "wof:placetype":"locality"
},
  "geometry": {"coordinates":[27.99186,-5.88871],"type":"Point"}
}