{
  "type": "Feature",
  "properties": {
    "gn:admin1_code":"22.0",
    "gn:asciiname":"Butu",
    "gn:country_code":"CD",
    "gn:dem":1242,
    "gn:feature_class":"P",
    "gn:feature_code":"PPL",
    "gn:name":"Butu",
    "gn:population":0,
    "gn:timezone":"Africa/Lubumbashi",
    "iso:country":"CD",
    "wof:name":"Butu",
    "wof:placetype":"locality"
},
  "geometry": {"coordinates":[24.43333,-10.71667],"type":"Point"}
}