{
  "type": "Feature",
  "properties": {
    "gn:admin1_code":"18.0",
    "gn:asciiname":"Tshifuafua",
    "gn:country_code":"CD",
    "gn:dem":497,
    "gn:feature_class":"P",
    "gn:feature_code":"PPL",
    "gn:name":"Tshifuafua",
    "gn:population":0,
    "gn:timezone":"Africa/Lubumbashi",
    "iso:country":"CD",
    "wof:name":"Tshifuafua",
    "wof:placetype":"locality"
},
  "geometry": {"coordinates":[20.53001,-4.69396],"type":"Point"}
}