{
  "type": "Feature",
  "properties": {
    "gn:admin1_code":"18.0",
    "gn:asciiname":"Lodi",
    "gn:country_code":"CD",
    "gn:dem":375,
    "gn:feature_class":"P",
    "gn:feature_code":"PPL",
    "gn:name":"Lodi",
    "gn:population":0,
    "gn:timezone":"Africa/Lubumbashi",
    "iso:country":"CD",
    "name:cat_x_preferred":[
        "Lodi"
    ],
    "name:ceb_x_preferred":[
        "Lodi"
    ],
    "name:deu_x_preferred":[
        "Lodi"
    ],
    "name:est_x_preferred":[
        "Lodi"
    ],
    "name:fas_x_preferred":[
        "\u0644\u0648\u062f\u06cc"
    ],
    "name:fin_x_preferred":[
        "Lodi"
    ],
    "name:fra_x_preferred":[
        "Lodi"
    ],
    "name:ita_x_preferred":[
        "Lodi"
    ],
    "name:nld_x_preferred":[
        "Lodi"
    ],
    "name:pms_x_preferred":[
        "Lodi"
    ],
    "name:pol_x_preferred":[
        "Lodi"
    ],
    "name:por_x_preferred":[
        "Lodi"
    ],
    "name:spa_x_preferred":[
        "Lodi"
    ],
    "name:swe_x_preferred":[
        "Lodi"
    ],
    "name:ukr_x_preferred":[
        "\u041b\u043e\u0434\u0456"
    ],
    "name:vol_x_preferred":[
        "Lodi"
    ],
    "wof:name":"Lodi",
    "wof:placetype":"locality"
},
  "geometry": {"coordinates":[21.32729,-4.03233],"type":"Point"}
}