{
  "type": "Feature",
  "properties": {
    "gn:admin1_code":"29.0",
    "gn:asciiname":"Selembe",
    "gn:country_code":"CD",
    "gn:dem":1714,
    "gn:feature_class":"P",
    "gn:feature_code":"PPL",
    "gn:name":"Selembe",
    "gn:population":0,
    "gn:timezone":"Africa/Lubumbashi",
    "iso:country":"CD",
    "wof:name":"Selembe",
    "wof:placetype":"locality"
},
  "geometry": {"coordinates":[29.73333,-8.03333],"type":"Point"}
}