{
  "type": "Feature",
  "properties": {
    "gn:admin1_code":"21.0",
    "gn:asciiname":"Kombo",
    "gn:country_code":"CD",
    "gn:dem":845,
    "gn:feature_class":"P",
    "gn:feature_code":"PPL",
    "gn:name":"Kombo",
    "gn:population":0,
    "gn:timezone":"Africa/Lubumbashi",
    "iso:country":"CD",
    "name:cat_x_preferred":[
        "Combo"
    ],
    "name:deu_x_preferred":[
        "Kombo"
    ],
    "wof:name":"Kombo",
    "wof:placetype":"locality"
},
  "geometry": {"coordinates":[23.89759,-7.48822],"type":"Point"}
}