{
  "type": "Feature",
  "properties": {
    "gn:admin1_code":"17.0",
    "gn:asciiname":"Midu",
    "gn:country_code":"CD",
    "gn:dem":1178,
    "gn:feature_class":"P",
    "gn:feature_code":"PPL",
    "gn:name":"Midu",
    "gn:population":0,
    "gn:timezone":"Africa/Lubumbashi",
    "iso:country":"CD",
    "wof:name":"Midu",
    "wof:placetype":"locality"
},
  "geometry": {"coordinates":[30.67872,3.33894],"type":"Point"}
}