{
  "type": "Feature",
  "properties": {
    "gn:admin1_code":"18.0",
    "gn:asciiname":"Kambatshipuka",
    "gn:country_code":"CD",
    "gn:dem":605,
    "gn:feature_class":"P",
    "gn:feature_code":"PPL",
    "gn:name":"Kambatshipuka",
    "gn:population":0,
    "gn:timezone":"Africa/Lubumbashi",
    "iso:country":"CD",
    "wof:name":"Kambatshipuka",
    "wof:placetype":"locality"
},
  "geometry": {"coordinates":[20.70489,-4.70556],"type":"Point"}
}