{
  "type": "Feature",
  "properties": {
    "gn:admin1_code":"23.0",
    "gn:asciiname":"Tundu",
    "gn:country_code":"CD",
    "gn:dem":931,
    "gn:feature_class":"P",
    "gn:feature_code":"PPL",
    "gn:name":"Tundu",
    "gn:population":0,
    "gn:timezone":"Africa/Lubumbashi",
    "iso:country":"CD",
    "wof:name":"Tundu",
    "wof:placetype":"locality"
},
  "geometry": {"coordinates":[23.08956,-7.14877],"type":"Point"}
}