{
  "type": "Feature",
  "properties": {
    "gn:admin1_code":"23.0",
    "gn:asciiname":"Tundu",
    "gn:country_code":"CD",
    "gn:dem":931,
    "gn:feature_class":"P",
    "gn:feature_code":"PPL",
    "gn:name":"Tundu",
    "gn:population":0,
    "gn:timezone":"Africa/Lubumbashi",
    "iso:country":"CD",
    "name:est_x_preferred":[
        "Tundu"
    ],
    "name:hye_x_preferred":[
        "\u054f\u0578\u0582\u0576\u0564\u0578\u0582"
    ],
    "name:pol_x_preferred":[
        "Tundu"
    ],
    "name:spa_x_preferred":[
        "Tundu"
    ],
    "name:ukr_x_preferred":[
        "\u0422\u0443\u043d\u0434\u0443"
    ],
    "name:vol_x_preferred":[
        "Tundu"
    ],
    "wof:name":"Tundu",
    "wof:placetype":"locality"
},
  "geometry": {"coordinates":[23.08956,-7.14877],"type":"Point"}
}