{
  "type": "Feature",
  "properties": {
    "gn:admin1_code":"30.0",
    "gn:asciiname":"Bangoka",
    "gn:country_code":"CD",
    "gn:dem":436,
    "gn:feature_class":"P",
    "gn:feature_code":"PPL",
    "gn:name":"Bangoka",
    "gn:population":0,
    "gn:timezone":"Africa/Lubumbashi",
    "iso:country":"CD",
    "wof:name":"Bangoka",
    "wof:placetype":"locality"
},
  "geometry": {"coordinates":[25.34331,0.46566],"type":"Point"}
}