{
  "type": "Feature",
  "properties": {
    "gn:admin1_code":"18.0",
    "gn:asciiname":"Lubudi",
    "gn:country_code":"CD",
    "gn:dem":668,
    "gn:feature_class":"P",
    "gn:feature_code":"PPL",
    "gn:name":"Lubudi",
    "gn:population":0,
    "gn:timezone":"Africa/Lubumbashi",
    "iso:country":"CD",
    "name:und_x_variant":[
        "Lubudie",
        "Lubudi"
    ],
    "wof:name":"Lubudi",
    "wof:placetype":"locality"
},
  "geometry": {"coordinates":[21.30321,-6.85178],"type":"Point"}
}