{
  "type": "Feature",
  "properties": {
    "gn:admin1_code":"16.0",
    "gn:asciiname":"Kakeritu",
    "gn:country_code":"CD",
    "gn:dem":818,
    "gn:feature_class":"P",
    "gn:feature_code":"PPL",
    "gn:name":"Kakeritu",
    "gn:population":0,
    "gn:timezone":"Africa/Lubumbashi",
    "iso:country":"CD",
    "name:und_x_variant":[
        "Kakerifu",
        "Kakeritu"
    ],
    "wof:name":"Kakeritu",
    "wof:placetype":"locality"
},
  "geometry": {"coordinates":[29.42626,3.38727],"type":"Point"}
}