{
  "type": "Feature",
  "properties": {
    "gn:admin1_code":"18.0",
    "gn:asciiname":"Ibombo-Gandjamba",
    "gn:country_code":"CD",
    "gn:dem":578,
    "gn:feature_class":"P",
    "gn:feature_code":"PPL",
    "gn:name":"Ibombo-Gandjamba",
    "gn:population":0,
    "gn:timezone":"Africa/Lubumbashi",
    "iso:country":"CD",
    "wof:name":"Ibombo-Gandjamba",
    "wof:placetype":"locality"
},
  "geometry": {"coordinates":[20.33787,-5.11958],"type":"Point"}
}