{
  "type": "Feature",
  "properties": {
    "gn:admin1_code":"7.0",
    "gn:asciiname":"Nzulo",
    "gn:country_code":"CD",
    "gn:dem":1470,
    "gn:feature_class":"P",
    "gn:feature_code":"PPL",
    "gn:name":"Nzulo",
    "gn:population":0,
    "gn:timezone":"Africa/Lubumbashi",
    "iso:country":"CD",
    "wof:name":"Nzulo",
    "wof:placetype":"locality"
},
  "geometry": {"coordinates":[29.11872,-1.62389],"type":"Point"}
}