{
  "type": "Feature",
  "properties": {
    "gn:admin1_code":"18.0",
    "gn:asciiname":"Muila-Bumba",
    "gn:country_code":"CD",
    "gn:dem":716,
    "gn:feature_class":"P",
    "gn:feature_code":"PPL",
    "gn:name":"Muila-Bumba",
    "gn:population":0,
    "gn:timezone":"Africa/Lubumbashi",
    "iso:country":"CD",
    "wof:name":"Muila-Bumba",
    "wof:placetype":"locality"
},
  "geometry": {"coordinates":[21.4845,-6.16066],"type":"Point"}
}