{
  "type": "Feature",
  "properties": {
    "gn:admin1_code":"28.0",
    "gn:asciiname":"Ibeli-Bima",
    "gn:country_code":"CD",
    "gn:dem":350,
    "gn:feature_class":"P",
    "gn:feature_code":"PPL",
    "gn:name":"Ibeli-Bima",
    "gn:population":0,
    "gn:timezone":"Africa/Kinshasa",
    "iso:country":"CD",
    "wof:name":"Ibeli-Bima",
    "wof:placetype":"locality"
},
  "geometry": {"coordinates":[18.70341,2.97483],"type":"Point"}
}