{
  "type": "Feature",
  "properties": {
    "gn:admin1_code":"8.0",
    "gn:asciiname":"Kikanga",
    "gn:country_code":"CD",
    "gn:dem":666,
    "gn:feature_class":"P",
    "gn:feature_code":"PPL",
    "gn:name":"Kikanga",
    "gn:population":0,
    "gn:timezone":"Africa/Kinshasa",
    "iso:country":"CD",
    "wof:name":"Kikanga",
    "wof:placetype":"locality"
},
  "geometry": {"coordinates":[15.41772,-5.35855],"type":"Point"}
}