{
  "type": "Feature",
  "properties": {
    "gn:admin1_code":"13.0",
    "gn:asciiname":"Ongosine",
    "gn:country_code":"CD",
    "gn:dem":657,
    "gn:feature_class":"P",
    "gn:feature_code":"PPL",
    "gn:name":"Ongosine",
    "gn:population":0,
    "gn:timezone":"Africa/Lubumbashi",
    "iso:country":"CD",
    "wof:name":"Ongosine",
    "wof:placetype":"locality"
},
  "geometry": {"coordinates":[26.44749,2.41023],"type":"Point"}
}