{
  "type": "Feature",
  "properties": {
    "gn:admin1_code":"24.0",
    "gn:asciiname":"Ikendji",
    "gn:country_code":"CD",
    "gn:dem":312,
    "gn:feature_class":"P",
    "gn:feature_code":"PPL",
    "gn:name":"Ikendji",
    "gn:population":0,
    "gn:timezone":"Africa/Kinshasa",
    "iso:country":"CD",
    "wof:name":"Ikendji",
    "wof:placetype":"locality"
},
  "geometry": {"coordinates":[16.88028,-2.10036],"type":"Point"}
}