{
  "type": "Feature",
  "properties": {
    "gn:admin1_code":"22.0",
    "gn:asciiname":"Kamusake",
    "gn:country_code":"CD",
    "gn:dem":1093,
    "gn:feature_class":"P",
    "gn:feature_code":"PPL",
    "gn:name":"Kamusake",
    "gn:population":0,
    "gn:timezone":"Africa/Lubumbashi",
    "iso:country":"CD",
    "wof:name":"Kamusake",
    "wof:placetype":"locality"
},
  "geometry": {"coordinates":[24.04625,-10.06579],"type":"Point"}
}