{
  "type": "Feature",
  "properties": {
    "gn:admin1_code":"10.0",
    "gn:asciiname":"Lubunda",
    "gn:country_code":"CD",
    "gn:dem":616,
    "gn:feature_class":"P",
    "gn:feature_code":"PPL",
    "gn:name":"Lubunda",
    "gn:population":0,
    "gn:timezone":"Africa/Lubumbashi",
    "iso:country":"CD",
    "wof:name":"Lubunda",
    "wof:placetype":"locality"
},
  "geometry": {"coordinates":[26.58333,-4.95],"type":"Point"}
}