{
  "type": "Feature",
  "properties": {
    "gn:admin1_code":"15.0",
    "gn:asciiname":"Sumba-Luwai",
    "gn:country_code":"CD",
    "gn:dem":943,
    "gn:feature_class":"P",
    "gn:feature_code":"PPL",
    "gn:name":"Sumba-Luwai",
    "gn:population":0,
    "gn:timezone":"Africa/Lubumbashi",
    "iso:country":"CD",
    "wof:name":"Sumba-Luwai",
    "wof:placetype":"locality"
},
  "geometry": {"coordinates":[24.08333,-8.25],"type":"Point"}
}