{
  "type": "Feature",
  "properties": {
    "gn:admin1_code":"10.0",
    "gn:asciiname":"Penge",
    "gn:country_code":"CD",
    "gn:dem":755,
    "gn:feature_class":"P",
    "gn:feature_code":"PPL",
    "gn:name":"Penge",
    "gn:population":0,
    "gn:timezone":"Africa/Lubumbashi",
    "iso:country":"CD",
    "wof:name":"Penge",
    "wof:placetype":"locality"
},
  "geometry": {"coordinates":[28.45401,-4.44692],"type":"Point"}
}