{
  "type": "Feature",
  "properties": {
    "gn:admin1_code":"10.0",
    "gn:asciiname":"Penge",
    "gn:country_code":"CD",
    "gn:dem":755,
    "gn:feature_class":"P",
    "gn:feature_code":"PPL",
    "gn:name":"Penge",
    "gn:population":0,
    "gn:timezone":"Africa/Lubumbashi",
    "iso:country":"CD",
    "name:afr_x_preferred":[
        "Penge"
    ],
    "name:azb_x_preferred":[
        "\u067e\u0646\u062c"
    ],
    "name:dan_x_preferred":[
        "Penge"
    ],
    "name:fas_x_preferred":[
        "\u067e\u0646\u062c"
    ],
    "name:hin_x_preferred":[
        "\u092a\u0947\u0902\u091c"
    ],
    "name:ita_x_preferred":[
        "Penge"
    ],
    "name:nld_x_preferred":[
        "Penge"
    ],
    "name:pol_x_preferred":[
        "Penge"
    ],
    "name:urd_x_preferred":[
        "\u067e\u06cc\u0646\u06af\u06d2"
    ],
    "wof:name":"Penge",
    "wof:placetype":"locality"
},
  "geometry": {"coordinates":[28.45401,-4.44692],"type":"Point"}
}