{
  "type": "Feature",
  "properties": {
    "gn:admin1_code":"15.0",
    "gn:asciiname":"Kapemba",
    "gn:country_code":"CD",
    "gn:dem":717,
    "gn:feature_class":"P",
    "gn:feature_code":"PPL",
    "gn:name":"Kapemba",
    "gn:population":0,
    "gn:timezone":"Africa/Lubumbashi",
    "iso:country":"CD",
    "wof:name":"Kapemba",
    "wof:placetype":"locality"
},
  "geometry": {"coordinates":[25.9482,-8.75505],"type":"Point"}
}