{
  "type": "Feature",
  "properties": {
    "gn:admin1_code":"22.0",
    "gn:asciiname":"Kakeche",
    "gn:country_code":"CD",
    "gn:dem":1065,
    "gn:feature_class":"P",
    "gn:feature_code":"PPL",
    "gn:name":"Kakeche",
    "gn:population":0,
    "gn:timezone":"Africa/Lubumbashi",
    "iso:country":"CD",
    "wof:name":"Kakeche",
    "wof:placetype":"locality"
},
  "geometry": {"coordinates":[22.46671,-10.69258],"type":"Point"}
}