{
  "type": "Feature",
  "properties": {
    "gn:admin1_code":"4.0",
    "gn:asciiname":"Muzembe",
    "gn:country_code":"CD",
    "gn:dem":804,
    "gn:feature_class":"P",
    "gn:feature_code":"PPL",
    "gn:name":"Muzembe",
    "gn:population":0,
    "gn:timezone":"Africa/Lubumbashi",
    "iso:country":"CD",
    "name:und_x_variant":[
        "Musembe"
    ],
    "wof:name":"Muzembe",
    "wof:placetype":"locality"
},
  "geometry": {"coordinates":[23.26694,-6.39467],"type":"Point"}
}