{
  "type": "Feature",
  "properties": {
    "gn:admin1_code":"28.0",
    "gn:asciiname":"Zu",
    "gn:country_code":"CD",
    "gn:dem":357,
    "gn:feature_class":"P",
    "gn:feature_code":"PPL",
    "gn:name":"Zu",
    "gn:population":0,
    "gn:timezone":"Africa/Kinshasa",
    "iso:country":"CD",
    "name:ceb_x_preferred":[
        "Zu"
    ],
    "name:eus_x_preferred":[
        "Zu"
    ],
    "name:rus_x_preferred":[
        "\u0426\u0437\u0443"
    ],
    "name:swe_x_preferred":[
        "Zu"
    ],
    "wof:name":"Zu",
    "wof:placetype":"locality"
},
  "geometry": {"coordinates":[18.70467,3.78409],"type":"Point"}
}