{
  "type": "Feature",
  "properties": {
    "gn:admin1_code":"30.0",
    "gn:asciiname":"Ikoto Premiere",
    "gn:country_code":"CD",
    "gn:dem":473,
    "gn:feature_class":"P",
    "gn:feature_code":"PPL",
    "gn:name":"Ikoto Premi\u00e8re",
    "gn:population":0,
    "gn:timezone":"Africa/Lubumbashi",
    "iso:country":"CD",
    "name:und_x_variant":[
        "Ikoto",
        "Ikoto I",
        "Ikoto Premi\u00e8re"
    ],
    "wof:name":"Ikoto Premiere",
    "wof:placetype":"locality"
},
  "geometry": {"coordinates":[24.68412,0.05659],"type":"Point"}
}