{
  "type": "Feature",
  "properties": {
    "gn:admin1_code":"19.0",
    "gn:asciiname":"Kisenzi",
    "gn:country_code":"CD",
    "gn:dem":764,
    "gn:feature_class":"P",
    "gn:feature_code":"PPL",
    "gn:name":"Kisenzi",
    "gn:population":0,
    "gn:timezone":"Africa/Kinshasa",
    "iso:country":"CD",
    "wof:name":"Kisenzi",
    "wof:placetype":"locality"
},
  "geometry": {"coordinates":[16.35586,-5.41174],"type":"Point"}
}