{
  "type": "Feature",
  "properties": {
    "gn:admin1_code":"26.0",
    "gn:asciiname":"Bosongindo",
    "gn:country_code":"CD",
    "gn:dem":430,
    "gn:feature_class":"P",
    "gn:feature_code":"PPL",
    "gn:name":"Bosongindo",
    "gn:population":0,
    "gn:timezone":"Africa/Kinshasa",
    "iso:country":"CD",
    "wof:name":"Bosongindo",
    "wof:placetype":"locality"
},
  "geometry": {"coordinates":[20.31207,4.51823],"type":"Point"}
}