{
  "type": "Feature",
  "properties": {
    "gn:admin1_code":"23.0",
    "gn:asciiname":"Masamba",
    "gn:country_code":"CD",
    "gn:dem":852,
    "gn:feature_class":"P",
    "gn:feature_code":"PPL",
    "gn:name":"Masamba",
    "gn:population":0,
    "gn:timezone":"Africa/Lubumbashi",
    "iso:country":"CD",
    "wof:name":"Masamba",
    "wof:placetype":"locality"
},
  "geometry": {"coordinates":[23.06131,-6.44404],"type":"Point"}
}