{
  "type": "Feature",
  "properties": {
    "gn:admin1_code":"23.0",
    "gn:asciiname":"Masamba",
    "gn:country_code":"CD",
    "gn:dem":852,
    "gn:feature_class":"P",
    "gn:feature_code":"PPL",
    "gn:name":"Masamba",
    "gn:population":0,
    "gn:timezone":"Africa/Lubumbashi",
    "iso:country":"CD",
    "name:ara_x_preferred":[
        "\u0645\u0627\u0633\u0627\u0645\u0628\u0627"
    ],
    "name:deu_x_preferred":[
        "Masamba"
    ],
    "name:ind_x_preferred":[
        "Masamba"
    ],
    "name:jav_x_preferred":[
        "Masamba"
    ],
    "name:msa_x_preferred":[
        "Masamba"
    ],
    "name:zho_x_preferred":[
        "\u9a6c\u6851\u5df4"
    ],
    "wof:name":"Masamba",
    "wof:placetype":"locality"
},
  "geometry": {"coordinates":[23.06131,-6.44404],"type":"Point"}
}