{
  "type": "Feature",
  "properties": {
    "gn:admin1_code":"22.0",
    "gn:asciiname":"Fumu-Tshimbundu",
    "gn:country_code":"CD",
    "gn:dem":921,
    "gn:feature_class":"P",
    "gn:feature_code":"PPL",
    "gn:name":"Fumu-Tshimbundu",
    "gn:population":0,
    "gn:timezone":"Africa/Lubumbashi",
    "iso:country":"CD",
    "wof:name":"Fumu-Tshimbundu",
    "wof:placetype":"locality"
},
  "geometry": {"coordinates":[23.05727000000001,-9.79595],"type":"Point"}
}