{
  "type": "Feature",
  "properties": {
    "gn:admin1_code":"17.0",
    "gn:asciiname":"Dani II",
    "gn:country_code":"CD",
    "gn:dem":892,
    "gn:feature_class":"P",
    "gn:feature_code":"PPL",
    "gn:name":"Dani II",
    "gn:population":0,
    "gn:timezone":"Africa/Lubumbashi",
    "iso:country":"CD",
    "name:fra_x_preferred":[
        "Dani II"
    ],
    "name:fra_x_variant":[
        "Daini II"
    ],
    "wof:name":"Dani II",
    "wof:placetype":"locality"
},
  "geometry": {"coordinates":[29.07972,1.56029],"type":"Point"}
}