{
  "type": "Feature",
  "properties": {
    "gn:admin1_code":"23.0",
    "gn:asciiname":"Ngweji-a-Kondi",
    "gn:country_code":"CD",
    "gn:dem":864,
    "gn:feature_class":"P",
    "gn:feature_code":"PPL",
    "gn:name":"Ngweji-a-Kondi",
    "gn:population":0,
    "gn:timezone":"Africa/Lubumbashi",
    "iso:country":"CD",
    "name:und_x_variant":[
        "Mweji-a-Kondi",
        "Ngweji-a-Kondi"
    ],
    "wof:name":"Ngweji-a-Kondi",
    "wof:placetype":"locality"
},
  "geometry": {"coordinates":[22.44069,-7.16059],"type":"Point"}
}