{
  "type": "Feature",
  "properties": {
    "gn:admin1_code":"18.0",
    "gn:asciiname":"Buabua-Lombo",
    "gn:country_code":"CD",
    "gn:dem":668,
    "gn:feature_class":"P",
    "gn:feature_code":"PPL",
    "gn:name":"Buabua-Lombo",
    "gn:population":0,
    "gn:timezone":"Africa/Lubumbashi",
    "iso:country":"CD",
    "wof:name":"Buabua-Lombo",
    "wof:placetype":"locality"
},
  "geometry": {"coordinates":[21.38127,-6.42237],"type":"Point"}
}