{
  "type": "Feature",
  "properties": {
    "gn:admin1_code":"11.0",
    "gn:asciiname":"Utu",
    "gn:country_code":"CD",
    "gn:dem":682,
    "gn:feature_class":"P",
    "gn:feature_code":"PPL",
    "gn:name":"Utu",
    "gn:population":0,
    "gn:timezone":"Africa/Lubumbashi",
    "iso:country":"CD",
    "name:und_x_variant":[
        "Uto"
    ],
    "wof:name":"Utu",
    "wof:placetype":"locality"
},
  "geometry": {"coordinates":[27.92275,-1.66551],"type":"Point"}
}