{
  "type": "Feature",
  "properties": {
    "gn:admin1_code":"11.0",
    "gn:asciiname":"Utu",
    "gn:country_code":"CD",
    "gn:dem":682,
    "gn:feature_class":"P",
    "gn:feature_code":"PPL",
    "gn:name":"Utu",
    "gn:population":0,
    "gn:timezone":"Africa/Lubumbashi",
    "iso:country":"CD",
    "name:afr_x_preferred":[
        "Utu"
    ],
    "name:ara_x_preferred":[
        "\u0623\u0648\u062a\u0648"
    ],
    "name:azb_x_preferred":[
        "\u0634\u0627\u0645\u0627\u0634"
    ],
    "name:aze_x_preferred":[
        "Utu"
    ],
    "name:bul_x_preferred":[
        "\u0423\u0442\u0443"
    ],
    "name:ces_x_preferred":[
        "Utu"
    ],
    "name:dan_x_preferred":[
        "Utu"
    ],
    "name:deu_x_preferred":[
        "Utu"
    ],
    "name:ell_x_preferred":[
        "\u039f\u03cd\u03c4\u03bf\u03c5"
    ],
    "name:est_x_preferred":[
        "Utu"
    ],
    "name:fas_x_preferred":[
        "\u0627\u0648\u062a\u0648"
    ],
    "name:fin_x_preferred":[
        "Utu"
    ],
    "name:hrv_x_preferred":[
        "Utu"
    ],
    "name:hun_x_preferred":[
        "Utu"
    ],
    "name:lit_x_preferred":[
        "Utu"
    ],
    "name:nld_x_preferred":[
        "Utu"
    ],
    "name:pol_x_preferred":[
        "Utu"
    ],
    "name:por_x_preferred":[
        "Utu"
    ],
    "name:ron_x_preferred":[
        "Utu"
    ],
    "name:rus_x_preferred":[
        "\u0423\u0442\u0443"
    ],
    "name:slv_x_preferred":[
        "Utu"
    ],
    "name:swe_x_preferred":[
        "Utu"
    ],
    "name:tam_x_preferred":[
        "\u0b89\u0ba4\u0bc1"
    ],
    "name:tur_x_preferred":[
        "Utu"
    ],
    "name:und_x_variant":[
        "Uto"
    ],
    "wof:name":"Utu",
    "wof:placetype":"locality"
},
  "geometry": {"coordinates":[27.92275,-1.66551],"type":"Point"}
}