{
  "type": "Feature",
  "properties": {
    "gn:admin1_code":"22.0",
    "gn:asciiname":"Tshiland",
    "gn:country_code":"CD",
    "gn:dem":946,
    "gn:feature_class":"P",
    "gn:feature_code":"PPL",
    "gn:name":"Tshiland",
    "gn:population":0,
    "gn:timezone":"Africa/Lubumbashi",
    "iso:country":"CD",
    "wof:name":"Tshiland",
    "wof:placetype":"locality"
},
  "geometry": {"coordinates":[23.14845,-8.15664],"type":"Point"}
}