{
  "type": "Feature",
  "properties": {
    "gn:admin1_code":"18.0",
    "gn:asciiname":"Misoko",
    "gn:country_code":"CD",
    "gn:dem":675,
    "gn:feature_class":"P",
    "gn:feature_code":"PPL",
    "gn:name":"Misoko",
    "gn:population":0,
    "gn:timezone":"Africa/Lubumbashi",
    "iso:country":"CD",
    "wof:name":"Misoko",
    "wof:placetype":"locality"
},
  "geometry": {"coordinates":[21.20562,-5.92473],"type":"Point"}
}