{
  "type": "Feature",
  "properties": {
    "gn:admin1_code":"14.0",
    "gn:asciiname":"Kakontoka",
    "gn:country_code":"CD",
    "gn:dem":1052,
    "gn:feature_class":"P",
    "gn:feature_code":"PPL",
    "gn:name":"Kakontoka",
    "gn:population":0,
    "gn:timezone":"Africa/Lubumbashi",
    "iso:country":"CD",
    "wof:name":"Kakontoka",
    "wof:placetype":"locality"
},
  "geometry": {"coordinates":[29.17359,-7.95483],"type":"Point"}
}