{
  "type": "Feature",
  "properties": {
    "gn:admin1_code":"8.0",
    "gn:asciiname":"Zimba",
    "gn:country_code":"CD",
    "gn:dem":425,
    "gn:feature_class":"P",
    "gn:feature_code":"PPL",
    "gn:name":"Zimba",
    "gn:population":0,
    "gn:timezone":"Africa/Kinshasa",
    "iso:country":"CD",
    "name:ceb_x_preferred":[
        "Zimba"
    ],
    "name:deu_x_preferred":[
        "Zimba"
    ],
    "name:fra_x_preferred":[
        "Zimba"
    ],
    "name:swe_x_preferred":[
        "Zimba"
    ],
    "wof:name":"Zimba",
    "wof:placetype":"locality"
},
  "geometry": {"coordinates":[14.34457,-4.8328],"type":"Point"}
}