{
  "type": "Feature",
  "properties": {
    "gn:admin1_code":"15.0",
    "gn:asciiname":"Kalonda",
    "gn:country_code":"CD",
    "gn:dem":978,
    "gn:feature_class":"P",
    "gn:feature_code":"PPL",
    "gn:name":"Kalonda",
    "gn:population":0,
    "gn:timezone":"Africa/Lubumbashi",
    "iso:country":"CD",
    "name:cat_x_preferred":[
        "Kalonda"
    ],
    "name:epo_x_preferred":[
        "Kalonda"
    ],
    "name:eus_x_preferred":[
        "Kalonda"
    ],
    "name:fra_x_preferred":[
        "Kalonda"
    ],
    "name:hun_x_preferred":[
        "Kalonda"
    ],
    "name:ita_x_preferred":[
        "Kalonda"
    ],
    "name:msa_x_preferred":[
        "Kalonda"
    ],
    "name:nld_x_preferred":[
        "Kalonda"
    ],
    "name:pol_x_preferred":[
        "Kalonda"
    ],
    "name:ron_x_preferred":[
        "Kalonda"
    ],
    "name:slk_x_preferred":[
        "Kalonda"
    ],
    "name:spa_x_preferred":[
        "Kalonda"
    ],
    "name:srp_x_preferred":[
        "\u041a\u0430\u043b\u043e\u043d\u0434\u0430"
    ],
    "name:ukr_x_preferred":[
        "\u041a\u0430\u043b\u043e\u043d\u0434\u0430"
    ],
    "name:war_x_preferred":[
        "Kalonda"
    ],
    "wof:name":"Kalonda",
    "wof:placetype":"locality"
},
  "geometry": {"coordinates":[24.25332,-8.15375],"type":"Point"}
}