{
  "type": "Feature",
  "properties": {
    "gn:admin1_code":"15.0",
    "gn:asciiname":"Kalonda",
    "gn:country_code":"CD",
    "gn:dem":978,
    "gn:feature_class":"P",
    "gn:feature_code":"PPL",
    "gn:name":"Kalonda",
    "gn:population":0,
    "gn:timezone":"Africa/Lubumbashi",
    "iso:country":"CD",
    "wof:name":"Kalonda",
    "wof:placetype":"locality"
},
  "geometry": {"coordinates":[24.25332,-8.15375],"type":"Point"}
}