{
  "type": "Feature",
  "properties": {
    "gn:admin1_code":"18.0",
    "gn:asciiname":"Konko",
    "gn:country_code":"CD",
    "gn:dem":606,
    "gn:feature_class":"P",
    "gn:feature_code":"PPL",
    "gn:name":"Konko",
    "gn:population":0,
    "gn:timezone":"Africa/Lubumbashi",
    "iso:country":"CD",
    "wof:name":"Konko",
    "wof:placetype":"locality"
},
  "geometry": {"coordinates":[21.02057000000001,-6.61766],"type":"Point"}
}