{
  "type": "Feature",
  "properties": {
    "gn:admin1_code":"28.0",
    "gn:asciiname":"Boyawaza-Kogba",
    "gn:country_code":"CD",
    "gn:dem":393,
    "gn:feature_class":"P",
    "gn:feature_code":"PPL",
    "gn:name":"Boyawaza-Kogba",
    "gn:population":0,
    "gn:timezone":"Africa/Kinshasa",
    "iso:country":"CD",
    "wof:name":"Boyawaza-Kogba",
    "wof:placetype":"locality"
},
  "geometry": {"coordinates":[20.04954,3.70114],"type":"Point"}
}