{
  "type": "Feature",
  "properties": {
    "gn:admin1_code":"13.0",
    "gn:asciiname":"Mabodi",
    "gn:country_code":"CD",
    "gn:dem":665,
    "gn:feature_class":"P",
    "gn:feature_code":"PPL",
    "gn:name":"Mabodi",
    "gn:population":0,
    "gn:timezone":"Africa/Lubumbashi",
    "iso:country":"CD",
    "wof:name":"Mabodi",
    "wof:placetype":"locality"
},
  "geometry": {"coordinates":[26.93333,3.16667],"type":"Point"}
}