{
  "type": "Feature",
  "properties": {
    "gn:admin1_code":"23.0",
    "gn:asciiname":"Kananga",
    "gn:country_code":"CD",
    "gn:dem":857,
    "gn:feature_class":"P",
    "gn:feature_code":"PPL",
    "gn:name":"Kananga",
    "gn:population":0,
    "gn:timezone":"Africa/Lubumbashi",
    "iso:country":"CD",
    "name:afr_x_preferred":[
        "Kananga"
    ],
    "name:ara_x_preferred":[
        "\u0643\u0627\u0646\u0627\u0646\u063a\u0627"
    ],
    "name:azb_x_preferred":[
        "\u06a9\u0627\u0646\u0627\u0646\u0642\u0627"
    ],
    "name:bul_x_preferred":[
        "\u041a\u0430\u043d\u0430\u043d\u0433\u0430"
    ],
    "name:ceb_x_preferred":[
        "Kananga"
    ],
    "name:ces_x_preferred":[
        "Kananga"
    ],
    "name:che_x_preferred":[
        "\u041a\u0430\u043d\u0430\u043d\u0433\u0430"
    ],
    "name:dan_x_preferred":[
        "Kananga"
    ],
    "name:deu_x_preferred":[
        "Kananga"
    ],
    "name:epo_x_preferred":[
        "Kananga"
    ],
    "name:est_x_preferred":[
        "Kananga"
    ],
    "name:eus_x_preferred":[
        "Kananga"
    ],
    "name:fas_x_preferred":[
        "\u06a9\u0627\u0646\u0627\u0646\u06af\u0627"
    ],
    "name:fin_x_preferred":[
        "Kananga"
    ],
    "name:fra_x_preferred":[
        "Kananga"
    ],
    "name:hau_x_preferred":[
        "Kananga"
    ],
    "name:hrv_x_preferred":[
        "Kananga"
    ],
    "name:hun_x_preferred":[
        "Kananga"
    ],
    "name:hye_x_preferred":[
        "\u053f\u0561\u0576\u0561\u0576\u0563\u0561"
    ],
    "name:ind_x_preferred":[
        "Kananga"
    ],
    "name:ita_x_preferred":[
        "Kananga"
    ],
    "name:jpn_x_preferred":[
        "\u30ab\u30ca\u30f3\u30ac"
    ],
    "name:kat_x_preferred":[
        "\u10d9\u10d0\u10dc\u10d0\u10dc\u10d2\u10d0"
    ],
    "name:kir_x_preferred":[
        "\u041a\u0430\u043d\u0430\u043d\u0433\u0430"
    ],
    "name:kor_x_preferred":[
        "\uce74\ub0ad\uac00"
    ],
    "name:lin_x_preferred":[
        "Kananga"
    ],
    "name:lit_x_preferred":[
        "Kananga"
    ],
    "name:nld_x_preferred":[
        "Kananga"
    ],
    "name:nor_x_preferred":[
        "Kananga"
    ],
    "name:pol_x_preferred":[
        "Kananga"
    ],
    "name:por_x_preferred":[
        "Kananga"
    ],
    "name:ron_x_preferred":[
        "Kananga"
    ],
    "name:rus_x_preferred":[
        "\u041a\u0430\u043d\u0430\u043d\u0433\u0430"
    ],
    "name:slk_x_preferred":[
        "Kananga"
    ],
    "name:sna_x_preferred":[
        "Kananga"
    ],
    "name:spa_x_preferred":[
        "Kananga"
    ],
    "name:srp_x_preferred":[
        "\u041a\u0430\u043d\u0430\u043d\u0433\u0430"
    ],
    "name:swa_x_preferred":[
        "Kananga"
    ],
    "name:swe_x_preferred":[
        "Kananga"
    ],
    "name:szl_x_preferred":[
        "Kananga"
    ],
    "name:tgl_x_preferred":[
        "Kananga"
    ],
    "name:tur_x_preferred":[
        "Kananga"
    ],
    "name:ukr_x_preferred":[
        "\u041a\u0430\u043d\u0430\u043d\u0433\u0430"
    ],
    "name:urd_x_preferred":[
        "\u06a9\u0627\u0646\u0627\u0646\u06af\u0627"
    ],
    "name:war_x_preferred":[
        "Kananga"
    ],
    "name:xmf_x_preferred":[
        "\u10d9\u10d0\u10dc\u10d0\u10dc\u10d2\u10d0"
    ],
    "name:zho_x_preferred":[
        "\u5361\u5357\u52a0"
    ],
    "wof:name":"Kananga",
    "wof:placetype":"locality"
},
  "geometry": {"coordinates":[22.23469,-6.91998],"type":"Point"}
}