{
  "type": "Feature",
  "properties": {
    "gn:admin1_code":"19.0",
    "gn:asciiname":"Kina-Lundulu",
    "gn:country_code":"CD",
    "gn:dem":523,
    "gn:feature_class":"P",
    "gn:feature_code":"PPL",
    "gn:name":"Kina-Lundulu",
    "gn:population":0,
    "gn:timezone":"Africa/Kinshasa",
    "iso:country":"CD",
    "wof:name":"Kina-Lundulu",
    "wof:placetype":"locality"
},
  "geometry": {"coordinates":[17.59891,-4.32013],"type":"Point"}
}