{
  "type": "Feature",
  "properties": {
    "gn:admin1_code":"12.0",
    "gn:asciiname":"Kalangala",
    "gn:country_code":"CD",
    "gn:dem":2233,
    "gn:feature_class":"P",
    "gn:feature_code":"PPL",
    "gn:name":"Kalangala",
    "gn:population":0,
    "gn:timezone":"Africa/Lubumbashi",
    "iso:country":"CD",
    "name:ceb_x_preferred":[
        "Kalangala"
    ],
    "name:deu_x_preferred":[
        "Kalangala"
    ],
    "name:fra_x_preferred":[
        "Kalangala"
    ],
    "name:ita_x_preferred":[
        "Kalangala"
    ],
    "name:jpn_x_preferred":[
        "\u30ab\u30e9\u30f3\u30ac\u30e9"
    ],
    "name:lit_x_preferred":[
        "Kalangala"
    ],
    "name:lug_x_preferred":[
        "Kalangala"
    ],
    "name:nld_x_preferred":[
        "Kalangala"
    ],
    "name:ron_x_preferred":[
        "Kalangala"
    ],
    "name:srp_x_preferred":[
        "\u041a\u0430\u043b\u0430\u043d\u0433\u0430\u043b\u0430"
    ],
    "name:swa_x_preferred":[
        "Kalangala"
    ],
    "name:urd_x_preferred":[
        "\u06a9\u0627\u0644\u0627\u06af\u0627\u0644\u0627"
    ],
    "wof:name":"Kalangala",
    "wof:placetype":"locality"
},
  "geometry": {"coordinates":[28.92676,-1.9086],"type":"Point"}
}