{
  "type": "Feature",
  "properties": {
    "gn:admin1_code":"12.0",
    "gn:asciiname":"Kalangala",
    "gn:country_code":"CD",
    "gn:dem":2233,
    "gn:feature_class":"P",
    "gn:feature_code":"PPL",
    "gn:name":"Kalangala",
    "gn:population":0,
    "gn:timezone":"Africa/Lubumbashi",
    "iso:country":"CD",
    "wof:name":"Kalangala",
    "wof:placetype":"locality"
},
  "geometry": {"coordinates":[28.92676,-1.9086],"type":"Point"}
}