{
  "type": "Feature",
  "properties": {
    "gn:admin1_code":"24.0",
    "gn:asciiname":"Ekoli",
    "gn:country_code":"CD",
    "gn:dem":371,
    "gn:feature_class":"P",
    "gn:feature_code":"PPL",
    "gn:name":"Ekoli",
    "gn:population":0,
    "gn:timezone":"Africa/Kinshasa",
    "iso:country":"CD",
    "wof:name":"Ekoli",
    "wof:placetype":"locality"
},
  "geometry": {"coordinates":[16.89728,-2.28694],"type":"Point"}
}