{
  "type": "Feature",
  "properties": {
    "gn:admin1_code":"30.0",
    "gn:asciiname":"Bobenga",
    "gn:country_code":"CD",
    "gn:dem":457,
    "gn:feature_class":"P",
    "gn:feature_code":"PPL",
    "gn:name":"Bobenga",
    "gn:population":0,
    "gn:timezone":"Africa/Lubumbashi",
    "iso:country":"CD",
    "wof:name":"Bobenga",
    "wof:placetype":"locality"
},
  "geometry": {"coordinates":[25.56097,1.67153],"type":"Point"}
}