{
  "type": "Feature",
  "properties": {
    "gn:admin1_code":"20.0",
    "gn:asciiname":"Meya-Mungwa",
    "gn:country_code":"CD",
    "gn:dem":749,
    "gn:feature_class":"P",
    "gn:feature_code":"PPL",
    "gn:name":"Meya-Mungwa",
    "gn:population":0,
    "gn:timezone":"Africa/Kinshasa",
    "iso:country":"CD",
    "wof:name":"Meya-Mungwa",
    "wof:placetype":"locality"
},
  "geometry": {"coordinates":[19.35197,-5.77949],"type":"Point"}
}