{
  "type": "Feature",
  "properties": {
    "gn:admin1_code":"28.0",
    "gn:asciiname":"Bominenge",
    "gn:country_code":"CD",
    "gn:dem":432,
    "gn:feature_class":"P",
    "gn:feature_code":"PPL",
    "gn:name":"Bominenge",
    "gn:population":0,
    "gn:timezone":"Africa/Kinshasa",
    "iso:country":"CD",
    "name:fra_x_preferred":[
        "Bominenge"
    ],
    "wof:name":"Bominenge",
    "wof:placetype":"locality"
},
  "geometry": {"coordinates":[19.33831,2.96384],"type":"Point"}
}