{
  "type": "Feature",
  "properties": {
    "gn:admin1_code":"20.0",
    "gn:asciiname":"Lukengo",
    "gn:country_code":"CD",
    "gn:dem":733,
    "gn:feature_class":"P",
    "gn:feature_code":"PPL",
    "gn:name":"Lukengo",
    "gn:population":0,
    "gn:timezone":"Africa/Kinshasa",
    "iso:country":"CD",
    "wof:name":"Lukengo",
    "wof:placetype":"locality"
},
  "geometry": {"coordinates":[17.91007,-5.44485],"type":"Point"}
}