{
  "type": "Feature",
  "properties": {
    "gn:admin1_code":"25.0",
    "gn:asciiname":"Bopoto",
    "gn:country_code":"CD",
    "gn:dem":356,
    "gn:feature_class":"P",
    "gn:feature_code":"PPL",
    "gn:name":"Bopoto",
    "gn:population":0,
    "gn:timezone":"Africa/Kinshasa",
    "iso:country":"CD",
    "wof:name":"Bopoto",
    "wof:placetype":"locality"
},
  "geometry": {"coordinates":[22.50072,2.16984],"type":"Point"}
}