{
  "type": "Feature",
  "properties": {
    "gn:admin1_code":"26.0",
    "gn:asciiname":"Vamburu",
    "gn:country_code":"CD",
    "gn:dem":417,
    "gn:feature_class":"P",
    "gn:feature_code":"PPL",
    "gn:name":"Vamburu",
    "gn:population":0,
    "gn:timezone":"Africa/Kinshasa",
    "iso:country":"CD",
    "name:und_x_variant":[
        "Vomburu",
        "Vamburu"
    ],
    "wof:name":"Vamburu",
    "wof:placetype":"locality"
},
  "geometry": {"coordinates":[22.52335,3.97906],"type":"Point"}
}