{
  "type": "Feature",
  "properties": {
    "gn:admin1_code":"22.0",
    "gn:asciiname":"Samufuka",
    "gn:country_code":"CD",
    "gn:dem":1081,
    "gn:feature_class":"P",
    "gn:feature_code":"PPL",
    "gn:name":"Samufuka",
    "gn:population":0,
    "gn:timezone":"Africa/Lubumbashi",
    "iso:country":"CD",
    "wof:name":"Samufuka",
    "wof:placetype":"locality"
},
  "geometry": {"coordinates":[23.39312,-9.4472],"type":"Point"}
}