{
  "type": "Feature",
  "properties": {
    "gn:admin1_code":"22.0",
    "gn:asciiname":"Ndumba",
    "gn:country_code":"CD",
    "gn:dem":1034,
    "gn:feature_class":"P",
    "gn:feature_code":"PPL",
    "gn:name":"Ndumba",
    "gn:population":0,
    "gn:timezone":"Africa/Lubumbashi",
    "iso:country":"CD",
    "name:und_x_variant":[
        "Dumba"
    ],
    "wof:name":"Ndumba",
    "wof:placetype":"locality"
},
  "geometry": {"coordinates":[22.35055,-10.71362],"type":"Point"}
}