{
  "type": "Feature",
  "properties": {
    "gn:admin1_code":"22.0",
    "gn:asciiname":"Mula",
    "gn:country_code":"CD",
    "gn:dem":929,
    "gn:feature_class":"P",
    "gn:feature_code":"PPL",
    "gn:name":"Mula",
    "gn:population":0,
    "gn:timezone":"Africa/Lubumbashi",
    "iso:country":"CD",
    "name:ara_x_preferred":[
        "\u0645\u0648\u0644\u0629"
    ],
    "name:arg_x_preferred":[
        "Mula"
    ],
    "name:cat_x_preferred":[
        "Mula"
    ],
    "name:ceb_x_preferred":[
        "Mula"
    ],
    "name:deu_x_preferred":[
        "Mula"
    ],
    "name:fra_x_preferred":[
        "Mula"
    ],
    "name:ita_x_preferred":[
        "Mula"
    ],
    "name:nds_x_preferred":[
        "Mula"
    ],
    "name:por_x_preferred":[
        "Mula"
    ],
    "name:spa_x_preferred":[
        "Mula"
    ],
    "name:swe_x_preferred":[
        "Mula"
    ],
    "name:tur_x_preferred":[
        "Mula"
    ],
    "wof:name":"Mula",
    "wof:placetype":"locality"
},
  "geometry": {"coordinates":[22.26197,-7.96948],"type":"Point"}
}