{
  "type": "Feature",
  "properties": {
    "gn:admin1_code":"22.0",
    "gn:asciiname":"Mula",
    "gn:country_code":"CD",
    "gn:dem":929,
    "gn:feature_class":"P",
    "gn:feature_code":"PPL",
    "gn:name":"Mula",
    "gn:population":0,
    "gn:timezone":"Africa/Lubumbashi",
    "iso:country":"CD",
    "wof:name":"Mula",
    "wof:placetype":"locality"
},
  "geometry": {"coordinates":[22.26197,-7.96948],"type":"Point"}
}