{
  "type": "Feature",
  "properties": {
    "gn:admin1_code":"29.0",
    "gn:asciiname":"Kilambi",
    "gn:country_code":"CD",
    "gn:dem":671,
    "gn:feature_class":"P",
    "gn:feature_code":"PPL",
    "gn:name":"Kilambi",
    "gn:population":0,
    "gn:timezone":"Africa/Lubumbashi",
    "iso:country":"CD",
    "wof:name":"Kilambi",
    "wof:placetype":"locality"
},
  "geometry": {"coordinates":[26.34309,-6.48037],"type":"Point"}
}