{
  "type": "Feature",
  "properties": {
    "gn:admin1_code":"23.0",
    "gn:asciiname":"Bao",
    "gn:country_code":"CD",
    "gn:dem":895,
    "gn:feature_class":"P",
    "gn:feature_code":"PPL",
    "gn:name":"Bao",
    "gn:population":0,
    "gn:timezone":"Africa/Lubumbashi",
    "iso:country":"CD",
    "wof:name":"Bao",
    "wof:placetype":"locality"
},
  "geometry": {"coordinates":[22.05201,-7.28073],"type":"Point"}
}