{
  "type": "Feature",
  "properties": {
    "gn:admin1_code":"12.0",
    "gn:asciiname":"Kabilongo",
    "gn:country_code":"CD",
    "gn:dem":629,
    "gn:feature_class":"P",
    "gn:feature_code":"PPL",
    "gn:name":"Kabilongo",
    "gn:population":0,
    "gn:timezone":"Africa/Lubumbashi",
    "iso:country":"CD",
    "wof:name":"Kabilongo",
    "wof:placetype":"locality"
},
  "geometry": {"coordinates":[28.03185,-3.38286],"type":"Point"}
}