{
  "type": "Feature",
  "properties": {
    "gn:admin1_code":"24.0",
    "gn:asciiname":"Boteke",
    "gn:country_code":"CD",
    "gn:dem":446,
    "gn:feature_class":"P",
    "gn:feature_code":"PPL",
    "gn:name":"Boteke",
    "gn:population":0,
    "gn:timezone":"Africa/Kinshasa",
    "iso:country":"CD",
    "wof:name":"Boteke",
    "wof:placetype":"locality"
},
  "geometry": {"coordinates":[20.41928,-4.21071],"type":"Point"}
}