{
  "type": "Feature",
  "properties": {
    "gn:admin1_code":"11.0",
    "gn:asciiname":"Bunyuka",
    "gn:country_code":"CD",
    "gn:dem":1873,
    "gn:feature_class":"P",
    "gn:feature_code":"PPL",
    "gn:name":"Bunyuka",
    "gn:population":0,
    "gn:timezone":"Africa/Lubumbashi",
    "iso:country":"CD",
    "wof:name":"Bunyuka",
    "wof:placetype":"locality"
},
  "geometry": {"coordinates":[29.36665,0.14268],"type":"Point"}
}