{
  "type": "Feature",
  "properties": {
    "gn:admin1_code":"21.0",
    "gn:asciiname":"Bao-Kakese",
    "gn:country_code":"CD",
    "gn:dem":753,
    "gn:feature_class":"P",
    "gn:feature_code":"PPL",
    "gn:name":"Bao-Kakese",
    "gn:population":0,
    "gn:timezone":"Africa/Lubumbashi",
    "iso:country":"CD",
    "wof:name":"Bao-Kakese",
    "wof:placetype":"locality"
},
  "geometry": {"coordinates":[24.29684,-6.93712],"type":"Point"}
}