{
  "type": "Feature",
  "properties": {
    "gn:admin1_code":"13.0",
    "gn:asciiname":"Pitamona",
    "gn:country_code":"CD",
    "gn:dem":683,
    "gn:feature_class":"P",
    "gn:feature_code":"PPL",
    "gn:name":"Pitamona",
    "gn:population":0,
    "gn:timezone":"Africa/Lubumbashi",
    "iso:country":"CD",
    "wof:name":"Pitamona",
    "wof:placetype":"locality"
},
  "geometry": {"coordinates":[27.16819000000001,3.30029],"type":"Point"}
}