{
  "type": "Feature",
  "properties": {
    "gn:admin1_code":"18.0",
    "gn:asciiname":"Dibwe",
    "gn:country_code":"CD",
    "gn:dem":627,
    "gn:feature_class":"P",
    "gn:feature_code":"PPL",
    "gn:name":"Dibwe",
    "gn:population":0,
    "gn:timezone":"Africa/Lubumbashi",
    "iso:country":"CD",
    "wof:name":"Dibwe",
    "wof:placetype":"locality"
},
  "geometry": {"coordinates":[21.29023,-5.84806],"type":"Point"}
}