{
  "type": "Feature",
  "properties": {
    "gn:admin1_code":"2.0",
    "gn:asciiname":"Nkeke",
    "gn:country_code":"CD",
    "gn:dem":306,
    "gn:feature_class":"P",
    "gn:feature_code":"PPL",
    "gn:name":"Nkeke",
    "gn:population":0,
    "gn:timezone":"Africa/Kinshasa",
    "iso:country":"CD",
    "name:und_x_variant":[
        "Nkake",
        "Nkeke"
    ],
    "wof:name":"Nkeke",
    "wof:placetype":"locality"
},
  "geometry": {"coordinates":[18.08333,-0.56667],"type":"Point"}
}