{
  "type": "Feature",
  "properties": {
    "gn:admin1_code":"13.0",
    "gn:asciiname":"Bangba",
    "gn:country_code":"CD",
    "gn:dem":545,
    "gn:feature_class":"P",
    "gn:feature_code":"PPL",
    "gn:name":"Bangba",
    "gn:population":0,
    "gn:timezone":"Africa/Lubumbashi",
    "iso:country":"CD",
    "wof:name":"Bangba",
    "wof:placetype":"locality"
},
  "geometry": {"coordinates":[22.79906,4.52499],"type":"Point"}
}