{
  "type": "Feature",
  "properties": {
    "gn:admin1_code":"19.0",
    "gn:asciiname":"Baringa-Gashi",
    "gn:country_code":"CD",
    "gn:dem":600,
    "gn:feature_class":"P",
    "gn:feature_code":"PPL",
    "gn:name":"Baringa-Gashi",
    "gn:population":0,
    "gn:timezone":"Africa/Kinshasa",
    "iso:country":"CD",
    "name:und_x_variant":[
        "Baringa",
        "Baringa-Gashi"
    ],
    "wof:name":"Baringa-Gashi",
    "wof:placetype":"locality"
},
  "geometry": {"coordinates":[16.75642,-4.4311],"type":"Point"}
}