{
  "type": "Feature",
  "properties": {
    "gn:admin1_code":"21.0",
    "gn:asciiname":"Lukunka",
    "gn:country_code":"CD",
    "gn:dem":630,
    "gn:feature_class":"P",
    "gn:feature_code":"PPL",
    "gn:name":"Lukunka",
    "gn:population":0,
    "gn:timezone":"Africa/Lubumbashi",
    "iso:country":"CD",
    "wof:name":"Lukunka",
    "wof:placetype":"locality"
},
  "geometry": {"coordinates":[24.04594,-5.84608],"type":"Point"}
}