{
  "type": "Feature",
  "properties": {
    "gn:admin1_code":"16.0",
    "gn:asciiname":"Boyote",
    "gn:country_code":"CD",
    "gn:dem":814,
    "gn:feature_class":"P",
    "gn:feature_code":"PPL",
    "gn:name":"Boyote",
    "gn:population":0,
    "gn:timezone":"Africa/Lubumbashi",
    "iso:country":"CD",
    "wof:name":"Boyote",
    "wof:placetype":"locality"
},
  "geometry": {"coordinates":[28.37724,3.09988],"type":"Point"}
}