{
  "type": "Feature",
  "properties": {
    "gn:admin1_code":"23.0",
    "gn:asciiname":"Mulumba-Fwamba",
    "gn:country_code":"CD",
    "gn:dem":746,
    "gn:feature_class":"P",
    "gn:feature_code":"PPL",
    "gn:name":"Mulumba-Fwamba",
    "gn:population":0,
    "gn:timezone":"Africa/Lubumbashi",
    "iso:country":"CD",
    "wof:name":"Mulumba-Fwamba",
    "wof:placetype":"locality"
},
  "geometry": {"coordinates":[22.29341,-6.14774],"type":"Point"}
}