{
  "type": "Feature",
  "properties": {
    "gn:admin1_code":"20.0",
    "gn:asciiname":"Kayenku",
    "gn:country_code":"CD",
    "gn:dem":393,
    "gn:feature_class":"P",
    "gn:feature_code":"PPL",
    "gn:name":"Kayenku",
    "gn:population":0,
    "gn:timezone":"Africa/Kinshasa",
    "iso:country":"CD",
    "wof:name":"Kayenku",
    "wof:placetype":"locality"
},
  "geometry": {"coordinates":[17.9049,-4.08576],"type":"Point"}
}