{
  "type": "Feature",
  "properties": {
    "gn:admin1_code":"14.0",
    "gn:asciiname":"Mususwa",
    "gn:country_code":"CD",
    "gn:dem":1220,
    "gn:feature_class":"P",
    "gn:feature_code":"PPL",
    "gn:name":"Mususwa",
    "gn:population":0,
    "gn:timezone":"Africa/Lubumbashi",
    "iso:country":"CD",
    "wof:name":"Mususwa",
    "wof:placetype":"locality"
},
  "geometry": {"coordinates":[27.62435,-11.5173],"type":"Point"}
}