{
  "type": "Feature",
  "properties": {
    "gn:admin1_code":"22.0",
    "gn:asciiname":"Mission Kimbanguiste",
    "gn:country_code":"CD",
    "gn:dem":1040,
    "gn:feature_class":"P",
    "gn:feature_code":"PPL",
    "gn:name":"Mission Kimbanguiste",
    "gn:population":0,
    "gn:timezone":"Africa/Lubumbashi",
    "iso:country":"CD",
    "wof:name":"Mission Kimbanguiste",
    "wof:placetype":"locality"
},
  "geometry": {"coordinates":[22.97571,-9.63773],"type":"Point"}
}