{
  "type": "Feature",
  "properties": {
    "gn:admin1_code":"26.0",
    "gn:asciiname":"Dayo-Bodo",
    "gn:country_code":"CD",
    "gn:dem":406,
    "gn:feature_class":"P",
    "gn:feature_code":"PPL",
    "gn:name":"Dayo-Bodo",
    "gn:population":0,
    "gn:timezone":"Africa/Kinshasa",
    "iso:country":"CD",
    "wof:name":"Dayo-Bodo",
    "wof:placetype":"locality"
},
  "geometry": {"coordinates":[22.42714,4.11281],"type":"Point"}
}