{
  "type": "Feature",
  "properties": {
    "gn:admin1_code":"23.0",
    "gn:asciiname":"Kazea",
    "gn:country_code":"CD",
    "gn:dem":901,
    "gn:feature_class":"P",
    "gn:feature_code":"PPL",
    "gn:name":"Kazea",
    "gn:population":0,
    "gn:timezone":"Africa/Lubumbashi",
    "iso:country":"CD",
    "wof:name":"Kazea",
    "wof:placetype":"locality"
},
  "geometry": {"coordinates":[22.45416,-7.39676],"type":"Point"}
}