{
  "type": "Feature",
  "properties": {
    "gn:admin1_code":"23.0",
    "gn:asciiname":"Ngandu-a-Lusamba",
    "gn:country_code":"CD",
    "gn:dem":543,
    "gn:feature_class":"P",
    "gn:feature_code":"PPL",
    "gn:name":"Ngandu-a-Lusamba",
    "gn:population":0,
    "gn:timezone":"Africa/Lubumbashi",
    "iso:country":"CD",
    "wof:name":"Ngandu-a-Lusamba",
    "wof:placetype":"locality"
},
  "geometry": {"coordinates":[23.34405,-5.63136],"type":"Point"}
}