{
  "type": "Feature",
  "properties": {
    "gn:admin1_code":"18.0",
    "gn:asciiname":"Kanianga",
    "gn:country_code":"CD",
    "gn:dem":731,
    "gn:feature_class":"P",
    "gn:feature_code":"PPL",
    "gn:name":"Kanianga",
    "gn:population":0,
    "gn:timezone":"Africa/Lubumbashi",
    "iso:country":"CD",
    "wof:name":"Kanianga",
    "wof:placetype":"locality"
},
  "geometry": {"coordinates":[20.22918,-6.45283],"type":"Point"}
}