{
  "type": "Feature",
  "properties": {
    "gn:admin1_code":"19.0",
    "gn:asciiname":"Shamwimba",
    "gn:country_code":"CD",
    "gn:dem":1086,
    "gn:feature_class":"P",
    "gn:feature_code":"PPL",
    "gn:name":"Shamwimba",
    "gn:population":0,
    "gn:timezone":"Africa/Kinshasa",
    "iso:country":"CD",
    "wof:name":"Shamwimba",
    "wof:placetype":"locality"
},
  "geometry": {"coordinates":[18.6289,-7.33376],"type":"Point"}
}