{
  "type": "Feature",
  "properties": {
    "gn:admin1_code":"25.0",
    "gn:asciiname":"Yamolima",
    "gn:country_code":"CD",
    "gn:dem":382,
    "gn:feature_class":"P",
    "gn:feature_code":"PPL",
    "gn:name":"Yamolima",
    "gn:population":0,
    "gn:timezone":"Africa/Kinshasa",
    "iso:country":"CD",
    "wof:name":"Yamolima",
    "wof:placetype":"locality"
},
  "geometry": {"coordinates":[22.8979,2.21267],"type":"Point"}
}