{
  "type": "Feature",
  "properties": {
    "gn:admin1_code":"22.0",
    "gn:asciiname":"Kajika",
    "gn:country_code":"CD",
    "gn:dem":1088,
    "gn:feature_class":"P",
    "gn:feature_code":"PPL",
    "gn:name":"Kajika",
    "gn:population":0,
    "gn:timezone":"Africa/Lubumbashi",
    "iso:country":"CD",
    "name:deu_x_preferred":[
        "Kajika"
    ],
    "name:fra_x_preferred":[
        "Kajika"
    ],
    "name:ita_x_preferred":[
        "Kajika"
    ],
    "name:jpn_x_preferred":[
        "\u30ab\u30b8\u30ab"
    ],
    "name:spa_x_preferred":[
        "Kajika"
    ],
    "name:swe_x_preferred":[
        "Kajika"
    ],
    "wof:name":"Kajika",
    "wof:placetype":"locality"
},
  "geometry": {"coordinates":[24.04333,-10.06295],"type":"Point"}
}