{
  "type": "Feature",
  "properties": {
    "gn:admin1_code":"21.0",
    "gn:asciiname":"Mifula",
    "gn:country_code":"CD",
    "gn:dem":694,
    "gn:feature_class":"P",
    "gn:feature_code":"PPL",
    "gn:name":"Mifula",
    "gn:population":0,
    "gn:timezone":"Africa/Lubumbashi",
    "iso:country":"CD",
    "wof:name":"Mifula",
    "wof:placetype":"locality"
},
  "geometry": {"coordinates":[25.82861,-5.49318],"type":"Point"}
}