{
  "type": "Feature",
  "properties": {
    "gn:admin1_code":"25.0",
    "gn:asciiname":"Yalikombi",
    "gn:country_code":"CD",
    "gn:dem":436,
    "gn:feature_class":"P",
    "gn:feature_code":"PPL",
    "gn:name":"Yalikombi",
    "gn:population":0,
    "gn:timezone":"Africa/Kinshasa",
    "iso:country":"CD",
    "wof:name":"Yalikombi",
    "wof:placetype":"locality"
},
  "geometry": {"coordinates":[22.08926,2.78209],"type":"Point"}
}