{
  "type": "Feature",
  "properties": {
    "gn:admin1_code":"22.0",
    "gn:asciiname":"Sumbulia",
    "gn:country_code":"CD",
    "gn:dem":1066,
    "gn:feature_class":"P",
    "gn:feature_code":"PPL",
    "gn:name":"Sumbulia",
    "gn:population":0,
    "gn:timezone":"Africa/Lubumbashi",
    "iso:country":"CD",
    "wof:name":"Sumbulia",
    "wof:placetype":"locality"
},
  "geometry": {"coordinates":[22.21327,-9.85351],"type":"Point"}
}