{
  "type": "Feature",
  "properties": {
    "gn:admin1_code":"17.0",
    "gn:asciiname":"Matukulu",
    "gn:country_code":"CD",
    "gn:dem":902,
    "gn:feature_class":"P",
    "gn:feature_code":"PPL",
    "gn:name":"Matukulu",
    "gn:population":0,
    "gn:timezone":"Africa/Lubumbashi",
    "iso:country":"CD",
    "name:fra_x_preferred":[
        "Matukulu"
    ],
    "wof:name":"Matukulu",
    "wof:placetype":"locality"
},
  "geometry": {"coordinates":[29.28326,1.36838],"type":"Point"}
}