{
  "type": "Feature",
  "properties": {
    "gn:admin1_code":"16.0",
    "gn:asciiname":"Anapuno",
    "gn:country_code":"CD",
    "gn:dem":765,
    "gn:feature_class":"P",
    "gn:feature_code":"PPL",
    "gn:name":"Anapuno",
    "gn:population":0,
    "gn:timezone":"Africa/Lubumbashi",
    "iso:country":"CD",
    "wof:name":"Anapuno",
    "wof:placetype":"locality"
},
  "geometry": {"coordinates":[27.72296,2.3387],"type":"Point"}
}