{
  "type": "Feature",
  "properties": {
    "gn:admin1_code":"23.0",
    "gn:asciiname":"Kamai",
    "gn:country_code":"CD",
    "gn:dem":869,
    "gn:feature_class":"P",
    "gn:feature_code":"PPL",
    "gn:name":"Kamai",
    "gn:population":0,
    "gn:timezone":"Africa/Lubumbashi",
    "iso:country":"CD",
    "name:ceb_x_preferred":[
        "Kamai"
    ],
    "name:swe_x_preferred":[
        "Kamai"
    ],
    "wof:name":"Kamai",
    "wof:placetype":"locality"
},
  "geometry": {"coordinates":[22.43357,-7.1816],"type":"Point"}
}