{
  "type": "Feature",
  "properties": {
    "gn:admin1_code":"13.0",
    "gn:asciiname":"Dabu",
    "gn:country_code":"CD",
    "gn:dem":619,
    "gn:feature_class":"P",
    "gn:feature_code":"PPL",
    "gn:name":"Dabu",
    "gn:population":0,
    "gn:timezone":"Africa/Lubumbashi",
    "iso:country":"CD",
    "name:ceb_x_preferred":[
        "Dabu"
    ],
    "name:deu_x_preferred":[
        "Dabu"
    ],
    "name:fra_x_preferred":[
        "Dabu"
    ],
    "name:ita_x_preferred":[
        "Dabu"
    ],
    "wof:name":"Dabu",
    "wof:placetype":"locality"
},
  "geometry": {"coordinates":[25.94522000000001,2.83283],"type":"Point"}
}