{
  "type": "Feature",
  "properties": {
    "gn:admin1_code":"10.0",
    "gn:asciiname":"Pene-Mangala",
    "gn:country_code":"CD",
    "gn:dem":746,
    "gn:feature_class":"P",
    "gn:feature_code":"PPL",
    "gn:name":"Pene-Mangala",
    "gn:population":0,
    "gn:timezone":"Africa/Lubumbashi",
    "iso:country":"CD",
    "name:und_x_variant":[
        "Mangala",
        "Pene-Mangala"
    ],
    "wof:name":"Pene-Mangala",
    "wof:placetype":"locality"
},
  "geometry": {"coordinates":[26.8203,-4.42804],"type":"Point"}
}