{
  "type": "Feature",
  "properties": {
    "gn:admin1_code":"17.0",
    "gn:asciiname":"Bavakitimba",
    "gn:country_code":"CD",
    "gn:dem":673,
    "gn:feature_class":"P",
    "gn:feature_code":"PPL",
    "gn:name":"Bavakitimba",
    "gn:population":0,
    "gn:timezone":"Africa/Lubumbashi",
    "iso:country":"CD",
    "wof:name":"Bavakitimba",
    "wof:placetype":"locality"
},
  "geometry": {"coordinates":[27.96407,1.16863],"type":"Point"}
}