{
  "type": "Feature",
  "properties": {
    "gn:admin1_code":"17.0",
    "gn:asciiname":"Kasenye",
    "gn:country_code":"CD",
    "gn:dem":635,
    "gn:feature_class":"P",
    "gn:feature_code":"PPL",
    "gn:name":"Kasenye",
    "gn:population":0,
    "gn:timezone":"Africa/Lubumbashi",
    "iso:country":"CD",
    "name:und_x_variant":[
        "Keseny",
        "Kasenyi",
        "Kiseny",
        "Kasenye"
    ],
    "wof:name":"Kasenye",
    "wof:placetype":"locality"
},
  "geometry": {"coordinates":[30.44024000000001,1.39197],"type":"Point"}
}