{
  "type": "Feature",
  "properties": {
    "gn:admin1_code":"22.0",
    "gn:asciiname":"Sakatanga",
    "gn:country_code":"CD",
    "gn:dem":1001,
    "gn:feature_class":"P",
    "gn:feature_code":"PPL",
    "gn:name":"Sakatanga",
    "gn:population":0,
    "gn:timezone":"Africa/Lubumbashi",
    "iso:country":"CD",
    "wof:name":"Sakatanga",
    "wof:placetype":"locality"
},
  "geometry": {"coordinates":[23.4778,-9.69087],"type":"Point"}
}