{
  "type": "Feature",
  "properties": {
    "gn:admin1_code":"17.0",
    "gn:asciiname":"Ngombo",
    "gn:country_code":"CD",
    "gn:dem":1214,
    "gn:feature_class":"P",
    "gn:feature_code":"PPL",
    "gn:name":"Ngombo",
    "gn:population":0,
    "gn:timezone":"Africa/Lubumbashi",
    "iso:country":"CD",
    "wof:name":"Ngombo",
    "wof:placetype":"locality"
},
  "geometry": {"coordinates":[30.79751,3.29541],"type":"Point"}
}