{
  "type": "Feature",
  "properties": {
    "gn:admin1_code":"31.0",
    "gn:asciiname":"Lonoli",
    "gn:country_code":"CD",
    "gn:dem":399,
    "gn:feature_class":"P",
    "gn:feature_code":"PPL",
    "gn:name":"Lonoli",
    "gn:population":0,
    "gn:timezone":"Africa/Kinshasa",
    "iso:country":"CD",
    "wof:name":"Lonoli",
    "wof:placetype":"locality"
},
  "geometry": {"coordinates":[21.61306,-0.50673],"type":"Point"}
}