{
  "type": "Feature",
  "properties": {
    "gn:admin1_code":"29.0",
    "gn:asciiname":"Mahole",
    "gn:country_code":"CD",
    "gn:dem":580,
    "gn:feature_class":"P",
    "gn:feature_code":"PPL",
    "gn:name":"Mahole",
    "gn:population":0,
    "gn:timezone":"Africa/Lubumbashi",
    "iso:country":"CD",
    "wof:name":"Mahole",
    "wof:placetype":"locality"
},
  "geometry": {"coordinates":[26.91259,-5.14576],"type":"Point"}
}