{
  "type": "Feature",
  "properties": {
    "gn:admin1_code":"15.0",
    "gn:asciiname":"Mwanza",
    "gn:country_code":"CD",
    "gn:dem":945,
    "gn:feature_class":"P",
    "gn:feature_code":"PPL",
    "gn:name":"Mwanza",
    "gn:population":0,
    "gn:timezone":"Africa/Lubumbashi",
    "iso:country":"CD",
    "wof:name":"Mwanza",
    "wof:placetype":"locality"
},
  "geometry": {"coordinates":[23.96503,-8.67391],"type":"Point"}
}