{
  "type": "Feature",
  "properties": {
    "gn:admin1_code":"15.0",
    "gn:asciiname":"Mwanza",
    "gn:country_code":"CD",
    "gn:dem":945,
    "gn:feature_class":"P",
    "gn:feature_code":"PPL",
    "gn:name":"Mwanza",
    "gn:population":0,
    "gn:timezone":"Africa/Lubumbashi",
    "iso:country":"CD",
    "name:ara_x_preferred":[
        "\u0645\u0648\u0627\u0646\u0632\u0627"
    ],
    "name:azb_x_preferred":[
        "\u0645\u0648\u0627\u0646\u0632\u0627"
    ],
    "name:bel_x_preferred":[
        "\u041c\u0432\u0430\u043d\u0437\u0430"
    ],
    "name:bre_x_preferred":[
        "Mwanza"
    ],
    "name:bul_x_preferred":[
        "\u041c\u0443\u0430\u043d\u0437\u0430"
    ],
    "name:ceb_x_preferred":[
        "Mwanza"
    ],
    "name:ces_x_preferred":[
        "Mwanza"
    ],
    "name:dan_x_preferred":[
        "Mwanza"
    ],
    "name:deu_x_preferred":[
        "Mwanza"
    ],
    "name:epo_x_preferred":[
        "Mwanza"
    ],
    "name:est_x_preferred":[
        "Mwanza"
    ],
    "name:eus_x_preferred":[
        "Mwanza"
    ],
    "name:fas_x_preferred":[
        "\u0645\u0648\u0627\u0646\u0632\u0627"
    ],
    "name:fin_x_preferred":[
        "Mwanza"
    ],
    "name:fra_x_preferred":[
        "Mwanza"
    ],
    "name:fry_x_preferred":[
        "Mwanza"
    ],
    "name:hrv_x_preferred":[
        "Mwanza"
    ],
    "name:hun_x_preferred":[
        "Mwanza"
    ],
    "name:ina_x_preferred":[
        "Mwanza"
    ],
    "name:ind_x_preferred":[
        "Mwanza"
    ],
    "name:ita_x_preferred":[
        "Mwanza"
    ],
    "name:jpn_x_preferred":[
        "\u30e0\u30ef\u30f3\u30b6"
    ],
    "name:kal_x_preferred":[
        "Mwanza"
    ],
    "name:kat_x_preferred":[
        "\u10db\u10d5\u10d0\u10dc\u10d6\u10d0"
    ],
    "name:kir_x_preferred":[
        "\u041c\u0432\u0430\u043d\u0437\u0430"
    ],
    "name:kor_x_preferred":[
        "\ubbc0\uc644\uc790"
    ],
    "name:lit_x_preferred":[
        "Mvanza"
    ],
    "name:mri_x_preferred":[
        "Mwanza"
    ],
    "name:nds_x_preferred":[
        "Mwanza"
    ],
    "name:nld_x_preferred":[
        "Mwanza"
    ],
    "name:nor_x_preferred":[
        "Mwanza"
    ],
    "name:pol_x_preferred":[
        "Mwanza"
    ],
    "name:ron_x_preferred":[
        "Mwanza"
    ],
    "name:rus_x_preferred":[
        "\u041c\u0432\u0430\u043d\u0437\u0430"
    ],
    "name:sco_x_preferred":[
        "Mwanza"
    ],
    "name:spa_x_preferred":[
        "Mwanza"
    ],
    "name:srp_x_preferred":[
        "\u041c\u0432\u0430\u043d\u0437\u0430"
    ],
    "name:swa_x_preferred":[
        "Mwanza"
    ],
    "name:swe_x_preferred":[
        "Mwanza"
    ],
    "name:tha_x_preferred":[
        "\u0e2d\u0e36\u0e21\u0e27\u0e31\u0e19\u0e0b\u0e32"
    ],
    "name:tum_x_preferred":[
        "Mwanza"
    ],
    "name:tur_x_preferred":[
        "Mwanza"
    ],
    "name:ukr_x_preferred":[
        "\u041c\u0432\u0430\u043d\u0437\u0430"
    ],
    "name:urd_x_preferred":[
        "\u0645\u0648\u0627\u0646\u0632\u0627"
    ],
    "name:uzb_x_preferred":[
        "Mvanza"
    ],
    "name:vie_x_preferred":[
        "Mwanza"
    ],
    "name:war_x_preferred":[
        "Mwanza"
    ],
    "name:yor_x_preferred":[
        "Mwanza"
    ],
    "name:zho_x_preferred":[
        "\u59c6\u4e07\u624e"
    ],
    "wof:name":"Mwanza",
    "wof:placetype":"locality"
},
  "geometry": {"coordinates":[23.96503,-8.67391],"type":"Point"}
}