{
  "type": "Feature",
  "properties": {
    "gn:admin1_code":"13.0",
    "gn:asciiname":"Pikisa",
    "gn:country_code":"CD",
    "gn:dem":527,
    "gn:feature_class":"P",
    "gn:feature_code":"PPL",
    "gn:name":"Pikisa",
    "gn:population":0,
    "gn:timezone":"Africa/Lubumbashi",
    "iso:country":"CD",
    "wof:name":"Pikisa",
    "wof:placetype":"locality"
},
  "geometry": {"coordinates":[24.00202,4.43972],"type":"Point"}
}