{
  "type": "Feature",
  "properties": {
    "gn:admin1_code":"18.0",
    "gn:asciiname":"Muakahila",
    "gn:country_code":"CD",
    "gn:dem":691,
    "gn:feature_class":"P",
    "gn:feature_code":"PPL",
    "gn:name":"Muakahila",
    "gn:population":0,
    "gn:timezone":"Africa/Lubumbashi",
    "iso:country":"CD",
    "name:und_x_variant":[
        "Muakahiya"
    ],
    "wof:name":"Muakahila",
    "wof:placetype":"locality"
},
  "geometry": {"coordinates":[20.91015,-7.21339],"type":"Point"}
}