{
  "type": "Feature",
  "properties": {
    "gn:admin1_code":"18.0",
    "gn:asciiname":"Ipoka",
    "gn:country_code":"CD",
    "gn:dem":526,
    "gn:feature_class":"P",
    "gn:feature_code":"PPL",
    "gn:name":"Ipoka",
    "gn:population":0,
    "gn:timezone":"Africa/Lubumbashi",
    "iso:country":"CD",
    "wof:name":"Ipoka",
    "wof:placetype":"locality"
},
  "geometry": {"coordinates":[21.71869,-3.75807],"type":"Point"}
}