{
  "type": "Feature",
  "properties": {
    "gn:admin1_code":"26.0",
    "gn:asciiname":"Wuga",
    "gn:country_code":"CD",
    "gn:dem":461,
    "gn:feature_class":"P",
    "gn:feature_code":"PPL",
    "gn:name":"Wuga",
    "gn:population":0,
    "gn:timezone":"Africa/Kinshasa",
    "iso:country":"CD",
    "wof:name":"Wuga",
    "wof:placetype":"locality"
},
  "geometry": {"coordinates":[19.65335,4.95361],"type":"Point"}
}