{
  "type": "Feature",
  "properties": {
    "gn:admin1_code":"22.0",
    "gn:asciiname":"Musumali",
    "gn:country_code":"CD",
    "gn:dem":1049,
    "gn:feature_class":"P",
    "gn:feature_code":"PPL",
    "gn:name":"Musumali",
    "gn:population":0,
    "gn:timezone":"Africa/Lubumbashi",
    "iso:country":"CD",
    "wof:name":"Musumali",
    "wof:placetype":"locality"
},
  "geometry": {"coordinates":[23.96328,-9.49862],"type":"Point"}
}