{
  "type": "Feature",
  "properties": {
    "gn:admin1_code":"13.0",
    "gn:asciiname":"Lalia",
    "gn:country_code":"CD",
    "gn:dem":690,
    "gn:feature_class":"P",
    "gn:feature_code":"PPL",
    "gn:name":"Lalia",
    "gn:population":0,
    "gn:timezone":"Africa/Lubumbashi",
    "iso:country":"CD",
    "name:ceb_x_preferred":[
        "Lalia"
    ],
    "name:deu_x_preferred":[
        "Lalia"
    ],
    "wof:name":"Lalia",
    "wof:placetype":"locality"
},
  "geometry": {"coordinates":[27.00914,2.98661],"type":"Point"}
}