{
  "type": "Feature",
  "properties": {
    "gn:admin1_code":"24.0",
    "gn:asciiname":"Betenkoi",
    "gn:country_code":"CD",
    "gn:dem":334,
    "gn:feature_class":"P",
    "gn:feature_code":"PPL",
    "gn:name":"Betenkoi",
    "gn:population":0,
    "gn:timezone":"Africa/Kinshasa",
    "iso:country":"CD",
    "wof:name":"Betenkoi",
    "wof:placetype":"locality"
},
  "geometry": {"coordinates":[19.63778,-2.60809],"type":"Point"}
}