{
  "type": "Feature",
  "properties": {
    "gn:admin1_code":"10.0",
    "gn:asciiname":"Lasiri-Gima",
    "gn:country_code":"CD",
    "gn:dem":590,
    "gn:feature_class":"P",
    "gn:feature_code":"PPL",
    "gn:name":"Lasiri-Gima",
    "gn:population":0,
    "gn:timezone":"Africa/Lubumbashi",
    "iso:country":"CD",
    "wof:name":"Lasiri-Gima",
    "wof:placetype":"locality"
},
  "geometry": {"coordinates":[26.9825,-4.4539],"type":"Point"}
}