{
  "type": "Feature",
  "properties": {
    "gn:admin1_code":"12.0",
    "gn:asciiname":"Molongo",
    "gn:country_code":"CD",
    "gn:dem":720,
    "gn:feature_class":"P",
    "gn:feature_code":"PPL",
    "gn:name":"Molongo",
    "gn:population":0,
    "gn:timezone":"Africa/Lubumbashi",
    "iso:country":"CD",
    "wof:name":"Molongo",
    "wof:placetype":"locality"
},
  "geometry": {"coordinates":[27.32227,-3.7341],"type":"Point"}
}