{
  "type": "Feature",
  "properties": {
    "gn:admin1_code":"21.0",
    "gn:asciiname":"Ngoyi",
    "gn:country_code":"CD",
    "gn:dem":892,
    "gn:feature_class":"P",
    "gn:feature_code":"PPL",
    "gn:name":"Ngoyi",
    "gn:population":0,
    "gn:timezone":"Africa/Lubumbashi",
    "iso:country":"CD",
    "wof:name":"Ngoyi",
    "wof:placetype":"locality"
},
  "geometry": {"coordinates":[23.60392,-7.39053],"type":"Point"}
}