{
  "type": "Feature",
  "properties": {
    "gn:admin1_code":"8.0",
    "gn:asciiname":"Kinsongo",
    "gn:country_code":"CD",
    "gn:dem":131,
    "gn:feature_class":"P",
    "gn:feature_code":"PPL",
    "gn:name":"Kinsongo",
    "gn:population":0,
    "gn:timezone":"Africa/Kinshasa",
    "iso:country":"CD",
    "wof:name":"Kinsongo",
    "wof:placetype":"locality"
},
  "geometry": {"coordinates":[12.47778,-5.96227],"type":"Point"}
}