{
  "type": "Feature",
  "properties": {
    "gn:admin1_code":"28.0",
    "gn:asciiname":"Bobei",
    "gn:country_code":"CD",
    "gn:dem":366,
    "gn:feature_class":"P",
    "gn:feature_code":"PPL",
    "gn:name":"Bobei",
    "gn:population":0,
    "gn:timezone":"Africa/Kinshasa",
    "iso:country":"CD",
    "name:und_x_variant":[
        "Bobey",
        "Bobei"
    ],
    "wof:name":"Bobei",
    "wof:placetype":"locality"
},
  "geometry": {"coordinates":[18.85308,2.50803],"type":"Point"}
}