{
  "type": "Feature",
  "properties": {
    "gn:admin1_code":"25.0",
    "gn:asciiname":"Lilongo",
    "gn:country_code":"CD",
    "gn:dem":456,
    "gn:feature_class":"P",
    "gn:feature_code":"PPL",
    "gn:name":"Lilongo",
    "gn:population":0,
    "gn:timezone":"Africa/Kinshasa",
    "iso:country":"CD",
    "wof:name":"Lilongo",
    "wof:placetype":"locality"
},
  "geometry": {"coordinates":[22.5445,2.87581],"type":"Point"}
}