{
  "type": "Feature",
  "properties": {
    "gn:admin1_code":"22.0",
    "gn:asciiname":"Kamuninga",
    "gn:country_code":"CD",
    "gn:dem":1048,
    "gn:feature_class":"P",
    "gn:feature_code":"PPL",
    "gn:name":"Kamuninga",
    "gn:population":0,
    "gn:timezone":"Africa/Lubumbashi",
    "iso:country":"CD",
    "wof:name":"Kamuninga",
    "wof:placetype":"locality"
},
  "geometry": {"coordinates":[23.51557,-10.59073],"type":"Point"}
}