{
  "type": "Feature",
  "properties": {
    "gn:admin1_code":"23.0",
    "gn:asciiname":"Kanda-Nsapo",
    "gn:country_code":"CD",
    "gn:dem":653,
    "gn:feature_class":"P",
    "gn:feature_code":"PPL",
    "gn:name":"Kanda-Nsapo",
    "gn:population":0,
    "gn:timezone":"Africa/Lubumbashi",
    "iso:country":"CD",
    "name:und_x_variant":[
        "Kande-Nsapo"
    ],
    "wof:name":"Kanda-Nsapo",
    "wof:placetype":"locality"
},
  "geometry": {"coordinates":[22.47568,-5.91402],"type":"Point"}
}