{
  "type": "Feature",
  "properties": {
    "gn:admin1_code":"19.0",
    "gn:asciiname":"Shambamvu",
    "gn:country_code":"CD",
    "gn:dem":1058,
    "gn:feature_class":"P",
    "gn:feature_code":"PPL",
    "gn:name":"Shambamvu",
    "gn:population":0,
    "gn:timezone":"Africa/Kinshasa",
    "iso:country":"CD",
    "wof:name":"Shambamvu",
    "wof:placetype":"locality"
},
  "geometry": {"coordinates":[19.03128,-7.43419],"type":"Point"}
}