{
  "type": "Feature",
  "properties": {
    "gn:admin1_code":"11.0",
    "gn:asciiname":"Kasangano",
    "gn:country_code":"CD",
    "gn:dem":652,
    "gn:feature_class":"P",
    "gn:feature_code":"PPL",
    "gn:name":"Kasangano",
    "gn:population":0,
    "gn:timezone":"Africa/Lubumbashi",
    "iso:country":"CD",
    "wof:name":"Kasangano",
    "wof:placetype":"locality"
},
  "geometry": {"coordinates":[27.93553,-1.32616],"type":"Point"}
}