{
  "type": "Feature",
  "properties": {
    "gn:admin1_code":"21.0",
    "gn:asciiname":"Nifula",
    "gn:country_code":"CD",
    "gn:dem":565,
    "gn:feature_class":"P",
    "gn:feature_code":"PPL",
    "gn:name":"Nifula",
    "gn:population":0,
    "gn:timezone":"Africa/Lubumbashi",
    "iso:country":"CD",
    "wof:name":"Nifula",
    "wof:placetype":"locality"
},
  "geometry": {"coordinates":[25.56667,-5.26667],"type":"Point"}
}