{
  "type": "Feature",
  "properties": {
    "gn:admin1_code":"30.0",
    "gn:asciiname":"Yawana",
    "gn:country_code":"CD",
    "gn:dem":370,
    "gn:feature_class":"P",
    "gn:feature_code":"PPL",
    "gn:name":"Yawana",
    "gn:population":0,
    "gn:timezone":"Africa/Lubumbashi",
    "iso:country":"CD",
    "wof:name":"Yawana",
    "wof:placetype":"locality"
},
  "geometry": {"coordinates":[23.01952,1.98958],"type":"Point"}
}