{
  "type": "Feature",
  "properties": {
    "gn:admin1_code":"6.0",
    "gn:asciiname":"Nselekoti",
    "gn:country_code":"CD",
    "gn:dem":377,
    "gn:feature_class":"P",
    "gn:feature_code":"PPL",
    "gn:name":"Nselekoti",
    "gn:population":0,
    "gn:timezone":"Africa/Kinshasa",
    "iso:country":"CD",
    "wof:name":"Nselekoti",
    "wof:placetype":"locality"
},
  "geometry": {"coordinates":[15.68552,-4.2845],"type":"Point"}
}