{
  "type": "Feature",
  "properties": {
    "gn:admin1_code":"12.0",
    "gn:asciiname":"Kakasi",
    "gn:country_code":"CD",
    "gn:dem":783,
    "gn:feature_class":"P",
    "gn:feature_code":"PPL",
    "gn:name":"Kakasi",
    "gn:population":0,
    "gn:timezone":"Africa/Lubumbashi",
    "iso:country":"CD",
    "wof:name":"Kakasi",
    "wof:placetype":"locality"
},
  "geometry": {"coordinates":[29.16472000000001,-4.27833],"type":"Point"}
}