{
  "type": "Feature",
  "properties": {
    "gn:admin1_code":"20.0",
    "gn:asciiname":"Kimpala",
    "gn:country_code":"CD",
    "gn:dem":352,
    "gn:feature_class":"P",
    "gn:feature_code":"PPL",
    "gn:name":"Kimpala",
    "gn:population":0,
    "gn:timezone":"Africa/Kinshasa",
    "iso:country":"CD",
    "wof:name":"Kimpala",
    "wof:placetype":"locality"
},
  "geometry": {"coordinates":[18.64057,-3.64136],"type":"Point"}
}