{
  "type": "Feature",
  "properties": {
    "gn:admin1_code":"23.0",
    "gn:asciiname":"Mponde",
    "gn:country_code":"CD",
    "gn:dem":785,
    "gn:feature_class":"P",
    "gn:feature_code":"PPL",
    "gn:name":"Mponde",
    "gn:population":0,
    "gn:timezone":"Africa/Lubumbashi",
    "iso:country":"CD",
    "wof:name":"Mponde",
    "wof:placetype":"locality"
},
  "geometry": {"coordinates":[22.60081,-7.09448],"type":"Point"}
}