{
  "type": "Feature",
  "properties": {
    "gn:admin1_code":"17.0",
    "gn:asciiname":"Kitanga",
    "gn:country_code":"CD",
    "gn:dem":870,
    "gn:feature_class":"P",
    "gn:feature_code":"PPL",
    "gn:name":"Kitanga",
    "gn:population":0,
    "gn:timezone":"Africa/Lubumbashi",
    "iso:country":"CD",
    "wof:name":"Kitanga",
    "wof:placetype":"locality"
},
  "geometry": {"coordinates":[28.92106,1.38237],"type":"Point"}
}