{
  "type": "Feature",
  "properties": {
    "gn:admin1_code":"30.0",
    "gn:asciiname":"Baduka",
    "gn:country_code":"CD",
    "gn:dem":715,
    "gn:feature_class":"P",
    "gn:feature_code":"PPL",
    "gn:name":"Baduka",
    "gn:population":0,
    "gn:timezone":"Africa/Lubumbashi",
    "iso:country":"CD",
    "wof:name":"Baduka",
    "wof:placetype":"locality"
},
  "geometry": {"coordinates":[27.26667,0.48333],"type":"Point"}
}