{
  "type": "Feature",
  "properties": {
    "gn:admin1_code":"13.0",
    "gn:asciiname":"Linzelinze",
    "gn:country_code":"CD",
    "gn:dem":637,
    "gn:feature_class":"P",
    "gn:feature_code":"PPL",
    "gn:name":"Linzelinze",
    "gn:population":0,
    "gn:timezone":"Africa/Lubumbashi",
    "iso:country":"CD",
    "wof:name":"Linzelinze",
    "wof:placetype":"locality"
},
  "geometry": {"coordinates":[26.36667000000001,3.43333],"type":"Point"}
}