{
  "type": "Feature",
  "properties": {
    "gn:admin1_code":"4.0",
    "gn:asciiname":"Bena-Kasonga",
    "gn:country_code":"CD",
    "gn:dem":794,
    "gn:feature_class":"P",
    "gn:feature_code":"PPL",
    "gn:name":"Bena-Kasonga",
    "gn:population":0,
    "gn:timezone":"Africa/Lubumbashi",
    "iso:country":"CD",
    "wof:name":"Bena-Kasonga",
    "wof:placetype":"locality"
},
  "geometry": {"coordinates":[23.38691,-6.2401],"type":"Point"}
}