{
  "type": "Feature",
  "properties": {
    "gn:admin1_code":"28.0",
    "gn:asciiname":"Vumbo-Kete",
    "gn:country_code":"CD",
    "gn:dem":352,
    "gn:feature_class":"P",
    "gn:feature_code":"PPL",
    "gn:name":"Vumbo-Kete",
    "gn:population":0,
    "gn:timezone":"Africa/Kinshasa",
    "iso:country":"CD",
    "wof:name":"Vumbo-Kete",
    "wof:placetype":"locality"
},
  "geometry": {"coordinates":[19.00978,3.17679],"type":"Point"}
}