{
  "type": "Feature",
  "properties": {
    "gn:admin1_code":"0.0",
    "gn:asciiname":"Lale",
    "gn:country_code":"CD",
    "gn:dem":535,
    "gn:feature_class":"P",
    "gn:feature_code":"PPL",
    "gn:name":"Lale",
    "gn:population":0,
    "gn:timezone":"Africa/Lubumbashi",
    "iso:country":"CD",
    "name:ceb_x_preferred":[
        "Lale"
    ],
    "name:deu_x_preferred":[
        "Lale"
    ],
    "name:fra_x_preferred":[
        "Lale"
    ],
    "name:glg_x_preferred":[
        "Lale"
    ],
    "name:swe_x_preferred":[
        "Lale"
    ],
    "name:tur_x_preferred":[
        "Lale"
    ],
    "wof:name":"Lale",
    "wof:placetype":"locality"
},
  "geometry": {"coordinates":[24.08333,-1.15],"type":"Point"}
}