{
  "type": "Feature",
  "properties": {
    "gn:admin1_code":"18.0",
    "gn:asciiname":"Tshanika",
    "gn:country_code":"CD",
    "gn:dem":707,
    "gn:feature_class":"P",
    "gn:feature_code":"PPL",
    "gn:name":"Tshanika",
    "gn:population":0,
    "gn:timezone":"Africa/Lubumbashi",
    "iso:country":"CD",
    "wof:name":"Tshanika",
    "wof:placetype":"locality"
},
  "geometry": {"coordinates":[21.01957,-7.03405],"type":"Point"}
}