{
  "type": "Feature",
  "properties": {
    "gn:admin1_code":"21.0",
    "gn:asciiname":"Mani",
    "gn:country_code":"CD",
    "gn:dem":849,
    "gn:feature_class":"P",
    "gn:feature_code":"PPL",
    "gn:name":"Mani",
    "gn:population":0,
    "gn:timezone":"Africa/Lubumbashi",
    "iso:country":"CD",
    "name:und_x_variant":[
        "Maniy",
        "Mani"
    ],
    "wof:name":"Mani",
    "wof:placetype":"locality"
},
  "geometry": {"coordinates":[25.30081,-6.48644],"type":"Point"}
}