{
  "type": "Feature",
  "properties": {
    "gn:admin1_code":"20.0",
    "gn:asciiname":"Kikianika-Kapasu",
    "gn:country_code":"CD",
    "gn:dem":880,
    "gn:feature_class":"P",
    "gn:feature_code":"PPL",
    "gn:name":"Kikianika-Kapasu",
    "gn:population":0,
    "gn:timezone":"Africa/Kinshasa",
    "iso:country":"CD",
    "wof:name":"Kikianika-Kapasu",
    "wof:placetype":"locality"
},
  "geometry": {"coordinates":[17.77492,-5.70939],"type":"Point"}
}