{
  "type": "Feature",
  "properties": {
    "gn:admin1_code":"19.0",
    "gn:asciiname":"Nambanza",
    "gn:country_code":"CD",
    "gn:dem":899,
    "gn:feature_class":"P",
    "gn:feature_code":"PPL",
    "gn:name":"Nambanza",
    "gn:population":0,
    "gn:timezone":"Africa/Kinshasa",
    "iso:country":"CD",
    "wof:name":"Nambanza",
    "wof:placetype":"locality"
},
  "geometry": {"coordinates":[18.189,-7.52049],"type":"Point"}
}