{
  "type": "Feature",
  "properties": {
    "gn:admin1_code":"18.0",
    "gn:asciiname":"Muana-Kasua",
    "gn:country_code":"CD",
    "gn:dem":563,
    "gn:feature_class":"P",
    "gn:feature_code":"PPL",
    "gn:name":"Muana-Kasua",
    "gn:population":0,
    "gn:timezone":"Africa/Lubumbashi",
    "iso:country":"CD",
    "wof:name":"Muana-Kasua",
    "wof:placetype":"locality"
},
  "geometry": {"coordinates":[20.73799,-6.15228],"type":"Point"}
}