{
  "type": "Feature",
  "properties": {
    "gn:admin1_code":"8.0",
    "gn:asciiname":"Nzambi",
    "gn:country_code":"CD",
    "gn:dem":371,
    "gn:feature_class":"P",
    "gn:feature_code":"PPL",
    "gn:name":"Nzambi",
    "gn:population":0,
    "gn:timezone":"Africa/Kinshasa",
    "iso:country":"CD",
    "wof:name":"Nzambi",
    "wof:placetype":"locality"
},
  "geometry": {"coordinates":[12.93333,-4.83333],"type":"Point"}
}