{
  "type": "Feature",
  "properties": {
    "gn:admin1_code":"16.0",
    "gn:asciiname":"Andikoi",
    "gn:country_code":"CD",
    "gn:dem":874,
    "gn:feature_class":"P",
    "gn:feature_code":"PPL",
    "gn:name":"Andikoi",
    "gn:population":0,
    "gn:timezone":"Africa/Lubumbashi",
    "iso:country":"CD",
    "wof:name":"Andikoi",
    "wof:placetype":"locality"
},
  "geometry": {"coordinates":[28.75872,2.63056],"type":"Point"}
}