{
  "type": "Feature",
  "properties": {
    "gn:admin1_code":"23.0",
    "gn:asciiname":"Mwene Mwamba",
    "gn:country_code":"CD",
    "gn:dem":946,
    "gn:feature_class":"P",
    "gn:feature_code":"PPL",
    "gn:name":"Mwene Mwamba",
    "gn:population":0,
    "gn:timezone":"Africa/Lubumbashi",
    "iso:country":"CD",
    "wof:name":"Mwene Mwamba",
    "wof:placetype":"locality"
},
  "geometry": {"coordinates":[23.1531,-7.69235],"type":"Point"}
}