{
  "type": "Feature",
  "properties": {
    "gn:admin1_code":"10.0",
    "gn:asciiname":"Musianga",
    "gn:country_code":"CD",
    "gn:dem":563,
    "gn:feature_class":"P",
    "gn:feature_code":"PPL",
    "gn:name":"Musianga",
    "gn:population":0,
    "gn:timezone":"Africa/Lubumbashi",
    "iso:country":"CD",
    "wof:name":"Musianga",
    "wof:placetype":"locality"
},
  "geometry": {"coordinates":[26.51667,-0.51667],"type":"Point"}
}