{
  "type": "Feature",
  "properties": {
    "gn:admin1_code":"27.0",
    "gn:asciiname":"A.V.P. Ndolo",
    "gn:country_code":"CD",
    "gn:dem":570,
    "gn:feature_class":"P",
    "gn:feature_code":"PPL",
    "gn:name":"A.V.P. Ndolo",
    "gn:population":0,
    "gn:timezone":"Africa/Lubumbashi",
    "iso:country":"CD",
    "name:und_x_variant":[
        "Ndolo"
    ],
    "wof:name":"A.V.P. Ndolo",
    "wof:placetype":"locality"
},
  "geometry": {"coordinates":[23.13781,-3.68632],"type":"Point"}
}