{
  "type": "Feature",
  "properties": {
    "gn:admin1_code":"18.0",
    "gn:asciiname":"Malu-Fwamba",
    "gn:country_code":"CD",
    "gn:dem":650,
    "gn:feature_class":"P",
    "gn:feature_code":"PPL",
    "gn:name":"Malu-Fwamba",
    "gn:population":0,
    "gn:timezone":"Africa/Lubumbashi",
    "iso:country":"CD",
    "wof:name":"Malu-Fwamba",
    "wof:placetype":"locality"
},
  "geometry": {"coordinates":[21.30683,-5.84862],"type":"Point"}
}