{
  "type": "Feature",
  "properties": {
    "gn:admin1_code":"20.0",
    "gn:asciiname":"Kisangi",
    "gn:country_code":"CD",
    "gn:dem":754,
    "gn:feature_class":"P",
    "gn:feature_code":"PPL",
    "gn:name":"Kisangi",
    "gn:population":0,
    "gn:timezone":"Africa/Kinshasa",
    "iso:country":"CD",
    "name:und_x_variant":[
        "Sangu",
        "Sangi",
        "Kisangi"
    ],
    "wof:name":"Kisangi",
    "wof:placetype":"locality"
},
  "geometry": {"coordinates":[18.93937,-5.51979],"type":"Point"}
}