{
  "type": "Feature",
  "properties": {
    "gn:admin1_code":"19.0",
    "gn:asciiname":"Pungu",
    "gn:country_code":"CD",
    "gn:dem":697,
    "gn:feature_class":"P",
    "gn:feature_code":"PPL",
    "gn:name":"Pungu",
    "gn:population":0,
    "gn:timezone":"Africa/Kinshasa",
    "iso:country":"CD",
    "wof:name":"Pungu",
    "wof:placetype":"locality"
},
  "geometry": {"coordinates":[17.48959,-6.77933],"type":"Point"}
}