{
  "type": "Feature",
  "properties": {
    "gn:admin1_code":"19.0",
    "gn:asciiname":"Pungu",
    "gn:country_code":"CD",
    "gn:dem":697,
    "gn:feature_class":"P",
    "gn:feature_code":"PPL",
    "gn:name":"Pungu",
    "gn:population":0,
    "gn:timezone":"Africa/Kinshasa",
    "iso:country":"CD",
    "name:cat_x_preferred":[
        "Pungu maclareni"
    ],
    "name:ceb_x_preferred":[
        "Pungu maclareni"
    ],
    "name:deu_x_preferred":[
        "Pungu maclareni"
    ],
    "name:eus_x_preferred":[
        "Pungu maclareni"
    ],
    "name:fra_x_preferred":[
        "Pungu maclareni"
    ],
    "name:ita_x_preferred":[
        "Pungu maclareni"
    ],
    "name:mrj_x_preferred":[
        "\u041f\u0443\u043d\u0433\u0443"
    ],
    "name:nld_x_preferred":[
        "Pungu maclareni"
    ],
    "name:pol_x_preferred":[
        "Pungu maclareni"
    ],
    "name:por_x_preferred":[
        "Pungu maclareni"
    ],
    "name:spa_x_preferred":[
        "Pungu maclareni"
    ],
    "name:swe_x_preferred":[
        "Pungu maclareni"
    ],
    "name:ukr_x_preferred":[
        "Pungu maclareni"
    ],
    "name:vie_x_preferred":[
        "Pungu maclareni"
    ],
    "name:war_x_preferred":[
        "Pungu maclareni"
    ],
    "name:zho_x_preferred":[
        "\u9a6c\u6c0f\u86f0\u4e3d\u9c7c"
    ],
    "wof:name":"Pungu",
    "wof:placetype":"locality"
},
  "geometry": {"coordinates":[17.48959,-6.77933],"type":"Point"}
}