{
  "type": "Feature",
  "properties": {
    "gn:admin1_code":"18.0",
    "gn:asciiname":"Shayesua",
    "gn:country_code":"CD",
    "gn:dem":528,
    "gn:feature_class":"P",
    "gn:feature_code":"PPL",
    "gn:name":"Shayesua",
    "gn:population":0,
    "gn:timezone":"Africa/Lubumbashi",
    "iso:country":"CD",
    "wof:name":"Shayesua",
    "wof:placetype":"locality"
},
  "geometry": {"coordinates":[20.75913,-6.43971],"type":"Point"}
}