{
  "type": "Feature",
  "properties": {
    "gn:admin1_code":"12.0",
    "gn:asciiname":"Membo",
    "gn:country_code":"CD",
    "gn:dem":2166,
    "gn:feature_class":"P",
    "gn:feature_code":"PPL",
    "gn:name":"Membo",
    "gn:population":0,
    "gn:timezone":"Africa/Lubumbashi",
    "iso:country":"CD",
    "wof:name":"Membo",
    "wof:placetype":"locality"
},
  "geometry": {"coordinates":[29.05333,-3.34417],"type":"Point"}
}