{
  "type": "Feature",
  "properties": {
    "gn:admin1_code":"19.0",
    "gn:asciiname":"Kazemba",
    "gn:country_code":"CD",
    "gn:dem":809,
    "gn:feature_class":"P",
    "gn:feature_code":"PPL",
    "gn:name":"Kazemba",
    "gn:population":0,
    "gn:timezone":"Africa/Kinshasa",
    "iso:country":"CD",
    "wof:name":"Kazemba",
    "wof:placetype":"locality"
},
  "geometry": {"coordinates":[17.45824,-6.81255],"type":"Point"}
}