{
  "type": "Feature",
  "properties": {
    "gn:admin1_code":"22.0",
    "gn:asciiname":"Kayombo",
    "gn:country_code":"CD",
    "gn:dem":1032,
    "gn:feature_class":"P",
    "gn:feature_code":"PPL",
    "gn:name":"Kayombo",
    "gn:population":0,
    "gn:timezone":"Africa/Lubumbashi",
    "iso:country":"CD",
    "wof:name":"Kayombo",
    "wof:placetype":"locality"
},
  "geometry": {"coordinates":[23.17304,-10.29443],"type":"Point"}
}