{
  "type": "Feature",
  "properties": {
    "gn:admin1_code":"4.0",
    "gn:asciiname":"Kaboto",
    "gn:country_code":"CD",
    "gn:dem":667,
    "gn:feature_class":"P",
    "gn:feature_code":"PPL",
    "gn:name":"Kaboto",
    "gn:population":0,
    "gn:timezone":"Africa/Lubumbashi",
    "iso:country":"CD",
    "name:und_x_variant":[
        "Kabote",
        "Kaboto"
    ],
    "wof:name":"Kaboto",
    "wof:placetype":"locality"
},
  "geometry": {"coordinates":[23.18721,-5.76814],"type":"Point"}
}