{
  "type": "Feature",
  "properties": {
    "gn:admin1_code":"22.0",
    "gn:asciiname":"Ditwaye",
    "gn:country_code":"CD",
    "gn:dem":1276,
    "gn:feature_class":"P",
    "gn:feature_code":"PPL",
    "gn:name":"Ditwaye",
    "gn:population":0,
    "gn:timezone":"Africa/Lubumbashi",
    "iso:country":"CD",
    "wof:name":"Ditwaye",
    "wof:placetype":"locality"
},
  "geometry": {"coordinates":[25.56111,-10.50722],"type":"Point"}
}