{
  "type": "Feature",
  "properties": {
    "gn:admin1_code":"22.0",
    "gn:asciiname":"Yavua",
    "gn:country_code":"CD",
    "gn:dem":1063,
    "gn:feature_class":"P",
    "gn:feature_code":"PPL",
    "gn:name":"Yavua",
    "gn:population":0,
    "gn:timezone":"Africa/Lubumbashi",
    "iso:country":"CD",
    "wof:name":"Yavua",
    "wof:placetype":"locality"
},
  "geometry": {"coordinates":[23.06983,-10.61808],"type":"Point"}
}