{
  "type": "Feature",
  "properties": {
    "gn:admin1_code":"24.0",
    "gn:asciiname":"Patambalu",
    "gn:country_code":"CD",
    "gn:dem":304,
    "gn:feature_class":"P",
    "gn:feature_code":"PPL",
    "gn:name":"Patambalu",
    "gn:population":0,
    "gn:timezone":"Africa/Kinshasa",
    "iso:country":"CD",
    "name:und_x_variant":[
        "Palambalu",
        "Patambalu"
    ],
    "wof:name":"Patambalu",
    "wof:placetype":"locality"
},
  "geometry": {"coordinates":[18.29919,-2.27209],"type":"Point"}
}