{
  "type": "Feature",
  "properties": {
    "gn:admin1_code":"16.0",
    "gn:asciiname":"Wodi",
    "gn:country_code":"CD",
    "gn:dem":695,
    "gn:feature_class":"P",
    "gn:feature_code":"PPL",
    "gn:name":"Wodi",
    "gn:population":0,
    "gn:timezone":"Africa/Lubumbashi",
    "iso:country":"CD",
    "wof:name":"Wodi",
    "wof:placetype":"locality"
},
  "geometry": {"coordinates":[28.31404,3.85982],"type":"Point"}
}