{
  "type": "Feature",
  "properties": {
    "gn:admin1_code":"31.0",
    "gn:asciiname":"Yalansa",
    "gn:country_code":"CD",
    "gn:dem":415,
    "gn:feature_class":"P",
    "gn:feature_code":"PPL",
    "gn:name":"Yalansa",
    "gn:population":0,
    "gn:timezone":"Africa/Kinshasa",
    "iso:country":"CD",
    "wof:name":"Yalansa",
    "wof:placetype":"locality"
},
  "geometry": {"coordinates":[22.69195,-0.95912],"type":"Point"}
}