{
  "type": "Feature",
  "properties": {
    "gn:admin1_code":"19.0",
    "gn:asciiname":"Mukumbi-Tseke",
    "gn:country_code":"CD",
    "gn:dem":620,
    "gn:feature_class":"P",
    "gn:feature_code":"PPL",
    "gn:name":"Mukumbi-Tseke",
    "gn:population":0,
    "gn:timezone":"Africa/Kinshasa",
    "iso:country":"CD",
    "wof:name":"Mukumbi-Tseke",
    "wof:placetype":"locality"
},
  "geometry": {"coordinates":[17.12414,-5.08635],"type":"Point"}
}