{
  "type": "Feature",
  "properties": {
    "gn:admin1_code":"20.0",
    "gn:asciiname":"Kitshua-Nseke",
    "gn:country_code":"CD",
    "gn:dem":483,
    "gn:feature_class":"P",
    "gn:feature_code":"PPL",
    "gn:name":"Kitshua-Nseke",
    "gn:population":0,
    "gn:timezone":"Africa/Kinshasa",
    "iso:country":"CD",
    "name:und_x_variant":[
        "Kintshua",
        "Kitshua-Nseke"
    ],
    "wof:name":"Kitshua-Nseke",
    "wof:placetype":"locality"
},
  "geometry": {"coordinates":[19.62212,-4.43199],"type":"Point"}
}