{
  "type": "Feature",
  "properties": {
    "gn:admin1_code":"19.0",
    "gn:asciiname":"Kakugni",
    "gn:country_code":"CD",
    "gn:dem":1036,
    "gn:feature_class":"P",
    "gn:feature_code":"PPL",
    "gn:name":"Kakugni",
    "gn:population":0,
    "gn:timezone":"Africa/Kinshasa",
    "iso:country":"CD",
    "wof:name":"Kakugni",
    "wof:placetype":"locality"
},
  "geometry": {"coordinates":[19.16712,-7.36072],"type":"Point"}
}