{
  "type": "Feature",
  "properties": {
    "gn:admin1_code":"14.0",
    "gn:asciiname":"Kasumbalesa",
    "gn:country_code":"CD",
    "gn:dem":1400,
    "gn:feature_class":"P",
    "gn:feature_code":"PPL",
    "gn:name":"Kasumbalesa",
    "gn:population":0,
    "gn:timezone":"Africa/Lubumbashi",
    "iso:country":"CD",
    "name:und_x_variant":[
        "Kasamba",
        "Kasumba",
        "Kasumbalesa"
    ],
    "wof:name":"Kasumbalesa",
    "wof:placetype":"locality"
},
  "geometry": {"coordinates":[27.79542,-12.20258],"type":"Point"}
}