{
  "type": "Feature",
  "properties": {
    "gn:admin1_code":"19.0",
    "gn:asciiname":"Kindundu-Tsiala",
    "gn:country_code":"CD",
    "gn:dem":444,
    "gn:feature_class":"P",
    "gn:feature_code":"PPL",
    "gn:name":"Kindundu-Tsiala",
    "gn:population":0,
    "gn:timezone":"Africa/Kinshasa",
    "iso:country":"CD",
    "wof:name":"Kindundu-Tsiala",
    "wof:placetype":"locality"
},
  "geometry": {"coordinates":[17.61295,-4.59819],"type":"Point"}
}