{
  "type": "Feature",
  "properties": {
    "gn:admin1_code":"21.0",
    "gn:asciiname":"Tshikala-Mukeba",
    "gn:country_code":"CD",
    "gn:dem":863,
    "gn:feature_class":"P",
    "gn:feature_code":"PPL",
    "gn:name":"Tshikala-Mukeba",
    "gn:population":0,
    "gn:timezone":"Africa/Lubumbashi",
    "iso:country":"CD",
    "name:und_x_variant":[
        "Mukeba"
    ],
    "wof:name":"Tshikala-Mukeba",
    "wof:placetype":"locality"
},
  "geometry": {"coordinates":[23.53019,-7.04479],"type":"Point"}
}