{
  "type": "Feature",
  "properties": {
    "gn:admin1_code":"17.0",
    "gn:asciiname":"Medigo",
    "gn:country_code":"CD",
    "gn:dem":1176,
    "gn:feature_class":"P",
    "gn:feature_code":"PPL",
    "gn:name":"Medigo",
    "gn:population":0,
    "gn:timezone":"Africa/Lubumbashi",
    "iso:country":"CD",
    "wof:name":"Medigo",
    "wof:placetype":"locality"
},
  "geometry": {"coordinates":[30.81227,3.39364],"type":"Point"}
}