{
  "type": "Feature",
  "properties": {
    "gn:admin1_code":"13.0",
    "gn:asciiname":"Rubi",
    "gn:country_code":"CD",
    "gn:dem":566,
    "gn:feature_class":"P",
    "gn:feature_code":"PPL",
    "gn:name":"Rubi",
    "gn:population":0,
    "gn:timezone":"Africa/Lubumbashi",
    "iso:country":"CD",
    "wof:name":"Rubi",
    "wof:placetype":"locality"
},
  "geometry": {"coordinates":[25.23038,2.81299],"type":"Point"}
}