{
  "type": "Feature",
  "properties": {
    "gn:admin1_code":"12.0",
    "gn:asciiname":"Mutumbi",
    "gn:country_code":"CD",
    "gn:dem":653,
    "gn:feature_class":"P",
    "gn:feature_code":"PPL",
    "gn:name":"Mutumbi",
    "gn:population":0,
    "gn:timezone":"Africa/Lubumbashi",
    "iso:country":"CD",
    "wof:name":"Mutumbi",
    "wof:placetype":"locality"
},
  "geometry": {"coordinates":[27.35,-3.88333],"type":"Point"}
}