{
  "type": "Feature",
  "properties": {
    "gn:admin1_code":"18.0",
    "gn:asciiname":"Mukadi",
    "gn:country_code":"CD",
    "gn:dem":554,
    "gn:feature_class":"P",
    "gn:feature_code":"PPL",
    "gn:name":"Mukadi",
    "gn:population":0,
    "gn:timezone":"Africa/Lubumbashi",
    "iso:country":"CD",
    "wof:name":"Mukadi",
    "wof:placetype":"locality"
},
  "geometry": {"coordinates":[21.02704,-5.52621],"type":"Point"}
}