{
  "type": "Feature",
  "properties": {
    "gn:admin1_code":"20.0",
    "gn:asciiname":"Bushi",
    "gn:country_code":"CD",
    "gn:dem":445,
    "gn:feature_class":"P",
    "gn:feature_code":"PPL",
    "gn:name":"Bushi",
    "gn:population":0,
    "gn:timezone":"Africa/Kinshasa",
    "iso:country":"CD",
    "wof:name":"Bushi",
    "wof:placetype":"locality"
},
  "geometry": {"coordinates":[18.58077,-4.49138],"type":"Point"}
}