{
  "type": "Feature",
  "properties": {
    "gn:admin1_code":"19.0",
    "gn:asciiname":"Kinguangu",
    "gn:country_code":"CD",
    "gn:dem":599,
    "gn:feature_class":"P",
    "gn:feature_code":"PPL",
    "gn:name":"Kinguangu",
    "gn:population":0,
    "gn:timezone":"Africa/Kinshasa",
    "iso:country":"CD",
    "wof:name":"Kinguangu",
    "wof:placetype":"locality"
},
  "geometry": {"coordinates":[17.29247,-5.08499],"type":"Point"}
}