{
  "type": "Feature",
  "properties": {
    "gn:admin1_code":"19.0",
    "gn:asciiname":"Ka-Ngoma",
    "gn:country_code":"CD",
    "gn:dem":1053,
    "gn:feature_class":"P",
    "gn:feature_code":"PPL",
    "gn:name":"Ka-Ngoma",
    "gn:population":0,
    "gn:timezone":"Africa/Kinshasa",
    "iso:country":"CD",
    "wof:name":"Ka-Ngoma",
    "wof:placetype":"locality"
},
  "geometry": {"coordinates":[18.90117,-7.34009],"type":"Point"}
}