{
  "type": "Feature",
  "properties": {
    "gn:admin1_code":"28.0",
    "gn:asciiname":"Doroka",
    "gn:country_code":"CD",
    "gn:dem":375,
    "gn:feature_class":"P",
    "gn:feature_code":"PPL",
    "gn:name":"Doroka",
    "gn:population":0,
    "gn:timezone":"Africa/Kinshasa",
    "iso:country":"CD",
    "wof:name":"Doroka",
    "wof:placetype":"locality"
},
  "geometry": {"coordinates":[18.77143,3.72583],"type":"Point"}
}