{
  "type": "Feature",
  "properties": {
    "gn:admin1_code":"19.0",
    "gn:asciiname":"Tana",
    "gn:country_code":"CD",
    "gn:dem":389,
    "gn:feature_class":"P",
    "gn:feature_code":"PPL",
    "gn:name":"Tana",
    "gn:population":0,
    "gn:timezone":"Africa/Kinshasa",
    "iso:country":"CD",
    "wof:name":"Tana",
    "wof:placetype":"locality"
},
  "geometry": {"coordinates":[17.08163,-4.55134],"type":"Point"}
}