{
  "type": "Feature",
  "properties": {
    "gn:admin1_code":"6.0",
    "gn:asciiname":"Luvula",
    "gn:country_code":"CD",
    "gn:dem":300,
    "gn:feature_class":"P",
    "gn:feature_code":"PPL",
    "gn:name":"Luvula",
    "gn:population":0,
    "gn:timezone":"Africa/Kinshasa",
    "iso:country":"CD",
    "wof:name":"Luvula",
    "wof:placetype":"locality"
},
  "geometry": {"coordinates":[15.17197,-4.41479],"type":"Point"}
}