{
  "type": "Feature",
  "properties": {
    "gn:admin1_code":"25.0",
    "gn:asciiname":"Busu-Lingo",
    "gn:country_code":"CD",
    "gn:dem":386,
    "gn:feature_class":"P",
    "gn:feature_code":"PPL",
    "gn:name":"Busu-Lingo",
    "gn:population":0,
    "gn:timezone":"Africa/Kinshasa",
    "iso:country":"CD",
    "wof:name":"Busu-Lingo",
    "wof:placetype":"locality"
},
  "geometry": {"coordinates":[20.97816,2.90982],"type":"Point"}
}