{
  "type": "Feature",
  "properties": {
    "gn:admin1_code":"25.0",
    "gn:asciiname":"Yalikela",
    "gn:country_code":"CD",
    "gn:dem":455,
    "gn:feature_class":"P",
    "gn:feature_code":"PPL",
    "gn:name":"Yalikela",
    "gn:population":0,
    "gn:timezone":"Africa/Kinshasa",
    "iso:country":"CD",
    "wof:name":"Yalikela",
    "wof:placetype":"locality"
},
  "geometry": {"coordinates":[23.06087,2.36814],"type":"Point"}
}