{
  "type": "Feature",
  "properties": {
    "gn:admin1_code":"19.0",
    "gn:asciiname":"Kapalamba",
    "gn:country_code":"CD",
    "gn:dem":581,
    "gn:feature_class":"P",
    "gn:feature_code":"PPL",
    "gn:name":"Kapalamba",
    "gn:population":0,
    "gn:timezone":"Africa/Kinshasa",
    "iso:country":"CD",
    "wof:name":"Kapalamba",
    "wof:placetype":"locality"
},
  "geometry": {"coordinates":[19.6582,-6.36081],"type":"Point"}
}