{
  "type": "Feature",
  "properties": {
    "gn:admin1_code":"19.0",
    "gn:asciiname":"Shatshowa",
    "gn:country_code":"CD",
    "gn:dem":976,
    "gn:feature_class":"P",
    "gn:feature_code":"PPL",
    "gn:name":"Shatshowa",
    "gn:population":0,
    "gn:timezone":"Africa/Kinshasa",
    "iso:country":"CD",
    "wof:name":"Shatshowa",
    "wof:placetype":"locality"
},
  "geometry": {"coordinates":[19.27408,-7.42208],"type":"Point"}
}