{
  "type": "Feature",
  "properties": {
    "gn:admin1_code":"12.0",
    "gn:asciiname":"Fundi",
    "gn:country_code":"CD",
    "gn:dem":956,
    "gn:feature_class":"P",
    "gn:feature_code":"PPL",
    "gn:name":"Fundi",
    "gn:population":0,
    "gn:timezone":"Africa/Lubumbashi",
    "iso:country":"CD",
    "name:ceb_x_preferred":[
        "Fundi"
    ],
    "name:deu_x_preferred":[
        "Fundi"
    ],
    "name:fra_x_preferred":[
        "Fundi"
    ],
    "name:swe_x_preferred":[
        "Fundi"
    ],
    "wof:name":"Fundi",
    "wof:placetype":"locality"
},
  "geometry": {"coordinates":[27.86667000000001,-3.68333],"type":"Point"}
}