{
  "type": "Feature",
  "properties": {
    "gn:admin1_code":"19.0",
    "gn:asciiname":"Kigandu",
    "gn:country_code":"CD",
    "gn:dem":820,
    "gn:feature_class":"P",
    "gn:feature_code":"PPL",
    "gn:name":"Kigandu",
    "gn:population":0,
    "gn:timezone":"Africa/Kinshasa",
    "iso:country":"CD",
    "name:und_x_variant":[
        "Kingandu",
        "Kigandu"
    ],
    "wof:name":"Kigandu",
    "wof:placetype":"locality"
},
  "geometry": {"coordinates":[17.17332,-6.80877],"type":"Point"}
}