{
  "type": "Feature",
  "properties": {
    "gn:admin1_code":"24.0",
    "gn:asciiname":"Molumbu",
    "gn:country_code":"CD",
    "gn:dem":295,
    "gn:feature_class":"P",
    "gn:feature_code":"PPL",
    "gn:name":"Molumbu",
    "gn:population":0,
    "gn:timezone":"Africa/Kinshasa",
    "iso:country":"CD",
    "wof:name":"Molumbu",
    "wof:placetype":"locality"
},
  "geometry": {"coordinates":[16.52824,-1.92686],"type":"Point"}
}