{
  "type": "Feature",
  "properties": {
    "gn:admin1_code":"18.0",
    "gn:asciiname":"Djendja",
    "gn:country_code":"CD",
    "gn:dem":640,
    "gn:feature_class":"P",
    "gn:feature_code":"PPL",
    "gn:name":"Djendja",
    "gn:population":0,
    "gn:timezone":"Africa/Lubumbashi",
    "iso:country":"CD",
    "wof:name":"Djendja",
    "wof:placetype":"locality"
},
  "geometry": {"coordinates":[19.81454,-6.17057],"type":"Point"}
}