{
  "type": "Feature",
  "properties": {
    "gn:admin1_code":"15.0",
    "gn:asciiname":"Kela",
    "gn:country_code":"CD",
    "gn:dem":1051,
    "gn:feature_class":"P",
    "gn:feature_code":"PPL",
    "gn:name":"Kela",
    "gn:population":0,
    "gn:timezone":"Africa/Lubumbashi",
    "iso:country":"CD",
    "name:ceb_x_preferred":[
        "Kela"
    ],
    "name:deu_x_preferred":[
        "Kela"
    ],
    "name:fin_x_preferred":[
        "Kela"
    ],
    "name:fra_x_preferred":[
        "Kela"
    ],
    "name:heb_x_preferred":[
        "\u05e7\u05dc\u05e2"
    ],
    "name:swe_x_preferred":[
        "Kela"
    ],
    "wof:name":"Kela",
    "wof:placetype":"locality"
},
  "geometry": {"coordinates":[24.16667,-8.43333],"type":"Point"}
}