{
  "type": "Feature",
  "properties": {
    "gn:admin1_code":"26.0",
    "gn:asciiname":"Boyazudo",
    "gn:country_code":"CD",
    "gn:dem":519,
    "gn:feature_class":"P",
    "gn:feature_code":"PPL",
    "gn:name":"Boyazudo",
    "gn:population":0,
    "gn:timezone":"Africa/Kinshasa",
    "iso:country":"CD",
    "wof:name":"Boyazudo",
    "wof:placetype":"locality"
},
  "geometry": {"coordinates":[20.33137,3.42503],"type":"Point"}
}