{
  "type": "Feature",
  "properties": {
    "gn:admin1_code":"13.0",
    "gn:asciiname":"Madili",
    "gn:country_code":"CD",
    "gn:dem":718,
    "gn:feature_class":"P",
    "gn:feature_code":"PPL",
    "gn:name":"Madili",
    "gn:population":0,
    "gn:timezone":"Africa/Lubumbashi",
    "iso:country":"CD",
    "name:und_x_variant":[
        "Madeli",
        "Madili"
    ],
    "wof:name":"Madili",
    "wof:placetype":"locality"
},
  "geometry": {"coordinates":[26.91442,3.87685],"type":"Point"}
}