{
  "type": "Feature",
  "properties": {
    "gn:admin1_code":"25.0",
    "gn:asciiname":"Dundusana",
    "gn:country_code":"CD",
    "gn:dem":447,
    "gn:feature_class":"P",
    "gn:feature_code":"PPL",
    "gn:name":"Dundusana",
    "gn:population":0,
    "gn:timezone":"Africa/Kinshasa",
    "iso:country":"CD",
    "name:und_x_variant":[
        "Dundusuna",
        "Dundusana"
    ],
    "wof:name":"Dundusana",
    "wof:placetype":"locality"
},
  "geometry": {"coordinates":[22.26208,2.94659],"type":"Point"}
}