{
  "type": "Feature",
  "properties": {
    "gn:admin1_code":"11.0",
    "gn:asciiname":"Kirima",
    "gn:country_code":"CD",
    "gn:dem":1227,
    "gn:feature_class":"P",
    "gn:feature_code":"PPL",
    "gn:name":"Kirima",
    "gn:population":0,
    "gn:timezone":"Africa/Lubumbashi",
    "iso:country":"CD",
    "name:und_x_variant":[
        "Kilima"
    ],
    "wof:name":"Kirima",
    "wof:placetype":"locality"
},
  "geometry": {"coordinates":[29.19291,-0.98429],"type":"Point"}
}