{
  "type": "Feature",
  "properties": {
    "gn:admin1_code":"6.0",
    "gn:asciiname":"Maluku",
    "gn:country_code":"CD",
    "gn:dem":292,
    "gn:feature_class":"P",
    "gn:feature_code":"PPL",
    "gn:name":"Maluku",
    "gn:population":0,
    "gn:timezone":"Africa/Kinshasa",
    "iso:country":"CD",
    "name:ceb_x_preferred":[
        "Maluku"
    ],
    "name:est_x_preferred":[
        "Maluku"
    ],
    "name:fas_x_preferred":[
        "\u0645\u0644\u0648\u06a9"
    ],
    "name:fra_x_preferred":[
        "Maluku"
    ],
    "name:hun_x_preferred":[
        "Maluku"
    ],
    "name:ita_x_preferred":[
        "Maluku"
    ],
    "name:ron_x_preferred":[
        "Maluku"
    ],
    "name:swe_x_preferred":[
        "Maluku"
    ],
    "wof:name":"Maluku",
    "wof:placetype":"locality"
},
  "geometry": {"coordinates":[15.5375,-4.07306],"type":"Point"}
}