{
  "type": "Feature",
  "properties": {
    "gn:admin1_code":"17.0",
    "gn:asciiname":"Tiperitsa",
    "gn:country_code":"CD",
    "gn:dem":997,
    "gn:feature_class":"P",
    "gn:feature_code":"PPL",
    "gn:name":"Tiperitsa",
    "gn:population":0,
    "gn:timezone":"Africa/Lubumbashi",
    "iso:country":"CD",
    "name:fra_x_preferred":[
        "Tiperitsa"
    ],
    "wof:name":"Tiperitsa",
    "wof:placetype":"locality"
},
  "geometry": {"coordinates":[29.6615,1.01058],"type":"Point"}
}