{
  "type": "Feature",
  "properties": {
    "gn:admin1_code":"13.0",
    "gn:asciiname":"Libaki",
    "gn:country_code":"CD",
    "gn:dem":575,
    "gn:feature_class":"P",
    "gn:feature_code":"PPL",
    "gn:name":"Libaki",
    "gn:population":0,
    "gn:timezone":"Africa/Lubumbashi",
    "iso:country":"CD",
    "wof:name":"Libaki",
    "wof:placetype":"locality"
},
  "geometry": {"coordinates":[25.12564,4.17771],"type":"Point"}
}