{
  "type": "Feature",
  "properties": {
    "gn:admin1_code":"10.0",
    "gn:asciiname":"Bunza",
    "gn:country_code":"CD",
    "gn:dem":572,
    "gn:feature_class":"P",
    "gn:feature_code":"PPL",
    "gn:name":"Bunza",
    "gn:population":0,
    "gn:timezone":"Africa/Lubumbashi",
    "iso:country":"CD",
    "name:fra_x_preferred":[
        "Bunza"
    ],
    "name:hau_x_preferred":[
        "Bunza"
    ],
    "name:ita_x_preferred":[
        "Bunza"
    ],
    "name:spa_x_preferred":[
        "Bunza"
    ],
    "name:und_x_variant":[
        "Bundja"
    ],
    "wof:name":"Bunza",
    "wof:placetype":"locality"
},
  "geometry": {"coordinates":[26.53029,-2.63758],"type":"Point"}
}