{
  "type": "Feature",
  "properties": {
    "gn:admin1_code":"21.0",
    "gn:asciiname":"Ngoie",
    "gn:country_code":"CD",
    "gn:dem":986,
    "gn:feature_class":"P",
    "gn:feature_code":"PPL",
    "gn:name":"Ngoie",
    "gn:population":0,
    "gn:timezone":"Africa/Lubumbashi",
    "iso:country":"CD",
    "wof:name":"Ngoie",
    "wof:placetype":"locality"
},
  "geometry": {"coordinates":[23.41464,-7.40061],"type":"Point"}
}