{
  "type": "Feature",
  "properties": {
    "gn:admin1_code":"19.0",
    "gn:asciiname":"Makodia-Mutayi",
    "gn:country_code":"CD",
    "gn:dem":812,
    "gn:feature_class":"P",
    "gn:feature_code":"PPL",
    "gn:name":"Makodia-Mutayi",
    "gn:population":0,
    "gn:timezone":"Africa/Kinshasa",
    "iso:country":"CD",
    "wof:name":"Makodia-Mutayi",
    "wof:placetype":"locality"
},
  "geometry": {"coordinates":[16.28789,-5.56788],"type":"Point"}
}