{
  "type": "Feature",
  "properties": {
    "gn:admin1_code":"23.0",
    "gn:asciiname":"Mayoyo-Lunsanyi",
    "gn:country_code":"CD",
    "gn:dem":573,
    "gn:feature_class":"P",
    "gn:feature_code":"PPL",
    "gn:name":"Mayoyo-Lunsanyi",
    "gn:population":0,
    "gn:timezone":"Africa/Lubumbashi",
    "iso:country":"CD",
    "wof:name":"Mayoyo-Lunsanyi",
    "wof:placetype":"locality"
},
  "geometry": {"coordinates":[21.81333,-5.34037],"type":"Point"}
}