{
  "type": "Feature",
  "properties": {
    "gn:admin1_code":"19.0",
    "gn:asciiname":"Bibala",
    "gn:country_code":"CD",
    "gn:dem":721,
    "gn:feature_class":"P",
    "gn:feature_code":"PPL",
    "gn:name":"Bibala",
    "gn:population":0,
    "gn:timezone":"Africa/Kinshasa",
    "iso:country":"CD",
    "name:cat_x_preferred":[
        "Bibala"
    ],
    "name:deu_x_preferred":[
        "Bibala"
    ],
    "name:fas_x_preferred":[
        "\u0628\u06cc\u0628\u0627\u0644\u0627"
    ],
    "name:ita_x_preferred":[
        "Bibala"
    ],
    "name:por_x_preferred":[
        "Bibala"
    ],
    "name:ron_x_preferred":[
        "Bibala"
    ],
    "name:spa_x_preferred":[
        "Bibala"
    ],
    "name:zho_x_preferred":[
        "\u6bd4\u5df4\u62c9"
    ],
    "wof:name":"Bibala",
    "wof:placetype":"locality"
},
  "geometry": {"coordinates":[17.11883,-5.25489],"type":"Point"}
}