{
  "type": "Feature",
  "properties": {
    "gn:admin1_code":"11.0",
    "gn:asciiname":"Mukabo",
    "gn:country_code":"CD",
    "gn:dem":636,
    "gn:feature_class":"P",
    "gn:feature_code":"PPL",
    "gn:name":"Mukabo",
    "gn:population":0,
    "gn:timezone":"Africa/Lubumbashi",
    "iso:country":"CD",
    "wof:name":"Mukabo",
    "wof:placetype":"locality"
},
  "geometry": {"coordinates":[27.87185,-1.49287],"type":"Point"}
}