{
  "type": "Feature",
  "properties": {
    "gn:admin1_code":"29.0",
    "gn:asciiname":"Lubundji",
    "gn:country_code":"CD",
    "gn:dem":673,
    "gn:feature_class":"P",
    "gn:feature_code":"PPL",
    "gn:name":"Lubundji",
    "gn:population":0,
    "gn:timezone":"Africa/Lubumbashi",
    "iso:country":"CD",
    "wof:name":"Lubundji",
    "wof:placetype":"locality"
},
  "geometry": {"coordinates":[27.62207,-7.57817],"type":"Point"}
}