{
  "type": "Feature",
  "properties": {
    "gn:admin1_code":"2.0",
    "gn:asciiname":"Latakemela",
    "gn:country_code":"CD",
    "gn:dem":316,
    "gn:feature_class":"P",
    "gn:feature_code":"PPL",
    "gn:name":"Latakemela",
    "gn:population":0,
    "gn:timezone":"Africa/Kinshasa",
    "iso:country":"CD",
    "wof:name":"Latakemela",
    "wof:placetype":"locality"
},
  "geometry": {"coordinates":[18.16019,-0.07866],"type":"Point"}
}