{
  "type": "Feature",
  "properties": {
    "gn:admin1_code":"13.0",
    "gn:asciiname":"Bokoi",
    "gn:country_code":"CD",
    "gn:dem":620,
    "gn:feature_class":"P",
    "gn:feature_code":"PPL",
    "gn:name":"Bokoi",
    "gn:population":0,
    "gn:timezone":"Africa/Lubumbashi",
    "iso:country":"CD",
    "wof:name":"Bokoi",
    "wof:placetype":"locality"
},
  "geometry": {"coordinates":[26.47989,2.26521],"type":"Point"}
}