{
  "type": "Feature",
  "properties": {
    "gn:admin1_code":"22.0",
    "gn:asciiname":"Mukanda",
    "gn:country_code":"CD",
    "gn:dem":1101,
    "gn:feature_class":"P",
    "gn:feature_code":"PPL",
    "gn:name":"Mukanda",
    "gn:population":0,
    "gn:timezone":"Africa/Lubumbashi",
    "iso:country":"CD",
    "wof:name":"Mukanda",
    "wof:placetype":"locality"
},
  "geometry": {"coordinates":[22.92692000000001,-9.24511],"type":"Point"}
}