{
  "type": "Feature",
  "properties": {
    "gn:admin1_code":"27.0",
    "gn:asciiname":"Usniwo",
    "gn:country_code":"CD",
    "gn:dem":473,
    "gn:feature_class":"P",
    "gn:feature_code":"PPL",
    "gn:name":"Usniwo",
    "gn:population":0,
    "gn:timezone":"Africa/Lubumbashi",
    "iso:country":"CD",
    "name:und_x_variant":[
        "Usniwa",
        "Usniwo"
    ],
    "wof:name":"Usniwo",
    "wof:placetype":"locality"
},
  "geometry": {"coordinates":[23.38333,-3.58333],"type":"Point"}
}