{
  "type": "Feature",
  "properties": {
    "gn:admin1_code":"23.0",
    "gn:asciiname":"Kalamba",
    "gn:country_code":"CD",
    "gn:dem":782,
    "gn:feature_class":"P",
    "gn:feature_code":"PPL",
    "gn:name":"Kalamba",
    "gn:population":0,
    "gn:timezone":"Africa/Lubumbashi",
    "iso:country":"CD",
    "wof:name":"Kalamba",
    "wof:placetype":"locality"
},
  "geometry": {"coordinates":[22.34078,-6.33164],"type":"Point"}
}