{
  "type": "Feature",
  "properties": {
    "gn:admin1_code":"8.0",
    "gn:asciiname":"Luema",
    "gn:country_code":"CD",
    "gn:dem":127,
    "gn:feature_class":"P",
    "gn:feature_code":"PPL",
    "gn:name":"Luema",
    "gn:population":0,
    "gn:timezone":"Africa/Kinshasa",
    "iso:country":"CD",
    "wof:name":"Luema",
    "wof:placetype":"locality"
},
  "geometry": {"coordinates":[13.06677,-5.67167],"type":"Point"}
}