{
  "type": "Feature",
  "properties": {
    "gn:admin1_code":"21.0",
    "gn:asciiname":"Panda",
    "gn:country_code":"CD",
    "gn:dem":815,
    "gn:feature_class":"P",
    "gn:feature_code":"PPL",
    "gn:name":"Panda",
    "gn:population":0,
    "gn:timezone":"Africa/Lubumbashi",
    "iso:country":"CD",
    "wof:name":"Panda",
    "wof:placetype":"locality"
},
  "geometry": {"coordinates":[24.58811,-6.05817],"type":"Point"}
}