{
  "type": "Feature",
  "properties": {
    "gn:admin1_code":"24.0",
    "gn:asciiname":"Semondane",
    "gn:country_code":"CD",
    "gn:dem":344,
    "gn:feature_class":"P",
    "gn:feature_code":"PPL",
    "gn:name":"Semondane",
    "gn:population":0,
    "gn:timezone":"Africa/Kinshasa",
    "iso:country":"CD",
    "name:und_x_variant":[
        "Semandane",
        "Semondane",
        "Semondani"
    ],
    "wof:name":"Semondane",
    "wof:placetype":"locality"
},
  "geometry": {"coordinates":[18.35046,-3.50743],"type":"Point"}
}