{
  "type": "Feature",
  "properties": {
    "gn:admin1_code":"8.0",
    "gn:asciiname":"Bambala",
    "gn:country_code":"CD",
    "gn:dem":592,
    "gn:feature_class":"P",
    "gn:feature_code":"PPL",
    "gn:name":"Bambala",
    "gn:population":0,
    "gn:timezone":"Africa/Kinshasa",
    "iso:country":"CD",
    "name:kon_x_preferred":[
        "Bambala"
    ],
    "wof:name":"Bambala",
    "wof:placetype":"locality"
},
  "geometry": {"coordinates":[14.38926,-5.39765],"type":"Point"}
}