{
  "type": "Feature",
  "properties": {
    "gn:admin1_code":"17.0",
    "gn:asciiname":"Ambo",
    "gn:country_code":"CD",
    "gn:dem":1456,
    "gn:feature_class":"P",
    "gn:feature_code":"PPL",
    "gn:name":"Ambo",
    "gn:population":0,
    "gn:timezone":"Africa/Lubumbashi",
    "iso:country":"CD",
    "name:cat_x_preferred":[
        "Ambo"
    ],
    "name:ceb_x_preferred":[
        "Ambo"
    ],
    "name:deu_x_preferred":[
        "Ambo"
    ],
    "name:fra_x_preferred":[
        "Ambo"
    ],
    "name:ita_x_preferred":[
        "Ambo"
    ],
    "name:nld_x_preferred":[
        "Ambo"
    ],
    "name:pol_x_preferred":[
        "Ambo"
    ],
    "name:spa_x_preferred":[
        "Ambo"
    ],
    "name:swe_x_preferred":[
        "Ambo"
    ],
    "wof:name":"Ambo",
    "wof:placetype":"locality"
},
  "geometry": {"coordinates":[30.41667,2.31667],"type":"Point"}
}