{
  "type": "Feature",
  "properties": {
    "gn:admin1_code":"28.0",
    "gn:asciiname":"Busu-Efuta",
    "gn:country_code":"CD",
    "gn:dem":401,
    "gn:feature_class":"P",
    "gn:feature_code":"PPL",
    "gn:name":"Busu-Efuta",
    "gn:population":0,
    "gn:timezone":"Africa/Kinshasa",
    "iso:country":"CD",
    "name:und_x_variant":[
        "Busu Efutu",
        "Busu-Efuta"
    ],
    "wof:name":"Busu-Efuta",
    "wof:placetype":"locality"
},
  "geometry": {"coordinates":[20.6266,3.03041],"type":"Point"}
}