{
  "type": "Feature",
  "properties": {
    "gn:admin1_code":"8.0",
    "gn:asciiname":"Botongo",
    "gn:country_code":"CD",
    "gn:dem":602,
    "gn:feature_class":"P",
    "gn:feature_code":"PPL",
    "gn:name":"Botongo",
    "gn:population":0,
    "gn:timezone":"Africa/Kinshasa",
    "iso:country":"CD",
    "wof:name":"Botongo",
    "wof:placetype":"locality"
},
  "geometry": {"coordinates":[14.71593,-5.02332],"type":"Point"}
}