{
  "type": "Feature",
  "properties": {
    "gn:admin1_code":"26.0",
    "gn:asciiname":"Kongo",
    "gn:country_code":"CD",
    "gn:dem":447,
    "gn:feature_class":"P",
    "gn:feature_code":"PPL",
    "gn:name":"Kongo",
    "gn:population":0,
    "gn:timezone":"Africa/Kinshasa",
    "iso:country":"CD",
    "wof:name":"Kongo",
    "wof:placetype":"locality"
},
  "geometry": {"coordinates":[21.76016,3.68218],"type":"Point"}
}