{
  "type": "Feature",
  "properties": {
    "gn:admin1_code":"20.0",
    "gn:asciiname":"Kizulu",
    "gn:country_code":"CD",
    "gn:dem":738,
    "gn:feature_class":"P",
    "gn:feature_code":"PPL",
    "gn:name":"Kizulu",
    "gn:population":0,
    "gn:timezone":"Africa/Kinshasa",
    "iso:country":"CD",
    "wof:name":"Kizulu",
    "wof:placetype":"locality"
},
  "geometry": {"coordinates":[17.5607,-5.33408],"type":"Point"}
}