{
  "type": "Feature",
  "properties": {
    "gn:admin1_code":"20.0",
    "gn:asciiname":"Kimbengi",
    "gn:country_code":"CD",
    "gn:dem":708,
    "gn:feature_class":"P",
    "gn:feature_code":"PPL",
    "gn:name":"Kimbengi",
    "gn:population":0,
    "gn:timezone":"Africa/Kinshasa",
    "iso:country":"CD",
    "wof:name":"Kimbengi",
    "wof:placetype":"locality"
},
  "geometry": {"coordinates":[17.63559,-5.41407],"type":"Point"}
}