{
  "type": "Feature",
  "properties": {
    "gn:admin1_code":"18.0",
    "gn:asciiname":"Lumbala",
    "gn:country_code":"CD",
    "gn:dem":535,
    "gn:feature_class":"P",
    "gn:feature_code":"PPL",
    "gn:name":"Lumbala",
    "gn:population":0,
    "gn:timezone":"Africa/Lubumbashi",
    "iso:country":"CD",
    "wof:name":"Lumbala",
    "wof:placetype":"locality"
},
  "geometry": {"coordinates":[20.80544,-6.31652],"type":"Point"}
}