{
  "type": "Feature",
  "properties": {
    "gn:admin1_code":"13.0",
    "gn:asciiname":"Akpome",
    "gn:country_code":"CD",
    "gn:dem":600,
    "gn:feature_class":"P",
    "gn:feature_code":"PPL",
    "gn:name":"Akpome",
    "gn:population":0,
    "gn:timezone":"Africa/Lubumbashi",
    "iso:country":"CD",
    "wof:name":"Akpome",
    "wof:placetype":"locality"
},
  "geometry": {"coordinates":[25.95142,3.08206],"type":"Point"}
}