{
  "type": "Feature",
  "properties": {
    "gn:admin1_code":"14.0",
    "gn:asciiname":"Kafwira",
    "gn:country_code":"CD",
    "gn:dem":1326,
    "gn:feature_class":"P",
    "gn:feature_code":"PPL",
    "gn:name":"Kafwira",
    "gn:population":0,
    "gn:timezone":"Africa/Lubumbashi",
    "iso:country":"CD",
    "name:und_x_variant":[
        "Kafuira",
        "Kafwira"
    ],
    "wof:name":"Kafwira",
    "wof:placetype":"locality"
},
  "geometry": {"coordinates":[27.54167,-12.17528],"type":"Point"}
}