{
  "type": "Feature",
  "properties": {
    "gn:admin1_code":"21.0",
    "gn:asciiname":"Tshipoko",
    "gn:country_code":"CD",
    "gn:dem":909,
    "gn:feature_class":"P",
    "gn:feature_code":"PPL",
    "gn:name":"Tshipoko",
    "gn:population":0,
    "gn:timezone":"Africa/Lubumbashi",
    "iso:country":"CD",
    "name:und_x_variant":[
        "Tshiboko",
        "Tshipoko"
    ],
    "wof:name":"Tshipoko",
    "wof:placetype":"locality"
},
  "geometry": {"coordinates":[23.3846,-6.87028],"type":"Point"}
}