{
  "type": "Feature",
  "properties": {
    "gn:admin1_code":"21.0",
    "gn:asciiname":"Nzaji",
    "gn:country_code":"CD",
    "gn:dem":694,
    "gn:feature_class":"P",
    "gn:feature_code":"PPL",
    "gn:name":"Nzaji",
    "gn:population":0,
    "gn:timezone":"Africa/Lubumbashi",
    "iso:country":"CD",
    "wof:name":"Nzaji",
    "wof:placetype":"locality"
},
  "geometry": {"coordinates":[24.33112,-6.56091],"type":"Point"}
}