{
  "type": "Feature",
  "properties": {
    "gn:admin1_code":"15.0",
    "gn:asciiname":"Muine-Songa",
    "gn:country_code":"CD",
    "gn:dem":982,
    "gn:feature_class":"P",
    "gn:feature_code":"PPL",
    "gn:name":"Muine-Songa",
    "gn:population":0,
    "gn:timezone":"Africa/Lubumbashi",
    "iso:country":"CD",
    "wof:name":"Muine-Songa",
    "wof:placetype":"locality"
},
  "geometry": {"coordinates":[24.06227,-7.77219],"type":"Point"}
}