{
  "type": "Feature",
  "properties": {
    "gn:admin1_code":"22.0",
    "gn:asciiname":"Marino",
    "gn:country_code":"CD",
    "gn:dem":1385,
    "gn:feature_class":"P",
    "gn:feature_code":"PPL",
    "gn:name":"Marino",
    "gn:population":0,
    "gn:timezone":"Africa/Lubumbashi",
    "iso:country":"CD",
    "wof:name":"Marino",
    "wof:placetype":"locality"
},
  "geometry": {"coordinates":[25.41778,-10.625],"type":"Point"}
}