{
  "type": "Feature",
  "properties": {
    "gn:admin1_code":"22.0",
    "gn:asciiname":"Marino",
    "gn:country_code":"CD",
    "gn:dem":1385,
    "gn:feature_class":"P",
    "gn:feature_code":"PPL",
    "gn:name":"Marino",
    "gn:population":0,
    "gn:timezone":"Africa/Lubumbashi",
    "iso:country":"CD",
    "name:bel_x_preferred":[
        "\u041c\u0430\u0440\u044b\u043d\u0430"
    ],
    "name:bul_x_preferred":[
        "\u041c\u0430\u0440\u0438\u043d\u043e"
    ],
    "name:cat_x_preferred":[
        "Marino"
    ],
    "name:ceb_x_preferred":[
        "Marino"
    ],
    "name:ces_x_preferred":[
        "Marino"
    ],
    "name:dan_x_preferred":[
        "Marino"
    ],
    "name:deu_x_preferred":[
        "Marino"
    ],
    "name:epo_x_preferred":[
        "Marino"
    ],
    "name:eus_x_preferred":[
        "Marino"
    ],
    "name:fra_x_preferred":[
        "Marino"
    ],
    "name:ita_x_preferred":[
        "Marino"
    ],
    "name:jpn_x_preferred":[
        "\u30de\u30ea\u30ce"
    ],
    "name:kor_x_preferred":[
        "\ub9c8\ub9ac\ub178"
    ],
    "name:nds_x_preferred":[
        "Marino"
    ],
    "name:nld_x_preferred":[
        "Marino"
    ],
    "name:pol_x_preferred":[
        "Marino"
    ],
    "name:por_x_preferred":[
        "Marino"
    ],
    "name:rus_x_preferred":[
        "\u041c\u0430\u0440\u0438\u043d\u043e"
    ],
    "name:sco_x_preferred":[
        "Marino"
    ],
    "name:slv_x_preferred":[
        "Marino"
    ],
    "name:srp_x_preferred":[
        "\u041c\u0430\u0440\u0438\u043d\u043e"
    ],
    "name:swe_x_preferred":[
        "Marino"
    ],
    "name:ukr_x_preferred":[
        "\u041c\u0430\u0440\u0438\u043d\u043e"
    ],
    "wof:name":"Marino",
    "wof:placetype":"locality"
},
  "geometry": {"coordinates":[25.41778,-10.625],"type":"Point"}
}