{
  "type": "Feature",
  "properties": {
    "gn:admin1_code":"13.0",
    "gn:asciiname":"Banangi",
    "gn:country_code":"CD",
    "gn:dem":590,
    "gn:feature_class":"P",
    "gn:feature_code":"PPL",
    "gn:name":"Banangi",
    "gn:population":0,
    "gn:timezone":"Africa/Lubumbashi",
    "iso:country":"CD",
    "wof:name":"Banangi",
    "wof:placetype":"locality"
},
  "geometry": {"coordinates":[24.89603,3.64562],"type":"Point"}
}