{
  "type": "Feature",
  "properties": {
    "gn:admin1_code":"24.0",
    "gn:asciiname":"Donga",
    "gn:country_code":"CD",
    "gn:dem":307,
    "gn:feature_class":"P",
    "gn:feature_code":"PPL",
    "gn:name":"Donga",
    "gn:population":0,
    "gn:timezone":"Africa/Kinshasa",
    "iso:country":"CD",
    "name:ceb_x_preferred":[
        "Donga"
    ],
    "name:deu_x_preferred":[
        "Donga"
    ],
    "name:fas_x_preferred":[
        "\u062f\u0648\u0646\u06af\u0627"
    ],
    "name:fra_x_preferred":[
        "Donga"
    ],
    "name:ita_x_preferred":[
        "Donga"
    ],
    "name:jpn_x_preferred":[
        "\u30c9\u30f3\u30ac"
    ],
    "name:slk_x_preferred":[
        "Donga"
    ],
    "name:swe_x_preferred":[
        "Donga"
    ],
    "name:und_x_variant":[
        "Doriga"
    ],
    "wof:name":"Donga",
    "wof:placetype":"locality"
},
  "geometry": {"coordinates":[18.16667,-1.63333],"type":"Point"}
}