{
  "type": "Feature",
  "properties": {
    "gn:admin1_code":"29.0",
    "gn:asciiname":"Mukonga",
    "gn:country_code":"CD",
    "gn:dem":1174,
    "gn:feature_class":"P",
    "gn:feature_code":"PPL",
    "gn:name":"Mukonga",
    "gn:population":0,
    "gn:timezone":"Africa/Lubumbashi",
    "iso:country":"CD",
    "wof:name":"Mukonga",
    "wof:placetype":"locality"
},
  "geometry": {"coordinates":[29.75926,-7.17091],"type":"Point"}
}