{
  "type": "Feature",
  "properties": {
    "gn:admin1_code":"13.0",
    "gn:asciiname":"Nagombe",
    "gn:country_code":"CD",
    "gn:dem":737,
    "gn:feature_class":"P",
    "gn:feature_code":"PPL",
    "gn:name":"Nagombe",
    "gn:population":0,
    "gn:timezone":"Africa/Lubumbashi",
    "iso:country":"CD",
    "wof:name":"Nagombe",
    "wof:placetype":"locality"
},
  "geometry": {"coordinates":[27.36855,2.91896],"type":"Point"}
}