{
  "type": "Feature",
  "properties": {
    "gn:admin1_code":"16.0",
    "gn:asciiname":"Nesolo",
    "gn:country_code":"CD",
    "gn:dem":741,
    "gn:feature_class":"P",
    "gn:feature_code":"PPL",
    "gn:name":"Nesolo",
    "gn:population":0,
    "gn:timezone":"Africa/Lubumbashi",
    "iso:country":"CD",
    "wof:name":"Nesolo",
    "wof:placetype":"locality"
},
  "geometry": {"coordinates":[27.48638,2.6724],"type":"Point"}
}