{
  "type": "Feature",
  "properties": {
    "gn:admin1_code":"0.0",
    "gn:asciiname":"Kisengere",
    "gn:country_code":"CD",
    "gn:dem":1055,
    "gn:feature_class":"P",
    "gn:feature_code":"PPL",
    "gn:name":"Kisengere",
    "gn:population":0,
    "gn:timezone":"Africa/Lusaka",
    "iso:country":"CD",
    "wof:name":"Kisengere",
    "wof:placetype":"locality"
},
  "geometry": {"coordinates":[28.81667,-12.08333],"type":"Point"}
}