{
  "type": "Feature",
  "properties": {
    "gn:admin1_code":"8.0",
    "gn:asciiname":"Kinsoma",
    "gn:country_code":"CD",
    "gn:dem":652,
    "gn:feature_class":"P",
    "gn:feature_code":"PPL",
    "gn:name":"Kinsoma",
    "gn:population":0,
    "gn:timezone":"Africa/Kinshasa",
    "iso:country":"CD",
    "wof:name":"Kinsoma",
    "wof:placetype":"locality"
},
  "geometry": {"coordinates":[15.09583,-5.78832],"type":"Point"}
}