{
  "type": "Feature",
  "properties": {
    "gn:admin1_code":"30.0",
    "gn:asciiname":"Bolonga",
    "gn:country_code":"CD",
    "gn:dem":418,
    "gn:feature_class":"P",
    "gn:feature_code":"PPL",
    "gn:name":"Bolonga",
    "gn:population":0,
    "gn:timezone":"Africa/Lubumbashi",
    "iso:country":"CD",
    "wof:name":"Bolonga",
    "wof:placetype":"locality"
},
  "geometry": {"coordinates":[23.51667,-0.46667],"type":"Point"}
}