{
  "type": "Feature",
  "properties": {
    "gn:admin1_code":"21.0",
    "gn:asciiname":"Panza",
    "gn:country_code":"CD",
    "gn:dem":863,
    "gn:feature_class":"P",
    "gn:feature_code":"PPL",
    "gn:name":"Panza",
    "gn:population":0,
    "gn:timezone":"Africa/Lubumbashi",
    "iso:country":"CD",
    "name:deu_x_preferred":[
        "Panza"
    ],
    "name:ita_x_preferred":[
        "Panza"
    ],
    "wof:name":"Panza",
    "wof:placetype":"locality"
},
  "geometry": {"coordinates":[24.27996,-6.00545],"type":"Point"}
}