{
  "type": "Feature",
  "properties": {
    "gn:admin1_code":"20.0",
    "gn:asciiname":"Kibulu",
    "gn:country_code":"CD",
    "gn:dem":693,
    "gn:feature_class":"P",
    "gn:feature_code":"PPL",
    "gn:name":"Kibulu",
    "gn:population":0,
    "gn:timezone":"Africa/Kinshasa",
    "iso:country":"CD",
    "wof:name":"Kibulu",
    "wof:placetype":"locality"
},
  "geometry": {"coordinates":[19.72103,-5.19901],"type":"Point"}
}