{
  "type": "Feature",
  "properties": {
    "gn:admin1_code":"29.0",
    "gn:asciiname":"Sanki",
    "gn:country_code":"CD",
    "gn:dem":662,
    "gn:feature_class":"P",
    "gn:feature_code":"PPL",
    "gn:name":"Sanki",
    "gn:population":0,
    "gn:timezone":"Africa/Lubumbashi",
    "iso:country":"CD",
    "wof:name":"Sanki",
    "wof:placetype":"locality"
},
  "geometry": {"coordinates":[27.06107,-5.27733],"type":"Point"}
}