{
  "type": "Feature",
  "properties": {
    "gn:admin1_code":"22.0",
    "gn:asciiname":"Kayambo",
    "gn:country_code":"CD",
    "gn:dem":1012,
    "gn:feature_class":"P",
    "gn:feature_code":"PPL",
    "gn:name":"Kayambo",
    "gn:population":0,
    "gn:timezone":"Africa/Lubumbashi",
    "iso:country":"CD",
    "wof:name":"Kayambo",
    "wof:placetype":"locality"
},
  "geometry": {"coordinates":[22.27372,-9.9757],"type":"Point"}
}