{
  "type": "Feature",
  "properties": {
    "gn:admin1_code":"19.0",
    "gn:asciiname":"Kipipa",
    "gn:country_code":"CD",
    "gn:dem":566,
    "gn:feature_class":"P",
    "gn:feature_code":"PPL",
    "gn:name":"Kipipa",
    "gn:population":0,
    "gn:timezone":"Africa/Kinshasa",
    "iso:country":"CD",
    "wof:name":"Kipipa",
    "wof:placetype":"locality"
},
  "geometry": {"coordinates":[17.06889,-4.87374],"type":"Point"}
}