{
  "type": "Feature",
  "properties": {
    "gn:admin1_code":"16.0",
    "gn:asciiname":"Tingbe",
    "gn:country_code":"CD",
    "gn:dem":679,
    "gn:feature_class":"P",
    "gn:feature_code":"PPL",
    "gn:name":"Tingbe",
    "gn:population":0,
    "gn:timezone":"Africa/Lubumbashi",
    "iso:country":"CD",
    "wof:name":"Tingbe",
    "wof:placetype":"locality"
},
  "geometry": {"coordinates":[27.30345,3.89729],"type":"Point"}
}