{
  "type": "Feature",
  "properties": {
    "gn:admin1_code":"23.0",
    "gn:asciiname":"Katende Deuxieme",
    "gn:country_code":"CD",
    "gn:dem":752,
    "gn:feature_class":"P",
    "gn:feature_code":"PPL",
    "gn:name":"Katende Deuxi\u00e8me",
    "gn:population":0,
    "gn:timezone":"Africa/Lubumbashi",
    "iso:country":"CD",
    "name:und_x_variant":[
        "Katende Deuxi\u00e8me",
        "Katende"
    ],
    "wof:name":"Katende Deuxieme",
    "wof:placetype":"locality"
},
  "geometry": {"coordinates":[22.39985,-6.319],"type":"Point"}
}