{
  "type": "Feature",
  "properties": {
    "gn:admin1_code":"28.0",
    "gn:asciiname":"Singu",
    "gn:country_code":"CD",
    "gn:dem":440,
    "gn:feature_class":"P",
    "gn:feature_code":"PPL",
    "gn:name":"Singu",
    "gn:population":0,
    "gn:timezone":"Africa/Kinshasa",
    "iso:country":"CD",
    "name:fra_x_preferred":[
        "Singu"
    ],
    "wof:name":"Singu",
    "wof:placetype":"locality"
},
  "geometry": {"coordinates":[19.90871,2.64353],"type":"Point"}
}