{
  "type": "Feature",
  "properties": {
    "gn:admin1_code":"24.0",
    "gn:asciiname":"Motoko",
    "gn:country_code":"CD",
    "gn:dem":361,
    "gn:feature_class":"P",
    "gn:feature_code":"PPL",
    "gn:name":"Motoko",
    "gn:population":0,
    "gn:timezone":"Africa/Kinshasa",
    "iso:country":"CD",
    "wof:name":"Motoko",
    "wof:placetype":"locality"
},
  "geometry": {"coordinates":[17.1189,-2.09048],"type":"Point"}
}