{
  "type": "Feature",
  "properties": {
    "gn:admin1_code":"8.0",
    "gn:asciiname":"Mbolo",
    "gn:country_code":"CD",
    "gn:dem":449,
    "gn:feature_class":"P",
    "gn:feature_code":"PPL",
    "gn:name":"Mbolo",
    "gn:population":0,
    "gn:timezone":"Africa/Kinshasa",
    "iso:country":"CD",
    "wof:name":"Mbolo",
    "wof:placetype":"locality"
},
  "geometry": {"coordinates":[15.46438,-4.61572],"type":"Point"}
}