{
  "type": "Feature",
  "properties": {
    "gn:admin1_code":"22.0",
    "gn:asciiname":"Nakulusu",
    "gn:country_code":"CD",
    "gn:dem":1022,
    "gn:feature_class":"P",
    "gn:feature_code":"PPL",
    "gn:name":"Nakulusu",
    "gn:population":0,
    "gn:timezone":"Africa/Lubumbashi",
    "iso:country":"CD",
    "name:und_x_variant":[
        "Nakulusa",
        "Nakulusu"
    ],
    "wof:name":"Nakulusu",
    "wof:placetype":"locality"
},
  "geometry": {"coordinates":[24.52955,-10.04627],"type":"Point"}
}