{
  "type": "Feature",
  "properties": {
    "gn:admin1_code":"14.0",
    "gn:asciiname":"Welgelegen",
    "gn:country_code":"CD",
    "gn:dem":1327,
    "gn:feature_class":"P",
    "gn:feature_code":"PPL",
    "gn:name":"Welgelegen",
    "gn:population":0,
    "gn:timezone":"Africa/Lubumbashi",
    "iso:country":"CD",
    "name:fry_x_preferred":[
        "Welgelegen"
    ],
    "name:ita_x_preferred":[
        "Welgelegen"
    ],
    "name:nld_x_preferred":[
        "Welgelegen"
    ],
    "name:spa_x_preferred":[
        "Welgelegen"
    ],
    "wof:name":"Welgelegen",
    "wof:placetype":"locality"
},
  "geometry": {"coordinates":[27.51889000000001,-12.08333],"type":"Point"}
}