{
  "type": "Feature",
  "properties": {
    "gn:admin1_code":"21.0",
    "gn:asciiname":"Komami",
    "gn:country_code":"CD",
    "gn:dem":697,
    "gn:feature_class":"P",
    "gn:feature_code":"PPL",
    "gn:name":"Komami",
    "gn:population":0,
    "gn:timezone":"Africa/Lubumbashi",
    "iso:country":"CD",
    "wof:name":"Komami",
    "wof:placetype":"locality"
},
  "geometry": {"coordinates":[25.81662,-5.47609],"type":"Point"}
}