{
  "type": "Feature",
  "properties": {
    "gn:admin1_code":"15.0",
    "gn:asciiname":"Tshiketa",
    "gn:country_code":"CD",
    "gn:dem":1007,
    "gn:feature_class":"P",
    "gn:feature_code":"PPL",
    "gn:name":"Tshiketa",
    "gn:population":0,
    "gn:timezone":"Africa/Lubumbashi",
    "iso:country":"CD",
    "wof:name":"Tshiketa",
    "wof:placetype":"locality"
},
  "geometry": {"coordinates":[24.38982,-7.92615],"type":"Point"}
}