{
  "type": "Feature",
  "properties": {
    "gn:admin1_code":"27.0",
    "gn:asciiname":"Ilebo",
    "gn:country_code":"CD",
    "gn:dem":488,
    "gn:feature_class":"P",
    "gn:feature_code":"PPL",
    "gn:name":"Ilebo",
    "gn:population":0,
    "gn:timezone":"Africa/Lubumbashi",
    "iso:country":"CD",
    "name:afr_x_preferred":[
        "Ilebo"
    ],
    "name:azb_x_preferred":[
        "\u0627\u06cc\u0644\u06cc\u0628\u0648"
    ],
    "name:cat_x_preferred":[
        "Ilebo"
    ],
    "name:ceb_x_preferred":[
        "Ilebo"
    ],
    "name:epo_x_preferred":[
        "Ilebo"
    ],
    "name:fas_x_preferred":[
        "\u0627\u06cc\u0644\u06cc\u0628\u0648"
    ],
    "name:fra_x_preferred":[
        "Ilebo"
    ],
    "name:hun_x_preferred":[
        "Ilebo"
    ],
    "name:ita_x_preferred":[
        "Ilebo"
    ],
    "name:jpn_x_preferred":[
        "\u30a4\u30ec\u30dc"
    ],
    "name:kat_x_preferred":[
        "\u10d8\u10da\u10d4\u10d1\u10dd"
    ],
    "name:kon_x_preferred":[
        "Ilebo"
    ],
    "name:kor_x_preferred":[
        "\uc77c\ub808\ubcf4"
    ],
    "name:lit_x_preferred":[
        "Ilebas"
    ],
    "name:nld_x_preferred":[
        "Ilebo"
    ],
    "name:pol_x_preferred":[
        "Ilebo"
    ],
    "name:ron_x_preferred":[
        "Ilebo"
    ],
    "name:rus_x_preferred":[
        "\u0418\u043b\u0435\u0431\u043e"
    ],
    "name:spa_x_preferred":[
        "Ilebo"
    ],
    "name:srp_x_preferred":[
        "\u0418\u043b\u0435\u0431\u043e"
    ],
    "name:swa_x_preferred":[
        "Ilebo"
    ],
    "name:swe_x_preferred":[
        "Ilebo"
    ],
    "name:tgl_x_preferred":[
        "Ilebo"
    ],
    "name:ukr_x_preferred":[
        "\u0406\u043b\u0435\u0431\u043e"
    ],
    "name:xmf_x_preferred":[
        "\u10d8\u10da\u10d4\u10d1\u10dd"
    ],
    "name:zho_x_preferred":[
        "\u4f0a\u840a\u535a"
    ],
    "wof:name":"Ilebo",
    "wof:placetype":"locality"
},
  "geometry": {"coordinates":[23.89188,-4.82437],"type":"Point"}
}