{
  "type": "Feature",
  "properties": {
    "gn:admin1_code":"28.0",
    "gn:asciiname":"Kamba",
    "gn:country_code":"CD",
    "gn:dem":357,
    "gn:feature_class":"P",
    "gn:feature_code":"PPL",
    "gn:name":"Kamba",
    "gn:population":0,
    "gn:timezone":"Africa/Kinshasa",
    "iso:country":"CD",
    "name:ceb_x_preferred":[
        "Kamba"
    ],
    "name:deu_x_preferred":[
        "Kamba"
    ],
    "name:fra_x_preferred":[
        "Kamba"
    ],
    "name:nld_x_preferred":[
        "Kamba"
    ],
    "name:slv_x_preferred":[
        "Kamba"
    ],
    "name:swa_x_preferred":[
        "Kamba"
    ],
    "name:swe_x_preferred":[
        "Kamba"
    ],
    "name:und_x_variant":[
        "Kanda"
    ],
    "wof:name":"Kamba",
    "wof:placetype":"locality"
},
  "geometry": {"coordinates":[18.80106,3.10125],"type":"Point"}
}