{
  "type": "Feature",
  "properties": {
    "gn:admin1_code":"26.0",
    "gn:asciiname":"Modjengo",
    "gn:country_code":"CD",
    "gn:dem":427,
    "gn:feature_class":"P",
    "gn:feature_code":"PPL",
    "gn:name":"Modjengo",
    "gn:population":0,
    "gn:timezone":"Africa/Kinshasa",
    "iso:country":"CD",
    "name:und_x_variant":[
        "Mondjengo",
        "Modjengo"
    ],
    "wof:name":"Modjengo",
    "wof:placetype":"locality"
},
  "geometry": {"coordinates":[21.02765,3.09423],"type":"Point"}
}