{
  "type": "Feature",
  "properties": {
    "gn:admin1_code":"8.0",
    "gn:asciiname":"Ngoyo Moka",
    "gn:country_code":"CD",
    "gn:dem":107,
    "gn:feature_class":"P",
    "gn:feature_code":"PPL",
    "gn:name":"Ngoyo Moka",
    "gn:population":0,
    "gn:timezone":"Africa/Kinshasa",
    "iso:country":"CD",
    "wof:name":"Ngoyo Moka",
    "wof:placetype":"locality"
},
  "geometry": {"coordinates":[12.40725,-5.83365],"type":"Point"}
}