{
  "type": "Feature",
  "properties": {
    "gn:admin1_code":"21.0",
    "gn:asciiname":"Tshilombe",
    "gn:country_code":"CD",
    "gn:dem":856,
    "gn:feature_class":"P",
    "gn:feature_code":"PPL",
    "gn:name":"Tshilombe",
    "gn:population":0,
    "gn:timezone":"Africa/Lubumbashi",
    "iso:country":"CD",
    "wof:name":"Tshilombe",
    "wof:placetype":"locality"
},
  "geometry": {"coordinates":[23.39625,-7.19182],"type":"Point"}
}