{
  "type": "Feature",
  "properties": {
    "gn:admin1_code":"17.0",
    "gn:asciiname":"Tali-Tali",
    "gn:country_code":"CD",
    "gn:dem":1332,
    "gn:feature_class":"P",
    "gn:feature_code":"PPL",
    "gn:name":"Tali-Tali",
    "gn:population":0,
    "gn:timezone":"Africa/Lubumbashi",
    "iso:country":"CD",
    "wof:name":"Tali-Tali",
    "wof:placetype":"locality"
},
  "geometry": {"coordinates":[30.51749,2.51841],"type":"Point"}
}