{
  "type": "Feature",
  "properties": {
    "gn:admin1_code":"8.0",
    "gn:asciiname":"Kibueya",
    "gn:country_code":"CD",
    "gn:dem":567,
    "gn:feature_class":"P",
    "gn:feature_code":"PPL",
    "gn:name":"Kibueya",
    "gn:population":0,
    "gn:timezone":"Africa/Kinshasa",
    "iso:country":"CD",
    "wof:name":"Kibueya",
    "wof:placetype":"locality"
},
  "geometry": {"coordinates":[13.62903,-4.98137],"type":"Point"}
}