{
  "type": "Feature",
  "properties": {
    "gn:admin1_code":"18.0",
    "gn:asciiname":"Dibaya",
    "gn:country_code":"CD",
    "gn:dem":587,
    "gn:feature_class":"P",
    "gn:feature_code":"PPL",
    "gn:name":"Dibaya",
    "gn:population":0,
    "gn:timezone":"Africa/Lubumbashi",
    "iso:country":"CD",
    "name:fra_x_preferred":[
        "Dibaya"
    ],
    "name:ron_x_preferred":[
        "Dibaya"
    ],
    "wof:name":"Dibaya",
    "wof:placetype":"locality"
},
  "geometry": {"coordinates":[20.94347,-6.89406],"type":"Point"}
}