{
  "type": "Feature",
  "properties": {
    "gn:admin1_code":"24.0",
    "gn:asciiname":"Bolula",
    "gn:country_code":"CD",
    "gn:dem":305,
    "gn:feature_class":"P",
    "gn:feature_code":"PPL",
    "gn:name":"Bolula",
    "gn:population":0,
    "gn:timezone":"Africa/Kinshasa",
    "iso:country":"CD",
    "name:und_x_variant":[
        "Boluba",
        "Bolula"
    ],
    "wof:name":"Bolula",
    "wof:placetype":"locality"
},
  "geometry": {"coordinates":[18.05,-1.51667],"type":"Point"}
}