{
  "type": "Feature",
  "properties": {
    "gn:admin1_code":"22.0",
    "gn:asciiname":"Sambaz",
    "gn:country_code":"CD",
    "gn:dem":976,
    "gn:feature_class":"P",
    "gn:feature_code":"PPL",
    "gn:name":"Sambaz",
    "gn:population":0,
    "gn:timezone":"Africa/Lubumbashi",
    "iso:country":"CD",
    "name:und_x_variant":[
        "Sambaza"
    ],
    "wof:name":"Sambaz",
    "wof:placetype":"locality"
},
  "geometry": {"coordinates":[22.79001,-8.19901],"type":"Point"}
}