{
  "type": "Feature",
  "properties": {
    "gn:admin1_code":"22.0",
    "gn:asciiname":"Kabelenge",
    "gn:country_code":"CD",
    "gn:dem":908,
    "gn:feature_class":"P",
    "gn:feature_code":"PPL",
    "gn:name":"Kabelenge",
    "gn:population":0,
    "gn:timezone":"Africa/Lubumbashi",
    "iso:country":"CD",
    "name:und_x_variant":[
        "Kabilenge"
    ],
    "wof:name":"Kabelenge",
    "wof:placetype":"locality"
},
  "geometry": {"coordinates":[22.81895,-9.7649],"type":"Point"}
}