{
  "type": "Feature",
  "properties": {
    "gn:admin1_code":"13.0",
    "gn:asciiname":"Limo",
    "gn:country_code":"CD",
    "gn:dem":612,
    "gn:feature_class":"P",
    "gn:feature_code":"PPL",
    "gn:name":"Limo",
    "gn:population":0,
    "gn:timezone":"Africa/Lubumbashi",
    "iso:country":"CD",
    "name:arg_x_preferred":[
        "Limo"
    ],
    "name:ceb_x_preferred":[
        "Limo"
    ],
    "name:deu_x_preferred":[
        "Limo"
    ],
    "name:epo_x_preferred":[
        "Limo"
    ],
    "name:fin_x_preferred":[
        "Limo"
    ],
    "name:fra_x_preferred":[
        "Limo"
    ],
    "name:ita_x_preferred":[
        "Limo"
    ],
    "name:nld_x_preferred":[
        "Limo"
    ],
    "name:pol_x_preferred":[
        "Limo"
    ],
    "name:swe_x_preferred":[
        "Limo"
    ],
    "wof:name":"Limo",
    "wof:placetype":"locality"
},
  "geometry": {"coordinates":[25.97383,2.50926],"type":"Point"}
}