{
  "type": "Feature",
  "properties": {
    "gn:admin1_code":"27.0",
    "gn:asciiname":"Okania",
    "gn:country_code":"CD",
    "gn:dem":554,
    "gn:feature_class":"P",
    "gn:feature_code":"PPL",
    "gn:name":"Okania",
    "gn:population":0,
    "gn:timezone":"Africa/Lubumbashi",
    "iso:country":"CD",
    "wof:name":"Okania",
    "wof:placetype":"locality"
},
  "geometry": {"coordinates":[22.63333,-2.85],"type":"Point"}
}