{
  "type": "Feature",
  "properties": {
    "gn:admin1_code":"19.0",
    "gn:asciiname":"Mwakatende",
    "gn:country_code":"CD",
    "gn:dem":899,
    "gn:feature_class":"P",
    "gn:feature_code":"PPL",
    "gn:name":"Mwakatende",
    "gn:population":0,
    "gn:timezone":"Africa/Kinshasa",
    "iso:country":"CD",
    "wof:name":"Mwakatende",
    "wof:placetype":"locality"
},
  "geometry": {"coordinates":[19.74487,-6.90859],"type":"Point"}
}