{
  "type": "Feature",
  "properties": {
    "gn:admin1_code":"25.0",
    "gn:asciiname":"Yamombenga",
    "gn:country_code":"CD",
    "gn:dem":381,
    "gn:feature_class":"P",
    "gn:feature_code":"PPL",
    "gn:name":"Yamombenga",
    "gn:population":0,
    "gn:timezone":"Africa/Kinshasa",
    "iso:country":"CD",
    "wof:name":"Yamombenga",
    "wof:placetype":"locality"
},
  "geometry": {"coordinates":[22.48603,2.24707],"type":"Point"}
}