{
  "type": "Feature",
  "properties": {
    "gn:admin1_code":"8.0",
    "gn:asciiname":"Kitumba",
    "gn:country_code":"CD",
    "gn:dem":809,
    "gn:feature_class":"P",
    "gn:feature_code":"PPL",
    "gn:name":"Kitumba",
    "gn:population":0,
    "gn:timezone":"Africa/Kinshasa",
    "iso:country":"CD",
    "wof:name":"Kitumba",
    "wof:placetype":"locality"
},
  "geometry": {"coordinates":[15.07796,-5.49909],"type":"Point"}
}