{
  "type": "Feature",
  "properties": {
    "gn:admin1_code":"8.0",
    "gn:asciiname":"Mabuidi",
    "gn:country_code":"CD",
    "gn:dem":580,
    "gn:feature_class":"P",
    "gn:feature_code":"PPL",
    "gn:name":"Mabuidi",
    "gn:population":0,
    "gn:timezone":"Africa/Kinshasa",
    "iso:country":"CD",
    "name:und_x_variant":[
        "Mabidi"
    ],
    "wof:name":"Mabuidi",
    "wof:placetype":"locality"
},
  "geometry": {"coordinates":[13.85089,-4.61471],"type":"Point"}
}