{
  "type": "Feature",
  "properties": {
    "gn:admin1_code":"14.0",
    "gn:asciiname":"Katete",
    "gn:country_code":"CD",
    "gn:dem":1081,
    "gn:feature_class":"P",
    "gn:feature_code":"PPL",
    "gn:name":"Katete",
    "gn:population":0,
    "gn:timezone":"Africa/Lubumbashi",
    "iso:country":"CD",
    "name:bul_x_preferred":[
        "\u041a\u0430\u0442\u0435\u0442\u0435"
    ],
    "name:deu_x_preferred":[
        "Katete"
    ],
    "name:ita_x_preferred":[
        "Katete"
    ],
    "name:mrj_x_preferred":[
        "\u041a\u0430\u0442\u0435\u0442\u0435"
    ],
    "name:pol_x_preferred":[
        "Katete"
    ],
    "name:por_x_preferred":[
        "Katete"
    ],
    "name:ron_x_preferred":[
        "Katete"
    ],
    "name:spa_x_preferred":[
        "Katete"
    ],
    "name:und_x_variant":[
        "Kalele"
    ],
    "name:zho_x_preferred":[
        "\u5361\u6cf0\u7279"
    ],
    "wof:name":"Katete",
    "wof:placetype":"locality"
},
  "geometry": {"coordinates":[27.90089,-10.91096],"type":"Point"}
}