{
  "type": "Feature",
  "properties": {
    "gn:admin1_code":"14.0",
    "gn:asciiname":"Katete",
    "gn:country_code":"CD",
    "gn:dem":1081,
    "gn:feature_class":"P",
    "gn:feature_code":"PPL",
    "gn:name":"Katete",
    "gn:population":0,
    "gn:timezone":"Africa/Lubumbashi",
    "iso:country":"CD",
    "name:und_x_variant":[
        "Kalele",
        "Katete"
    ],
    "wof:name":"Katete",
    "wof:placetype":"locality"
},
  "geometry": {"coordinates":[27.90089,-10.91096],"type":"Point"}
}