{
  "type": "Feature",
  "properties": {
    "gn:admin1_code":"16.0",
    "gn:asciiname":"Katukunane",
    "gn:country_code":"CD",
    "gn:dem":840,
    "gn:feature_class":"P",
    "gn:feature_code":"PPL",
    "gn:name":"Katukunane",
    "gn:population":0,
    "gn:timezone":"Africa/Lubumbashi",
    "iso:country":"CD",
    "wof:name":"Katukunane",
    "wof:placetype":"locality"
},
  "geometry": {"coordinates":[27.74553,2.60086],"type":"Point"}
}