{
  "type": "Feature",
  "properties": {
    "gn:admin1_code":"21.0",
    "gn:asciiname":"Kibandila",
    "gn:country_code":"CD",
    "gn:dem":929,
    "gn:feature_class":"P",
    "gn:feature_code":"PPL",
    "gn:name":"Kibandila",
    "gn:population":0,
    "gn:timezone":"Africa/Lubumbashi",
    "iso:country":"CD",
    "wof:name":"Kibandila",
    "wof:placetype":"locality"
},
  "geometry": {"coordinates":[25.11701,-6.54522],"type":"Point"}
}