{
  "type": "Feature",
  "properties": {
    "gn:admin1_code":"23.0",
    "gn:asciiname":"Kalombela",
    "gn:country_code":"CD",
    "gn:dem":664,
    "gn:feature_class":"P",
    "gn:feature_code":"PPL",
    "gn:name":"Kalombela",
    "gn:population":0,
    "gn:timezone":"Africa/Lubumbashi",
    "iso:country":"CD",
    "wof:name":"Kalombela",
    "wof:placetype":"locality"
},
  "geometry": {"coordinates":[22.0439,-6.02342],"type":"Point"}
}