{
  "type": "Feature",
  "properties": {
    "gn:admin1_code":"27.0",
    "gn:asciiname":"Lekama",
    "gn:country_code":"CD",
    "gn:dem":656,
    "gn:feature_class":"P",
    "gn:feature_code":"PPL",
    "gn:name":"Lekama",
    "gn:population":0,
    "gn:timezone":"Africa/Lubumbashi",
    "iso:country":"CD",
    "wof:name":"Lekama",
    "wof:placetype":"locality"
},
  "geometry": {"coordinates":[24.49983,-4.66411],"type":"Point"}
}