{
  "type": "Feature",
  "properties": {
    "gn:admin1_code":"30.0",
    "gn:asciiname":"Basua",
    "gn:country_code":"CD",
    "gn:dem":418,
    "gn:feature_class":"P",
    "gn:feature_code":"PPL",
    "gn:name":"Basua",
    "gn:population":0,
    "gn:timezone":"Africa/Lubumbashi",
    "iso:country":"CD",
    "wof:name":"Basua",
    "wof:placetype":"locality"
},
  "geometry": {"coordinates":[25.40298,-0.5168],"type":"Point"}
}