{
  "type": "Feature",
  "properties": {
    "gn:admin1_code":"28.0",
    "gn:asciiname":"Busu-Likulu",
    "gn:country_code":"CD",
    "gn:dem":362,
    "gn:feature_class":"P",
    "gn:feature_code":"PPL",
    "gn:name":"Busu-Likulu",
    "gn:population":0,
    "gn:timezone":"Africa/Kinshasa",
    "iso:country":"CD",
    "name:fra_x_preferred":[
        "Busu-Likulu"
    ],
    "wof:name":"Busu-Likulu",
    "wof:placetype":"locality"
},
  "geometry": {"coordinates":[19.10509,2.41599],"type":"Point"}
}