{
  "type": "Feature",
  "properties": {
    "gn:admin1_code":"31.0",
    "gn:asciiname":"Bosangu",
    "gn:country_code":"CD",
    "gn:dem":369,
    "gn:feature_class":"P",
    "gn:feature_code":"PPL",
    "gn:name":"Bosangu",
    "gn:population":0,
    "gn:timezone":"Africa/Kinshasa",
    "iso:country":"CD",
    "wof:name":"Bosangu",
    "wof:placetype":"locality"
},
  "geometry": {"coordinates":[21.81667,0.13333],"type":"Point"}
}