{
  "type": "Feature",
  "properties": {
    "gn:admin1_code":"19.0",
    "gn:asciiname":"Mobingu",
    "gn:country_code":"CD",
    "gn:dem":857,
    "gn:feature_class":"P",
    "gn:feature_code":"PPL",
    "gn:name":"Mobingu",
    "gn:population":0,
    "gn:timezone":"Africa/Kinshasa",
    "iso:country":"CD",
    "wof:name":"Mobingu",
    "wof:placetype":"locality"
},
  "geometry": {"coordinates":[17.9357,-5.87804],"type":"Point"}
}