{
  "type": "Feature",
  "properties": {
    "gn:admin1_code":"8.0",
    "gn:asciiname":"Madimba-Lundu",
    "gn:country_code":"CD",
    "gn:dem":591,
    "gn:feature_class":"P",
    "gn:feature_code":"PPL",
    "gn:name":"Madimba-Lundu",
    "gn:population":0,
    "gn:timezone":"Africa/Kinshasa",
    "iso:country":"CD",
    "wof:name":"Madimba-Lundu",
    "wof:placetype":"locality"
},
  "geometry": {"coordinates":[14.12533,-4.57248],"type":"Point"}
}