{
  "type": "Feature",
  "properties": {
    "gn:admin1_code":"24.0",
    "gn:asciiname":"Enkutu",
    "gn:country_code":"CD",
    "gn:dem":326,
    "gn:feature_class":"P",
    "gn:feature_code":"PPL",
    "gn:name":"Enkutu",
    "gn:population":0,
    "gn:timezone":"Africa/Kinshasa",
    "iso:country":"CD",
    "wof:name":"Enkutu",
    "wof:placetype":"locality"
},
  "geometry": {"coordinates":[18.68966,-3.05553],"type":"Point"}
}