{
  "type": "Feature",
  "properties": {
    "gn:admin1_code":"19.0",
    "gn:asciiname":"Bangala",
    "gn:country_code":"CD",
    "gn:dem":498,
    "gn:feature_class":"P",
    "gn:feature_code":"PPL",
    "gn:name":"Bangala",
    "gn:population":0,
    "gn:timezone":"Africa/Luanda",
    "iso:country":"CD",
    "wof:name":"Bangala",
    "wof:placetype":"locality"
},
  "geometry": {"coordinates":[16.85,-6.81667],"type":"Point"}
}