{
  "type": "Feature",
  "properties": {
    "gn:admin1_code":"19.0",
    "gn:asciiname":"Kipaka",
    "gn:country_code":"CD",
    "gn:dem":886,
    "gn:feature_class":"P",
    "gn:feature_code":"PPL",
    "gn:name":"Kipaka",
    "gn:population":0,
    "gn:timezone":"Africa/Kinshasa",
    "iso:country":"CD",
    "wof:name":"Kipaka",
    "wof:placetype":"locality"
},
  "geometry": {"coordinates":[18.17641,-6.34429],"type":"Point"}
}