{
  "type": "Feature",
  "properties": {
    "gn:admin1_code":"21.0",
    "gn:asciiname":"Kibunge",
    "gn:country_code":"CD",
    "gn:dem":778,
    "gn:feature_class":"P",
    "gn:feature_code":"PPL",
    "gn:name":"Kibunge",
    "gn:population":0,
    "gn:timezone":"Africa/Lubumbashi",
    "iso:country":"CD",
    "wof:name":"Kibunge",
    "wof:placetype":"locality"
},
  "geometry": {"coordinates":[24.7491,-6.18869],"type":"Point"}
}