{
  "type": "Feature",
  "properties": {
    "gn:admin1_code":"17.0",
    "gn:asciiname":"Daraza",
    "gn:country_code":"CD",
    "gn:dem":1378,
    "gn:feature_class":"P",
    "gn:feature_code":"PPL",
    "gn:name":"Daraza",
    "gn:population":0,
    "gn:timezone":"Africa/Lubumbashi",
    "iso:country":"CD",
    "name:fas_x_preferred":[
        "\u062f\u0631\u0627\u0632\u0647"
    ],
    "name:snd_x_preferred":[
        "\u062f\u0631\u0627\u0632\u0627"
    ],
    "name:urd_x_preferred":[
        "\u062f\u0631\u0627\u0632\u0627"
    ],
    "wof:name":"Daraza",
    "wof:placetype":"locality"
},
  "geometry": {"coordinates":[30.02095,1.13881],"type":"Point"}
}