{
  "type": "Feature",
  "properties": {
    "gn:admin1_code":"13.0",
    "gn:asciiname":"Gbiliwa",
    "gn:country_code":"CD",
    "gn:dem":717,
    "gn:feature_class":"P",
    "gn:feature_code":"PPL",
    "gn:name":"Gbiliwa",
    "gn:population":0,
    "gn:timezone":"Africa/Lubumbashi",
    "iso:country":"CD",
    "wof:name":"Gbiliwa",
    "wof:placetype":"locality"
},
  "geometry": {"coordinates":[27.39916,3.26242],"type":"Point"}
}