{
  "type": "Feature",
  "properties": {
    "gn:admin1_code":"18.0",
    "gn:asciiname":"Ineme",
    "gn:country_code":"CD",
    "gn:dem":571,
    "gn:feature_class":"P",
    "gn:feature_code":"PPL",
    "gn:name":"Ineme",
    "gn:population":0,
    "gn:timezone":"Africa/Lubumbashi",
    "iso:country":"CD",
    "name:und_x_variant":[
        "Neme",
        "Neme Pungu",
        "Ineme"
    ],
    "wof:name":"Ineme",
    "wof:placetype":"locality"
},
  "geometry": {"coordinates":[21.83725,-4.97876],"type":"Point"}
}