{
  "type": "Feature",
  "properties": {
    "gn:admin1_code":"30.0",
    "gn:asciiname":"Babugombe",
    "gn:country_code":"CD",
    "gn:dem":705,
    "gn:feature_class":"P",
    "gn:feature_code":"PPL",
    "gn:name":"Babugombe",
    "gn:population":0,
    "gn:timezone":"Africa/Lubumbashi",
    "iso:country":"CD",
    "name:und_x_variant":[
        "Babogombe"
    ],
    "wof:name":"Babugombe",
    "wof:placetype":"locality"
},
  "geometry": {"coordinates":[27.24201,0.42107],"type":"Point"}
}