{
  "type": "Feature",
  "properties": {
    "gn:admin1_code":"18.0",
    "gn:asciiname":"Lupanga",
    "gn:country_code":"CD",
    "gn:dem":639,
    "gn:feature_class":"P",
    "gn:feature_code":"PPL",
    "gn:name":"Lupanga",
    "gn:population":0,
    "gn:timezone":"Africa/Lubumbashi",
    "iso:country":"CD",
    "name:ceb_x_preferred":[
        "Lupanga"
    ],
    "name:swa_x_preferred":[
        "Mlima Lupanga"
    ],
    "wof:name":"Lupanga",
    "wof:placetype":"locality"
},
  "geometry": {"coordinates":[20.58591,-6.35084],"type":"Point"}
}