{
  "type": "Feature",
  "properties": {
    "gn:admin1_code":"29.0",
    "gn:asciiname":"Sangwa",
    "gn:country_code":"CD",
    "gn:dem":1344,
    "gn:feature_class":"P",
    "gn:feature_code":"PPL",
    "gn:name":"Sangwa",
    "gn:population":0,
    "gn:timezone":"Africa/Lubumbashi",
    "iso:country":"CD",
    "wof:name":"Sangwa",
    "wof:placetype":"locality"
},
  "geometry": {"coordinates":[29.05944,-5.23306],"type":"Point"}
}