{
  "type": "Feature",
  "properties": {
    "gn:admin1_code":"15.0",
    "gn:asciiname":"Kalemba",
    "gn:country_code":"CD",
    "gn:dem":855,
    "gn:feature_class":"P",
    "gn:feature_code":"PPL",
    "gn:name":"Kalemba",
    "gn:population":0,
    "gn:timezone":"Africa/Lubumbashi",
    "iso:country":"CD",
    "name:und_x_variant":[
        "Kilemba",
        "Kalemba"
    ],
    "wof:name":"Kalemba",
    "wof:placetype":"locality"
},
  "geometry": {"coordinates":[24.66667,-9.68333],"type":"Point"}
}