{
  "type": "Feature",
  "properties": {
    "gn:admin1_code":"13.0",
    "gn:asciiname":"Kalea",
    "gn:country_code":"CD",
    "gn:dem":556,
    "gn:feature_class":"P",
    "gn:feature_code":"PPL",
    "gn:name":"Kalea",
    "gn:population":0,
    "gn:timezone":"Africa/Lubumbashi",
    "iso:country":"CD",
    "wof:name":"Kalea",
    "wof:placetype":"locality"
},
  "geometry": {"coordinates":[24.20052,4.44778],"type":"Point"}
}