{
  "type": "Feature",
  "properties": {
    "gn:admin1_code":"28.0",
    "gn:asciiname":"Bokonge",
    "gn:country_code":"CD",
    "gn:dem":351,
    "gn:feature_class":"P",
    "gn:feature_code":"PPL",
    "gn:name":"Bokonge",
    "gn:population":0,
    "gn:timezone":"Africa/Kinshasa",
    "iso:country":"CD",
    "wof:name":"Bokonge",
    "wof:placetype":"locality"
},
  "geometry": {"coordinates":[20.76248,2.77106],"type":"Point"}
}