{
  "type": "Feature",
  "properties": {
    "gn:admin1_code":"21.0",
    "gn:asciiname":"Kibwe",
    "gn:country_code":"CD",
    "gn:dem":888,
    "gn:feature_class":"P",
    "gn:feature_code":"PPL",
    "gn:name":"Kibwe",
    "gn:population":0,
    "gn:timezone":"Africa/Lubumbashi",
    "iso:country":"CD",
    "wof:name":"Kibwe",
    "wof:placetype":"locality"
},
  "geometry": {"coordinates":[24.99194,-6.59728],"type":"Point"}
}