{
  "type": "Feature",
  "properties": {
    "gn:admin1_code":"8.0",
    "gn:asciiname":"Kuyi",
    "gn:country_code":"CD",
    "gn:dem":255,
    "gn:feature_class":"P",
    "gn:feature_code":"PPL",
    "gn:name":"Kuyi",
    "gn:population":0,
    "gn:timezone":"Africa/Kinshasa",
    "iso:country":"CD",
    "wof:name":"Kuyi",
    "wof:placetype":"locality"
},
  "geometry": {"coordinates":[13.64078,-5.8202],"type":"Point"}
}