{
  "type": "Feature",
  "properties": {
    "gn:admin1_code":"20.0",
    "gn:asciiname":"Kinzamba-Nzombi",
    "gn:country_code":"CD",
    "gn:dem":695,
    "gn:feature_class":"P",
    "gn:feature_code":"PPL",
    "gn:name":"Kinzamba-Nzombi",
    "gn:population":0,
    "gn:timezone":"Africa/Kinshasa",
    "iso:country":"CD",
    "wof:name":"Kinzamba-Nzombi",
    "wof:placetype":"locality"
},
  "geometry": {"coordinates":[17.97339,-5.2149],"type":"Point"}
}