{
  "type": "Feature",
  "properties": {
    "gn:admin1_code":"13.0",
    "gn:asciiname":"Dimboli",
    "gn:country_code":"CD",
    "gn:dem":427,
    "gn:feature_class":"P",
    "gn:feature_code":"PPL",
    "gn:name":"Dimboli",
    "gn:population":0,
    "gn:timezone":"Africa/Lubumbashi",
    "iso:country":"CD",
    "wof:name":"Dimboli",
    "wof:placetype":"locality"
},
  "geometry": {"coordinates":[23.62406,2.58983],"type":"Point"}
}