{
  "type": "Feature",
  "properties": {
    "gn:admin1_code":"28.0",
    "gn:asciiname":"Liosinga",
    "gn:country_code":"CD",
    "gn:dem":334,
    "gn:feature_class":"P",
    "gn:feature_code":"PPL",
    "gn:name":"Liosinga",
    "gn:population":0,
    "gn:timezone":"Africa/Kinshasa",
    "iso:country":"CD",
    "wof:name":"Liosinga",
    "wof:placetype":"locality"
},
  "geometry": {"coordinates":[18.97325,2.23032],"type":"Point"}
}