{
  "type": "Feature",
  "properties": {
    "gn:admin1_code":"31.0",
    "gn:asciiname":"Yalongonde",
    "gn:country_code":"CD",
    "gn:dem":440,
    "gn:feature_class":"P",
    "gn:feature_code":"PPL",
    "gn:name":"Yalongonde",
    "gn:population":0,
    "gn:timezone":"Africa/Kinshasa",
    "iso:country":"CD",
    "name:und_x_variant":[
        "Yalongondo",
        "Yalongonde"
    ],
    "wof:name":"Yalongonde",
    "wof:placetype":"locality"
},
  "geometry": {"coordinates":[22.86667000000001,-1.25],"type":"Point"}
}