{
  "type": "Feature",
  "properties": {
    "gn:admin1_code":"22.0",
    "gn:asciiname":"Sakasuanga",
    "gn:country_code":"CD",
    "gn:dem":1017,
    "gn:feature_class":"P",
    "gn:feature_code":"PPL",
    "gn:name":"Sakasuanga",
    "gn:population":0,
    "gn:timezone":"Africa/Lubumbashi",
    "iso:country":"CD",
    "wof:name":"Sakasuanga",
    "wof:placetype":"locality"
},
  "geometry": {"coordinates":[22.12343,-9.83108],"type":"Point"}
}