{
  "type": "Feature",
  "properties": {
    "gn:admin1_code":"23.0",
    "gn:asciiname":"Kasombo",
    "gn:country_code":"CD",
    "gn:dem":913,
    "gn:feature_class":"P",
    "gn:feature_code":"PPL",
    "gn:name":"Kasombo",
    "gn:population":0,
    "gn:timezone":"Africa/Lubumbashi",
    "iso:country":"CD",
    "wof:name":"Kasombo",
    "wof:placetype":"locality"
},
  "geometry": {"coordinates":[22.14582,-7.59597],"type":"Point"}
}