{
  "type": "Feature",
  "properties": {
    "gn:admin1_code":"14.0",
    "gn:asciiname":"Mwango",
    "gn:country_code":"CD",
    "gn:dem":837,
    "gn:feature_class":"P",
    "gn:feature_code":"PPL",
    "gn:name":"Mwango",
    "gn:population":0,
    "gn:timezone":"Africa/Lubumbashi",
    "iso:country":"CD",
    "wof:name":"Mwango",
    "wof:placetype":"locality"
},
  "geometry": {"coordinates":[27.02086,-9.45297],"type":"Point"}
}