{
  "type": "Feature",
  "properties": {
    "gn:admin1_code":"23.0",
    "gn:asciiname":"Kamba-Mvula",
    "gn:country_code":"CD",
    "gn:dem":712,
    "gn:feature_class":"P",
    "gn:feature_code":"PPL",
    "gn:name":"Kamba-Mvula",
    "gn:population":0,
    "gn:timezone":"Africa/Lubumbashi",
    "iso:country":"CD",
    "wof:name":"Kamba-Mvula",
    "wof:placetype":"locality"
},
  "geometry": {"coordinates":[22.82384,-5.78174],"type":"Point"}
}