{
  "type": "Feature",
  "properties": {
    "gn:admin1_code":"14.0",
    "gn:asciiname":"Tshangola",
    "gn:country_code":"CD",
    "gn:dem":1141,
    "gn:feature_class":"P",
    "gn:feature_code":"PPL",
    "gn:name":"Tshangola",
    "gn:population":0,
    "gn:timezone":"Africa/Lubumbashi",
    "iso:country":"CD",
    "wof:name":"Tshangola",
    "wof:placetype":"locality"
},
  "geometry": {"coordinates":[26.89194,-10.77833],"type":"Point"}
}