{
  "type": "Feature",
  "properties": {
    "gn:admin1_code":"11.0",
    "gn:asciiname":"Kalehe",
    "gn:country_code":"CD",
    "gn:dem":1345,
    "gn:feature_class":"P",
    "gn:feature_code":"PPL",
    "gn:name":"Kalehe",
    "gn:population":0,
    "gn:timezone":"Africa/Lubumbashi",
    "iso:country":"CD",
    "wof:name":"Kalehe",
    "wof:placetype":"locality"
},
  "geometry": {"coordinates":[29.48175,-1.16845],"type":"Point"}
}