{
  "type": "Feature",
  "properties": {
    "gn:admin1_code":"26.0",
    "gn:asciiname":"Gasamba",
    "gn:country_code":"CD",
    "gn:dem":404,
    "gn:feature_class":"P",
    "gn:feature_code":"PPL",
    "gn:name":"Gasamba",
    "gn:population":0,
    "gn:timezone":"Africa/Kinshasa",
    "iso:country":"CD",
    "wof:name":"Gasamba",
    "wof:placetype":"locality"
},
  "geometry": {"coordinates":[22.43317,4.11351],"type":"Point"}
}