{
  "type": "Feature",
  "properties": {
    "gn:admin1_code":"13.0",
    "gn:asciiname":"Angangasi",
    "gn:country_code":"CD",
    "gn:dem":584,
    "gn:feature_class":"P",
    "gn:feature_code":"PPL",
    "gn:name":"Angangasi",
    "gn:population":0,
    "gn:timezone":"Africa/Lubumbashi",
    "iso:country":"CD",
    "wof:name":"Angangasi",
    "wof:placetype":"locality"
},
  "geometry": {"coordinates":[25.62657,3.2208],"type":"Point"}
}