{
  "type": "Feature",
  "properties": {
    "gn:admin1_code":"22.0",
    "gn:asciiname":"Samuhalila",
    "gn:country_code":"CD",
    "gn:dem":1032,
    "gn:feature_class":"P",
    "gn:feature_code":"PPL",
    "gn:name":"Samuhalila",
    "gn:population":0,
    "gn:timezone":"Africa/Lubumbashi",
    "iso:country":"CD",
    "wof:name":"Samuhalila",
    "wof:placetype":"locality"
},
  "geometry": {"coordinates":[22.34643,-10.66784],"type":"Point"}
}