{
  "type": "Feature",
  "properties": {
    "gn:admin1_code":"11.0",
    "gn:asciiname":"Ngesho",
    "gn:country_code":"CD",
    "gn:dem":1902,
    "gn:feature_class":"P",
    "gn:feature_code":"PPL",
    "gn:name":"Ngesho",
    "gn:population":0,
    "gn:timezone":"Africa/Lubumbashi",
    "iso:country":"CD",
    "wof:name":"Ngesho",
    "wof:placetype":"locality"
},
  "geometry": {"coordinates":[29.10742,-1.29111],"type":"Point"}
}