{
  "type": "Feature",
  "properties": {
    "gn:admin1_code":"16.0",
    "gn:asciiname":"Magobo",
    "gn:country_code":"CD",
    "gn:dem":769,
    "gn:feature_class":"P",
    "gn:feature_code":"PPL",
    "gn:name":"Magobo",
    "gn:population":0,
    "gn:timezone":"Africa/Lubumbashi",
    "iso:country":"CD",
    "wof:name":"Magobo",
    "wof:placetype":"locality"
},
  "geometry": {"coordinates":[29.40685,3.28503],"type":"Point"}
}