{
  "type": "Feature",
  "properties": {
    "gn:admin1_code":"28.0",
    "gn:asciiname":"Boduli",
    "gn:country_code":"CD",
    "gn:dem":398,
    "gn:feature_class":"P",
    "gn:feature_code":"PPL",
    "gn:name":"Boduli",
    "gn:population":0,
    "gn:timezone":"Africa/Kinshasa",
    "iso:country":"CD",
    "wof:name":"Boduli",
    "wof:placetype":"locality"
},
  "geometry": {"coordinates":[19.09567,3.68498],"type":"Point"}
}