{
  "type": "Feature",
  "properties": {
    "gn:admin1_code":"27.0",
    "gn:asciiname":"Shele",
    "gn:country_code":"CD",
    "gn:dem":556,
    "gn:feature_class":"P",
    "gn:feature_code":"PPL",
    "gn:name":"Shele",
    "gn:population":0,
    "gn:timezone":"Africa/Lubumbashi",
    "iso:country":"CD",
    "wof:name":"Shele",
    "wof:placetype":"locality"
},
  "geometry": {"coordinates":[23.88333,-3.43333],"type":"Point"}
}