{
  "type": "Feature",
  "properties": {
    "gn:admin1_code":"25.0",
    "gn:asciiname":"Bolombo",
    "gn:country_code":"CD",
    "gn:dem":375,
    "gn:feature_class":"P",
    "gn:feature_code":"PPL",
    "gn:name":"Bolombo",
    "gn:population":0,
    "gn:timezone":"Africa/Kinshasa",
    "iso:country":"CD",
    "name:und_x_variant":[
        "Bolomba"
    ],
    "wof:name":"Bolombo",
    "wof:placetype":"locality"
},
  "geometry": {"coordinates":[20.88577,2.92891],"type":"Point"}
}