{
  "type": "Feature",
  "properties": {
    "gn:admin1_code":"24.0",
    "gn:asciiname":"Nkile",
    "gn:country_code":"CD",
    "gn:dem":339,
    "gn:feature_class":"P",
    "gn:feature_code":"PPL",
    "gn:name":"Nkile",
    "gn:population":0,
    "gn:timezone":"Africa/Kinshasa",
    "iso:country":"CD",
    "wof:name":"Nkile",
    "wof:placetype":"locality"
},
  "geometry": {"coordinates":[18.99266,-3.34928],"type":"Point"}
}