{
  "type": "Feature",
  "properties": {
    "gn:admin1_code":"23.0",
    "gn:asciiname":"Fwamba",
    "gn:country_code":"CD",
    "gn:dem":772,
    "gn:feature_class":"P",
    "gn:feature_code":"PPL",
    "gn:name":"Fwamba",
    "gn:population":0,
    "gn:timezone":"Africa/Lubumbashi",
    "iso:country":"CD",
    "wof:name":"Fwamba",
    "wof:placetype":"locality"
},
  "geometry": {"coordinates":[22.11964,-6.5857],"type":"Point"}
}