{
  "type": "Feature",
  "properties": {
    "gn:admin1_code":"2.0",
    "gn:asciiname":"Dzenge",
    "gn:country_code":"CD",
    "gn:dem":331,
    "gn:feature_class":"P",
    "gn:feature_code":"PPL",
    "gn:name":"Dzenge",
    "gn:population":0,
    "gn:timezone":"Africa/Kinshasa",
    "iso:country":"CD",
    "wof:name":"Dzenge",
    "wof:placetype":"locality"
},
  "geometry": {"coordinates":[18.11667000000001,0.98333],"type":"Point"}
}