{
  "type": "Feature",
  "properties": {
    "gn:admin1_code":"29.0",
    "gn:asciiname":"Katanta",
    "gn:country_code":"CD",
    "gn:dem":807,
    "gn:feature_class":"P",
    "gn:feature_code":"PPL",
    "gn:name":"Katanta",
    "gn:population":0,
    "gn:timezone":"Africa/Lubumbashi",
    "iso:country":"CD",
    "wof:name":"Katanta",
    "wof:placetype":"locality"
},
  "geometry": {"coordinates":[28.2725,-5.21889],"type":"Point"}
}