{
  "type": "Feature",
  "properties": {
    "gn:admin1_code":"13.0",
    "gn:asciiname":"Ndego",
    "gn:country_code":"CD",
    "gn:dem":600,
    "gn:feature_class":"P",
    "gn:feature_code":"PPL",
    "gn:name":"Ndego",
    "gn:population":0,
    "gn:timezone":"Africa/Lubumbashi",
    "iso:country":"CD",
    "wof:name":"Ndego",
    "wof:placetype":"locality"
},
  "geometry": {"coordinates":[25.65798,3.1736],"type":"Point"}
}