{
  "type": "Feature",
  "properties": {
    "gn:admin1_code":"17.0",
    "gn:asciiname":"Landjo",
    "gn:country_code":"CD",
    "gn:dem":1875,
    "gn:feature_class":"P",
    "gn:feature_code":"PPL",
    "gn:name":"Landjo",
    "gn:population":0,
    "gn:timezone":"Africa/Lubumbashi",
    "iso:country":"CD",
    "name:und_x_variant":[
        "Laudjo",
        "Landjo"
    ],
    "wof:name":"Landjo",
    "wof:placetype":"locality"
},
  "geometry": {"coordinates":[30.63459000000001,1.81179],"type":"Point"}
}