{
  "type": "Feature",
  "properties": {
    "gn:admin1_code":"13.0",
    "gn:asciiname":"Kisikomba-Moto",
    "gn:country_code":"CD",
    "gn:dem":525,
    "gn:feature_class":"P",
    "gn:feature_code":"PPL",
    "gn:name":"Kisikomba-Moto",
    "gn:population":0,
    "gn:timezone":"Africa/Lubumbashi",
    "iso:country":"CD",
    "wof:name":"Kisikomba-Moto",
    "wof:placetype":"locality"
},
  "geometry": {"coordinates":[24.02371,3.56171],"type":"Point"}
}