{
  "type": "Feature",
  "properties": {
    "gn:admin1_code":"24.0",
    "gn:asciiname":"Nko",
    "gn:country_code":"CD",
    "gn:dem":482,
    "gn:feature_class":"P",
    "gn:feature_code":"PPL",
    "gn:name":"Nko",
    "gn:population":0,
    "gn:timezone":"Africa/Kinshasa",
    "iso:country":"CD",
    "wof:name":"Nko",
    "wof:placetype":"locality"
},
  "geometry": {"coordinates":[16.46645,-2.65195],"type":"Point"}
}