{
  "type": "Feature",
  "properties": {
    "gn:admin1_code":"10.0",
    "gn:asciiname":"Liwamba",
    "gn:country_code":"CD",
    "gn:dem":511,
    "gn:feature_class":"P",
    "gn:feature_code":"PPL",
    "gn:name":"Liwamba",
    "gn:population":0,
    "gn:timezone":"Africa/Lubumbashi",
    "iso:country":"CD",
    "wof:name":"Liwamba",
    "wof:placetype":"locality"
},
  "geometry": {"coordinates":[25.48333,-2.86667],"type":"Point"}
}