{
  "type": "Feature",
  "properties": {
    "gn:admin1_code":"19.0",
    "gn:asciiname":"Kapambala",
    "gn:country_code":"CD",
    "gn:dem":886,
    "gn:feature_class":"P",
    "gn:feature_code":"PPL",
    "gn:name":"Kapambala",
    "gn:population":0,
    "gn:timezone":"Africa/Kinshasa",
    "iso:country":"CD",
    "wof:name":"Kapambala",
    "wof:placetype":"locality"
},
  "geometry": {"coordinates":[19.75915,-6.88286],"type":"Point"}
}