{
  "type": "Feature",
  "properties": {
    "gn:admin1_code":"26.0",
    "gn:asciiname":"Bomasi",
    "gn:country_code":"CD",
    "gn:dem":438,
    "gn:feature_class":"P",
    "gn:feature_code":"PPL",
    "gn:name":"Bomasi",
    "gn:population":0,
    "gn:timezone":"Africa/Kinshasa",
    "iso:country":"CD",
    "wof:name":"Bomasi",
    "wof:placetype":"locality"
},
  "geometry": {"coordinates":[20.43781,4.28102],"type":"Point"}
}