{
  "type": "Feature",
  "properties": {
    "gn:admin1_code":"30.0",
    "gn:asciiname":"Bafwakwama",
    "gn:country_code":"CD",
    "gn:dem":486,
    "gn:feature_class":"P",
    "gn:feature_code":"PPL",
    "gn:name":"Bafwakwama",
    "gn:population":0,
    "gn:timezone":"Africa/Lubumbashi",
    "iso:country":"CD",
    "wof:name":"Bafwakwama",
    "wof:placetype":"locality"
},
  "geometry": {"coordinates":[26.30406,1.32441],"type":"Point"}
}