{
  "type": "Feature",
  "properties": {
    "gn:admin1_code":"15.0",
    "gn:asciiname":"Sompo",
    "gn:country_code":"CD",
    "gn:dem":729,
    "gn:feature_class":"P",
    "gn:feature_code":"PPL",
    "gn:name":"Sompo",
    "gn:population":0,
    "gn:timezone":"Africa/Lubumbashi",
    "iso:country":"CD",
    "wof:name":"Sompo",
    "wof:placetype":"locality"
},
  "geometry": {"coordinates":[26.75679,-7.92092],"type":"Point"}
}