{
  "type": "Feature",
  "properties": {
    "gn:admin1_code":"8.0",
    "gn:asciiname":"Kimayata",
    "gn:country_code":"CD",
    "gn:dem":922,
    "gn:feature_class":"P",
    "gn:feature_code":"PPL",
    "gn:name":"Kimayata",
    "gn:population":0,
    "gn:timezone":"Africa/Kinshasa",
    "iso:country":"CD",
    "wof:name":"Kimayata",
    "wof:placetype":"locality"
},
  "geometry": {"coordinates":[15.88099,-5.74074],"type":"Point"}
}