{
  "type": "Feature",
  "properties": {
    "gn:admin1_code":"13.0",
    "gn:asciiname":"Mongbali",
    "gn:country_code":"CD",
    "gn:dem":534,
    "gn:feature_class":"P",
    "gn:feature_code":"PPL",
    "gn:name":"Mongbali",
    "gn:population":0,
    "gn:timezone":"Africa/Lubumbashi",
    "iso:country":"CD",
    "wof:name":"Mongbali",
    "wof:placetype":"locality"
},
  "geometry": {"coordinates":[24.59281,3.43502],"type":"Point"}
}