{
  "type": "Feature",
  "properties": {
    "gn:admin1_code":"20.0",
    "gn:asciiname":"Pienene",
    "gn:country_code":"CD",
    "gn:dem":349,
    "gn:feature_class":"P",
    "gn:feature_code":"PPL",
    "gn:name":"Pienene",
    "gn:population":0,
    "gn:timezone":"Africa/Kinshasa",
    "iso:country":"CD",
    "wof:name":"Pienene",
    "wof:placetype":"locality"
},
  "geometry": {"coordinates":[18.42048,-3.69674],"type":"Point"}
}