{
  "type": "Feature",
  "properties": {
    "gn:admin1_code":"15.0",
    "gn:asciiname":"Songwe",
    "gn:country_code":"CD",
    "gn:dem":584,
    "gn:feature_class":"P",
    "gn:feature_code":"PPL",
    "gn:name":"Songwe",
    "gn:population":0,
    "gn:timezone":"Africa/Lubumbashi",
    "iso:country":"CD",
    "wof:name":"Songwe",
    "wof:placetype":"locality"
},
  "geometry": {"coordinates":[26.94135,-7.88913],"type":"Point"}
}