{
  "type": "Feature",
  "properties": {
    "gn:admin1_code":"30.0",
    "gn:asciiname":"Bobiti",
    "gn:country_code":"CD",
    "gn:dem":416,
    "gn:feature_class":"P",
    "gn:feature_code":"PPL",
    "gn:name":"Bobiti",
    "gn:population":0,
    "gn:timezone":"Africa/Lubumbashi",
    "iso:country":"CD",
    "wof:name":"Bobiti",
    "wof:placetype":"locality"
},
  "geometry": {"coordinates":[25.18696,0.80206],"type":"Point"}
}