{
  "type": "Feature",
  "properties": {
    "gn:admin1_code":"19.0",
    "gn:asciiname":"Mbinda",
    "gn:country_code":"CD",
    "gn:dem":600,
    "gn:feature_class":"P",
    "gn:feature_code":"PPL",
    "gn:name":"Mbinda",
    "gn:population":0,
    "gn:timezone":"Africa/Kinshasa",
    "iso:country":"CD",
    "name:bul_x_preferred":[
        "\u041c\u0431\u0438\u043d\u0434\u0430"
    ],
    "name:fra_x_preferred":[
        "Mbinda"
    ],
    "name:ita_x_preferred":[
        "Mbinda"
    ],
    "name:jpn_x_preferred":[
        "\u30e0\u30d3\u30f3\u30c0"
    ],
    "name:kor_x_preferred":[
        "\uc74c\ube48\ub2e4"
    ],
    "name:nld_x_preferred":[
        "Mbinda"
    ],
    "name:por_x_preferred":[
        "Mbinda"
    ],
    "name:ron_x_preferred":[
        "Mbinda"
    ],
    "name:urd_x_preferred":[
        "\u0645\u0628\u06cc\u0646\u0688\u0627"
    ],
    "name:zho_x_preferred":[
        "\u59c6\u8cd3\u9054"
    ],
    "wof:name":"Mbinda",
    "wof:placetype":"locality"
},
  "geometry": {"coordinates":[17.15578,-6.3719],"type":"Point"}
}