{
  "type": "Feature",
  "properties": {
    "gn:admin1_code":"24.0",
    "gn:asciiname":"Nkurukwaka",
    "gn:country_code":"CD",
    "gn:dem":385,
    "gn:feature_class":"P",
    "gn:feature_code":"PPL",
    "gn:name":"Nkurukwaka",
    "gn:population":0,
    "gn:timezone":"Africa/Kinshasa",
    "iso:country":"CD",
    "wof:name":"Nkurukwaka",
    "wof:placetype":"locality"
},
  "geometry": {"coordinates":[16.84159,-2.79053],"type":"Point"}
}