{
  "type": "Feature",
  "properties": {
    "gn:admin1_code":"22.0",
    "gn:asciiname":"Kahongo",
    "gn:country_code":"CD",
    "gn:dem":1185,
    "gn:feature_class":"P",
    "gn:feature_code":"PPL",
    "gn:name":"Kahongo",
    "gn:population":0,
    "gn:timezone":"Africa/Lubumbashi",
    "iso:country":"CD",
    "wof:name":"Kahongo",
    "wof:placetype":"locality"
},
  "geometry": {"coordinates":[24.14753,-10.41467],"type":"Point"}
}