{
  "type": "Feature",
  "properties": {
    "gn:admin1_code":"27.0",
    "gn:asciiname":"Koiekoie",
    "gn:country_code":"CD",
    "gn:dem":471,
    "gn:feature_class":"P",
    "gn:feature_code":"PPL",
    "gn:name":"Koiekoie",
    "gn:population":0,
    "gn:timezone":"Africa/Lubumbashi",
    "iso:country":"CD",
    "wof:name":"Koiekoie",
    "wof:placetype":"locality"
},
  "geometry": {"coordinates":[23.35677,-3.37726],"type":"Point"}
}