{
  "type": "Feature",
  "properties": {
    "gn:admin1_code":"13.0",
    "gn:asciiname":"Likingi",
    "gn:country_code":"CD",
    "gn:dem":423,
    "gn:feature_class":"P",
    "gn:feature_code":"PPL",
    "gn:name":"Likingi",
    "gn:population":0,
    "gn:timezone":"Africa/Lubumbashi",
    "iso:country":"CD",
    "wof:name":"Likingi",
    "wof:placetype":"locality"
},
  "geometry": {"coordinates":[23.64955,2.48108],"type":"Point"}
}