{
  "type": "Feature",
  "properties": {
    "gn:admin1_code":"21.0",
    "gn:asciiname":"Sewe",
    "gn:country_code":"CD",
    "gn:dem":835,
    "gn:feature_class":"P",
    "gn:feature_code":"PPL",
    "gn:name":"Sewe",
    "gn:population":0,
    "gn:timezone":"Africa/Lubumbashi",
    "iso:country":"CD",
    "name:und_x_variant":[
        "Sowe",
        "Sewe"
    ],
    "wof:name":"Sewe",
    "wof:placetype":"locality"
},
  "geometry": {"coordinates":[24.52729,-6.12385],"type":"Point"}
}