{
  "type": "Feature",
  "properties": {
    "gn:admin1_code":"23.0",
    "gn:asciiname":"Kashama",
    "gn:country_code":"CD",
    "gn:dem":800,
    "gn:feature_class":"P",
    "gn:feature_code":"PPL",
    "gn:name":"Kashama",
    "gn:population":0,
    "gn:timezone":"Africa/Lubumbashi",
    "iso:country":"CD",
    "wof:name":"Kashama",
    "wof:placetype":"locality"
},
  "geometry": {"coordinates":[22.02761,-6.51901],"type":"Point"}
}