{
  "type": "Feature",
  "properties": {
    "gn:admin1_code":"22.0",
    "gn:asciiname":"Lundu",
    "gn:country_code":"CD",
    "gn:dem":1227,
    "gn:feature_class":"P",
    "gn:feature_code":"PPL",
    "gn:name":"Lundu",
    "gn:population":0,
    "gn:timezone":"Africa/Lubumbashi",
    "iso:country":"CD",
    "wof:name":"Lundu",
    "wof:placetype":"locality"
},
  "geometry": {"coordinates":[23.4525,-10.89134],"type":"Point"}
}