{
  "type": "Feature",
  "properties": {
    "gn:admin1_code":"8.0",
    "gn:asciiname":"Mahana",
    "gn:country_code":"CD",
    "gn:dem":608,
    "gn:feature_class":"P",
    "gn:feature_code":"PPL",
    "gn:name":"Mahana",
    "gn:population":0,
    "gn:timezone":"Africa/Kinshasa",
    "iso:country":"CD",
    "wof:name":"Mahana",
    "wof:placetype":"locality"
},
  "geometry": {"coordinates":[14.07651,-4.4157],"type":"Point"}
}