{
  "type": "Feature",
  "properties": {
    "gn:admin1_code":"30.0",
    "gn:asciiname":"Yalikunda",
    "gn:country_code":"CD",
    "gn:dem":384,
    "gn:feature_class":"P",
    "gn:feature_code":"PPL",
    "gn:name":"Yalikunda",
    "gn:population":0,
    "gn:timezone":"Africa/Lubumbashi",
    "iso:country":"CD",
    "wof:name":"Yalikunda",
    "wof:placetype":"locality"
},
  "geometry": {"coordinates":[22.65387,1.86387],"type":"Point"}
}