{
  "type": "Feature",
  "properties": {
    "gn:admin1_code":"24.0",
    "gn:asciiname":"Semokaw",
    "gn:country_code":"CD",
    "gn:dem":320,
    "gn:feature_class":"P",
    "gn:feature_code":"PPL",
    "gn:name":"Semokaw",
    "gn:population":0,
    "gn:timezone":"Africa/Kinshasa",
    "iso:country":"CD",
    "wof:name":"Semokaw",
    "wof:placetype":"locality"
},
  "geometry": {"coordinates":[18.43333,-2.95],"type":"Point"}
}