{
  "type": "Feature",
  "properties": {
    "gn:admin1_code":"19.0",
    "gn:asciiname":"Kizozo",
    "gn:country_code":"CD",
    "gn:dem":950,
    "gn:feature_class":"P",
    "gn:feature_code":"PPL",
    "gn:name":"Kizozo",
    "gn:population":0,
    "gn:timezone":"Africa/Kinshasa",
    "iso:country":"CD",
    "wof:name":"Kizozo",
    "wof:placetype":"locality"
},
  "geometry": {"coordinates":[18.47896,-7.73949],"type":"Point"}
}