{
  "type": "Feature",
  "properties": {
    "gn:admin1_code":"13.0",
    "gn:asciiname":"Tilipi",
    "gn:country_code":"CD",
    "gn:dem":600,
    "gn:feature_class":"P",
    "gn:feature_code":"PPL",
    "gn:name":"Tilipi",
    "gn:population":0,
    "gn:timezone":"Africa/Lubumbashi",
    "iso:country":"CD",
    "name:und_x_variant":[
        "Tilipili",
        "Tilipi"
    ],
    "wof:name":"Tilipi",
    "wof:placetype":"locality"
},
  "geometry": {"coordinates":[25.71011,2.8158],"type":"Point"}
}