{
  "type": "Feature",
  "properties": {
    "gn:admin1_code":"8.0",
    "gn:asciiname":"Kunda",
    "gn:country_code":"CD",
    "gn:dem":473,
    "gn:feature_class":"P",
    "gn:feature_code":"PPL",
    "gn:name":"Kunda",
    "gn:population":0,
    "gn:timezone":"Africa/Kinshasa",
    "iso:country":"CD",
    "wof:name":"Kunda",
    "wof:placetype":"locality"
},
  "geometry": {"coordinates":[14.72873,-5.34773],"type":"Point"}
}