{
  "type": "Feature",
  "properties": {
    "gn:admin1_code":"20.0",
    "gn:asciiname":"Buzala",
    "gn:country_code":"CD",
    "gn:dem":301,
    "gn:feature_class":"P",
    "gn:feature_code":"PPL",
    "gn:name":"Buzala",
    "gn:population":0,
    "gn:timezone":"Africa/Kinshasa",
    "iso:country":"CD",
    "wof:name":"Buzala",
    "wof:placetype":"locality"
},
  "geometry": {"coordinates":[17.39847,-3.37707],"type":"Point"}
}