{
  "type": "Feature",
  "properties": {
    "gn:admin1_code":"20.0",
    "gn:asciiname":"Buzala",
    "gn:country_code":"CD",
    "gn:dem":301,
    "gn:feature_class":"P",
    "gn:feature_code":"PPL",
    "gn:name":"Buzala",
    "gn:population":0,
    "gn:timezone":"Africa/Kinshasa",
    "iso:country":"CD",
    "name:hye_x_preferred":[
        "\u0532\u0578\u0582\u0566\u0561\u056c\u0561"
    ],
    "name:kat_x_preferred":[
        "\u10d1\u10e3\u10d6\u10d0\u10da\u10d0"
    ],
    "name:oss_x_preferred":[
        "\u0411\u0443\u0437\u0430\u043b\u0430"
    ],
    "name:rus_x_preferred":[
        "\u0411\u0443\u0437\u0430\u043b\u0430"
    ],
    "wof:name":"Buzala",
    "wof:placetype":"locality"
},
  "geometry": {"coordinates":[17.39847,-3.37707],"type":"Point"}
}