{
  "type": "Feature",
  "properties": {
    "gn:admin1_code":"14.0",
    "gn:asciiname":"Musisa",
    "gn:country_code":"CD",
    "gn:dem":981,
    "gn:feature_class":"P",
    "gn:feature_code":"PPL",
    "gn:name":"Musisa",
    "gn:population":0,
    "gn:timezone":"Africa/Lubumbashi",
    "iso:country":"CD",
    "name:und_x_variant":[
        "Mushisa"
    ],
    "wof:name":"Musisa",
    "wof:placetype":"locality"
},
  "geometry": {"coordinates":[27.38302,-9.46823],"type":"Point"}
}