{
  "type": "Feature",
  "properties": {
    "gn:admin1_code":"11.0",
    "gn:asciiname":"Tusoke",
    "gn:country_code":"CD",
    "gn:dem":680,
    "gn:feature_class":"P",
    "gn:feature_code":"PPL",
    "gn:name":"Tusoke",
    "gn:population":0,
    "gn:timezone":"Africa/Lubumbashi",
    "iso:country":"CD",
    "wof:name":"Tusoke",
    "wof:placetype":"locality"
},
  "geometry": {"coordinates":[28.14032000000001,-1.6773],"type":"Point"}
}