{
  "type": "Feature",
  "properties": {
    "gn:admin1_code":"29.0",
    "gn:asciiname":"Kazunga",
    "gn:country_code":"CD",
    "gn:dem":783,
    "gn:feature_class":"P",
    "gn:feature_code":"PPL",
    "gn:name":"Kazunga",
    "gn:population":0,
    "gn:timezone":"Africa/Lubumbashi",
    "iso:country":"CD",
    "wof:name":"Kazunga",
    "wof:placetype":"locality"
},
  "geometry": {"coordinates":[28.53192,-6.93243],"type":"Point"}
}