{
  "type": "Feature",
  "properties": {
    "gn:admin1_code":"15.0",
    "gn:asciiname":"Kankomba",
    "gn:country_code":"CD",
    "gn:dem":981,
    "gn:feature_class":"P",
    "gn:feature_code":"PPL",
    "gn:name":"Kankomba",
    "gn:population":0,
    "gn:timezone":"Africa/Lubumbashi",
    "iso:country":"CD",
    "name:und_x_variant":[
        "Kankemba",
        "Kankomba"
    ],
    "wof:name":"Kankomba",
    "wof:placetype":"locality"
},
  "geometry": {"coordinates":[24.11531,-7.93361],"type":"Point"}
}