{
  "type": "Feature",
  "properties": {
    "gn:admin1_code":"8.0",
    "gn:asciiname":"Fumba Tshi Tandu",
    "gn:country_code":"CD",
    "gn:dem":122,
    "gn:feature_class":"P",
    "gn:feature_code":"PPL",
    "gn:name":"Fumba Tshi Tandu",
    "gn:population":0,
    "gn:timezone":"Africa/Kinshasa",
    "iso:country":"CD",
    "wof:name":"Fumba Tshi Tandu",
    "wof:placetype":"locality"
},
  "geometry": {"coordinates":[12.39651,-5.82801],"type":"Point"}
}