{
  "type": "Feature",
  "properties": {
    "gn:admin1_code":"24.0",
    "gn:asciiname":"Onko II",
    "gn:country_code":"CD",
    "gn:dem":409,
    "gn:feature_class":"P",
    "gn:feature_code":"PPL",
    "gn:name":"Onko II",
    "gn:population":0,
    "gn:timezone":"Africa/Kinshasa",
    "iso:country":"CD",
    "wof:name":"Onko II",
    "wof:placetype":"locality"
},
  "geometry": {"coordinates":[19.93333,-4.16667],"type":"Point"}
}