{
  "type": "Feature",
  "properties": {
    "gn:admin1_code":"8.0",
    "gn:asciiname":"Kai-Tulu",
    "gn:country_code":"CD",
    "gn:dem":343,
    "gn:feature_class":"P",
    "gn:feature_code":"PPL",
    "gn:name":"Kai-Tulu",
    "gn:population":0,
    "gn:timezone":"Africa/Kinshasa",
    "iso:country":"CD",
    "wof:name":"Kai-Tulu",
    "wof:placetype":"locality"
},
  "geometry": {"coordinates":[13.08333,-5.33333],"type":"Point"}
}