{
  "type": "Feature",
  "properties": {
    "gn:admin1_code":"13.0",
    "gn:asciiname":"Siro",
    "gn:country_code":"CD",
    "gn:dem":621,
    "gn:feature_class":"P",
    "gn:feature_code":"PPL",
    "gn:name":"Siro",
    "gn:population":0,
    "gn:timezone":"Africa/Lubumbashi",
    "iso:country":"CD",
    "wof:name":"Siro",
    "wof:placetype":"locality"
},
  "geometry": {"coordinates":[25.69612,3.11747],"type":"Point"}
}