{
  "type": "Feature",
  "properties": {
    "gn:admin1_code":"23.0",
    "gn:asciiname":"Uputu",
    "gn:country_code":"CD",
    "gn:dem":878,
    "gn:feature_class":"P",
    "gn:feature_code":"PPL",
    "gn:name":"Uputu",
    "gn:population":0,
    "gn:timezone":"Africa/Lubumbashi",
    "iso:country":"CD",
    "wof:name":"Uputu",
    "wof:placetype":"locality"
},
  "geometry": {"coordinates":[22.39286,-7.18357],"type":"Point"}
}