{
  "type": "Feature",
  "properties": {
    "gn:admin1_code":"21.0",
    "gn:asciiname":"Kibila",
    "gn:country_code":"CD",
    "gn:dem":854,
    "gn:feature_class":"P",
    "gn:feature_code":"PPL",
    "gn:name":"Kibila",
    "gn:population":0,
    "gn:timezone":"Africa/Lubumbashi",
    "iso:country":"CD",
    "wof:name":"Kibila",
    "wof:placetype":"locality"
},
  "geometry": {"coordinates":[24.61107,-6.45157],"type":"Point"}
}