{
  "type": "Feature",
  "properties": {
    "gn:admin1_code":"20.0",
    "gn:asciiname":"Kikama",
    "gn:country_code":"CD",
    "gn:dem":395,
    "gn:feature_class":"P",
    "gn:feature_code":"PPL",
    "gn:name":"Kikama",
    "gn:population":0,
    "gn:timezone":"Africa/Kinshasa",
    "iso:country":"CD",
    "wof:name":"Kikama",
    "wof:placetype":"locality"
},
  "geometry": {"coordinates":[17.94232000000001,-4.84848],"type":"Point"}
}