{
  "type": "Feature",
  "properties": {
    "gn:admin1_code":"18.0",
    "gn:asciiname":"Muamuzombo",
    "gn:country_code":"CD",
    "gn:dem":651,
    "gn:feature_class":"P",
    "gn:feature_code":"PPL",
    "gn:name":"Muamuzombo",
    "gn:population":0,
    "gn:timezone":"Africa/Lubumbashi",
    "iso:country":"CD",
    "wof:name":"Muamuzombo",
    "wof:placetype":"locality"
},
  "geometry": {"coordinates":[20.75146,-6.78298],"type":"Point"}
}