{
  "type": "Feature",
  "properties": {
    "gn:admin1_code":"24.0",
    "gn:asciiname":"Miaka Premiere",
    "gn:country_code":"CD",
    "gn:dem":310,
    "gn:feature_class":"P",
    "gn:feature_code":"PPL",
    "gn:name":"Miaka Premi\u00e8re",
    "gn:population":0,
    "gn:timezone":"Africa/Kinshasa",
    "iso:country":"CD",
    "wof:name":"Miaka Premiere",
    "wof:placetype":"locality"
},
  "geometry": {"coordinates":[18.78383,-3.24047],"type":"Point"}
}