{
  "type": "Feature",
  "properties": {
    "gn:admin1_code":"28.0",
    "gn:asciiname":"Bokonga",
    "gn:country_code":"CD",
    "gn:dem":376,
    "gn:feature_class":"P",
    "gn:feature_code":"PPL",
    "gn:name":"Bokonga",
    "gn:population":0,
    "gn:timezone":"Africa/Kinshasa",
    "iso:country":"CD",
    "wof:name":"Bokonga",
    "wof:placetype":"locality"
},
  "geometry": {"coordinates":[19.23633,3.1724],"type":"Point"}
}