{
  "type": "Feature",
  "properties": {
    "gn:admin1_code":"25.0",
    "gn:asciiname":"Boso-Monino",
    "gn:country_code":"CD",
    "gn:dem":348,
    "gn:feature_class":"P",
    "gn:feature_code":"PPL",
    "gn:name":"Boso-Monino",
    "gn:population":0,
    "gn:timezone":"Africa/Kinshasa",
    "iso:country":"CD",
    "wof:name":"Boso-Monino",
    "wof:placetype":"locality"
},
  "geometry": {"coordinates":[21.53,2.0581],"type":"Point"}
}