{
  "type": "Feature",
  "properties": {
    "gn:admin1_code":"23.0",
    "gn:asciiname":"Bena-Sungu",
    "gn:country_code":"CD",
    "gn:dem":515,
    "gn:feature_class":"P",
    "gn:feature_code":"PPL",
    "gn:name":"Bena-Sungu",
    "gn:population":0,
    "gn:timezone":"Africa/Lubumbashi",
    "iso:country":"CD",
    "name:und_x_variant":[
        "Bakwa-Sungu",
        "Bena-Sungu"
    ],
    "wof:name":"Bena-Sungu",
    "wof:placetype":"locality"
},
  "geometry": {"coordinates":[23.00402,-4.70903],"type":"Point"}
}