{
  "type": "Feature",
  "properties": {
    "gn:admin1_code":"10.0",
    "gn:asciiname":"Yumbi",
    "gn:country_code":"CD",
    "gn:dem":480,
    "gn:feature_class":"P",
    "gn:feature_code":"PPL",
    "gn:name":"Yumbi",
    "gn:population":0,
    "gn:timezone":"Africa/Lubumbashi",
    "iso:country":"CD",
    "name:ceb_x_preferred":[
        "Yumbi"
    ],
    "name:deu_x_preferred":[
        "Yumbi"
    ],
    "name:fra_x_preferred":[
        "Yumbi"
    ],
    "name:swe_x_preferred":[
        "Yumbi"
    ],
    "name:urd_x_preferred":[
        "\u06cc\u0648\u0645\u0628\u06cc"
    ],
    "wof:name":"Yumbi",
    "wof:placetype":"locality"
},
  "geometry": {"coordinates":[26.22345,-1.25017],"type":"Point"}
}