{
  "type": "Feature",
  "properties": {
    "gn:admin1_code":"21.0",
    "gn:asciiname":"Pamba Zeo",
    "gn:country_code":"CD",
    "gn:dem":735,
    "gn:feature_class":"P",
    "gn:feature_code":"PPL",
    "gn:name":"Pamba Zeo",
    "gn:population":0,
    "gn:timezone":"Africa/Lubumbashi",
    "iso:country":"CD",
    "wof:name":"Pamba Zeo",
    "wof:placetype":"locality"
},
  "geometry": {"coordinates":[24.01667,-6.81667],"type":"Point"}
}