{
  "type": "Feature",
  "properties": {
    "gn:admin1_code":"21.0",
    "gn:asciiname":"Lukolela",
    "gn:country_code":"CD",
    "gn:dem":791,
    "gn:feature_class":"P",
    "gn:feature_code":"PPL",
    "gn:name":"Lukolela",
    "gn:population":0,
    "gn:timezone":"Africa/Lubumbashi",
    "iso:country":"CD",
    "name:ceb_x_preferred":[
        "Lukolela"
    ],
    "name:fra_x_preferred":[
        "Lukolela"
    ],
    "name:ita_x_preferred":[
        "Lukolela"
    ],
    "name:ron_x_preferred":[
        "Lukolela"
    ],
    "name:swe_x_preferred":[
        "Lukolela"
    ],
    "wof:name":"Lukolela",
    "wof:placetype":"locality"
},
  "geometry": {"coordinates":[24.53479,-5.38612],"type":"Point"}
}