{
  "type": "Feature",
  "properties": {
    "gn:admin1_code":"21.0",
    "gn:asciiname":"Kamatanga",
    "gn:country_code":"CD",
    "gn:dem":562,
    "gn:feature_class":"P",
    "gn:feature_code":"PPL",
    "gn:name":"Kamatanga",
    "gn:population":0,
    "gn:timezone":"Africa/Lubumbashi",
    "iso:country":"CD",
    "wof:name":"Kamatanga",
    "wof:placetype":"locality"
},
  "geometry": {"coordinates":[25.98333,-5.21667],"type":"Point"}
}