{
  "type": "Feature",
  "properties": {
    "gn:admin1_code":"12.0",
    "gn:asciiname":"Kashukwe",
    "gn:country_code":"CD",
    "gn:dem":2044,
    "gn:feature_class":"P",
    "gn:feature_code":"PPL",
    "gn:name":"Kashukwe",
    "gn:population":0,
    "gn:timezone":"Africa/Lubumbashi",
    "iso:country":"CD",
    "wof:name":"Kashukwe",
    "wof:placetype":"locality"
},
  "geometry": {"coordinates":[28.77333,-3.33306],"type":"Point"}
}