{
  "type": "Feature",
  "properties": {
    "gn:admin1_code":"22.0",
    "gn:asciiname":"Ngule",
    "gn:country_code":"CD",
    "gn:dem":1521,
    "gn:feature_class":"P",
    "gn:feature_code":"PPL",
    "gn:name":"Ngule",
    "gn:population":0,
    "gn:timezone":"Africa/Lubumbashi",
    "iso:country":"CD",
    "name:und_x_variant":[
        "Gule",
        "Ngule"
    ],
    "wof:name":"Ngule",
    "wof:placetype":"locality"
},
  "geometry": {"coordinates":[26.04638,-10.44736],"type":"Point"}
}