{
  "type": "Feature",
  "properties": {
    "gn:admin1_code":"30.0",
    "gn:asciiname":"Bahume",
    "gn:country_code":"CD",
    "gn:dem":466,
    "gn:feature_class":"P",
    "gn:feature_code":"PPL",
    "gn:name":"Bahume",
    "gn:population":0,
    "gn:timezone":"Africa/Lubumbashi",
    "iso:country":"CD",
    "wof:name":"Bahume",
    "wof:placetype":"locality"
},
  "geometry": {"coordinates":[25.26091,1.3441],"type":"Point"}
}