{
  "type": "Feature",
  "properties": {
    "gn:admin1_code":"28.0",
    "gn:asciiname":"Setuma",
    "gn:country_code":"CD",
    "gn:dem":417,
    "gn:feature_class":"P",
    "gn:feature_code":"PPL",
    "gn:name":"Setuma",
    "gn:population":0,
    "gn:timezone":"Africa/Kinshasa",
    "iso:country":"CD",
    "name:fra_x_preferred":[
        "Setuma"
    ],
    "wof:name":"Setuma",
    "wof:placetype":"locality"
},
  "geometry": {"coordinates":[19.22395,2.92677],"type":"Point"}
}