{
  "type": "Feature",
  "properties": {
    "gn:admin1_code":"10.0",
    "gn:asciiname":"Makongo",
    "gn:country_code":"CD",
    "gn:dem":572,
    "gn:feature_class":"P",
    "gn:feature_code":"PPL",
    "gn:name":"Makongo",
    "gn:population":0,
    "gn:timezone":"Africa/Lubumbashi",
    "iso:country":"CD",
    "wof:name":"Makongo",
    "wof:placetype":"locality"
},
  "geometry": {"coordinates":[26.88333,-3.16667],"type":"Point"}
}