{
  "type": "Feature",
  "properties": {
    "gn:admin1_code":"26.0",
    "gn:asciiname":"Pagwa",
    "gn:country_code":"CD",
    "gn:dem":379,
    "gn:feature_class":"P",
    "gn:feature_code":"PPL",
    "gn:name":"Pagwa",
    "gn:population":0,
    "gn:timezone":"Africa/Kinshasa",
    "iso:country":"CD",
    "wof:name":"Pagwa",
    "wof:placetype":"locality"
},
  "geometry": {"coordinates":[20.08388,4.86672],"type":"Point"}
}