{
  "type": "Feature",
  "properties": {
    "gn:admin1_code":"20.0",
    "gn:asciiname":"Wutu",
    "gn:country_code":"CD",
    "gn:dem":568,
    "gn:feature_class":"P",
    "gn:feature_code":"PPL",
    "gn:name":"Wutu",
    "gn:population":0,
    "gn:timezone":"Africa/Kinshasa",
    "iso:country":"CD",
    "wof:name":"Wutu",
    "wof:placetype":"locality"
},
  "geometry": {"coordinates":[19.05678,-4.94526],"type":"Point"}
}