{
  "type": "Feature",
  "properties": {
    "gn:admin1_code":"22.0",
    "gn:asciiname":"Sambala",
    "gn:country_code":"CD",
    "gn:dem":1071,
    "gn:feature_class":"P",
    "gn:feature_code":"PPL",
    "gn:name":"Sambala",
    "gn:population":0,
    "gn:timezone":"Africa/Lubumbashi",
    "iso:country":"CD",
    "name:und_x_variant":[
        "Samba",
        "Sambala"
    ],
    "wof:name":"Sambala",
    "wof:placetype":"locality"
},
  "geometry": {"coordinates":[22.98947,-9.33816],"type":"Point"}
}