{
  "type": "Feature",
  "properties": {
    "gn:admin1_code":"22.0",
    "gn:asciiname":"Sawaka",
    "gn:country_code":"CD",
    "gn:dem":933,
    "gn:feature_class":"P",
    "gn:feature_code":"PPL",
    "gn:name":"Sawaka",
    "gn:population":0,
    "gn:timezone":"Africa/Lubumbashi",
    "iso:country":"CD",
    "wof:name":"Sawaka",
    "wof:placetype":"locality"
},
  "geometry": {"coordinates":[24.78732,-10.22671],"type":"Point"}
}