{
  "type": "Feature",
  "properties": {
    "gn:admin1_code":"8.0",
    "gn:asciiname":"Kinimi",
    "gn:country_code":"CD",
    "gn:dem":395,
    "gn:feature_class":"P",
    "gn:feature_code":"PPL",
    "gn:name":"Kinimi",
    "gn:population":0,
    "gn:timezone":"Africa/Kinshasa",
    "iso:country":"CD",
    "wof:name":"Kinimi",
    "wof:placetype":"locality"
},
  "geometry": {"coordinates":[15.13333,-4.58333],"type":"Point"}
}