{
  "type": "Feature",
  "properties": {
    "gn:admin1_code":"11.0",
    "gn:asciiname":"Mutsora",
    "gn:country_code":"CD",
    "gn:dem":1158,
    "gn:feature_class":"P",
    "gn:feature_code":"PPL",
    "gn:name":"Mutsora",
    "gn:population":0,
    "gn:timezone":"Africa/Lubumbashi",
    "iso:country":"CD",
    "wof:name":"Mutsora",
    "wof:placetype":"locality"
},
  "geometry": {"coordinates":[29.74542000000001,0.3224],"type":"Point"}
}