{
  "type": "Feature",
  "properties": {
    "gn:admin1_code":"23.0",
    "gn:asciiname":"Bena-Imbwama-Mitete",
    "gn:country_code":"CD",
    "gn:dem":543,
    "gn:feature_class":"P",
    "gn:feature_code":"PPL",
    "gn:name":"Bena-Imbwama-Mitete",
    "gn:population":0,
    "gn:timezone":"Africa/Lubumbashi",
    "iso:country":"CD",
    "wof:name":"Bena-Imbwama-Mitete",
    "wof:placetype":"locality"
},
  "geometry": {"coordinates":[22.7341,-4.38943],"type":"Point"}
}