{
  "type": "Feature",
  "properties": {
    "gn:admin1_code":"29.0",
    "gn:asciiname":"Katuta",
    "gn:country_code":"CD",
    "gn:dem":625,
    "gn:feature_class":"P",
    "gn:feature_code":"PPL",
    "gn:name":"Katuta",
    "gn:population":0,
    "gn:timezone":"Africa/Lubumbashi",
    "iso:country":"CD",
    "wof:name":"Katuta",
    "wof:placetype":"locality"
},
  "geometry": {"coordinates":[27.46091,-7.18285],"type":"Point"}
}