{
  "type": "Feature",
  "properties": {
    "gn:admin1_code":"8.0",
    "gn:asciiname":"Kimpanda",
    "gn:country_code":"CD",
    "gn:dem":550,
    "gn:feature_class":"P",
    "gn:feature_code":"PPL",
    "gn:name":"Kimpanda",
    "gn:population":0,
    "gn:timezone":"Africa/Kinshasa",
    "iso:country":"CD",
    "wof:name":"Kimpanda",
    "wof:placetype":"locality"
},
  "geometry": {"coordinates":[15.03199,-5.0866],"type":"Point"}
}