{
  "type": "Feature",
  "properties": {
    "gn:admin1_code":"24.0",
    "gn:asciiname":"Mpanda",
    "gn:country_code":"CD",
    "gn:dem":409,
    "gn:feature_class":"P",
    "gn:feature_code":"PPL",
    "gn:name":"Mpanda",
    "gn:population":0,
    "gn:timezone":"Africa/Kinshasa",
    "iso:country":"CD",
    "name:azb_x_preferred":[
        "\u0627\u0645\u067e\u0627\u0646\u062f\u0627"
    ],
    "name:ben_x_preferred":[
        "\u098f\u09ae\u09cd\u09aa\u09be\u09a8\u09cd\u09a1\u09be"
    ],
    "name:ceb_x_preferred":[
        "Mpanda"
    ],
    "name:deu_x_preferred":[
        "Mpanda"
    ],
    "name:fas_x_preferred":[
        "\u0627\u0645\u067e\u0627\u0646\u062f\u0627"
    ],
    "name:fin_x_preferred":[
        "Mpanda"
    ],
    "name:fra_x_preferred":[
        "Mpanda"
    ],
    "name:heb_x_preferred":[
        "\u05de\u05e4\u05e0\u05d3\u05d4"
    ],
    "name:hin_x_preferred":[
        "\u090f\u0902\u092a\u093e\u0902\u0921\u093e"
    ],
    "name:hun_x_preferred":[
        "Mpanda"
    ],
    "name:ind_x_preferred":[
        "Mpanda"
    ],
    "name:ita_x_preferred":[
        "Mpanda"
    ],
    "name:kor_x_preferred":[
        "\uc74c\ud310\ub2e4"
    ],
    "name:pol_x_preferred":[
        "Mpanda"
    ],
    "name:ron_x_preferred":[
        "Mpanda"
    ],
    "name:rus_x_preferred":[
        "\u041c\u043f\u0430\u043d\u0434\u0430"
    ],
    "name:swa_x_preferred":[
        "Mpanda"
    ],
    "name:swe_x_preferred":[
        "Mpanda"
    ],
    "name:tur_x_preferred":[
        "Mpanda"
    ],
    "name:ukr_x_preferred":[
        "\u041c\u043f\u0430\u043d\u0434\u0430"
    ],
    "name:urd_x_preferred":[
        "\u067e\u0627\u0646\u0688\u0627"
    ],
    "name:vie_x_preferred":[
        "Mpanda"
    ],
    "wof:name":"Mpanda",
    "wof:placetype":"locality"
},
  "geometry": {"coordinates":[18.80818,-3.52083],"type":"Point"}
}