{
  "type": "Feature",
  "properties": {
    "gn:admin1_code":"8.0",
    "gn:asciiname":"Sala-Duma",
    "gn:country_code":"CD",
    "gn:dem":594,
    "gn:feature_class":"P",
    "gn:feature_code":"PPL",
    "gn:name":"Sala-Duma",
    "gn:population":0,
    "gn:timezone":"Africa/Kinshasa",
    "iso:country":"CD",
    "wof:name":"Sala-Duma",
    "wof:placetype":"locality"
},
  "geometry": {"coordinates":[14.0409,-4.70617],"type":"Point"}
}