{
  "type": "Feature",
  "properties": {
    "gn:admin1_code":"11.0",
    "gn:asciiname":"Kulata",
    "gn:country_code":"CD",
    "gn:dem":887,
    "gn:feature_class":"P",
    "gn:feature_code":"PPL",
    "gn:name":"Kulata",
    "gn:population":0,
    "gn:timezone":"Africa/Lubumbashi",
    "iso:country":"CD",
    "name:bul_x_preferred":[
        "\u041a\u0443\u043b\u0430\u0442\u0430"
    ],
    "name:deu_x_preferred":[
        "Kulata"
    ],
    "name:ell_x_preferred":[
        "\u039a\u03bf\u03cd\u03bb\u03b1\u03c4\u03b1"
    ],
    "name:fas_x_preferred":[
        "\u06a9\u0648\u0644\u0627\u062a\u0627"
    ],
    "name:kat_x_preferred":[
        "\u10d9\u10e3\u10da\u10d0\u10e2\u10d0"
    ],
    "name:kaz_x_preferred":[
        "\u041a\u0443\u043b\u0430\u0442\u0430"
    ],
    "name:mkd_x_preferred":[
        "\u041a\u0443\u043b\u0430\u0442\u0430"
    ],
    "name:msa_x_preferred":[
        "Kulata"
    ],
    "name:pol_x_preferred":[
        "Kulata"
    ],
    "name:ron_x_preferred":[
        "Kulata"
    ],
    "name:rus_x_preferred":[
        "\u041a\u0443\u043b\u0430\u0442\u0430"
    ],
    "name:ukr_x_preferred":[
        "\u041a\u0443\u043b\u0430\u0442\u0430"
    ],
    "wof:name":"Kulata",
    "wof:placetype":"locality"
},
  "geometry": {"coordinates":[28.37714,0.4185],"type":"Point"}
}