{
  "type": "Feature",
  "properties": {
    "gn:admin1_code":"11.0",
    "gn:asciiname":"Kulata",
    "gn:country_code":"CD",
    "gn:dem":887,
    "gn:feature_class":"P",
    "gn:feature_code":"PPL",
    "gn:name":"Kulata",
    "gn:population":0,
    "gn:timezone":"Africa/Lubumbashi",
    "iso:country":"CD",
    "wof:name":"Kulata",
    "wof:placetype":"locality"
},
  "geometry": {"coordinates":[28.37714,0.4185],"type":"Point"}
}