{
  "type": "Feature",
  "properties": {
    "gn:admin1_code":"19.0",
    "gn:asciiname":"Fwangi",
    "gn:country_code":"CD",
    "gn:dem":896,
    "gn:feature_class":"P",
    "gn:feature_code":"PPL",
    "gn:name":"Fwangi",
    "gn:population":0,
    "gn:timezone":"Africa/Kinshasa",
    "iso:country":"CD",
    "wof:name":"Fwangi",
    "wof:placetype":"locality"
},
  "geometry": {"coordinates":[17.8982,-6.14422],"type":"Point"}
}