{
  "type": "Feature",
  "properties": {
    "gn:admin1_code":"22.0",
    "gn:asciiname":"Solisa",
    "gn:country_code":"CD",
    "gn:dem":1025,
    "gn:feature_class":"P",
    "gn:feature_code":"PPL",
    "gn:name":"Solisa",
    "gn:population":0,
    "gn:timezone":"Africa/Lubumbashi",
    "iso:country":"CD",
    "wof:name":"Solisa",
    "wof:placetype":"locality"
},
  "geometry": {"coordinates":[23.09842,-10.47655],"type":"Point"}
}