{
  "type": "Feature",
  "properties": {
    "gn:admin1_code":"24.0",
    "gn:asciiname":"Mongama",
    "gn:country_code":"CD",
    "gn:dem":408,
    "gn:feature_class":"P",
    "gn:feature_code":"PPL",
    "gn:name":"Mongama",
    "gn:population":0,
    "gn:timezone":"Africa/Kinshasa",
    "iso:country":"CD",
    "wof:name":"Mongama",
    "wof:placetype":"locality"
},
  "geometry": {"coordinates":[16.62301,-2.61795],"type":"Point"}
}