{
  "type": "Feature",
  "properties": {
    "gn:admin1_code":"23.0",
    "gn:asciiname":"Mansamba",
    "gn:country_code":"CD",
    "gn:dem":769,
    "gn:feature_class":"P",
    "gn:feature_code":"PPL",
    "gn:name":"Mansamba",
    "gn:population":0,
    "gn:timezone":"Africa/Lubumbashi",
    "iso:country":"CD",
    "wof:name":"Mansamba",
    "wof:placetype":"locality"
},
  "geometry": {"coordinates":[22.98355,-6.34982],"type":"Point"}
}