{
  "type": "Feature",
  "properties": {
    "gn:admin1_code":"19.0",
    "gn:asciiname":"Kiala",
    "gn:country_code":"CD",
    "gn:dem":671,
    "gn:feature_class":"P",
    "gn:feature_code":"PPL",
    "gn:name":"Kiala",
    "gn:population":0,
    "gn:timezone":"Africa/Kinshasa",
    "iso:country":"CD",
    "name:fas_x_preferred":[
        "\u06a9\u06cc\u0627\u0644\u0647"
    ],
    "wof:name":"Kiala",
    "wof:placetype":"locality"
},
  "geometry": {"coordinates":[17.50849,-7.01722],"type":"Point"}
}