{
  "type": "Feature",
  "properties": {
    "gn:admin1_code":"20.0",
    "gn:asciiname":"Musenge-Munene",
    "gn:country_code":"CD",
    "gn:dem":669,
    "gn:feature_class":"P",
    "gn:feature_code":"PPL",
    "gn:name":"Musenge-Munene",
    "gn:population":0,
    "gn:timezone":"Africa/Kinshasa",
    "iso:country":"CD",
    "wof:name":"Musenge-Munene",
    "wof:placetype":"locality"
},
  "geometry": {"coordinates":[19.41185,-4.75815],"type":"Point"}
}