{
  "type": "Feature",
  "properties": {
    "gn:admin1_code":"19.0",
    "gn:asciiname":"Swa-Kibula",
    "gn:country_code":"CD",
    "gn:dem":459,
    "gn:feature_class":"P",
    "gn:feature_code":"PPL",
    "gn:name":"Swa-Kibula",
    "gn:population":0,
    "gn:timezone":"Africa/Luanda",
    "iso:country":"CD",
    "name:und_x_variant":[
        "Sua Kibula",
        "Swa-Kibula"
    ],
    "wof:name":"Swa-Kibula",
    "wof:placetype":"locality"
},
  "geometry": {"coordinates":[16.98293,-7.23777],"type":"Point"}
}