{
  "type": "Feature",
  "properties": {
    "gn:admin1_code":"11.0",
    "gn:asciiname":"Kalingote",
    "gn:country_code":"CD",
    "gn:dem":1481,
    "gn:feature_class":"P",
    "gn:feature_code":"PPL",
    "gn:name":"Kalingote",
    "gn:population":0,
    "gn:timezone":"Africa/Lubumbashi",
    "iso:country":"CD",
    "wof:name":"Kalingote",
    "wof:placetype":"locality"
},
  "geometry": {"coordinates":[29.47797000000001,0.43099],"type":"Point"}
}