{
  "type": "Feature",
  "properties": {
    "gn:admin1_code":"10.0",
    "gn:asciiname":"Deo",
    "gn:country_code":"CD",
    "gn:dem":479,
    "gn:feature_class":"P",
    "gn:feature_code":"PPL",
    "gn:name":"Deo",
    "gn:population":0,
    "gn:timezone":"Africa/Lubumbashi",
    "iso:country":"CD",
    "name:ceb_x_preferred":[
        "Deo"
    ],
    "name:deu_x_preferred":[
        "Deo"
    ],
    "name:nld_x_preferred":[
        "Deo"
    ],
    "name:swe_x_preferred":[
        "Deo"
    ],
    "wof:name":"Deo",
    "wof:placetype":"locality"
},
  "geometry": {"coordinates":[25.03904,-3.23107],"type":"Point"}
}