{
  "type": "Feature",
  "properties": {
    "gn:admin1_code":"19.0",
    "gn:asciiname":"Kikwati",
    "gn:country_code":"CD",
    "gn:dem":604,
    "gn:feature_class":"P",
    "gn:feature_code":"PPL",
    "gn:name":"Kikwati",
    "gn:population":0,
    "gn:timezone":"Africa/Kinshasa",
    "iso:country":"CD",
    "wof:name":"Kikwati",
    "wof:placetype":"locality"
},
  "geometry": {"coordinates":[16.86667000000001,-6.48333],"type":"Point"}
}