{
  "type": "Feature",
  "properties": {
    "gn:admin1_code":"8.0",
    "gn:asciiname":"Kinsuamu",
    "gn:country_code":"CD",
    "gn:dem":812,
    "gn:feature_class":"P",
    "gn:feature_code":"PPL",
    "gn:name":"Kinsuamu",
    "gn:population":0,
    "gn:timezone":"Africa/Kinshasa",
    "iso:country":"CD",
    "wof:name":"Kinsuamu",
    "wof:placetype":"locality"
},
  "geometry": {"coordinates":[15.98106,-5.44421],"type":"Point"}
}