{
  "type": "Feature",
  "properties": {
    "gn:admin1_code":"11.0",
    "gn:asciiname":"Vitshumbi",
    "gn:country_code":"CD",
    "gn:dem":915,
    "gn:feature_class":"P",
    "gn:feature_code":"PPL",
    "gn:name":"Vitshumbi",
    "gn:population":0,
    "gn:timezone":"Africa/Lubumbashi",
    "iso:country":"CD",
    "wof:name":"Vitshumbi",
    "wof:placetype":"locality"
},
  "geometry": {"coordinates":[29.37161,-0.70492],"type":"Point"}
}