{
  "type": "Feature",
  "properties": {
    "gn:admin1_code":"18.0",
    "gn:asciiname":"Ngandu",
    "gn:country_code":"CD",
    "gn:dem":830,
    "gn:feature_class":"P",
    "gn:feature_code":"PPL",
    "gn:name":"Ngandu",
    "gn:population":0,
    "gn:timezone":"Africa/Lubumbashi",
    "iso:country":"CD",
    "name:ceb_x_preferred":[
        "Ngandu"
    ],
    "name:swe_x_preferred":[
        "Ngandu"
    ],
    "name:und_x_variant":[
        "Gandu",
        "Ngandu"
    ],
    "wof:name":"Ngandu",
    "wof:placetype":"locality"
},
  "geometry": {"coordinates":[20.16717,-6.62776],"type":"Point"}
}