{
  "type": "Feature",
  "properties": {
    "gn:admin1_code":"27.0",
    "gn:asciiname":"Penda",
    "gn:country_code":"CD",
    "gn:dem":472,
    "gn:feature_class":"P",
    "gn:feature_code":"PPL",
    "gn:name":"Penda",
    "gn:population":0,
    "gn:timezone":"Africa/Lubumbashi",
    "iso:country":"CD",
    "wof:name":"Penda",
    "wof:placetype":"locality"
},
  "geometry": {"coordinates":[23.45,-2.28333],"type":"Point"}
}