{
  "type": "Feature",
  "properties": {
    "gn:admin1_code":"6.0",
    "gn:asciiname":"Kisangolu",
    "gn:country_code":"CD",
    "gn:dem":297,
    "gn:feature_class":"P",
    "gn:feature_code":"PPL",
    "gn:name":"Kisangolu",
    "gn:population":0,
    "gn:timezone":"Africa/Kinshasa",
    "iso:country":"CD",
    "wof:name":"Kisangolu",
    "wof:placetype":"locality"
},
  "geometry": {"coordinates":[15.17575,-4.40693],"type":"Point"}
}