{
  "type": "Feature",
  "properties": {
    "gn:admin1_code":"20.0",
    "gn:asciiname":"Kihunda",
    "gn:country_code":"CD",
    "gn:dem":747,
    "gn:feature_class":"P",
    "gn:feature_code":"PPL",
    "gn:name":"Kihunda",
    "gn:population":0,
    "gn:timezone":"Africa/Kinshasa",
    "iso:country":"CD",
    "wof:name":"Kihunda",
    "wof:placetype":"locality"
},
  "geometry": {"coordinates":[19.32968,-5.69187],"type":"Point"}
}