{
  "type": "Feature",
  "properties": {
    "gn:admin1_code":"15.0",
    "gn:asciiname":"Boto",
    "gn:country_code":"CD",
    "gn:dem":1078,
    "gn:feature_class":"P",
    "gn:feature_code":"PPL",
    "gn:name":"Boto",
    "gn:population":0,
    "gn:timezone":"Africa/Lubumbashi",
    "iso:country":"CD",
    "name:und_x_variant":[
        "Bolo",
        "Boto"
    ],
    "wof:name":"Boto",
    "wof:placetype":"locality"
},
  "geometry": {"coordinates":[25.16667,-8.23333],"type":"Point"}
}