{
  "type": "Feature",
  "properties": {
    "gn:admin1_code":"23.0",
    "gn:asciiname":"Nkuna",
    "gn:country_code":"CD",
    "gn:dem":752,
    "gn:feature_class":"P",
    "gn:feature_code":"PPL",
    "gn:name":"Nkuna",
    "gn:population":0,
    "gn:timezone":"Africa/Lubumbashi",
    "iso:country":"CD",
    "name:und_x_variant":[
        "Kuna",
        "Nkuna"
    ],
    "wof:name":"Nkuna",
    "wof:placetype":"locality"
},
  "geometry": {"coordinates":[22.98779,-6.18],"type":"Point"}
}