{
  "type": "Feature",
  "properties": {
    "gn:admin1_code":"16.0",
    "gn:asciiname":"Agboiso",
    "gn:country_code":"CD",
    "gn:dem":822,
    "gn:feature_class":"P",
    "gn:feature_code":"PPL",
    "gn:name":"Agboiso",
    "gn:population":0,
    "gn:timezone":"Africa/Lubumbashi",
    "iso:country":"CD",
    "wof:name":"Agboiso",
    "wof:placetype":"locality"
},
  "geometry": {"coordinates":[27.55653,2.10824],"type":"Point"}
}