{
  "type": "Feature",
  "properties": {
    "gn:admin1_code":"21.0",
    "gn:asciiname":"Kiambe",
    "gn:country_code":"CD",
    "gn:dem":681,
    "gn:feature_class":"P",
    "gn:feature_code":"PPL",
    "gn:name":"Kiambe",
    "gn:population":0,
    "gn:timezone":"Africa/Lubumbashi",
    "iso:country":"CD",
    "wof:name":"Kiambe",
    "wof:placetype":"locality"
},
  "geometry": {"coordinates":[24.80972,-5.38176],"type":"Point"}
}