{
  "type": "Feature",
  "properties": {
    "gn:admin1_code":"26.0",
    "gn:asciiname":"Dengbwili",
    "gn:country_code":"CD",
    "gn:dem":393,
    "gn:feature_class":"P",
    "gn:feature_code":"PPL",
    "gn:name":"Dengbwili",
    "gn:population":0,
    "gn:timezone":"Africa/Kinshasa",
    "iso:country":"CD",
    "wof:name":"Dengbwili",
    "wof:placetype":"locality"
},
  "geometry": {"coordinates":[19.43334,4.94714],"type":"Point"}
}