{
  "type": "Feature",
  "properties": {
    "gn:admin1_code":"28.0",
    "gn:asciiname":"Bobabili",
    "gn:country_code":"CD",
    "gn:dem":350,
    "gn:feature_class":"P",
    "gn:feature_code":"PPL",
    "gn:name":"Bobabili",
    "gn:population":0,
    "gn:timezone":"Africa/Kinshasa",
    "iso:country":"CD",
    "wof:name":"Bobabili",
    "wof:placetype":"locality"
},
  "geometry": {"coordinates":[19.06021,3.07883],"type":"Point"}
}