{
  "type": "Feature",
  "properties": {
    "gn:admin1_code":"24.0",
    "gn:asciiname":"Mafwa",
    "gn:country_code":"CD",
    "gn:dem":303,
    "gn:feature_class":"P",
    "gn:feature_code":"PPL",
    "gn:name":"Mafwa",
    "gn:population":0,
    "gn:timezone":"Africa/Kinshasa",
    "iso:country":"CD",
    "name:und_x_variant":[
        "Mafua"
    ],
    "wof:name":"Mafwa",
    "wof:placetype":"locality"
},
  "geometry": {"coordinates":[17.70619,-2.2608],"type":"Point"}
}