{
  "type": "Feature",
  "properties": {
    "gn:admin1_code":"22.0",
    "gn:asciiname":"Tshitshele",
    "gn:country_code":"CD",
    "gn:dem":1065,
    "gn:feature_class":"P",
    "gn:feature_code":"PPL",
    "gn:name":"Tshitshele",
    "gn:population":0,
    "gn:timezone":"Africa/Lubumbashi",
    "iso:country":"CD",
    "wof:name":"Tshitshele",
    "wof:placetype":"locality"
},
  "geometry": {"coordinates":[23.12656,-10.65075],"type":"Point"}
}