{
  "type": "Feature",
  "properties": {
    "gn:admin1_code":"25.0",
    "gn:asciiname":"Yaliwila",
    "gn:country_code":"CD",
    "gn:dem":386,
    "gn:feature_class":"P",
    "gn:feature_code":"PPL",
    "gn:name":"Yaliwila",
    "gn:population":0,
    "gn:timezone":"Africa/Kinshasa",
    "iso:country":"CD",
    "wof:name":"Yaliwila",
    "wof:placetype":"locality"
},
  "geometry": {"coordinates":[22.4459,2.22924],"type":"Point"}
}