{
  "type": "Feature",
  "properties": {
    "gn:admin1_code":"30.0",
    "gn:asciiname":"Bombwa",
    "gn:country_code":"CD",
    "gn:dem":435,
    "gn:feature_class":"P",
    "gn:feature_code":"PPL",
    "gn:name":"Bombwa",
    "gn:population":0,
    "gn:timezone":"Africa/Lubumbashi",
    "iso:country":"CD",
    "wof:name":"Bombwa",
    "wof:placetype":"locality"
},
  "geometry": {"coordinates":[25.63169,1.89935],"type":"Point"}
}