{
  "type": "Feature",
  "properties": {
    "gn:admin1_code":"18.0",
    "gn:asciiname":"Tshilumbai-Katalayie",
    "gn:country_code":"CD",
    "gn:dem":713,
    "gn:feature_class":"P",
    "gn:feature_code":"PPL",
    "gn:name":"Tshilumbai-Katalayie",
    "gn:population":0,
    "gn:timezone":"Africa/Lubumbashi",
    "iso:country":"CD",
    "wof:name":"Tshilumbai-Katalayie",
    "wof:placetype":"locality"
},
  "geometry": {"coordinates":[21.06409,-6.27059],"type":"Point"}
}