{
  "type": "Feature",
  "properties": {
    "gn:admin1_code":"8.0",
    "gn:asciiname":"Sangi",
    "gn:country_code":"CD",
    "gn:dem":566,
    "gn:feature_class":"P",
    "gn:feature_code":"PPL",
    "gn:name":"Sangi",
    "gn:population":0,
    "gn:timezone":"Africa/Kinshasa",
    "iso:country":"CD",
    "name:ceb_x_preferred":[
        "Sangi"
    ],
    "name:swe_x_preferred":[
        "Sangi"
    ],
    "wof:name":"Sangi",
    "wof:placetype":"locality"
},
  "geometry": {"coordinates":[15.02799,-5.21371],"type":"Point"}
}