{
  "type": "Feature",
  "properties": {
    "gn:admin1_code":"16.0",
    "gn:asciiname":"Ngaluma",
    "gn:country_code":"CD",
    "gn:dem":794,
    "gn:feature_class":"P",
    "gn:feature_code":"PPL",
    "gn:name":"Ngaluma",
    "gn:population":0,
    "gn:timezone":"Africa/Lubumbashi",
    "iso:country":"CD",
    "wof:name":"Ngaluma",
    "wof:placetype":"locality"
},
  "geometry": {"coordinates":[27.97576,2.18239],"type":"Point"}
}