{
  "type": "Feature",
  "properties": {
    "gn:admin1_code":"14.0",
    "gn:asciiname":"Kitubulushi",
    "gn:country_code":"CD",
    "gn:dem":1252,
    "gn:feature_class":"P",
    "gn:feature_code":"PPL",
    "gn:name":"Kitubulushi",
    "gn:population":0,
    "gn:timezone":"Africa/Lubumbashi",
    "iso:country":"CD",
    "name:und_x_variant":[
        "Kilubulushi",
        "Kitubulushi"
    ],
    "wof:name":"Kitubulushi",
    "wof:placetype":"locality"
},
  "geometry": {"coordinates":[28.94078,-12.74954],"type":"Point"}
}