{
  "type": "Feature",
  "properties": {
    "gn:admin1_code":"17.0",
    "gn:asciiname":"Ekumva",
    "gn:country_code":"CD",
    "gn:dem":1018,
    "gn:feature_class":"P",
    "gn:feature_code":"PPL",
    "gn:name":"Ekumva",
    "gn:population":0,
    "gn:timezone":"Africa/Lubumbashi",
    "iso:country":"CD",
    "wof:name":"Ekumva",
    "wof:placetype":"locality"
},
  "geometry": {"coordinates":[30.23333,2.98333],"type":"Point"}
}