{
  "type": "Feature",
  "properties": {
    "gn:admin1_code":"25.0",
    "gn:asciiname":"Yamombelu",
    "gn:country_code":"CD",
    "gn:dem":390,
    "gn:feature_class":"P",
    "gn:feature_code":"PPL",
    "gn:name":"Yamombelu",
    "gn:population":0,
    "gn:timezone":"Africa/Kinshasa",
    "iso:country":"CD",
    "wof:name":"Yamombelu",
    "wof:placetype":"locality"
},
  "geometry": {"coordinates":[22.19858,2.35853],"type":"Point"}
}