{
  "type": "Feature",
  "properties": {
    "gn:admin1_code":"30.0",
    "gn:asciiname":"Yabangia I",
    "gn:country_code":"CD",
    "gn:dem":403,
    "gn:feature_class":"P",
    "gn:feature_code":"PPL",
    "gn:name":"Yabangia I",
    "gn:population":0,
    "gn:timezone":"Africa/Lubumbashi",
    "iso:country":"CD",
    "wof:name":"Yabangia I",
    "wof:placetype":"locality"
},
  "geometry": {"coordinates":[23.71667,1.41667],"type":"Point"}
}