{
  "type": "Feature",
  "properties": {
    "gn:admin1_code":"24.0",
    "gn:asciiname":"Ilongo",
    "gn:country_code":"CD",
    "gn:dem":404,
    "gn:feature_class":"P",
    "gn:feature_code":"PPL",
    "gn:name":"Ilongo",
    "gn:population":0,
    "gn:timezone":"Africa/Kinshasa",
    "iso:country":"CD",
    "wof:name":"Ilongo",
    "wof:placetype":"locality"
},
  "geometry": {"coordinates":[18.93651,-3.42977],"type":"Point"}
}