{
  "type": "Feature",
  "properties": {
    "gn:admin1_code":"22.0",
    "gn:asciiname":"Dijila",
    "gn:country_code":"CD",
    "gn:dem":989,
    "gn:feature_class":"P",
    "gn:feature_code":"PPL",
    "gn:name":"Dijila",
    "gn:population":0,
    "gn:timezone":"Africa/Lubumbashi",
    "iso:country":"CD",
    "wof:name":"Dijila",
    "wof:placetype":"locality"
},
  "geometry": {"coordinates":[22.81629,-9.38793],"type":"Point"}
}