{
  "type": "Feature",
  "properties": {
    "gn:admin1_code":"22.0",
    "gn:asciiname":"Tshipalama",
    "gn:country_code":"CD",
    "gn:dem":1534,
    "gn:feature_class":"P",
    "gn:feature_code":"PPL",
    "gn:name":"Tshipalama",
    "gn:population":0,
    "gn:timezone":"Africa/Lubumbashi",
    "iso:country":"CD",
    "wof:name":"Tshipalama",
    "wof:placetype":"locality"
},
  "geometry": {"coordinates":[25.30965,-11.46164],"type":"Point"}
}