{
  "type": "Feature",
  "properties": {
    "gn:admin1_code":"11.0",
    "gn:asciiname":"Mpunga",
    "gn:country_code":"CD",
    "gn:dem":1177,
    "gn:feature_class":"P",
    "gn:feature_code":"PPL",
    "gn:name":"Mpunga",
    "gn:population":0,
    "gn:timezone":"Africa/Lubumbashi",
    "iso:country":"CD",
    "wof:name":"Mpunga",
    "wof:placetype":"locality"
},
  "geometry": {"coordinates":[29.46471,-1.10467],"type":"Point"}
}