{
  "type": "Feature",
  "properties": {
    "gn:admin1_code":"23.0",
    "gn:asciiname":"Kasova",
    "gn:country_code":"CD",
    "gn:dem":786,
    "gn:feature_class":"P",
    "gn:feature_code":"PPL",
    "gn:name":"Kasova",
    "gn:population":0,
    "gn:timezone":"Africa/Lubumbashi",
    "iso:country":"CD",
    "wof:name":"Kasova",
    "wof:placetype":"locality"
},
  "geometry": {"coordinates":[22.48407000000001,-6.95842],"type":"Point"}
}