{
  "type": "Feature",
  "properties": {
    "gn:admin1_code":"24.0",
    "gn:asciiname":"Botulu",
    "gn:country_code":"CD",
    "gn:dem":629,
    "gn:feature_class":"P",
    "gn:feature_code":"PPL",
    "gn:name":"Botulu",
    "gn:population":0,
    "gn:timezone":"Africa/Kinshasa",
    "iso:country":"CD",
    "name:che_x_preferred":[
        "\u0411\u043e\u0442\u0443\u043b\u0443"
    ],
    "name:rus_x_preferred":[
        "\u0411\u043e\u0442\u0443\u043b\u0443"
    ],
    "name:sah_x_preferred":[
        "\u0411\u043e\u043e\u0442\u0443\u043b\u0443"
    ],
    "name:ukr_x_preferred":[
        "\u0411\u043e\u0442\u0443\u043b\u0443"
    ],
    "name:und_x_variant":[
        "Butulu",
        "Botulu"
    ],
    "wof:name":"Botulu",
    "wof:placetype":"locality"
},
  "geometry": {"coordinates":[16.44847,-3.96917],"type":"Point"}
}