{
  "type": "Feature",
  "properties": {
    "gn:admin1_code":"19.0",
    "gn:asciiname":"Kaseka",
    "gn:country_code":"CD",
    "gn:dem":989,
    "gn:feature_class":"P",
    "gn:feature_code":"PPL",
    "gn:name":"Kaseka",
    "gn:population":0,
    "gn:timezone":"Africa/Kinshasa",
    "iso:country":"CD",
    "wof:name":"Kaseka",
    "wof:placetype":"locality"
},
  "geometry": {"coordinates":[18.01543,-7.13764],"type":"Point"}
}