{
  "type": "Feature",
  "properties": {
    "gn:admin1_code":"18.0",
    "gn:asciiname":"Shakalulu",
    "gn:country_code":"CD",
    "gn:dem":653,
    "gn:feature_class":"P",
    "gn:feature_code":"PPL",
    "gn:name":"Shakalulu",
    "gn:population":0,
    "gn:timezone":"Africa/Lubumbashi",
    "iso:country":"CD",
    "wof:name":"Shakalulu",
    "wof:placetype":"locality"
},
  "geometry": {"coordinates":[20.46548,-6.63684],"type":"Point"}
}