{
  "type": "Feature",
  "properties": {
    "gn:admin1_code":"23.0",
    "gn:asciiname":"Tshiswaka-Fwatatshi",
    "gn:country_code":"CD",
    "gn:dem":537,
    "gn:feature_class":"P",
    "gn:feature_code":"PPL",
    "gn:name":"Tshiswaka-Fwatatshi",
    "gn:population":0,
    "gn:timezone":"Africa/Lubumbashi",
    "iso:country":"CD",
    "wof:name":"Tshiswaka-Fwatatshi",
    "wof:placetype":"locality"
},
  "geometry": {"coordinates":[22.31859,-5.90167],"type":"Point"}
}