{
  "type": "Feature",
  "properties": {
    "gn:admin1_code":"19.0",
    "gn:asciiname":"Shatshihango",
    "gn:country_code":"CD",
    "gn:dem":916,
    "gn:feature_class":"P",
    "gn:feature_code":"PPL",
    "gn:name":"Shatshihango",
    "gn:population":0,
    "gn:timezone":"Africa/Kinshasa",
    "iso:country":"CD",
    "wof:name":"Shatshihango",
    "wof:placetype":"locality"
},
  "geometry": {"coordinates":[19.49849,-7.15905],"type":"Point"}
}