{
  "type": "Feature",
  "properties": {
    "gn:admin1_code":"22.0",
    "gn:asciiname":"Mushima",
    "gn:country_code":"CD",
    "gn:dem":1346,
    "gn:feature_class":"P",
    "gn:feature_code":"PPL",
    "gn:name":"Mushima",
    "gn:population":0,
    "gn:timezone":"Africa/Lubumbashi",
    "iso:country":"CD",
    "wof:name":"Mushima",
    "wof:placetype":"locality"
},
  "geometry": {"coordinates":[25.64539,-11.38547],"type":"Point"}
}