{
  "type": "Feature",
  "properties": {
    "gn:admin1_code":"14.0",
    "gn:asciiname":"Lukalela",
    "gn:country_code":"CD",
    "gn:dem":1022,
    "gn:feature_class":"P",
    "gn:feature_code":"PPL",
    "gn:name":"Lukalela",
    "gn:population":0,
    "gn:timezone":"Africa/Lubumbashi",
    "iso:country":"CD",
    "wof:name":"Lukalela",
    "wof:placetype":"locality"
},
  "geometry": {"coordinates":[28.97105,-8.36722],"type":"Point"}
}