{
  "type": "Feature",
  "properties": {
    "gn:admin1_code":"20.0",
    "gn:asciiname":"Mutema",
    "gn:country_code":"CD",
    "gn:dem":683,
    "gn:feature_class":"P",
    "gn:feature_code":"PPL",
    "gn:name":"Mutema",
    "gn:population":0,
    "gn:timezone":"Africa/Kinshasa",
    "iso:country":"CD",
    "wof:name":"Mutema",
    "wof:placetype":"locality"
},
  "geometry": {"coordinates":[18.08827,-5.15708],"type":"Point"}
}