{
  "type": "Feature",
  "properties": {
    "gn:admin1_code":"18.0",
    "gn:asciiname":"Shamatemu",
    "gn:country_code":"CD",
    "gn:dem":525,
    "gn:feature_class":"P",
    "gn:feature_code":"PPL",
    "gn:name":"Shamatemu",
    "gn:population":0,
    "gn:timezone":"Africa/Lubumbashi",
    "iso:country":"CD",
    "wof:name":"Shamatemu",
    "wof:placetype":"locality"
},
  "geometry": {"coordinates":[20.66729,-4.6542],"type":"Point"}
}