{
  "type": "Feature",
  "properties": {
    "gn:admin1_code":"22.0",
    "gn:asciiname":"Mukuza",
    "gn:country_code":"CD",
    "gn:dem":1135,
    "gn:feature_class":"P",
    "gn:feature_code":"PPL",
    "gn:name":"Mukuza",
    "gn:population":0,
    "gn:timezone":"Africa/Lubumbashi",
    "iso:country":"CD",
    "wof:name":"Mukuza",
    "wof:placetype":"locality"
},
  "geometry": {"coordinates":[22.49086,-11.04682],"type":"Point"}
}