{
  "type": "Feature",
  "properties": {
    "gn:admin1_code":"17.0",
    "gn:asciiname":"Ngodja",
    "gn:country_code":"CD",
    "gn:dem":1646,
    "gn:feature_class":"P",
    "gn:feature_code":"PPL",
    "gn:name":"Ngodja",
    "gn:population":0,
    "gn:timezone":"Africa/Lubumbashi",
    "iso:country":"CD",
    "wof:name":"Ngodja",
    "wof:placetype":"locality"
},
  "geometry": {"coordinates":[30.48428,2.22919],"type":"Point"}
}