{
  "type": "Feature",
  "properties": {
    "gn:admin1_code":"21.0",
    "gn:asciiname":"Bakwa-Bowa",
    "gn:country_code":"CD",
    "gn:dem":846,
    "gn:feature_class":"P",
    "gn:feature_code":"PPL",
    "gn:name":"Bakwa-Bowa",
    "gn:population":0,
    "gn:timezone":"Africa/Lubumbashi",
    "iso:country":"CD",
    "wof:name":"Bakwa-Bowa",
    "wof:placetype":"locality"
},
  "geometry": {"coordinates":[23.55314,-6.78059],"type":"Point"}
}