{
  "type": "Feature",
  "properties": {
    "gn:admin1_code":"15.0",
    "gn:asciiname":"Kabwe Katanda",
    "gn:country_code":"CD",
    "gn:dem":885,
    "gn:feature_class":"P",
    "gn:feature_code":"PPL",
    "gn:name":"Kabwe Katanda",
    "gn:population":0,
    "gn:timezone":"Africa/Lubumbashi",
    "iso:country":"CD",
    "wof:name":"Kabwe Katanda",
    "wof:placetype":"locality"
},
  "geometry": {"coordinates":[24.00875,-7.6091],"type":"Point"}
}