{
  "type": "Feature",
  "properties": {
    "gn:admin1_code":"15.0",
    "gn:asciiname":"Lupulu",
    "gn:country_code":"CD",
    "gn:dem":1104,
    "gn:feature_class":"P",
    "gn:feature_code":"PPL",
    "gn:name":"Lupulu",
    "gn:population":0,
    "gn:timezone":"Africa/Lubumbashi",
    "iso:country":"CD",
    "name:und_x_variant":[
        "Lupula",
        "Lupulu"
    ],
    "wof:name":"Lupulu",
    "wof:placetype":"locality"
},
  "geometry": {"coordinates":[25.15583,-8.65917],"type":"Point"}
}