{
  "type": "Feature",
  "properties": {
    "gn:admin1_code":"19.0",
    "gn:asciiname":"Kikwengu",
    "gn:country_code":"CD",
    "gn:dem":728,
    "gn:feature_class":"P",
    "gn:feature_code":"PPL",
    "gn:name":"Kikwengu",
    "gn:population":0,
    "gn:timezone":"Africa/Kinshasa",
    "iso:country":"CD",
    "wof:name":"Kikwengu",
    "wof:placetype":"locality"
},
  "geometry": {"coordinates":[17.70045,-5.75857],"type":"Point"}
}