{
  "type": "Feature",
  "properties": {
    "gn:admin1_code":"14.0",
    "gn:asciiname":"Bombwe",
    "gn:country_code":"CD",
    "gn:dem":1155,
    "gn:feature_class":"P",
    "gn:feature_code":"PPL",
    "gn:name":"Bombwe",
    "gn:population":0,
    "gn:timezone":"Africa/Lubumbashi",
    "iso:country":"CD",
    "wof:name":"Bombwe",
    "wof:placetype":"locality"
},
  "geometry": {"coordinates":[27.78387,-11.75061],"type":"Point"}
}