{
  "type": "Feature",
  "properties": {
    "gn:admin1_code":"18.0",
    "gn:asciiname":"Kaluimbi",
    "gn:country_code":"CD",
    "gn:dem":684,
    "gn:feature_class":"P",
    "gn:feature_code":"PPL",
    "gn:name":"Kaluimbi",
    "gn:population":0,
    "gn:timezone":"Africa/Lubumbashi",
    "iso:country":"CD",
    "wof:name":"Kaluimbi",
    "wof:placetype":"locality"
},
  "geometry": {"coordinates":[20.91546,-7.11716],"type":"Point"}
}