{
  "type": "Feature",
  "properties": {
    "gn:admin1_code":"18.0",
    "gn:asciiname":"Muyombo",
    "gn:country_code":"CD",
    "gn:dem":691,
    "gn:feature_class":"P",
    "gn:feature_code":"PPL",
    "gn:name":"Muyombo",
    "gn:population":0,
    "gn:timezone":"Africa/Lubumbashi",
    "iso:country":"CD",
    "wof:name":"Muyombo",
    "wof:placetype":"locality"
},
  "geometry": {"coordinates":[20.84612000000001,-6.67978],"type":"Point"}
}