{
  "type": "Feature",
  "properties": {
    "gn:admin1_code":"15.0",
    "gn:asciiname":"Kibambi",
    "gn:country_code":"CD",
    "gn:dem":964,
    "gn:feature_class":"P",
    "gn:feature_code":"PPL",
    "gn:name":"Kibambi",
    "gn:population":0,
    "gn:timezone":"Africa/Lubumbashi",
    "iso:country":"CD",
    "wof:name":"Kibambi",
    "wof:placetype":"locality"
},
  "geometry": {"coordinates":[25.46335,-7.03113],"type":"Point"}
}