{
  "type": "Feature",
  "properties": {
    "gn:admin1_code":"20.0",
    "gn:asciiname":"Kongo-Luwai",
    "gn:country_code":"CD",
    "gn:dem":776,
    "gn:feature_class":"P",
    "gn:feature_code":"PPL",
    "gn:name":"Kongo-Luwai",
    "gn:population":0,
    "gn:timezone":"Africa/Kinshasa",
    "iso:country":"CD",
    "wof:name":"Kongo-Luwai",
    "wof:placetype":"locality"
},
  "geometry": {"coordinates":[17.83961,-5.60225],"type":"Point"}
}