{
  "type": "Feature",
  "properties": {
    "gn:admin1_code":"21.0",
    "gn:asciiname":"Bena-Matemba",
    "gn:country_code":"CD",
    "gn:dem":721,
    "gn:feature_class":"P",
    "gn:feature_code":"PPL",
    "gn:name":"Bena-Matemba",
    "gn:population":0,
    "gn:timezone":"Africa/Lubumbashi",
    "iso:country":"CD",
    "wof:name":"Bena-Matemba",
    "wof:placetype":"locality"
},
  "geometry": {"coordinates":[23.95952,-6.58845],"type":"Point"}
}