{
  "type": "Feature",
  "properties": {
    "gn:admin1_code":"22.0",
    "gn:asciiname":"Tshinialulu",
    "gn:country_code":"CD",
    "gn:dem":1113,
    "gn:feature_class":"P",
    "gn:feature_code":"PPL",
    "gn:name":"Tshinialulu",
    "gn:population":0,
    "gn:timezone":"Africa/Lubumbashi",
    "iso:country":"CD",
    "wof:name":"Tshinialulu",
    "wof:placetype":"locality"
},
  "geometry": {"coordinates":[22.37066,-11.15453],"type":"Point"}
}