{
  "type": "Feature",
  "properties": {
    "gn:admin1_code":"8.0",
    "gn:asciiname":"Londe-Nzadi",
    "gn:country_code":"CD",
    "gn:dem":485,
    "gn:feature_class":"P",
    "gn:feature_code":"PPL",
    "gn:name":"Londe-Nzadi",
    "gn:population":0,
    "gn:timezone":"Africa/Kinshasa",
    "iso:country":"CD",
    "wof:name":"Londe-Nzadi",
    "wof:placetype":"locality"
},
  "geometry": {"coordinates":[14.45245,-4.44496],"type":"Point"}
}