{
  "type": "Feature",
  "properties": {
    "gn:admin1_code":"24.0",
    "gn:asciiname":"Etumba",
    "gn:country_code":"CD",
    "gn:dem":403,
    "gn:feature_class":"P",
    "gn:feature_code":"PPL",
    "gn:name":"Etumba",
    "gn:population":0,
    "gn:timezone":"Africa/Kinshasa",
    "iso:country":"CD",
    "wof:name":"Etumba",
    "wof:placetype":"locality"
},
  "geometry": {"coordinates":[19.91102,-2.91803],"type":"Point"}
}