{
  "type": "Feature",
  "properties": {
    "gn:admin1_code":"15.0",
    "gn:asciiname":"Kaseba",
    "gn:country_code":"CD",
    "gn:dem":763,
    "gn:feature_class":"P",
    "gn:feature_code":"PPL",
    "gn:name":"Kaseba",
    "gn:population":0,
    "gn:timezone":"Africa/Lubumbashi",
    "iso:country":"CD",
    "wof:name":"Kaseba",
    "wof:placetype":"locality"
},
  "geometry": {"coordinates":[26.08495,-7.40379],"type":"Point"}
}