{
  "type": "Feature",
  "properties": {
    "gn:admin1_code":"28.0",
    "gn:asciiname":"Bele",
    "gn:country_code":"CD",
    "gn:dem":456,
    "gn:feature_class":"P",
    "gn:feature_code":"PPL",
    "gn:name":"Bele",
    "gn:population":0,
    "gn:timezone":"Africa/Kinshasa",
    "iso:country":"CD",
    "name:ceb_x_preferred":[
        "Bele"
    ],
    "name:swe_x_preferred":[
        "Bele"
    ],
    "wof:name":"Bele",
    "wof:placetype":"locality"
},
  "geometry": {"coordinates":[19.24637,4.0982],"type":"Point"}
}