{
  "type": "Feature",
  "properties": {
    "gn:admin1_code":"26.0",
    "gn:asciiname":"Kandu",
    "gn:country_code":"CD",
    "gn:dem":418,
    "gn:feature_class":"P",
    "gn:feature_code":"PPL",
    "gn:name":"Kandu",
    "gn:population":0,
    "gn:timezone":"Africa/Kinshasa",
    "iso:country":"CD",
    "wof:name":"Kandu",
    "wof:placetype":"locality"
},
  "geometry": {"coordinates":[22.23179,4.06845],"type":"Point"}
}