{
  "type": "Feature",
  "properties": {
    "gn:admin1_code":"24.0",
    "gn:asciiname":"Bodja",
    "gn:country_code":"CD",
    "gn:dem":392,
    "gn:feature_class":"P",
    "gn:feature_code":"PPL",
    "gn:name":"Bodja",
    "gn:population":0,
    "gn:timezone":"Africa/Kinshasa",
    "iso:country":"CD",
    "wof:name":"Bodja",
    "wof:placetype":"locality"
},
  "geometry": {"coordinates":[18.50474,-3.31073],"type":"Point"}
}