{
  "type": "Feature",
  "properties": {
    "gn:admin1_code":"24.0",
    "gn:asciiname":"Ganda de Bolombo I",
    "gn:country_code":"CD",
    "gn:dem":308,
    "gn:feature_class":"P",
    "gn:feature_code":"PPL",
    "gn:name":"Ganda de Bolombo I",
    "gn:population":0,
    "gn:timezone":"Africa/Kinshasa",
    "iso:country":"CD",
    "name:und_x_variant":[
        "Ganda de Bolombo",
        "Ganda de Bolombo I"
    ],
    "wof:name":"Ganda de Bolombo I",
    "wof:placetype":"locality"
},
  "geometry": {"coordinates":[18.98333,-1.88333],"type":"Point"}
}