{
  "type": "Feature",
  "properties": {
    "gn:admin1_code":"19.0",
    "gn:asciiname":"Muyalala",
    "gn:country_code":"CD",
    "gn:dem":729,
    "gn:feature_class":"P",
    "gn:feature_code":"PPL",
    "gn:name":"Muyalala",
    "gn:population":0,
    "gn:timezone":"Africa/Kinshasa",
    "iso:country":"CD",
    "wof:name":"Muyalala",
    "wof:placetype":"locality"
},
  "geometry": {"coordinates":[16.30528,-5.42683],"type":"Point"}
}