{
  "type": "Feature",
  "properties": {
    "gn:admin1_code":"24.0",
    "gn:asciiname":"Gelenkolo",
    "gn:country_code":"CD",
    "gn:dem":406,
    "gn:feature_class":"P",
    "gn:feature_code":"PPL",
    "gn:name":"Gelenkolo",
    "gn:population":0,
    "gn:timezone":"Africa/Kinshasa",
    "iso:country":"CD",
    "wof:name":"Gelenkolo",
    "wof:placetype":"locality"
},
  "geometry": {"coordinates":[19.88333,-4.08333],"type":"Point"}
}