{
  "type": "Feature",
  "properties": {
    "gn:admin1_code":"26.0",
    "gn:asciiname":"Yangwate",
    "gn:country_code":"CD",
    "gn:dem":373,
    "gn:feature_class":"P",
    "gn:feature_code":"PPL",
    "gn:name":"Yangwate",
    "gn:population":0,
    "gn:timezone":"Africa/Kinshasa",
    "iso:country":"CD",
    "wof:name":"Yangwate",
    "wof:placetype":"locality"
},
  "geometry": {"coordinates":[21.13722000000001,3.4272],"type":"Point"}
}