{
  "type": "Feature",
  "properties": {
    "gn:admin1_code":"20.0",
    "gn:asciiname":"Fangulu",
    "gn:country_code":"CD",
    "gn:dem":374,
    "gn:feature_class":"P",
    "gn:feature_code":"PPL",
    "gn:name":"Fangulu",
    "gn:population":0,
    "gn:timezone":"Africa/Kinshasa",
    "iso:country":"CD",
    "wof:name":"Fangulu",
    "wof:placetype":"locality"
},
  "geometry": {"coordinates":[17.26207,-4.18924],"type":"Point"}
}