{
  "type": "Feature",
  "properties": {
    "gn:admin1_code":"26.0",
    "gn:asciiname":"Watoro",
    "gn:country_code":"CD",
    "gn:dem":375,
    "gn:feature_class":"P",
    "gn:feature_code":"PPL",
    "gn:name":"Watoro",
    "gn:population":0,
    "gn:timezone":"Africa/Kinshasa",
    "iso:country":"CD",
    "name:deu_x_preferred":[
        "Watoro"
    ],
    "name:fra_x_preferred":[
        "Watoro"
    ],
    "name:spa_x_preferred":[
        "Watoro"
    ],
    "wof:name":"Watoro",
    "wof:placetype":"locality"
},
  "geometry": {"coordinates":[20.10431,4.8361],"type":"Point"}
}