{
  "type": "Feature",
  "properties": {
    "gn:admin1_code":"22.0",
    "gn:asciiname":"Muhusu",
    "gn:country_code":"CD",
    "gn:dem":1126,
    "gn:feature_class":"P",
    "gn:feature_code":"PPL",
    "gn:name":"Muhusu",
    "gn:population":0,
    "gn:timezone":"Africa/Lubumbashi",
    "iso:country":"CD",
    "wof:name":"Muhusu",
    "wof:placetype":"locality"
},
  "geometry": {"coordinates":[22.67339,-11.03751],"type":"Point"}
}