{
  "type": "Feature",
  "properties": {
    "gn:admin1_code":"19.0",
    "gn:asciiname":"Kiloanda",
    "gn:country_code":"CD",
    "gn:dem":445,
    "gn:feature_class":"P",
    "gn:feature_code":"PPL",
    "gn:name":"Kiloanda",
    "gn:population":0,
    "gn:timezone":"Africa/Kinshasa",
    "iso:country":"CD",
    "wof:name":"Kiloanda",
    "wof:placetype":"locality"
},
  "geometry": {"coordinates":[16.65831,-5.81845],"type":"Point"}
}