{
  "type": "Feature",
  "properties": {
    "gn:admin1_code":"8.0",
    "gn:asciiname":"Bimbulu",
    "gn:country_code":"CD",
    "gn:dem":467,
    "gn:feature_class":"P",
    "gn:feature_code":"PPL",
    "gn:name":"Bimbulu",
    "gn:population":0,
    "gn:timezone":"Africa/Kinshasa",
    "iso:country":"CD",
    "wof:name":"Bimbulu",
    "wof:placetype":"locality"
},
  "geometry": {"coordinates":[14.52655,-4.98234],"type":"Point"}
}