{
  "type": "Feature",
  "properties": {
    "gn:admin1_code":"21.0",
    "gn:asciiname":"Bena-Tite",
    "gn:country_code":"CD",
    "gn:dem":660,
    "gn:feature_class":"P",
    "gn:feature_code":"PPL",
    "gn:name":"Bena-Tite",
    "gn:population":0,
    "gn:timezone":"Africa/Lubumbashi",
    "iso:country":"CD",
    "wof:name":"Bena-Tite",
    "wof:placetype":"locality"
},
  "geometry": {"coordinates":[23.85985,-6.44146],"type":"Point"}
}