{
  "type": "Feature",
  "properties": {
    "gn:admin1_code":"20.0",
    "gn:asciiname":"Kayongo",
    "gn:country_code":"CD",
    "gn:dem":772,
    "gn:feature_class":"P",
    "gn:feature_code":"PPL",
    "gn:name":"Kayongo",
    "gn:population":0,
    "gn:timezone":"Africa/Kinshasa",
    "iso:country":"CD",
    "wof:name":"Kayongo",
    "wof:placetype":"locality"
},
  "geometry": {"coordinates":[19.32134,-5.9171],"type":"Point"}
}