{
  "type": "Feature",
  "properties": {
    "gn:admin1_code":"4.0",
    "gn:asciiname":"Bena-Kadima",
    "gn:country_code":"CD",
    "gn:dem":631,
    "gn:feature_class":"P",
    "gn:feature_code":"PPL",
    "gn:name":"Bena-Kadima",
    "gn:population":0,
    "gn:timezone":"Africa/Lubumbashi",
    "iso:country":"CD",
    "name:und_x_variant":[
        "Kadima",
        "Bena Kapemba",
        "Bena-Kadima"
    ],
    "wof:name":"Bena-Kadima",
    "wof:placetype":"locality"
},
  "geometry": {"coordinates":[23.78071,-6.28798],"type":"Point"}
}