{
  "type": "Feature",
  "properties": {
    "gn:admin1_code":"12.0",
    "gn:asciiname":"Lutala",
    "gn:country_code":"CD",
    "gn:dem":579,
    "gn:feature_class":"P",
    "gn:feature_code":"PPL",
    "gn:name":"Lutala",
    "gn:population":0,
    "gn:timezone":"Africa/Lubumbashi",
    "iso:country":"CD",
    "wof:name":"Lutala",
    "wof:placetype":"locality"
},
  "geometry": {"coordinates":[27.23333,-2.55],"type":"Point"}
}