{
  "type": "Feature",
  "properties": {
    "gn:admin1_code":"21.0",
    "gn:asciiname":"Kisampi",
    "gn:country_code":"CD",
    "gn:dem":678,
    "gn:feature_class":"P",
    "gn:feature_code":"PPL",
    "gn:name":"Kisampi",
    "gn:population":0,
    "gn:timezone":"Africa/Lubumbashi",
    "iso:country":"CD",
    "wof:name":"Kisampi",
    "wof:placetype":"locality"
},
  "geometry": {"coordinates":[25.83333,-5.51667],"type":"Point"}
}