{
  "type": "Feature",
  "properties": {
    "gn:admin1_code":"26.0",
    "gn:asciiname":"Vambena",
    "gn:country_code":"CD",
    "gn:dem":482,
    "gn:feature_class":"P",
    "gn:feature_code":"PPL",
    "gn:name":"Vambena",
    "gn:population":0,
    "gn:timezone":"Africa/Kinshasa",
    "iso:country":"CD",
    "wof:name":"Vambena",
    "wof:placetype":"locality"
},
  "geometry": {"coordinates":[22.19334,3.30944],"type":"Point"}
}