{
  "type": "Feature",
  "properties": {
    "gn:admin1_code":"28.0",
    "gn:asciiname":"Boyagonda",
    "gn:country_code":"CD",
    "gn:dem":410,
    "gn:feature_class":"P",
    "gn:feature_code":"PPL",
    "gn:name":"Boyagonda",
    "gn:population":0,
    "gn:timezone":"Africa/Kinshasa",
    "iso:country":"CD",
    "name:und_x_variant":[
        "Boyangonda",
        "Boyangonde",
        "Boyagonda"
    ],
    "wof:name":"Boyagonda",
    "wof:placetype":"locality"
},
  "geometry": {"coordinates":[20.16869,3.1157],"type":"Point"}
}