{
  "type": "Feature",
  "properties": {
    "gn:admin1_code":"26.0",
    "gn:asciiname":"Pundungu",
    "gn:country_code":"CD",
    "gn:dem":380,
    "gn:feature_class":"P",
    "gn:feature_code":"PPL",
    "gn:name":"Pundungu",
    "gn:population":0,
    "gn:timezone":"Africa/Kinshasa",
    "iso:country":"CD",
    "name:und_x_variant":[
        "Pudngu"
    ],
    "wof:name":"Pundungu",
    "wof:placetype":"locality"
},
  "geometry": {"coordinates":[20.29736,4.74831],"type":"Point"}
}