{
  "type": "Feature",
  "properties": {
    "gn:admin1_code":"12.0",
    "gn:asciiname":"Kasa",
    "gn:country_code":"CD",
    "gn:dem":594,
    "gn:feature_class":"P",
    "gn:feature_code":"PPL",
    "gn:name":"Kasa",
    "gn:population":0,
    "gn:timezone":"Africa/Lubumbashi",
    "iso:country":"CD",
    "name:aze_x_preferred":[
        "Kasa"
    ],
    "name:ceb_x_preferred":[
        "Kasa"
    ],
    "name:deu_x_preferred":[
        "Kasa"
    ],
    "name:fra_x_preferred":[
        "Kasa"
    ],
    "name:ind_x_preferred":[
        "Kasa"
    ],
    "name:ita_x_preferred":[
        "Kasa"
    ],
    "name:pol_x_preferred":[
        "Kasa"
    ],
    "name:que_x_preferred":[
        "Kasa"
    ],
    "name:spa_x_preferred":[
        "Kasa"
    ],
    "name:swe_x_preferred":[
        "Kasa"
    ],
    "name:vie_x_preferred":[
        "Kasa"
    ],
    "wof:name":"Kasa",
    "wof:placetype":"locality"
},
  "geometry": {"coordinates":[27.08333,-2.71667],"type":"Point"}
}