{
  "type": "Feature",
  "properties": {
    "gn:admin1_code":"12.0",
    "gn:asciiname":"Kasa",
    "gn:country_code":"CD",
    "gn:dem":594,
    "gn:feature_class":"P",
    "gn:feature_code":"PPL",
    "gn:name":"Kasa",
    "gn:population":0,
    "gn:timezone":"Africa/Lubumbashi",
    "iso:country":"CD",
    "wof:name":"Kasa",
    "wof:placetype":"locality"
},
  "geometry": {"coordinates":[27.08333,-2.71667],"type":"Point"}
}