{
  "type": "Feature",
  "properties": {
    "gn:admin1_code":"18.0",
    "gn:asciiname":"Shatshipata",
    "gn:country_code":"CD",
    "gn:dem":710,
    "gn:feature_class":"P",
    "gn:feature_code":"PPL",
    "gn:name":"Shatshipata",
    "gn:population":0,
    "gn:timezone":"Africa/Lubumbashi",
    "iso:country":"CD",
    "wof:name":"Shatshipata",
    "wof:placetype":"locality"
},
  "geometry": {"coordinates":[19.91895,-6.55075],"type":"Point"}
}