{
  "type": "Feature",
  "properties": {
    "gn:admin1_code":"31.0",
    "gn:asciiname":"Welia",
    "gn:country_code":"CD",
    "gn:dem":431,
    "gn:feature_class":"P",
    "gn:feature_code":"PPL",
    "gn:name":"Welia",
    "gn:population":0,
    "gn:timezone":"Africa/Kinshasa",
    "iso:country":"CD",
    "wof:name":"Welia",
    "wof:placetype":"locality"
},
  "geometry": {"coordinates":[20.95,-1.86667],"type":"Point"}
}