{
  "type": "Feature",
  "properties": {
    "gn:admin1_code":"15.0",
    "gn:asciiname":"Ilunga",
    "gn:country_code":"CD",
    "gn:dem":1026,
    "gn:feature_class":"P",
    "gn:feature_code":"PPL",
    "gn:name":"Ilunga",
    "gn:population":0,
    "gn:timezone":"Africa/Lubumbashi",
    "iso:country":"CD",
    "wof:name":"Ilunga",
    "wof:placetype":"locality"
},
  "geometry": {"coordinates":[25.18535,-7.99727],"type":"Point"}
}