{
  "type": "Feature",
  "properties": {
    "gn:admin1_code":"15.0",
    "gn:asciiname":"Ilunga",
    "gn:country_code":"CD",
    "gn:dem":1026,
    "gn:feature_class":"P",
    "gn:feature_code":"PPL",
    "gn:name":"Ilunga",
    "gn:population":0,
    "gn:timezone":"Africa/Lubumbashi",
    "iso:country":"CD",
    "name:ara_x_preferred":[
        "\u0625\u064a\u0644\u0646\u063a\u0627"
    ],
    "name:deu_x_preferred":[
        "Ilunga"
    ],
    "name:fin_x_preferred":[
        "Ilunga"
    ],
    "name:spa_x_preferred":[
        "Ilunga"
    ],
    "wof:name":"Ilunga",
    "wof:placetype":"locality"
},
  "geometry": {"coordinates":[25.18535,-7.99727],"type":"Point"}
}