{
  "type": "Feature",
  "properties": {
    "gn:admin1_code":"21.0",
    "gn:asciiname":"Lubanga Musengie",
    "gn:country_code":"CD",
    "gn:dem":726,
    "gn:feature_class":"P",
    "gn:feature_code":"PPL",
    "gn:name":"Lubanga Musengie",
    "gn:population":0,
    "gn:timezone":"Africa/Lubumbashi",
    "iso:country":"CD",
    "wof:name":"Lubanga Musengie",
    "wof:placetype":"locality"
},
  "geometry": {"coordinates":[24.63595,-5.77007],"type":"Point"}
}