{
  "type": "Feature",
  "properties": {
    "gn:admin1_code":"19.0",
    "gn:asciiname":"Shamufuka",
    "gn:country_code":"CD",
    "gn:dem":1040,
    "gn:feature_class":"P",
    "gn:feature_code":"PPL",
    "gn:name":"Shamufuka",
    "gn:population":0,
    "gn:timezone":"Africa/Kinshasa",
    "iso:country":"CD",
    "wof:name":"Shamufuka",
    "wof:placetype":"locality"
},
  "geometry": {"coordinates":[18.67734,-7.45238],"type":"Point"}
}