{
  "type": "Feature",
  "properties": {
    "gn:admin1_code":"27.0",
    "gn:asciiname":"Lohonda",
    "gn:country_code":"CD",
    "gn:dem":584,
    "gn:feature_class":"P",
    "gn:feature_code":"PPL",
    "gn:name":"Lohonda",
    "gn:population":0,
    "gn:timezone":"Africa/Lubumbashi",
    "iso:country":"CD",
    "wof:name":"Lohonda",
    "wof:placetype":"locality"
},
  "geometry": {"coordinates":[24.28333,-3.06667],"type":"Point"}
}