{
  "type": "Feature",
  "properties": {
    "gn:admin1_code":"8.0",
    "gn:asciiname":"Mutuka",
    "gn:country_code":"CD",
    "gn:dem":651,
    "gn:feature_class":"P",
    "gn:feature_code":"PPL",
    "gn:name":"Mutuka",
    "gn:population":0,
    "gn:timezone":"Africa/Kinshasa",
    "iso:country":"CD",
    "wof:name":"Mutuka",
    "wof:placetype":"locality"
},
  "geometry": {"coordinates":[13.84938,-4.48537],"type":"Point"}
}