{
  "type": "Feature",
  "properties": {
    "gn:admin1_code":"17.0",
    "gn:asciiname":"Li",
    "gn:country_code":"CD",
    "gn:dem":1555,
    "gn:feature_class":"P",
    "gn:feature_code":"PPL",
    "gn:name":"Li",
    "gn:population":0,
    "gn:timezone":"Africa/Lubumbashi",
    "iso:country":"CD",
    "wof:name":"Li",
    "wof:placetype":"locality"
},
  "geometry": {"coordinates":[30.43333,1.85],"type":"Point"}
}