{
  "type": "Feature",
  "properties": {
    "gn:admin1_code":"15.0",
    "gn:asciiname":"Kabengere",
    "gn:country_code":"CD",
    "gn:dem":640,
    "gn:feature_class":"P",
    "gn:feature_code":"PPL",
    "gn:name":"Kabengere",
    "gn:population":0,
    "gn:timezone":"Africa/Lubumbashi",
    "iso:country":"CD",
    "wof:name":"Kabengere",
    "wof:placetype":"locality"
},
  "geometry": {"coordinates":[26.27567,-9.10699],"type":"Point"}
}