{
  "type": "Feature",
  "properties": {
    "gn:admin1_code":"19.0",
    "gn:asciiname":"Dondji",
    "gn:country_code":"CD",
    "gn:dem":465,
    "gn:feature_class":"P",
    "gn:feature_code":"PPL",
    "gn:name":"Dondji",
    "gn:population":0,
    "gn:timezone":"Africa/Kinshasa",
    "iso:country":"CD",
    "wof:name":"Dondji",
    "wof:placetype":"locality"
},
  "geometry": {"coordinates":[17.1872,-7.46255],"type":"Point"}
}