{
  "type": "Feature",
  "properties": {
    "gn:admin1_code":"21.0",
    "gn:asciiname":"Lubimbi",
    "gn:country_code":"CD",
    "gn:dem":662,
    "gn:feature_class":"P",
    "gn:feature_code":"PPL",
    "gn:name":"Lubimbi",
    "gn:population":0,
    "gn:timezone":"Africa/Lubumbashi",
    "iso:country":"CD",
    "wof:name":"Lubimbi",
    "wof:placetype":"locality"
},
  "geometry": {"coordinates":[26.05,-6.01667],"type":"Point"}
}