{
  "type": "Feature",
  "properties": {
    "gn:admin1_code":"19.0",
    "gn:asciiname":"Makengo",
    "gn:country_code":"CD",
    "gn:dem":703,
    "gn:feature_class":"P",
    "gn:feature_code":"PPL",
    "gn:name":"Makengo",
    "gn:population":0,
    "gn:timezone":"Africa/Kinshasa",
    "iso:country":"CD",
    "wof:name":"Makengo",
    "wof:placetype":"locality"
},
  "geometry": {"coordinates":[16.31667,-4.76667],"type":"Point"}
}