{
  "type": "Feature",
  "properties": {
    "gn:admin1_code":"15.0",
    "gn:asciiname":"Dai",
    "gn:country_code":"CD",
    "gn:dem":1039,
    "gn:feature_class":"P",
    "gn:feature_code":"PPL",
    "gn:name":"Dai",
    "gn:population":0,
    "gn:timezone":"Africa/Lubumbashi",
    "iso:country":"CD",
    "name:cat_x_preferred":[
        "Dai"
    ],
    "name:ceb_x_preferred":[
        "Dai"
    ],
    "name:dan_x_preferred":[
        "Dai"
    ],
    "name:deu_x_preferred":[
        "Dai"
    ],
    "name:fra_x_preferred":[
        "Dai"
    ],
    "name:heb_x_preferred":[
        "\u05d3\u05d0\u05d9"
    ],
    "name:nld_x_preferred":[
        "Dai"
    ],
    "name:nor_x_preferred":[
        "Dai"
    ],
    "name:pol_x_preferred":[
        "Dai"
    ],
    "name:por_x_preferred":[
        "Dai"
    ],
    "name:rus_x_preferred":[
        "\u0414\u0430\u0439"
    ],
    "name:swe_x_preferred":[
        "Dai"
    ],
    "name:ukr_x_preferred":[
        "\u0414\u0430\u0439"
    ],
    "wof:name":"Dai",
    "wof:placetype":"locality"
},
  "geometry": {"coordinates":[24.78559,-8.25184],"type":"Point"}
}