{
  "type": "Feature",
  "properties": {
    "gn:admin1_code":"15.0",
    "gn:asciiname":"Dai",
    "gn:country_code":"CD",
    "gn:dem":1039,
    "gn:feature_class":"P",
    "gn:feature_code":"PPL",
    "gn:name":"Dai",
    "gn:population":0,
    "gn:timezone":"Africa/Lubumbashi",
    "iso:country":"CD",
    "wof:name":"Dai",
    "wof:placetype":"locality"
},
  "geometry": {"coordinates":[24.78559,-8.25184],"type":"Point"}
}