{
  "type": "Feature",
  "properties": {
    "gn:admin1_code":"19.0",
    "gn:asciiname":"Kabari",
    "gn:country_code":"CD",
    "gn:dem":904,
    "gn:feature_class":"P",
    "gn:feature_code":"PPL",
    "gn:name":"Kabari",
    "gn:population":0,
    "gn:timezone":"Africa/Kinshasa",
    "iso:country":"CD",
    "wof:name":"Kabari",
    "wof:placetype":"locality"
},
  "geometry": {"coordinates":[17.94852999999999,-7.27715],"type":"Point"}
}