{
  "type": "Feature",
  "properties": {
    "gn:admin1_code":"8.0",
    "gn:asciiname":"Kintin",
    "gn:country_code":"CD",
    "gn:dem":661,
    "gn:feature_class":"P",
    "gn:feature_code":"PPL",
    "gn:name":"Kintin",
    "gn:population":0,
    "gn:timezone":"Africa/Kinshasa",
    "iso:country":"CD",
    "name:und_x_variant":[
        "Kintinu"
    ],
    "wof:name":"Kintin",
    "wof:placetype":"locality"
},
  "geometry": {"coordinates":[15.28244,-5.36822],"type":"Point"}
}