{
  "type": "Feature",
  "properties": {
    "gn:admin1_code":"20.0",
    "gn:asciiname":"Zofu",
    "gn:country_code":"CD",
    "gn:dem":740,
    "gn:feature_class":"P",
    "gn:feature_code":"PPL",
    "gn:name":"Zofu",
    "gn:population":0,
    "gn:timezone":"Africa/Kinshasa",
    "iso:country":"CD",
    "wof:name":"Zofu",
    "wof:placetype":"locality"
},
  "geometry": {"coordinates":[17.58403,-5.41722],"type":"Point"}
}