{
  "type": "Feature",
  "properties": {
    "gn:admin1_code":"25.0",
    "gn:asciiname":"Boyange",
    "gn:country_code":"CD",
    "gn:dem":444,
    "gn:feature_class":"P",
    "gn:feature_code":"PPL",
    "gn:name":"Boyange",
    "gn:population":0,
    "gn:timezone":"Africa/Kinshasa",
    "iso:country":"CD",
    "wof:name":"Boyange",
    "wof:placetype":"locality"
},
  "geometry": {"coordinates":[21.70483,2.26839],"type":"Point"}
}