{
  "type": "Feature",
  "properties": {
    "gn:admin1_code":"14.0",
    "gn:asciiname":"Kalenga",
    "gn:country_code":"CD",
    "gn:dem":1167,
    "gn:feature_class":"P",
    "gn:feature_code":"PPL",
    "gn:name":"Kalenga",
    "gn:population":0,
    "gn:timezone":"Africa/Lubumbashi",
    "iso:country":"CD",
    "name:ita_x_preferred":[
        "Kalenga"
    ],
    "name:swa_x_preferred":[
        "Kalenga"
    ],
    "wof:name":"Kalenga",
    "wof:placetype":"locality"
},
  "geometry": {"coordinates":[26.7175,-10.75889],"type":"Point"}
}