{
  "type": "Feature",
  "properties": {
    "gn:admin1_code":"27.0",
    "gn:asciiname":"Wemalaka",
    "gn:country_code":"CD",
    "gn:dem":478,
    "gn:feature_class":"P",
    "gn:feature_code":"PPL",
    "gn:name":"Wemalaka",
    "gn:population":0,
    "gn:timezone":"Africa/Lubumbashi",
    "iso:country":"CD",
    "wof:name":"Wemalaka",
    "wof:placetype":"locality"
},
  "geometry": {"coordinates":[23.96667,-1.95],"type":"Point"}
}