{
  "type": "Feature",
  "properties": {
    "gn:admin1_code":"27.0",
    "gn:asciiname":"Mulumbu",
    "gn:country_code":"CD",
    "gn:dem":591,
    "gn:feature_class":"P",
    "gn:feature_code":"PPL",
    "gn:name":"Mulumbu",
    "gn:population":0,
    "gn:timezone":"Africa/Lubumbashi",
    "iso:country":"CD",
    "wof:name":"Mulumbu",
    "wof:placetype":"locality"
},
  "geometry": {"coordinates":[23.36078,-5.14759],"type":"Point"}
}