{
  "type": "Feature",
  "properties": {
    "gn:admin1_code":"18.0",
    "gn:asciiname":"Mudiambongo",
    "gn:country_code":"CD",
    "gn:dem":560,
    "gn:feature_class":"P",
    "gn:feature_code":"PPL",
    "gn:name":"Mudiambongo",
    "gn:population":0,
    "gn:timezone":"Africa/Lubumbashi",
    "iso:country":"CD",
    "wof:name":"Mudiambongo",
    "wof:placetype":"locality"
},
  "geometry": {"coordinates":[20.73402,-6.46811],"type":"Point"}
}