{
  "type": "Feature",
  "properties": {
    "gn:admin1_code":"11.0",
    "gn:asciiname":"Kiriba",
    "gn:country_code":"CD",
    "gn:dem":1120,
    "gn:feature_class":"P",
    "gn:feature_code":"PPL",
    "gn:name":"Kiriba",
    "gn:population":0,
    "gn:timezone":"Africa/Lubumbashi",
    "iso:country":"CD",
    "wof:name":"Kiriba",
    "wof:placetype":"locality"
},
  "geometry": {"coordinates":[28.80085,-0.96197],"type":"Point"}
}