{
  "type": "Feature",
  "properties": {
    "gn:admin1_code":"22.0",
    "gn:asciiname":"Kapatu",
    "gn:country_code":"CD",
    "gn:dem":1061,
    "gn:feature_class":"P",
    "gn:feature_code":"PPL",
    "gn:name":"Kapatu",
    "gn:population":0,
    "gn:timezone":"Africa/Lubumbashi",
    "iso:country":"CD",
    "wof:name":"Kapatu",
    "wof:placetype":"locality"
},
  "geometry": {"coordinates":[22.7909,-10.65478],"type":"Point"}
}