{
  "type": "Feature",
  "properties": {
    "gn:admin1_code":"18.0",
    "gn:asciiname":"Shamukoso",
    "gn:country_code":"CD",
    "gn:dem":760,
    "gn:feature_class":"P",
    "gn:feature_code":"PPL",
    "gn:name":"Shamukoso",
    "gn:population":0,
    "gn:timezone":"Africa/Lubumbashi",
    "iso:country":"CD",
    "wof:name":"Shamukoso",
    "wof:placetype":"locality"
},
  "geometry": {"coordinates":[20.14768,-6.6134],"type":"Point"}
}