{
  "type": "Feature",
  "properties": {
    "gn:admin1_code":"10.0",
    "gn:asciiname":"Bekoli",
    "gn:country_code":"CD",
    "gn:dem":518,
    "gn:feature_class":"P",
    "gn:feature_code":"PPL",
    "gn:name":"Bekoli",
    "gn:population":0,
    "gn:timezone":"Africa/Lubumbashi",
    "iso:country":"CD",
    "wof:name":"Bekoli",
    "wof:placetype":"locality"
},
  "geometry": {"coordinates":[25.85,-2.18333],"type":"Point"}
}