{
  "type": "Feature",
  "properties": {
    "gn:admin1_code":"11.0",
    "gn:asciiname":"Lushekere",
    "gn:country_code":"CD",
    "gn:dem":1691,
    "gn:feature_class":"P",
    "gn:feature_code":"PPL",
    "gn:name":"Lushekere",
    "gn:population":0,
    "gn:timezone":"Africa/Lubumbashi",
    "iso:country":"CD",
    "wof:name":"Lushekere",
    "wof:placetype":"locality"
},
  "geometry": {"coordinates":[29.11559,-1.03209],"type":"Point"}
}