{
  "type": "Feature",
  "properties": {
    "gn:admin1_code":"30.0",
    "gn:asciiname":"Pene Olanga",
    "gn:country_code":"CD",
    "gn:dem":483,
    "gn:feature_class":"P",
    "gn:feature_code":"PPL",
    "gn:name":"Pene Olanga",
    "gn:population":0,
    "gn:timezone":"Africa/Lubumbashi",
    "iso:country":"CD",
    "wof:name":"Pene Olanga",
    "wof:placetype":"locality"
},
  "geometry": {"coordinates":[25.69333,0.23111],"type":"Point"}
}