{
  "type": "Feature",
  "properties": {
    "gn:admin1_code":"17.0",
    "gn:asciiname":"Soleniama Deuxieme",
    "gn:country_code":"CD",
    "gn:dem":1323,
    "gn:feature_class":"P",
    "gn:feature_code":"PPL",
    "gn:name":"Soleniama Deuxi\u00e8me",
    "gn:population":0,
    "gn:timezone":"Africa/Lubumbashi",
    "iso:country":"CD",
    "name:und_x_variant":[
        "Soleniama Deuxi\u00e8me",
        "Soleniama"
    ],
    "wof:name":"Soleniama Deuxieme",
    "wof:placetype":"locality"
},
  "geometry": {"coordinates":[30.27742000000001,1.68221],"type":"Point"}
}