{
  "type": "Feature",
  "properties": {
    "gn:admin1_code":"30.0",
    "gn:asciiname":"Bopomili",
    "gn:country_code":"CD",
    "gn:dem":463,
    "gn:feature_class":"P",
    "gn:feature_code":"PPL",
    "gn:name":"Bopomili",
    "gn:population":0,
    "gn:timezone":"Africa/Lubumbashi",
    "iso:country":"CD",
    "wof:name":"Bopomili",
    "wof:placetype":"locality"
},
  "geometry": {"coordinates":[25.40009,1.9136],"type":"Point"}
}