{
  "type": "Feature",
  "properties": {
    "gn:admin1_code":"20.0",
    "gn:asciiname":"Maka",
    "gn:country_code":"CD",
    "gn:dem":368,
    "gn:feature_class":"P",
    "gn:feature_code":"PPL",
    "gn:name":"Maka",
    "gn:population":0,
    "gn:timezone":"Africa/Kinshasa",
    "iso:country":"CD",
    "wof:name":"Maka",
    "wof:placetype":"locality"
},
  "geometry": {"coordinates":[18.25225,-3.90449],"type":"Point"}
}