{
  "type": "Feature",
  "properties": {
    "gn:admin1_code":"20.0",
    "gn:asciiname":"Maka",
    "gn:country_code":"CD",
    "gn:dem":368,
    "gn:feature_class":"P",
    "gn:feature_code":"PPL",
    "gn:name":"Maka",
    "gn:population":0,
    "gn:timezone":"Africa/Kinshasa",
    "iso:country":"CD",
    "name:ceb_x_preferred":[
        "Maka"
    ],
    "name:deu_x_preferred":[
        "Maka"
    ],
    "name:fra_x_preferred":[
        "Maka"
    ],
    "name:ita_x_preferred":[
        "Maka"
    ],
    "name:jpn_x_preferred":[
        "\u30de\u30ab"
    ],
    "name:rus_x_preferred":[
        "\u041c\u0430\u043a\u0430"
    ],
    "name:slk_x_preferred":[
        "Maka"
    ],
    "name:swe_x_preferred":[
        "Maka"
    ],
    "wof:name":"Maka",
    "wof:placetype":"locality"
},
  "geometry": {"coordinates":[18.25225,-3.90449],"type":"Point"}
}