{
  "type": "Feature",
  "properties": {
    "gn:admin1_code":"8.0",
    "gn:asciiname":"Mbanza",
    "gn:country_code":"CD",
    "gn:dem":778,
    "gn:feature_class":"P",
    "gn:feature_code":"PPL",
    "gn:name":"Mbanza",
    "gn:population":0,
    "gn:timezone":"Africa/Kinshasa",
    "iso:country":"CD",
    "name:ceb_x_preferred":[
        "Mbanza"
    ],
    "name:fra_x_preferred":[
        "Mbanza"
    ],
    "name:lin_x_preferred":[
        "Mbanza"
    ],
    "name:pol_x_preferred":[
        "Mbanza"
    ],
    "name:swe_x_preferred":[
        "Mbanza"
    ],
    "wof:name":"Mbanza",
    "wof:placetype":"locality"
},
  "geometry": {"coordinates":[15.16301,-5.76621],"type":"Point"}
}