{
  "type": "Feature",
  "properties": {
    "gn:admin1_code":"22.0",
    "gn:asciiname":"Salinaka",
    "gn:country_code":"CD",
    "gn:dem":1027,
    "gn:feature_class":"P",
    "gn:feature_code":"PPL",
    "gn:name":"Salinaka",
    "gn:population":0,
    "gn:timezone":"Africa/Lubumbashi",
    "iso:country":"CD",
    "wof:name":"Salinaka",
    "wof:placetype":"locality"
},
  "geometry": {"coordinates":[23.15177000000001,-10.7235],"type":"Point"}
}