{
  "type": "Feature",
  "properties": {
    "gn:admin1_code":"18.0",
    "gn:asciiname":"Musangu",
    "gn:country_code":"CD",
    "gn:dem":613,
    "gn:feature_class":"P",
    "gn:feature_code":"PPL",
    "gn:name":"Musangu",
    "gn:population":0,
    "gn:timezone":"Africa/Lubumbashi",
    "iso:country":"CD",
    "wof:name":"Musangu",
    "wof:placetype":"locality"
},
  "geometry": {"coordinates":[21.50225,-5.44164],"type":"Point"}
}