{
  "type": "Feature",
  "properties": {
    "gn:admin1_code":"15.0",
    "gn:asciiname":"Kasenga",
    "gn:country_code":"CD",
    "gn:dem":715,
    "gn:feature_class":"P",
    "gn:feature_code":"PPL",
    "gn:name":"Kasenga",
    "gn:population":0,
    "gn:timezone":"Africa/Lubumbashi",
    "iso:country":"CD",
    "name:fra_x_preferred":[
        "Kasenga"
    ],
    "name:ron_x_preferred":[
        "Kasenga"
    ],
    "wof:name":"Kasenga",
    "wof:placetype":"locality"
},
  "geometry": {"coordinates":[25.73147,-6.35353],"type":"Point"}
}