{
  "type": "Feature",
  "properties": {
    "gn:admin1_code":"20.0",
    "gn:asciiname":"Mosai",
    "gn:country_code":"CD",
    "gn:dem":549,
    "gn:feature_class":"P",
    "gn:feature_code":"PPL",
    "gn:name":"Mosai",
    "gn:population":0,
    "gn:timezone":"Africa/Kinshasa",
    "iso:country":"CD",
    "wof:name":"Mosai",
    "wof:placetype":"locality"
},
  "geometry": {"coordinates":[19.40866,-4.40702],"type":"Point"}
}