{
  "type": "Feature",
  "properties": {
    "gn:admin1_code":"30.0",
    "gn:asciiname":"Bage Premiere",
    "gn:country_code":"CD",
    "gn:dem":551,
    "gn:feature_class":"P",
    "gn:feature_code":"PPL",
    "gn:name":"Bage Premi\u00e8re",
    "gn:population":0,
    "gn:timezone":"Africa/Lubumbashi",
    "iso:country":"CD",
    "name:und_x_variant":[
        "Bage Premi\u00e8re",
        "Bage I"
    ],
    "wof:name":"Bage Premiere",
    "wof:placetype":"locality"
},
  "geometry": {"coordinates":[26.24317000000001,1.86906],"type":"Point"}
}