{
  "type": "Feature",
  "properties": {
    "gn:admin1_code":"19.0",
    "gn:asciiname":"Mwako",
    "gn:country_code":"CD",
    "gn:dem":848,
    "gn:feature_class":"P",
    "gn:feature_code":"PPL",
    "gn:name":"Mwako",
    "gn:population":0,
    "gn:timezone":"Africa/Kinshasa",
    "iso:country":"CD",
    "wof:name":"Mwako",
    "wof:placetype":"locality"
},
  "geometry": {"coordinates":[17.20421,-5.99612],"type":"Point"}
}