{
  "type": "Feature",
  "properties": {
    "gn:admin1_code":"25.0",
    "gn:asciiname":"Akula",
    "gn:country_code":"CD",
    "gn:dem":337,
    "gn:feature_class":"P",
    "gn:feature_code":"PPL",
    "gn:name":"Akula",
    "gn:population":0,
    "gn:timezone":"Africa/Kinshasa",
    "iso:country":"CD",
    "name:ceb_x_preferred":[
        "Akula"
    ],
    "name:deu_x_preferred":[
        "Akula"
    ],
    "name:fin_x_preferred":[
        "Akula"
    ],
    "name:srp_x_preferred":[
        "\u0410\u043a\u0443\u043b\u0430"
    ],
    "name:swe_x_preferred":[
        "Akula"
    ],
    "wof:name":"Akula",
    "wof:placetype":"locality"
},
  "geometry": {"coordinates":[20.18898,2.37697],"type":"Point"}
}