{
  "type": "Feature",
  "properties": {
    "gn:admin1_code":"18.0",
    "gn:asciiname":"Madimadi",
    "gn:country_code":"CD",
    "gn:dem":595,
    "gn:feature_class":"P",
    "gn:feature_code":"PPL",
    "gn:name":"Madimadi",
    "gn:population":0,
    "gn:timezone":"Africa/Lubumbashi",
    "iso:country":"CD",
    "wof:name":"Madimadi",
    "wof:placetype":"locality"
},
  "geometry": {"coordinates":[20.74352,-6.41927],"type":"Point"}
}