{
  "type": "Feature",
  "properties": {
    "gn:admin1_code":"23.0",
    "gn:asciiname":"Tshisuyi",
    "gn:country_code":"CD",
    "gn:dem":696,
    "gn:feature_class":"P",
    "gn:feature_code":"PPL",
    "gn:name":"Tshisuyi",
    "gn:population":0,
    "gn:timezone":"Africa/Lubumbashi",
    "iso:country":"CD",
    "wof:name":"Tshisuyi",
    "wof:placetype":"locality"
},
  "geometry": {"coordinates":[22.05681,-6.00504],"type":"Point"}
}