{
  "type": "Feature",
  "properties": {
    "gn:admin1_code":"20.0",
    "gn:asciiname":"Belo",
    "gn:country_code":"CD",
    "gn:dem":611,
    "gn:feature_class":"P",
    "gn:feature_code":"PPL",
    "gn:name":"Belo",
    "gn:population":0,
    "gn:timezone":"Africa/Kinshasa",
    "iso:country":"CD",
    "name:deu_x_preferred":[
        "Belo"
    ],
    "name:ita_x_preferred":[
        "Belo"
    ],
    "name:swe_x_preferred":[
        "Belo"
    ],
    "wof:name":"Belo",
    "wof:placetype":"locality"
},
  "geometry": {"coordinates":[20.02699,-5.20153],"type":"Point"}
}