{
  "type": "Feature",
  "properties": {
    "gn:admin1_code":"2.0",
    "gn:asciiname":"Litumba-Djololo",
    "gn:country_code":"CD",
    "gn:dem":332,
    "gn:feature_class":"P",
    "gn:feature_code":"PPL",
    "gn:name":"Litumba-Djololo",
    "gn:population":0,
    "gn:timezone":"Africa/Kinshasa",
    "iso:country":"CD",
    "wof:name":"Litumba-Djololo",
    "wof:placetype":"locality"
},
  "geometry": {"coordinates":[18.5886,-0.43423],"type":"Point"}
}