{
  "type": "Feature",
  "properties": {
    "gn:admin1_code":"8.0",
    "gn:asciiname":"Pelo",
    "gn:country_code":"CD",
    "gn:dem":303,
    "gn:feature_class":"P",
    "gn:feature_code":"PPL",
    "gn:name":"Pelo",
    "gn:population":0,
    "gn:timezone":"Africa/Kinshasa",
    "iso:country":"CD",
    "wof:name":"Pelo",
    "wof:placetype":"locality"
},
  "geometry": {"coordinates":[14.03847,-5.2964],"type":"Point"}
}