{
  "type": "Feature",
  "properties": {
    "gn:admin1_code":"22.0",
    "gn:asciiname":"Satomo",
    "gn:country_code":"CD",
    "gn:dem":1011,
    "gn:feature_class":"P",
    "gn:feature_code":"PPL",
    "gn:name":"Satomo",
    "gn:population":0,
    "gn:timezone":"Africa/Lubumbashi",
    "iso:country":"CD",
    "wof:name":"Satomo",
    "wof:placetype":"locality"
},
  "geometry": {"coordinates":[22.11856,-9.82656],"type":"Point"}
}