{
  "type": "Feature",
  "properties": {
    "gn:admin1_code":"19.0",
    "gn:asciiname":"Shakatanga",
    "gn:country_code":"CD",
    "gn:dem":955,
    "gn:feature_class":"P",
    "gn:feature_code":"PPL",
    "gn:name":"Shakatanga",
    "gn:population":0,
    "gn:timezone":"Africa/Kinshasa",
    "iso:country":"CD",
    "wof:name":"Shakatanga",
    "wof:placetype":"locality"
},
  "geometry": {"coordinates":[19.32928,-6.99229],"type":"Point"}
}