{
  "type": "Feature",
  "properties": {
    "gn:admin1_code":"23.0",
    "gn:asciiname":"Bunkonde",
    "gn:country_code":"CD",
    "gn:dem":736,
    "gn:feature_class":"P",
    "gn:feature_code":"PPL",
    "gn:name":"Bunkonde",
    "gn:population":0,
    "gn:timezone":"Africa/Lubumbashi",
    "iso:country":"CD",
    "name:und_x_variant":[
        "Hemptinne",
        "Hemptinne-Saint-Benoit",
        "Bukonde",
        "Bunkonde"
    ],
    "wof:name":"Bunkonde",
    "wof:placetype":"locality"
},
  "geometry": {"coordinates":[22.53083,-6.30427],"type":"Point"}
}