{
  "type": "Feature",
  "properties": {
    "gn:admin1_code":"20.0",
    "gn:asciiname":"Dibaya",
    "gn:country_code":"CD",
    "gn:dem":787,
    "gn:feature_class":"P",
    "gn:feature_code":"PPL",
    "gn:name":"Dibaya",
    "gn:population":0,
    "gn:timezone":"Africa/Kinshasa",
    "iso:country":"CD",
    "name:fra_x_preferred":[
        "Dibaya"
    ],
    "name:ron_x_preferred":[
        "Dibaya"
    ],
    "wof:name":"Dibaya",
    "wof:placetype":"locality"
},
  "geometry": {"coordinates":[19.35496,-6.02691],"type":"Point"}
}