{
  "type": "Feature",
  "properties": {
    "gn:admin1_code":"17.0",
    "gn:asciiname":"Bengasoli",
    "gn:country_code":"CD",
    "gn:dem":895,
    "gn:feature_class":"P",
    "gn:feature_code":"PPL",
    "gn:name":"Bengasoli",
    "gn:population":0,
    "gn:timezone":"Africa/Lubumbashi",
    "iso:country":"CD",
    "name:fra_x_preferred":[
        "Bengasoli"
    ],
    "wof:name":"Bengasoli",
    "wof:placetype":"locality"
},
  "geometry": {"coordinates":[29.18962,1.35662],"type":"Point"}
}