{
  "type": "Feature",
  "properties": {
    "gn:admin1_code":"6.0",
    "gn:asciiname":"Mangamu",
    "gn:country_code":"CD",
    "gn:dem":688,
    "gn:feature_class":"P",
    "gn:feature_code":"PPL",
    "gn:name":"Mangamu",
    "gn:population":0,
    "gn:timezone":"Africa/Kinshasa",
    "iso:country":"CD",
    "wof:name":"Mangamu",
    "wof:placetype":"locality"
},
  "geometry": {"coordinates":[15.68593,-4.15032],"type":"Point"}
}