{
  "type": "Feature",
  "properties": {
    "gn:admin1_code":"28.0",
    "gn:asciiname":"Bomanga-Fataki",
    "gn:country_code":"CD",
    "gn:dem":376,
    "gn:feature_class":"P",
    "gn:feature_code":"PPL",
    "gn:name":"Bomanga-Fataki",
    "gn:population":0,
    "gn:timezone":"Africa/Kinshasa",
    "iso:country":"CD",
    "wof:name":"Bomanga-Fataki",
    "wof:placetype":"locality"
},
  "geometry": {"coordinates":[18.88996,3.77703],"type":"Point"}
}