{
  "type": "Feature",
  "properties": {
    "gn:admin1_code":"31.0",
    "gn:asciiname":"Yambula",
    "gn:country_code":"CD",
    "gn:dem":397,
    "gn:feature_class":"P",
    "gn:feature_code":"PPL",
    "gn:name":"Yambula",
    "gn:population":0,
    "gn:timezone":"Africa/Kinshasa",
    "iso:country":"CD",
    "wof:name":"Yambula",
    "wof:placetype":"locality"
},
  "geometry": {"coordinates":[21.96667,0.56667],"type":"Point"}
}