{
  "type": "Feature",
  "properties": {
    "gn:admin1_code":"8.0",
    "gn:asciiname":"Yongo",
    "gn:country_code":"CD",
    "gn:dem":686,
    "gn:feature_class":"P",
    "gn:feature_code":"PPL",
    "gn:name":"Yongo",
    "gn:population":0,
    "gn:timezone":"Africa/Kinshasa",
    "iso:country":"CD",
    "wof:name":"Yongo",
    "wof:placetype":"locality"
},
  "geometry": {"coordinates":[15.04189,-5.33938],"type":"Point"}
}