{
  "type": "Feature",
  "properties": {
    "gn:admin1_code":"24.0",
    "gn:asciiname":"Bokagne",
    "gn:country_code":"CD",
    "gn:dem":377,
    "gn:feature_class":"P",
    "gn:feature_code":"PPL",
    "gn:name":"Bokagne",
    "gn:population":0,
    "gn:timezone":"Africa/Kinshasa",
    "iso:country":"CD",
    "wof:name":"Bokagne",
    "wof:placetype":"locality"
},
  "geometry": {"coordinates":[18.82755,-3.33183],"type":"Point"}
}