{
  "type": "Feature",
  "properties": {
    "gn:admin1_code":"22.0",
    "gn:asciiname":"Murub",
    "gn:country_code":"CD",
    "gn:dem":944,
    "gn:feature_class":"P",
    "gn:feature_code":"PPL",
    "gn:name":"Murub",
    "gn:population":0,
    "gn:timezone":"Africa/Lubumbashi",
    "iso:country":"CD",
    "wof:name":"Murub",
    "wof:placetype":"locality"
},
  "geometry": {"coordinates":[22.22451,-8.00523],"type":"Point"}
}