{
  "type": "Feature",
  "properties": {
    "gn:admin1_code":"22.0",
    "gn:asciiname":"Sawina",
    "gn:country_code":"CD",
    "gn:dem":987,
    "gn:feature_class":"P",
    "gn:feature_code":"PPL",
    "gn:name":"Sawina",
    "gn:population":0,
    "gn:timezone":"Africa/Lubumbashi",
    "iso:country":"CD",
    "wof:name":"Sawina",
    "wof:placetype":"locality"
},
  "geometry": {"coordinates":[22.78228,-10.45377],"type":"Point"}
}