{
  "type": "Feature",
  "properties": {
    "gn:admin1_code":"18.0",
    "gn:asciiname":"Ngoyo",
    "gn:country_code":"CD",
    "gn:dem":543,
    "gn:feature_class":"P",
    "gn:feature_code":"PPL",
    "gn:name":"Ngoyo",
    "gn:population":0,
    "gn:timezone":"Africa/Lubumbashi",
    "iso:country":"CD",
    "name:ast_x_preferred":[
        "Ngoyo"
    ],
    "name:cat_x_preferred":[
        "Ngoyo"
    ],
    "name:deu_x_preferred":[
        "Ngoyo"
    ],
    "name:ell_x_preferred":[
        "\u039d\u03b3\u03ba\u03cc\u03b3\u03b9\u03bf"
    ],
    "name:fra_x_preferred":[
        "Ngoyo"
    ],
    "name:ind_x_preferred":[
        "Ngoyo"
    ],
    "name:lit_x_preferred":[
        "Ngojo karalyst\u0117"
    ],
    "name:pol_x_preferred":[
        "Ngoyo"
    ],
    "name:por_x_preferred":[
        "Ngoyo"
    ],
    "name:rus_x_preferred":[
        "\u041a\u043e\u0440\u043e\u043b\u0435\u0432\u0441\u0442\u0432\u043e \u041d\u0433\u043e\u0439\u043e"
    ],
    "name:spa_x_preferred":[
        "Ngoyo"
    ],
    "wof:name":"Ngoyo",
    "wof:placetype":"locality"
},
  "geometry": {"coordinates":[21.445,-4.76109],"type":"Point"}
}