{
  "type": "Feature",
  "properties": {
    "gn:admin1_code":"18.0",
    "gn:asciiname":"Ngoyo",
    "gn:country_code":"CD",
    "gn:dem":543,
    "gn:feature_class":"P",
    "gn:feature_code":"PPL",
    "gn:name":"Ngoyo",
    "gn:population":0,
    "gn:timezone":"Africa/Lubumbashi",
    "iso:country":"CD",
    "wof:name":"Ngoyo",
    "wof:placetype":"locality"
},
  "geometry": {"coordinates":[21.445,-4.76109],"type":"Point"}
}