{
  "type": "Feature",
  "properties": {
    "gn:admin1_code":"29.0",
    "gn:asciiname":"Maloba",
    "gn:country_code":"CD",
    "gn:dem":799,
    "gn:feature_class":"P",
    "gn:feature_code":"PPL",
    "gn:name":"Maloba",
    "gn:population":0,
    "gn:timezone":"Africa/Lubumbashi",
    "iso:country":"CD",
    "name:und_x_variant":[
        "Maleba"
    ],
    "wof:name":"Maloba",
    "wof:placetype":"locality"
},
  "geometry": {"coordinates":[26.59607,-7.34883],"type":"Point"}
}