{
  "type": "Feature",
  "properties": {
    "gn:admin1_code":"11.0",
    "gn:asciiname":"Kabare",
    "gn:country_code":"CD",
    "gn:dem":3227,
    "gn:feature_class":"P",
    "gn:feature_code":"PPL",
    "gn:name":"Kabare",
    "gn:population":0,
    "gn:timezone":"Africa/Lubumbashi",
    "iso:country":"CD",
    "wof:name":"Kabare",
    "wof:placetype":"locality"
},
  "geometry": {"coordinates":[29.42833,-1.48056],"type":"Point"}
}