{
  "type": "Feature",
  "properties": {
    "gn:admin1_code":"22.0",
    "gn:asciiname":"Nidaikanga",
    "gn:country_code":"CD",
    "gn:dem":1153,
    "gn:feature_class":"P",
    "gn:feature_code":"PPL",
    "gn:name":"Nidaikanga",
    "gn:population":0,
    "gn:timezone":"Africa/Lubumbashi",
    "iso:country":"CD",
    "wof:name":"Nidaikanga",
    "wof:placetype":"locality"
},
  "geometry": {"coordinates":[24.29978,-10.60453],"type":"Point"}
}