{
  "type": "Feature",
  "properties": {
    "gn:admin1_code":"23.0",
    "gn:asciiname":"Tshibwita",
    "gn:country_code":"CD",
    "gn:dem":942,
    "gn:feature_class":"P",
    "gn:feature_code":"PPL",
    "gn:name":"Tshibwita",
    "gn:population":0,
    "gn:timezone":"Africa/Lubumbashi",
    "iso:country":"CD",
    "wof:name":"Tshibwita",
    "wof:placetype":"locality"
},
  "geometry": {"coordinates":[22.9481,-7.08265],"type":"Point"}
}