{
  "type": "Feature",
  "properties": {
    "gn:admin1_code":"19.0",
    "gn:asciiname":"Munisindji",
    "gn:country_code":"CD",
    "gn:dem":484,
    "gn:feature_class":"P",
    "gn:feature_code":"PPL",
    "gn:name":"Munisindji",
    "gn:population":0,
    "gn:timezone":"Africa/Kinshasa",
    "iso:country":"CD",
    "wof:name":"Munisindji",
    "wof:placetype":"locality"
},
  "geometry": {"coordinates":[16.73698,-6.03279],"type":"Point"}
}