{
  "type": "Feature",
  "properties": {
    "gn:admin1_code":"25.0",
    "gn:asciiname":"Yamodonga",
    "gn:country_code":"CD",
    "gn:dem":409,
    "gn:feature_class":"P",
    "gn:feature_code":"PPL",
    "gn:name":"Yamodonga",
    "gn:population":0,
    "gn:timezone":"Africa/Kinshasa",
    "iso:country":"CD",
    "wof:name":"Yamodonga",
    "wof:placetype":"locality"
},
  "geometry": {"coordinates":[22.49659,2.42853],"type":"Point"}
}