{
  "type": "Feature",
  "properties": {
    "gn:admin1_code":"22.0",
    "gn:asciiname":"Muswalisa",
    "gn:country_code":"CD",
    "gn:dem":1012,
    "gn:feature_class":"P",
    "gn:feature_code":"PPL",
    "gn:name":"Muswalisa",
    "gn:population":0,
    "gn:timezone":"Africa/Lubumbashi",
    "iso:country":"CD",
    "wof:name":"Muswalisa",
    "wof:placetype":"locality"
},
  "geometry": {"coordinates":[23.68306,-9.69048],"type":"Point"}
}