{
  "type": "Feature",
  "properties": {
    "gn:admin1_code":"31.0",
    "gn:asciiname":"Lokole",
    "gn:country_code":"CD",
    "gn:dem":447,
    "gn:feature_class":"P",
    "gn:feature_code":"PPL",
    "gn:name":"Lokole",
    "gn:population":0,
    "gn:timezone":"Africa/Kinshasa",
    "iso:country":"CD",
    "name:fra_x_preferred":[
        "Lokole"
    ],
    "name:lin_x_preferred":[
        "Lokol\u00e9"
    ],
    "wof:name":"Lokole",
    "wof:placetype":"locality"
},
  "geometry": {"coordinates":[21.78333,-0.23333],"type":"Point"}
}