{
  "type": "Feature",
  "properties": {
    "gn:admin1_code":"19.0",
    "gn:asciiname":"Kienga",
    "gn:country_code":"CD",
    "gn:dem":740,
    "gn:feature_class":"P",
    "gn:feature_code":"PPL",
    "gn:name":"Kienga",
    "gn:population":0,
    "gn:timezone":"Africa/Kinshasa",
    "iso:country":"CD",
    "wof:name":"Kienga",
    "wof:placetype":"locality"
},
  "geometry": {"coordinates":[17.33673,-5.9835],"type":"Point"}
}