{
  "type": "Feature",
  "properties": {
    "gn:admin1_code":"30.0",
    "gn:asciiname":"Buma",
    "gn:country_code":"CD",
    "gn:dem":483,
    "gn:feature_class":"P",
    "gn:feature_code":"PPL",
    "gn:name":"Buma",
    "gn:population":0,
    "gn:timezone":"Africa/Lubumbashi",
    "iso:country":"CD",
    "wof:name":"Buma",
    "wof:placetype":"locality"
},
  "geometry": {"coordinates":[22.93333,1.01667],"type":"Point"}
}