{
  "type": "Feature",
  "properties": {
    "gn:admin1_code":"20.0",
    "gn:asciiname":"Dumbi-Manda",
    "gn:country_code":"CD",
    "gn:dem":652,
    "gn:feature_class":"P",
    "gn:feature_code":"PPL",
    "gn:name":"Dumbi-Manda",
    "gn:population":0,
    "gn:timezone":"Africa/Kinshasa",
    "iso:country":"CD",
    "wof:name":"Dumbi-Manda",
    "wof:placetype":"locality"
},
  "geometry": {"coordinates":[19.9098,-5.76842],"type":"Point"}
}