{
  "type": "Feature",
  "properties": {
    "gn:admin1_code":"8.0",
    "gn:asciiname":"Kama",
    "gn:country_code":"CD",
    "gn:dem":455,
    "gn:feature_class":"P",
    "gn:feature_code":"PPL",
    "gn:name":"Kama",
    "gn:population":0,
    "gn:timezone":"Africa/Kinshasa",
    "iso:country":"CD",
    "wof:name":"Kama",
    "wof:placetype":"locality"
},
  "geometry": {"coordinates":[14.68249,-5.3249],"type":"Point"}
}