{
  "type": "Feature",
  "properties": {
    "gn:admin1_code":"29.0",
    "gn:asciiname":"Ganie-Kasenga",
    "gn:country_code":"CD",
    "gn:dem":1396,
    "gn:feature_class":"P",
    "gn:feature_code":"PPL",
    "gn:name":"Ganie-Kasenga",
    "gn:population":0,
    "gn:timezone":"Africa/Lubumbashi",
    "iso:country":"CD",
    "wof:name":"Ganie-Kasenga",
    "wof:placetype":"locality"
},
  "geometry": {"coordinates":[28.85245,-7.59515],"type":"Point"}
}