{
  "type": "Feature",
  "properties": {
    "gn:admin1_code":"10.0",
    "gn:asciiname":"Bisamengo",
    "gn:country_code":"CD",
    "gn:dem":668,
    "gn:feature_class":"P",
    "gn:feature_code":"PPL",
    "gn:name":"Bisamengo",
    "gn:population":0,
    "gn:timezone":"Africa/Lubumbashi",
    "iso:country":"CD",
    "wof:name":"Bisamengo",
    "wof:placetype":"locality"
},
  "geometry": {"coordinates":[26.6081,-2.57529],"type":"Point"}
}