{
  "type": "Feature",
  "properties": {
    "gn:admin1_code":"19.0",
    "gn:asciiname":"Moipa",
    "gn:country_code":"CD",
    "gn:dem":437,
    "gn:feature_class":"P",
    "gn:feature_code":"PPL",
    "gn:name":"Moipa",
    "gn:population":0,
    "gn:timezone":"Africa/Kinshasa",
    "iso:country":"CD",
    "wof:name":"Moipa",
    "wof:placetype":"locality"
},
  "geometry": {"coordinates":[16.73899,-6.16331],"type":"Point"}
}