{
  "type": "Feature",
  "properties": {
    "gn:admin1_code":"23.0",
    "gn:asciiname":"Mulungaie",
    "gn:country_code":"CD",
    "gn:dem":814,
    "gn:feature_class":"P",
    "gn:feature_code":"PPL",
    "gn:name":"Mulungaie",
    "gn:population":0,
    "gn:timezone":"Africa/Lubumbashi",
    "iso:country":"CD",
    "wof:name":"Mulungaie",
    "wof:placetype":"locality"
},
  "geometry": {"coordinates":[22.89997,-6.29526],"type":"Point"}
}