{
  "type": "Feature",
  "properties": {
    "gn:admin1_code":"12.0",
    "gn:asciiname":"Kitembe",
    "gn:country_code":"CD",
    "gn:dem":2779,
    "gn:feature_class":"P",
    "gn:feature_code":"PPL",
    "gn:name":"Kitembe",
    "gn:population":0,
    "gn:timezone":"Africa/Lubumbashi",
    "iso:country":"CD",
    "wof:name":"Kitembe",
    "wof:placetype":"locality"
},
  "geometry": {"coordinates":[28.87111,-3.19806],"type":"Point"}
}