{
  "type": "Feature",
  "properties": {
    "gn:admin1_code":"20.0",
    "gn:asciiname":"Emmaus",
    "gn:country_code":"CD",
    "gn:dem":382,
    "gn:feature_class":"P",
    "gn:feature_code":"PPL",
    "gn:name":"Emma\u00fcs",
    "gn:population":0,
    "gn:timezone":"Africa/Kinshasa",
    "iso:country":"CD",
    "name:ara_x_preferred":[
        "\u0639\u0645\u0648\u0627\u0633"
    ],
    "name:cat_x_preferred":[
        "Emma\u00fas"
    ],
    "name:ces_x_preferred":[
        "Emauzy"
    ],
    "name:deu_x_preferred":[
        "Emmaus"
    ],
    "name:ell_x_preferred":[
        "\u0395\u03bc\u03bc\u03b1\u03bf\u03cd\u03c2"
    ],
    "name:epo_x_preferred":[
        "Emaus"
    ],
    "name:eus_x_preferred":[
        "Emaus"
    ],
    "name:fas_x_preferred":[
        "\u0639\u0645\u0648\u0627\u0633"
    ],
    "name:fin_x_preferred":[
        "Emmaus"
    ],
    "name:fra_x_preferred":[
        "P\u00e8lerins d'Emma\u00fcs"
    ],
    "name:heb_x_preferred":[
        "\u05d0\u05de\u05d0\u05d5\u05e1"
    ],
    "name:hrv_x_preferred":[
        "Emaus"
    ],
    "name:hun_x_preferred":[
        "Emmausz"
    ],
    "name:ind_x_preferred":[
        "Emaus"
    ],
    "name:ita_x_preferred":[
        "Emmaus"
    ],
    "name:jpn_x_preferred":[
        "\u30a8\u30de\u30aa"
    ],
    "name:nld_x_preferred":[
        "Emma\u00fcs"
    ],
    "name:nno_x_preferred":[
        "Emmaus"
    ],
    "name:nor_x_preferred":[
        "Emmaus"
    ],
    "name:pol_x_preferred":[
        "Emaus"
    ],
    "name:por_x_preferred":[
        "Ema\u00fas"
    ],
    "name:spa_x_preferred":[
        "Ema\u00fas"
    ],
    "name:srp_x_preferred":[
        "\u0415\u043c\u0430\u0443\u0441"
    ],
    "name:swe_x_preferred":[
        "Emmaus"
    ],
    "name:tam_x_preferred":[
        "\u0b8e\u0bae\u0bcd\u0bae\u0bbe\u0bb5\u0bc1"
    ],
    "name:urd_x_preferred":[
        "\u0627\u0645\u0627\u0624\u0633"
    ],
    "name:vie_x_preferred":[
        "Em-mau"
    ],
    "wof:name":"Emmaus",
    "wof:placetype":"locality"
},
  "geometry": {"coordinates":[19.06667,-3.95],"type":"Point"}
}