{
  "type": "Feature",
  "properties": {
    "gn:admin1_code":"20.0",
    "gn:asciiname":"Emmaus",
    "gn:country_code":"CD",
    "gn:dem":382,
    "gn:feature_class":"P",
    "gn:feature_code":"PPL",
    "gn:name":"Emma\u00fcs",
    "gn:population":0,
    "gn:timezone":"Africa/Kinshasa",
    "iso:country":"CD",
    "wof:name":"Emmaus",
    "wof:placetype":"locality"
},
  "geometry": {"coordinates":[19.06667,-3.95],"type":"Point"}
}