{
  "type": "Feature",
  "properties": {
    "gn:admin1_code":"25.0",
    "gn:asciiname":"Bopolo",
    "gn:country_code":"CD",
    "gn:dem":342,
    "gn:feature_class":"P",
    "gn:feature_code":"PPL",
    "gn:name":"Bopolo",
    "gn:population":0,
    "gn:timezone":"Africa/Kinshasa",
    "iso:country":"CD",
    "wof:name":"Bopolo",
    "wof:placetype":"locality"
},
  "geometry": {"coordinates":[21.57549,2.10365],"type":"Point"}
}