{
  "type": "Feature",
  "properties": {
    "gn:admin1_code":"22.0",
    "gn:asciiname":"Swana Mume",
    "gn:country_code":"CD",
    "gn:dem":934,
    "gn:feature_class":"P",
    "gn:feature_code":"PPL",
    "gn:name":"Swana Mume",
    "gn:population":0,
    "gn:timezone":"Africa/Lubumbashi",
    "iso:country":"CD",
    "wof:name":"Swana Mume",
    "wof:placetype":"locality"
},
  "geometry": {"coordinates":[23.14312,-9.80196],"type":"Point"}
}