{
  "type": "Feature",
  "properties": {
    "gn:admin1_code":"22.0",
    "gn:asciiname":"Kakenge",
    "gn:country_code":"CD",
    "gn:dem":922,
    "gn:feature_class":"P",
    "gn:feature_code":"PPL",
    "gn:name":"Kakenge",
    "gn:population":0,
    "gn:timezone":"Africa/Lubumbashi",
    "iso:country":"CD",
    "name:und_x_variant":[
        "Kakenga"
    ],
    "wof:name":"Kakenge",
    "wof:placetype":"locality"
},
  "geometry": {"coordinates":[23.01053,-10.08858],"type":"Point"}
}