{
  "type": "Feature",
  "properties": {
    "gn:admin1_code":"19.0",
    "gn:asciiname":"Mutombo",
    "gn:country_code":"CD",
    "gn:dem":1150,
    "gn:feature_class":"P",
    "gn:feature_code":"PPL",
    "gn:name":"Mutombo",
    "gn:population":0,
    "gn:timezone":"Africa/Kinshasa",
    "iso:country":"CD",
    "wof:name":"Mutombo",
    "wof:placetype":"locality"
},
  "geometry": {"coordinates":[18.57346,-7.71005],"type":"Point"}
}