{
  "type": "Feature",
  "properties": {
    "gn:admin1_code":"24.0",
    "gn:asciiname":"Moshemokwa",
    "gn:country_code":"CD",
    "gn:dem":332,
    "gn:feature_class":"P",
    "gn:feature_code":"PPL",
    "gn:name":"Moshemokwa",
    "gn:population":0,
    "gn:timezone":"Africa/Kinshasa",
    "iso:country":"CD",
    "wof:name":"Moshemokwa",
    "wof:placetype":"locality"
},
  "geometry": {"coordinates":[17.78639,-2.88428],"type":"Point"}
}