{
  "type": "Feature",
  "properties": {
    "gn:admin1_code":"21.0",
    "gn:asciiname":"Tshiamvi",
    "gn:country_code":"CD",
    "gn:dem":839,
    "gn:feature_class":"P",
    "gn:feature_code":"PPL",
    "gn:name":"Tshiamvi",
    "gn:population":0,
    "gn:timezone":"Africa/Lubumbashi",
    "iso:country":"CD",
    "wof:name":"Tshiamvi",
    "wof:placetype":"locality"
},
  "geometry": {"coordinates":[23.65445,-7.06189],"type":"Point"}
}