{
  "type": "Feature",
  "properties": {
    "gn:admin1_code":"22.0",
    "gn:asciiname":"Majila",
    "gn:country_code":"CD",
    "gn:dem":1182,
    "gn:feature_class":"P",
    "gn:feature_code":"PPL",
    "gn:name":"Majila",
    "gn:population":0,
    "gn:timezone":"Africa/Lubumbashi",
    "iso:country":"CD",
    "wof:name":"Majila",
    "wof:placetype":"locality"
},
  "geometry": {"coordinates":[23.6013,-10.84619],"type":"Point"}
}