{
  "type": "Feature",
  "properties": {
    "gn:admin1_code":"13.0",
    "gn:asciiname":"Neru",
    "gn:country_code":"CD",
    "gn:dem":706,
    "gn:feature_class":"P",
    "gn:feature_code":"PPL",
    "gn:name":"Neru",
    "gn:population":0,
    "gn:timezone":"Africa/Lubumbashi",
    "iso:country":"CD",
    "wof:name":"Neru",
    "wof:placetype":"locality"
},
  "geometry": {"coordinates":[27.17153,3.05059],"type":"Point"}
}