{
  "type": "Feature",
  "properties": {
    "gn:admin1_code":"21.0",
    "gn:asciiname":"Kitumbwilu",
    "gn:country_code":"CD",
    "gn:dem":724,
    "gn:feature_class":"P",
    "gn:feature_code":"PPL",
    "gn:name":"Kitumbwilu",
    "gn:population":0,
    "gn:timezone":"Africa/Lubumbashi",
    "iso:country":"CD",
    "wof:name":"Kitumbwilu",
    "wof:placetype":"locality"
},
  "geometry": {"coordinates":[24.25808,-5.56329],"type":"Point"}
}