{
  "type": "Feature",
  "properties": {
    "gn:admin1_code":"24.0",
    "gn:asciiname":"Ilombe",
    "gn:country_code":"CD",
    "gn:dem":319,
    "gn:feature_class":"P",
    "gn:feature_code":"PPL",
    "gn:name":"Ilombe",
    "gn:population":0,
    "gn:timezone":"Africa/Kinshasa",
    "iso:country":"CD",
    "name:und_x_variant":[
        "Ilombe en Tomba",
        "Ilombe"
    ],
    "wof:name":"Ilombe",
    "wof:placetype":"locality"
},
  "geometry": {"coordinates":[18.13333,-1.41667],"type":"Point"}
}