{
  "type": "Feature",
  "properties": {
    "gn:admin1_code":"19.0",
    "gn:asciiname":"Lukinda-Kwenge",
    "gn:country_code":"CD",
    "gn:dem":953,
    "gn:feature_class":"P",
    "gn:feature_code":"PPL",
    "gn:name":"Lukinda-Kwenge",
    "gn:population":0,
    "gn:timezone":"Africa/Kinshasa",
    "iso:country":"CD",
    "wof:name":"Lukinda-Kwenge",
    "wof:placetype":"locality"
},
  "geometry": {"coordinates":[18.45161,-7.03459],"type":"Point"}
}