{
  "type": "Feature",
  "properties": {
    "gn:admin1_code":"16.0",
    "gn:asciiname":"Maziriso",
    "gn:country_code":"CD",
    "gn:dem":869,
    "gn:feature_class":"P",
    "gn:feature_code":"PPL",
    "gn:name":"Maziriso",
    "gn:population":0,
    "gn:timezone":"Africa/Lubumbashi",
    "iso:country":"CD",
    "wof:name":"Maziriso",
    "wof:placetype":"locality"
},
  "geometry": {"coordinates":[30.14034,3.88925],"type":"Point"}
}