{
  "type": "Feature",
  "properties": {
    "gn:admin1_code":"31.0",
    "gn:asciiname":"Lieke-Asangu",
    "gn:country_code":"CD",
    "gn:dem":474,
    "gn:feature_class":"P",
    "gn:feature_code":"PPL",
    "gn:name":"Lieke-Asangu",
    "gn:population":0,
    "gn:timezone":"Africa/Lubumbashi",
    "iso:country":"CD",
    "wof:name":"Lieke-Asangu",
    "wof:placetype":"locality"
},
  "geometry": {"coordinates":[24.1074,-1.32739],"type":"Point"}
}