{
  "type": "Feature",
  "properties": {
    "gn:admin1_code":"23.0",
    "gn:asciiname":"Sapo-Luela",
    "gn:country_code":"CD",
    "gn:dem":580,
    "gn:feature_class":"P",
    "gn:feature_code":"PPL",
    "gn:name":"Sapo-Luela",
    "gn:population":0,
    "gn:timezone":"Africa/Lubumbashi",
    "iso:country":"CD",
    "wof:name":"Sapo-Luela",
    "wof:placetype":"locality"
},
  "geometry": {"coordinates":[21.87191,-5.2005],"type":"Point"}
}