{
  "type": "Feature",
  "properties": {
    "gn:admin1_code":"22.0",
    "gn:asciiname":"Mutobo",
    "gn:country_code":"CD",
    "gn:dem":1136,
    "gn:feature_class":"P",
    "gn:feature_code":"PPL",
    "gn:name":"Mutobo",
    "gn:population":0,
    "gn:timezone":"Africa/Lubumbashi",
    "iso:country":"CD",
    "wof:name":"Mutobo",
    "wof:placetype":"locality"
},
  "geometry": {"coordinates":[26.25328,-10.31184],"type":"Point"}
}