{
  "type": "Feature",
  "properties": {
    "gn:admin1_code":"19.0",
    "gn:asciiname":"Lusenga",
    "gn:country_code":"CD",
    "gn:dem":868,
    "gn:feature_class":"P",
    "gn:feature_code":"PPL",
    "gn:name":"Lusenga",
    "gn:population":0,
    "gn:timezone":"Africa/Kinshasa",
    "iso:country":"CD",
    "wof:name":"Lusenga",
    "wof:placetype":"locality"
},
  "geometry": {"coordinates":[19.68977000000001,-6.68664],"type":"Point"}
}