{
  "type": "Feature",
  "properties": {
    "gn:admin1_code":"23.0",
    "gn:asciiname":"Lubuyi",
    "gn:country_code":"CD",
    "gn:dem":612,
    "gn:feature_class":"P",
    "gn:feature_code":"PPL",
    "gn:name":"Lubuyi",
    "gn:population":0,
    "gn:timezone":"Africa/Lubumbashi",
    "iso:country":"CD",
    "name:und_x_variant":[
        "Lubuie",
        "Lubuyi"
    ],
    "wof:name":"Lubuyi",
    "wof:placetype":"locality"
},
  "geometry": {"coordinates":[22.41966,-5.57463],"type":"Point"}
}