{
  "type": "Feature",
  "properties": {
    "gn:admin1_code":"20.0",
    "gn:asciiname":"Kipita",
    "gn:country_code":"CD",
    "gn:dem":572,
    "gn:feature_class":"P",
    "gn:feature_code":"PPL",
    "gn:name":"Kipita",
    "gn:population":0,
    "gn:timezone":"Africa/Kinshasa",
    "iso:country":"CD",
    "wof:name":"Kipita",
    "wof:placetype":"locality"
},
  "geometry": {"coordinates":[20.06953,-5.79383],"type":"Point"}
}