{
  "type": "Feature",
  "properties": {
    "gn:admin1_code":"16.0",
    "gn:asciiname":"Vore-Loui",
    "gn:country_code":"CD",
    "gn:dem":865,
    "gn:feature_class":"P",
    "gn:feature_code":"PPL",
    "gn:name":"Vore-Loui",
    "gn:population":0,
    "gn:timezone":"Africa/Lubumbashi",
    "iso:country":"CD",
    "wof:name":"Vore-Loui",
    "wof:placetype":"locality"
},
  "geometry": {"coordinates":[29.1492,2.83014],"type":"Point"}
}