{
  "type": "Feature",
  "properties": {
    "gn:admin1_code":"13.0",
    "gn:asciiname":"Babuya",
    "gn:country_code":"CD",
    "gn:dem":671,
    "gn:feature_class":"P",
    "gn:feature_code":"PPL",
    "gn:name":"Babuya",
    "gn:population":0,
    "gn:timezone":"Africa/Lubumbashi",
    "iso:country":"CD",
    "wof:name":"Babuya",
    "wof:placetype":"locality"
},
  "geometry": {"coordinates":[26.89559,4.63745],"type":"Point"}
}