{
  "type": "Feature",
  "properties": {
    "gn:admin1_code":"18.0",
    "gn:asciiname":"Muaisaki",
    "gn:country_code":"CD",
    "gn:dem":745,
    "gn:feature_class":"P",
    "gn:feature_code":"PPL",
    "gn:name":"Muaisaki",
    "gn:population":0,
    "gn:timezone":"Africa/Lubumbashi",
    "iso:country":"CD",
    "wof:name":"Muaisaki",
    "wof:placetype":"locality"
},
  "geometry": {"coordinates":[21.34878,-7.24717],"type":"Point"}
}