{
  "type": "Feature",
  "properties": {
    "gn:admin1_code":"22.0",
    "gn:asciiname":"Samolenga",
    "gn:country_code":"CD",
    "gn:dem":1029,
    "gn:feature_class":"P",
    "gn:feature_code":"PPL",
    "gn:name":"Samolenga",
    "gn:population":0,
    "gn:timezone":"Africa/Lubumbashi",
    "iso:country":"CD",
    "wof:name":"Samolenga",
    "wof:placetype":"locality"
},
  "geometry": {"coordinates":[23.10486,-10.48373],"type":"Point"}
}