{
  "type": "Feature",
  "properties": {
    "gn:admin1_code":"30.0",
    "gn:asciiname":"Bafwatebu",
    "gn:country_code":"CD",
    "gn:dem":551,
    "gn:feature_class":"P",
    "gn:feature_code":"PPL",
    "gn:name":"Bafwatebu",
    "gn:population":0,
    "gn:timezone":"Africa/Lubumbashi",
    "iso:country":"CD",
    "wof:name":"Bafwatebu",
    "wof:placetype":"locality"
},
  "geometry": {"coordinates":[27.11348,1.16237],"type":"Point"}
}