{
  "type": "Feature",
  "properties": {
    "gn:admin1_code":"16.0",
    "gn:asciiname":"Abongomabu",
    "gn:country_code":"CD",
    "gn:dem":778,
    "gn:feature_class":"P",
    "gn:feature_code":"PPL",
    "gn:name":"Abongomabu",
    "gn:population":0,
    "gn:timezone":"Africa/Lubumbashi",
    "iso:country":"CD",
    "wof:name":"Abongomabu",
    "wof:placetype":"locality"
},
  "geometry": {"coordinates":[27.79963,2.32326],"type":"Point"}
}