{
  "type": "Feature",
  "properties": {
    "gn:admin1_code":"20.0",
    "gn:asciiname":"Minsia",
    "gn:country_code":"CD",
    "gn:dem":398,
    "gn:feature_class":"P",
    "gn:feature_code":"PPL",
    "gn:name":"Minsia",
    "gn:population":0,
    "gn:timezone":"Africa/Kinshasa",
    "iso:country":"CD",
    "wof:name":"Minsia",
    "wof:placetype":"locality"
},
  "geometry": {"coordinates":[17.15749,-4.00149],"type":"Point"}
}