{
  "type": "Feature",
  "properties": {
    "gn:admin1_code":"13.0",
    "gn:asciiname":"Asetonie",
    "gn:country_code":"CD",
    "gn:dem":638,
    "gn:feature_class":"P",
    "gn:feature_code":"PPL",
    "gn:name":"Asetonie",
    "gn:population":0,
    "gn:timezone":"Africa/Lubumbashi",
    "iso:country":"CD",
    "wof:name":"Asetonie",
    "wof:placetype":"locality"
},
  "geometry": {"coordinates":[26.18753,2.62374],"type":"Point"}
}