{
  "type": "Feature",
  "properties": {
    "gn:admin1_code":"30.0",
    "gn:asciiname":"Ngode",
    "gn:country_code":"CD",
    "gn:dem":451,
    "gn:feature_class":"P",
    "gn:feature_code":"PPL",
    "gn:name":"Ngode",
    "gn:population":0,
    "gn:timezone":"Africa/Lubumbashi",
    "iso:country":"CD",
    "wof:name":"Ngode",
    "wof:placetype":"locality"
},
  "geometry": {"coordinates":[25.38162,1.49293],"type":"Point"}
}