{
  "type": "Feature",
  "properties": {
    "gn:admin1_code":"16.0",
    "gn:asciiname":"Edzeleya",
    "gn:country_code":"CD",
    "gn:dem":788,
    "gn:feature_class":"P",
    "gn:feature_code":"PPL",
    "gn:name":"Edzeleya",
    "gn:population":0,
    "gn:timezone":"Africa/Lubumbashi",
    "iso:country":"CD",
    "name:und_x_variant":[
        "Edzaleya",
        "Edzeleya"
    ],
    "wof:name":"Edzeleya",
    "wof:placetype":"locality"
},
  "geometry": {"coordinates":[27.83409,2.16858],"type":"Point"}
}