{
  "type": "Feature",
  "properties": {
    "gn:admin1_code":"19.0",
    "gn:asciiname":"Kambundi",
    "gn:country_code":"CD",
    "gn:dem":759,
    "gn:feature_class":"P",
    "gn:feature_code":"PPL",
    "gn:name":"Kambundi",
    "gn:population":0,
    "gn:timezone":"Africa/Kinshasa",
    "iso:country":"CD",
    "wof:name":"Kambundi",
    "wof:placetype":"locality"
},
  "geometry": {"coordinates":[17.46951,-5.62358],"type":"Point"}
}