{
  "type": "Feature",
  "properties": {
    "gn:admin1_code":"14.0",
    "gn:asciiname":"Menge",
    "gn:country_code":"CD",
    "gn:dem":1106,
    "gn:feature_class":"P",
    "gn:feature_code":"PPL",
    "gn:name":"Menge",
    "gn:population":0,
    "gn:timezone":"Africa/Lubumbashi",
    "iso:country":"CD",
    "name:ceb_x_preferred":[
        "Menge"
    ],
    "name:deu_x_preferred":[
        "Menge"
    ],
    "name:fra_x_preferred":[
        "Menge"
    ],
    "name:ita_x_preferred":[
        "Menge"
    ],
    "name:swe_x_preferred":[
        "Menge"
    ],
    "name:und_x_variant":[
        "Mwenge"
    ],
    "wof:name":"Menge",
    "wof:placetype":"locality"
},
  "geometry": {"coordinates":[27.93349000000001,-11.09664],"type":"Point"}
}