{
  "type": "Feature",
  "properties": {
    "gn:admin1_code":"19.0",
    "gn:asciiname":"Mungulu-Tsakala Troisieme",
    "gn:country_code":"CD",
    "gn:dem":728,
    "gn:feature_class":"P",
    "gn:feature_code":"PPL",
    "gn:name":"Mungulu-Tsakala Troisi\u00e8me",
    "gn:population":0,
    "gn:timezone":"Africa/Kinshasa",
    "iso:country":"CD",
    "wof:name":"Mungulu-Tsakala Troisieme",
    "wof:placetype":"locality"
},
  "geometry": {"coordinates":[17.42501,-5.65196],"type":"Point"}
}