{
  "type": "Feature",
  "properties": {
    "gn:admin1_code":"20.0",
    "gn:asciiname":"Mosongo-Mill",
    "gn:country_code":"CD",
    "gn:dem":429,
    "gn:feature_class":"P",
    "gn:feature_code":"PPL",
    "gn:name":"Mosongo-Mill",
    "gn:population":0,
    "gn:timezone":"Africa/Kinshasa",
    "iso:country":"CD",
    "wof:name":"Mosongo-Mill",
    "wof:placetype":"locality"
},
  "geometry": {"coordinates":[18.82445,-4.95073],"type":"Point"}
}