{
  "type": "Feature",
  "properties": {
    "gn:admin1_code":"22.0",
    "gn:asciiname":"Kaneji",
    "gn:country_code":"CD",
    "gn:dem":950,
    "gn:feature_class":"P",
    "gn:feature_code":"PPL",
    "gn:name":"Kaneji",
    "gn:population":0,
    "gn:timezone":"Africa/Lubumbashi",
    "iso:country":"CD",
    "wof:name":"Kaneji",
    "wof:placetype":"locality"
},
  "geometry": {"coordinates":[22.63981,-8.72165],"type":"Point"}
}