{
  "type": "Feature",
  "properties": {
    "gn:admin1_code":"10.0",
    "gn:asciiname":"Kikolobo",
    "gn:country_code":"CD",
    "gn:dem":449,
    "gn:feature_class":"P",
    "gn:feature_code":"PPL",
    "gn:name":"Kikolobo",
    "gn:population":0,
    "gn:timezone":"Africa/Lubumbashi",
    "iso:country":"CD",
    "wof:name":"Kikolobo",
    "wof:placetype":"locality"
},
  "geometry": {"coordinates":[25.73333,-2.46667],"type":"Point"}
}