{
  "type": "Feature",
  "properties": {
    "gn:admin1_code":"19.0",
    "gn:asciiname":"Shambungu",
    "gn:country_code":"CD",
    "gn:dem":1070,
    "gn:feature_class":"P",
    "gn:feature_code":"PPL",
    "gn:name":"Shambungu",
    "gn:population":0,
    "gn:timezone":"Africa/Kinshasa",
    "iso:country":"CD",
    "wof:name":"Shambungu",
    "wof:placetype":"locality"
},
  "geometry": {"coordinates":[19.21757,-7.68796],"type":"Point"}
}