{
  "type": "Feature",
  "properties": {
    "gn:admin1_code":"12.0",
    "gn:asciiname":"Kake",
    "gn:country_code":"CD",
    "gn:dem":819,
    "gn:feature_class":"P",
    "gn:feature_code":"PPL",
    "gn:name":"Kake",
    "gn:population":0,
    "gn:timezone":"Africa/Lubumbashi",
    "iso:country":"CD",
    "name:azb_x_preferred":[
        "\u06a9\u0627\u06a9\u06cc"
    ],
    "name:ceb_x_preferred":[
        "Kake"
    ],
    "name:fin_x_preferred":[
        "Kake"
    ],
    "name:pol_x_preferred":[
        "Kake"
    ],
    "name:por_x_preferred":[
        "Kake"
    ],
    "name:rus_x_preferred":[
        "\u041a\u0435\u0439\u043a"
    ],
    "name:swe_x_preferred":[
        "Kake"
    ],
    "wof:name":"Kake",
    "wof:placetype":"locality"
},
  "geometry": {"coordinates":[29.13389,-3.6775],"type":"Point"}
}