{
  "type": "Feature",
  "properties": {
    "gn:admin1_code":"10.0",
    "gn:asciiname":"Kawaya",
    "gn:country_code":"CD",
    "gn:dem":723,
    "gn:feature_class":"P",
    "gn:feature_code":"PPL",
    "gn:name":"Kawaya",
    "gn:population":0,
    "gn:timezone":"Africa/Lubumbashi",
    "iso:country":"CD",
    "wof:name":"Kawaya",
    "wof:placetype":"locality"
},
  "geometry": {"coordinates":[27.10157,-4.30494],"type":"Point"}
}