{
  "type": "Feature",
  "properties": {
    "gn:admin1_code":"8.0",
    "gn:asciiname":"Ango Ango",
    "gn:country_code":"CD",
    "gn:dem":161,
    "gn:feature_class":"P",
    "gn:feature_code":"PPL",
    "gn:name":"Ango Ango",
    "gn:population":0,
    "gn:timezone":"Africa/Kinshasa",
    "iso:country":"CD",
    "wof:name":"Ango Ango",
    "wof:placetype":"locality"
},
  "geometry": {"coordinates":[13.44434,-5.76912],"type":"Point"}
}