{
  "type": "Feature",
  "properties": {
    "gn:admin1_code":"27.0",
    "gn:asciiname":"Komi",
    "gn:country_code":"CD",
    "gn:dem":511,
    "gn:feature_class":"P",
    "gn:feature_code":"PPL",
    "gn:name":"Komi",
    "gn:population":0,
    "gn:timezone":"Africa/Lubumbashi",
    "iso:country":"CD",
    "wof:name":"Komi",
    "wof:placetype":"locality"
},
  "geometry": {"coordinates":[23.76667,-3.38333],"type":"Point"}
}