{
  "type": "Feature",
  "properties": {
    "gn:admin1_code":"20.0",
    "gn:asciiname":"Bulundu",
    "gn:country_code":"CD",
    "gn:dem":734,
    "gn:feature_class":"P",
    "gn:feature_code":"PPL",
    "gn:name":"Bulundu",
    "gn:population":0,
    "gn:timezone":"Africa/Kinshasa",
    "iso:country":"CD",
    "wof:name":"Bulundu",
    "wof:placetype":"locality"
},
  "geometry": {"coordinates":[17.59351000000001,-5.22168],"type":"Point"}
}