{
  "type": "Feature",
  "properties": {
    "gn:admin1_code":"31.0",
    "gn:asciiname":"Nongiema",
    "gn:country_code":"CD",
    "gn:dem":371,
    "gn:feature_class":"P",
    "gn:feature_code":"PPL",
    "gn:name":"Nongiema",
    "gn:population":0,
    "gn:timezone":"Africa/Kinshasa",
    "iso:country":"CD",
    "wof:name":"Nongiema",
    "wof:placetype":"locality"
},
  "geometry": {"coordinates":[20.43333,-0.51667],"type":"Point"}
}