{
  "type": "Feature",
  "properties": {
    "gn:admin1_code":"17.0",
    "gn:asciiname":"Busu",
    "gn:country_code":"CD",
    "gn:dem":1538,
    "gn:feature_class":"P",
    "gn:feature_code":"PPL",
    "gn:name":"Busu",
    "gn:population":0,
    "gn:timezone":"Africa/Lubumbashi",
    "iso:country":"CD",
    "wof:name":"Busu",
    "wof:placetype":"locality"
},
  "geometry": {"coordinates":[30.25336,2.02091],"type":"Point"}
}