{
  "type": "Feature",
  "properties": {
    "gn:admin1_code":"30.0",
    "gn:asciiname":"Bafwamalambu",
    "gn:country_code":"CD",
    "gn:dem":512,
    "gn:feature_class":"P",
    "gn:feature_code":"PPL",
    "gn:name":"Bafwamalambu",
    "gn:population":0,
    "gn:timezone":"Africa/Lubumbashi",
    "iso:country":"CD",
    "wof:name":"Bafwamalambu",
    "wof:placetype":"locality"
},
  "geometry": {"coordinates":[26.01667,1.36667],"type":"Point"}
}