{
  "type": "Feature",
  "properties": {
    "gn:admin1_code":"17.0",
    "gn:asciiname":"Aribado",
    "gn:country_code":"CD",
    "gn:dem":1122,
    "gn:feature_class":"P",
    "gn:feature_code":"PPL",
    "gn:name":"Aribado",
    "gn:population":0,
    "gn:timezone":"Africa/Lubumbashi",
    "iso:country":"CD",
    "wof:name":"Aribado",
    "wof:placetype":"locality"
},
  "geometry": {"coordinates":[30.55438,3.37985],"type":"Point"}
}