{
  "type": "Feature",
  "properties": {
    "gn:admin1_code":"23.0",
    "gn:asciiname":"Sakaji Palovo",
    "gn:country_code":"CD",
    "gn:dem":860,
    "gn:feature_class":"P",
    "gn:feature_code":"PPL",
    "gn:name":"Sakaji Palovo",
    "gn:population":0,
    "gn:timezone":"Africa/Lubumbashi",
    "iso:country":"CD",
    "wof:name":"Sakaji Palovo",
    "wof:placetype":"locality"
},
  "geometry": {"coordinates":[22.54714,-7.45593],"type":"Point"}
}