{
  "type": "Feature",
  "properties": {
    "gn:admin1_code":"22.0",
    "gn:asciiname":"Mapatshi",
    "gn:country_code":"CD",
    "gn:dem":1038,
    "gn:feature_class":"P",
    "gn:feature_code":"PPL",
    "gn:name":"Mapatshi",
    "gn:population":0,
    "gn:timezone":"Africa/Lubumbashi",
    "iso:country":"CD",
    "wof:name":"Mapatshi",
    "wof:placetype":"locality"
},
  "geometry": {"coordinates":[22.80302,-10.71163],"type":"Point"}
}