{
  "type": "Feature",
  "properties": {
    "gn:admin1_code":"8.0",
    "gn:asciiname":"Goma",
    "gn:country_code":"CD",
    "gn:dem":262,
    "gn:feature_class":"P",
    "gn:feature_code":"PPL",
    "gn:name":"Goma",
    "gn:population":0,
    "gn:timezone":"Africa/Kinshasa",
    "iso:country":"CD",
    "wof:name":"Goma",
    "wof:placetype":"locality"
},
  "geometry": {"coordinates":[14.40386,-5.32104],"type":"Point"}
}