{
  "type": "Feature",
  "properties": {
    "gn:admin1_code":"22.0",
    "gn:asciiname":"Shamusinga",
    "gn:country_code":"CD",
    "gn:dem":1028,
    "gn:feature_class":"P",
    "gn:feature_code":"PPL",
    "gn:name":"Shamusinga",
    "gn:population":0,
    "gn:timezone":"Africa/Lubumbashi",
    "iso:country":"CD",
    "name:und_x_variant":[
        "Samusinga",
        "Mujinga",
        "Shamusinga",
        "Samujinga"
    ],
    "wof:name":"Shamusinga",
    "wof:placetype":"locality"
},
  "geometry": {"coordinates":[24.75631,-10.38537],"type":"Point"}
}