{
  "type": "Feature",
  "properties": {
    "gn:admin1_code":"23.0",
    "gn:asciiname":"Piana-Tshiniama",
    "gn:country_code":"CD",
    "gn:dem":760,
    "gn:feature_class":"P",
    "gn:feature_code":"PPL",
    "gn:name":"Piana-Tshiniama",
    "gn:population":0,
    "gn:timezone":"Africa/Lubumbashi",
    "iso:country":"CD",
    "wof:name":"Piana-Tshiniama",
    "wof:placetype":"locality"
},
  "geometry": {"coordinates":[22.93571,-5.92028],"type":"Point"}
}