{
  "type": "Feature",
  "properties": {
    "gn:admin1_code":"21.0",
    "gn:asciiname":"Mukendi-Bakwa",
    "gn:country_code":"CD",
    "gn:dem":792,
    "gn:feature_class":"P",
    "gn:feature_code":"PPL",
    "gn:name":"Mukendi-Bakwa",
    "gn:population":0,
    "gn:timezone":"Africa/Lubumbashi",
    "iso:country":"CD",
    "wof:name":"Mukendi-Bakwa",
    "wof:placetype":"locality"
},
  "geometry": {"coordinates":[23.60626,-6.99118],"type":"Point"}
}