{
  "type": "Feature",
  "properties": {
    "gn:admin1_code":"0.0",
    "gn:asciiname":"Kilwa",
    "gn:country_code":"CD",
    "gn:dem":950,
    "gn:feature_class":"P",
    "gn:feature_code":"PPL",
    "gn:name":"Kilwa",
    "gn:population":0,
    "gn:timezone":"Africa/Lubumbashi",
    "iso:country":"CD",
    "name:deu_x_preferred":[
        "Kilwa"
    ],
    "name:eng_x_preferred":[
        "Kilwa"
    ],
    "wof:name":"Kilwa",
    "wof:placetype":"locality"
},
  "geometry": {"coordinates":[28.33288,-9.28528],"type":"Point"}
}