{
  "type": "Feature",
  "properties": {
    "gn:admin1_code":"22.0",
    "gn:asciiname":"Mwimba",
    "gn:country_code":"CD",
    "gn:dem":1101,
    "gn:feature_class":"P",
    "gn:feature_code":"PPL",
    "gn:name":"Mwimba",
    "gn:population":0,
    "gn:timezone":"Africa/Lubumbashi",
    "iso:country":"CD",
    "name:und_x_variant":[
        "Mwimbu"
    ],
    "wof:name":"Mwimba",
    "wof:placetype":"locality"
},
  "geometry": {"coordinates":[22.75686,-9.2002],"type":"Point"}
}