{
  "type": "Feature",
  "properties": {
    "gn:admin1_code":"30.0",
    "gn:asciiname":"Bavodini",
    "gn:country_code":"CD",
    "gn:dem":538,
    "gn:feature_class":"P",
    "gn:feature_code":"PPL",
    "gn:name":"Bavodini",
    "gn:population":0,
    "gn:timezone":"Africa/Lubumbashi",
    "iso:country":"CD",
    "wof:name":"Bavodini",
    "wof:placetype":"locality"
},
  "geometry": {"coordinates":[26.67556,1.97323],"type":"Point"}
}