{
  "type": "Feature",
  "properties": {
    "gn:admin1_code":"14.0",
    "gn:asciiname":"Yombwe",
    "gn:country_code":"CD",
    "gn:dem":1026,
    "gn:feature_class":"P",
    "gn:feature_code":"PPL",
    "gn:name":"Yombwe",
    "gn:population":0,
    "gn:timezone":"Africa/Lubumbashi",
    "iso:country":"CD",
    "wof:name":"Yombwe",
    "wof:placetype":"locality"
},
  "geometry": {"coordinates":[28.46667,-11.11667],"type":"Point"}
}