{
  "type": "Feature",
  "properties": {
    "gn:admin1_code":"20.0",
    "gn:asciiname":"Boka",
    "gn:country_code":"CD",
    "gn:dem":322,
    "gn:feature_class":"P",
    "gn:feature_code":"PPL",
    "gn:name":"Boka",
    "gn:population":0,
    "gn:timezone":"Africa/Kinshasa",
    "iso:country":"CD",
    "name:ceb_x_preferred":[
        "Boka"
    ],
    "name:deu_x_preferred":[
        "Boka"
    ],
    "name:fra_x_preferred":[
        "Boka"
    ],
    "name:hun_x_preferred":[
        "Boka"
    ],
    "name:rus_x_preferred":[
        "\u0411\u043e\u043a\u0430"
    ],
    "name:slv_x_preferred":[
        "Boka"
    ],
    "name:srp_x_preferred":[
        "\u0411\u043e\u043a\u0430"
    ],
    "name:swe_x_preferred":[
        "Boka"
    ],
    "name:und_x_variant":[
        "Beka",
        "Bokulu",
        "Boka"
    ],
    "wof:name":"Boka",
    "wof:placetype":"locality"
},
  "geometry": {"coordinates":[17.55877000000001,-3.38185],"type":"Point"}
}