{
  "type": "Feature",
  "properties": {
    "gn:admin1_code":"25.0",
    "gn:asciiname":"Djobolia",
    "gn:country_code":"CD",
    "gn:dem":461,
    "gn:feature_class":"P",
    "gn:feature_code":"PPL",
    "gn:name":"Djobolia",
    "gn:population":0,
    "gn:timezone":"Africa/Kinshasa",
    "iso:country":"CD",
    "wof:name":"Djobolia",
    "wof:placetype":"locality"
},
  "geometry": {"coordinates":[22.31155,2.92387],"type":"Point"}
}