{
  "type": "Feature",
  "properties": {
    "gn:admin1_code":"23.0",
    "gn:asciiname":"Kambaie",
    "gn:country_code":"CD",
    "gn:dem":599,
    "gn:feature_class":"P",
    "gn:feature_code":"PPL",
    "gn:name":"Kambaie",
    "gn:population":0,
    "gn:timezone":"Africa/Lubumbashi",
    "iso:country":"CD",
    "wof:name":"Kambaie",
    "wof:placetype":"locality"
},
  "geometry": {"coordinates":[22.38294,-5.85928],"type":"Point"}
}