{
  "type": "Feature",
  "properties": {
    "gn:admin1_code":"22.0",
    "gn:asciiname":"Sapasa",
    "gn:country_code":"CD",
    "gn:dem":1157,
    "gn:feature_class":"P",
    "gn:feature_code":"PPL",
    "gn:name":"Sapasa",
    "gn:population":0,
    "gn:timezone":"Africa/Lubumbashi",
    "iso:country":"CD",
    "wof:name":"Sapasa",
    "wof:placetype":"locality"
},
  "geometry": {"coordinates":[23.73277,-10.41876],"type":"Point"}
}