{
  "type": "Feature",
  "properties": {
    "gn:admin1_code":"25.0",
    "gn:asciiname":"Yamangele II",
    "gn:country_code":"CD",
    "gn:dem":449,
    "gn:feature_class":"P",
    "gn:feature_code":"PPL",
    "gn:name":"Yamangele II",
    "gn:population":0,
    "gn:timezone":"Africa/Kinshasa",
    "iso:country":"CD",
    "name:fra_x_preferred":[
        "Yamangele Deuxi\u00e8me"
    ],
    "wof:name":"Yamangele II",
    "wof:placetype":"locality"
},
  "geometry": {"coordinates":[22.44969,2.74717],"type":"Point"}
}