{
  "type": "Feature",
  "properties": {
    "gn:admin1_code":"22.0",
    "gn:asciiname":"Sangungola",
    "gn:country_code":"CD",
    "gn:dem":906,
    "gn:feature_class":"P",
    "gn:feature_code":"PPL",
    "gn:name":"Sangungola",
    "gn:population":0,
    "gn:timezone":"Africa/Lubumbashi",
    "iso:country":"CD",
    "wof:name":"Sangungola",
    "wof:placetype":"locality"
},
  "geometry": {"coordinates":[23.10709,-9.75297],"type":"Point"}
}