{
  "type": "Feature",
  "properties": {
    "gn:admin1_code":"22.0",
    "gn:asciiname":"Mukwakwa",
    "gn:country_code":"CD",
    "gn:dem":1173,
    "gn:feature_class":"P",
    "gn:feature_code":"PPL",
    "gn:name":"Mukwakwa",
    "gn:population":0,
    "gn:timezone":"Africa/Lubumbashi",
    "iso:country":"CD",
    "wof:name":"Mukwakwa",
    "wof:placetype":"locality"
},
  "geometry": {"coordinates":[23.95519,-10.2734],"type":"Point"}
}