{
  "type": "Feature",
  "properties": {
    "gn:admin1_code":"24.0",
    "gn:asciiname":"Bobo Deuxieme",
    "gn:country_code":"CD",
    "gn:dem":339,
    "gn:feature_class":"P",
    "gn:feature_code":"PPL",
    "gn:name":"Bobo Deuxi\u00e8me",
    "gn:population":0,
    "gn:timezone":"Africa/Kinshasa",
    "iso:country":"CD",
    "name:und_x_variant":[
        "Bobo Deuxi\u00e8me",
        "Bobo II"
    ],
    "wof:name":"Bobo Deuxieme",
    "wof:placetype":"locality"
},
  "geometry": {"coordinates":[18.46901,-3.56514],"type":"Point"}
}