{
  "type": "Feature",
  "properties": {
    "gn:admin1_code":"14.0",
    "gn:asciiname":"Kipompwe",
    "gn:country_code":"CD",
    "gn:dem":1211,
    "gn:feature_class":"P",
    "gn:feature_code":"PPL",
    "gn:name":"Kipompwe",
    "gn:population":0,
    "gn:timezone":"Africa/Lubumbashi",
    "iso:country":"CD",
    "wof:name":"Kipompwe",
    "wof:placetype":"locality"
},
  "geometry": {"coordinates":[26.74204000000001,-11.40807],"type":"Point"}
}