{
  "type": "Feature",
  "properties": {
    "gn:admin1_code":"21.0",
    "gn:asciiname":"Niambwi",
    "gn:country_code":"CD",
    "gn:dem":913,
    "gn:feature_class":"P",
    "gn:feature_code":"PPL",
    "gn:name":"Niambwi",
    "gn:population":0,
    "gn:timezone":"Africa/Lubumbashi",
    "iso:country":"CD",
    "wof:name":"Niambwi",
    "wof:placetype":"locality"
},
  "geometry": {"coordinates":[24.95578,-6.56321],"type":"Point"}
}