{
  "type": "Feature",
  "properties": {
    "gn:admin1_code":"8.0",
    "gn:asciiname":"Muala Deuxieme",
    "gn:country_code":"CD",
    "gn:dem":588,
    "gn:feature_class":"P",
    "gn:feature_code":"PPL",
    "gn:name":"Muala Deuxi\u00e8me",
    "gn:population":0,
    "gn:timezone":"Africa/Kinshasa",
    "iso:country":"CD",
    "wof:name":"Muala Deuxieme",
    "wof:placetype":"locality"
},
  "geometry": {"coordinates":[15.01049,-5.27008],"type":"Point"}
}