{
  "type": "Feature",
  "properties": {
    "gn:admin1_code":"18.0",
    "gn:asciiname":"Kambangoma",
    "gn:country_code":"CD",
    "gn:dem":625,
    "gn:feature_class":"P",
    "gn:feature_code":"PPL",
    "gn:name":"Kambangoma",
    "gn:population":0,
    "gn:timezone":"Africa/Lubumbashi",
    "iso:country":"CD",
    "wof:name":"Kambangoma",
    "wof:placetype":"locality"
},
  "geometry": {"coordinates":[21.53706,-5.47617],"type":"Point"}
}