{
  "type": "Feature",
  "properties": {
    "gn:admin1_code":"10.0",
    "gn:asciiname":"Tubile",
    "gn:country_code":"CD",
    "gn:dem":597,
    "gn:feature_class":"P",
    "gn:feature_code":"PPL",
    "gn:name":"Tubile",
    "gn:population":0,
    "gn:timezone":"Africa/Lubumbashi",
    "iso:country":"CD",
    "wof:name":"Tubile",
    "wof:placetype":"locality"
},
  "geometry": {"coordinates":[26.8014,-1.6943],"type":"Point"}
}