{
  "type": "Feature",
  "properties": {
    "gn:admin1_code":"22.0",
    "gn:asciiname":"Kunga",
    "gn:country_code":"CD",
    "gn:dem":1037,
    "gn:feature_class":"P",
    "gn:feature_code":"PPL",
    "gn:name":"Kunga",
    "gn:population":0,
    "gn:timezone":"Africa/Lubumbashi",
    "iso:country":"CD",
    "wof:name":"Kunga",
    "wof:placetype":"locality"
},
  "geometry": {"coordinates":[23.17807,-10.30498],"type":"Point"}
}