{
  "type": "Feature",
  "properties": {
    "gn:admin1_code":"13.0",
    "gn:asciiname":"Nglia",
    "gn:country_code":"CD",
    "gn:dem":468,
    "gn:feature_class":"P",
    "gn:feature_code":"PPL",
    "gn:name":"Nglia",
    "gn:population":0,
    "gn:timezone":"Africa/Lubumbashi",
    "iso:country":"CD",
    "name:und_x_variant":[
        "Ngalia"
    ],
    "wof:name":"Nglia",
    "wof:placetype":"locality"
},
  "geometry": {"coordinates":[23.32054,3.46688],"type":"Point"}
}