{
  "type": "Feature",
  "properties": {
    "gn:admin1_code":"17.0",
    "gn:asciiname":"Nzinzi",
    "gn:country_code":"CD",
    "gn:dem":1342,
    "gn:feature_class":"P",
    "gn:feature_code":"PPL",
    "gn:name":"Nzinzi",
    "gn:population":0,
    "gn:timezone":"Africa/Lubumbashi",
    "iso:country":"CD",
    "wof:name":"Nzinzi",
    "wof:placetype":"locality"
},
  "geometry": {"coordinates":[30.52851,2.54164],"type":"Point"}
}