{
  "type": "Feature",
  "properties": {
    "gn:admin1_code":"31.0",
    "gn:asciiname":"Booli",
    "gn:country_code":"CD",
    "gn:dem":362,
    "gn:feature_class":"P",
    "gn:feature_code":"PPL",
    "gn:name":"Booli",
    "gn:population":0,
    "gn:timezone":"Africa/Kinshasa",
    "iso:country":"CD",
    "wof:name":"Booli",
    "wof:placetype":"locality"
},
  "geometry": {"coordinates":[21.53485,0.16269],"type":"Point"}
}