{
  "type": "Feature",
  "properties": {
    "gn:admin1_code":"24.0",
    "gn:asciiname":"Bileke",
    "gn:country_code":"CD",
    "gn:dem":293,
    "gn:feature_class":"P",
    "gn:feature_code":"PPL",
    "gn:name":"Bileke",
    "gn:population":0,
    "gn:timezone":"Africa/Kinshasa",
    "iso:country":"CD",
    "wof:name":"Bileke",
    "wof:placetype":"locality"
},
  "geometry": {"coordinates":[17.75905,-2.71342],"type":"Point"}
}