{
  "type": "Feature",
  "properties": {
    "gn:admin1_code":"31.0",
    "gn:asciiname":"Mona-Imba",
    "gn:country_code":"CD",
    "gn:dem":420,
    "gn:feature_class":"P",
    "gn:feature_code":"PPL",
    "gn:name":"Mona-Imba",
    "gn:population":0,
    "gn:timezone":"Africa/Kinshasa",
    "iso:country":"CD",
    "wof:name":"Mona-Imba",
    "wof:placetype":"locality"
},
  "geometry": {"coordinates":[23.41667,-0.95],"type":"Point"}
}