{
  "type": "Feature",
  "properties": {
    "gn:admin1_code":"19.0",
    "gn:asciiname":"Kandi-Kunga",
    "gn:country_code":"CD",
    "gn:dem":894,
    "gn:feature_class":"P",
    "gn:feature_code":"PPL",
    "gn:name":"Kandi-Kunga",
    "gn:population":0,
    "gn:timezone":"Africa/Kinshasa",
    "iso:country":"CD",
    "wof:name":"Kandi-Kunga",
    "wof:placetype":"locality"
},
  "geometry": {"coordinates":[18.03973,-5.96193],"type":"Point"}
}