{
  "type": "Feature",
  "properties": {
    "gn:admin1_code":"13.0",
    "gn:asciiname":"Namape",
    "gn:country_code":"CD",
    "gn:dem":649,
    "gn:feature_class":"P",
    "gn:feature_code":"PPL",
    "gn:name":"Namape",
    "gn:population":0,
    "gn:timezone":"Africa/Lubumbashi",
    "iso:country":"CD",
    "wof:name":"Namape",
    "wof:placetype":"locality"
},
  "geometry": {"coordinates":[26.36562,2.60052],"type":"Point"}
}