{
  "type": "Feature",
  "properties": {
    "gn:admin1_code":"28.0",
    "gn:asciiname":"Bomwele",
    "gn:country_code":"CD",
    "gn:dem":337,
    "gn:feature_class":"P",
    "gn:feature_code":"PPL",
    "gn:name":"Bomwele",
    "gn:population":0,
    "gn:timezone":"Africa/Kinshasa",
    "iso:country":"CD",
    "name:fra_x_preferred":[
        "Bomwele"
    ],
    "wof:name":"Bomwele",
    "wof:placetype":"locality"
},
  "geometry": {"coordinates":[18.97573,2.25157],"type":"Point"}
}