{
  "type": "Feature",
  "properties": {
    "gn:admin1_code":"13.0",
    "gn:asciiname":"Ingasu",
    "gn:country_code":"CD",
    "gn:dem":548,
    "gn:feature_class":"P",
    "gn:feature_code":"PPL",
    "gn:name":"Ingasu",
    "gn:population":0,
    "gn:timezone":"Africa/Lubumbashi",
    "iso:country":"CD",
    "wof:name":"Ingasu",
    "wof:placetype":"locality"
},
  "geometry": {"coordinates":[24.94238,4.00113],"type":"Point"}
}