{
  "type": "Feature",
  "properties": {
    "gn:admin1_code":"18.0",
    "gn:asciiname":"Bongamba",
    "gn:country_code":"CD",
    "gn:dem":601,
    "gn:feature_class":"P",
    "gn:feature_code":"PPL",
    "gn:name":"Bongamba",
    "gn:population":0,
    "gn:timezone":"Africa/Lubumbashi",
    "iso:country":"CD",
    "wof:name":"Bongamba",
    "wof:placetype":"locality"
},
  "geometry": {"coordinates":[21.49937000000001,-5.0106],"type":"Point"}
}