{
  "type": "Feature",
  "properties": {
    "gn:admin1_code":"8.0",
    "gn:asciiname":"Mani",
    "gn:country_code":"CD",
    "gn:dem":833,
    "gn:feature_class":"P",
    "gn:feature_code":"PPL",
    "gn:name":"Mani",
    "gn:population":0,
    "gn:timezone":"Africa/Kinshasa",
    "iso:country":"CD",
    "name:cat_x_preferred":[
        "Mani"
    ],
    "name:ceb_x_preferred":[
        "Mani"
    ],
    "name:ces_x_preferred":[
        "Mani"
    ],
    "name:dan_x_preferred":[
        "Mani"
    ],
    "name:deu_x_preferred":[
        "Mani"
    ],
    "name:epo_x_preferred":[
        "Mani"
    ],
    "name:fas_x_preferred":[
        "\u0645\u0627\u0646\u06cc"
    ],
    "name:fin_x_preferred":[
        "Mani"
    ],
    "name:fra_x_preferred":[
        "Mani"
    ],
    "name:heb_x_preferred":[
        "\u05de\u05e0\u05d9"
    ],
    "name:hrv_x_preferred":[
        "Mani"
    ],
    "name:ind_x_preferred":[
        "Mani"
    ],
    "name:isl_x_preferred":[
        "M\u00e1ni"
    ],
    "name:ita_x_preferred":[
        "Mani"
    ],
    "name:kat_x_preferred":[
        "\u10db\u10d0\u10dc\u10d8"
    ],
    "name:lin_x_preferred":[
        "Mani"
    ],
    "name:nld_x_preferred":[
        "Mani"
    ],
    "name:nno_x_preferred":[
        "Mani"
    ],
    "name:pol_x_preferred":[
        "Mani"
    ],
    "name:por_x_preferred":[
        "Mani"
    ],
    "name:rus_x_preferred":[
        "\u041c\u0430\u043d\u0438"
    ],
    "name:slk_x_preferred":[
        "Mani"
    ],
    "name:spa_x_preferred":[
        "Mani"
    ],
    "name:srp_x_preferred":[
        "\u041c\u0430\u043d\u0438"
    ],
    "name:swe_x_preferred":[
        "Mani"
    ],
    "name:tel_x_preferred":[
        "\u0c2e\u0c23\u0c3f"
    ],
    "name:tgl_x_preferred":[
        "Mani"
    ],
    "name:tur_x_preferred":[
        "Mani"
    ],
    "name:ukr_x_preferred":[
        "\u041c\u0430\u043d\u0456"
    ],
    "wof:name":"Mani",
    "wof:placetype":"locality"
},
  "geometry": {"coordinates":[15.02667,-5.42454],"type":"Point"}
}