{
  "type": "Feature",
  "properties": {
    "gn:admin1_code":"18.0",
    "gn:asciiname":"Mubulungu",
    "gn:country_code":"CD",
    "gn:dem":470,
    "gn:feature_class":"P",
    "gn:feature_code":"PPL",
    "gn:name":"Mubulungu",
    "gn:population":0,
    "gn:timezone":"Africa/Lubumbashi",
    "iso:country":"CD",
    "wof:name":"Mubulungu",
    "wof:placetype":"locality"
},
  "geometry": {"coordinates":[20.09964,-5.8548],"type":"Point"}
}