{
  "type": "Feature",
  "properties": {
    "gn:admin1_code":"21.0",
    "gn:asciiname":"Baule-Panda",
    "gn:country_code":"CD",
    "gn:dem":796,
    "gn:feature_class":"P",
    "gn:feature_code":"PPL",
    "gn:name":"Baule-Panda",
    "gn:population":0,
    "gn:timezone":"Africa/Lubumbashi",
    "iso:country":"CD",
    "name:und_x_variant":[
        "Baula"
    ],
    "wof:name":"Baule-Panda",
    "wof:placetype":"locality"
},
  "geometry": {"coordinates":[24.60315,-5.96014],"type":"Point"}
}