{
  "type": "Feature",
  "properties": {
    "gn:admin1_code":"15.0",
    "gn:asciiname":"Shimbu",
    "gn:country_code":"CD",
    "gn:dem":590,
    "gn:feature_class":"P",
    "gn:feature_code":"PPL",
    "gn:name":"Shimbu",
    "gn:population":0,
    "gn:timezone":"Africa/Lubumbashi",
    "iso:country":"CD",
    "wof:name":"Shimbu",
    "wof:placetype":"locality"
},
  "geometry": {"coordinates":[26.75534,-8.04747],"type":"Point"}
}