{
  "type": "Feature",
  "properties": {
    "gn:admin1_code":"8.0",
    "gn:asciiname":"Kavaya",
    "gn:country_code":"CD",
    "gn:dem":531,
    "gn:feature_class":"P",
    "gn:feature_code":"PPL",
    "gn:name":"Kavaya",
    "gn:population":0,
    "gn:timezone":"Africa/Kinshasa",
    "iso:country":"CD",
    "wof:name":"Kavaya",
    "wof:placetype":"locality"
},
  "geometry": {"coordinates":[15.12957,-5.0629],"type":"Point"}
}