{
  "type": "Feature",
  "properties": {
    "gn:admin1_code":"16.0",
    "gn:asciiname":"Ekibondo",
    "gn:country_code":"CD",
    "gn:dem":738,
    "gn:feature_class":"P",
    "gn:feature_code":"PPL",
    "gn:name":"Ekibondo",
    "gn:population":0,
    "gn:timezone":"Africa/Lubumbashi",
    "iso:country":"CD",
    "name:und_x_variant":[
        "Ekibundo",
        "Ekibondo"
    ],
    "wof:name":"Ekibondo",
    "wof:placetype":"locality"
},
  "geometry": {"coordinates":[28.34031,3.54736],"type":"Point"}
}