{
  "type": "Feature",
  "properties": {
    "gn:admin1_code":"19.0",
    "gn:asciiname":"Kamwanga",
    "gn:country_code":"CD",
    "gn:dem":1030,
    "gn:feature_class":"P",
    "gn:feature_code":"PPL",
    "gn:name":"Kamwanga",
    "gn:population":0,
    "gn:timezone":"Africa/Kinshasa",
    "iso:country":"CD",
    "wof:name":"Kamwanga",
    "wof:placetype":"locality"
},
  "geometry": {"coordinates":[18.5302,-6.94512],"type":"Point"}
}