{
  "type": "Feature",
  "properties": {
    "gn:admin1_code":"16.0",
    "gn:asciiname":"Atandra",
    "gn:country_code":"CD",
    "gn:dem":991,
    "gn:feature_class":"P",
    "gn:feature_code":"PPL",
    "gn:name":"Atandra",
    "gn:population":0,
    "gn:timezone":"Africa/Lubumbashi",
    "iso:country":"CD",
    "wof:name":"Atandra",
    "wof:placetype":"locality"
},
  "geometry": {"coordinates":[30.3024,3.37806],"type":"Point"}
}