{
  "type": "Feature",
  "properties": {
    "gn:admin1_code":"14.0",
    "gn:asciiname":"Kazeba",
    "gn:country_code":"CD",
    "gn:dem":998,
    "gn:feature_class":"P",
    "gn:feature_code":"PPL",
    "gn:name":"Kazeba",
    "gn:population":0,
    "gn:timezone":"Africa/Lubumbashi",
    "iso:country":"CD",
    "wof:name":"Kazeba",
    "wof:placetype":"locality"
},
  "geometry": {"coordinates":[28.18333,-9.35],"type":"Point"}
}