{
  "type": "Feature",
  "properties": {
    "gn:admin1_code":"28.0",
    "gn:asciiname":"Furu Bumbwa",
    "gn:country_code":"CD",
    "gn:dem":366,
    "gn:feature_class":"P",
    "gn:feature_code":"PPL",
    "gn:name":"Furu Bumbwa",
    "gn:population":0,
    "gn:timezone":"Africa/Kinshasa",
    "iso:country":"CD",
    "name:fra_x_preferred":[
        "Furu Bumbwa"
    ],
    "wof:name":"Furu Bumbwa",
    "wof:placetype":"locality"
},
  "geometry": {"coordinates":[19.13315,2.99101],"type":"Point"}
}