{
  "type": "Feature",
  "properties": {
    "gn:admin1_code":"30.0",
    "gn:asciiname":"Bavombo",
    "gn:country_code":"CD",
    "gn:dem":521,
    "gn:feature_class":"P",
    "gn:feature_code":"PPL",
    "gn:name":"Bavombo",
    "gn:population":0,
    "gn:timezone":"Africa/Lubumbashi",
    "iso:country":"CD",
    "wof:name":"Bavombo",
    "wof:placetype":"locality"
},
  "geometry": {"coordinates":[26.84138,1.91068],"type":"Point"}
}