{
  "type": "Feature",
  "properties": {
    "gn:admin1_code":"14.0",
    "gn:asciiname":"Tembe-Tembe",
    "gn:country_code":"CD",
    "gn:dem":941,
    "gn:feature_class":"P",
    "gn:feature_code":"PPL",
    "gn:name":"Tembe-Tembe",
    "gn:population":0,
    "gn:timezone":"Africa/Lubumbashi",
    "iso:country":"CD",
    "name:und_x_variant":[
        "Tombe Tombe",
        "Tembe-Tembe"
    ],
    "wof:name":"Tembe-Tembe",
    "wof:placetype":"locality"
},
  "geometry": {"coordinates":[28.31497,-9.16048],"type":"Point"}
}