{
  "type": "Feature",
  "properties": {
    "gn:admin1_code":"28.0",
    "gn:asciiname":"Bopanga",
    "gn:country_code":"CD",
    "gn:dem":428,
    "gn:feature_class":"P",
    "gn:feature_code":"PPL",
    "gn:name":"Bopanga",
    "gn:population":0,
    "gn:timezone":"Africa/Kinshasa",
    "iso:country":"CD",
    "name:fra_x_preferred":[
        "Bopanga"
    ],
    "wof:name":"Bopanga",
    "wof:placetype":"locality"
},
  "geometry": {"coordinates":[19.18668,2.33827],"type":"Point"}
}