{
  "type": "Feature",
  "properties": {
    "gn:admin1_code":"20.0",
    "gn:asciiname":"Kudi",
    "gn:country_code":"CD",
    "gn:dem":787,
    "gn:feature_class":"P",
    "gn:feature_code":"PPL",
    "gn:name":"Kudi",
    "gn:population":0,
    "gn:timezone":"Africa/Kinshasa",
    "iso:country":"CD",
    "wof:name":"Kudi",
    "wof:placetype":"locality"
},
  "geometry": {"coordinates":[19.33683,-6.00617],"type":"Point"}
}