{
  "type": "Feature",
  "properties": {
    "gn:admin1_code":"23.0",
    "gn:asciiname":"Tshikaji",
    "gn:country_code":"CD",
    "gn:dem":702,
    "gn:feature_class":"P",
    "gn:feature_code":"PPL",
    "gn:name":"Tshikaji",
    "gn:population":0,
    "gn:timezone":"Africa/Lubumbashi",
    "iso:country":"CD",
    "wof:name":"Tshikaji",
    "wof:placetype":"locality"
},
  "geometry": {"coordinates":[22.46772,-5.95407],"type":"Point"}
}