{
  "type": "Feature",
  "properties": {
    "gn:admin1_code":"25.0",
    "gn:asciiname":"Bomanga",
    "gn:country_code":"CD",
    "gn:dem":426,
    "gn:feature_class":"P",
    "gn:feature_code":"PPL",
    "gn:name":"Bomanga",
    "gn:population":0,
    "gn:timezone":"Africa/Kinshasa",
    "iso:country":"CD",
    "wof:name":"Bomanga",
    "wof:placetype":"locality"
},
  "geometry": {"coordinates":[22.66552,2.55309],"type":"Point"}
}