{
  "type": "Feature",
  "properties": {
    "gn:admin1_code":"20.0",
    "gn:asciiname":"Tundu-Mapepe",
    "gn:country_code":"CD",
    "gn:dem":536,
    "gn:feature_class":"P",
    "gn:feature_code":"PPL",
    "gn:name":"Tundu-Mapepe",
    "gn:population":0,
    "gn:timezone":"Africa/Kinshasa",
    "iso:country":"CD",
    "wof:name":"Tundu-Mapepe",
    "wof:placetype":"locality"
},
  "geometry": {"coordinates":[20.0082,-4.83145],"type":"Point"}
}