{
  "type": "Feature",
  "properties": {
    "gn:admin1_code":"12.0",
    "gn:asciiname":"Izege",
    "gn:country_code":"CD",
    "gn:dem":1908,
    "gn:feature_class":"P",
    "gn:feature_code":"PPL",
    "gn:name":"Izege",
    "gn:population":0,
    "gn:timezone":"Africa/Lubumbashi",
    "iso:country":"CD",
    "wof:name":"Izege",
    "wof:placetype":"locality"
},
  "geometry": {"coordinates":[28.67122,-2.57001],"type":"Point"}
}