{
  "type": "Feature",
  "properties": {
    "gn:admin1_code":"15.0",
    "gn:asciiname":"Kilombo",
    "gn:country_code":"CD",
    "gn:dem":710,
    "gn:feature_class":"P",
    "gn:feature_code":"PPL",
    "gn:name":"Kilombo",
    "gn:population":0,
    "gn:timezone":"Africa/Lubumbashi",
    "iso:country":"CD",
    "wof:name":"Kilombo",
    "wof:placetype":"locality"
},
  "geometry": {"coordinates":[25.83753,-7.80513],"type":"Point"}
}