{
  "type": "Feature",
  "properties": {
    "gn:admin1_code":"25.0",
    "gn:asciiname":"Yambaya",
    "gn:country_code":"CD",
    "gn:dem":501,
    "gn:feature_class":"P",
    "gn:feature_code":"PPL",
    "gn:name":"Yambaya",
    "gn:population":0,
    "gn:timezone":"Africa/Kinshasa",
    "iso:country":"CD",
    "wof:name":"Yambaya",
    "wof:placetype":"locality"
},
  "geometry": {"coordinates":[22.27243,2.83392],"type":"Point"}
}