{
  "type": "Feature",
  "properties": {
    "gn:admin1_code":"23.0",
    "gn:asciiname":"Mukuimbi",
    "gn:country_code":"CD",
    "gn:dem":848,
    "gn:feature_class":"P",
    "gn:feature_code":"PPL",
    "gn:name":"Mukuimbi",
    "gn:population":0,
    "gn:timezone":"Africa/Lubumbashi",
    "iso:country":"CD",
    "wof:name":"Mukuimbi",
    "wof:placetype":"locality"
},
  "geometry": {"coordinates":[22.42895,-6.85841],"type":"Point"}
}