{
  "type": "Feature",
  "properties": {
    "gn:admin1_code":"30.0",
    "gn:asciiname":"Badzoge",
    "gn:country_code":"CD",
    "gn:dem":455,
    "gn:feature_class":"P",
    "gn:feature_code":"PPL",
    "gn:name":"Badzoge",
    "gn:population":0,
    "gn:timezone":"Africa/Lubumbashi",
    "iso:country":"CD",
    "wof:name":"Badzoge",
    "wof:placetype":"locality"
},
  "geometry": {"coordinates":[25.26578,1.42043],"type":"Point"}
}