{
  "type": "Feature",
  "properties": {
    "gn:admin1_code":"15.0",
    "gn:asciiname":"Mwadi-Katoloka",
    "gn:country_code":"CD",
    "gn:dem":913,
    "gn:feature_class":"P",
    "gn:feature_code":"PPL",
    "gn:name":"Mwadi-Katoloka",
    "gn:population":0,
    "gn:timezone":"Africa/Lubumbashi",
    "iso:country":"CD",
    "wof:name":"Mwadi-Katoloka",
    "wof:placetype":"locality"
},
  "geometry": {"coordinates":[25.65601,-6.97937],"type":"Point"}
}