{
  "type": "Feature",
  "properties": {
    "gn:admin1_code":"26.0",
    "gn:asciiname":"Boroto Premiere",
    "gn:country_code":"CD",
    "gn:dem":474,
    "gn:feature_class":"P",
    "gn:feature_code":"PPL",
    "gn:name":"Boroto Premi\u00e8re",
    "gn:population":0,
    "gn:timezone":"Africa/Kinshasa",
    "iso:country":"CD",
    "name:und_x_variant":[
        "Boroto",
        "Boroto I",
        "Boroto Premi\u00e8re"
    ],
    "wof:name":"Boroto Premiere",
    "wof:placetype":"locality"
},
  "geometry": {"coordinates":[19.56613,4.9664],"type":"Point"}
}