{
  "type": "Feature",
  "properties": {
    "gn:admin1_code":"2.0",
    "gn:asciiname":"Bolakwafumba",
    "gn:country_code":"CD",
    "gn:dem":339,
    "gn:feature_class":"P",
    "gn:feature_code":"PPL",
    "gn:name":"Bolakwafumba",
    "gn:population":0,
    "gn:timezone":"Africa/Kinshasa",
    "iso:country":"CD",
    "wof:name":"Bolakwafumba",
    "wof:placetype":"locality"
},
  "geometry": {"coordinates":[19.93333,-0.38333],"type":"Point"}
}