{
  "type": "Feature",
  "properties": {
    "gn:admin1_code":"23.0",
    "gn:asciiname":"Mwena Tshuma",
    "gn:country_code":"CD",
    "gn:dem":947,
    "gn:feature_class":"P",
    "gn:feature_code":"PPL",
    "gn:name":"Mwena Tshuma",
    "gn:population":0,
    "gn:timezone":"Africa/Lubumbashi",
    "iso:country":"CD",
    "wof:name":"Mwena Tshuma",
    "wof:placetype":"locality"
},
  "geometry": {"coordinates":[22.92144,-7.24394],"type":"Point"}
}