{
  "type": "Feature",
  "properties": {
    "gn:admin1_code":"16.0",
    "gn:asciiname":"Mando",
    "gn:country_code":"CD",
    "gn:dem":789,
    "gn:feature_class":"P",
    "gn:feature_code":"PPL",
    "gn:name":"Mando",
    "gn:population":0,
    "gn:timezone":"Africa/Lubumbashi",
    "iso:country":"CD",
    "wof:name":"Mando",
    "wof:placetype":"locality"
},
  "geometry": {"coordinates":[27.92062,2.23247],"type":"Point"}
}