{
  "type": "Feature",
  "properties": {
    "gn:admin1_code":"8.0",
    "gn:asciiname":"Paza Premiere",
    "gn:country_code":"CD",
    "gn:dem":593,
    "gn:feature_class":"P",
    "gn:feature_code":"PPL",
    "gn:name":"Paza Premi\u00e8re",
    "gn:population":0,
    "gn:timezone":"Africa/Kinshasa",
    "iso:country":"CD",
    "wof:name":"Paza Premiere",
    "wof:placetype":"locality"
},
  "geometry": {"coordinates":[14.84382,-5.1989],"type":"Point"}
}