{
  "type": "Feature",
  "properties": {
    "gn:admin1_code":"18.0",
    "gn:asciiname":"Mwayila-Lubudi",
    "gn:country_code":"CD",
    "gn:dem":635,
    "gn:feature_class":"P",
    "gn:feature_code":"PPL",
    "gn:name":"Mwayila-Lubudi",
    "gn:population":0,
    "gn:timezone":"Africa/Lubumbashi",
    "iso:country":"CD",
    "wof:name":"Mwayila-Lubudi",
    "wof:placetype":"locality"
},
  "geometry": {"coordinates":[20.60642,-5.1335],"type":"Point"}
}