{
  "type": "Feature",
  "properties": {
    "gn:admin1_code":"21.0",
    "gn:asciiname":"Bitshi-Kabango",
    "gn:country_code":"CD",
    "gn:dem":739,
    "gn:feature_class":"P",
    "gn:feature_code":"PPL",
    "gn:name":"Bitshi-Kabango",
    "gn:population":0,
    "gn:timezone":"Africa/Lubumbashi",
    "iso:country":"CD",
    "name:und_x_variant":[
        "Bitshi"
    ],
    "wof:name":"Bitshi-Kabango",
    "wof:placetype":"locality"
},
  "geometry": {"coordinates":[24.85124,-6.03385],"type":"Point"}
}