{
  "type": "Feature",
  "properties": {
    "gn:admin1_code":"22.0",
    "gn:asciiname":"Mwene Kelela",
    "gn:country_code":"CD",
    "gn:dem":1075,
    "gn:feature_class":"P",
    "gn:feature_code":"PPL",
    "gn:name":"Mwene Kelela",
    "gn:population":0,
    "gn:timezone":"Africa/Lubumbashi",
    "iso:country":"CD",
    "wof:name":"Mwene Kelela",
    "wof:placetype":"locality"
},
  "geometry": {"coordinates":[23.23648,-9.49814],"type":"Point"}
}