{
  "type": "Feature",
  "properties": {
    "gn:admin1_code":"8.0",
    "gn:asciiname":"Kinfuka",
    "gn:country_code":"CD",
    "gn:dem":268,
    "gn:feature_class":"P",
    "gn:feature_code":"PPL",
    "gn:name":"Kinfuka",
    "gn:population":0,
    "gn:timezone":"Africa/Kinshasa",
    "iso:country":"CD",
    "wof:name":"Kinfuka",
    "wof:placetype":"locality"
},
  "geometry": {"coordinates":[13.62733,-5.19055],"type":"Point"}
}