{
  "type": "Feature",
  "properties": {
    "gn:admin1_code":"24.0",
    "gn:asciiname":"Wombali",
    "gn:country_code":"CD",
    "gn:dem":299,
    "gn:feature_class":"P",
    "gn:feature_code":"PPL",
    "gn:name":"Wombali",
    "gn:population":0,
    "gn:timezone":"Africa/Kinshasa",
    "iso:country":"CD",
    "wof:name":"Wombali",
    "wof:placetype":"locality"
},
  "geometry": {"coordinates":[17.36982,-3.27585],"type":"Point"}
}