{
  "type": "Feature",
  "properties": {
    "gn:admin1_code":"20.0",
    "gn:asciiname":"Bokumi",
    "gn:country_code":"CD",
    "gn:dem":365,
    "gn:feature_class":"P",
    "gn:feature_code":"PPL",
    "gn:name":"Bokumi",
    "gn:population":0,
    "gn:timezone":"Africa/Kinshasa",
    "iso:country":"CD",
    "name:und_x_variant":[
        "Kiabokumi",
        "Bokumi"
    ],
    "wof:name":"Bokumi",
    "wof:placetype":"locality"
},
  "geometry": {"coordinates":[17.84196,-3.59267],"type":"Point"}
}