{
  "type": "Feature",
  "properties": {
    "gn:admin1_code":"20.0",
    "gn:asciiname":"Kingulu",
    "gn:country_code":"CD",
    "gn:dem":562,
    "gn:feature_class":"P",
    "gn:feature_code":"PPL",
    "gn:name":"Kingulu",
    "gn:population":0,
    "gn:timezone":"Africa/Kinshasa",
    "iso:country":"CD",
    "wof:name":"Kingulu",
    "wof:placetype":"locality"
},
  "geometry": {"coordinates":[17.65255,-4.7614],"type":"Point"}
}