{
  "type": "Feature",
  "properties": {
    "gn:admin1_code":"13.0",
    "gn:asciiname":"Batayo",
    "gn:country_code":"CD",
    "gn:dem":484,
    "gn:feature_class":"P",
    "gn:feature_code":"PPL",
    "gn:name":"Batayo",
    "gn:population":0,
    "gn:timezone":"Africa/Lubumbashi",
    "iso:country":"CD",
    "wof:name":"Batayo",
    "wof:placetype":"locality"
},
  "geometry": {"coordinates":[23.06667,4.26667],"type":"Point"}
}