{
  "type": "Feature",
  "properties": {
    "gn:admin1_code":"8.0",
    "gn:asciiname":"Bulu",
    "gn:country_code":"CD",
    "gn:dem":5,
    "gn:feature_class":"P",
    "gn:feature_code":"PPL",
    "gn:name":"Bulu",
    "gn:population":0,
    "gn:timezone":"Africa/Kinshasa",
    "iso:country":"CD",
    "name:ceb_x_preferred":[
        "Bulu"
    ],
    "name:deu_x_preferred":[
        "Bulu"
    ],
    "name:fra_x_preferred":[
        "Bulu"
    ],
    "name:ind_x_preferred":[
        "Bulu"
    ],
    "name:ita_x_preferred":[
        "Bulu"
    ],
    "name:nld_x_preferred":[
        "Bulu"
    ],
    "name:srp_x_preferred":[
        "\u0411\u0443\u043b\u0443"
    ],
    "name:swe_x_preferred":[
        "Bulu"
    ],
    "wof:name":"Bulu",
    "wof:placetype":"locality"
},
  "geometry": {"coordinates":[12.8255,-5.93994],"type":"Point"}
}