{
  "type": "Feature",
  "properties": {
    "gn:admin1_code":"15.0",
    "gn:asciiname":"Kibiangulube",
    "gn:country_code":"CD",
    "gn:dem":847,
    "gn:feature_class":"P",
    "gn:feature_code":"PPL",
    "gn:name":"Kibiangulube",
    "gn:population":0,
    "gn:timezone":"Africa/Lubumbashi",
    "iso:country":"CD",
    "wof:name":"Kibiangulube",
    "wof:placetype":"locality"
},
  "geometry": {"coordinates":[25.86041,-8.78394],"type":"Point"}
}