{
  "type": "Feature",
  "properties": {
    "gn:admin1_code":"13.0",
    "gn:asciiname":"Bama",
    "gn:country_code":"CD",
    "gn:dem":662,
    "gn:feature_class":"P",
    "gn:feature_code":"PPL",
    "gn:name":"Bama",
    "gn:population":0,
    "gn:timezone":"Africa/Lubumbashi",
    "iso:country":"CD",
    "name:cat_x_preferred":[
        "Bama"
    ],
    "name:ceb_x_preferred":[
        "Bama"
    ],
    "name:deu_x_preferred":[
        "Bama"
    ],
    "name:fra_x_preferred":[
        "Bama"
    ],
    "name:glg_x_preferred":[
        "Bama"
    ],
    "name:ita_x_preferred":[
        "Bama"
    ],
    "name:nld_x_preferred":[
        "Bama"
    ],
    "name:nor_x_preferred":[
        "Bama"
    ],
    "name:swe_x_preferred":[
        "Bama"
    ],
    "wof:name":"Bama",
    "wof:placetype":"locality"
},
  "geometry": {"coordinates":[26.11667000000001,3.36667],"type":"Point"}
}