{
  "type": "Feature",
  "properties": {
    "gn:admin1_code":"11.0",
    "gn:asciiname":"Mugando",
    "gn:country_code":"CD",
    "gn:dem":1863,
    "gn:feature_class":"P",
    "gn:feature_code":"PPL",
    "gn:name":"Mugando",
    "gn:population":0,
    "gn:timezone":"Africa/Lubumbashi",
    "iso:country":"CD",
    "name:und_x_variant":[
        "Muganda",
        "Mugando"
    ],
    "wof:name":"Mugando",
    "wof:placetype":"locality"
},
  "geometry": {"coordinates":[29.08333,-1.46667],"type":"Point"}
}