{
  "type": "Feature",
  "properties": {
    "gn:admin1_code":"22.0",
    "gn:asciiname":"Satela",
    "gn:country_code":"CD",
    "gn:dem":1083,
    "gn:feature_class":"P",
    "gn:feature_code":"PPL",
    "gn:name":"Satela",
    "gn:population":0,
    "gn:timezone":"Africa/Lubumbashi",
    "iso:country":"CD",
    "wof:name":"Satela",
    "wof:placetype":"locality"
},
  "geometry": {"coordinates":[22.03252,-9.64962],"type":"Point"}
}