{
  "type": "Feature",
  "properties": {
    "gn:admin1_code":"23.0",
    "gn:asciiname":"Mulumba-Nkusu",
    "gn:country_code":"CD",
    "gn:dem":638,
    "gn:feature_class":"P",
    "gn:feature_code":"PPL",
    "gn:name":"Mulumba-Nkusu",
    "gn:population":0,
    "gn:timezone":"Africa/Lubumbashi",
    "iso:country":"CD",
    "wof:name":"Mulumba-Nkusu",
    "wof:placetype":"locality"
},
  "geometry": {"coordinates":[22.4609,-5.70715],"type":"Point"}
}