{
  "type": "Feature",
  "properties": {
    "gn:admin1_code":"20.0",
    "gn:asciiname":"Kimboli",
    "gn:country_code":"CD",
    "gn:dem":752,
    "gn:feature_class":"P",
    "gn:feature_code":"PPL",
    "gn:name":"Kimboli",
    "gn:population":0,
    "gn:timezone":"Africa/Kinshasa",
    "iso:country":"CD",
    "wof:name":"Kimboli",
    "wof:placetype":"locality"
},
  "geometry": {"coordinates":[17.68465,-5.39411],"type":"Point"}
}