{
  "type": "Feature",
  "properties": {
    "gn:admin1_code":"24.0",
    "gn:asciiname":"Sansan",
    "gn:country_code":"CD",
    "gn:dem":347,
    "gn:feature_class":"P",
    "gn:feature_code":"PPL",
    "gn:name":"Sansan",
    "gn:population":0,
    "gn:timezone":"Africa/Kinshasa",
    "iso:country":"CD",
    "wof:name":"Sansan",
    "wof:placetype":"locality"
},
  "geometry": {"coordinates":[18.42631,-3.49483],"type":"Point"}
}