{
  "type": "Feature",
  "properties": {
    "gn:admin1_code":"19.0",
    "gn:asciiname":"Mvula-Kandi",
    "gn:country_code":"CD",
    "gn:dem":847,
    "gn:feature_class":"P",
    "gn:feature_code":"PPL",
    "gn:name":"Mvula-Kandi",
    "gn:population":0,
    "gn:timezone":"Africa/Kinshasa",
    "iso:country":"CD",
    "wof:name":"Mvula-Kandi",
    "wof:placetype":"locality"
},
  "geometry": {"coordinates":[17.69676,-6.01681],"type":"Point"}
}