{
  "type": "Feature",
  "properties": {
    "gn:admin1_code":"23.0",
    "gn:asciiname":"Kapanku",
    "gn:country_code":"CD",
    "gn:dem":611,
    "gn:feature_class":"P",
    "gn:feature_code":"PPL",
    "gn:name":"Kapanku",
    "gn:population":0,
    "gn:timezone":"Africa/Lubumbashi",
    "iso:country":"CD",
    "wof:name":"Kapanku",
    "wof:placetype":"locality"
},
  "geometry": {"coordinates":[22.43947,-5.58212],"type":"Point"}
}