{
  "type": "Feature",
  "properties": {
    "gn:admin1_code":"10.0",
    "gn:asciiname":"Mesaraba",
    "gn:country_code":"CD",
    "gn:dem":601,
    "gn:feature_class":"P",
    "gn:feature_code":"PPL",
    "gn:name":"Mesaraba",
    "gn:population":0,
    "gn:timezone":"Africa/Lubumbashi",
    "iso:country":"CD",
    "name:und_x_variant":[
        "Mesarabe",
        "Messaraba",
        "Mesaraba",
        "Massaraba"
    ],
    "wof:name":"Mesaraba",
    "wof:placetype":"locality"
},
  "geometry": {"coordinates":[26.82669000000001,-2.54163],"type":"Point"}
}