{
  "type": "Feature",
  "properties": {
    "gn:admin1_code":"12.0",
    "gn:asciiname":"Nyagezi",
    "gn:country_code":"CD",
    "gn:dem":1570,
    "gn:feature_class":"P",
    "gn:feature_code":"PPL",
    "gn:name":"Nyagezi",
    "gn:population":0,
    "gn:timezone":"Africa/Lubumbashi",
    "iso:country":"CD",
    "name:und_x_variant":[
        "Nya-Ghezi",
        "Nya Ngezi",
        "Nyagezi"
    ],
    "wof:name":"Nyagezi",
    "wof:placetype":"locality"
},
  "geometry": {"coordinates":[28.87998,-2.68649],"type":"Point"}
}