{
  "type": "Feature",
  "properties": {
    "gn:admin1_code":"31.0",
    "gn:asciiname":"Nkuse",
    "gn:country_code":"CD",
    "gn:dem":385,
    "gn:feature_class":"P",
    "gn:feature_code":"PPL",
    "gn:name":"Nkuse",
    "gn:population":0,
    "gn:timezone":"Africa/Kinshasa",
    "iso:country":"CD",
    "wof:name":"Nkuse",
    "wof:placetype":"locality"
},
  "geometry": {"coordinates":[21.53333,0.25],"type":"Point"}
}