{
  "type": "Feature",
  "properties": {
    "gn:admin1_code":"6.0",
    "gn:asciiname":"Kinzolo",
    "gn:country_code":"CD",
    "gn:dem":434,
    "gn:feature_class":"P",
    "gn:feature_code":"PPL",
    "gn:name":"Kinzolo",
    "gn:population":0,
    "gn:timezone":"Africa/Kinshasa",
    "iso:country":"CD",
    "wof:name":"Kinzolo",
    "wof:placetype":"locality"
},
  "geometry": {"coordinates":[15.71167,-4.84444],"type":"Point"}
}