{
  "type": "Feature",
  "properties": {
    "gn:admin1_code":"19.0",
    "gn:asciiname":"Munikwengo",
    "gn:country_code":"CD",
    "gn:dem":1053,
    "gn:feature_class":"P",
    "gn:feature_code":"PPL",
    "gn:name":"Munikwengo",
    "gn:population":0,
    "gn:timezone":"Africa/Kinshasa",
    "iso:country":"CD",
    "wof:name":"Munikwengo",
    "wof:placetype":"locality"
},
  "geometry": {"coordinates":[18.67982,-7.55479],"type":"Point"}
}