{
  "type": "Feature",
  "properties": {
    "gn:admin1_code":"4.0",
    "gn:asciiname":"Bakwa-Mpuka",
    "gn:country_code":"CD",
    "gn:dem":742,
    "gn:feature_class":"P",
    "gn:feature_code":"PPL",
    "gn:name":"Bakwa-Mpuka",
    "gn:population":0,
    "gn:timezone":"Africa/Lubumbashi",
    "iso:country":"CD",
    "wof:name":"Bakwa-Mpuka",
    "wof:placetype":"locality"
},
  "geometry": {"coordinates":[23.47636,-6.11168],"type":"Point"}
}