{
  "type": "Feature",
  "properties": {
    "gn:admin1_code":"26.0",
    "gn:asciiname":"Sangba",
    "gn:country_code":"CD",
    "gn:dem":454,
    "gn:feature_class":"P",
    "gn:feature_code":"PPL",
    "gn:name":"Sangba",
    "gn:population":0,
    "gn:timezone":"Africa/Kinshasa",
    "iso:country":"CD",
    "name:msa_x_preferred":[
        "Sangba"
    ],
    "wof:name":"Sangba",
    "wof:placetype":"locality"
},
  "geometry": {"coordinates":[21.61125,4.18209],"type":"Point"}
}