{
  "type": "Feature",
  "properties": {
    "gn:admin1_code":"20.0",
    "gn:asciiname":"Luano",
    "gn:country_code":"CD",
    "gn:dem":476,
    "gn:feature_class":"P",
    "gn:feature_code":"PPL",
    "gn:name":"Luano",
    "gn:population":0,
    "gn:timezone":"Africa/Kinshasa",
    "iso:country":"CD",
    "wof:name":"Luano",
    "wof:placetype":"locality"
},
  "geometry": {"coordinates":[17.64903,-4.14326],"type":"Point"}
}