{
  "type": "Feature",
  "properties": {
    "gn:admin1_code":"11.0",
    "gn:asciiname":"Berida",
    "gn:country_code":"CD",
    "gn:dem":1492,
    "gn:feature_class":"P",
    "gn:feature_code":"PPL",
    "gn:name":"Berida",
    "gn:population":0,
    "gn:timezone":"Africa/Lubumbashi",
    "iso:country":"CD",
    "wof:name":"Berida",
    "wof:placetype":"locality"
},
  "geometry": {"coordinates":[29.10312,0.02564],"type":"Point"}
}