{
  "type": "Feature",
  "properties": {
    "gn:admin1_code":"22.0",
    "gn:asciiname":"Ngwadi",
    "gn:country_code":"CD",
    "gn:dem":931,
    "gn:feature_class":"P",
    "gn:feature_code":"PPL",
    "gn:name":"Ngwadi",
    "gn:population":0,
    "gn:timezone":"Africa/Lubumbashi",
    "iso:country":"CD",
    "wof:name":"Ngwadi",
    "wof:placetype":"locality"
},
  "geometry": {"coordinates":[23.18275,-8.22544],"type":"Point"}
}