{
  "type": "Feature",
  "properties": {
    "gn:admin1_code":"22.0",
    "gn:asciiname":"Tshikamba",
    "gn:country_code":"CD",
    "gn:dem":1168,
    "gn:feature_class":"P",
    "gn:feature_code":"PPL",
    "gn:name":"Tshikamba",
    "gn:population":0,
    "gn:timezone":"Africa/Lubumbashi",
    "iso:country":"CD",
    "wof:name":"Tshikamba",
    "wof:placetype":"locality"
},
  "geometry": {"coordinates":[23.93796,-10.30601],"type":"Point"}
}