{
  "type": "Feature",
  "properties": {
    "gn:admin1_code":"20.0",
    "gn:asciiname":"Fayala",
    "gn:country_code":"CD",
    "gn:dem":341,
    "gn:feature_class":"P",
    "gn:feature_code":"PPL",
    "gn:name":"Fayala",
    "gn:population":0,
    "gn:timezone":"Africa/Kinshasa",
    "iso:country":"CD",
    "wof:name":"Fayala",
    "wof:placetype":"locality"
},
  "geometry": {"coordinates":[17.18481,-3.96507],"type":"Point"}
}