{
  "type": "Feature",
  "properties": {
    "gn:admin1_code":"31.0",
    "gn:asciiname":"Yaonga",
    "gn:country_code":"CD",
    "gn:dem":431,
    "gn:feature_class":"P",
    "gn:feature_code":"PPL",
    "gn:name":"Yaonga",
    "gn:population":0,
    "gn:timezone":"Africa/Kinshasa",
    "iso:country":"CD",
    "wof:name":"Yaonga",
    "wof:placetype":"locality"
},
  "geometry": {"coordinates":[22.45,-1.23333],"type":"Point"}
}