{
  "type": "Feature",
  "properties": {
    "gn:admin1_code":"10.0",
    "gn:asciiname":"Babango",
    "gn:country_code":"CD",
    "gn:dem":544,
    "gn:feature_class":"P",
    "gn:feature_code":"PPL",
    "gn:name":"Babango",
    "gn:population":0,
    "gn:timezone":"Africa/Lubumbashi",
    "iso:country":"CD",
    "wof:name":"Babango",
    "wof:placetype":"locality"
},
  "geometry": {"coordinates":[26.61667000000001,-0.68333],"type":"Point"}
}