{
  "type": "Feature",
  "properties": {
    "gn:admin1_code":"11.0",
    "gn:asciiname":"Kiangitsi",
    "gn:country_code":"CD",
    "gn:dem":1814,
    "gn:feature_class":"P",
    "gn:feature_code":"PPL",
    "gn:name":"Kiangitsi",
    "gn:population":0,
    "gn:timezone":"Africa/Lubumbashi",
    "iso:country":"CD",
    "name:und_x_variant":[
        "Kiangitshi",
        "Kiangitsi"
    ],
    "wof:name":"Kiangitsi",
    "wof:placetype":"locality"
},
  "geometry": {"coordinates":[28.60972000000001,-1.525],"type":"Point"}
}