{
  "type": "Feature",
  "properties": {
    "gn:admin1_code":"8.0",
    "gn:asciiname":"Mbumbi",
    "gn:country_code":"CD",
    "gn:dem":582,
    "gn:feature_class":"P",
    "gn:feature_code":"PPL",
    "gn:name":"Mbumbi",
    "gn:population":0,
    "gn:timezone":"Africa/Kinshasa",
    "iso:country":"CD",
    "wof:name":"Mbumbi",
    "wof:placetype":"locality"
},
  "geometry": {"coordinates":[14.90216,-5.05382],"type":"Point"}
}