{
  "type": "Feature",
  "properties": {
    "gn:admin1_code":"17.0",
    "gn:asciiname":"Sumbusu",
    "gn:country_code":"CD",
    "gn:dem":1833,
    "gn:feature_class":"P",
    "gn:feature_code":"PPL",
    "gn:name":"Sumbusu",
    "gn:population":0,
    "gn:timezone":"Africa/Lubumbashi",
    "iso:country":"CD",
    "wof:name":"Sumbusu",
    "wof:placetype":"locality"
},
  "geometry": {"coordinates":[30.69678,1.95625],"type":"Point"}
}