{
  "type": "Feature",
  "properties": {
    "gn:admin1_code":"17.0",
    "gn:asciiname":"Abakwasimbo",
    "gn:country_code":"CD",
    "gn:dem":1053,
    "gn:feature_class":"P",
    "gn:feature_code":"PPL",
    "gn:name":"Abakwasimbo",
    "gn:population":0,
    "gn:timezone":"Africa/Lubumbashi",
    "iso:country":"CD",
    "name:azb_x_preferred":[
        "\u0622\u0628\u0627\u06a9\u0648\u0627\u0633\u06cc\u0645\u0628\u0648"
    ],
    "name:fas_x_preferred":[
        "\u0622\u0628\u0627\u06a9\u0648\u0627\u0633\u06cc\u0645\u0628\u0648"
    ],
    "name:ita_x_preferred":[
        "Abakwasimbo"
    ],
    "name:scn_x_preferred":[
        "Abakwasimbo"
    ],
    "name:und_x_variant":[
        "Abokwasimbe",
        "Abakuasimbo"
    ],
    "wof:name":"Abakwasimbo",
    "wof:placetype":"locality"
},
  "geometry": {"coordinates":[28.73145,0.58419],"type":"Point"}
}