{
  "type": "Feature",
  "properties": {
    "gn:admin1_code":"11.0",
    "gn:asciiname":"Bikara",
    "gn:country_code":"CD",
    "gn:dem":2170,
    "gn:feature_class":"P",
    "gn:feature_code":"PPL",
    "gn:name":"Bikara",
    "gn:population":0,
    "gn:timezone":"Africa/Lubumbashi",
    "iso:country":"CD",
    "wof:name":"Bikara",
    "wof:placetype":"locality"
},
  "geometry": {"coordinates":[29.20149,-0.25078],"type":"Point"}
}