{
  "type": "Feature",
  "properties": {
    "gn:admin1_code":"24.0",
    "gn:asciiname":"Ingimi",
    "gn:country_code":"CD",
    "gn:dem":609,
    "gn:feature_class":"P",
    "gn:feature_code":"PPL",
    "gn:name":"Ingimi",
    "gn:population":0,
    "gn:timezone":"Africa/Kinshasa",
    "iso:country":"CD",
    "wof:name":"Ingimi",
    "wof:placetype":"locality"
},
  "geometry": {"coordinates":[16.28333,-3.96667],"type":"Point"}
}