{
  "type": "Feature",
  "properties": {
    "gn:admin1_code":"20.0",
    "gn:asciiname":"Kikangi",
    "gn:country_code":"CD",
    "gn:dem":749,
    "gn:feature_class":"P",
    "gn:feature_code":"PPL",
    "gn:name":"Kikangi",
    "gn:population":0,
    "gn:timezone":"Africa/Kinshasa",
    "iso:country":"CD",
    "wof:name":"Kikangi",
    "wof:placetype":"locality"
},
  "geometry": {"coordinates":[18.94076,-5.44129],"type":"Point"}
}