{
  "type": "Feature",
  "properties": {
    "gn:admin1_code":"20.0",
    "gn:asciiname":"Mubolo",
    "gn:country_code":"CD",
    "gn:dem":462,
    "gn:feature_class":"P",
    "gn:feature_code":"PPL",
    "gn:name":"Mubolo",
    "gn:population":0,
    "gn:timezone":"Africa/Kinshasa",
    "iso:country":"CD",
    "wof:name":"Mubolo",
    "wof:placetype":"locality"
},
  "geometry": {"coordinates":[18.79825,-4.35717],"type":"Point"}
}