{
  "type": "Feature",
  "properties": {
    "gn:admin1_code":"11.0",
    "gn:asciiname":"Kabaya",
    "gn:country_code":"CD",
    "gn:dem":1609,
    "gn:feature_class":"P",
    "gn:feature_code":"PPL",
    "gn:name":"Kabaya",
    "gn:population":0,
    "gn:timezone":"Africa/Lubumbashi",
    "iso:country":"CD",
    "name:jpn_x_preferred":[
        "\u30ab\u30d0\u30e4\u98df\u54c1"
    ],
    "name:kor_x_preferred":[
        "\uac00\ubc14\uc57c \uc2dd\ud488"
    ],
    "wof:name":"Kabaya",
    "wof:placetype":"locality"
},
  "geometry": {"coordinates":[29.41249,-1.33327],"type":"Point"}
}