{
  "type": "Feature",
  "properties": {
    "gn:admin1_code":"22.0",
    "gn:asciiname":"Kafakumba",
    "gn:country_code":"CD",
    "gn:dem":986,
    "gn:feature_class":"P",
    "gn:feature_code":"PPL",
    "gn:name":"Kafakumba",
    "gn:population":0,
    "gn:timezone":"Africa/Lubumbashi",
    "iso:country":"CD",
    "wof:name":"Kafakumba",
    "wof:placetype":"locality"
},
  "geometry": {"coordinates":[23.75887,-9.67651],"type":"Point"}
}