{
  "type": "Feature",
  "properties": {
    "gn:admin1_code":"27.0",
    "gn:asciiname":"Lungala",
    "gn:country_code":"CD",
    "gn:dem":540,
    "gn:feature_class":"P",
    "gn:feature_code":"PPL",
    "gn:name":"Lungala",
    "gn:population":0,
    "gn:timezone":"Africa/Lubumbashi",
    "iso:country":"CD",
    "wof:name":"Lungala",
    "wof:placetype":"locality"
},
  "geometry": {"coordinates":[24.23333,-2.78333],"type":"Point"}
}