{
  "type": "Feature",
  "properties": {
    "gn:admin1_code":"26.0",
    "gn:asciiname":"Mogbonga",
    "gn:country_code":"CD",
    "gn:dem":403,
    "gn:feature_class":"P",
    "gn:feature_code":"PPL",
    "gn:name":"Mogbonga",
    "gn:population":0,
    "gn:timezone":"Africa/Kinshasa",
    "iso:country":"CD",
    "wof:name":"Mogbonga",
    "wof:placetype":"locality"
},
  "geometry": {"coordinates":[21.62127000000001,2.96316],"type":"Point"}
}