{
  "type": "Feature",
  "properties": {
    "gn:admin1_code":"23.0",
    "gn:asciiname":"Kabalu",
    "gn:country_code":"CD",
    "gn:dem":803,
    "gn:feature_class":"P",
    "gn:feature_code":"PPL",
    "gn:name":"Kabalu",
    "gn:population":0,
    "gn:timezone":"Africa/Lubumbashi",
    "iso:country":"CD",
    "wof:name":"Kabalu",
    "wof:placetype":"locality"
},
  "geometry": {"coordinates":[22.92586,-6.19079],"type":"Point"}
}