{
  "type": "Feature",
  "properties": {
    "gn:admin1_code":"27.0",
    "gn:asciiname":"Malaba",
    "gn:country_code":"CD",
    "gn:dem":530,
    "gn:feature_class":"P",
    "gn:feature_code":"PPL",
    "gn:name":"Malaba",
    "gn:population":0,
    "gn:timezone":"Africa/Lubumbashi",
    "iso:country":"CD",
    "name:ceb_x_preferred":[
        "Malaba"
    ],
    "name:deu_x_preferred":[
        "Malaba"
    ],
    "name:fra_x_preferred":[
        "Malaba"
    ],
    "name:jpn_x_preferred":[
        "\u30de\u30e9\u30d0"
    ],
    "name:nds_x_preferred":[
        "Malaba"
    ],
    "name:swe_x_preferred":[
        "Malaba"
    ],
    "wof:name":"Malaba",
    "wof:placetype":"locality"
},
  "geometry": {"coordinates":[23.94068,-4.80673],"type":"Point"}
}