{
  "type": "Feature",
  "properties": {
    "gn:admin1_code":"23.0",
    "gn:asciiname":"Tshipamba",
    "gn:country_code":"CD",
    "gn:dem":843,
    "gn:feature_class":"P",
    "gn:feature_code":"PPL",
    "gn:name":"Tshipamba",
    "gn:population":0,
    "gn:timezone":"Africa/Lubumbashi",
    "iso:country":"CD",
    "wof:name":"Tshipamba",
    "wof:placetype":"locality"
},
  "geometry": {"coordinates":[22.88679,-6.40225],"type":"Point"}
}