{
  "type": "Feature",
  "properties": {
    "gn:admin1_code":"13.0",
    "gn:asciiname":"Akangai",
    "gn:country_code":"CD",
    "gn:dem":425,
    "gn:feature_class":"P",
    "gn:feature_code":"PPL",
    "gn:name":"Akangai",
    "gn:population":0,
    "gn:timezone":"Africa/Lubumbashi",
    "iso:country":"CD",
    "wof:name":"Akangai",
    "wof:placetype":"locality"
},
  "geometry": {"coordinates":[23.90286,3.43192],"type":"Point"}
}