{
  "type": "Feature",
  "properties": {
    "gn:admin1_code":"2.0",
    "gn:asciiname":"Bolemba",
    "gn:country_code":"CD",
    "gn:dem":330,
    "gn:feature_class":"P",
    "gn:feature_code":"PPL",
    "gn:name":"Bolemba",
    "gn:population":0,
    "gn:timezone":"Africa/Kinshasa",
    "iso:country":"CD",
    "name:und_x_variant":[
        "Bolembe",
        "Bolemba"
    ],
    "wof:name":"Bolemba",
    "wof:placetype":"locality"
},
  "geometry": {"coordinates":[18.29628,1.37239],"type":"Point"}
}