{
  "type": "Feature",
  "properties": {
    "gn:admin1_code":"8.0",
    "gn:asciiname":"Zaunti",
    "gn:country_code":"CD",
    "gn:dem":518,
    "gn:feature_class":"P",
    "gn:feature_code":"PPL",
    "gn:name":"Zaunti",
    "gn:population":0,
    "gn:timezone":"Africa/Kinshasa",
    "iso:country":"CD",
    "wof:name":"Zaunti",
    "wof:placetype":"locality"
},
  "geometry": {"coordinates":[13.51132,-5.01822],"type":"Point"}
}