{
  "type": "Feature",
  "properties": {
    "gn:admin1_code":"27.0",
    "gn:asciiname":"Elenge",
    "gn:country_code":"CD",
    "gn:dem":605,
    "gn:feature_class":"P",
    "gn:feature_code":"PPL",
    "gn:name":"Elenge",
    "gn:population":0,
    "gn:timezone":"Africa/Lubumbashi",
    "iso:country":"CD",
    "wof:name":"Elenge",
    "wof:placetype":"locality"
},
  "geometry": {"coordinates":[23.99209,-3.45582],"type":"Point"}
}