{
  "type": "Feature",
  "properties": {
    "gn:admin1_code":"22.0",
    "gn:asciiname":"Fwalukinda",
    "gn:country_code":"CD",
    "gn:dem":936,
    "gn:feature_class":"P",
    "gn:feature_code":"PPL",
    "gn:name":"Fwalukinda",
    "gn:population":0,
    "gn:timezone":"Africa/Lubumbashi",
    "iso:country":"CD",
    "wof:name":"Fwalukinda",
    "wof:placetype":"locality"
},
  "geometry": {"coordinates":[23.21771,-8.20308],"type":"Point"}
}