{
  "type": "Feature",
  "properties": {
    "gn:admin1_code":"24.0",
    "gn:asciiname":"Nkala",
    "gn:country_code":"CD",
    "gn:dem":294,
    "gn:feature_class":"P",
    "gn:feature_code":"PPL",
    "gn:name":"Nkala",
    "gn:population":0,
    "gn:timezone":"Africa/Kinshasa",
    "iso:country":"CD",
    "name:und_x_variant":[
        "Kala",
        "Nkala"
    ],
    "wof:name":"Nkala",
    "wof:placetype":"locality"
},
  "geometry": {"coordinates":[18.38333,-2.75],"type":"Point"}
}