{
  "type": "Feature",
  "properties": {
    "gn:admin1_code":"10.0",
    "gn:asciiname":"Luhembwe",
    "gn:country_code":"CD",
    "gn:dem":544,
    "gn:feature_class":"P",
    "gn:feature_code":"PPL",
    "gn:name":"Luhembwe",
    "gn:population":0,
    "gn:timezone":"Africa/Lubumbashi",
    "iso:country":"CD",
    "name:und_x_variant":[
        "Lukembwe",
        "Luhembwe"
    ],
    "wof:name":"Luhembwe",
    "wof:placetype":"locality"
},
  "geometry": {"coordinates":[25.92507,-4.44876],"type":"Point"}
}