{
  "type": "Feature",
  "properties": {
    "gn:admin1_code":"19.0",
    "gn:asciiname":"Kikongo-Kalala",
    "gn:country_code":"CD",
    "gn:dem":452,
    "gn:feature_class":"P",
    "gn:feature_code":"PPL",
    "gn:name":"Kikongo-Kalala",
    "gn:population":0,
    "gn:timezone":"Africa/Luanda",
    "iso:country":"CD",
    "wof:name":"Kikongo-Kalala",
    "wof:placetype":"locality"
},
  "geometry": {"coordinates":[16.81533,-6.7983],"type":"Point"}
}