{
  "type": "Feature",
  "properties": {
    "gn:admin1_code":"21.0",
    "gn:asciiname":"Gabo",
    "gn:country_code":"CD",
    "gn:dem":834,
    "gn:feature_class":"P",
    "gn:feature_code":"PPL",
    "gn:name":"Gabo",
    "gn:population":0,
    "gn:timezone":"Africa/Lubumbashi",
    "iso:country":"CD",
    "name:ceb_x_preferred":[
        "Gabo"
    ],
    "name:deu_x_preferred":[
        "Gabo"
    ],
    "name:fra_x_preferred":[
        "Gabo"
    ],
    "name:por_x_preferred":[
        "Gabo"
    ],
    "name:swe_x_preferred":[
        "Gabo"
    ],
    "wof:name":"Gabo",
    "wof:placetype":"locality"
},
  "geometry": {"coordinates":[24.65893,-6.38826],"type":"Point"}
}