{
  "type": "Feature",
  "properties": {
    "gn:admin1_code":"19.0",
    "gn:asciiname":"Masingi",
    "gn:country_code":"CD",
    "gn:dem":643,
    "gn:feature_class":"P",
    "gn:feature_code":"PPL",
    "gn:name":"Masingi",
    "gn:population":0,
    "gn:timezone":"Africa/Kinshasa",
    "iso:country":"CD",
    "wof:name":"Masingi",
    "wof:placetype":"locality"
},
  "geometry": {"coordinates":[17.06158,-5.0583],"type":"Point"}
}