{
  "type": "Feature",
  "properties": {
    "gn:admin1_code":"13.0",
    "gn:asciiname":"Nambakai",
    "gn:country_code":"CD",
    "gn:dem":702,
    "gn:feature_class":"P",
    "gn:feature_code":"PPL",
    "gn:name":"Nambakai",
    "gn:population":0,
    "gn:timezone":"Africa/Lubumbashi",
    "iso:country":"CD",
    "wof:name":"Nambakai",
    "wof:placetype":"locality"
},
  "geometry": {"coordinates":[27.13272000000001,4.21708],"type":"Point"}
}