{
  "type": "Feature",
  "properties": {
    "gn:admin1_code":"8.0",
    "gn:asciiname":"Bumba",
    "gn:country_code":"CD",
    "gn:dem":716,
    "gn:feature_class":"P",
    "gn:feature_code":"PPL",
    "gn:name":"Bumba",
    "gn:population":0,
    "gn:timezone":"Africa/Kinshasa",
    "iso:country":"CD",
    "name:ceb_x_preferred":[
        "Bumba"
    ],
    "name:deu_x_preferred":[
        "Bumba"
    ],
    "name:fin_x_preferred":[
        "Bumba"
    ],
    "name:fra_x_preferred":[
        "Bumba"
    ],
    "name:ind_x_preferred":[
        "Bumba"
    ],
    "name:nld_x_preferred":[
        "Bumba"
    ],
    "name:ron_x_preferred":[
        "Bumba"
    ],
    "name:swe_x_preferred":[
        "Bumba"
    ],
    "name:ukr_x_preferred":[
        "\u0411\u0443\u043c\u0431\u0430"
    ],
    "wof:name":"Bumba",
    "wof:placetype":"locality"
},
  "geometry": {"coordinates":[13.70248,-4.92225],"type":"Point"}
}