{
  "type": "Feature",
  "properties": {
    "gn:admin1_code":"8.0",
    "gn:asciiname":"Bumba",
    "gn:country_code":"CD",
    "gn:dem":716,
    "gn:feature_class":"P",
    "gn:feature_code":"PPL",
    "gn:name":"Bumba",
    "gn:population":0,
    "gn:timezone":"Africa/Kinshasa",
    "iso:country":"CD",
    "wof:name":"Bumba",
    "wof:placetype":"locality"
},
  "geometry": {"coordinates":[13.70248,-4.92225],"type":"Point"}
}