{
  "type": "Feature",
  "properties": {
    "gn:admin1_code":"26.0",
    "gn:asciiname":"Karawa",
    "gn:country_code":"CD",
    "gn:dem":397,
    "gn:feature_class":"P",
    "gn:feature_code":"PPL",
    "gn:name":"Karawa",
    "gn:population":0,
    "gn:timezone":"Africa/Kinshasa",
    "iso:country":"CD",
    "wof:name":"Karawa",
    "wof:placetype":"locality"
},
  "geometry": {"coordinates":[20.30103,3.33219],"type":"Point"}
}