{
  "type": "Feature",
  "properties": {
    "gn:admin1_code":"14.0",
    "gn:asciiname":"Pande",
    "gn:country_code":"CD",
    "gn:dem":1136,
    "gn:feature_class":"P",
    "gn:feature_code":"PPL",
    "gn:name":"Pande",
    "gn:population":0,
    "gn:timezone":"Africa/Lubumbashi",
    "iso:country":"CD",
    "name:und_x_variant":[
        "Panda",
        "Pande"
    ],
    "wof:name":"Pande",
    "wof:placetype":"locality"
},
  "geometry": {"coordinates":[26.83333,-10.61667],"type":"Point"}
}