{
  "type": "Feature",
  "properties": {
    "gn:admin1_code":"8.0",
    "gn:asciiname":"Kimamba",
    "gn:country_code":"CD",
    "gn:dem":559,
    "gn:feature_class":"P",
    "gn:feature_code":"PPL",
    "gn:name":"Kimamba",
    "gn:population":0,
    "gn:timezone":"Africa/Kinshasa",
    "iso:country":"CD",
    "wof:name":"Kimamba",
    "wof:placetype":"locality"
},
  "geometry": {"coordinates":[13.97056,-4.70256],"type":"Point"}
}