{
  "type": "Feature",
  "properties": {
    "gn:admin1_code":"24.0",
    "gn:asciiname":"Izono Deuxieme",
    "gn:country_code":"CD",
    "gn:dem":309,
    "gn:feature_class":"P",
    "gn:feature_code":"PPL",
    "gn:name":"Izono Deuxi\u00e8me",
    "gn:population":0,
    "gn:timezone":"Africa/Kinshasa",
    "iso:country":"CD",
    "wof:name":"Izono Deuxieme",
    "wof:placetype":"locality"
},
  "geometry": {"coordinates":[17.5623,-2.59845],"type":"Point"}
}