{
  "type": "Feature",
  "properties": {
    "gn:admin1_code":"24.0",
    "gn:asciiname":"Izono Quatrieme",
    "gn:country_code":"CD",
    "gn:dem":319,
    "gn:feature_class":"P",
    "gn:feature_code":"PPL",
    "gn:name":"Izono Quatri\u00e8me",
    "gn:population":0,
    "gn:timezone":"Africa/Kinshasa",
    "iso:country":"CD",
    "wof:name":"Izono Quatrieme",
    "wof:placetype":"locality"
},
  "geometry": {"coordinates":[17.55883,-2.6082],"type":"Point"}
}