{
  "type": "Feature",
  "properties": {
    "gn:admin1_code":"21.0",
    "gn:asciiname":"Kapuekela",
    "gn:country_code":"CD",
    "gn:dem":975,
    "gn:feature_class":"P",
    "gn:feature_code":"PPL",
    "gn:name":"Kapuekela",
    "gn:population":0,
    "gn:timezone":"Africa/Lubumbashi",
    "iso:country":"CD",
    "wof:name":"Kapuekela",
    "wof:placetype":"locality"
},
  "geometry": {"coordinates":[23.39091,-7.59562],"type":"Point"}
}