{
  "type": "Feature",
  "properties": {
    "gn:admin1_code":"2.0",
    "gn:asciiname":"Mpanza",
    "gn:country_code":"CD",
    "gn:dem":329,
    "gn:feature_class":"P",
    "gn:feature_code":"PPL",
    "gn:name":"Mpanza",
    "gn:population":0,
    "gn:timezone":"Africa/Kinshasa",
    "iso:country":"CD",
    "wof:name":"Mpanza",
    "wof:placetype":"locality"
},
  "geometry": {"coordinates":[18.26435,1.2788],"type":"Point"}
}