{
  "type": "Feature",
  "properties": {
    "gn:admin1_code":"23.0",
    "gn:asciiname":"Binzembu",
    "gn:country_code":"CD",
    "gn:dem":814,
    "gn:feature_class":"P",
    "gn:feature_code":"PPL",
    "gn:name":"Binzembu",
    "gn:population":0,
    "gn:timezone":"Africa/Lubumbashi",
    "iso:country":"CD",
    "wof:name":"Binzembu",
    "wof:placetype":"locality"
},
  "geometry": {"coordinates":[21.87226,-7.32142],"type":"Point"}
}