{
  "type": "Feature",
  "properties": {
    "gn:admin1_code":"26.0",
    "gn:asciiname":"Bongbwoin",
    "gn:country_code":"CD",
    "gn:dem":372,
    "gn:feature_class":"P",
    "gn:feature_code":"PPL",
    "gn:name":"Bongbwoin",
    "gn:population":0,
    "gn:timezone":"Africa/Kinshasa",
    "iso:country":"CD",
    "wof:name":"Bongbwoin",
    "wof:placetype":"locality"
},
  "geometry": {"coordinates":[21.12793,3.42393],"type":"Point"}
}