{
  "type": "Feature",
  "properties": {
    "gn:admin1_code":"20.0",
    "gn:asciiname":"Bele-Buluem",
    "gn:country_code":"CD",
    "gn:dem":486,
    "gn:feature_class":"P",
    "gn:feature_code":"PPL",
    "gn:name":"Bele-Buluem",
    "gn:population":0,
    "gn:timezone":"Africa/Kinshasa",
    "iso:country":"CD",
    "wof:name":"Bele-Buluem",
    "wof:placetype":"locality"
},
  "geometry": {"coordinates":[19.33333,-4.61667],"type":"Point"}
}