{
  "type": "Feature",
  "properties": {
    "gn:admin1_code":"22.0",
    "gn:asciiname":"Dibungu",
    "gn:country_code":"CD",
    "gn:dem":1011,
    "gn:feature_class":"P",
    "gn:feature_code":"PPL",
    "gn:name":"Dibungu",
    "gn:population":0,
    "gn:timezone":"Africa/Lubumbashi",
    "iso:country":"CD",
    "name:und_x_variant":[
        "Dibungo",
        "Dibungu"
    ],
    "wof:name":"Dibungu",
    "wof:placetype":"locality"
},
  "geometry": {"coordinates":[22.47723,-8.04276],"type":"Point"}
}