{
  "type": "Feature",
  "properties": {
    "gn:admin1_code":"2.0",
    "gn:asciiname":"Bombeka",
    "gn:country_code":"CD",
    "gn:dem":387,
    "gn:feature_class":"P",
    "gn:feature_code":"PPL",
    "gn:name":"Bombeka",
    "gn:population":0,
    "gn:timezone":"Africa/Kinshasa",
    "iso:country":"CD",
    "wof:name":"Bombeka",
    "wof:placetype":"locality"
},
  "geometry": {"coordinates":[20.11667000000001,0.13333],"type":"Point"}
}