{
  "type": "Feature",
  "properties": {
    "iso:country":"CD",
    "name:eng_x_preferred":[
        "Kabar\u00e9"
    ],
    "name:fra_x_preferred":[
        "Kabar\u00e9"
    ],
    "name:nld_x_preferred":[
        "Kabar\u00e9"
    ],
    "qs:gn_country":"CD",
    "qs:gn_fcode":"PPL",
    "qs:gn_pop":37034,
    "qs:name":"Kabare",
    "qs:name_adm0":"R\u00e9publique D\u00e9mocratique du Congo",
    "qs:name_adm1":"Sud-Kivu",
    "qs:photos":30,
    "qs:photos_1k":6,
    "qs:photos_9k":1,
    "qs:photos_9r":2,
    "qs:photos_all":30,
    "qs:photos_sr":2,
    "qs:placetype":"Town",
    "qs:pop_sr":"7",
    "qs:woe_adm0":23424780,
    "wd:wordcount":26,
    "wof:name":"Kabare",
    "wof:placetype":"locality",
    "wof:population":37034
},
  "geometry": {"coordinates":[28.79081,-2.49682],"type":"Point"}
}