{
  "type": "Feature",
  "properties": {
    "gn:admin1_code":"21.0",
    "gn:asciiname":"Tshimanda",
    "gn:country_code":"CD",
    "gn:dem":956,
    "gn:feature_class":"P",
    "gn:feature_code":"PPL",
    "gn:name":"Tshimanda",
    "gn:population":0,
    "gn:timezone":"Africa/Lubumbashi",
    "iso:country":"CD",
    "wof:name":"Tshimanda",
    "wof:placetype":"locality"
},
  "geometry": {"coordinates":[23.40885,-7.63901],"type":"Point"}
}