{
  "type": "Feature",
  "properties": {
    "gn:admin1_code":"10.0",
    "gn:asciiname":"Kenge",
    "gn:country_code":"CD",
    "gn:dem":647,
    "gn:feature_class":"P",
    "gn:feature_code":"PPL",
    "gn:name":"Kenge",
    "gn:population":0,
    "gn:timezone":"Africa/Lubumbashi",
    "iso:country":"CD",
    "name:ceb_x_preferred":[
        "Kenge"
    ],
    "name:swe_x_preferred":[
        "Kenge"
    ],
    "wof:name":"Kenge",
    "wof:placetype":"locality"
},
  "geometry": {"coordinates":[26.56667,-1.53333],"type":"Point"}
}