{
  "type": "Feature",
  "properties": {
    "gn:admin1_code":"10.0",
    "gn:asciiname":"Kenge",
    "gn:country_code":"CD",
    "gn:dem":647,
    "gn:feature_class":"P",
    "gn:feature_code":"PPL",
    "gn:name":"Kenge",
    "gn:population":0,
    "gn:timezone":"Africa/Lubumbashi",
    "iso:country":"CD",
    "name:ara_x_preferred":[
        "\u0643\u064a\u0646\u062c\u064a"
    ],
    "name:ben_x_preferred":[
        "\u0995\u09c7\u0999\u09cd\u0997\u09c7"
    ],
    "name:ceb_x_preferred":[
        "Kenge"
    ],
    "name:ell_x_preferred":[
        "\u039a\u03ad\u03bd\u03b3\u03ba\u03b5"
    ],
    "name:fas_x_preferred":[
        "\u06a9\u0646\u06af\u0647"
    ],
    "name:heb_x_preferred":[
        "\u05e7\u05e0\u05d2\u05d4"
    ],
    "name:hin_x_preferred":[
        "\u0915\u0947\u0902\u0917\u0947"
    ],
    "name:ind_x_preferred":[
        "Kenge"
    ],
    "name:kor_x_preferred":[
        "\ucf04\uac8c"
    ],
    "name:swe_x_preferred":[
        "Kenge"
    ],
    "name:tur_x_preferred":[
        "Kenge"
    ],
    "name:urd_x_preferred":[
        "\u06a9\u06cc\u0646\u06af\u06d2"
    ],
    "name:vie_x_preferred":[
        "Kenge"
    ],
    "wof:name":"Kenge",
    "wof:placetype":"locality"
},
  "geometry": {"coordinates":[26.56667,-1.53333],"type":"Point"}
}