{
  "type": "Feature",
  "properties": {
    "gn:admin1_code":"10.0",
    "gn:asciiname":"Musenge",
    "gn:country_code":"CD",
    "gn:dem":537,
    "gn:feature_class":"P",
    "gn:feature_code":"PPL",
    "gn:name":"Musenge",
    "gn:population":0,
    "gn:timezone":"Africa/Lubumbashi",
    "iso:country":"CD",
    "wof:name":"Musenge",
    "wof:placetype":"locality"
},
  "geometry": {"coordinates":[26.41667,-1.55],"type":"Point"}
}