{
  "type": "Feature",
  "properties": {
    "gn:admin1_code":"14.0",
    "gn:asciiname":"Musomali",
    "gn:country_code":"CD",
    "gn:dem":1493,
    "gn:feature_class":"P",
    "gn:feature_code":"PPL",
    "gn:name":"Musomali",
    "gn:population":0,
    "gn:timezone":"Africa/Lubumbashi",
    "iso:country":"CD",
    "name:und_x_variant":[
        "Musamari",
        "Musomali"
    ],
    "wof:name":"Musomali",
    "wof:placetype":"locality"
},
  "geometry": {"coordinates":[27.15063,-8.64036],"type":"Point"}
}