{
  "type": "Feature",
  "properties": {
    "gn:admin1_code":"10.0",
    "gn:asciiname":"Kibangula",
    "gn:country_code":"CD",
    "gn:dem":655,
    "gn:feature_class":"P",
    "gn:feature_code":"PPL",
    "gn:name":"Kibangula",
    "gn:population":0,
    "gn:timezone":"Africa/Lubumbashi",
    "iso:country":"CD",
    "wof:name":"Kibangula",
    "wof:placetype":"locality"
},
  "geometry": {"coordinates":[27.05764000000001,-4.88235],"type":"Point"}
}