{
  "type": "Feature",
  "properties": {
    "gn:admin1_code":"10.0",
    "gn:asciiname":"Lusumba",
    "gn:country_code":"CD",
    "gn:dem":557,
    "gn:feature_class":"P",
    "gn:feature_code":"PPL",
    "gn:name":"Lusumba",
    "gn:population":0,
    "gn:timezone":"Africa/Lubumbashi",
    "iso:country":"CD",
    "name:und_x_variant":[
        "Lusamba",
        "Lusumba"
    ],
    "wof:name":"Lusumba",
    "wof:placetype":"locality"
},
  "geometry": {"coordinates":[26.48333,-3.45],"type":"Point"}
}