{
  "type": "Feature",
  "properties": {
    "gn:admin1_code":"20.0",
    "gn:asciiname":"Gweme-Shie",
    "gn:country_code":"CD",
    "gn:dem":396,
    "gn:feature_class":"P",
    "gn:feature_code":"PPL",
    "gn:name":"Gweme-Shie",
    "gn:population":0,
    "gn:timezone":"Africa/Kinshasa",
    "iso:country":"CD",
    "name:und_x_variant":[
        "Gwene",
        "Gwene-Shie",
        "Gweme-Shie"
    ],
    "wof:name":"Gweme-Shie",
    "wof:placetype":"locality"
},
  "geometry": {"coordinates":[17.69077,-3.95173],"type":"Point"}
}