{
  "type": "Feature",
  "properties": {
    "gn:admin1_code":"13.0",
    "gn:asciiname":"Bandia",
    "gn:country_code":"CD",
    "gn:dem":564,
    "gn:feature_class":"P",
    "gn:feature_code":"PPL",
    "gn:name":"Bandia",
    "gn:population":0,
    "gn:timezone":"Africa/Lubumbashi",
    "iso:country":"CD",
    "name:bpy_x_preferred":[
        "\u09ac\u09be\u09a8\u09cd\u09a6\u09bf\u09af\u09bc\u09be"
    ],
    "name:hin_x_preferred":[
        "\u092c\u093e\u0928\u094d\u0926\u093f\u092f\u093e"
    ],
    "name:ita_x_preferred":[
        "Bandia"
    ],
    "name:mlg_x_preferred":[
        "Bandia"
    ],
    "name:msa_x_preferred":[
        "Bandia"
    ],
    "name:new_x_preferred":[
        "\u092c\u0928\u094d\u0926\u093f\u092f\u093e"
    ],
    "name:nld_x_preferred":[
        "Bandia"
    ],
    "name:pol_x_preferred":[
        "Bandia"
    ],
    "name:por_x_preferred":[
        "Bandia"
    ],
    "name:vie_x_preferred":[
        "Bandia"
    ],
    "name:zho_x_preferred":[
        "\u73ed\u8fea\u4e9a"
    ],
    "wof:name":"Bandia",
    "wof:placetype":"locality"
},
  "geometry": {"coordinates":[24.2456,3.97269],"type":"Point"}
}