{
  "type": "Feature",
  "properties": {
    "gn:admin1_code":"19.0",
    "gn:asciiname":"Matsingi-Yeyi",
    "gn:country_code":"CD",
    "gn:dem":764,
    "gn:feature_class":"P",
    "gn:feature_code":"PPL",
    "gn:name":"Matsingi-Yeyi",
    "gn:population":0,
    "gn:timezone":"Africa/Kinshasa",
    "iso:country":"CD",
    "wof:name":"Matsingi-Yeyi",
    "wof:placetype":"locality"
},
  "geometry": {"coordinates":[17.70902000000001,-5.71872],"type":"Point"}
}