{
  "type": "Feature",
  "properties": {
    "gn:admin1_code":"24.0",
    "gn:asciiname":"Longo-Biole",
    "gn:country_code":"CD",
    "gn:dem":317,
    "gn:feature_class":"P",
    "gn:feature_code":"PPL",
    "gn:name":"Longo-Biole",
    "gn:population":0,
    "gn:timezone":"Africa/Kinshasa",
    "iso:country":"CD",
    "name:und_x_variant":[
        "Longo",
        "Loango",
        "Longo-Biole"
    ],
    "wof:name":"Longo-Biole",
    "wof:placetype":"locality"
},
  "geometry": {"coordinates":[18.73333,-1.16667],"type":"Point"}
}