{
  "type": "Feature",
  "properties": {
    "gn:admin1_code":"2.0",
    "gn:asciiname":"Isia",
    "gn:country_code":"CD",
    "gn:dem":304,
    "gn:feature_class":"P",
    "gn:feature_code":"PPL",
    "gn:name":"Isia",
    "gn:population":0,
    "gn:timezone":"Africa/Kinshasa",
    "iso:country":"CD",
    "wof:name":"Isia",
    "wof:placetype":"locality"
},
  "geometry": {"coordinates":[18.26667,0.11667],"type":"Point"}
}