{
  "type": "Feature",
  "properties": {
    "gn:admin1_code":"27.0",
    "gn:asciiname":"Pene-Musindo",
    "gn:country_code":"CD",
    "gn:dem":479,
    "gn:feature_class":"P",
    "gn:feature_code":"PPL",
    "gn:name":"Pene-Musindo",
    "gn:population":0,
    "gn:timezone":"Africa/Lubumbashi",
    "iso:country":"CD",
    "name:und_x_variant":[
        "Pene Mosindo",
        "Pene-Musindo"
    ],
    "wof:name":"Pene-Musindo",
    "wof:placetype":"locality"
},
  "geometry": {"coordinates":[25.00415,-2.83936],"type":"Point"}
}