{
  "type": "Feature",
  "properties": {
    "gn:admin1_code":"2.0",
    "gn:asciiname":"Lite Indigene",
    "gn:country_code":"CD",
    "gn:dem":317,
    "gn:feature_class":"P",
    "gn:feature_code":"PPL",
    "gn:name":"Lite Indigene",
    "gn:population":0,
    "gn:timezone":"Africa/Kinshasa",
    "iso:country":"CD",
    "wof:name":"Lite Indigene",
    "wof:placetype":"locality"
},
  "geometry": {"coordinates":[18.29078,0.04445],"type":"Point"}
}