{
  "type": "Feature",
  "properties": {
    "gn:admin1_code":"20.0",
    "gn:asciiname":"Gonga",
    "gn:country_code":"CD",
    "gn:dem":805,
    "gn:feature_class":"P",
    "gn:feature_code":"PPL",
    "gn:name":"Gonga",
    "gn:population":0,
    "gn:timezone":"Africa/Kinshasa",
    "iso:country":"CD",
    "name:ceb_x_preferred":[
        "Gonga"
    ],
    "name:fra_x_preferred":[
        "Gonga"
    ],
    "name:swe_x_preferred":[
        "Gonga"
    ],
    "wof:name":"Gonga",
    "wof:placetype":"locality"
},
  "geometry": {"coordinates":[19.52301,-6.10211],"type":"Point"}
}