{
  "type": "Feature",
  "properties": {
    "gn:admin1_code":"18.0",
    "gn:asciiname":"Shongolo-Mabondo",
    "gn:country_code":"CD",
    "gn:dem":567,
    "gn:feature_class":"P",
    "gn:feature_code":"PPL",
    "gn:name":"Shongolo-Mabondo",
    "gn:population":0,
    "gn:timezone":"Africa/Lubumbashi",
    "iso:country":"CD",
    "wof:name":"Shongolo-Mabondo",
    "wof:placetype":"locality"
},
  "geometry": {"coordinates":[20.76758,-4.82744],"type":"Point"}
}