{
  "type": "Feature",
  "properties": {
    "gn:admin1_code":"22.0",
    "gn:asciiname":"Kabing",
    "gn:country_code":"CD",
    "gn:dem":973,
    "gn:feature_class":"P",
    "gn:feature_code":"PPL",
    "gn:name":"Kabing",
    "gn:population":0,
    "gn:timezone":"Africa/Lubumbashi",
    "iso:country":"CD",
    "name:und_x_variant":[
        "Kabinga"
    ],
    "wof:name":"Kabing",
    "wof:placetype":"locality"
},
  "geometry": {"coordinates":[22.24672,-7.95181],"type":"Point"}
}