{
  "type": "Feature",
  "properties": {
    "gn:admin1_code":"12.0",
    "gn:asciiname":"Mampulia",
    "gn:country_code":"CD",
    "gn:dem":1270,
    "gn:feature_class":"P",
    "gn:feature_code":"PPL",
    "gn:name":"Mampulia",
    "gn:population":0,
    "gn:timezone":"Africa/Lubumbashi",
    "iso:country":"CD",
    "wof:name":"Mampulia",
    "wof:placetype":"locality"
},
  "geometry": {"coordinates":[28.36667000000001,-3.03333],"type":"Point"}
}