{
  "type": "Feature",
  "properties": {
    "gn:admin1_code":"13.0",
    "gn:asciiname":"Banga",
    "gn:country_code":"CD",
    "gn:dem":440,
    "gn:feature_class":"P",
    "gn:feature_code":"PPL",
    "gn:name":"Banga",
    "gn:population":0,
    "gn:timezone":"Africa/Lubumbashi",
    "iso:country":"CD",
    "wof:name":"Banga",
    "wof:placetype":"locality"
},
  "geometry": {"coordinates":[23.67352,3.32349],"type":"Point"}
}