{
  "type": "Feature",
  "properties": {
    "gn:admin1_code":"22.0",
    "gn:asciiname":"Ferme",
    "gn:country_code":"CD",
    "gn:dem":1101,
    "gn:feature_class":"P",
    "gn:feature_code":"PPL",
    "gn:name":"Ferme",
    "gn:population":0,
    "gn:timezone":"Africa/Lubumbashi",
    "iso:country":"CD",
    "wof:name":"Ferme",
    "wof:placetype":"locality"
},
  "geometry": {"coordinates":[23.10508,-8.93367],"type":"Point"}
}