{
  "type": "Feature",
  "properties": {
    "gn:admin1_code":"0.0",
    "gn:asciiname":"Sokele",
    "gn:country_code":"CD",
    "gn:dem":1021,
    "gn:feature_class":"P",
    "gn:feature_code":"PPL",
    "gn:name":"Sokele",
    "gn:population":0,
    "gn:timezone":"Africa/Lubumbashi",
    "iso:country":"CD",
    "wof:name":"Sokele",
    "wof:placetype":"locality"
},
  "geometry": {"coordinates":[25.30237,-10.42113],"type":"Point"}
}