{
  "type": "Feature",
  "properties": {
    "gn:admin1_code":"25.0",
    "gn:asciiname":"Renika",
    "gn:country_code":"CD",
    "gn:dem":351,
    "gn:feature_class":"P",
    "gn:feature_code":"PPL",
    "gn:name":"Renika",
    "gn:population":0,
    "gn:timezone":"Africa/Kinshasa",
    "iso:country":"CD",
    "wof:name":"Renika",
    "wof:placetype":"locality"
},
  "geometry": {"coordinates":[20.57274,1.81009],"type":"Point"}
}