{
  "type": "Feature",
  "properties": {
    "gn:admin1_code":"14.0",
    "gn:asciiname":"Lukungu",
    "gn:country_code":"CD",
    "gn:dem":1136,
    "gn:feature_class":"P",
    "gn:feature_code":"PPL",
    "gn:name":"Lukungu",
    "gn:population":0,
    "gn:timezone":"Africa/Lubumbashi",
    "iso:country":"CD",
    "wof:name":"Lukungu",
    "wof:placetype":"locality"
},
  "geometry": {"coordinates":[27.2385,-10.80405],"type":"Point"}
}