{
  "type": "Feature",
  "properties": {
    "gn:admin1_code":"12.0",
    "gn:asciiname":"Lushiga",
    "gn:country_code":"CD",
    "gn:dem":1850,
    "gn:feature_class":"P",
    "gn:feature_code":"PPL",
    "gn:name":"Lushiga",
    "gn:population":0,
    "gn:timezone":"Africa/Lubumbashi",
    "iso:country":"CD",
    "wof:name":"Lushiga",
    "wof:placetype":"locality"
},
  "geometry": {"coordinates":[28.69811,-2.7488],"type":"Point"}
}