{
  "type": "Feature",
  "properties": {
    "gn:admin1_code":"15.0",
    "gn:asciiname":"Ditongwe",
    "gn:country_code":"CD",
    "gn:dem":612,
    "gn:feature_class":"P",
    "gn:feature_code":"PPL",
    "gn:name":"Ditongwe",
    "gn:population":0,
    "gn:timezone":"Africa/Lubumbashi",
    "iso:country":"CD",
    "wof:name":"Ditongwe",
    "wof:placetype":"locality"
},
  "geometry": {"coordinates":[25.82162000000001,-9.35659],"type":"Point"}
}