{
  "type": "Feature",
  "properties": {
    "gn:admin1_code":"21.0",
    "gn:asciiname":"Kasebwe",
    "gn:country_code":"CD",
    "gn:dem":773,
    "gn:feature_class":"P",
    "gn:feature_code":"PPL",
    "gn:name":"Kasebwe",
    "gn:population":0,
    "gn:timezone":"Africa/Lubumbashi",
    "iso:country":"CD",
    "wof:name":"Kasebwe",
    "wof:placetype":"locality"
},
  "geometry": {"coordinates":[24.45287,-5.83351],"type":"Point"}
}