{
  "type": "Feature",
  "properties": {
    "gn:admin1_code":"28.0",
    "gn:asciiname":"Mokandja",
    "gn:country_code":"CD",
    "gn:dem":437,
    "gn:feature_class":"P",
    "gn:feature_code":"PPL",
    "gn:name":"Mokandja",
    "gn:population":0,
    "gn:timezone":"Africa/Kinshasa",
    "iso:country":"CD",
    "name:fra_x_preferred":[
        "Mokandja"
    ],
    "wof:name":"Mokandja",
    "wof:placetype":"locality"
},
  "geometry": {"coordinates":[19.01781,2.47694],"type":"Point"}
}