{
  "type": "Feature",
  "properties": {
    "gn:admin1_code":"22.0",
    "gn:asciiname":"Satshiongo",
    "gn:country_code":"CD",
    "gn:dem":1092,
    "gn:feature_class":"P",
    "gn:feature_code":"PPL",
    "gn:name":"Satshiongo",
    "gn:population":0,
    "gn:timezone":"Africa/Lubumbashi",
    "iso:country":"CD",
    "wof:name":"Satshiongo",
    "wof:placetype":"locality"
},
  "geometry": {"coordinates":[22.61667000000001,-10.76667],"type":"Point"}
}