{
  "type": "Feature",
  "properties": {
    "gn:admin1_code":"20.0",
    "gn:asciiname":"Bantsame II",
    "gn:country_code":"CD",
    "gn:dem":516,
    "gn:feature_class":"P",
    "gn:feature_code":"PPL",
    "gn:name":"Bantsame II",
    "gn:population":0,
    "gn:timezone":"Africa/Kinshasa",
    "iso:country":"CD",
    "name:und_x_variant":[
        "Bantshame II",
        "Bantsame II"
    ],
    "wof:name":"Bantsame II",
    "wof:placetype":"locality"
},
  "geometry": {"coordinates":[19.73333,-4.55],"type":"Point"}
}