{
  "type": "Feature",
  "properties": {
    "gn:admin1_code":"13.0",
    "gn:asciiname":"Bongba",
    "gn:country_code":"CD",
    "gn:dem":584,
    "gn:feature_class":"P",
    "gn:feature_code":"PPL",
    "gn:name":"Bongba",
    "gn:population":0,
    "gn:timezone":"Africa/Lubumbashi",
    "iso:country":"CD",
    "name:msa_x_preferred":[
        "Bongba"
    ],
    "wof:name":"Bongba",
    "wof:placetype":"locality"
},
  "geometry": {"coordinates":[25.47206,3.51255],"type":"Point"}
}