{
  "type": "Feature",
  "properties": {
    "gn:admin1_code":"29.0",
    "gn:asciiname":"Makenkebwe",
    "gn:country_code":"CD",
    "gn:dem":762,
    "gn:feature_class":"P",
    "gn:feature_code":"PPL",
    "gn:name":"Makenkebwe",
    "gn:population":0,
    "gn:timezone":"Africa/Lubumbashi",
    "iso:country":"CD",
    "wof:name":"Makenkebwe",
    "wof:placetype":"locality"
},
  "geometry": {"coordinates":[28.02654,-7.88383],"type":"Point"}
}