{
  "type": "Feature",
  "properties": {
    "gn:admin1_code":"22.0",
    "gn:asciiname":"Tshibala",
    "gn:country_code":"CD",
    "gn:dem":1110,
    "gn:feature_class":"P",
    "gn:feature_code":"PPL",
    "gn:name":"Tshibala",
    "gn:population":0,
    "gn:timezone":"Africa/Lubumbashi",
    "iso:country":"CD",
    "wof:name":"Tshibala",
    "wof:placetype":"locality"
},
  "geometry": {"coordinates":[23.48807,-10.39901],"type":"Point"}
}