{
  "type": "Feature",
  "properties": {
    "gn:admin1_code":"30.0",
    "gn:asciiname":"Bagbangana",
    "gn:country_code":"CD",
    "gn:dem":413,
    "gn:feature_class":"P",
    "gn:feature_code":"PPL",
    "gn:name":"Bagbangana",
    "gn:population":0,
    "gn:timezone":"Africa/Lubumbashi",
    "iso:country":"CD",
    "name:und_x_variant":[
        "Baghangana"
    ],
    "wof:name":"Bagbangana",
    "wof:placetype":"locality"
},
  "geometry": {"coordinates":[25.08668,0.5324],"type":"Point"}
}