{
  "type": "Feature",
  "properties": {
    "gn:admin1_code":"8.0",
    "gn:asciiname":"Mayambula",
    "gn:country_code":"CD",
    "gn:dem":219,
    "gn:feature_class":"P",
    "gn:feature_code":"PPL",
    "gn:name":"Mayambula",
    "gn:population":0,
    "gn:timezone":"Africa/Kinshasa",
    "iso:country":"CD",
    "wof:name":"Mayambula",
    "wof:placetype":"locality"
},
  "geometry": {"coordinates":[14.30713,-5.01658],"type":"Point"}
}