{
  "type": "Feature",
  "properties": {
    "gn:admin1_code":"23.0",
    "gn:asciiname":"Kasongo",
    "gn:country_code":"CD",
    "gn:dem":805,
    "gn:feature_class":"P",
    "gn:feature_code":"PPL",
    "gn:name":"Kasongo",
    "gn:population":0,
    "gn:timezone":"Africa/Lubumbashi",
    "iso:country":"CD",
    "name:ceb_x_preferred":[
        "Kasongo"
    ],
    "name:epo_x_preferred":[
        "Kasongo"
    ],
    "name:fra_x_preferred":[
        "Kasongo"
    ],
    "name:hun_x_preferred":[
        "Kasongo"
    ],
    "name:ita_x_preferred":[
        "Kasongo"
    ],
    "name:kat_x_preferred":[
        "\u10d9\u10d0\u10e1\u10dd\u10dc\u10d2\u10dd"
    ],
    "name:nld_x_preferred":[
        "Kasongo"
    ],
    "name:ron_x_preferred":[
        "Kasongo"
    ],
    "name:rus_x_preferred":[
        "\u041a\u0430\u0441\u043e\u043d\u0433\u043e"
    ],
    "name:swa_x_preferred":[
        "Kasongo"
    ],
    "name:swe_x_preferred":[
        "Kasongo"
    ],
    "name:tgl_x_preferred":[
        "Kasongo"
    ],
    "name:ukr_x_preferred":[
        "\u041a\u0430\u0441\u043e\u043d\u0433\u043e"
    ],
    "name:xmf_x_preferred":[
        "\u10d9\u10d0\u10e1\u10dd\u10dc\u10d2\u10dd"
    ],
    "name:zho_x_preferred":[
        "\u5361\u677e\u6208"
    ],
    "wof:name":"Kasongo",
    "wof:placetype":"locality"
},
  "geometry": {"coordinates":[21.78658,-6.63222],"type":"Point"}
}