{
  "type": "Feature",
  "properties": {
    "gn:admin1_code":"23.0",
    "gn:asciiname":"Kanlanga",
    "gn:country_code":"CD",
    "gn:dem":841,
    "gn:feature_class":"P",
    "gn:feature_code":"PPL",
    "gn:name":"Kanlanga",
    "gn:population":0,
    "gn:timezone":"Africa/Lubumbashi",
    "iso:country":"CD",
    "wof:name":"Kanlanga",
    "wof:placetype":"locality"
},
  "geometry": {"coordinates":[22.39655,-6.69791],"type":"Point"}
}