{
  "type": "Feature",
  "properties": {
    "gn:admin1_code":"22.0",
    "gn:asciiname":"Kamasaki Deuxieme",
    "gn:country_code":"CD",
    "gn:dem":967,
    "gn:feature_class":"P",
    "gn:feature_code":"PPL",
    "gn:name":"Kamasaki Deuxi\u00e8me",
    "gn:population":0,
    "gn:timezone":"Africa/Lubumbashi",
    "iso:country":"CD",
    "wof:name":"Kamasaki Deuxieme",
    "wof:placetype":"locality"
},
  "geometry": {"coordinates":[23.17495,-10.45525],"type":"Point"}
}