{
  "type": "Feature",
  "properties": {
    "gn:admin1_code":"23.0",
    "gn:asciiname":"Tshibaia",
    "gn:country_code":"CD",
    "gn:dem":880,
    "gn:feature_class":"P",
    "gn:feature_code":"PPL",
    "gn:name":"Tshibaia",
    "gn:population":0,
    "gn:timezone":"Africa/Lubumbashi",
    "iso:country":"CD",
    "name:und_x_variant":[
        "Tshibala"
    ],
    "wof:name":"Tshibaia",
    "wof:placetype":"locality"
},
  "geometry": {"coordinates":[21.95274,-6.931],"type":"Point"}
}