{
  "type": "Feature",
  "properties": {
    "gn:admin1_code":"12.0",
    "gn:asciiname":"Munanira",
    "gn:country_code":"CD",
    "gn:dem":1934,
    "gn:feature_class":"P",
    "gn:feature_code":"PPL",
    "gn:name":"Munanira",
    "gn:population":0,
    "gn:timezone":"Africa/Lubumbashi",
    "iso:country":"CD",
    "wof:name":"Munanira",
    "wof:placetype":"locality"
},
  "geometry": {"coordinates":[28.90722,-2.80611],"type":"Point"}
}