{
  "type": "Feature",
  "properties": {
    "gn:admin1_code":"22.0",
    "gn:asciiname":"Sakapopo",
    "gn:country_code":"CD",
    "gn:dem":1109,
    "gn:feature_class":"P",
    "gn:feature_code":"PPL",
    "gn:name":"Sakapopo",
    "gn:population":0,
    "gn:timezone":"Africa/Lubumbashi",
    "iso:country":"CD",
    "wof:name":"Sakapopo",
    "wof:placetype":"locality"
},
  "geometry": {"coordinates":[22.85287000000001,-9.27451],"type":"Point"}
}