{
  "type": "Feature",
  "properties": {
    "gn:admin1_code":"13.0",
    "gn:asciiname":"Bobago",
    "gn:country_code":"CD",
    "gn:dem":481,
    "gn:feature_class":"P",
    "gn:feature_code":"PPL",
    "gn:name":"Bobago",
    "gn:population":0,
    "gn:timezone":"Africa/Lubumbashi",
    "iso:country":"CD",
    "wof:name":"Bobago",
    "wof:placetype":"locality"
},
  "geometry": {"coordinates":[23.20846,2.61064],"type":"Point"}
}