{
  "type": "Feature",
  "properties": {
    "gn:admin1_code":"16.0",
    "gn:asciiname":"Madobo",
    "gn:country_code":"CD",
    "gn:dem":826,
    "gn:feature_class":"P",
    "gn:feature_code":"PPL",
    "gn:name":"Madobo",
    "gn:population":0,
    "gn:timezone":"Africa/Lubumbashi",
    "iso:country":"CD",
    "wof:name":"Madobo",
    "wof:placetype":"locality"
},
  "geometry": {"coordinates":[28.45033,3.0234],"type":"Point"}
}