{
  "type": "Feature",
  "properties": {
    "gn:admin1_code":"22.0",
    "gn:asciiname":"Bingilika",
    "gn:country_code":"CD",
    "gn:dem":1158,
    "gn:feature_class":"P",
    "gn:feature_code":"PPL",
    "gn:name":"Bingilika",
    "gn:population":0,
    "gn:timezone":"Africa/Kinshasa",
    "iso:country":"CD",
    "wof:name":"Bingilika",
    "wof:placetype":"locality"
},
  "geometry": {"coordinates":[22.74663,-11.09331],"type":"Point"}
}