{
  "type": "Feature",
  "properties": {
    "gn:admin1_code":"20.0",
    "gn:asciiname":"Namba",
    "gn:country_code":"CD",
    "gn:dem":520,
    "gn:feature_class":"P",
    "gn:feature_code":"PPL",
    "gn:name":"Namba",
    "gn:population":0,
    "gn:timezone":"Africa/Kinshasa",
    "iso:country":"CD",
    "name:epo_x_preferred":[
        "Namba"
    ],
    "name:fra_x_preferred":[
        "Namba"
    ],
    "name:ind_x_preferred":[
        "Namba"
    ],
    "name:ita_x_preferred":[
        "Namba"
    ],
    "name:tha_x_preferred":[
        "\u0e19\u0e31\u0e21\u0e1a\u0e30"
    ],
    "wof:name":"Namba",
    "wof:placetype":"locality"
},
  "geometry": {"coordinates":[18.45387,-4.58263],"type":"Point"}
}