{
  "type": "Feature",
  "properties": {
    "gn:admin1_code":"15.0",
    "gn:asciiname":"Kenga",
    "gn:country_code":"CD",
    "gn:dem":749,
    "gn:feature_class":"P",
    "gn:feature_code":"PPL",
    "gn:name":"Kenga",
    "gn:population":0,
    "gn:timezone":"Africa/Lubumbashi",
    "iso:country":"CD",
    "wof:name":"Kenga",
    "wof:placetype":"locality"
},
  "geometry": {"coordinates":[25.24486,-9.39335],"type":"Point"}
}