{
  "type": "Feature",
  "properties": {
    "gn:admin1_code":"18.0",
    "gn:asciiname":"Mapumba",
    "gn:country_code":"CD",
    "gn:dem":667,
    "gn:feature_class":"P",
    "gn:feature_code":"PPL",
    "gn:name":"Mapumba",
    "gn:population":0,
    "gn:timezone":"Africa/Lubumbashi",
    "iso:country":"CD",
    "wof:name":"Mapumba",
    "wof:placetype":"locality"
},
  "geometry": {"coordinates":[21.62861,-5.63625],"type":"Point"}
}