{
  "type": "Feature",
  "properties": {
    "gn:admin1_code":"29.0",
    "gn:asciiname":"Kabemba",
    "gn:country_code":"CD",
    "gn:dem":612,
    "gn:feature_class":"P",
    "gn:feature_code":"PPL",
    "gn:name":"Kabemba",
    "gn:population":0,
    "gn:timezone":"Africa/Lubumbashi",
    "iso:country":"CD",
    "name:und_x_variant":[
        "Kikomba"
    ],
    "wof:name":"Kabemba",
    "wof:placetype":"locality"
},
  "geometry": {"coordinates":[27.4164,-6.21058],"type":"Point"}
}