{
  "type": "Feature",
  "properties": {
    "gn:admin1_code":"16.0",
    "gn:asciiname":"Batonoku",
    "gn:country_code":"CD",
    "gn:dem":768,
    "gn:feature_class":"P",
    "gn:feature_code":"PPL",
    "gn:name":"Batonoku",
    "gn:population":0,
    "gn:timezone":"Africa/Lubumbashi",
    "iso:country":"CD",
    "wof:name":"Batonoku",
    "wof:placetype":"locality"
},
  "geometry": {"coordinates":[27.66559,2.07598],"type":"Point"}
}