{
  "type": "Feature",
  "properties": {
    "gn:admin1_code":"0.0",
    "gn:asciiname":"Swa-Dungu",
    "gn:country_code":"CD",
    "gn:dem":432,
    "gn:feature_class":"P",
    "gn:feature_code":"PPL",
    "gn:name":"Swa-Dungu",
    "gn:population":0,
    "gn:timezone":"Africa/Kinshasa",
    "iso:country":"CD",
    "wof:name":"Swa-Dungu",
    "wof:placetype":"locality"
},
  "geometry": {"coordinates":[16.95,-7.08333],"type":"Point"}
}