{
  "type": "Feature",
  "properties": {
    "gn:admin1_code":"8.0",
    "gn:asciiname":"Kingusi",
    "gn:country_code":"CD",
    "gn:dem":596,
    "gn:feature_class":"P",
    "gn:feature_code":"PPL",
    "gn:name":"Kingusi",
    "gn:population":0,
    "gn:timezone":"Africa/Kinshasa",
    "iso:country":"CD",
    "wof:name":"Kingusi",
    "wof:placetype":"locality"
},
  "geometry": {"coordinates":[15.22965,-4.87505],"type":"Point"}
}