{
  "type": "Feature",
  "properties": {
    "gn:admin1_code":"20.0",
    "gn:asciiname":"Kinkue",
    "gn:country_code":"CD",
    "gn:dem":447,
    "gn:feature_class":"P",
    "gn:feature_code":"PPL",
    "gn:name":"Kinkue",
    "gn:population":0,
    "gn:timezone":"Africa/Kinshasa",
    "iso:country":"CD",
    "wof:name":"Kinkue",
    "wof:placetype":"locality"
},
  "geometry": {"coordinates":[17.69838,-4.47129],"type":"Point"}
}