{
  "type": "Feature",
  "properties": {
    "gn:admin1_code":"10.0",
    "gn:asciiname":"Kimano Premiere",
    "gn:country_code":"CD",
    "gn:dem":686,
    "gn:feature_class":"P",
    "gn:feature_code":"PPL",
    "gn:name":"Kimano Premi\u00e8re",
    "gn:population":0,
    "gn:timezone":"Africa/Lubumbashi",
    "iso:country":"CD",
    "name:und_x_variant":[
        "Kimano I",
        "Kimano",
        "Kimano Premi\u00e8re"
    ],
    "wof:name":"Kimano Premiere",
    "wof:placetype":"locality"
},
  "geometry": {"coordinates":[28.00076,-4.59563],"type":"Point"}
}