{
  "type": "Feature",
  "properties": {
    "gn:admin1_code":"23.0",
    "gn:asciiname":"Kashikashika",
    "gn:country_code":"CD",
    "gn:dem":809,
    "gn:feature_class":"P",
    "gn:feature_code":"PPL",
    "gn:name":"Kashikashika",
    "gn:population":0,
    "gn:timezone":"Africa/Lubumbashi",
    "iso:country":"CD",
    "wof:name":"Kashikashika",
    "wof:placetype":"locality"
},
  "geometry": {"coordinates":[21.80944,-7.18806],"type":"Point"}
}