{
  "type": "Feature",
  "properties": {
    "gn:admin1_code":"26.0",
    "gn:asciiname":"Kuluwa",
    "gn:country_code":"CD",
    "gn:dem":412,
    "gn:feature_class":"P",
    "gn:feature_code":"PPL",
    "gn:name":"Kuluwa",
    "gn:population":0,
    "gn:timezone":"Africa/Kinshasa",
    "iso:country":"CD",
    "wof:name":"Kuluwa",
    "wof:placetype":"locality"
},
  "geometry": {"coordinates":[20.74218,3.93178],"type":"Point"}
}