{
  "type": "Feature",
  "properties": {
    "gn:admin1_code":"17.0",
    "gn:asciiname":"Diri",
    "gn:country_code":"CD",
    "gn:dem":1027,
    "gn:feature_class":"P",
    "gn:feature_code":"PPL",
    "gn:name":"Diri",
    "gn:population":0,
    "gn:timezone":"Africa/Lubumbashi",
    "iso:country":"CD",
    "wof:name":"Diri",
    "wof:placetype":"locality"
},
  "geometry": {"coordinates":[30.36461,2.87981],"type":"Point"}
}