{
  "type": "Feature",
  "properties": {
    "gn:admin1_code":"22.0",
    "gn:asciiname":"Masikini",
    "gn:country_code":"CD",
    "gn:dem":933,
    "gn:feature_class":"P",
    "gn:feature_code":"PPL",
    "gn:name":"Masikini",
    "gn:population":0,
    "gn:timezone":"Africa/Lubumbashi",
    "iso:country":"CD",
    "wof:name":"Masikini",
    "wof:placetype":"locality"
},
  "geometry": {"coordinates":[22.86042,-9.59617],"type":"Point"}
}