{
  "type": "Feature",
  "properties": {
    "gn:admin1_code":"12.0",
    "gn:asciiname":"Mulonge",
    "gn:country_code":"CD",
    "gn:dem":1547,
    "gn:feature_class":"P",
    "gn:feature_code":"PPL",
    "gn:name":"Mulonge",
    "gn:population":0,
    "gn:timezone":"Africa/Lubumbashi",
    "iso:country":"CD",
    "wof:name":"Mulonge",
    "wof:placetype":"locality"
},
  "geometry": {"coordinates":[28.63333,-2.16667],"type":"Point"}
}