{
  "type": "Feature",
  "properties": {
    "gn:admin1_code":"30.0",
    "gn:asciiname":"Bokpi",
    "gn:country_code":"CD",
    "gn:dem":447,
    "gn:feature_class":"P",
    "gn:feature_code":"PPL",
    "gn:name":"Bokpi",
    "gn:population":0,
    "gn:timezone":"Africa/Lubumbashi",
    "iso:country":"CD",
    "wof:name":"Bokpi",
    "wof:placetype":"locality"
},
  "geometry": {"coordinates":[25.97686,1.77797],"type":"Point"}
}