{
  "type": "Feature",
  "properties": {
    "gn:admin1_code":"24.0",
    "gn:asciiname":"Madja",
    "gn:country_code":"CD",
    "gn:dem":314,
    "gn:feature_class":"P",
    "gn:feature_code":"PPL",
    "gn:name":"Madja",
    "gn:population":0,
    "gn:timezone":"Africa/Kinshasa",
    "iso:country":"CD",
    "wof:name":"Madja",
    "wof:placetype":"locality"
},
  "geometry": {"coordinates":[17.48529,-2.89624],"type":"Point"}
}