{
  "type": "Feature",
  "properties": {
    "gn:admin1_code":"31.0",
    "gn:asciiname":"Ifumo",
    "gn:country_code":"CD",
    "gn:dem":397,
    "gn:feature_class":"P",
    "gn:feature_code":"PPL",
    "gn:name":"Ifumo",
    "gn:population":0,
    "gn:timezone":"Africa/Kinshasa",
    "iso:country":"CD",
    "wof:name":"Ifumo",
    "wof:placetype":"locality"
},
  "geometry": {"coordinates":[20.81796,-1.82755],"type":"Point"}
}