{
  "type": "Feature",
  "properties": {
    "gn:admin1_code":"19.0",
    "gn:asciiname":"Shamalela",
    "gn:country_code":"CD",
    "gn:dem":1031,
    "gn:feature_class":"P",
    "gn:feature_code":"PPL",
    "gn:name":"Shamalela",
    "gn:population":0,
    "gn:timezone":"Africa/Kinshasa",
    "iso:country":"CD",
    "wof:name":"Shamalela",
    "wof:placetype":"locality"
},
  "geometry": {"coordinates":[18.48918,-7.00528],"type":"Point"}
}