{
  "type": "Feature",
  "properties": {
    "gn:admin1_code":"22.0",
    "gn:asciiname":"Tshibung",
    "gn:country_code":"CD",
    "gn:dem":920,
    "gn:feature_class":"P",
    "gn:feature_code":"PPL",
    "gn:name":"Tshibung",
    "gn:population":0,
    "gn:timezone":"Africa/Lubumbashi",
    "iso:country":"CD",
    "wof:name":"Tshibung",
    "wof:placetype":"locality"
},
  "geometry": {"coordinates":[22.74137,-7.97078],"type":"Point"}
}