{
  "type": "Feature",
  "properties": {
    "gn:admin1_code":"11.0",
    "gn:asciiname":"Mulopia",
    "gn:country_code":"CD",
    "gn:dem":853,
    "gn:feature_class":"P",
    "gn:feature_code":"PPL",
    "gn:name":"Mulopia",
    "gn:population":0,
    "gn:timezone":"Africa/Lubumbashi",
    "iso:country":"CD",
    "name:und_x_variant":[
        "Molopia",
        "Malopia",
        "Mulopia"
    ],
    "wof:name":"Mulopia",
    "wof:placetype":"locality"
},
  "geometry": {"coordinates":[29.91503,0.69146],"type":"Point"}
}