{
  "type": "Feature",
  "properties": {
    "gn:admin1_code":"22.0",
    "gn:asciiname":"Postolo Premiere",
    "gn:country_code":"CD",
    "gn:dem":1062,
    "gn:feature_class":"P",
    "gn:feature_code":"PPL",
    "gn:name":"Postolo Premi\u00e8re",
    "gn:population":0,
    "gn:timezone":"Africa/Lubumbashi",
    "iso:country":"CD",
    "wof:name":"Postolo Premiere",
    "wof:placetype":"locality"
},
  "geometry": {"coordinates":[23.31698,-10.38324],"type":"Point"}
}