{
  "type": "Feature",
  "properties": {
    "gn:admin1_code":"24.0",
    "gn:asciiname":"Bekalo",
    "gn:country_code":"CD",
    "gn:dem":306,
    "gn:feature_class":"P",
    "gn:feature_code":"PPL",
    "gn:name":"Bekalo",
    "gn:population":0,
    "gn:timezone":"Africa/Kinshasa",
    "iso:country":"CD",
    "name:und_x_variant":[
        "Bekale"
    ],
    "wof:name":"Bekalo",
    "wof:placetype":"locality"
},
  "geometry": {"coordinates":[18.30588,-2.45686],"type":"Point"}
}