{
  "type": "Feature",
  "properties": {
    "gn:admin1_code":"23.0",
    "gn:asciiname":"Katumba",
    "gn:country_code":"CD",
    "gn:dem":712,
    "gn:feature_class":"P",
    "gn:feature_code":"PPL",
    "gn:name":"Katumba",
    "gn:population":0,
    "gn:timezone":"Africa/Lubumbashi",
    "iso:country":"CD",
    "name:ceb_x_preferred":[
        "Katumba"
    ],
    "name:fra_x_preferred":[
        "Katumba"
    ],
    "name:pol_x_preferred":[
        "Katumba"
    ],
    "name:swa_x_preferred":[
        "Katumba"
    ],
    "wof:name":"Katumba",
    "wof:placetype":"locality"
},
  "geometry": {"coordinates":[22.66039,-5.9294],"type":"Point"}
}