{
  "type": "Feature",
  "properties": {
    "gn:admin1_code":"16.0",
    "gn:asciiname":"Beverendi",
    "gn:country_code":"CD",
    "gn:dem":1060,
    "gn:feature_class":"P",
    "gn:feature_code":"PPL",
    "gn:name":"Beverendi",
    "gn:population":0,
    "gn:timezone":"Africa/Lubumbashi",
    "iso:country":"CD",
    "wof:name":"Beverendi",
    "wof:placetype":"locality"
},
  "geometry": {"coordinates":[29.50382,2.87665],"type":"Point"}
}