{
  "type": "Feature",
  "properties": {
    "gn:admin1_code":"19.0",
    "gn:asciiname":"Kikomba",
    "gn:country_code":"CD",
    "gn:dem":787,
    "gn:feature_class":"P",
    "gn:feature_code":"PPL",
    "gn:name":"Kikomba",
    "gn:population":0,
    "gn:timezone":"Africa/Kinshasa",
    "iso:country":"CD",
    "wof:name":"Kikomba",
    "wof:placetype":"locality"
},
  "geometry": {"coordinates":[17.47487000000001,-6.2584],"type":"Point"}
}