{
  "type": "Feature",
  "properties": {
    "gn:admin1_code":"25.0",
    "gn:asciiname":"Yamisiko",
    "gn:country_code":"CD",
    "gn:dem":391,
    "gn:feature_class":"P",
    "gn:feature_code":"PPL",
    "gn:name":"Yamisiko",
    "gn:population":0,
    "gn:timezone":"Africa/Kinshasa",
    "iso:country":"CD",
    "name:und_x_variant":[
        "Yamisika",
        "Yamisiko"
    ],
    "wof:name":"Yamisiko",
    "wof:placetype":"locality"
},
  "geometry": {"coordinates":[22.43557,2.31432],"type":"Point"}
}