{
  "type": "Feature",
  "properties": {
    "gn:admin1_code":"29.0",
    "gn:asciiname":"Tompa",
    "gn:country_code":"CD",
    "gn:dem":1967,
    "gn:feature_class":"P",
    "gn:feature_code":"PPL",
    "gn:name":"Tompa",
    "gn:population":0,
    "gn:timezone":"Africa/Lubumbashi",
    "iso:country":"CD",
    "wof:name":"Tompa",
    "wof:placetype":"locality"
},
  "geometry": {"coordinates":[29.88333,-7.21667],"type":"Point"}
}