{
  "type": "Feature",
  "properties": {
    "gn:admin1_code":"29.0",
    "gn:asciiname":"Tompa",
    "gn:country_code":"CD",
    "gn:dem":1967,
    "gn:feature_class":"P",
    "gn:feature_code":"PPL",
    "gn:name":"Tompa",
    "gn:population":0,
    "gn:timezone":"Africa/Lubumbashi",
    "iso:country":"CD",
    "name:ara_x_preferred":[
        "\u062a\u0648\u0645\u0628\u0627"
    ],
    "name:ceb_x_preferred":[
        "Tompa"
    ],
    "name:ces_x_preferred":[
        "Tompa"
    ],
    "name:deu_x_preferred":[
        "Tompa"
    ],
    "name:epo_x_preferred":[
        "Tompa"
    ],
    "name:fas_x_preferred":[
        "\u062a\u0648\u0645\u067e\u0627"
    ],
    "name:fra_x_preferred":[
        "Tompa"
    ],
    "name:hrv_x_preferred":[
        "Tompa"
    ],
    "name:hun_x_preferred":[
        "Tompa"
    ],
    "name:ita_x_preferred":[
        "Tompa"
    ],
    "name:mal_x_preferred":[
        "\u0d1f\u0d4b\u0d02\u0d2a"
    ],
    "name:msa_x_preferred":[
        "Tompa"
    ],
    "name:nld_x_preferred":[
        "Tompa"
    ],
    "name:pol_x_preferred":[
        "Tompa"
    ],
    "name:ron_x_preferred":[
        "Tompa"
    ],
    "name:rus_x_preferred":[
        "\u0422\u043e\u043c\u043f\u0430"
    ],
    "name:slk_x_preferred":[
        "Tompa"
    ],
    "name:slv_x_preferred":[
        "Tompa"
    ],
    "name:srp_x_preferred":[
        "\u0422\u043e\u043c\u043f\u0430"
    ],
    "name:swe_x_preferred":[
        "Tompa"
    ],
    "name:ukr_x_preferred":[
        "\u0422\u043e\u043c\u043f\u0430"
    ],
    "name:vie_x_preferred":[
        "Tompa"
    ],
    "wof:name":"Tompa",
    "wof:placetype":"locality"
},
  "geometry": {"coordinates":[29.88333,-7.21667],"type":"Point"}
}