{
  "type": "Feature",
  "properties": {
    "gn:admin1_code":"20.0",
    "gn:asciiname":"Sonji",
    "gn:country_code":"CD",
    "gn:dem":621,
    "gn:feature_class":"P",
    "gn:feature_code":"PPL",
    "gn:name":"Sonji",
    "gn:population":0,
    "gn:timezone":"Africa/Kinshasa",
    "iso:country":"CD",
    "name:und_x_variant":[
        "Sondji"
    ],
    "wof:name":"Sonji",
    "wof:placetype":"locality"
},
  "geometry": {"coordinates":[18.38201,-5.55962],"type":"Point"}
}