{
  "type": "Feature",
  "properties": {
    "gn:admin1_code":"28.0",
    "gn:asciiname":"Busu-Nongu",
    "gn:country_code":"CD",
    "gn:dem":376,
    "gn:feature_class":"P",
    "gn:feature_code":"PPL",
    "gn:name":"Busu-Nongu",
    "gn:population":0,
    "gn:timezone":"Africa/Kinshasa",
    "iso:country":"CD",
    "name:fra_x_preferred":[
        "Busu-Nongu"
    ],
    "wof:name":"Busu-Nongu",
    "wof:placetype":"locality"
},
  "geometry": {"coordinates":[19.00363,2.49814],"type":"Point"}
}