{
  "type": "Feature",
  "properties": {
    "gn:admin1_code":"27.0",
    "gn:asciiname":"Losa",
    "gn:country_code":"CD",
    "gn:dem":600,
    "gn:feature_class":"P",
    "gn:feature_code":"PPL",
    "gn:name":"Losa",
    "gn:population":0,
    "gn:timezone":"Africa/Lubumbashi",
    "iso:country":"CD",
    "wof:name":"Losa",
    "wof:placetype":"locality"
},
  "geometry": {"coordinates":[24.43071,-4.31901],"type":"Point"}
}