{
  "type": "Feature",
  "properties": {
    "gn:admin1_code":"16.0",
    "gn:asciiname":"Azimogu",
    "gn:country_code":"CD",
    "gn:dem":763,
    "gn:feature_class":"P",
    "gn:feature_code":"PPL",
    "gn:name":"Azimogu",
    "gn:population":0,
    "gn:timezone":"Africa/Lubumbashi",
    "iso:country":"CD",
    "wof:name":"Azimogu",
    "wof:placetype":"locality"
},
  "geometry": {"coordinates":[29.34772,3.38013],"type":"Point"}
}