{
  "type": "Feature",
  "properties": {
    "gn:admin1_code":"20.0",
    "gn:asciiname":"Kimeya",
    "gn:country_code":"CD",
    "gn:dem":508,
    "gn:feature_class":"P",
    "gn:feature_code":"PPL",
    "gn:name":"Kimeya",
    "gn:population":0,
    "gn:timezone":"Africa/Kinshasa",
    "iso:country":"CD",
    "wof:name":"Kimeya",
    "wof:placetype":"locality"
},
  "geometry": {"coordinates":[18.3192,-5.37794],"type":"Point"}
}