{
  "type": "Feature",
  "properties": {
    "gn:admin1_code":"18.0",
    "gn:asciiname":"Kituba",
    "gn:country_code":"CD",
    "gn:dem":670,
    "gn:feature_class":"P",
    "gn:feature_code":"PPL",
    "gn:name":"Kituba",
    "gn:population":0,
    "gn:timezone":"Africa/Lubumbashi",
    "iso:country":"CD",
    "wof:name":"Kituba",
    "wof:placetype":"locality"
},
  "geometry": {"coordinates":[20.1728,-6.18213],"type":"Point"}
}