{
  "type": "Feature",
  "properties": {
    "gn:admin1_code":"22.0",
    "gn:asciiname":"Kinga",
    "gn:country_code":"CD",
    "gn:dem":919,
    "gn:feature_class":"P",
    "gn:feature_code":"PPL",
    "gn:name":"Kinga",
    "gn:population":0,
    "gn:timezone":"Africa/Lubumbashi",
    "iso:country":"CD",
    "name:ceb_x_preferred":[
        "Kinga"
    ],
    "name:deu_x_preferred":[
        "Kinga"
    ],
    "name:fra_x_preferred":[
        "Kinga"
    ],
    "name:swe_x_preferred":[
        "Kinga"
    ],
    "wof:name":"Kinga",
    "wof:placetype":"locality"
},
  "geometry": {"coordinates":[24.67381,-10.06167],"type":"Point"}
}