{
  "type": "Feature",
  "properties": {
    "gn:admin1_code":"2.0",
    "gn:asciiname":"Bondji",
    "gn:country_code":"CD",
    "gn:dem":355,
    "gn:feature_class":"P",
    "gn:feature_code":"PPL",
    "gn:name":"Bondji",
    "gn:population":0,
    "gn:timezone":"Africa/Kinshasa",
    "iso:country":"CD",
    "wof:name":"Bondji",
    "wof:placetype":"locality"
},
  "geometry": {"coordinates":[19.58333,0.51667],"type":"Point"}
}