{
  "type": "Feature",
  "properties": {
    "gn:admin1_code":"12.0",
    "gn:asciiname":"Panzi",
    "gn:country_code":"CD",
    "gn:dem":1557,
    "gn:feature_class":"P",
    "gn:feature_code":"PPL",
    "gn:name":"Panzi",
    "gn:population":0,
    "gn:timezone":"Africa/Lubumbashi",
    "iso:country":"CD",
    "wof:name":"Panzi",
    "wof:placetype":"locality"
},
  "geometry": {"coordinates":[28.86646,-2.54508],"type":"Point"}
}