{
  "type": "Feature",
  "properties": {
    "gn:admin1_code":"12.0",
    "gn:asciiname":"Belshi",
    "gn:country_code":"CD",
    "gn:dem":776,
    "gn:feature_class":"P",
    "gn:feature_code":"PPL",
    "gn:name":"Belshi",
    "gn:population":0,
    "gn:timezone":"Africa/Lubumbashi",
    "iso:country":"CD",
    "wof:name":"Belshi",
    "wof:placetype":"locality"
},
  "geometry": {"coordinates":[29.195,-3.34056],"type":"Point"}
}