{
  "type": "Feature",
  "properties": {
    "gn:admin1_code":"27.0",
    "gn:asciiname":"Bidiamba",
    "gn:country_code":"CD",
    "gn:dem":426,
    "gn:feature_class":"P",
    "gn:feature_code":"PPL",
    "gn:name":"Bidiamba",
    "gn:population":0,
    "gn:timezone":"Africa/Lubumbashi",
    "iso:country":"CD",
    "wof:name":"Bidiamba",
    "wof:placetype":"locality"
},
  "geometry": {"coordinates":[22.65193,-1.94129],"type":"Point"}
}