{
  "type": "Feature",
  "properties": {
    "gn:admin1_code":"10.0",
    "gn:asciiname":"Kabandilwa",
    "gn:country_code":"CD",
    "gn:dem":559,
    "gn:feature_class":"P",
    "gn:feature_code":"PPL",
    "gn:name":"Kabandilwa",
    "gn:population":0,
    "gn:timezone":"Africa/Lubumbashi",
    "iso:country":"CD",
    "wof:name":"Kabandilwa",
    "wof:placetype":"locality"
},
  "geometry": {"coordinates":[26.38528,-3.23128],"type":"Point"}
}