{
  "type": "Feature",
  "properties": {
    "gn:admin1_code":"19.0",
    "gn:asciiname":"Makulo-Koshi",
    "gn:country_code":"CD",
    "gn:dem":488,
    "gn:feature_class":"P",
    "gn:feature_code":"PPL",
    "gn:name":"Makulo-Koshi",
    "gn:population":0,
    "gn:timezone":"Africa/Kinshasa",
    "iso:country":"CD",
    "wof:name":"Makulo-Koshi",
    "wof:placetype":"locality"
},
  "geometry": {"coordinates":[17.49306,-4.35935],"type":"Point"}
}