{
  "type": "Feature",
  "properties": {
    "gn:admin1_code":"14.0",
    "gn:asciiname":"Yamba-Yamba",
    "gn:country_code":"CD",
    "gn:dem":914,
    "gn:feature_class":"P",
    "gn:feature_code":"PPL",
    "gn:name":"Yamba-Yamba",
    "gn:population":0,
    "gn:timezone":"Africa/Lubumbashi",
    "iso:country":"CD",
    "wof:name":"Yamba-Yamba",
    "wof:placetype":"locality"
},
  "geometry": {"coordinates":[27.36488,-9.31453],"type":"Point"}
}