{
  "type": "Feature",
  "properties": {
    "gn:admin1_code":"18.0",
    "gn:asciiname":"Boma",
    "gn:country_code":"CD",
    "gn:dem":576,
    "gn:feature_class":"P",
    "gn:feature_code":"PPL",
    "gn:name":"Boma",
    "gn:population":0,
    "gn:timezone":"Africa/Lubumbashi",
    "iso:country":"CD",
    "name:ceb_x_preferred":[
        "Boma"
    ],
    "name:deu_x_preferred":[
        "Boma"
    ],
    "name:fra_x_preferred":[
        "Boma"
    ],
    "name:ita_x_preferred":[
        "Boma"
    ],
    "name:lin_x_preferred":[
        "Boma"
    ],
    "name:nld_x_preferred":[
        "Boma"
    ],
    "name:pol_x_preferred":[
        "Boma"
    ],
    "name:por_x_preferred":[
        "Boma"
    ],
    "name:rus_x_preferred":[
        "\u0411\u043e\u043c\u0430"
    ],
    "name:srp_x_preferred":[
        "\u0411\u043e\u043c\u0430"
    ],
    "name:swe_x_preferred":[
        "Boma"
    ],
    "wof:name":"Boma",
    "wof:placetype":"locality"
},
  "geometry": {"coordinates":[20.5352,-4.41067],"type":"Point"}
}