{
  "type": "Feature",
  "properties": {
    "gn:admin1_code":"22.0",
    "gn:asciiname":"Mpao",
    "gn:country_code":"CD",
    "gn:dem":1079,
    "gn:feature_class":"P",
    "gn:feature_code":"PPL",
    "gn:name":"Mpao",
    "gn:population":0,
    "gn:timezone":"Africa/Lubumbashi",
    "iso:country":"CD",
    "wof:name":"Mpao",
    "wof:placetype":"locality"
},
  "geometry": {"coordinates":[24.06667,-10.06667],"type":"Point"}
}