{
  "type": "Feature",
  "properties": {
    "gn:admin1_code":"19.0",
    "gn:asciiname":"Uta-Bangi",
    "gn:country_code":"CD",
    "gn:dem":579,
    "gn:feature_class":"P",
    "gn:feature_code":"PPL",
    "gn:name":"Uta-Bangi",
    "gn:population":0,
    "gn:timezone":"Africa/Kinshasa",
    "iso:country":"CD",
    "wof:name":"Uta-Bangi",
    "wof:placetype":"locality"
},
  "geometry": {"coordinates":[17.14608,-7.24837],"type":"Point"}
}