{
  "type": "Feature",
  "properties": {
    "gn:admin1_code":"2.0",
    "gn:asciiname":"Esangelenkoi",
    "gn:country_code":"CD",
    "gn:dem":365,
    "gn:feature_class":"P",
    "gn:feature_code":"PPL",
    "gn:name":"Esangelenkoi",
    "gn:population":0,
    "gn:timezone":"Africa/Kinshasa",
    "iso:country":"CD",
    "name:und_x_variant":[
        "Esangelenkoy",
        "Esangelenkoi"
    ],
    "wof:name":"Esangelenkoi",
    "wof:placetype":"locality"
},
  "geometry": {"coordinates":[18.76667,-0.28333],"type":"Point"}
}