{
  "type": "Feature",
  "properties": {
    "gn:admin1_code":"30.0",
    "gn:asciiname":"Katina",
    "gn:country_code":"CD",
    "gn:dem":486,
    "gn:feature_class":"P",
    "gn:feature_code":"PPL",
    "gn:name":"Katina",
    "gn:population":0,
    "gn:timezone":"Africa/Lubumbashi",
    "iso:country":"CD",
    "name:srp_x_preferred":[
        "\u041a\u0430\u0442\u0438\u043d\u0430"
    ],
    "wof:name":"Katina",
    "wof:placetype":"locality"
},
  "geometry": {"coordinates":[25.96667,-1.41667],"type":"Point"}
}