{
  "type": "Feature",
  "properties": {
    "gn:admin1_code":"20.0",
    "gn:asciiname":"Kitota",
    "gn:country_code":"CD",
    "gn:dem":530,
    "gn:feature_class":"P",
    "gn:feature_code":"PPL",
    "gn:name":"Kitota",
    "gn:population":0,
    "gn:timezone":"Africa/Kinshasa",
    "iso:country":"CD",
    "wof:name":"Kitota",
    "wof:placetype":"locality"
},
  "geometry": {"coordinates":[19.81905,-5.98124],"type":"Point"}
}