{
  "type": "Feature",
  "properties": {
    "gn:admin1_code":"18.0",
    "gn:asciiname":"Bosenge-Ola",
    "gn:country_code":"CD",
    "gn:dem":467,
    "gn:feature_class":"P",
    "gn:feature_code":"PPL",
    "gn:name":"Bosenge-Ola",
    "gn:population":0,
    "gn:timezone":"Africa/Lubumbashi",
    "iso:country":"CD",
    "wof:name":"Bosenge-Ola",
    "wof:placetype":"locality"
},
  "geometry": {"coordinates":[21.96667,-3.33333],"type":"Point"}
}