{
  "type": "Feature",
  "properties": {
    "gn:admin1_code":"19.0",
    "gn:asciiname":"Shakabuma",
    "gn:country_code":"CD",
    "gn:dem":937,
    "gn:feature_class":"P",
    "gn:feature_code":"PPL",
    "gn:name":"Shakabuma",
    "gn:population":0,
    "gn:timezone":"Africa/Kinshasa",
    "iso:country":"CD",
    "wof:name":"Shakabuma",
    "wof:placetype":"locality"
},
  "geometry": {"coordinates":[18.64656,-6.96423],"type":"Point"}
}