{
  "type": "Feature",
  "properties": {
    "gn:admin1_code":"20.0",
    "gn:asciiname":"Wele-Wele",
    "gn:country_code":"CD",
    "gn:dem":346,
    "gn:feature_class":"P",
    "gn:feature_code":"PPL",
    "gn:name":"Wele-Wele",
    "gn:population":0,
    "gn:timezone":"Africa/Kinshasa",
    "iso:country":"CD",
    "wof:name":"Wele-Wele",
    "wof:placetype":"locality"
},
  "geometry": {"coordinates":[17.91057,-3.81706],"type":"Point"}
}