{
  "type": "Feature",
  "properties": {
    "gn:admin1_code":"8.0",
    "gn:asciiname":"Viaza",
    "gn:country_code":"CD",
    "gn:dem":293,
    "gn:feature_class":"P",
    "gn:feature_code":"PPL",
    "gn:name":"Viaza",
    "gn:population":0,
    "gn:timezone":"Africa/Kinshasa",
    "iso:country":"CD",
    "wof:name":"Viaza",
    "wof:placetype":"locality"
},
  "geometry": {"coordinates":[14.08639,-5.37048],"type":"Point"}
}