{
  "type": "Feature",
  "properties": {
    "gn:admin1_code":"26.0",
    "gn:asciiname":"Badja",
    "gn:country_code":"CD",
    "gn:dem":455,
    "gn:feature_class":"P",
    "gn:feature_code":"PPL",
    "gn:name":"Badja",
    "gn:population":0,
    "gn:timezone":"Africa/Kinshasa",
    "iso:country":"CD",
    "name:cat_x_preferred":[
        "Badja"
    ],
    "name:ceb_x_preferred":[
        "Badja"
    ],
    "name:swe_x_preferred":[
        "Badja"
    ],
    "wof:name":"Badja",
    "wof:placetype":"locality"
},
  "geometry": {"coordinates":[20.6722,4.31813],"type":"Point"}
}