{
  "type": "Feature",
  "properties": {
    "gn:admin1_code":"20.0",
    "gn:asciiname":"Kipalanga-Mpwa",
    "gn:country_code":"CD",
    "gn:dem":663,
    "gn:feature_class":"P",
    "gn:feature_code":"PPL",
    "gn:name":"Kipalanga-Mpwa",
    "gn:population":0,
    "gn:timezone":"Africa/Kinshasa",
    "iso:country":"CD",
    "wof:name":"Kipalanga-Mpwa",
    "wof:placetype":"locality"
},
  "geometry": {"coordinates":[18.33216,-5.31505],"type":"Point"}
}