{
  "type": "Feature",
  "properties": {
    "gn:admin1_code":"14.0",
    "gn:asciiname":"Musenge",
    "gn:country_code":"CD",
    "gn:dem":1008,
    "gn:feature_class":"P",
    "gn:feature_code":"PPL",
    "gn:name":"Musenge",
    "gn:population":0,
    "gn:timezone":"Africa/Lubumbashi",
    "iso:country":"CD",
    "name:und_x_variant":[
        "Musanga",
        "Musenge"
    ],
    "wof:name":"Musenge",
    "wof:placetype":"locality"
},
  "geometry": {"coordinates":[28.33312,-8.65311],"type":"Point"}
}