{
  "type": "Feature",
  "properties": {
    "gn:admin1_code":"26.0",
    "gn:asciiname":"Ngatungu Deuxieme",
    "gn:country_code":"CD",
    "gn:dem":368,
    "gn:feature_class":"P",
    "gn:feature_code":"PPL",
    "gn:name":"Ngatungu Deuxi\u00e8me",
    "gn:population":0,
    "gn:timezone":"Africa/Kinshasa",
    "iso:country":"CD",
    "name:und_x_variant":[
        "Ngatungu Deuxi\u00e8me",
        "Ngatungu II"
    ],
    "wof:name":"Ngatungu Deuxieme",
    "wof:placetype":"locality"
},
  "geometry": {"coordinates":[19.24329,4.9847],"type":"Point"}
}