{
  "type": "Feature",
  "properties": {
    "gn:admin1_code":"22.0",
    "gn:asciiname":"Lukama",
    "gn:country_code":"CD",
    "gn:dem":1049,
    "gn:feature_class":"P",
    "gn:feature_code":"PPL",
    "gn:name":"Lukama",
    "gn:population":0,
    "gn:timezone":"Africa/Lubumbashi",
    "iso:country":"CD",
    "wof:name":"Lukama",
    "wof:placetype":"locality"
},
  "geometry": {"coordinates":[23.13158,-9.56846],"type":"Point"}
}