{
  "type": "Feature",
  "properties": {
    "gn:admin1_code":"18.0",
    "gn:asciiname":"Mai-Kania",
    "gn:country_code":"CD",
    "gn:dem":661,
    "gn:feature_class":"P",
    "gn:feature_code":"PPL",
    "gn:name":"Mai-Kania",
    "gn:population":0,
    "gn:timezone":"Africa/Lubumbashi",
    "iso:country":"CD",
    "wof:name":"Mai-Kania",
    "wof:placetype":"locality"
},
  "geometry": {"coordinates":[21.14791,-6.72075],"type":"Point"}
}