{
  "type": "Feature",
  "properties": {
    "gn:admin1_code":"2.0",
    "gn:asciiname":"Bayange",
    "gn:country_code":"CD",
    "gn:dem":312,
    "gn:feature_class":"P",
    "gn:feature_code":"PPL",
    "gn:name":"Bayange",
    "gn:population":0,
    "gn:timezone":"Africa/Kinshasa",
    "iso:country":"CD",
    "name:und_x_variant":[
        "Bayenge",
        "Bayange"
    ],
    "wof:name":"Bayange",
    "wof:placetype":"locality"
},
  "geometry": {"coordinates":[17.68332999999999,-0.83333],"type":"Point"}
}