{
  "type": "Feature",
  "properties": {
    "gn:admin1_code":"25.0",
    "gn:asciiname":"Bosambi",
    "gn:country_code":"CD",
    "gn:dem":394,
    "gn:feature_class":"P",
    "gn:feature_code":"PPL",
    "gn:name":"Bosambi",
    "gn:population":0,
    "gn:timezone":"Africa/Kinshasa",
    "iso:country":"CD",
    "wof:name":"Bosambi",
    "wof:placetype":"locality"
},
  "geometry": {"coordinates":[23.20858,2.28294],"type":"Point"}
}