{
  "type": "Feature",
  "properties": {
    "gn:admin1_code":"21.0",
    "gn:asciiname":"Mwanza-Ngudie",
    "gn:country_code":"CD",
    "gn:dem":744,
    "gn:feature_class":"P",
    "gn:feature_code":"PPL",
    "gn:name":"Mwanza-Ngudie",
    "gn:population":0,
    "gn:timezone":"Africa/Lubumbashi",
    "iso:country":"CD",
    "wof:name":"Mwanza-Ngudie",
    "wof:placetype":"locality"
},
  "geometry": {"coordinates":[23.95243,-6.97297],"type":"Point"}
}