{
  "type": "Feature",
  "properties": {
    "gn:admin1_code":"21.0",
    "gn:asciiname":"Kalunga",
    "gn:country_code":"CD",
    "gn:dem":713,
    "gn:feature_class":"P",
    "gn:feature_code":"PPL",
    "gn:name":"Kalunga",
    "gn:population":0,
    "gn:timezone":"Africa/Lubumbashi",
    "iso:country":"CD",
    "name:por_x_preferred":[
        "Calungas"
    ],
    "name:spa_x_preferred":[
        "Calungas"
    ],
    "name:und_x_variant":[
        "Kalungu"
    ],
    "wof:name":"Kalunga",
    "wof:placetype":"locality"
},
  "geometry": {"coordinates":[24.95528,-4.96483],"type":"Point"}
}