{
  "type": "Feature",
  "properties": {
    "gn:admin1_code":"21.0",
    "gn:asciiname":"Bwanga",
    "gn:country_code":"CD",
    "gn:dem":880,
    "gn:feature_class":"P",
    "gn:feature_code":"PPL",
    "gn:name":"Bwanga",
    "gn:population":0,
    "gn:timezone":"Africa/Lubumbashi",
    "iso:country":"CD",
    "wof:name":"Bwanga",
    "wof:placetype":"locality"
},
  "geometry": {"coordinates":[24.92024,-6.62303],"type":"Point"}
}