{
  "type": "Feature",
  "properties": {
    "gn:admin1_code":"30.0",
    "gn:asciiname":"Badumbe",
    "gn:country_code":"CD",
    "gn:dem":423,
    "gn:feature_class":"P",
    "gn:feature_code":"PPL",
    "gn:name":"Badumbe",
    "gn:population":0,
    "gn:timezone":"Africa/Lubumbashi",
    "iso:country":"CD",
    "wof:name":"Badumbe",
    "wof:placetype":"locality"
},
  "geometry": {"coordinates":[23.99182,1.53113],"type":"Point"}
}