{
  "type": "Feature",
  "properties": {
    "gn:admin1_code":"24.0",
    "gn:asciiname":"Looma",
    "gn:country_code":"CD",
    "gn:dem":377,
    "gn:feature_class":"P",
    "gn:feature_code":"PPL",
    "gn:name":"Looma",
    "gn:population":0,
    "gn:timezone":"Africa/Kinshasa",
    "iso:country":"CD",
    "wof:name":"Looma",
    "wof:placetype":"locality"
},
  "geometry": {"coordinates":[19.53333,-3.15],"type":"Point"}
}