{
  "type": "Feature",
  "properties": {
    "gn:admin1_code":"22.0",
    "gn:asciiname":"Mbumb",
    "gn:country_code":"CD",
    "gn:dem":898,
    "gn:feature_class":"P",
    "gn:feature_code":"PPL",
    "gn:name":"Mbumb",
    "gn:population":0,
    "gn:timezone":"Africa/Lubumbashi",
    "iso:country":"CD",
    "wof:name":"Mbumb",
    "wof:placetype":"locality"
},
  "geometry": {"coordinates":[22.60152,-9.11821],"type":"Point"}
}