{
  "type": "Feature",
  "properties": {
    "gn:admin1_code":"19.0",
    "gn:asciiname":"Mwashidi",
    "gn:country_code":"CD",
    "gn:dem":919,
    "gn:feature_class":"P",
    "gn:feature_code":"PPL",
    "gn:name":"Mwashidi",
    "gn:population":0,
    "gn:timezone":"Africa/Kinshasa",
    "iso:country":"CD",
    "wof:name":"Mwashidi",
    "wof:placetype":"locality"
},
  "geometry": {"coordinates":[18.84201,-6.67822],"type":"Point"}
}