{
  "type": "Feature",
  "properties": {
    "gn:admin1_code":"22.0",
    "gn:asciiname":"Zama",
    "gn:country_code":"CD",
    "gn:dem":1131,
    "gn:feature_class":"P",
    "gn:feature_code":"PPL",
    "gn:name":"Zama",
    "gn:population":0,
    "gn:timezone":"Africa/Lubumbashi",
    "iso:country":"CD",
    "wof:name":"Zama",
    "wof:placetype":"locality"
},
  "geometry": {"coordinates":[23.84468,-10.74249],"type":"Point"}
}