{
  "type": "Feature",
  "properties": {
    "gn:admin1_code":"22.0",
    "gn:asciiname":"Zama",
    "gn:country_code":"CD",
    "gn:dem":1131,
    "gn:feature_class":"P",
    "gn:feature_code":"PPL",
    "gn:name":"Zama",
    "gn:population":0,
    "gn:timezone":"Africa/Lubumbashi",
    "iso:country":"CD",
    "name:ceb_x_preferred":[
        "Zama"
    ],
    "name:deu_x_preferred":[
        "Zama"
    ],
    "name:fra_x_preferred":[
        "Zama"
    ],
    "name:ind_x_preferred":[
        "Zama"
    ],
    "name:ita_x_preferred":[
        "Zama"
    ],
    "name:nld_x_preferred":[
        "Zama"
    ],
    "name:oci_x_preferred":[
        "Zama"
    ],
    "name:pol_x_preferred":[
        "Zama"
    ],
    "name:por_x_preferred":[
        "Zama"
    ],
    "name:swe_x_preferred":[
        "Zama"
    ],
    "name:tur_x_preferred":[
        "Zama"
    ],
    "wof:name":"Zama",
    "wof:placetype":"locality"
},
  "geometry": {"coordinates":[23.84468,-10.74249],"type":"Point"}
}