{
  "type": "Feature",
  "properties": {
    "gn:admin1_code":"17.0",
    "gn:asciiname":"Ofai",
    "gn:country_code":"CD",
    "gn:dem":954,
    "gn:feature_class":"P",
    "gn:feature_code":"PPL",
    "gn:name":"Ofai",
    "gn:population":0,
    "gn:timezone":"Africa/Lubumbashi",
    "iso:country":"CD",
    "name:fra_x_preferred":[
        "Ofai"
    ],
    "name:fra_x_variant":[
        "Ofay",
        "Atunukve"
    ],
    "name:und_x_variant":[
        "Atunukve",
        "Ofay"
    ],
    "wof:name":"Ofai",
    "wof:placetype":"locality"
},
  "geometry": {"coordinates":[29.69291,1.20918],"type":"Point"}
}