{
  "type": "Feature",
  "properties": {
    "gn:admin1_code":"14.0",
    "gn:asciiname":"Lusinga",
    "gn:country_code":"CD",
    "gn:dem":1785,
    "gn:feature_class":"P",
    "gn:feature_code":"PPL",
    "gn:name":"Lusinga",
    "gn:population":0,
    "gn:timezone":"Africa/Lubumbashi",
    "iso:country":"CD",
    "wof:name":"Lusinga",
    "wof:placetype":"locality"
},
  "geometry": {"coordinates":[27.20564,-8.93207],"type":"Point"}
}