{
  "type": "Feature",
  "properties": {
    "gn:admin1_code":"31.0",
    "gn:asciiname":"Imbo",
    "gn:country_code":"CD",
    "gn:dem":372,
    "gn:feature_class":"P",
    "gn:feature_code":"PPL",
    "gn:name":"Imbo",
    "gn:population":0,
    "gn:timezone":"Africa/Kinshasa",
    "iso:country":"CD",
    "wof:name":"Imbo",
    "wof:placetype":"locality"
},
  "geometry": {"coordinates":[21.20491,0.16591],"type":"Point"}
}