{
  "type": "Feature",
  "properties": {
    "gn:admin1_code":"10.0",
    "gn:asciiname":"Kasinda",
    "gn:country_code":"CD",
    "gn:dem":576,
    "gn:feature_class":"P",
    "gn:feature_code":"PPL",
    "gn:name":"Kasinda",
    "gn:population":0,
    "gn:timezone":"Africa/Lubumbashi",
    "iso:country":"CD",
    "wof:name":"Kasinda",
    "wof:placetype":"locality"
},
  "geometry": {"coordinates":[25.61243,-4.43625],"type":"Point"}
}