{
  "type": "Feature",
  "properties": {
    "gn:admin1_code":"12.0",
    "gn:asciiname":"Ali",
    "gn:country_code":"CD",
    "gn:dem":837,
    "gn:feature_class":"P",
    "gn:feature_code":"PPL",
    "gn:name":"Ali",
    "gn:population":0,
    "gn:timezone":"Africa/Lubumbashi",
    "iso:country":"CD",
    "name:und_x_variant":[
        "Ali Moya",
        "Ali Moia",
        "Ali"
    ],
    "wof:name":"Ali",
    "wof:placetype":"locality"
},
  "geometry": {"coordinates":[28.80517,-5.00066],"type":"Point"}
}