{
  "type": "Feature",
  "properties": {
    "gn:admin1_code":"22.0",
    "gn:asciiname":"Mikengere",
    "gn:country_code":"CD",
    "gn:dem":734,
    "gn:feature_class":"P",
    "gn:feature_code":"PPL",
    "gn:name":"Mikengere",
    "gn:population":0,
    "gn:timezone":"Africa/Lubumbashi",
    "iso:country":"CD",
    "wof:name":"Mikengere",
    "wof:placetype":"locality"
},
  "geometry": {"coordinates":[25.52192,-9.90634],"type":"Point"}
}