{
  "type": "Feature",
  "properties": {
    "gn:admin1_code":"11.0",
    "gn:asciiname":"Makoka",
    "gn:country_code":"CD",
    "gn:dem":2204,
    "gn:feature_class":"P",
    "gn:feature_code":"PPL",
    "gn:name":"Makoka",
    "gn:population":0,
    "gn:timezone":"Africa/Lubumbashi",
    "iso:country":"CD",
    "wof:name":"Makoka",
    "wof:placetype":"locality"
},
  "geometry": {"coordinates":[29.21372,-0.22615],"type":"Point"}
}