{
  "type": "Feature",
  "properties": {
    "gn:admin1_code":"20.0",
    "gn:asciiname":"Kimatu",
    "gn:country_code":"CD",
    "gn:dem":630,
    "gn:feature_class":"P",
    "gn:feature_code":"PPL",
    "gn:name":"Kimatu",
    "gn:population":0,
    "gn:timezone":"Africa/Kinshasa",
    "iso:country":"CD",
    "wof:name":"Kimatu",
    "wof:placetype":"locality"
},
  "geometry": {"coordinates":[18.04527,-5.16304],"type":"Point"}
}