{
  "type": "Feature",
  "properties": {
    "gn:admin1_code":"8.0",
    "gn:asciiname":"Luanika",
    "gn:country_code":"CD",
    "gn:dem":384,
    "gn:feature_class":"P",
    "gn:feature_code":"PPL",
    "gn:name":"Luanika",
    "gn:population":0,
    "gn:timezone":"Africa/Kinshasa",
    "iso:country":"CD",
    "name:und_x_variant":[
        "Luenika",
        "Luanika"
    ],
    "wof:name":"Luanika",
    "wof:placetype":"locality"
},
  "geometry": {"coordinates":[14.34928,-5.65493],"type":"Point"}
}