{
  "type": "Feature",
  "properties": {
    "gn:admin1_code":"18.0",
    "gn:asciiname":"Mitunda",
    "gn:country_code":"CD",
    "gn:dem":458,
    "gn:feature_class":"P",
    "gn:feature_code":"PPL",
    "gn:name":"Mitunda",
    "gn:population":0,
    "gn:timezone":"Africa/Lubumbashi",
    "iso:country":"CD",
    "wof:name":"Mitunda",
    "wof:placetype":"locality"
},
  "geometry": {"coordinates":[20.57899,-5.93954],"type":"Point"}
}