{
  "type": "Feature",
  "properties": {
    "gn:admin1_code":"13.0",
    "gn:asciiname":"Palembo",
    "gn:country_code":"CD",
    "gn:dem":656,
    "gn:feature_class":"P",
    "gn:feature_code":"PPL",
    "gn:name":"Palembo",
    "gn:population":0,
    "gn:timezone":"Africa/Lubumbashi",
    "iso:country":"CD",
    "wof:name":"Palembo",
    "wof:placetype":"locality"
},
  "geometry": {"coordinates":[25.60962,3.78732],"type":"Point"}
}