{
  "type": "Feature",
  "properties": {
    "gn:admin1_code":"14.0",
    "gn:asciiname":"Mushikatala",
    "gn:country_code":"CD",
    "gn:dem":1138,
    "gn:feature_class":"P",
    "gn:feature_code":"PPL",
    "gn:name":"Mushikatala",
    "gn:population":0,
    "gn:timezone":"Africa/Lubumbashi",
    "iso:country":"CD",
    "name:und_x_variant":[
        "Mushikatata",
        "Mushikatala"
    ],
    "wof:name":"Mushikatala",
    "wof:placetype":"locality"
},
  "geometry": {"coordinates":[27.06667,-11.05],"type":"Point"}
}