{
  "type": "Feature",
  "properties": {
    "gn:admin1_code":"22.0",
    "gn:asciiname":"Sakalonda",
    "gn:country_code":"CD",
    "gn:dem":1021,
    "gn:feature_class":"P",
    "gn:feature_code":"PPL",
    "gn:name":"Sakalonda",
    "gn:population":0,
    "gn:timezone":"Africa/Lubumbashi",
    "iso:country":"CD",
    "wof:name":"Sakalonda",
    "wof:placetype":"locality"
},
  "geometry": {"coordinates":[23.2024,-9.56732],"type":"Point"}
}