{
  "type": "Feature",
  "properties": {
    "gn:admin1_code":"18.0",
    "gn:asciiname":"Shambinga",
    "gn:country_code":"CD",
    "gn:dem":592,
    "gn:feature_class":"P",
    "gn:feature_code":"PPL",
    "gn:name":"Shambinga",
    "gn:population":0,
    "gn:timezone":"Africa/Lubumbashi",
    "iso:country":"CD",
    "wof:name":"Shambinga",
    "wof:placetype":"locality"
},
  "geometry": {"coordinates":[20.5735,-4.46488],"type":"Point"}
}