{
  "type": "Feature",
  "properties": {
    "gn:admin1_code":"18.0",
    "gn:asciiname":"Njilo",
    "gn:country_code":"CD",
    "gn:dem":642,
    "gn:feature_class":"P",
    "gn:feature_code":"PPL",
    "gn:name":"Njilo",
    "gn:population":0,
    "gn:timezone":"Africa/Lubumbashi",
    "iso:country":"CD",
    "wof:name":"Njilo",
    "wof:placetype":"locality"
},
  "geometry": {"coordinates":[20.17063,-6.17979],"type":"Point"}
}