{
  "type": "Feature",
  "properties": {
    "gn:admin1_code":"16.0",
    "gn:asciiname":"Banda",
    "gn:country_code":"CD",
    "gn:dem":750,
    "gn:feature_class":"P",
    "gn:feature_code":"PPL",
    "gn:name":"Banda",
    "gn:population":0,
    "gn:timezone":"Africa/Lubumbashi",
    "iso:country":"CD",
    "wof:name":"Banda",
    "wof:placetype":"locality"
},
  "geometry": {"coordinates":[27.39352,2.56073],"type":"Point"}
}