{
  "type": "Feature",
  "properties": {
    "gn:admin1_code":"28.0",
    "gn:asciiname":"Bongo",
    "gn:country_code":"CD",
    "gn:dem":357,
    "gn:feature_class":"P",
    "gn:feature_code":"PPL",
    "gn:name":"Bongo",
    "gn:population":0,
    "gn:timezone":"Africa/Kinshasa",
    "iso:country":"CD",
    "wof:name":"Bongo",
    "wof:placetype":"locality"
},
  "geometry": {"coordinates":[18.69566,3.2892],"type":"Point"}
}