{
  "type": "Feature",
  "properties": {
    "gn:admin1_code":"18.0",
    "gn:asciiname":"Kasaba",
    "gn:country_code":"CD",
    "gn:dem":486,
    "gn:feature_class":"P",
    "gn:feature_code":"PPL",
    "gn:name":"Kasaba",
    "gn:population":0,
    "gn:timezone":"Africa/Lubumbashi",
    "iso:country":"CD",
    "name:hye_x_preferred":[
        "\u0544\u0565\u0576\u0569\u0565\u0577"
    ],
    "name:ita_x_preferred":[
        "Kasaba"
    ],
    "name:tur_x_preferred":[
        "Kasaba"
    ],
    "name:vie_x_preferred":[
        "Kasaba"
    ],
    "wof:name":"Kasaba",
    "wof:placetype":"locality"
},
  "geometry": {"coordinates":[20.57224,-6.04355],"type":"Point"}
}