{
  "type": "Feature",
  "properties": {
    "gn:admin1_code":"17.0",
    "gn:asciiname":"Saliboko",
    "gn:country_code":"CD",
    "gn:dem":1417,
    "gn:feature_class":"P",
    "gn:feature_code":"PPL",
    "gn:name":"Saliboko",
    "gn:population":0,
    "gn:timezone":"Africa/Lubumbashi",
    "iso:country":"CD",
    "wof:name":"Saliboko",
    "wof:placetype":"locality"
},
  "geometry": {"coordinates":[30.20167,1.66013],"type":"Point"}
}