{
  "type": "Feature",
  "properties": {
    "gn:admin1_code":"13.0",
    "gn:asciiname":"Makpangba",
    "gn:country_code":"CD",
    "gn:dem":702,
    "gn:feature_class":"P",
    "gn:feature_code":"PPL",
    "gn:name":"Makpangba",
    "gn:population":0,
    "gn:timezone":"Africa/Lubumbashi",
    "iso:country":"CD",
    "wof:name":"Makpangba",
    "wof:placetype":"locality"
},
  "geometry": {"coordinates":[26.83553,2.59648],"type":"Point"}
}