{
  "type": "Feature",
  "properties": {
    "gn:admin1_code":"8.0",
    "gn:asciiname":"Kitomesa",
    "gn:country_code":"CD",
    "gn:dem":284,
    "gn:feature_class":"P",
    "gn:feature_code":"PPL",
    "gn:name":"Kitomesa",
    "gn:population":0,
    "gn:timezone":"Africa/Kinshasa",
    "iso:country":"CD",
    "wof:name":"Kitomesa",
    "wof:placetype":"locality"
},
  "geometry": {"coordinates":[13.9145,-5.57124],"type":"Point"}
}