{
  "type": "Feature",
  "properties": {
    "gn:admin1_code":"31.0",
    "gn:asciiname":"Yambotekoko",
    "gn:country_code":"CD",
    "gn:dem":466,
    "gn:feature_class":"P",
    "gn:feature_code":"PPL",
    "gn:name":"Yambotekoko",
    "gn:population":0,
    "gn:timezone":"Africa/Kinshasa",
    "iso:country":"CD",
    "name:und_x_variant":[
        "Yombote Koko",
        "Yambotekoko"
    ],
    "wof:name":"Yambotekoko",
    "wof:placetype":"locality"
},
  "geometry": {"coordinates":[22.02591,0.8891],"type":"Point"}
}