{
  "type": "Feature",
  "properties": {
    "gn:admin1_code":"28.0",
    "gn:asciiname":"Togbonguya",
    "gn:country_code":"CD",
    "gn:dem":599,
    "gn:feature_class":"P",
    "gn:feature_code":"PPL",
    "gn:name":"Togbonguya",
    "gn:population":0,
    "gn:timezone":"Africa/Kinshasa",
    "iso:country":"CD",
    "wof:name":"Togbonguya",
    "wof:placetype":"locality"
},
  "geometry": {"coordinates":[19.23028,4.08778],"type":"Point"}
}