{
  "type": "Feature",
  "properties": {
    "gn:admin1_code":"22.0",
    "gn:asciiname":"Samutete",
    "gn:country_code":"CD",
    "gn:dem":1147,
    "gn:feature_class":"P",
    "gn:feature_code":"PPL",
    "gn:name":"Samutete",
    "gn:population":0,
    "gn:timezone":"Africa/Lubumbashi",
    "iso:country":"CD",
    "name:und_x_variant":[
        "Samutate",
        "Samutete"
    ],
    "wof:name":"Samutete",
    "wof:placetype":"locality"
},
  "geometry": {"coordinates":[22.5602,-11.01272],"type":"Point"}
}