{
  "type": "Feature",
  "properties": {
    "gn:admin1_code":"20.0",
    "gn:asciiname":"Kituenge",
    "gn:country_code":"CD",
    "gn:dem":426,
    "gn:feature_class":"P",
    "gn:feature_code":"PPL",
    "gn:name":"Kituenge",
    "gn:population":0,
    "gn:timezone":"Africa/Kinshasa",
    "iso:country":"CD",
    "wof:name":"Kituenge",
    "wof:placetype":"locality"
},
  "geometry": {"coordinates":[17.97903999999999,-4.53648],"type":"Point"}
}