{
  "type": "Feature",
  "properties": {
    "gn:admin1_code":"10.0",
    "gn:asciiname":"Metsera",
    "gn:country_code":"CD",
    "gn:dem":542,
    "gn:feature_class":"P",
    "gn:feature_code":"PPL",
    "gn:name":"Metsera",
    "gn:population":0,
    "gn:timezone":"Africa/Lubumbashi",
    "iso:country":"CD",
    "wof:name":"Metsera",
    "wof:placetype":"locality"
},
  "geometry": {"coordinates":[26.1326,-2.57868],"type":"Point"}
}