{
  "type": "Feature",
  "properties": {
    "gn:admin1_code":"13.0",
    "gn:asciiname":"Mabruki",
    "gn:country_code":"CD",
    "gn:dem":529,
    "gn:feature_class":"P",
    "gn:feature_code":"PPL",
    "gn:name":"Mabruki",
    "gn:population":0,
    "gn:timezone":"Africa/Lubumbashi",
    "iso:country":"CD",
    "wof:name":"Mabruki",
    "wof:placetype":"locality"
},
  "geometry": {"coordinates":[23.89772,3.86396],"type":"Point"}
}