{
  "type": "Feature",
  "properties": {
    "gn:admin1_code":"19.0",
    "gn:asciiname":"Kowa",
    "gn:country_code":"CD",
    "gn:dem":778,
    "gn:feature_class":"P",
    "gn:feature_code":"PPL",
    "gn:name":"Kowa",
    "gn:population":0,
    "gn:timezone":"Africa/Kinshasa",
    "iso:country":"CD",
    "name:ceb_x_preferred":[
        "Kowa"
    ],
    "name:deu_x_preferred":[
        "Kowa"
    ],
    "name:fra_x_preferred":[
        "K\u014dwa"
    ],
    "name:swe_x_preferred":[
        "Kowa"
    ],
    "wof:name":"Kowa",
    "wof:placetype":"locality"
},
  "geometry": {"coordinates":[18.20484,-5.82906],"type":"Point"}
}