{
  "type": "Feature",
  "properties": {
    "gn:admin1_code":"24.0",
    "gn:asciiname":"Elangankole",
    "gn:country_code":"CD",
    "gn:dem":343,
    "gn:feature_class":"P",
    "gn:feature_code":"PPL",
    "gn:name":"Elangankole",
    "gn:population":0,
    "gn:timezone":"Africa/Kinshasa",
    "iso:country":"CD",
    "wof:name":"Elangankole",
    "wof:placetype":"locality"
},
  "geometry": {"coordinates":[19.43333,-3.36667],"type":"Point"}
}