{
  "type": "Feature",
  "properties": {
    "gn:admin1_code":"21.0",
    "gn:asciiname":"Kazenga",
    "gn:country_code":"CD",
    "gn:dem":949,
    "gn:feature_class":"P",
    "gn:feature_code":"PPL",
    "gn:name":"Kazenga",
    "gn:population":0,
    "gn:timezone":"Africa/Lubumbashi",
    "iso:country":"CD",
    "wof:name":"Kazenga",
    "wof:placetype":"locality"
},
  "geometry": {"coordinates":[23.25688,-7.80239],"type":"Point"}
}