{
  "type": "Feature",
  "properties": {
    "gn:admin1_code":"8.0",
    "gn:asciiname":"Puta",
    "gn:country_code":"CD",
    "gn:dem":407,
    "gn:feature_class":"P",
    "gn:feature_code":"PPL",
    "gn:name":"Puta",
    "gn:population":0,
    "gn:timezone":"Africa/Kinshasa",
    "iso:country":"CD",
    "name:ceb_x_preferred":[
        "Puta"
    ],
    "name:por_x_preferred":[
        "Puta"
    ],
    "name:swe_x_preferred":[
        "Puta"
    ],
    "wof:name":"Puta",
    "wof:placetype":"locality"
},
  "geometry": {"coordinates":[14.62446,-5.77494],"type":"Point"}
}