{
  "type": "Feature",
  "properties": {
    "gn:admin1_code":"12.0",
    "gn:asciiname":"Ibonga",
    "gn:country_code":"CD",
    "gn:dem":950,
    "gn:feature_class":"P",
    "gn:feature_code":"PPL",
    "gn:name":"Ibonga",
    "gn:population":0,
    "gn:timezone":"Africa/Lubumbashi",
    "iso:country":"CD",
    "wof:name":"Ibonga",
    "wof:placetype":"locality"
},
  "geometry": {"coordinates":[27.96667,-2.91667],"type":"Point"}
}