{
  "type": "Feature",
  "properties": {
    "gn:admin1_code":"8.0",
    "gn:asciiname":"Kindundu Premiere",
    "gn:country_code":"CD",
    "gn:dem":521,
    "gn:feature_class":"P",
    "gn:feature_code":"PPL",
    "gn:name":"Kindundu Premi\u00e8re",
    "gn:population":0,
    "gn:timezone":"Africa/Kinshasa",
    "iso:country":"CD",
    "wof:name":"Kindundu Premiere",
    "wof:placetype":"locality"
},
  "geometry": {"coordinates":[15.02204,-5.20344],"type":"Point"}
}