{
  "type": "Feature",
  "properties": {
    "gn:admin1_code":"22.0",
    "gn:asciiname":"Kajila",
    "gn:country_code":"CD",
    "gn:dem":1006,
    "gn:feature_class":"P",
    "gn:feature_code":"PPL",
    "gn:name":"Kajila",
    "gn:population":0,
    "gn:timezone":"Africa/Lubumbashi",
    "iso:country":"CD",
    "wof:name":"Kajila",
    "wof:placetype":"locality"
},
  "geometry": {"coordinates":[23.58829,-9.68329],"type":"Point"}
}