{
  "type": "Feature",
  "properties": {
    "gn:admin1_code":"31.0",
    "gn:asciiname":"Yaweta",
    "gn:country_code":"CD",
    "gn:dem":408,
    "gn:feature_class":"P",
    "gn:feature_code":"PPL",
    "gn:name":"Yaweta",
    "gn:population":0,
    "gn:timezone":"Africa/Kinshasa",
    "iso:country":"CD",
    "name:und_x_variant":[
        "Jaweta",
        "Yaweta"
    ],
    "wof:name":"Yaweta",
    "wof:placetype":"locality"
},
  "geometry": {"coordinates":[22.91549,-0.59849],"type":"Point"}
}