{
  "type": "Feature",
  "properties": {
    "gn:admin1_code":"28.0",
    "gn:asciiname":"Gwele-Banza",
    "gn:country_code":"CD",
    "gn:dem":440,
    "gn:feature_class":"P",
    "gn:feature_code":"PPL",
    "gn:name":"Gwele-Banza",
    "gn:population":0,
    "gn:timezone":"Africa/Kinshasa",
    "iso:country":"CD",
    "name:und_x_variant":[
        "Gwele",
        "Gwele-Banza"
    ],
    "wof:name":"Gwele-Banza",
    "wof:placetype":"locality"
},
  "geometry": {"coordinates":[20.27928,2.6914],"type":"Point"}
}