{
  "type": "Feature",
  "properties": {
    "gn:admin1_code":"10.0",
    "gn:asciiname":"Kabayeye",
    "gn:country_code":"CD",
    "gn:dem":566,
    "gn:feature_class":"P",
    "gn:feature_code":"PPL",
    "gn:name":"Kabayeye",
    "gn:population":0,
    "gn:timezone":"Africa/Lubumbashi",
    "iso:country":"CD",
    "name:und_x_variant":[
        "Kayeye"
    ],
    "wof:name":"Kabayeye",
    "wof:placetype":"locality"
},
  "geometry": {"coordinates":[26.51066,-4.18705],"type":"Point"}
}