{
  "type": "Feature",
  "properties": {
    "gn:admin1_code":"27.0",
    "gn:asciiname":"Kumedjonge",
    "gn:country_code":"CD",
    "gn:dem":554,
    "gn:feature_class":"P",
    "gn:feature_code":"PPL",
    "gn:name":"Kumedjonge",
    "gn:population":0,
    "gn:timezone":"Africa/Lubumbashi",
    "iso:country":"CD",
    "wof:name":"Kumedjonge",
    "wof:placetype":"locality"
},
  "geometry": {"coordinates":[23.72847,-3.09984],"type":"Point"}
}