{
  "type": "Feature",
  "properties": {
    "gn:admin1_code":"30.0",
    "gn:asciiname":"Bomisa",
    "gn:country_code":"CD",
    "gn:dem":471,
    "gn:feature_class":"P",
    "gn:feature_code":"PPL",
    "gn:name":"Bomisa",
    "gn:population":0,
    "gn:timezone":"Africa/Lubumbashi",
    "iso:country":"CD",
    "wof:name":"Bomisa",
    "wof:placetype":"locality"
},
  "geometry": {"coordinates":[25.33468,2.00489],"type":"Point"}
}