{
  "type": "Feature",
  "properties": {
    "gn:admin1_code":"22.0",
    "gn:asciiname":"Tshitumba",
    "gn:country_code":"CD",
    "gn:dem":904,
    "gn:feature_class":"P",
    "gn:feature_code":"PPL",
    "gn:name":"Tshitumba",
    "gn:population":0,
    "gn:timezone":"Africa/Lubumbashi",
    "iso:country":"CD",
    "wof:name":"Tshitumba",
    "wof:placetype":"locality"
},
  "geometry": {"coordinates":[22.74467000000001,-8.09387],"type":"Point"}
}