{
  "type": "Feature",
  "properties": {
    "gn:admin1_code":"10.0",
    "gn:asciiname":"Amundala",
    "gn:country_code":"CD",
    "gn:dem":648,
    "gn:feature_class":"P",
    "gn:feature_code":"PPL",
    "gn:name":"Amundala",
    "gn:population":0,
    "gn:timezone":"Africa/Lubumbashi",
    "iso:country":"CD",
    "wof:name":"Amundala",
    "wof:placetype":"locality"
},
  "geometry": {"coordinates":[27.39765,-4.76489],"type":"Point"}
}