{
  "type": "Feature",
  "properties": {
    "gn:admin1_code":"14.0",
    "gn:asciiname":"Lukonzolwa",
    "gn:country_code":"CD",
    "gn:dem":1048,
    "gn:feature_class":"P",
    "gn:feature_code":"PPL",
    "gn:name":"Lukonzolwa",
    "gn:population":0,
    "gn:timezone":"Africa/Lubumbashi",
    "iso:country":"CD",
    "wof:name":"Lukonzolwa",
    "wof:placetype":"locality"
},
  "geometry": {"coordinates":[28.63496,-8.78061],"type":"Point"}
}