{
  "type": "Feature",
  "properties": {
    "gn:admin1_code":"29.0",
    "gn:asciiname":"Ankoro",
    "gn:country_code":"CD",
    "gn:dem":589,
    "gn:feature_class":"P",
    "gn:feature_code":"PPL",
    "gn:name":"Ankoro",
    "gn:population":0,
    "gn:timezone":"Africa/Lubumbashi",
    "iso:country":"CD",
    "name:fra_x_preferred":[
        "Ankoro"
    ],
    "name:kab_x_preferred":[
        "Ankoro"
    ],
    "wof:name":"Ankoro",
    "wof:placetype":"locality"
},
  "geometry": {"coordinates":[26.94401,-6.75023],"type":"Point"}
}