{
  "type": "Feature",
  "properties": {
    "gn:admin1_code":"8.0",
    "gn:asciiname":"Nkumba",
    "gn:country_code":"CD",
    "gn:dem":551,
    "gn:feature_class":"P",
    "gn:feature_code":"PPL",
    "gn:name":"Nkumba",
    "gn:population":0,
    "gn:timezone":"Africa/Kinshasa",
    "iso:country":"CD",
    "name:und_x_variant":[
        "Kumba"
    ],
    "wof:name":"Nkumba",
    "wof:placetype":"locality"
},
  "geometry": {"coordinates":[14.98556,-5.20703],"type":"Point"}
}