{
  "type": "Feature",
  "properties": {
    "gn:admin1_code":"17.0",
    "gn:asciiname":"Manlobe",
    "gn:country_code":"CD",
    "gn:dem":1033,
    "gn:feature_class":"P",
    "gn:feature_code":"PPL",
    "gn:name":"Manlobe",
    "gn:population":0,
    "gn:timezone":"Africa/Lubumbashi",
    "iso:country":"CD",
    "name:fra_x_preferred":[
        "Manlobe"
    ],
    "wof:name":"Manlobe",
    "wof:placetype":"locality"
},
  "geometry": {"coordinates":[29.6684,1.15549],"type":"Point"}
}