{
  "type": "Feature",
  "properties": {
    "gn:admin1_code":"13.0",
    "gn:asciiname":"Melume",
    "gn:country_code":"CD",
    "gn:dem":452,
    "gn:feature_class":"P",
    "gn:feature_code":"PPL",
    "gn:name":"Melume",
    "gn:population":0,
    "gn:timezone":"Africa/Lubumbashi",
    "iso:country":"CD",
    "wof:name":"Melume",
    "wof:placetype":"locality"
},
  "geometry": {"coordinates":[24.93335,2.96938],"type":"Point"}
}