{
  "type": "Feature",
  "properties": {
    "gn:admin1_code":"10.0",
    "gn:asciiname":"Mbulu",
    "gn:country_code":"CD",
    "gn:dem":706,
    "gn:feature_class":"P",
    "gn:feature_code":"PPL",
    "gn:name":"Mbulu",
    "gn:population":0,
    "gn:timezone":"Africa/Lubumbashi",
    "iso:country":"CD",
    "name:deu_x_preferred":[
        "Mbulu"
    ],
    "name:ell_x_preferred":[
        "\u039c\u03c0\u03bf\u03cd\u03bb\u03bf\u03c5"
    ],
    "name:swa_x_preferred":[
        "Mbulu mjini"
    ],
    "name:ukr_x_preferred":[
        "\u041c\u0431\u0443\u043b\u0443"
    ],
    "name:vie_x_preferred":[
        "Mbulu"
    ],
    "wof:name":"Mbulu",
    "wof:placetype":"locality"
},
  "geometry": {"coordinates":[28.13333,-4.31667],"type":"Point"}
}