{
  "type": "Feature",
  "properties": {
    "gn:admin1_code":"19.0",
    "gn:asciiname":"Nampasa-Mutelembe",
    "gn:country_code":"CD",
    "gn:dem":1067,
    "gn:feature_class":"P",
    "gn:feature_code":"PPL",
    "gn:name":"Nampasa-Mutelembe",
    "gn:population":0,
    "gn:timezone":"Africa/Kinshasa",
    "iso:country":"CD",
    "name:und_x_variant":[
        "Nampasa",
        "Nampasa-Mutelembe"
    ],
    "wof:name":"Nampasa-Mutelembe",
    "wof:placetype":"locality"
},
  "geometry": {"coordinates":[19.06366,-7.53691],"type":"Point"}
}