{
  "type": "Feature",
  "properties": {
    "gn:admin1_code":"12.0",
    "gn:asciiname":"Kakungu-Kahamba",
    "gn:country_code":"CD",
    "gn:dem":1098,
    "gn:feature_class":"P",
    "gn:feature_code":"PPL",
    "gn:name":"Kakungu-Kahamba",
    "gn:population":0,
    "gn:timezone":"Africa/Lubumbashi",
    "iso:country":"CD",
    "name:und_x_variant":[
        "Kakungu Kahamba",
        "Kakungu-Kahamba"
    ],
    "wof:name":"Kakungu-Kahamba",
    "wof:placetype":"locality"
},
  "geometry": {"coordinates":[28.80556,-4.39722],"type":"Point"}
}