{
  "type": "Feature",
  "properties": {
    "gn:admin1_code":"13.0",
    "gn:asciiname":"Liko",
    "gn:country_code":"CD",
    "gn:dem":672,
    "gn:feature_class":"P",
    "gn:feature_code":"PPL",
    "gn:name":"Liko",
    "gn:population":0,
    "gn:timezone":"Africa/Lubumbashi",
    "iso:country":"CD",
    "name:swe_x_preferred":[
        "Liko"
    ],
    "wof:name":"Liko",
    "wof:placetype":"locality"
},
  "geometry": {"coordinates":[26.06709,4.63692],"type":"Point"}
}