{
  "type": "Feature",
  "properties": {
    "gn:admin1_code":"22.0",
    "gn:asciiname":"Kamungu",
    "gn:country_code":"CD",
    "gn:dem":1306,
    "gn:feature_class":"P",
    "gn:feature_code":"PPL",
    "gn:name":"Kamungu",
    "gn:population":0,
    "gn:timezone":"Africa/Lubumbashi",
    "iso:country":"CD",
    "wof:name":"Kamungu",
    "wof:placetype":"locality"
},
  "geometry": {"coordinates":[26.13897,-10.81835],"type":"Point"}
}