{
  "type": "Feature",
  "properties": {
    "gn:admin1_code":"16.0",
    "gn:asciiname":"Mondoyi-Marabi",
    "gn:country_code":"CD",
    "gn:dem":905,
    "gn:feature_class":"P",
    "gn:feature_code":"PPL",
    "gn:name":"Mondoyi-Marabi",
    "gn:population":0,
    "gn:timezone":"Africa/Lubumbashi",
    "iso:country":"CD",
    "wof:name":"Mondoyi-Marabi",
    "wof:placetype":"locality"
},
  "geometry": {"coordinates":[29.6868,3.16188],"type":"Point"}
}