{
  "type": "Feature",
  "properties": {
    "gn:admin1_code":"19.0",
    "gn:asciiname":"Mosango",
    "gn:country_code":"CD",
    "gn:dem":489,
    "gn:feature_class":"P",
    "gn:feature_code":"PPL",
    "gn:name":"Mosango",
    "gn:population":0,
    "gn:timezone":"Africa/Kinshasa",
    "iso:country":"CD",
    "wof:name":"Mosango",
    "wof:placetype":"locality"
},
  "geometry": {"coordinates":[17.58308,-4.52015],"type":"Point"}
}