{
  "type": "Feature",
  "properties": {
    "gn:admin1_code":"4.0",
    "gn:asciiname":"Lusasa",
    "gn:country_code":"CD",
    "gn:dem":779,
    "gn:feature_class":"P",
    "gn:feature_code":"PPL",
    "gn:name":"Lusasa",
    "gn:population":0,
    "gn:timezone":"Africa/Lubumbashi",
    "iso:country":"CD",
    "wof:name":"Lusasa",
    "wof:placetype":"locality"
},
  "geometry": {"coordinates":[22.97539,-6.04937],"type":"Point"}
}