{
  "type": "Feature",
  "properties": {
    "gn:admin1_code":"25.0",
    "gn:asciiname":"Gundji",
    "gn:country_code":"CD",
    "gn:dem":347,
    "gn:feature_class":"P",
    "gn:feature_code":"PPL",
    "gn:name":"Gundji",
    "gn:population":0,
    "gn:timezone":"Africa/Kinshasa",
    "iso:country":"CD",
    "wof:name":"Gundji",
    "wof:placetype":"locality"
},
  "geometry": {"coordinates":[21.19348,1.88096],"type":"Point"}
}