{
  "type": "Feature",
  "properties": {
    "gn:admin1_code":"8.0",
    "gn:asciiname":"Luangu",
    "gn:country_code":"CD",
    "gn:dem":570,
    "gn:feature_class":"P",
    "gn:feature_code":"PPL",
    "gn:name":"Luangu",
    "gn:population":0,
    "gn:timezone":"Africa/Kinshasa",
    "iso:country":"CD",
    "wof:name":"Luangu",
    "wof:placetype":"locality"
},
  "geometry": {"coordinates":[14.07356,-4.65969],"type":"Point"}
}