{
  "type": "Feature",
  "properties": {
    "gn:admin1_code":"12.0",
    "gn:asciiname":"Rambo",
    "gn:country_code":"CD",
    "gn:dem":1494,
    "gn:feature_class":"P",
    "gn:feature_code":"PPL",
    "gn:name":"Rambo",
    "gn:population":0,
    "gn:timezone":"Africa/Lubumbashi",
    "iso:country":"CD",
    "wof:name":"Rambo",
    "wof:placetype":"locality"
},
  "geometry": {"coordinates":[29.04428,-2.21402],"type":"Point"}
}