{
  "type": "Feature",
  "properties": {
    "gn:admin1_code":"12.0",
    "gn:asciiname":"Rambo",
    "gn:country_code":"CD",
    "gn:dem":1494,
    "gn:feature_class":"P",
    "gn:feature_code":"PPL",
    "gn:name":"Rambo",
    "gn:population":0,
    "gn:timezone":"Africa/Lubumbashi",
    "iso:country":"CD",
    "name:ara_x_preferred":[
        "\u0631\u0627\u0645\u0628\u0648"
    ],
    "name:ben_x_preferred":[
        "\u09b0\u200c\u09cd\u09af\u09be\u09ae\u09cd\u09ac\u09cb"
    ],
    "name:ceb_x_preferred":[
        "Rambo"
    ],
    "name:ces_x_preferred":[
        "Rambo"
    ],
    "name:deu_x_preferred":[
        "Rambo"
    ],
    "name:eus_x_preferred":[
        "Rambo"
    ],
    "name:fas_x_preferred":[
        "\u0631\u0645\u0628\u0648"
    ],
    "name:fin_x_preferred":[
        "Rambo"
    ],
    "name:fra_x_preferred":[
        "Rambo"
    ],
    "name:heb_x_preferred":[
        "\u05e8\u05de\u05d1\u05d5"
    ],
    "name:ita_x_preferred":[
        "Rambo"
    ],
    "name:nld_x_preferred":[
        "Rambo"
    ],
    "name:pol_x_preferred":[
        "Rambo"
    ],
    "name:por_x_preferred":[
        "Rambo"
    ],
    "name:ron_x_preferred":[
        "Rambo"
    ],
    "name:rus_x_preferred":[
        "\u0420\u0435\u043c\u0431\u043e"
    ],
    "name:swe_x_preferred":[
        "Rambo"
    ],
    "name:tha_x_preferred":[
        "\u0e41\u0e23\u0e21\u0e42\u0e1a\u0e49"
    ],
    "name:tur_x_preferred":[
        "Rambo"
    ],
    "name:ukr_x_preferred":[
        "\u0420\u0435\u043c\u0431\u043e"
    ],
    "wof:name":"Rambo",
    "wof:placetype":"locality"
},
  "geometry": {"coordinates":[29.04428,-2.21402],"type":"Point"}
}