{
  "type": "Feature",
  "properties": {
    "gn:admin1_code":"8.0",
    "gn:asciiname":"Kisuan",
    "gn:country_code":"CD",
    "gn:dem":481,
    "gn:feature_class":"P",
    "gn:feature_code":"PPL",
    "gn:name":"Kisuan",
    "gn:population":0,
    "gn:timezone":"Africa/Kinshasa",
    "iso:country":"CD",
    "wof:name":"Kisuan",
    "wof:placetype":"locality"
},
  "geometry": {"coordinates":[14.87258,-5.54091],"type":"Point"}
}