{
  "type": "Feature",
  "properties": {
    "gn:admin1_code":"11.0",
    "gn:asciiname":"Venamba",
    "gn:country_code":"CD",
    "gn:dem":2046,
    "gn:feature_class":"P",
    "gn:feature_code":"PPL",
    "gn:name":"Venamba",
    "gn:population":0,
    "gn:timezone":"Africa/Lubumbashi",
    "iso:country":"CD",
    "name:und_x_variant":[
        "Vehemba",
        "Wehamba",
        "Veamba",
        "Vehamba",
        "Venamba"
    ],
    "wof:name":"Venamba",
    "wof:placetype":"locality"
},
  "geometry": {"coordinates":[29.44574,0.02725],"type":"Point"}
}