{
  "type": "Feature",
  "properties": {
    "gn:admin1_code":"16.0",
    "gn:asciiname":"Anzabowa",
    "gn:country_code":"CD",
    "gn:dem":770,
    "gn:feature_class":"P",
    "gn:feature_code":"PPL",
    "gn:name":"Anzabowa",
    "gn:population":0,
    "gn:timezone":"Africa/Lubumbashi",
    "iso:country":"CD",
    "name:und_x_variant":[
        "Anzaboa",
        "Anzabowa"
    ],
    "wof:name":"Anzabowa",
    "wof:placetype":"locality"
},
  "geometry": {"coordinates":[27.77005,2.06574],"type":"Point"}
}