{
  "type": "Feature",
  "properties": {
    "gn:admin1_code":"27.0",
    "gn:asciiname":"Mwana Miko",
    "gn:country_code":"CD",
    "gn:dem":536,
    "gn:feature_class":"P",
    "gn:feature_code":"PPL",
    "gn:name":"Mwana Miko",
    "gn:population":0,
    "gn:timezone":"Africa/Lubumbashi",
    "iso:country":"CD",
    "wof:name":"Mwana Miko",
    "wof:placetype":"locality"
},
  "geometry": {"coordinates":[23.79881,-5.03946],"type":"Point"}
}