{
  "type": "Feature",
  "properties": {
    "gn:admin1_code":"18.0",
    "gn:asciiname":"Bena-Makuba",
    "gn:country_code":"CD",
    "gn:dem":583,
    "gn:feature_class":"P",
    "gn:feature_code":"PPL",
    "gn:name":"Bena-Makuba",
    "gn:population":0,
    "gn:timezone":"Africa/Lubumbashi",
    "iso:country":"CD",
    "wof:name":"Bena-Makuba",
    "wof:placetype":"locality"
},
  "geometry": {"coordinates":[20.48692,-4.67153],"type":"Point"}
}