{
  "type": "Feature",
  "properties": {
    "gn:admin1_code":"15.0",
    "gn:asciiname":"Lukaya",
    "gn:country_code":"CD",
    "gn:dem":1068,
    "gn:feature_class":"P",
    "gn:feature_code":"PPL",
    "gn:name":"Lukaya",
    "gn:population":0,
    "gn:timezone":"Africa/Lubumbashi",
    "iso:country":"CD",
    "name:ceb_x_preferred":[
        "Lukaya"
    ],
    "name:fra_x_preferred":[
        "Lukaya"
    ],
    "name:swe_x_preferred":[
        "Lukaya"
    ],
    "wof:name":"Lukaya",
    "wof:placetype":"locality"
},
  "geometry": {"coordinates":[25.06667,-8.28333],"type":"Point"}
}