{
  "type": "Feature",
  "properties": {
    "gn:admin1_code":"16.0",
    "gn:asciiname":"Siambobolo",
    "gn:country_code":"CD",
    "gn:dem":699,
    "gn:feature_class":"P",
    "gn:feature_code":"PPL",
    "gn:name":"Siambobolo",
    "gn:population":0,
    "gn:timezone":"Africa/Lubumbashi",
    "iso:country":"CD",
    "wof:name":"Siambobolo",
    "wof:placetype":"locality"
},
  "geometry": {"coordinates":[27.35075,4.49677],"type":"Point"}
}