{
  "type": "Feature",
  "properties": {
    "gn:admin1_code":"27.0",
    "gn:asciiname":"Uvungu",
    "gn:country_code":"CD",
    "gn:dem":515,
    "gn:feature_class":"P",
    "gn:feature_code":"PPL",
    "gn:name":"Uvungu",
    "gn:population":0,
    "gn:timezone":"Africa/Lubumbashi",
    "iso:country":"CD",
    "name:und_x_variant":[
        "Avungu",
        "Uvungu"
    ],
    "wof:name":"Uvungu",
    "wof:placetype":"locality"
},
  "geometry": {"coordinates":[24.24758,-3.70742],"type":"Point"}
}