{
  "type": "Feature",
  "properties": {
    "gn:admin1_code":"24.0",
    "gn:asciiname":"Bokole",
    "gn:country_code":"CD",
    "gn:dem":322,
    "gn:feature_class":"P",
    "gn:feature_code":"PPL",
    "gn:name":"Bokole",
    "gn:population":0,
    "gn:timezone":"Africa/Kinshasa",
    "iso:country":"CD",
    "wof:name":"Bokole",
    "wof:placetype":"locality"
},
  "geometry": {"coordinates":[17.65,-1.53333],"type":"Point"}
}