{
  "type": "Feature",
  "properties": {
    "gn:admin1_code":"16.0",
    "gn:asciiname":"Matikwandre",
    "gn:country_code":"CD",
    "gn:dem":813,
    "gn:feature_class":"P",
    "gn:feature_code":"PPL",
    "gn:name":"Matikwandre",
    "gn:population":0,
    "gn:timezone":"Africa/Lubumbashi",
    "iso:country":"CD",
    "wof:name":"Matikwandre",
    "wof:placetype":"locality"
},
  "geometry": {"coordinates":[29.54668,3.31991],"type":"Point"}
}