{
  "type": "Feature",
  "properties": {
    "gn:admin1_code":"22.0",
    "gn:asciiname":"Nasamba",
    "gn:country_code":"CD",
    "gn:dem":1100,
    "gn:feature_class":"P",
    "gn:feature_code":"PPL",
    "gn:name":"Nasamba",
    "gn:population":0,
    "gn:timezone":"Africa/Lubumbashi",
    "iso:country":"CD",
    "wof:name":"Nasamba",
    "wof:placetype":"locality"
},
  "geometry": {"coordinates":[22.69573,-10.60627],"type":"Point"}
}