{
  "type": "Feature",
  "properties": {
    "gn:admin1_code":"2.0",
    "gn:asciiname":"Bolima",
    "gn:country_code":"CD",
    "gn:dem":342,
    "gn:feature_class":"P",
    "gn:feature_code":"PPL",
    "gn:name":"Bolima",
    "gn:population":0,
    "gn:timezone":"Africa/Kinshasa",
    "iso:country":"CD",
    "wof:name":"Bolima",
    "wof:placetype":"locality"
},
  "geometry": {"coordinates":[18.7381,-0.23541],"type":"Point"}
}