{
  "type": "Feature",
  "properties": {
    "gn:admin1_code":"8.0",
    "gn:asciiname":"Kimbaka",
    "gn:country_code":"CD",
    "gn:dem":929,
    "gn:feature_class":"P",
    "gn:feature_code":"PPL",
    "gn:name":"Kimbaka",
    "gn:population":0,
    "gn:timezone":"Africa/Kinshasa",
    "iso:country":"CD",
    "wof:name":"Kimbaka",
    "wof:placetype":"locality"
},
  "geometry": {"coordinates":[15.88631,-5.72947],"type":"Point"}
}