{
  "type": "Feature",
  "properties": {
    "gn:admin1_code":"11.0",
    "gn:asciiname":"Kabatwa",
    "gn:country_code":"CD",
    "gn:dem":1015,
    "gn:feature_class":"P",
    "gn:feature_code":"PPL",
    "gn:name":"Kabatwa",
    "gn:population":0,
    "gn:timezone":"Africa/Lubumbashi",
    "iso:country":"CD",
    "wof:name":"Kabatwa",
    "wof:placetype":"locality"
},
  "geometry": {"coordinates":[29.7091,0.36585],"type":"Point"}
}