{
  "type": "Feature",
  "properties": {
    "gn:admin1_code":"23.0",
    "gn:asciiname":"Dikasa",
    "gn:country_code":"CD",
    "gn:dem":819,
    "gn:feature_class":"P",
    "gn:feature_code":"PPL",
    "gn:name":"Dikasa",
    "gn:population":0,
    "gn:timezone":"Africa/Lubumbashi",
    "iso:country":"CD",
    "wof:name":"Dikasa",
    "wof:placetype":"locality"
},
  "geometry": {"coordinates":[22.67488,-6.455],"type":"Point"}
}