{
  "type": "Feature",
  "properties": {
    "gn:admin1_code":"14.0",
    "gn:asciiname":"Kipata-Kibamba",
    "gn:country_code":"CD",
    "gn:dem":987,
    "gn:feature_class":"P",
    "gn:feature_code":"PPL",
    "gn:name":"Kipata-Kibamba",
    "gn:population":0,
    "gn:timezone":"Africa/Lubumbashi",
    "iso:country":"CD",
    "wof:name":"Kipata-Kibamba",
    "wof:placetype":"locality"
},
  "geometry": {"coordinates":[28.5667,-8.50824],"type":"Point"}
}