{
  "type": "Feature",
  "properties": {
    "gn:admin1_code":"27.0",
    "gn:asciiname":"Sangale",
    "gn:country_code":"CD",
    "gn:dem":498,
    "gn:feature_class":"P",
    "gn:feature_code":"PPL",
    "gn:name":"Sangale",
    "gn:population":0,
    "gn:timezone":"Africa/Lubumbashi",
    "iso:country":"CD",
    "name:und_x_variant":[
        "Sangaie"
    ],
    "wof:name":"Sangale",
    "wof:placetype":"locality"
},
  "geometry": {"coordinates":[23.51337,-4.98989],"type":"Point"}
}