{
  "type": "Feature",
  "properties": {
    "gn:admin1_code":"29.0",
    "gn:asciiname":"Lumba-Kahenia",
    "gn:country_code":"CD",
    "gn:dem":749,
    "gn:feature_class":"P",
    "gn:feature_code":"PPL",
    "gn:name":"Lumba-Kahenia",
    "gn:population":0,
    "gn:timezone":"Africa/Lubumbashi",
    "iso:country":"CD",
    "wof:name":"Lumba-Kahenia",
    "wof:placetype":"locality"
},
  "geometry": {"coordinates":[28.55194,-5.06944],"type":"Point"}
}