{
  "type": "Feature",
  "properties": {
    "gn:admin1_code":"13.0",
    "gn:asciiname":"Liongoda",
    "gn:country_code":"CD",
    "gn:dem":689,
    "gn:feature_class":"P",
    "gn:feature_code":"PPL",
    "gn:name":"Liongoda",
    "gn:population":0,
    "gn:timezone":"Africa/Lubumbashi",
    "iso:country":"CD",
    "wof:name":"Liongoda",
    "wof:placetype":"locality"
},
  "geometry": {"coordinates":[26.65537,3.47071],"type":"Point"}
}