{
  "type": "Feature",
  "properties": {
    "gn:admin1_code":"23.0",
    "gn:asciiname":"Kabuita",
    "gn:country_code":"CD",
    "gn:dem":880,
    "gn:feature_class":"P",
    "gn:feature_code":"PPL",
    "gn:name":"Kabuita",
    "gn:population":0,
    "gn:timezone":"Africa/Lubumbashi",
    "iso:country":"CD",
    "wof:name":"Kabuita",
    "wof:placetype":"locality"
},
  "geometry": {"coordinates":[22.2356,-7.35182],"type":"Point"}
}