{
  "type": "Feature",
  "properties": {
    "gn:admin1_code":"22.0",
    "gn:asciiname":"Ndemba",
    "gn:country_code":"CD",
    "gn:dem":1067,
    "gn:feature_class":"P",
    "gn:feature_code":"PPL",
    "gn:name":"Ndemba",
    "gn:population":0,
    "gn:timezone":"Africa/Lubumbashi",
    "iso:country":"CD",
    "wof:name":"Ndemba",
    "wof:placetype":"locality"
},
  "geometry": {"coordinates":[22.22394,-9.8634],"type":"Point"}
}