{
  "type": "Feature",
  "properties": {
    "gn:admin1_code":"23.0",
    "gn:asciiname":"Kamuanga-Mafuta",
    "gn:country_code":"CD",
    "gn:dem":771,
    "gn:feature_class":"P",
    "gn:feature_code":"PPL",
    "gn:name":"Kamuanga-Mafuta",
    "gn:population":0,
    "gn:timezone":"Africa/Lubumbashi",
    "iso:country":"CD",
    "wof:name":"Kamuanga-Mafuta",
    "wof:placetype":"locality"
},
  "geometry": {"coordinates":[21.67408,-6.66478],"type":"Point"}
}