{
  "type": "Feature",
  "properties": {
    "gn:admin1_code":"16.0",
    "gn:asciiname":"Mobongotongo",
    "gn:country_code":"CD",
    "gn:dem":770,
    "gn:feature_class":"P",
    "gn:feature_code":"PPL",
    "gn:name":"Mobongotongo",
    "gn:population":0,
    "gn:timezone":"Africa/Lubumbashi",
    "iso:country":"CD",
    "wof:name":"Mobongotongo",
    "wof:placetype":"locality"
},
  "geometry": {"coordinates":[27.79046,2.17936],"type":"Point"}
}