{
  "type": "Feature",
  "properties": {
    "gn:admin1_code":"20.0",
    "gn:asciiname":"Madimbi",
    "gn:country_code":"CD",
    "gn:dem":603,
    "gn:feature_class":"P",
    "gn:feature_code":"PPL",
    "gn:name":"Madimbi",
    "gn:population":0,
    "gn:timezone":"Africa/Kinshasa",
    "iso:country":"CD",
    "wof:name":"Madimbi",
    "wof:placetype":"locality"
},
  "geometry": {"coordinates":[19.91835,-5.58291],"type":"Point"}
}