{
  "type": "Feature",
  "properties": {
    "gn:admin1_code":"23.0",
    "gn:asciiname":"Kanyinda",
    "gn:country_code":"CD",
    "gn:dem":695,
    "gn:feature_class":"P",
    "gn:feature_code":"PPL",
    "gn:name":"Kanyinda",
    "gn:population":0,
    "gn:timezone":"Africa/Lubumbashi",
    "iso:country":"CD",
    "wof:name":"Kanyinda",
    "wof:placetype":"locality"
},
  "geometry": {"coordinates":[22.35814,-6.10678],"type":"Point"}
}