{
  "type": "Feature",
  "properties": {
    "gn:admin1_code":"17.0",
    "gn:asciiname":"Djokwa",
    "gn:country_code":"CD",
    "gn:dem":1760,
    "gn:feature_class":"P",
    "gn:feature_code":"PPL",
    "gn:name":"Djokwa",
    "gn:population":0,
    "gn:timezone":"Africa/Lubumbashi",
    "iso:country":"CD",
    "wof:name":"Djokwa",
    "wof:placetype":"locality"
},
  "geometry": {"coordinates":[30.63234000000001,1.99637],"type":"Point"}
}