{
  "type": "Feature",
  "properties": {
    "gn:admin1_code":"22.0",
    "gn:asciiname":"Musefu",
    "gn:country_code":"CD",
    "gn:dem":1010,
    "gn:feature_class":"P",
    "gn:feature_code":"PPL",
    "gn:name":"Musefu",
    "gn:population":0,
    "gn:timezone":"Africa/Lubumbashi",
    "iso:country":"CD",
    "name:fra_x_preferred":[
        "Musefu"
    ],
    "name:ita_x_preferred":[
        "Musefu"
    ],
    "name:lin_x_preferred":[
        "Musefu"
    ],
    "wof:name":"Musefu",
    "wof:placetype":"locality"
},
  "geometry": {"coordinates":[22.748,-9.90286],"type":"Point"}
}