{
  "type": "Feature",
  "properties": {
    "gn:admin1_code":"16.0",
    "gn:asciiname":"Kongbo",
    "gn:country_code":"CD",
    "gn:dem":1142,
    "gn:feature_class":"P",
    "gn:feature_code":"PPL",
    "gn:name":"Kongbo",
    "gn:population":0,
    "gn:timezone":"Africa/Lubumbashi",
    "iso:country":"CD",
    "wof:name":"Kongbo",
    "wof:placetype":"locality"
},
  "geometry": {"coordinates":[29.77187,2.73281],"type":"Point"}
}