{
  "type": "Feature",
  "properties": {
    "gn:admin1_code":"14.0",
    "gn:asciiname":"Mufunta",
    "gn:country_code":"CD",
    "gn:dem":1258,
    "gn:feature_class":"P",
    "gn:feature_code":"PPL",
    "gn:name":"Mufunta",
    "gn:population":0,
    "gn:timezone":"Africa/Lubumbashi",
    "iso:country":"CD",
    "name:und_x_variant":[
        "Mafunta",
        "Mufunta"
    ],
    "wof:name":"Mufunta",
    "wof:placetype":"locality"
},
  "geometry": {"coordinates":[27.66667,-11.76667],"type":"Point"}
}