{
  "type": "Feature",
  "properties": {
    "gn:admin1_code":"18.0",
    "gn:asciiname":"Kahembe",
    "gn:country_code":"CD",
    "gn:dem":630,
    "gn:feature_class":"P",
    "gn:feature_code":"PPL",
    "gn:name":"Kahembe",
    "gn:population":0,
    "gn:timezone":"Africa/Lubumbashi",
    "iso:country":"CD",
    "wof:name":"Kahembe",
    "wof:placetype":"locality"
},
  "geometry": {"coordinates":[20.37906,-6.24319],"type":"Point"}
}