{
  "type": "Feature",
  "properties": {
    "gn:admin1_code":"18.0",
    "gn:asciiname":"Muambinzo",
    "gn:country_code":"CD",
    "gn:dem":717,
    "gn:feature_class":"P",
    "gn:feature_code":"PPL",
    "gn:name":"Muambinzo",
    "gn:population":0,
    "gn:timezone":"Africa/Lubumbashi",
    "iso:country":"CD",
    "wof:name":"Muambinzo",
    "wof:placetype":"locality"
},
  "geometry": {"coordinates":[20.23466,-6.37406],"type":"Point"}
}