{
  "type": "Feature",
  "properties": {
    "gn:admin1_code":"16.0",
    "gn:asciiname":"Nebanaye",
    "gn:country_code":"CD",
    "gn:dem":734,
    "gn:feature_class":"P",
    "gn:feature_code":"PPL",
    "gn:name":"Nebanaye",
    "gn:population":0,
    "gn:timezone":"Africa/Lubumbashi",
    "iso:country":"CD",
    "wof:name":"Nebanaye",
    "wof:placetype":"locality"
},
  "geometry": {"coordinates":[27.40975,3.57444],"type":"Point"}
}