{
  "type": "Feature",
  "properties": {
    "gn:admin1_code":"24.0",
    "gn:asciiname":"Malundu",
    "gn:country_code":"CD",
    "gn:dem":353,
    "gn:feature_class":"P",
    "gn:feature_code":"PPL",
    "gn:name":"Malundu",
    "gn:population":0,
    "gn:timezone":"Africa/Kinshasa",
    "iso:country":"CD",
    "wof:name":"Malundu",
    "wof:placetype":"locality"
},
  "geometry": {"coordinates":[16.95839,-2.11272],"type":"Point"}
}