{
  "type": "Feature",
  "properties": {
    "gn:admin1_code":"23.0",
    "gn:asciiname":"Kalunge",
    "gn:country_code":"CD",
    "gn:dem":758,
    "gn:feature_class":"P",
    "gn:feature_code":"PPL",
    "gn:name":"Kalunge",
    "gn:population":0,
    "gn:timezone":"Africa/Lubumbashi",
    "iso:country":"CD",
    "wof:name":"Kalunge",
    "wof:placetype":"locality"
},
  "geometry": {"coordinates":[21.88019,-6.2233],"type":"Point"}
}