{
  "type": "Feature",
  "properties": {
    "gn:admin1_code":"30.0",
    "gn:asciiname":"Nionugolo",
    "gn:country_code":"CD",
    "gn:dem":492,
    "gn:feature_class":"P",
    "gn:feature_code":"PPL",
    "gn:name":"Nionugolo",
    "gn:population":0,
    "gn:timezone":"Africa/Lubumbashi",
    "iso:country":"CD",
    "wof:name":"Nionugolo",
    "wof:placetype":"locality"
},
  "geometry": {"coordinates":[25.62528,0.21306],"type":"Point"}
}