{
  "type": "Feature",
  "properties": {
    "gn:admin1_code":"22.0",
    "gn:asciiname":"Mukumbu",
    "gn:country_code":"CD",
    "gn:dem":709,
    "gn:feature_class":"P",
    "gn:feature_code":"PPL",
    "gn:name":"Mukumbu",
    "gn:population":0,
    "gn:timezone":"Africa/Lubumbashi",
    "iso:country":"CD",
    "wof:name":"Mukumbu",
    "wof:placetype":"locality"
},
  "geometry": {"coordinates":[25.52526,-9.66448],"type":"Point"}
}