{
  "type": "Feature",
  "properties": {
    "gn:admin1_code":"17.0",
    "gn:asciiname":"Ozuba",
    "gn:country_code":"CD",
    "gn:dem":1574,
    "gn:feature_class":"P",
    "gn:feature_code":"PPL",
    "gn:name":"Ozuba",
    "gn:population":0,
    "gn:timezone":"Africa/Lubumbashi",
    "iso:country":"CD",
    "wof:name":"Ozuba",
    "wof:placetype":"locality"
},
  "geometry": {"coordinates":[30.0218,1.21495],"type":"Point"}
}