{
  "type": "Feature",
  "properties": {
    "gn:admin1_code":"8.0",
    "gn:asciiname":"Banza-Ngoyo",
    "gn:country_code":"CD",
    "gn:dem":642,
    "gn:feature_class":"P",
    "gn:feature_code":"PPL",
    "gn:name":"Banza-Ngoyo",
    "gn:population":0,
    "gn:timezone":"Africa/Kinshasa",
    "iso:country":"CD",
    "wof:name":"Banza-Ngoyo",
    "wof:placetype":"locality"
},
  "geometry": {"coordinates":[14.52895,-5.12882],"type":"Point"}
}