{
  "type": "Feature",
  "properties": {
    "gn:admin1_code":"8.0",
    "gn:asciiname":"Nseka",
    "gn:country_code":"CD",
    "gn:dem":630,
    "gn:feature_class":"P",
    "gn:feature_code":"PPL",
    "gn:name":"Nseka",
    "gn:population":0,
    "gn:timezone":"Africa/Kinshasa",
    "iso:country":"CD",
    "wof:name":"Nseka",
    "wof:placetype":"locality"
},
  "geometry": {"coordinates":[14.61391,-5.07984],"type":"Point"}
}