{
  "type": "Feature",
  "properties": {
    "gn:admin1_code":"15.0",
    "gn:asciiname":"Waomeko",
    "gn:country_code":"CD",
    "gn:dem":1100,
    "gn:feature_class":"P",
    "gn:feature_code":"PPL",
    "gn:name":"Waomeko",
    "gn:population":0,
    "gn:timezone":"Africa/Lubumbashi",
    "iso:country":"CD",
    "name:und_x_variant":[
        "Wadmeko",
        "Waomeko"
    ],
    "wof:name":"Waomeko",
    "wof:placetype":"locality"
},
  "geometry": {"coordinates":[24.14712,-8.56013],"type":"Point"}
}