{
  "type": "Feature",
  "properties": {
    "gn:admin1_code":"4.0",
    "gn:asciiname":"Tshikui",
    "gn:country_code":"CD",
    "gn:dem":654,
    "gn:feature_class":"P",
    "gn:feature_code":"PPL",
    "gn:name":"Tshikui",
    "gn:population":0,
    "gn:timezone":"Africa/Lubumbashi",
    "iso:country":"CD",
    "name:und_x_variant":[
        "Tshikuy",
        "Tshikui"
    ],
    "wof:name":"Tshikui",
    "wof:placetype":"locality"
},
  "geometry": {"coordinates":[23.87604,-6.30425],"type":"Point"}
}