{
  "type": "Feature",
  "properties": {
    "gn:admin1_code":"14.0",
    "gn:asciiname":"Kiabwe",
    "gn:country_code":"CD",
    "gn:dem":1105,
    "gn:feature_class":"P",
    "gn:feature_code":"PPL",
    "gn:name":"Kiabwe",
    "gn:population":0,
    "gn:timezone":"Africa/Lubumbashi",
    "iso:country":"CD",
    "wof:name":"Kiabwe",
    "wof:placetype":"locality"
},
  "geometry": {"coordinates":[27.96164000000001,-8.38352],"type":"Point"}
}