{
  "type": "Feature",
  "properties": {
    "gn:admin1_code":"19.0",
    "gn:asciiname":"Sunza",
    "gn:country_code":"CD",
    "gn:dem":783,
    "gn:feature_class":"P",
    "gn:feature_code":"PPL",
    "gn:name":"Sunza",
    "gn:population":0,
    "gn:timezone":"Africa/Kinshasa",
    "iso:country":"CD",
    "wof:name":"Sunza",
    "wof:placetype":"locality"
},
  "geometry": {"coordinates":[18.1456,-6.11945],"type":"Point"}
}