{
  "type": "Feature",
  "properties": {
    "gn:admin1_code":"25.0",
    "gn:asciiname":"Yameke",
    "gn:country_code":"CD",
    "gn:dem":398,
    "gn:feature_class":"P",
    "gn:feature_code":"PPL",
    "gn:name":"Yameke",
    "gn:population":0,
    "gn:timezone":"Africa/Kinshasa",
    "iso:country":"CD",
    "wof:name":"Yameke",
    "wof:placetype":"locality"
},
  "geometry": {"coordinates":[22.48547,2.37501],"type":"Point"}
}