{
  "type": "Feature",
  "properties": {
    "gn:admin1_code":"22.0",
    "gn:asciiname":"Kapila",
    "gn:country_code":"CD",
    "gn:dem":932,
    "gn:feature_class":"P",
    "gn:feature_code":"PPL",
    "gn:name":"Kapila",
    "gn:population":0,
    "gn:timezone":"Africa/Lubumbashi",
    "iso:country":"CD",
    "wof:name":"Kapila",
    "wof:placetype":"locality"
},
  "geometry": {"coordinates":[22.58242000000001,-7.8788],"type":"Point"}
}