{
  "type": "Feature",
  "properties": {
    "gn:admin1_code":"15.0",
    "gn:asciiname":"Sobongo",
    "gn:country_code":"CD",
    "gn:dem":1115,
    "gn:feature_class":"P",
    "gn:feature_code":"PPL",
    "gn:name":"Sobongo",
    "gn:population":0,
    "gn:timezone":"Africa/Lubumbashi",
    "iso:country":"CD",
    "name:und_x_variant":[
        "Sobonga"
    ],
    "wof:name":"Sobongo",
    "wof:placetype":"locality"
},
  "geometry": {"coordinates":[24.95187,-8.73371],"type":"Point"}
}