{
  "type": "Feature",
  "properties": {
    "gn:admin1_code":"15.0",
    "gn:asciiname":"Kilomboye",
    "gn:country_code":"CD",
    "gn:dem":572,
    "gn:feature_class":"P",
    "gn:feature_code":"PPL",
    "gn:name":"Kilomboye",
    "gn:population":0,
    "gn:timezone":"Africa/Lubumbashi",
    "iso:country":"CD",
    "wof:name":"Kilomboye",
    "wof:placetype":"locality"
},
  "geometry": {"coordinates":[26.46613,-8.71608],"type":"Point"}
}