{
  "type": "Feature",
  "properties": {
    "gn:admin1_code":"21.0",
    "gn:asciiname":"Kangulube",
    "gn:country_code":"CD",
    "gn:dem":574,
    "gn:feature_class":"P",
    "gn:feature_code":"PPL",
    "gn:name":"Kangulube",
    "gn:population":0,
    "gn:timezone":"Africa/Lubumbashi",
    "iso:country":"CD",
    "wof:name":"Kangulube",
    "wof:placetype":"locality"
},
  "geometry": {"coordinates":[25.51667,-5.33333],"type":"Point"}
}