{
  "type": "Feature",
  "properties": {
    "gn:admin1_code":"8.0",
    "gn:asciiname":"Mukimbungu",
    "gn:country_code":"CD",
    "gn:dem":344,
    "gn:feature_class":"P",
    "gn:feature_code":"PPL",
    "gn:name":"Mukimbungu",
    "gn:population":0,
    "gn:timezone":"Africa/Kinshasa",
    "iso:country":"CD",
    "wof:name":"Mukimbungu",
    "wof:placetype":"locality"
},
  "geometry": {"coordinates":[14.03984,-5.14071],"type":"Point"}
}