{
  "type": "Feature",
  "properties": {
    "gn:admin1_code":"20.0",
    "gn:asciiname":"Binde",
    "gn:country_code":"CD",
    "gn:dem":507,
    "gn:feature_class":"P",
    "gn:feature_code":"PPL",
    "gn:name":"Binde",
    "gn:population":0,
    "gn:timezone":"Africa/Kinshasa",
    "iso:country":"CD",
    "name:ceb_x_preferred":[
        "Binde"
    ],
    "name:deu_x_preferred":[
        "Binde"
    ],
    "name:lav_x_preferred":[
        "Binde"
    ],
    "name:nld_x_preferred":[
        "Binde"
    ],
    "name:swe_x_preferred":[
        "Binde"
    ],
    "wof:name":"Binde",
    "wof:placetype":"locality"
},
  "geometry": {"coordinates":[19.89404,-4.85339],"type":"Point"}
}