{
  "type": "Feature",
  "properties": {
    "gn:admin1_code":"29.0",
    "gn:asciiname":"Kalezo",
    "gn:country_code":"CD",
    "gn:dem":2156,
    "gn:feature_class":"P",
    "gn:feature_code":"PPL",
    "gn:name":"Kalezo",
    "gn:population":0,
    "gn:timezone":"Africa/Lubumbashi",
    "iso:country":"CD",
    "wof:name":"Kalezo",
    "wof:placetype":"locality"
},
  "geometry": {"coordinates":[29.93404,-7.21997],"type":"Point"}
}