{
  "type": "Feature",
  "properties": {
    "gn:admin1_code":"20.0",
    "gn:asciiname":"Kimbwempi",
    "gn:country_code":"CD",
    "gn:dem":750,
    "gn:feature_class":"P",
    "gn:feature_code":"PPL",
    "gn:name":"Kimbwempi",
    "gn:population":0,
    "gn:timezone":"Africa/Kinshasa",
    "iso:country":"CD",
    "wof:name":"Kimbwempi",
    "wof:placetype":"locality"
},
  "geometry": {"coordinates":[19.33267,-5.56671],"type":"Point"}
}