{
  "type": "Feature",
  "properties": {
    "gn:admin1_code":"23.0",
    "gn:asciiname":"Biasamba",
    "gn:country_code":"CD",
    "gn:dem":747,
    "gn:feature_class":"P",
    "gn:feature_code":"PPL",
    "gn:name":"Biasamba",
    "gn:population":0,
    "gn:timezone":"Africa/Lubumbashi",
    "iso:country":"CD",
    "wof:name":"Biasamba",
    "wof:placetype":"locality"
},
  "geometry": {"coordinates":[21.89251,-7.232],"type":"Point"}
}