{
  "type": "Feature",
  "properties": {
    "gn:admin1_code":"19.0",
    "gn:asciiname":"Kiala",
    "gn:country_code":"CD",
    "gn:dem":717,
    "gn:feature_class":"P",
    "gn:feature_code":"PPL",
    "gn:name":"Kiala",
    "gn:population":0,
    "gn:timezone":"Africa/Kinshasa",
    "iso:country":"CD",
    "wof:name":"Kiala",
    "wof:placetype":"locality"
},
  "geometry": {"coordinates":[17.08333,-7.08333],"type":"Point"}
}