{
  "type": "Feature",
  "properties": {
    "gn:admin1_code":"8.0",
    "gn:asciiname":"Zengita",
    "gn:country_code":"CD",
    "gn:dem":627,
    "gn:feature_class":"P",
    "gn:feature_code":"PPL",
    "gn:name":"Zengita",
    "gn:population":0,
    "gn:timezone":"Africa/Kinshasa",
    "iso:country":"CD",
    "wof:name":"Zengita",
    "wof:placetype":"locality"
},
  "geometry": {"coordinates":[13.85332,-4.54213],"type":"Point"}
}