{
  "type": "Feature",
  "properties": {
    "gn:admin1_code":"21.0",
    "gn:asciiname":"Kabanga",
    "gn:country_code":"CD",
    "gn:dem":891,
    "gn:feature_class":"P",
    "gn:feature_code":"PPL",
    "gn:name":"Kabanga",
    "gn:population":0,
    "gn:timezone":"Africa/Lubumbashi",
    "iso:country":"CD",
    "name:ceb_x_preferred":[
        "Kabanga"
    ],
    "name:fra_x_preferred":[
        "Kabanga"
    ],
    "name:swe_x_preferred":[
        "Kabanga"
    ],
    "wof:name":"Kabanga",
    "wof:placetype":"locality"
},
  "geometry": {"coordinates":[24.95287,-6.61273],"type":"Point"}
}