{
  "type": "Feature",
  "properties": {
    "gn:admin1_code":"23.0",
    "gn:asciiname":"Bitande",
    "gn:country_code":"CD",
    "gn:dem":791,
    "gn:feature_class":"P",
    "gn:feature_code":"PPL",
    "gn:name":"Bitande",
    "gn:population":0,
    "gn:timezone":"Africa/Lubumbashi",
    "iso:country":"CD",
    "wof:name":"Bitande",
    "wof:placetype":"locality"
},
  "geometry": {"coordinates":[22.79567,-6.25988],"type":"Point"}
}