{
  "type": "Feature",
  "properties": {
    "gn:admin1_code":"31.0",
    "gn:asciiname":"Ekole",
    "gn:country_code":"CD",
    "gn:dem":382,
    "gn:feature_class":"P",
    "gn:feature_code":"PPL",
    "gn:name":"Ekole",
    "gn:population":0,
    "gn:timezone":"Africa/Kinshasa",
    "iso:country":"CD",
    "wof:name":"Ekole",
    "wof:placetype":"locality"
},
  "geometry": {"coordinates":[20.53333,0.05],"type":"Point"}
}