{
  "type": "Feature",
  "properties": {
    "gn:admin1_code":"25.0",
    "gn:asciiname":"Yanama",
    "gn:country_code":"CD",
    "gn:dem":415,
    "gn:feature_class":"P",
    "gn:feature_code":"PPL",
    "gn:name":"Yanama",
    "gn:population":0,
    "gn:timezone":"Africa/Kinshasa",
    "iso:country":"CD",
    "name:und_x_variant":[
        "Yapama"
    ],
    "name:zho_x_preferred":[
        "\u4e9e\u7d0d\u99ac\u5c71"
    ],
    "wof:name":"Yanama",
    "wof:placetype":"locality"
},
  "geometry": {"coordinates":[21.94193,2.79613],"type":"Point"}
}