{
  "type": "Feature",
  "properties": {
    "gn:admin1_code":"26.0",
    "gn:asciiname":"Tobe",
    "gn:country_code":"CD",
    "gn:dem":487,
    "gn:feature_class":"P",
    "gn:feature_code":"PPL",
    "gn:name":"Tobe",
    "gn:population":0,
    "gn:timezone":"Africa/Kinshasa",
    "iso:country":"CD",
    "name:ceb_x_preferred":[
        "Tobe"
    ],
    "name:deu_x_preferred":[
        "Tobe"
    ],
    "name:swe_x_preferred":[
        "Tobe"
    ],
    "wof:name":"Tobe",
    "wof:placetype":"locality"
},
  "geometry": {"coordinates":[22.46241,3.64746],"type":"Point"}
}