{
  "type": "Feature",
  "properties": {
    "gn:admin1_code":"8.0",
    "gn:asciiname":"Kingemba-Lona",
    "gn:country_code":"CD",
    "gn:dem":568,
    "gn:feature_class":"P",
    "gn:feature_code":"PPL",
    "gn:name":"Kingemba-Lona",
    "gn:population":0,
    "gn:timezone":"Africa/Kinshasa",
    "iso:country":"CD",
    "wof:name":"Kingemba-Lona",
    "wof:placetype":"locality"
},
  "geometry": {"coordinates":[15.94951,-5.7101],"type":"Point"}
}