{
  "type": "Feature",
  "properties": {
    "gn:admin1_code":"19.0",
    "gn:asciiname":"Kabwebwe",
    "gn:country_code":"CD",
    "gn:dem":1081,
    "gn:feature_class":"P",
    "gn:feature_code":"PPL",
    "gn:name":"Kabwebwe",
    "gn:population":0,
    "gn:timezone":"Africa/Kinshasa",
    "iso:country":"CD",
    "wof:name":"Kabwebwe",
    "wof:placetype":"locality"
},
  "geometry": {"coordinates":[19.13557,-7.70174],"type":"Point"}
}