{
  "type": "Feature",
  "properties": {
    "gn:admin1_code":"20.0",
    "gn:asciiname":"Fumubungu",
    "gn:country_code":"CD",
    "gn:dem":366,
    "gn:feature_class":"P",
    "gn:feature_code":"PPL",
    "gn:name":"Fumubungu",
    "gn:population":0,
    "gn:timezone":"Africa/Kinshasa",
    "iso:country":"CD",
    "wof:name":"Fumubungu",
    "wof:placetype":"locality"
},
  "geometry": {"coordinates":[18.83911,-4.71967],"type":"Point"}
}