{
  "type": "Feature",
  "properties": {
    "gn:admin1_code":"31.0",
    "gn:asciiname":"Bomeka-Moke",
    "gn:country_code":"CD",
    "gn:dem":419,
    "gn:feature_class":"P",
    "gn:feature_code":"PPL",
    "gn:name":"Bomeka-Moke",
    "gn:population":0,
    "gn:timezone":"Africa/Kinshasa",
    "iso:country":"CD",
    "wof:name":"Bomeka-Moke",
    "wof:placetype":"locality"
},
  "geometry": {"coordinates":[21.65,-0.21667],"type":"Point"}
}