{
  "type": "Feature",
  "properties": {
    "gn:admin1_code":"15.0",
    "gn:asciiname":"Nambia",
    "gn:country_code":"CD",
    "gn:dem":798,
    "gn:feature_class":"P",
    "gn:feature_code":"PPL",
    "gn:name":"Nambia",
    "gn:population":0,
    "gn:timezone":"Africa/Lubumbashi",
    "iso:country":"CD",
    "name:und_x_variant":[
        "Lambia",
        "Nambia"
    ],
    "wof:name":"Nambia",
    "wof:placetype":"locality"
},
  "geometry": {"coordinates":[27.28227,-8.16868],"type":"Point"}
}