{
  "type": "Feature",
  "properties": {
    "gn:admin1_code":"27.0",
    "gn:asciiname":"Longelimo",
    "gn:country_code":"CD",
    "gn:dem":509,
    "gn:feature_class":"P",
    "gn:feature_code":"PPL",
    "gn:name":"Longelimo",
    "gn:population":0,
    "gn:timezone":"Africa/Lubumbashi",
    "iso:country":"CD",
    "wof:name":"Longelimo",
    "wof:placetype":"locality"
},
  "geometry": {"coordinates":[24.79204,-3.14129],"type":"Point"}
}