{
  "type": "Feature",
  "properties": {
    "gn:admin1_code":"14.0",
    "gn:asciiname":"Kasombora",
    "gn:country_code":"CD",
    "gn:dem":1415,
    "gn:feature_class":"P",
    "gn:feature_code":"PPL",
    "gn:name":"Kasombora",
    "gn:population":0,
    "gn:timezone":"Africa/Lubumbashi",
    "iso:country":"CD",
    "wof:name":"Kasombora",
    "wof:placetype":"locality"
},
  "geometry": {"coordinates":[26.01869,-11.75796],"type":"Point"}
}