{
  "type": "Feature",
  "properties": {
    "gn:admin1_code":"4.0",
    "gn:asciiname":"Kwadi",
    "gn:country_code":"CD",
    "gn:dem":625,
    "gn:feature_class":"P",
    "gn:feature_code":"PPL",
    "gn:name":"Kwadi",
    "gn:population":0,
    "gn:timezone":"Africa/Lubumbashi",
    "iso:country":"CD",
    "name:und_x_variant":[
        "Mkwadi",
        "Kwadi"
    ],
    "wof:name":"Kwadi",
    "wof:placetype":"locality"
},
  "geometry": {"coordinates":[23.80175,-6.35663],"type":"Point"}
}