{
  "type": "Feature",
  "properties": {
    "gn:admin1_code":"19.0",
    "gn:asciiname":"Kizanga-Mibala",
    "gn:country_code":"CD",
    "gn:dem":832,
    "gn:feature_class":"P",
    "gn:feature_code":"PPL",
    "gn:name":"Kizanga-Mibala",
    "gn:population":0,
    "gn:timezone":"Africa/Kinshasa",
    "iso:country":"CD",
    "wof:name":"Kizanga-Mibala",
    "wof:placetype":"locality"
},
  "geometry": {"coordinates":[17.98785,-5.79349],"type":"Point"}
}