{
  "type": "Feature",
  "properties": {
    "gn:admin1_code":"12.0",
    "gn:asciiname":"Kankisu",
    "gn:country_code":"CD",
    "gn:dem":606,
    "gn:feature_class":"P",
    "gn:feature_code":"PPL",
    "gn:name":"Kankisu",
    "gn:population":0,
    "gn:timezone":"Africa/Lubumbashi",
    "iso:country":"CD",
    "wof:name":"Kankisu",
    "wof:placetype":"locality"
},
  "geometry": {"coordinates":[27.18571,-2.97113],"type":"Point"}
}