{
  "type": "Feature",
  "properties": {
    "gn:admin1_code":"21.0",
    "gn:asciiname":"Kaniange",
    "gn:country_code":"CD",
    "gn:dem":731,
    "gn:feature_class":"P",
    "gn:feature_code":"PPL",
    "gn:name":"Kaniange",
    "gn:population":0,
    "gn:timezone":"Africa/Lubumbashi",
    "iso:country":"CD",
    "wof:name":"Kaniange",
    "wof:placetype":"locality"
},
  "geometry": {"coordinates":[24.56963,-5.92873],"type":"Point"}
}