{
  "type": "Feature",
  "properties": {
    "gn:admin1_code":"2.0",
    "gn:asciiname":"Mokongo",
    "gn:country_code":"CD",
    "gn:dem":326,
    "gn:feature_class":"P",
    "gn:feature_code":"PPL",
    "gn:name":"Mokongo",
    "gn:population":0,
    "gn:timezone":"Africa/Kinshasa",
    "iso:country":"CD",
    "wof:name":"Mokongo",
    "wof:placetype":"locality"
},
  "geometry": {"coordinates":[18.23208,1.1631],"type":"Point"}
}