{
  "type": "Feature",
  "properties": {
    "gn:admin1_code":"8.0",
    "gn:asciiname":"Mbengo",
    "gn:country_code":"CD",
    "gn:dem":532,
    "gn:feature_class":"P",
    "gn:feature_code":"PPL",
    "gn:name":"Mbengo",
    "gn:population":0,
    "gn:timezone":"Africa/Kinshasa",
    "iso:country":"CD",
    "wof:name":"Mbengo",
    "wof:placetype":"locality"
},
  "geometry": {"coordinates":[15.05361,-4.73083],"type":"Point"}
}