{
  "type": "Feature",
  "properties": {
    "gn:admin1_code":"8.0",
    "gn:asciiname":"Noki",
    "gn:country_code":"CD",
    "gn:dem":502,
    "gn:feature_class":"P",
    "gn:feature_code":"PPL",
    "gn:name":"Noki",
    "gn:population":0,
    "gn:timezone":"Africa/Kinshasa",
    "iso:country":"CD",
    "wof:name":"Noki",
    "wof:placetype":"locality"
},
  "geometry": {"coordinates":[14.54909,-4.97355],"type":"Point"}
}