{
  "type": "Feature",
  "properties": {
    "gn:admin1_code":"29.0",
    "gn:asciiname":"Kibele",
    "gn:country_code":"CD",
    "gn:dem":617,
    "gn:feature_class":"P",
    "gn:feature_code":"PPL",
    "gn:name":"Kibele",
    "gn:population":0,
    "gn:timezone":"Africa/Lubumbashi",
    "iso:country":"CD",
    "wof:name":"Kibele",
    "wof:placetype":"locality"
},
  "geometry": {"coordinates":[27.36795,-5.49761],"type":"Point"}
}