{
  "type": "Feature",
  "properties": {
    "gn:admin1_code":"15.0",
    "gn:asciiname":"Kabiondo",
    "gn:country_code":"CD",
    "gn:dem":855,
    "gn:feature_class":"P",
    "gn:feature_code":"PPL",
    "gn:name":"Kabiondo",
    "gn:population":0,
    "gn:timezone":"Africa/Lubumbashi",
    "iso:country":"CD",
    "wof:name":"Kabiondo",
    "wof:placetype":"locality"
},
  "geometry": {"coordinates":[25.63333,-7.65],"type":"Point"}
}