{
  "type": "Feature",
  "properties": {
    "gn:admin1_code":"16.0",
    "gn:asciiname":"Vingumb'ya",
    "gn:country_code":"CD",
    "gn:dem":848,
    "gn:feature_class":"P",
    "gn:feature_code":"PPL",
    "gn:name":"Vingumb\u2019ya",
    "gn:population":0,
    "gn:timezone":"Africa/Lubumbashi",
    "iso:country":"CD",
    "wof:name":"Vingumb'ya",
    "wof:placetype":"locality"
},
  "geometry": {"coordinates":[29.50705,4.59485],"type":"Point"}
}