{
  "type": "Feature",
  "properties": {
    "gn:admin1_code":"20.0",
    "gn:asciiname":"Kindji",
    "gn:country_code":"CD",
    "gn:dem":855,
    "gn:feature_class":"P",
    "gn:feature_code":"PPL",
    "gn:name":"Kindji",
    "gn:population":0,
    "gn:timezone":"Africa/Kinshasa",
    "iso:country":"CD",
    "wof:name":"Kindji",
    "wof:placetype":"locality"
},
  "geometry": {"coordinates":[18.9926,-6.2367],"type":"Point"}
}