{
  "type": "Feature",
  "properties": {
    "gn:admin1_code":"22.0",
    "gn:asciiname":"Kasaji",
    "gn:country_code":"CD",
    "gn:dem":1112,
    "gn:feature_class":"P",
    "gn:feature_code":"PPL",
    "gn:name":"Kasaji",
    "gn:population":0,
    "gn:timezone":"Africa/Lubumbashi",
    "iso:country":"CD",
    "wof:name":"Kasaji",
    "wof:placetype":"locality"
},
  "geometry": {"coordinates":[23.73491,-8.84904],"type":"Point"}
}