{
  "type": "Feature",
  "properties": {
    "gn:admin1_code":"22.0",
    "gn:asciiname":"Diswahila",
    "gn:country_code":"CD",
    "gn:dem":1141,
    "gn:feature_class":"P",
    "gn:feature_code":"PPL",
    "gn:name":"Diswahila",
    "gn:population":0,
    "gn:timezone":"Africa/Lubumbashi",
    "iso:country":"CD",
    "wof:name":"Diswahila",
    "wof:placetype":"locality"
},
  "geometry": {"coordinates":[24.25837000000001,-10.25129],"type":"Point"}
}