{
  "type": "Feature",
  "properties": {
    "gn:admin1_code":"26.0",
    "gn:asciiname":"Bongonda",
    "gn:country_code":"CD",
    "gn:dem":609,
    "gn:feature_class":"P",
    "gn:feature_code":"PPL",
    "gn:name":"Bongonda",
    "gn:population":0,
    "gn:timezone":"Africa/Kinshasa",
    "iso:country":"CD",
    "name:und_x_variant":[
        "Bangonda"
    ],
    "wof:name":"Bongonda",
    "wof:placetype":"locality"
},
  "geometry": {"coordinates":[20.49056,4.26758],"type":"Point"}
}