{
  "type": "Feature",
  "properties": {
    "gn:admin1_code":"16.0",
    "gn:asciiname":"Tambala",
    "gn:country_code":"CD",
    "gn:dem":751,
    "gn:feature_class":"P",
    "gn:feature_code":"PPL",
    "gn:name":"Tambala",
    "gn:population":0,
    "gn:timezone":"Africa/Lubumbashi",
    "iso:country":"CD",
    "wof:name":"Tambala",
    "wof:placetype":"locality"
},
  "geometry": {"coordinates":[28.85822000000001,4.36058],"type":"Point"}
}