{
  "type": "Feature",
  "properties": {
    "gn:admin1_code":"30.0",
    "gn:asciiname":"Bafwalipa",
    "gn:country_code":"CD",
    "gn:dem":535,
    "gn:feature_class":"P",
    "gn:feature_code":"PPL",
    "gn:name":"Bafwalipa",
    "gn:population":0,
    "gn:timezone":"Africa/Lubumbashi",
    "iso:country":"CD",
    "wof:name":"Bafwalipa",
    "wof:placetype":"locality"
},
  "geometry": {"coordinates":[26.82391,1.08174],"type":"Point"}
}