{
  "type": "Feature",
  "properties": {
    "gn:admin1_code":"18.0",
    "gn:asciiname":"Mupoie",
    "gn:country_code":"CD",
    "gn:dem":635,
    "gn:feature_class":"P",
    "gn:feature_code":"PPL",
    "gn:name":"Mupoie",
    "gn:population":0,
    "gn:timezone":"Africa/Lubumbashi",
    "iso:country":"CD",
    "wof:name":"Mupoie",
    "wof:placetype":"locality"
},
  "geometry": {"coordinates":[20.96614,-6.87041],"type":"Point"}
}