{
  "type": "Feature",
  "properties": {
    "gn:admin1_code":"12.0",
    "gn:asciiname":"Kikonde",
    "gn:country_code":"CD",
    "gn:dem":827,
    "gn:feature_class":"P",
    "gn:feature_code":"PPL",
    "gn:name":"Kikonde",
    "gn:population":0,
    "gn:timezone":"Africa/Lubumbashi",
    "iso:country":"CD",
    "wof:name":"Kikonde",
    "wof:placetype":"locality"
},
  "geometry": {"coordinates":[29.08333,-4.45],"type":"Point"}
}