{
  "type": "Feature",
  "properties": {
    "gn:admin1_code":"26.0",
    "gn:asciiname":"Bigi-Nord",
    "gn:country_code":"CD",
    "gn:dem":457,
    "gn:feature_class":"P",
    "gn:feature_code":"PPL",
    "gn:name":"Bigi-Nord",
    "gn:population":0,
    "gn:timezone":"Africa/Kinshasa",
    "iso:country":"CD",
    "wof:name":"Bigi-Nord",
    "wof:placetype":"locality"
},
  "geometry": {"coordinates":[22.36572,3.80975],"type":"Point"}
}