{
  "type": "Feature",
  "properties": {
    "gn:admin1_code":"15.0",
    "gn:asciiname":"Bulembo",
    "gn:country_code":"CD",
    "gn:dem":683,
    "gn:feature_class":"P",
    "gn:feature_code":"PPL",
    "gn:name":"Bulembo",
    "gn:population":0,
    "gn:timezone":"Africa/Lubumbashi",
    "iso:country":"CD",
    "wof:name":"Bulembo",
    "wof:placetype":"locality"
},
  "geometry": {"coordinates":[25.88333,-8.16667],"type":"Point"}
}