{
  "type": "Feature",
  "properties": {
    "gn:admin1_code":"31.0",
    "gn:asciiname":"Longola",
    "gn:country_code":"CD",
    "gn:dem":410,
    "gn:feature_class":"P",
    "gn:feature_code":"PPL",
    "gn:name":"Longola",
    "gn:population":0,
    "gn:timezone":"Africa/Kinshasa",
    "iso:country":"CD",
    "name:und_x_variant":[
        "Longole",
        "Longola"
    ],
    "wof:name":"Longola",
    "wof:placetype":"locality"
},
  "geometry": {"coordinates":[22.45,-0.86667],"type":"Point"}
}