{
  "type": "Feature",
  "properties": {
    "gn:admin1_code":"20.0",
    "gn:asciiname":"Kikindi",
    "gn:country_code":"CD",
    "gn:dem":763,
    "gn:feature_class":"P",
    "gn:feature_code":"PPL",
    "gn:name":"Kikindi",
    "gn:population":0,
    "gn:timezone":"Africa/Kinshasa",
    "iso:country":"CD",
    "wof:name":"Kikindi",
    "wof:placetype":"locality"
},
  "geometry": {"coordinates":[17.74091,-5.55711],"type":"Point"}
}