{
  "type": "Feature",
  "properties": {
    "gn:admin1_code":"23.0",
    "gn:asciiname":"Kabunda",
    "gn:country_code":"CD",
    "gn:dem":908,
    "gn:feature_class":"P",
    "gn:feature_code":"PPL",
    "gn:name":"Kabunda",
    "gn:population":0,
    "gn:timezone":"Africa/Lubumbashi",
    "iso:country":"CD",
    "wof:name":"Kabunda",
    "wof:placetype":"locality"
},
  "geometry": {"coordinates":[22.12529,-7.4014],"type":"Point"}
}