{
  "type": "Feature",
  "properties": {
    "gn:admin1_code":"24.0",
    "gn:asciiname":"Ilombe",
    "gn:country_code":"CD",
    "gn:dem":298,
    "gn:feature_class":"P",
    "gn:feature_code":"PPL",
    "gn:name":"Ilombe",
    "gn:population":0,
    "gn:timezone":"Africa/Kinshasa",
    "iso:country":"CD",
    "name:und_x_variant":[
        "Ilembe",
        "Elombe",
        "Ilombe"
    ],
    "wof:name":"Ilombe",
    "wof:placetype":"locality"
},
  "geometry": {"coordinates":[18.24252000000001,-2.83931],"type":"Point"}
}