{
  "type": "Feature",
  "properties": {
    "gn:admin1_code":"15.0",
    "gn:asciiname":"Kanda Kanda",
    "gn:country_code":"CD",
    "gn:dem":926,
    "gn:feature_class":"P",
    "gn:feature_code":"PPL",
    "gn:name":"Kanda Kanda",
    "gn:population":0,
    "gn:timezone":"Africa/Lubumbashi",
    "iso:country":"CD",
    "wof:name":"Kanda Kanda",
    "wof:placetype":"locality"
},
  "geometry": {"coordinates":[25.23159,-9.88467],"type":"Point"}
}