{
  "type": "Feature",
  "properties": {
    "gn:admin1_code":"22.0",
    "gn:asciiname":"Kasangata",
    "gn:country_code":"CD",
    "gn:dem":956,
    "gn:feature_class":"P",
    "gn:feature_code":"PPL",
    "gn:name":"Kasangata",
    "gn:population":0,
    "gn:timezone":"Africa/Lubumbashi",
    "iso:country":"CD",
    "wof:name":"Kasangata",
    "wof:placetype":"locality"
},
  "geometry": {"coordinates":[22.7533,-9.67051],"type":"Point"}
}