{
  "type": "Feature",
  "properties": {
    "gn:admin1_code":"31.0",
    "gn:asciiname":"Isaka",
    "gn:country_code":"CD",
    "gn:dem":360,
    "gn:feature_class":"P",
    "gn:feature_code":"PPL",
    "gn:name":"Isaka",
    "gn:population":0,
    "gn:timezone":"Africa/Kinshasa",
    "iso:country":"CD",
    "name:ita_x_preferred":[
        "Isaka"
    ],
    "name:swa_x_preferred":[
        "Isaka"
    ],
    "wof:name":"Isaka",
    "wof:placetype":"locality"
},
  "geometry": {"coordinates":[20.41667,-0.46667],"type":"Point"}
}