{
  "type": "Feature",
  "properties": {
    "gn:admin1_code":"14.0",
    "gn:asciiname":"Kabela",
    "gn:country_code":"CD",
    "gn:dem":949,
    "gn:feature_class":"P",
    "gn:feature_code":"PPL",
    "gn:name":"Kabela",
    "gn:population":0,
    "gn:timezone":"Africa/Lubumbashi",
    "iso:country":"CD",
    "wof:name":"Kabela",
    "wof:placetype":"locality"
},
  "geometry": {"coordinates":[27.26788,-9.26129],"type":"Point"}
}