{
  "type": "Feature",
  "properties": {
    "gn:admin1_code":"17.0",
    "gn:asciiname":"Duge",
    "gn:country_code":"CD",
    "gn:dem":1077,
    "gn:feature_class":"P",
    "gn:feature_code":"PPL",
    "gn:name":"Duge",
    "gn:population":0,
    "gn:timezone":"Africa/Lubumbashi",
    "iso:country":"CD",
    "name:fra_x_preferred":[
        "Duge"
    ],
    "wof:name":"Duge",
    "wof:placetype":"locality"
},
  "geometry": {"coordinates":[29.85784,1.30721],"type":"Point"}
}