{
  "type": "Feature",
  "properties": {
    "gn:admin1_code":"22.0",
    "gn:asciiname":"Nabaya",
    "gn:country_code":"CD",
    "gn:dem":1130,
    "gn:feature_class":"P",
    "gn:feature_code":"PPL",
    "gn:name":"Nabaya",
    "gn:population":0,
    "gn:timezone":"Africa/Lubumbashi",
    "iso:country":"CD",
    "wof:name":"Nabaya",
    "wof:placetype":"locality"
},
  "geometry": {"coordinates":[24.30463,-10.33277],"type":"Point"}
}