{
  "type": "Feature",
  "properties": {
    "gn:admin1_code":"29.0",
    "gn:asciiname":"Goi",
    "gn:country_code":"CD",
    "gn:dem":664,
    "gn:feature_class":"P",
    "gn:feature_code":"PPL",
    "gn:name":"Goi",
    "gn:population":0,
    "gn:timezone":"Africa/Lubumbashi",
    "iso:country":"CD",
    "name:und_x_variant":[
        "Goy",
        "Goi"
    ],
    "wof:name":"Goi",
    "wof:placetype":"locality"
},
  "geometry": {"coordinates":[27.84841,-6.2699],"type":"Point"}
}