{
  "type": "Feature",
  "properties": {
    "gn:admin1_code":"22.0",
    "gn:asciiname":"Tshibang",
    "gn:country_code":"CD",
    "gn:dem":902,
    "gn:feature_class":"P",
    "gn:feature_code":"PPL",
    "gn:name":"Tshibang",
    "gn:population":0,
    "gn:timezone":"Africa/Lubumbashi",
    "iso:country":"CD",
    "name:und_x_variant":[
        "Tshibangu"
    ],
    "wof:name":"Tshibang",
    "wof:placetype":"locality"
},
  "geometry": {"coordinates":[22.2588,-8.18426],"type":"Point"}
}