{
  "type": "Feature",
  "properties": {
    "gn:admin1_code":"27.0",
    "gn:asciiname":"Pumbu",
    "gn:country_code":"CD",
    "gn:dem":459,
    "gn:feature_class":"P",
    "gn:feature_code":"PPL",
    "gn:name":"Pumbu",
    "gn:population":0,
    "gn:timezone":"Africa/Lubumbashi",
    "iso:country":"CD",
    "wof:name":"Pumbu",
    "wof:placetype":"locality"
},
  "geometry": {"coordinates":[22.48333,-2.21667],"type":"Point"}
}