{
  "type": "Feature",
  "properties": {
    "gn:admin1_code":"20.0",
    "gn:asciiname":"Kasende",
    "gn:country_code":"CD",
    "gn:dem":800,
    "gn:feature_class":"P",
    "gn:feature_code":"PPL",
    "gn:name":"Kasende",
    "gn:population":0,
    "gn:timezone":"Africa/Kinshasa",
    "iso:country":"CD",
    "wof:name":"Kasende",
    "wof:placetype":"locality"
},
  "geometry": {"coordinates":[19.34758,-6.07819],"type":"Point"}
}