{
  "type": "Feature",
  "properties": {
    "gn:admin1_code":"28.0",
    "gn:asciiname":"Bombili",
    "gn:country_code":"CD",
    "gn:dem":359,
    "gn:feature_class":"P",
    "gn:feature_code":"PPL",
    "gn:name":"Bombili",
    "gn:population":0,
    "gn:timezone":"Africa/Kinshasa",
    "iso:country":"CD",
    "wof:name":"Bombili",
    "wof:placetype":"locality"
},
  "geometry": {"coordinates":[18.84077000000001,3.00518],"type":"Point"}
}