{
  "type": "Feature",
  "properties": {
    "gn:admin1_code":"20.0",
    "gn:asciiname":"Kilomo",
    "gn:country_code":"CD",
    "gn:dem":442,
    "gn:feature_class":"P",
    "gn:feature_code":"PPL",
    "gn:name":"Kilomo",
    "gn:population":0,
    "gn:timezone":"Africa/Kinshasa",
    "iso:country":"CD",
    "name:und_x_variant":[
        "Kilomo Diata",
        "Kilomo"
    ],
    "wof:name":"Kilomo",
    "wof:placetype":"locality"
},
  "geometry": {"coordinates":[19.01399,-4.19197],"type":"Point"}
}