{
  "type": "Feature",
  "properties": {
    "gn:admin1_code":"20.0",
    "gn:asciiname":"Salamlota",
    "gn:country_code":"CD",
    "gn:dem":299,
    "gn:feature_class":"P",
    "gn:feature_code":"PPL",
    "gn:name":"Salamlota",
    "gn:population":0,
    "gn:timezone":"Africa/Kinshasa",
    "iso:country":"CD",
    "wof:name":"Salamlota",
    "wof:placetype":"locality"
},
  "geometry": {"coordinates":[17.36098,-3.35283],"type":"Point"}
}