{
  "type": "Feature",
  "properties": {
    "gn:admin1_code":"23.0",
    "gn:asciiname":"Mulombela",
    "gn:country_code":"CD",
    "gn:dem":742,
    "gn:feature_class":"P",
    "gn:feature_code":"PPL",
    "gn:name":"Mulombela",
    "gn:population":0,
    "gn:timezone":"Africa/Lubumbashi",
    "iso:country":"CD",
    "wof:name":"Mulombela",
    "wof:placetype":"locality"
},
  "geometry": {"coordinates":[22.87046,-5.91768],"type":"Point"}
}