{
  "type": "Feature",
  "properties": {
    "gn:admin1_code":"14.0",
    "gn:asciiname":"Kiatwala",
    "gn:country_code":"CD",
    "gn:dem":1137,
    "gn:feature_class":"P",
    "gn:feature_code":"PPL",
    "gn:name":"Kiatwala",
    "gn:population":0,
    "gn:timezone":"Africa/Lubumbashi",
    "iso:country":"CD",
    "wof:name":"Kiatwala",
    "wof:placetype":"locality"
},
  "geometry": {"coordinates":[27.84837000000001,-11.47039],"type":"Point"}
}