{
  "type": "Feature",
  "properties": {
    "gn:admin1_code":"13.0",
    "gn:asciiname":"Munzwa",
    "gn:country_code":"CD",
    "gn:dem":633,
    "gn:feature_class":"P",
    "gn:feature_code":"PPL",
    "gn:name":"Munzwa",
    "gn:population":0,
    "gn:timezone":"Africa/Lubumbashi",
    "iso:country":"CD",
    "name:und_x_variant":[
        "Munza",
        "Munzwa",
        "Munzua"
    ],
    "wof:name":"Munzwa",
    "wof:placetype":"locality"
},
  "geometry": {"coordinates":[26.79406,4.11236],"type":"Point"}
}