{
  "type": "Feature",
  "properties": {
    "gn:admin1_code":"20.0",
    "gn:asciiname":"Kindungu",
    "gn:country_code":"CD",
    "gn:dem":507,
    "gn:feature_class":"P",
    "gn:feature_code":"PPL",
    "gn:name":"Kindungu",
    "gn:population":0,
    "gn:timezone":"Africa/Kinshasa",
    "iso:country":"CD",
    "wof:name":"Kindungu",
    "wof:placetype":"locality"
},
  "geometry": {"coordinates":[17.65057999999999,-4.88026],"type":"Point"}
}