{
  "type": "Feature",
  "properties": {
    "gn:admin1_code":"29.0",
    "gn:asciiname":"Mokambwe",
    "gn:country_code":"CD",
    "gn:dem":1336,
    "gn:feature_class":"P",
    "gn:feature_code":"PPL",
    "gn:name":"Mokambwe",
    "gn:population":0,
    "gn:timezone":"Africa/Lubumbashi",
    "iso:country":"CD",
    "wof:name":"Mokambwe",
    "wof:placetype":"locality"
},
  "geometry": {"coordinates":[28.76628,-7.54685],"type":"Point"}
}