{
  "type": "Feature",
  "properties": {
    "gn:admin1_code":"21.0",
    "gn:asciiname":"Kajiba",
    "gn:country_code":"CD",
    "gn:dem":782,
    "gn:feature_class":"P",
    "gn:feature_code":"PPL",
    "gn:name":"Kajiba",
    "gn:population":0,
    "gn:timezone":"Africa/Lubumbashi",
    "iso:country":"CD",
    "wof:name":"Kajiba",
    "wof:placetype":"locality"
},
  "geometry": {"coordinates":[24.62234,-6.24781],"type":"Point"}
}