{
  "type": "Feature",
  "properties": {
    "gn:admin1_code":"15.0",
    "gn:asciiname":"Mulunda",
    "gn:country_code":"CD",
    "gn:dem":582,
    "gn:feature_class":"P",
    "gn:feature_code":"PPL",
    "gn:name":"Mulunda",
    "gn:population":0,
    "gn:timezone":"Africa/Lubumbashi",
    "iso:country":"CD",
    "wof:name":"Mulunda",
    "wof:placetype":"locality"
},
  "geometry": {"coordinates":[26.77028,-8.04729],"type":"Point"}
}