{
  "type": "Feature",
  "properties": {
    "gn:admin1_code":"20.0",
    "gn:asciiname":"Ubimwei",
    "gn:country_code":"CD",
    "gn:dem":343,
    "gn:feature_class":"P",
    "gn:feature_code":"PPL",
    "gn:name":"Ubimwei",
    "gn:population":0,
    "gn:timezone":"Africa/Kinshasa",
    "iso:country":"CD",
    "name:und_x_variant":[
        "Ubinwe",
        "Ubimwei"
    ],
    "wof:name":"Ubimwei",
    "wof:placetype":"locality"
},
  "geometry": {"coordinates":[17.82971000000001,-3.71024],"type":"Point"}
}