{
  "type": "Feature",
  "properties": {
    "gn:admin1_code":"20.0",
    "gn:asciiname":"Bangalala-Kisala",
    "gn:country_code":"CD",
    "gn:dem":734,
    "gn:feature_class":"P",
    "gn:feature_code":"PPL",
    "gn:name":"Bangalala-Kisala",
    "gn:population":0,
    "gn:timezone":"Africa/Kinshasa",
    "iso:country":"CD",
    "wof:name":"Bangalala-Kisala",
    "wof:placetype":"locality"
},
  "geometry": {"coordinates":[18.08952,-5.36073],"type":"Point"}
}