{
  "type": "Feature",
  "properties": {
    "gn:admin1_code":"20.0",
    "gn:asciiname":"Lukula",
    "gn:country_code":"CD",
    "gn:dem":766,
    "gn:feature_class":"P",
    "gn:feature_code":"PPL",
    "gn:name":"Lukula",
    "gn:population":0,
    "gn:timezone":"Africa/Kinshasa",
    "iso:country":"CD",
    "wof:name":"Lukula",
    "wof:placetype":"locality"
},
  "geometry": {"coordinates":[18.99626,-5.85666],"type":"Point"}
}