{
  "type": "Feature",
  "properties": {
    "gn:admin1_code":"21.0",
    "gn:asciiname":"Imeno",
    "gn:country_code":"CD",
    "gn:dem":661,
    "gn:feature_class":"P",
    "gn:feature_code":"PPL",
    "gn:name":"Imeno",
    "gn:population":0,
    "gn:timezone":"Africa/Lubumbashi",
    "iso:country":"CD",
    "name:bos_x_preferred":[
        "Imeno"
    ],
    "name:ceb_x_preferred":[
        "Imeno"
    ],
    "name:hrv_x_preferred":[
        "Imeno"
    ],
    "name:nld_x_preferred":[
        "Imeno"
    ],
    "name:pol_x_preferred":[
        "Imeno"
    ],
    "name:ron_x_preferred":[
        "Imeno"
    ],
    "name:slv_x_preferred":[
        "Imeno"
    ],
    "name:ukr_x_preferred":[
        "\u0406\u043c\u0435\u043d\u043e"
    ],
    "wof:name":"Imeno",
    "wof:placetype":"locality"
},
  "geometry": {"coordinates":[24.97251,-5.35208],"type":"Point"}
}