{
  "type": "Feature",
  "properties": {
    "gn:admin1_code":"22.0",
    "gn:asciiname":"Satshimbu",
    "gn:country_code":"CD",
    "gn:dem":926,
    "gn:feature_class":"P",
    "gn:feature_code":"PPL",
    "gn:name":"Satshimbu",
    "gn:population":0,
    "gn:timezone":"Africa/Lubumbashi",
    "iso:country":"CD",
    "wof:name":"Satshimbu",
    "wof:placetype":"locality"
},
  "geometry": {"coordinates":[22.82322000000001,-9.64315],"type":"Point"}
}