{
  "type": "Feature",
  "properties": {
    "gn:admin1_code":"24.0",
    "gn:asciiname":"Yumuyumu",
    "gn:country_code":"CD",
    "gn:dem":363,
    "gn:feature_class":"P",
    "gn:feature_code":"PPL",
    "gn:name":"Yumuyumu",
    "gn:population":0,
    "gn:timezone":"Africa/Kinshasa",
    "iso:country":"CD",
    "wof:name":"Yumuyumu",
    "wof:placetype":"locality"
},
  "geometry": {"coordinates":[17.74418,-3.02263],"type":"Point"}
}