{
  "type": "Feature",
  "properties": {
    "gn:admin1_code":"23.0",
    "gn:asciiname":"Tshashimoba",
    "gn:country_code":"CD",
    "gn:dem":719,
    "gn:feature_class":"P",
    "gn:feature_code":"PPL",
    "gn:name":"Tshashimoba",
    "gn:population":0,
    "gn:timezone":"Africa/Lubumbashi",
    "iso:country":"CD",
    "wof:name":"Tshashimoba",
    "wof:placetype":"locality"
},
  "geometry": {"coordinates":[22.52822,-6.04757],"type":"Point"}
}