{
  "type": "Feature",
  "properties": {
    "gn:admin1_code":"8.0",
    "gn:asciiname":"Kibemba-Tala",
    "gn:country_code":"CD",
    "gn:dem":188,
    "gn:feature_class":"P",
    "gn:feature_code":"PPL",
    "gn:name":"Kibemba-Tala",
    "gn:population":0,
    "gn:timezone":"Africa/Kinshasa",
    "iso:country":"CD",
    "name:und_x_variant":[
        "Kimbemba-Tala"
    ],
    "wof:name":"Kibemba-Tala",
    "wof:placetype":"locality"
},
  "geometry": {"coordinates":[14.17173,-4.95645],"type":"Point"}
}