{
  "type": "Feature",
  "properties": {
    "gn:admin1_code":"2.0",
    "gn:asciiname":"Buya-Ekole Premiere",
    "gn:country_code":"CD",
    "gn:dem":322,
    "gn:feature_class":"P",
    "gn:feature_code":"PPL",
    "gn:name":"Buya-Ekole Premi\u00e8re",
    "gn:population":0,
    "gn:timezone":"Africa/Kinshasa",
    "iso:country":"CD",
    "name:und_x_variant":[
        "Buya-Ekole Premi\u00e8re",
        "Buya-Ekole I"
    ],
    "wof:name":"Buya-Ekole Premiere",
    "wof:placetype":"locality"
},
  "geometry": {"coordinates":[18.23542,-0.22363],"type":"Point"}
}