{
  "type": "Feature",
  "properties": {
    "gn:admin1_code":"23.0",
    "gn:asciiname":"Kayembe-Nzolo",
    "gn:country_code":"CD",
    "gn:dem":838,
    "gn:feature_class":"P",
    "gn:feature_code":"PPL",
    "gn:name":"Kayembe-Nzolo",
    "gn:population":0,
    "gn:timezone":"Africa/Lubumbashi",
    "iso:country":"CD",
    "wof:name":"Kayembe-Nzolo",
    "wof:placetype":"locality"
},
  "geometry": {"coordinates":[22.88558,-6.43529],"type":"Point"}
}