{
  "type": "Feature",
  "properties": {
    "gn:admin1_code":"22.0",
    "gn:asciiname":"Tshingangu",
    "gn:country_code":"CD",
    "gn:dem":1038,
    "gn:feature_class":"P",
    "gn:feature_code":"PPL",
    "gn:name":"Tshingangu",
    "gn:population":0,
    "gn:timezone":"Africa/Lubumbashi",
    "iso:country":"CD",
    "wof:name":"Tshingangu",
    "wof:placetype":"locality"
},
  "geometry": {"coordinates":[23.50524,-10.10242],"type":"Point"}
}