{
  "type": "Feature",
  "properties": {
    "gn:admin1_code":"20.0",
    "gn:asciiname":"Mopalanga",
    "gn:country_code":"CD",
    "gn:dem":727,
    "gn:feature_class":"P",
    "gn:feature_code":"PPL",
    "gn:name":"Mopalanga",
    "gn:population":0,
    "gn:timezone":"Africa/Kinshasa",
    "iso:country":"CD",
    "wof:name":"Mopalanga",
    "wof:placetype":"locality"
},
  "geometry": {"coordinates":[17.66818,-5.43308],"type":"Point"}
}