{
  "type": "Feature",
  "properties": {
    "gn:admin1_code":"20.0",
    "gn:asciiname":"Lunelo",
    "gn:country_code":"CD",
    "gn:dem":593,
    "gn:feature_class":"P",
    "gn:feature_code":"PPL",
    "gn:name":"Lunelo",
    "gn:population":0,
    "gn:timezone":"Africa/Kinshasa",
    "iso:country":"CD",
    "wof:name":"Lunelo",
    "wof:placetype":"locality"
},
  "geometry": {"coordinates":[19.92638,-5.98717],"type":"Point"}
}