{
  "type": "Feature",
  "properties": {
    "gn:admin1_code":"19.0",
    "gn:asciiname":"Kizomba",
    "gn:country_code":"CD",
    "gn:dem":629,
    "gn:feature_class":"P",
    "gn:feature_code":"PPL",
    "gn:name":"Kizomba",
    "gn:population":0,
    "gn:timezone":"Africa/Kinshasa",
    "iso:country":"CD",
    "wof:name":"Kizomba",
    "wof:placetype":"locality"
},
  "geometry": {"coordinates":[17.22054,-5.03583],"type":"Point"}
}