{
  "type": "Feature",
  "properties": {
    "gn:admin1_code":"19.0",
    "gn:asciiname":"Kizomba",
    "gn:country_code":"CD",
    "gn:dem":629,
    "gn:feature_class":"P",
    "gn:feature_code":"PPL",
    "gn:name":"Kizomba",
    "gn:population":0,
    "gn:timezone":"Africa/Kinshasa",
    "iso:country":"CD",
    "name:aze_x_preferred":[
        "Kizomba"
    ],
    "name:bul_x_preferred":[
        "\u041a\u0438\u0437\u043e\u043c\u0431\u0430"
    ],
    "name:cat_x_preferred":[
        "Kizomba"
    ],
    "name:ces_x_preferred":[
        "Kizomba"
    ],
    "name:deu_x_preferred":[
        "Kizomba"
    ],
    "name:fas_x_preferred":[
        "\u06a9\u06cc\u0632\u0648\u0645\u0628\u0627"
    ],
    "name:fin_x_preferred":[
        "Kizomba"
    ],
    "name:fra_x_preferred":[
        "Kizomba"
    ],
    "name:heb_x_preferred":[
        "\u05e7\u05d9\u05d6\u05d5\u05de\u05d1\u05d4"
    ],
    "name:ita_x_preferred":[
        "Kizomba"
    ],
    "name:jpn_x_preferred":[
        "\u30ad\u30be\u30f3\u30d0"
    ],
    "name:kor_x_preferred":[
        "\ud0a4\uc880\ubc14"
    ],
    "name:nld_x_preferred":[
        "Kizomba"
    ],
    "name:pol_x_preferred":[
        "Kizomba"
    ],
    "name:por_x_preferred":[
        "Kizomba"
    ],
    "name:rus_x_preferred":[
        "\u041a\u0438\u0437\u043e\u043c\u0431\u0430"
    ],
    "name:spa_x_preferred":[
        "Kizomba"
    ],
    "name:srp_x_preferred":[
        "\u041a\u0438\u0437\u043e\u043c\u0431\u0430"
    ],
    "name:swe_x_preferred":[
        "Kizomba"
    ],
    "name:tam_x_preferred":[
        "\u0b95\u0bbf\u0b9a\u0bcb\u0bae\u0bcd\u0baa\u0bbe \u0ba8\u0b9f\u0ba9\u0bae\u0bcd"
    ],
    "name:ukr_x_preferred":[
        "\u041a\u0456\u0437\u043e\u043c\u0431\u0430"
    ],
    "name:zho_x_preferred":[
        "\u57fa\u5b97\u5df4"
    ],
    "wof:name":"Kizomba",
    "wof:placetype":"locality"
},
  "geometry": {"coordinates":[17.22054,-5.03583],"type":"Point"}
}