{
  "type": "Feature",
  "properties": {
    "gn:admin1_code":"19.0",
    "gn:asciiname":"Shakalala",
    "gn:country_code":"CD",
    "gn:dem":1074,
    "gn:feature_class":"P",
    "gn:feature_code":"PPL",
    "gn:name":"Shakalala",
    "gn:population":0,
    "gn:timezone":"Africa/Kinshasa",
    "iso:country":"CD",
    "wof:name":"Shakalala",
    "wof:placetype":"locality"
},
  "geometry": {"coordinates":[19.17468,-7.92321],"type":"Point"}
}