{
  "type": "Feature",
  "properties": {
    "gn:admin1_code":"18.0",
    "gn:asciiname":"Koi-Kayeye-Muana",
    "gn:country_code":"CD",
    "gn:dem":611,
    "gn:feature_class":"P",
    "gn:feature_code":"PPL",
    "gn:name":"Koi-Kayeye-Muana",
    "gn:population":0,
    "gn:timezone":"Africa/Lubumbashi",
    "iso:country":"CD",
    "wof:name":"Koi-Kayeye-Muana",
    "wof:placetype":"locality"
},
  "geometry": {"coordinates":[20.83186,-6.02227],"type":"Point"}
}