{
  "type": "Feature",
  "properties": {
    "gn:admin1_code":"13.0",
    "gn:asciiname":"Nangende",
    "gn:country_code":"CD",
    "gn:dem":636,
    "gn:feature_class":"P",
    "gn:feature_code":"PPL",
    "gn:name":"Nangende",
    "gn:population":0,
    "gn:timezone":"Africa/Lubumbashi",
    "iso:country":"CD",
    "wof:name":"Nangende",
    "wof:placetype":"locality"
},
  "geometry": {"coordinates":[26.20562,2.70133],"type":"Point"}
}