{
  "type": "Feature",
  "properties": {
    "gn:admin1_code":"29.0",
    "gn:asciiname":"Lwendo",
    "gn:country_code":"CD",
    "gn:dem":1878,
    "gn:feature_class":"P",
    "gn:feature_code":"PPL",
    "gn:name":"Lwendo",
    "gn:population":0,
    "gn:timezone":"Africa/Lubumbashi",
    "iso:country":"CD",
    "name:und_x_variant":[
        "Luendo",
        "Lwendo"
    ],
    "wof:name":"Lwendo",
    "wof:placetype":"locality"
},
  "geometry": {"coordinates":[30.03333,-7.43333],"type":"Point"}
}