{
  "type": "Feature",
  "properties": {
    "gn:admin1_code":"13.0",
    "gn:asciiname":"Abogwomadu",
    "gn:country_code":"CD",
    "gn:dem":641,
    "gn:feature_class":"P",
    "gn:feature_code":"PPL",
    "gn:name":"Abogwomadu",
    "gn:population":0,
    "gn:timezone":"Africa/Lubumbashi",
    "iso:country":"CD",
    "name:und_x_variant":[
        "Abogwomado"
    ],
    "wof:name":"Abogwomadu",
    "wof:placetype":"locality"
},
  "geometry": {"coordinates":[26.3047,2.49771],"type":"Point"}
}