{
  "type": "Feature",
  "properties": {
    "gn:admin1_code":"23.0",
    "gn:asciiname":"Paku",
    "gn:country_code":"CD",
    "gn:dem":745,
    "gn:feature_class":"P",
    "gn:feature_code":"PPL",
    "gn:name":"Paku",
    "gn:population":0,
    "gn:timezone":"Africa/Lubumbashi",
    "iso:country":"CD",
    "name:ceb_x_preferred":[
        "Paku"
    ],
    "name:deu_x_preferred":[
        "Paku"
    ],
    "name:swe_x_preferred":[
        "Paku"
    ],
    "wof:name":"Paku",
    "wof:placetype":"locality"
},
  "geometry": {"coordinates":[22.01667,-7.05],"type":"Point"}
}