{
  "type": "Feature",
  "properties": {
    "gn:admin1_code":"28.0",
    "gn:asciiname":"Basene",
    "gn:country_code":"CD",
    "gn:dem":520,
    "gn:feature_class":"P",
    "gn:feature_code":"PPL",
    "gn:name":"Basene",
    "gn:population":0,
    "gn:timezone":"Africa/Kinshasa",
    "iso:country":"CD",
    "name:und_x_variant":[
        "Bazene",
        "Basene"
    ],
    "wof:name":"Basene",
    "wof:placetype":"locality"
},
  "geometry": {"coordinates":[18.98285,4.60867],"type":"Point"}
}