{
  "type": "Feature",
  "properties": {
    "gn:admin1_code":"13.0",
    "gn:asciiname":"Langwanga",
    "gn:country_code":"CD",
    "gn:dem":602,
    "gn:feature_class":"P",
    "gn:feature_code":"PPL",
    "gn:name":"Langwanga",
    "gn:population":0,
    "gn:timezone":"Africa/Lubumbashi",
    "iso:country":"CD",
    "wof:name":"Langwanga",
    "wof:placetype":"locality"
},
  "geometry": {"coordinates":[25.45885,3.36802],"type":"Point"}
}