{
  "type": "Feature",
  "properties": {
    "gn:admin1_code":"17.0",
    "gn:asciiname":"Ongobo",
    "gn:country_code":"CD",
    "gn:dem":1141,
    "gn:feature_class":"P",
    "gn:feature_code":"PPL",
    "gn:name":"Ongobo",
    "gn:population":0,
    "gn:timezone":"Africa/Lubumbashi",
    "iso:country":"CD",
    "wof:name":"Ongobo",
    "wof:placetype":"locality"
},
  "geometry": {"coordinates":[30.63273,3.42155],"type":"Point"}
}