{
  "type": "Feature",
  "properties": {
    "gn:admin1_code":"29.0",
    "gn:asciiname":"Katuvirisho",
    "gn:country_code":"CD",
    "gn:dem":1312,
    "gn:feature_class":"P",
    "gn:feature_code":"PPL",
    "gn:name":"Katuvirisho",
    "gn:population":0,
    "gn:timezone":"Africa/Lusaka",
    "iso:country":"CD",
    "wof:name":"Katuvirisho",
    "wof:placetype":"locality"
},
  "geometry": {"coordinates":[30.43558,-8.30377],"type":"Point"}
}