{
  "type": "Feature",
  "properties": {
    "gn:admin1_code":"8.0",
    "gn:asciiname":"Taki",
    "gn:country_code":"CD",
    "gn:dem":495,
    "gn:feature_class":"P",
    "gn:feature_code":"PPL",
    "gn:name":"Taki",
    "gn:population":0,
    "gn:timezone":"Africa/Kinshasa",
    "iso:country":"CD",
    "wof:name":"Taki",
    "wof:placetype":"locality"
},
  "geometry": {"coordinates":[14.15942,-4.75128],"type":"Point"}
}