{
  "type": "Feature",
  "properties": {
    "gn:admin1_code":"8.0",
    "gn:asciiname":"Taki",
    "gn:country_code":"CD",
    "gn:dem":495,
    "gn:feature_class":"P",
    "gn:feature_code":"PPL",
    "gn:name":"Taki",
    "gn:population":0,
    "gn:timezone":"Africa/Kinshasa",
    "iso:country":"CD",
    "name:ben_x_preferred":[
        "\u099f\u09be\u0995\u09bf"
    ],
    "name:ceb_x_preferred":[
        "Taki"
    ],
    "name:deu_x_preferred":[
        "Taki"
    ],
    "name:fra_x_preferred":[
        "Taki"
    ],
    "name:ita_x_preferred":[
        "Taki"
    ],
    "name:msa_x_preferred":[
        "Taki"
    ],
    "name:rus_x_preferred":[
        "\u0422\u0430\u043a\u0438"
    ],
    "name:swe_x_preferred":[
        "Taki"
    ],
    "wof:name":"Taki",
    "wof:placetype":"locality"
},
  "geometry": {"coordinates":[14.15942,-4.75128],"type":"Point"}
}