{
  "type": "Feature",
  "properties": {
    "gn:admin1_code":"18.0",
    "gn:asciiname":"Luenu",
    "gn:country_code":"CD",
    "gn:dem":454,
    "gn:feature_class":"P",
    "gn:feature_code":"PPL",
    "gn:name":"Luenu",
    "gn:population":0,
    "gn:timezone":"Africa/Lubumbashi",
    "iso:country":"CD",
    "name:und_x_variant":[
        "Luemu",
        "Luenu"
    ],
    "wof:name":"Luenu",
    "wof:placetype":"locality"
},
  "geometry": {"coordinates":[22.15,-4.73333],"type":"Point"}
}