{
  "type": "Feature",
  "properties": {
    "gn:admin1_code":"14.0",
    "gn:asciiname":"Kipora",
    "gn:country_code":"CD",
    "gn:dem":1377,
    "gn:feature_class":"P",
    "gn:feature_code":"PPL",
    "gn:name":"Kipora",
    "gn:population":0,
    "gn:timezone":"Africa/Lubumbashi",
    "iso:country":"CD",
    "wof:name":"Kipora",
    "wof:placetype":"locality"
},
  "geometry": {"coordinates":[25.69475,-11.57055],"type":"Point"}
}