{
  "type": "Feature",
  "properties": {
    "gn:admin1_code":"16.0",
    "gn:asciiname":"Tuludru",
    "gn:country_code":"CD",
    "gn:dem":940,
    "gn:feature_class":"P",
    "gn:feature_code":"PPL",
    "gn:name":"Tuludru",
    "gn:population":0,
    "gn:timezone":"Africa/Lubumbashi",
    "iso:country":"CD",
    "wof:name":"Tuludru",
    "wof:placetype":"locality"
},
  "geometry": {"coordinates":[29.18333,2.68333],"type":"Point"}
}