{
  "type": "Feature",
  "properties": {
    "gn:admin1_code":"20.0",
    "gn:asciiname":"Lungu Premiere",
    "gn:country_code":"CD",
    "gn:dem":649,
    "gn:feature_class":"P",
    "gn:feature_code":"PPL",
    "gn:name":"Lungu Premi\u00e8re",
    "gn:population":0,
    "gn:timezone":"Africa/Kinshasa",
    "iso:country":"CD",
    "name:und_x_variant":[
        "Lungu",
        "Lungu I",
        "Lungu Premi\u00e8re"
    ],
    "wof:name":"Lungu Premiere",
    "wof:placetype":"locality"
},
  "geometry": {"coordinates":[19.49554,-4.99608],"type":"Point"}
}