{
  "type": "Feature",
  "properties": {
    "gn:admin1_code":"13.0",
    "gn:asciiname":"Tezunipe",
    "gn:country_code":"CD",
    "gn:dem":605,
    "gn:feature_class":"P",
    "gn:feature_code":"PPL",
    "gn:name":"Tezunipe",
    "gn:population":0,
    "gn:timezone":"Africa/Lubumbashi",
    "iso:country":"CD",
    "wof:name":"Tezunipe",
    "wof:placetype":"locality"
},
  "geometry": {"coordinates":[25.73726,3.12111],"type":"Point"}
}