{
  "type": "Feature",
  "properties": {
    "gn:admin1_code":"8.0",
    "gn:asciiname":"Kimuanza",
    "gn:country_code":"CD",
    "gn:dem":580,
    "gn:feature_class":"P",
    "gn:feature_code":"PPL",
    "gn:name":"Kimuanza",
    "gn:population":0,
    "gn:timezone":"Africa/Brazzaville",
    "iso:country":"CD",
    "wof:name":"Kimuanza",
    "wof:placetype":"locality"
},
  "geometry": {"coordinates":[14.37005,-4.5633],"type":"Point"}
}