{
  "type": "Feature",
  "properties": {
    "gn:admin1_code":"16.0",
    "gn:asciiname":"Kotimai",
    "gn:country_code":"CD",
    "gn:dem":776,
    "gn:feature_class":"P",
    "gn:feature_code":"PPL",
    "gn:name":"Kotimai",
    "gn:population":0,
    "gn:timezone":"Africa/Lubumbashi",
    "iso:country":"CD",
    "name:und_x_variant":[
        "Kotimay",
        "Kotimai"
    ],
    "wof:name":"Kotimai",
    "wof:placetype":"locality"
},
  "geometry": {"coordinates":[27.61565,2.3618],"type":"Point"}
}