{
  "type": "Feature",
  "properties": {
    "gn:admin1_code":"11.0",
    "gn:asciiname":"Matete",
    "gn:country_code":"CD",
    "gn:dem":1723,
    "gn:feature_class":"P",
    "gn:feature_code":"PPL",
    "gn:name":"Matete",
    "gn:population":0,
    "gn:timezone":"Africa/Lubumbashi",
    "iso:country":"CD",
    "wof:name":"Matete",
    "wof:placetype":"locality"
},
  "geometry": {"coordinates":[28.95,-0.23333],"type":"Point"}
}