{
  "type": "Feature",
  "properties": {
    "gn:admin1_code":"19.0",
    "gn:asciiname":"Kwango",
    "gn:country_code":"CD",
    "gn:dem":888,
    "gn:feature_class":"P",
    "gn:feature_code":"PPL",
    "gn:name":"Kwango",
    "gn:population":0,
    "gn:timezone":"Africa/Kinshasa",
    "iso:country":"CD",
    "wof:name":"Kwango",
    "wof:placetype":"locality"
},
  "geometry": {"coordinates":[17.44869,-6.47051],"type":"Point"}
}