{
  "type": "Feature",
  "properties": {
    "gn:admin1_code":"19.0",
    "gn:asciiname":"Kwango",
    "gn:country_code":"CD",
    "gn:dem":888,
    "gn:feature_class":"P",
    "gn:feature_code":"PPL",
    "gn:name":"Kwango",
    "gn:population":0,
    "gn:timezone":"Africa/Kinshasa",
    "iso:country":"CD",
    "name:bel_x_preferred":[
        "\u041a\u0432\u0430\u043d\u0433\u043e"
    ],
    "name:bul_x_preferred":[
        "\u041a\u0432\u0430\u043d\u0433\u043e"
    ],
    "name:cat_x_preferred":[
        "Kwango"
    ],
    "name:deu_x_preferred":[
        "Kwango"
    ],
    "name:fin_x_preferred":[
        "Kwango"
    ],
    "name:fra_x_preferred":[
        "Kwango"
    ],
    "name:frr_x_preferred":[
        "Kwango"
    ],
    "name:hun_x_preferred":[
        "Kwango tartom\u00e1ny"
    ],
    "name:hye_x_preferred":[
        "\u053f\u057e\u0561\u0576\u0563\u0578"
    ],
    "name:ina_x_preferred":[
        "Provincia Kwango"
    ],
    "name:ind_x_preferred":[
        "Provinsi Kwango"
    ],
    "name:jpn_x_preferred":[
        "\u30af\u30ef\u30f3\u30b4\u5dde"
    ],
    "name:kat_x_preferred":[
        "\u10d9\u10e3\u10d0\u10dc\u10d2\u10dd\u10e1 \u10de\u10e0\u10dd\u10d5\u10d8\u10dc\u10ea\u10d8\u10d0"
    ],
    "name:kor_x_preferred":[
        "\ucf85\uace0\uc8fc"
    ],
    "name:nld_x_preferred":[
        "Kwango"
    ],
    "name:nor_x_preferred":[
        "Kwango"
    ],
    "name:pol_x_preferred":[
        "Kwango"
    ],
    "name:por_x_preferred":[
        "Kwango"
    ],
    "name:ron_x_preferred":[
        "Provincia Kwango"
    ],
    "name:rus_x_preferred":[
        "\u041a\u0432\u0430\u043d\u0433\u043e"
    ],
    "name:swe_x_preferred":[
        "Kwango"
    ],
    "name:ukr_x_preferred":[
        "\u041a\u0432\u0430\u043d\u0433\u043e"
    ],
    "name:war_x_preferred":[
        "Kwango"
    ],
    "name:wuu_x_preferred":[
        "\u5bbd\u679c\u7701"
    ],
    "name:xmf_x_preferred":[
        "\u10d9\u10e3\u10d0\u10dc\u10d2\u10dd\u10e8 \u10de\u10e0\u10dd\u10d5\u10d8\u10dc\u10ea\u10d8\u10d0"
    ],
    "name:zho_x_preferred":[
        "\u5bbd\u679c\u7701"
    ],
    "wof:name":"Kwango",
    "wof:placetype":"locality"
},
  "geometry": {"coordinates":[17.44869,-6.47051],"type":"Point"}
}