{
  "type": "Feature",
  "properties": {
    "gn:admin1_code":"15.0",
    "gn:asciiname":"Kito",
    "gn:country_code":"CD",
    "gn:dem":955,
    "gn:feature_class":"P",
    "gn:feature_code":"PPL",
    "gn:name":"Kito",
    "gn:population":0,
    "gn:timezone":"Africa/Lubumbashi",
    "iso:country":"CD",
    "name:ceb_x_preferred":[
        "Kito"
    ],
    "name:deu_x_preferred":[
        "Kito"
    ],
    "name:eus_x_preferred":[
        "Kito"
    ],
    "name:ita_x_preferred":[
        "Kito"
    ],
    "name:swa_x_preferred":[
        "Kito"
    ],
    "name:swe_x_preferred":[
        "Kito"
    ],
    "wof:name":"Kito",
    "wof:placetype":"locality"
},
  "geometry": {"coordinates":[25.19397,-7.82251],"type":"Point"}
}