{
  "type": "Feature",
  "properties": {
    "gn:admin1_code":"17.0",
    "gn:asciiname":"Dodoi",
    "gn:country_code":"CD",
    "gn:dem":1400,
    "gn:feature_class":"P",
    "gn:feature_code":"PPL",
    "gn:name":"Dodoi",
    "gn:population":0,
    "gn:timezone":"Africa/Lubumbashi",
    "iso:country":"CD",
    "wof:name":"Dodoi",
    "wof:placetype":"locality"
},
  "geometry": {"coordinates":[30.27587,1.42667],"type":"Point"}
}