{
  "type": "Feature",
  "properties": {
    "gn:admin1_code":"18.0",
    "gn:asciiname":"Shalengele-Katuama",
    "gn:country_code":"CD",
    "gn:dem":637,
    "gn:feature_class":"P",
    "gn:feature_code":"PPL",
    "gn:name":"Shalengele-Katuama",
    "gn:population":0,
    "gn:timezone":"Africa/Lubumbashi",
    "iso:country":"CD",
    "wof:name":"Shalengele-Katuama",
    "wof:placetype":"locality"
},
  "geometry": {"coordinates":[20.53482,-5.6723],"type":"Point"}
}