{
  "type": "Feature",
  "properties": {
    "gn:admin1_code":"22.0",
    "gn:asciiname":"Samafuka",
    "gn:country_code":"CD",
    "gn:dem":1123,
    "gn:feature_class":"P",
    "gn:feature_code":"PPL",
    "gn:name":"Samafuka",
    "gn:population":0,
    "gn:timezone":"Africa/Lubumbashi",
    "iso:country":"CD",
    "wof:name":"Samafuka",
    "wof:placetype":"locality"
},
  "geometry": {"coordinates":[23.60265,-10.42249],"type":"Point"}
}