{
  "type": "Feature",
  "properties": {
    "gn:admin1_code":"19.0",
    "gn:asciiname":"Kakalenge",
    "gn:country_code":"CD",
    "gn:dem":719,
    "gn:feature_class":"P",
    "gn:feature_code":"PPL",
    "gn:name":"Kakalenge",
    "gn:population":0,
    "gn:timezone":"Africa/Kinshasa",
    "iso:country":"CD",
    "wof:name":"Kakalenge",
    "wof:placetype":"locality"
},
  "geometry": {"coordinates":[17.45853,-7.91363],"type":"Point"}
}