{
  "type": "Feature",
  "properties": {
    "gn:admin1_code":"13.0",
    "gn:asciiname":"Nganzi",
    "gn:country_code":"CD",
    "gn:dem":534,
    "gn:feature_class":"P",
    "gn:feature_code":"PPL",
    "gn:name":"Nganzi",
    "gn:population":0,
    "gn:timezone":"Africa/Lubumbashi",
    "iso:country":"CD",
    "wof:name":"Nganzi",
    "wof:placetype":"locality"
},
  "geometry": {"coordinates":[23.81821,3.85097],"type":"Point"}
}