{
  "type": "Feature",
  "properties": {
    "gn:admin1_code":"13.0",
    "gn:asciiname":"Notonde",
    "gn:country_code":"CD",
    "gn:dem":600,
    "gn:feature_class":"P",
    "gn:feature_code":"PPL",
    "gn:name":"Notonde",
    "gn:population":0,
    "gn:timezone":"Africa/Lubumbashi",
    "iso:country":"CD",
    "wof:name":"Notonde",
    "wof:placetype":"locality"
},
  "geometry": {"coordinates":[25.55568,3.12933],"type":"Point"}
}