{
  "type": "Feature",
  "properties": {
    "gn:admin1_code":"19.0",
    "gn:asciiname":"Kimwangala",
    "gn:country_code":"CD",
    "gn:dem":556,
    "gn:feature_class":"P",
    "gn:feature_code":"PPL",
    "gn:name":"Kimwangala",
    "gn:population":0,
    "gn:timezone":"Africa/Kinshasa",
    "iso:country":"CD",
    "wof:name":"Kimwangala",
    "wof:placetype":"locality"
},
  "geometry": {"coordinates":[17.02263,-5.02492],"type":"Point"}
}