{
  "type": "Feature",
  "properties": {
    "gn:admin1_code":"13.0",
    "gn:asciiname":"Moko",
    "gn:country_code":"CD",
    "gn:dem":442,
    "gn:feature_class":"P",
    "gn:feature_code":"PPL",
    "gn:name":"Moko",
    "gn:population":0,
    "gn:timezone":"Africa/Lubumbashi",
    "iso:country":"CD",
    "name:deu_x_preferred":[
        "Moko"
    ],
    "wof:name":"Moko",
    "wof:placetype":"locality"
},
  "geometry": {"coordinates":[23.88522,2.56952],"type":"Point"}
}