{
  "type": "Feature",
  "properties": {
    "gn:admin1_code":"0.0",
    "gn:asciiname":"Kieru Base South",
    "gn:country_code":"CD",
    "gn:dem":648,
    "gn:feature_class":"P",
    "gn:feature_code":"PPL",
    "gn:name":"Kieru Base South",
    "gn:population":0,
    "gn:timezone":"Africa/Lubumbashi",
    "iso:country":"CD",
    "wof:name":"Kieru Base South",
    "wof:placetype":"locality"
},
  "geometry": {"coordinates":[30.18143,0.95839],"type":"Point"}
}