{
  "type": "Feature",
  "properties": {
    "gn:admin1_code":"25.0",
    "gn:asciiname":"Mitoko",
    "gn:country_code":"CD",
    "gn:dem":380,
    "gn:feature_class":"P",
    "gn:feature_code":"PPL",
    "gn:name":"Mitoko",
    "gn:population":0,
    "gn:timezone":"Africa/Kinshasa",
    "iso:country":"CD",
    "wof:name":"Mitoko",
    "wof:placetype":"locality"
},
  "geometry": {"coordinates":[20.40305,2.26952],"type":"Point"}
}