{
  "type": "Feature",
  "properties": {
    "gn:admin1_code":"15.0",
    "gn:asciiname":"Kakokweka",
    "gn:country_code":"CD",
    "gn:dem":805,
    "gn:feature_class":"P",
    "gn:feature_code":"PPL",
    "gn:name":"Kakokweka",
    "gn:population":0,
    "gn:timezone":"Africa/Lubumbashi",
    "iso:country":"CD",
    "wof:name":"Kakokweka",
    "wof:placetype":"locality"
},
  "geometry": {"coordinates":[25.65205,-9.06358],"type":"Point"}
}