{
  "type": "Feature",
  "properties": {
    "gn:admin1_code":"4.0",
    "gn:asciiname":"Kalengaie",
    "gn:country_code":"CD",
    "gn:dem":632,
    "gn:feature_class":"P",
    "gn:feature_code":"PPL",
    "gn:name":"Kalengaie",
    "gn:population":0,
    "gn:timezone":"Africa/Lubumbashi",
    "iso:country":"CD",
    "wof:name":"Kalengaie",
    "wof:placetype":"locality"
},
  "geometry": {"coordinates":[23.22559,-6.19689],"type":"Point"}
}