{
  "type": "Feature",
  "properties": {
    "gn:admin1_code":"15.0",
    "gn:asciiname":"Fukui",
    "gn:country_code":"CD",
    "gn:dem":1098,
    "gn:feature_class":"P",
    "gn:feature_code":"PPL",
    "gn:name":"Fukui",
    "gn:population":0,
    "gn:timezone":"Africa/Lubumbashi",
    "iso:country":"CD",
    "name:ces_x_preferred":[
        "Fukui"
    ],
    "name:deu_x_preferred":[
        "Fukui"
    ],
    "name:epo_x_preferred":[
        "Fukui"
    ],
    "name:fas_x_preferred":[
        "\u0641\u0648\u06a9\u0648\u0626\u06cc"
    ],
    "name:hun_x_preferred":[
        "Fukui"
    ],
    "name:ita_x_preferred":[
        "Fukui"
    ],
    "name:kor_x_preferred":[
        "\ud6c4\ucfe0\uc774"
    ],
    "name:nld_x_preferred":[
        "Fukui"
    ],
    "name:nor_x_preferred":[
        "Fukui"
    ],
    "name:por_x_preferred":[
        "Fukui"
    ],
    "name:ron_x_preferred":[
        "Fukui"
    ],
    "name:rus_x_preferred":[
        "\u0424\u0443\u043a\u0443\u0438"
    ],
    "name:slk_x_preferred":[
        "Fukui"
    ],
    "name:spa_x_preferred":[
        "Fukui"
    ],
    "name:swa_x_preferred":[
        "Fukui"
    ],
    "name:ukr_x_preferred":[
        "\u0424\u0443\u043a\u0443\u0439"
    ],
    "name:und_x_variant":[
        "Fukuie",
        "Fukuy"
    ],
    "wof:name":"Fukui",
    "wof:placetype":"locality"
},
  "geometry": {"coordinates":[25.01278,-8.55417],"type":"Point"}
}