{
  "type": "Feature",
  "properties": {
    "gn:admin1_code":"15.0",
    "gn:asciiname":"Fukui",
    "gn:country_code":"CD",
    "gn:dem":1098,
    "gn:feature_class":"P",
    "gn:feature_code":"PPL",
    "gn:name":"Fukui",
    "gn:population":0,
    "gn:timezone":"Africa/Lubumbashi",
    "iso:country":"CD",
    "name:und_x_variant":[
        "Fukuie",
        "Fukuy",
        "Fukui"
    ],
    "wof:name":"Fukui",
    "wof:placetype":"locality"
},
  "geometry": {"coordinates":[25.01278,-8.55417],"type":"Point"}
}