{
  "type": "Feature",
  "properties": {
    "gn:admin1_code":"16.0",
    "gn:asciiname":"Konia",
    "gn:country_code":"CD",
    "gn:dem":812,
    "gn:feature_class":"P",
    "gn:feature_code":"PPL",
    "gn:name":"Konia",
    "gn:population":0,
    "gn:timezone":"Africa/Lubumbashi",
    "iso:country":"CD",
    "name:ceb_x_preferred":[
        "Konia"
    ],
    "name:pol_x_preferred":[
        "Konia"
    ],
    "name:swe_x_preferred":[
        "Konia"
    ],
    "wof:name":"Konia",
    "wof:placetype":"locality"
},
  "geometry": {"coordinates":[28.80778,3.028],"type":"Point"}
}