{
  "type": "Feature",
  "properties": {
    "gn:admin1_code":"16.0",
    "gn:asciiname":"Baru",
    "gn:country_code":"CD",
    "gn:dem":701,
    "gn:feature_class":"P",
    "gn:feature_code":"PPL",
    "gn:name":"Baru",
    "gn:population":0,
    "gn:timezone":"Africa/Lubumbashi",
    "iso:country":"CD",
    "name:ces_x_preferred":[
        "Baru"
    ],
    "name:nld_x_preferred":[
        "Baru"
    ],
    "name:spa_x_preferred":[
        "Baru"
    ],
    "wof:name":"Baru",
    "wof:placetype":"locality"
},
  "geometry": {"coordinates":[28.38755,3.578],"type":"Point"}
}