{
  "type": "Feature",
  "properties": {
    "gn:admin1_code":"20.0",
    "gn:asciiname":"Mukota",
    "gn:country_code":"CD",
    "gn:dem":626,
    "gn:feature_class":"P",
    "gn:feature_code":"PPL",
    "gn:name":"Mukota",
    "gn:population":0,
    "gn:timezone":"Africa/Kinshasa",
    "iso:country":"CD",
    "name:deu_x_preferred":[
        "Mukota-Schwein"
    ],
    "name:vie_x_preferred":[
        "L\u1ee3n Mukota"
    ],
    "wof:name":"Mukota",
    "wof:placetype":"locality"
},
  "geometry": {"coordinates":[19.84058,-5.84884],"type":"Point"}
}