{
  "type": "Feature",
  "properties": {
    "gn:admin1_code":"23.0",
    "gn:asciiname":"Mwamba-Mudimba",
    "gn:country_code":"CD",
    "gn:dem":685,
    "gn:feature_class":"P",
    "gn:feature_code":"PPL",
    "gn:name":"Mwamba-Mudimba",
    "gn:population":0,
    "gn:timezone":"Africa/Lubumbashi",
    "iso:country":"CD",
    "wof:name":"Mwamba-Mudimba",
    "wof:placetype":"locality"
},
  "geometry": {"coordinates":[22.56524,-5.96726],"type":"Point"}
}