{
  "type": "Feature",
  "properties": {
    "gn:admin1_code":"21.0",
    "gn:asciiname":"Katupuile",
    "gn:country_code":"CD",
    "gn:dem":784,
    "gn:feature_class":"P",
    "gn:feature_code":"PPL",
    "gn:name":"Katupuile",
    "gn:population":0,
    "gn:timezone":"Africa/Lubumbashi",
    "iso:country":"CD",
    "wof:name":"Katupuile",
    "wof:placetype":"locality"
},
  "geometry": {"coordinates":[24.06667,-6.88333],"type":"Point"}
}