{
  "type": "Feature",
  "properties": {
    "gn:admin1_code":"22.0",
    "gn:asciiname":"Kansusi",
    "gn:country_code":"CD",
    "gn:dem":746,
    "gn:feature_class":"P",
    "gn:feature_code":"PPL",
    "gn:name":"Kansusi",
    "gn:population":0,
    "gn:timezone":"Africa/Lubumbashi",
    "iso:country":"CD",
    "wof:name":"Kansusi",
    "wof:placetype":"locality"
},
  "geometry": {"coordinates":[25.64555,-9.60986],"type":"Point"}
}