{
  "type": "Feature",
  "properties": {
    "gn:admin1_code":"24.0",
    "gn:asciiname":"Mushie",
    "gn:country_code":"CD",
    "gn:dem":351,
    "gn:feature_class":"P",
    "gn:feature_code":"PPL",
    "gn:name":"Mushie",
    "gn:population":0,
    "gn:timezone":"Africa/Kinshasa",
    "iso:country":"CD",
    "name:ceb_x_preferred":[
        "Mushie"
    ],
    "name:fra_x_preferred":[
        "Mushie"
    ],
    "name:ron_x_preferred":[
        "Mushie"
    ],
    "name:swe_x_preferred":[
        "Mushie"
    ],
    "wof:name":"Mushie",
    "wof:placetype":"locality"
},
  "geometry": {"coordinates":[18.37601,-3.13636],"type":"Point"}
}