{
  "type": "Feature",
  "properties": {
    "gn:admin1_code":"18.0",
    "gn:asciiname":"Kashikashika-Kitangua",
    "gn:country_code":"CD",
    "gn:dem":648,
    "gn:feature_class":"P",
    "gn:feature_code":"PPL",
    "gn:name":"Kashikashika-Kitangua",
    "gn:population":0,
    "gn:timezone":"Africa/Lubumbashi",
    "iso:country":"CD",
    "wof:name":"Kashikashika-Kitangua",
    "wof:placetype":"locality"
},
  "geometry": {"coordinates":[20.32162000000001,-6.30011],"type":"Point"}
}