{
  "type": "Feature",
  "properties": {
    "gn:admin1_code":"18.0",
    "gn:asciiname":"Nkese",
    "gn:country_code":"CD",
    "gn:dem":424,
    "gn:feature_class":"P",
    "gn:feature_code":"PPL",
    "gn:name":"Nkese",
    "gn:population":0,
    "gn:timezone":"Africa/Lubumbashi",
    "iso:country":"CD",
    "name:und_x_variant":[
        "Nsese"
    ],
    "wof:name":"Nkese",
    "wof:placetype":"locality"
},
  "geometry": {"coordinates":[21.52182,-2.5317],"type":"Point"}
}