{
  "type": "Feature",
  "properties": {
    "gn:admin1_code":"2.0",
    "gn:asciiname":"Kodoro",
    "gn:country_code":"CD",
    "gn:dem":357,
    "gn:feature_class":"P",
    "gn:feature_code":"PPL",
    "gn:name":"Kodoro",
    "gn:population":0,
    "gn:timezone":"Africa/Kinshasa",
    "iso:country":"CD",
    "wof:name":"Kodoro",
    "wof:placetype":"locality"
},
  "geometry": {"coordinates":[20.11609,1.27181],"type":"Point"}
}