{
  "type": "Feature",
  "properties": {
    "gn:admin1_code":"19.0",
    "gn:asciiname":"Mwakengi",
    "gn:country_code":"CD",
    "gn:dem":678,
    "gn:feature_class":"P",
    "gn:feature_code":"PPL",
    "gn:name":"Mwakengi",
    "gn:population":0,
    "gn:timezone":"Africa/Kinshasa",
    "iso:country":"CD",
    "wof:name":"Mwakengi",
    "wof:placetype":"locality"
},
  "geometry": {"coordinates":[17.36167,-7.60493],"type":"Point"}
}