{
  "type": "Feature",
  "properties": {
    "gn:admin1_code":"0.0",
    "gn:asciiname":"Lumpande",
    "gn:country_code":"CD",
    "gn:dem":1177,
    "gn:feature_class":"P",
    "gn:feature_code":"PPL",
    "gn:name":"Lumpande",
    "gn:population":0,
    "gn:timezone":"Africa/Lubumbashi",
    "iso:country":"CD",
    "wof:name":"Lumpande",
    "wof:placetype":"locality"
},
  "geometry": {"coordinates":[25.21431,-10.51916],"type":"Point"}
}