{
  "type": "Feature",
  "properties": {
    "gn:admin1_code":"13.0",
    "gn:asciiname":"Zeketembia",
    "gn:country_code":"CD",
    "gn:dem":533,
    "gn:feature_class":"P",
    "gn:feature_code":"PPL",
    "gn:name":"Zeketembia",
    "gn:population":0,
    "gn:timezone":"Africa/Lubumbashi",
    "iso:country":"CD",
    "wof:name":"Zeketembia",
    "wof:placetype":"locality"
},
  "geometry": {"coordinates":[24.02018,4.42788],"type":"Point"}
}