{
  "type": "Feature",
  "properties": {
    "gn:admin1_code":"22.0",
    "gn:asciiname":"Sandjandja",
    "gn:country_code":"CD",
    "gn:dem":1068,
    "gn:feature_class":"P",
    "gn:feature_code":"PPL",
    "gn:name":"Sandjandja",
    "gn:population":0,
    "gn:timezone":"Africa/Lubumbashi",
    "iso:country":"CD",
    "wof:name":"Sandjandja",
    "wof:placetype":"locality"
},
  "geometry": {"coordinates":[22.28352000000001,-9.82345],"type":"Point"}
}