{
  "type": "Feature",
  "properties": {
    "gn:admin1_code":"11.0",
    "gn:asciiname":"Kirungu",
    "gn:country_code":"CD",
    "gn:dem":1488,
    "gn:feature_class":"P",
    "gn:feature_code":"PPL",
    "gn:name":"Kirungu",
    "gn:population":0,
    "gn:timezone":"Africa/Lubumbashi",
    "iso:country":"CD",
    "wof:name":"Kirungu",
    "wof:placetype":"locality"
},
  "geometry": {"coordinates":[29.03333,-0.18333],"type":"Point"}
}