{
  "type": "Feature",
  "properties": {
    "gn:admin1_code":"22.0",
    "gn:asciiname":"Kasata",
    "gn:country_code":"CD",
    "gn:dem":997,
    "gn:feature_class":"P",
    "gn:feature_code":"PPL",
    "gn:name":"Kasata",
    "gn:population":0,
    "gn:timezone":"Africa/Lubumbashi",
    "iso:country":"CD",
    "wof:name":"Kasata",
    "wof:placetype":"locality"
},
  "geometry": {"coordinates":[23.1231,-10.45542],"type":"Point"}
}