{
  "type": "Feature",
  "properties": {
    "gn:admin1_code":"15.0",
    "gn:asciiname":"Kalongo",
    "gn:country_code":"CD",
    "gn:dem":726,
    "gn:feature_class":"P",
    "gn:feature_code":"PPL",
    "gn:name":"Kalongo",
    "gn:population":0,
    "gn:timezone":"Africa/Lubumbashi",
    "iso:country":"CD",
    "name:ceb_x_preferred":[
        "Kalongo"
    ],
    "name:fra_x_preferred":[
        "Kalongo"
    ],
    "name:lug_x_preferred":[
        "Kalongo"
    ],
    "name:urd_x_preferred":[
        "\u06a9\u0627\u0644\u0648\u0646\u06af\u0648"
    ],
    "wof:name":"Kalongo",
    "wof:placetype":"locality"
},
  "geometry": {"coordinates":[26.27475,-8.01421],"type":"Point"}
}