{
  "type": "Feature",
  "properties": {
    "gn:admin1_code":"19.0",
    "gn:asciiname":"Fwangongo",
    "gn:country_code":"CD",
    "gn:dem":624,
    "gn:feature_class":"P",
    "gn:feature_code":"PPL",
    "gn:name":"Fwangongo",
    "gn:population":0,
    "gn:timezone":"Africa/Kinshasa",
    "iso:country":"CD",
    "wof:name":"Fwangongo",
    "wof:placetype":"locality"
},
  "geometry": {"coordinates":[17.10817999999999,-6.975],"type":"Point"}
}