{
  "type": "Feature",
  "properties": {
    "gn:admin1_code":"18.0",
    "gn:asciiname":"Muakahandju",
    "gn:country_code":"CD",
    "gn:dem":823,
    "gn:feature_class":"P",
    "gn:feature_code":"PPL",
    "gn:name":"Muakahandju",
    "gn:population":0,
    "gn:timezone":"Africa/Lubumbashi",
    "iso:country":"CD",
    "wof:name":"Muakahandju",
    "wof:placetype":"locality"
},
  "geometry": {"coordinates":[20.24763,-6.58387],"type":"Point"}
}