{
  "type": "Feature",
  "properties": {
    "gn:admin1_code":"13.0",
    "gn:asciiname":"Epetia",
    "gn:country_code":"CD",
    "gn:dem":625,
    "gn:feature_class":"P",
    "gn:feature_code":"PPL",
    "gn:name":"Epetia",
    "gn:population":0,
    "gn:timezone":"Africa/Lubumbashi",
    "iso:country":"CD",
    "wof:name":"Epetia",
    "wof:placetype":"locality"
},
  "geometry": {"coordinates":[25.62116,3.37768],"type":"Point"}
}