{
  "type": "Feature",
  "properties": {
    "gn:admin1_code":"4.0",
    "gn:asciiname":"Tshisungu",
    "gn:country_code":"CD",
    "gn:dem":762,
    "gn:feature_class":"P",
    "gn:feature_code":"PPL",
    "gn:name":"Tshisungu",
    "gn:population":0,
    "gn:timezone":"Africa/Lubumbashi",
    "iso:country":"CD",
    "wof:name":"Tshisungu",
    "wof:placetype":"locality"
},
  "geometry": {"coordinates":[23.12631,-6.26311],"type":"Point"}
}