{
  "type": "Feature",
  "properties": {
    "gn:admin1_code":"14.0",
    "gn:asciiname":"Saya",
    "gn:country_code":"CD",
    "gn:dem":1126,
    "gn:feature_class":"P",
    "gn:feature_code":"PPL",
    "gn:name":"Saya",
    "gn:population":0,
    "gn:timezone":"Africa/Lubumbashi",
    "iso:country":"CD",
    "name:ceb_x_preferred":[
        "Saya"
    ],
    "name:deu_x_preferred":[
        "Saya"
    ],
    "name:fra_x_preferred":[
        "Saya"
    ],
    "name:ind_x_preferred":[
        "Saya"
    ],
    "name:spa_x_preferred":[
        "Saya"
    ],
    "name:swe_x_preferred":[
        "Saya"
    ],
    "wof:name":"Saya",
    "wof:placetype":"locality"
},
  "geometry": {"coordinates":[26.71849000000001,-10.65265],"type":"Point"}
}