{
  "type": "Feature",
  "properties": {
    "gn:admin1_code":"19.0",
    "gn:asciiname":"Kakenda",
    "gn:country_code":"CD",
    "gn:dem":879,
    "gn:feature_class":"P",
    "gn:feature_code":"PPL",
    "gn:name":"Kakenda",
    "gn:population":0,
    "gn:timezone":"Africa/Kinshasa",
    "iso:country":"CD",
    "wof:name":"Kakenda",
    "wof:placetype":"locality"
},
  "geometry": {"coordinates":[19.27891,-6.72264],"type":"Point"}
}