{
  "type": "Feature",
  "properties": {
    "gn:admin1_code":"16.0",
    "gn:asciiname":"Tibodri",
    "gn:country_code":"CD",
    "gn:dem":840,
    "gn:feature_class":"P",
    "gn:feature_code":"PPL",
    "gn:name":"Tibodri",
    "gn:population":0,
    "gn:timezone":"Africa/Lubumbashi",
    "iso:country":"CD",
    "name:und_x_variant":[
        "Tibodji",
        "Tibodri"
    ],
    "wof:name":"Tibodri",
    "wof:placetype":"locality"
},
  "geometry": {"coordinates":[29.07402,2.84433],"type":"Point"}
}