{
  "type": "Feature",
  "properties": {
    "gn:admin1_code":"30.0",
    "gn:asciiname":"Bakiliso",
    "gn:country_code":"CD",
    "gn:dem":702,
    "gn:feature_class":"P",
    "gn:feature_code":"PPL",
    "gn:name":"Bakiliso",
    "gn:population":0,
    "gn:timezone":"Africa/Lubumbashi",
    "iso:country":"CD",
    "wof:name":"Bakiliso",
    "wof:placetype":"locality"
},
  "geometry": {"coordinates":[27.18836,0.48996],"type":"Point"}
}