{
  "type": "Feature",
  "properties": {
    "gn:admin1_code":"20.0",
    "gn:asciiname":"Kilunda",
    "gn:country_code":"CD",
    "gn:dem":748,
    "gn:feature_class":"P",
    "gn:feature_code":"PPL",
    "gn:name":"Kilunda",
    "gn:population":0,
    "gn:timezone":"Africa/Kinshasa",
    "iso:country":"CD",
    "wof:name":"Kilunda",
    "wof:placetype":"locality"
},
  "geometry": {"coordinates":[17.69799,-5.66223],"type":"Point"}
}