{
  "type": "Feature",
  "properties": {
    "gn:admin1_code":"19.0",
    "gn:asciiname":"Malalo",
    "gn:country_code":"CD",
    "gn:dem":825,
    "gn:feature_class":"P",
    "gn:feature_code":"PPL",
    "gn:name":"Malalo",
    "gn:population":0,
    "gn:timezone":"Africa/Kinshasa",
    "iso:country":"CD",
    "wof:name":"Malalo",
    "wof:placetype":"locality"
},
  "geometry": {"coordinates":[17.22954,-5.99796],"type":"Point"}
}