{
  "type": "Feature",
  "properties": {
    "gn:admin1_code":"24.0",
    "gn:asciiname":"Kaiba",
    "gn:country_code":"CD",
    "gn:dem":373,
    "gn:feature_class":"P",
    "gn:feature_code":"PPL",
    "gn:name":"Kaiba",
    "gn:population":0,
    "gn:timezone":"Africa/Kinshasa",
    "iso:country":"CD",
    "name:deu_x_preferred":[
        "Kaiba"
    ],
    "name:fas_x_preferred":[
        "\u06a9\u0627\u06cc\u0628\u0627"
    ],
    "name:fra_x_preferred":[
        "Kaiba"
    ],
    "name:ita_x_preferred":[
        "Kaiba"
    ],
    "name:jpn_x_preferred":[
        "\u30ab\u30a4\u30d0"
    ],
    "name:rus_x_preferred":[
        "Kaiba"
    ],
    "name:spa_x_preferred":[
        "Kaiba"
    ],
    "name:ukr_x_preferred":[
        "Kaiba"
    ],
    "name:zho_x_preferred":[
        "\u6d77\u99ac"
    ],
    "wof:name":"Kaiba",
    "wof:placetype":"locality"
},
  "geometry": {"coordinates":[18.5632,-3.12069],"type":"Point"}
}