{
  "type": "Feature",
  "properties": {
    "gn:admin1_code":"30.0",
    "gn:asciiname":"Ongoka",
    "gn:country_code":"CD",
    "gn:dem":502,
    "gn:feature_class":"P",
    "gn:feature_code":"PPL",
    "gn:name":"Ongoka",
    "gn:population":0,
    "gn:timezone":"Africa/Lubumbashi",
    "iso:country":"CD",
    "name:und_x_variant":[
        "Ongoke",
        "Ongoka"
    ],
    "wof:name":"Ongoka",
    "wof:placetype":"locality"
},
  "geometry": {"coordinates":[26.02433,-1.41985],"type":"Point"}
}