{
  "type": "Feature",
  "properties": {
    "gn:admin1_code":"24.0",
    "gn:asciiname":"Malangwa",
    "gn:country_code":"CD",
    "gn:dem":308,
    "gn:feature_class":"P",
    "gn:feature_code":"PPL",
    "gn:name":"Malangwa",
    "gn:population":0,
    "gn:timezone":"Africa/Kinshasa",
    "iso:country":"CD",
    "wof:name":"Malangwa",
    "wof:placetype":"locality"
},
  "geometry": {"coordinates":[17.60303,-2.83318],"type":"Point"}
}