{
  "type": "Feature",
  "properties": {
    "gn:admin1_code":"18.0",
    "gn:asciiname":"Tshingungu",
    "gn:country_code":"CD",
    "gn:dem":780,
    "gn:feature_class":"P",
    "gn:feature_code":"PPL",
    "gn:name":"Tshingungu",
    "gn:population":0,
    "gn:timezone":"Africa/Lubumbashi",
    "iso:country":"CD",
    "wof:name":"Tshingungu",
    "wof:placetype":"locality"
},
  "geometry": {"coordinates":[21.66887,-6.65684],"type":"Point"}
}