{
  "type": "Feature",
  "properties": {
    "gn:admin1_code":"20.0",
    "gn:asciiname":"Mulule",
    "gn:country_code":"CD",
    "gn:dem":392,
    "gn:feature_class":"P",
    "gn:feature_code":"PPL",
    "gn:name":"Mulule",
    "gn:population":0,
    "gn:timezone":"Africa/Kinshasa",
    "iso:country":"CD",
    "name:und_x_variant":[
        "Mululu",
        "Mulule",
        "Mulole"
    ],
    "wof:name":"Mulule",
    "wof:placetype":"locality"
},
  "geometry": {"coordinates":[17.88022999999999,-3.97768],"type":"Point"}
}