{
  "type": "Feature",
  "properties": {
    "gn:admin1_code":"12.0",
    "gn:asciiname":"Lutshimu",
    "gn:country_code":"CD",
    "gn:dem":801,
    "gn:feature_class":"P",
    "gn:feature_code":"PPL",
    "gn:name":"Lutshimu",
    "gn:population":0,
    "gn:timezone":"Africa/Lubumbashi",
    "iso:country":"CD",
    "name:und_x_variant":[
        "Lutshima",
        "Lutshimu"
    ],
    "wof:name":"Lutshimu",
    "wof:placetype":"locality"
},
  "geometry": {"coordinates":[28.65258,-4.66859],"type":"Point"}
}