{
  "type": "Feature",
  "properties": {
    "gn:admin1_code":"10.0",
    "gn:asciiname":"Mukulumani",
    "gn:country_code":"CD",
    "gn:dem":777,
    "gn:feature_class":"P",
    "gn:feature_code":"PPL",
    "gn:name":"Mukulumani",
    "gn:population":0,
    "gn:timezone":"Africa/Lubumbashi",
    "iso:country":"CD",
    "wof:name":"Mukulumani",
    "wof:placetype":"locality"
},
  "geometry": {"coordinates":[27.81667,-4.68333],"type":"Point"}
}