{
  "type": "Feature",
  "properties": {
    "gn:admin1_code":"19.0",
    "gn:asciiname":"Mututia",
    "gn:country_code":"CD",
    "gn:dem":891,
    "gn:feature_class":"P",
    "gn:feature_code":"PPL",
    "gn:name":"Mututia",
    "gn:population":0,
    "gn:timezone":"Africa/Kinshasa",
    "iso:country":"CD",
    "wof:name":"Mututia",
    "wof:placetype":"locality"
},
  "geometry": {"coordinates":[17.60107,-6.56423],"type":"Point"}
}