{
  "type": "Feature",
  "properties": {
    "gn:admin1_code":"29.0",
    "gn:asciiname":"Lubasila",
    "gn:country_code":"CD",
    "gn:dem":678,
    "gn:feature_class":"P",
    "gn:feature_code":"PPL",
    "gn:name":"Lubasila",
    "gn:population":0,
    "gn:timezone":"Africa/Lubumbashi",
    "iso:country":"CD",
    "wof:name":"Lubasila",
    "wof:placetype":"locality"
},
  "geometry": {"coordinates":[28.34811,-7.12761],"type":"Point"}
}