{
  "type": "Feature",
  "properties": {
    "gn:admin1_code":"15.0",
    "gn:asciiname":"Kaluamba",
    "gn:country_code":"CD",
    "gn:dem":950,
    "gn:feature_class":"P",
    "gn:feature_code":"PPL",
    "gn:name":"Kaluamba",
    "gn:population":0,
    "gn:timezone":"Africa/Lubumbashi",
    "iso:country":"CD",
    "wof:name":"Kaluamba",
    "wof:placetype":"locality"
},
  "geometry": {"coordinates":[25.09805,-9.2466],"type":"Point"}
}