{
  "type": "Feature",
  "properties": {
    "gn:admin1_code":"8.0",
    "gn:asciiname":"Kumbi Troisieme",
    "gn:country_code":"CD",
    "gn:dem":549,
    "gn:feature_class":"P",
    "gn:feature_code":"PPL",
    "gn:name":"Kumbi Troisi\u00e8me",
    "gn:population":0,
    "gn:timezone":"Africa/Kinshasa",
    "iso:country":"CD",
    "wof:name":"Kumbi Troisieme",
    "wof:placetype":"locality"
},
  "geometry": {"coordinates":[14.32902,-5.83258],"type":"Point"}
}