{
  "type": "Feature",
  "properties": {
    "gn:admin1_code":"30.0",
    "gn:asciiname":"Yatola",
    "gn:country_code":"CD",
    "gn:dem":412,
    "gn:feature_class":"P",
    "gn:feature_code":"PPL",
    "gn:name":"Yatola",
    "gn:population":0,
    "gn:timezone":"Africa/Lubumbashi",
    "iso:country":"CD",
    "wof:name":"Yatola",
    "wof:placetype":"locality"
},
  "geometry": {"coordinates":[23.96667,-0.11667],"type":"Point"}
}