{
  "type": "Feature",
  "properties": {
    "gn:admin1_code":"13.0",
    "gn:asciiname":"Mbwa",
    "gn:country_code":"CD",
    "gn:dem":614,
    "gn:feature_class":"P",
    "gn:feature_code":"PPL",
    "gn:name":"Mbwa",
    "gn:population":0,
    "gn:timezone":"Africa/Lubumbashi",
    "iso:country":"CD",
    "wof:name":"Mbwa",
    "wof:placetype":"locality"
},
  "geometry": {"coordinates":[25.82224,3.69112],"type":"Point"}
}