{
  "type": "Feature",
  "properties": {
    "gn:admin1_code":"0.0",
    "gn:asciiname":"Mulowa",
    "gn:country_code":"CD",
    "gn:dem":1095,
    "gn:feature_class":"P",
    "gn:feature_code":"PPL",
    "gn:name":"Mulowa",
    "gn:population":0,
    "gn:timezone":"Africa/Lusaka",
    "iso:country":"CD",
    "wof:name":"Mulowa",
    "wof:placetype":"locality"
},
  "geometry": {"coordinates":[29.08333,-12.38333],"type":"Point"}
}