{
  "type": "Feature",
  "properties": {
    "gn:admin1_code":"10.0",
    "gn:asciiname":"Longalonga",
    "gn:country_code":"CD",
    "gn:dem":536,
    "gn:feature_class":"P",
    "gn:feature_code":"PPL",
    "gn:name":"Longalonga",
    "gn:population":0,
    "gn:timezone":"Africa/Lubumbashi",
    "iso:country":"CD",
    "wof:name":"Longalonga",
    "wof:placetype":"locality"
},
  "geometry": {"coordinates":[26.28333,-2.23333],"type":"Point"}
}