{
  "type": "Feature",
  "properties": {
    "gn:admin1_code":"25.0",
    "gn:asciiname":"Bolanga",
    "gn:country_code":"CD",
    "gn:dem":428,
    "gn:feature_class":"P",
    "gn:feature_code":"PPL",
    "gn:name":"Bolanga",
    "gn:population":0,
    "gn:timezone":"Africa/Kinshasa",
    "iso:country":"CD",
    "wof:name":"Bolanga",
    "wof:placetype":"locality"
},
  "geometry": {"coordinates":[21.4595,2.86964],"type":"Point"}
}