{
  "type": "Feature",
  "properties": {
    "gn:admin1_code":"31.0",
    "gn:asciiname":"Yaniangombula",
    "gn:country_code":"CD",
    "gn:dem":413,
    "gn:feature_class":"P",
    "gn:feature_code":"PPL",
    "gn:name":"Yaniangombula",
    "gn:population":0,
    "gn:timezone":"Africa/Kinshasa",
    "iso:country":"CD",
    "wof:name":"Yaniangombula",
    "wof:placetype":"locality"
},
  "geometry": {"coordinates":[22.90296,-1.04832],"type":"Point"}
}