{
  "type": "Feature",
  "properties": {
    "gn:admin1_code":"19.0",
    "gn:asciiname":"Mulasa-Kakwitu",
    "gn:country_code":"CD",
    "gn:dem":790,
    "gn:feature_class":"P",
    "gn:feature_code":"PPL",
    "gn:name":"Mulasa-Kakwitu",
    "gn:population":0,
    "gn:timezone":"Africa/Kinshasa",
    "iso:country":"CD",
    "wof:name":"Mulasa-Kakwitu",
    "wof:placetype":"locality"
},
  "geometry": {"coordinates":[17.8011,-5.70075],"type":"Point"}
}