{
  "type": "Feature",
  "properties": {
    "gn:admin1_code":"27.0",
    "gn:asciiname":"Dikandakate",
    "gn:country_code":"CD",
    "gn:dem":555,
    "gn:feature_class":"P",
    "gn:feature_code":"PPL",
    "gn:name":"Dikandakate",
    "gn:population":0,
    "gn:timezone":"Africa/Lubumbashi",
    "iso:country":"CD",
    "wof:name":"Dikandakate",
    "wof:placetype":"locality"
},
  "geometry": {"coordinates":[23.35,-3.56667],"type":"Point"}
}