{
  "type": "Feature",
  "properties": {
    "gn:admin1_code":"18.0",
    "gn:asciiname":"Kayembe",
    "gn:country_code":"CD",
    "gn:dem":646,
    "gn:feature_class":"P",
    "gn:feature_code":"PPL",
    "gn:name":"Kayembe",
    "gn:population":0,
    "gn:timezone":"Africa/Lubumbashi",
    "iso:country":"CD",
    "wof:name":"Kayembe",
    "wof:placetype":"locality"
},
  "geometry": {"coordinates":[21.61678,-5.63436],"type":"Point"}
}