{
  "type": "Feature",
  "properties": {
    "gn:admin1_code":"19.0",
    "gn:asciiname":"Shamanzenze",
    "gn:country_code":"CD",
    "gn:dem":1088,
    "gn:feature_class":"P",
    "gn:feature_code":"PPL",
    "gn:name":"Shamanzenze",
    "gn:population":0,
    "gn:timezone":"Africa/Kinshasa",
    "iso:country":"CD",
    "wof:name":"Shamanzenze",
    "wof:placetype":"locality"
},
  "geometry": {"coordinates":[19.28763,-7.9469],"type":"Point"}
}