{
  "type": "Feature",
  "properties": {
    "gn:admin1_code":"12.0",
    "gn:asciiname":"Nyamukubi",
    "gn:country_code":"CD",
    "gn:dem":1748,
    "gn:feature_class":"P",
    "gn:feature_code":"PPL",
    "gn:name":"Nyamukubi",
    "gn:population":0,
    "gn:timezone":"Africa/Lubumbashi",
    "iso:country":"CD",
    "name:und_x_variant":[
        "Nyamakubi",
        "Nyamukubi"
    ],
    "wof:name":"Nyamukubi",
    "wof:placetype":"locality"
},
  "geometry": {"coordinates":[28.90333,-1.98361],"type":"Point"}
}