{
  "type": "Feature",
  "properties": {
    "gn:admin1_code":"18.0",
    "gn:asciiname":"Shadito",
    "gn:country_code":"CD",
    "gn:dem":469,
    "gn:feature_class":"P",
    "gn:feature_code":"PPL",
    "gn:name":"Shadito",
    "gn:population":0,
    "gn:timezone":"Africa/Lubumbashi",
    "iso:country":"CD",
    "wof:name":"Shadito",
    "wof:placetype":"locality"
},
  "geometry": {"coordinates":[20.26739,-4.55301],"type":"Point"}
}