{
  "type": "Feature",
  "properties": {
    "gn:admin1_code":"16.0",
    "gn:asciiname":"Bokwoyo",
    "gn:country_code":"CD",
    "gn:dem":720,
    "gn:feature_class":"P",
    "gn:feature_code":"PPL",
    "gn:name":"Bokwoyo",
    "gn:population":0,
    "gn:timezone":"Africa/Lubumbashi",
    "iso:country":"CD",
    "wof:name":"Bokwoyo",
    "wof:placetype":"locality"
},
  "geometry": {"coordinates":[27.95589,4.50476],"type":"Point"}
}