{
  "type": "Feature",
  "properties": {
    "gn:admin1_code":"4.0",
    "gn:asciiname":"Tshaba",
    "gn:country_code":"CD",
    "gn:dem":655,
    "gn:feature_class":"P",
    "gn:feature_code":"PPL",
    "gn:name":"Tshaba",
    "gn:population":0,
    "gn:timezone":"Africa/Lubumbashi",
    "iso:country":"CD",
    "wof:name":"Tshaba",
    "wof:placetype":"locality"
},
  "geometry": {"coordinates":[23.50854,-6.33176],"type":"Point"}
}