{
  "type": "Feature",
  "properties": {
    "gn:admin1_code":"25.0",
    "gn:asciiname":"Busu-Mabo",
    "gn:country_code":"CD",
    "gn:dem":366,
    "gn:feature_class":"P",
    "gn:feature_code":"PPL",
    "gn:name":"Busu-Mabo",
    "gn:population":0,
    "gn:timezone":"Africa/Kinshasa",
    "iso:country":"CD",
    "name:und_x_variant":[
        "Busu Maso",
        "Busu-Mabo"
    ],
    "wof:name":"Busu-Mabo",
    "wof:placetype":"locality"
},
  "geometry": {"coordinates":[20.86817000000001,2.82811],"type":"Point"}
}