{
  "type": "Feature",
  "properties": {
    "gn:admin1_code":"27.0",
    "gn:asciiname":"Lubo",
    "gn:country_code":"CD",
    "gn:dem":419,
    "gn:feature_class":"P",
    "gn:feature_code":"PPL",
    "gn:name":"Lubo",
    "gn:population":0,
    "gn:timezone":"Africa/Lubumbashi",
    "iso:country":"CD",
    "name:und_x_variant":[
        "Lobo",
        "Lobo I",
        "Lubo"
    ],
    "wof:name":"Lubo",
    "wof:placetype":"locality"
},
  "geometry": {"coordinates":[23.26236,-4.80534],"type":"Point"}
}