{
  "type": "Feature",
  "properties": {
    "gn:admin1_code":"18.0",
    "gn:asciiname":"Kikungamashi",
    "gn:country_code":"CD",
    "gn:dem":486,
    "gn:feature_class":"P",
    "gn:feature_code":"PPL",
    "gn:name":"Kikungamashi",
    "gn:population":0,
    "gn:timezone":"Africa/Lubumbashi",
    "iso:country":"CD",
    "wof:name":"Kikungamashi",
    "wof:placetype":"locality"
},
  "geometry": {"coordinates":[20.57125,-6.02931],"type":"Point"}
}