{
  "type": "Feature",
  "properties": {
    "gn:admin1_code":"27.0",
    "gn:asciiname":"Tumba",
    "gn:country_code":"CD",
    "gn:dem":558,
    "gn:feature_class":"P",
    "gn:feature_code":"PPL",
    "gn:name":"Tumba",
    "gn:population":0,
    "gn:timezone":"Africa/Lubumbashi",
    "iso:country":"CD",
    "name:ceb_x_preferred":[
        "Tumba"
    ],
    "name:ces_x_preferred":[
        "Tumba"
    ],
    "name:deu_x_preferred":[
        "Tumba"
    ],
    "name:fin_x_preferred":[
        "Tumba"
    ],
    "name:fra_x_preferred":[
        "Tumba"
    ],
    "name:hrv_x_preferred":[
        "Tumba"
    ],
    "name:ita_x_preferred":[
        "Tumba"
    ],
    "name:lat_x_preferred":[
        "Tumba"
    ],
    "name:lav_x_preferred":[
        "Tumba"
    ],
    "name:nld_x_preferred":[
        "Tumba"
    ],
    "name:pol_x_preferred":[
        "Tumba"
    ],
    "name:slk_x_preferred":[
        "Tumba"
    ],
    "name:swe_x_preferred":[
        "Tumba"
    ],
    "wof:name":"Tumba",
    "wof:placetype":"locality"
},
  "geometry": {"coordinates":[22.53333,-3.63333],"type":"Point"}
}