{
  "type": "Feature",
  "properties": {
    "gn:admin1_code":"12.0",
    "gn:asciiname":"Lubafu",
    "gn:country_code":"CD",
    "gn:dem":1848,
    "gn:feature_class":"P",
    "gn:feature_code":"PPL",
    "gn:name":"Lubafu",
    "gn:population":0,
    "gn:timezone":"Africa/Lubumbashi",
    "iso:country":"CD",
    "wof:name":"Lubafu",
    "wof:placetype":"locality"
},
  "geometry": {"coordinates":[28.71231,-1.93696],"type":"Point"}
}