{
  "type": "Feature",
  "properties": {
    "gn:admin1_code":"11.0",
    "gn:asciiname":"Kyalema",
    "gn:country_code":"CD",
    "gn:dem":1438,
    "gn:feature_class":"P",
    "gn:feature_code":"PPL",
    "gn:name":"Kyalema",
    "gn:population":0,
    "gn:timezone":"Africa/Lubumbashi",
    "iso:country":"CD",
    "wof:name":"Kyalema",
    "wof:placetype":"locality"
},
  "geometry": {"coordinates":[29.76257,0.23388],"type":"Point"}
}