{
  "type": "Feature",
  "properties": {
    "gn:admin1_code":"13.0",
    "gn:asciiname":"Baengu",
    "gn:country_code":"CD",
    "gn:dem":429,
    "gn:feature_class":"P",
    "gn:feature_code":"PPL",
    "gn:name":"Baengu",
    "gn:population":0,
    "gn:timezone":"Africa/Lubumbashi",
    "iso:country":"CD",
    "wof:name":"Baengu",
    "wof:placetype":"locality"
},
  "geometry": {"coordinates":[23.62375,2.44946],"type":"Point"}
}