{
  "type": "Feature",
  "properties": {
    "gn:admin1_code":"17.0",
    "gn:asciiname":"Shari",
    "gn:country_code":"CD",
    "gn:dem":1569,
    "gn:feature_class":"P",
    "gn:feature_code":"PPL",
    "gn:name":"Shari",
    "gn:population":0,
    "gn:timezone":"Africa/Lubumbashi",
    "iso:country":"CD",
    "wof:name":"Shari",
    "wof:placetype":"locality"
},
  "geometry": {"coordinates":[30.3461,1.93279],"type":"Point"}
}