{
  "type": "Feature",
  "properties": {
    "gn:admin1_code":"17.0",
    "gn:asciiname":"Shari",
    "gn:country_code":"CD",
    "gn:dem":1569,
    "gn:feature_class":"P",
    "gn:feature_code":"PPL",
    "gn:name":"Shari",
    "gn:population":0,
    "gn:timezone":"Africa/Lubumbashi",
    "iso:country":"CD",
    "name:ceb_x_preferred":[
        "Shari"
    ],
    "name:deu_x_preferred":[
        "Shari"
    ],
    "name:fra_x_preferred":[
        "Shari"
    ],
    "name:hrv_x_preferred":[
        "Shari"
    ],
    "name:nld_x_preferred":[
        "Shari"
    ],
    "name:rus_x_preferred":[
        "\u0428\u0430\u0440\u0438"
    ],
    "name:swe_x_preferred":[
        "Shari"
    ],
    "name:ukr_x_preferred":[
        "\u0428\u0430\u0440\u0456"
    ],
    "name:uzb_x_preferred":[
        "Shari"
    ],
    "wof:name":"Shari",
    "wof:placetype":"locality"
},
  "geometry": {"coordinates":[30.3461,1.93279],"type":"Point"}
}