{
  "type": "Feature",
  "properties": {
    "gn:admin1_code":"10.0",
    "gn:asciiname":"Kabinda Mukandilwa",
    "gn:country_code":"CD",
    "gn:dem":566,
    "gn:feature_class":"P",
    "gn:feature_code":"PPL",
    "gn:name":"Kabinda Mukandilwa",
    "gn:population":0,
    "gn:timezone":"Africa/Lubumbashi",
    "iso:country":"CD",
    "wof:name":"Kabinda Mukandilwa",
    "wof:placetype":"locality"
},
  "geometry": {"coordinates":[26.30765,-4.06575],"type":"Point"}
}