{
  "type": "Feature",
  "properties": {
    "gn:admin1_code":"19.0",
    "gn:asciiname":"Kimbidji",
    "gn:country_code":"CD",
    "gn:dem":743,
    "gn:feature_class":"P",
    "gn:feature_code":"PPL",
    "gn:name":"Kimbidji",
    "gn:population":0,
    "gn:timezone":"Africa/Kinshasa",
    "iso:country":"CD",
    "wof:name":"Kimbidji",
    "wof:placetype":"locality"
},
  "geometry": {"coordinates":[17.60986,-7.20078],"type":"Point"}
}