{
  "type": "Feature",
  "properties": {
    "gn:admin1_code":"31.0",
    "gn:asciiname":"Wamba",
    "gn:country_code":"CD",
    "gn:dem":370,
    "gn:feature_class":"P",
    "gn:feature_code":"PPL",
    "gn:name":"Wamba",
    "gn:population":0,
    "gn:timezone":"Africa/Kinshasa",
    "iso:country":"CD",
    "name:ceb_x_preferred":[
        "Wamba"
    ],
    "name:deu_x_preferred":[
        "Wamba"
    ],
    "name:eus_x_preferred":[
        "Wamba"
    ],
    "name:fra_x_preferred":[
        "Wamba"
    ],
    "name:glg_x_preferred":[
        "Wamba"
    ],
    "name:hye_x_preferred":[
        "\u054e\u0561\u0574\u0562\u0561"
    ],
    "name:ita_x_preferred":[
        "Wamba"
    ],
    "name:nld_x_preferred":[
        "Wamba"
    ],
    "name:por_x_preferred":[
        "Wamba"
    ],
    "name:por_x_variant":[
        "Vamba"
    ],
    "name:ron_x_preferred":[
        "Wamba"
    ],
    "name:rus_x_preferred":[
        "\u0412\u0430\u043c\u0431\u0430"
    ],
    "name:spa_x_preferred":[
        "Wamba"
    ],
    "name:swe_x_preferred":[
        "Wamba"
    ],
    "name:tur_x_preferred":[
        "Wamba"
    ],
    "name:ukr_x_preferred":[
        "\u0412\u0430\u043c\u0431\u0430"
    ],
    "name:urd_x_preferred":[
        "\u0648\u0627\u0645\u0628\u0627"
    ],
    "name:vie_x_preferred":[
        "Wamba"
    ],
    "name:war_x_preferred":[
        "Wamba"
    ],
    "name:zho_cn_x_preferred":[
        "\u4e07\u5df4"
    ],
    "name:zho_tw_x_preferred":[
        "\u842c\u5df4"
    ],
    "wof:name":"Wamba",
    "wof:placetype":"locality"
},
  "geometry": {"coordinates":[21.82246,0.1565],"type":"Point"}
}