{
  "type": "Feature",
  "properties": {
    "gn:admin1_code":"23.0",
    "gn:asciiname":"Kamwenga",
    "gn:country_code":"CD",
    "gn:dem":785,
    "gn:feature_class":"P",
    "gn:feature_code":"PPL",
    "gn:name":"Kamwenga",
    "gn:population":0,
    "gn:timezone":"Africa/Lubumbashi",
    "iso:country":"CD",
    "wof:name":"Kamwenga",
    "wof:placetype":"locality"
},
  "geometry": {"coordinates":[22.51893,-6.5512],"type":"Point"}
}