{
  "type": "Feature",
  "properties": {
    "gn:admin1_code":"15.0",
    "gn:asciiname":"Gaba",
    "gn:country_code":"CD",
    "gn:dem":943,
    "gn:feature_class":"P",
    "gn:feature_code":"PPL",
    "gn:name":"Gaba",
    "gn:population":0,
    "gn:timezone":"Africa/Lubumbashi",
    "iso:country":"CD",
    "name:und_x_variant":[
        "Gambo",
        "Gaba"
    ],
    "wof:name":"Gaba",
    "wof:placetype":"locality"
},
  "geometry": {"coordinates":[25.95145,-8.52797],"type":"Point"}
}