{
  "type": "Feature",
  "properties": {
    "gn:admin1_code":"29.0",
    "gn:asciiname":"Moliro",
    "gn:country_code":"CD",
    "gn:dem":825,
    "gn:feature_class":"P",
    "gn:feature_code":"PPL",
    "gn:name":"Moliro",
    "gn:population":0,
    "gn:timezone":"Africa/Lubumbashi",
    "iso:country":"CD",
    "wof:name":"Moliro",
    "wof:placetype":"locality"
},
  "geometry": {"coordinates":[30.56338,-8.24914],"type":"Point"}
}