{
  "type": "Feature",
  "properties": {
    "gn:admin1_code":"19.0",
    "gn:asciiname":"Kambakala",
    "gn:country_code":"CD",
    "gn:dem":1003,
    "gn:feature_class":"P",
    "gn:feature_code":"PPL",
    "gn:name":"Kambakala",
    "gn:population":0,
    "gn:timezone":"Africa/Kinshasa",
    "iso:country":"CD",
    "wof:name":"Kambakala",
    "wof:placetype":"locality"
},
  "geometry": {"coordinates":[18.41915,-7.00282],"type":"Point"}
}