{
  "type": "Feature",
  "properties": {
    "gn:admin1_code":"23.0",
    "gn:asciiname":"Tshisuaka",
    "gn:country_code":"CD",
    "gn:dem":833,
    "gn:feature_class":"P",
    "gn:feature_code":"PPL",
    "gn:name":"Tshisuaka",
    "gn:population":0,
    "gn:timezone":"Africa/Lubumbashi",
    "iso:country":"CD",
    "wof:name":"Tshisuaka",
    "wof:placetype":"locality"
},
  "geometry": {"coordinates":[22.64473,-6.49849],"type":"Point"}
}