{
  "type": "Feature",
  "properties": {
    "gn:admin1_code":"23.0",
    "gn:asciiname":"Kolambo",
    "gn:country_code":"CD",
    "gn:dem":904,
    "gn:feature_class":"P",
    "gn:feature_code":"PPL",
    "gn:name":"Kolambo",
    "gn:population":0,
    "gn:timezone":"Africa/Lubumbashi",
    "iso:country":"CD",
    "name:und_x_variant":[
        "Kasombo",
        "Kalombo",
        "Kolambo"
    ],
    "wof:name":"Kolambo",
    "wof:placetype":"locality"
},
  "geometry": {"coordinates":[21.97318,-7.56337],"type":"Point"}
}