{
  "type": "Feature",
  "properties": {
    "gn:admin1_code":"18.0",
    "gn:asciiname":"Lolo",
    "gn:country_code":"CD",
    "gn:dem":491,
    "gn:feature_class":"P",
    "gn:feature_code":"PPL",
    "gn:name":"Lolo",
    "gn:population":0,
    "gn:timezone":"Africa/Lubumbashi",
    "iso:country":"CD",
    "name:ceb_x_preferred":[
        "Lolo"
    ],
    "name:deu_x_preferred":[
        "Lolo"
    ],
    "name:fra_x_preferred":[
        "Lolo"
    ],
    "name:heb_x_preferred":[
        "\u05dc\u05d5\u05dc\u05d5"
    ],
    "name:ind_x_preferred":[
        "Lolo"
    ],
    "name:ita_x_preferred":[
        "Lolo"
    ],
    "name:nld_x_preferred":[
        "Lolo"
    ],
    "name:por_x_preferred":[
        "Lolo"
    ],
    "name:rus_x_preferred":[
        "\u041b\u043e\u043b\u043e"
    ],
    "name:spa_x_preferred":[
        "Lolo"
    ],
    "name:swe_x_preferred":[
        "Lolo"
    ],
    "wof:name":"Lolo",
    "wof:placetype":"locality"
},
  "geometry": {"coordinates":[21.88552,-3.79352],"type":"Point"}
}