{
  "type": "Feature",
  "properties": {
    "gn:admin1_code":"14.0",
    "gn:asciiname":"Lula",
    "gn:country_code":"CD",
    "gn:dem":1467,
    "gn:feature_class":"P",
    "gn:feature_code":"PPL",
    "gn:name":"Lula",
    "gn:population":0,
    "gn:timezone":"Africa/Lubumbashi",
    "iso:country":"CD",
    "wof:name":"Lula",
    "wof:placetype":"locality"
},
  "geometry": {"coordinates":[27.46667,-8.58333],"type":"Point"}
}