{
  "type": "Feature",
  "properties": {
    "gn:admin1_code":"19.0",
    "gn:asciiname":"Mafumu",
    "gn:country_code":"CD",
    "gn:dem":846,
    "gn:feature_class":"P",
    "gn:feature_code":"PPL",
    "gn:name":"Mafumu",
    "gn:population":0,
    "gn:timezone":"Africa/Kinshasa",
    "iso:country":"CD",
    "wof:name":"Mafumu",
    "wof:placetype":"locality"
},
  "geometry": {"coordinates":[17.51794,-6.15415],"type":"Point"}
}