{
  "type": "Feature",
  "properties": {
    "gn:admin1_code":"8.0",
    "gn:asciiname":"Lokandu",
    "gn:country_code":"CD",
    "gn:dem":96,
    "gn:feature_class":"P",
    "gn:feature_code":"PPL",
    "gn:name":"Lokandu",
    "gn:population":0,
    "gn:timezone":"Africa/Kinshasa",
    "iso:country":"CD",
    "name:fra_x_preferred":[
        "Lokandu"
    ],
    "wof:name":"Lokandu",
    "wof:placetype":"locality"
},
  "geometry": {"coordinates":[13.01833,-5.79969],"type":"Point"}
}