{
  "type": "Feature",
  "properties": {
    "gn:admin1_code":"22.0",
    "gn:asciiname":"Madia-Musonge",
    "gn:country_code":"CD",
    "gn:dem":887,
    "gn:feature_class":"P",
    "gn:feature_code":"PPL",
    "gn:name":"Madia-Musonge",
    "gn:population":0,
    "gn:timezone":"Africa/Lubumbashi",
    "iso:country":"CD",
    "wof:name":"Madia-Musonge",
    "wof:placetype":"locality"
},
  "geometry": {"coordinates":[22.6011,-8.30054],"type":"Point"}
}