{
  "type": "Feature",
  "properties": {
    "gn:admin1_code":"19.0",
    "gn:asciiname":"Gabia",
    "gn:country_code":"CD",
    "gn:dem":402,
    "gn:feature_class":"P",
    "gn:feature_code":"PPL",
    "gn:name":"Gabia",
    "gn:population":0,
    "gn:timezone":"Africa/Kinshasa",
    "iso:country":"CD",
    "name:glg_x_preferred":[
        "Gabia"
    ],
    "name:spa_x_preferred":[
        "Gabia"
    ],
    "wof:name":"Gabia",
    "wof:placetype":"locality"
},
  "geometry": {"coordinates":[17.12415,-4.56467],"type":"Point"}
}