{
  "type": "Feature",
  "properties": {
    "gn:admin1_code":"22.0",
    "gn:asciiname":"Samukundu",
    "gn:country_code":"CD",
    "gn:dem":1093,
    "gn:feature_class":"P",
    "gn:feature_code":"PPL",
    "gn:name":"Samukundu",
    "gn:population":0,
    "gn:timezone":"Africa/Lubumbashi",
    "iso:country":"CD",
    "wof:name":"Samukundu",
    "wof:placetype":"locality"
},
  "geometry": {"coordinates":[23.33826,-10.40532],"type":"Point"}
}