{
  "type": "Feature",
  "properties": {
    "gn:admin1_code":"16.0",
    "gn:asciiname":"Solonga",
    "gn:country_code":"CD",
    "gn:dem":733,
    "gn:feature_class":"P",
    "gn:feature_code":"PPL",
    "gn:name":"Solonga",
    "gn:population":0,
    "gn:timezone":"Africa/Lubumbashi",
    "iso:country":"CD",
    "wof:name":"Solonga",
    "wof:placetype":"locality"
},
  "geometry": {"coordinates":[28.07257,4.03852],"type":"Point"}
}