{
  "type": "Feature",
  "properties": {
    "gn:admin1_code":"19.0",
    "gn:asciiname":"Mvula-Mavumbi",
    "gn:country_code":"CD",
    "gn:dem":600,
    "gn:feature_class":"P",
    "gn:feature_code":"PPL",
    "gn:name":"Mvula-Mavumbi",
    "gn:population":0,
    "gn:timezone":"Africa/Kinshasa",
    "iso:country":"CD",
    "name:und_x_variant":[
        "Mvula-Muvumbi"
    ],
    "wof:name":"Mvula-Mavumbi",
    "wof:placetype":"locality"
},
  "geometry": {"coordinates":[17.37088,-4.96552],"type":"Point"}
}