{
  "type": "Feature",
  "properties": {
    "gn:admin1_code":"13.0",
    "gn:asciiname":"Sobia",
    "gn:country_code":"CD",
    "gn:dem":408,
    "gn:feature_class":"P",
    "gn:feature_code":"PPL",
    "gn:name":"Sobia",
    "gn:population":0,
    "gn:timezone":"Africa/Lubumbashi",
    "iso:country":"CD",
    "name:ara_x_preferred":[
        "\u062b\u0648\u064a\u0628\u0629"
    ],
    "name:ava_x_preferred":[
        "\u0421\u0443\u0432\u0430\u0439\u0431\u0430"
    ],
    "name:urd_x_preferred":[
        "\u062b\u0648\u06cc\u0628\u06c1"
    ],
    "wof:name":"Sobia",
    "wof:placetype":"locality"
},
  "geometry": {"coordinates":[23.89746,3.40721],"type":"Point"}
}