{
  "type": "Feature",
  "properties": {
    "gn:admin1_code":"25.0",
    "gn:asciiname":"Yapama",
    "gn:country_code":"CD",
    "gn:dem":429,
    "gn:feature_class":"P",
    "gn:feature_code":"PPL",
    "gn:name":"Yapama",
    "gn:population":0,
    "gn:timezone":"Africa/Kinshasa",
    "iso:country":"CD",
    "wof:name":"Yapama",
    "wof:placetype":"locality"
},
  "geometry": {"coordinates":[21.963,2.77701],"type":"Point"}
}