{
  "type": "Feature",
  "properties": {
    "gn:admin1_code":"22.0",
    "gn:asciiname":"Postolo Deuxieme",
    "gn:country_code":"CD",
    "gn:dem":1008,
    "gn:feature_class":"P",
    "gn:feature_code":"PPL",
    "gn:name":"Postolo Deuxi\u00e8me",
    "gn:population":0,
    "gn:timezone":"Africa/Lubumbashi",
    "iso:country":"CD",
    "wof:name":"Postolo Deuxieme",
    "wof:placetype":"locality"
},
  "geometry": {"coordinates":[23.16022,-10.24729],"type":"Point"}
}