{
  "type": "Feature",
  "properties": {
    "gn:admin1_code":"16.0",
    "gn:asciiname":"Likambo",
    "gn:country_code":"CD",
    "gn:dem":662,
    "gn:feature_class":"P",
    "gn:feature_code":"PPL",
    "gn:name":"Likambo",
    "gn:population":0,
    "gn:timezone":"Africa/Lubumbashi",
    "iso:country":"CD",
    "wof:name":"Likambo",
    "wof:placetype":"locality"
},
  "geometry": {"coordinates":[27.35873,3.8739],"type":"Point"}
}