{
  "type": "Feature",
  "properties": {
    "gn:admin1_code":"23.0",
    "gn:asciiname":"Tshimbadi",
    "gn:country_code":"CD",
    "gn:dem":761,
    "gn:feature_class":"P",
    "gn:feature_code":"PPL",
    "gn:name":"Tshimbadi",
    "gn:population":0,
    "gn:timezone":"Africa/Lubumbashi",
    "iso:country":"CD",
    "wof:name":"Tshimbadi",
    "wof:placetype":"locality"
},
  "geometry": {"coordinates":[22.89857,-5.99489],"type":"Point"}
}