{
  "type": "Feature",
  "properties": {
    "gn:admin1_code":"26.0",
    "gn:asciiname":"Kulua-Loko",
    "gn:country_code":"CD",
    "gn:dem":377,
    "gn:feature_class":"P",
    "gn:feature_code":"PPL",
    "gn:name":"Kulua-Loko",
    "gn:population":0,
    "gn:timezone":"Africa/Kinshasa",
    "iso:country":"CD",
    "name:und_x_variant":[
        "Kulua-Loka",
        "Kulua-Loko"
    ],
    "wof:name":"Kulua-Loko",
    "wof:placetype":"locality"
},
  "geometry": {"coordinates":[20.67532000000001,3.91038],"type":"Point"}
}