{
  "type": "Feature",
  "properties": {
    "gn:admin1_code":"14.0",
    "gn:asciiname":"Washile",
    "gn:country_code":"CD",
    "gn:dem":1204,
    "gn:feature_class":"P",
    "gn:feature_code":"PPL",
    "gn:name":"Washile",
    "gn:population":0,
    "gn:timezone":"Africa/Lubumbashi",
    "iso:country":"CD",
    "wof:name":"Washile",
    "wof:placetype":"locality"
},
  "geometry": {"coordinates":[27.84785,-8.87892],"type":"Point"}
}