{
  "type": "Feature",
  "properties": {
    "gn:admin1_code":"28.0",
    "gn:asciiname":"Mangbwala",
    "gn:country_code":"CD",
    "gn:dem":329,
    "gn:feature_class":"P",
    "gn:feature_code":"PPL",
    "gn:name":"Mangbwala",
    "gn:population":0,
    "gn:timezone":"Africa/Kinshasa",
    "iso:country":"CD",
    "name:und_x_variant":[
        "Mongbwala",
        "Mongwala",
        "Mangbwala"
    ],
    "wof:name":"Mangbwala",
    "wof:placetype":"locality"
},
  "geometry": {"coordinates":[18.15747,2.23479],"type":"Point"}
}