{
  "type": "Feature",
  "properties": {
    "gn:admin1_code":"12.0",
    "gn:asciiname":"Mboko",
    "gn:country_code":"CD",
    "gn:dem":803,
    "gn:feature_class":"P",
    "gn:feature_code":"PPL",
    "gn:name":"Mboko",
    "gn:population":0,
    "gn:timezone":"Africa/Lubumbashi",
    "iso:country":"CD",
    "name:ceb_x_preferred":[
        "Mboko"
    ],
    "name:swe_x_preferred":[
        "Mboko"
    ],
    "wof:name":"Mboko",
    "wof:placetype":"locality"
},
  "geometry": {"coordinates":[29.09485,-3.77444],"type":"Point"}
}