{
  "type": "Feature",
  "properties": {
    "gn:admin1_code":"25.0",
    "gn:asciiname":"Kwanza",
    "gn:country_code":"CD",
    "gn:dem":398,
    "gn:feature_class":"P",
    "gn:feature_code":"PPL",
    "gn:name":"Kwanza",
    "gn:population":0,
    "gn:timezone":"Africa/Kinshasa",
    "iso:country":"CD",
    "wof:name":"Kwanza",
    "wof:placetype":"locality"
},
  "geometry": {"coordinates":[22.35054,2.46978],"type":"Point"}
}