{
  "type": "Feature",
  "properties": {
    "gn:admin1_code":"18.0",
    "gn:asciiname":"Kaluendi",
    "gn:country_code":"CD",
    "gn:dem":644,
    "gn:feature_class":"P",
    "gn:feature_code":"PPL",
    "gn:name":"Kaluendi",
    "gn:population":0,
    "gn:timezone":"Africa/Lubumbashi",
    "iso:country":"CD",
    "wof:name":"Kaluendi",
    "wof:placetype":"locality"
},
  "geometry": {"coordinates":[21.55758,-5.55069],"type":"Point"}
}