{
  "type": "Feature",
  "properties": {
    "gn:admin1_code":"29.0",
    "gn:asciiname":"Mulula",
    "gn:country_code":"CD",
    "gn:dem":796,
    "gn:feature_class":"P",
    "gn:feature_code":"PPL",
    "gn:name":"Mulula",
    "gn:population":0,
    "gn:timezone":"Africa/Lubumbashi",
    "iso:country":"CD",
    "wof:name":"Mulula",
    "wof:placetype":"locality"
},
  "geometry": {"coordinates":[29.22312,-5.88282],"type":"Point"}
}