{
  "type": "Feature",
  "properties": {
    "gn:admin1_code":"22.0",
    "gn:asciiname":"Satshikunga",
    "gn:country_code":"CD",
    "gn:dem":1099,
    "gn:feature_class":"P",
    "gn:feature_code":"PPL",
    "gn:name":"Satshikunga",
    "gn:population":0,
    "gn:timezone":"Africa/Lubumbashi",
    "iso:country":"CD",
    "wof:name":"Satshikunga",
    "wof:placetype":"locality"
},
  "geometry": {"coordinates":[22.69737000000001,-10.59245],"type":"Point"}
}