{
  "type": "Feature",
  "properties": {
    "gn:admin1_code":"30.0",
    "gn:asciiname":"Kondolole",
    "gn:country_code":"CD",
    "gn:dem":447,
    "gn:feature_class":"P",
    "gn:feature_code":"PPL",
    "gn:name":"Kondolole",
    "gn:population":0,
    "gn:timezone":"Africa/Lubumbashi",
    "iso:country":"CD",
    "name:und_x_variant":[
        "Kandololo",
        "Kondolole"
    ],
    "wof:name":"Kondolole",
    "wof:placetype":"locality"
},
  "geometry": {"coordinates":[25.93155,1.33698],"type":"Point"}
}