{
  "type": "Feature",
  "properties": {
    "gn:admin1_code":"29.0",
    "gn:asciiname":"Katelwa",
    "gn:country_code":"CD",
    "gn:dem":558,
    "gn:feature_class":"P",
    "gn:feature_code":"PPL",
    "gn:name":"Katelwa",
    "gn:population":0,
    "gn:timezone":"Africa/Lubumbashi",
    "iso:country":"CD",
    "wof:name":"Katelwa",
    "wof:placetype":"locality"
},
  "geometry": {"coordinates":[26.9294,-6.13615],"type":"Point"}
}