{
  "type": "Feature",
  "properties": {
    "gn:admin1_code":"26.0",
    "gn:asciiname":"Mondunga",
    "gn:country_code":"CD",
    "gn:dem":457,
    "gn:feature_class":"P",
    "gn:feature_code":"PPL",
    "gn:name":"Mondunga",
    "gn:population":0,
    "gn:timezone":"Africa/Kinshasa",
    "iso:country":"CD",
    "wof:name":"Mondunga",
    "wof:placetype":"locality"
},
  "geometry": {"coordinates":[22.27448,3.18073],"type":"Point"}
}