{
  "type": "Feature",
  "properties": {
    "gn:admin1_code":"25.0",
    "gn:asciiname":"Yamongili",
    "gn:country_code":"CD",
    "gn:dem":441,
    "gn:feature_class":"P",
    "gn:feature_code":"PPL",
    "gn:name":"Yamongili",
    "gn:population":0,
    "gn:timezone":"Africa/Kinshasa",
    "iso:country":"CD",
    "wof:name":"Yamongili",
    "wof:placetype":"locality"
},
  "geometry": {"coordinates":[22.6428,2.40153],"type":"Point"}
}