{
  "type": "Feature",
  "properties": {
    "gn:admin1_code":"31.0",
    "gn:asciiname":"Mompanga",
    "gn:country_code":"CD",
    "gn:dem":343,
    "gn:feature_class":"P",
    "gn:feature_code":"PPL",
    "gn:name":"Mompanga",
    "gn:population":0,
    "gn:timezone":"Africa/Kinshasa",
    "iso:country":"CD",
    "name:und_x_variant":[
        "Montanga",
        "Mompanga"
    ],
    "wof:name":"Mompanga",
    "wof:placetype":"locality"
},
  "geometry": {"coordinates":[20.473,0.91087],"type":"Point"}
}