{
  "type": "Feature",
  "properties": {
    "gn:admin1_code":"19.0",
    "gn:asciiname":"Muniania",
    "gn:country_code":"CD",
    "gn:dem":697,
    "gn:feature_class":"P",
    "gn:feature_code":"PPL",
    "gn:name":"Muniania",
    "gn:population":0,
    "gn:timezone":"Africa/Kinshasa",
    "iso:country":"CD",
    "name:und_x_variant":[
        "Muninia",
        "Muniania"
    ],
    "wof:name":"Muniania",
    "wof:placetype":"locality"
},
  "geometry": {"coordinates":[17.38795,-5.13358],"type":"Point"}
}