{
  "type": "Feature",
  "properties": {
    "gn:admin1_code":"22.0",
    "gn:asciiname":"Waidonga",
    "gn:country_code":"CD",
    "gn:dem":997,
    "gn:feature_class":"P",
    "gn:feature_code":"PPL",
    "gn:name":"Waidonga",
    "gn:population":0,
    "gn:timezone":"Africa/Lubumbashi",
    "iso:country":"CD",
    "wof:name":"Waidonga",
    "wof:placetype":"locality"
},
  "geometry": {"coordinates":[24.47444,-10.14672],"type":"Point"}
}