{
  "type": "Feature",
  "properties": {
    "gn:admin1_code":"31.0",
    "gn:asciiname":"Mompona",
    "gn:country_code":"CD",
    "gn:dem":383,
    "gn:feature_class":"P",
    "gn:feature_code":"PPL",
    "gn:name":"Mompona",
    "gn:population":0,
    "gn:timezone":"Africa/Kinshasa",
    "iso:country":"CD",
    "wof:name":"Mompona",
    "wof:placetype":"locality"
},
  "geometry": {"coordinates":[20.28683,-1.55643],"type":"Point"}
}