{
  "type": "Feature",
  "properties": {
    "gn:admin1_code":"24.0",
    "gn:asciiname":"Pekesu",
    "gn:country_code":"CD",
    "gn:dem":363,
    "gn:feature_class":"P",
    "gn:feature_code":"PPL",
    "gn:name":"Pekesu",
    "gn:population":0,
    "gn:timezone":"Africa/Kinshasa",
    "iso:country":"CD",
    "wof:name":"Pekesu",
    "wof:placetype":"locality"
},
  "geometry": {"coordinates":[20.17432,-2.32108],"type":"Point"}
}