{
  "type": "Feature",
  "properties": {
    "gn:admin1_code":"19.0",
    "gn:asciiname":"Mwana-Mutombo",
    "gn:country_code":"CD",
    "gn:dem":973,
    "gn:feature_class":"P",
    "gn:feature_code":"PPL",
    "gn:name":"Mwana-Mutombo",
    "gn:population":0,
    "gn:timezone":"Africa/Kinshasa",
    "iso:country":"CD",
    "wof:name":"Mwana-Mutombo",
    "wof:placetype":"locality"
},
  "geometry": {"coordinates":[17.63756,-6.76481],"type":"Point"}
}