{
  "type": "Feature",
  "properties": {
    "gn:admin1_code":"20.0",
    "gn:asciiname":"Mazinga",
    "gn:country_code":"CD",
    "gn:dem":688,
    "gn:feature_class":"P",
    "gn:feature_code":"PPL",
    "gn:name":"Mazinga",
    "gn:population":0,
    "gn:timezone":"Africa/Kinshasa",
    "iso:country":"CD",
    "wof:name":"Mazinga",
    "wof:placetype":"locality"
},
  "geometry": {"coordinates":[19.21418,-4.88841],"type":"Point"}
}