{
  "type": "Feature",
  "properties": {
    "gn:admin1_code":"14.0",
    "gn:asciiname":"Kibara",
    "gn:country_code":"CD",
    "gn:dem":1603,
    "gn:feature_class":"P",
    "gn:feature_code":"PPL",
    "gn:name":"Kibara",
    "gn:population":0,
    "gn:timezone":"Africa/Lubumbashi",
    "iso:country":"CD",
    "name:ceb_x_preferred":[
        "Kibara"
    ],
    "name:swe_x_preferred":[
        "Kibara"
    ],
    "wof:name":"Kibara",
    "wof:placetype":"locality"
},
  "geometry": {"coordinates":[27.34478,-8.64441],"type":"Point"}
}