{
  "type": "Feature",
  "properties": {
    "gn:admin1_code":"11.0",
    "gn:asciiname":"Katuhunda",
    "gn:country_code":"CD",
    "gn:dem":1422,
    "gn:feature_class":"P",
    "gn:feature_code":"PPL",
    "gn:name":"Katuhunda",
    "gn:population":0,
    "gn:timezone":"Africa/Lubumbashi",
    "iso:country":"CD",
    "wof:name":"Katuhunda",
    "wof:placetype":"locality"
},
  "geometry": {"coordinates":[28.73333,-1.71667],"type":"Point"}
}