{
  "type": "Feature",
  "properties": {
    "gn:admin1_code":"21.0",
    "gn:asciiname":"Kilembwe",
    "gn:country_code":"CD",
    "gn:dem":665,
    "gn:feature_class":"P",
    "gn:feature_code":"PPL",
    "gn:name":"Kilembwe",
    "gn:population":0,
    "gn:timezone":"Africa/Lubumbashi",
    "iso:country":"CD",
    "wof:name":"Kilembwe",
    "wof:placetype":"locality"
},
  "geometry": {"coordinates":[26.08599,-5.55584],"type":"Point"}
}