{
  "type": "Feature",
  "properties": {
    "gn:admin1_code":"8.0",
    "gn:asciiname":"Kula",
    "gn:country_code":"CD",
    "gn:dem":332,
    "gn:feature_class":"P",
    "gn:feature_code":"PPL",
    "gn:name":"Kula",
    "gn:population":0,
    "gn:timezone":"Africa/Kinshasa",
    "iso:country":"CD",
    "name:ara_x_preferred":[
        "\u0643\u0648\u0644\u0627"
    ],
    "name:azb_x_preferred":[
        "\u06a9\u0648\u0644\u0627"
    ],
    "name:bos_x_preferred":[
        "Kula"
    ],
    "name:bul_x_preferred":[
        "\u041a\u0443\u043b\u0430"
    ],
    "name:ceb_x_preferred":[
        "Kula"
    ],
    "name:ces_x_preferred":[
        "Kula"
    ],
    "name:deu_x_preferred":[
        "Kula"
    ],
    "name:est_x_preferred":[
        "Kula"
    ],
    "name:fra_x_preferred":[
        "Kula"
    ],
    "name:hrv_x_preferred":[
        "Kula"
    ],
    "name:ita_x_preferred":[
        "Kula"
    ],
    "name:kaz_x_preferred":[
        "\u041a\u0443\u043b\u0430"
    ],
    "name:lit_x_preferred":[
        "Kula"
    ],
    "name:nld_x_preferred":[
        "Kula"
    ],
    "name:pol_x_preferred":[
        "Kula"
    ],
    "name:por_x_preferred":[
        "Kula"
    ],
    "name:ron_x_preferred":[
        "Kula"
    ],
    "name:rus_x_preferred":[
        "\u041a\u0443\u043b\u0430"
    ],
    "name:slk_x_preferred":[
        "Kula"
    ],
    "name:slv_x_preferred":[
        "Kula"
    ],
    "name:spa_x_preferred":[
        "Kula"
    ],
    "name:srp_x_preferred":[
        "\u041a\u0443\u043b\u0430"
    ],
    "name:swe_x_preferred":[
        "Kula"
    ],
    "name:tur_x_preferred":[
        "Kula"
    ],
    "wof:name":"Kula",
    "wof:placetype":"locality"
},
  "geometry": {"coordinates":[14.23585,-5.63585],"type":"Point"}
}