{
  "type": "Feature",
  "properties": {
    "gn:admin1_code":"31.0",
    "gn:asciiname":"Motema-Nongo",
    "gn:country_code":"CD",
    "gn:dem":408,
    "gn:feature_class":"P",
    "gn:feature_code":"PPL",
    "gn:name":"Motema-Nongo",
    "gn:population":0,
    "gn:timezone":"Africa/Kinshasa",
    "iso:country":"CD",
    "wof:name":"Motema-Nongo",
    "wof:placetype":"locality"
},
  "geometry": {"coordinates":[23.32277,-0.84859],"type":"Point"}
}