{
  "type": "Feature",
  "properties": {
    "gn:admin1_code":"15.0",
    "gn:asciiname":"Sungu-Mwana",
    "gn:country_code":"CD",
    "gn:dem":1105,
    "gn:feature_class":"P",
    "gn:feature_code":"PPL",
    "gn:name":"Sungu-Mwana",
    "gn:population":0,
    "gn:timezone":"Africa/Lubumbashi",
    "iso:country":"CD",
    "wof:name":"Sungu-Mwana",
    "wof:placetype":"locality"
},
  "geometry": {"coordinates":[25.37671,-8.5422],"type":"Point"}
}