{
  "type": "Feature",
  "properties": {
    "gn:admin1_code":"8.0",
    "gn:asciiname":"Wombo",
    "gn:country_code":"CD",
    "gn:dem":284,
    "gn:feature_class":"P",
    "gn:feature_code":"PPL",
    "gn:name":"Wombo",
    "gn:population":0,
    "gn:timezone":"Africa/Kinshasa",
    "iso:country":"CD",
    "wof:name":"Wombo",
    "wof:placetype":"locality"
},
  "geometry": {"coordinates":[13.93286,-4.98564],"type":"Point"}
}