{
  "type": "Feature",
  "properties": {
    "gn:admin1_code":"20.0",
    "gn:asciiname":"Etubi",
    "gn:country_code":"CD",
    "gn:dem":340,
    "gn:feature_class":"P",
    "gn:feature_code":"PPL",
    "gn:name":"Etubi",
    "gn:population":0,
    "gn:timezone":"Africa/Kinshasa",
    "iso:country":"CD",
    "wof:name":"Etubi",
    "wof:placetype":"locality"
},
  "geometry": {"coordinates":[18.69837,-3.64574],"type":"Point"}
}