{
  "type": "Feature",
  "properties": {
    "gn:admin1_code":"28.0",
    "gn:asciiname":"Bubwala Deuxieme",
    "gn:country_code":"CD",
    "gn:dem":528,
    "gn:feature_class":"P",
    "gn:feature_code":"PPL",
    "gn:name":"Bubwala Deuxi\u00e8me",
    "gn:population":0,
    "gn:timezone":"Africa/Kinshasa",
    "iso:country":"CD",
    "name:und_x_variant":[
        "Bubwala Deuxi\u00e8me",
        "Bubwala II"
    ],
    "wof:name":"Bubwala Deuxieme",
    "wof:placetype":"locality"
},
  "geometry": {"coordinates":[19.12746,4.70024],"type":"Point"}
}