{
  "type": "Feature",
  "properties": {
    "gn:admin1_code":"20.0",
    "gn:asciiname":"Bulukumbi",
    "gn:country_code":"CD",
    "gn:dem":425,
    "gn:feature_class":"P",
    "gn:feature_code":"PPL",
    "gn:name":"Bulukumbi",
    "gn:population":0,
    "gn:timezone":"Africa/Kinshasa",
    "iso:country":"CD",
    "name:und_x_variant":[
        "Bulukumbi I"
    ],
    "wof:name":"Bulukumbi",
    "wof:placetype":"locality"
},
  "geometry": {"coordinates":[17.49634,-4.19273],"type":"Point"}
}