{
  "type": "Feature",
  "properties": {
    "gn:admin1_code":"26.0",
    "gn:asciiname":"Boyakpolo",
    "gn:country_code":"CD",
    "gn:dem":439,
    "gn:feature_class":"P",
    "gn:feature_code":"PPL",
    "gn:name":"Boyakpolo",
    "gn:population":0,
    "gn:timezone":"Africa/Kinshasa",
    "iso:country":"CD",
    "wof:name":"Boyakpolo",
    "wof:placetype":"locality"
},
  "geometry": {"coordinates":[20.38333,3.81667],"type":"Point"}
}