{
  "type": "Feature",
  "properties": {
    "gn:admin1_code":"18.0",
    "gn:asciiname":"Shamutama",
    "gn:country_code":"CD",
    "gn:dem":624,
    "gn:feature_class":"P",
    "gn:feature_code":"PPL",
    "gn:name":"Shamutama",
    "gn:population":0,
    "gn:timezone":"Africa/Lubumbashi",
    "iso:country":"CD",
    "wof:name":"Shamutama",
    "wof:placetype":"locality"
},
  "geometry": {"coordinates":[20.9266,-6.96678],"type":"Point"}
}