{
  "type": "Feature",
  "properties": {
    "gn:admin1_code":"13.0",
    "gn:asciiname":"Dimbia",
    "gn:country_code":"CD",
    "gn:dem":706,
    "gn:feature_class":"P",
    "gn:feature_code":"PPL",
    "gn:name":"Dimbia",
    "gn:population":0,
    "gn:timezone":"Africa/Lubumbashi",
    "iso:country":"CD",
    "wof:name":"Dimbia",
    "wof:placetype":"locality"
},
  "geometry": {"coordinates":[27.46886,2.9446],"type":"Point"}
}