{
  "type": "Feature",
  "properties": {
    "gn:admin1_code":"2.0",
    "gn:asciiname":"Moheli",
    "gn:country_code":"CD",
    "gn:dem":316,
    "gn:feature_class":"P",
    "gn:feature_code":"PPL",
    "gn:name":"Moheli",
    "gn:population":0,
    "gn:timezone":"Africa/Kinshasa",
    "iso:country":"CD",
    "wof:name":"Moheli",
    "wof:placetype":"locality"
},
  "geometry": {"coordinates":[18.23005,-0.78716],"type":"Point"}
}