{
  "type": "Feature",
  "properties": {
    "gn:admin1_code":"19.0",
    "gn:asciiname":"Gongo",
    "gn:country_code":"CD",
    "gn:dem":345,
    "gn:feature_class":"P",
    "gn:feature_code":"PPL",
    "gn:name":"Gongo",
    "gn:population":0,
    "gn:timezone":"Africa/Kinshasa",
    "iso:country":"CD",
    "name:und_x_variant":[
        "Ngongo",
        "Gonga",
        "Gongo"
    ],
    "wof:name":"Gongo",
    "wof:placetype":"locality"
},
  "geometry": {"coordinates":[17.6993,-4.39949],"type":"Point"}
}