{
  "type": "Feature",
  "properties": {
    "gn:admin1_code":"19.0",
    "gn:asciiname":"Mutetama",
    "gn:country_code":"CD",
    "gn:dem":1101,
    "gn:feature_class":"P",
    "gn:feature_code":"PPL",
    "gn:name":"Mutetama",
    "gn:population":0,
    "gn:timezone":"Africa/Kinshasa",
    "iso:country":"CD",
    "wof:name":"Mutetama",
    "wof:placetype":"locality"
},
  "geometry": {"coordinates":[18.6366,-7.84889],"type":"Point"}
}