{
  "type": "Feature",
  "properties": {
    "gn:admin1_code":"22.0",
    "gn:asciiname":"Kataie",
    "gn:country_code":"CD",
    "gn:dem":949,
    "gn:feature_class":"P",
    "gn:feature_code":"PPL",
    "gn:name":"Kataie",
    "gn:population":0,
    "gn:timezone":"Africa/Lubumbashi",
    "iso:country":"CD",
    "name:und_x_variant":[
        "Katai"
    ],
    "wof:name":"Kataie",
    "wof:placetype":"locality"
},
  "geometry": {"coordinates":[22.79722000000001,-9.4636],"type":"Point"}
}