{
  "type": "Feature",
  "properties": {
    "gn:admin1_code":"21.0",
    "gn:asciiname":"Mukoko",
    "gn:country_code":"CD",
    "gn:dem":900,
    "gn:feature_class":"P",
    "gn:feature_code":"PPL",
    "gn:name":"Mukoko",
    "gn:population":0,
    "gn:timezone":"Africa/Lubumbashi",
    "iso:country":"CD",
    "wof:name":"Mukoko",
    "wof:placetype":"locality"
},
  "geometry": {"coordinates":[24.50092,-6.20471],"type":"Point"}
}