{
  "type": "Feature",
  "properties": {
    "gn:admin1_code":"22.0",
    "gn:asciiname":"Kandjangu",
    "gn:country_code":"CD",
    "gn:dem":905,
    "gn:feature_class":"P",
    "gn:feature_code":"PPL",
    "gn:name":"Kandjangu",
    "gn:population":0,
    "gn:timezone":"Africa/Lubumbashi",
    "iso:country":"CD",
    "wof:name":"Kandjangu",
    "wof:placetype":"locality"
},
  "geometry": {"coordinates":[22.87277000000001,-9.71905],"type":"Point"}
}