{
  "type": "Feature",
  "properties": {
    "gn:admin1_code":"20.0",
    "gn:asciiname":"Bonga-Masoko",
    "gn:country_code":"CD",
    "gn:dem":490,
    "gn:feature_class":"P",
    "gn:feature_code":"PPL",
    "gn:name":"Bonga-Masoko",
    "gn:population":0,
    "gn:timezone":"Africa/Kinshasa",
    "iso:country":"CD",
    "wof:name":"Bonga-Masoko",
    "wof:placetype":"locality"
},
  "geometry": {"coordinates":[18.62506,-4.71949],"type":"Point"}
}