{
  "type": "Feature",
  "properties": {
    "gn:admin1_code":"13.0",
    "gn:asciiname":"Votoko",
    "gn:country_code":"CD",
    "gn:dem":516,
    "gn:feature_class":"P",
    "gn:feature_code":"PPL",
    "gn:name":"Votoko",
    "gn:population":0,
    "gn:timezone":"Africa/Lubumbashi",
    "iso:country":"CD",
    "wof:name":"Votoko",
    "wof:placetype":"locality"
},
  "geometry": {"coordinates":[23.75225,4.45848],"type":"Point"}
}