{
  "type": "Feature",
  "properties": {
    "gn:admin1_code":"8.0",
    "gn:asciiname":"Temo",
    "gn:country_code":"CD",
    "gn:dem":448,
    "gn:feature_class":"P",
    "gn:feature_code":"PPL",
    "gn:name":"Temo",
    "gn:population":0,
    "gn:timezone":"Africa/Kinshasa",
    "iso:country":"CD",
    "wof:name":"Temo",
    "wof:placetype":"locality"
},
  "geometry": {"coordinates":[14.53989,-5.83676],"type":"Point"}
}