{
  "type": "Feature",
  "properties": {
    "gn:admin1_code":"31.0",
    "gn:asciiname":"Bolondo",
    "gn:country_code":"CD",
    "gn:dem":370,
    "gn:feature_class":"P",
    "gn:feature_code":"PPL",
    "gn:name":"Bolondo",
    "gn:population":0,
    "gn:timezone":"Africa/Kinshasa",
    "iso:country":"CD",
    "name:cat_x_preferred":[
        "Bolondo"
    ],
    "name:ita_x_preferred":[
        "Bolondo"
    ],
    "name:nld_x_preferred":[
        "Bolondo"
    ],
    "name:spa_x_preferred":[
        "Bolondo"
    ],
    "name:und_x_variant":[
        "Bolando"
    ],
    "wof:name":"Bolondo",
    "wof:placetype":"locality"
},
  "geometry": {"coordinates":[21.35001,-0.40393],"type":"Point"}
}