{
  "type": "Feature",
  "properties": {
    "gn:admin1_code":"11.0",
    "gn:asciiname":"Mbuhi",
    "gn:country_code":"CD",
    "gn:dem":990,
    "gn:feature_class":"P",
    "gn:feature_code":"PPL",
    "gn:name":"Mbuhi",
    "gn:population":0,
    "gn:timezone":"Africa/Lubumbashi",
    "iso:country":"CD",
    "wof:name":"Mbuhi",
    "wof:placetype":"locality"
},
  "geometry": {"coordinates":[28.68395,-0.90689],"type":"Point"}
}