{
  "type": "Feature",
  "properties": {
    "gn:admin1_code":"17.0",
    "gn:asciiname":"Labo",
    "gn:country_code":"CD",
    "gn:dem":1263,
    "gn:feature_class":"P",
    "gn:feature_code":"PPL",
    "gn:name":"Labo",
    "gn:population":0,
    "gn:timezone":"Africa/Lubumbashi",
    "iso:country":"CD",
    "name:ceb_x_preferred":[
        "Labo"
    ],
    "name:deu_x_preferred":[
        "Labo"
    ],
    "name:fra_x_preferred":[
        "Labo"
    ],
    "name:nld_x_preferred":[
        "Labo"
    ],
    "name:swe_x_preferred":[
        "Labo"
    ],
    "wof:name":"Labo",
    "wof:placetype":"locality"
},
  "geometry": {"coordinates":[30.68673,3.19128],"type":"Point"}
}