{
  "type": "Feature",
  "properties": {
    "gn:admin1_code":"24.0",
    "gn:asciiname":"Bokangamoi",
    "gn:country_code":"CD",
    "gn:dem":337,
    "gn:feature_class":"P",
    "gn:feature_code":"PPL",
    "gn:name":"Bokangamoi",
    "gn:population":0,
    "gn:timezone":"Africa/Kinshasa",
    "iso:country":"CD",
    "name:und_x_variant":[
        "Bokangamoy",
        "Bokangamoi"
    ],
    "wof:name":"Bokangamoi",
    "wof:placetype":"locality"
},
  "geometry": {"coordinates":[16.3848,-2.08507],"type":"Point"}
}