{
  "type": "Feature",
  "properties": {
    "gn:admin1_code":"22.0",
    "gn:asciiname":"Ndolo",
    "gn:country_code":"CD",
    "gn:dem":897,
    "gn:feature_class":"P",
    "gn:feature_code":"PPL",
    "gn:name":"Ndolo",
    "gn:population":0,
    "gn:timezone":"Africa/Lubumbashi",
    "iso:country":"CD",
    "name:ceb_x_preferred":[
        "Ndolo"
    ],
    "name:deu_x_preferred":[
        "Ndolo"
    ],
    "name:fra_x_preferred":[
        "Ndolo"
    ],
    "name:swe_x_preferred":[
        "Ndolo"
    ],
    "wof:name":"Ndolo",
    "wof:placetype":"locality"
},
  "geometry": {"coordinates":[23.08333,-9.91667],"type":"Point"}
}