{
  "type": "Feature",
  "properties": {
    "gn:admin1_code":"15.0",
    "gn:asciiname":"Koto",
    "gn:country_code":"CD",
    "gn:dem":675,
    "gn:feature_class":"P",
    "gn:feature_code":"PPL",
    "gn:name":"Koto",
    "gn:population":0,
    "gn:timezone":"Africa/Lubumbashi",
    "iso:country":"CD",
    "wof:name":"Koto",
    "wof:placetype":"locality"
},
  "geometry": {"coordinates":[25.86667000000001,-8.15],"type":"Point"}
}