{
  "type": "Feature",
  "properties": {
    "gn:admin1_code":"15.0",
    "gn:asciiname":"Koto",
    "gn:country_code":"CD",
    "gn:dem":675,
    "gn:feature_class":"P",
    "gn:feature_code":"PPL",
    "gn:name":"Koto",
    "gn:population":0,
    "gn:timezone":"Africa/Lubumbashi",
    "iso:country":"CD",
    "name:ara_x_preferred":[
        "\u0643\u0648\u062a\u0648"
    ],
    "name:bos_x_preferred":[
        "Koto"
    ],
    "name:ceb_x_preferred":[
        "Koto"
    ],
    "name:deu_x_preferred":[
        "Koto"
    ],
    "name:epo_x_preferred":[
        "Koto"
    ],
    "name:fin_x_preferred":[
        "Koto"
    ],
    "name:fra_x_preferred":[
        "Koto"
    ],
    "name:heb_x_preferred":[
        "\u05e7\u05d5\u05d8\u05d5"
    ],
    "name:ita_x_preferred":[
        "Koto"
    ],
    "name:nld_x_preferred":[
        "Koto"
    ],
    "name:nor_x_preferred":[
        "Koto"
    ],
    "name:ron_x_preferred":[
        "Koto"
    ],
    "name:spa_x_preferred":[
        "Koto"
    ],
    "name:swe_x_preferred":[
        "Koto"
    ],
    "wof:name":"Koto",
    "wof:placetype":"locality"
},
  "geometry": {"coordinates":[25.86667000000001,-8.15],"type":"Point"}
}