{
  "type": "Feature",
  "properties": {
    "gn:admin1_code":"10.0",
    "gn:asciiname":"Maiti",
    "gn:country_code":"CD",
    "gn:dem":647,
    "gn:feature_class":"P",
    "gn:feature_code":"PPL",
    "gn:name":"Maiti",
    "gn:population":0,
    "gn:timezone":"Africa/Lubumbashi",
    "iso:country":"CD",
    "wof:name":"Maiti",
    "wof:placetype":"locality"
},
  "geometry": {"coordinates":[26.66453,-4.45983],"type":"Point"}
}