{
  "type": "Feature",
  "properties": {
    "gn:admin1_code":"20.0",
    "gn:asciiname":"Mwela-Kwati",
    "gn:country_code":"CD",
    "gn:dem":701,
    "gn:feature_class":"P",
    "gn:feature_code":"PPL",
    "gn:name":"Mwela-Kwati",
    "gn:population":0,
    "gn:timezone":"Africa/Kinshasa",
    "iso:country":"CD",
    "wof:name":"Mwela-Kwati",
    "wof:placetype":"locality"
},
  "geometry": {"coordinates":[17.57034,-5.59174],"type":"Point"}
}