{
  "type": "Feature",
  "properties": {
    "gn:admin1_code":"29.0",
    "gn:asciiname":"Shiele",
    "gn:country_code":"CD",
    "gn:dem":555,
    "gn:feature_class":"P",
    "gn:feature_code":"PPL",
    "gn:name":"Shiele",
    "gn:population":0,
    "gn:timezone":"Africa/Lubumbashi",
    "iso:country":"CD",
    "name:und_x_variant":[
        "Shiole",
        "Shiele"
    ],
    "wof:name":"Shiele",
    "wof:placetype":"locality"
},
  "geometry": {"coordinates":[26.96667,-6.41667],"type":"Point"}
}