{
  "type": "Feature",
  "properties": {
    "gn:admin1_code":"4.0",
    "gn:asciiname":"Buyamba",
    "gn:country_code":"CD",
    "gn:dem":636,
    "gn:feature_class":"P",
    "gn:feature_code":"PPL",
    "gn:name":"Buyamba",
    "gn:population":0,
    "gn:timezone":"Africa/Lubumbashi",
    "iso:country":"CD",
    "wof:name":"Buyamba",
    "wof:placetype":"locality"
},
  "geometry": {"coordinates":[23.17353,-6.12417],"type":"Point"}
}