{
  "type": "Feature",
  "properties": {
    "gn:admin1_code":"19.0",
    "gn:asciiname":"Kibunda",
    "gn:country_code":"CD",
    "gn:dem":963,
    "gn:feature_class":"P",
    "gn:feature_code":"PPL",
    "gn:name":"Kibunda",
    "gn:population":0,
    "gn:timezone":"Africa/Kinshasa",
    "iso:country":"CD",
    "wof:name":"Kibunda",
    "wof:placetype":"locality"
},
  "geometry": {"coordinates":[17.60909,-6.70296],"type":"Point"}
}