{
  "type": "Feature",
  "properties": {
    "gn:admin1_code":"20.0",
    "gn:asciiname":"Metuna",
    "gn:country_code":"CD",
    "gn:dem":348,
    "gn:feature_class":"P",
    "gn:feature_code":"PPL",
    "gn:name":"Metuna",
    "gn:population":0,
    "gn:timezone":"Africa/Kinshasa",
    "iso:country":"CD",
    "wof:name":"Metuna",
    "wof:placetype":"locality"
},
  "geometry": {"coordinates":[18.20027,-4.02594],"type":"Point"}
}