{
  "type": "Feature",
  "properties": {
    "gn:admin1_code":"15.0",
    "gn:asciiname":"Kakisa",
    "gn:country_code":"CD",
    "gn:dem":1020,
    "gn:feature_class":"P",
    "gn:feature_code":"PPL",
    "gn:name":"Kakisa",
    "gn:population":0,
    "gn:timezone":"Africa/Lubumbashi",
    "iso:country":"CD",
    "name:deu_x_preferred":[
        "Kakisa"
    ],
    "name:fas_x_preferred":[
        "\u06a9\u0627\u06a9\u06cc\u0633\u0627"
    ],
    "name:fra_x_preferred":[
        "Kakisa"
    ],
    "name:por_x_preferred":[
        "Kakisa"
    ],
    "wof:name":"Kakisa",
    "wof:placetype":"locality"
},
  "geometry": {"coordinates":[24.9771,-10.10157],"type":"Point"}
}