{
  "type": "Feature",
  "properties": {
    "gn:admin1_code":"29.0",
    "gn:asciiname":"Muzinga",
    "gn:country_code":"CD",
    "gn:dem":743,
    "gn:feature_class":"P",
    "gn:feature_code":"PPL",
    "gn:name":"Muzinga",
    "gn:population":0,
    "gn:timezone":"Africa/Lubumbashi",
    "iso:country":"CD",
    "wof:name":"Muzinga",
    "wof:placetype":"locality"
},
  "geometry": {"coordinates":[26.76205,-7.16407],"type":"Point"}
}