{
  "type": "Feature",
  "properties": {
    "gn:admin1_code":"22.0",
    "gn:asciiname":"Kalamba-Kamule",
    "gn:country_code":"CD",
    "gn:dem":1029,
    "gn:feature_class":"P",
    "gn:feature_code":"PPL",
    "gn:name":"Kalamba-Kamule",
    "gn:population":0,
    "gn:timezone":"Africa/Lubumbashi",
    "iso:country":"CD",
    "wof:name":"Kalamba-Kamule",
    "wof:placetype":"locality"
},
  "geometry": {"coordinates":[23.36791,-7.99758],"type":"Point"}
}