{
  "type": "Feature",
  "properties": {
    "gn:admin1_code":"8.0",
    "gn:asciiname":"Mputi",
    "gn:country_code":"CD",
    "gn:dem":606,
    "gn:feature_class":"P",
    "gn:feature_code":"PPL",
    "gn:name":"Mputi",
    "gn:population":0,
    "gn:timezone":"Africa/Kinshasa",
    "iso:country":"CD",
    "wof:name":"Mputi",
    "wof:placetype":"locality"
},
  "geometry": {"coordinates":[15.48198,-5.18895],"type":"Point"}
}