{
  "type": "Feature",
  "properties": {
    "gn:admin1_code":"13.0",
    "gn:asciiname":"Dada",
    "gn:country_code":"CD",
    "gn:dem":643,
    "gn:feature_class":"P",
    "gn:feature_code":"PPL",
    "gn:name":"Dada",
    "gn:population":0,
    "gn:timezone":"Africa/Lubumbashi",
    "iso:country":"CD",
    "wof:name":"Dada",
    "wof:placetype":"locality"
},
  "geometry": {"coordinates":[26.96787,4.41046],"type":"Point"}
}