{
  "type": "Feature",
  "properties": {
    "gn:admin1_code":"18.0",
    "gn:asciiname":"Milengele-Ngeshi",
    "gn:country_code":"CD",
    "gn:dem":638,
    "gn:feature_class":"P",
    "gn:feature_code":"PPL",
    "gn:name":"Milengele-Ngeshi",
    "gn:population":0,
    "gn:timezone":"Africa/Lubumbashi",
    "iso:country":"CD",
    "wof:name":"Milengele-Ngeshi",
    "wof:placetype":"locality"
},
  "geometry": {"coordinates":[20.53475,-4.77803],"type":"Point"}
}