{
  "type": "Feature",
  "properties": {
    "gn:admin1_code":"12.0",
    "gn:asciiname":"Nyamikuba",
    "gn:country_code":"CD",
    "gn:dem":587,
    "gn:feature_class":"P",
    "gn:feature_code":"PPL",
    "gn:name":"Nyamikuba",
    "gn:population":0,
    "gn:timezone":"Africa/Lubumbashi",
    "iso:country":"CD",
    "wof:name":"Nyamikuba",
    "wof:placetype":"locality"
},
  "geometry": {"coordinates":[27.29021,-2.69594],"type":"Point"}
}