{
  "type": "Feature",
  "properties": {
    "gn:admin1_code":"12.0",
    "gn:asciiname":"Penekusu",
    "gn:country_code":"CD",
    "gn:dem":588,
    "gn:feature_class":"P",
    "gn:feature_code":"PPL",
    "gn:name":"Penekusu",
    "gn:population":0,
    "gn:timezone":"Africa/Lubumbashi",
    "iso:country":"CD",
    "wof:name":"Penekusu",
    "wof:placetype":"locality"
},
  "geometry": {"coordinates":[27.18929,-3.46222],"type":"Point"}
}