{
  "type": "Feature",
  "properties": {
    "gn:admin1_code":"22.0",
    "gn:asciiname":"Ngwali",
    "gn:country_code":"CD",
    "gn:dem":1096,
    "gn:feature_class":"P",
    "gn:feature_code":"PPL",
    "gn:name":"Ngwali",
    "gn:population":0,
    "gn:timezone":"Africa/Lubumbashi",
    "iso:country":"CD",
    "wof:name":"Ngwali",
    "wof:placetype":"locality"
},
  "geometry": {"coordinates":[23.45306,-10.37234],"type":"Point"}
}