{
  "type": "Feature",
  "properties": {
    "gn:admin1_code":"23.0",
    "gn:asciiname":"Mubongo",
    "gn:country_code":"CD",
    "gn:dem":873,
    "gn:feature_class":"P",
    "gn:feature_code":"PPL",
    "gn:name":"Mubongo",
    "gn:population":0,
    "gn:timezone":"Africa/Lubumbashi",
    "iso:country":"CD",
    "wof:name":"Mubongo",
    "wof:placetype":"locality"
},
  "geometry": {"coordinates":[22.56667,-7.53333],"type":"Point"}
}