{
  "type": "Feature",
  "properties": {
    "gn:admin1_code":"20.0",
    "gn:asciiname":"Kibangu",
    "gn:country_code":"CD",
    "gn:dem":841,
    "gn:feature_class":"P",
    "gn:feature_code":"PPL",
    "gn:name":"Kibangu",
    "gn:population":0,
    "gn:timezone":"Africa/Kinshasa",
    "iso:country":"CD",
    "wof:name":"Kibangu",
    "wof:placetype":"locality"
},
  "geometry": {"coordinates":[17.76477000000001,-5.65081],"type":"Point"}
}