{
  "type": "Feature",
  "properties": {
    "gn:admin1_code":"28.0",
    "gn:asciiname":"Bodoromo",
    "gn:country_code":"CD",
    "gn:dem":416,
    "gn:feature_class":"P",
    "gn:feature_code":"PPL",
    "gn:name":"Bodoromo",
    "gn:population":0,
    "gn:timezone":"Africa/Kinshasa",
    "iso:country":"CD",
    "wof:name":"Bodoromo",
    "wof:placetype":"locality"
},
  "geometry": {"coordinates":[20.14727,3.19969],"type":"Point"}
}