{
  "type": "Feature",
  "properties": {
    "gn:admin1_code":"16.0",
    "gn:asciiname":"Siringi-Moku",
    "gn:country_code":"CD",
    "gn:dem":936,
    "gn:feature_class":"P",
    "gn:feature_code":"PPL",
    "gn:name":"Siringi-Moku",
    "gn:population":0,
    "gn:timezone":"Africa/Lubumbashi",
    "iso:country":"CD",
    "name:und_x_variant":[
        "Sirigi-Moke"
    ],
    "wof:name":"Siringi-Moku",
    "wof:placetype":"locality"
},
  "geometry": {"coordinates":[29.84104,2.95883],"type":"Point"}
}