{
  "type": "Feature",
  "properties": {
    "gn:admin1_code":"30.0",
    "gn:asciiname":"Bombakita",
    "gn:country_code":"CD",
    "gn:dem":511,
    "gn:feature_class":"P",
    "gn:feature_code":"PPL",
    "gn:name":"Bombakita",
    "gn:population":0,
    "gn:timezone":"Africa/Lubumbashi",
    "iso:country":"CD",
    "wof:name":"Bombakita",
    "wof:placetype":"locality"
},
  "geometry": {"coordinates":[26.04413,0.37552],"type":"Point"}
}