{
  "type": "Feature",
  "properties": {
    "gn:admin1_code":"12.0",
    "gn:asciiname":"Kitwabaluzi",
    "gn:country_code":"CD",
    "gn:dem":1128,
    "gn:feature_class":"P",
    "gn:feature_code":"PPL",
    "gn:name":"Kitwabaluzi",
    "gn:population":0,
    "gn:timezone":"Africa/Lubumbashi",
    "iso:country":"CD",
    "wof:name":"Kitwabaluzi",
    "wof:placetype":"locality"
},
  "geometry": {"coordinates":[28.58959,-2.89697],"type":"Point"}
}