{
  "type": "Feature",
  "properties": {
    "gn:admin1_code":"29.0",
    "gn:asciiname":"Lugunda",
    "gn:country_code":"CD",
    "gn:dem":963,
    "gn:feature_class":"P",
    "gn:feature_code":"PPL",
    "gn:name":"Lugunda",
    "gn:population":0,
    "gn:timezone":"Africa/Lubumbashi",
    "iso:country":"CD",
    "name:und_x_variant":[
        "Lugenda",
        "Lugunda"
    ],
    "wof:name":"Lugunda",
    "wof:placetype":"locality"
},
  "geometry": {"coordinates":[27.89941,-5.23535],"type":"Point"}
}