{
  "type": "Feature",
  "properties": {
    "gn:admin1_code":"7.0",
    "gn:asciiname":"Lweza",
    "gn:country_code":"CD",
    "gn:dem":1631,
    "gn:feature_class":"P",
    "gn:feature_code":"PPL",
    "gn:name":"Lweza",
    "gn:population":0,
    "gn:timezone":"Africa/Lubumbashi",
    "iso:country":"CD",
    "wof:name":"Lweza",
    "wof:placetype":"locality"
},
  "geometry": {"coordinates":[29.05723,-2.09731],"type":"Point"}
}