{
  "type": "Feature",
  "properties": {
    "gn:admin1_code":"22.0",
    "gn:asciiname":"Shiliopibe",
    "gn:country_code":"CD",
    "gn:dem":911,
    "gn:feature_class":"P",
    "gn:feature_code":"PPL",
    "gn:name":"Shiliopibe",
    "gn:population":0,
    "gn:timezone":"Africa/Lubumbashi",
    "iso:country":"CD",
    "wof:name":"Shiliopibe",
    "wof:placetype":"locality"
},
  "geometry": {"coordinates":[22.96984,-9.75375],"type":"Point"}
}