{
  "type": "Feature",
  "properties": {
    "gn:admin1_code":"19.0",
    "gn:asciiname":"Manzangi Premiere",
    "gn:country_code":"CD",
    "gn:dem":753,
    "gn:feature_class":"P",
    "gn:feature_code":"PPL",
    "gn:name":"Manzangi Premi\u00e8re",
    "gn:population":0,
    "gn:timezone":"Africa/Kinshasa",
    "iso:country":"CD",
    "wof:name":"Manzangi Premiere",
    "wof:placetype":"locality"
},
  "geometry": {"coordinates":[17.44234,-5.74864],"type":"Point"}
}