{
  "type": "Feature",
  "properties": {
    "gn:admin1_code":"22.0",
    "gn:asciiname":"Sakatoweji",
    "gn:country_code":"CD",
    "gn:dem":1012,
    "gn:feature_class":"P",
    "gn:feature_code":"PPL",
    "gn:name":"Sakatoweji",
    "gn:population":0,
    "gn:timezone":"Africa/Lubumbashi",
    "iso:country":"CD",
    "wof:name":"Sakatoweji",
    "wof:placetype":"locality"
},
  "geometry": {"coordinates":[22.38863,-8.29481],"type":"Point"}
}