{
  "type": "Feature",
  "properties": {
    "gn:admin1_code":"12.0",
    "gn:asciiname":"Kagulube",
    "gn:country_code":"CD",
    "gn:dem":614,
    "gn:feature_class":"P",
    "gn:feature_code":"PPL",
    "gn:name":"Kagulube",
    "gn:population":0,
    "gn:timezone":"Africa/Lubumbashi",
    "iso:country":"CD",
    "wof:name":"Kagulube",
    "wof:placetype":"locality"
},
  "geometry": {"coordinates":[27.39696,-3.64714],"type":"Point"}
}