{
  "type": "Feature",
  "properties": {
    "gn:admin1_code":"13.0",
    "gn:asciiname":"Sakiweli",
    "gn:country_code":"CD",
    "gn:dem":701,
    "gn:feature_class":"P",
    "gn:feature_code":"PPL",
    "gn:name":"Sakiweli",
    "gn:population":0,
    "gn:timezone":"Africa/Lubumbashi",
    "iso:country":"CD",
    "wof:name":"Sakiweli",
    "wof:placetype":"locality"
},
  "geometry": {"coordinates":[27.15723,4.20826],"type":"Point"}
}