{
  "type": "Feature",
  "properties": {
    "gn:admin1_code":"30.0",
    "gn:asciiname":"Yauta",
    "gn:country_code":"CD",
    "gn:dem":405,
    "gn:feature_class":"P",
    "gn:feature_code":"PPL",
    "gn:name":"Yauta",
    "gn:population":0,
    "gn:timezone":"Africa/Lubumbashi",
    "iso:country":"CD",
    "wof:name":"Yauta",
    "wof:placetype":"locality"
},
  "geometry": {"coordinates":[24.00112,-0.11563],"type":"Point"}
}