{
  "type": "Feature",
  "properties": {
    "gn:admin1_code":"18.0",
    "gn:asciiname":"Kalunga",
    "gn:country_code":"CD",
    "gn:dem":724,
    "gn:feature_class":"P",
    "gn:feature_code":"PPL",
    "gn:name":"Kalunga",
    "gn:population":0,
    "gn:timezone":"Africa/Lubumbashi",
    "iso:country":"CD",
    "wof:name":"Kalunga",
    "wof:placetype":"locality"
},
  "geometry": {"coordinates":[20.95296,-7.15271],"type":"Point"}
}