{
  "type": "Feature",
  "properties": {
    "gn:admin1_code":"22.0",
    "gn:asciiname":"Kamapela",
    "gn:country_code":"CD",
    "gn:dem":937,
    "gn:feature_class":"P",
    "gn:feature_code":"PPL",
    "gn:name":"Kamapela",
    "gn:population":0,
    "gn:timezone":"Africa/Lubumbashi",
    "iso:country":"CD",
    "wof:name":"Kamapela",
    "wof:placetype":"locality"
},
  "geometry": {"coordinates":[22.51626,-9.13453],"type":"Point"}
}