{
  "type": "Feature",
  "properties": {
    "gn:admin1_code":"17.0",
    "gn:asciiname":"Ubilo",
    "gn:country_code":"CD",
    "gn:dem":1165,
    "gn:feature_class":"P",
    "gn:feature_code":"PPL",
    "gn:name":"Ubilo",
    "gn:population":0,
    "gn:timezone":"Africa/Lubumbashi",
    "iso:country":"CD",
    "name:fra_x_preferred":[
        "Ubilo"
    ],
    "wof:name":"Ubilo",
    "wof:placetype":"locality"
},
  "geometry": {"coordinates":[29.66667,2.01667],"type":"Point"}
}