{
  "type": "Feature",
  "properties": {
    "gn:admin1_code":"11.0",
    "gn:asciiname":"Aloi",
    "gn:country_code":"CD",
    "gn:dem":917,
    "gn:feature_class":"P",
    "gn:feature_code":"PPL",
    "gn:name":"Aloi",
    "gn:population":0,
    "gn:timezone":"Africa/Lubumbashi",
    "iso:country":"CD",
    "name:lug_x_preferred":[
        "Aloi"
    ],
    "wof:name":"Aloi",
    "wof:placetype":"locality"
},
  "geometry": {"coordinates":[29.14182000000001,0.50934],"type":"Point"}
}