{
  "type": "Feature",
  "properties": {
    "gn:admin1_code":"18.0",
    "gn:asciiname":"Shamunanga",
    "gn:country_code":"CD",
    "gn:dem":667,
    "gn:feature_class":"P",
    "gn:feature_code":"PPL",
    "gn:name":"Shamunanga",
    "gn:population":0,
    "gn:timezone":"Africa/Lubumbashi",
    "iso:country":"CD",
    "wof:name":"Shamunanga",
    "wof:placetype":"locality"
},
  "geometry": {"coordinates":[20.54891,-5.03467],"type":"Point"}
}