{
  "type": "Feature",
  "properties": {
    "gn:admin1_code":"22.0",
    "gn:asciiname":"Mwepo Lusamba",
    "gn:country_code":"CD",
    "gn:dem":1160,
    "gn:feature_class":"P",
    "gn:feature_code":"PPL",
    "gn:name":"Mwepo Lusamba",
    "gn:population":0,
    "gn:timezone":"Africa/Lubumbashi",
    "iso:country":"CD",
    "wof:name":"Mwepo Lusamba",
    "wof:placetype":"locality"
},
  "geometry": {"coordinates":[26.25665,-9.98807],"type":"Point"}
}