{
  "type": "Feature",
  "properties": {
    "gn:admin1_code":"2.0",
    "gn:asciiname":"Botenge",
    "gn:country_code":"CD",
    "gn:dem":320,
    "gn:feature_class":"P",
    "gn:feature_code":"PPL",
    "gn:name":"Botenge",
    "gn:population":0,
    "gn:timezone":"Africa/Kinshasa",
    "iso:country":"CD",
    "name:und_x_variant":[
        "Botende",
        "Bolenge"
    ],
    "wof:name":"Botenge",
    "wof:placetype":"locality"
},
  "geometry": {"coordinates":[18.30324,-0.56166],"type":"Point"}
}