{
  "type": "Feature",
  "properties": {
    "gn:admin1_code":"23.0",
    "gn:asciiname":"Kabata",
    "gn:country_code":"CD",
    "gn:dem":844,
    "gn:feature_class":"P",
    "gn:feature_code":"PPL",
    "gn:name":"Kabata",
    "gn:population":0,
    "gn:timezone":"Africa/Lubumbashi",
    "iso:country":"CD",
    "wof:name":"Kabata",
    "wof:placetype":"locality"
},
  "geometry": {"coordinates":[22.22915,-6.88468],"type":"Point"}
}