{
  "type": "Feature",
  "properties": {
    "gn:admin1_code":"13.0",
    "gn:asciiname":"Baro",
    "gn:country_code":"CD",
    "gn:dem":677,
    "gn:feature_class":"P",
    "gn:feature_code":"PPL",
    "gn:name":"Baro",
    "gn:population":0,
    "gn:timezone":"Africa/Lubumbashi",
    "iso:country":"CD",
    "name:ceb_x_preferred":[
        "Baro"
    ],
    "name:deu_x_preferred":[
        "Baro"
    ],
    "name:epo_x_preferred":[
        "Baro"
    ],
    "name:fra_x_preferred":[
        "Baro"
    ],
    "name:hrv_x_preferred":[
        "Baro"
    ],
    "name:ita_x_preferred":[
        "Baro"
    ],
    "name:lat_x_preferred":[
        "Baro"
    ],
    "name:nld_x_preferred":[
        "Baro"
    ],
    "name:spa_x_preferred":[
        "Baro"
    ],
    "name:sun_x_preferred":[
        "Baro"
    ],
    "name:swe_x_preferred":[
        "Baro"
    ],
    "wof:name":"Baro",
    "wof:placetype":"locality"
},
  "geometry": {"coordinates":[27.05321,3.67525],"type":"Point"}
}