{
  "type": "Feature",
  "properties": {
    "gn:admin1_code":"2.0",
    "gn:asciiname":"Mandjindi",
    "gn:country_code":"CD",
    "gn:dem":338,
    "gn:feature_class":"P",
    "gn:feature_code":"PPL",
    "gn:name":"Mandjindi",
    "gn:population":0,
    "gn:timezone":"Africa/Kinshasa",
    "iso:country":"CD",
    "wof:name":"Mandjindi",
    "wof:placetype":"locality"
},
  "geometry": {"coordinates":[20.233,1.33352],"type":"Point"}
}