{
  "type": "Feature",
  "properties": {
    "gn:admin1_code":"15.0",
    "gn:asciiname":"Busansa",
    "gn:country_code":"CD",
    "gn:dem":918,
    "gn:feature_class":"P",
    "gn:feature_code":"PPL",
    "gn:name":"Busansa",
    "gn:population":0,
    "gn:timezone":"Africa/Lubumbashi",
    "iso:country":"CD",
    "wof:name":"Busansa",
    "wof:placetype":"locality"
},
  "geometry": {"coordinates":[25.6553,-8.86546],"type":"Point"}
}