{
  "type": "Feature",
  "properties": {
    "gn:admin1_code":"15.0",
    "gn:asciiname":"Kilimba",
    "gn:country_code":"CD",
    "gn:dem":756,
    "gn:feature_class":"P",
    "gn:feature_code":"PPL",
    "gn:name":"Kilimba",
    "gn:population":0,
    "gn:timezone":"Africa/Lubumbashi",
    "iso:country":"CD",
    "name:und_x_variant":[
        "Kidimba"
    ],
    "wof:name":"Kilimba",
    "wof:placetype":"locality"
},
  "geometry": {"coordinates":[25.13952,-9.34369],"type":"Point"}
}