{
  "type": "Feature",
  "properties": {
    "gn:admin1_code":"23.0",
    "gn:asciiname":"Tshibabi",
    "gn:country_code":"CD",
    "gn:dem":863,
    "gn:feature_class":"P",
    "gn:feature_code":"PPL",
    "gn:name":"Tshibabi",
    "gn:population":0,
    "gn:timezone":"Africa/Lubumbashi",
    "iso:country":"CD",
    "wof:name":"Tshibabi",
    "wof:placetype":"locality"
},
  "geometry": {"coordinates":[21.98435,-6.834],"type":"Point"}
}