{
  "type": "Feature",
  "properties": {
    "gn:admin1_code":"8.0",
    "gn:asciiname":"Mayambu",
    "gn:country_code":"CD",
    "gn:dem":611,
    "gn:feature_class":"P",
    "gn:feature_code":"PPL",
    "gn:name":"Mayambu",
    "gn:population":0,
    "gn:timezone":"Africa/Kinshasa",
    "iso:country":"CD",
    "wof:name":"Mayambu",
    "wof:placetype":"locality"
},
  "geometry": {"coordinates":[15.19988,-4.77309],"type":"Point"}
}