{
  "type": "Feature",
  "properties": {
    "gn:admin1_code":"8.0",
    "gn:asciiname":"Kai-Kumbi",
    "gn:country_code":"CD",
    "gn:dem":310,
    "gn:feature_class":"P",
    "gn:feature_code":"PPL",
    "gn:name":"Kai-Kumbi",
    "gn:population":0,
    "gn:timezone":"Africa/Kinshasa",
    "iso:country":"CD",
    "wof:name":"Kai-Kumbi",
    "wof:placetype":"locality"
},
  "geometry": {"coordinates":[13.84082,-5.18941],"type":"Point"}
}