{
  "type": "Feature",
  "properties": {
    "gn:admin1_code":"16.0",
    "gn:asciiname":"Kandi",
    "gn:country_code":"CD",
    "gn:dem":738,
    "gn:feature_class":"P",
    "gn:feature_code":"PPL",
    "gn:name":"Kandi",
    "gn:population":0,
    "gn:timezone":"Africa/Lubumbashi",
    "iso:country":"CD",
    "name:ceb_x_preferred":[
        "Kandi"
    ],
    "name:deu_x_preferred":[
        "Kandi"
    ],
    "name:fin_x_preferred":[
        "Kandi"
    ],
    "name:fra_x_preferred":[
        "Kandi"
    ],
    "name:heb_x_preferred":[
        "\u05e7\u05e0\u05d3\u05d9"
    ],
    "name:hin_x_preferred":[
        "\u0915\u093e\u0902\u0921\u0940"
    ],
    "name:hun_x_preferred":[
        "Kandi"
    ],
    "name:swe_x_preferred":[
        "Kandi"
    ],
    "name:tur_x_preferred":[
        "Kandi"
    ],
    "wof:name":"Kandi",
    "wof:placetype":"locality"
},
  "geometry": {"coordinates":[27.95677,3.27948],"type":"Point"}
}