{
  "type": "Feature",
  "properties": {
    "gn:admin1_code":"14.0",
    "gn:asciiname":"Kabulili",
    "gn:country_code":"CD",
    "gn:dem":1265,
    "gn:feature_class":"P",
    "gn:feature_code":"PPL",
    "gn:name":"Kabulili",
    "gn:population":0,
    "gn:timezone":"Africa/Lubumbashi",
    "iso:country":"CD",
    "wof:name":"Kabulili",
    "wof:placetype":"locality"
},
  "geometry": {"coordinates":[27.71026,-12.18632],"type":"Point"}
}