{
  "type": "Feature",
  "properties": {
    "gn:admin1_code":"2.0",
    "gn:asciiname":"Djalikenga",
    "gn:country_code":"CD",
    "gn:dem":318,
    "gn:feature_class":"P",
    "gn:feature_code":"PPL",
    "gn:name":"Djalikenga",
    "gn:population":0,
    "gn:timezone":"Africa/Kinshasa",
    "iso:country":"CD",
    "name:und_x_variant":[
        "Djallkenga",
        "Djalikenga"
    ],
    "wof:name":"Djalikenga",
    "wof:placetype":"locality"
},
  "geometry": {"coordinates":[18.25198,-0.88578],"type":"Point"}
}