{
  "type": "Feature",
  "properties": {
    "gn:admin1_code":"8.0",
    "gn:asciiname":"Kimfutu",
    "gn:country_code":"CD",
    "gn:dem":372,
    "gn:feature_class":"P",
    "gn:feature_code":"PPL",
    "gn:name":"Kimfutu",
    "gn:population":0,
    "gn:timezone":"Africa/Kinshasa",
    "iso:country":"CD",
    "wof:name":"Kimfutu",
    "wof:placetype":"locality"
},
  "geometry": {"coordinates":[14.3834,-4.84422],"type":"Point"}
}