{
  "type": "Feature",
  "properties": {
    "gn:admin1_code":"20.0",
    "gn:asciiname":"Intshume-Ebaya",
    "gn:country_code":"CD",
    "gn:dem":562,
    "gn:feature_class":"P",
    "gn:feature_code":"PPL",
    "gn:name":"Intshume-Ebaya",
    "gn:population":0,
    "gn:timezone":"Africa/Kinshasa",
    "iso:country":"CD",
    "name:und_x_variant":[
        "Ebaya",
        "Intshume-Ebaya"
    ],
    "wof:name":"Intshume-Ebaya",
    "wof:placetype":"locality"
},
  "geometry": {"coordinates":[19.44387,-4.51437],"type":"Point"}
}