{
  "type": "Feature",
  "properties": {
    "gn:admin1_code":"23.0",
    "gn:asciiname":"Tambwe-Mulumba",
    "gn:country_code":"CD",
    "gn:dem":767,
    "gn:feature_class":"P",
    "gn:feature_code":"PPL",
    "gn:name":"Tambwe-Mulumba",
    "gn:population":0,
    "gn:timezone":"Africa/Lubumbashi",
    "iso:country":"CD",
    "wof:name":"Tambwe-Mulumba",
    "wof:placetype":"locality"
},
  "geometry": {"coordinates":[22.82703,-6.15552],"type":"Point"}
}