{
  "type": "Feature",
  "properties": {
    "gn:admin1_code":"30.0",
    "gn:asciiname":"Lisoku",
    "gn:country_code":"CD",
    "gn:dem":524,
    "gn:feature_class":"P",
    "gn:feature_code":"PPL",
    "gn:name":"Lisoku",
    "gn:population":0,
    "gn:timezone":"Africa/Lubumbashi",
    "iso:country":"CD",
    "wof:name":"Lisoku",
    "wof:placetype":"locality"
},
  "geometry": {"coordinates":[22.9799,0.86578],"type":"Point"}
}