{
  "type": "Feature",
  "properties": {
    "gn:admin1_code":"14.0",
    "gn:asciiname":"Mwau",
    "gn:country_code":"CD",
    "gn:dem":1050,
    "gn:feature_class":"P",
    "gn:feature_code":"PPL",
    "gn:name":"Mwau",
    "gn:population":0,
    "gn:timezone":"Africa/Lubumbashi",
    "iso:country":"CD",
    "wof:name":"Mwau",
    "wof:placetype":"locality"
},
  "geometry": {"coordinates":[28.47787000000001,-7.68843],"type":"Point"}
}