{
  "type": "Feature",
  "properties": {
    "gn:admin1_code":"21.0",
    "gn:asciiname":"Muteba-Lubanda",
    "gn:country_code":"CD",
    "gn:dem":843,
    "gn:feature_class":"P",
    "gn:feature_code":"PPL",
    "gn:name":"Muteba-Lubanda",
    "gn:population":0,
    "gn:timezone":"Africa/Lubumbashi",
    "iso:country":"CD",
    "wof:name":"Muteba-Lubanda",
    "wof:placetype":"locality"
},
  "geometry": {"coordinates":[24.27236,-5.95547],"type":"Point"}
}