{
  "type": "Feature",
  "properties": {
    "gn:admin1_code":"30.0",
    "gn:asciiname":"Angumu",
    "gn:country_code":"CD",
    "gn:dem":742,
    "gn:feature_class":"P",
    "gn:feature_code":"PPL",
    "gn:name":"Angumu",
    "gn:population":0,
    "gn:timezone":"Africa/Lubumbashi",
    "iso:country":"CD",
    "name:und_x_variant":[
        "Angumu Etat",
        "Angumu"
    ],
    "wof:name":"Angumu",
    "wof:placetype":"locality"
},
  "geometry": {"coordinates":[27.70344,-0.13912],"type":"Point"}
}