{
  "type": "Feature",
  "properties": {
    "gn:admin1_code":"19.0",
    "gn:asciiname":"Dembo",
    "gn:country_code":"CD",
    "gn:dem":818,
    "gn:feature_class":"P",
    "gn:feature_code":"PPL",
    "gn:name":"Dembo",
    "gn:population":0,
    "gn:timezone":"Africa/Kinshasa",
    "iso:country":"CD",
    "name:ita_x_preferred":[
        "Dembo"
    ],
    "wof:name":"Dembo",
    "wof:placetype":"locality"
},
  "geometry": {"coordinates":[18.17463,-6.21561],"type":"Point"}
}