{
  "type": "Feature",
  "properties": {
    "gn:admin1_code":"13.0",
    "gn:asciiname":"Epumba",
    "gn:country_code":"CD",
    "gn:dem":619,
    "gn:feature_class":"P",
    "gn:feature_code":"PPL",
    "gn:name":"Epumba",
    "gn:population":0,
    "gn:timezone":"Africa/Lubumbashi",
    "iso:country":"CD",
    "wof:name":"Epumba",
    "wof:placetype":"locality"
},
  "geometry": {"coordinates":[25.79769,3.08537],"type":"Point"}
}