{
  "type": "Feature",
  "properties": {
    "gn:admin1_code":"28.0",
    "gn:asciiname":"Bokembi",
    "gn:country_code":"CD",
    "gn:dem":352,
    "gn:feature_class":"P",
    "gn:feature_code":"PPL",
    "gn:name":"Bokembi",
    "gn:population":0,
    "gn:timezone":"Africa/Kinshasa",
    "iso:country":"CD",
    "wof:name":"Bokembi",
    "wof:placetype":"locality"
},
  "geometry": {"coordinates":[19.38414,3.41508],"type":"Point"}
}