{
  "type": "Feature",
  "properties": {
    "gn:admin1_code":"21.0",
    "gn:asciiname":"Nzengu",
    "gn:country_code":"CD",
    "gn:dem":905,
    "gn:feature_class":"P",
    "gn:feature_code":"PPL",
    "gn:name":"Nzengu",
    "gn:population":0,
    "gn:timezone":"Africa/Lubumbashi",
    "iso:country":"CD",
    "wof:name":"Nzengu",
    "wof:placetype":"locality"
},
  "geometry": {"coordinates":[23.49066,-6.86512],"type":"Point"}
}