{
  "type": "Feature",
  "properties": {
    "gn:admin1_code":"22.0",
    "gn:asciiname":"Kashinda",
    "gn:country_code":"CD",
    "gn:dem":1033,
    "gn:feature_class":"P",
    "gn:feature_code":"PPL",
    "gn:name":"Kashinda",
    "gn:population":0,
    "gn:timezone":"Africa/Lubumbashi",
    "iso:country":"CD",
    "wof:name":"Kashinda",
    "wof:placetype":"locality"
},
  "geometry": {"coordinates":[23.87265,-9.4468],"type":"Point"}
}