{
  "type": "Feature",
  "properties": {
    "gn:admin1_code":"21.0",
    "gn:asciiname":"Sangu",
    "gn:country_code":"CD",
    "gn:dem":849,
    "gn:feature_class":"P",
    "gn:feature_code":"PPL",
    "gn:name":"Sangu",
    "gn:population":0,
    "gn:timezone":"Africa/Lubumbashi",
    "iso:country":"CD",
    "wof:name":"Sangu",
    "wof:placetype":"locality"
},
  "geometry": {"coordinates":[23.51091,-7.19243],"type":"Point"}
}