{
  "type": "Feature",
  "properties": {
    "gn:admin1_code":"29.0",
    "gn:asciiname":"Lubumbu",
    "gn:country_code":"CD",
    "gn:dem":736,
    "gn:feature_class":"P",
    "gn:feature_code":"PPL",
    "gn:name":"Lubumbu",
    "gn:population":0,
    "gn:timezone":"Africa/Lubumbashi",
    "iso:country":"CD",
    "wof:name":"Lubumbu",
    "wof:placetype":"locality"
},
  "geometry": {"coordinates":[27.83269,-5.53462],"type":"Point"}
}