{
  "type": "Feature",
  "properties": {
    "gn:admin1_code":"20.0",
    "gn:asciiname":"Songo",
    "gn:country_code":"CD",
    "gn:dem":748,
    "gn:feature_class":"P",
    "gn:feature_code":"PPL",
    "gn:name":"Songo",
    "gn:population":0,
    "gn:timezone":"Africa/Kinshasa",
    "iso:country":"CD",
    "wof:name":"Songo",
    "wof:placetype":"locality"
},
  "geometry": {"coordinates":[19.08719,-5.48744],"type":"Point"}
}