{
  "type": "Feature",
  "properties": {
    "gn:admin1_code":"20.0",
    "gn:asciiname":"Tongo-Tongo",
    "gn:country_code":"CD",
    "gn:dem":424,
    "gn:feature_class":"P",
    "gn:feature_code":"PPL",
    "gn:name":"Tongo-Tongo",
    "gn:population":0,
    "gn:timezone":"Africa/Kinshasa",
    "iso:country":"CD",
    "wof:name":"Tongo-Tongo",
    "wof:placetype":"locality"
},
  "geometry": {"coordinates":[17.93447999999999,-5.17113],"type":"Point"}
}