{
  "type": "Feature",
  "properties": {
    "gn:admin1_code":"18.0",
    "gn:asciiname":"Nakambamba",
    "gn:country_code":"CD",
    "gn:dem":706,
    "gn:feature_class":"P",
    "gn:feature_code":"PPL",
    "gn:name":"Nakambamba",
    "gn:population":0,
    "gn:timezone":"Africa/Lubumbashi",
    "iso:country":"CD",
    "wof:name":"Nakambamba",
    "wof:placetype":"locality"
},
  "geometry": {"coordinates":[19.9217,-6.53263],"type":"Point"}
}