{
  "type": "Feature",
  "properties": {
    "gn:admin1_code":"19.0",
    "gn:asciiname":"Kipombo",
    "gn:country_code":"CD",
    "gn:dem":810,
    "gn:feature_class":"P",
    "gn:feature_code":"PPL",
    "gn:name":"Kipombo",
    "gn:population":0,
    "gn:timezone":"Africa/Kinshasa",
    "iso:country":"CD",
    "wof:name":"Kipombo",
    "wof:placetype":"locality"
},
  "geometry": {"coordinates":[18.35296,-6.12156],"type":"Point"}
}