{
  "type": "Feature",
  "properties": {
    "gn:admin1_code":"12.0",
    "gn:asciiname":"Kiandjo",
    "gn:country_code":"CD",
    "gn:dem":2002,
    "gn:feature_class":"P",
    "gn:feature_code":"PPL",
    "gn:name":"Kiandjo",
    "gn:population":0,
    "gn:timezone":"Africa/Lubumbashi",
    "iso:country":"CD",
    "wof:name":"Kiandjo",
    "wof:placetype":"locality"
},
  "geometry": {"coordinates":[28.65722,-3.39528],"type":"Point"}
}