{
  "type": "Feature",
  "properties": {
    "gn:admin1_code":"19.0",
    "gn:asciiname":"Mokiki",
    "gn:country_code":"CD",
    "gn:dem":698,
    "gn:feature_class":"P",
    "gn:feature_code":"PPL",
    "gn:name":"Mokiki",
    "gn:population":0,
    "gn:timezone":"Africa/Kinshasa",
    "iso:country":"CD",
    "wof:name":"Mokiki",
    "wof:placetype":"locality"
},
  "geometry": {"coordinates":[17.1856,-5.42115],"type":"Point"}
}