{
  "type": "Feature",
  "properties": {
    "gn:admin1_code":"22.0",
    "gn:asciiname":"Mwene-Kalombe",
    "gn:country_code":"CD",
    "gn:dem":1194,
    "gn:feature_class":"P",
    "gn:feature_code":"PPL",
    "gn:name":"Mwene-Kalombe",
    "gn:population":0,
    "gn:timezone":"Africa/Lubumbashi",
    "iso:country":"CD",
    "wof:name":"Mwene-Kalombe",
    "wof:placetype":"locality"
},
  "geometry": {"coordinates":[24.76667,-10.78333],"type":"Point"}
}