{
  "type": "Feature",
  "properties": {
    "gn:admin1_code":"2.0",
    "gn:asciiname":"Montoku",
    "gn:country_code":"CD",
    "gn:dem":338,
    "gn:feature_class":"P",
    "gn:feature_code":"PPL",
    "gn:name":"Montoku",
    "gn:population":0,
    "gn:timezone":"Africa/Kinshasa",
    "iso:country":"CD",
    "wof:name":"Montoku",
    "wof:placetype":"locality"
},
  "geometry": {"coordinates":[19.92929,1.41798],"type":"Point"}
}