{
  "type": "Feature",
  "properties": {
    "gn:admin1_code":"15.0",
    "gn:asciiname":"Zaji",
    "gn:country_code":"CD",
    "gn:dem":808,
    "gn:feature_class":"P",
    "gn:feature_code":"PPL",
    "gn:name":"Zaji",
    "gn:population":0,
    "gn:timezone":"Africa/Lubumbashi",
    "iso:country":"CD",
    "wof:name":"Zaji",
    "wof:placetype":"locality"
},
  "geometry": {"coordinates":[24.85024,-9.7723],"type":"Point"}
}