{
  "type": "Feature",
  "properties": {
    "gn:admin1_code":"15.0",
    "gn:asciiname":"Sokele",
    "gn:country_code":"CD",
    "gn:dem":940,
    "gn:feature_class":"P",
    "gn:feature_code":"PPL",
    "gn:name":"Sokele",
    "gn:population":0,
    "gn:timezone":"Africa/Lubumbashi",
    "iso:country":"CD",
    "wof:name":"Sokele",
    "wof:placetype":"locality"
},
  "geometry": {"coordinates":[24.60283,-9.9145],"type":"Point"}
}