{
  "type": "Feature",
  "properties": {
    "gn:admin1_code":"24.0",
    "gn:asciiname":"Mansele",
    "gn:country_code":"CD",
    "gn:dem":320,
    "gn:feature_class":"P",
    "gn:feature_code":"PPL",
    "gn:name":"Mansele",
    "gn:population":0,
    "gn:timezone":"Africa/Kinshasa",
    "iso:country":"CD",
    "wof:name":"Mansele",
    "wof:placetype":"locality"
},
  "geometry": {"coordinates":[16.45527,-2.08313],"type":"Point"}
}