{
  "type": "Feature",
  "properties": {
    "gn:admin1_code":"18.0",
    "gn:asciiname":"Tshinkembe",
    "gn:country_code":"CD",
    "gn:dem":834,
    "gn:feature_class":"P",
    "gn:feature_code":"PPL",
    "gn:name":"Tshinkembe",
    "gn:population":0,
    "gn:timezone":"Africa/Lubumbashi",
    "iso:country":"CD",
    "wof:name":"Tshinkembe",
    "wof:placetype":"locality"
},
  "geometry": {"coordinates":[21.58238,-7.22001],"type":"Point"}
}