{
  "type": "Feature",
  "properties": {
    "gn:admin1_code":"17.0",
    "gn:asciiname":"Rungu",
    "gn:country_code":"CD",
    "gn:dem":986,
    "gn:feature_class":"P",
    "gn:feature_code":"PPL",
    "gn:name":"Rungu",
    "gn:population":0,
    "gn:timezone":"Africa/Lubumbashi",
    "iso:country":"CD",
    "name:ceb_x_preferred":[
        "Rungu"
    ],
    "name:fra_x_preferred":[
        "Rungu"
    ],
    "name:swe_x_preferred":[
        "Rungu"
    ],
    "wof:name":"Rungu",
    "wof:placetype":"locality"
},
  "geometry": {"coordinates":[30.3108,2.96906],"type":"Point"}
}