{
  "type": "Feature",
  "properties": {
    "gn:admin1_code":"18.0",
    "gn:asciiname":"Bilenge",
    "gn:country_code":"CD",
    "gn:dem":607,
    "gn:feature_class":"P",
    "gn:feature_code":"PPL",
    "gn:name":"Bilenge",
    "gn:population":0,
    "gn:timezone":"Africa/Lubumbashi",
    "iso:country":"CD",
    "wof:name":"Bilenge",
    "wof:placetype":"locality"
},
  "geometry": {"coordinates":[20.99801,-6.49728],"type":"Point"}
}