{
  "type": "Feature",
  "properties": {
    "gn:admin1_code":"13.0",
    "gn:asciiname":"Abugosodio",
    "gn:country_code":"CD",
    "gn:dem":707,
    "gn:feature_class":"P",
    "gn:feature_code":"PPL",
    "gn:name":"Abugosodio",
    "gn:population":0,
    "gn:timezone":"Africa/Lubumbashi",
    "iso:country":"CD",
    "wof:name":"Abugosodio",
    "wof:placetype":"locality"
},
  "geometry": {"coordinates":[26.84905,2.58442],"type":"Point"}
}