{
  "type": "Feature",
  "properties": {
    "gn:admin1_code":"16.0",
    "gn:asciiname":"Koyo",
    "gn:country_code":"CD",
    "gn:dem":728,
    "gn:feature_class":"P",
    "gn:feature_code":"PPL",
    "gn:name":"Koyo",
    "gn:population":0,
    "gn:timezone":"Africa/Lubumbashi",
    "iso:country":"CD",
    "wof:name":"Koyo",
    "wof:placetype":"locality"
},
  "geometry": {"coordinates":[27.63135,3.43671],"type":"Point"}
}