{
  "type": "Feature",
  "properties": {
    "gn:admin1_code":"12.0",
    "gn:asciiname":"Kobokobo",
    "gn:country_code":"CD",
    "gn:dem":1039,
    "gn:feature_class":"P",
    "gn:feature_code":"PPL",
    "gn:name":"Kobokobo",
    "gn:population":0,
    "gn:timezone":"Africa/Lubumbashi",
    "iso:country":"CD",
    "wof:name":"Kobokobo",
    "wof:placetype":"locality"
},
  "geometry": {"coordinates":[28.15958,-3.09674],"type":"Point"}
}