{
  "type": "Feature",
  "properties": {
    "gn:admin1_code":"2.0",
    "gn:asciiname":"Bwalanga",
    "gn:country_code":"CD",
    "gn:dem":311,
    "gn:feature_class":"P",
    "gn:feature_code":"PPL",
    "gn:name":"Bwalanga",
    "gn:population":0,
    "gn:timezone":"Africa/Kinshasa",
    "iso:country":"CD",
    "wof:name":"Bwalanga",
    "wof:placetype":"locality"
},
  "geometry": {"coordinates":[18.12621,-0.89238],"type":"Point"}
}