{
  "type": "Feature",
  "properties": {
    "gn:admin1_code":"2.0",
    "gn:asciiname":"Ilanga Deuxieme",
    "gn:country_code":"CD",
    "gn:dem":332,
    "gn:feature_class":"P",
    "gn:feature_code":"PPL",
    "gn:name":"Ilanga Deuxi\u00e8me",
    "gn:population":0,
    "gn:timezone":"Africa/Kinshasa",
    "iso:country":"CD",
    "wof:name":"Ilanga Deuxieme",
    "wof:placetype":"locality"
},
  "geometry": {"coordinates":[18.23374,-0.25172],"type":"Point"}
}