{
  "type": "Feature",
  "properties": {
    "gn:admin1_code":"22.0",
    "gn:asciiname":"Kambuze",
    "gn:country_code":"CD",
    "gn:dem":1077,
    "gn:feature_class":"P",
    "gn:feature_code":"PPL",
    "gn:name":"Kambuze",
    "gn:population":0,
    "gn:timezone":"Africa/Lubumbashi",
    "iso:country":"CD",
    "wof:name":"Kambuze",
    "wof:placetype":"locality"
},
  "geometry": {"coordinates":[22.32661,-11.00799],"type":"Point"}
}