{
  "type": "Feature",
  "properties": {
    "gn:admin1_code":"23.0",
    "gn:asciiname":"Sapo-Kumuambo",
    "gn:country_code":"CD",
    "gn:dem":650,
    "gn:feature_class":"P",
    "gn:feature_code":"PPL",
    "gn:name":"Sapo-Kumuambo",
    "gn:population":0,
    "gn:timezone":"Africa/Lubumbashi",
    "iso:country":"CD",
    "name:und_x_variant":[
        "Sapo",
        "Sapo-Kumuambo"
    ],
    "wof:name":"Sapo-Kumuambo",
    "wof:placetype":"locality"
},
  "geometry": {"coordinates":[22.48998,-5.76594],"type":"Point"}
}