{
  "type": "Feature",
  "properties": {
    "gn:admin1_code":"8.0",
    "gn:asciiname":"Mbula",
    "gn:country_code":"CD",
    "gn:dem":565,
    "gn:feature_class":"P",
    "gn:feature_code":"PPL",
    "gn:name":"Mbula",
    "gn:population":0,
    "gn:timezone":"Africa/Kinshasa",
    "iso:country":"CD",
    "wof:name":"Mbula",
    "wof:placetype":"locality"
},
  "geometry": {"coordinates":[14.04597,-4.76305],"type":"Point"}
}