{
  "type": "Feature",
  "properties": {
    "gn:admin1_code":"22.0",
    "gn:asciiname":"Mukila-Kasaka",
    "gn:country_code":"CD",
    "gn:dem":949,
    "gn:feature_class":"P",
    "gn:feature_code":"PPL",
    "gn:name":"Mukila-Kasaka",
    "gn:population":0,
    "gn:timezone":"Africa/Lubumbashi",
    "iso:country":"CD",
    "wof:name":"Mukila-Kasaka",
    "wof:placetype":"locality"
},
  "geometry": {"coordinates":[22.61868,-9.29229],"type":"Point"}
}