{
  "type": "Feature",
  "properties": {
    "gn:admin1_code":"24.0",
    "gn:asciiname":"Ndamu",
    "gn:country_code":"CD",
    "gn:dem":336,
    "gn:feature_class":"P",
    "gn:feature_code":"PPL",
    "gn:name":"Ndamu",
    "gn:population":0,
    "gn:timezone":"Africa/Kinshasa",
    "iso:country":"CD",
    "wof:name":"Ndamu",
    "wof:placetype":"locality"
},
  "geometry": {"coordinates":[17.13516,-2.36517],"type":"Point"}
}