{
  "type": "Feature",
  "properties": {
    "gn:admin1_code":"19.0",
    "gn:asciiname":"Tsakala",
    "gn:country_code":"CD",
    "gn:dem":844,
    "gn:feature_class":"P",
    "gn:feature_code":"PPL",
    "gn:name":"Tsakala",
    "gn:population":0,
    "gn:timezone":"Africa/Kinshasa",
    "iso:country":"CD",
    "wof:name":"Tsakala",
    "wof:placetype":"locality"
},
  "geometry": {"coordinates":[17.91181,-7.7333],"type":"Point"}
}