{
  "type": "Feature",
  "properties": {
    "gn:admin1_code":"2.0",
    "gn:asciiname":"Balankole",
    "gn:country_code":"CD",
    "gn:dem":327,
    "gn:feature_class":"P",
    "gn:feature_code":"PPL",
    "gn:name":"Balankole",
    "gn:population":0,
    "gn:timezone":"Africa/Kinshasa",
    "iso:country":"CD",
    "wof:name":"Balankole",
    "wof:placetype":"locality"
},
  "geometry": {"coordinates":[19.48333,-0.15],"type":"Point"}
}