{
  "type": "Feature",
  "properties": {
    "gn:admin1_code":"21.0",
    "gn:asciiname":"Kananga",
    "gn:country_code":"CD",
    "gn:dem":775,
    "gn:feature_class":"P",
    "gn:feature_code":"PPL",
    "gn:name":"Kananga",
    "gn:population":0,
    "gn:timezone":"Africa/Lubumbashi",
    "iso:country":"CD",
    "wof:name":"Kananga",
    "wof:placetype":"locality"
},
  "geometry": {"coordinates":[24.39449,-5.77125],"type":"Point"}
}