{
  "type": "Feature",
  "properties": {
    "gn:admin1_code":"10.0",
    "gn:asciiname":"Alimasi",
    "gn:country_code":"CD",
    "gn:dem":588,
    "gn:feature_class":"P",
    "gn:feature_code":"PPL",
    "gn:name":"Alimasi",
    "gn:population":0,
    "gn:timezone":"Africa/Lubumbashi",
    "iso:country":"CD",
    "wof:name":"Alimasi",
    "wof:placetype":"locality"
},
  "geometry": {"coordinates":[26.18333,-1.78333],"type":"Point"}
}