{
  "type": "Feature",
  "properties": {
    "gn:admin1_code":"20.0",
    "gn:asciiname":"Moyeke",
    "gn:country_code":"CD",
    "gn:dem":341,
    "gn:feature_class":"P",
    "gn:feature_code":"PPL",
    "gn:name":"Moyeke",
    "gn:population":0,
    "gn:timezone":"Africa/Kinshasa",
    "iso:country":"CD",
    "wof:name":"Moyeke",
    "wof:placetype":"locality"
},
  "geometry": {"coordinates":[18.45,-4.31667],"type":"Point"}
}