{
  "type": "Feature",
  "properties": {
    "gn:admin1_code":"24.0",
    "gn:asciiname":"Pwa",
    "gn:country_code":"CD",
    "gn:dem":303,
    "gn:feature_class":"P",
    "gn:feature_code":"PPL",
    "gn:name":"Pwa",
    "gn:population":0,
    "gn:timezone":"Africa/Kinshasa",
    "iso:country":"CD",
    "wof:name":"Pwa",
    "wof:placetype":"locality"
},
  "geometry": {"coordinates":[17.28732,-3.44692],"type":"Point"}
}