{
  "type": "Feature",
  "properties": {
    "gn:admin1_code":"25.0",
    "gn:asciiname":"Yakala",
    "gn:country_code":"CD",
    "gn:dem":384,
    "gn:feature_class":"P",
    "gn:feature_code":"PPL",
    "gn:name":"Yakala",
    "gn:population":0,
    "gn:timezone":"Africa/Kinshasa",
    "iso:country":"CD",
    "wof:name":"Yakala",
    "wof:placetype":"locality"
},
  "geometry": {"coordinates":[23.1918,2.24451],"type":"Point"}
}