{
  "type": "Feature",
  "properties": {
    "gn:admin1_code":"18.0",
    "gn:asciiname":"Kabuanga-Tshisenge",
    "gn:country_code":"CD",
    "gn:dem":569,
    "gn:feature_class":"P",
    "gn:feature_code":"PPL",
    "gn:name":"Kabuanga-Tshisenge",
    "gn:population":0,
    "gn:timezone":"Africa/Lubumbashi",
    "iso:country":"CD",
    "wof:name":"Kabuanga-Tshisenge",
    "wof:placetype":"locality"
},
  "geometry": {"coordinates":[20.74433,-5.88658],"type":"Point"}
}