{
  "type": "Feature",
  "properties": {
    "gn:admin1_code":"14.0",
    "gn:asciiname":"Panda",
    "gn:country_code":"CD",
    "gn:dem":1176,
    "gn:feature_class":"P",
    "gn:feature_code":"PPL",
    "gn:name":"Panda",
    "gn:population":0,
    "gn:timezone":"Africa/Lubumbashi",
    "iso:country":"CD",
    "name:ara_x_preferred":[
        "\u0628\u0627\u0646\u062f\u0627"
    ],
    "name:ben_x_preferred":[
        "\u09aa\u09be\u09a8\u09cd\u09a1\u09be"
    ],
    "name:deu_x_preferred":[
        "Panda"
    ],
    "name:ell_x_preferred":[
        "\u03a0\u03ac\u03bd\u03c4\u03b1"
    ],
    "name:eng_x_preferred":[
        "Panda"
    ],
    "name:fas_x_preferred":[
        "\u067e\u0627\u0646\u062f\u0627"
    ],
    "name:fra_x_preferred":[
        "Panda"
    ],
    "name:heb_x_preferred":[
        "\u05e4\u05e0\u05d3\u05d4"
    ],
    "name:hin_x_preferred":[
        "\u092a\u093e\u0902\u0921\u093e"
    ],
    "name:hun_x_preferred":[
        "Panda"
    ],
    "name:ind_x_preferred":[
        "Panda"
    ],
    "name:ita_x_preferred":[
        "Panda"
    ],
    "name:jpn_x_preferred":[
        "\u30d1\u30f3\u30c0"
    ],
    "name:kor_x_preferred":[
        "\ud310\ub2e4"
    ],
    "name:nld_x_preferred":[
        "Panda"
    ],
    "name:pol_x_preferred":[
        "Panda"
    ],
    "name:por_x_preferred":[
        "Panda"
    ],
    "name:rus_x_preferred":[
        "\u041f\u0430\u043d\u0434\u0430"
    ],
    "name:spa_x_preferred":[
        "Panda"
    ],
    "name:swe_x_preferred":[
        "Panda"
    ],
    "name:tur_x_preferred":[
        "Panda"
    ],
    "name:ukr_x_preferred":[
        "\u041f\u0430\u043d\u0434\u0430"
    ],
    "name:urd_x_preferred":[
        "\u067e\u0627\u0646\u0688\u0627"
    ],
    "name:vie_x_preferred":[
        "Panda"
    ],
    "name:zho_cn_x_preferred":[
        "\u6f58\u8fbe"
    ],
    "name:zho_tw_x_preferred":[
        "\u6f58\u9054"
    ],
    "wof:name":"Panda",
    "wof:placetype":"locality"
},
  "geometry": {"coordinates":[27.64276,-11.78153],"type":"Point"}
}