{
  "type": "Feature",
  "properties": {
    "gn:admin1_code":"20.0",
    "gn:asciiname":"Katembo",
    "gn:country_code":"CD",
    "gn:dem":488,
    "gn:feature_class":"P",
    "gn:feature_code":"PPL",
    "gn:name":"Katembo",
    "gn:population":0,
    "gn:timezone":"Africa/Kinshasa",
    "iso:country":"CD",
    "wof:name":"Katembo",
    "wof:placetype":"locality"
},
  "geometry": {"coordinates":[18.98336,-5.37916],"type":"Point"}
}