{
  "type": "Feature",
  "properties": {
    "gn:admin1_code":"15.0",
    "gn:asciiname":"Poyo Kisanga",
    "gn:country_code":"CD",
    "gn:dem":756,
    "gn:feature_class":"P",
    "gn:feature_code":"PPL",
    "gn:name":"Poyo Kisanga",
    "gn:population":0,
    "gn:timezone":"Africa/Lubumbashi",
    "iso:country":"CD",
    "wof:name":"Poyo Kisanga",
    "wof:placetype":"locality"
},
  "geometry": {"coordinates":[26.35084,-7.78565],"type":"Point"}
}