{
  "type": "Feature",
  "properties": {
    "gn:admin1_code":"8.0",
    "gn:asciiname":"Kidesa",
    "gn:country_code":"CD",
    "gn:dem":405,
    "gn:feature_class":"P",
    "gn:feature_code":"PPL",
    "gn:name":"Kidesa",
    "gn:population":0,
    "gn:timezone":"Africa/Kinshasa",
    "iso:country":"CD",
    "wof:name":"Kidesa",
    "wof:placetype":"locality"
},
  "geometry": {"coordinates":[14.73337,-5.62683],"type":"Point"}
}