{
  "type": "Feature",
  "properties": {
    "gn:admin1_code":"30.0",
    "gn:asciiname":"Bogata",
    "gn:country_code":"CD",
    "gn:dem":456,
    "gn:feature_class":"P",
    "gn:feature_code":"PPL",
    "gn:name":"Bogata",
    "gn:population":0,
    "gn:timezone":"Africa/Lubumbashi",
    "iso:country":"CD",
    "name:ceb_x_preferred":[
        "Bogata"
    ],
    "name:deu_x_preferred":[
        "Bogata"
    ],
    "name:epo_x_preferred":[
        "Bogata"
    ],
    "name:hun_x_preferred":[
        "Bogata"
    ],
    "name:nld_x_preferred":[
        "Bogata"
    ],
    "name:por_x_preferred":[
        "Bogata"
    ],
    "name:ron_x_preferred":[
        "Bogata"
    ],
    "name:srp_x_preferred":[
        "\u0411\u043e\u0433\u0430\u0442\u0430"
    ],
    "name:vol_x_preferred":[
        "Bogata"
    ],
    "wof:name":"Bogata",
    "wof:placetype":"locality"
},
  "geometry": {"coordinates":[25.35988,1.73352],"type":"Point"}
}