{
  "type": "Feature",
  "properties": {
    "gn:admin1_code":"23.0",
    "gn:asciiname":"Mbala-Kalonda",
    "gn:country_code":"CD",
    "gn:dem":613,
    "gn:feature_class":"P",
    "gn:feature_code":"PPL",
    "gn:name":"Mbala-Kalonda",
    "gn:population":0,
    "gn:timezone":"Africa/Lubumbashi",
    "iso:country":"CD",
    "wof:name":"Mbala-Kalonda",
    "wof:placetype":"locality"
},
  "geometry": {"coordinates":[22.35246,-5.89388],"type":"Point"}
}