{
  "type": "Feature",
  "properties": {
    "gn:admin1_code":"18.0",
    "gn:asciiname":"Tshimbofu",
    "gn:country_code":"CD",
    "gn:dem":552,
    "gn:feature_class":"P",
    "gn:feature_code":"PPL",
    "gn:name":"Tshimbofu",
    "gn:population":0,
    "gn:timezone":"Africa/Lubumbashi",
    "iso:country":"CD",
    "wof:name":"Tshimbofu",
    "wof:placetype":"locality"
},
  "geometry": {"coordinates":[20.70547,-6.53052],"type":"Point"}
}