{
  "type": "Feature",
  "properties": {
    "gn:admin1_code":"10.0",
    "gn:asciiname":"Pene-Senga",
    "gn:country_code":"CD",
    "gn:dem":607,
    "gn:feature_class":"P",
    "gn:feature_code":"PPL",
    "gn:name":"Pene-Senga",
    "gn:population":0,
    "gn:timezone":"Africa/Lubumbashi",
    "iso:country":"CD",
    "wof:name":"Pene-Senga",
    "wof:placetype":"locality"
},
  "geometry": {"coordinates":[26.74559,-4.3767],"type":"Point"}
}