{
  "type": "Feature",
  "properties": {
    "gn:admin1_code":"10.0",
    "gn:asciiname":"Kubitaka",
    "gn:country_code":"CD",
    "gn:dem":606,
    "gn:feature_class":"P",
    "gn:feature_code":"PPL",
    "gn:name":"Kubitaka",
    "gn:population":0,
    "gn:timezone":"Africa/Lubumbashi",
    "iso:country":"CD",
    "wof:name":"Kubitaka",
    "wof:placetype":"locality"
},
  "geometry": {"coordinates":[26.69855,-1.71561],"type":"Point"}
}