{
  "type": "Feature",
  "properties": {
    "gn:admin1_code":"27.0",
    "gn:asciiname":"Yani",
    "gn:country_code":"CD",
    "gn:dem":502,
    "gn:feature_class":"P",
    "gn:feature_code":"PPL",
    "gn:name":"Yani",
    "gn:population":0,
    "gn:timezone":"Africa/Lubumbashi",
    "iso:country":"CD",
    "wof:name":"Yani",
    "wof:placetype":"locality"
},
  "geometry": {"coordinates":[23.05,-3.33333],"type":"Point"}
}