{
  "type": "Feature",
  "properties": {
    "gn:admin1_code":"8.0",
    "gn:asciiname":"Wanga",
    "gn:country_code":"CD",
    "gn:dem":164,
    "gn:feature_class":"P",
    "gn:feature_code":"PPL",
    "gn:name":"Wanga",
    "gn:population":0,
    "gn:timezone":"Africa/Kinshasa",
    "iso:country":"CD",
    "wof:name":"Wanga",
    "wof:placetype":"locality"
},
  "geometry": {"coordinates":[12.64176,-5.71246],"type":"Point"}
}