{
  "type": "Feature",
  "properties": {
    "gn:admin1_code":"2.0",
    "gn:asciiname":"Bonkita",
    "gn:country_code":"CD",
    "gn:dem":335,
    "gn:feature_class":"P",
    "gn:feature_code":"PPL",
    "gn:name":"Bonkita",
    "gn:population":0,
    "gn:timezone":"Africa/Kinshasa",
    "iso:country":"CD",
    "wof:name":"Bonkita",
    "wof:placetype":"locality"
},
  "geometry": {"coordinates":[19.65999,1.2668],"type":"Point"}
}