{
  "type": "Feature",
  "properties": {
    "gn:admin1_code":"21.0",
    "gn:asciiname":"Kongolo",
    "gn:country_code":"CD",
    "gn:dem":700,
    "gn:feature_class":"P",
    "gn:feature_code":"PPL",
    "gn:name":"Kongolo",
    "gn:population":0,
    "gn:timezone":"Africa/Lubumbashi",
    "iso:country":"CD",
    "name:ceb_x_preferred":[
        "Kongolo"
    ],
    "name:deu_x_preferred":[
        "Kongolo"
    ],
    "name:rus_x_preferred":[
        "\u041a\u043e\u043d\u0433\u043e\u043b\u043e"
    ],
    "name:swe_x_preferred":[
        "Kongolo"
    ],
    "wof:name":"Kongolo",
    "wof:placetype":"locality"
},
  "geometry": {"coordinates":[24.65649,-6.60809],"type":"Point"}
}