{
  "type": "Feature",
  "properties": {
    "gn:admin1_code":"2.0",
    "gn:asciiname":"Ikengo",
    "gn:country_code":"CD",
    "gn:dem":302,
    "gn:feature_class":"P",
    "gn:feature_code":"PPL",
    "gn:name":"Ikengo",
    "gn:population":0,
    "gn:timezone":"Africa/Kinshasa",
    "iso:country":"CD",
    "name:und_x_variant":[
        "Ikange",
        "Ikenge",
        "Ikengo"
    ],
    "wof:name":"Ikengo",
    "wof:placetype":"locality"
},
  "geometry": {"coordinates":[18.13092,-0.12892],"type":"Point"}
}