{
  "type": "Feature",
  "properties": {
    "gn:admin1_code":"28.0",
    "gn:asciiname":"Bodjangele",
    "gn:country_code":"CD",
    "gn:dem":407,
    "gn:feature_class":"P",
    "gn:feature_code":"PPL",
    "gn:name":"Bodjangele",
    "gn:population":0,
    "gn:timezone":"Africa/Kinshasa",
    "iso:country":"CD",
    "wof:name":"Bodjangele",
    "wof:placetype":"locality"
},
  "geometry": {"coordinates":[18.78152,2.40506],"type":"Point"}
}