{
  "type": "Feature",
  "properties": {
    "gn:admin1_code":"29.0",
    "gn:asciiname":"Kabeya-Mayj",
    "gn:country_code":"CD",
    "gn:dem":613,
    "gn:feature_class":"P",
    "gn:feature_code":"PPL",
    "gn:name":"Kabeya-Mayj",
    "gn:population":0,
    "gn:timezone":"Africa/Lubumbashi",
    "iso:country":"CD",
    "name:und_x_variant":[
        "Kabeya",
        "Kabeya Maji"
    ],
    "wof:name":"Kabeya-Mayj",
    "wof:placetype":"locality"
},
  "geometry": {"coordinates":[27.96714,-5.67163],"type":"Point"}
}