{
  "type": "Feature",
  "properties": {
    "gn:admin1_code":"26.0",
    "gn:asciiname":"Bosanga",
    "gn:country_code":"CD",
    "gn:dem":453,
    "gn:feature_class":"P",
    "gn:feature_code":"PPL",
    "gn:name":"Bosanga",
    "gn:population":0,
    "gn:timezone":"Africa/Kinshasa",
    "iso:country":"CD",
    "wof:name":"Bosanga",
    "wof:placetype":"locality"
},
  "geometry": {"coordinates":[21.88439,3.70518],"type":"Point"}
}