{
  "type": "Feature",
  "properties": {
    "gn:admin1_code":"8.0",
    "gn:asciiname":"Kimbenza-Bunu",
    "gn:country_code":"CD",
    "gn:dem":712,
    "gn:feature_class":"P",
    "gn:feature_code":"PPL",
    "gn:name":"Kimbenza-Bunu",
    "gn:population":0,
    "gn:timezone":"Africa/Kinshasa",
    "iso:country":"CD",
    "wof:name":"Kimbenza-Bunu",
    "wof:placetype":"locality"
},
  "geometry": {"coordinates":[13.80225,-4.43734],"type":"Point"}
}