{
  "type": "Feature",
  "properties": {
    "gn:admin1_code":"16.0",
    "gn:asciiname":"Mongwa",
    "gn:country_code":"CD",
    "gn:dem":851,
    "gn:feature_class":"P",
    "gn:feature_code":"PPL",
    "gn:name":"Mongwa",
    "gn:population":0,
    "gn:timezone":"Africa/Lubumbashi",
    "iso:country":"CD",
    "wof:name":"Mongwa",
    "wof:placetype":"locality"
},
  "geometry": {"coordinates":[29.98223,3.89135],"type":"Point"}
}