{
  "type": "Feature",
  "properties": {
    "gn:admin1_code":"2.0",
    "gn:asciiname":"Motwa",
    "gn:country_code":"CD",
    "gn:dem":356,
    "gn:feature_class":"P",
    "gn:feature_code":"PPL",
    "gn:name":"Motwa",
    "gn:population":0,
    "gn:timezone":"Africa/Kinshasa",
    "iso:country":"CD",
    "wof:name":"Motwa",
    "wof:placetype":"locality"
},
  "geometry": {"coordinates":[18.79431,0.15234],"type":"Point"}
}