{
  "type": "Feature",
  "properties": {
    "gn:admin1_code":"23.0",
    "gn:asciiname":"Tshimbao",
    "gn:country_code":"CD",
    "gn:dem":773,
    "gn:feature_class":"P",
    "gn:feature_code":"PPL",
    "gn:name":"Tshimbao",
    "gn:population":0,
    "gn:timezone":"Africa/Lubumbashi",
    "iso:country":"CD",
    "name:und_x_variant":[
        "Tshimba",
        "Tshimbao"
    ],
    "wof:name":"Tshimbao",
    "wof:placetype":"locality"
},
  "geometry": {"coordinates":[22.83264,-5.98726],"type":"Point"}
}