{
  "type": "Feature",
  "properties": {
    "gn:admin1_code":"2.0",
    "gn:asciiname":"Lulungu",
    "gn:country_code":"CD",
    "gn:dem":319,
    "gn:feature_class":"P",
    "gn:feature_code":"PPL",
    "gn:name":"Lulungu",
    "gn:population":0,
    "gn:timezone":"Africa/Kinshasa",
    "iso:country":"CD",
    "name:und_x_variant":[
        "Lolungu"
    ],
    "wof:name":"Lulungu",
    "wof:placetype":"locality"
},
  "geometry": {"coordinates":[18.44035,-0.15383],"type":"Point"}
}