{
  "type": "Feature",
  "properties": {
    "gn:admin1_code":"22.0",
    "gn:asciiname":"Dumbatshitutshi",
    "gn:country_code":"CD",
    "gn:dem":1009,
    "gn:feature_class":"P",
    "gn:feature_code":"PPL",
    "gn:name":"Dumbatshitutshi",
    "gn:population":0,
    "gn:timezone":"Africa/Lubumbashi",
    "iso:country":"CD",
    "wof:name":"Dumbatshitutshi",
    "wof:placetype":"locality"
},
  "geometry": {"coordinates":[23.51788,-10.08579],"type":"Point"}
}