{
  "type": "Feature",
  "properties": {
    "gn:admin1_code":"14.0",
    "gn:asciiname":"Mufunga",
    "gn:country_code":"CD",
    "gn:dem":938,
    "gn:feature_class":"P",
    "gn:feature_code":"PPL",
    "gn:name":"Mufunga",
    "gn:population":0,
    "gn:timezone":"Africa/Lubumbashi",
    "iso:country":"CD",
    "wof:name":"Mufunga",
    "wof:placetype":"locality"
},
  "geometry": {"coordinates":[27.44567,-9.34953],"type":"Point"}
}