{
  "type": "Feature",
  "properties": {
    "gn:admin1_code":"11.0",
    "gn:asciiname":"Nyamasa",
    "gn:country_code":"CD",
    "gn:dem":631,
    "gn:feature_class":"P",
    "gn:feature_code":"PPL",
    "gn:name":"Nyamasa",
    "gn:population":0,
    "gn:timezone":"Africa/Lubumbashi",
    "iso:country":"CD",
    "wof:name":"Nyamasa",
    "wof:placetype":"locality"
},
  "geometry": {"coordinates":[27.52083,-1.36767],"type":"Point"}
}