{
  "type": "Feature",
  "properties": {
    "gn:admin1_code":"18.0",
    "gn:asciiname":"Kapata",
    "gn:country_code":"CD",
    "gn:dem":513,
    "gn:feature_class":"P",
    "gn:feature_code":"PPL",
    "gn:name":"Kapata",
    "gn:population":0,
    "gn:timezone":"Africa/Lubumbashi",
    "iso:country":"CD",
    "wof:name":"Kapata",
    "wof:placetype":"locality"
},
  "geometry": {"coordinates":[20.99806,-5.47949],"type":"Point"}
}