{
  "type": "Feature",
  "properties": {
    "gn:admin1_code":"28.0",
    "gn:asciiname":"Bokuda",
    "gn:country_code":"CD",
    "gn:dem":553,
    "gn:feature_class":"P",
    "gn:feature_code":"PPL",
    "gn:name":"Bokuda",
    "gn:population":0,
    "gn:timezone":"Africa/Kinshasa",
    "iso:country":"CD",
    "wof:name":"Bokuda",
    "wof:placetype":"locality"
},
  "geometry": {"coordinates":[19.77488,3.22025],"type":"Point"}
}