{
  "type": "Feature",
  "properties": {
    "gn:admin1_code":"22.0",
    "gn:asciiname":"Kahudi",
    "gn:country_code":"CD",
    "gn:dem":1200,
    "gn:feature_class":"P",
    "gn:feature_code":"PPL",
    "gn:name":"Kahudi",
    "gn:population":0,
    "gn:timezone":"Africa/Lubumbashi",
    "iso:country":"CD",
    "wof:name":"Kahudi",
    "wof:placetype":"locality"
},
  "geometry": {"coordinates":[24.14261,-10.44541],"type":"Point"}
}