{
  "type": "Feature",
  "properties": {
    "gn:admin1_code":"12.0",
    "gn:asciiname":"Nkuba Premiere",
    "gn:country_code":"CD",
    "gn:dem":841,
    "gn:feature_class":"P",
    "gn:feature_code":"PPL",
    "gn:name":"Nkuba Premi\u00e8re",
    "gn:population":0,
    "gn:timezone":"Africa/Lubumbashi",
    "iso:country":"CD",
    "name:und_x_variant":[
        "Nkuba Premi\u00e8re",
        "Nkuba I"
    ],
    "wof:name":"Nkuba Premiere",
    "wof:placetype":"locality"
},
  "geometry": {"coordinates":[27.63123,-2.24668],"type":"Point"}
}