{
  "type": "Feature",
  "properties": {
    "gn:admin1_code":"19.0",
    "gn:asciiname":"Kadibala",
    "gn:country_code":"CD",
    "gn:dem":917,
    "gn:feature_class":"P",
    "gn:feature_code":"PPL",
    "gn:name":"Kadibala",
    "gn:population":0,
    "gn:timezone":"Africa/Kinshasa",
    "iso:country":"CD",
    "wof:name":"Kadibala",
    "wof:placetype":"locality"
},
  "geometry": {"coordinates":[19.56957,-6.98562],"type":"Point"}
}