{
  "type": "Feature",
  "properties": {
    "gn:admin1_code":"25.0",
    "gn:asciiname":"Yandunda",
    "gn:country_code":"CD",
    "gn:dem":450,
    "gn:feature_class":"P",
    "gn:feature_code":"PPL",
    "gn:name":"Yandunda",
    "gn:population":0,
    "gn:timezone":"Africa/Kinshasa",
    "iso:country":"CD",
    "wof:name":"Yandunda",
    "wof:placetype":"locality"
},
  "geometry": {"coordinates":[22.16202,2.56278],"type":"Point"}
}