{
  "type": "Feature",
  "properties": {
    "gn:admin1_code":"19.0",
    "gn:asciiname":"Kimbinga",
    "gn:country_code":"CD",
    "gn:dem":449,
    "gn:feature_class":"P",
    "gn:feature_code":"PPL",
    "gn:name":"Kimbinga",
    "gn:population":0,
    "gn:timezone":"Africa/Kinshasa",
    "iso:country":"CD",
    "wof:name":"Kimbinga",
    "wof:placetype":"locality"
},
  "geometry": {"coordinates":[17.66127000000001,-4.42031],"type":"Point"}
}