{
  "type": "Feature",
  "properties": {
    "gn:admin1_code":"12.0",
    "gn:asciiname":"Lwiro",
    "gn:country_code":"CD",
    "gn:dem":1975,
    "gn:feature_class":"P",
    "gn:feature_code":"PPL",
    "gn:name":"Lwiro",
    "gn:population":0,
    "gn:timezone":"Africa/Lubumbashi",
    "iso:country":"CD",
    "name:und_x_variant":[
        "Mwiru",
        "Luiro",
        "Lwiro"
    ],
    "wof:name":"Lwiro",
    "wof:placetype":"locality"
},
  "geometry": {"coordinates":[28.78642,-2.23193],"type":"Point"}
}