{
  "type": "Feature",
  "properties": {
    "gn:admin1_code":"22.0",
    "gn:asciiname":"Demba",
    "gn:country_code":"CD",
    "gn:dem":1071,
    "gn:feature_class":"P",
    "gn:feature_code":"PPL",
    "gn:name":"Demba",
    "gn:population":0,
    "gn:timezone":"Africa/Lubumbashi",
    "iso:country":"CD",
    "name:ceb_x_preferred":[
        "Demba"
    ],
    "name:deu_x_preferred":[
        "Demba"
    ],
    "name:ron_x_preferred":[
        "Demba"
    ],
    "name:swe_x_preferred":[
        "Demba"
    ],
    "wof:name":"Demba",
    "wof:placetype":"locality"
},
  "geometry": {"coordinates":[22.20548,-9.8461],"type":"Point"}
}