{
  "type": "Feature",
  "properties": {
    "gn:admin1_code":"11.0",
    "gn:asciiname":"Luandumbi",
    "gn:country_code":"CD",
    "gn:dem":1495,
    "gn:feature_class":"P",
    "gn:feature_code":"PPL",
    "gn:name":"Luandumbi",
    "gn:population":0,
    "gn:timezone":"Africa/Lubumbashi",
    "iso:country":"CD",
    "wof:name":"Luandumbi",
    "wof:placetype":"locality"
},
  "geometry": {"coordinates":[29.72448,0.19457],"type":"Point"}
}