{
  "type": "Feature",
  "properties": {
    "gn:admin1_code":"22.0",
    "gn:asciiname":"Kavula Katende",
    "gn:country_code":"CD",
    "gn:dem":1088,
    "gn:feature_class":"P",
    "gn:feature_code":"PPL",
    "gn:name":"Kavula Katende",
    "gn:population":0,
    "gn:timezone":"Africa/Lubumbashi",
    "iso:country":"CD",
    "wof:name":"Kavula Katende",
    "wof:placetype":"locality"
},
  "geometry": {"coordinates":[22.10077,-9.68652],"type":"Point"}
}