{
  "type": "Feature",
  "properties": {
    "gn:admin1_code":"21.0",
    "gn:asciiname":"Lubembele-Kilue",
    "gn:country_code":"CD",
    "gn:dem":663,
    "gn:feature_class":"P",
    "gn:feature_code":"PPL",
    "gn:name":"Lubembele-Kilue",
    "gn:population":0,
    "gn:timezone":"Africa/Lubumbashi",
    "iso:country":"CD",
    "wof:name":"Lubembele-Kilue",
    "wof:placetype":"locality"
},
  "geometry": {"coordinates":[26.01667,-6.06667],"type":"Point"}
}