{
  "type": "Feature",
  "properties": {
    "gn:admin1_code":"8.0",
    "gn:asciiname":"Zingu",
    "gn:country_code":"CD",
    "gn:dem":631,
    "gn:feature_class":"P",
    "gn:feature_code":"PPL",
    "gn:name":"Zingu",
    "gn:population":0,
    "gn:timezone":"Africa/Kinshasa",
    "iso:country":"CD",
    "wof:name":"Zingu",
    "wof:placetype":"locality"
},
  "geometry": {"coordinates":[15.3844,-5.55013],"type":"Point"}
}