{
  "type": "Feature",
  "properties": {
    "gn:admin1_code":"15.0",
    "gn:asciiname":"Musamba",
    "gn:country_code":"CD",
    "gn:dem":575,
    "gn:feature_class":"P",
    "gn:feature_code":"PPL",
    "gn:name":"Musamba",
    "gn:population":0,
    "gn:timezone":"Africa/Lubumbashi",
    "iso:country":"CD",
    "wof:name":"Musamba",
    "wof:placetype":"locality"
},
  "geometry": {"coordinates":[26.80199,-7.64495],"type":"Point"}
}