{
  "type": "Feature",
  "properties": {
    "gn:admin1_code":"8.0",
    "gn:asciiname":"Kinsundi",
    "gn:country_code":"CD",
    "gn:dem":732,
    "gn:feature_class":"P",
    "gn:feature_code":"PPL",
    "gn:name":"Kinsundi",
    "gn:population":0,
    "gn:timezone":"Africa/Kinshasa",
    "iso:country":"CD",
    "wof:name":"Kinsundi",
    "wof:placetype":"locality"
},
  "geometry": {"coordinates":[15.41305,-5.82662],"type":"Point"}
}