{
  "type": "Feature",
  "properties": {
    "gn:admin1_code":"30.0",
    "gn:asciiname":"Lelema",
    "gn:country_code":"CD",
    "gn:dem":434,
    "gn:feature_class":"P",
    "gn:feature_code":"PPL",
    "gn:name":"Lelema",
    "gn:population":0,
    "gn:timezone":"Africa/Lubumbashi",
    "iso:country":"CD",
    "wof:name":"Lelema",
    "wof:placetype":"locality"
},
  "geometry": {"coordinates":[24.04267,-0.32541],"type":"Point"}
}