{
  "type": "Feature",
  "properties": {
    "gn:admin1_code":"14.0",
    "gn:asciiname":"Meba",
    "gn:country_code":"CD",
    "gn:dem":1251,
    "gn:feature_class":"P",
    "gn:feature_code":"PPL",
    "gn:name":"Meba",
    "gn:population":0,
    "gn:timezone":"Africa/Lubumbashi",
    "iso:country":"CD",
    "wof:name":"Meba",
    "wof:placetype":"locality"
},
  "geometry": {"coordinates":[27.71462,-8.78263],"type":"Point"}
}