{
  "type": "Feature",
  "properties": {
    "gn:admin1_code":"27.0",
    "gn:asciiname":"Diampangila",
    "gn:country_code":"CD",
    "gn:dem":570,
    "gn:feature_class":"P",
    "gn:feature_code":"PPL",
    "gn:name":"Diampangila",
    "gn:population":0,
    "gn:timezone":"Africa/Lubumbashi",
    "iso:country":"CD",
    "name:und_x_variant":[
        "Djompongila"
    ],
    "wof:name":"Diampangila",
    "wof:placetype":"locality"
},
  "geometry": {"coordinates":[22.13588,-3.35696],"type":"Point"}
}