{
  "type": "Feature",
  "properties": {
    "gn:admin1_code":"15.0",
    "gn:asciiname":"Kime",
    "gn:country_code":"CD",
    "gn:dem":1014,
    "gn:feature_class":"P",
    "gn:feature_code":"PPL",
    "gn:name":"Kime",
    "gn:population":0,
    "gn:timezone":"Africa/Lubumbashi",
    "iso:country":"CD",
    "wof:name":"Kime",
    "wof:placetype":"locality"
},
  "geometry": {"coordinates":[25.61124,-7.38021],"type":"Point"}
}