{
  "type": "Feature",
  "properties": {
    "gn:admin1_code":"18.0",
    "gn:asciiname":"Bakwa-Malombe",
    "gn:country_code":"CD",
    "gn:dem":503,
    "gn:feature_class":"P",
    "gn:feature_code":"PPL",
    "gn:name":"Bakwa-Malombe",
    "gn:population":0,
    "gn:timezone":"Africa/Lubumbashi",
    "iso:country":"CD",
    "wof:name":"Bakwa-Malombe",
    "wof:placetype":"locality"
},
  "geometry": {"coordinates":[21.2906,-5.22519],"type":"Point"}
}