{
  "type": "Feature",
  "properties": {
    "gn:admin1_code":"19.0",
    "gn:asciiname":"Kipalanga-Koto",
    "gn:country_code":"CD",
    "gn:dem":561,
    "gn:feature_class":"P",
    "gn:feature_code":"PPL",
    "gn:name":"Kipalanga-Koto",
    "gn:population":0,
    "gn:timezone":"Africa/Kinshasa",
    "iso:country":"CD",
    "name:und_x_variant":[
        "Koto",
        "Kapalanga",
        "Kipalanga-Koto"
    ],
    "wof:name":"Kipalanga-Koto",
    "wof:placetype":"locality"
},
  "geometry": {"coordinates":[17.44422999999999,-4.429],"type":"Point"}
}