{
  "type": "Feature",
  "properties": {
    "gn:admin1_code":"15.0",
    "gn:asciiname":"Dibanda",
    "gn:country_code":"CD",
    "gn:dem":1042,
    "gn:feature_class":"P",
    "gn:feature_code":"PPL",
    "gn:name":"Dibanda",
    "gn:population":0,
    "gn:timezone":"Africa/Lubumbashi",
    "iso:country":"CD",
    "wof:name":"Dibanda",
    "wof:placetype":"locality"
},
  "geometry": {"coordinates":[25.58333,-8.18333],"type":"Point"}
}