{
  "type": "Feature",
  "properties": {
    "gn:admin1_code":"12.0",
    "gn:asciiname":"Kikuku",
    "gn:country_code":"CD",
    "gn:dem":568,
    "gn:feature_class":"P",
    "gn:feature_code":"PPL",
    "gn:name":"Kikuku",
    "gn:population":0,
    "gn:timezone":"Africa/Lubumbashi",
    "iso:country":"CD",
    "wof:name":"Kikuku",
    "wof:placetype":"locality"
},
  "geometry": {"coordinates":[27.12216,-2.21612],"type":"Point"}
}