{
  "type": "Feature",
  "properties": {
    "gn:admin1_code":"23.0",
    "gn:asciiname":"Kambimbi",
    "gn:country_code":"CD",
    "gn:dem":850,
    "gn:feature_class":"P",
    "gn:feature_code":"PPL",
    "gn:name":"Kambimbi",
    "gn:population":0,
    "gn:timezone":"Africa/Lubumbashi",
    "iso:country":"CD",
    "wof:name":"Kambimbi",
    "wof:placetype":"locality"
},
  "geometry": {"coordinates":[22.63981,-7.28796],"type":"Point"}
}