{
  "type": "Feature",
  "properties": {
    "gn:admin1_code":"18.0",
    "gn:asciiname":"Kabeya-Kapita",
    "gn:country_code":"CD",
    "gn:dem":642,
    "gn:feature_class":"P",
    "gn:feature_code":"PPL",
    "gn:name":"Kabeya-Kapita",
    "gn:population":0,
    "gn:timezone":"Africa/Lubumbashi",
    "iso:country":"CD",
    "wof:name":"Kabeya-Kapita",
    "wof:placetype":"locality"
},
  "geometry": {"coordinates":[21.15884,-5.78582],"type":"Point"}
}