{
  "type": "Feature",
  "properties": {
    "gn:admin1_code":"22.0",
    "gn:asciiname":"Sandefu",
    "gn:country_code":"CD",
    "gn:dem":1057,
    "gn:feature_class":"P",
    "gn:feature_code":"PPL",
    "gn:name":"Sandefu",
    "gn:population":0,
    "gn:timezone":"Africa/Lubumbashi",
    "iso:country":"CD",
    "wof:name":"Sandefu",
    "wof:placetype":"locality"
},
  "geometry": {"coordinates":[23.42137,-10.48699],"type":"Point"}
}