{
  "type": "Feature",
  "properties": {
    "gn:admin1_code":"22.0",
    "gn:asciiname":"Kakwata",
    "gn:country_code":"CD",
    "gn:dem":1063,
    "gn:feature_class":"P",
    "gn:feature_code":"PPL",
    "gn:name":"Kakwata",
    "gn:population":0,
    "gn:timezone":"Africa/Lubumbashi",
    "iso:country":"CD",
    "wof:name":"Kakwata",
    "wof:placetype":"locality"
},
  "geometry": {"coordinates":[23.98919,-9.67731],"type":"Point"}
}