{
  "type": "Feature",
  "properties": {
    "gn:admin1_code":"16.0",
    "gn:asciiname":"Lezomia",
    "gn:country_code":"CD",
    "gn:dem":830,
    "gn:feature_class":"P",
    "gn:feature_code":"PPL",
    "gn:name":"Lezomia",
    "gn:population":0,
    "gn:timezone":"Africa/Lubumbashi",
    "iso:country":"CD",
    "wof:name":"Lezomia",
    "wof:placetype":"locality"
},
  "geometry": {"coordinates":[29.5303,3.32655],"type":"Point"}
}