{
  "type": "Feature",
  "properties": {
    "gn:admin1_code":"24.0",
    "gn:asciiname":"Bunianga Deuxieme",
    "gn:country_code":"CD",
    "gn:dem":446,
    "gn:feature_class":"P",
    "gn:feature_code":"PPL",
    "gn:name":"Bunianga Deuxi\u00e8me",
    "gn:population":0,
    "gn:timezone":"Africa/Kinshasa",
    "iso:country":"CD",
    "name:und_x_variant":[
        "Bunianga Deuxi\u00e8me",
        "Bunianga II"
    ],
    "wof:name":"Bunianga Deuxieme",
    "wof:placetype":"locality"
},
  "geometry": {"coordinates":[20.17783,-3.49451],"type":"Point"}
}