{
  "type": "Feature",
  "properties": {
    "gn:admin1_code":"18.0",
    "gn:asciiname":"Kambinga",
    "gn:country_code":"CD",
    "gn:dem":618,
    "gn:feature_class":"P",
    "gn:feature_code":"PPL",
    "gn:name":"Kambinga",
    "gn:population":0,
    "gn:timezone":"Africa/Lubumbashi",
    "iso:country":"CD",
    "name:und_x_variant":[
        "Kambimbi",
        "Kambinga"
    ],
    "wof:name":"Kambinga",
    "wof:placetype":"locality"
},
  "geometry": {"coordinates":[20.3446,-5.74343],"type":"Point"}
}