{
  "type": "Feature",
  "properties": {
    "gn:admin1_code":"16.0",
    "gn:asciiname":"Balakpulani",
    "gn:country_code":"CD",
    "gn:dem":780,
    "gn:feature_class":"P",
    "gn:feature_code":"PPL",
    "gn:name":"Balakpulani",
    "gn:population":0,
    "gn:timezone":"Africa/Lubumbashi",
    "iso:country":"CD",
    "wof:name":"Balakpulani",
    "wof:placetype":"locality"
},
  "geometry": {"coordinates":[28.79576,4.46122],"type":"Point"}
}