{
  "type": "Feature",
  "properties": {
    "gn:admin1_code":"6.0",
    "gn:asciiname":"Mikamu",
    "gn:country_code":"CD",
    "gn:dem":659,
    "gn:feature_class":"P",
    "gn:feature_code":"PPL",
    "gn:name":"Mikamu",
    "gn:population":0,
    "gn:timezone":"Africa/Kinshasa",
    "iso:country":"CD",
    "wof:name":"Mikamu",
    "wof:placetype":"locality"
},
  "geometry": {"coordinates":[15.83455,-4.04981],"type":"Point"}
}