{
  "type": "Feature",
  "properties": {
    "gn:admin1_code":"12.0",
    "gn:asciiname":"Kitoga",
    "gn:country_code":"CD",
    "gn:dem":2642,
    "gn:feature_class":"P",
    "gn:feature_code":"PPL",
    "gn:name":"Kitoga",
    "gn:population":0,
    "gn:timezone":"Africa/Lubumbashi",
    "iso:country":"CD",
    "wof:name":"Kitoga",
    "wof:placetype":"locality"
},
  "geometry": {"coordinates":[28.84917,-3.15528],"type":"Point"}
}