{
  "type": "Feature",
  "properties": {
    "gn:admin1_code":"23.0",
    "gn:asciiname":"Munene",
    "gn:country_code":"CD",
    "gn:dem":866,
    "gn:feature_class":"P",
    "gn:feature_code":"PPL",
    "gn:name":"Munene",
    "gn:population":0,
    "gn:timezone":"Africa/Lubumbashi",
    "iso:country":"CD",
    "wof:name":"Munene",
    "wof:placetype":"locality"
},
  "geometry": {"coordinates":[23.0541,-6.4538],"type":"Point"}
}