{
  "type": "Feature",
  "properties": {
    "gn:admin1_code":"19.0",
    "gn:asciiname":"Muana-Uta-Kabela-Mafula",
    "gn:country_code":"CD",
    "gn:dem":441,
    "gn:feature_class":"P",
    "gn:feature_code":"PPL",
    "gn:name":"Muana-Uta-Kabela-Mafula",
    "gn:population":0,
    "gn:timezone":"Africa/Luanda",
    "iso:country":"CD",
    "wof:name":"Muana-Uta-Kabela-Mafula",
    "wof:placetype":"locality"
},
  "geometry": {"coordinates":[17.18655,-7.44465],"type":"Point"}
}