{
  "type": "Feature",
  "properties": {
    "gn:admin1_code":"12.0",
    "gn:asciiname":"Lubimbe",
    "gn:country_code":"CD",
    "gn:dem":1258,
    "gn:feature_class":"P",
    "gn:feature_code":"PPL",
    "gn:name":"Lubimbe",
    "gn:population":0,
    "gn:timezone":"Africa/Lubumbashi",
    "iso:country":"CD",
    "wof:name":"Lubimbe",
    "wof:placetype":"locality"
},
  "geometry": {"coordinates":[28.38367,-2.62405],"type":"Point"}
}