{
  "type": "Feature",
  "properties": {
    "gn:admin1_code":"19.0",
    "gn:asciiname":"Bumba Deuxieme",
    "gn:country_code":"CD",
    "gn:dem":510,
    "gn:feature_class":"P",
    "gn:feature_code":"PPL",
    "gn:name":"Bumba Deuxi\u00e8me",
    "gn:population":0,
    "gn:timezone":"Africa/Kinshasa",
    "iso:country":"CD",
    "wof:name":"Bumba Deuxieme",
    "wof:placetype":"locality"
},
  "geometry": {"coordinates":[16.71134,-6.03019],"type":"Point"}
}