{
  "type": "Feature",
  "properties": {
    "gn:admin1_code":"8.0",
    "gn:asciiname":"Yedika",
    "gn:country_code":"CD",
    "gn:dem":97,
    "gn:feature_class":"P",
    "gn:feature_code":"PPL",
    "gn:name":"Yedika",
    "gn:population":0,
    "gn:timezone":"Africa/Kinshasa",
    "iso:country":"CD",
    "wof:name":"Yedika",
    "wof:placetype":"locality"
},
  "geometry": {"coordinates":[12.84895,-5.50383],"type":"Point"}
}