{
  "type": "Feature",
  "properties": {
    "gn:admin1_code":"27.0",
    "gn:asciiname":"Okitanima",
    "gn:country_code":"CD",
    "gn:dem":583,
    "gn:feature_class":"P",
    "gn:feature_code":"PPL",
    "gn:name":"Okitanima",
    "gn:population":0,
    "gn:timezone":"Africa/Lubumbashi",
    "iso:country":"CD",
    "wof:name":"Okitanima",
    "wof:placetype":"locality"
},
  "geometry": {"coordinates":[24.28926,-4.42777],"type":"Point"}
}