{
  "type": "Feature",
  "properties": {
    "gn:admin1_code":"30.0",
    "gn:asciiname":"Bafwakage",
    "gn:country_code":"CD",
    "gn:dem":574,
    "gn:feature_class":"P",
    "gn:feature_code":"PPL",
    "gn:name":"Bafwakage",
    "gn:population":0,
    "gn:timezone":"Africa/Lubumbashi",
    "iso:country":"CD",
    "wof:name":"Bafwakage",
    "wof:placetype":"locality"
},
  "geometry": {"coordinates":[27.10316,1.18952],"type":"Point"}
}