{
  "type": "Feature",
  "properties": {
    "gn:admin1_code":"19.0",
    "gn:asciiname":"Tshipungu",
    "gn:country_code":"CD",
    "gn:dem":960,
    "gn:feature_class":"P",
    "gn:feature_code":"PPL",
    "gn:name":"Tshipungu",
    "gn:population":0,
    "gn:timezone":"Africa/Kinshasa",
    "iso:country":"CD",
    "wof:name":"Tshipungu",
    "wof:placetype":"locality"
},
  "geometry": {"coordinates":[18.68408,-6.92496],"type":"Point"}
}