{
  "type": "Feature",
  "properties": {
    "gn:admin1_code":"19.0",
    "gn:asciiname":"Shamwenze",
    "gn:country_code":"CD",
    "gn:dem":840,
    "gn:feature_class":"P",
    "gn:feature_code":"PPL",
    "gn:name":"Shamwenze",
    "gn:population":0,
    "gn:timezone":"Africa/Kinshasa",
    "iso:country":"CD",
    "wof:name":"Shamwenze",
    "wof:placetype":"locality"
},
  "geometry": {"coordinates":[18.23187,-7.93656],"type":"Point"}
}