{
  "type": "Feature",
  "properties": {
    "gn:admin1_code":"21.0",
    "gn:asciiname":"Muyumba",
    "gn:country_code":"CD",
    "gn:dem":863,
    "gn:feature_class":"P",
    "gn:feature_code":"PPL",
    "gn:name":"Muyumba",
    "gn:population":0,
    "gn:timezone":"Africa/Lubumbashi",
    "iso:country":"CD",
    "name:und_x_variant":[
        "Mugumba",
        "Mayumba",
        "Muyumba"
    ],
    "wof:name":"Muyumba",
    "wof:placetype":"locality"
},
  "geometry": {"coordinates":[24.43613,-6.10685],"type":"Point"}
}