{
  "type": "Feature",
  "properties": {
    "gn:admin1_code":"8.0",
    "gn:asciiname":"Kilembika",
    "gn:country_code":"CD",
    "gn:dem":688,
    "gn:feature_class":"P",
    "gn:feature_code":"PPL",
    "gn:name":"Kilembika",
    "gn:population":0,
    "gn:timezone":"Africa/Kinshasa",
    "iso:country":"CD",
    "wof:name":"Kilembika",
    "wof:placetype":"locality"
},
  "geometry": {"coordinates":[15.27952,-5.62385],"type":"Point"}
}