{
  "type": "Feature",
  "properties": {
    "gn:admin1_code":"16.0",
    "gn:asciiname":"Bagale",
    "gn:country_code":"CD",
    "gn:dem":772,
    "gn:feature_class":"P",
    "gn:feature_code":"PPL",
    "gn:name":"Bagale",
    "gn:population":0,
    "gn:timezone":"Africa/Lubumbashi",
    "iso:country":"CD",
    "wof:name":"Bagale",
    "wof:placetype":"locality"
},
  "geometry": {"coordinates":[29.76788,3.71703],"type":"Point"}
}