{
  "type": "Feature",
  "properties": {
    "gn:admin1_code":"27.0",
    "gn:asciiname":"Bakasanga",
    "gn:country_code":"CD",
    "gn:dem":597,
    "gn:feature_class":"P",
    "gn:feature_code":"PPL",
    "gn:name":"Bakasanga",
    "gn:population":0,
    "gn:timezone":"Africa/Lubumbashi",
    "iso:country":"CD",
    "wof:name":"Bakasanga",
    "wof:placetype":"locality"
},
  "geometry": {"coordinates":[23.25335,-5.1792],"type":"Point"}
}