{
  "type": "Feature",
  "properties": {
    "gn:admin1_code":"24.0",
    "gn:asciiname":"Musekono",
    "gn:country_code":"CD",
    "gn:dem":321,
    "gn:feature_class":"P",
    "gn:feature_code":"PPL",
    "gn:name":"Musekono",
    "gn:population":0,
    "gn:timezone":"Africa/Kinshasa",
    "iso:country":"CD",
    "wof:name":"Musekono",
    "wof:placetype":"locality"
},
  "geometry": {"coordinates":[17.41878,-2.51991],"type":"Point"}
}