{
  "type": "Feature",
  "properties": {
    "gn:admin1_code":"18.0",
    "gn:asciiname":"Shamusanda",
    "gn:country_code":"CD",
    "gn:dem":569,
    "gn:feature_class":"P",
    "gn:feature_code":"PPL",
    "gn:name":"Shamusanda",
    "gn:population":0,
    "gn:timezone":"Africa/Lubumbashi",
    "iso:country":"CD",
    "wof:name":"Shamusanda",
    "wof:placetype":"locality"
},
  "geometry": {"coordinates":[20.80326,-6.50814],"type":"Point"}
}