{
  "type": "Feature",
  "properties": {
    "gn:admin1_code":"10.0",
    "gn:asciiname":"Kingombe-Musese",
    "gn:country_code":"CD",
    "gn:dem":567,
    "gn:feature_class":"P",
    "gn:feature_code":"PPL",
    "gn:name":"Kingombe-Musese",
    "gn:population":0,
    "gn:timezone":"Africa/Lubumbashi",
    "iso:country":"CD",
    "wof:name":"Kingombe-Musese",
    "wof:placetype":"locality"
},
  "geometry": {"coordinates":[26.33975,-3.55327],"type":"Point"}
}