{
  "type": "Feature",
  "properties": {
    "gn:admin1_code":"24.0",
    "gn:asciiname":"Ishwa",
    "gn:country_code":"CD",
    "gn:dem":365,
    "gn:feature_class":"P",
    "gn:feature_code":"PPL",
    "gn:name":"Ishwa",
    "gn:population":0,
    "gn:timezone":"Africa/Kinshasa",
    "iso:country":"CD",
    "name:ara_x_preferred":[
        "\u0625\u0634\u0648\u0639"
    ],
    "name:heb_x_preferred":[
        "\u05d0\u05d9\u05e9\u05d5\u05e2"
    ],
    "name:pol_x_preferred":[
        "Iszwa"
    ],
    "wof:name":"Ishwa",
    "wof:placetype":"locality"
},
  "geometry": {"coordinates":[17.80869,-3.23956],"type":"Point"}
}