{
  "type": "Feature",
  "properties": {
    "gn:admin1_code":"25.0",
    "gn:asciiname":"Busu-Dengasia",
    "gn:country_code":"CD",
    "gn:dem":342,
    "gn:feature_class":"P",
    "gn:feature_code":"PPL",
    "gn:name":"Busu-Dengasia",
    "gn:population":0,
    "gn:timezone":"Africa/Kinshasa",
    "iso:country":"CD",
    "wof:name":"Busu-Dengasia",
    "wof:placetype":"locality"
},
  "geometry": {"coordinates":[20.27742000000001,2.12383],"type":"Point"}
}