{
  "type": "Feature",
  "properties": {
    "gn:admin1_code":"18.0",
    "gn:asciiname":"Tshiluata",
    "gn:country_code":"CD",
    "gn:dem":615,
    "gn:feature_class":"P",
    "gn:feature_code":"PPL",
    "gn:name":"Tshiluata",
    "gn:population":0,
    "gn:timezone":"Africa/Lubumbashi",
    "iso:country":"CD",
    "wof:name":"Tshiluata",
    "wof:placetype":"locality"
},
  "geometry": {"coordinates":[20.75903,-5.92576],"type":"Point"}
}