{
  "type": "Feature",
  "properties": {
    "gn:admin1_code":"15.0",
    "gn:asciiname":"Kayambi",
    "gn:country_code":"CD",
    "gn:dem":760,
    "gn:feature_class":"P",
    "gn:feature_code":"PPL",
    "gn:name":"Kayambi",
    "gn:population":0,
    "gn:timezone":"Africa/Lubumbashi",
    "iso:country":"CD",
    "wof:name":"Kayambi",
    "wof:placetype":"locality"
},
  "geometry": {"coordinates":[26.11555,-7.38362],"type":"Point"}
}