{
  "type": "Feature",
  "properties": {
    "gn:admin1_code":"24.0",
    "gn:asciiname":"Kutu-Moke",
    "gn:country_code":"CD",
    "gn:dem":296,
    "gn:feature_class":"P",
    "gn:feature_code":"PPL",
    "gn:name":"Kutu-Moke",
    "gn:population":0,
    "gn:timezone":"Africa/Kinshasa",
    "iso:country":"CD",
    "wof:name":"Kutu-Moke",
    "wof:placetype":"locality"
},
  "geometry": {"coordinates":[17.34312000000001,-3.20233],"type":"Point"}
}