{
  "type": "Feature",
  "properties": {
    "gn:admin1_code":"17.0",
    "gn:asciiname":"Odumini",
    "gn:country_code":"CD",
    "gn:dem":1257,
    "gn:feature_class":"P",
    "gn:feature_code":"PPL",
    "gn:name":"Odumini",
    "gn:population":0,
    "gn:timezone":"Africa/Lubumbashi",
    "iso:country":"CD",
    "wof:name":"Odumini",
    "wof:placetype":"locality"
},
  "geometry": {"coordinates":[30.9243,3.4108],"type":"Point"}
}