{
  "type": "Feature",
  "properties": {
    "gn:admin1_code":"13.0",
    "gn:asciiname":"Engegusie",
    "gn:country_code":"CD",
    "gn:dem":714,
    "gn:feature_class":"P",
    "gn:feature_code":"PPL",
    "gn:name":"Engegusie",
    "gn:population":0,
    "gn:timezone":"Africa/Lubumbashi",
    "iso:country":"CD",
    "wof:name":"Engegusie",
    "wof:placetype":"locality"
},
  "geometry": {"coordinates":[27.38445,2.7989],"type":"Point"}
}