{
  "type": "Feature",
  "properties": {
    "gn:admin1_code":"29.0",
    "gn:asciiname":"Kabimba",
    "gn:country_code":"CD",
    "gn:dem":808,
    "gn:feature_class":"P",
    "gn:feature_code":"PPL",
    "gn:name":"Kabimba",
    "gn:population":0,
    "gn:timezone":"Africa/Lubumbashi",
    "iso:country":"CD",
    "wof:name":"Kabimba",
    "wof:placetype":"locality"
},
  "geometry": {"coordinates":[29.34375,-5.56348],"type":"Point"}
}