{
  "type": "Feature",
  "properties": {
    "gn:admin1_code":"22.0",
    "gn:asciiname":"Tshibwete",
    "gn:country_code":"CD",
    "gn:dem":1080,
    "gn:feature_class":"P",
    "gn:feature_code":"PPL",
    "gn:name":"Tshibwete",
    "gn:population":0,
    "gn:timezone":"Africa/Lubumbashi",
    "iso:country":"CD",
    "wof:name":"Tshibwete",
    "wof:placetype":"locality"
},
  "geometry": {"coordinates":[21.87178,-9.49946],"type":"Point"}
}