{
  "type": "Feature",
  "properties": {
    "gn:admin1_code":"19.0",
    "gn:asciiname":"Swa-Ngoye",
    "gn:country_code":"CD",
    "gn:dem":485,
    "gn:feature_class":"P",
    "gn:feature_code":"PPL",
    "gn:name":"Swa-Ngoye",
    "gn:population":0,
    "gn:timezone":"Africa/Kinshasa",
    "iso:country":"CD",
    "wof:name":"Swa-Ngoye",
    "wof:placetype":"locality"
},
  "geometry": {"coordinates":[17.48048,-5.10973],"type":"Point"}
}