{
  "type": "Feature",
  "properties": {
    "gn:admin1_code":"14.0",
    "gn:asciiname":"Kapiri",
    "gn:country_code":"CD",
    "gn:dem":878,
    "gn:feature_class":"P",
    "gn:feature_code":"PPL",
    "gn:name":"Kapiri",
    "gn:population":0,
    "gn:timezone":"Africa/Lubumbashi",
    "iso:country":"CD",
    "wof:name":"Kapiri",
    "wof:placetype":"locality"
},
  "geometry": {"coordinates":[27.22207,-9.69661],"type":"Point"}
}