{
  "type": "Feature",
  "properties": {
    "gn:admin1_code":"2.0",
    "gn:asciiname":"Bokuku",
    "gn:country_code":"CD",
    "gn:dem":333,
    "gn:feature_class":"P",
    "gn:feature_code":"PPL",
    "gn:name":"Bokuku",
    "gn:population":0,
    "gn:timezone":"Africa/Kinshasa",
    "iso:country":"CD",
    "wof:name":"Bokuku",
    "wof:placetype":"locality"
},
  "geometry": {"coordinates":[19.48868,-0.28951],"type":"Point"}
}