{
  "type": "Feature",
  "properties": {
    "gn:admin1_code":"8.0",
    "gn:asciiname":"Inkisi",
    "gn:country_code":"CD",
    "gn:dem":516,
    "gn:feature_class":"P",
    "gn:feature_code":"PPL",
    "gn:name":"Inkisi",
    "gn:population":0,
    "gn:timezone":"Africa/Kinshasa",
    "iso:country":"CD",
    "name:ceb_x_preferred":[
        "Inkisi"
    ],
    "wof:name":"Inkisi",
    "wof:placetype":"locality"
},
  "geometry": {"coordinates":[15.0541,-5.13122],"type":"Point"}
}