{
  "type": "Feature",
  "properties": {
    "gn:admin1_code":"8.0",
    "gn:asciiname":"Inkisi",
    "gn:country_code":"CD",
    "gn:dem":516,
    "gn:feature_class":"P",
    "gn:feature_code":"PPL",
    "gn:name":"Inkisi",
    "gn:population":0,
    "gn:timezone":"Africa/Kinshasa",
    "iso:country":"CD",
    "name:ara_x_preferred":[
        "\u0625\u0646\u0643\u064a\u0633\u064a"
    ],
    "name:ben_x_preferred":[
        "\u0987\u09a8\u0995\u09bf\u09b8\u09bf"
    ],
    "name:ceb_x_preferred":[
        "Inkisi"
    ],
    "name:deu_x_preferred":[
        "Inkisi"
    ],
    "name:ell_x_preferred":[
        "\u0399\u03bd\u03ba\u03af\u03c3\u03b9"
    ],
    "name:fas_x_preferred":[
        "\u0627\u06cc\u0646\u06a9\u06cc\u0633\u06cc"
    ],
    "name:fra_x_preferred":[
        "Inkisi River"
    ],
    "name:heb_x_preferred":[
        "\u05d0\u05d9\u05e0\u05e7\u05d9\u05e1\u05d9"
    ],
    "name:hin_x_preferred":[
        "\u0907\u0902\u0915\u093f\u0938\u093f"
    ],
    "name:hun_x_preferred":[
        "Inkisi"
    ],
    "name:ind_x_preferred":[
        "Inkisi"
    ],
    "name:ita_x_preferred":[
        "Inkisi"
    ],
    "name:jpn_x_preferred":[
        "\u30a4\u30f3\u30ad\u30b7\u5ddd"
    ],
    "name:kor_x_preferred":[
        "\uc778\uae30\uc2dc"
    ],
    "name:nld_x_preferred":[
        "Inkisi"
    ],
    "name:pol_x_preferred":[
        "Inkisi"
    ],
    "name:por_x_preferred":[
        "Inkisi"
    ],
    "name:rus_x_preferred":[
        "\u0440\u0435\u043a\u0430 \u0418\u043d\u043a\u0438\u0441\u0438"
    ],
    "name:spa_x_preferred":[
        "Inkisi"
    ],
    "name:swe_x_preferred":[
        "Inkisi"
    ],
    "name:tur_x_preferred":[
        "Inkisi"
    ],
    "name:ukr_x_preferred":[
        "\u0406\u043d\u043a\u0456\u0441\u0456"
    ],
    "name:urd_x_preferred":[
        "\u0627\u0646\u06a9\u0633\u06cc"
    ],
    "name:vie_x_preferred":[
        "S\u00f4ng Inkisi"
    ],
    "name:zho_cn_x_preferred":[
        "\u56e0\u57fa\u897f\u6cb3"
    ],
    "name:zho_tw_x_preferred":[
        "\u5370\u57fa\u897f\u6cb3"
    ],
    "wof:name":"Inkisi",
    "wof:placetype":"locality"
},
  "geometry": {"coordinates":[15.0541,-5.13122],"type":"Point"}
}