{
  "type": "Feature",
  "properties": {
    "gn:admin1_code":"25.0",
    "gn:asciiname":"Boso-Modjebo",
    "gn:country_code":"CD",
    "gn:dem":374,
    "gn:feature_class":"P",
    "gn:feature_code":"PPL",
    "gn:name":"Boso-Modjebo",
    "gn:population":0,
    "gn:timezone":"Africa/Kinshasa",
    "iso:country":"CD",
    "wof:name":"Boso-Modjebo",
    "wof:placetype":"locality"
},
  "geometry": {"coordinates":[20.77942,3.08746],"type":"Point"}
}