{
  "type": "Feature",
  "properties": {
    "gn:admin1_code":"19.0",
    "gn:asciiname":"Shatamwe",
    "gn:country_code":"CD",
    "gn:dem":1046,
    "gn:feature_class":"P",
    "gn:feature_code":"PPL",
    "gn:name":"Shatamwe",
    "gn:population":0,
    "gn:timezone":"Africa/Kinshasa",
    "iso:country":"CD",
    "wof:name":"Shatamwe",
    "wof:placetype":"locality"
},
  "geometry": {"coordinates":[19.03276,-7.35623],"type":"Point"}
}