{
  "type": "Feature",
  "properties": {
    "gn:admin1_code":"8.0",
    "gn:asciiname":"Sanga-Pe",
    "gn:country_code":"CD",
    "gn:dem":756,
    "gn:feature_class":"P",
    "gn:feature_code":"PPL",
    "gn:name":"Sanga-Pe",
    "gn:population":0,
    "gn:timezone":"Africa/Kinshasa",
    "iso:country":"CD",
    "wof:name":"Sanga-Pe",
    "wof:placetype":"locality"
},
  "geometry": {"coordinates":[15.32495,-5.83221],"type":"Point"}
}