{
  "type": "Feature",
  "properties": {
    "gn:admin1_code":"30.0",
    "gn:asciiname":"Obomongo",
    "gn:country_code":"CD",
    "gn:dem":688,
    "gn:feature_class":"P",
    "gn:feature_code":"PPL",
    "gn:name":"Obomongo",
    "gn:population":0,
    "gn:timezone":"Africa/Lubumbashi",
    "iso:country":"CD",
    "wof:name":"Obomongo",
    "wof:placetype":"locality"
},
  "geometry": {"coordinates":[27.5358,0.12691],"type":"Point"}
}