{
  "type": "Feature",
  "properties": {
    "gn:admin1_code":"24.0",
    "gn:asciiname":"Mpe",
    "gn:country_code":"CD",
    "gn:dem":313,
    "gn:feature_class":"P",
    "gn:feature_code":"PPL",
    "gn:name":"Mpe",
    "gn:population":0,
    "gn:timezone":"Africa/Kinshasa",
    "iso:country":"CD",
    "wof:name":"Mpe",
    "wof:placetype":"locality"
},
  "geometry": {"coordinates":[17.65899,-2.19546],"type":"Point"}
}