{
  "type": "Feature",
  "properties": {
    "gn:admin1_code":"22.0",
    "gn:asciiname":"Tshibuma",
    "gn:country_code":"CD",
    "gn:dem":983,
    "gn:feature_class":"P",
    "gn:feature_code":"PPL",
    "gn:name":"Tshibuma",
    "gn:population":0,
    "gn:timezone":"Africa/Lubumbashi",
    "iso:country":"CD",
    "wof:name":"Tshibuma",
    "wof:placetype":"locality"
},
  "geometry": {"coordinates":[22.40552000000001,-8.27674],"type":"Point"}
}