{
  "type": "Feature",
  "properties": {
    "gn:admin1_code":"16.0",
    "gn:asciiname":"Nava",
    "gn:country_code":"CD",
    "gn:dem":714,
    "gn:feature_class":"P",
    "gn:feature_code":"PPL",
    "gn:name":"Nava",
    "gn:population":0,
    "gn:timezone":"Africa/Lubumbashi",
    "iso:country":"CD",
    "name:arg_x_preferred":[
        "Nava"
    ],
    "name:ast_x_preferred":[
        "Nava"
    ],
    "name:ceb_x_preferred":[
        "Nava"
    ],
    "name:deu_x_preferred":[
        "Nava"
    ],
    "name:epo_x_preferred":[
        "Nava"
    ],
    "name:est_x_preferred":[
        "Nava"
    ],
    "name:fra_x_preferred":[
        "Nava"
    ],
    "name:ita_x_preferred":[
        "Nava"
    ],
    "name:lmo_x_preferred":[
        "Nava"
    ],
    "name:ron_x_preferred":[
        "Nav\u0103"
    ],
    "name:spa_x_preferred":[
        "Nava"
    ],
    "name:srp_x_preferred":[
        "\u041d\u0430\u0432\u0430"
    ],
    "name:swe_x_preferred":[
        "Nava"
    ],
    "name:vol_x_preferred":[
        "Nava"
    ],
    "wof:name":"Nava",
    "wof:placetype":"locality"
},
  "geometry": {"coordinates":[27.3006,2.42546],"type":"Point"}
}