{
  "type": "Feature",
  "properties": {
    "gn:admin1_code":"29.0",
    "gn:asciiname":"Koka",
    "gn:country_code":"CD",
    "gn:dem":714,
    "gn:feature_class":"P",
    "gn:feature_code":"PPL",
    "gn:name":"Koka",
    "gn:population":0,
    "gn:timezone":"Africa/Lubumbashi",
    "iso:country":"CD",
    "wof:name":"Koka",
    "wof:placetype":"locality"
},
  "geometry": {"coordinates":[26.3288,-6.36081],"type":"Point"}
}