{
  "type": "Feature",
  "properties": {
    "gn:admin1_code":"16.0",
    "gn:asciiname":"Bamungu",
    "gn:country_code":"CD",
    "gn:dem":816,
    "gn:feature_class":"P",
    "gn:feature_code":"PPL",
    "gn:name":"Bamungu",
    "gn:population":0,
    "gn:timezone":"Africa/Lubumbashi",
    "iso:country":"CD",
    "wof:name":"Bamungu",
    "wof:placetype":"locality"
},
  "geometry": {"coordinates":[28.6017,2.83856],"type":"Point"}
}