{
  "type": "Feature",
  "properties": {
    "gn:admin1_code":"2.0",
    "gn:asciiname":"Boso-Eboma",
    "gn:country_code":"CD",
    "gn:dem":375,
    "gn:feature_class":"P",
    "gn:feature_code":"PPL",
    "gn:name":"Boso-Eboma",
    "gn:population":0,
    "gn:timezone":"Africa/Kinshasa",
    "iso:country":"CD",
    "wof:name":"Boso-Eboma",
    "wof:placetype":"locality"
},
  "geometry": {"coordinates":[20.15994,1.26146],"type":"Point"}
}