{
  "type": "Feature",
  "properties": {
    "gn:admin1_code":"2.0",
    "gn:asciiname":"Baazinga",
    "gn:country_code":"CD",
    "gn:dem":331,
    "gn:feature_class":"P",
    "gn:feature_code":"PPL",
    "gn:name":"Baazinga",
    "gn:population":0,
    "gn:timezone":"Africa/Kinshasa",
    "iso:country":"CD",
    "name:fra_x_preferred":[
        "Baazinga"
    ],
    "wof:name":"Baazinga",
    "wof:placetype":"locality"
},
  "geometry": {"coordinates":[19.08038,2.0685],"type":"Point"}
}