{
  "type": "Feature",
  "properties": {
    "gn:admin1_code":"8.0",
    "gn:asciiname":"Kianika",
    "gn:country_code":"CD",
    "gn:dem":598,
    "gn:feature_class":"P",
    "gn:feature_code":"PPL",
    "gn:name":"Kianika",
    "gn:population":0,
    "gn:timezone":"Africa/Kinshasa",
    "iso:country":"CD",
    "wof:name":"Kianika",
    "wof:placetype":"locality"
},
  "geometry": {"coordinates":[15.50162,-5.37375],"type":"Point"}
}