{
  "type": "Feature",
  "properties": {
    "gn:admin1_code":"8.0",
    "gn:asciiname":"Bembele",
    "gn:country_code":"CD",
    "gn:dem":619,
    "gn:feature_class":"P",
    "gn:feature_code":"PPL",
    "gn:name":"Bembele",
    "gn:population":0,
    "gn:timezone":"Africa/Kinshasa",
    "iso:country":"CD",
    "wof:name":"Bembele",
    "wof:placetype":"locality"
},
  "geometry": {"coordinates":[16.04208,-5.83489],"type":"Point"}
}