{
  "type": "Feature",
  "properties": {
    "gn:admin1_code":"8.0",
    "gn:asciiname":"Kilempo",
    "gn:country_code":"CD",
    "gn:dem":508,
    "gn:feature_class":"P",
    "gn:feature_code":"PPL",
    "gn:name":"Kilempo",
    "gn:population":0,
    "gn:timezone":"Africa/Kinshasa",
    "iso:country":"CD",
    "wof:name":"Kilempo",
    "wof:placetype":"locality"
},
  "geometry": {"coordinates":[15.16404,-4.69878],"type":"Point"}
}