{
  "type": "Feature",
  "properties": {
    "gn:admin1_code":"11.0",
    "gn:asciiname":"Rumangabo",
    "gn:country_code":"CD",
    "gn:dem":1552,
    "gn:feature_class":"P",
    "gn:feature_code":"PPL",
    "gn:name":"Rumangabo",
    "gn:population":0,
    "gn:timezone":"Africa/Lubumbashi",
    "iso:country":"CD",
    "name:und_x_variant":[
        "Rumengabo",
        "Ramangabo",
        "Rumangabo"
    ],
    "wof:name":"Rumangabo",
    "wof:placetype":"locality"
},
  "geometry": {"coordinates":[29.36906,-1.35766],"type":"Point"}
}