{
  "type": "Feature",
  "properties": {
    "gn:admin1_code":"15.0",
    "gn:asciiname":"Kale",
    "gn:country_code":"CD",
    "gn:dem":853,
    "gn:feature_class":"P",
    "gn:feature_code":"PPL",
    "gn:name":"Kale",
    "gn:population":0,
    "gn:timezone":"Africa/Lubumbashi",
    "iso:country":"CD",
    "wof:name":"Kale",
    "wof:placetype":"locality"
},
  "geometry": {"coordinates":[25.41667,-9.48333],"type":"Point"}
}