{
  "type": "Feature",
  "properties": {
    "gn:admin1_code":"8.0",
    "gn:asciiname":"Kimpungi",
    "gn:country_code":"CD",
    "gn:dem":670,
    "gn:feature_class":"P",
    "gn:feature_code":"PPL",
    "gn:name":"Kimpungi",
    "gn:population":0,
    "gn:timezone":"Africa/Kinshasa",
    "iso:country":"CD",
    "wof:name":"Kimpungi",
    "wof:placetype":"locality"
},
  "geometry": {"coordinates":[15.34123,-5.46316],"type":"Point"}
}