{
  "type": "Feature",
  "properties": {
    "gn:admin1_code":"22.0",
    "gn:asciiname":"Kazembe",
    "gn:country_code":"CD",
    "gn:dem":926,
    "gn:feature_class":"P",
    "gn:feature_code":"PPL",
    "gn:name":"Kazembe",
    "gn:population":0,
    "gn:timezone":"Africa/Lubumbashi",
    "iso:country":"CD",
    "name:cat_x_preferred":[
        "Kazembe"
    ],
    "name:ind_x_preferred":[
        "Kerajaan Kazembe"
    ],
    "name:lit_x_preferred":[
        "Kazemb\u0117"
    ],
    "wof:name":"Kazembe",
    "wof:placetype":"locality"
},
  "geometry": {"coordinates":[22.60586,-8.44355],"type":"Point"}
}