{
  "type": "Feature",
  "properties": {
    "gn:admin1_code":"23.0",
    "gn:asciiname":"Tshibala",
    "gn:country_code":"CD",
    "gn:dem":839,
    "gn:feature_class":"P",
    "gn:feature_code":"PPL",
    "gn:name":"Tshibala",
    "gn:population":0,
    "gn:timezone":"Africa/Lubumbashi",
    "iso:country":"CD",
    "wof:name":"Tshibala",
    "wof:placetype":"locality"
},
  "geometry": {"coordinates":[22.12768,-6.92004],"type":"Point"}
}