{
  "type": "Feature",
  "properties": {
    "gn:admin1_code":"19.0",
    "gn:asciiname":"Shasikua",
    "gn:country_code":"CD",
    "gn:dem":1083,
    "gn:feature_class":"P",
    "gn:feature_code":"PPL",
    "gn:name":"Shasikua",
    "gn:population":0,
    "gn:timezone":"Africa/Kinshasa",
    "iso:country":"CD",
    "wof:name":"Shasikua",
    "wof:placetype":"locality"
},
  "geometry": {"coordinates":[18.67004,-7.38527],"type":"Point"}
}