{
  "type": "Feature",
  "properties": {
    "gn:admin1_code":"19.0",
    "gn:asciiname":"Bumanima",
    "gn:country_code":"CD",
    "gn:dem":519,
    "gn:feature_class":"P",
    "gn:feature_code":"PPL",
    "gn:name":"Bumanima",
    "gn:population":0,
    "gn:timezone":"Africa/Kinshasa",
    "iso:country":"CD",
    "wof:name":"Bumanima",
    "wof:placetype":"locality"
},
  "geometry": {"coordinates":[17.22149,-4.48793],"type":"Point"}
}