{
  "type": "Feature",
  "properties": {
    "gn:admin1_code":"11.0",
    "gn:asciiname":"Miriki",
    "gn:country_code":"CD",
    "gn:dem":1582,
    "gn:feature_class":"P",
    "gn:feature_code":"PPL",
    "gn:name":"Miriki",
    "gn:population":0,
    "gn:timezone":"Africa/Lubumbashi",
    "iso:country":"CD",
    "name:und_x_variant":[
        "Miliki"
    ],
    "wof:name":"Miriki",
    "wof:placetype":"locality"
},
  "geometry": {"coordinates":[29.05451,-0.71215],"type":"Point"}
}