{
  "type": "Feature",
  "properties": {
    "gn:admin1_code":"21.0",
    "gn:asciiname":"Bashingile",
    "gn:country_code":"CD",
    "gn:dem":872,
    "gn:feature_class":"P",
    "gn:feature_code":"PPL",
    "gn:name":"Bashingile",
    "gn:population":0,
    "gn:timezone":"Africa/Lubumbashi",
    "iso:country":"CD",
    "wof:name":"Bashingile",
    "wof:placetype":"locality"
},
  "geometry": {"coordinates":[24.30668,-6.0162],"type":"Point"}
}