{
  "type": "Feature",
  "properties": {
    "gn:admin1_code":"18.0",
    "gn:asciiname":"Bandesha-Pumbu",
    "gn:country_code":"CD",
    "gn:dem":717,
    "gn:feature_class":"P",
    "gn:feature_code":"PPL",
    "gn:name":"Bandesha-Pumbu",
    "gn:population":0,
    "gn:timezone":"Africa/Lubumbashi",
    "iso:country":"CD",
    "wof:name":"Bandesha-Pumbu",
    "wof:placetype":"locality"
},
  "geometry": {"coordinates":[21.61614,-6.58678],"type":"Point"}
}