{
  "type": "Feature",
  "properties": {
    "gn:admin1_code":"11.0",
    "gn:asciiname":"Bishusha",
    "gn:country_code":"CD",
    "gn:dem":1906,
    "gn:feature_class":"P",
    "gn:feature_code":"PPL",
    "gn:name":"Bishusha",
    "gn:population":0,
    "gn:timezone":"Africa/Lubumbashi",
    "iso:country":"CD",
    "wof:name":"Bishusha",
    "wof:placetype":"locality"
},
  "geometry": {"coordinates":[29.11894,-1.27726],"type":"Point"}
}