{
  "type": "Feature",
  "properties": {
    "gn:admin1_code":"19.0",
    "gn:asciiname":"Mokesi",
    "gn:country_code":"CD",
    "gn:dem":857,
    "gn:feature_class":"P",
    "gn:feature_code":"PPL",
    "gn:name":"Mokesi",
    "gn:population":0,
    "gn:timezone":"Africa/Kinshasa",
    "iso:country":"CD",
    "wof:name":"Mokesi",
    "wof:placetype":"locality"
},
  "geometry": {"coordinates":[17.53548,-6.30043],"type":"Point"}
}