{
  "type": "Feature",
  "properties": {
    "gn:admin1_code":"14.0",
    "gn:asciiname":"Kilenge",
    "gn:country_code":"CD",
    "gn:dem":979,
    "gn:feature_class":"P",
    "gn:feature_code":"PPL",
    "gn:name":"Kilenge",
    "gn:population":0,
    "gn:timezone":"Africa/Lubumbashi",
    "iso:country":"CD",
    "wof:name":"Kilenge",
    "wof:placetype":"locality"
},
  "geometry": {"coordinates":[27.48012,-9.10892],"type":"Point"}
}