{
  "type": "Feature",
  "properties": {
    "gn:admin1_code":"17.0",
    "gn:asciiname":"Berunda",
    "gn:country_code":"CD",
    "gn:dem":1406,
    "gn:feature_class":"P",
    "gn:feature_code":"PPL",
    "gn:name":"Berunda",
    "gn:population":0,
    "gn:timezone":"Africa/Lubumbashi",
    "iso:country":"CD",
    "wof:name":"Berunda",
    "wof:placetype":"locality"
},
  "geometry": {"coordinates":[30.29875,2.33605],"type":"Point"}
}