{
  "type": "Feature",
  "properties": {
    "gn:admin1_code":"22.0",
    "gn:asciiname":"Tshikinda",
    "gn:country_code":"CD",
    "gn:dem":987,
    "gn:feature_class":"P",
    "gn:feature_code":"PPL",
    "gn:name":"Tshikinda",
    "gn:population":0,
    "gn:timezone":"Africa/Lubumbashi",
    "iso:country":"CD",
    "wof:name":"Tshikinda",
    "wof:placetype":"locality"
},
  "geometry": {"coordinates":[22.64232,-9.44703],"type":"Point"}
}