{
  "type": "Feature",
  "properties": {
    "gn:admin1_code":"13.0",
    "gn:asciiname":"Abula",
    "gn:country_code":"CD",
    "gn:dem":632,
    "gn:feature_class":"P",
    "gn:feature_code":"PPL",
    "gn:name":"Abula",
    "gn:population":0,
    "gn:timezone":"Africa/Lubumbashi",
    "iso:country":"CD",
    "name:ara_x_preferred":[
        "\u0623\u0628\u0648\u0644\u0627"
    ],
    "name:deu_x_preferred":[
        "Abula"
    ],
    "name:est_x_preferred":[
        "Abula"
    ],
    "name:fas_x_preferred":[
        "\u0627\u0628\u0648\u0644\u0627"
    ],
    "name:hye_x_preferred":[
        "\u0531\u0562\u0578\u0582\u056c\u0561"
    ],
    "name:pol_x_preferred":[
        "Abula"
    ],
    "name:spa_x_preferred":[
        "Abula"
    ],
    "name:vol_x_preferred":[
        "Abula"
    ],
    "wof:name":"Abula",
    "wof:placetype":"locality"
},
  "geometry": {"coordinates":[25.96195,3.51279],"type":"Point"}
}