{
  "type": "Feature",
  "properties": {
    "gn:admin1_code":"20.0",
    "gn:asciiname":"Musuri",
    "gn:country_code":"CD",
    "gn:dem":545,
    "gn:feature_class":"P",
    "gn:feature_code":"PPL",
    "gn:name":"Musuri",
    "gn:population":0,
    "gn:timezone":"Africa/Kinshasa",
    "iso:country":"CD",
    "name:ind_x_preferred":[
        "Musuri"
    ],
    "name:kor_x_preferred":[
        "\ubb34\uc218\ub9ac"
    ],
    "wof:name":"Musuri",
    "wof:placetype":"locality"
},
  "geometry": {"coordinates":[17.81569,-4.75078],"type":"Point"}
}