{
  "type": "Feature",
  "properties": {
    "gn:admin1_code":"8.0",
    "gn:asciiname":"Pioka",
    "gn:country_code":"CD",
    "gn:dem":192,
    "gn:feature_class":"P",
    "gn:feature_code":"PPL",
    "gn:name":"Pioka",
    "gn:population":0,
    "gn:timezone":"Africa/Kinshasa",
    "iso:country":"CD",
    "wof:name":"Pioka",
    "wof:placetype":"locality"
},
  "geometry": {"coordinates":[14.40082,-4.89347],"type":"Point"}
}