{
  "type": "Feature",
  "properties": {
    "gn:admin1_code":"18.0",
    "gn:asciiname":"Kandu",
    "gn:country_code":"CD",
    "gn:dem":593,
    "gn:feature_class":"P",
    "gn:feature_code":"PPL",
    "gn:name":"Kandu",
    "gn:population":0,
    "gn:timezone":"Africa/Lubumbashi",
    "iso:country":"CD",
    "wof:name":"Kandu",
    "wof:placetype":"locality"
},
  "geometry": {"coordinates":[20.93803,-6.34948],"type":"Point"}
}