{
  "type": "Feature",
  "properties": {
    "gn:admin1_code":"28.0",
    "gn:asciiname":"Yakodu",
    "gn:country_code":"CD",
    "gn:dem":372,
    "gn:feature_class":"P",
    "gn:feature_code":"PPL",
    "gn:name":"Yakodu",
    "gn:population":0,
    "gn:timezone":"Africa/Kinshasa",
    "iso:country":"CD",
    "wof:name":"Yakodu",
    "wof:placetype":"locality"
},
  "geometry": {"coordinates":[18.69959,3.59099],"type":"Point"}
}