{
  "type": "Feature",
  "properties": {
    "gn:admin1_code":"24.0",
    "gn:asciiname":"Epokenkoso",
    "gn:country_code":"CD",
    "gn:dem":386,
    "gn:feature_class":"P",
    "gn:feature_code":"PPL",
    "gn:name":"Epokenkoso",
    "gn:population":0,
    "gn:timezone":"Africa/Kinshasa",
    "iso:country":"CD",
    "name:und_x_variant":[
        "Epokenkaso",
        "Epokenkoso"
    ],
    "wof:name":"Epokenkoso",
    "wof:placetype":"locality"
},
  "geometry": {"coordinates":[16.88172999999999,-2.28094],"type":"Point"}
}