{
  "type": "Feature",
  "properties": {
    "gn:admin1_code":"25.0",
    "gn:asciiname":"Bongabola",
    "gn:country_code":"CD",
    "gn:dem":414,
    "gn:feature_class":"P",
    "gn:feature_code":"PPL",
    "gn:name":"Bongabola",
    "gn:population":0,
    "gn:timezone":"Africa/Kinshasa",
    "iso:country":"CD",
    "wof:name":"Bongabola",
    "wof:placetype":"locality"
},
  "geometry": {"coordinates":[21.3562,2.94551],"type":"Point"}
}