{
  "type": "Feature",
  "properties": {
    "gn:admin1_code":"28.0",
    "gn:asciiname":"Boyaswe",
    "gn:country_code":"CD",
    "gn:dem":378,
    "gn:feature_class":"P",
    "gn:feature_code":"PPL",
    "gn:name":"Boyaswe",
    "gn:population":0,
    "gn:timezone":"Africa/Kinshasa",
    "iso:country":"CD",
    "wof:name":"Boyaswe",
    "wof:placetype":"locality"
},
  "geometry": {"coordinates":[20.14841,2.98532],"type":"Point"}
}