{
  "type": "Feature",
  "properties": {
    "gn:admin1_code":"17.0",
    "gn:asciiname":"Adumbi",
    "gn:country_code":"CD",
    "gn:dem":663,
    "gn:feature_class":"P",
    "gn:feature_code":"PPL",
    "gn:name":"Adumbi",
    "gn:population":0,
    "gn:timezone":"Africa/Lubumbashi",
    "iso:country":"CD",
    "wof:name":"Adumbi",
    "wof:placetype":"locality"
},
  "geometry": {"coordinates":[27.84599,1.73172],"type":"Point"}
}