{
  "type": "Feature",
  "properties": {
    "gn:admin1_code":"19.0",
    "gn:asciiname":"Kitondo",
    "gn:country_code":"CD",
    "gn:dem":850,
    "gn:feature_class":"P",
    "gn:feature_code":"PPL",
    "gn:name":"Kitondo",
    "gn:population":0,
    "gn:timezone":"Africa/Kinshasa",
    "iso:country":"CD",
    "wof:name":"Kitondo",
    "wof:placetype":"locality"
},
  "geometry": {"coordinates":[19.0454,-6.62715],"type":"Point"}
}