{
  "type": "Feature",
  "properties": {
    "gn:admin1_code":"17.0",
    "gn:asciiname":"Abika",
    "gn:country_code":"CD",
    "gn:dem":1148,
    "gn:feature_class":"P",
    "gn:feature_code":"PPL",
    "gn:name":"Abika",
    "gn:population":0,
    "gn:timezone":"Africa/Lubumbashi",
    "iso:country":"CD",
    "wof:name":"Abika",
    "wof:placetype":"locality"
},
  "geometry": {"coordinates":[30.53809,3.07627],"type":"Point"}
}