{
  "type": "Feature",
  "properties": {
    "gn:admin1_code":"2.0",
    "gn:asciiname":"Mboya",
    "gn:country_code":"CD",
    "gn:dem":321,
    "gn:feature_class":"P",
    "gn:feature_code":"PPL",
    "gn:name":"Mboya",
    "gn:population":0,
    "gn:timezone":"Africa/Kinshasa",
    "iso:country":"CD",
    "wof:name":"Mboya",
    "wof:placetype":"locality"
},
  "geometry": {"coordinates":[19.06667,1.56667],"type":"Point"}
}