{
  "type": "Feature",
  "properties": {
    "gn:admin1_code":"8.0",
    "gn:asciiname":"Mbuku",
    "gn:country_code":"CD",
    "gn:dem":577,
    "gn:feature_class":"P",
    "gn:feature_code":"PPL",
    "gn:name":"Mbuku",
    "gn:population":0,
    "gn:timezone":"Africa/Kinshasa",
    "iso:country":"CD",
    "wof:name":"Mbuku",
    "wof:placetype":"locality"
},
  "geometry": {"coordinates":[14.26274,-4.6018],"type":"Point"}
}