{
  "type": "Feature",
  "properties": {
    "gn:admin1_code":"20.0",
    "gn:asciiname":"Motorensiene",
    "gn:country_code":"CD",
    "gn:dem":384,
    "gn:feature_class":"P",
    "gn:feature_code":"PPL",
    "gn:name":"Motorensiene",
    "gn:population":0,
    "gn:timezone":"Africa/Kinshasa",
    "iso:country":"CD",
    "wof:name":"Motorensiene",
    "wof:placetype":"locality"
},
  "geometry": {"coordinates":[18.07211,-3.98537],"type":"Point"}
}