{
  "type": "Feature",
  "properties": {
    "gn:admin1_code":"10.0",
    "gn:asciiname":"Bukafu-Kasambule",
    "gn:country_code":"CD",
    "gn:dem":557,
    "gn:feature_class":"P",
    "gn:feature_code":"PPL",
    "gn:name":"Bukafu-Kasambule",
    "gn:population":0,
    "gn:timezone":"Africa/Lubumbashi",
    "iso:country":"CD",
    "name:und_x_variant":[
        "Kazambula",
        "Kasambula",
        "Bukafu-Kasambule"
    ],
    "wof:name":"Bukafu-Kasambule",
    "wof:placetype":"locality"
},
  "geometry": {"coordinates":[26.14816,-3.3628],"type":"Point"}
}