{
  "type": "Feature",
  "properties": {
    "gn:admin1_code":"30.0",
    "gn:asciiname":"Yasaka",
    "gn:country_code":"CD",
    "gn:dem":360,
    "gn:feature_class":"P",
    "gn:feature_code":"PPL",
    "gn:name":"Yasaka",
    "gn:population":0,
    "gn:timezone":"Africa/Lubumbashi",
    "iso:country":"CD",
    "wof:name":"Yasaka",
    "wof:placetype":"locality"
},
  "geometry": {"coordinates":[23.28595,1.57681],"type":"Point"}
}