{
  "type": "Feature",
  "properties": {
    "gn:admin1_code":"30.0",
    "gn:asciiname":"Bakarada",
    "gn:country_code":"CD",
    "gn:dem":536,
    "gn:feature_class":"P",
    "gn:feature_code":"PPL",
    "gn:name":"Bakarada",
    "gn:population":0,
    "gn:timezone":"Africa/Lubumbashi",
    "iso:country":"CD",
    "wof:name":"Bakarada",
    "wof:placetype":"locality"
},
  "geometry": {"coordinates":[27.08442,1.05737],"type":"Point"}
}