{
  "type": "Feature",
  "properties": {
    "gn:admin1_code":"15.0",
    "gn:asciiname":"Lubombo",
    "gn:country_code":"CD",
    "gn:dem":777,
    "gn:feature_class":"P",
    "gn:feature_code":"PPL",
    "gn:name":"Lubombo",
    "gn:population":0,
    "gn:timezone":"Africa/Lubumbashi",
    "iso:country":"CD",
    "name:ceb_x_preferred":[
        "Lubombo"
    ],
    "name:hun_x_preferred":[
        "Lubombo"
    ],
    "name:ita_x_preferred":[
        "Lubombo"
    ],
    "name:swe_x_preferred":[
        "Lubombo"
    ],
    "wof:name":"Lubombo",
    "wof:placetype":"locality"
},
  "geometry": {"coordinates":[26.68811,-7.88013],"type":"Point"}
}