{
  "type": "Feature",
  "properties": {
    "gn:admin1_code":"8.0",
    "gn:asciiname":"Ndeke",
    "gn:country_code":"CD",
    "gn:dem":489,
    "gn:feature_class":"P",
    "gn:feature_code":"PPL",
    "gn:name":"Ndeke",
    "gn:population":0,
    "gn:timezone":"Africa/Kinshasa",
    "iso:country":"CD",
    "wof:name":"Ndeke",
    "wof:placetype":"locality"
},
  "geometry": {"coordinates":[14.92834,-4.77969],"type":"Point"}
}