{
  "type": "Feature",
  "properties": {
    "gn:admin1_code":"28.0",
    "gn:asciiname":"Bogale",
    "gn:country_code":"CD",
    "gn:dem":349,
    "gn:feature_class":"P",
    "gn:feature_code":"PPL",
    "gn:name":"Bogale",
    "gn:population":0,
    "gn:timezone":"Africa/Kinshasa",
    "iso:country":"CD",
    "wof:name":"Bogale",
    "wof:placetype":"locality"
},
  "geometry": {"coordinates":[19.08725,3.10654],"type":"Point"}
}