{
  "type": "Feature",
  "properties": {
    "gn:admin1_code":"28.0",
    "gn:asciiname":"Bogale",
    "gn:country_code":"CD",
    "gn:dem":349,
    "gn:feature_class":"P",
    "gn:feature_code":"PPL",
    "gn:name":"Bogale",
    "gn:population":0,
    "gn:timezone":"Africa/Kinshasa",
    "iso:country":"CD",
    "name:ceb_x_preferred":[
        "Bogale"
    ],
    "name:mya_x_preferred":[
        "\u1018\u102d\u102f\u1000\u101c\u1031\u1038\u1019\u103c\u102d\u102f\u1037"
    ],
    "name:nld_x_preferred":[
        "Bogale"
    ],
    "name:nor_x_preferred":[
        "Bogale"
    ],
    "name:pol_x_preferred":[
        "Bogalay"
    ],
    "name:rus_x_preferred":[
        "\u0411\u043e\u0433\u0430\u043b\u0435"
    ],
    "name:swe_x_preferred":[
        "Bogale"
    ],
    "wof:name":"Bogale",
    "wof:placetype":"locality"
},
  "geometry": {"coordinates":[19.08725,3.10654],"type":"Point"}
}