{
  "type": "Feature",
  "properties": {
    "gn:admin1_code":"17.0",
    "gn:asciiname":"Amalse",
    "gn:country_code":"CD",
    "gn:dem":1361,
    "gn:feature_class":"P",
    "gn:feature_code":"PPL",
    "gn:name":"Amalse",
    "gn:population":0,
    "gn:timezone":"Africa/Lubumbashi",
    "iso:country":"CD",
    "wof:name":"Amalse",
    "wof:placetype":"locality"
},
  "geometry": {"coordinates":[30.76261,2.82606],"type":"Point"}
}