{
  "type": "Feature",
  "properties": {
    "gn:admin1_code":"29.0",
    "gn:asciiname":"Kahoho",
    "gn:country_code":"CD",
    "gn:dem":727,
    "gn:feature_class":"P",
    "gn:feature_code":"PPL",
    "gn:name":"Kahoho",
    "gn:population":0,
    "gn:timezone":"Africa/Lubumbashi",
    "iso:country":"CD",
    "wof:name":"Kahoho",
    "wof:placetype":"locality"
},
  "geometry": {"coordinates":[26.26748,-6.77798],"type":"Point"}
}