{
  "type": "Feature",
  "properties": {
    "gn:admin1_code":"8.0",
    "gn:asciiname":"Soma",
    "gn:country_code":"CD",
    "gn:dem":381,
    "gn:feature_class":"P",
    "gn:feature_code":"PPL",
    "gn:name":"Soma",
    "gn:population":0,
    "gn:timezone":"Africa/Kinshasa",
    "iso:country":"CD",
    "name:und_x_variant":[
        "Sonja"
    ],
    "wof:name":"Soma",
    "wof:placetype":"locality"
},
  "geometry": {"coordinates":[14.73451,-5.45709],"type":"Point"}
}