{
  "type": "Feature",
  "properties": {
    "gn:admin1_code":"19.0",
    "gn:asciiname":"Yungululu",
    "gn:country_code":"CD",
    "gn:dem":531,
    "gn:feature_class":"P",
    "gn:feature_code":"PPL",
    "gn:name":"Yungululu",
    "gn:population":0,
    "gn:timezone":"Africa/Kinshasa",
    "iso:country":"CD",
    "wof:name":"Yungululu",
    "wof:placetype":"locality"
},
  "geometry": {"coordinates":[16.81073,-6.04981],"type":"Point"}
}