{
  "type": "Feature",
  "properties": {
    "gn:admin1_code":"6.0",
    "gn:asciiname":"Nsuni-Kitoko",
    "gn:country_code":"CD",
    "gn:dem":661,
    "gn:feature_class":"P",
    "gn:feature_code":"PPL",
    "gn:name":"Nsuni-Kitoko",
    "gn:population":0,
    "gn:timezone":"Africa/Kinshasa",
    "iso:country":"CD",
    "wof:name":"Nsuni-Kitoko",
    "wof:placetype":"locality"
},
  "geometry": {"coordinates":[16.26667,-4.35],"type":"Point"}
}