{
  "type": "Feature",
  "properties": {
    "gn:admin1_code":"16.0",
    "gn:asciiname":"Mbiri",
    "gn:country_code":"CD",
    "gn:dem":1229,
    "gn:feature_class":"P",
    "gn:feature_code":"PPL",
    "gn:name":"Mbiri",
    "gn:population":0,
    "gn:timezone":"Africa/Lubumbashi",
    "iso:country":"CD",
    "wof:name":"Mbiri",
    "wof:placetype":"locality"
},
  "geometry": {"coordinates":[29.90922,2.68779],"type":"Point"}
}