{
  "type": "Feature",
  "properties": {
    "gn:admin1_code":"11.0",
    "gn:asciiname":"Buhumba",
    "gn:country_code":"CD",
    "gn:dem":2066,
    "gn:feature_class":"P",
    "gn:feature_code":"PPL",
    "gn:name":"Buhumba",
    "gn:population":0,
    "gn:timezone":"Africa/Lubumbashi",
    "iso:country":"CD",
    "wof:name":"Buhumba",
    "wof:placetype":"locality"
},
  "geometry": {"coordinates":[29.34589,-1.52327],"type":"Point"}
}