{
  "type": "Feature",
  "properties": {
    "gn:admin1_code":"22.0",
    "gn:asciiname":"Tsninanga",
    "gn:country_code":"CD",
    "gn:dem":933,
    "gn:feature_class":"P",
    "gn:feature_code":"PPL",
    "gn:name":"Tsninanga",
    "gn:population":0,
    "gn:timezone":"Africa/Lubumbashi",
    "iso:country":"CD",
    "wof:name":"Tsninanga",
    "wof:placetype":"locality"
},
  "geometry": {"coordinates":[23.06921,-10.06161],"type":"Point"}
}