{
  "type": "Feature",
  "properties": {
    "gn:admin1_code":"14.0",
    "gn:asciiname":"Kambikila",
    "gn:country_code":"CD",
    "gn:dem":1165,
    "gn:feature_class":"P",
    "gn:feature_code":"PPL",
    "gn:name":"Kambikila",
    "gn:population":0,
    "gn:timezone":"Africa/Lubumbashi",
    "iso:country":"CD",
    "wof:name":"Kambikila",
    "wof:placetype":"locality"
},
  "geometry": {"coordinates":[27.66956,-11.81745],"type":"Point"}
}