{
  "type": "Feature",
  "properties": {
    "gn:admin1_code":"23.0",
    "gn:asciiname":"Tshiniama",
    "gn:country_code":"CD",
    "gn:dem":657,
    "gn:feature_class":"P",
    "gn:feature_code":"PPL",
    "gn:name":"Tshiniama",
    "gn:population":0,
    "gn:timezone":"Africa/Lubumbashi",
    "iso:country":"CD",
    "wof:name":"Tshiniama",
    "wof:placetype":"locality"
},
  "geometry": {"coordinates":[22.86847,-5.12998],"type":"Point"}
}