{
  "type": "Feature",
  "properties": {
    "gn:admin1_code":"8.0",
    "gn:asciiname":"Songa-Mani",
    "gn:country_code":"CD",
    "gn:dem":527,
    "gn:feature_class":"P",
    "gn:feature_code":"PPL",
    "gn:name":"Songa-Mani",
    "gn:population":0,
    "gn:timezone":"Africa/Kinshasa",
    "iso:country":"CD",
    "wof:name":"Songa-Mani",
    "wof:placetype":"locality"
},
  "geometry": {"coordinates":[14.54495,-5.88685],"type":"Point"}
}