{
  "type": "Feature",
  "properties": {
    "gn:admin1_code":"20.0",
    "gn:asciiname":"Pana-Onatra",
    "gn:country_code":"CD",
    "gn:dem":341,
    "gn:feature_class":"P",
    "gn:feature_code":"PPL",
    "gn:name":"Pana-Onatra",
    "gn:population":0,
    "gn:timezone":"Africa/Kinshasa",
    "iso:country":"CD",
    "name:und_x_variant":[
        "Pana",
        "Pana-Otraco",
        "Pana-Onatra"
    ],
    "wof:name":"Pana-Onatra",
    "wof:placetype":"locality"
},
  "geometry": {"coordinates":[18.77499,-3.66954],"type":"Point"}
}