{
  "type": "Feature",
  "properties": {
    "gn:admin1_code":"29.0",
    "gn:asciiname":"Kaunga",
    "gn:country_code":"CD",
    "gn:dem":1616,
    "gn:feature_class":"P",
    "gn:feature_code":"PPL",
    "gn:name":"Kaunga",
    "gn:population":0,
    "gn:timezone":"Africa/Lubumbashi",
    "iso:country":"CD",
    "wof:name":"Kaunga",
    "wof:placetype":"locality"
},
  "geometry": {"coordinates":[29.57155,-7.22846],"type":"Point"}
}