{
  "type": "Feature",
  "properties": {
    "gn:admin1_code":"2.0",
    "gn:asciiname":"Isaka-Rive",
    "gn:country_code":"CD",
    "gn:dem":336,
    "gn:feature_class":"P",
    "gn:feature_code":"PPL",
    "gn:name":"Isaka-Rive",
    "gn:population":0,
    "gn:timezone":"Africa/Kinshasa",
    "iso:country":"CD",
    "wof:name":"Isaka-Rive",
    "wof:placetype":"locality"
},
  "geometry": {"coordinates":[20.15097,-0.53041],"type":"Point"}
}