{
  "type": "Feature",
  "properties": {
    "gn:admin1_code":"20.0",
    "gn:asciiname":"Songo",
    "gn:country_code":"CD",
    "gn:dem":399,
    "gn:feature_class":"P",
    "gn:feature_code":"PPL",
    "gn:name":"Songo",
    "gn:population":0,
    "gn:timezone":"Africa/Kinshasa",
    "iso:country":"CD",
    "name:ceb_x_preferred":[
        "Songo"
    ],
    "name:deu_x_preferred":[
        "Songo"
    ],
    "name:fra_x_preferred":[
        "Songo"
    ],
    "name:por_x_preferred":[
        "Songo"
    ],
    "name:swe_x_preferred":[
        "Songo"
    ],
    "wof:name":"Songo",
    "wof:placetype":"locality"
},
  "geometry": {"coordinates":[18.41548,-4.40448],"type":"Point"}
}