{
  "type": "Feature",
  "properties": {
    "gn:admin1_code":"8.0",
    "gn:asciiname":"Yema",
    "gn:country_code":"CD",
    "gn:dem":60,
    "gn:feature_class":"P",
    "gn:feature_code":"PPL",
    "gn:name":"Yema",
    "gn:population":0,
    "gn:timezone":"Africa/Kinshasa",
    "iso:country":"CD",
    "name:ceb_x_preferred":[
        "Yema"
    ],
    "name:swe_x_preferred":[
        "Yema"
    ],
    "wof:name":"Yema",
    "wof:placetype":"locality"
},
  "geometry": {"coordinates":[12.28498,-5.74751],"type":"Point"}
}