{
  "type": "Feature",
  "properties": {
    "gn:admin1_code":"21.0",
    "gn:asciiname":"Djele",
    "gn:country_code":"CD",
    "gn:dem":601,
    "gn:feature_class":"P",
    "gn:feature_code":"PPL",
    "gn:name":"Djele",
    "gn:population":0,
    "gn:timezone":"Africa/Lubumbashi",
    "iso:country":"CD",
    "wof:name":"Djele",
    "wof:placetype":"locality"
},
  "geometry": {"coordinates":[24.78333,-4.95],"type":"Point"}
}