{
  "type": "Feature",
  "properties": {
    "gn:admin1_code":"22.0",
    "gn:asciiname":"Samulila",
    "gn:country_code":"CD",
    "gn:dem":1055,
    "gn:feature_class":"P",
    "gn:feature_code":"PPL",
    "gn:name":"Samulila",
    "gn:population":0,
    "gn:timezone":"Africa/Lubumbashi",
    "iso:country":"CD",
    "wof:name":"Samulila",
    "wof:placetype":"locality"
},
  "geometry": {"coordinates":[23.00898,-10.64432],"type":"Point"}
}