{
  "type": "Feature",
  "properties": {
    "gn:admin1_code":"22.0",
    "gn:asciiname":"Lumanga",
    "gn:country_code":"CD",
    "gn:dem":919,
    "gn:feature_class":"P",
    "gn:feature_code":"PPL",
    "gn:name":"Lumanga",
    "gn:population":0,
    "gn:timezone":"Africa/Lubumbashi",
    "iso:country":"CD",
    "wof:name":"Lumanga",
    "wof:placetype":"locality"
},
  "geometry": {"coordinates":[23.16271,-8.22951],"type":"Point"}
}