{
  "type": "Feature",
  "properties": {
    "gn:admin1_code":"2.0",
    "gn:asciiname":"Lokondola",
    "gn:country_code":"CD",
    "gn:dem":332,
    "gn:feature_class":"P",
    "gn:feature_code":"PPL",
    "gn:name":"Lokondola",
    "gn:population":0,
    "gn:timezone":"Africa/Kinshasa",
    "iso:country":"CD",
    "wof:name":"Lokondola",
    "wof:placetype":"locality"
},
  "geometry": {"coordinates":[19.15757,-0.4587],"type":"Point"}
}