{
  "type": "Feature",
  "properties": {
    "gn:admin1_code":"30.0",
    "gn:asciiname":"Bodjaba",
    "gn:country_code":"CD",
    "gn:dem":481,
    "gn:feature_class":"P",
    "gn:feature_code":"PPL",
    "gn:name":"Bodjaba",
    "gn:population":0,
    "gn:timezone":"Africa/Lubumbashi",
    "iso:country":"CD",
    "wof:name":"Bodjaba",
    "wof:placetype":"locality"
},
  "geometry": {"coordinates":[25.14141,1.65316],"type":"Point"}
}