{
  "type": "Feature",
  "properties": {
    "gn:admin1_code":"6.0",
    "gn:asciiname":"Masiau",
    "gn:country_code":"CD",
    "gn:dem":645,
    "gn:feature_class":"P",
    "gn:feature_code":"PPL",
    "gn:name":"Masiau",
    "gn:population":0,
    "gn:timezone":"Africa/Kinshasa",
    "iso:country":"CD",
    "wof:name":"Masiau",
    "wof:placetype":"locality"
},
  "geometry": {"coordinates":[15.86973,-4.2534],"type":"Point"}
}