{
  "type": "Feature",
  "properties": {
    "gn:admin1_code":"23.0",
    "gn:asciiname":"Mailamba",
    "gn:country_code":"CD",
    "gn:dem":938,
    "gn:feature_class":"P",
    "gn:feature_code":"PPL",
    "gn:name":"Mailamba",
    "gn:population":0,
    "gn:timezone":"Africa/Lubumbashi",
    "iso:country":"CD",
    "wof:name":"Mailamba",
    "wof:placetype":"locality"
},
  "geometry": {"coordinates":[23.12887000000001,-7.70092],"type":"Point"}
}