{
  "type": "Feature",
  "properties": {
    "gn:admin1_code":"31.0",
    "gn:asciiname":"Yayemola",
    "gn:country_code":"CD",
    "gn:dem":390,
    "gn:feature_class":"P",
    "gn:feature_code":"PPL",
    "gn:name":"Yayemola",
    "gn:population":0,
    "gn:timezone":"Africa/Kinshasa",
    "iso:country":"CD",
    "wof:name":"Yayemola",
    "wof:placetype":"locality"
},
  "geometry": {"coordinates":[22.83333,-0.76667],"type":"Point"}
}