{
  "type": "Feature",
  "properties": {
    "gn:admin1_code":"15.0",
    "gn:asciiname":"Kilamba",
    "gn:country_code":"CD",
    "gn:dem":842,
    "gn:feature_class":"P",
    "gn:feature_code":"PPL",
    "gn:name":"Kilamba",
    "gn:population":0,
    "gn:timezone":"Africa/Lubumbashi",
    "iso:country":"CD",
    "wof:name":"Kilamba",
    "wof:placetype":"locality"
},
  "geometry": {"coordinates":[25.02946,-9.3423],"type":"Point"}
}