{
  "type": "Feature",
  "properties": {
    "gn:admin1_code":"15.0",
    "gn:asciiname":"Kilamba",
    "gn:country_code":"CD",
    "gn:dem":842,
    "gn:feature_class":"P",
    "gn:feature_code":"PPL",
    "gn:name":"Kilamba",
    "gn:population":0,
    "gn:timezone":"Africa/Lubumbashi",
    "iso:country":"CD",
    "name:ara_x_preferred":[
        "\u0643\u064a\u0644\u0645\u0628\u0627"
    ],
    "name:deu_x_preferred":[
        "Kilamba"
    ],
    "name:fin_x_preferred":[
        "Kilamba"
    ],
    "name:fra_x_preferred":[
        "Kilamba"
    ],
    "name:ita_x_preferred":[
        "Kilamba"
    ],
    "name:nor_x_preferred":[
        "Kilamba"
    ],
    "name:pol_x_preferred":[
        "Kilamba"
    ],
    "name:por_x_preferred":[
        "Quilamba"
    ],
    "name:rus_x_preferred":[
        "\u041a\u0438\u043b\u0430\u043c\u0431\u0430"
    ],
    "name:spa_x_preferred":[
        "Kilamba"
    ],
    "name:vie_x_preferred":[
        "Kilamba"
    ],
    "name:zho_x_preferred":[
        "\u51ef\u5170\u5df4"
    ],
    "wof:name":"Kilamba",
    "wof:placetype":"locality"
},
  "geometry": {"coordinates":[25.02946,-9.3423],"type":"Point"}
}