{
  "type": "Feature",
  "properties": {
    "gn:admin1_code":"22.0",
    "gn:asciiname":"Fimbo",
    "gn:country_code":"CD",
    "gn:dem":1034,
    "gn:feature_class":"P",
    "gn:feature_code":"PPL",
    "gn:name":"Fimbo",
    "gn:population":0,
    "gn:timezone":"Africa/Lubumbashi",
    "iso:country":"CD",
    "wof:name":"Fimbo",
    "wof:placetype":"locality"
},
  "geometry": {"coordinates":[23.43406,-10.10908],"type":"Point"}
}