{
  "type": "Feature",
  "properties": {
    "gn:admin1_code":"20.0",
    "gn:asciiname":"Nkata",
    "gn:country_code":"CD",
    "gn:dem":742,
    "gn:feature_class":"P",
    "gn:feature_code":"PPL",
    "gn:name":"Nkata",
    "gn:population":0,
    "gn:timezone":"Africa/Kinshasa",
    "iso:country":"CD",
    "wof:name":"Nkata",
    "wof:placetype":"locality"
},
  "geometry": {"coordinates":[19.29406,-5.4521],"type":"Point"}
}