{
  "type": "Feature",
  "properties": {
    "gn:admin1_code":"22.0",
    "gn:asciiname":"Kafunda",
    "gn:country_code":"CD",
    "gn:dem":1019,
    "gn:feature_class":"P",
    "gn:feature_code":"PPL",
    "gn:name":"Kafunda",
    "gn:population":0,
    "gn:timezone":"Africa/Lubumbashi",
    "iso:country":"CD",
    "wof:name":"Kafunda",
    "wof:placetype":"locality"
},
  "geometry": {"coordinates":[22.18234,-8.1449],"type":"Point"}
}