{
  "type": "Feature",
  "properties": {
    "gn:admin1_code":"20.0",
    "gn:asciiname":"Mariala",
    "gn:country_code":"CD",
    "gn:dem":335,
    "gn:feature_class":"P",
    "gn:feature_code":"PPL",
    "gn:name":"Mariala",
    "gn:population":0,
    "gn:timezone":"Africa/Kinshasa",
    "iso:country":"CD",
    "wof:name":"Mariala",
    "wof:placetype":"locality"
},
  "geometry": {"coordinates":[17.54797,-3.66434],"type":"Point"}
}