{
  "type": "Feature",
  "properties": {
    "gn:admin1_code":"0.0",
    "gn:asciiname":"Kapako",
    "gn:country_code":"CD",
    "gn:dem":654,
    "gn:feature_class":"P",
    "gn:feature_code":"PPL",
    "gn:name":"Kapako",
    "gn:population":0,
    "gn:timezone":"Africa/Lubumbashi",
    "iso:country":"CD",
    "wof:name":"Kapako",
    "wof:placetype":"locality"
},
  "geometry": {"coordinates":[25.58333,-5.56667],"type":"Point"}
}