{
  "type": "Feature",
  "properties": {
    "gn:admin1_code":"14.0",
    "gn:asciiname":"Kigongo",
    "gn:country_code":"CD",
    "gn:dem":1159,
    "gn:feature_class":"P",
    "gn:feature_code":"PPL",
    "gn:name":"Kigongo",
    "gn:population":0,
    "gn:timezone":"Africa/Lubumbashi",
    "iso:country":"CD",
    "wof:name":"Kigongo",
    "wof:placetype":"locality"
},
  "geometry": {"coordinates":[27.36566,-10.85812],"type":"Point"}
}