{
  "type": "Feature",
  "properties": {
    "gn:admin1_code":"18.0",
    "gn:asciiname":"Shanuma",
    "gn:country_code":"CD",
    "gn:dem":662,
    "gn:feature_class":"P",
    "gn:feature_code":"PPL",
    "gn:name":"Shanuma",
    "gn:population":0,
    "gn:timezone":"Africa/Lubumbashi",
    "iso:country":"CD",
    "name:und_x_variant":[
        "Kanuma",
        "Shanuma"
    ],
    "wof:name":"Shanuma",
    "wof:placetype":"locality"
},
  "geometry": {"coordinates":[20.88358,-6.8011],"type":"Point"}
}