{
  "type": "Feature",
  "properties": {
    "gn:admin1_code":"2.0",
    "gn:asciiname":"Songo",
    "gn:country_code":"CD",
    "gn:dem":352,
    "gn:feature_class":"P",
    "gn:feature_code":"PPL",
    "gn:name":"Songo",
    "gn:population":0,
    "gn:timezone":"Africa/Kinshasa",
    "iso:country":"CD",
    "name:ara_x_preferred":[
        "\u0633\u0648\u0646\u062c\u0648"
    ],
    "name:ben_x_preferred":[
        "\u09b8\u0999\u09cd\u0997\u09cb"
    ],
    "name:ceb_x_preferred":[
        "Songo"
    ],
    "name:deu_x_preferred":[
        "Songo"
    ],
    "name:ell_x_preferred":[
        "\u03a3\u03cc\u03bd\u03b3\u03ba\u03bf"
    ],
    "name:eng_x_preferred":[
        "Songo"
    ],
    "name:fas_x_preferred":[
        "\u0633\u0648\u0646\u06af\u0648"
    ],
    "name:fra_x_preferred":[
        "Songo"
    ],
    "name:heb_x_preferred":[
        "\u05e1\u05d5\u05e0\u05d2\u05d5"
    ],
    "name:hin_x_preferred":[
        "\u0938\u094b\u0902\u0917\u094b"
    ],
    "name:hun_x_preferred":[
        "Songo"
    ],
    "name:ind_x_preferred":[
        "Songo"
    ],
    "name:ita_x_preferred":[
        "Songo"
    ],
    "name:jpn_x_preferred":[
        "\u30bd\u30f3\u30b4"
    ],
    "name:kor_x_preferred":[
        "\uc1a1\uace0"
    ],
    "name:nld_x_preferred":[
        "Songo"
    ],
    "name:pol_x_preferred":[
        "Songo"
    ],
    "name:por_x_preferred":[
        "Songo"
    ],
    "name:rus_x_preferred":[
        "\u0421\u043e\u043d\u0433\u043e"
    ],
    "name:spa_x_preferred":[
        "Songo"
    ],
    "name:swe_x_preferred":[
        "Songo"
    ],
    "name:tur_x_preferred":[
        "Songo"
    ],
    "name:ukr_x_preferred":[
        "\u0421\u043e\u043d\u0433\u043e"
    ],
    "name:urd_x_preferred":[
        "\u0633\u0627\u0646\u06af\u0648"
    ],
    "name:vie_x_preferred":[
        "Songo"
    ],
    "name:zho_cn_x_preferred":[
        "\u677e\u6208"
    ],
    "name:zho_tw_x_preferred":[
        "\u6851\u679c"
    ],
    "wof:name":"Songo",
    "wof:placetype":"locality"
},
  "geometry": {"coordinates":[20.05867,-0.05228],"type":"Point"}
}