{
  "type": "Feature",
  "properties": {
    "gn:admin1_code":"8.0",
    "gn:asciiname":"Manionda",
    "gn:country_code":"CD",
    "gn:dem":506,
    "gn:feature_class":"P",
    "gn:feature_code":"PPL",
    "gn:name":"Manionda",
    "gn:population":0,
    "gn:timezone":"Africa/Kinshasa",
    "iso:country":"CD",
    "wof:name":"Manionda",
    "wof:placetype":"locality"
},
  "geometry": {"coordinates":[14.42898,-4.47159],"type":"Point"}
}