{
  "type": "Feature",
  "properties": {
    "gn:admin1_code":"10.0",
    "gn:asciiname":"Pene-Fundi",
    "gn:country_code":"CD",
    "gn:dem":667,
    "gn:feature_class":"P",
    "gn:feature_code":"PPL",
    "gn:name":"Pene-Fundi",
    "gn:population":0,
    "gn:timezone":"Africa/Lubumbashi",
    "iso:country":"CD",
    "wof:name":"Pene-Fundi",
    "wof:placetype":"locality"
},
  "geometry": {"coordinates":[27.08676,-4.8995],"type":"Point"}
}