{
  "type": "Feature",
  "properties": {
    "gn:admin1_code":"28.0",
    "gn:asciiname":"Busu-Bita",
    "gn:country_code":"CD",
    "gn:dem":343,
    "gn:feature_class":"P",
    "gn:feature_code":"PPL",
    "gn:name":"Busu-Bita",
    "gn:population":0,
    "gn:timezone":"Africa/Kinshasa",
    "iso:country":"CD",
    "name:fra_x_preferred":[
        "Busu-Bita"
    ],
    "wof:name":"Busu-Bita",
    "wof:placetype":"locality"
},
  "geometry": {"coordinates":[18.99439,2.39457],"type":"Point"}
}