{
  "type": "Feature",
  "properties": {
    "gn:admin1_code":"21.0",
    "gn:asciiname":"Mukwanda",
    "gn:country_code":"CD",
    "gn:dem":738,
    "gn:feature_class":"P",
    "gn:feature_code":"PPL",
    "gn:name":"Mukwanda",
    "gn:population":0,
    "gn:timezone":"Africa/Lubumbashi",
    "iso:country":"CD",
    "wof:name":"Mukwanda",
    "wof:placetype":"locality"
},
  "geometry": {"coordinates":[23.68102,-6.86877],"type":"Point"}
}