{
  "type": "Feature",
  "properties": {
    "gn:admin1_code":"8.0",
    "gn:asciiname":"Senga",
    "gn:country_code":"CD",
    "gn:dem":454,
    "gn:feature_class":"P",
    "gn:feature_code":"PPL",
    "gn:name":"Senga",
    "gn:population":0,
    "gn:timezone":"Africa/Kinshasa",
    "iso:country":"CD",
    "wof:name":"Senga",
    "wof:placetype":"locality"
},
  "geometry": {"coordinates":[14.91181,-5.4378],"type":"Point"}
}