{
  "type": "Feature",
  "properties": {
    "gn:admin1_code":"22.0",
    "gn:asciiname":"Mushitu",
    "gn:country_code":"CD",
    "gn:dem":1072,
    "gn:feature_class":"P",
    "gn:feature_code":"PPL",
    "gn:name":"Mushitu",
    "gn:population":0,
    "gn:timezone":"Africa/Lubumbashi",
    "iso:country":"CD",
    "name:und_x_variant":[
        "Mushilu",
        "Mushitu"
    ],
    "wof:name":"Mushitu",
    "wof:placetype":"locality"
},
  "geometry": {"coordinates":[22.19464,-9.83641],"type":"Point"}
}