{
  "type": "Feature",
  "properties": {
    "gn:admin1_code":"21.0",
    "gn:asciiname":"Kipange",
    "gn:country_code":"CD",
    "gn:dem":784,
    "gn:feature_class":"P",
    "gn:feature_code":"PPL",
    "gn:name":"Kipange",
    "gn:population":0,
    "gn:timezone":"Africa/Lubumbashi",
    "iso:country":"CD",
    "wof:name":"Kipange",
    "wof:placetype":"locality"
},
  "geometry": {"coordinates":[25.06865,-6.24144],"type":"Point"}
}