{
  "type": "Feature",
  "properties": {
    "gn:admin1_code":"11.0",
    "gn:asciiname":"Abakutsha",
    "gn:country_code":"CD",
    "gn:dem":786,
    "gn:feature_class":"P",
    "gn:feature_code":"PPL",
    "gn:name":"Abakutsha",
    "gn:population":0,
    "gn:timezone":"Africa/Lubumbashi",
    "iso:country":"CD",
    "wof:name":"Abakutsha",
    "wof:placetype":"locality"
},
  "geometry": {"coordinates":[28.13611,-0.36504],"type":"Point"}
}