{
  "type": "Feature",
  "properties": {
    "gn:admin1_code":"11.0",
    "gn:asciiname":"Mbaya",
    "gn:country_code":"CD",
    "gn:dem":1337,
    "gn:feature_class":"P",
    "gn:feature_code":"PPL",
    "gn:name":"Mbaya",
    "gn:population":0,
    "gn:timezone":"Africa/Lubumbashi",
    "iso:country":"CD",
    "wof:name":"Mbaya",
    "wof:placetype":"locality"
},
  "geometry": {"coordinates":[29.40248,0.4156],"type":"Point"}
}