{
  "type": "Feature",
  "properties": {
    "gn:admin1_code":"17.0",
    "gn:asciiname":"Tza",
    "gn:country_code":"CD",
    "gn:dem":1644,
    "gn:feature_class":"P",
    "gn:feature_code":"PPL",
    "gn:name":"Tza",
    "gn:population":0,
    "gn:timezone":"Africa/Lubumbashi",
    "iso:country":"CD",
    "wof:name":"Tza",
    "wof:placetype":"locality"
},
  "geometry": {"coordinates":[30.55229000000001,2.18056],"type":"Point"}
}