{
  "type": "Feature",
  "properties": {
    "gn:admin1_code":"27.0",
    "gn:asciiname":"Lotshetsha Sango",
    "gn:country_code":"CD",
    "gn:dem":473,
    "gn:feature_class":"P",
    "gn:feature_code":"PPL",
    "gn:name":"Lotshetsha Sango",
    "gn:population":0,
    "gn:timezone":"Africa/Lubumbashi",
    "iso:country":"CD",
    "wof:name":"Lotshetsha Sango",
    "wof:placetype":"locality"
},
  "geometry": {"coordinates":[24.95,-2.63333],"type":"Point"}
}