{
  "type": "Feature",
  "properties": {
    "gn:admin1_code":"27.0",
    "gn:asciiname":"Lukulu",
    "gn:country_code":"CD",
    "gn:dem":538,
    "gn:feature_class":"P",
    "gn:feature_code":"PPL",
    "gn:name":"Lukulu",
    "gn:population":0,
    "gn:timezone":"Africa/Lubumbashi",
    "iso:country":"CD",
    "wof:name":"Lukulu",
    "wof:placetype":"locality"
},
  "geometry": {"coordinates":[23.28908,-2.54219],"type":"Point"}
}