{
  "type": "Feature",
  "properties": {
    "gn:admin1_code":"27.0",
    "gn:asciiname":"Lukulu",
    "gn:country_code":"CD",
    "gn:dem":538,
    "gn:feature_class":"P",
    "gn:feature_code":"PPL",
    "gn:name":"Lukulu",
    "gn:population":0,
    "gn:timezone":"Africa/Lubumbashi",
    "iso:country":"CD",
    "name:ceb_x_preferred":[
        "Lukulu"
    ],
    "name:deu_x_preferred":[
        "Lukulu"
    ],
    "name:fra_x_preferred":[
        "Lukulu"
    ],
    "name:ita_x_preferred":[
        "Lukulu"
    ],
    "name:mrj_x_preferred":[
        "\u041b\u0443\u043a\u0443\u043b\u0443"
    ],
    "name:pol_x_preferred":[
        "Lukulu"
    ],
    "name:por_x_preferred":[
        "Lukulu"
    ],
    "name:ron_x_preferred":[
        "Lukulu"
    ],
    "name:zho_x_preferred":[
        "\u76e7\u5eab\u76e7"
    ],
    "wof:name":"Lukulu",
    "wof:placetype":"locality"
},
  "geometry": {"coordinates":[23.28908,-2.54219],"type":"Point"}
}