{
  "type": "Feature",
  "properties": {
    "gn:admin1_code":"20.0",
    "gn:asciiname":"Zambo",
    "gn:country_code":"CD",
    "gn:dem":569,
    "gn:feature_class":"P",
    "gn:feature_code":"PPL",
    "gn:name":"Zambo",
    "gn:population":0,
    "gn:timezone":"Africa/Kinshasa",
    "iso:country":"CD",
    "wof:name":"Zambo",
    "wof:placetype":"locality"
},
  "geometry": {"coordinates":[20.09797,-5.25463],"type":"Point"}
}