{
  "type": "Feature",
  "properties": {
    "gn:admin1_code":"27.0",
    "gn:asciiname":"Ntete",
    "gn:country_code":"CD",
    "gn:dem":542,
    "gn:feature_class":"P",
    "gn:feature_code":"PPL",
    "gn:name":"Ntete",
    "gn:population":0,
    "gn:timezone":"Africa/Lubumbashi",
    "iso:country":"CD",
    "wof:name":"Ntete",
    "wof:placetype":"locality"
},
  "geometry": {"coordinates":[24.72676,-3.14587],"type":"Point"}
}