{
  "type": "Feature",
  "properties": {
    "gn:admin1_code":"20.0",
    "gn:asciiname":"Kibongo",
    "gn:country_code":"CD",
    "gn:dem":463,
    "gn:feature_class":"P",
    "gn:feature_code":"PPL",
    "gn:name":"Kibongo",
    "gn:population":0,
    "gn:timezone":"Africa/Kinshasa",
    "iso:country":"CD",
    "wof:name":"Kibongo",
    "wof:placetype":"locality"
},
  "geometry": {"coordinates":[18.72122,-4.42372],"type":"Point"}
}