{
  "type": "Feature",
  "properties": {
    "gn:admin1_code":"20.0",
    "gn:asciiname":"Milundu",
    "gn:country_code":"CD",
    "gn:dem":433,
    "gn:feature_class":"P",
    "gn:feature_code":"PPL",
    "gn:name":"Milundu",
    "gn:population":0,
    "gn:timezone":"Africa/Kinshasa",
    "iso:country":"CD",
    "wof:name":"Milundu",
    "wof:placetype":"locality"
},
  "geometry": {"coordinates":[19.01125,-4.25069],"type":"Point"}
}