{
  "type": "Feature",
  "properties": {
    "gn:admin1_code":"25.0",
    "gn:asciiname":"Yakambili",
    "gn:country_code":"CD",
    "gn:dem":495,
    "gn:feature_class":"P",
    "gn:feature_code":"PPL",
    "gn:name":"Yakambili",
    "gn:population":0,
    "gn:timezone":"Africa/Kinshasa",
    "iso:country":"CD",
    "wof:name":"Yakambili",
    "wof:placetype":"locality"
},
  "geometry": {"coordinates":[22.20583,2.65299],"type":"Point"}
}