{
  "type": "Feature",
  "properties": {
    "gn:admin1_code":"15.0",
    "gn:asciiname":"Kaseya",
    "gn:country_code":"CD",
    "gn:dem":963,
    "gn:feature_class":"P",
    "gn:feature_code":"PPL",
    "gn:name":"Kaseya",
    "gn:population":0,
    "gn:timezone":"Africa/Lubumbashi",
    "iso:country":"CD",
    "wof:name":"Kaseya",
    "wof:placetype":"locality"
},
  "geometry": {"coordinates":[25.80009,-7.01279],"type":"Point"}
}