{
  "type": "Feature",
  "properties": {
    "gn:admin1_code":"15.0",
    "gn:asciiname":"Pita",
    "gn:country_code":"CD",
    "gn:dem":585,
    "gn:feature_class":"P",
    "gn:feature_code":"PPL",
    "gn:name":"Pita",
    "gn:population":0,
    "gn:timezone":"Africa/Lubumbashi",
    "iso:country":"CD",
    "wof:name":"Pita",
    "wof:placetype":"locality"
},
  "geometry": {"coordinates":[27.16667,-7.91667],"type":"Point"}
}