{
  "type": "Feature",
  "properties": {
    "gn:admin1_code":"13.0",
    "gn:asciiname":"Gia",
    "gn:country_code":"CD",
    "gn:dem":713,
    "gn:feature_class":"P",
    "gn:feature_code":"PPL",
    "gn:name":"Gia",
    "gn:population":0,
    "gn:timezone":"Africa/Lubumbashi",
    "iso:country":"CD",
    "wof:name":"Gia",
    "wof:placetype":"locality"
},
  "geometry": {"coordinates":[26.72689,2.60008],"type":"Point"}
}