{
  "type": "Feature",
  "properties": {
    "gn:admin1_code":"13.0",
    "gn:asciiname":"Gia",
    "gn:country_code":"CD",
    "gn:dem":713,
    "gn:feature_class":"P",
    "gn:feature_code":"PPL",
    "gn:name":"Gia",
    "gn:population":0,
    "gn:timezone":"Africa/Lubumbashi",
    "iso:country":"CD",
    "name:ara_x_preferred":[
        "\u062c\u064a\u0627"
    ],
    "name:ben_x_preferred":[
        "\u099c\u09bf\u09af\u09bc\u09be"
    ],
    "name:ces_x_preferred":[
        "Gia"
    ],
    "name:est_x_preferred":[
        "Gia"
    ],
    "name:fas_x_preferred":[
        "\u062c\u06cc\u0627"
    ],
    "name:heb_x_preferred":[
        "\u05d2'\u05d9\u05d4"
    ],
    "name:hye_x_preferred":[
        "\u054b\u056b\u0561"
    ],
    "name:ind_x_preferred":[
        "Gia"
    ],
    "name:jpn_x_preferred":[
        "\u30b8\u30fc\u30a2/\u60b2\u5287\u306e\u30b9\u30fc\u30d1\u30fc\u30e2\u30c7\u30eb"
    ],
    "name:kor_x_preferred":[
        "\uc9c0\uc544"
    ],
    "name:lav_x_preferred":[
        "D\u017eia"
    ],
    "name:nld_x_preferred":[
        "Gia"
    ],
    "name:pol_x_preferred":[
        "Gia"
    ],
    "name:por_x_preferred":[
        "Gia"
    ],
    "name:ron_x_preferred":[
        "Gia"
    ],
    "name:rus_x_preferred":[
        "\u0414\u0436\u0438\u0430"
    ],
    "name:slk_x_preferred":[
        "Gia"
    ],
    "name:spa_x_preferred":[
        "Gia"
    ],
    "name:swe_x_preferred":[
        "Gia"
    ],
    "name:ukr_x_preferred":[
        "\u0414\u0436\u0456\u0430"
    ],
    "name:vie_x_preferred":[
        "Gia"
    ],
    "name:zho_x_preferred":[
        "\u9713\u88f3\u60c5\u6311"
    ],
    "wof:name":"Gia",
    "wof:placetype":"locality"
},
  "geometry": {"coordinates":[26.72689,2.60008],"type":"Point"}
}