{
  "type": "Feature",
  "properties": {
    "gn:admin1_code":"20.0",
    "gn:asciiname":"Mokubi",
    "gn:country_code":"CD",
    "gn:dem":351,
    "gn:feature_class":"P",
    "gn:feature_code":"PPL",
    "gn:name":"Mokubi",
    "gn:population":0,
    "gn:timezone":"Africa/Kinshasa",
    "iso:country":"CD",
    "wof:name":"Mokubi",
    "wof:placetype":"locality"
},
  "geometry": {"coordinates":[18.05428,-3.66915],"type":"Point"}
}