{
  "type": "Feature",
  "properties": {
    "gn:admin1_code":"19.0",
    "gn:asciiname":"Kindundu-Muni-Mukambo",
    "gn:country_code":"CD",
    "gn:dem":470,
    "gn:feature_class":"P",
    "gn:feature_code":"PPL",
    "gn:name":"Kindundu-Muni-Mukambo",
    "gn:population":0,
    "gn:timezone":"Africa/Kinshasa",
    "iso:country":"CD",
    "wof:name":"Kindundu-Muni-Mukambo",
    "wof:placetype":"locality"
},
  "geometry": {"coordinates":[17.60928999999999,-4.60288],"type":"Point"}
}