{
  "type": "Feature",
  "properties": {
    "gn:admin1_code":"10.0",
    "gn:asciiname":"Kibamba",
    "gn:country_code":"CD",
    "gn:dem":563,
    "gn:feature_class":"P",
    "gn:feature_code":"PPL",
    "gn:name":"Kibamba",
    "gn:population":0,
    "gn:timezone":"Africa/Lubumbashi",
    "iso:country":"CD",
    "name:ita_x_preferred":[
        "Kibamba"
    ],
    "name:swa_x_preferred":[
        "Kibamba"
    ],
    "name:und_x_variant":[
        "Kibamba Lubunda",
        "Kibamba"
    ],
    "wof:name":"Kibamba",
    "wof:placetype":"locality"
},
  "geometry": {"coordinates":[26.55736,-4.89846],"type":"Point"}
}