{
  "type": "Feature",
  "properties": {
    "gn:admin1_code":"16.0",
    "gn:asciiname":"Gendedi",
    "gn:country_code":"CD",
    "gn:dem":1008,
    "gn:feature_class":"P",
    "gn:feature_code":"PPL",
    "gn:name":"Gendedi",
    "gn:population":0,
    "gn:timezone":"Africa/Lubumbashi",
    "iso:country":"CD",
    "wof:name":"Gendedi",
    "wof:placetype":"locality"
},
  "geometry": {"coordinates":[29.62316,2.77222],"type":"Point"}
}