{
  "type": "Feature",
  "properties": {
    "gn:admin1_code":"10.0",
    "gn:asciiname":"Kebanza",
    "gn:country_code":"CD",
    "gn:dem":493,
    "gn:feature_class":"P",
    "gn:feature_code":"PPL",
    "gn:name":"Kebanza",
    "gn:population":0,
    "gn:timezone":"Africa/Lubumbashi",
    "iso:country":"CD",
    "name:und_x_variant":[
        "Kebenza",
        "Kebandja",
        "Kebanza"
    ],
    "wof:name":"Kebanza",
    "wof:placetype":"locality"
},
  "geometry": {"coordinates":[25.36542,-2.56909],"type":"Point"}
}