{
  "type": "Feature",
  "properties": {
    "gn:admin1_code":"13.0",
    "gn:asciiname":"Bakilingba",
    "gn:country_code":"CD",
    "gn:dem":622,
    "gn:feature_class":"P",
    "gn:feature_code":"PPL",
    "gn:name":"Bakilingba",
    "gn:population":0,
    "gn:timezone":"Africa/Lubumbashi",
    "iso:country":"CD",
    "wof:name":"Bakilingba",
    "wof:placetype":"locality"
},
  "geometry": {"coordinates":[26.20284,3.75486],"type":"Point"}
}