{
  "type": "Feature",
  "properties": {
    "gn:admin1_code":"19.0",
    "gn:asciiname":"Kisenda",
    "gn:country_code":"CD",
    "gn:dem":752,
    "gn:feature_class":"P",
    "gn:feature_code":"PPL",
    "gn:name":"Kisenda",
    "gn:population":0,
    "gn:timezone":"Africa/Kinshasa",
    "iso:country":"CD",
    "wof:name":"Kisenda",
    "wof:placetype":"locality"
},
  "geometry": {"coordinates":[17.28328,-6.91235],"type":"Point"}
}