{
  "type": "Feature",
  "properties": {
    "gn:admin1_code":"8.0",
    "gn:asciiname":"Kinkenge-Kinzinga",
    "gn:country_code":"CD",
    "gn:dem":662,
    "gn:feature_class":"P",
    "gn:feature_code":"PPL",
    "gn:name":"Kinkenge-Kinzinga",
    "gn:population":0,
    "gn:timezone":"Africa/Kinshasa",
    "iso:country":"CD",
    "wof:name":"Kinkenge-Kinzinga",
    "wof:placetype":"locality"
},
  "geometry": {"coordinates":[13.68056,-4.96542],"type":"Point"}
}