{
  "type": "Feature",
  "properties": {
    "gn:admin1_code":"22.0",
    "gn:asciiname":"Kasanga",
    "gn:country_code":"CD",
    "gn:dem":1206,
    "gn:feature_class":"P",
    "gn:feature_code":"PPL",
    "gn:name":"Kasanga",
    "gn:population":0,
    "gn:timezone":"Africa/Lubumbashi",
    "iso:country":"CD",
    "name:deu_x_preferred":[
        "Bismarckburg"
    ],
    "name:ron_x_preferred":[
        "Kasanga"
    ],
    "name:swa_x_preferred":[
        "Kasanga"
    ],
    "name:zho_x_preferred":[
        "\u5361\u6851\u52a0"
    ],
    "wof:name":"Kasanga",
    "wof:placetype":"locality"
},
  "geometry": {"coordinates":[23.18906,-10.98813],"type":"Point"}
}