{
  "type": "Feature",
  "properties": {
    "gn:admin1_code":"20.0",
    "gn:asciiname":"Kumbi Moteba",
    "gn:country_code":"CD",
    "gn:dem":775,
    "gn:feature_class":"P",
    "gn:feature_code":"PPL",
    "gn:name":"Kumbi Moteba",
    "gn:population":0,
    "gn:timezone":"Africa/Kinshasa",
    "iso:country":"CD",
    "wof:name":"Kumbi Moteba",
    "wof:placetype":"locality"
},
  "geometry": {"coordinates":[17.54474,-5.37616],"type":"Point"}
}