{
  "type": "Feature",
  "properties": {
    "gn:admin1_code":"2.0",
    "gn:asciiname":"Ibele",
    "gn:country_code":"CD",
    "gn:dem":322,
    "gn:feature_class":"P",
    "gn:feature_code":"PPL",
    "gn:name":"Ibele",
    "gn:population":0,
    "gn:timezone":"Africa/Kinshasa",
    "iso:country":"CD",
    "wof:name":"Ibele",
    "wof:placetype":"locality"
},
  "geometry": {"coordinates":[18.46667,-1.05],"type":"Point"}
}