{
  "type": "Feature",
  "properties": {
    "gn:admin1_code":"14.0",
    "gn:asciiname":"Kanioka",
    "gn:country_code":"CD",
    "gn:dem":1007,
    "gn:feature_class":"P",
    "gn:feature_code":"PPL",
    "gn:name":"Kanioka",
    "gn:population":0,
    "gn:timezone":"Africa/Lubumbashi",
    "iso:country":"CD",
    "wof:name":"Kanioka",
    "wof:placetype":"locality"
},
  "geometry": {"coordinates":[28.66372,-8.2408],"type":"Point"}
}