{
  "type": "Feature",
  "properties": {
    "gn:admin1_code":"20.0",
    "gn:asciiname":"Musanga",
    "gn:country_code":"CD",
    "gn:dem":844,
    "gn:feature_class":"P",
    "gn:feature_code":"PPL",
    "gn:name":"Musanga",
    "gn:population":0,
    "gn:timezone":"Africa/Kinshasa",
    "iso:country":"CD",
    "wof:name":"Musanga",
    "wof:placetype":"locality"
},
  "geometry": {"coordinates":[19.00174,-6.16715],"type":"Point"}
}