{
  "type": "Feature",
  "properties": {
    "gn:admin1_code":"14.0",
    "gn:asciiname":"Baya",
    "gn:country_code":"CD",
    "gn:dem":1297,
    "gn:feature_class":"P",
    "gn:feature_code":"PPL",
    "gn:name":"Baya",
    "gn:population":0,
    "gn:timezone":"Africa/Lubumbashi",
    "iso:country":"CD",
    "name:ara_x_preferred":[
        "\u0628\u0627\u064a\u0629"
    ],
    "name:ceb_x_preferred":[
        "Baya"
    ],
    "name:deu_x_preferred":[
        "Baya"
    ],
    "name:fra_x_preferred":[
        "Baya"
    ],
    "name:spa_x_preferred":[
        "Baya"
    ],
    "name:swe_x_preferred":[
        "Baya"
    ],
    "wof:name":"Baya",
    "wof:placetype":"locality"
},
  "geometry": {"coordinates":[27.45,-11.86667],"type":"Point"}
}