{
  "type": "Feature",
  "properties": {
    "gn:admin1_code":"22.0",
    "gn:asciiname":"Inabanza",
    "gn:country_code":"CD",
    "gn:dem":862,
    "gn:feature_class":"P",
    "gn:feature_code":"PPL",
    "gn:name":"Inabanza",
    "gn:population":0,
    "gn:timezone":"Africa/Lubumbashi",
    "iso:country":"CD",
    "wof:name":"Inabanza",
    "wof:placetype":"locality"
},
  "geometry": {"coordinates":[25.32335,-9.95361],"type":"Point"}
}