{
  "type": "Feature",
  "properties": {
    "gn:admin1_code":"13.0",
    "gn:asciiname":"Nzanga",
    "gn:country_code":"CD",
    "gn:dem":423,
    "gn:feature_class":"P",
    "gn:feature_code":"PPL",
    "gn:name":"Nzanga",
    "gn:population":0,
    "gn:timezone":"Africa/Lubumbashi",
    "iso:country":"CD",
    "wof:name":"Nzanga",
    "wof:placetype":"locality"
},
  "geometry": {"coordinates":[24.39561,2.87744],"type":"Point"}
}