{
  "type": "Feature",
  "properties": {
    "gn:admin1_code":"27.0",
    "gn:asciiname":"Omeonga",
    "gn:country_code":"CD",
    "gn:dem":569,
    "gn:feature_class":"P",
    "gn:feature_code":"PPL",
    "gn:name":"Omeonga",
    "gn:population":0,
    "gn:timezone":"Africa/Lubumbashi",
    "iso:country":"CD",
    "wof:name":"Omeonga",
    "wof:placetype":"locality"
},
  "geometry": {"coordinates":[24.46886,-3.67272],"type":"Point"}
}