{
  "type": "Feature",
  "properties": {
    "gn:admin1_code":"18.0",
    "gn:asciiname":"Kambembo",
    "gn:country_code":"CD",
    "gn:dem":556,
    "gn:feature_class":"P",
    "gn:feature_code":"PPL",
    "gn:name":"Kambembo",
    "gn:population":0,
    "gn:timezone":"Africa/Lubumbashi",
    "iso:country":"CD",
    "wof:name":"Kambembo",
    "wof:placetype":"locality"
},
  "geometry": {"coordinates":[20.49085,-4.67932],"type":"Point"}
}