{
  "type": "Feature",
  "properties": {
    "gn:admin1_code":"15.0",
    "gn:asciiname":"Kadibwe",
    "gn:country_code":"CD",
    "gn:dem":838,
    "gn:feature_class":"P",
    "gn:feature_code":"PPL",
    "gn:name":"Kadibwe",
    "gn:population":0,
    "gn:timezone":"Africa/Lubumbashi",
    "iso:country":"CD",
    "wof:name":"Kadibwe",
    "wof:placetype":"locality"
},
  "geometry": {"coordinates":[25.81193,-8.84724],"type":"Point"}
}