{
  "type": "Feature",
  "properties": {
    "gn:admin1_code":"20.0",
    "gn:asciiname":"Kibunze",
    "gn:country_code":"CD",
    "gn:dem":640,
    "gn:feature_class":"P",
    "gn:feature_code":"PPL",
    "gn:name":"Kibunze",
    "gn:population":0,
    "gn:timezone":"Africa/Kinshasa",
    "iso:country":"CD",
    "wof:name":"Kibunze",
    "wof:placetype":"locality"
},
  "geometry": {"coordinates":[19.78997,-5.59799],"type":"Point"}
}