{
  "type": "Feature",
  "properties": {
    "gn:admin1_code":"14.0",
    "gn:asciiname":"Kiamulimba",
    "gn:country_code":"CD",
    "gn:dem":1145,
    "gn:feature_class":"P",
    "gn:feature_code":"PPL",
    "gn:name":"Kiamulimba",
    "gn:population":0,
    "gn:timezone":"Africa/Lubumbashi",
    "iso:country":"CD",
    "wof:name":"Kiamulimba",
    "wof:placetype":"locality"
},
  "geometry": {"coordinates":[26.66194,-10.70972],"type":"Point"}
}