{
  "type": "Feature",
  "properties": {
    "gn:admin1_code":"8.0",
    "gn:asciiname":"Kinlungi",
    "gn:country_code":"CD",
    "gn:dem":628,
    "gn:feature_class":"P",
    "gn:feature_code":"PPL",
    "gn:name":"Kinlungi",
    "gn:population":0,
    "gn:timezone":"Africa/Kinshasa",
    "iso:country":"CD",
    "wof:name":"Kinlungi",
    "wof:placetype":"locality"
},
  "geometry": {"coordinates":[14.58614,-5.17514],"type":"Point"}
}