{
  "type": "Feature",
  "properties": {
    "gn:admin1_code":"30.0",
    "gn:asciiname":"Munamansi",
    "gn:country_code":"CD",
    "gn:dem":716,
    "gn:feature_class":"P",
    "gn:feature_code":"PPL",
    "gn:name":"Munamansi",
    "gn:population":0,
    "gn:timezone":"Africa/Lubumbashi",
    "iso:country":"CD",
    "name:und_x_variant":[
        "Munamangi",
        "Munamansi"
    ],
    "wof:name":"Munamansi",
    "wof:placetype":"locality"
},
  "geometry": {"coordinates":[28.15,0.13333],"type":"Point"}
}