{
  "type": "Feature",
  "properties": {
    "gn:admin1_code":"30.0",
    "gn:asciiname":"Bomoa",
    "gn:country_code":"CD",
    "gn:dem":470,
    "gn:feature_class":"P",
    "gn:feature_code":"PPL",
    "gn:name":"Bomoa",
    "gn:population":0,
    "gn:timezone":"Africa/Lubumbashi",
    "iso:country":"CD",
    "wof:name":"Bomoa",
    "wof:placetype":"locality"
},
  "geometry": {"coordinates":[25.24985,2.1886],"type":"Point"}
}