{
  "type": "Feature",
  "properties": {
    "gn:admin1_code":"22.0",
    "gn:asciiname":"Mbumba",
    "gn:country_code":"CD",
    "gn:dem":1069,
    "gn:feature_class":"P",
    "gn:feature_code":"PPL",
    "gn:name":"Mbumba",
    "gn:population":0,
    "gn:timezone":"Africa/Lubumbashi",
    "iso:country":"CD",
    "name:fra_x_preferred":[
        "Mbumba"
    ],
    "wof:name":"Mbumba",
    "wof:placetype":"locality"
},
  "geometry": {"coordinates":[23.89596,-9.49571],"type":"Point"}
}