{
  "type": "Feature",
  "properties": {
    "gn:admin1_code":"12.0",
    "gn:asciiname":"Musatiri",
    "gn:country_code":"CD",
    "gn:dem":800,
    "gn:feature_class":"P",
    "gn:feature_code":"PPL",
    "gn:name":"Musatiri",
    "gn:population":0,
    "gn:timezone":"Africa/Lubumbashi",
    "iso:country":"CD",
    "wof:name":"Musatiri",
    "wof:placetype":"locality"
},
  "geometry": {"coordinates":[29.08765,-4.10232],"type":"Point"}
}