{
  "type": "Feature",
  "properties": {
    "gn:admin1_code":"30.0",
    "gn:asciiname":"Bafwakalolo",
    "gn:country_code":"CD",
    "gn:dem":696,
    "gn:feature_class":"P",
    "gn:feature_code":"PPL",
    "gn:name":"Bafwakalolo",
    "gn:population":0,
    "gn:timezone":"Africa/Lubumbashi",
    "iso:country":"CD",
    "wof:name":"Bafwakalolo",
    "wof:placetype":"locality"
},
  "geometry": {"coordinates":[27.53365,1.24287],"type":"Point"}
}