{
  "type": "Feature",
  "properties": {
    "gn:admin1_code":"24.0",
    "gn:asciiname":"Sekeka",
    "gn:country_code":"CD",
    "gn:dem":394,
    "gn:feature_class":"P",
    "gn:feature_code":"PPL",
    "gn:name":"Sekeka",
    "gn:population":0,
    "gn:timezone":"Africa/Kinshasa",
    "iso:country":"CD",
    "wof:name":"Sekeka",
    "wof:placetype":"locality"
},
  "geometry": {"coordinates":[18.51893,-3.25959],"type":"Point"}
}