{
  "type": "Feature",
  "properties": {
    "gn:admin1_code":"20.0",
    "gn:asciiname":"Nsadi",
    "gn:country_code":"CD",
    "gn:dem":694,
    "gn:feature_class":"P",
    "gn:feature_code":"PPL",
    "gn:name":"Nsadi",
    "gn:population":0,
    "gn:timezone":"Africa/Kinshasa",
    "iso:country":"CD",
    "wof:name":"Nsadi",
    "wof:placetype":"locality"
},
  "geometry": {"coordinates":[19.38405,-6.21748],"type":"Point"}
}