{
  "type": "Feature",
  "properties": {
    "gn:admin1_code":"10.0",
    "gn:asciiname":"Motela Deuxieme",
    "gn:country_code":"CD",
    "gn:dem":580,
    "gn:feature_class":"P",
    "gn:feature_code":"PPL",
    "gn:name":"Motela Deuxi\u00e8me",
    "gn:population":0,
    "gn:timezone":"Africa/Lubumbashi",
    "iso:country":"CD",
    "wof:name":"Motela Deuxieme",
    "wof:placetype":"locality"
},
  "geometry": {"coordinates":[26.45347000000001,-1.79337],"type":"Point"}
}