{
  "type": "Feature",
  "properties": {
    "gn:admin1_code":"20.0",
    "gn:asciiname":"Samo",
    "gn:country_code":"CD",
    "gn:dem":433,
    "gn:feature_class":"P",
    "gn:feature_code":"PPL",
    "gn:name":"Samo",
    "gn:population":0,
    "gn:timezone":"Africa/Kinshasa",
    "iso:country":"CD",
    "wof:name":"Samo",
    "wof:placetype":"locality"
},
  "geometry": {"coordinates":[17.9956,-4.35217],"type":"Point"}
}