{
  "type": "Feature",
  "properties": {
    "gn:admin1_code":"22.0",
    "gn:asciiname":"Shipangu",
    "gn:country_code":"CD",
    "gn:dem":1102,
    "gn:feature_class":"P",
    "gn:feature_code":"PPL",
    "gn:name":"Shipangu",
    "gn:population":0,
    "gn:timezone":"Africa/Lubumbashi",
    "iso:country":"CD",
    "wof:name":"Shipangu",
    "wof:placetype":"locality"
},
  "geometry": {"coordinates":[23.92951,-10.1367],"type":"Point"}
}