{
  "type": "Feature",
  "properties": {
    "gn:admin1_code":"17.0",
    "gn:asciiname":"Ndele",
    "gn:country_code":"CD",
    "gn:dem":1284,
    "gn:feature_class":"P",
    "gn:feature_code":"PPL",
    "gn:name":"Ndele",
    "gn:population":0,
    "gn:timezone":"Africa/Lubumbashi",
    "iso:country":"CD",
    "name:ceb_x_preferred":[
        "Ndele"
    ],
    "name:deu_x_preferred":[
        "Ndele"
    ],
    "name:fas_x_preferred":[
        "\u0646\u062f\u0644"
    ],
    "name:heb_x_preferred":[
        "\u05e0\u05d3\u05dc\u05d4"
    ],
    "name:hun_x_preferred":[
        "Ndele"
    ],
    "name:swe_x_preferred":[
        "Ndele"
    ],
    "wof:name":"Ndele",
    "wof:placetype":"locality"
},
  "geometry": {"coordinates":[30.26667,1.51667],"type":"Point"}
}