{
  "type": "Feature",
  "properties": {
    "gn:admin1_code":"15.0",
    "gn:asciiname":"Kankebe",
    "gn:country_code":"CD",
    "gn:dem":761,
    "gn:feature_class":"P",
    "gn:feature_code":"PPL",
    "gn:name":"Kankebe",
    "gn:population":0,
    "gn:timezone":"Africa/Lubumbashi",
    "iso:country":"CD",
    "name:und_x_variant":[
        "Kankele"
    ],
    "wof:name":"Kankebe",
    "wof:placetype":"locality"
},
  "geometry": {"coordinates":[26.18516,-7.13503],"type":"Point"}
}