{
  "type": "Feature",
  "properties": {
    "gn:admin1_code":"22.0",
    "gn:asciiname":"Mukansa",
    "gn:country_code":"CD",
    "gn:dem":1307,
    "gn:feature_class":"P",
    "gn:feature_code":"PPL",
    "gn:name":"Mukansa",
    "gn:population":0,
    "gn:timezone":"Africa/Lubumbashi",
    "iso:country":"CD",
    "wof:name":"Mukansa",
    "wof:placetype":"locality"
},
  "geometry": {"coordinates":[25.08525,-11.15006],"type":"Point"}
}