{
  "type": "Feature",
  "properties": {
    "gn:admin1_code":"28.0",
    "gn:asciiname":"Bumbwa",
    "gn:country_code":"CD",
    "gn:dem":367,
    "gn:feature_class":"P",
    "gn:feature_code":"PPL",
    "gn:name":"Bumbwa",
    "gn:population":0,
    "gn:timezone":"Africa/Kinshasa",
    "iso:country":"CD",
    "wof:name":"Bumbwa",
    "wof:placetype":"locality"
},
  "geometry": {"coordinates":[18.74583,4.02083],"type":"Point"}
}