{
  "type": "Feature",
  "properties": {
    "gn:admin1_code":"12.0",
    "gn:asciiname":"Maga",
    "gn:country_code":"CD",
    "gn:dem":879,
    "gn:feature_class":"P",
    "gn:feature_code":"PPL",
    "gn:name":"Maga",
    "gn:population":0,
    "gn:timezone":"Africa/Lubumbashi",
    "iso:country":"CD",
    "name:ceb_x_preferred":[
        "Maga"
    ],
    "name:deu_x_preferred":[
        "Maga"
    ],
    "name:fra_x_preferred":[
        "Maga"
    ],
    "name:nds_x_preferred":[
        "Maga"
    ],
    "name:nld_x_preferred":[
        "Maga"
    ],
    "name:rus_x_preferred":[
        "\u041c\u0430\u0433\u0430"
    ],
    "name:spa_x_preferred":[
        "Maga"
    ],
    "name:swe_x_preferred":[
        "Maga"
    ],
    "name:ukr_x_preferred":[
        "\u041c\u0430\u0433\u0430"
    ],
    "wof:name":"Maga",
    "wof:placetype":"locality"
},
  "geometry": {"coordinates":[28.16667,-3.31667],"type":"Point"}
}