{
  "type": "Feature",
  "properties": {
    "gn:admin1_code":"14.0",
    "gn:asciiname":"Mwenga",
    "gn:country_code":"CD",
    "gn:dem":1137,
    "gn:feature_class":"P",
    "gn:feature_code":"PPL",
    "gn:name":"Mwenga",
    "gn:population":0,
    "gn:timezone":"Africa/Lubumbashi",
    "iso:country":"CD",
    "wof:name":"Mwenga",
    "wof:placetype":"locality"
},
  "geometry": {"coordinates":[26.69972000000001,-10.69583],"type":"Point"}
}