{
  "type": "Feature",
  "properties": {
    "gn:admin1_code":"20.0",
    "gn:asciiname":"Kiluma",
    "gn:country_code":"CD",
    "gn:dem":711,
    "gn:feature_class":"P",
    "gn:feature_code":"PPL",
    "gn:name":"Kiluma",
    "gn:population":0,
    "gn:timezone":"Africa/Kinshasa",
    "iso:country":"CD",
    "wof:name":"Kiluma",
    "wof:placetype":"locality"
},
  "geometry": {"coordinates":[18.64897,-5.42051],"type":"Point"}
}