{
  "type": "Feature",
  "properties": {
    "gn:admin1_code":"8.0",
    "gn:asciiname":"Kitombadio",
    "gn:country_code":"CD",
    "gn:dem":299,
    "gn:feature_class":"P",
    "gn:feature_code":"PPL",
    "gn:name":"Kitombadio",
    "gn:population":0,
    "gn:timezone":"Africa/Kinshasa",
    "iso:country":"CD",
    "wof:name":"Kitombadio",
    "wof:placetype":"locality"
},
  "geometry": {"coordinates":[13.95574,-5.58635],"type":"Point"}
}