{
  "type": "Feature",
  "properties": {
    "gn:admin1_code":"21.0",
    "gn:asciiname":"Kasenda",
    "gn:country_code":"CD",
    "gn:dem":865,
    "gn:feature_class":"P",
    "gn:feature_code":"PPL",
    "gn:name":"Kasenda",
    "gn:population":0,
    "gn:timezone":"Africa/Lubumbashi",
    "iso:country":"CD",
    "wof:name":"Kasenda",
    "wof:placetype":"locality"
},
  "geometry": {"coordinates":[25.13773,-6.44566],"type":"Point"}
}