{
  "type": "Feature",
  "properties": {
    "gn:admin1_code":"19.0",
    "gn:asciiname":"Ngelele",
    "gn:country_code":"CD",
    "gn:dem":427,
    "gn:feature_class":"P",
    "gn:feature_code":"PPL",
    "gn:name":"Ngelele",
    "gn:population":0,
    "gn:timezone":"Africa/Luanda",
    "iso:country":"CD",
    "wof:name":"Ngelele",
    "wof:placetype":"locality"
},
  "geometry": {"coordinates":[16.74273,-6.58306],"type":"Point"}
}