{
  "type": "Feature",
  "properties": {
    "gn:admin1_code":"14.0",
    "gn:asciiname":"Musabira",
    "gn:country_code":"CD",
    "gn:dem":872,
    "gn:feature_class":"P",
    "gn:feature_code":"PPL",
    "gn:name":"Musabira",
    "gn:population":0,
    "gn:timezone":"Africa/Lubumbashi",
    "iso:country":"CD",
    "wof:name":"Musabira",
    "wof:placetype":"locality"
},
  "geometry": {"coordinates":[27.04594,-9.5099],"type":"Point"}
}