{
  "type": "Feature",
  "properties": {
    "gn:admin1_code":"22.0",
    "gn:asciiname":"Kayiva",
    "gn:country_code":"CD",
    "gn:dem":1067,
    "gn:feature_class":"P",
    "gn:feature_code":"PPL",
    "gn:name":"Kayiva",
    "gn:population":0,
    "gn:timezone":"Africa/Lubumbashi",
    "iso:country":"CD",
    "wof:name":"Kayiva",
    "wof:placetype":"locality"
},
  "geometry": {"coordinates":[23.49878,-10.32361],"type":"Point"}
}