{
  "type": "Feature",
  "properties": {
    "gn:admin1_code":"15.0",
    "gn:asciiname":"Lundu",
    "gn:country_code":"CD",
    "gn:dem":1123,
    "gn:feature_class":"P",
    "gn:feature_code":"PPL",
    "gn:name":"Lundu",
    "gn:population":0,
    "gn:timezone":"Africa/Lubumbashi",
    "iso:country":"CD",
    "name:ceb_x_preferred":[
        "Lundu"
    ],
    "name:nld_x_preferred":[
        "Lundu"
    ],
    "name:swe_x_preferred":[
        "Lundu"
    ],
    "name:vie_x_preferred":[
        "Lundu"
    ],
    "wof:name":"Lundu",
    "wof:placetype":"locality"
},
  "geometry": {"coordinates":[24.7066,-8.69332],"type":"Point"}
}