{
  "type": "Feature",
  "properties": {
    "gn:admin1_code":"20.0",
    "gn:asciiname":"Shimba",
    "gn:country_code":"CD",
    "gn:dem":507,
    "gn:feature_class":"P",
    "gn:feature_code":"PPL",
    "gn:name":"Shimba",
    "gn:population":0,
    "gn:timezone":"Africa/Kinshasa",
    "iso:country":"CD",
    "wof:name":"Shimba",
    "wof:placetype":"locality"
},
  "geometry": {"coordinates":[19.85715,-4.60964],"type":"Point"}
}