{
  "type": "Feature",
  "properties": {
    "gn:admin1_code":"6.0",
    "gn:asciiname":"Kinati",
    "gn:country_code":"CD",
    "gn:dem":690,
    "gn:feature_class":"P",
    "gn:feature_code":"PPL",
    "gn:name":"Kinati",
    "gn:population":0,
    "gn:timezone":"Africa/Kinshasa",
    "iso:country":"CD",
    "wof:name":"Kinati",
    "wof:placetype":"locality"
},
  "geometry": {"coordinates":[15.86074,-4.42144],"type":"Point"}
}