{
  "type": "Feature",
  "properties": {
    "gn:admin1_code":"22.0",
    "gn:asciiname":"Kalonga",
    "gn:country_code":"CD",
    "gn:dem":995,
    "gn:feature_class":"P",
    "gn:feature_code":"PPL",
    "gn:name":"Kalonga",
    "gn:population":0,
    "gn:timezone":"Africa/Lubumbashi",
    "iso:country":"CD",
    "wof:name":"Kalonga",
    "wof:placetype":"locality"
},
  "geometry": {"coordinates":[26.54867,-10.25984],"type":"Point"}
}