{
  "type": "Feature",
  "properties": {
    "gn:admin1_code":"23.0",
    "gn:asciiname":"Kalonji-Batukonka",
    "gn:country_code":"CD",
    "gn:dem":633,
    "gn:feature_class":"P",
    "gn:feature_code":"PPL",
    "gn:name":"Kalonji-Batukonka",
    "gn:population":0,
    "gn:timezone":"Africa/Lubumbashi",
    "iso:country":"CD",
    "wof:name":"Kalonji-Batukonka",
    "wof:placetype":"locality"
},
  "geometry": {"coordinates":[22.30799,-5.95446],"type":"Point"}
}