{
  "type": "Feature",
  "properties": {
    "gn:admin1_code":"30.0",
    "gn:asciiname":"Yambela",
    "gn:country_code":"CD",
    "gn:dem":500,
    "gn:feature_class":"P",
    "gn:feature_code":"PPL",
    "gn:name":"Yambela",
    "gn:population":0,
    "gn:timezone":"Africa/Lubumbashi",
    "iso:country":"CD",
    "wof:name":"Yambela",
    "wof:placetype":"locality"
},
  "geometry": {"coordinates":[24.82743,0.32688],"type":"Point"}
}