{
  "type": "Feature",
  "properties": {
    "gn:admin1_code":"11.0",
    "gn:asciiname":"Kamuhole",
    "gn:country_code":"CD",
    "gn:dem":1464,
    "gn:feature_class":"P",
    "gn:feature_code":"PPL",
    "gn:name":"Kamuhole",
    "gn:population":0,
    "gn:timezone":"Africa/Lubumbashi",
    "iso:country":"CD",
    "wof:name":"Kamuhole",
    "wof:placetype":"locality"
},
  "geometry": {"coordinates":[28.78333,-1.68333],"type":"Point"}
}