{
  "type": "Feature",
  "properties": {
    "gn:admin1_code":"31.0",
    "gn:asciiname":"Bofila",
    "gn:country_code":"CD",
    "gn:dem":391,
    "gn:feature_class":"P",
    "gn:feature_code":"PPL",
    "gn:name":"Bofila",
    "gn:population":0,
    "gn:timezone":"Africa/Kinshasa",
    "iso:country":"CD",
    "wof:name":"Bofila",
    "wof:placetype":"locality"
},
  "geometry": {"coordinates":[21.15,-0.15],"type":"Point"}
}