{
  "type": "Feature",
  "properties": {
    "gn:admin1_code":"16.0",
    "gn:asciiname":"Mbali",
    "gn:country_code":"CD",
    "gn:dem":681,
    "gn:feature_class":"P",
    "gn:feature_code":"PPL",
    "gn:name":"Mbali",
    "gn:population":0,
    "gn:timezone":"Africa/Lubumbashi",
    "iso:country":"CD",
    "name:ceb_x_preferred":[
        "Mbali"
    ],
    "name:deu_x_preferred":[
        "Mbali"
    ],
    "name:swe_x_preferred":[
        "Mbali"
    ],
    "wof:name":"Mbali",
    "wof:placetype":"locality"
},
  "geometry": {"coordinates":[27.84962,3.18966],"type":"Point"}
}