{
  "type": "Feature",
  "properties": {
    "gn:admin1_code":"20.0",
    "gn:asciiname":"Ndzonto",
    "gn:country_code":"CD",
    "gn:dem":666,
    "gn:feature_class":"P",
    "gn:feature_code":"PPL",
    "gn:name":"Ndzonto",
    "gn:population":0,
    "gn:timezone":"Africa/Kinshasa",
    "iso:country":"CD",
    "wof:name":"Ndzonto",
    "wof:placetype":"locality"
},
  "geometry": {"coordinates":[19.27203,-5.04874],"type":"Point"}
}