{
  "type": "Feature",
  "properties": {
    "gn:admin1_code":"26.0",
    "gn:asciiname":"Kabe-Balakpwa",
    "gn:country_code":"CD",
    "gn:dem":390,
    "gn:feature_class":"P",
    "gn:feature_code":"PPL",
    "gn:name":"Kabe-Balakpwa",
    "gn:population":0,
    "gn:timezone":"Africa/Kinshasa",
    "iso:country":"CD",
    "wof:name":"Kabe-Balakpwa",
    "wof:placetype":"locality"
},
  "geometry": {"coordinates":[20.77407,3.92569],"type":"Point"}
}