{
  "type": "Feature",
  "properties": {
    "gn:admin1_code":"28.0",
    "gn:asciiname":"Mondongo",
    "gn:country_code":"CD",
    "gn:dem":330,
    "gn:feature_class":"P",
    "gn:feature_code":"PPL",
    "gn:name":"Mondongo",
    "gn:population":0,
    "gn:timezone":"Africa/Kinshasa",
    "iso:country":"CD",
    "name:fra_x_preferred":[
        "Mondongo"
    ],
    "wof:name":"Mondongo",
    "wof:placetype":"locality"
},
  "geometry": {"coordinates":[19.15608,2.27662],"type":"Point"}
}