{
  "type": "Feature",
  "properties": {
    "gn:admin1_code":"6.0",
    "gn:asciiname":"Kingono",
    "gn:country_code":"CD",
    "gn:dem":652,
    "gn:feature_class":"P",
    "gn:feature_code":"PPL",
    "gn:name":"Kingono",
    "gn:population":0,
    "gn:timezone":"Africa/Kinshasa",
    "iso:country":"CD",
    "wof:name":"Kingono",
    "wof:placetype":"locality"
},
  "geometry": {"coordinates":[16.36667000000001,-4.33333],"type":"Point"}
}