{
  "type": "Feature",
  "properties": {
    "gn:admin1_code":"4.0",
    "gn:asciiname":"Kajila-Bunyi",
    "gn:country_code":"CD",
    "gn:dem":771,
    "gn:feature_class":"P",
    "gn:feature_code":"PPL",
    "gn:name":"Kajila-Bunyi",
    "gn:population":0,
    "gn:timezone":"Africa/Lubumbashi",
    "iso:country":"CD",
    "wof:name":"Kajila-Bunyi",
    "wof:placetype":"locality"
},
  "geometry": {"coordinates":[23.29862,-6.30618],"type":"Point"}
}