{
  "type": "Feature",
  "properties": {
    "gn:admin1_code":"19.0",
    "gn:asciiname":"Mubanza",
    "gn:country_code":"CD",
    "gn:dem":875,
    "gn:feature_class":"P",
    "gn:feature_code":"PPL",
    "gn:name":"Mubanza",
    "gn:population":0,
    "gn:timezone":"Africa/Kinshasa",
    "iso:country":"CD",
    "wof:name":"Mubanza",
    "wof:placetype":"locality"
},
  "geometry": {"coordinates":[16.97494,-6.24689],"type":"Point"}
}