{
  "type": "Feature",
  "properties": {
    "gn:admin1_code":"22.0",
    "gn:asciiname":"Kalala",
    "gn:country_code":"CD",
    "gn:dem":1432,
    "gn:feature_class":"P",
    "gn:feature_code":"PPL",
    "gn:name":"Kalala",
    "gn:population":0,
    "gn:timezone":"Africa/Lubumbashi",
    "iso:country":"CD",
    "wof:name":"Kalala",
    "wof:placetype":"locality"
},
  "geometry": {"coordinates":[25.40393,-11.35411],"type":"Point"}
}