{
  "type": "Feature",
  "properties": {
    "gn:admin1_code":"18.0",
    "gn:asciiname":"Kasongo-Kakese",
    "gn:country_code":"CD",
    "gn:dem":663,
    "gn:feature_class":"P",
    "gn:feature_code":"PPL",
    "gn:name":"Kasongo-Kakese",
    "gn:population":0,
    "gn:timezone":"Africa/Lubumbashi",
    "iso:country":"CD",
    "wof:name":"Kasongo-Kakese",
    "wof:placetype":"locality"
},
  "geometry": {"coordinates":[21.23105,-6.55807],"type":"Point"}
}