{
  "type": "Feature",
  "properties": {
    "gn:admin1_code":"10.0",
    "gn:asciiname":"Katengo",
    "gn:country_code":"CD",
    "gn:dem":868,
    "gn:feature_class":"P",
    "gn:feature_code":"PPL",
    "gn:name":"Katengo",
    "gn:population":0,
    "gn:timezone":"Africa/Lubumbashi",
    "iso:country":"CD",
    "wof:name":"Katengo",
    "wof:placetype":"locality"
},
  "geometry": {"coordinates":[28.73183,-4.94057],"type":"Point"}
}