{
  "type": "Feature",
  "properties": {
    "gn:admin1_code":"21.0",
    "gn:asciiname":"Bena-Kazadi-Kavula",
    "gn:country_code":"CD",
    "gn:dem":720,
    "gn:feature_class":"P",
    "gn:feature_code":"PPL",
    "gn:name":"Bena-Kazadi-Kavula",
    "gn:population":0,
    "gn:timezone":"Africa/Lubumbashi",
    "iso:country":"CD",
    "wof:name":"Bena-Kazadi-Kavula",
    "wof:placetype":"locality"
},
  "geometry": {"coordinates":[24.02875,-7.08941],"type":"Point"}
}