{
  "type": "Feature",
  "properties": {
    "gn:admin1_code":"18.0",
    "gn:asciiname":"Mukalenge-Mukaji",
    "gn:country_code":"CD",
    "gn:dem":516,
    "gn:feature_class":"P",
    "gn:feature_code":"PPL",
    "gn:name":"Mukalenge-Mukaji",
    "gn:population":0,
    "gn:timezone":"Africa/Lubumbashi",
    "iso:country":"CD",
    "wof:name":"Mukalenge-Mukaji",
    "wof:placetype":"locality"
},
  "geometry": {"coordinates":[20.96181,-4.69775],"type":"Point"}
}