{
  "type": "Feature",
  "properties": {
    "gn:admin1_code":"17.0",
    "gn:asciiname":"Pesao",
    "gn:country_code":"CD",
    "gn:dem":707,
    "gn:feature_class":"P",
    "gn:feature_code":"PPL",
    "gn:name":"Pesao",
    "gn:population":0,
    "gn:timezone":"Africa/Lubumbashi",
    "iso:country":"CD",
    "wof:name":"Pesao",
    "wof:placetype":"locality"
},
  "geometry": {"coordinates":[28.20408,1.43198],"type":"Point"}
}