{
  "type": "Feature",
  "properties": {
    "gn:admin1_code":"15.0",
    "gn:asciiname":"Kavwaya",
    "gn:country_code":"CD",
    "gn:dem":902,
    "gn:feature_class":"P",
    "gn:feature_code":"PPL",
    "gn:name":"Kavwaya",
    "gn:population":0,
    "gn:timezone":"Africa/Lubumbashi",
    "iso:country":"CD",
    "name:und_x_variant":[
        "Kawaya",
        "Kavwaya"
    ],
    "wof:name":"Kavwaya",
    "wof:placetype":"locality"
},
  "geometry": {"coordinates":[25.06667,-9.76667],"type":"Point"}
}