{
  "type": "Feature",
  "properties": {
    "gn:admin1_code":"10.0",
    "gn:asciiname":"Lusangi",
    "gn:country_code":"CD",
    "gn:dem":745,
    "gn:feature_class":"P",
    "gn:feature_code":"PPL",
    "gn:name":"Lusangi",
    "gn:population":0,
    "gn:timezone":"Africa/Lubumbashi",
    "iso:country":"CD",
    "name:und_x_variant":[
        "Piani Lusangi",
        "Lusangi"
    ],
    "wof:name":"Lusangi",
    "wof:placetype":"locality"
},
  "geometry": {"coordinates":[27.12637,-4.64015],"type":"Point"}
}