{
  "type": "Feature",
  "properties": {
    "gn:admin1_code":"20.0",
    "gn:asciiname":"Lowala",
    "gn:country_code":"CD",
    "gn:dem":511,
    "gn:feature_class":"P",
    "gn:feature_code":"PPL",
    "gn:name":"Lowala",
    "gn:population":0,
    "gn:timezone":"Africa/Kinshasa",
    "iso:country":"CD",
    "wof:name":"Lowala",
    "wof:placetype":"locality"
},
  "geometry": {"coordinates":[18.99564,-5.16977],"type":"Point"}
}