{
  "type": "Feature",
  "properties": {
    "gn:admin1_code":"31.0",
    "gn:asciiname":"Kuse",
    "gn:country_code":"CD",
    "gn:dem":329,
    "gn:feature_class":"P",
    "gn:feature_code":"PPL",
    "gn:name":"Kuse",
    "gn:population":0,
    "gn:timezone":"Africa/Kinshasa",
    "iso:country":"CD",
    "wof:name":"Kuse",
    "wof:placetype":"locality"
},
  "geometry": {"coordinates":[19.93568,-0.24633],"type":"Point"}
}