{
  "type": "Feature",
  "properties": {
    "gn:admin1_code":"31.0",
    "gn:asciiname":"Ilombe",
    "gn:country_code":"CD",
    "gn:dem":381,
    "gn:feature_class":"P",
    "gn:feature_code":"PPL",
    "gn:name":"Ilombe",
    "gn:population":0,
    "gn:timezone":"Africa/Kinshasa",
    "iso:country":"CD",
    "wof:name":"Ilombe",
    "wof:placetype":"locality"
},
  "geometry": {"coordinates":[20.63333,-0.11667],"type":"Point"}
}