{
  "type": "Feature",
  "properties": {
    "gn:admin1_code":"2.0",
    "gn:asciiname":"Bolombo-Ikengo",
    "gn:country_code":"CD",
    "gn:dem":312,
    "gn:feature_class":"P",
    "gn:feature_code":"PPL",
    "gn:name":"Bolombo-Ikengo",
    "gn:population":0,
    "gn:timezone":"Africa/Kinshasa",
    "iso:country":"CD",
    "wof:name":"Bolombo-Ikengo",
    "wof:placetype":"locality"
},
  "geometry": {"coordinates":[18.93333,-0.26667],"type":"Point"}
}