{
  "type": "Feature",
  "properties": {
    "gn:admin1_code":"23.0",
    "gn:asciiname":"Mboi",
    "gn:country_code":"CD",
    "gn:dem":864,
    "gn:feature_class":"P",
    "gn:feature_code":"PPL",
    "gn:name":"Mboi",
    "gn:population":0,
    "gn:timezone":"Africa/Lubumbashi",
    "iso:country":"CD",
    "wof:name":"Mboi",
    "wof:placetype":"locality"
},
  "geometry": {"coordinates":[22.001,-6.84729],"type":"Point"}
}