{
  "type": "Feature",
  "properties": {
    "gn:admin1_code":"22.0",
    "gn:asciiname":"Lumbili",
    "gn:country_code":"CD",
    "gn:dem":1033,
    "gn:feature_class":"P",
    "gn:feature_code":"PPL",
    "gn:name":"Lumbili",
    "gn:population":0,
    "gn:timezone":"Africa/Lubumbashi",
    "iso:country":"CD",
    "wof:name":"Lumbili",
    "wof:placetype":"locality"
},
  "geometry": {"coordinates":[23.50939,-10.07856],"type":"Point"}
}