{
  "type": "Feature",
  "properties": {
    "gn:admin1_code":"19.0",
    "gn:asciiname":"Kabengo",
    "gn:country_code":"CD",
    "gn:dem":797,
    "gn:feature_class":"P",
    "gn:feature_code":"PPL",
    "gn:name":"Kabengo",
    "gn:population":0,
    "gn:timezone":"Africa/Kinshasa",
    "iso:country":"CD",
    "wof:name":"Kabengo",
    "wof:placetype":"locality"
},
  "geometry": {"coordinates":[18.11547,-7.96871],"type":"Point"}
}