{
  "type": "Feature",
  "properties": {
    "gn:admin1_code":"29.0",
    "gn:asciiname":"Kasongo",
    "gn:country_code":"CD",
    "gn:dem":700,
    "gn:feature_class":"P",
    "gn:feature_code":"PPL",
    "gn:name":"Kasongo",
    "gn:population":0,
    "gn:timezone":"Africa/Lubumbashi",
    "iso:country":"CD",
    "wof:name":"Kasongo",
    "wof:placetype":"locality"
},
  "geometry": {"coordinates":[27.55248,-6.1893],"type":"Point"}
}