{
  "type": "Feature",
  "properties": {
    "gn:admin1_code":"22.0",
    "gn:asciiname":"Kayeke",
    "gn:country_code":"CD",
    "gn:dem":1102,
    "gn:feature_class":"P",
    "gn:feature_code":"PPL",
    "gn:name":"Kayeke",
    "gn:population":0,
    "gn:timezone":"Africa/Lubumbashi",
    "iso:country":"CD",
    "wof:name":"Kayeke",
    "wof:placetype":"locality"
},
  "geometry": {"coordinates":[24.86879,-10.28928],"type":"Point"}
}