{
  "type": "Feature",
  "properties": {
    "gn:admin1_code":"22.0",
    "gn:asciiname":"Mumbumbu",
    "gn:country_code":"CD",
    "gn:dem":1171,
    "gn:feature_class":"P",
    "gn:feature_code":"PPL",
    "gn:name":"Mumbumbu",
    "gn:population":0,
    "gn:timezone":"Africa/Lubumbashi",
    "iso:country":"CD",
    "wof:name":"Mumbumbu",
    "wof:placetype":"locality"
},
  "geometry": {"coordinates":[23.94619,-10.2854],"type":"Point"}
}