{
  "type": "Feature",
  "properties": {
    "gn:admin1_code":"13.0",
    "gn:asciiname":"Moku",
    "gn:country_code":"CD",
    "gn:dem":617,
    "gn:feature_class":"P",
    "gn:feature_code":"PPL",
    "gn:name":"Moku",
    "gn:population":0,
    "gn:timezone":"Africa/Lubumbashi",
    "iso:country":"CD",
    "wof:name":"Moku",
    "wof:placetype":"locality"
},
  "geometry": {"coordinates":[25.96667,2.51667],"type":"Point"}
}