{
  "type": "Feature",
  "properties": {
    "gn:admin1_code":"15.0",
    "gn:asciiname":"Kalai-Yulu",
    "gn:country_code":"CD",
    "gn:dem":917,
    "gn:feature_class":"P",
    "gn:feature_code":"PPL",
    "gn:name":"Kalai-Yulu",
    "gn:population":0,
    "gn:timezone":"Africa/Lubumbashi",
    "iso:country":"CD",
    "wof:name":"Kalai-Yulu",
    "wof:placetype":"locality"
},
  "geometry": {"coordinates":[25.6039,-8.88525],"type":"Point"}
}