{
  "type": "Feature",
  "properties": {
    "gn:admin1_code":"16.0",
    "gn:asciiname":"Aniasu",
    "gn:country_code":"CD",
    "gn:dem":687,
    "gn:feature_class":"P",
    "gn:feature_code":"PPL",
    "gn:name":"Aniasu",
    "gn:population":0,
    "gn:timezone":"Africa/Lubumbashi",
    "iso:country":"CD",
    "name:und_x_variant":[
        "Asiasu"
    ],
    "wof:name":"Aniasu",
    "wof:placetype":"locality"
},
  "geometry": {"coordinates":[27.56986,3.62649],"type":"Point"}
}