{
  "type": "Feature",
  "properties": {
    "gn:admin1_code":"22.0",
    "gn:asciiname":"Mukendeye",
    "gn:country_code":"CD",
    "gn:dem":1063,
    "gn:feature_class":"P",
    "gn:feature_code":"PPL",
    "gn:name":"Mukendeye",
    "gn:population":0,
    "gn:timezone":"Africa/Lubumbashi",
    "iso:country":"CD",
    "wof:name":"Mukendeye",
    "wof:placetype":"locality"
},
  "geometry": {"coordinates":[24.52724,-10.2972],"type":"Point"}
}