{
  "type": "Feature",
  "properties": {
    "gn:admin1_code":"22.0",
    "gn:asciiname":"Musasha",
    "gn:country_code":"CD",
    "gn:dem":1378,
    "gn:feature_class":"P",
    "gn:feature_code":"PPL",
    "gn:name":"Musasha",
    "gn:population":0,
    "gn:timezone":"Africa/Lubumbashi",
    "iso:country":"CD",
    "wof:name":"Musasha",
    "wof:placetype":"locality"
},
  "geometry": {"coordinates":[26.06364,-9.88965],"type":"Point"}
}