{
  "type": "Feature",
  "properties": {
    "gn:admin1_code":"18.0",
    "gn:asciiname":"Shatatshi",
    "gn:country_code":"CD",
    "gn:dem":505,
    "gn:feature_class":"P",
    "gn:feature_code":"PPL",
    "gn:name":"Shatatshi",
    "gn:population":0,
    "gn:timezone":"Africa/Lubumbashi",
    "iso:country":"CD",
    "name:und_x_variant":[
        "Satatshi",
        "Shatatshi"
    ],
    "wof:name":"Shatatshi",
    "wof:placetype":"locality"
},
  "geometry": {"coordinates":[20.28333,-4.63333],"type":"Point"}
}