{
  "type": "Feature",
  "properties": {
    "gn:admin1_code":"22.0",
    "gn:asciiname":"Kakunyi",
    "gn:country_code":"CD",
    "gn:dem":964,
    "gn:feature_class":"P",
    "gn:feature_code":"PPL",
    "gn:name":"Kakunyi",
    "gn:population":0,
    "gn:timezone":"Africa/Lubumbashi",
    "iso:country":"CD",
    "wof:name":"Kakunyi",
    "wof:placetype":"locality"
},
  "geometry": {"coordinates":[22.04523,-8.30322],"type":"Point"}
}