{
  "type": "Feature",
  "properties": {
    "gn:admin1_code":"31.0",
    "gn:asciiname":"Lotulu",
    "gn:country_code":"CD",
    "gn:dem":435,
    "gn:feature_class":"P",
    "gn:feature_code":"PPL",
    "gn:name":"Lotulu",
    "gn:population":0,
    "gn:timezone":"Africa/Kinshasa",
    "iso:country":"CD",
    "wof:name":"Lotulu",
    "wof:placetype":"locality"
},
  "geometry": {"coordinates":[21.95,0.45],"type":"Point"}
}