{
  "type": "Feature",
  "properties": {
    "gn:admin1_code":"30.0",
    "gn:asciiname":"Bangupa",
    "gn:country_code":"CD",
    "gn:dem":459,
    "gn:feature_class":"P",
    "gn:feature_code":"PPL",
    "gn:name":"Bangupa",
    "gn:population":0,
    "gn:timezone":"Africa/Lubumbashi",
    "iso:country":"CD",
    "wof:name":"Bangupa",
    "wof:placetype":"locality"
},
  "geometry": {"coordinates":[26.14368,0.67405],"type":"Point"}
}