{
  "type": "Feature",
  "properties": {
    "gn:admin1_code":"18.0",
    "gn:asciiname":"Shongolo-Gwapitshi",
    "gn:country_code":"CD",
    "gn:dem":552,
    "gn:feature_class":"P",
    "gn:feature_code":"PPL",
    "gn:name":"Shongolo-Gwapitshi",
    "gn:population":0,
    "gn:timezone":"Africa/Lubumbashi",
    "iso:country":"CD",
    "wof:name":"Shongolo-Gwapitshi",
    "wof:placetype":"locality"
},
  "geometry": {"coordinates":[20.86113,-4.78523],"type":"Point"}
}