{
  "type": "Feature",
  "properties": {
    "gn:admin1_code":"19.0",
    "gn:asciiname":"Mawunga",
    "gn:country_code":"CD",
    "gn:dem":595,
    "gn:feature_class":"P",
    "gn:feature_code":"PPL",
    "gn:name":"Mawunga",
    "gn:population":0,
    "gn:timezone":"Africa/Kinshasa",
    "iso:country":"CD",
    "wof:name":"Mawunga",
    "wof:placetype":"locality"
},
  "geometry": {"coordinates":[17.1248,-5.071],"type":"Point"}
}