{
  "type": "Feature",
  "properties": {
    "gn:admin1_code":"29.0",
    "gn:asciiname":"Fwampa",
    "gn:country_code":"CD",
    "gn:dem":1939,
    "gn:feature_class":"P",
    "gn:feature_code":"PPL",
    "gn:name":"Fwampa",
    "gn:population":0,
    "gn:timezone":"Africa/Lubumbashi",
    "iso:country":"CD",
    "wof:name":"Fwampa",
    "wof:placetype":"locality"
},
  "geometry": {"coordinates":[30.15,-7.51667],"type":"Point"}
}