{
  "type": "Feature",
  "properties": {
    "gn:admin1_code":"21.0",
    "gn:asciiname":"Bimbo",
    "gn:country_code":"CD",
    "gn:dem":705,
    "gn:feature_class":"P",
    "gn:feature_code":"PPL",
    "gn:name":"Bimbo",
    "gn:population":0,
    "gn:timezone":"Africa/Lubumbashi",
    "iso:country":"CD",
    "name:und_x_variant":[
        "Dimbo",
        "Bimbo"
    ],
    "wof:name":"Bimbo",
    "wof:placetype":"locality"
},
  "geometry": {"coordinates":[25.44182,-5.65277],"type":"Point"}
}