{
  "type": "Feature",
  "properties": {
    "gn:admin1_code":"21.0",
    "gn:asciiname":"Bimbo",
    "gn:country_code":"CD",
    "gn:dem":705,
    "gn:feature_class":"P",
    "gn:feature_code":"PPL",
    "gn:name":"Bimbo",
    "gn:population":0,
    "gn:timezone":"Africa/Lubumbashi",
    "iso:country":"CD",
    "name:deu_x_preferred":[
        "Bimbo"
    ],
    "name:fas_x_preferred":[
        "\u0628\u06cc\u0645\u0628\u0648"
    ],
    "name:fra_x_preferred":[
        "Bimbo"
    ],
    "name:hin_x_preferred":[
        "\u092c\u093f\u092e\u094d\u092c\u094b"
    ],
    "name:ita_x_preferred":[
        "Bimbo"
    ],
    "name:nor_x_preferred":[
        "Bimbo"
    ],
    "name:spa_x_preferred":[
        "Bimbo"
    ],
    "name:sqi_x_preferred":[
        "Bimbo"
    ],
    "name:tel_x_preferred":[
        "\u0c2c\u0c3f\u0c2e\u0c4d\u0c2c\u0c4b"
    ],
    "name:und_x_variant":[
        "Dimbo",
        "Bimbo"
    ],
    "wof:name":"Bimbo",
    "wof:placetype":"locality"
},
  "geometry": {"coordinates":[25.44182,-5.65277],"type":"Point"}
}