{
  "type": "Feature",
  "properties": {
    "gn:admin1_code":"22.0",
    "gn:asciiname":"Djika-Twita",
    "gn:country_code":"CD",
    "gn:dem":921,
    "gn:feature_class":"P",
    "gn:feature_code":"PPL",
    "gn:name":"Djika-Twita",
    "gn:population":0,
    "gn:timezone":"Africa/Lubumbashi",
    "iso:country":"CD",
    "wof:name":"Djika-Twita",
    "wof:placetype":"locality"
},
  "geometry": {"coordinates":[22.59901,-9.0897],"type":"Point"}
}