{
  "type": "Feature",
  "properties": {
    "gn:admin1_code":"29.0",
    "gn:asciiname":"Nkoba",
    "gn:country_code":"CD",
    "gn:dem":1515,
    "gn:feature_class":"P",
    "gn:feature_code":"PPL",
    "gn:name":"Nkoba",
    "gn:population":0,
    "gn:timezone":"Africa/Lubumbashi",
    "iso:country":"CD",
    "name:und_x_variant":[
        "Koba",
        "Nkoba"
    ],
    "wof:name":"Nkoba",
    "wof:placetype":"locality"
},
  "geometry": {"coordinates":[29.1609,-7.24053],"type":"Point"}
}