{
  "type": "Feature",
  "properties": {
    "gn:admin1_code":"16.0",
    "gn:asciiname":"Didema",
    "gn:country_code":"CD",
    "gn:dem":802,
    "gn:feature_class":"P",
    "gn:feature_code":"PPL",
    "gn:name":"Didema",
    "gn:population":0,
    "gn:timezone":"Africa/Lubumbashi",
    "iso:country":"CD",
    "wof:name":"Didema",
    "wof:placetype":"locality"
},
  "geometry": {"coordinates":[27.9246,2.48848],"type":"Point"}
}