{
  "type": "Feature",
  "properties": {
    "gn:admin1_code":"27.0",
    "gn:asciiname":"Tshileta",
    "gn:country_code":"CD",
    "gn:dem":428,
    "gn:feature_class":"P",
    "gn:feature_code":"PPL",
    "gn:name":"Tshileta",
    "gn:population":0,
    "gn:timezone":"Africa/Lubumbashi",
    "iso:country":"CD",
    "name:und_x_variant":[
        "Tshiteta"
    ],
    "wof:name":"Tshileta",
    "wof:placetype":"locality"
},
  "geometry": {"coordinates":[23.43205,-4.99377],"type":"Point"}
}