{
  "type": "Feature",
  "properties": {
    "gn:admin1_code":"13.0",
    "gn:asciiname":"Mongo-Mokpongobo",
    "gn:country_code":"CD",
    "gn:dem":506,
    "gn:feature_class":"P",
    "gn:feature_code":"PPL",
    "gn:name":"Mongo-Mokpongobo",
    "gn:population":0,
    "gn:timezone":"Africa/Lubumbashi",
    "iso:country":"CD",
    "wof:name":"Mongo-Mokpongobo",
    "wof:placetype":"locality"
},
  "geometry": {"coordinates":[23.42679,3.04169],"type":"Point"}
}