{
  "type": "Feature",
  "properties": {
    "gn:admin1_code":"19.0",
    "gn:asciiname":"Tshikondo",
    "gn:country_code":"CD",
    "gn:dem":1031,
    "gn:feature_class":"P",
    "gn:feature_code":"PPL",
    "gn:name":"Tshikondo",
    "gn:population":0,
    "gn:timezone":"Africa/Kinshasa",
    "iso:country":"CD",
    "wof:name":"Tshikondo",
    "wof:placetype":"locality"
},
  "geometry": {"coordinates":[18.52649,-6.94011],"type":"Point"}
}