{
  "type": "Feature",
  "properties": {
    "gn:admin1_code":"21.0",
    "gn:asciiname":"Miombe Mwavi Premiere",
    "gn:country_code":"CD",
    "gn:dem":754,
    "gn:feature_class":"P",
    "gn:feature_code":"PPL",
    "gn:name":"Miombe Mwavi Premi\u00e8re",
    "gn:population":0,
    "gn:timezone":"Africa/Lubumbashi",
    "iso:country":"CD",
    "name:und_x_variant":[
        "Miombe-Mwavi",
        "Miombe Mwavi I",
        "Miombe Mwavi Premi\u00e8re",
        "Miombe"
    ],
    "wof:name":"Miombe Mwavi Premiere",
    "wof:placetype":"locality"
},
  "geometry": {"coordinates":[24.65841,-5.86182],"type":"Point"}
}