{
  "type": "Feature",
  "properties": {
    "gn:admin1_code":"30.0",
    "gn:asciiname":"Okongo",
    "gn:country_code":"CD",
    "gn:dem":722,
    "gn:feature_class":"P",
    "gn:feature_code":"PPL",
    "gn:name":"Okongo",
    "gn:population":0,
    "gn:timezone":"Africa/Lubumbashi",
    "iso:country":"CD",
    "wof:name":"Okongo",
    "wof:placetype":"locality"
},
  "geometry": {"coordinates":[27.23742,0.40205],"type":"Point"}
}