{
  "type": "Feature",
  "properties": {
    "gn:admin1_code":"8.0",
    "gn:asciiname":"Kinsangi",
    "gn:country_code":"CD",
    "gn:dem":612,
    "gn:feature_class":"P",
    "gn:feature_code":"PPL",
    "gn:name":"Kinsangi",
    "gn:population":0,
    "gn:timezone":"Africa/Kinshasa",
    "iso:country":"CD",
    "wof:name":"Kinsangi",
    "wof:placetype":"locality"
},
  "geometry": {"coordinates":[15.34862,-5.00765],"type":"Point"}
}