{
  "type": "Feature",
  "properties": {
    "gn:admin1_code":"13.0",
    "gn:asciiname":"Abogandra",
    "gn:country_code":"CD",
    "gn:dem":709,
    "gn:feature_class":"P",
    "gn:feature_code":"PPL",
    "gn:name":"Abogandra",
    "gn:population":0,
    "gn:timezone":"Africa/Lubumbashi",
    "iso:country":"CD",
    "wof:name":"Abogandra",
    "wof:placetype":"locality"
},
  "geometry": {"coordinates":[26.81835,2.60947],"type":"Point"}
}