{
  "type": "Feature",
  "properties": {
    "gn:admin1_code":"23.0",
    "gn:asciiname":"Tshisenge",
    "gn:country_code":"CD",
    "gn:dem":851,
    "gn:feature_class":"P",
    "gn:feature_code":"PPL",
    "gn:name":"Tshisenge",
    "gn:population":0,
    "gn:timezone":"Africa/Lubumbashi",
    "iso:country":"CD",
    "wof:name":"Tshisenge",
    "wof:placetype":"locality"
},
  "geometry": {"coordinates":[21.90115,-6.93248],"type":"Point"}
}