{
  "type": "Feature",
  "properties": {
    "gn:admin1_code":"27.0",
    "gn:asciiname":"Futela",
    "gn:country_code":"CD",
    "gn:dem":488,
    "gn:feature_class":"P",
    "gn:feature_code":"PPL",
    "gn:name":"Futela",
    "gn:population":0,
    "gn:timezone":"Africa/Lubumbashi",
    "iso:country":"CD",
    "wof:name":"Futela",
    "wof:placetype":"locality"
},
  "geometry": {"coordinates":[23.19977,-4.38252],"type":"Point"}
}