{
  "type": "Feature",
  "properties": {
    "gn:admin1_code":"20.0",
    "gn:asciiname":"Banza-Kikumba",
    "gn:country_code":"CD",
    "gn:dem":691,
    "gn:feature_class":"P",
    "gn:feature_code":"PPL",
    "gn:name":"Banza-Kikumba",
    "gn:population":0,
    "gn:timezone":"Africa/Kinshasa",
    "iso:country":"CD",
    "name:und_x_variant":[
        "Banza",
        "Banza-Kikumba"
    ],
    "wof:name":"Banza-Kikumba",
    "wof:placetype":"locality"
},
  "geometry": {"coordinates":[18.34277,-4.98358],"type":"Point"}
}