{
  "type": "Feature",
  "properties": {
    "gn:admin1_code":"29.0",
    "gn:asciiname":"Sulumba",
    "gn:country_code":"CD",
    "gn:dem":728,
    "gn:feature_class":"P",
    "gn:feature_code":"PPL",
    "gn:name":"Sulumba",
    "gn:population":0,
    "gn:timezone":"Africa/Lubumbashi",
    "iso:country":"CD",
    "wof:name":"Sulumba",
    "wof:placetype":"locality"
},
  "geometry": {"coordinates":[27.76134,-5.55918],"type":"Point"}
}