{
  "type": "Feature",
  "properties": {
    "gn:admin1_code":"17.0",
    "gn:asciiname":"Aluna",
    "gn:country_code":"CD",
    "gn:dem":892,
    "gn:feature_class":"P",
    "gn:feature_code":"PPL",
    "gn:name":"Aluna",
    "gn:population":0,
    "gn:timezone":"Africa/Lubumbashi",
    "iso:country":"CD",
    "name:spa_x_preferred":[
        "Aluna"
    ],
    "wof:name":"Aluna",
    "wof:placetype":"locality"
},
  "geometry": {"coordinates":[29.23487,0.92081],"type":"Point"}
}