{
  "type": "Feature",
  "properties": {
    "gn:admin1_code":"28.0",
    "gn:asciiname":"Bosengwene",
    "gn:country_code":"CD",
    "gn:dem":411,
    "gn:feature_class":"P",
    "gn:feature_code":"PPL",
    "gn:name":"Bosengwene",
    "gn:population":0,
    "gn:timezone":"Africa/Kinshasa",
    "iso:country":"CD",
    "wof:name":"Bosengwene",
    "wof:placetype":"locality"
},
  "geometry": {"coordinates":[19.71867,3.24209],"type":"Point"}
}