{
  "type": "Feature",
  "properties": {
    "gn:admin1_code":"8.0",
    "gn:asciiname":"Mawu",
    "gn:country_code":"CD",
    "gn:dem":464,
    "gn:feature_class":"P",
    "gn:feature_code":"PPL",
    "gn:name":"Mawu",
    "gn:population":0,
    "gn:timezone":"Africa/Kinshasa",
    "iso:country":"CD",
    "name:bul_x_preferred":[
        "\u041c\u0430\u0432\u0443"
    ],
    "name:fin_x_preferred":[
        "Mawu"
    ],
    "name:fra_x_preferred":[
        "Mawu"
    ],
    "name:nld_x_preferred":[
        "Mawu"
    ],
    "name:por_x_preferred":[
        "Mawu"
    ],
    "name:slv_x_preferred":[
        "Mawu"
    ],
    "name:swe_x_preferred":[
        "Mawu"
    ],
    "name:tur_x_preferred":[
        "Mawu"
    ],
    "wof:name":"Mawu",
    "wof:placetype":"locality"
},
  "geometry": {"coordinates":[15.13528,-4.73201],"type":"Point"}
}