{
  "type": "Feature",
  "properties": {
    "gn:admin1_code":"19.0",
    "gn:asciiname":"Bwangongo",
    "gn:country_code":"CD",
    "gn:dem":863,
    "gn:feature_class":"P",
    "gn:feature_code":"PPL",
    "gn:name":"Bwangongo",
    "gn:population":0,
    "gn:timezone":"Africa/Kinshasa",
    "iso:country":"CD",
    "wof:name":"Bwangongo",
    "wof:placetype":"locality"
},
  "geometry": {"coordinates":[17.542,-6.44646],"type":"Point"}
}