{
  "type": "Feature",
  "properties": {
    "gn:admin1_code":"20.0",
    "gn:asciiname":"Kakoi",
    "gn:country_code":"CD",
    "gn:dem":463,
    "gn:feature_class":"P",
    "gn:feature_code":"PPL",
    "gn:name":"Kakoi",
    "gn:population":0,
    "gn:timezone":"Africa/Kinshasa",
    "iso:country":"CD",
    "wof:name":"Kakoi",
    "wof:placetype":"locality"
},
  "geometry": {"coordinates":[18.931,-5.1064],"type":"Point"}
}