{
  "type": "Feature",
  "properties": {
    "gn:admin1_code":"24.0",
    "gn:asciiname":"Lewo",
    "gn:country_code":"CD",
    "gn:dem":459,
    "gn:feature_class":"P",
    "gn:feature_code":"PPL",
    "gn:name":"Lewo",
    "gn:population":0,
    "gn:timezone":"Africa/Kinshasa",
    "iso:country":"CD",
    "wof:name":"Lewo",
    "wof:placetype":"locality"
},
  "geometry": {"coordinates":[16.3069,-2.62717],"type":"Point"}
}