{
  "type": "Feature",
  "properties": {
    "gn:admin1_code":"30.0",
    "gn:asciiname":"Yandjali",
    "gn:country_code":"CD",
    "gn:dem":401,
    "gn:feature_class":"P",
    "gn:feature_code":"PPL",
    "gn:name":"Yandjali",
    "gn:population":0,
    "gn:timezone":"Africa/Lubumbashi",
    "iso:country":"CD",
    "wof:name":"Yandjali",
    "wof:placetype":"locality"
},
  "geometry": {"coordinates":[24.14436,0.65606],"type":"Point"}
}