{
  "type": "Feature",
  "properties": {
    "gn:admin1_code":"29.0",
    "gn:asciiname":"Kalongwe",
    "gn:country_code":"CD",
    "gn:dem":1394,
    "gn:feature_class":"P",
    "gn:feature_code":"PPL",
    "gn:name":"Kalongwe",
    "gn:population":0,
    "gn:timezone":"Africa/Lubumbashi",
    "iso:country":"CD",
    "wof:name":"Kalongwe",
    "wof:placetype":"locality"
},
  "geometry": {"coordinates":[28.64495,-7.54251],"type":"Point"}
}