{
  "type": "Feature",
  "properties": {
    "gn:admin1_code":"12.0",
    "gn:asciiname":"Bunyakiri",
    "gn:country_code":"CD",
    "gn:dem":1105,
    "gn:feature_class":"P",
    "gn:feature_code":"PPL",
    "gn:name":"Bunyakiri",
    "gn:population":0,
    "gn:timezone":"Africa/Lubumbashi",
    "iso:country":"CD",
    "name:fra_x_preferred":[
        "Bunyakiri"
    ],
    "wof:name":"Bunyakiri",
    "wof:placetype":"locality"
},
  "geometry": {"coordinates":[28.56424,-2.07232],"type":"Point"}
}