{
  "type": "Feature",
  "properties": {
    "gn:admin1_code":"22.0",
    "gn:asciiname":"Kandjikandji",
    "gn:country_code":"CD",
    "gn:dem":981,
    "gn:feature_class":"P",
    "gn:feature_code":"PPL",
    "gn:name":"Kandjikandji",
    "gn:population":0,
    "gn:timezone":"Africa/Lubumbashi",
    "iso:country":"CD",
    "wof:name":"Kandjikandji",
    "wof:placetype":"locality"
},
  "geometry": {"coordinates":[23.0261,-10.1205],"type":"Point"}
}