{
  "type": "Feature",
  "properties": {
    "gn:admin1_code":"15.0",
    "gn:asciiname":"Kabudji",
    "gn:country_code":"CD",
    "gn:dem":658,
    "gn:feature_class":"P",
    "gn:feature_code":"PPL",
    "gn:name":"Kabudji",
    "gn:population":0,
    "gn:timezone":"Africa/Lubumbashi",
    "iso:country":"CD",
    "name:und_x_variant":[
        "Kabunji",
        "Kabudji",
        "Kabundji"
    ],
    "wof:name":"Kabudji",
    "wof:placetype":"locality"
},
  "geometry": {"coordinates":[26.07704,-8.17251],"type":"Point"}
}