{
  "type": "Feature",
  "properties": {
    "gn:admin1_code":"30.0",
    "gn:asciiname":"Yamasela",
    "gn:country_code":"CD",
    "gn:dem":410,
    "gn:feature_class":"P",
    "gn:feature_code":"PPL",
    "gn:name":"Yamasela",
    "gn:population":0,
    "gn:timezone":"Africa/Lubumbashi",
    "iso:country":"CD",
    "wof:name":"Yamasela",
    "wof:placetype":"locality"
},
  "geometry": {"coordinates":[23.6451,1.78371],"type":"Point"}
}