{
  "type": "Feature",
  "properties": {
    "gn:admin1_code":"26.0",
    "gn:asciiname":"Bubanda",
    "gn:country_code":"CD",
    "gn:dem":390,
    "gn:feature_class":"P",
    "gn:feature_code":"PPL",
    "gn:name":"Bubanda",
    "gn:population":0,
    "gn:timezone":"Africa/Kinshasa",
    "iso:country":"CD",
    "name:und_x_variant":[
        "Bobanda",
        "Bubanda"
    ],
    "wof:name":"Bubanda",
    "wof:placetype":"locality"
},
  "geometry": {"coordinates":[19.62308,4.23447],"type":"Point"}
}