{
  "type": "Feature",
  "properties": {
    "gn:admin1_code":"22.0",
    "gn:asciiname":"Tshikaji",
    "gn:country_code":"CD",
    "gn:dem":1078,
    "gn:feature_class":"P",
    "gn:feature_code":"PPL",
    "gn:name":"Tshikaji",
    "gn:population":0,
    "gn:timezone":"Africa/Lubumbashi",
    "iso:country":"CD",
    "name:und_x_variant":[
        "Tshikashi",
        "Tshikaji"
    ],
    "wof:name":"Tshikaji",
    "wof:placetype":"locality"
},
  "geometry": {"coordinates":[24.7671,-10.54412],"type":"Point"}
}