{
  "type": "Feature",
  "properties": {
    "gn:admin1_code":"15.0",
    "gn:asciiname":"Mwindia",
    "gn:country_code":"CD",
    "gn:dem":668,
    "gn:feature_class":"P",
    "gn:feature_code":"PPL",
    "gn:name":"Mwindia",
    "gn:population":0,
    "gn:timezone":"Africa/Lubumbashi",
    "iso:country":"CD",
    "name:und_x_variant":[
        "Mwidia",
        "Mwidya",
        "Mwindia"
    ],
    "wof:name":"Mwindia",
    "wof:placetype":"locality"
},
  "geometry": {"coordinates":[25.79511,-9.40211],"type":"Point"}
}