{
  "type": "Feature",
  "properties": {
    "gn:admin1_code":"23.0",
    "gn:asciiname":"Tshibanda-Kadiala",
    "gn:country_code":"CD",
    "gn:dem":636,
    "gn:feature_class":"P",
    "gn:feature_code":"PPL",
    "gn:name":"Tshibanda-Kadiala",
    "gn:population":0,
    "gn:timezone":"Africa/Lubumbashi",
    "iso:country":"CD",
    "wof:name":"Tshibanda-Kadiala",
    "wof:placetype":"locality"
},
  "geometry": {"coordinates":[22.30733,-5.96115],"type":"Point"}
}