{
  "type": "Feature",
  "properties": {
    "gn:admin1_code":"8.0",
    "gn:asciiname":"Kitona",
    "gn:country_code":"CD",
    "gn:dem":115,
    "gn:feature_class":"P",
    "gn:feature_code":"PPL",
    "gn:name":"Kitona",
    "gn:population":0,
    "gn:timezone":"Africa/Kinshasa",
    "iso:country":"CD",
    "name:ceb_x_preferred":[
        "Kitona"
    ],
    "name:fra_x_preferred":[
        "Kitona"
    ],
    "name:kor_x_preferred":[
        "\ud0a4\ud1a0\ub098"
    ],
    "name:ron_x_preferred":[
        "Kitona"
    ],
    "name:rus_x_preferred":[
        "\u041a\u0438\u0442\u043e\u043d\u0430"
    ],
    "name:spa_x_preferred":[
        "Kitona"
    ],
    "name:swe_x_preferred":[
        "Kitona"
    ],
    "wof:name":"Kitona",
    "wof:placetype":"locality"
},
  "geometry": {"coordinates":[12.45403,-5.96666],"type":"Point"}
}