{
  "type": "Feature",
  "properties": {
    "gn:admin1_code":"22.0",
    "gn:asciiname":"Mokombo",
    "gn:country_code":"CD",
    "gn:dem":1022,
    "gn:feature_class":"P",
    "gn:feature_code":"PPL",
    "gn:name":"Mokombo",
    "gn:population":0,
    "gn:timezone":"Africa/Lubumbashi",
    "iso:country":"CD",
    "wof:name":"Mokombo",
    "wof:placetype":"locality"
},
  "geometry": {"coordinates":[24.47975,-10.1827],"type":"Point"}
}