{
  "type": "Feature",
  "properties": {
    "gn:admin1_code":"8.0",
    "gn:asciiname":"Vanga",
    "gn:country_code":"CD",
    "gn:dem":507,
    "gn:feature_class":"P",
    "gn:feature_code":"PPL",
    "gn:name":"Vanga",
    "gn:population":0,
    "gn:timezone":"Africa/Kinshasa",
    "iso:country":"CD",
    "name:und_x_variant":[
        "Venga",
        "Vanga",
        "Vungu"
    ],
    "wof:name":"Vanga",
    "wof:placetype":"locality"
},
  "geometry": {"coordinates":[13.28382,-5.42159],"type":"Point"}
}