{
  "type": "Feature",
  "properties": {
    "gn:admin1_code":"15.0",
    "gn:asciiname":"Saikulu",
    "gn:country_code":"CD",
    "gn:dem":1092,
    "gn:feature_class":"P",
    "gn:feature_code":"PPL",
    "gn:name":"Saikulu",
    "gn:population":0,
    "gn:timezone":"Africa/Lubumbashi",
    "iso:country":"CD",
    "wof:name":"Saikulu",
    "wof:placetype":"locality"
},
  "geometry": {"coordinates":[23.7301,-8.51424],"type":"Point"}
}