{
  "type": "Feature",
  "properties": {
    "gn:admin1_code":"25.0",
    "gn:asciiname":"Yamolengeli",
    "gn:country_code":"CD",
    "gn:dem":428,
    "gn:feature_class":"P",
    "gn:feature_code":"PPL",
    "gn:name":"Yamolengeli",
    "gn:population":0,
    "gn:timezone":"Africa/Kinshasa",
    "iso:country":"CD",
    "wof:name":"Yamolengeli",
    "wof:placetype":"locality"
},
  "geometry": {"coordinates":[22.13148,2.42863],"type":"Point"}
}