{
  "type": "Feature",
  "properties": {
    "gn:admin1_code":"11.0",
    "gn:asciiname":"Masahi",
    "gn:country_code":"CD",
    "gn:dem":910,
    "gn:feature_class":"P",
    "gn:feature_code":"PPL",
    "gn:name":"Masahi",
    "gn:population":0,
    "gn:timezone":"Africa/Lubumbashi",
    "iso:country":"CD",
    "wof:name":"Masahi",
    "wof:placetype":"locality"
},
  "geometry": {"coordinates":[28.75585,0.42015],"type":"Point"}
}