{
  "type": "Feature",
  "properties": {
    "gn:admin1_code":"10.0",
    "gn:asciiname":"Munkula",
    "gn:country_code":"CD",
    "gn:dem":561,
    "gn:feature_class":"P",
    "gn:feature_code":"PPL",
    "gn:name":"Munkula",
    "gn:population":0,
    "gn:timezone":"Africa/Lubumbashi",
    "iso:country":"CD",
    "wof:name":"Munkula",
    "wof:placetype":"locality"
},
  "geometry": {"coordinates":[26.07781,-3.27021],"type":"Point"}
}