{
  "type": "Feature",
  "properties": {
    "gn:admin1_code":"21.0",
    "gn:asciiname":"Kabangu-Sapio",
    "gn:country_code":"CD",
    "gn:dem":778,
    "gn:feature_class":"P",
    "gn:feature_code":"PPL",
    "gn:name":"Kabangu-Sapio",
    "gn:population":0,
    "gn:timezone":"Africa/Lubumbashi",
    "iso:country":"CD",
    "name:und_x_variant":[
        "Kabangu-Sapidi",
        "Kabangu-Sapio"
    ],
    "wof:name":"Kabangu-Sapio",
    "wof:placetype":"locality"
},
  "geometry": {"coordinates":[24.93096,-6.15138],"type":"Point"}
}