{
  "type": "Feature",
  "properties": {
    "gn:admin1_code":"24.0",
    "gn:asciiname":"Ekwayolo",
    "gn:country_code":"CD",
    "gn:dem":365,
    "gn:feature_class":"P",
    "gn:feature_code":"PPL",
    "gn:name":"Ekwayolo",
    "gn:population":0,
    "gn:timezone":"Africa/Kinshasa",
    "iso:country":"CD",
    "name:und_x_variant":[
        "Ikwayolo"
    ],
    "wof:name":"Ekwayolo",
    "wof:placetype":"locality"
},
  "geometry": {"coordinates":[19.1811,-2.99195],"type":"Point"}
}