{
  "type": "Feature",
  "properties": {
    "gn:admin1_code":"23.0",
    "gn:asciiname":"Nganda",
    "gn:country_code":"CD",
    "gn:dem":826,
    "gn:feature_class":"P",
    "gn:feature_code":"PPL",
    "gn:name":"Nganda",
    "gn:population":0,
    "gn:timezone":"Africa/Lubumbashi",
    "iso:country":"CD",
    "wof:name":"Nganda",
    "wof:placetype":"locality"
},
  "geometry": {"coordinates":[23.03515,-6.36131],"type":"Point"}
}