{
  "type": "Feature",
  "properties": {
    "gn:admin1_code":"19.0",
    "gn:asciiname":"Buka-Luba",
    "gn:country_code":"CD",
    "gn:dem":762,
    "gn:feature_class":"P",
    "gn:feature_code":"PPL",
    "gn:name":"Buka-Luba",
    "gn:population":0,
    "gn:timezone":"Africa/Kinshasa",
    "iso:country":"CD",
    "name:und_x_variant":[
        "Bukaluba"
    ],
    "wof:name":"Buka-Luba",
    "wof:placetype":"locality"
},
  "geometry": {"coordinates":[17.34967,-5.77851],"type":"Point"}
}