{
  "type": "Feature",
  "properties": {
    "gn:admin1_code":"20.0",
    "gn:asciiname":"Kikuabi",
    "gn:country_code":"CD",
    "gn:dem":723,
    "gn:feature_class":"P",
    "gn:feature_code":"PPL",
    "gn:name":"Kikuabi",
    "gn:population":0,
    "gn:timezone":"Africa/Kinshasa",
    "iso:country":"CD",
    "wof:name":"Kikuabi",
    "wof:placetype":"locality"
},
  "geometry": {"coordinates":[18.47774,-5.7402],"type":"Point"}
}