{
  "type": "Feature",
  "properties": {
    "gn:admin1_code":"13.0",
    "gn:asciiname":"Yero",
    "gn:country_code":"CD",
    "gn:dem":648,
    "gn:feature_class":"P",
    "gn:feature_code":"PPL",
    "gn:name":"Yero",
    "gn:population":0,
    "gn:timezone":"Africa/Lubumbashi",
    "iso:country":"CD",
    "wof:name":"Yero",
    "wof:placetype":"locality"
},
  "geometry": {"coordinates":[25.98955,3.43069],"type":"Point"}
}