{
  "type": "Feature",
  "properties": {
    "gn:admin1_code":"20.0",
    "gn:asciiname":"Kiwala",
    "gn:country_code":"CD",
    "gn:dem":485,
    "gn:feature_class":"P",
    "gn:feature_code":"PPL",
    "gn:name":"Kiwala",
    "gn:population":0,
    "gn:timezone":"Africa/Kinshasa",
    "iso:country":"CD",
    "wof:name":"Kiwala",
    "wof:placetype":"locality"
},
  "geometry": {"coordinates":[18.57459,-5.02213],"type":"Point"}
}