{
  "type": "Feature",
  "properties": {
    "gn:admin1_code":"29.0",
    "gn:asciiname":"Kilombi",
    "gn:country_code":"CD",
    "gn:dem":622,
    "gn:feature_class":"P",
    "gn:feature_code":"PPL",
    "gn:name":"Kilombi",
    "gn:population":0,
    "gn:timezone":"Africa/Lubumbashi",
    "iso:country":"CD",
    "name:und_x_variant":[
        "Kilembi"
    ],
    "wof:name":"Kilombi",
    "wof:placetype":"locality"
},
  "geometry": {"coordinates":[26.28273,-5.18566],"type":"Point"}
}