{
  "type": "Feature",
  "properties": {
    "gn:admin1_code":"15.0",
    "gn:asciiname":"Kayeye",
    "gn:country_code":"CD",
    "gn:dem":1034,
    "gn:feature_class":"P",
    "gn:feature_code":"PPL",
    "gn:name":"Kayeye",
    "gn:population":0,
    "gn:timezone":"Africa/Lubumbashi",
    "iso:country":"CD",
    "wof:name":"Kayeye",
    "wof:placetype":"locality"
},
  "geometry": {"coordinates":[25.6409,-7.47779],"type":"Point"}
}