{
  "type": "Feature",
  "properties": {
    "gn:admin1_code":"23.0",
    "gn:asciiname":"Tshefu",
    "gn:country_code":"CD",
    "gn:dem":655,
    "gn:feature_class":"P",
    "gn:feature_code":"PPL",
    "gn:name":"Tshefu",
    "gn:population":0,
    "gn:timezone":"Africa/Lubumbashi",
    "iso:country":"CD",
    "wof:name":"Tshefu",
    "wof:placetype":"locality"
},
  "geometry": {"coordinates":[22.35664,-6.04127],"type":"Point"}
}