{
  "type": "Feature",
  "properties": {
    "gn:admin1_code":"8.0",
    "gn:asciiname":"Bisika",
    "gn:country_code":"CD",
    "gn:dem":379,
    "gn:feature_class":"P",
    "gn:feature_code":"PPL",
    "gn:name":"Bisika",
    "gn:population":0,
    "gn:timezone":"Africa/Kinshasa",
    "iso:country":"CD",
    "wof:name":"Bisika",
    "wof:placetype":"locality"
},
  "geometry": {"coordinates":[15.05407,-4.54994],"type":"Point"}
}