{
  "type": "Feature",
  "properties": {
    "gn:admin1_code":"8.0",
    "gn:asciiname":"Mami",
    "gn:country_code":"CD",
    "gn:dem":334,
    "gn:feature_class":"P",
    "gn:feature_code":"PPL",
    "gn:name":"Mami",
    "gn:population":0,
    "gn:timezone":"Africa/Kinshasa",
    "iso:country":"CD",
    "name:ceb_x_preferred":[
        "Mami"
    ],
    "name:deu_x_preferred":[
        "Mami"
    ],
    "name:eus_x_preferred":[
        "Mami"
    ],
    "name:fas_x_preferred":[
        "\u0645\u0645\u06cc"
    ],
    "name:fra_x_preferred":[
        "Mami"
    ],
    "name:hun_x_preferred":[
        "Mami"
    ],
    "name:por_x_preferred":[
        "Mami"
    ],
    "name:swe_x_preferred":[
        "Mami"
    ],
    "name:tur_x_preferred":[
        "Mami"
    ],
    "wof:name":"Mami",
    "wof:placetype":"locality"
},
  "geometry": {"coordinates":[13.31823,-5.70084],"type":"Point"}
}