{
  "type": "Feature",
  "properties": {
    "gn:admin1_code":"21.0",
    "gn:asciiname":"Kasongo",
    "gn:country_code":"CD",
    "gn:dem":869,
    "gn:feature_class":"P",
    "gn:feature_code":"PPL",
    "gn:name":"Kasongo",
    "gn:population":0,
    "gn:timezone":"Africa/Lubumbashi",
    "iso:country":"CD",
    "wof:name":"Kasongo",
    "wof:placetype":"locality"
},
  "geometry": {"coordinates":[23.61001,-7.33226],"type":"Point"}
}