{
  "type": "Feature",
  "properties": {
    "gn:admin1_code":"21.0",
    "gn:asciiname":"Kasongo",
    "gn:country_code":"CD",
    "gn:dem":869,
    "gn:feature_class":"P",
    "gn:feature_code":"PPL",
    "gn:name":"Kasongo",
    "gn:population":0,
    "gn:timezone":"Africa/Lubumbashi",
    "iso:country":"CD",
    "name:ben_x_preferred":[
        "\u0995\u09be\u09b8\u09cb\u0982\u0997\u09cb"
    ],
    "name:ceb_x_preferred":[
        "Kasongo"
    ],
    "name:deu_x_preferred":[
        "Kasongo"
    ],
    "name:ell_x_preferred":[
        "\u039a\u03b1\u03c3\u03cc\u03bd\u03b3\u03ba\u03bf"
    ],
    "name:epo_x_preferred":[
        "Kasongo"
    ],
    "name:fas_x_preferred":[
        "\u06a9\u0633\u0648\u0646\u06af\u0648"
    ],
    "name:fra_x_preferred":[
        "Kasongo"
    ],
    "name:hin_x_preferred":[
        "\u0915\u0938\u094b\u0902\u0917\u094b"
    ],
    "name:hun_x_preferred":[
        "Kasongo"
    ],
    "name:ind_x_preferred":[
        "Kasongo"
    ],
    "name:ita_x_preferred":[
        "Kasongo"
    ],
    "name:kat_x_preferred":[
        "\u10d9\u10d0\u10e1\u10dd\u10dc\u10d2\u10dd"
    ],
    "name:kor_x_preferred":[
        "\uce74\uc1a1\uace0"
    ],
    "name:nld_x_preferred":[
        "Kasongo"
    ],
    "name:ron_x_preferred":[
        "Kasongo"
    ],
    "name:rus_x_preferred":[
        "\u041a\u0430\u0441\u043e\u043d\u0433\u043e"
    ],
    "name:spa_x_preferred":[
        "Kasongo"
    ],
    "name:swa_x_preferred":[
        "Kasongo"
    ],
    "name:swe_x_preferred":[
        "Kasongo"
    ],
    "name:tgl_x_preferred":[
        "Kasongo"
    ],
    "name:tur_x_preferred":[
        "Kasongo"
    ],
    "name:ukr_x_preferred":[
        "\u041a\u0430\u0441\u043e\u043d\u0433\u043e"
    ],
    "name:urd_x_preferred":[
        "\u06a9\u0627\u0633\u0648\u0646\u06af\u0648"
    ],
    "name:vie_x_preferred":[
        "Kasongo"
    ],
    "name:xmf_x_preferred":[
        "\u10d9\u10d0\u10e1\u10dd\u10dc\u10d2\u10dd"
    ],
    "name:zho_x_preferred":[
        "\u5361\u677e\u6208"
    ],
    "wof:name":"Kasongo",
    "wof:placetype":"locality"
},
  "geometry": {"coordinates":[23.61001,-7.33226],"type":"Point"}
}