{
  "type": "Feature",
  "properties": {
    "gn:admin1_code":"28.0",
    "gn:asciiname":"Togbo-Damashua",
    "gn:country_code":"CD",
    "gn:dem":389,
    "gn:feature_class":"P",
    "gn:feature_code":"PPL",
    "gn:name":"Togbo-Damashua",
    "gn:population":0,
    "gn:timezone":"Africa/Kinshasa",
    "iso:country":"CD",
    "name:und_x_variant":[
        "Togbo-Danashua"
    ],
    "wof:name":"Togbo-Damashua",
    "wof:placetype":"locality"
},
  "geometry": {"coordinates":[18.9882,3.95298],"type":"Point"}
}