{
  "type": "Feature",
  "properties": {
    "gn:admin1_code":"15.0",
    "gn:asciiname":"Kamiba",
    "gn:country_code":"CD",
    "gn:dem":664,
    "gn:feature_class":"P",
    "gn:feature_code":"PPL",
    "gn:name":"Kamiba",
    "gn:population":0,
    "gn:timezone":"Africa/Lubumbashi",
    "iso:country":"CD",
    "wof:name":"Kamiba",
    "wof:placetype":"locality"
},
  "geometry": {"coordinates":[26.0428,-9.38217],"type":"Point"}
}