{
  "type": "Feature",
  "properties": {
    "gn:admin1_code":"31.0",
    "gn:asciiname":"Yasakanga",
    "gn:country_code":"CD",
    "gn:dem":477,
    "gn:feature_class":"P",
    "gn:feature_code":"PPL",
    "gn:name":"Yasakanga",
    "gn:population":0,
    "gn:timezone":"Africa/Kinshasa",
    "iso:country":"CD",
    "wof:name":"Yasakanga",
    "wof:placetype":"locality"
},
  "geometry": {"coordinates":[23.83333,-1.53333],"type":"Point"}
}