{
  "type": "Feature",
  "properties": {
    "gn:admin1_code":"13.0",
    "gn:asciiname":"Yinou",
    "gn:country_code":"CD",
    "gn:dem":480,
    "gn:feature_class":"P",
    "gn:feature_code":"PPL",
    "gn:name":"Yinou",
    "gn:population":0,
    "gn:timezone":"Africa/Lubumbashi",
    "iso:country":"CD",
    "wof:name":"Yinou",
    "wof:placetype":"locality"
},
  "geometry": {"coordinates":[22.65008,4.25008],"type":"Point"}
}