{
  "type": "Feature",
  "properties": {
    "gn:admin1_code":"27.0",
    "gn:asciiname":"Elumi",
    "gn:country_code":"CD",
    "gn:dem":560,
    "gn:feature_class":"P",
    "gn:feature_code":"PPL",
    "gn:name":"Elumi",
    "gn:population":0,
    "gn:timezone":"Africa/Lubumbashi",
    "iso:country":"CD",
    "wof:name":"Elumi",
    "wof:placetype":"locality"
},
  "geometry": {"coordinates":[22.71667,-2.66667],"type":"Point"}
}