{
  "type": "Feature",
  "properties": {
    "gn:admin1_code":"22.0",
    "gn:asciiname":"Kiala",
    "gn:country_code":"CD",
    "gn:dem":1412,
    "gn:feature_class":"P",
    "gn:feature_code":"PPL",
    "gn:name":"Kiala",
    "gn:population":0,
    "gn:timezone":"Africa/Lubumbashi",
    "iso:country":"CD",
    "wof:name":"Kiala",
    "wof:placetype":"locality"
},
  "geometry": {"coordinates":[25.43333,-10.65],"type":"Point"}
}