{
  "type": "Feature",
  "properties": {
    "gn:admin1_code":"23.0",
    "gn:asciiname":"Bangila",
    "gn:country_code":"CD",
    "gn:dem":656,
    "gn:feature_class":"P",
    "gn:feature_code":"PPL",
    "gn:name":"Bangila",
    "gn:population":0,
    "gn:timezone":"Africa/Lubumbashi",
    "iso:country":"CD",
    "wof:name":"Bangila",
    "wof:placetype":"locality"
},
  "geometry": {"coordinates":[22.10688,-5.8985],"type":"Point"}
}