{
  "type": "Feature",
  "properties": {
    "gn:admin1_code":"18.0",
    "gn:asciiname":"Tshingila",
    "gn:country_code":"CD",
    "gn:dem":684,
    "gn:feature_class":"P",
    "gn:feature_code":"PPL",
    "gn:name":"Tshingila",
    "gn:population":0,
    "gn:timezone":"Africa/Lubumbashi",
    "iso:country":"CD",
    "wof:name":"Tshingila",
    "wof:placetype":"locality"
},
  "geometry": {"coordinates":[20.25536,-6.13658],"type":"Point"}
}