{
  "type": "Feature",
  "properties": {
    "gn:admin1_code":"20.0",
    "gn:asciiname":"Kasanofi Deuxieme",
    "gn:country_code":"CD",
    "gn:dem":737,
    "gn:feature_class":"P",
    "gn:feature_code":"PPL",
    "gn:name":"Kasanofi Deuxi\u00e8me",
    "gn:population":0,
    "gn:timezone":"Africa/Kinshasa",
    "iso:country":"CD",
    "wof:name":"Kasanofi Deuxieme",
    "wof:placetype":"locality"
},
  "geometry": {"coordinates":[19.12245,-5.46754],"type":"Point"}
}