{
  "type": "Feature",
  "properties": {
    "gn:admin1_code":"21.0",
    "gn:asciiname":"Kalambo",
    "gn:country_code":"CD",
    "gn:dem":846,
    "gn:feature_class":"P",
    "gn:feature_code":"PPL",
    "gn:name":"Kalambo",
    "gn:population":0,
    "gn:timezone":"Africa/Lubumbashi",
    "iso:country":"CD",
    "name:ceb_x_preferred":[
        "Kalambo"
    ],
    "name:ces_x_preferred":[
        "Kalambo"
    ],
    "name:ita_x_preferred":[
        "Kalambo"
    ],
    "name:srp_x_preferred":[
        "Kalambo"
    ],
    "name:swe_x_preferred":[
        "Kalambo"
    ],
    "wof:name":"Kalambo",
    "wof:placetype":"locality"
},
  "geometry": {"coordinates":[24.21026,-6.13416],"type":"Point"}
}