{
  "type": "Feature",
  "properties": {
    "gn:admin1_code":"14.0",
    "gn:asciiname":"Kasimike",
    "gn:country_code":"CD",
    "gn:dem":1415,
    "gn:feature_class":"P",
    "gn:feature_code":"PPL",
    "gn:name":"Kasimike",
    "gn:population":0,
    "gn:timezone":"Africa/Lubumbashi",
    "iso:country":"CD",
    "wof:name":"Kasimike",
    "wof:placetype":"locality"
},
  "geometry": {"coordinates":[29.16667,-7.83333],"type":"Point"}
}