{
  "type": "Feature",
  "properties": {
    "gn:admin1_code":"28.0",
    "gn:asciiname":"Mabo-Moke",
    "gn:country_code":"CD",
    "gn:dem":359,
    "gn:feature_class":"P",
    "gn:feature_code":"PPL",
    "gn:name":"Mabo-Moke",
    "gn:population":0,
    "gn:timezone":"Africa/Kinshasa",
    "iso:country":"CD",
    "wof:name":"Mabo-Moke",
    "wof:placetype":"locality"
},
  "geometry": {"coordinates":[18.92839,3.35972],"type":"Point"}
}