{
  "type": "Feature",
  "properties": {
    "gn:admin1_code":"16.0",
    "gn:asciiname":"Namunza",
    "gn:country_code":"CD",
    "gn:dem":718,
    "gn:feature_class":"P",
    "gn:feature_code":"PPL",
    "gn:name":"Namunza",
    "gn:population":0,
    "gn:timezone":"Africa/Lubumbashi",
    "iso:country":"CD",
    "wof:name":"Namunza",
    "wof:placetype":"locality"
},
  "geometry": {"coordinates":[27.93631,3.0992],"type":"Point"}
}