{
  "type": "Feature",
  "properties": {
    "gn:admin1_code":"27.0",
    "gn:asciiname":"Tshula",
    "gn:country_code":"CD",
    "gn:dem":474,
    "gn:feature_class":"P",
    "gn:feature_code":"PPL",
    "gn:name":"Tshula",
    "gn:population":0,
    "gn:timezone":"Africa/Lubumbashi",
    "iso:country":"CD",
    "wof:name":"Tshula",
    "wof:placetype":"locality"
},
  "geometry": {"coordinates":[22.97901,-2.51768],"type":"Point"}
}