{
  "type": "Feature",
  "properties": {
    "gn:admin1_code":"20.0",
    "gn:asciiname":"Kindinga",
    "gn:country_code":"CD",
    "gn:dem":670,
    "gn:feature_class":"P",
    "gn:feature_code":"PPL",
    "gn:name":"Kindinga",
    "gn:population":0,
    "gn:timezone":"Africa/Kinshasa",
    "iso:country":"CD",
    "wof:name":"Kindinga",
    "wof:placetype":"locality"
},
  "geometry": {"coordinates":[18.0542,-5.13802],"type":"Point"}
}