{
  "type": "Feature",
  "properties": {
    "gn:admin1_code":"24.0",
    "gn:asciiname":"Semampia",
    "gn:country_code":"CD",
    "gn:dem":376,
    "gn:feature_class":"P",
    "gn:feature_code":"PPL",
    "gn:name":"Semampia",
    "gn:population":0,
    "gn:timezone":"Africa/Kinshasa",
    "iso:country":"CD",
    "name:und_x_variant":[
        "Semanpia",
        "Semapia",
        "Semampia"
    ],
    "wof:name":"Semampia",
    "wof:placetype":"locality"
},
  "geometry": {"coordinates":[18.17362,-3.15027],"type":"Point"}
}