{
  "type": "Feature",
  "properties": {
    "gn:admin1_code":"22.0",
    "gn:asciiname":"Sombo",
    "gn:country_code":"CD",
    "gn:dem":1076,
    "gn:feature_class":"P",
    "gn:feature_code":"PPL",
    "gn:name":"Sombo",
    "gn:population":0,
    "gn:timezone":"Africa/Lubumbashi",
    "iso:country":"CD",
    "wof:name":"Sombo",
    "wof:placetype":"locality"
},
  "geometry": {"coordinates":[22.7387,-10.52977],"type":"Point"}
}