{
  "type": "Feature",
  "properties": {
    "gn:admin1_code":"30.0",
    "gn:asciiname":"Lusuma",
    "gn:country_code":"CD",
    "gn:dem":487,
    "gn:feature_class":"P",
    "gn:feature_code":"PPL",
    "gn:name":"Lusuma",
    "gn:population":0,
    "gn:timezone":"Africa/Lubumbashi",
    "iso:country":"CD",
    "wof:name":"Lusuma",
    "wof:placetype":"locality"
},
  "geometry": {"coordinates":[24.394,-0.35849],"type":"Point"}
}