{
  "type": "Feature",
  "properties": {
    "gn:admin1_code":"19.0",
    "gn:asciiname":"Ngona-Mutunda",
    "gn:country_code":"CD",
    "gn:dem":875,
    "gn:feature_class":"P",
    "gn:feature_code":"PPL",
    "gn:name":"Ngona-Mutunda",
    "gn:population":0,
    "gn:timezone":"Africa/Kinshasa",
    "iso:country":"CD",
    "wof:name":"Ngona-Mutunda",
    "wof:placetype":"locality"
},
  "geometry": {"coordinates":[17.96095,-6.3165],"type":"Point"}
}