{
  "type": "Feature",
  "properties": {
    "gn:admin1_code":"10.0",
    "gn:asciiname":"Mandjondja",
    "gn:country_code":"CD",
    "gn:dem":703,
    "gn:feature_class":"P",
    "gn:feature_code":"PPL",
    "gn:name":"Mandjondja",
    "gn:population":0,
    "gn:timezone":"Africa/Lubumbashi",
    "iso:country":"CD",
    "name:und_x_variant":[
        "Mandjonja"
    ],
    "wof:name":"Mandjondja",
    "wof:placetype":"locality"
},
  "geometry": {"coordinates":[27.21145,-1.65938],"type":"Point"}
}