{
  "type": "Feature",
  "properties": {
    "gn:admin1_code":"16.0",
    "gn:asciiname":"Bengenga",
    "gn:country_code":"CD",
    "gn:dem":737,
    "gn:feature_class":"P",
    "gn:feature_code":"PPL",
    "gn:name":"Bengenga",
    "gn:population":0,
    "gn:timezone":"Africa/Lubumbashi",
    "iso:country":"CD",
    "name:und_x_variant":[
        "Bangenga",
        "Bengengai",
        "Bengenga"
    ],
    "wof:name":"Bengenga",
    "wof:placetype":"locality"
},
  "geometry": {"coordinates":[27.69587000000001,4.81019],"type":"Point"}
}