{
  "type": "Feature",
  "properties": {
    "gn:admin1_code":"19.0",
    "gn:asciiname":"Kanapumba",
    "gn:country_code":"CD",
    "gn:dem":518,
    "gn:feature_class":"P",
    "gn:feature_code":"PPL",
    "gn:name":"Kanapumba",
    "gn:population":0,
    "gn:timezone":"Africa/Kinshasa",
    "iso:country":"CD",
    "wof:name":"Kanapumba",
    "wof:placetype":"locality"
},
  "geometry": {"coordinates":[17.12643,-6.97085],"type":"Point"}
}