{
  "type": "Feature",
  "properties": {
    "gn:admin1_code":"20.0",
    "gn:asciiname":"Kitsona",
    "gn:country_code":"CD",
    "gn:dem":785,
    "gn:feature_class":"P",
    "gn:feature_code":"PPL",
    "gn:name":"Kitsona",
    "gn:population":0,
    "gn:timezone":"Africa/Kinshasa",
    "iso:country":"CD",
    "wof:name":"Kitsona",
    "wof:placetype":"locality"
},
  "geometry": {"coordinates":[17.80866,-5.34262],"type":"Point"}
}