{
  "type": "Feature",
  "properties": {
    "gn:admin1_code":"4.0",
    "gn:asciiname":"Kabeya-Kamwanga",
    "gn:country_code":"CD",
    "gn:dem":649,
    "gn:feature_class":"P",
    "gn:feature_code":"PPL",
    "gn:name":"Kabeya-Kamwanga",
    "gn:population":0,
    "gn:timezone":"Africa/Lubumbashi",
    "iso:country":"CD",
    "name:und_x_variant":[
        "Kabeya"
    ],
    "wof:name":"Kabeya-Kamwanga",
    "wof:placetype":"locality"
},
  "geometry": {"coordinates":[23.25386,-5.9988],"type":"Point"}
}