{
  "type": "Feature",
  "properties": {
    "gn:admin1_code":"15.0",
    "gn:asciiname":"Musala",
    "gn:country_code":"CD",
    "gn:dem":568,
    "gn:feature_class":"P",
    "gn:feature_code":"PPL",
    "gn:name":"Musala",
    "gn:population":0,
    "gn:timezone":"Africa/Lubumbashi",
    "iso:country":"CD",
    "wof:name":"Musala",
    "wof:placetype":"locality"
},
  "geometry": {"coordinates":[26.30338,-8.54635],"type":"Point"}
}