{
  "type": "Feature",
  "properties": {
    "gn:admin1_code":"23.0",
    "gn:asciiname":"Kaniemba",
    "gn:country_code":"CD",
    "gn:dem":796,
    "gn:feature_class":"P",
    "gn:feature_code":"PPL",
    "gn:name":"Kaniemba",
    "gn:population":0,
    "gn:timezone":"Africa/Lubumbashi",
    "iso:country":"CD",
    "wof:name":"Kaniemba",
    "wof:placetype":"locality"
},
  "geometry": {"coordinates":[21.77082,-6.58455],"type":"Point"}
}