{
  "type": "Feature",
  "properties": {
    "gn:admin1_code":"10.0",
    "gn:asciiname":"Kasuku",
    "gn:country_code":"CD",
    "gn:dem":480,
    "gn:feature_class":"P",
    "gn:feature_code":"PPL",
    "gn:name":"Kasuku",
    "gn:population":0,
    "gn:timezone":"Africa/Lubumbashi",
    "iso:country":"CD",
    "name:fra_x_preferred":[
        "Kasuku"
    ],
    "wof:name":"Kasuku",
    "wof:placetype":"locality"
},
  "geometry": {"coordinates":[25.75681,-3.0082],"type":"Point"}
}