{
  "type": "Feature",
  "properties": {
    "gn:admin1_code":"27.0",
    "gn:asciiname":"Gongo",
    "gn:country_code":"CD",
    "gn:dem":477,
    "gn:feature_class":"P",
    "gn:feature_code":"PPL",
    "gn:name":"Gongo",
    "gn:population":0,
    "gn:timezone":"Africa/Lubumbashi",
    "iso:country":"CD",
    "wof:name":"Gongo",
    "wof:placetype":"locality"
},
  "geometry": {"coordinates":[23.02331,-4.09999],"type":"Point"}
}