{
  "type": "Feature",
  "properties": {
    "gn:admin1_code":"13.0",
    "gn:asciiname":"Bagbaya",
    "gn:country_code":"CD",
    "gn:dem":662,
    "gn:feature_class":"P",
    "gn:feature_code":"PPL",
    "gn:name":"Bagbaya",
    "gn:population":0,
    "gn:timezone":"Africa/Lubumbashi",
    "iso:country":"CD",
    "wof:name":"Bagbaya",
    "wof:placetype":"locality"
},
  "geometry": {"coordinates":[25.99319,3.46046],"type":"Point"}
}