{
  "type": "Feature",
  "properties": {
    "gn:admin1_code":"18.0",
    "gn:asciiname":"Bwabwa-Munene",
    "gn:country_code":"CD",
    "gn:dem":510,
    "gn:feature_class":"P",
    "gn:feature_code":"PPL",
    "gn:name":"Bwabwa-Munene",
    "gn:population":0,
    "gn:timezone":"Africa/Lubumbashi",
    "iso:country":"CD",
    "name:und_x_variant":[
        "Bwawa Munene",
        "Bwabwa-Munene"
    ],
    "wof:name":"Bwabwa-Munene",
    "wof:placetype":"locality"
},
  "geometry": {"coordinates":[20.17673,-5.01676],"type":"Point"}
}