{
  "type": "Feature",
  "properties": {
    "gn:admin1_code":"23.0",
    "gn:asciiname":"Dumba",
    "gn:country_code":"CD",
    "gn:dem":809,
    "gn:feature_class":"P",
    "gn:feature_code":"PPL",
    "gn:name":"Dumba",
    "gn:population":0,
    "gn:timezone":"Africa/Lubumbashi",
    "iso:country":"CD",
    "name:und_x_variant":[
        "Dumbi",
        "Dumba"
    ],
    "wof:name":"Dumba",
    "wof:placetype":"locality"
},
  "geometry": {"coordinates":[21.68888,-6.98276],"type":"Point"}
}