{
  "type": "Feature",
  "properties": {
    "gn:admin1_code":"0.0",
    "gn:asciiname":"Kalimba",
    "gn:country_code":"CD",
    "gn:dem":2266,
    "gn:feature_class":"P",
    "gn:feature_code":"PPL",
    "gn:name":"Kalimba",
    "gn:population":0,
    "gn:timezone":"Africa/Lubumbashi",
    "iso:country":"CD",
    "wof:name":"Kalimba",
    "wof:placetype":"locality"
},
  "geometry": {"coordinates":[29.05611,-3.24472],"type":"Point"}
}