{
  "type": "Feature",
  "properties": {
    "gn:admin1_code":"21.0",
    "gn:asciiname":"Kifinde Deuxieme",
    "gn:country_code":"CD",
    "gn:dem":689,
    "gn:feature_class":"P",
    "gn:feature_code":"PPL",
    "gn:name":"Kifinde Deuxi\u00e8me",
    "gn:population":0,
    "gn:timezone":"Africa/Lubumbashi",
    "iso:country":"CD",
    "name:und_x_variant":[
        "Kifinde",
        "Kifinde II",
        "Kifinde Deuxi\u00e8me"
    ],
    "wof:name":"Kifinde Deuxieme",
    "wof:placetype":"locality"
},
  "geometry": {"coordinates":[24.34869,-6.26678],"type":"Point"}
}