{
  "type": "Feature",
  "properties": {
    "gn:admin1_code":"16.0",
    "gn:asciiname":"Buza",
    "gn:country_code":"CD",
    "gn:dem":945,
    "gn:feature_class":"P",
    "gn:feature_code":"PPL",
    "gn:name":"Buza",
    "gn:population":0,
    "gn:timezone":"Africa/Lubumbashi",
    "iso:country":"CD",
    "name:fra_x_preferred":[
        "Buza"
    ],
    "name:pol_x_preferred":[
        "Buza"
    ],
    "wof:name":"Buza",
    "wof:placetype":"locality"
},
  "geometry": {"coordinates":[29.95975,2.97582],"type":"Point"}
}