{
  "type": "Feature",
  "properties": {
    "gn:admin1_code":"18.0",
    "gn:asciiname":"Malonga-Muturi",
    "gn:country_code":"CD",
    "gn:dem":552,
    "gn:feature_class":"P",
    "gn:feature_code":"PPL",
    "gn:name":"Malonga-Muturi",
    "gn:population":0,
    "gn:timezone":"Africa/Lubumbashi",
    "iso:country":"CD",
    "wof:name":"Malonga-Muturi",
    "wof:placetype":"locality"
},
  "geometry": {"coordinates":[20.18095,-4.46185],"type":"Point"}
}