{
  "type": "Feature",
  "properties": {
    "gn:admin1_code":"8.0",
    "gn:asciiname":"Mbuma",
    "gn:country_code":"CD",
    "gn:dem":711,
    "gn:feature_class":"P",
    "gn:feature_code":"PPL",
    "gn:name":"Mbuma",
    "gn:population":0,
    "gn:timezone":"Africa/Kinshasa",
    "iso:country":"CD",
    "name:nld_x_preferred":[
        "Mbuma"
    ],
    "wof:name":"Mbuma",
    "wof:placetype":"locality"
},
  "geometry": {"coordinates":[15.25975,-5.6615],"type":"Point"}
}