{
  "type": "Feature",
  "properties": {
    "gn:admin1_code":"24.0",
    "gn:asciiname":"Ebongia",
    "gn:country_code":"CD",
    "gn:dem":318,
    "gn:feature_class":"P",
    "gn:feature_code":"PPL",
    "gn:name":"Ebongia",
    "gn:population":0,
    "gn:timezone":"Africa/Kinshasa",
    "iso:country":"CD",
    "wof:name":"Ebongia",
    "wof:placetype":"locality"
},
  "geometry": {"coordinates":[19.08408,-1.50081],"type":"Point"}
}