{
  "type": "Feature",
  "properties": {
    "gn:admin1_code":"8.0",
    "gn:asciiname":"Pinda",
    "gn:country_code":"CD",
    "gn:dem":648,
    "gn:feature_class":"P",
    "gn:feature_code":"PPL",
    "gn:name":"Pinda",
    "gn:population":0,
    "gn:timezone":"Africa/Kinshasa",
    "iso:country":"CD",
    "name:ceb_x_preferred":[
        "Pinda"
    ],
    "name:pol_x_preferred":[
        "Pinda"
    ],
    "name:por_x_preferred":[
        "Pinda"
    ],
    "name:swe_x_preferred":[
        "Pinda"
    ],
    "wof:name":"Pinda",
    "wof:placetype":"locality"
},
  "geometry": {"coordinates":[14.36297,-5.87703],"type":"Point"}
}