{
  "type": "Feature",
  "properties": {
    "gn:admin1_code":"24.0",
    "gn:asciiname":"Kwinsin",
    "gn:country_code":"CD",
    "gn:dem":342,
    "gn:feature_class":"P",
    "gn:feature_code":"PPL",
    "gn:name":"Kwinsin",
    "gn:population":0,
    "gn:timezone":"Africa/Kinshasa",
    "iso:country":"CD",
    "name:und_x_variant":[
        "Kwinson",
        "Kwinsin"
    ],
    "wof:name":"Kwinsin",
    "wof:placetype":"locality"
},
  "geometry": {"coordinates":[18.27304,-2.89647],"type":"Point"}
}