{
  "type": "Feature",
  "properties": {
    "gn:admin1_code":"19.0",
    "gn:asciiname":"Shasupi",
    "gn:country_code":"CD",
    "gn:dem":1037,
    "gn:feature_class":"P",
    "gn:feature_code":"PPL",
    "gn:name":"Shasupi",
    "gn:population":0,
    "gn:timezone":"Africa/Kinshasa",
    "iso:country":"CD",
    "wof:name":"Shasupi",
    "wof:placetype":"locality"
},
  "geometry": {"coordinates":[19.28649,-7.55081],"type":"Point"}
}