{
  "type": "Feature",
  "properties": {
    "gn:admin1_code":"19.0",
    "gn:asciiname":"Ka-Muka",
    "gn:country_code":"CD",
    "gn:dem":1022,
    "gn:feature_class":"P",
    "gn:feature_code":"PPL",
    "gn:name":"Ka-Muka",
    "gn:population":0,
    "gn:timezone":"Africa/Kinshasa",
    "iso:country":"CD",
    "wof:name":"Ka-Muka",
    "wof:placetype":"locality"
},
  "geometry": {"coordinates":[18.50927,-7.06209],"type":"Point"}
}