{
  "type": "Feature",
  "properties": {
    "gn:admin1_code":"15.0",
    "gn:asciiname":"Kamakundu",
    "gn:country_code":"CD",
    "gn:dem":818,
    "gn:feature_class":"P",
    "gn:feature_code":"PPL",
    "gn:name":"Kamakundu",
    "gn:population":0,
    "gn:timezone":"Africa/Lubumbashi",
    "iso:country":"CD",
    "name:und_x_variant":[
        "Kamukundu",
        "Kamakundu"
    ],
    "wof:name":"Kamakundu",
    "wof:placetype":"locality"
},
  "geometry": {"coordinates":[26.48409,-7.60168],"type":"Point"}
}