{
  "type": "Feature",
  "properties": {
    "gn:admin1_code":"8.0",
    "gn:asciiname":"Kinanga",
    "gn:country_code":"CD",
    "gn:dem":564,
    "gn:feature_class":"P",
    "gn:feature_code":"PPL",
    "gn:name":"Kinanga",
    "gn:population":0,
    "gn:timezone":"Africa/Kinshasa",
    "iso:country":"CD",
    "name:por_x_preferred":[
        "Kinanga"
    ],
    "wof:name":"Kinanga",
    "wof:placetype":"locality"
},
  "geometry": {"coordinates":[15.19874,-5.19376],"type":"Point"}
}