{
  "type": "Feature",
  "properties": {
    "gn:admin1_code":"12.0",
    "gn:asciiname":"Kiniekele",
    "gn:country_code":"CD",
    "gn:dem":805,
    "gn:feature_class":"P",
    "gn:feature_code":"PPL",
    "gn:name":"Kiniekele",
    "gn:population":0,
    "gn:timezone":"Africa/Lubumbashi",
    "iso:country":"CD",
    "wof:name":"Kiniekele",
    "wof:placetype":"locality"
},
  "geometry": {"coordinates":[29.08611,-4.03583],"type":"Point"}
}