{
  "type": "Feature",
  "properties": {
    "gn:admin1_code":"13.0",
    "gn:asciiname":"Takpa",
    "gn:country_code":"CD",
    "gn:dem":477,
    "gn:feature_class":"P",
    "gn:feature_code":"PPL",
    "gn:name":"Takpa",
    "gn:population":0,
    "gn:timezone":"Africa/Lubumbashi",
    "iso:country":"CD",
    "wof:name":"Takpa",
    "wof:placetype":"locality"
},
  "geometry": {"coordinates":[23.38774,3.3112],"type":"Point"}
}