{
  "type": "Feature",
  "properties": {
    "gn:admin1_code":"29.0",
    "gn:asciiname":"Kabundi",
    "gn:country_code":"CD",
    "gn:dem":672,
    "gn:feature_class":"P",
    "gn:feature_code":"PPL",
    "gn:name":"Kabundi",
    "gn:population":0,
    "gn:timezone":"Africa/Lubumbashi",
    "iso:country":"CD",
    "wof:name":"Kabundi",
    "wof:placetype":"locality"
},
  "geometry": {"coordinates":[27.15468,-5.24462],"type":"Point"}
}