{
  "type": "Feature",
  "properties": {
    "gn:admin1_code":"20.0",
    "gn:asciiname":"Mutoi",
    "gn:country_code":"CD",
    "gn:dem":493,
    "gn:feature_class":"P",
    "gn:feature_code":"PPL",
    "gn:name":"Mutoi",
    "gn:population":0,
    "gn:timezone":"Africa/Kinshasa",
    "iso:country":"CD",
    "wof:name":"Mutoi",
    "wof:placetype":"locality"
},
  "geometry": {"coordinates":[19.19036,-4.4162],"type":"Point"}
}