{
  "type": "Feature",
  "properties": {
    "gn:admin1_code":"15.0",
    "gn:asciiname":"Kiabukwa",
    "gn:country_code":"CD",
    "gn:dem":1138,
    "gn:feature_class":"P",
    "gn:feature_code":"PPL",
    "gn:name":"Kiabukwa",
    "gn:population":0,
    "gn:timezone":"Africa/Lubumbashi",
    "iso:country":"CD",
    "name:und_x_variant":[
        "Tshiabukwa",
        "Kiabukwa"
    ],
    "wof:name":"Kiabukwa",
    "wof:placetype":"locality"
},
  "geometry": {"coordinates":[24.83008,-8.75323],"type":"Point"}
}