{
  "type": "Feature",
  "properties": {
    "gn:admin1_code":"27.0",
    "gn:asciiname":"Ondjembe",
    "gn:country_code":"CD",
    "gn:dem":562,
    "gn:feature_class":"P",
    "gn:feature_code":"PPL",
    "gn:name":"Ondjembe",
    "gn:population":0,
    "gn:timezone":"Africa/Lubumbashi",
    "iso:country":"CD",
    "wof:name":"Ondjembe",
    "wof:placetype":"locality"
},
  "geometry": {"coordinates":[24.77044,-4.40254],"type":"Point"}
}