{
  "type": "Feature",
  "properties": {
    "gn:admin1_code":"17.0",
    "gn:asciiname":"Ambisi",
    "gn:country_code":"CD",
    "gn:dem":1587,
    "gn:feature_class":"P",
    "gn:feature_code":"PPL",
    "gn:name":"Ambisi",
    "gn:population":0,
    "gn:timezone":"Africa/Lubumbashi",
    "iso:country":"CD",
    "wof:name":"Ambisi",
    "wof:placetype":"locality"
},
  "geometry": {"coordinates":[30.70572,2.58791],"type":"Point"}
}