{
  "type": "Feature",
  "properties": {
    "gn:admin1_code":"8.0",
    "gn:asciiname":"Valentim",
    "gn:country_code":"CD",
    "gn:dem":7,
    "gn:feature_class":"P",
    "gn:feature_code":"PPL",
    "gn:name":"Valentim",
    "gn:population":0,
    "gn:timezone":"Africa/Kinshasa",
    "iso:country":"CD",
    "wof:name":"Valentim",
    "wof:placetype":"locality"
},
  "geometry": {"coordinates":[12.72976,-5.9626],"type":"Point"}
}