{
  "type": "Feature",
  "properties": {
    "gn:admin1_code":"12.0",
    "gn:asciiname":"Bugobe",
    "gn:country_code":"CD",
    "gn:dem":1988,
    "gn:feature_class":"P",
    "gn:feature_code":"PPL",
    "gn:name":"Bugobe",
    "gn:population":0,
    "gn:timezone":"Africa/Lubumbashi",
    "iso:country":"CD",
    "wof:name":"Bugobe",
    "wof:placetype":"locality"
},
  "geometry": {"coordinates":[28.74056,-2.52397],"type":"Point"}
}