{
  "type": "Feature",
  "properties": {
    "gn:admin1_code":"18.0",
    "gn:asciiname":"Tshimpumpu",
    "gn:country_code":"CD",
    "gn:dem":520,
    "gn:feature_class":"P",
    "gn:feature_code":"PPL",
    "gn:name":"Tshimpumpu",
    "gn:population":0,
    "gn:timezone":"Africa/Lubumbashi",
    "iso:country":"CD",
    "wof:name":"Tshimpumpu",
    "wof:placetype":"locality"
},
  "geometry": {"coordinates":[21.40868,-5.31966],"type":"Point"}
}