{
  "type": "Feature",
  "properties": {
    "gn:admin1_code":"15.0",
    "gn:asciiname":"Kamukesa",
    "gn:country_code":"CD",
    "gn:dem":735,
    "gn:feature_class":"P",
    "gn:feature_code":"PPL",
    "gn:name":"Kamukesa",
    "gn:population":0,
    "gn:timezone":"Africa/Lubumbashi",
    "iso:country":"CD",
    "wof:name":"Kamukesa",
    "wof:placetype":"locality"
},
  "geometry": {"coordinates":[25.32567,-9.24567],"type":"Point"}
}