{
  "type": "Feature",
  "properties": {
    "gn:admin1_code":"22.0",
    "gn:asciiname":"Sausaki",
    "gn:country_code":"CD",
    "gn:dem":1044,
    "gn:feature_class":"P",
    "gn:feature_code":"PPL",
    "gn:name":"Sausaki",
    "gn:population":0,
    "gn:timezone":"Africa/Lubumbashi",
    "iso:country":"CD",
    "name:und_x_variant":[
        "Sauseke"
    ],
    "wof:name":"Sausaki",
    "wof:placetype":"locality"
},
  "geometry": {"coordinates":[23.36637,-9.4788],"type":"Point"}
}