{
  "type": "Feature",
  "properties": {
    "gn:admin1_code":"16.0",
    "gn:asciiname":"Bogutali",
    "gn:country_code":"CD",
    "gn:dem":881,
    "gn:feature_class":"P",
    "gn:feature_code":"PPL",
    "gn:name":"Bogutali",
    "gn:population":0,
    "gn:timezone":"Africa/Lubumbashi",
    "iso:country":"CD",
    "wof:name":"Bogutali",
    "wof:placetype":"locality"
},
  "geometry": {"coordinates":[29.23785,3.07655],"type":"Point"}
}