{
  "type": "Feature",
  "properties": {
    "gn:admin1_code":"24.0",
    "gn:asciiname":"Nkiemu",
    "gn:country_code":"CD",
    "gn:dem":298,
    "gn:feature_class":"P",
    "gn:feature_code":"PPL",
    "gn:name":"Nkiemu",
    "gn:population":0,
    "gn:timezone":"Africa/Kinshasa",
    "iso:country":"CD",
    "wof:name":"Nkiemu",
    "wof:placetype":"locality"
},
  "geometry": {"coordinates":[17.74346,-2.58849],"type":"Point"}
}