{
  "type": "Feature",
  "properties": {
    "gn:admin1_code":"15.0",
    "gn:asciiname":"Kalenga",
    "gn:country_code":"CD",
    "gn:dem":1105,
    "gn:feature_class":"P",
    "gn:feature_code":"PPL",
    "gn:name":"Kalenga",
    "gn:population":0,
    "gn:timezone":"Africa/Lubumbashi",
    "iso:country":"CD",
    "wof:name":"Kalenga",
    "wof:placetype":"locality"
},
  "geometry": {"coordinates":[25.16667,-8.65],"type":"Point"}
}