{
  "type": "Feature",
  "properties": {
    "gn:admin1_code":"22.0",
    "gn:asciiname":"Kambulotete",
    "gn:country_code":"CD",
    "gn:dem":1049,
    "gn:feature_class":"P",
    "gn:feature_code":"PPL",
    "gn:name":"Kambulotete",
    "gn:population":0,
    "gn:timezone":"Africa/Lubumbashi",
    "iso:country":"CD",
    "wof:name":"Kambulotete",
    "wof:placetype":"locality"
},
  "geometry": {"coordinates":[21.97557,-8.75527],"type":"Point"}
}