{
  "type": "Feature",
  "properties": {
    "gn:admin1_code":"8.0",
    "gn:asciiname":"Makanga",
    "gn:country_code":"CD",
    "gn:dem":593,
    "gn:feature_class":"P",
    "gn:feature_code":"PPL",
    "gn:name":"Makanga",
    "gn:population":0,
    "gn:timezone":"Africa/Kinshasa",
    "iso:country":"CD",
    "wof:name":"Makanga",
    "wof:placetype":"locality"
},
  "geometry": {"coordinates":[15.23579,-5.48726],"type":"Point"}
}