{
  "type": "Feature",
  "properties": {
    "gn:admin1_code":"31.0",
    "gn:asciiname":"Lileke",
    "gn:country_code":"CD",
    "gn:dem":402,
    "gn:feature_class":"P",
    "gn:feature_code":"PPL",
    "gn:name":"Lileke",
    "gn:population":0,
    "gn:timezone":"Africa/Kinshasa",
    "iso:country":"CD",
    "wof:name":"Lileke",
    "wof:placetype":"locality"
},
  "geometry": {"coordinates":[23.43333,-1.08333],"type":"Point"}
}