{
  "type": "Feature",
  "properties": {
    "gn:admin1_code":"16.0",
    "gn:asciiname":"Karume",
    "gn:country_code":"CD",
    "gn:dem":778,
    "gn:feature_class":"P",
    "gn:feature_code":"PPL",
    "gn:name":"Karume",
    "gn:population":0,
    "gn:timezone":"Africa/Lubumbashi",
    "iso:country":"CD",
    "wof:name":"Karume",
    "wof:placetype":"locality"
},
  "geometry": {"coordinates":[27.8215,2.30819],"type":"Point"}
}