{
  "type": "Feature",
  "properties": {
    "gn:admin1_code":"19.0",
    "gn:asciiname":"Koko Mombo",
    "gn:country_code":"CD",
    "gn:dem":909,
    "gn:feature_class":"P",
    "gn:feature_code":"PPL",
    "gn:name":"Koko Mombo",
    "gn:population":0,
    "gn:timezone":"Africa/Kinshasa",
    "iso:country":"CD",
    "wof:name":"Koko Mombo",
    "wof:placetype":"locality"
},
  "geometry": {"coordinates":[17.33246,-6.44574],"type":"Point"}
}