{
  "type": "Feature",
  "properties": {
    "gn:admin1_code":"19.0",
    "gn:asciiname":"Kikwe-Kavunga",
    "gn:country_code":"CD",
    "gn:dem":470,
    "gn:feature_class":"P",
    "gn:feature_code":"PPL",
    "gn:name":"Kikwe-Kavunga",
    "gn:population":0,
    "gn:timezone":"Africa/Kinshasa",
    "iso:country":"CD",
    "wof:name":"Kikwe-Kavunga",
    "wof:placetype":"locality"
},
  "geometry": {"coordinates":[17.59186,-4.4348],"type":"Point"}
}