{
  "type": "Feature",
  "properties": {
    "gn:admin1_code":"14.0",
    "gn:asciiname":"Polygone-Luantete",
    "gn:country_code":"CD",
    "gn:dem":1064,
    "gn:feature_class":"P",
    "gn:feature_code":"PPL",
    "gn:name":"Polygone-Luantete",
    "gn:population":0,
    "gn:timezone":"Africa/Lubumbashi",
    "iso:country":"CD",
    "wof:name":"Polygone-Luantete",
    "wof:placetype":"locality"
},
  "geometry": {"coordinates":[28.27146,-8.87368],"type":"Point"}
}