{
  "type": "Feature",
  "properties": {
    "gn:admin1_code":"25.0",
    "gn:asciiname":"Bongolu",
    "gn:country_code":"CD",
    "gn:dem":490,
    "gn:feature_class":"P",
    "gn:feature_code":"PPL",
    "gn:name":"Bongolu",
    "gn:population":0,
    "gn:timezone":"Africa/Kinshasa",
    "iso:country":"CD",
    "wof:name":"Bongolu",
    "wof:placetype":"locality"
},
  "geometry": {"coordinates":[22.48978,2.80508],"type":"Point"}
}