{
  "type": "Feature",
  "properties": {
    "gn:admin1_code":"28.0",
    "gn:asciiname":"Boyadodo Premiere",
    "gn:country_code":"CD",
    "gn:dem":445,
    "gn:feature_class":"P",
    "gn:feature_code":"PPL",
    "gn:name":"Boyadodo Premi\u00e8re",
    "gn:population":0,
    "gn:timezone":"Africa/Kinshasa",
    "iso:country":"CD",
    "wof:name":"Boyadodo Premiere",
    "wof:placetype":"locality"
},
  "geometry": {"coordinates":[20.1611,3.30755],"type":"Point"}
}