{
  "type": "Feature",
  "properties": {
    "gn:admin1_code":"29.0",
    "gn:asciiname":"Kiyalo",
    "gn:country_code":"CD",
    "gn:dem":975,
    "gn:feature_class":"P",
    "gn:feature_code":"PPL",
    "gn:name":"Kiyalo",
    "gn:population":0,
    "gn:timezone":"Africa/Lubumbashi",
    "iso:country":"CD",
    "wof:name":"Kiyalo",
    "wof:placetype":"locality"
},
  "geometry": {"coordinates":[28.7767,-6.31358],"type":"Point"}
}