{
  "type": "Feature",
  "properties": {
    "gn:admin1_code":"20.0",
    "gn:asciiname":"Musenge-Kimbimbi",
    "gn:country_code":"CD",
    "gn:dem":551,
    "gn:feature_class":"P",
    "gn:feature_code":"PPL",
    "gn:name":"Musenge-Kimbimbi",
    "gn:population":0,
    "gn:timezone":"Africa/Kinshasa",
    "iso:country":"CD",
    "wof:name":"Musenge-Kimbimbi",
    "wof:placetype":"locality"
},
  "geometry": {"coordinates":[20.04172,-5.08284],"type":"Point"}
}