{
  "type": "Feature",
  "properties": {
    "gn:admin1_code":"28.0",
    "gn:asciiname":"Bogbazudo",
    "gn:country_code":"CD",
    "gn:dem":360,
    "gn:feature_class":"P",
    "gn:feature_code":"PPL",
    "gn:name":"Bogbazudo",
    "gn:population":0,
    "gn:timezone":"Africa/Kinshasa",
    "iso:country":"CD",
    "wof:name":"Bogbazudo",
    "wof:placetype":"locality"
},
  "geometry": {"coordinates":[18.91037,3.02273],"type":"Point"}
}