{
  "type": "Feature",
  "properties": {
    "gn:admin1_code":"10.0",
    "gn:asciiname":"Biunkutu",
    "gn:country_code":"CD",
    "gn:dem":661,
    "gn:feature_class":"P",
    "gn:feature_code":"PPL",
    "gn:name":"Biunkutu",
    "gn:population":0,
    "gn:timezone":"Africa/Lubumbashi",
    "iso:country":"CD",
    "wof:name":"Biunkutu",
    "wof:placetype":"locality"
},
  "geometry": {"coordinates":[26.68184,-3.5881],"type":"Point"}
}