{
  "type": "Feature",
  "properties": {
    "gn:admin1_code":"21.0",
    "gn:asciiname":"Kenge-Tambwe",
    "gn:country_code":"CD",
    "gn:dem":749,
    "gn:feature_class":"P",
    "gn:feature_code":"PPL",
    "gn:name":"Kenge-Tambwe",
    "gn:population":0,
    "gn:timezone":"Africa/Lubumbashi",
    "iso:country":"CD",
    "wof:name":"Kenge-Tambwe",
    "wof:placetype":"locality"
},
  "geometry": {"coordinates":[24.84571,-5.99782],"type":"Point"}
}