{
  "type": "Feature",
  "properties": {
    "gn:admin1_code":"20.0",
    "gn:asciiname":"Kwanga",
    "gn:country_code":"CD",
    "gn:dem":494,
    "gn:feature_class":"P",
    "gn:feature_code":"PPL",
    "gn:name":"Kwanga",
    "gn:population":0,
    "gn:timezone":"Africa/Kinshasa",
    "iso:country":"CD",
    "wof:name":"Kwanga",
    "wof:placetype":"locality"
},
  "geometry": {"coordinates":[19.71303,-5.07573],"type":"Point"}
}