{
  "type": "Feature",
  "properties": {
    "gn:admin1_code":"12.0",
    "gn:asciiname":"Matali",
    "gn:country_code":"CD",
    "gn:dem":1011,
    "gn:feature_class":"P",
    "gn:feature_code":"PPL",
    "gn:name":"Matali",
    "gn:population":0,
    "gn:timezone":"Africa/Lubumbashi",
    "iso:country":"CD",
    "wof:name":"Matali",
    "wof:placetype":"locality"
},
  "geometry": {"coordinates":[28.19898,-3.26706],"type":"Point"}
}