{
  "type": "Feature",
  "properties": {
    "gn:admin1_code":"23.0",
    "gn:asciiname":"Kalamba",
    "gn:country_code":"CD",
    "gn:dem":592,
    "gn:feature_class":"P",
    "gn:feature_code":"PPL",
    "gn:name":"Kalamba",
    "gn:population":0,
    "gn:timezone":"Africa/Lubumbashi",
    "iso:country":"CD",
    "name:ita_x_preferred":[
        "Kalamba"
    ],
    "name:swa_x_preferred":[
        "Kalamba"
    ],
    "wof:name":"Kalamba",
    "wof:placetype":"locality"
},
  "geometry": {"coordinates":[21.88546,-5.08291],"type":"Point"}
}