{
  "type": "Feature",
  "properties": {
    "gn:admin1_code":"19.0",
    "gn:asciiname":"Kamvumbu",
    "gn:country_code":"CD",
    "gn:dem":1015,
    "gn:feature_class":"P",
    "gn:feature_code":"PPL",
    "gn:name":"Kamvumbu",
    "gn:population":0,
    "gn:timezone":"Africa/Kinshasa",
    "iso:country":"CD",
    "wof:name":"Kamvumbu",
    "wof:placetype":"locality"
},
  "geometry": {"coordinates":[19.42397,-7.49799],"type":"Point"}
}