{
  "type": "Feature",
  "properties": {
    "gn:admin1_code":"23.0",
    "gn:asciiname":"Musango",
    "gn:country_code":"CD",
    "gn:dem":804,
    "gn:feature_class":"P",
    "gn:feature_code":"PPL",
    "gn:name":"Musango",
    "gn:population":0,
    "gn:timezone":"Africa/Lubumbashi",
    "iso:country":"CD",
    "wof:name":"Musango",
    "wof:placetype":"locality"
},
  "geometry": {"coordinates":[22.84893,-6.20659],"type":"Point"}
}