{
  "type": "Feature",
  "properties": {
    "gn:admin1_code":"21.0",
    "gn:asciiname":"Seke",
    "gn:country_code":"CD",
    "gn:dem":622,
    "gn:feature_class":"P",
    "gn:feature_code":"PPL",
    "gn:name":"Seke",
    "gn:population":0,
    "gn:timezone":"Africa/Lubumbashi",
    "iso:country":"CD",
    "name:und_x_variant":[
        "Kiluka",
        "Seke"
    ],
    "wof:name":"Seke",
    "wof:placetype":"locality"
},
  "geometry": {"coordinates":[25.74054,-5.13138],"type":"Point"}
}