{
  "type": "Feature",
  "properties": {
    "gn:admin1_code":"28.0",
    "gn:asciiname":"Bandi I",
    "gn:country_code":"CD",
    "gn:dem":542,
    "gn:feature_class":"P",
    "gn:feature_code":"PPL",
    "gn:name":"Bandi I",
    "gn:population":0,
    "gn:timezone":"Africa/Kinshasa",
    "iso:country":"CD",
    "name:und_x_variant":[
        "Bandi",
        "Bandi I"
    ],
    "wof:name":"Bandi I",
    "wof:placetype":"locality"
},
  "geometry": {"coordinates":[18.85,4.51667],"type":"Point"}
}