{
  "type": "Feature",
  "properties": {
    "gn:admin1_code":"8.0",
    "gn:asciiname":"Mpata",
    "gn:country_code":"CD",
    "gn:dem":687,
    "gn:feature_class":"P",
    "gn:feature_code":"PPL",
    "gn:name":"Mpata",
    "gn:population":0,
    "gn:timezone":"Africa/Kinshasa",
    "iso:country":"CD",
    "wof:name":"Mpata",
    "wof:placetype":"locality"
},
  "geometry": {"coordinates":[15.33348,-5.29614],"type":"Point"}
}