{
  "type": "Feature",
  "properties": {
    "gn:admin1_code":"19.0",
    "gn:asciiname":"Tshitanga",
    "gn:country_code":"CD",
    "gn:dem":1025,
    "gn:feature_class":"P",
    "gn:feature_code":"PPL",
    "gn:name":"Tshitanga",
    "gn:population":0,
    "gn:timezone":"Africa/Kinshasa",
    "iso:country":"CD",
    "wof:name":"Tshitanga",
    "wof:placetype":"locality"
},
  "geometry": {"coordinates":[19.11395,-7.32625],"type":"Point"}
}