{
  "type": "Feature",
  "properties": {
    "gn:admin1_code":"25.0",
    "gn:asciiname":"Busu-Gumani",
    "gn:country_code":"CD",
    "gn:dem":347,
    "gn:feature_class":"P",
    "gn:feature_code":"PPL",
    "gn:name":"Busu-Gumani",
    "gn:population":0,
    "gn:timezone":"Africa/Kinshasa",
    "iso:country":"CD",
    "name:und_x_variant":[
        "Busu-Gomani",
        "Gumani",
        "Busu-Gumani"
    ],
    "wof:name":"Busu-Gumani",
    "wof:placetype":"locality"
},
  "geometry": {"coordinates":[20.65006,2.181],"type":"Point"}
}