{
  "type": "Feature",
  "properties": {
    "gn:admin1_code":"14.0",
    "gn:asciiname":"Mukandala",
    "gn:country_code":"CD",
    "gn:dem":1088,
    "gn:feature_class":"P",
    "gn:feature_code":"PPL",
    "gn:name":"Mukandala",
    "gn:population":0,
    "gn:timezone":"Africa/Lubumbashi",
    "iso:country":"CD",
    "wof:name":"Mukandala",
    "wof:placetype":"locality"
},
  "geometry": {"coordinates":[28.92424,-8.40273],"type":"Point"}
}