{
  "type": "Feature",
  "properties": {
    "gn:admin1_code":"8.0",
    "gn:asciiname":"Mawete",
    "gn:country_code":"CD",
    "gn:dem":340,
    "gn:feature_class":"P",
    "gn:feature_code":"PPL",
    "gn:name":"Mawete",
    "gn:population":0,
    "gn:timezone":"Africa/Kinshasa",
    "iso:country":"CD",
    "wof:name":"Mawete",
    "wof:placetype":"locality"
},
  "geometry": {"coordinates":[14.20394,-5.82395],"type":"Point"}
}