{
  "type": "Feature",
  "properties": {
    "gn:admin1_code":"17.0",
    "gn:asciiname":"Litshunga",
    "gn:country_code":"CD",
    "gn:dem":1376,
    "gn:feature_class":"P",
    "gn:feature_code":"PPL",
    "gn:name":"Litshunga",
    "gn:population":0,
    "gn:timezone":"Africa/Lubumbashi",
    "iso:country":"CD",
    "wof:name":"Litshunga",
    "wof:placetype":"locality"
},
  "geometry": {"coordinates":[30.3848,1.80338],"type":"Point"}
}