{
  "type": "Feature",
  "properties": {
    "gn:admin1_code":"15.0",
    "gn:asciiname":"Kitebele Kya Luie",
    "gn:country_code":"CD",
    "gn:dem":935,
    "gn:feature_class":"P",
    "gn:feature_code":"PPL",
    "gn:name":"Kitebele Kya Luie",
    "gn:population":0,
    "gn:timezone":"Africa/Lubumbashi",
    "iso:country":"CD",
    "name:und_x_variant":[
        "Kitebele-ya-Ntanda"
    ],
    "wof:name":"Kitebele Kya Luie",
    "wof:placetype":"locality"
},
  "geometry": {"coordinates":[25.34756,-7.13707],"type":"Point"}
}