{
  "type": "Feature",
  "properties": {
    "gn:admin1_code":"10.0",
    "gn:asciiname":"Mwitia",
    "gn:country_code":"CD",
    "gn:dem":483,
    "gn:feature_class":"P",
    "gn:feature_code":"PPL",
    "gn:name":"Mwitia",
    "gn:population":0,
    "gn:timezone":"Africa/Lubumbashi",
    "iso:country":"CD",
    "wof:name":"Mwitia",
    "wof:placetype":"locality"
},
  "geometry": {"coordinates":[25.31694,-2.52026],"type":"Point"}
}