{
  "type": "Feature",
  "properties": {
    "gn:admin1_code":"23.0",
    "gn:asciiname":"Mai",
    "gn:country_code":"CD",
    "gn:dem":806,
    "gn:feature_class":"P",
    "gn:feature_code":"PPL",
    "gn:name":"Mai",
    "gn:population":0,
    "gn:timezone":"Africa/Lubumbashi",
    "iso:country":"CD",
    "wof:name":"Mai",
    "wof:placetype":"locality"
},
  "geometry": {"coordinates":[21.77958,-6.61765],"type":"Point"}
}