{
  "type": "Feature",
  "properties": {
    "gn:admin1_code":"26.0",
    "gn:asciiname":"Lengo",
    "gn:country_code":"CD",
    "gn:dem":609,
    "gn:feature_class":"P",
    "gn:feature_code":"PPL",
    "gn:name":"Lengo",
    "gn:population":0,
    "gn:timezone":"Africa/Kinshasa",
    "iso:country":"CD",
    "wof:name":"Lengo",
    "wof:placetype":"locality"
},
  "geometry": {"coordinates":[20.26108,4.3389],"type":"Point"}
}