{
  "type": "Feature",
  "properties": {
    "gn:admin1_code":"18.0",
    "gn:asciiname":"Tshinyama",
    "gn:country_code":"CD",
    "gn:dem":659,
    "gn:feature_class":"P",
    "gn:feature_code":"PPL",
    "gn:name":"Tshinyama",
    "gn:population":0,
    "gn:timezone":"Africa/Lubumbashi",
    "iso:country":"CD",
    "wof:name":"Tshinyama",
    "wof:placetype":"locality"
},
  "geometry": {"coordinates":[21.48996,-6.09656],"type":"Point"}
}