{
  "type": "Feature",
  "properties": {
    "gn:admin1_code":"16.0",
    "gn:asciiname":"Mambata",
    "gn:country_code":"CD",
    "gn:dem":771,
    "gn:feature_class":"P",
    "gn:feature_code":"PPL",
    "gn:name":"Mambata",
    "gn:population":0,
    "gn:timezone":"Africa/Lubumbashi",
    "iso:country":"CD",
    "wof:name":"Mambata",
    "wof:placetype":"locality"
},
  "geometry": {"coordinates":[27.57627,2.24504],"type":"Point"}
}