{
  "type": "Feature",
  "properties": {
    "gn:admin1_code":"19.0",
    "gn:asciiname":"Mulopo-Fuangulu",
    "gn:country_code":"CD",
    "gn:dem":609,
    "gn:feature_class":"P",
    "gn:feature_code":"PPL",
    "gn:name":"Mulopo-Fuangulu",
    "gn:population":0,
    "gn:timezone":"Africa/Kinshasa",
    "iso:country":"CD",
    "wof:name":"Mulopo-Fuangulu",
    "wof:placetype":"locality"
},
  "geometry": {"coordinates":[16.8604,-4.33579],"type":"Point"}
}