{
  "type": "Feature",
  "properties": {
    "gn:admin1_code":"28.0",
    "gn:asciiname":"Yakili",
    "gn:country_code":"CD",
    "gn:dem":395,
    "gn:feature_class":"P",
    "gn:feature_code":"PPL",
    "gn:name":"Yakili",
    "gn:population":0,
    "gn:timezone":"Africa/Kinshasa",
    "iso:country":"CD",
    "wof:name":"Yakili",
    "wof:placetype":"locality"
},
  "geometry": {"coordinates":[18.68167,4.21806],"type":"Point"}
}