{
  "type": "Feature",
  "properties": {
    "gn:admin1_code":"25.0",
    "gn:asciiname":"Mombilo-Lipembe",
    "gn:country_code":"CD",
    "gn:dem":432,
    "gn:feature_class":"P",
    "gn:feature_code":"PPL",
    "gn:name":"Mombilo-Lipembe",
    "gn:population":0,
    "gn:timezone":"Africa/Kinshasa",
    "iso:country":"CD",
    "name:und_x_variant":[
        "Molimo-Lipembe",
        "Mombilo-Lipembe"
    ],
    "wof:name":"Mombilo-Lipembe",
    "wof:placetype":"locality"
},
  "geometry": {"coordinates":[21.46715,2.27086],"type":"Point"}
}