{
  "type": "Feature",
  "properties": {
    "gn:admin1_code":"26.0",
    "gn:asciiname":"Zamba",
    "gn:country_code":"CD",
    "gn:dem":544,
    "gn:feature_class":"P",
    "gn:feature_code":"PPL",
    "gn:name":"Zamba",
    "gn:population":0,
    "gn:timezone":"Africa/Kinshasa",
    "iso:country":"CD",
    "wof:name":"Zamba",
    "wof:placetype":"locality"
},
  "geometry": {"coordinates":[21.67234,4.19604],"type":"Point"}
}