{
  "type": "Feature",
  "properties": {
    "gn:admin1_code":"15.0",
    "gn:asciiname":"Madja",
    "gn:country_code":"CD",
    "gn:dem":998,
    "gn:feature_class":"P",
    "gn:feature_code":"PPL",
    "gn:name":"Madja",
    "gn:population":0,
    "gn:timezone":"Africa/Lubumbashi",
    "iso:country":"CD",
    "name:und_x_variant":[
        "Mabia",
        "Madia",
        "Madja"
    ],
    "wof:name":"Madja",
    "wof:placetype":"locality"
},
  "geometry": {"coordinates":[26.00147,-7.13238],"type":"Point"}
}