{
  "type": "Feature",
  "properties": {
    "gn:admin1_code":"8.0",
    "gn:asciiname":"Kinkayika",
    "gn:country_code":"CD",
    "gn:dem":912,
    "gn:feature_class":"P",
    "gn:feature_code":"PPL",
    "gn:name":"Kinkayika",
    "gn:population":0,
    "gn:timezone":"Africa/Kinshasa",
    "iso:country":"CD",
    "wof:name":"Kinkayika",
    "wof:placetype":"locality"
},
  "geometry": {"coordinates":[15.79252,-5.6914],"type":"Point"}
}