{
  "type": "Feature",
  "properties": {
    "gn:admin1_code":"8.0",
    "gn:asciiname":"Kingalasa",
    "gn:country_code":"CD",
    "gn:dem":67,
    "gn:feature_class":"P",
    "gn:feature_code":"PPL",
    "gn:name":"Kingalasa",
    "gn:population":0,
    "gn:timezone":"Africa/Kinshasa",
    "iso:country":"CD",
    "wof:name":"Kingalasa",
    "wof:placetype":"locality"
},
  "geometry": {"coordinates":[12.4862,-5.95767],"type":"Point"}
}