{
  "type": "Feature",
  "properties": {
    "gn:admin1_code":"15.0",
    "gn:asciiname":"Kamusenga",
    "gn:country_code":"CD",
    "gn:dem":889,
    "gn:feature_class":"P",
    "gn:feature_code":"PPL",
    "gn:name":"Kamusenga",
    "gn:population":0,
    "gn:timezone":"Africa/Lubumbashi",
    "iso:country":"CD",
    "wof:name":"Kamusenga",
    "wof:placetype":"locality"
},
  "geometry": {"coordinates":[25.21667,-7.36667],"type":"Point"}
}