{
  "type": "Feature",
  "properties": {
    "gn:admin1_code":"27.0",
    "gn:asciiname":"Mukundji",
    "gn:country_code":"CD",
    "gn:dem":589,
    "gn:feature_class":"P",
    "gn:feature_code":"PPL",
    "gn:name":"Mukundji",
    "gn:population":0,
    "gn:timezone":"Africa/Lubumbashi",
    "iso:country":"CD",
    "wof:name":"Mukundji",
    "wof:placetype":"locality"
},
  "geometry": {"coordinates":[24.27221,-4.76411],"type":"Point"}
}