{
  "type": "Feature",
  "properties": {
    "gn:admin1_code":"23.0",
    "gn:asciiname":"Ndesha",
    "gn:country_code":"CD",
    "gn:dem":612,
    "gn:feature_class":"P",
    "gn:feature_code":"PPL",
    "gn:name":"Ndesha",
    "gn:population":0,
    "gn:timezone":"Africa/Lubumbashi",
    "iso:country":"CD",
    "name:und_x_variant":[
        "Ndesiha",
        "Ndeshia",
        "Ndesha"
    ],
    "wof:name":"Ndesha",
    "wof:placetype":"locality"
},
  "geometry": {"coordinates":[22.38593,-5.86514],"type":"Point"}
}