{
  "type": "Feature",
  "properties": {
    "gn:admin1_code":"14.0",
    "gn:asciiname":"Musoshi-Salesienne",
    "gn:country_code":"CD",
    "gn:dem":1151,
    "gn:feature_class":"P",
    "gn:feature_code":"PPL",
    "gn:name":"Musoshi-Salesienne",
    "gn:population":0,
    "gn:timezone":"Africa/Lubumbashi",
    "iso:country":"CD",
    "wof:name":"Musoshi-Salesienne",
    "wof:placetype":"locality"
},
  "geometry": {"coordinates":[27.78588,-11.93189],"type":"Point"}
}