{
  "type": "Feature",
  "properties": {
    "gn:admin1_code":"15.0",
    "gn:asciiname":"Butu",
    "gn:country_code":"CD",
    "gn:dem":723,
    "gn:feature_class":"P",
    "gn:feature_code":"PPL",
    "gn:name":"Butu",
    "gn:population":0,
    "gn:timezone":"Africa/Lubumbashi",
    "iso:country":"CD",
    "wof:name":"Butu",
    "wof:placetype":"locality"
},
  "geometry": {"coordinates":[25.79235,-7.98289],"type":"Point"}
}