{
  "type": "Feature",
  "properties": {
    "gn:admin1_code":"28.0",
    "gn:asciiname":"Banza-Kombe",
    "gn:country_code":"CD",
    "gn:dem":346,
    "gn:feature_class":"P",
    "gn:feature_code":"PPL",
    "gn:name":"Banza-Kombe",
    "gn:population":0,
    "gn:timezone":"Africa/Kinshasa",
    "iso:country":"CD",
    "wof:name":"Banza-Kombe",
    "wof:placetype":"locality"
},
  "geometry": {"coordinates":[18.13072,2.02766],"type":"Point"}
}