{
  "type": "Feature",
  "properties": {
    "gn:admin1_code":"14.0",
    "gn:asciiname":"Kabombo",
    "gn:country_code":"CD",
    "gn:dem":1201,
    "gn:feature_class":"P",
    "gn:feature_code":"PPL",
    "gn:name":"Kabombo",
    "gn:population":0,
    "gn:timezone":"Africa/Lubumbashi",
    "iso:country":"CD",
    "wof:name":"Kabombo",
    "wof:placetype":"locality"
},
  "geometry": {"coordinates":[26.60667,-10.76194],"type":"Point"}
}