{
  "type": "Feature",
  "properties": {
    "gn:admin1_code":"29.0",
    "gn:asciiname":"Maliangi",
    "gn:country_code":"CD",
    "gn:dem":628,
    "gn:feature_class":"P",
    "gn:feature_code":"PPL",
    "gn:name":"Maliangi",
    "gn:population":0,
    "gn:timezone":"Africa/Lubumbashi",
    "iso:country":"CD",
    "wof:name":"Maliangi",
    "wof:placetype":"locality"
},
  "geometry": {"coordinates":[27.97321,-5.64157],"type":"Point"}
}