{
  "type": "Feature",
  "properties": {
    "gn:admin1_code":"22.0",
    "gn:asciiname":"Kitentashi",
    "gn:country_code":"CD",
    "gn:dem":1063,
    "gn:feature_class":"P",
    "gn:feature_code":"PPL",
    "gn:name":"Kitentashi",
    "gn:population":0,
    "gn:timezone":"Africa/Lubumbashi",
    "iso:country":"CD",
    "wof:name":"Kitentashi",
    "wof:placetype":"locality"
},
  "geometry": {"coordinates":[24.02737,-10.0051],"type":"Point"}
}