{
  "type": "Feature",
  "properties": {
    "gn:admin1_code":"24.0",
    "gn:asciiname":"Ikilimoru",
    "gn:country_code":"CD",
    "gn:dem":381,
    "gn:feature_class":"P",
    "gn:feature_code":"PPL",
    "gn:name":"Ikilimoru",
    "gn:population":0,
    "gn:timezone":"Africa/Kinshasa",
    "iso:country":"CD",
    "wof:name":"Ikilimoru",
    "wof:placetype":"locality"
},
  "geometry": {"coordinates":[16.85817999999999,-2.82391],"type":"Point"}
}