{
  "type": "Feature",
  "properties": {
    "gn:admin1_code":"30.0",
    "gn:asciiname":"Basayo",
    "gn:country_code":"CD",
    "gn:dem":379,
    "gn:feature_class":"P",
    "gn:feature_code":"PPL",
    "gn:name":"Basayo",
    "gn:population":0,
    "gn:timezone":"Africa/Lubumbashi",
    "iso:country":"CD",
    "wof:name":"Basayo",
    "wof:placetype":"locality"
},
  "geometry": {"coordinates":[23.57387,1.27569],"type":"Point"}
}