{
  "type": "Feature",
  "properties": {
    "gn:admin1_code":"10.0",
    "gn:asciiname":"Monganga",
    "gn:country_code":"CD",
    "gn:dem":576,
    "gn:feature_class":"P",
    "gn:feature_code":"PPL",
    "gn:name":"Monganga",
    "gn:population":0,
    "gn:timezone":"Africa/Lubumbashi",
    "iso:country":"CD",
    "wof:name":"Monganga",
    "wof:placetype":"locality"
},
  "geometry": {"coordinates":[26.56667,-4.26667],"type":"Point"}
}