{
  "type": "Feature",
  "properties": {
    "gn:admin1_code":"28.0",
    "gn:asciiname":"Bowasi-Tamba",
    "gn:country_code":"CD",
    "gn:dem":354,
    "gn:feature_class":"P",
    "gn:feature_code":"PPL",
    "gn:name":"Bowasi-Tamba",
    "gn:population":0,
    "gn:timezone":"Africa/Kinshasa",
    "iso:country":"CD",
    "name:und_x_variant":[
        "Bowasi",
        "Bowasi-Tamba"
    ],
    "wof:name":"Bowasi-Tamba",
    "wof:placetype":"locality"
},
  "geometry": {"coordinates":[19.3914,3.47612],"type":"Point"}
}