{
  "type": "Feature",
  "properties": {
    "gn:admin1_code":"4.0",
    "gn:asciiname":"Tshibuyi",
    "gn:country_code":"CD",
    "gn:dem":615,
    "gn:feature_class":"P",
    "gn:feature_code":"PPL",
    "gn:name":"Tshibuyi",
    "gn:population":0,
    "gn:timezone":"Africa/Lubumbashi",
    "iso:country":"CD",
    "wof:name":"Tshibuyi",
    "wof:placetype":"locality"
},
  "geometry": {"coordinates":[23.1887,-6.08441],"type":"Point"}
}