{
  "type": "Feature",
  "properties": {
    "gn:admin1_code":"16.0",
    "gn:asciiname":"Bakbuku",
    "gn:country_code":"CD",
    "gn:dem":700,
    "gn:feature_class":"P",
    "gn:feature_code":"PPL",
    "gn:name":"Bakbuku",
    "gn:population":0,
    "gn:timezone":"Africa/Lubumbashi",
    "iso:country":"CD",
    "wof:name":"Bakbuku",
    "wof:placetype":"locality"
},
  "geometry": {"coordinates":[27.40932,4.01928],"type":"Point"}
}