{
  "type": "Feature",
  "properties": {
    "gn:admin1_code":"13.0",
    "gn:asciiname":"Zima",
    "gn:country_code":"CD",
    "gn:dem":716,
    "gn:feature_class":"P",
    "gn:feature_code":"PPL",
    "gn:name":"Zima",
    "gn:population":0,
    "gn:timezone":"Africa/Lubumbashi",
    "iso:country":"CD",
    "name:bel_x_preferred":[
        "\u0417\u0456\u043c\u0430"
    ],
    "name:ceb_x_preferred":[
        "Zima"
    ],
    "name:ces_x_preferred":[
        "Zima"
    ],
    "name:deu_x_preferred":[
        "Zima"
    ],
    "name:ita_x_preferred":[
        "Zima"
    ],
    "name:pol_x_preferred":[
        "Zima"
    ],
    "name:slk_x_preferred":[
        "Zima"
    ],
    "name:swe_x_preferred":[
        "Zima"
    ],
    "name:ukr_x_preferred":[
        "\u0417\u0438\u043c\u0430"
    ],
    "wof:name":"Zima",
    "wof:placetype":"locality"
},
  "geometry": {"coordinates":[27.32966,3.59658],"type":"Point"}
}