{
  "type": "Feature",
  "properties": {
    "gn:admin1_code":"29.0",
    "gn:asciiname":"Yayi",
    "gn:country_code":"CD",
    "gn:dem":549,
    "gn:feature_class":"P",
    "gn:feature_code":"PPL",
    "gn:name":"Yayi",
    "gn:population":0,
    "gn:timezone":"Africa/Lubumbashi",
    "iso:country":"CD",
    "name:und_x_variant":[
        "Yaya",
        "Yayi"
    ],
    "wof:name":"Yayi",
    "wof:placetype":"locality"
},
  "geometry": {"coordinates":[27.00092,-5.24531],"type":"Point"}
}