{
  "type": "Feature",
  "properties": {
    "gn:admin1_code":"30.0",
    "gn:asciiname":"Yaeloti",
    "gn:country_code":"CD",
    "gn:dem":399,
    "gn:feature_class":"P",
    "gn:feature_code":"PPL",
    "gn:name":"Yaeloti",
    "gn:population":0,
    "gn:timezone":"Africa/Lubumbashi",
    "iso:country":"CD",
    "wof:name":"Yaeloti",
    "wof:placetype":"locality"
},
  "geometry": {"coordinates":[23.53333,1.58333],"type":"Point"}
}