{
  "type": "Feature",
  "properties": {
    "gn:admin1_code":"28.0",
    "gn:asciiname":"Boso-Libwa",
    "gn:country_code":"CD",
    "gn:dem":385,
    "gn:feature_class":"P",
    "gn:feature_code":"PPL",
    "gn:name":"Boso-Libwa",
    "gn:population":0,
    "gn:timezone":"Africa/Kinshasa",
    "iso:country":"CD",
    "name:fra_x_preferred":[
        "Boso-Libwa"
    ],
    "wof:name":"Boso-Libwa",
    "wof:placetype":"locality"
},
  "geometry": {"coordinates":[19.52086,2.429],"type":"Point"}
}