{
  "type": "Feature",
  "properties": {
    "gn:admin1_code":"13.0",
    "gn:asciiname":"Aniza",
    "gn:country_code":"CD",
    "gn:dem":649,
    "gn:feature_class":"P",
    "gn:feature_code":"PPL",
    "gn:name":"Aniza",
    "gn:population":0,
    "gn:timezone":"Africa/Lubumbashi",
    "iso:country":"CD",
    "wof:name":"Aniza",
    "wof:placetype":"locality"
},
  "geometry": {"coordinates":[25.78293,4.39783],"type":"Point"}
}