{
  "type": "Feature",
  "properties": {
    "gn:admin1_code":"27.0",
    "gn:asciiname":"Ipeko",
    "gn:country_code":"CD",
    "gn:dem":484,
    "gn:feature_class":"P",
    "gn:feature_code":"PPL",
    "gn:name":"Ipeko",
    "gn:population":0,
    "gn:timezone":"Africa/Lubumbashi",
    "iso:country":"CD",
    "wof:name":"Ipeko",
    "wof:placetype":"locality"
},
  "geometry": {"coordinates":[22.28333,-3.05],"type":"Point"}
}