{
  "type": "Feature",
  "properties": {
    "gn:admin1_code":"23.0",
    "gn:asciiname":"Tshidiama-Kalu",
    "gn:country_code":"CD",
    "gn:dem":687,
    "gn:feature_class":"P",
    "gn:feature_code":"PPL",
    "gn:name":"Tshidiama-Kalu",
    "gn:population":0,
    "gn:timezone":"Africa/Lubumbashi",
    "iso:country":"CD",
    "wof:name":"Tshidiama-Kalu",
    "wof:placetype":"locality"
},
  "geometry": {"coordinates":[21.5816,-6.84747],"type":"Point"}
}