{
  "type": "Feature",
  "properties": {
    "gn:admin1_code":"27.0",
    "gn:asciiname":"Pata Ikundji",
    "gn:country_code":"CD",
    "gn:dem":587,
    "gn:feature_class":"P",
    "gn:feature_code":"PPL",
    "gn:name":"Pata Ikundji",
    "gn:population":0,
    "gn:timezone":"Africa/Lubumbashi",
    "iso:country":"CD",
    "wof:name":"Pata Ikundji",
    "wof:placetype":"locality"
},
  "geometry": {"coordinates":[22.21623,-3.88129],"type":"Point"}
}