{
  "type": "Feature",
  "properties": {
    "gn:admin1_code":"30.0",
    "gn:asciiname":"Banisoba",
    "gn:country_code":"CD",
    "gn:dem":470,
    "gn:feature_class":"P",
    "gn:feature_code":"PPL",
    "gn:name":"Banisoba",
    "gn:population":0,
    "gn:timezone":"Africa/Lubumbashi",
    "iso:country":"CD",
    "wof:name":"Banisoba",
    "wof:placetype":"locality"
},
  "geometry": {"coordinates":[25.46667,-0.86667],"type":"Point"}
}