{
  "type": "Feature",
  "properties": {
    "gn:admin1_code":"17.0",
    "gn:asciiname":"Butsha",
    "gn:country_code":"CD",
    "gn:dem":873,
    "gn:feature_class":"P",
    "gn:feature_code":"PPL",
    "gn:name":"Butsha",
    "gn:population":0,
    "gn:timezone":"Africa/Lubumbashi",
    "iso:country":"CD",
    "name:und_x_variant":[
        "Butsa"
    ],
    "wof:name":"Butsha",
    "wof:placetype":"locality"
},
  "geometry": {"coordinates":[29.22994000000001,0.94577],"type":"Point"}
}