{
  "type": "Feature",
  "properties": {
    "gn:admin1_code":"16.0",
    "gn:asciiname":"Alagwa",
    "gn:country_code":"CD",
    "gn:dem":952,
    "gn:feature_class":"P",
    "gn:feature_code":"PPL",
    "gn:name":"Alagwa",
    "gn:population":0,
    "gn:timezone":"Africa/Lubumbashi",
    "iso:country":"CD",
    "wof:name":"Alagwa",
    "wof:placetype":"locality"
},
  "geometry": {"coordinates":[30.01943,3.24189],"type":"Point"}
}