{
  "type": "Feature",
  "properties": {
    "gn:admin1_code":"23.0",
    "gn:asciiname":"Bumba",
    "gn:country_code":"CD",
    "gn:dem":806,
    "gn:feature_class":"P",
    "gn:feature_code":"PPL",
    "gn:name":"Bumba",
    "gn:population":0,
    "gn:timezone":"Africa/Lubumbashi",
    "iso:country":"CD",
    "wof:name":"Bumba",
    "wof:placetype":"locality"
},
  "geometry": {"coordinates":[22.25002000000001,-6.55804],"type":"Point"}
}