{
  "type": "Feature",
  "properties": {
    "gn:admin1_code":"27.0",
    "gn:asciiname":"Teke",
    "gn:country_code":"CD",
    "gn:dem":547,
    "gn:feature_class":"P",
    "gn:feature_code":"PPL",
    "gn:name":"Teke",
    "gn:population":0,
    "gn:timezone":"Africa/Lubumbashi",
    "iso:country":"CD",
    "wof:name":"Teke",
    "wof:placetype":"locality"
},
  "geometry": {"coordinates":[23.55401,-3.34966],"type":"Point"}
}