{
  "type": "Feature",
  "properties": {
    "gn:admin1_code":"2.0",
    "gn:asciiname":"Likedji",
    "gn:country_code":"CD",
    "gn:dem":364,
    "gn:feature_class":"P",
    "gn:feature_code":"PPL",
    "gn:name":"Likedji",
    "gn:population":0,
    "gn:timezone":"Africa/Kinshasa",
    "iso:country":"CD",
    "wof:name":"Likedji",
    "wof:placetype":"locality"
},
  "geometry": {"coordinates":[20.03333,0.41667],"type":"Point"}
}