{
  "type": "Feature",
  "properties": {
    "gn:admin1_code":"8.0",
    "gn:asciiname":"Nionga",
    "gn:country_code":"CD",
    "gn:dem":703,
    "gn:feature_class":"P",
    "gn:feature_code":"PPL",
    "gn:name":"Nionga",
    "gn:population":0,
    "gn:timezone":"Africa/Kinshasa",
    "iso:country":"CD",
    "wof:name":"Nionga",
    "wof:placetype":"locality"
},
  "geometry": {"coordinates":[14.63687,-5.20451],"type":"Point"}
}