{
  "type": "Feature",
  "properties": {
    "gn:admin1_code":"28.0",
    "gn:asciiname":"Boso-Zimbero",
    "gn:country_code":"CD",
    "gn:dem":383,
    "gn:feature_class":"P",
    "gn:feature_code":"PPL",
    "gn:name":"Boso-Zimbero",
    "gn:population":0,
    "gn:timezone":"Africa/Kinshasa",
    "iso:country":"CD",
    "wof:name":"Boso-Zimbero",
    "wof:placetype":"locality"
},
  "geometry": {"coordinates":[18.6725,3.66398],"type":"Point"}
}