{
  "type": "Feature",
  "properties": {
    "gn:admin1_code":"23.0",
    "gn:asciiname":"Nsafu",
    "gn:country_code":"CD",
    "gn:dem":832,
    "gn:feature_class":"P",
    "gn:feature_code":"PPL",
    "gn:name":"Nsafu",
    "gn:population":0,
    "gn:timezone":"Africa/Lubumbashi",
    "iso:country":"CD",
    "wof:name":"Nsafu",
    "wof:placetype":"locality"
},
  "geometry": {"coordinates":[22.50928,-6.88414],"type":"Point"}
}