{
  "type": "Feature",
  "properties": {
    "gn:admin1_code":"20.0",
    "gn:asciiname":"Lukanga",
    "gn:country_code":"CD",
    "gn:dem":397,
    "gn:feature_class":"P",
    "gn:feature_code":"PPL",
    "gn:name":"Lukanga",
    "gn:population":0,
    "gn:timezone":"Africa/Kinshasa",
    "iso:country":"CD",
    "name:ceb_x_preferred":[
        "Lukanga"
    ],
    "name:swe_x_preferred":[
        "Lukanga"
    ],
    "wof:name":"Lukanga",
    "wof:placetype":"locality"
},
  "geometry": {"coordinates":[18.76536,-4.00875],"type":"Point"}
}