{
  "type": "Feature",
  "properties": {
    "gn:admin1_code":"11.0",
    "gn:asciiname":"Home",
    "gn:country_code":"CD",
    "gn:dem":963,
    "gn:feature_class":"P",
    "gn:feature_code":"PPL",
    "gn:name":"Home",
    "gn:population":0,
    "gn:timezone":"Africa/Lubumbashi",
    "iso:country":"CD",
    "name:ang_x_preferred":[
        "H\u0101m"
    ],
    "name:ara_x_preferred":[
        "\u0628\u064a\u062a"
    ],
    "name:aym_x_preferred":[
        "Utjawi"
    ],
    "name:bul_x_preferred":[
        "\u0414\u043e\u043c"
    ],
    "name:cat_x_preferred":[
        "Llar"
    ],
    "name:ckb_x_preferred":[
        "\u0645\u0627\u06b5"
    ],
    "name:epo_x_preferred":[
        "Hejmo"
    ],
    "name:est_x_preferred":[
        "Kodu"
    ],
    "name:fas_x_preferred":[
        "\u062e\u0627\u0646\u0645\u0627\u0646"
    ],
    "name:fin_x_preferred":[
        "Koti"
    ],
    "name:fra_x_preferred":[
        "Foyer"
    ],
    "name:isl_x_preferred":[
        "Heimili"
    ],
    "name:kan_x_preferred":[
        "\u0cb5\u0cb8\u0ca4\u0cbf"
    ],
    "name:kur_x_preferred":[
        "Mal"
    ],
    "name:mkd_x_preferred":[
        "\u0414\u043e\u043c"
    ],
    "name:nld_x_preferred":[
        "Thuis"
    ],
    "name:nno_x_preferred":[
        "Heim"
    ],
    "name:nor_x_preferred":[
        "Hjem"
    ],
    "name:por_x_preferred":[
        "Lar"
    ],
    "name:ron_x_preferred":[
        "Acas\u0103"
    ],
    "name:sat_x_preferred":[
        "\u1c5a\u1c72\u1c5f\u1c5c"
    ],
    "name:snd_x_preferred":[
        "\u06af\u06be\u0631"
    ],
    "name:spa_x_preferred":[
        "Hogar"
    ],
    "name:srp_x_preferred":[
        "\u0414\u043e\u043c"
    ],
    "name:swe_x_preferred":[
        "Hem"
    ],
    "name:und_x_variant":[
        "Mhome"
    ],
    "name:urd_x_preferred":[
        "\u06af\u06be\u0631"
    ],
    "name:vie_x_preferred":[
        "Ch\u1ed7 \u1edf"
    ],
    "wof:name":"Home",
    "wof:placetype":"locality"
},
  "geometry": {"coordinates":[29.32442,0.55692],"type":"Point"}
}