{
  "type": "Feature",
  "properties": {
    "gn:admin1_code":"14.0",
    "gn:asciiname":"Lubwe",
    "gn:country_code":"CD",
    "gn:dem":955,
    "gn:feature_class":"P",
    "gn:feature_code":"PPL",
    "gn:name":"Lubwe",
    "gn:population":0,
    "gn:timezone":"Africa/Lubumbashi",
    "iso:country":"CD",
    "name:und_x_variant":[
        "Lumbwe",
        "Lubwe"
    ],
    "wof:name":"Lubwe",
    "wof:placetype":"locality"
},
  "geometry": {"coordinates":[28.55986,-10.37783],"type":"Point"}
}