{
  "type": "Feature",
  "properties": {
    "gn:admin1_code":"14.0",
    "gn:asciiname":"Kitanda",
    "gn:country_code":"CD",
    "gn:dem":945,
    "gn:feature_class":"P",
    "gn:feature_code":"PPL",
    "gn:name":"Kitanda",
    "gn:population":0,
    "gn:timezone":"Africa/Lubumbashi",
    "iso:country":"CD",
    "name:und_x_variant":[
        "Kitande",
        "Kitanda"
    ],
    "wof:name":"Kitanda",
    "wof:placetype":"locality"
},
  "geometry": {"coordinates":[27.46946,-9.97928],"type":"Point"}
}