{
  "type": "Feature",
  "properties": {
    "gn:admin1_code":"28.0",
    "gn:asciiname":"Burutu",
    "gn:country_code":"CD",
    "gn:dem":423,
    "gn:feature_class":"P",
    "gn:feature_code":"PPL",
    "gn:name":"Burutu",
    "gn:population":0,
    "gn:timezone":"Africa/Kinshasa",
    "iso:country":"CD",
    "name:ceb_x_preferred":[
        "Burutu"
    ],
    "name:fra_x_preferred":[
        "Burutu"
    ],
    "name:hau_x_preferred":[
        "Burutu"
    ],
    "name:ita_x_preferred":[
        "Burutu"
    ],
    "name:por_x_preferred":[
        "Burutu"
    ],
    "name:spa_x_preferred":[
        "Burutu"
    ],
    "name:yor_x_preferred":[
        "Burutu"
    ],
    "wof:name":"Burutu",
    "wof:placetype":"locality"
},
  "geometry": {"coordinates":[19.49262,2.81098],"type":"Point"}
}