{
  "type": "Feature",
  "properties": {
    "gn:admin1_code":"10.0",
    "gn:asciiname":"Nianga-Kambelembele",
    "gn:country_code":"CD",
    "gn:dem":552,
    "gn:feature_class":"P",
    "gn:feature_code":"PPL",
    "gn:name":"Nianga-Kambelembele",
    "gn:population":0,
    "gn:timezone":"Africa/Lubumbashi",
    "iso:country":"CD",
    "wof:name":"Nianga-Kambelembele",
    "wof:placetype":"locality"
},
  "geometry": {"coordinates":[26.15,-3.65],"type":"Point"}
}