{
  "type": "Feature",
  "properties": {
    "gn:admin1_code":"14.0",
    "gn:asciiname":"Mulenga",
    "gn:country_code":"CD",
    "gn:dem":955,
    "gn:feature_class":"P",
    "gn:feature_code":"PPL",
    "gn:name":"Mulenga",
    "gn:population":0,
    "gn:timezone":"Africa/Lubumbashi",
    "iso:country":"CD",
    "wof:name":"Mulenga",
    "wof:placetype":"locality"
},
  "geometry": {"coordinates":[27.63835,-10.67755],"type":"Point"}
}