{
  "type": "Feature",
  "properties": {
    "gn:admin1_code":"22.0",
    "gn:asciiname":"Mutaka",
    "gn:country_code":"CD",
    "gn:dem":1444,
    "gn:feature_class":"P",
    "gn:feature_code":"PPL",
    "gn:name":"Mutaka",
    "gn:population":0,
    "gn:timezone":"Africa/Lubumbashi",
    "iso:country":"CD",
    "wof:name":"Mutaka",
    "wof:placetype":"locality"
},
  "geometry": {"coordinates":[25.51528,-10.80306],"type":"Point"}
}