{
  "type": "Feature",
  "properties": {
    "gn:admin1_code":"8.0",
    "gn:asciiname":"Yongo Premiere",
    "gn:country_code":"CD",
    "gn:dem":634,
    "gn:feature_class":"P",
    "gn:feature_code":"PPL",
    "gn:name":"Yongo Premi\u00e8re",
    "gn:population":0,
    "gn:timezone":"Africa/Kinshasa",
    "iso:country":"CD",
    "name:und_x_variant":[
        "Yongo Premi\u00e8re",
        "Yongo I"
    ],
    "wof:name":"Yongo Premiere",
    "wof:placetype":"locality"
},
  "geometry": {"coordinates":[15.00198,-5.04491],"type":"Point"}
}