{
  "type": "Feature",
  "properties": {
    "gn:admin1_code":"19.0",
    "gn:asciiname":"Kawanda",
    "gn:country_code":"CD",
    "gn:dem":892,
    "gn:feature_class":"P",
    "gn:feature_code":"PPL",
    "gn:name":"Kawanda",
    "gn:population":0,
    "gn:timezone":"Africa/Kinshasa",
    "iso:country":"CD",
    "name:lug_x_preferred":[
        "Kawanda"
    ],
    "wof:name":"Kawanda",
    "wof:placetype":"locality"
},
  "geometry": {"coordinates":[17.92224,-7.21657],"type":"Point"}
}