{
  "type": "Feature",
  "properties": {
    "gn:admin1_code":"13.0",
    "gn:asciiname":"Bokpekpe",
    "gn:country_code":"CD",
    "gn:dem":467,
    "gn:feature_class":"P",
    "gn:feature_code":"PPL",
    "gn:name":"Bokpekpe",
    "gn:population":0,
    "gn:timezone":"Africa/Lubumbashi",
    "iso:country":"CD",
    "wof:name":"Bokpekpe",
    "wof:placetype":"locality"
},
  "geometry": {"coordinates":[23.06281,2.59859],"type":"Point"}
}