{
  "type": "Feature",
  "properties": {
    "gn:admin1_code":"22.0",
    "gn:asciiname":"Satshilefu",
    "gn:country_code":"CD",
    "gn:dem":1061,
    "gn:feature_class":"P",
    "gn:feature_code":"PPL",
    "gn:name":"Satshilefu",
    "gn:population":0,
    "gn:timezone":"Africa/Lubumbashi",
    "iso:country":"CD",
    "wof:name":"Satshilefu",
    "wof:placetype":"locality"
},
  "geometry": {"coordinates":[23.33804,-8.33204],"type":"Point"}
}