{
  "type": "Feature",
  "properties": {
    "gn:admin1_code":"20.0",
    "gn:asciiname":"Nienkongo",
    "gn:country_code":"CD",
    "gn:dem":677,
    "gn:feature_class":"P",
    "gn:feature_code":"PPL",
    "gn:name":"Nienkongo",
    "gn:population":0,
    "gn:timezone":"Africa/Kinshasa",
    "iso:country":"CD",
    "name:und_x_variant":[
        "Niekongo",
        "Nienkongo"
    ],
    "wof:name":"Nienkongo",
    "wof:placetype":"locality"
},
  "geometry": {"coordinates":[19.43774,-5.37159],"type":"Point"}
}