{
  "type": "Feature",
  "properties": {
    "gn:admin1_code":"11.0",
    "gn:asciiname":"Kisomi",
    "gn:country_code":"CD",
    "gn:dem":1305,
    "gn:feature_class":"P",
    "gn:feature_code":"PPL",
    "gn:name":"Kisomi",
    "gn:population":0,
    "gn:timezone":"Africa/Lubumbashi",
    "iso:country":"CD",
    "wof:name":"Kisomi",
    "wof:placetype":"locality"
},
  "geometry": {"coordinates":[29.92591,0.59237],"type":"Point"}
}