{
  "type": "Feature",
  "properties": {
    "gn:admin1_code":"25.0",
    "gn:asciiname":"Libangi",
    "gn:country_code":"CD",
    "gn:dem":401,
    "gn:feature_class":"P",
    "gn:feature_code":"PPL",
    "gn:name":"Libangi",
    "gn:population":0,
    "gn:timezone":"Africa/Kinshasa",
    "iso:country":"CD",
    "wof:name":"Libangi",
    "wof:placetype":"locality"
},
  "geometry": {"coordinates":[21.31292,2.19665],"type":"Point"}
}