{
  "type": "Feature",
  "properties": {
    "gn:admin1_code":"18.0",
    "gn:asciiname":"Maniayi",
    "gn:country_code":"CD",
    "gn:dem":728,
    "gn:feature_class":"P",
    "gn:feature_code":"PPL",
    "gn:name":"Maniayi",
    "gn:population":0,
    "gn:timezone":"Africa/Lubumbashi",
    "iso:country":"CD",
    "wof:name":"Maniayi",
    "wof:placetype":"locality"
},
  "geometry": {"coordinates":[21.54376,-6.57474],"type":"Point"}
}