{
  "type": "Feature",
  "properties": {
    "gn:admin1_code":"8.0",
    "gn:asciiname":"Kingana",
    "gn:country_code":"CD",
    "gn:dem":871,
    "gn:feature_class":"P",
    "gn:feature_code":"PPL",
    "gn:name":"Kingana",
    "gn:population":0,
    "gn:timezone":"Africa/Kinshasa",
    "iso:country":"CD",
    "name:und_x_variant":[
        "Kinganga",
        "Kingana"
    ],
    "wof:name":"Kingana",
    "wof:placetype":"locality"
},
  "geometry": {"coordinates":[15.93004,-5.67684],"type":"Point"}
}