{
  "type": "Feature",
  "properties": {
    "gn:admin1_code":"20.0",
    "gn:asciiname":"Mulasa",
    "gn:country_code":"CD",
    "gn:dem":673,
    "gn:feature_class":"P",
    "gn:feature_code":"PPL",
    "gn:name":"Mulasa",
    "gn:population":0,
    "gn:timezone":"Africa/Kinshasa",
    "iso:country":"CD",
    "name:und_x_variant":[
        "Mulase",
        "Mulasa"
    ],
    "wof:name":"Mulasa",
    "wof:placetype":"locality"
},
  "geometry": {"coordinates":[19.6607,-5.20439],"type":"Point"}
}