{
  "type": "Feature",
  "properties": {
    "gn:admin1_code":"22.0",
    "gn:asciiname":"Wakas",
    "gn:country_code":"CD",
    "gn:dem":1001,
    "gn:feature_class":"P",
    "gn:feature_code":"PPL",
    "gn:name":"Wakas",
    "gn:population":0,
    "gn:timezone":"Africa/Lubumbashi",
    "iso:country":"CD",
    "wof:name":"Wakas",
    "wof:placetype":"locality"
},
  "geometry": {"coordinates":[21.99513,-8.18779],"type":"Point"}
}