{
  "type": "Feature",
  "properties": {
    "gn:admin1_code":"20.0",
    "gn:asciiname":"Banza-Mabungu",
    "gn:country_code":"CD",
    "gn:dem":587,
    "gn:feature_class":"P",
    "gn:feature_code":"PPL",
    "gn:name":"Banza-Mabungu",
    "gn:population":0,
    "gn:timezone":"Africa/Kinshasa",
    "iso:country":"CD",
    "wof:name":"Banza-Mabungu",
    "wof:placetype":"locality"
},
  "geometry": {"coordinates":[17.80511,-4.85118],"type":"Point"}
}