{
  "type": "Feature",
  "properties": {
    "gn:admin1_code":"22.0",
    "gn:asciiname":"Tshibwabwa",
    "gn:country_code":"CD",
    "gn:dem":1303,
    "gn:feature_class":"P",
    "gn:feature_code":"PPL",
    "gn:name":"Tshibwabwa",
    "gn:population":0,
    "gn:timezone":"Africa/Lubumbashi",
    "iso:country":"CD",
    "wof:name":"Tshibwabwa",
    "wof:placetype":"locality"
},
  "geometry": {"coordinates":[24.34057,-10.84285],"type":"Point"}
}