{
  "type": "Feature",
  "properties": {
    "gn:admin1_code":"21.0",
    "gn:asciiname":"Kulanda",
    "gn:country_code":"CD",
    "gn:dem":969,
    "gn:feature_class":"P",
    "gn:feature_code":"PPL",
    "gn:name":"Kulanda",
    "gn:population":0,
    "gn:timezone":"Africa/Lubumbashi",
    "iso:country":"CD",
    "wof:name":"Kulanda",
    "wof:placetype":"locality"
},
  "geometry": {"coordinates":[23.45472,-7.74289],"type":"Point"}
}