{
  "type": "Feature",
  "properties": {
    "gn:admin1_code":"19.0",
    "gn:asciiname":"Ikomba-Mulapo",
    "gn:country_code":"CD",
    "gn:dem":487,
    "gn:feature_class":"P",
    "gn:feature_code":"PPL",
    "gn:name":"Ikomba-Mulapo",
    "gn:population":0,
    "gn:timezone":"Africa/Kinshasa",
    "iso:country":"CD",
    "wof:name":"Ikomba-Mulapo",
    "wof:placetype":"locality"
},
  "geometry": {"coordinates":[16.40187,-5.84828],"type":"Point"}
}