{
  "type": "Feature",
  "properties": {
    "gn:admin1_code":"8.0",
    "gn:asciiname":"Seke-Banza",
    "gn:country_code":"CD",
    "gn:dem":555,
    "gn:feature_class":"P",
    "gn:feature_code":"PPL",
    "gn:name":"Seke-Banza",
    "gn:population":0,
    "gn:timezone":"Africa/Kinshasa",
    "iso:country":"CD",
    "name:fra_x_preferred":[
        "Seke-Banza"
    ],
    "name:ron_x_preferred":[
        "Seke-Banza"
    ],
    "name:und_x_variant":[
        "Seke Banga"
    ],
    "wof:name":"Seke-Banza",
    "wof:placetype":"locality"
},
  "geometry": {"coordinates":[13.28099,-5.33844],"type":"Point"}
}