{
  "type": "Feature",
  "properties": {
    "gn:admin1_code":"16.0",
    "gn:asciiname":"Maituru",
    "gn:country_code":"CD",
    "gn:dem":1238,
    "gn:feature_class":"P",
    "gn:feature_code":"PPL",
    "gn:name":"Maituru",
    "gn:population":0,
    "gn:timezone":"Africa/Lubumbashi",
    "iso:country":"CD",
    "wof:name":"Maituru",
    "wof:placetype":"locality"
},
  "geometry": {"coordinates":[29.89084,2.70483],"type":"Point"}
}