{
  "type": "Feature",
  "properties": {
    "gn:admin1_code":"18.0",
    "gn:asciiname":"Shongoningeri",
    "gn:country_code":"CD",
    "gn:dem":439,
    "gn:feature_class":"P",
    "gn:feature_code":"PPL",
    "gn:name":"Shongoningeri",
    "gn:population":0,
    "gn:timezone":"Africa/Lubumbashi",
    "iso:country":"CD",
    "name:und_x_variant":[
        "Shongoningiri",
        "Shongoningeri"
    ],
    "wof:name":"Shongoningeri",
    "wof:placetype":"locality"
},
  "geometry": {"coordinates":[21.36667000000001,-4.13333],"type":"Point"}
}