{
  "type": "Feature",
  "properties": {
    "gn:admin1_code":"26.0",
    "gn:asciiname":"Mobeke",
    "gn:country_code":"CD",
    "gn:dem":461,
    "gn:feature_class":"P",
    "gn:feature_code":"PPL",
    "gn:name":"Mobeke",
    "gn:population":0,
    "gn:timezone":"Africa/Kinshasa",
    "iso:country":"CD",
    "name:und_x_variant":[
        "Mabeke"
    ],
    "wof:name":"Mobeke",
    "wof:placetype":"locality"
},
  "geometry": {"coordinates":[20.86314,4.26559],"type":"Point"}
}