{
  "type": "Feature",
  "properties": {
    "gn:admin1_code":"22.0",
    "gn:asciiname":"Kamwale",
    "gn:country_code":"CD",
    "gn:dem":955,
    "gn:feature_class":"P",
    "gn:feature_code":"PPL",
    "gn:name":"Kamwale",
    "gn:population":0,
    "gn:timezone":"Africa/Lubumbashi",
    "iso:country":"CD",
    "name:und_x_variant":[
        "Kamwala"
    ],
    "wof:name":"Kamwale",
    "wof:placetype":"locality"
},
  "geometry": {"coordinates":[22.82131,-9.51268],"type":"Point"}
}