{
  "type": "Feature",
  "properties": {
    "gn:admin1_code":"22.0",
    "gn:asciiname":"Kasembo",
    "gn:country_code":"CD",
    "gn:dem":1266,
    "gn:feature_class":"P",
    "gn:feature_code":"PPL",
    "gn:name":"Kasembo",
    "gn:population":0,
    "gn:timezone":"Africa/Lubumbashi",
    "iso:country":"CD",
    "wof:name":"Kasembo",
    "wof:placetype":"locality"
},
  "geometry": {"coordinates":[23.64544,-10.98785],"type":"Point"}
}