{
  "type": "Feature",
  "properties": {
    "gn:admin1_code":"18.0",
    "gn:asciiname":"Itambi-Munene",
    "gn:country_code":"CD",
    "gn:dem":650,
    "gn:feature_class":"P",
    "gn:feature_code":"PPL",
    "gn:name":"Itambi-Munene",
    "gn:population":0,
    "gn:timezone":"Africa/Lubumbashi",
    "iso:country":"CD",
    "wof:name":"Itambi-Munene",
    "wof:placetype":"locality"
},
  "geometry": {"coordinates":[20.54126,-4.97086],"type":"Point"}
}