{
  "type": "Feature",
  "properties": {
    "gn:admin1_code":"24.0",
    "gn:asciiname":"Mia",
    "gn:country_code":"CD",
    "gn:dem":318,
    "gn:feature_class":"P",
    "gn:feature_code":"PPL",
    "gn:name":"Mia",
    "gn:population":0,
    "gn:timezone":"Africa/Kinshasa",
    "iso:country":"CD",
    "wof:name":"Mia",
    "wof:placetype":"locality"
},
  "geometry": {"coordinates":[17.61538999999999,-2.12369],"type":"Point"}
}