{
  "type": "Feature",
  "properties": {
    "gn:admin1_code":"21.0",
    "gn:asciiname":"Lubole",
    "gn:country_code":"CD",
    "gn:dem":833,
    "gn:feature_class":"P",
    "gn:feature_code":"PPL",
    "gn:name":"Lubole",
    "gn:population":0,
    "gn:timezone":"Africa/Lubumbashi",
    "iso:country":"CD",
    "wof:name":"Lubole",
    "wof:placetype":"locality"
},
  "geometry": {"coordinates":[25.45628,-6.66089],"type":"Point"}
}