{
  "type": "Feature",
  "properties": {
    "gn:admin1_code":"23.0",
    "gn:asciiname":"Tshisenga",
    "gn:country_code":"CD",
    "gn:dem":712,
    "gn:feature_class":"P",
    "gn:feature_code":"PPL",
    "gn:name":"Tshisenga",
    "gn:population":0,
    "gn:timezone":"Africa/Lubumbashi",
    "iso:country":"CD",
    "wof:name":"Tshisenga",
    "wof:placetype":"locality"
},
  "geometry": {"coordinates":[22.39907,-6.22957],"type":"Point"}
}