{
  "type": "Feature",
  "properties": {
    "gn:admin1_code":"23.0",
    "gn:asciiname":"Denille",
    "gn:country_code":"CD",
    "gn:dem":846,
    "gn:feature_class":"P",
    "gn:feature_code":"PPL",
    "gn:name":"Denille",
    "gn:population":0,
    "gn:timezone":"Africa/Lubumbashi",
    "iso:country":"CD",
    "wof:name":"Denille",
    "wof:placetype":"locality"
},
  "geometry": {"coordinates":[22.7428,-7.30766],"type":"Point"}
}