{
  "type": "Feature",
  "properties": {
    "gn:admin1_code":"18.0",
    "gn:asciiname":"Kakolo",
    "gn:country_code":"CD",
    "gn:dem":658,
    "gn:feature_class":"P",
    "gn:feature_code":"PPL",
    "gn:name":"Kakolo",
    "gn:population":0,
    "gn:timezone":"Africa/Lubumbashi",
    "iso:country":"CD",
    "wof:name":"Kakolo",
    "wof:placetype":"locality"
},
  "geometry": {"coordinates":[21.70055,-5.77669],"type":"Point"}
}