{
  "type": "Feature",
  "properties": {
    "gn:admin1_code":"24.0",
    "gn:asciiname":"Kolo",
    "gn:country_code":"CD",
    "gn:dem":317,
    "gn:feature_class":"P",
    "gn:feature_code":"PPL",
    "gn:name":"Kolo",
    "gn:population":0,
    "gn:timezone":"Africa/Kinshasa",
    "iso:country":"CD",
    "name:bos_x_preferred":[
        "Kolo"
    ],
    "name:ceb_x_preferred":[
        "Kolo"
    ],
    "name:ces_x_preferred":[
        "Kolo"
    ],
    "name:deu_x_preferred":[
        "Kolo"
    ],
    "name:fra_x_preferred":[
        "Kolo"
    ],
    "name:hrv_x_preferred":[
        "Kolo"
    ],
    "name:ita_x_preferred":[
        "Kolo"
    ],
    "name:nld_x_preferred":[
        "Kolo"
    ],
    "name:pol_x_preferred":[
        "Ko\u0142o"
    ],
    "name:rus_x_preferred":[
        "\u041a\u043e\u043b\u043e"
    ],
    "name:slk_x_preferred":[
        "Kolo"
    ],
    "name:srp_x_preferred":[
        "\u041a\u043e\u043b\u043e"
    ],
    "name:swe_x_preferred":[
        "Kolo"
    ],
    "name:szl_x_preferred":[
        "Ko\u0142o"
    ],
    "wof:name":"Kolo",
    "wof:placetype":"locality"
},
  "geometry": {"coordinates":[18.45,-2.81667],"type":"Point"}
}