{
  "type": "Feature",
  "properties": {
    "gn:admin1_code":"20.0",
    "gn:asciiname":"Badibundu",
    "gn:country_code":"CD",
    "gn:dem":465,
    "gn:feature_class":"P",
    "gn:feature_code":"PPL",
    "gn:name":"Badibundu",
    "gn:population":0,
    "gn:timezone":"Africa/Kinshasa",
    "iso:country":"CD",
    "wof:name":"Badibundu",
    "wof:placetype":"locality"
},
  "geometry": {"coordinates":[18.35752,-4.67325],"type":"Point"}
}