{
  "type": "Feature",
  "properties": {
    "gn:admin1_code":"19.0",
    "gn:asciiname":"Kabangu",
    "gn:country_code":"CD",
    "gn:dem":596,
    "gn:feature_class":"P",
    "gn:feature_code":"PPL",
    "gn:name":"Kabangu",
    "gn:population":0,
    "gn:timezone":"Africa/Kinshasa",
    "iso:country":"CD",
    "wof:name":"Kabangu",
    "wof:placetype":"locality"
},
  "geometry": {"coordinates":[16.69004,-5.81705],"type":"Point"}
}