{
  "type": "Feature",
  "properties": {
    "gn:admin1_code":"18.0",
    "gn:asciiname":"Kabolo",
    "gn:country_code":"CD",
    "gn:dem":528,
    "gn:feature_class":"P",
    "gn:feature_code":"PPL",
    "gn:name":"Kabolo",
    "gn:population":0,
    "gn:timezone":"Africa/Lubumbashi",
    "iso:country":"CD",
    "name:und_x_variant":[
        "Kobolo",
        "Kabolo"
    ],
    "wof:name":"Kabolo",
    "wof:placetype":"locality"
},
  "geometry": {"coordinates":[21.36813,-4.113],"type":"Point"}
}