{
  "type": "Feature",
  "properties": {
    "gn:admin1_code":"14.0",
    "gn:asciiname":"Kashobwe",
    "gn:country_code":"CD",
    "gn:dem":931,
    "gn:feature_class":"P",
    "gn:feature_code":"PPL",
    "gn:name":"Kashobwe",
    "gn:population":0,
    "gn:timezone":"Africa/Lubumbashi",
    "iso:country":"CD",
    "name:und_x_variant":[
        "Kashiobwe"
    ],
    "wof:name":"Kashobwe",
    "wof:placetype":"locality"
},
  "geometry": {"coordinates":[28.61839,-9.67868],"type":"Point"}
}