{
  "type": "Feature",
  "properties": {
    "gn:admin1_code":"4.0",
    "gn:asciiname":"Katende-Kaboko",
    "gn:country_code":"CD",
    "gn:dem":682,
    "gn:feature_class":"P",
    "gn:feature_code":"PPL",
    "gn:name":"Katende-Kaboko",
    "gn:population":0,
    "gn:timezone":"Africa/Lubumbashi",
    "iso:country":"CD",
    "wof:name":"Katende-Kaboko",
    "wof:placetype":"locality"
},
  "geometry": {"coordinates":[23.34791,-6.0791],"type":"Point"}
}