{
  "type": "Feature",
  "properties": {
    "gn:admin1_code":"23.0",
    "gn:asciiname":"Kamemba",
    "gn:country_code":"CD",
    "gn:dem":834,
    "gn:feature_class":"P",
    "gn:feature_code":"PPL",
    "gn:name":"Kamemba",
    "gn:population":0,
    "gn:timezone":"Africa/Lubumbashi",
    "iso:country":"CD",
    "wof:name":"Kamemba",
    "wof:placetype":"locality"
},
  "geometry": {"coordinates":[22.60542,-6.61129],"type":"Point"}
}