{
  "type": "Feature",
  "properties": {
    "gn:admin1_code":"30.0",
    "gn:asciiname":"Baboandja",
    "gn:country_code":"CD",
    "gn:dem":422,
    "gn:feature_class":"P",
    "gn:feature_code":"PPL",
    "gn:name":"Baboandja",
    "gn:population":0,
    "gn:timezone":"Africa/Lubumbashi",
    "iso:country":"CD",
    "wof:name":"Baboandja",
    "wof:placetype":"locality"
},
  "geometry": {"coordinates":[25.18236,0.56925],"type":"Point"}
}