{
  "type": "Feature",
  "properties": {
    "gn:admin1_code":"18.0",
    "gn:asciiname":"Tshitanyi",
    "gn:country_code":"CD",
    "gn:dem":617,
    "gn:feature_class":"P",
    "gn:feature_code":"PPL",
    "gn:name":"Tshitanyi",
    "gn:population":0,
    "gn:timezone":"Africa/Lubumbashi",
    "iso:country":"CD",
    "wof:name":"Tshitanyi",
    "wof:placetype":"locality"
},
  "geometry": {"coordinates":[21.03054,-6.63588],"type":"Point"}
}