{
  "type": "Feature",
  "properties": {
    "gn:admin1_code":"19.0",
    "gn:asciiname":"Shaluange",
    "gn:country_code":"CD",
    "gn:dem":976,
    "gn:feature_class":"P",
    "gn:feature_code":"PPL",
    "gn:name":"Shaluange",
    "gn:population":0,
    "gn:timezone":"Africa/Kinshasa",
    "iso:country":"CD",
    "wof:name":"Shaluange",
    "wof:placetype":"locality"
},
  "geometry": {"coordinates":[19.13469,-7.07559],"type":"Point"}
}