{
  "type": "Feature",
  "properties": {
    "gn:admin1_code":"29.0",
    "gn:asciiname":"Luinda",
    "gn:country_code":"CD",
    "gn:dem":964,
    "gn:feature_class":"P",
    "gn:feature_code":"PPL",
    "gn:name":"Luinda",
    "gn:population":0,
    "gn:timezone":"Africa/Lubumbashi",
    "iso:country":"CD",
    "wof:name":"Luinda",
    "wof:placetype":"locality"
},
  "geometry": {"coordinates":[27.86667000000001,-5.38333],"type":"Point"}
}