{
  "type": "Feature",
  "properties": {
    "gn:admin1_code":"11.0",
    "gn:asciiname":"Kitongo",
    "gn:country_code":"CD",
    "gn:dem":789,
    "gn:feature_class":"P",
    "gn:feature_code":"PPL",
    "gn:name":"Kitongo",
    "gn:population":0,
    "gn:timezone":"Africa/Lubumbashi",
    "iso:country":"CD",
    "wof:name":"Kitongo",
    "wof:placetype":"locality"
},
  "geometry": {"coordinates":[28.2245,-1.87116],"type":"Point"}
}