{
  "type": "Feature",
  "properties": {
    "gn:admin1_code":"30.0",
    "gn:asciiname":"Yalikaka",
    "gn:country_code":"CD",
    "gn:dem":453,
    "gn:feature_class":"P",
    "gn:feature_code":"PPL",
    "gn:name":"Yalikaka",
    "gn:population":0,
    "gn:timezone":"Africa/Lubumbashi",
    "iso:country":"CD",
    "name:und_x_variant":[
        "Yalikaka-Moke"
    ],
    "wof:name":"Yalikaka",
    "wof:placetype":"locality"
},
  "geometry": {"coordinates":[24.75594,0.25399],"type":"Point"}
}