{
  "type": "Feature",
  "properties": {
    "gn:admin1_code":"24.0",
    "gn:asciiname":"Zankwi",
    "gn:country_code":"CD",
    "gn:dem":350,
    "gn:feature_class":"P",
    "gn:feature_code":"PPL",
    "gn:name":"Zankwi",
    "gn:population":0,
    "gn:timezone":"Africa/Kinshasa",
    "iso:country":"CD",
    "wof:name":"Zankwi",
    "wof:placetype":"locality"
},
  "geometry": {"coordinates":[17.7459,-3.2662],"type":"Point"}
}