{
  "type": "Feature",
  "properties": {
    "gn:admin1_code":"29.0",
    "gn:asciiname":"Beya",
    "gn:country_code":"CD",
    "gn:dem":599,
    "gn:feature_class":"P",
    "gn:feature_code":"PPL",
    "gn:name":"Beya",
    "gn:population":0,
    "gn:timezone":"Africa/Lubumbashi",
    "iso:country":"CD",
    "name:ceb_x_preferred":[
        "Beya"
    ],
    "name:fra_x_preferred":[
        "Beya"
    ],
    "name:swe_x_preferred":[
        "Beya"
    ],
    "name:und_x_variant":[
        "Buyu",
        "Beya"
    ],
    "wof:name":"Beya",
    "wof:placetype":"locality"
},
  "geometry": {"coordinates":[26.52631,-6.71021],"type":"Point"}
}