{
  "type": "Feature",
  "properties": {
    "gn:admin1_code":"8.0",
    "gn:asciiname":"Luenda",
    "gn:country_code":"CD",
    "gn:dem":553,
    "gn:feature_class":"P",
    "gn:feature_code":"PPL",
    "gn:name":"Luenda",
    "gn:population":0,
    "gn:timezone":"Africa/Kinshasa",
    "iso:country":"CD",
    "name:und_x_variant":[
        "Luende",
        "Luenda"
    ],
    "wof:name":"Luenda",
    "wof:placetype":"locality"
},
  "geometry": {"coordinates":[14.44399,-5.28771],"type":"Point"}
}