{
  "type": "Feature",
  "properties": {
    "gn:admin1_code":"21.0",
    "gn:asciiname":"Kabwa",
    "gn:country_code":"CD",
    "gn:dem":887,
    "gn:feature_class":"P",
    "gn:feature_code":"PPL",
    "gn:name":"Kabwa",
    "gn:population":0,
    "gn:timezone":"Africa/Lubumbashi",
    "iso:country":"CD",
    "wof:name":"Kabwa",
    "wof:placetype":"locality"
},
  "geometry": {"coordinates":[23.52904,-6.87909],"type":"Point"}
}