{
  "type": "Feature",
  "properties": {
    "gn:admin1_code":"19.0",
    "gn:asciiname":"Shamusongo",
    "gn:country_code":"CD",
    "gn:dem":1134,
    "gn:feature_class":"P",
    "gn:feature_code":"PPL",
    "gn:name":"Shamusongo",
    "gn:population":0,
    "gn:timezone":"Africa/Kinshasa",
    "iso:country":"CD",
    "wof:name":"Shamusongo",
    "wof:placetype":"locality"
},
  "geometry": {"coordinates":[18.83962,-7.95476],"type":"Point"}
}