{
  "type": "Feature",
  "properties": {
    "gn:admin1_code":"18.0",
    "gn:asciiname":"Shatshiamba",
    "gn:country_code":"CD",
    "gn:dem":765,
    "gn:feature_class":"P",
    "gn:feature_code":"PPL",
    "gn:name":"Shatshiamba",
    "gn:population":0,
    "gn:timezone":"Africa/Lubumbashi",
    "iso:country":"CD",
    "wof:name":"Shatshiamba",
    "wof:placetype":"locality"
},
  "geometry": {"coordinates":[21.39365,-7.04144],"type":"Point"}
}