{
  "type": "Feature",
  "properties": {
    "gn:admin1_code":"28.0",
    "gn:asciiname":"Buma",
    "gn:country_code":"CD",
    "gn:dem":366,
    "gn:feature_class":"P",
    "gn:feature_code":"PPL",
    "gn:name":"Buma",
    "gn:population":0,
    "gn:timezone":"Africa/Kinshasa",
    "iso:country":"CD",
    "name:ceb_x_preferred":[
        "Buma"
    ],
    "name:nld_x_preferred":[
        "Buma"
    ],
    "name:swe_x_preferred":[
        "Buma"
    ],
    "wof:name":"Buma",
    "wof:placetype":"locality"
},
  "geometry": {"coordinates":[18.7942,2.81647],"type":"Point"}
}