{
  "type": "Feature",
  "properties": {
    "gn:admin1_code":"20.0",
    "gn:asciiname":"Oha",
    "gn:country_code":"CD",
    "gn:dem":366,
    "gn:feature_class":"P",
    "gn:feature_code":"PPL",
    "gn:name":"Oha",
    "gn:population":0,
    "gn:timezone":"Africa/Kinshasa",
    "iso:country":"CD",
    "wof:name":"Oha",
    "wof:placetype":"locality"
},
  "geometry": {"coordinates":[19.05,-3.86667],"type":"Point"}
}