{
  "type": "Feature",
  "properties": {
    "gn:admin1_code":"13.0",
    "gn:asciiname":"Lobi",
    "gn:country_code":"CD",
    "gn:dem":506,
    "gn:feature_class":"P",
    "gn:feature_code":"PPL",
    "gn:name":"Lobi",
    "gn:population":0,
    "gn:timezone":"Africa/Lubumbashi",
    "iso:country":"CD",
    "name:ceb_x_preferred":[
        "Lobi"
    ],
    "name:fra_x_preferred":[
        "Lobi"
    ],
    "name:hye_x_preferred":[
        "\u053c\u0578\u0562\u056b"
    ],
    "name:nld_x_preferred":[
        "Lobi"
    ],
    "name:rus_x_preferred":[
        "\u041b\u043e\u0431\u0438"
    ],
    "name:swe_x_preferred":[
        "Lobi"
    ],
    "wof:name":"Lobi",
    "wof:placetype":"locality"
},
  "geometry": {"coordinates":[23.09201,4.16099],"type":"Point"}
}