{
  "type": "Feature",
  "properties": {
    "gn:admin1_code":"26.0",
    "gn:asciiname":"Mombwa-Toya",
    "gn:country_code":"CD",
    "gn:dem":496,
    "gn:feature_class":"P",
    "gn:feature_code":"PPL",
    "gn:name":"Mombwa-Toya",
    "gn:population":0,
    "gn:timezone":"Africa/Kinshasa",
    "iso:country":"CD",
    "wof:name":"Mombwa-Toya",
    "wof:placetype":"locality"
},
  "geometry": {"coordinates":[21.96891,3.55089],"type":"Point"}
}