{
  "type": "Feature",
  "properties": {
    "gn:admin1_code":"24.0",
    "gn:asciiname":"Kaka",
    "gn:country_code":"CD",
    "gn:dem":396,
    "gn:feature_class":"P",
    "gn:feature_code":"PPL",
    "gn:name":"Kaka",
    "gn:population":0,
    "gn:timezone":"Africa/Kinshasa",
    "iso:country":"CD",
    "name:ara_x_preferred":[
        "\u0643\u0627\u0643\u0627"
    ],
    "name:bul_x_preferred":[
        "\u041a\u0430\u043a\u0430"
    ],
    "name:cat_x_preferred":[
        "Kaka"
    ],
    "name:ceb_x_preferred":[
        "Kaka"
    ],
    "name:dan_x_preferred":[
        "Kaka"
    ],
    "name:deu_x_preferred":[
        "Kaka"
    ],
    "name:est_x_preferred":[
        "Kaka"
    ],
    "name:fas_x_preferred":[
        "\u06a9\u0627\u06a9\u0627"
    ],
    "name:fin_x_preferred":[
        "Kaka"
    ],
    "name:fra_x_preferred":[
        "Kaka"
    ],
    "name:hrv_x_preferred":[
        "Kaka"
    ],
    "name:hun_x_preferred":[
        "Kaka"
    ],
    "name:ita_x_preferred":[
        "Kak\u00e1"
    ],
    "name:kor_x_preferred":[
        "\uce74\uce74"
    ],
    "name:lav_x_preferred":[
        "Kaka"
    ],
    "name:nld_x_preferred":[
        "Kaka"
    ],
    "name:nor_x_preferred":[
        "Kaka"
    ],
    "name:pol_x_preferred":[
        "Kaka"
    ],
    "name:por_x_preferred":[
        "Kak\u00e1"
    ],
    "name:rus_x_preferred":[
        "\u041a\u0430\u043a\u0430"
    ],
    "name:spa_x_preferred":[
        "Kaka"
    ],
    "name:srp_x_preferred":[
        "\u041a\u0430\u043a\u0430"
    ],
    "name:swe_x_preferred":[
        "Kaka"
    ],
    "name:tam_x_preferred":[
        "\u0b95\u0bbe\u0b95\u0bcd\u0b95\u0bbe"
    ],
    "name:tgl_x_preferred":[
        "Kaka"
    ],
    "name:tur_x_preferred":[
        "Kaka"
    ],
    "name:ukr_x_preferred":[
        "\u041a\u0430\u043a\u0430"
    ],
    "name:vie_x_preferred":[
        "Kaka"
    ],
    "wof:name":"Kaka",
    "wof:placetype":"locality"
},
  "geometry": {"coordinates":[20.31667,-2.33333],"type":"Point"}
}