{
  "type": "Feature",
  "properties": {
    "gn:admin1_code":"8.0",
    "gn:asciiname":"Mamputu",
    "gn:country_code":"CD",
    "gn:dem":41,
    "gn:feature_class":"P",
    "gn:feature_code":"PPL",
    "gn:name":"Mamputu",
    "gn:population":0,
    "gn:timezone":"Africa/Kinshasa",
    "iso:country":"CD",
    "wof:name":"Mamputu",
    "wof:placetype":"locality"
},
  "geometry": {"coordinates":[12.40105,-5.92414],"type":"Point"}
}