{
  "type": "Feature",
  "properties": {
    "gn:admin1_code":"8.0",
    "gn:asciiname":"Kindi",
    "gn:country_code":"CD",
    "gn:dem":479,
    "gn:feature_class":"P",
    "gn:feature_code":"PPL",
    "gn:name":"Kindi",
    "gn:population":0,
    "gn:timezone":"Africa/Kinshasa",
    "iso:country":"CD",
    "name:ceb_x_preferred":[
        "Kindi"
    ],
    "name:deu_x_preferred":[
        "Kindi"
    ],
    "name:fra_x_preferred":[
        "Kindi"
    ],
    "name:swe_x_preferred":[
        "Kindi"
    ],
    "wof:name":"Kindi",
    "wof:placetype":"locality"
},
  "geometry": {"coordinates":[14.91294,-5.42522],"type":"Point"}
}