{
  "type": "Feature",
  "properties": {
    "gn:admin1_code":"23.0",
    "gn:asciiname":"Kande wa-Mbala",
    "gn:country_code":"CD",
    "gn:dem":638,
    "gn:feature_class":"P",
    "gn:feature_code":"PPL",
    "gn:name":"Kande wa-Mbala",
    "gn:population":0,
    "gn:timezone":"Africa/Lubumbashi",
    "iso:country":"CD",
    "wof:name":"Kande wa-Mbala",
    "wof:placetype":"locality"
},
  "geometry": {"coordinates":[22.46753,-5.89025],"type":"Point"}
}