{
  "type": "Feature",
  "properties": {
    "gn:admin1_code":"22.0",
    "gn:asciiname":"Matafwa",
    "gn:country_code":"CD",
    "gn:dem":936,
    "gn:feature_class":"P",
    "gn:feature_code":"PPL",
    "gn:name":"Matafwa",
    "gn:population":0,
    "gn:timezone":"Africa/Lubumbashi",
    "iso:country":"CD",
    "wof:name":"Matafwa",
    "wof:placetype":"locality"
},
  "geometry": {"coordinates":[22.79004,-9.61985],"type":"Point"}
}