{
  "type": "Feature",
  "properties": {
    "gn:admin1_code":"8.0",
    "gn:asciiname":"Tembopete",
    "gn:country_code":"CD",
    "gn:dem":629,
    "gn:feature_class":"P",
    "gn:feature_code":"PPL",
    "gn:name":"Tembopete",
    "gn:population":0,
    "gn:timezone":"Africa/Kinshasa",
    "iso:country":"CD",
    "wof:name":"Tembopete",
    "wof:placetype":"locality"
},
  "geometry": {"coordinates":[13.89099,-4.61812],"type":"Point"}
}