{
  "type": "Feature",
  "properties": {
    "gn:admin1_code":"18.0",
    "gn:asciiname":"Konji",
    "gn:country_code":"CD",
    "gn:dem":572,
    "gn:feature_class":"P",
    "gn:feature_code":"PPL",
    "gn:name":"Konji",
    "gn:population":0,
    "gn:timezone":"Africa/Lubumbashi",
    "iso:country":"CD",
    "wof:name":"Konji",
    "wof:placetype":"locality"
},
  "geometry": {"coordinates":[21.35159,-5.47306],"type":"Point"}
}