{
  "type": "Feature",
  "properties": {
    "gn:admin1_code":"18.0",
    "gn:asciiname":"Konji",
    "gn:country_code":"CD",
    "gn:dem":572,
    "gn:feature_class":"P",
    "gn:feature_code":"PPL",
    "gn:name":"Konji",
    "gn:population":0,
    "gn:timezone":"Africa/Lubumbashi",
    "iso:country":"CD",
    "name:ara_x_preferred":[
        "\u0643\u0646\u062c\u064a"
    ],
    "name:ceb_x_preferred":[
        "Konj\u012b"
    ],
    "name:fas_x_preferred":[
        "\u06a9\u0646\u0686\u06cc"
    ],
    "name:msa_x_preferred":[
        "Konji"
    ],
    "wof:name":"Konji",
    "wof:placetype":"locality"
},
  "geometry": {"coordinates":[21.35159,-5.47306],"type":"Point"}
}