{
  "type": "Feature",
  "properties": {
    "gn:admin1_code":"21.0",
    "gn:asciiname":"Tshinene",
    "gn:country_code":"CD",
    "gn:dem":828,
    "gn:feature_class":"P",
    "gn:feature_code":"PPL",
    "gn:name":"Tshinene",
    "gn:population":0,
    "gn:timezone":"Africa/Lubumbashi",
    "iso:country":"CD",
    "name:und_x_variant":[
        "Tshinena",
        "Tshinene"
    ],
    "wof:name":"Tshinene",
    "wof:placetype":"locality"
},
  "geometry": {"coordinates":[23.7634,-6.9759],"type":"Point"}
}