{
  "type": "Feature",
  "properties": {
    "gn:admin1_code":"0.0",
    "gn:asciiname":"Mutindi",
    "gn:country_code":"CD",
    "gn:dem":767,
    "gn:feature_class":"P",
    "gn:feature_code":"PPL",
    "gn:name":"Mutindi",
    "gn:population":0,
    "gn:timezone":"Africa/Lubumbashi",
    "iso:country":"CD",
    "wof:name":"Mutindi",
    "wof:placetype":"locality"
},
  "geometry": {"coordinates":[30.06667,-7.15],"type":"Point"}
}