{
  "type": "Feature",
  "properties": {
    "gn:admin1_code":"18.0",
    "gn:asciiname":"Kalomba-Boni",
    "gn:country_code":"CD",
    "gn:dem":708,
    "gn:feature_class":"P",
    "gn:feature_code":"PPL",
    "gn:name":"Kalomba-Boni",
    "gn:population":0,
    "gn:timezone":"Africa/Lubumbashi",
    "iso:country":"CD",
    "wof:name":"Kalomba-Boni",
    "wof:placetype":"locality"
},
  "geometry": {"coordinates":[21.48369,-6.30931],"type":"Point"}
}