{
  "type": "Feature",
  "properties": {
    "gn:admin1_code":"10.0",
    "gn:asciiname":"Bwana I",
    "gn:country_code":"CD",
    "gn:dem":620,
    "gn:feature_class":"P",
    "gn:feature_code":"PPL",
    "gn:name":"Bwana I",
    "gn:population":0,
    "gn:timezone":"Africa/Lubumbashi",
    "iso:country":"CD",
    "wof:name":"Bwana I",
    "wof:placetype":"locality"
},
  "geometry": {"coordinates":[26.56667,-3.96667],"type":"Point"}
}