{
  "type": "Feature",
  "properties": {
    "gn:admin1_code":"22.0",
    "gn:asciiname":"Mwin Kabukusu",
    "gn:country_code":"CD",
    "gn:dem":1008,
    "gn:feature_class":"P",
    "gn:feature_code":"PPL",
    "gn:name":"Mwin Kabukusu",
    "gn:population":0,
    "gn:timezone":"Africa/Lubumbashi",
    "iso:country":"CD",
    "wof:name":"Mwin Kabukusu",
    "wof:placetype":"locality"
},
  "geometry": {"coordinates":[22.3651,-9.08856],"type":"Point"}
}