{
  "type": "Feature",
  "properties": {
    "gn:admin1_code":"26.0",
    "gn:asciiname":"Vobora",
    "gn:country_code":"CD",
    "gn:dem":402,
    "gn:feature_class":"P",
    "gn:feature_code":"PPL",
    "gn:name":"Vobora",
    "gn:population":0,
    "gn:timezone":"Africa/Kinshasa",
    "iso:country":"CD",
    "wof:name":"Vobora",
    "wof:placetype":"locality"
},
  "geometry": {"coordinates":[21.18552,3.41122],"type":"Point"}
}