{
  "type": "Feature",
  "properties": {
    "gn:admin1_code":"23.0",
    "gn:asciiname":"Munsense",
    "gn:country_code":"CD",
    "gn:dem":766,
    "gn:feature_class":"P",
    "gn:feature_code":"PPL",
    "gn:name":"Munsense",
    "gn:population":0,
    "gn:timezone":"Africa/Lubumbashi",
    "iso:country":"CD",
    "wof:name":"Munsense",
    "wof:placetype":"locality"
},
  "geometry": {"coordinates":[22.95,-6.25],"type":"Point"}
}