{
  "type": "Feature",
  "properties": {
    "gn:admin1_code":"23.0",
    "gn:asciiname":"Mpungu",
    "gn:country_code":"CD",
    "gn:dem":797,
    "gn:feature_class":"P",
    "gn:feature_code":"PPL",
    "gn:name":"Mpungu",
    "gn:population":0,
    "gn:timezone":"Africa/Lubumbashi",
    "iso:country":"CD",
    "name:deu_x_preferred":[
        "Mpungu"
    ],
    "name:fin_x_preferred":[
        "Mpungu"
    ],
    "wof:name":"Mpungu",
    "wof:placetype":"locality"
},
  "geometry": {"coordinates":[22.60405,-7.0904],"type":"Point"}
}