{
  "type": "Feature",
  "properties": {
    "gn:admin1_code":"13.0",
    "gn:asciiname":"Wase",
    "gn:country_code":"CD",
    "gn:dem":550,
    "gn:feature_class":"P",
    "gn:feature_code":"PPL",
    "gn:name":"Wase",
    "gn:population":0,
    "gn:timezone":"Africa/Lubumbashi",
    "iso:country":"CD",
    "name:ceb_x_preferred":[
        "Wase"
    ],
    "name:deu_x_preferred":[
        "Wase"
    ],
    "name:ita_x_preferred":[
        "Wase"
    ],
    "name:spa_x_preferred":[
        "Wase"
    ],
    "name:swe_x_preferred":[
        "Wase"
    ],
    "wof:name":"Wase",
    "wof:placetype":"locality"
},
  "geometry": {"coordinates":[24.80451,3.55042],"type":"Point"}
}