{
  "type": "Feature",
  "properties": {
    "gn:admin1_code":"21.0",
    "gn:asciiname":"Piatshi",
    "gn:country_code":"CD",
    "gn:dem":596,
    "gn:feature_class":"P",
    "gn:feature_code":"PPL",
    "gn:name":"Piatshi",
    "gn:population":0,
    "gn:timezone":"Africa/Lubumbashi",
    "iso:country":"CD",
    "wof:name":"Piatshi",
    "wof:placetype":"locality"
},
  "geometry": {"coordinates":[25.68333,-5.13333],"type":"Point"}
}