{
  "type": "Feature",
  "properties": {
    "gn:admin1_code":"25.0",
    "gn:asciiname":"Busu-Mayele",
    "gn:country_code":"CD",
    "gn:dem":362,
    "gn:feature_class":"P",
    "gn:feature_code":"PPL",
    "gn:name":"Busu-Mayele",
    "gn:population":0,
    "gn:timezone":"Africa/Kinshasa",
    "iso:country":"CD",
    "name:und_x_variant":[
        "Busu Mayala",
        "Busu-Mayale",
        "Busu-Mayele"
    ],
    "wof:name":"Busu-Mayele",
    "wof:placetype":"locality"
},
  "geometry": {"coordinates":[21.24588,1.77516],"type":"Point"}
}