{
  "type": "Feature",
  "properties": {
    "gn:admin1_code":"8.0",
    "gn:asciiname":"Kingonda",
    "gn:country_code":"CD",
    "gn:dem":671,
    "gn:feature_class":"P",
    "gn:feature_code":"PPL",
    "gn:name":"Kingonda",
    "gn:population":0,
    "gn:timezone":"Africa/Kinshasa",
    "iso:country":"CD",
    "wof:name":"Kingonda",
    "wof:placetype":"locality"
},
  "geometry": {"coordinates":[15.34463,-5.21674],"type":"Point"}
}