{
  "type": "Feature",
  "properties": {
    "gn:admin1_code":"24.0",
    "gn:asciiname":"Kebikenkale",
    "gn:country_code":"CD",
    "gn:dem":337,
    "gn:feature_class":"P",
    "gn:feature_code":"PPL",
    "gn:name":"Kebikenkale",
    "gn:population":0,
    "gn:timezone":"Africa/Kinshasa",
    "iso:country":"CD",
    "wof:name":"Kebikenkale",
    "wof:placetype":"locality"
},
  "geometry": {"coordinates":[17.70857,-2.90361],"type":"Point"}
}