{
  "type": "Feature",
  "properties": {
    "gn:admin1_code":"19.0",
    "gn:asciiname":"Ngonde-Luwe",
    "gn:country_code":"CD",
    "gn:dem":521,
    "gn:feature_class":"P",
    "gn:feature_code":"PPL",
    "gn:name":"Ngonde-Luwe",
    "gn:population":0,
    "gn:timezone":"Africa/Kinshasa",
    "iso:country":"CD",
    "wof:name":"Ngonde-Luwe",
    "wof:placetype":"locality"
},
  "geometry": {"coordinates":[17.59201,-4.36045],"type":"Point"}
}