{
  "type": "Feature",
  "properties": {
    "gn:admin1_code":"8.0",
    "gn:asciiname":"Kinkuku",
    "gn:country_code":"CD",
    "gn:dem":511,
    "gn:feature_class":"P",
    "gn:feature_code":"PPL",
    "gn:name":"Kinkuku",
    "gn:population":0,
    "gn:timezone":"Africa/Kinshasa",
    "iso:country":"CD",
    "wof:name":"Kinkuku",
    "wof:placetype":"locality"
},
  "geometry": {"coordinates":[13.18333,-4.88333],"type":"Point"}
}