{
  "type": "Feature",
  "properties": {
    "gn:admin1_code":"23.0",
    "gn:asciiname":"Beleke",
    "gn:country_code":"CD",
    "gn:dem":797,
    "gn:feature_class":"P",
    "gn:feature_code":"PPL",
    "gn:name":"Beleke",
    "gn:population":0,
    "gn:timezone":"Africa/Lubumbashi",
    "iso:country":"CD",
    "wof:name":"Beleke",
    "wof:placetype":"locality"
},
  "geometry": {"coordinates":[21.83905,-7.12182],"type":"Point"}
}