{
  "type": "Feature",
  "properties": {
    "gn:admin1_code":"19.0",
    "gn:asciiname":"Mandosi",
    "gn:country_code":"CD",
    "gn:dem":757,
    "gn:feature_class":"P",
    "gn:feature_code":"PPL",
    "gn:name":"Mandosi",
    "gn:population":0,
    "gn:timezone":"Africa/Kinshasa",
    "iso:country":"CD",
    "wof:name":"Mandosi",
    "wof:placetype":"locality"
},
  "geometry": {"coordinates":[17.19438,-5.35156],"type":"Point"}
}