{
  "type": "Feature",
  "properties": {
    "gn:admin1_code":"22.0",
    "gn:asciiname":"Zumbi Deuxieme",
    "gn:country_code":"CD",
    "gn:dem":956,
    "gn:feature_class":"P",
    "gn:feature_code":"PPL",
    "gn:name":"Zumbi Deuxi\u00e8me",
    "gn:population":0,
    "gn:timezone":"Africa/Lubumbashi",
    "iso:country":"CD",
    "wof:name":"Zumbi Deuxieme",
    "wof:placetype":"locality"
},
  "geometry": {"coordinates":[22.22811,-7.97781],"type":"Point"}
}