{
  "type": "Feature",
  "properties": {
    "gn:admin1_code":"22.0",
    "gn:asciiname":"Sakambundji",
    "gn:country_code":"CD",
    "gn:dem":1085,
    "gn:feature_class":"P",
    "gn:feature_code":"PPL",
    "gn:name":"Sakambundji",
    "gn:population":0,
    "gn:timezone":"Africa/Lubumbashi",
    "iso:country":"CD",
    "wof:name":"Sakambundji",
    "wof:placetype":"locality"
},
  "geometry": {"coordinates":[22.47573,-10.594],"type":"Point"}
}