{
  "type": "Feature",
  "properties": {
    "gn:admin1_code":"16.0",
    "gn:asciiname":"Mbisalsoio",
    "gn:country_code":"CD",
    "gn:dem":787,
    "gn:feature_class":"P",
    "gn:feature_code":"PPL",
    "gn:name":"Mbisalsoio",
    "gn:population":0,
    "gn:timezone":"Africa/Lubumbashi",
    "iso:country":"CD",
    "wof:name":"Mbisalsoio",
    "wof:placetype":"locality"
},
  "geometry": {"coordinates":[27.62695,2.35791],"type":"Point"}
}