{
  "type": "Feature",
  "properties": {
    "gn:admin1_code":"21.0",
    "gn:asciiname":"Etombale",
    "gn:country_code":"CD",
    "gn:dem":760,
    "gn:feature_class":"P",
    "gn:feature_code":"PPL",
    "gn:name":"Etombale",
    "gn:population":0,
    "gn:timezone":"Africa/Lubumbashi",
    "iso:country":"CD",
    "name:und_x_variant":[
        "Etombole"
    ],
    "wof:name":"Etombale",
    "wof:placetype":"locality"
},
  "geometry": {"coordinates":[24.58343,-5.66272],"type":"Point"}
}