{
  "type": "Feature",
  "properties": {
    "gn:admin1_code":"18.0",
    "gn:asciiname":"Kalenga",
    "gn:country_code":"CD",
    "gn:dem":750,
    "gn:feature_class":"P",
    "gn:feature_code":"PPL",
    "gn:name":"Kalenga",
    "gn:population":0,
    "gn:timezone":"Africa/Lubumbashi",
    "iso:country":"CD",
    "wof:name":"Kalenga",
    "wof:placetype":"locality"
},
  "geometry": {"coordinates":[20.00941,-6.59201],"type":"Point"}
}