{
  "type": "Feature",
  "properties": {
    "gn:admin1_code":"28.0",
    "gn:asciiname":"Dongo",
    "gn:country_code":"CD",
    "gn:dem":362,
    "gn:feature_class":"P",
    "gn:feature_code":"PPL",
    "gn:name":"Dongo",
    "gn:population":0,
    "gn:timezone":"Africa/Kinshasa",
    "iso:country":"CD",
    "name:fra_x_preferred":[
        "Dongo"
    ],
    "wof:name":"Dongo",
    "wof:placetype":"locality"
},
  "geometry": {"coordinates":[18.40174,2.71901],"type":"Point"}
}