{
  "type": "Feature",
  "properties": {
    "gn:admin1_code":"30.0",
    "gn:asciiname":"Luale",
    "gn:country_code":"CD",
    "gn:dem":514,
    "gn:feature_class":"P",
    "gn:feature_code":"PPL",
    "gn:name":"Luale",
    "gn:population":0,
    "gn:timezone":"Africa/Lubumbashi",
    "iso:country":"CD",
    "name:und_x_variant":[
        "Lualo"
    ],
    "wof:name":"Luale",
    "wof:placetype":"locality"
},
  "geometry": {"coordinates":[23.04724,1.16252],"type":"Point"}
}