{
  "type": "Feature",
  "properties": {
    "gn:admin1_code":"10.0",
    "gn:asciiname":"Musongewa",
    "gn:country_code":"CD",
    "gn:dem":657,
    "gn:feature_class":"P",
    "gn:feature_code":"PPL",
    "gn:name":"Musongewa",
    "gn:population":0,
    "gn:timezone":"Africa/Lubumbashi",
    "iso:country":"CD",
    "name:und_x_variant":[
        "Musongelwa"
    ],
    "wof:name":"Musongewa",
    "wof:placetype":"locality"
},
  "geometry": {"coordinates":[27.22562000000001,-3.96064],"type":"Point"}
}