{
  "type": "Feature",
  "properties": {
    "gn:admin1_code":"14.0",
    "gn:asciiname":"Malata",
    "gn:country_code":"CD",
    "gn:dem":1498,
    "gn:feature_class":"P",
    "gn:feature_code":"PPL",
    "gn:name":"Malata",
    "gn:population":0,
    "gn:timezone":"Africa/Lubumbashi",
    "iso:country":"CD",
    "wof:name":"Malata",
    "wof:placetype":"locality"
},
  "geometry": {"coordinates":[26.38333,-11.58333],"type":"Point"}
}