{
  "type": "Feature",
  "properties": {
    "gn:admin1_code":"8.0",
    "gn:asciiname":"Kinsongunia",
    "gn:country_code":"CD",
    "gn:dem":625,
    "gn:feature_class":"P",
    "gn:feature_code":"PPL",
    "gn:name":"Kinsongunia",
    "gn:population":0,
    "gn:timezone":"Africa/Kinshasa",
    "iso:country":"CD",
    "wof:name":"Kinsongunia",
    "wof:placetype":"locality"
},
  "geometry": {"coordinates":[13.68887,-4.94875],"type":"Point"}
}