{
  "type": "Feature",
  "properties": {
    "gn:admin1_code":"22.0",
    "gn:asciiname":"Kalule-Nord",
    "gn:country_code":"CD",
    "gn:dem":869,
    "gn:feature_class":"P",
    "gn:feature_code":"PPL",
    "gn:name":"Kalule-Nord",
    "gn:population":0,
    "gn:timezone":"Africa/Lubumbashi",
    "iso:country":"CD",
    "wof:name":"Kalule-Nord",
    "wof:placetype":"locality"
},
  "geometry": {"coordinates":[25.87536,-9.69024],"type":"Point"}
}