{
  "type": "Feature",
  "properties": {
    "gn:admin1_code":"8.0",
    "gn:asciiname":"Kilemba",
    "gn:country_code":"CD",
    "gn:dem":664,
    "gn:feature_class":"P",
    "gn:feature_code":"PPL",
    "gn:name":"Kilemba",
    "gn:population":0,
    "gn:timezone":"Africa/Kinshasa",
    "iso:country":"CD",
    "wof:name":"Kilemba",
    "wof:placetype":"locality"
},
  "geometry": {"coordinates":[15.43839,-5.32493],"type":"Point"}
}