{
  "type": "Feature",
  "properties": {
    "gn:admin1_code":"14.0",
    "gn:asciiname":"Mwenze",
    "gn:country_code":"CD",
    "gn:dem":1195,
    "gn:feature_class":"P",
    "gn:feature_code":"PPL",
    "gn:name":"Mwenze",
    "gn:population":0,
    "gn:timezone":"Africa/Lubumbashi",
    "iso:country":"CD",
    "wof:name":"Mwenze",
    "wof:placetype":"locality"
},
  "geometry": {"coordinates":[27.83135,-8.90591],"type":"Point"}
}