{
  "type": "Feature",
  "properties": {
    "gn:admin1_code":"21.0",
    "gn:asciiname":"Lukusa",
    "gn:country_code":"CD",
    "gn:dem":946,
    "gn:feature_class":"P",
    "gn:feature_code":"PPL",
    "gn:name":"Lukusa",
    "gn:population":0,
    "gn:timezone":"Africa/Lubumbashi",
    "iso:country":"CD",
    "wof:name":"Lukusa",
    "wof:placetype":"locality"
},
  "geometry": {"coordinates":[23.46837,-6.98549],"type":"Point"}
}