{
  "type": "Feature",
  "properties": {
    "gn:admin1_code":"24.0",
    "gn:asciiname":"Mokila",
    "gn:country_code":"CD",
    "gn:dem":331,
    "gn:feature_class":"P",
    "gn:feature_code":"PPL",
    "gn:name":"Mokila",
    "gn:population":0,
    "gn:timezone":"Africa/Kinshasa",
    "iso:country":"CD",
    "wof:name":"Mokila",
    "wof:placetype":"locality"
},
  "geometry": {"coordinates":[18.24888,-3.41205],"type":"Point"}
}