{
  "type": "Feature",
  "properties": {
    "gn:admin1_code":"14.0",
    "gn:asciiname":"Sepele",
    "gn:country_code":"CD",
    "gn:dem":1141,
    "gn:feature_class":"P",
    "gn:feature_code":"PPL",
    "gn:name":"Sepele",
    "gn:population":0,
    "gn:timezone":"Africa/Lubumbashi",
    "iso:country":"CD",
    "wof:name":"Sepele",
    "wof:placetype":"locality"
},
  "geometry": {"coordinates":[26.95472,-10.96917],"type":"Point"}
}