{
  "type": "Feature",
  "properties": {
    "gn:admin1_code":"22.0",
    "gn:asciiname":"Kamimbi",
    "gn:country_code":"CD",
    "gn:dem":1212,
    "gn:feature_class":"P",
    "gn:feature_code":"PPL",
    "gn:name":"Kamimbi",
    "gn:population":0,
    "gn:timezone":"Africa/Lubumbashi",
    "iso:country":"CD",
    "wof:name":"Kamimbi",
    "wof:placetype":"locality"
},
  "geometry": {"coordinates":[26.44238,-10.75409],"type":"Point"}
}