{
  "type": "Feature",
  "properties": {
    "gn:admin1_code":"22.0",
    "gn:asciiname":"Mukabe",
    "gn:country_code":"CD",
    "gn:dem":1333,
    "gn:feature_class":"P",
    "gn:feature_code":"PPL",
    "gn:name":"Mukabe",
    "gn:population":0,
    "gn:timezone":"Africa/Lubumbashi",
    "iso:country":"CD",
    "name:und_x_variant":[
        "Mokabe",
        "Mukabe"
    ],
    "wof:name":"Mukabe",
    "wof:placetype":"locality"
},
  "geometry": {"coordinates":[26.10158,-10.69935],"type":"Point"}
}