{
  "type": "Feature",
  "properties": {
    "gn:admin1_code":"22.0",
    "gn:asciiname":"Mutombo-a-Tshibang",
    "gn:country_code":"CD",
    "gn:dem":893,
    "gn:feature_class":"P",
    "gn:feature_code":"PPL",
    "gn:name":"Mutombo-a-Tshibang",
    "gn:population":0,
    "gn:timezone":"Africa/Lubumbashi",
    "iso:country":"CD",
    "name:und_x_variant":[
        "Mutombo-Tshibango"
    ],
    "wof:name":"Mutombo-a-Tshibang",
    "wof:placetype":"locality"
},
  "geometry": {"coordinates":[23.17742,-7.84765],"type":"Point"}
}