{
  "type": "Feature",
  "properties": {
    "gn:admin1_code":"30.0",
    "gn:asciiname":"Bafwapipoyo",
    "gn:country_code":"CD",
    "gn:dem":500,
    "gn:feature_class":"P",
    "gn:feature_code":"PPL",
    "gn:name":"Bafwapipoyo",
    "gn:population":0,
    "gn:timezone":"Africa/Lubumbashi",
    "iso:country":"CD",
    "wof:name":"Bafwapipoyo",
    "wof:placetype":"locality"
},
  "geometry": {"coordinates":[26.09349,1.41231],"type":"Point"}
}