{
  "type": "Feature",
  "properties": {
    "gn:admin1_code":"13.0",
    "gn:asciiname":"Andrekoladi",
    "gn:country_code":"CD",
    "gn:dem":727,
    "gn:feature_class":"P",
    "gn:feature_code":"PPL",
    "gn:name":"Andrekoladi",
    "gn:population":0,
    "gn:timezone":"Africa/Lubumbashi",
    "iso:country":"CD",
    "wof:name":"Andrekoladi",
    "wof:placetype":"locality"
},
  "geometry": {"coordinates":[27.42609,2.76971],"type":"Point"}
}