{
  "type": "Feature",
  "properties": {
    "gn:admin1_code":"8.0",
    "gn:asciiname":"Kibusi",
    "gn:country_code":"CD",
    "gn:dem":220,
    "gn:feature_class":"P",
    "gn:feature_code":"PPL",
    "gn:name":"Kibusi",
    "gn:population":0,
    "gn:timezone":"Africa/Kinshasa",
    "iso:country":"CD",
    "wof:name":"Kibusi",
    "wof:placetype":"locality"
},
  "geometry": {"coordinates":[14.08575,-4.88639],"type":"Point"}
}