{
  "type": "Feature",
  "properties": {
    "gn:admin1_code":"23.0",
    "gn:asciiname":"Samashita",
    "gn:country_code":"CD",
    "gn:dem":871,
    "gn:feature_class":"P",
    "gn:feature_code":"PPL",
    "gn:name":"Samashita",
    "gn:population":0,
    "gn:timezone":"Africa/Lubumbashi",
    "iso:country":"CD",
    "wof:name":"Samashita",
    "wof:placetype":"locality"
},
  "geometry": {"coordinates":[22.53989,-7.35986],"type":"Point"}
}