{
  "type": "Feature",
  "properties": {
    "gn:admin1_code":"12.0",
    "gn:asciiname":"Lutulo",
    "gn:country_code":"CD",
    "gn:dem":1648,
    "gn:feature_class":"P",
    "gn:feature_code":"PPL",
    "gn:name":"Lutulo",
    "gn:population":0,
    "gn:timezone":"Africa/Lubumbashi",
    "iso:country":"CD",
    "wof:name":"Lutulo",
    "wof:placetype":"locality"
},
  "geometry": {"coordinates":[28.88389,-4.80528],"type":"Point"}
}