{
  "type": "Feature",
  "properties": {
    "gn:admin1_code":"28.0",
    "gn:asciiname":"Bopingima",
    "gn:country_code":"CD",
    "gn:dem":373,
    "gn:feature_class":"P",
    "gn:feature_code":"PPL",
    "gn:name":"Bopingima",
    "gn:population":0,
    "gn:timezone":"Africa/Kinshasa",
    "iso:country":"CD",
    "wof:name":"Bopingima",
    "wof:placetype":"locality"
},
  "geometry": {"coordinates":[19.70682,3.06212],"type":"Point"}
}