{
  "type": "Feature",
  "properties": {
    "gn:admin1_code":"19.0",
    "gn:asciiname":"Shamukondo",
    "gn:country_code":"CD",
    "gn:dem":865,
    "gn:feature_class":"P",
    "gn:feature_code":"PPL",
    "gn:name":"Shamukondo",
    "gn:population":0,
    "gn:timezone":"Africa/Kinshasa",
    "iso:country":"CD",
    "wof:name":"Shamukondo",
    "wof:placetype":"locality"
},
  "geometry": {"coordinates":[18.58704,-6.61232],"type":"Point"}
}