{
  "type": "Feature",
  "properties": {
    "gn:admin1_code":"18.0",
    "gn:asciiname":"Misumba",
    "gn:country_code":"CD",
    "gn:dem":489,
    "gn:feature_class":"P",
    "gn:feature_code":"PPL",
    "gn:name":"Misumba",
    "gn:population":0,
    "gn:timezone":"Africa/Lubumbashi",
    "iso:country":"CD",
    "wof:name":"Misumba",
    "wof:placetype":"locality"
},
  "geometry": {"coordinates":[20.46381,-4.55605],"type":"Point"}
}