{
  "type": "Feature",
  "properties": {
    "gn:admin1_code":"21.0",
    "gn:asciiname":"Pio Mitondo",
    "gn:country_code":"CD",
    "gn:dem":730,
    "gn:feature_class":"P",
    "gn:feature_code":"PPL",
    "gn:name":"Pio Mitondo",
    "gn:population":0,
    "gn:timezone":"Africa/Lubumbashi",
    "iso:country":"CD",
    "wof:name":"Pio Mitondo",
    "wof:placetype":"locality"
},
  "geometry": {"coordinates":[23.90755,-6.62058],"type":"Point"}
}