{
  "type": "Feature",
  "properties": {
    "gn:admin1_code":"16.0",
    "gn:asciiname":"Matete",
    "gn:country_code":"CD",
    "gn:dem":773,
    "gn:feature_class":"P",
    "gn:feature_code":"PPL",
    "gn:name":"Matete",
    "gn:population":0,
    "gn:timezone":"Africa/Lubumbashi",
    "iso:country":"CD",
    "name:ceb_x_preferred":[
        "Matete"
    ],
    "name:eus_x_preferred":[
        "Matete"
    ],
    "name:fra_x_preferred":[
        "Matete"
    ],
    "name:lin_x_preferred":[
        "Matete"
    ],
    "name:swe_x_preferred":[
        "Matete"
    ],
    "wof:name":"Matete",
    "wof:placetype":"locality"
},
  "geometry": {"coordinates":[27.60383,2.43028],"type":"Point"}
}