{
  "type": "Feature",
  "properties": {
    "gn:admin1_code":"20.0",
    "gn:asciiname":"Kapita-Nzadi",
    "gn:country_code":"CD",
    "gn:dem":374,
    "gn:feature_class":"P",
    "gn:feature_code":"PPL",
    "gn:name":"Kapita-Nzadi",
    "gn:population":0,
    "gn:timezone":"Africa/Kinshasa",
    "iso:country":"CD",
    "wof:name":"Kapita-Nzadi",
    "wof:placetype":"locality"
},
  "geometry": {"coordinates":[17.20006,-4.28279],"type":"Point"}
}