{
  "type": "Feature",
  "properties": {
    "gn:admin1_code":"23.0",
    "gn:asciiname":"Sampashi",
    "gn:country_code":"CD",
    "gn:dem":879,
    "gn:feature_class":"P",
    "gn:feature_code":"PPL",
    "gn:name":"Sampashi",
    "gn:population":0,
    "gn:timezone":"Africa/Lubumbashi",
    "iso:country":"CD",
    "wof:name":"Sampashi",
    "wof:placetype":"locality"
},
  "geometry": {"coordinates":[22.51112,-7.25935],"type":"Point"}
}