{
  "type": "Feature",
  "properties": {
    "gn:admin1_code":"19.0",
    "gn:asciiname":"Muni-Mayala",
    "gn:country_code":"CD",
    "gn:dem":654,
    "gn:feature_class":"P",
    "gn:feature_code":"PPL",
    "gn:name":"Muni-Mayala",
    "gn:population":0,
    "gn:timezone":"Africa/Kinshasa",
    "iso:country":"CD",
    "wof:name":"Muni-Mayala",
    "wof:placetype":"locality"
},
  "geometry": {"coordinates":[17.41135,-7.02018],"type":"Point"}
}