{
  "type": "Feature",
  "properties": {
    "gn:admin1_code":"31.0",
    "gn:asciiname":"Lokombo-Lileke",
    "gn:country_code":"CD",
    "gn:dem":403,
    "gn:feature_class":"P",
    "gn:feature_code":"PPL",
    "gn:name":"Lokombo-Lileke",
    "gn:population":0,
    "gn:timezone":"Africa/Kinshasa",
    "iso:country":"CD",
    "name:und_x_variant":[
        "Lokomb-Lileke",
        "Lokombo-Lileke"
    ],
    "wof:name":"Lokombo-Lileke",
    "wof:placetype":"locality"
},
  "geometry": {"coordinates":[21.43333,-0.03333],"type":"Point"}
}