{
  "type": "Feature",
  "properties": {
    "gn:admin1_code":"20.0",
    "gn:asciiname":"Kimbuku",
    "gn:country_code":"CD",
    "gn:dem":464,
    "gn:feature_class":"P",
    "gn:feature_code":"PPL",
    "gn:name":"Kimbuku",
    "gn:population":0,
    "gn:timezone":"Africa/Kinshasa",
    "iso:country":"CD",
    "wof:name":"Kimbuku",
    "wof:placetype":"locality"
},
  "geometry": {"coordinates":[18.59558,-5.25483],"type":"Point"}
}