{
  "type": "Feature",
  "properties": {
    "gn:admin1_code":"4.0",
    "gn:asciiname":"Sengeyabo",
    "gn:country_code":"CD",
    "gn:dem":766,
    "gn:feature_class":"P",
    "gn:feature_code":"PPL",
    "gn:name":"Sengeyabo",
    "gn:population":0,
    "gn:timezone":"Africa/Lubumbashi",
    "iso:country":"CD",
    "wof:name":"Sengeyabo",
    "wof:placetype":"locality"
},
  "geometry": {"coordinates":[23.9283,-6.14696],"type":"Point"}
}