{
  "type": "Feature",
  "properties": {
    "gn:admin1_code":"29.0",
    "gn:asciiname":"Mugumba",
    "gn:country_code":"CD",
    "gn:dem":1129,
    "gn:feature_class":"P",
    "gn:feature_code":"PPL",
    "gn:name":"Mugumba",
    "gn:population":0,
    "gn:timezone":"Africa/Lubumbashi",
    "iso:country":"CD",
    "wof:name":"Mugumba",
    "wof:placetype":"locality"
},
  "geometry": {"coordinates":[28.58795,-6.40101],"type":"Point"}
}