{
  "type": "Feature",
  "properties": {
    "gn:admin1_code":"28.0",
    "gn:asciiname":"Mbila",
    "gn:country_code":"CD",
    "gn:dem":354,
    "gn:feature_class":"P",
    "gn:feature_code":"PPL",
    "gn:name":"Mbila",
    "gn:population":0,
    "gn:timezone":"Africa/Kinshasa",
    "iso:country":"CD",
    "wof:name":"Mbila",
    "wof:placetype":"locality"
},
  "geometry": {"coordinates":[18.68526,3.15511],"type":"Point"}
}