{
  "type": "Feature",
  "properties": {
    "gn:admin1_code":"10.0",
    "gn:asciiname":"Yamba",
    "gn:country_code":"CD",
    "gn:dem":783,
    "gn:feature_class":"P",
    "gn:feature_code":"PPL",
    "gn:name":"Yamba",
    "gn:population":0,
    "gn:timezone":"Africa/Lubumbashi",
    "iso:country":"CD",
    "name:ceb_x_preferred":[
        "Yamba"
    ],
    "name:deu_x_preferred":[
        "Yamba"
    ],
    "name:fra_x_preferred":[
        "Yamba"
    ],
    "name:swe_x_preferred":[
        "Yamba"
    ],
    "wof:name":"Yamba",
    "wof:placetype":"locality"
},
  "geometry": {"coordinates":[27.46667,-4.35],"type":"Point"}
}