{
  "type": "Feature",
  "properties": {
    "gn:admin1_code":"19.0",
    "gn:asciiname":"Watakanuki",
    "gn:country_code":"CD",
    "gn:dem":1009,
    "gn:feature_class":"P",
    "gn:feature_code":"PPL",
    "gn:name":"Watakanuki",
    "gn:population":0,
    "gn:timezone":"Africa/Kinshasa",
    "iso:country":"CD",
    "wof:name":"Watakanuki",
    "wof:placetype":"locality"
},
  "geometry": {"coordinates":[18.17872,-6.7189],"type":"Point"}
}