{
  "type": "Feature",
  "properties": {
    "gn:admin1_code":"27.0",
    "gn:asciiname":"Tshudi",
    "gn:country_code":"CD",
    "gn:dem":556,
    "gn:feature_class":"P",
    "gn:feature_code":"PPL",
    "gn:name":"Tshudi",
    "gn:population":0,
    "gn:timezone":"Africa/Lubumbashi",
    "iso:country":"CD",
    "name:und_x_variant":[
        "N.S.M. Tshudi"
    ],
    "wof:name":"Tshudi",
    "wof:placetype":"locality"
},
  "geometry": {"coordinates":[22.66806,-2.7428],"type":"Point"}
}