{
  "type": "Feature",
  "properties": {
    "gn:admin1_code":"28.0",
    "gn:asciiname":"Bonduma",
    "gn:country_code":"CD",
    "gn:dem":397,
    "gn:feature_class":"P",
    "gn:feature_code":"PPL",
    "gn:name":"Bonduma",
    "gn:population":0,
    "gn:timezone":"Africa/Kinshasa",
    "iso:country":"CD",
    "name:fra_x_preferred":[
        "Bonduma"
    ],
    "wof:name":"Bonduma",
    "wof:placetype":"locality"
},
  "geometry": {"coordinates":[19.05566,2.75031],"type":"Point"}
}