{
  "type": "Feature",
  "properties": {
    "gn:admin1_code":"23.0",
    "gn:asciiname":"Kasonji",
    "gn:country_code":"CD",
    "gn:dem":732,
    "gn:feature_class":"P",
    "gn:feature_code":"PPL",
    "gn:name":"Kasonji",
    "gn:population":0,
    "gn:timezone":"Africa/Lubumbashi",
    "iso:country":"CD",
    "wof:name":"Kasonji",
    "wof:placetype":"locality"
},
  "geometry": {"coordinates":[22.78805,-5.95627],"type":"Point"}
}