{
  "type": "Feature",
  "properties": {
    "gn:admin1_code":"26.0",
    "gn:asciiname":"Litoro",
    "gn:country_code":"CD",
    "gn:dem":450,
    "gn:feature_class":"P",
    "gn:feature_code":"PPL",
    "gn:name":"Litoro",
    "gn:population":0,
    "gn:timezone":"Africa/Kinshasa",
    "iso:country":"CD",
    "wof:name":"Litoro",
    "wof:placetype":"locality"
},
  "geometry": {"coordinates":[19.71835,5.04314],"type":"Point"}
}