{
  "type": "Feature",
  "properties": {
    "gn:admin1_code":"16.0",
    "gn:asciiname":"Dule",
    "gn:country_code":"CD",
    "gn:dem":735,
    "gn:feature_class":"P",
    "gn:feature_code":"PPL",
    "gn:name":"Dule",
    "gn:population":0,
    "gn:timezone":"Africa/Lubumbashi",
    "iso:country":"CD",
    "name:bos_x_preferred":[
        "Dule"
    ],
    "name:ceb_x_preferred":[
        "Dule"
    ],
    "name:hrv_x_preferred":[
        "Dule"
    ],
    "name:nld_x_preferred":[
        "Dule"
    ],
    "name:pol_x_preferred":[
        "Dule"
    ],
    "name:slv_x_preferred":[
        "Dule"
    ],
    "name:srp_x_preferred":[
        "\u0414\u0443\u043b\u0435"
    ],
    "name:swe_x_preferred":[
        "Dule"
    ],
    "wof:name":"Dule",
    "wof:placetype":"locality"
},
  "geometry": {"coordinates":[28.74828,4.00373],"type":"Point"}
}