{
  "type": "Feature",
  "properties": {
    "gn:admin1_code":"22.0",
    "gn:asciiname":"Mwin Mwisam",
    "gn:country_code":"CD",
    "gn:dem":1047,
    "gn:feature_class":"P",
    "gn:feature_code":"PPL",
    "gn:name":"Mwin Mwisam",
    "gn:population":0,
    "gn:timezone":"Africa/Lubumbashi",
    "iso:country":"CD",
    "wof:name":"Mwin Mwisam",
    "wof:placetype":"locality"
},
  "geometry": {"coordinates":[22.06556,-9.00752],"type":"Point"}
}