{
  "type": "Feature",
  "properties": {
    "gn:admin1_code":"21.0",
    "gn:asciiname":"Kasolo",
    "gn:country_code":"CD",
    "gn:dem":770,
    "gn:feature_class":"P",
    "gn:feature_code":"PPL",
    "gn:name":"Kasolo",
    "gn:population":0,
    "gn:timezone":"Africa/Lubumbashi",
    "iso:country":"CD",
    "wof:name":"Kasolo",
    "wof:placetype":"locality"
},
  "geometry": {"coordinates":[25.37366,-6.27815],"type":"Point"}
}