{
  "type": "Feature",
  "properties": {
    "gn:admin1_code":"22.0",
    "gn:asciiname":"Mwin Nduu",
    "gn:country_code":"CD",
    "gn:dem":963,
    "gn:feature_class":"P",
    "gn:feature_code":"PPL",
    "gn:name":"Mwin Nduu",
    "gn:population":0,
    "gn:timezone":"Africa/Lubumbashi",
    "iso:country":"CD",
    "name:und_x_variant":[
        "Mwene-Ndua"
    ],
    "wof:name":"Mwin Nduu",
    "wof:placetype":"locality"
},
  "geometry": {"coordinates":[23.32826,-8.07162],"type":"Point"}
}