{
  "type": "Feature",
  "properties": {
    "gn:admin1_code":"15.0",
    "gn:asciiname":"Lubanda",
    "gn:country_code":"CD",
    "gn:dem":860,
    "gn:feature_class":"P",
    "gn:feature_code":"PPL",
    "gn:name":"Lubanda",
    "gn:population":0,
    "gn:timezone":"Africa/Lubumbashi",
    "iso:country":"CD",
    "name:swa_x_preferred":[
        "Lubanda"
    ],
    "wof:name":"Lubanda",
    "wof:placetype":"locality"
},
  "geometry": {"coordinates":[24.26607000000001,-7.2726],"type":"Point"}
}