{
  "type": "Feature",
  "properties": {
    "gn:admin1_code":"8.0",
    "gn:asciiname":"Vinda",
    "gn:country_code":"CD",
    "gn:dem":693,
    "gn:feature_class":"P",
    "gn:feature_code":"PPL",
    "gn:name":"Vinda",
    "gn:population":0,
    "gn:timezone":"Africa/Kinshasa",
    "iso:country":"CD",
    "name:ceb_x_preferred":[
        "Vinda"
    ],
    "name:deu_x_preferred":[
        "Vinda"
    ],
    "name:swe_x_preferred":[
        "Vinda"
    ],
    "wof:name":"Vinda",
    "wof:placetype":"locality"
},
  "geometry": {"coordinates":[15.22258,-5.69326],"type":"Point"}
}