{
  "type": "Feature",
  "properties": {
    "gn:admin1_code":"22.0",
    "gn:asciiname":"Djamba",
    "gn:country_code":"CD",
    "gn:dem":1018,
    "gn:feature_class":"P",
    "gn:feature_code":"PPL",
    "gn:name":"Djamba",
    "gn:population":0,
    "gn:timezone":"Africa/Lubumbashi",
    "iso:country":"CD",
    "wof:name":"Djamba",
    "wof:placetype":"locality"
},
  "geometry": {"coordinates":[22.13861,-9.83243],"type":"Point"}
}