{
  "type": "Feature",
  "properties": {
    "gn:admin1_code":"13.0",
    "gn:asciiname":"Bando",
    "gn:country_code":"CD",
    "gn:dem":648,
    "gn:feature_class":"P",
    "gn:feature_code":"PPL",
    "gn:name":"Bando",
    "gn:population":0,
    "gn:timezone":"Africa/Lubumbashi",
    "iso:country":"CD",
    "wof:name":"Bando",
    "wof:placetype":"locality"
},
  "geometry": {"coordinates":[26.5987,3.67851],"type":"Point"}
}