{
  "type": "Feature",
  "properties": {
    "gn:admin1_code":"28.0",
    "gn:asciiname":"Kangalanga",
    "gn:country_code":"CD",
    "gn:dem":362,
    "gn:feature_class":"P",
    "gn:feature_code":"PPL",
    "gn:name":"Kangalanga",
    "gn:population":0,
    "gn:timezone":"Africa/Kinshasa",
    "iso:country":"CD",
    "wof:name":"Kangalanga",
    "wof:placetype":"locality"
},
  "geometry": {"coordinates":[20.2107,2.68495],"type":"Point"}
}