{
  "type": "Feature",
  "properties": {
    "gn:admin1_code":"20.0",
    "gn:asciiname":"Mienge",
    "gn:country_code":"CD",
    "gn:dem":520,
    "gn:feature_class":"P",
    "gn:feature_code":"PPL",
    "gn:name":"Mienge",
    "gn:population":0,
    "gn:timezone":"Africa/Kinshasa",
    "iso:country":"CD",
    "wof:name":"Mienge",
    "wof:placetype":"locality"
},
  "geometry": {"coordinates":[20.12312,-5.49033],"type":"Point"}
}