{
  "type": "Feature",
  "properties": {
    "gn:admin1_code":"8.0",
    "gn:asciiname":"Lukunga",
    "gn:country_code":"CD",
    "gn:dem":222,
    "gn:feature_class":"P",
    "gn:feature_code":"PPL",
    "gn:name":"Lukunga",
    "gn:population":0,
    "gn:timezone":"Africa/Kinshasa",
    "iso:country":"CD",
    "wof:name":"Lukunga",
    "wof:placetype":"locality"
},
  "geometry": {"coordinates":[14.30807,-5.02186],"type":"Point"}
}