{
  "type": "Feature",
  "properties": {
    "gn:admin1_code":"22.0",
    "gn:asciiname":"Tshala Deuxieme",
    "gn:country_code":"CD",
    "gn:dem":1020,
    "gn:feature_class":"P",
    "gn:feature_code":"PPL",
    "gn:name":"Tshala Deuxi\u00e8me",
    "gn:population":0,
    "gn:timezone":"Africa/Lubumbashi",
    "iso:country":"CD",
    "wof:name":"Tshala Deuxieme",
    "wof:placetype":"locality"
},
  "geometry": {"coordinates":[23.70941,-9.6745],"type":"Point"}
}