{
  "type": "Feature",
  "properties": {
    "gn:admin1_code":"8.0",
    "gn:asciiname":"Tadiankosi",
    "gn:country_code":"CD",
    "gn:dem":763,
    "gn:feature_class":"P",
    "gn:feature_code":"PPL",
    "gn:name":"Tadiankosi",
    "gn:population":0,
    "gn:timezone":"Africa/Kinshasa",
    "iso:country":"CD",
    "wof:name":"Tadiankosi",
    "wof:placetype":"locality"
},
  "geometry": {"coordinates":[15.08565,-5.47136],"type":"Point"}
}