{
  "type": "Feature",
  "properties": {
    "gn:admin1_code":"24.0",
    "gn:asciiname":"Moshie",
    "gn:country_code":"CD",
    "gn:dem":346,
    "gn:feature_class":"P",
    "gn:feature_code":"PPL",
    "gn:name":"Moshie",
    "gn:population":0,
    "gn:timezone":"Africa/Kinshasa",
    "iso:country":"CD",
    "wof:name":"Moshie",
    "wof:placetype":"locality"
},
  "geometry": {"coordinates":[17.92745,-3.00404],"type":"Point"}
}