{
  "type": "Feature",
  "properties": {
    "gn:admin1_code":"18.0",
    "gn:asciiname":"Mushidi",
    "gn:country_code":"CD",
    "gn:dem":660,
    "gn:feature_class":"P",
    "gn:feature_code":"PPL",
    "gn:name":"Mushidi",
    "gn:population":0,
    "gn:timezone":"Africa/Lubumbashi",
    "iso:country":"CD",
    "wof:name":"Mushidi",
    "wof:placetype":"locality"
},
  "geometry": {"coordinates":[21.0259,-6.83765],"type":"Point"}
}