{
  "type": "Feature",
  "properties": {
    "gn:admin1_code":"12.0",
    "gn:asciiname":"Budjenge",
    "gn:country_code":"CD",
    "gn:dem":1653,
    "gn:feature_class":"P",
    "gn:feature_code":"PPL",
    "gn:name":"Budjenge",
    "gn:population":0,
    "gn:timezone":"Africa/Lubumbashi",
    "iso:country":"CD",
    "wof:name":"Budjenge",
    "wof:placetype":"locality"
},
  "geometry": {"coordinates":[28.54224,-2.67079],"type":"Point"}
}