{
  "type": "Feature",
  "properties": {
    "gn:admin1_code":"30.0",
    "gn:asciiname":"Tokele",
    "gn:country_code":"CD",
    "gn:dem":354,
    "gn:feature_class":"P",
    "gn:feature_code":"PPL",
    "gn:name":"Tokele",
    "gn:population":0,
    "gn:timezone":"Africa/Lubumbashi",
    "iso:country":"CD",
    "wof:name":"Tokele",
    "wof:placetype":"locality"
},
  "geometry": {"coordinates":[22.71667,1.95],"type":"Point"}
}