{
  "type": "Feature",
  "properties": {
    "gn:admin1_code":"11.0",
    "gn:asciiname":"Lueshe",
    "gn:country_code":"CD",
    "gn:dem":1532,
    "gn:feature_class":"P",
    "gn:feature_code":"PPL",
    "gn:name":"Lueshe",
    "gn:population":0,
    "gn:timezone":"Africa/Lubumbashi",
    "iso:country":"CD",
    "wof:name":"Lueshe",
    "wof:placetype":"locality"
},
  "geometry": {"coordinates":[29.13825,-0.99052],"type":"Point"}
}