{
  "type": "Feature",
  "properties": {
    "gn:admin1_code":"21.0",
    "gn:asciiname":"Tshungu",
    "gn:country_code":"CD",
    "gn:dem":829,
    "gn:feature_class":"P",
    "gn:feature_code":"PPL",
    "gn:name":"Tshungu",
    "gn:population":0,
    "gn:timezone":"Africa/Lubumbashi",
    "iso:country":"CD",
    "name:und_x_variant":[
        "Kishungu",
        "Kitoto",
        "Tshungu"
    ],
    "wof:name":"Tshungu",
    "wof:placetype":"locality"
},
  "geometry": {"coordinates":[25.14643,-6.07564],"type":"Point"}
}