{
  "type": "Feature",
  "properties": {
    "gn:admin1_code":"31.0",
    "gn:asciiname":"Ifake",
    "gn:country_code":"CD",
    "gn:dem":394,
    "gn:feature_class":"P",
    "gn:feature_code":"PPL",
    "gn:name":"Ifake",
    "gn:population":0,
    "gn:timezone":"Africa/Kinshasa",
    "iso:country":"CD",
    "wof:name":"Ifake",
    "wof:placetype":"locality"
},
  "geometry": {"coordinates":[21.61667000000001,-0.65],"type":"Point"}
}