{
  "type": "Feature",
  "properties": {
    "gn:admin1_code":"29.0",
    "gn:asciiname":"Kalamata",
    "gn:country_code":"CD",
    "gn:dem":679,
    "gn:feature_class":"P",
    "gn:feature_code":"PPL",
    "gn:name":"Kalamata",
    "gn:population":0,
    "gn:timezone":"Africa/Lubumbashi",
    "iso:country":"CD",
    "name:ara_x_preferred":[
        "\u0643\u0627\u0644\u0627\u0645\u0627\u062a\u0627"
    ],
    "name:bos_x_preferred":[
        "Kalamata"
    ],
    "name:bul_x_preferred":[
        "\u041a\u0430\u043b\u0430\u043c\u0430\u0442\u0430"
    ],
    "name:cat_x_preferred":[
        "Kalamata"
    ],
    "name:ceb_x_preferred":[
        "Kalam\u00e1ta"
    ],
    "name:ces_x_preferred":[
        "Kalamata"
    ],
    "name:dan_x_preferred":[
        "Kalamata"
    ],
    "name:deu_x_preferred":[
        "Kalamata"
    ],
    "name:ell_x_preferred":[
        "\u039a\u03b1\u03bb\u03b1\u03bc\u03ac\u03c4\u03b1"
    ],
    "name:epo_x_preferred":[
        "Kalamata"
    ],
    "name:est_x_preferred":[
        "Kalam\u00e1ta"
    ],
    "name:eus_x_preferred":[
        "Kalamata"
    ],
    "name:fas_x_preferred":[
        "\u06a9\u0627\u0644\u0627\u0645\u0627\u062a\u0627"
    ],
    "name:fin_x_preferred":[
        "Kalam\u00e1ta"
    ],
    "name:fra_x_preferred":[
        "Kalamata"
    ],
    "name:heb_x_preferred":[
        "\u05e7\u05dc\u05de\u05d8\u05d4"
    ],
    "name:hrv_x_preferred":[
        "Kalamata"
    ],
    "name:hun_x_preferred":[
        "Kalam\u00e1ta"
    ],
    "name:hye_x_preferred":[
        "\u053f\u0561\u056c\u0561\u0574\u0561\u057f\u0561"
    ],
    "name:ind_x_preferred":[
        "Kalamata"
    ],
    "name:ita_x_preferred":[
        "Calamata"
    ],
    "name:jpn_x_preferred":[
        "\u30ab\u30e9\u30de\u30bf"
    ],
    "name:kor_x_preferred":[
        "\uce7c\ub77c\ub9c8\ud0c0"
    ],
    "name:lat_x_preferred":[
        "Calamata"
    ],
    "name:lit_x_preferred":[
        "Kalamata"
    ],
    "name:nld_x_preferred":[
        "Kalam\u00e1ta"
    ],
    "name:nno_x_preferred":[
        "Kalam\u00e1ta"
    ],
    "name:nor_x_preferred":[
        "Kalamata"
    ],
    "name:pnb_x_preferred":[
        "\u06a9\u0627\u0644\u0627\u0645\u0627\u062a\u0627"
    ],
    "name:pol_x_preferred":[
        "Kalamata"
    ],
    "name:por_x_preferred":[
        "Calamata"
    ],
    "name:ron_x_preferred":[
        "Kalamata"
    ],
    "name:rus_x_preferred":[
        "\u041a\u0430\u043b\u0430\u043c\u0430\u0442\u0430"
    ],
    "name:slk_x_preferred":[
        "Kalamata"
    ],
    "name:spa_x_preferred":[
        "Kalamata"
    ],
    "name:srp_x_preferred":[
        "\u041a\u0430\u043b\u0430\u043c\u0430\u0442\u0430"
    ],
    "name:swe_x_preferred":[
        "Kalamata"
    ],
    "name:tur_x_preferred":[
        "Kalamata"
    ],
    "name:ukr_x_preferred":[
        "\u041a\u0430\u043b\u0430\u043c\u0430\u0442\u0430"
    ],
    "name:urd_x_preferred":[
        "\u06a9\u0627\u0644\u0627\u0645\u0627\u062a\u0627"
    ],
    "name:vie_x_preferred":[
        "Kalamata"
    ],
    "name:war_x_preferred":[
        "Kalamata"
    ],
    "name:zho_x_preferred":[
        "\u5361\u62c9\u9a6c\u5854"
    ],
    "wof:name":"Kalamata",
    "wof:placetype":"locality"
},
  "geometry": {"coordinates":[28.24709,-7.75515],"type":"Point"}
}