{
  "type": "Feature",
  "properties": {
    "gn:admin1_code":"29.0",
    "gn:asciiname":"Kalamata",
    "gn:country_code":"CD",
    "gn:dem":679,
    "gn:feature_class":"P",
    "gn:feature_code":"PPL",
    "gn:name":"Kalamata",
    "gn:population":0,
    "gn:timezone":"Africa/Lubumbashi",
    "iso:country":"CD",
    "wof:name":"Kalamata",
    "wof:placetype":"locality"
},
  "geometry": {"coordinates":[28.24709,-7.75515],"type":"Point"}
}