{
  "type": "Feature",
  "properties": {
    "gn:admin1_code":"18.0",
    "gn:asciiname":"Kaputshia",
    "gn:country_code":"CD",
    "gn:dem":643,
    "gn:feature_class":"P",
    "gn:feature_code":"PPL",
    "gn:name":"Kaputshia",
    "gn:population":0,
    "gn:timezone":"Africa/Lubumbashi",
    "iso:country":"CD",
    "wof:name":"Kaputshia",
    "wof:placetype":"locality"
},
  "geometry": {"coordinates":[20.09213,-6.60527],"type":"Point"}
}