{
  "type": "Feature",
  "properties": {
    "gn:admin1_code":"21.0",
    "gn:asciiname":"Kaseka",
    "gn:country_code":"CD",
    "gn:dem":868,
    "gn:feature_class":"P",
    "gn:feature_code":"PPL",
    "gn:name":"Kaseka",
    "gn:population":0,
    "gn:timezone":"Africa/Lubumbashi",
    "iso:country":"CD",
    "name:und_x_variant":[
        "Kisako",
        "Kaseka"
    ],
    "wof:name":"Kaseka",
    "wof:placetype":"locality"
},
  "geometry": {"coordinates":[23.52123,-7.22769],"type":"Point"}
}