{
  "type": "Feature",
  "properties": {
    "gn:admin1_code":"27.0",
    "gn:asciiname":"Balangaie",
    "gn:country_code":"CD",
    "gn:dem":462,
    "gn:feature_class":"P",
    "gn:feature_code":"PPL",
    "gn:name":"Balangaie",
    "gn:population":0,
    "gn:timezone":"Africa/Lubumbashi",
    "iso:country":"CD",
    "wof:name":"Balangaie",
    "wof:placetype":"locality"
},
  "geometry": {"coordinates":[23.80517,-5.11808],"type":"Point"}
}