{
  "type": "Feature",
  "properties": {
    "gn:admin1_code":"13.0",
    "gn:asciiname":"Nebasa",
    "gn:country_code":"CD",
    "gn:dem":669,
    "gn:feature_class":"P",
    "gn:feature_code":"PPL",
    "gn:name":"Nebasa",
    "gn:population":0,
    "gn:timezone":"Africa/Lubumbashi",
    "iso:country":"CD",
    "wof:name":"Nebasa",
    "wof:placetype":"locality"
},
  "geometry": {"coordinates":[26.32787,3.03803],"type":"Point"}
}