{
  "type": "Feature",
  "properties": {
    "gn:admin1_code":"20.0",
    "gn:asciiname":"Mwela",
    "gn:country_code":"CD",
    "gn:dem":732,
    "gn:feature_class":"P",
    "gn:feature_code":"PPL",
    "gn:name":"Mwela",
    "gn:population":0,
    "gn:timezone":"Africa/Kinshasa",
    "iso:country":"CD",
    "wof:name":"Mwela",
    "wof:placetype":"locality"
},
  "geometry": {"coordinates":[17.61218,-5.38172],"type":"Point"}
}