{
  "type": "Feature",
  "properties": {
    "gn:admin1_code":"12.0",
    "gn:asciiname":"Mwezi",
    "gn:country_code":"CD",
    "gn:dem":982,
    "gn:feature_class":"P",
    "gn:feature_code":"PPL",
    "gn:name":"Mwezi",
    "gn:population":0,
    "gn:timezone":"Africa/Lubumbashi",
    "iso:country":"CD",
    "wof:name":"Mwezi",
    "wof:placetype":"locality"
},
  "geometry": {"coordinates":[29.06669,-3.82745],"type":"Point"}
}