{
  "type": "Feature",
  "properties": {
    "gn:admin1_code":"10.0",
    "gn:asciiname":"Makelele",
    "gn:country_code":"CD",
    "gn:dem":551,
    "gn:feature_class":"P",
    "gn:feature_code":"PPL",
    "gn:name":"Makelele",
    "gn:population":0,
    "gn:timezone":"Africa/Lubumbashi",
    "iso:country":"CD",
    "wof:name":"Makelele",
    "wof:placetype":"locality"
},
  "geometry": {"coordinates":[26.39916,-1.71471],"type":"Point"}
}