{
  "type": "Feature",
  "properties": {
    "gn:admin1_code":"22.0",
    "gn:asciiname":"Samandjata",
    "gn:country_code":"CD",
    "gn:dem":948,
    "gn:feature_class":"P",
    "gn:feature_code":"PPL",
    "gn:name":"Samandjata",
    "gn:population":0,
    "gn:timezone":"Africa/Lubumbashi",
    "iso:country":"CD",
    "wof:name":"Samandjata",
    "wof:placetype":"locality"
},
  "geometry": {"coordinates":[22.7495,-9.62047],"type":"Point"}
}