{
  "type": "Feature",
  "properties": {
    "gn:admin1_code":"18.0",
    "gn:asciiname":"Lukombo Deuxieme",
    "gn:country_code":"CD",
    "gn:dem":588,
    "gn:feature_class":"P",
    "gn:feature_code":"PPL",
    "gn:name":"Lukombo Deuxi\u00e8me",
    "gn:population":0,
    "gn:timezone":"Africa/Lubumbashi",
    "iso:country":"CD",
    "wof:name":"Lukombo Deuxieme",
    "wof:placetype":"locality"
},
  "geometry": {"coordinates":[20.83543,-5.80537],"type":"Point"}
}