{
  "type": "Feature",
  "properties": {
    "gn:admin1_code":"4.0",
    "gn:asciiname":"Bena Kabombo",
    "gn:country_code":"CD",
    "gn:dem":585,
    "gn:feature_class":"P",
    "gn:feature_code":"PPL",
    "gn:name":"Bena Kabombo",
    "gn:population":0,
    "gn:timezone":"Africa/Lubumbashi",
    "iso:country":"CD",
    "wof:name":"Bena Kabombo",
    "wof:placetype":"locality"
},
  "geometry": {"coordinates":[23.62249,-6.12015],"type":"Point"}
}