{
  "type": "Feature",
  "properties": {
    "gn:admin1_code":"24.0",
    "gn:asciiname":"Elali",
    "gn:country_code":"CD",
    "gn:dem":326,
    "gn:feature_class":"P",
    "gn:feature_code":"PPL",
    "gn:name":"Elali",
    "gn:population":0,
    "gn:timezone":"Africa/Kinshasa",
    "iso:country":"CD",
    "wof:name":"Elali",
    "wof:placetype":"locality"
},
  "geometry": {"coordinates":[19.41667,-1.45],"type":"Point"}
}