{
  "type": "Feature",
  "properties": {
    "gn:admin1_code":"0.0",
    "gn:asciiname":"Loadi",
    "gn:cc2":"CD",
    "gn:country_code":"CD",
    "gn:dem":420,
    "gn:feature_class":"P",
    "gn:feature_code":"PPL",
    "gn:name":"Loadi",
    "gn:population":0,
    "gn:timezone":"Africa/Kinshasa",
    "iso:country":"CD",
    "name:und_x_variant":[
        "Luidi",
        "Luadi",
        "Loadi"
    ],
    "wof:name":"Loadi",
    "wof:placetype":"locality"
},
  "geometry": {"coordinates":[13.48333,-5.86667],"type":"Point"}
}