{
  "type": "Feature",
  "properties": {
    "gn:admin1_code":"30.0",
    "gn:asciiname":"Bandjambo",
    "gn:country_code":"CD",
    "gn:dem":468,
    "gn:feature_class":"P",
    "gn:feature_code":"PPL",
    "gn:name":"Bandjambo",
    "gn:population":0,
    "gn:timezone":"Africa/Lubumbashi",
    "iso:country":"CD",
    "wof:name":"Bandjambo",
    "wof:placetype":"locality"
},
  "geometry": {"coordinates":[25.51251,1.24213],"type":"Point"}
}