{
  "type": "Feature",
  "properties": {
    "gn:admin1_code":"11.0",
    "gn:asciiname":"Mesela",
    "gn:country_code":"CD",
    "gn:dem":2018,
    "gn:feature_class":"P",
    "gn:feature_code":"PPL",
    "gn:name":"Mesela",
    "gn:population":0,
    "gn:timezone":"Africa/Lubumbashi",
    "iso:country":"CD",
    "wof:name":"Mesela",
    "wof:placetype":"locality"
},
  "geometry": {"coordinates":[28.96111,-0.37444],"type":"Point"}
}