{
  "type": "Feature",
  "properties": {
    "gn:admin1_code":"25.0",
    "gn:asciiname":"Yalobonga",
    "gn:country_code":"CD",
    "gn:dem":476,
    "gn:feature_class":"P",
    "gn:feature_code":"PPL",
    "gn:name":"Yalobonga",
    "gn:population":0,
    "gn:timezone":"Africa/Kinshasa",
    "iso:country":"CD",
    "wof:name":"Yalobonga",
    "wof:placetype":"locality"
},
  "geometry": {"coordinates":[22.75359,2.72086],"type":"Point"}
}