{
  "type": "Feature",
  "properties": {
    "gn:admin1_code":"16.0",
    "gn:asciiname":"Atoloba",
    "gn:country_code":"CD",
    "gn:dem":685,
    "gn:feature_class":"P",
    "gn:feature_code":"PPL",
    "gn:name":"Atoloba",
    "gn:population":0,
    "gn:timezone":"Africa/Lubumbashi",
    "iso:country":"CD",
    "wof:name":"Atoloba",
    "wof:placetype":"locality"
},
  "geometry": {"coordinates":[27.66557,3.79111],"type":"Point"}
}