{
  "type": "Feature",
  "properties": {
    "gn:admin1_code":"20.0",
    "gn:asciiname":"Shakatwala",
    "gn:country_code":"CD",
    "gn:dem":639,
    "gn:feature_class":"P",
    "gn:feature_code":"PPL",
    "gn:name":"Shakatwala",
    "gn:population":0,
    "gn:timezone":"Africa/Kinshasa",
    "iso:country":"CD",
    "wof:name":"Shakatwala",
    "wof:placetype":"locality"
},
  "geometry": {"coordinates":[19.63189,-6.25422],"type":"Point"}
}