{
  "type": "Feature",
  "properties": {
    "gn:admin1_code":"27.0",
    "gn:asciiname":"Osongo-Djinga",
    "gn:country_code":"CD",
    "gn:dem":546,
    "gn:feature_class":"P",
    "gn:feature_code":"PPL",
    "gn:name":"Osongo-Djinga",
    "gn:population":0,
    "gn:timezone":"Africa/Lubumbashi",
    "iso:country":"CD",
    "name:und_x_variant":[
        "Osonga-Djinga",
        "Osenga Djinga",
        "Osongo-Djinga"
    ],
    "wof:name":"Osongo-Djinga",
    "wof:placetype":"locality"
},
  "geometry": {"coordinates":[24.4466,-3.5816],"type":"Point"}
}