{
  "type": "Feature",
  "properties": {
    "gn:admin1_code":"19.0",
    "gn:asciiname":"Buka-Tsaye",
    "gn:country_code":"CD",
    "gn:dem":790,
    "gn:feature_class":"P",
    "gn:feature_code":"PPL",
    "gn:name":"Buka-Tsaye",
    "gn:population":0,
    "gn:timezone":"Africa/Kinshasa",
    "iso:country":"CD",
    "wof:name":"Buka-Tsaye",
    "wof:placetype":"locality"
},
  "geometry": {"coordinates":[17.74021,-6.28335],"type":"Point"}
}