{
  "type": "Feature",
  "properties": {
    "gn:admin1_code":"10.0",
    "gn:asciiname":"Kalongosola",
    "gn:country_code":"CD",
    "gn:dem":570,
    "gn:feature_class":"P",
    "gn:feature_code":"PPL",
    "gn:name":"Kalongosola",
    "gn:population":0,
    "gn:timezone":"Africa/Lubumbashi",
    "iso:country":"CD",
    "wof:name":"Kalongosola",
    "wof:placetype":"locality"
},
  "geometry": {"coordinates":[26.35765,-4.07981],"type":"Point"}
}