{
  "type": "Feature",
  "properties": {
    "gn:admin1_code":"20.0",
    "gn:asciiname":"Kisala",
    "gn:country_code":"CD",
    "gn:dem":729,
    "gn:feature_class":"P",
    "gn:feature_code":"PPL",
    "gn:name":"Kisala",
    "gn:population":0,
    "gn:timezone":"Africa/Kinshasa",
    "iso:country":"CD",
    "wof:name":"Kisala",
    "wof:placetype":"locality"
},
  "geometry": {"coordinates":[18.18535,-5.65856],"type":"Point"}
}