{
  "type": "Feature",
  "properties": {
    "gn:admin1_code":"26.0",
    "gn:asciiname":"Monzanga",
    "gn:country_code":"CD",
    "gn:dem":424,
    "gn:feature_class":"P",
    "gn:feature_code":"PPL",
    "gn:name":"Monzanga",
    "gn:population":0,
    "gn:timezone":"Africa/Kinshasa",
    "iso:country":"CD",
    "wof:name":"Monzanga",
    "wof:placetype":"locality"
},
  "geometry": {"coordinates":[22.03026,3.73697],"type":"Point"}
}