{
  "type": "Feature",
  "properties": {
    "gn:admin1_code":"12.0",
    "gn:asciiname":"Kitibingi",
    "gn:country_code":"CD",
    "gn:dem":1313,
    "gn:feature_class":"P",
    "gn:feature_code":"PPL",
    "gn:name":"Kitibingi",
    "gn:population":0,
    "gn:timezone":"Africa/Lubumbashi",
    "iso:country":"CD",
    "wof:name":"Kitibingi",
    "wof:placetype":"locality"
},
  "geometry": {"coordinates":[28.46667,-3.46667],"type":"Point"}
}