{
  "type": "Feature",
  "properties": {
    "gn:admin1_code":"20.0",
    "gn:asciiname":"Imbasi",
    "gn:country_code":"CD",
    "gn:dem":706,
    "gn:feature_class":"P",
    "gn:feature_code":"PPL",
    "gn:name":"Imbasi",
    "gn:population":0,
    "gn:timezone":"Africa/Kinshasa",
    "iso:country":"CD",
    "wof:name":"Imbasi",
    "wof:placetype":"locality"
},
  "geometry": {"coordinates":[19.75496,-5.33291],"type":"Point"}
}