{
  "type": "Feature",
  "properties": {
    "gn:admin1_code":"22.0",
    "gn:asciiname":"Kasanda",
    "gn:country_code":"CD",
    "gn:dem":1064,
    "gn:feature_class":"P",
    "gn:feature_code":"PPL",
    "gn:name":"Kasanda",
    "gn:population":0,
    "gn:timezone":"Africa/Lubumbashi",
    "iso:country":"CD",
    "name:und_x_variant":[
        "Kasonda"
    ],
    "wof:name":"Kasanda",
    "wof:placetype":"locality"
},
  "geometry": {"coordinates":[24.53852,-10.30209],"type":"Point"}
}