{
  "type": "Feature",
  "properties": {
    "gn:admin1_code":"2.0",
    "gn:asciiname":"Itoma",
    "gn:country_code":"CD",
    "gn:dem":343,
    "gn:feature_class":"P",
    "gn:feature_code":"PPL",
    "gn:name":"Itoma",
    "gn:population":0,
    "gn:timezone":"Africa/Kinshasa",
    "iso:country":"CD",
    "wof:name":"Itoma",
    "wof:placetype":"locality"
},
  "geometry": {"coordinates":[18.25,1.78333],"type":"Point"}
}