{
  "type": "Feature",
  "properties": {
    "gn:admin1_code":"28.0",
    "gn:asciiname":"Mobambo",
    "gn:country_code":"CD",
    "gn:dem":337,
    "gn:feature_class":"P",
    "gn:feature_code":"PPL",
    "gn:name":"Mobambo",
    "gn:population":0,
    "gn:timezone":"Africa/Kinshasa",
    "iso:country":"CD",
    "wof:name":"Mobambo",
    "wof:placetype":"locality"
},
  "geometry": {"coordinates":[18.23138,2.40013],"type":"Point"}
}