{
  "type": "Feature",
  "properties": {
    "gn:admin1_code":"15.0",
    "gn:asciiname":"Mako",
    "gn:country_code":"CD",
    "gn:dem":898,
    "gn:feature_class":"P",
    "gn:feature_code":"PPL",
    "gn:name":"Mako",
    "gn:population":0,
    "gn:timezone":"Africa/Lubumbashi",
    "iso:country":"CD",
    "name:ceb_x_preferred":[
        "Mako"
    ],
    "name:ces_x_preferred":[
        "Mako"
    ],
    "name:deu_x_preferred":[
        "Mako"
    ],
    "name:epo_x_preferred":[
        "Mako"
    ],
    "name:fin_x_preferred":[
        "Mako"
    ],
    "name:fra_x_preferred":[
        "Mako"
    ],
    "name:heb_x_preferred":[
        "\u05de\u05d0\u05e7\u05d5"
    ],
    "name:ita_x_preferred":[
        "Mako"
    ],
    "name:kaz_x_preferred":[
        "\u041c\u0430\u043a\u043e"
    ],
    "name:nld_x_preferred":[
        "Mako"
    ],
    "name:nor_x_preferred":[
        "Mako"
    ],
    "name:pol_x_preferred":[
        "Mako"
    ],
    "name:rus_x_preferred":[
        "\u041c\u0430\u043a\u043e"
    ],
    "name:slk_x_preferred":[
        "Mako"
    ],
    "name:spa_x_preferred":[
        "Mako"
    ],
    "name:swe_x_preferred":[
        "Mako"
    ],
    "name:tgl_x_preferred":[
        "Mako"
    ],
    "name:ukr_x_preferred":[
        "\u041c\u0430\u043a\u043e"
    ],
    "wof:name":"Mako",
    "wof:placetype":"locality"
},
  "geometry": {"coordinates":[25.30715,-7.23678],"type":"Point"}
}