{
  "type": "Feature",
  "properties": {
    "gn:admin1_code":"15.0",
    "gn:asciiname":"Mako",
    "gn:country_code":"CD",
    "gn:dem":898,
    "gn:feature_class":"P",
    "gn:feature_code":"PPL",
    "gn:name":"Mako",
    "gn:population":0,
    "gn:timezone":"Africa/Lubumbashi",
    "iso:country":"CD",
    "wof:name":"Mako",
    "wof:placetype":"locality"
},
  "geometry": {"coordinates":[25.30715,-7.23678],"type":"Point"}
}