{
  "type": "Feature",
  "properties": {
    "gn:admin1_code":"8.0",
    "gn:asciiname":"Sengesi",
    "gn:country_code":"CD",
    "gn:dem":452,
    "gn:feature_class":"P",
    "gn:feature_code":"PPL",
    "gn:name":"Sengesi",
    "gn:population":0,
    "gn:timezone":"Africa/Kinshasa",
    "iso:country":"CD",
    "wof:name":"Sengesi",
    "wof:placetype":"locality"
},
  "geometry": {"coordinates":[14.71713,-5.20025],"type":"Point"}
}