{
  "type": "Feature",
  "properties": {
    "gn:admin1_code":"16.0",
    "gn:asciiname":"Kesibu",
    "gn:country_code":"CD",
    "gn:dem":666,
    "gn:feature_class":"P",
    "gn:feature_code":"PPL",
    "gn:name":"Kesibu",
    "gn:population":0,
    "gn:timezone":"Africa/Lubumbashi",
    "iso:country":"CD",
    "wof:name":"Kesibu",
    "wof:placetype":"locality"
},
  "geometry": {"coordinates":[27.46833,3.66193],"type":"Point"}
}