{
  "type": "Feature",
  "properties": {
    "gn:admin1_code":"30.0",
    "gn:asciiname":"Yatunda",
    "gn:country_code":"CD",
    "gn:dem":499,
    "gn:feature_class":"P",
    "gn:feature_code":"PPL",
    "gn:name":"Yatunda",
    "gn:population":0,
    "gn:timezone":"Africa/Lubumbashi",
    "iso:country":"CD",
    "name:und_x_variant":[
        "Yatonda",
        "Yatunda"
    ],
    "wof:name":"Yatunda",
    "wof:placetype":"locality"
},
  "geometry": {"coordinates":[23.31667,0.98333],"type":"Point"}
}