{
  "type": "Feature",
  "properties": {
    "gn:admin1_code":"10.0",
    "gn:asciiname":"Tabora",
    "gn:country_code":"CD",
    "gn:dem":513,
    "gn:feature_class":"P",
    "gn:feature_code":"PPL",
    "gn:name":"Tabora",
    "gn:population":0,
    "gn:timezone":"Africa/Lubumbashi",
    "iso:country":"CD",
    "name:ara_x_preferred":[
        "\u062a\u0627\u0628\u0648\u0631\u0627"
    ],
    "name:azb_x_preferred":[
        "\u062a\u0627\u0628\u0648\u0631\u0627"
    ],
    "name:bel_x_preferred":[
        "\u0422\u0430\u0431\u043e\u0440\u0430"
    ],
    "name:bul_x_preferred":[
        "\u0422\u0430\u0431\u043e\u0440\u0430"
    ],
    "name:cat_x_preferred":[
        "Tabora"
    ],
    "name:ceb_x_preferred":[
        "Tabora"
    ],
    "name:dan_x_preferred":[
        "Tabora"
    ],
    "name:deu_x_preferred":[
        "Tabora"
    ],
    "name:ell_x_preferred":[
        "\u03a4\u03b1\u03bc\u03c0\u03cc\u03c1\u03b1"
    ],
    "name:epo_x_preferred":[
        "Tabora"
    ],
    "name:fas_x_preferred":[
        "\u062a\u0627\u0628\u0648\u0631\u0627"
    ],
    "name:fin_x_preferred":[
        "Tabora"
    ],
    "name:fra_x_preferred":[
        "Tabora"
    ],
    "name:heb_x_preferred":[
        "\u05d8\u05d1\u05d5\u05e8\u05d4"
    ],
    "name:hrv_x_preferred":[
        "Tabora"
    ],
    "name:hun_x_preferred":[
        "Tabora"
    ],
    "name:ita_x_preferred":[
        "Tabora"
    ],
    "name:jpn_x_preferred":[
        "\u30bf\u30dc\u30e9"
    ],
    "name:kor_x_preferred":[
        "\ud0c0\ubcf4\ub77c"
    ],
    "name:lit_x_preferred":[
        "Tabora"
    ],
    "name:nld_x_preferred":[
        "Tabora"
    ],
    "name:nor_x_preferred":[
        "Tabora"
    ],
    "name:pol_x_preferred":[
        "Tabora"
    ],
    "name:por_x_preferred":[
        "Tabora"
    ],
    "name:ron_x_preferred":[
        "Tabora"
    ],
    "name:rus_x_preferred":[
        "\u0422\u0430\u0431\u043e\u0440\u0430"
    ],
    "name:spa_x_preferred":[
        "Tabora"
    ],
    "name:swa_x_preferred":[
        "Tabora"
    ],
    "name:swe_x_preferred":[
        "Tabora"
    ],
    "name:tur_x_preferred":[
        "Tabora"
    ],
    "name:ukr_x_preferred":[
        "\u0422\u0430\u0431\u043e\u0440\u0430"
    ],
    "name:urd_x_preferred":[
        "\u062a\u0627\u0628\u0648\u0631\u0627"
    ],
    "name:yor_x_preferred":[
        "Tabora"
    ],
    "name:zho_x_preferred":[
        "\u5854\u6ce2\u62c9"
    ],
    "wof:name":"Tabora",
    "wof:placetype":"locality"
},
  "geometry": {"coordinates":[25.78333,-2.25],"type":"Point"}
}