{
  "type": "Feature",
  "properties": {
    "gn:admin1_code":"10.0",
    "gn:asciiname":"Tabora",
    "gn:country_code":"CD",
    "gn:dem":513,
    "gn:feature_class":"P",
    "gn:feature_code":"PPL",
    "gn:name":"Tabora",
    "gn:population":0,
    "gn:timezone":"Africa/Lubumbashi",
    "iso:country":"CD",
    "wof:name":"Tabora",
    "wof:placetype":"locality"
},
  "geometry": {"coordinates":[25.78333,-2.25],"type":"Point"}
}