{
  "type": "Feature",
  "properties": {
    "gn:admin1_code":"30.0",
    "gn:asciiname":"Bafwangele",
    "gn:country_code":"CD",
    "gn:dem":551,
    "gn:feature_class":"P",
    "gn:feature_code":"PPL",
    "gn:name":"Bafwangele",
    "gn:population":0,
    "gn:timezone":"Africa/Lubumbashi",
    "iso:country":"CD",
    "wof:name":"Bafwangele",
    "wof:placetype":"locality"
},
  "geometry": {"coordinates":[26.7754,1.92552],"type":"Point"}
}