{
  "type": "Feature",
  "properties": {
    "gn:admin1_code":"8.0",
    "gn:asciiname":"Banza",
    "gn:country_code":"CD",
    "gn:dem":469,
    "gn:feature_class":"P",
    "gn:feature_code":"PPL",
    "gn:name":"Banza",
    "gn:population":0,
    "gn:timezone":"Africa/Kinshasa",
    "iso:country":"CD",
    "wof:name":"Banza",
    "wof:placetype":"locality"
},
  "geometry": {"coordinates":[14.92641,-4.71061],"type":"Point"}
}