{
  "type": "Feature",
  "properties": {
    "gn:admin1_code":"12.0",
    "gn:asciiname":"Isasa",
    "gn:country_code":"CD",
    "gn:dem":784,
    "gn:feature_class":"P",
    "gn:feature_code":"PPL",
    "gn:name":"Isasa",
    "gn:population":0,
    "gn:timezone":"Africa/Lubumbashi",
    "iso:country":"CD",
    "wof:name":"Isasa",
    "wof:placetype":"locality"
},
  "geometry": {"coordinates":[28.18668,-3.10405],"type":"Point"}
}