{
  "type": "Feature",
  "properties": {
    "gn:admin1_code":"8.0",
    "gn:asciiname":"Vizi",
    "gn:country_code":"CD",
    "gn:dem":223,
    "gn:feature_class":"P",
    "gn:feature_code":"PPL",
    "gn:name":"Vizi",
    "gn:population":0,
    "gn:timezone":"Africa/Kinshasa",
    "iso:country":"CD",
    "wof:name":"Vizi",
    "wof:placetype":"locality"
},
  "geometry": {"coordinates":[13.81418,-5.27898],"type":"Point"}
}