{
  "type": "Feature",
  "properties": {
    "gn:admin1_code":"10.0",
    "gn:asciiname":"Likulu",
    "gn:country_code":"CD",
    "gn:dem":610,
    "gn:feature_class":"P",
    "gn:feature_code":"PPL",
    "gn:name":"Likulu",
    "gn:population":0,
    "gn:timezone":"Africa/Lubumbashi",
    "iso:country":"CD",
    "wof:name":"Likulu",
    "wof:placetype":"locality"
},
  "geometry": {"coordinates":[26.624,-2.7731],"type":"Point"}
}