{
  "type": "Feature",
  "properties": {
    "gn:admin1_code":"22.0",
    "gn:asciiname":"Mbangalala",
    "gn:country_code":"CD",
    "gn:dem":1069,
    "gn:feature_class":"P",
    "gn:feature_code":"PPL",
    "gn:name":"Mbangalala",
    "gn:population":0,
    "gn:timezone":"Africa/Lubumbashi",
    "iso:country":"CD",
    "name:und_x_variant":[
        "Bangalala"
    ],
    "wof:name":"Mbangalala",
    "wof:placetype":"locality"
},
  "geometry": {"coordinates":[22.35952,-9.90505],"type":"Point"}
}