{
  "type": "Feature",
  "properties": {
    "gn:admin1_code":"8.0",
    "gn:asciiname":"Kinkuanga Deuxieme",
    "gn:country_code":"CD",
    "gn:dem":878,
    "gn:feature_class":"P",
    "gn:feature_code":"PPL",
    "gn:name":"Kinkuanga Deuxi\u00e8me",
    "gn:population":0,
    "gn:timezone":"Africa/Kinshasa",
    "iso:country":"CD",
    "wof:name":"Kinkuanga Deuxieme",
    "wof:placetype":"locality"
},
  "geometry": {"coordinates":[16.08495,-5.65998],"type":"Point"}
}