{
  "type": "Feature",
  "properties": {
    "gn:admin1_code":"23.0",
    "gn:asciiname":"Tshibuba",
    "gn:country_code":"CD",
    "gn:dem":864,
    "gn:feature_class":"P",
    "gn:feature_code":"PPL",
    "gn:name":"Tshibuba",
    "gn:population":0,
    "gn:timezone":"Africa/Lubumbashi",
    "iso:country":"CD",
    "wof:name":"Tshibuba",
    "wof:placetype":"locality"
},
  "geometry": {"coordinates":[22.71276,-6.63028],"type":"Point"}
}