{
  "type": "Feature",
  "properties": {
    "gn:admin1_code":"21.0",
    "gn:asciiname":"Piani Gongo",
    "gn:country_code":"CD",
    "gn:dem":676,
    "gn:feature_class":"P",
    "gn:feature_code":"PPL",
    "gn:name":"Piani Gongo",
    "gn:population":0,
    "gn:timezone":"Africa/Lubumbashi",
    "iso:country":"CD",
    "wof:name":"Piani Gongo",
    "wof:placetype":"locality"
},
  "geometry": {"coordinates":[25.16667,-5.85],"type":"Point"}
}