{
  "type": "Feature",
  "properties": {
    "gn:admin1_code":"19.0",
    "gn:asciiname":"Kabokalanda",
    "gn:country_code":"CD",
    "gn:dem":982,
    "gn:feature_class":"P",
    "gn:feature_code":"PPL",
    "gn:name":"Kabokalanda",
    "gn:population":0,
    "gn:timezone":"Africa/Kinshasa",
    "iso:country":"CD",
    "wof:name":"Kabokalanda",
    "wof:placetype":"locality"
},
  "geometry": {"coordinates":[18.48171,-7.94651],"type":"Point"}
}