{
  "type": "Feature",
  "properties": {
    "gn:admin1_code":"20.0",
    "gn:asciiname":"Ndundu",
    "gn:country_code":"CD",
    "gn:dem":739,
    "gn:feature_class":"P",
    "gn:feature_code":"PPL",
    "gn:name":"Ndundu",
    "gn:population":0,
    "gn:timezone":"Africa/Kinshasa",
    "iso:country":"CD",
    "wof:name":"Ndundu",
    "wof:placetype":"locality"
},
  "geometry": {"coordinates":[19.32498,-5.56076],"type":"Point"}
}