{
  "type": "Feature",
  "properties": {
    "gn:admin1_code":"23.0",
    "gn:asciiname":"Nzuji-Kalamba",
    "gn:country_code":"CD",
    "gn:dem":776,
    "gn:feature_class":"P",
    "gn:feature_code":"PPL",
    "gn:name":"Nzuji-Kalamba",
    "gn:population":0,
    "gn:timezone":"Africa/Lubumbashi",
    "iso:country":"CD",
    "name:und_x_variant":[
        "Kalamba",
        "Nsuji-Kalamba",
        "Nzuji-Kalamba"
    ],
    "wof:name":"Nzuji-Kalamba",
    "wof:placetype":"locality"
},
  "geometry": {"coordinates":[22.20815,-6.43856],"type":"Point"}
}