{
  "type": "Feature",
  "properties": {
    "gn:admin1_code":"13.0",
    "gn:asciiname":"Edale",
    "gn:country_code":"CD",
    "gn:dem":450,
    "gn:feature_class":"P",
    "gn:feature_code":"PPL",
    "gn:name":"Edale",
    "gn:population":0,
    "gn:timezone":"Africa/Lubumbashi",
    "iso:country":"CD",
    "wof:name":"Edale",
    "wof:placetype":"locality"
},
  "geometry": {"coordinates":[23.51028,2.99098],"type":"Point"}
}