{
  "type": "Feature",
  "properties": {
    "gn:admin1_code":"13.0",
    "gn:asciiname":"Edale",
    "gn:country_code":"CD",
    "gn:dem":450,
    "gn:feature_class":"P",
    "gn:feature_code":"PPL",
    "gn:name":"Edale",
    "gn:population":0,
    "gn:timezone":"Africa/Lubumbashi",
    "iso:country":"CD",
    "name:ceb_x_preferred":[
        "Edale"
    ],
    "name:cym_x_preferred":[
        "Edale"
    ],
    "name:dan_x_preferred":[
        "Edale"
    ],
    "name:fas_x_preferred":[
        "\u0627\u062f\u06cc\u0644"
    ],
    "name:ita_x_preferred":[
        "Edale"
    ],
    "name:nld_x_preferred":[
        "Edale"
    ],
    "name:pol_x_preferred":[
        "Edale"
    ],
    "name:swe_x_preferred":[
        "Edale"
    ],
    "wof:name":"Edale",
    "wof:placetype":"locality"
},
  "geometry": {"coordinates":[23.51028,2.99098],"type":"Point"}
}