{
  "type": "Feature",
  "properties": {
    "gn:admin1_code":"23.0",
    "gn:asciiname":"Tshimea-Kabata",
    "gn:country_code":"CD",
    "gn:dem":792,
    "gn:feature_class":"P",
    "gn:feature_code":"PPL",
    "gn:name":"Tshimea-Kabata",
    "gn:population":0,
    "gn:timezone":"Africa/Lubumbashi",
    "iso:country":"CD",
    "wof:name":"Tshimea-Kabata",
    "wof:placetype":"locality"
},
  "geometry": {"coordinates":[22.90586,-6.07745],"type":"Point"}
}