{
  "type": "Feature",
  "properties": {
    "gn:admin1_code":"28.0",
    "gn:asciiname":"Tulu",
    "gn:country_code":"CD",
    "gn:dem":445,
    "gn:feature_class":"P",
    "gn:feature_code":"PPL",
    "gn:name":"Tulu",
    "gn:population":0,
    "gn:timezone":"Africa/Kinshasa",
    "iso:country":"CD",
    "name:ceb_x_preferred":[
        "Tulu"
    ],
    "name:deu_x_preferred":[
        "Tulu"
    ],
    "name:fra_x_preferred":[
        "Tulu"
    ],
    "name:rus_x_preferred":[
        "\u0422\u0443\u043b\u0443"
    ],
    "name:swe_x_preferred":[
        "Tulu"
    ],
    "wof:name":"Tulu",
    "wof:placetype":"locality"
},
  "geometry": {"coordinates":[19.75249,2.71222],"type":"Point"}
}