{
  "type": "Feature",
  "properties": {
    "gn:admin1_code":"20.0",
    "gn:asciiname":"Impashi Bulu",
    "gn:country_code":"CD",
    "gn:dem":667,
    "gn:feature_class":"P",
    "gn:feature_code":"PPL",
    "gn:name":"Impashi Bulu",
    "gn:population":0,
    "gn:timezone":"Africa/Kinshasa",
    "iso:country":"CD",
    "name:und_x_variant":[
        "Impashi",
        "Impashi Bulu"
    ],
    "wof:name":"Impashi Bulu",
    "wof:placetype":"locality"
},
  "geometry": {"coordinates":[19.55323,-4.80832],"type":"Point"}
}