{
  "type": "Feature",
  "properties": {
    "gn:admin1_code":"21.0",
    "gn:asciiname":"Makasa",
    "gn:country_code":"CD",
    "gn:dem":835,
    "gn:feature_class":"P",
    "gn:feature_code":"PPL",
    "gn:name":"Makasa",
    "gn:population":0,
    "gn:timezone":"Africa/Lubumbashi",
    "iso:country":"CD",
    "wof:name":"Makasa",
    "wof:placetype":"locality"
},
  "geometry": {"coordinates":[23.63278,-7.11208],"type":"Point"}
}