{
  "type": "Feature",
  "properties": {
    "gn:admin1_code":"22.0",
    "gn:asciiname":"Welenioka",
    "gn:country_code":"CD",
    "gn:dem":749,
    "gn:feature_class":"P",
    "gn:feature_code":"PPL",
    "gn:name":"Welenioka",
    "gn:population":0,
    "gn:timezone":"Africa/Lubumbashi",
    "iso:country":"CD",
    "wof:name":"Welenioka",
    "wof:placetype":"locality"
},
  "geometry": {"coordinates":[25.62861,-9.70173],"type":"Point"}
}