{
  "type": "Feature",
  "properties": {
    "gn:admin1_code":"18.0",
    "gn:asciiname":"Saku",
    "gn:country_code":"CD",
    "gn:dem":722,
    "gn:feature_class":"P",
    "gn:feature_code":"PPL",
    "gn:name":"Saku",
    "gn:population":0,
    "gn:timezone":"Africa/Lubumbashi",
    "iso:country":"CD",
    "name:ceb_x_preferred":[
        "Saku"
    ],
    "name:ces_x_preferred":[
        "Saku"
    ],
    "name:deu_x_preferred":[
        "Saku"
    ],
    "name:fin_x_preferred":[
        "Saku"
    ],
    "name:fra_x_preferred":[
        "Saku"
    ],
    "name:hye_x_preferred":[
        "\u054d\u0561\u056f\u0578\u0582"
    ],
    "name:ita_x_preferred":[
        "Saku"
    ],
    "name:jpn_x_preferred":[
        "Saku"
    ],
    "name:mlg_x_preferred":[
        "Saku"
    ],
    "name:nld_x_preferred":[
        "Saku"
    ],
    "name:pol_x_preferred":[
        "Saku"
    ],
    "name:por_x_preferred":[
        "Saku"
    ],
    "name:ron_x_preferred":[
        "Saku"
    ],
    "name:rus_x_preferred":[
        "\u0421\u0430\u043a\u0443"
    ],
    "name:sco_x_preferred":[
        "Saku"
    ],
    "name:spa_x_preferred":[
        "Saku"
    ],
    "name:swe_x_preferred":[
        "Saku"
    ],
    "name:ukr_x_preferred":[
        "\u0421\u0430\u043a\u0443"
    ],
    "wof:name":"Saku",
    "wof:placetype":"locality"
},
  "geometry": {"coordinates":[19.91844,-6.5453],"type":"Point"}
}