{
  "type": "Feature",
  "properties": {
    "gn:admin1_code":"18.0",
    "gn:asciiname":"Lukuye",
    "gn:country_code":"CD",
    "gn:dem":573,
    "gn:feature_class":"P",
    "gn:feature_code":"PPL",
    "gn:name":"Lukuye",
    "gn:population":0,
    "gn:timezone":"Africa/Lubumbashi",
    "iso:country":"CD",
    "wof:name":"Lukuye",
    "wof:placetype":"locality"
},
  "geometry": {"coordinates":[21.07549,-5.44957],"type":"Point"}
}