{
  "type": "Feature",
  "properties": {
    "gn:admin1_code":"19.0",
    "gn:asciiname":"Kipumba",
    "gn:country_code":"CD",
    "gn:dem":1028,
    "gn:feature_class":"P",
    "gn:feature_code":"PPL",
    "gn:name":"Kipumba",
    "gn:population":0,
    "gn:timezone":"Africa/Kinshasa",
    "iso:country":"CD",
    "wof:name":"Kipumba",
    "wof:placetype":"locality"
},
  "geometry": {"coordinates":[18.48337,-7.18296],"type":"Point"}
}