{
  "type": "Feature",
  "properties": {
    "gn:admin1_code":"30.0",
    "gn:asciiname":"Dayuma",
    "gn:country_code":"CD",
    "gn:dem":517,
    "gn:feature_class":"P",
    "gn:feature_code":"PPL",
    "gn:name":"Dayuma",
    "gn:population":0,
    "gn:timezone":"Africa/Lubumbashi",
    "iso:country":"CD",
    "wof:name":"Dayuma",
    "wof:placetype":"locality"
},
  "geometry": {"coordinates":[26.36667000000001,0.48333],"type":"Point"}
}