{
  "type": "Feature",
  "properties": {
    "gn:admin1_code":"22.0",
    "gn:asciiname":"Musansya",
    "gn:country_code":"CD",
    "gn:dem":936,
    "gn:feature_class":"P",
    "gn:feature_code":"PPL",
    "gn:name":"Musansya",
    "gn:population":0,
    "gn:timezone":"Africa/Lubumbashi",
    "iso:country":"CD",
    "wof:name":"Musansya",
    "wof:placetype":"locality"
},
  "geometry": {"coordinates":[27.04355,-10.35805],"type":"Point"}
}