{
  "type": "Feature",
  "properties": {
    "gn:admin1_code":"21.0",
    "gn:asciiname":"Tshilondo",
    "gn:country_code":"CD",
    "gn:dem":866,
    "gn:feature_class":"P",
    "gn:feature_code":"PPL",
    "gn:name":"Tshilondo",
    "gn:population":0,
    "gn:timezone":"Africa/Lubumbashi",
    "iso:country":"CD",
    "name:und_x_variant":[
        "Tshibondo"
    ],
    "wof:name":"Tshilondo",
    "wof:placetype":"locality"
},
  "geometry": {"coordinates":[23.54686,-7.25287],"type":"Point"}
}