{
  "type": "Feature",
  "properties": {
    "gn:admin1_code":"8.0",
    "gn:asciiname":"Kanka",
    "gn:country_code":"CD",
    "gn:dem":528,
    "gn:feature_class":"P",
    "gn:feature_code":"PPL",
    "gn:name":"Kanka",
    "gn:population":0,
    "gn:timezone":"Africa/Kinshasa",
    "iso:country":"CD",
    "name:ceb_x_preferred":[
        "Kanka"
    ],
    "name:ces_x_preferred":[
        "Ka\u0148ka"
    ],
    "name:deu_x_preferred":[
        "Kanka"
    ],
    "name:fra_x_preferred":[
        "Kanka"
    ],
    "name:swe_x_preferred":[
        "Kanka"
    ],
    "wof:name":"Kanka",
    "wof:placetype":"locality"
},
  "geometry": {"coordinates":[14.9527,-4.9907],"type":"Point"}
}