{
  "type": "Feature",
  "properties": {
    "gn:admin1_code":"13.0",
    "gn:asciiname":"Mangiembo",
    "gn:country_code":"CD",
    "gn:dem":678,
    "gn:feature_class":"P",
    "gn:feature_code":"PPL",
    "gn:name":"Mangiembo",
    "gn:population":0,
    "gn:timezone":"Africa/Lubumbashi",
    "iso:country":"CD",
    "wof:name":"Mangiembo",
    "wof:placetype":"locality"
},
  "geometry": {"coordinates":[26.97245,3.50705],"type":"Point"}
}