{
  "type": "Feature",
  "properties": {
    "gn:admin1_code":"19.0",
    "gn:asciiname":"Kasandzi",
    "gn:country_code":"CD",
    "gn:dem":434,
    "gn:feature_class":"P",
    "gn:feature_code":"PPL",
    "gn:name":"Kasandzi",
    "gn:population":0,
    "gn:timezone":"Africa/Kinshasa",
    "iso:country":"CD",
    "wof:name":"Kasandzi",
    "wof:placetype":"locality"
},
  "geometry": {"coordinates":[17.46244,-5.05103],"type":"Point"}
}