{
  "type": "Feature",
  "properties": {
    "gn:admin1_code":"29.0",
    "gn:asciiname":"Malwa",
    "gn:country_code":"CD",
    "gn:dem":737,
    "gn:feature_class":"P",
    "gn:feature_code":"PPL",
    "gn:name":"Malwa",
    "gn:population":0,
    "gn:timezone":"Africa/Lubumbashi",
    "iso:country":"CD",
    "name:ara_x_preferred":[
        "\u0645\u0627\u0644\u0648\u0627"
    ],
    "name:ben_x_preferred":[
        "\u09ae\u09be\u09b2\u09ac\u09c7"
    ],
    "name:cat_x_preferred":[
        "Malwa"
    ],
    "name:ces_x_preferred":[
        "M\u00e1lva"
    ],
    "name:deu_x_preferred":[
        "Malwa"
    ],
    "name:eus_x_preferred":[
        "Malwa"
    ],
    "name:fin_x_preferred":[
        "Malwa"
    ],
    "name:fra_x_preferred":[
        "Malva"
    ],
    "name:hin_x_preferred":[
        "\u092e\u093e\u0932\u0935\u093e"
    ],
    "name:ind_x_preferred":[
        "Malwa"
    ],
    "name:ita_x_preferred":[
        "Malwa"
    ],
    "name:jpn_x_preferred":[
        "\u30de\u30fc\u30eb\u30ef\u30fc"
    ],
    "name:mar_x_preferred":[
        "\u092e\u093e\u0933\u0935\u093e"
    ],
    "name:nld_x_preferred":[
        "Malwa"
    ],
    "name:pan_x_preferred":[
        "\u0a2e\u0a3e\u0a32\u0a35\u0a3e"
    ],
    "name:rus_x_preferred":[
        "\u041c\u0430\u043b\u0432\u0430"
    ],
    "name:san_x_preferred":[
        "\u092e\u093e\u0932\u0935\u093e"
    ],
    "name:spa_x_preferred":[
        "Malwa"
    ],
    "name:swe_x_preferred":[
        "Malwa"
    ],
    "name:tam_x_preferred":[
        "\u0bae\u0bbe\u0bb2\u0bcd\u0bb5\u0bbe"
    ],
    "name:ukr_x_preferred":[
        "\u041c\u0430\u043b\u0430\u0432\u0430"
    ],
    "name:urd_x_preferred":[
        "\u0645\u0627\u0644\u0648\u06c1"
    ],
    "name:zho_x_preferred":[
        "\u6469\u814a\u5a46"
    ],
    "wof:name":"Malwa",
    "wof:placetype":"locality"
},
  "geometry": {"coordinates":[27.46667,-5.93333],"type":"Point"}
}