{
  "type": "Feature",
  "properties": {
    "gn:admin1_code":"16.0",
    "gn:asciiname":"Kurukwata",
    "gn:country_code":"CD",
    "gn:dem":849,
    "gn:feature_class":"P",
    "gn:feature_code":"PPL",
    "gn:name":"Kurukwata",
    "gn:population":0,
    "gn:timezone":"Africa/Lubumbashi",
    "iso:country":"CD",
    "wof:name":"Kurukwata",
    "wof:placetype":"locality"
},
  "geometry": {"coordinates":[30.04589,3.84877],"type":"Point"}
}