{
  "type": "Feature",
  "properties": {
    "gn:admin1_code":"27.0",
    "gn:asciiname":"Ematela",
    "gn:country_code":"CD",
    "gn:dem":481,
    "gn:feature_class":"P",
    "gn:feature_code":"PPL",
    "gn:name":"Ematela",
    "gn:population":0,
    "gn:timezone":"Africa/Lubumbashi",
    "iso:country":"CD",
    "wof:name":"Ematela",
    "wof:placetype":"locality"
},
  "geometry": {"coordinates":[22.56667,-2.48333],"type":"Point"}
}