{
  "type": "Feature",
  "properties": {
    "gn:admin1_code":"27.0",
    "gn:asciiname":"Dihuka",
    "gn:country_code":"CD",
    "gn:dem":671,
    "gn:feature_class":"P",
    "gn:feature_code":"PPL",
    "gn:name":"Dihuka",
    "gn:population":0,
    "gn:timezone":"Africa/Lubumbashi",
    "iso:country":"CD",
    "name:und_x_variant":[
        "Dikuka"
    ],
    "wof:name":"Dihuka",
    "wof:placetype":"locality"
},
  "geometry": {"coordinates":[24.5242,-4.61612],"type":"Point"}
}