{
  "type": "Feature",
  "properties": {
    "gn:admin1_code":"14.0",
    "gn:asciiname":"Tenki",
    "gn:country_code":"CD",
    "gn:dem":1205,
    "gn:feature_class":"P",
    "gn:feature_code":"PPL",
    "gn:name":"Tenki",
    "gn:population":0,
    "gn:timezone":"Africa/Lubumbashi",
    "iso:country":"CD",
    "name:und_x_variant":[
        "Tenke"
    ],
    "wof:name":"Tenki",
    "wof:placetype":"locality"
},
  "geometry": {"coordinates":[26.7619,-11.36051],"type":"Point"}
}