{
  "type": "Feature",
  "properties": {
    "gn:admin1_code":"16.0",
    "gn:asciiname":"Aluadu",
    "gn:country_code":"CD",
    "gn:dem":1203,
    "gn:feature_class":"P",
    "gn:feature_code":"PPL",
    "gn:name":"Aluadu",
    "gn:population":0,
    "gn:timezone":"Africa/Lubumbashi",
    "iso:country":"CD",
    "wof:name":"Aluadu",
    "wof:placetype":"locality"
},
  "geometry": {"coordinates":[29.81741,2.69213],"type":"Point"}
}