{
  "type": "Feature",
  "properties": {
    "gn:admin1_code":"23.0",
    "gn:asciiname":"Kabuanga",
    "gn:country_code":"CD",
    "gn:dem":874,
    "gn:feature_class":"P",
    "gn:feature_code":"PPL",
    "gn:name":"Kabuanga",
    "gn:population":0,
    "gn:timezone":"Africa/Lubumbashi",
    "iso:country":"CD",
    "wof:name":"Kabuanga",
    "wof:placetype":"locality"
},
  "geometry": {"coordinates":[22.29516,-6.96624],"type":"Point"}
}