{
  "type": "Feature",
  "properties": {
    "gn:admin1_code":"20.0",
    "gn:asciiname":"Tshongo-Dungu",
    "gn:country_code":"CD",
    "gn:dem":505,
    "gn:feature_class":"P",
    "gn:feature_code":"PPL",
    "gn:name":"Tshongo-Dungu",
    "gn:population":0,
    "gn:timezone":"Africa/Kinshasa",
    "iso:country":"CD",
    "wof:name":"Tshongo-Dungu",
    "wof:placetype":"locality"
},
  "geometry": {"coordinates":[19.45151,-4.33525],"type":"Point"}
}