{
  "type": "Feature",
  "properties": {
    "gn:admin1_code":"28.0",
    "gn:asciiname":"Yambukulu",
    "gn:country_code":"CD",
    "gn:dem":359,
    "gn:feature_class":"P",
    "gn:feature_code":"PPL",
    "gn:name":"Yambukulu",
    "gn:population":0,
    "gn:timezone":"Africa/Kinshasa",
    "iso:country":"CD",
    "wof:name":"Yambukulu",
    "wof:placetype":"locality"
},
  "geometry": {"coordinates":[18.82663,2.82519],"type":"Point"}
}