{
  "type": "Feature",
  "properties": {
    "gn:admin1_code":"13.0",
    "gn:asciiname":"Tutu",
    "gn:country_code":"CD",
    "gn:dem":692,
    "gn:feature_class":"P",
    "gn:feature_code":"PPL",
    "gn:name":"Tutu",
    "gn:population":0,
    "gn:timezone":"Africa/Lubumbashi",
    "iso:country":"CD",
    "name:ceb_x_preferred":[
        "Tutu"
    ],
    "name:deu_x_preferred":[
        "Tutu"
    ],
    "name:eus_x_preferred":[
        "Tutu"
    ],
    "name:fra_x_preferred":[
        "Tutu"
    ],
    "name:ita_x_preferred":[
        "Tutu"
    ],
    "name:jpn_x_preferred":[
        "\u30c8\u30a5\u30c8\u30a5"
    ],
    "name:nld_x_preferred":[
        "Tutu"
    ],
    "name:por_x_preferred":[
        "Tutu"
    ],
    "name:slk_x_preferred":[
        "Tutu"
    ],
    "name:spa_x_preferred":[
        "Tutu"
    ],
    "name:swe_x_preferred":[
        "Tutu"
    ],
    "name:tur_x_preferred":[
        "Tutu"
    ],
    "wof:name":"Tutu",
    "wof:placetype":"locality"
},
  "geometry": {"coordinates":[27.00884000000001,2.86231],"type":"Point"}
}