{
  "type": "Feature",
  "properties": {
    "gn:admin1_code":"13.0",
    "gn:asciiname":"Tutu",
    "gn:country_code":"CD",
    "gn:dem":692,
    "gn:feature_class":"P",
    "gn:feature_code":"PPL",
    "gn:name":"Tutu",
    "gn:population":0,
    "gn:timezone":"Africa/Lubumbashi",
    "iso:country":"CD",
    "wof:name":"Tutu",
    "wof:placetype":"locality"
},
  "geometry": {"coordinates":[27.00884000000001,2.86231],"type":"Point"}
}