{
  "type": "Feature",
  "properties": {
    "gn:admin1_code":"19.0",
    "gn:asciiname":"Masangwa",
    "gn:country_code":"CD",
    "gn:dem":467,
    "gn:feature_class":"P",
    "gn:feature_code":"PPL",
    "gn:name":"Masangwa",
    "gn:population":0,
    "gn:timezone":"Africa/Kinshasa",
    "iso:country":"CD",
    "wof:name":"Masangwa",
    "wof:placetype":"locality"
},
  "geometry": {"coordinates":[16.45524,-5.68562],"type":"Point"}
}