{
  "type": "Feature",
  "properties": {
    "gn:admin1_code":"14.0",
    "gn:asciiname":"Mukenge",
    "gn:country_code":"CD",
    "gn:dem":881,
    "gn:feature_class":"P",
    "gn:feature_code":"PPL",
    "gn:name":"Mukenge",
    "gn:population":0,
    "gn:timezone":"Africa/Lubumbashi",
    "iso:country":"CD",
    "wof:name":"Mukenge",
    "wof:placetype":"locality"
},
  "geometry": {"coordinates":[27.21441,-9.96317],"type":"Point"}
}