{
  "type": "Feature",
  "properties": {
    "gn:admin1_code":"17.0",
    "gn:asciiname":"Makombo",
    "gn:country_code":"CD",
    "gn:dem":1283,
    "gn:feature_class":"P",
    "gn:feature_code":"PPL",
    "gn:name":"Makombo",
    "gn:population":0,
    "gn:timezone":"Africa/Lubumbashi",
    "iso:country":"CD",
    "wof:name":"Makombo",
    "wof:placetype":"locality"
},
  "geometry": {"coordinates":[30.16472000000001,1.61075],"type":"Point"}
}