{
  "type": "Feature",
  "properties": {
    "gn:admin1_code":"18.0",
    "gn:asciiname":"Kavumbu",
    "gn:country_code":"CD",
    "gn:dem":827,
    "gn:feature_class":"P",
    "gn:feature_code":"PPL",
    "gn:name":"Kavumbu",
    "gn:population":0,
    "gn:timezone":"Africa/Lubumbashi",
    "iso:country":"CD",
    "wof:name":"Kavumbu",
    "wof:placetype":"locality"
},
  "geometry": {"coordinates":[21.51133,-7.24664],"type":"Point"}
}