{
  "type": "Feature",
  "properties": {
    "gn:admin1_code":"27.0",
    "gn:asciiname":"Etenesha",
    "gn:country_code":"CD",
    "gn:dem":602,
    "gn:feature_class":"P",
    "gn:feature_code":"PPL",
    "gn:name":"Etenesha",
    "gn:population":0,
    "gn:timezone":"Africa/Lubumbashi",
    "iso:country":"CD",
    "wof:name":"Etenesha",
    "wof:placetype":"locality"
},
  "geometry": {"coordinates":[24.20341,-3.24772],"type":"Point"}
}