{
  "type": "Feature",
  "properties": {
    "gn:admin1_code":"18.0",
    "gn:asciiname":"Shawadia",
    "gn:country_code":"CD",
    "gn:dem":832,
    "gn:feature_class":"P",
    "gn:feature_code":"PPL",
    "gn:name":"Shawadia",
    "gn:population":0,
    "gn:timezone":"Africa/Lubumbashi",
    "iso:country":"CD",
    "wof:name":"Shawadia",
    "wof:placetype":"locality"
},
  "geometry": {"coordinates":[21.49486,-7.14021],"type":"Point"}
}