{
  "type": "Feature",
  "properties": {
    "gn:admin1_code":"20.0",
    "gn:asciiname":"Kimbongo-Subu",
    "gn:country_code":"CD",
    "gn:dem":586,
    "gn:feature_class":"P",
    "gn:feature_code":"PPL",
    "gn:name":"Kimbongo-Subu",
    "gn:population":0,
    "gn:timezone":"Africa/Kinshasa",
    "iso:country":"CD",
    "wof:name":"Kimbongo-Subu",
    "wof:placetype":"locality"
},
  "geometry": {"coordinates":[17.87082999999999,-4.86047],"type":"Point"}
}