{
  "type": "Feature",
  "properties": {
    "gn:admin1_code":"16.0",
    "gn:asciiname":"Embaneba",
    "gn:country_code":"CD",
    "gn:dem":736,
    "gn:feature_class":"P",
    "gn:feature_code":"PPL",
    "gn:name":"Embaneba",
    "gn:population":0,
    "gn:timezone":"Africa/Lubumbashi",
    "iso:country":"CD",
    "wof:name":"Embaneba",
    "wof:placetype":"locality"
},
  "geometry": {"coordinates":[27.50898,2.52209],"type":"Point"}
}