{
  "type": "Feature",
  "properties": {
    "gn:admin1_code":"13.0",
    "gn:asciiname":"Kembisa",
    "gn:country_code":"CD",
    "gn:dem":735,
    "gn:feature_class":"P",
    "gn:feature_code":"PPL",
    "gn:name":"Kembisa",
    "gn:population":0,
    "gn:timezone":"Africa/Lubumbashi",
    "iso:country":"CD",
    "wof:name":"Kembisa",
    "wof:placetype":"locality"
},
  "geometry": {"coordinates":[27.25847000000001,3.57779],"type":"Point"}
}