{
  "type": "Feature",
  "properties": {
    "gn:admin1_code":"20.0",
    "gn:asciiname":"Kumbi-Makopa",
    "gn:country_code":"CD",
    "gn:dem":560,
    "gn:feature_class":"P",
    "gn:feature_code":"PPL",
    "gn:name":"Kumbi-Makopa",
    "gn:population":0,
    "gn:timezone":"Africa/Kinshasa",
    "iso:country":"CD",
    "wof:name":"Kumbi-Makopa",
    "wof:placetype":"locality"
},
  "geometry": {"coordinates":[18.03713,-4.82088],"type":"Point"}
}