{
  "type": "Feature",
  "properties": {
    "gn:admin1_code":"29.0",
    "gn:asciiname":"Ilunga",
    "gn:country_code":"CD",
    "gn:dem":892,
    "gn:feature_class":"P",
    "gn:feature_code":"PPL",
    "gn:name":"Ilunga",
    "gn:population":0,
    "gn:timezone":"Africa/Lubumbashi",
    "iso:country":"CD",
    "wof:name":"Ilunga",
    "wof:placetype":"locality"
},
  "geometry": {"coordinates":[28.0636,-6.18649],"type":"Point"}
}