{
  "type": "Feature",
  "properties": {
    "gn:admin1_code":"23.0",
    "gn:asciiname":"Mbala",
    "gn:country_code":"CD",
    "gn:dem":843,
    "gn:feature_class":"P",
    "gn:feature_code":"PPL",
    "gn:name":"Mbala",
    "gn:population":0,
    "gn:timezone":"Africa/Lubumbashi",
    "iso:country":"CD",
    "name:ceb_x_preferred":[
        "Mbala"
    ],
    "name:fra_x_preferred":[
        "Mbala"
    ],
    "name:swe_x_preferred":[
        "Mbala"
    ],
    "wof:name":"Mbala",
    "wof:placetype":"locality"
},
  "geometry": {"coordinates":[21.95382,-7.45124],"type":"Point"}
}