{
  "type": "Feature",
  "properties": {
    "gn:admin1_code":"4.0",
    "gn:asciiname":"Lumpungu",
    "gn:country_code":"CD",
    "gn:dem":747,
    "gn:feature_class":"P",
    "gn:feature_code":"PPL",
    "gn:name":"Lumpungu",
    "gn:population":0,
    "gn:timezone":"Africa/Lubumbashi",
    "iso:country":"CD",
    "wof:name":"Lumpungu",
    "wof:placetype":"locality"
},
  "geometry": {"coordinates":[22.99406,-5.91329],"type":"Point"}
}