{
  "type": "Feature",
  "properties": {
    "gn:admin1_code":"22.0",
    "gn:asciiname":"Nalemba",
    "gn:country_code":"CD",
    "gn:dem":934,
    "gn:feature_class":"P",
    "gn:feature_code":"PPL",
    "gn:name":"Nalemba",
    "gn:population":0,
    "gn:timezone":"Africa/Lubumbashi",
    "iso:country":"CD",
    "wof:name":"Nalemba",
    "wof:placetype":"locality"
},
  "geometry": {"coordinates":[23.35042,-8.06672],"type":"Point"}
}