{
  "type": "Feature",
  "properties": {
    "gn:admin1_code":"22.0",
    "gn:asciiname":"Mwakaita",
    "gn:country_code":"CD",
    "gn:dem":1052,
    "gn:feature_class":"P",
    "gn:feature_code":"PPL",
    "gn:name":"Mwakaita",
    "gn:population":0,
    "gn:timezone":"Africa/Lubumbashi",
    "iso:country":"CD",
    "wof:name":"Mwakaita",
    "wof:placetype":"locality"
},
  "geometry": {"coordinates":[23.65907,-9.6566],"type":"Point"}
}