{
  "type": "Feature",
  "properties": {
    "gn:admin1_code":"14.0",
    "gn:asciiname":"Kiabu",
    "gn:country_code":"CD",
    "gn:dem":1302,
    "gn:feature_class":"P",
    "gn:feature_code":"PPL",
    "gn:name":"Kiabu",
    "gn:population":0,
    "gn:timezone":"Africa/Lubumbashi",
    "iso:country":"CD",
    "wof:name":"Kiabu",
    "wof:placetype":"locality"
},
  "geometry": {"coordinates":[26.95,-11.61667],"type":"Point"}
}