{
  "type": "Feature",
  "properties": {
    "gn:admin1_code":"8.0",
    "gn:asciiname":"Banza-Sanda",
    "gn:country_code":"CD",
    "gn:dem":195,
    "gn:feature_class":"P",
    "gn:feature_code":"PPL",
    "gn:name":"Banza-Sanda",
    "gn:population":0,
    "gn:timezone":"Africa/Kinshasa",
    "iso:country":"CD",
    "wof:name":"Banza-Sanda",
    "wof:placetype":"locality"
},
  "geometry": {"coordinates":[14.14395,-4.98794],"type":"Point"}
}