{
  "type": "Feature",
  "properties": {
    "gn:admin1_code":"19.0",
    "gn:asciiname":"Kabanga",
    "gn:country_code":"CD",
    "gn:dem":855,
    "gn:feature_class":"P",
    "gn:feature_code":"PPL",
    "gn:name":"Kabanga",
    "gn:population":0,
    "gn:timezone":"Africa/Kinshasa",
    "iso:country":"CD",
    "name:ceb_x_preferred":[
        "Kabanga"
    ],
    "name:fra_x_preferred":[
        "Kabanga"
    ],
    "name:swe_x_preferred":[
        "Kabanga"
    ],
    "wof:name":"Kabanga",
    "wof:placetype":"locality"
},
  "geometry": {"coordinates":[18.63524,-6.32734],"type":"Point"}
}