{
  "type": "Feature",
  "properties": {
    "gn:admin1_code":"16.0",
    "gn:asciiname":"Bilali",
    "gn:country_code":"CD",
    "gn:dem":792,
    "gn:feature_class":"P",
    "gn:feature_code":"PPL",
    "gn:name":"Bilali",
    "gn:population":0,
    "gn:timezone":"Africa/Lubumbashi",
    "iso:country":"CD",
    "wof:name":"Bilali",
    "wof:placetype":"locality"
},
  "geometry": {"coordinates":[29.78825,3.78439],"type":"Point"}
}