{
  "type": "Feature",
  "properties": {
    "gn:admin1_code":"22.0",
    "gn:asciiname":"Kazamba",
    "gn:country_code":"CD",
    "gn:dem":989,
    "gn:feature_class":"P",
    "gn:feature_code":"PPL",
    "gn:name":"Kazamba",
    "gn:population":0,
    "gn:timezone":"Africa/Lubumbashi",
    "iso:country":"CD",
    "name:fra_x_preferred":[
        "Kazamba"
    ],
    "wof:name":"Kazamba",
    "wof:placetype":"locality"
},
  "geometry": {"coordinates":[22.9666,-9.98263],"type":"Point"}
}