{
  "type": "Feature",
  "properties": {
    "gn:admin1_code":"20.0",
    "gn:asciiname":"Moliambo",
    "gn:country_code":"CD",
    "gn:dem":521,
    "gn:feature_class":"P",
    "gn:feature_code":"PPL",
    "gn:name":"Moliambo",
    "gn:population":0,
    "gn:timezone":"Africa/Kinshasa",
    "iso:country":"CD",
    "wof:name":"Moliambo",
    "wof:placetype":"locality"
},
  "geometry": {"coordinates":[18.1547,-4.65494],"type":"Point"}
}