{
  "type": "Feature",
  "properties": {
    "gn:admin1_code":"19.0",
    "gn:asciiname":"Shanguvulu",
    "gn:country_code":"CD",
    "gn:dem":1018,
    "gn:feature_class":"P",
    "gn:feature_code":"PPL",
    "gn:name":"Shanguvulu",
    "gn:population":0,
    "gn:timezone":"Africa/Kinshasa",
    "iso:country":"CD",
    "wof:name":"Shanguvulu",
    "wof:placetype":"locality"
},
  "geometry": {"coordinates":[19.16379,-7.27127],"type":"Point"}
}