{
  "type": "Feature",
  "properties": {
    "gn:admin1_code":"15.0",
    "gn:asciiname":"Kindele",
    "gn:country_code":"CD",
    "gn:dem":1107,
    "gn:feature_class":"P",
    "gn:feature_code":"PPL",
    "gn:name":"Kindele",
    "gn:population":0,
    "gn:timezone":"Africa/Lubumbashi",
    "iso:country":"CD",
    "name:und_x_variant":[
        "Pastorale Kindele",
        "Kindele"
    ],
    "wof:name":"Kindele",
    "wof:placetype":"locality"
},
  "geometry": {"coordinates":[24.18268,-8.65369],"type":"Point"}
}