{
  "type": "Feature",
  "properties": {
    "gn:admin1_code":"24.0",
    "gn:asciiname":"Besomba",
    "gn:country_code":"CD",
    "gn:dem":373,
    "gn:feature_class":"P",
    "gn:feature_code":"PPL",
    "gn:name":"Besomba",
    "gn:population":0,
    "gn:timezone":"Africa/Kinshasa",
    "iso:country":"CD",
    "wof:name":"Besomba",
    "wof:placetype":"locality"
},
  "geometry": {"coordinates":[19.76667,-1.81667],"type":"Point"}
}