{
  "type": "Feature",
  "properties": {
    "gn:admin1_code":"20.0",
    "gn:asciiname":"Makoso",
    "gn:country_code":"CD",
    "gn:dem":433,
    "gn:feature_class":"P",
    "gn:feature_code":"PPL",
    "gn:name":"Makoso",
    "gn:population":0,
    "gn:timezone":"Africa/Kinshasa",
    "iso:country":"CD",
    "wof:name":"Makoso",
    "wof:placetype":"locality"
},
  "geometry": {"coordinates":[18.46667,-4.63333],"type":"Point"}
}