{
  "type": "Feature",
  "properties": {
    "gn:admin1_code":"28.0",
    "gn:asciiname":"Taliba",
    "gn:country_code":"CD",
    "gn:dem":419,
    "gn:feature_class":"P",
    "gn:feature_code":"PPL",
    "gn:name":"Taliba",
    "gn:population":0,
    "gn:timezone":"Africa/Kinshasa",
    "iso:country":"CD",
    "wof:name":"Taliba",
    "wof:placetype":"locality"
},
  "geometry": {"coordinates":[20.2428,2.58308],"type":"Point"}
}