{
  "type": "Feature",
  "properties": {
    "gn:admin1_code":"16.0",
    "gn:asciiname":"Bobowa",
    "gn:country_code":"CD",
    "gn:dem":781,
    "gn:feature_class":"P",
    "gn:feature_code":"PPL",
    "gn:name":"Bobowa",
    "gn:population":0,
    "gn:timezone":"Africa/Lubumbashi",
    "iso:country":"CD",
    "name:bul_x_preferred":[
        "\u0411\u043e\u0431\u043e\u0432\u0430"
    ],
    "name:cat_x_preferred":[
        "Bobowa"
    ],
    "name:ceb_x_preferred":[
        "Bobowa"
    ],
    "name:deu_x_preferred":[
        "Bobowa"
    ],
    "name:est_x_preferred":[
        "Bobowa"
    ],
    "name:fra_x_preferred":[
        "Bobowa"
    ],
    "name:heb_x_preferred":[
        "\u05d1\u05d5\u05d1\u05d5\u05d1\u05d4"
    ],
    "name:lav_x_preferred":[
        "Bobova"
    ],
    "name:msa_x_preferred":[
        "Bobowa"
    ],
    "name:nld_x_preferred":[
        "Bobowa"
    ],
    "name:pol_x_preferred":[
        "Bobowa"
    ],
    "name:ron_x_preferred":[
        "Bobowa"
    ],
    "name:rus_x_preferred":[
        "\u0411\u043e\u0431\u043e\u0432\u0430"
    ],
    "name:spa_x_preferred":[
        "Bobowa"
    ],
    "name:srp_x_preferred":[
        "\u0411\u043e\u0431\u043e\u0432\u0430"
    ],
    "name:szl_x_preferred":[
        "Bobowo"
    ],
    "name:ukr_x_preferred":[
        "\u0411\u043e\u0431\u043e\u0432\u0430"
    ],
    "name:vie_x_preferred":[
        "Bobowa"
    ],
    "name:yid_x_preferred":[
        "\u05d1\u05d0\u05d1\u05d0\u05d5\u05d5"
    ],
    "name:zho_x_preferred":[
        "\u535a\u535a\u74e6"
    ],
    "wof:name":"Bobowa",
    "wof:placetype":"locality"
},
  "geometry": {"coordinates":[27.65283,2.27163],"type":"Point"}
}