{
  "type": "Feature",
  "properties": {
    "gn:admin1_code":"28.0",
    "gn:asciiname":"Bulugu",
    "gn:country_code":"CD",
    "gn:dem":407,
    "gn:feature_class":"P",
    "gn:feature_code":"PPL",
    "gn:name":"Bulugu",
    "gn:population":0,
    "gn:timezone":"Africa/Kinshasa",
    "iso:country":"CD",
    "name:fra_x_preferred":[
        "Bulugu"
    ],
    "wof:name":"Bulugu",
    "wof:placetype":"locality"
},
  "geometry": {"coordinates":[19.58275,2.74706],"type":"Point"}
}