{
  "type": "Feature",
  "properties": {
    "gn:admin1_code":"16.0",
    "gn:asciiname":"Egbita",
    "gn:country_code":"CD",
    "gn:dem":754,
    "gn:feature_class":"P",
    "gn:feature_code":"PPL",
    "gn:name":"Egbita",
    "gn:population":0,
    "gn:timezone":"Africa/Lubumbashi",
    "iso:country":"CD",
    "wof:name":"Egbita",
    "wof:placetype":"locality"
},
  "geometry": {"coordinates":[27.39986,2.71425],"type":"Point"}
}