{
  "type": "Feature",
  "properties": {
    "gn:admin1_code":"30.0",
    "gn:asciiname":"Bafwasiambo",
    "gn:country_code":"CD",
    "gn:dem":514,
    "gn:feature_class":"P",
    "gn:feature_code":"PPL",
    "gn:name":"Bafwasiambo",
    "gn:population":0,
    "gn:timezone":"Africa/Lubumbashi",
    "iso:country":"CD",
    "wof:name":"Bafwasiambo",
    "wof:placetype":"locality"
},
  "geometry": {"coordinates":[25.9303,1.45692],"type":"Point"}
}