{
  "type": "Feature",
  "properties": {
    "gn:admin1_code":"8.0",
    "gn:asciiname":"Kindamba",
    "gn:country_code":"CD",
    "gn:dem":572,
    "gn:feature_class":"P",
    "gn:feature_code":"PPL",
    "gn:name":"Kindamba",
    "gn:population":0,
    "gn:timezone":"Africa/Kinshasa",
    "iso:country":"CD",
    "wof:name":"Kindamba",
    "wof:placetype":"locality"
},
  "geometry": {"coordinates":[14.06185,-4.7381],"type":"Point"}
}