{
  "type": "Feature",
  "properties": {
    "gn:admin1_code":"18.0",
    "gn:asciiname":"Shavumbu",
    "gn:country_code":"CD",
    "gn:dem":758,
    "gn:feature_class":"P",
    "gn:feature_code":"PPL",
    "gn:name":"Shavumbu",
    "gn:population":0,
    "gn:timezone":"Africa/Lubumbashi",
    "iso:country":"CD",
    "wof:name":"Shavumbu",
    "wof:placetype":"locality"
},
  "geometry": {"coordinates":[21.38401,-7.02944],"type":"Point"}
}