{
  "type": "Feature",
  "properties": {
    "gn:admin1_code":"31.0",
    "gn:asciiname":"Bosekele",
    "gn:country_code":"CD",
    "gn:dem":426,
    "gn:feature_class":"P",
    "gn:feature_code":"PPL",
    "gn:name":"Bosekele",
    "gn:population":0,
    "gn:timezone":"Africa/Kinshasa",
    "iso:country":"CD",
    "wof:name":"Bosekele",
    "wof:placetype":"locality"
},
  "geometry": {"coordinates":[22.53759,1.17908],"type":"Point"}
}