{
  "type": "Feature",
  "properties": {
    "gn:admin1_code":"15.0",
    "gn:asciiname":"Mutoyo",
    "gn:country_code":"CD",
    "gn:dem":1090,
    "gn:feature_class":"P",
    "gn:feature_code":"PPL",
    "gn:name":"Mutoyo",
    "gn:population":0,
    "gn:timezone":"Africa/Lubumbashi",
    "iso:country":"CD",
    "wof:name":"Mutoyo",
    "wof:placetype":"locality"
},
  "geometry": {"coordinates":[23.79212,-8.3966],"type":"Point"}
}