{
  "type": "Feature",
  "properties": {
    "gn:admin1_code":"20.0",
    "gn:asciiname":"Kikiari",
    "gn:country_code":"CD",
    "gn:dem":694,
    "gn:feature_class":"P",
    "gn:feature_code":"PPL",
    "gn:name":"Kikiari",
    "gn:population":0,
    "gn:timezone":"Africa/Kinshasa",
    "iso:country":"CD",
    "wof:name":"Kikiari",
    "wof:placetype":"locality"
},
  "geometry": {"coordinates":[18.1734,-5.41993],"type":"Point"}
}