{
  "type": "Feature",
  "properties": {
    "gn:admin1_code":"22.0",
    "gn:asciiname":"Tshinguli",
    "gn:country_code":"CD",
    "gn:dem":1064,
    "gn:feature_class":"P",
    "gn:feature_code":"PPL",
    "gn:name":"Tshinguli",
    "gn:population":0,
    "gn:timezone":"Africa/Lubumbashi",
    "iso:country":"CD",
    "wof:name":"Tshinguli",
    "wof:placetype":"locality"
},
  "geometry": {"coordinates":[23.34299,-10.3828],"type":"Point"}
}