{
  "type": "Feature",
  "properties": {
    "gn:admin1_code":"26.0",
    "gn:asciiname":"Gomo",
    "gn:country_code":"CD",
    "gn:dem":423,
    "gn:feature_class":"P",
    "gn:feature_code":"PPL",
    "gn:name":"Gomo",
    "gn:population":0,
    "gn:timezone":"Africa/Kinshasa",
    "iso:country":"CD",
    "name:ceb_x_preferred":[
        "Gomo"
    ],
    "name:por_x_preferred":[
        "Gomo"
    ],
    "name:swe_x_preferred":[
        "Gomo"
    ],
    "wof:name":"Gomo",
    "wof:placetype":"locality"
},
  "geometry": {"coordinates":[20.85853,4.18001],"type":"Point"}
}