{
  "type": "Feature",
  "properties": {
    "gn:admin1_code":"22.0",
    "gn:asciiname":"Samulinga",
    "gn:country_code":"CD",
    "gn:dem":989,
    "gn:feature_class":"P",
    "gn:feature_code":"PPL",
    "gn:name":"Samulinga",
    "gn:population":0,
    "gn:timezone":"Africa/Lubumbashi",
    "iso:country":"CD",
    "wof:name":"Samulinga",
    "wof:placetype":"locality"
},
  "geometry": {"coordinates":[24.01987,-9.0296],"type":"Point"}
}