{
  "type": "Feature",
  "properties": {
    "gn:admin1_code":"11.0",
    "gn:asciiname":"Kiampala",
    "gn:country_code":"CD",
    "gn:dem":1736,
    "gn:feature_class":"P",
    "gn:feature_code":"PPL",
    "gn:name":"Kiampala",
    "gn:population":0,
    "gn:timezone":"Africa/Lubumbashi",
    "iso:country":"CD",
    "wof:name":"Kiampala",
    "wof:placetype":"locality"
},
  "geometry": {"coordinates":[28.98289,-0.74012],"type":"Point"}
}