{
  "type": "Feature",
  "properties": {
    "gn:admin1_code":"19.0",
    "gn:asciiname":"Shamusanda",
    "gn:country_code":"CD",
    "gn:dem":906,
    "gn:feature_class":"P",
    "gn:feature_code":"PPL",
    "gn:name":"Shamusanda",
    "gn:population":0,
    "gn:timezone":"Africa/Kinshasa",
    "iso:country":"CD",
    "wof:name":"Shamusanda",
    "wof:placetype":"locality"
},
  "geometry": {"coordinates":[19.67686,-6.86669],"type":"Point"}
}