{
  "type": "Feature",
  "properties": {
    "gn:admin1_code":"19.0",
    "gn:asciiname":"Kitaka-Tskeke",
    "gn:country_code":"CD",
    "gn:dem":526,
    "gn:feature_class":"P",
    "gn:feature_code":"PPL",
    "gn:name":"Kitaka-Tskeke",
    "gn:population":0,
    "gn:timezone":"Africa/Kinshasa",
    "iso:country":"CD",
    "wof:name":"Kitaka-Tskeke",
    "wof:placetype":"locality"
},
  "geometry": {"coordinates":[17.51605,-4.56892],"type":"Point"}
}