{
  "type": "Feature",
  "properties": {
    "gn:admin1_code":"17.0",
    "gn:asciiname":"Komanda",
    "gn:country_code":"CD",
    "gn:dem":958,
    "gn:feature_class":"P",
    "gn:feature_code":"PPL",
    "gn:name":"Komanda",
    "gn:population":0,
    "gn:timezone":"Africa/Lubumbashi",
    "iso:country":"CD",
    "name:fra_x_preferred":[
        "Komanda"
    ],
    "name:fra_x_variant":[
        "Komande"
    ],
    "name:und_x_variant":[
        "Komande"
    ],
    "wof:name":"Komanda",
    "wof:placetype":"locality"
},
  "geometry": {"coordinates":[29.76395,1.3651],"type":"Point"}
}