{
  "type": "Feature",
  "properties": {
    "gn:admin1_code":"24.0",
    "gn:asciiname":"Bokenge",
    "gn:country_code":"CD",
    "gn:dem":351,
    "gn:feature_class":"P",
    "gn:feature_code":"PPL",
    "gn:name":"Bokenge",
    "gn:population":0,
    "gn:timezone":"Africa/Kinshasa",
    "iso:country":"CD",
    "wof:name":"Bokenge",
    "wof:placetype":"locality"
},
  "geometry": {"coordinates":[19.08333,-0.98333],"type":"Point"}
}