{
  "type": "Feature",
  "properties": {
    "gn:admin1_code":"29.0",
    "gn:asciiname":"Kaboto",
    "gn:country_code":"CD",
    "gn:dem":2211,
    "gn:feature_class":"P",
    "gn:feature_code":"PPL",
    "gn:name":"Kaboto",
    "gn:population":0,
    "gn:timezone":"Africa/Lubumbashi",
    "iso:country":"CD",
    "wof:name":"Kaboto",
    "wof:placetype":"locality"
},
  "geometry": {"coordinates":[29.95,-7.45],"type":"Point"}
}