{
  "type": "Feature",
  "properties": {
    "gn:admin1_code":"15.0",
    "gn:asciiname":"Dongo",
    "gn:country_code":"CD",
    "gn:dem":1031,
    "gn:feature_class":"P",
    "gn:feature_code":"PPL",
    "gn:name":"Dongo",
    "gn:population":0,
    "gn:timezone":"Africa/Lubumbashi",
    "iso:country":"CD",
    "name:ceb_x_preferred":[
        "Dongo"
    ],
    "name:deu_x_preferred":[
        "Dongo"
    ],
    "name:epo_x_preferred":[
        "Dongo"
    ],
    "name:fra_x_preferred":[
        "Dongo"
    ],
    "name:ita_x_preferred":[
        "Dongo"
    ],
    "name:nld_x_preferred":[
        "Dongo"
    ],
    "name:rus_x_preferred":[
        "\u0414\u043e\u043d\u0433\u043e"
    ],
    "name:swe_x_preferred":[
        "Dongo"
    ],
    "wof:name":"Dongo",
    "wof:placetype":"locality"
},
  "geometry": {"coordinates":[25.98796,-8.67388],"type":"Point"}
}