{
  "type": "Feature",
  "properties": {
    "gn:admin1_code":"22.0",
    "gn:asciiname":"Kansangu",
    "gn:country_code":"CD",
    "gn:dem":1111,
    "gn:feature_class":"P",
    "gn:feature_code":"PPL",
    "gn:name":"Kansangu",
    "gn:population":0,
    "gn:timezone":"Africa/Lubumbashi",
    "iso:country":"CD",
    "wof:name":"Kansangu",
    "wof:placetype":"locality"
},
  "geometry": {"coordinates":[23.48914,-10.40142],"type":"Point"}
}