{
  "type": "Feature",
  "properties": {
    "gn:admin1_code":"11.0",
    "gn:asciiname":"Biriba",
    "gn:country_code":"CD",
    "gn:dem":1036,
    "gn:feature_class":"P",
    "gn:feature_code":"PPL",
    "gn:name":"Biriba",
    "gn:population":0,
    "gn:timezone":"Africa/Lubumbashi",
    "iso:country":"CD",
    "name:ell_x_preferred":[
        "\u039c\u03c0\u03b9\u03c1\u03af\u03bc\u03c0\u03b1"
    ],
    "wof:name":"Biriba",
    "wof:placetype":"locality"
},
  "geometry": {"coordinates":[28.70806,-1.04528],"type":"Point"}
}