{
  "type": "Feature",
  "properties": {
    "gn:admin1_code":"19.0",
    "gn:asciiname":"Mwanzita",
    "gn:country_code":"CD",
    "gn:dem":655,
    "gn:feature_class":"P",
    "gn:feature_code":"PPL",
    "gn:name":"Mwanzita",
    "gn:population":0,
    "gn:timezone":"Africa/Kinshasa",
    "iso:country":"CD",
    "wof:name":"Mwanzita",
    "wof:placetype":"locality"
},
  "geometry": {"coordinates":[17.22371,-6.02304],"type":"Point"}
}