{
  "type": "Feature",
  "properties": {
    "gn:admin1_code":"28.0",
    "gn:asciiname":"Bodetwa",
    "gn:country_code":"CD",
    "gn:dem":388,
    "gn:feature_class":"P",
    "gn:feature_code":"PPL",
    "gn:name":"Bodetwa",
    "gn:population":0,
    "gn:timezone":"Africa/Kinshasa",
    "iso:country":"CD",
    "wof:name":"Bodetwa",
    "wof:placetype":"locality"
},
  "geometry": {"coordinates":[19.82577,3.43807],"type":"Point"}
}