{
  "type": "Feature",
  "properties": {
    "gn:admin1_code":"23.0",
    "gn:asciiname":"Ngweji-a-Mbuta",
    "gn:country_code":"CD",
    "gn:dem":803,
    "gn:feature_class":"P",
    "gn:feature_code":"PPL",
    "gn:name":"Ngweji-a-Mbuta",
    "gn:population":0,
    "gn:timezone":"Africa/Lubumbashi",
    "iso:country":"CD",
    "wof:name":"Ngweji-a-Mbuta",
    "wof:placetype":"locality"
},
  "geometry": {"coordinates":[22.27923,-7.24101],"type":"Point"}
}