{
  "type": "Feature",
  "properties": {
    "gn:admin1_code":"28.0",
    "gn:asciiname":"Bondoro",
    "gn:country_code":"CD",
    "gn:dem":420,
    "gn:feature_class":"P",
    "gn:feature_code":"PPL",
    "gn:name":"Bondoro",
    "gn:population":0,
    "gn:timezone":"Africa/Kinshasa",
    "iso:country":"CD",
    "name:fra_x_preferred":[
        "Bondoro"
    ],
    "wof:name":"Bondoro",
    "wof:placetype":"locality"
},
  "geometry": {"coordinates":[19.48951,2.95346],"type":"Point"}
}