{
  "type": "Feature",
  "properties": {
    "gn:admin1_code":"27.0",
    "gn:asciiname":"Utsungu",
    "gn:country_code":"CD",
    "gn:dem":480,
    "gn:feature_class":"P",
    "gn:feature_code":"PPL",
    "gn:name":"Utsungu",
    "gn:population":0,
    "gn:timezone":"Africa/Lubumbashi",
    "iso:country":"CD",
    "wof:name":"Utsungu",
    "wof:placetype":"locality"
},
  "geometry": {"coordinates":[24.23648,-4.74455],"type":"Point"}
}