{
  "type": "Feature",
  "properties": {
    "gn:admin1_code":"19.0",
    "gn:asciiname":"Kadiata",
    "gn:country_code":"CD",
    "gn:dem":985,
    "gn:feature_class":"P",
    "gn:feature_code":"PPL",
    "gn:name":"Kadiata",
    "gn:population":0,
    "gn:timezone":"Africa/Kinshasa",
    "iso:country":"CD",
    "wof:name":"Kadiata",
    "wof:placetype":"locality"
},
  "geometry": {"coordinates":[18.79352,-7.2112],"type":"Point"}
}