{
  "type": "Feature",
  "properties": {
    "gn:admin1_code":"28.0",
    "gn:asciiname":"Yagba",
    "gn:country_code":"CD",
    "gn:dem":405,
    "gn:feature_class":"P",
    "gn:feature_code":"PPL",
    "gn:name":"Yagba",
    "gn:population":0,
    "gn:timezone":"Africa/Kinshasa",
    "iso:country":"CD",
    "name:fra_x_preferred":[
        "Yagba"
    ],
    "wof:name":"Yagba",
    "wof:placetype":"locality"
},
  "geometry": {"coordinates":[19.59965,2.8763],"type":"Point"}
}