{
  "type": "Feature",
  "properties": {
    "gn:admin1_code":"23.0",
    "gn:asciiname":"Dimbelenge",
    "gn:country_code":"CD",
    "gn:dem":633,
    "gn:feature_class":"P",
    "gn:feature_code":"PPL",
    "gn:name":"Dimbelenge",
    "gn:population":0,
    "gn:timezone":"Africa/Lubumbashi",
    "iso:country":"CD",
    "wof:name":"Dimbelenge",
    "wof:placetype":"locality"
},
  "geometry": {"coordinates":[23.11133,-5.54892],"type":"Point"}
}