{
  "type": "Feature",
  "properties": {
    "gn:admin1_code":"19.0",
    "gn:asciiname":"Mungulu-Tsakala Deuxieme",
    "gn:country_code":"CD",
    "gn:dem":711,
    "gn:feature_class":"P",
    "gn:feature_code":"PPL",
    "gn:name":"Mungulu-Tsakala Deuxi\u00e8me",
    "gn:population":0,
    "gn:timezone":"Africa/Kinshasa",
    "iso:country":"CD",
    "wof:name":"Mungulu-Tsakala Deuxieme",
    "wof:placetype":"locality"
},
  "geometry": {"coordinates":[17.42936,-5.66822],"type":"Point"}
}