{
  "type": "Feature",
  "properties": {
    "gn:admin1_code":"19.0",
    "gn:asciiname":"Kiwonda",
    "gn:country_code":"CD",
    "gn:dem":851,
    "gn:feature_class":"P",
    "gn:feature_code":"PPL",
    "gn:name":"Kiwonda",
    "gn:population":0,
    "gn:timezone":"Africa/Kinshasa",
    "iso:country":"CD",
    "wof:name":"Kiwonda",
    "wof:placetype":"locality"
},
  "geometry": {"coordinates":[17.26565,-6.82125],"type":"Point"}
}