{
  "type": "Feature",
  "properties": {
    "gn:admin1_code":"22.0",
    "gn:asciiname":"Sakalezi",
    "gn:country_code":"CD",
    "gn:dem":758,
    "gn:feature_class":"P",
    "gn:feature_code":"PPL",
    "gn:name":"Sakalezi",
    "gn:population":0,
    "gn:timezone":"Africa/Lubumbashi",
    "iso:country":"CD",
    "wof:name":"Sakalezi",
    "wof:placetype":"locality"
},
  "geometry": {"coordinates":[25.62899,-9.59309],"type":"Point"}
}