{
  "type": "Feature",
  "properties": {
    "gn:admin1_code":"22.0",
    "gn:asciiname":"Sapeleade",
    "gn:country_code":"CD",
    "gn:dem":1007,
    "gn:feature_class":"P",
    "gn:feature_code":"PPL",
    "gn:name":"Sapeleade",
    "gn:population":0,
    "gn:timezone":"Africa/Lubumbashi",
    "iso:country":"CD",
    "wof:name":"Sapeleade",
    "wof:placetype":"locality"
},
  "geometry": {"coordinates":[22.63761,-9.45029],"type":"Point"}
}