{
  "type": "Feature",
  "properties": {
    "gn:admin1_code":"30.0",
    "gn:asciiname":"Bagwase",
    "gn:country_code":"CD",
    "gn:dem":443,
    "gn:feature_class":"P",
    "gn:feature_code":"PPL",
    "gn:name":"Bagwase",
    "gn:population":0,
    "gn:timezone":"Africa/Lubumbashi",
    "iso:country":"CD",
    "name:und_x_variant":[
        "Ugwasi",
        "Bagwase"
    ],
    "wof:name":"Bagwase",
    "wof:placetype":"locality"
},
  "geometry": {"coordinates":[25.24927000000001,-0.36358],"type":"Point"}
}