{
  "type": "Feature",
  "properties": {
    "gn:admin1_code":"16.0",
    "gn:asciiname":"Nebogandato",
    "gn:country_code":"CD",
    "gn:dem":752,
    "gn:feature_class":"P",
    "gn:feature_code":"PPL",
    "gn:name":"Nebogandato",
    "gn:population":0,
    "gn:timezone":"Africa/Lubumbashi",
    "iso:country":"CD",
    "wof:name":"Nebogandato",
    "wof:placetype":"locality"
},
  "geometry": {"coordinates":[27.56809,2.77411],"type":"Point"}
}