{
  "type": "Feature",
  "properties": {
    "gn:admin1_code":"20.0",
    "gn:asciiname":"Kibwanga",
    "gn:country_code":"CD",
    "gn:dem":443,
    "gn:feature_class":"P",
    "gn:feature_code":"PPL",
    "gn:name":"Kibwanga",
    "gn:population":0,
    "gn:timezone":"Africa/Kinshasa",
    "iso:country":"CD",
    "wof:name":"Kibwanga",
    "wof:placetype":"locality"
},
  "geometry": {"coordinates":[17.71296,-4.2645],"type":"Point"}
}