{
  "type": "Feature",
  "properties": {
    "gn:admin1_code":"15.0",
    "gn:asciiname":"Kasakaie Kakona",
    "gn:country_code":"CD",
    "gn:dem":763,
    "gn:feature_class":"P",
    "gn:feature_code":"PPL",
    "gn:name":"Kasakaie Kakona",
    "gn:population":0,
    "gn:timezone":"Africa/Lubumbashi",
    "iso:country":"CD",
    "name:und_x_variant":[
        "Kasakai",
        "Kasakaie",
        "Kasakaie-Mabuki",
        "Kasakaie Kakona"
    ],
    "wof:name":"Kasakaie Kakona",
    "wof:placetype":"locality"
},
  "geometry": {"coordinates":[25.92888,-7.58681],"type":"Point"}
}