{
  "type": "Feature",
  "properties": {
    "gn:admin1_code":"22.0",
    "gn:asciiname":"Samunguza",
    "gn:country_code":"CD",
    "gn:dem":923,
    "gn:feature_class":"P",
    "gn:feature_code":"PPL",
    "gn:name":"Samunguza",
    "gn:population":0,
    "gn:timezone":"Africa/Lubumbashi",
    "iso:country":"CD",
    "wof:name":"Samunguza",
    "wof:placetype":"locality"
},
  "geometry": {"coordinates":[23.11788,-9.72325],"type":"Point"}
}