{
  "type": "Feature",
  "properties": {
    "gn:admin1_code":"22.0",
    "gn:asciiname":"Nambanza",
    "gn:country_code":"CD",
    "gn:dem":947,
    "gn:feature_class":"P",
    "gn:feature_code":"PPL",
    "gn:name":"Nambanza",
    "gn:population":0,
    "gn:timezone":"Africa/Lubumbashi",
    "iso:country":"CD",
    "wof:name":"Nambanza",
    "wof:placetype":"locality"
},
  "geometry": {"coordinates":[23.10057,-7.9011],"type":"Point"}
}