{
  "type": "Feature",
  "properties": {
    "gn:admin1_code":"23.0",
    "gn:asciiname":"Kabelesha",
    "gn:country_code":"CD",
    "gn:dem":804,
    "gn:feature_class":"P",
    "gn:feature_code":"PPL",
    "gn:name":"Kabelesha",
    "gn:population":0,
    "gn:timezone":"Africa/Lubumbashi",
    "iso:country":"CD",
    "wof:name":"Kabelesha",
    "wof:placetype":"locality"
},
  "geometry": {"coordinates":[22.00848,-7.01743],"type":"Point"}
}