{
  "type": "Feature",
  "properties": {
    "gn:admin1_code":"19.0",
    "gn:asciiname":"Shakambundji",
    "gn:country_code":"CD",
    "gn:dem":1094,
    "gn:feature_class":"P",
    "gn:feature_code":"PPL",
    "gn:name":"Shakambundji",
    "gn:population":0,
    "gn:timezone":"Africa/Kinshasa",
    "iso:country":"CD",
    "wof:name":"Shakambundji",
    "wof:placetype":"locality"
},
  "geometry": {"coordinates":[18.96996,-7.8952],"type":"Point"}
}