{
  "type": "Feature",
  "properties": {
    "gn:admin1_code":"14.0",
    "gn:asciiname":"Mioba",
    "gn:country_code":"CD",
    "gn:dem":1245,
    "gn:feature_class":"P",
    "gn:feature_code":"PPL",
    "gn:name":"Mioba",
    "gn:population":0,
    "gn:timezone":"Africa/Lubumbashi",
    "iso:country":"CD",
    "wof:name":"Mioba",
    "wof:placetype":"locality"
},
  "geometry": {"coordinates":[29.03333,-13.23333],"type":"Point"}
}