{
  "type": "Feature",
  "properties": {
    "gn:admin1_code":"21.0",
    "gn:asciiname":"Kata",
    "gn:country_code":"CD",
    "gn:dem":965,
    "gn:feature_class":"P",
    "gn:feature_code":"PPL",
    "gn:name":"Kata",
    "gn:population":0,
    "gn:timezone":"Africa/Lubumbashi",
    "iso:country":"CD",
    "name:ara_x_preferred":[
        "\u0643\u0627\u062a\u0627"
    ],
    "name:ast_x_preferred":[
        "Kata"
    ],
    "name:aze_x_preferred":[
        "Kata"
    ],
    "name:ben_x_preferred":[
        "\u0995\u09be\u09a4\u09be"
    ],
    "name:bos_x_preferred":[
        "Kata"
    ],
    "name:bul_x_preferred":[
        "\u041a\u0430\u0442\u0430"
    ],
    "name:cat_x_preferred":[
        "Kata"
    ],
    "name:ces_x_preferred":[
        "Kata"
    ],
    "name:dan_x_preferred":[
        "Kata"
    ],
    "name:deu_x_preferred":[
        "Form"
    ],
    "name:ell_x_preferred":[
        "\u039a\u03ac\u03c4\u03b1"
    ],
    "name:fas_x_preferred":[
        "\u06a9\u0627\u062a\u0627"
    ],
    "name:fin_x_preferred":[
        "Kata"
    ],
    "name:fra_x_preferred":[
        "Kata"
    ],
    "name:glg_x_preferred":[
        "Kata"
    ],
    "name:heb_x_preferred":[
        "\u05e7\u05d0\u05d8\u05d4"
    ],
    "name:hrv_x_preferred":[
        "Kate"
    ],
    "name:ind_x_preferred":[
        "Kata"
    ],
    "name:ita_x_preferred":[
        "Kata"
    ],
    "name:jpn_x_preferred":[
        "\u5f62\u7a3d\u53e4"
    ],
    "name:kaz_x_preferred":[
        "\u0422\u0438\u043f"
    ],
    "name:kir_x_preferred":[
        "\u0422\u0438\u043f"
    ],
    "name:lat_x_preferred":[
        "Kata"
    ],
    "name:nld_x_preferred":[
        "Kata"
    ],
    "name:nor_x_preferred":[
        "Kata"
    ],
    "name:oci_x_preferred":[
        "Kata"
    ],
    "name:pol_x_preferred":[
        "Kata"
    ],
    "name:por_x_preferred":[
        "Kata"
    ],
    "name:rus_x_preferred":[
        "\u041a\u0430\u0442\u0430"
    ],
    "name:sna_x_preferred":[
        "Mhando"
    ],
    "name:spa_x_preferred":[
        "Kata"
    ],
    "name:swe_x_preferred":[
        "Kata"
    ],
    "name:tur_x_preferred":[
        "Kata"
    ],
    "name:ukr_x_preferred":[
        "\u041a\u0430\u0442\u0430"
    ],
    "name:vie_x_preferred":[
        "Kata"
    ],
    "name:vls_x_preferred":[
        "Kata"
    ],
    "wof:name":"Kata",
    "wof:placetype":"locality"
},
  "geometry": {"coordinates":[23.35973,-7.62805],"type":"Point"}
}