{
  "type": "Feature",
  "properties": {
    "gn:admin1_code":"21.0",
    "gn:asciiname":"Kata",
    "gn:country_code":"CD",
    "gn:dem":965,
    "gn:feature_class":"P",
    "gn:feature_code":"PPL",
    "gn:name":"Kata",
    "gn:population":0,
    "gn:timezone":"Africa/Lubumbashi",
    "iso:country":"CD",
    "wof:name":"Kata",
    "wof:placetype":"locality"
},
  "geometry": {"coordinates":[23.35973,-7.62805],"type":"Point"}
}