{
  "type": "Feature",
  "properties": {
    "gn:admin1_code":"8.0",
    "gn:asciiname":"Kimbala Muke",
    "gn:country_code":"CD",
    "gn:dem":385,
    "gn:feature_class":"P",
    "gn:feature_code":"PPL",
    "gn:name":"Kimbala Muke",
    "gn:population":0,
    "gn:timezone":"Africa/Kinshasa",
    "iso:country":"CD",
    "wof:name":"Kimbala Muke",
    "wof:placetype":"locality"
},
  "geometry": {"coordinates":[15.46218,-4.5972],"type":"Point"}
}