{
  "type": "Feature",
  "properties": {
    "gn:admin1_code":"23.0",
    "gn:asciiname":"Kabemba",
    "gn:country_code":"CD",
    "gn:dem":764,
    "gn:feature_class":"P",
    "gn:feature_code":"PPL",
    "gn:name":"Kabemba",
    "gn:population":0,
    "gn:timezone":"Africa/Lubumbashi",
    "iso:country":"CD",
    "wof:name":"Kabemba",
    "wof:placetype":"locality"
},
  "geometry": {"coordinates":[22.67163,-6.11669],"type":"Point"}
}