{
  "type": "Feature",
  "properties": {
    "gn:admin1_code":"22.0",
    "gn:asciiname":"Bulava",
    "gn:country_code":"CD",
    "gn:dem":1100,
    "gn:feature_class":"P",
    "gn:feature_code":"PPL",
    "gn:name":"Bulava",
    "gn:population":0,
    "gn:timezone":"Africa/Lubumbashi",
    "iso:country":"CD",
    "wof:name":"Bulava",
    "wof:placetype":"locality"
},
  "geometry": {"coordinates":[23.47196,-10.39423],"type":"Point"}
}