{
  "type": "Feature",
  "properties": {
    "gn:admin1_code":"21.0",
    "gn:asciiname":"Kazadi",
    "gn:country_code":"CD",
    "gn:dem":823,
    "gn:feature_class":"P",
    "gn:feature_code":"PPL",
    "gn:name":"Kazadi",
    "gn:population":0,
    "gn:timezone":"Africa/Lubumbashi",
    "iso:country":"CD",
    "wof:name":"Kazadi",
    "wof:placetype":"locality"
},
  "geometry": {"coordinates":[23.64944,-6.90358],"type":"Point"}
}