{
  "type": "Feature",
  "properties": {
    "gn:admin1_code":"23.0",
    "gn:asciiname":"Tshkuma",
    "gn:country_code":"CD",
    "gn:dem":759,
    "gn:feature_class":"P",
    "gn:feature_code":"PPL",
    "gn:name":"Tshkuma",
    "gn:population":0,
    "gn:timezone":"Africa/Lubumbashi",
    "iso:country":"CD",
    "wof:name":"Tshkuma",
    "wof:placetype":"locality"
},
  "geometry": {"coordinates":[22.49591,-6.43855],"type":"Point"}
}