{
  "type": "Feature",
  "properties": {
    "gn:admin1_code":"30.0",
    "gn:asciiname":"Ebengi",
    "gn:country_code":"CD",
    "gn:dem":707,
    "gn:feature_class":"P",
    "gn:feature_code":"PPL",
    "gn:name":"Ebengi",
    "gn:population":0,
    "gn:timezone":"Africa/Lubumbashi",
    "iso:country":"CD",
    "wof:name":"Ebengi",
    "wof:placetype":"locality"
},
  "geometry": {"coordinates":[27.76667,-0.06667],"type":"Point"}
}