{
  "type": "Feature",
  "properties": {
    "gn:admin1_code":"19.0",
    "gn:asciiname":"Shanama",
    "gn:country_code":"CD",
    "gn:dem":998,
    "gn:feature_class":"P",
    "gn:feature_code":"PPL",
    "gn:name":"Shanama",
    "gn:population":0,
    "gn:timezone":"Africa/Kinshasa",
    "iso:country":"CD",
    "wof:name":"Shanama",
    "wof:placetype":"locality"
},
  "geometry": {"coordinates":[18.86609,-6.94728],"type":"Point"}
}