{
  "type": "Feature",
  "properties": {
    "gn:admin1_code":"20.0",
    "gn:asciiname":"Bukondu",
    "gn:country_code":"CD",
    "gn:dem":730,
    "gn:feature_class":"P",
    "gn:feature_code":"PPL",
    "gn:name":"Bukondu",
    "gn:population":0,
    "gn:timezone":"Africa/Kinshasa",
    "iso:country":"CD",
    "wof:name":"Bukondu",
    "wof:placetype":"locality"
},
  "geometry": {"coordinates":[19.19406,-5.3057],"type":"Point"}
}