{
  "type": "Feature",
  "properties": {
    "gn:admin1_code":"20.0",
    "gn:asciiname":"Kitsako",
    "gn:country_code":"CD",
    "gn:dem":714,
    "gn:feature_class":"P",
    "gn:feature_code":"PPL",
    "gn:name":"Kitsako",
    "gn:population":0,
    "gn:timezone":"Africa/Kinshasa",
    "iso:country":"CD",
    "wof:name":"Kitsako",
    "wof:placetype":"locality"
},
  "geometry": {"coordinates":[17.57546,-5.24407],"type":"Point"}
}