{
  "type": "Feature",
  "properties": {
    "gn:admin1_code":"26.0",
    "gn:asciiname":"Bosangabo",
    "gn:country_code":"CD",
    "gn:dem":435,
    "gn:feature_class":"P",
    "gn:feature_code":"PPL",
    "gn:name":"Bosangabo",
    "gn:population":0,
    "gn:timezone":"Africa/Kinshasa",
    "iso:country":"CD",
    "name:und_x_variant":[
        "Bodangabo"
    ],
    "wof:name":"Bosangabo",
    "wof:placetype":"locality"
},
  "geometry": {"coordinates":[20.61482,3.76837],"type":"Point"}
}