{
  "type": "Feature",
  "properties": {
    "gn:admin1_code":"27.0",
    "gn:asciiname":"Lusani",
    "gn:country_code":"CD",
    "gn:dem":647,
    "gn:feature_class":"P",
    "gn:feature_code":"PPL",
    "gn:name":"Lusani",
    "gn:population":0,
    "gn:timezone":"Africa/Lubumbashi",
    "iso:country":"CD",
    "name:und_x_variant":[
        "Lusuni",
        "Lusoni",
        "Lusani"
    ],
    "wof:name":"Lusani",
    "wof:placetype":"locality"
},
  "geometry": {"coordinates":[24.31518,-5.06916],"type":"Point"}
}