{
  "type": "Feature",
  "properties": {
    "gn:admin1_code":"11.0",
    "gn:asciiname":"Nyanza",
    "gn:country_code":"CD",
    "gn:dem":1092,
    "gn:feature_class":"P",
    "gn:feature_code":"PPL",
    "gn:name":"Nyanza",
    "gn:population":0,
    "gn:timezone":"Africa/Lubumbashi",
    "iso:country":"CD",
    "name:bre_x_preferred":[
        "Nyanza"
    ],
    "name:ceb_x_preferred":[
        "Nyanza"
    ],
    "name:deu_x_preferred":[
        "Nyanza"
    ],
    "name:nld_x_preferred":[
        "Nyanza"
    ],
    "name:rus_x_preferred":[
        "\u041d\u044c\u044f\u043d\u0437\u0430"
    ],
    "wof:name":"Nyanza",
    "wof:placetype":"locality"
},
  "geometry": {"coordinates":[29.74004,0.30763],"type":"Point"}
}