{
  "type": "Feature",
  "properties": {
    "gn:admin1_code":"8.0",
    "gn:asciiname":"Mansonde",
    "gn:country_code":"CD",
    "gn:dem":482,
    "gn:feature_class":"P",
    "gn:feature_code":"PPL",
    "gn:name":"Mansonde",
    "gn:population":0,
    "gn:timezone":"Africa/Kinshasa",
    "iso:country":"CD",
    "wof:name":"Mansonde",
    "wof:placetype":"locality"
},
  "geometry": {"coordinates":[14.86019,-5.76312],"type":"Point"}
}