{
  "type": "Feature",
  "properties": {
    "gn:admin1_code":"23.0",
    "gn:asciiname":"Pongo",
    "gn:country_code":"CD",
    "gn:dem":800,
    "gn:feature_class":"P",
    "gn:feature_code":"PPL",
    "gn:name":"Pongo",
    "gn:population":0,
    "gn:timezone":"Africa/Lubumbashi",
    "iso:country":"CD",
    "wof:name":"Pongo",
    "wof:placetype":"locality"
},
  "geometry": {"coordinates":[22.24014,-6.4656],"type":"Point"}
}