{
  "type": "Feature",
  "properties": {
    "gn:admin1_code":"26.0",
    "gn:asciiname":"Mbomo",
    "gn:country_code":"CD",
    "gn:dem":514,
    "gn:feature_class":"P",
    "gn:feature_code":"PPL",
    "gn:name":"Mbomo",
    "gn:population":0,
    "gn:timezone":"Africa/Kinshasa",
    "iso:country":"CD",
    "wof:name":"Mbomo",
    "wof:placetype":"locality"
},
  "geometry": {"coordinates":[22.55495,3.64854],"type":"Point"}
}