{
  "type": "Feature",
  "properties": {
    "gn:admin1_code":"11.0",
    "gn:asciiname":"Makingu",
    "gn:country_code":"CD",
    "gn:dem":1744,
    "gn:feature_class":"P",
    "gn:feature_code":"PPL",
    "gn:name":"Makingu",
    "gn:population":0,
    "gn:timezone":"Africa/Lubumbashi",
    "iso:country":"CD",
    "wof:name":"Makingu",
    "wof:placetype":"locality"
},
  "geometry": {"coordinates":[28.89902,-0.68003],"type":"Point"}
}