{
  "type": "Feature",
  "properties": {
    "gn:admin1_code":"22.0",
    "gn:asciiname":"Kakwata",
    "gn:country_code":"CD",
    "gn:dem":1163,
    "gn:feature_class":"P",
    "gn:feature_code":"PPL",
    "gn:name":"Kakwata",
    "gn:population":0,
    "gn:timezone":"Africa/Lubumbashi",
    "iso:country":"CD",
    "name:und_x_variant":[
        "Kakwapa",
        "Kakwata"
    ],
    "wof:name":"Kakwata",
    "wof:placetype":"locality"
},
  "geometry": {"coordinates":[24.85,-10.61667],"type":"Point"}
}