{
  "type": "Feature",
  "properties": {
    "gn:admin1_code":"12.0",
    "gn:asciiname":"Musabaka",
    "gn:country_code":"CD",
    "gn:dem":798,
    "gn:feature_class":"P",
    "gn:feature_code":"PPL",
    "gn:name":"Musabaka",
    "gn:population":0,
    "gn:timezone":"Africa/Lubumbashi",
    "iso:country":"CD",
    "wof:name":"Musabaka",
    "wof:placetype":"locality"
},
  "geometry": {"coordinates":[29.03922,-4.29758],"type":"Point"}
}