{
  "type": "Feature",
  "properties": {
    "gn:admin1_code":"8.0",
    "gn:asciiname":"Luila",
    "gn:country_code":"CD",
    "gn:dem":371,
    "gn:feature_class":"P",
    "gn:feature_code":"PPL",
    "gn:name":"Luila",
    "gn:population":0,
    "gn:timezone":"Africa/Kinshasa",
    "iso:country":"CD",
    "name:und_x_variant":[
        "Luila I"
    ],
    "wof:name":"Luila",
    "wof:placetype":"locality"
},
  "geometry": {"coordinates":[15.06144,-4.54202],"type":"Point"}
}