{
  "type": "Feature",
  "properties": {
    "gn:admin1_code":"19.0",
    "gn:asciiname":"Mutanda",
    "gn:country_code":"CD",
    "gn:dem":771,
    "gn:feature_class":"P",
    "gn:feature_code":"PPL",
    "gn:name":"Mutanda",
    "gn:population":0,
    "gn:timezone":"Africa/Kinshasa",
    "iso:country":"CD",
    "name:ceb_x_preferred":[
        "Mutanda"
    ],
    "name:swe_x_preferred":[
        "Mutanda"
    ],
    "wof:name":"Mutanda",
    "wof:placetype":"locality"
},
  "geometry": {"coordinates":[18.30098,-7.71477],"type":"Point"}
}