{
  "type": "Feature",
  "properties": {
    "gn:admin1_code":"18.0",
    "gn:asciiname":"Mutumba",
    "gn:country_code":"CD",
    "gn:dem":670,
    "gn:feature_class":"P",
    "gn:feature_code":"PPL",
    "gn:name":"Mutumba",
    "gn:population":0,
    "gn:timezone":"Africa/Lubumbashi",
    "iso:country":"CD",
    "wof:name":"Mutumba",
    "wof:placetype":"locality"
},
  "geometry": {"coordinates":[21.35524,-6.4607],"type":"Point"}
}