{
  "type": "Feature",
  "properties": {
    "gn:admin1_code":"19.0",
    "gn:asciiname":"Tshikindji",
    "gn:country_code":"CD",
    "gn:dem":923,
    "gn:feature_class":"P",
    "gn:feature_code":"PPL",
    "gn:name":"Tshikindji",
    "gn:population":0,
    "gn:timezone":"Africa/Kinshasa",
    "iso:country":"CD",
    "wof:name":"Tshikindji",
    "wof:placetype":"locality"
},
  "geometry": {"coordinates":[19.53665,-7.04968],"type":"Point"}
}