{
  "type": "Feature",
  "properties": {
    "gn:admin1_code":"18.0",
    "gn:asciiname":"Boie-Kapinda",
    "gn:country_code":"CD",
    "gn:dem":671,
    "gn:feature_class":"P",
    "gn:feature_code":"PPL",
    "gn:name":"Boie-Kapinda",
    "gn:population":0,
    "gn:timezone":"Africa/Lubumbashi",
    "iso:country":"CD",
    "wof:name":"Boie-Kapinda",
    "wof:placetype":"locality"
},
  "geometry": {"coordinates":[21.31069,-6.70252],"type":"Point"}
}