{
  "type": "Feature",
  "properties": {
    "gn:admin1_code":"9.0",
    "gn:asciiname":"Gatuna",
    "gn:country_code":"CD",
    "gn:dem":1041,
    "gn:feature_class":"P",
    "gn:feature_code":"PPL",
    "gn:name":"Gatuna",
    "gn:population":0,
    "gn:timezone":"Africa/Lubumbashi",
    "iso:country":"CD",
    "wof:name":"Gatuna",
    "wof:placetype":"locality"
},
  "geometry": {"coordinates":[30.02111,1.435],"type":"Point"}
}