{
  "type": "Feature",
  "properties": {
    "gn:admin1_code":"22.0",
    "gn:asciiname":"Nguji",
    "gn:country_code":"CD",
    "gn:dem":1088,
    "gn:feature_class":"P",
    "gn:feature_code":"PPL",
    "gn:name":"Nguji",
    "gn:population":0,
    "gn:timezone":"Africa/Lubumbashi",
    "iso:country":"CD",
    "wof:name":"Nguji",
    "wof:placetype":"locality"
},
  "geometry": {"coordinates":[21.94262,-9.56461],"type":"Point"}
}