{
  "type": "Feature",
  "properties": {
    "gn:admin1_code":"8.0",
    "gn:asciiname":"Matundulu",
    "gn:country_code":"CD",
    "gn:dem":552,
    "gn:feature_class":"P",
    "gn:feature_code":"PPL",
    "gn:name":"Matundulu",
    "gn:population":0,
    "gn:timezone":"Africa/Kinshasa",
    "iso:country":"CD",
    "wof:name":"Matundulu",
    "wof:placetype":"locality"
},
  "geometry": {"coordinates":[14.88256,-5.36187],"type":"Point"}
}