{
  "type": "Feature",
  "properties": {
    "gn:admin1_code":"26.0",
    "gn:asciiname":"Bosua",
    "gn:country_code":"CD",
    "gn:dem":382,
    "gn:feature_class":"P",
    "gn:feature_code":"PPL",
    "gn:name":"Bosua",
    "gn:population":0,
    "gn:timezone":"Africa/Kinshasa",
    "iso:country":"CD",
    "wof:name":"Bosua",
    "wof:placetype":"locality"
},
  "geometry": {"coordinates":[20.78812000000001,3.89041],"type":"Point"}
}