{
  "type": "Feature",
  "properties": {
    "gn:admin1_code":"27.0",
    "gn:asciiname":"Mbulu",
    "gn:country_code":"CD",
    "gn:dem":608,
    "gn:feature_class":"P",
    "gn:feature_code":"PPL",
    "gn:name":"Mbulu",
    "gn:population":0,
    "gn:timezone":"Africa/Lubumbashi",
    "iso:country":"CD",
    "wof:name":"Mbulu",
    "wof:placetype":"locality"
},
  "geometry": {"coordinates":[24.55,-3.55],"type":"Point"}
}