{
  "type": "Feature",
  "properties": {
    "gn:admin1_code":"27.0",
    "gn:asciiname":"Mbulu",
    "gn:country_code":"CD",
    "gn:dem":608,
    "gn:feature_class":"P",
    "gn:feature_code":"PPL",
    "gn:name":"Mbulu",
    "gn:population":0,
    "gn:timezone":"Africa/Lubumbashi",
    "iso:country":"CD",
    "name:ara_x_preferred":[
        "\u0645\u0628\u0648\u0644\u0648"
    ],
    "name:ben_x_preferred":[
        "\u098f\u09ae\u09cd\u09ac\u09c1\u09b2\u09c1"
    ],
    "name:deu_x_preferred":[
        "Mbulu"
    ],
    "name:ell_x_preferred":[
        "\u039c\u03c0\u03bf\u03cd\u03bb\u03bf\u03c5"
    ],
    "name:fas_x_preferred":[
        "\u0627\u0645\u0628\u0648\u0644\u0648"
    ],
    "name:fra_x_preferred":[
        "Mbulu"
    ],
    "name:heb_x_preferred":[
        "\u05de\u05d1\u05d5\u05dc\u05d5"
    ],
    "name:hin_x_preferred":[
        "\u092e\u094d\u092c\u0942\u0932\u0942"
    ],
    "name:hun_x_preferred":[
        "Mbulu"
    ],
    "name:ind_x_preferred":[
        "Mbulu"
    ],
    "name:jpn_x_preferred":[
        "\u30e0\u30d6\u30eb"
    ],
    "name:kor_x_preferred":[
        "\uc74c\ubd88\ub8e8"
    ],
    "name:pol_x_preferred":[
        "Mbulu"
    ],
    "name:por_x_preferred":[
        "Mbulu"
    ],
    "name:rus_x_preferred":[
        "\u041c\u0431\u0443\u043b\u0443"
    ],
    "name:spa_x_preferred":[
        "Mbulu"
    ],
    "name:swa_x_preferred":[
        "Mbulu mjini"
    ],
    "name:swe_x_preferred":[
        "Mbulu"
    ],
    "name:tur_x_preferred":[
        "Mbulu"
    ],
    "name:ukr_x_preferred":[
        "\u041c\u0431\u0443\u043b\u0443"
    ],
    "name:urd_x_preferred":[
        "\u0627\u06cc\u0645\u0628\u0648\u0644\u0648"
    ],
    "name:vie_x_preferred":[
        "Mbulu"
    ],
    "name:zho_cn_x_preferred":[
        "\u59c6\u5e03\u5362"
    ],
    "name:zho_tw_x_preferred":[
        "\u59c6\u5e03\u76e7"
    ],
    "wof:name":"Mbulu",
    "wof:placetype":"locality"
},
  "geometry": {"coordinates":[24.55,-3.55],"type":"Point"}
}