{
  "type": "Feature",
  "properties": {
    "gn:admin1_code":"18.0",
    "gn:asciiname":"Ibanga",
    "gn:country_code":"CD",
    "gn:dem":597,
    "gn:feature_class":"P",
    "gn:feature_code":"PPL",
    "gn:name":"Ibanga",
    "gn:population":0,
    "gn:timezone":"Africa/Lubumbashi",
    "iso:country":"CD",
    "name:und_x_variant":[
        "Kembe-Ibanga"
    ],
    "wof:name":"Ibanga",
    "wof:placetype":"locality"
},
  "geometry": {"coordinates":[20.33789,-5.26418],"type":"Point"}
}