{
  "type": "Feature",
  "properties": {
    "gn:admin1_code":"30.0",
    "gn:asciiname":"Batibungu",
    "gn:country_code":"CD",
    "gn:dem":464,
    "gn:feature_class":"P",
    "gn:feature_code":"PPL",
    "gn:name":"Batibungu",
    "gn:population":0,
    "gn:timezone":"Africa/Lubumbashi",
    "iso:country":"CD",
    "name:und_x_variant":[
        "Simba",
        "Batibungu"
    ],
    "wof:name":"Batibungu",
    "wof:placetype":"locality"
},
  "geometry": {"coordinates":[24.86408,-0.77417],"type":"Point"}
}