{
  "type": "Feature",
  "properties": {
    "gn:admin1_code":"30.0",
    "gn:asciiname":"Mombana",
    "gn:country_code":"CD",
    "gn:dem":427,
    "gn:feature_class":"P",
    "gn:feature_code":"PPL",
    "gn:name":"Mombana",
    "gn:population":0,
    "gn:timezone":"Africa/Lubumbashi",
    "iso:country":"CD",
    "wof:name":"Mombana",
    "wof:placetype":"locality"
},
  "geometry": {"coordinates":[24.17301,1.79888],"type":"Point"}
}