{
  "type": "Feature",
  "properties": {
    "gn:admin1_code":"20.0",
    "gn:asciiname":"Mitsumbatshi",
    "gn:country_code":"CD",
    "gn:dem":592,
    "gn:feature_class":"P",
    "gn:feature_code":"PPL",
    "gn:name":"Mitsumbatshi",
    "gn:population":0,
    "gn:timezone":"Africa/Kinshasa",
    "iso:country":"CD",
    "wof:name":"Mitsumbatshi",
    "wof:placetype":"locality"
},
  "geometry": {"coordinates":[19.80199,-6.06832],"type":"Point"}
}