{
  "type": "Feature",
  "properties": {
    "gn:admin1_code":"15.0",
    "gn:asciiname":"Kakipango",
    "gn:country_code":"CD",
    "gn:dem":1091,
    "gn:feature_class":"P",
    "gn:feature_code":"PPL",
    "gn:name":"Kakipango",
    "gn:population":0,
    "gn:timezone":"Africa/Lubumbashi",
    "iso:country":"CD",
    "wof:name":"Kakipango",
    "wof:placetype":"locality"
},
  "geometry": {"coordinates":[24.52063,-8.82155],"type":"Point"}
}