{
  "type": "Feature",
  "properties": {
    "gn:admin1_code":"21.0",
    "gn:asciiname":"Kesonkolo",
    "gn:country_code":"CD",
    "gn:dem":796,
    "gn:feature_class":"P",
    "gn:feature_code":"PPL",
    "gn:name":"Kesonkolo",
    "gn:population":0,
    "gn:timezone":"Africa/Lubumbashi",
    "iso:country":"CD",
    "wof:name":"Kesonkolo",
    "wof:placetype":"locality"
},
  "geometry": {"coordinates":[25.26081,-6.20359],"type":"Point"}
}