{
  "type": "Feature",
  "properties": {
    "gn:admin1_code":"17.0",
    "gn:asciiname":"Masiliko",
    "gn:country_code":"CD",
    "gn:dem":926,
    "gn:feature_class":"P",
    "gn:feature_code":"PPL",
    "gn:name":"Masiliko",
    "gn:population":0,
    "gn:timezone":"Africa/Lubumbashi",
    "iso:country":"CD",
    "name:fra_x_preferred":[
        "Masiliko"
    ],
    "wof:name":"Masiliko",
    "wof:placetype":"locality"
},
  "geometry": {"coordinates":[29.2252,1.35116],"type":"Point"}
}