{
  "type": "Feature",
  "properties": {
    "gn:admin1_code":"8.0",
    "gn:asciiname":"Kinsuki",
    "gn:country_code":"CD",
    "gn:dem":828,
    "gn:feature_class":"P",
    "gn:feature_code":"PPL",
    "gn:name":"Kinsuki",
    "gn:population":0,
    "gn:timezone":"Africa/Kinshasa",
    "iso:country":"CD",
    "wof:name":"Kinsuki",
    "wof:placetype":"locality"
},
  "geometry": {"coordinates":[14.93042,-5.70969],"type":"Point"}
}