{
  "type": "Feature",
  "properties": {
    "gn:admin1_code":"8.0",
    "gn:asciiname":"Kimbata-Finda",
    "gn:country_code":"CD",
    "gn:dem":606,
    "gn:feature_class":"P",
    "gn:feature_code":"PPL",
    "gn:name":"Kimbata-Finda",
    "gn:population":0,
    "gn:timezone":"Africa/Kinshasa",
    "iso:country":"CD",
    "wof:name":"Kimbata-Finda",
    "wof:placetype":"locality"
},
  "geometry": {"coordinates":[15.49836,-5.15492],"type":"Point"}
}