{
  "type": "Feature",
  "properties": {
    "gn:admin1_code":"19.0",
    "gn:asciiname":"Kapinipini",
    "gn:country_code":"CD",
    "gn:dem":894,
    "gn:feature_class":"P",
    "gn:feature_code":"PPL",
    "gn:name":"Kapinipini",
    "gn:population":0,
    "gn:timezone":"Africa/Kinshasa",
    "iso:country":"CD",
    "wof:name":"Kapinipini",
    "wof:placetype":"locality"
},
  "geometry": {"coordinates":[18.281,-7.94502],"type":"Point"}
}