{
  "type": "Feature",
  "properties": {
    "gn:admin1_code":"22.0",
    "gn:asciiname":"Mwakahila",
    "gn:country_code":"CD",
    "gn:dem":1076,
    "gn:feature_class":"P",
    "gn:feature_code":"PPL",
    "gn:name":"Mwakahila",
    "gn:population":0,
    "gn:timezone":"Africa/Lubumbashi",
    "iso:country":"CD",
    "wof:name":"Mwakahila",
    "wof:placetype":"locality"
},
  "geometry": {"coordinates":[22.25455,-9.78999],"type":"Point"}
}