{
  "type": "Feature",
  "properties": {
    "gn:admin1_code":"20.0",
    "gn:asciiname":"Kinamba",
    "gn:country_code":"CD",
    "gn:dem":745,
    "gn:feature_class":"P",
    "gn:feature_code":"PPL",
    "gn:name":"Kinamba",
    "gn:population":0,
    "gn:timezone":"Africa/Kinshasa",
    "iso:country":"CD",
    "name:und_x_variant":[
        "Kiwamba",
        "Kinamba"
    ],
    "wof:name":"Kinamba",
    "wof:placetype":"locality"
},
  "geometry": {"coordinates":[18.66006,-5.68174],"type":"Point"}
}