{
  "type": "Feature",
  "properties": {
    "gn:admin1_code":"21.0",
    "gn:asciiname":"Kibanga",
    "gn:country_code":"CD",
    "gn:dem":798,
    "gn:feature_class":"P",
    "gn:feature_code":"PPL",
    "gn:name":"Kibanga",
    "gn:population":0,
    "gn:timezone":"Africa/Lubumbashi",
    "iso:country":"CD",
    "wof:name":"Kibanga",
    "wof:placetype":"locality"
},
  "geometry": {"coordinates":[24.09019,-6.30688],"type":"Point"}
}