{
  "type": "Feature",
  "properties": {
    "gn:admin1_code":"15.0",
    "gn:asciiname":"Kiniakaka",
    "gn:country_code":"CD",
    "gn:dem":675,
    "gn:feature_class":"P",
    "gn:feature_code":"PPL",
    "gn:name":"Kiniakaka",
    "gn:population":0,
    "gn:timezone":"Africa/Lubumbashi",
    "iso:country":"CD",
    "name:und_x_variant":[
        "Kimiaka"
    ],
    "wof:name":"Kiniakaka",
    "wof:placetype":"locality"
},
  "geometry": {"coordinates":[26.04245,-9.43944],"type":"Point"}
}