{
  "type": "Feature",
  "properties": {
    "gn:admin1_code":"8.0",
    "gn:asciiname":"Nianga-Goyo",
    "gn:country_code":"CD",
    "gn:dem":573,
    "gn:feature_class":"P",
    "gn:feature_code":"PPL",
    "gn:name":"Nianga-Goyo",
    "gn:population":0,
    "gn:timezone":"Africa/Kinshasa",
    "iso:country":"CD",
    "wof:name":"Nianga-Goyo",
    "wof:placetype":"locality"
},
  "geometry": {"coordinates":[14.17078,-4.5223],"type":"Point"}
}