{
  "type": "Feature",
  "properties": {
    "gn:admin1_code":"29.0",
    "gn:asciiname":"Musofoi",
    "gn:country_code":"CD",
    "gn:dem":638,
    "gn:feature_class":"P",
    "gn:feature_code":"PPL",
    "gn:name":"Musofoi",
    "gn:population":0,
    "gn:timezone":"Africa/Lubumbashi",
    "iso:country":"CD",
    "name:und_x_variant":[
        "Musofoy",
        "Musofoi"
    ],
    "wof:name":"Musofoi",
    "wof:placetype":"locality"
},
  "geometry": {"coordinates":[27.81733,-7.47232],"type":"Point"}
}