{
  "type": "Feature",
  "properties": {
    "gn:admin1_code":"25.0",
    "gn:asciiname":"Gale",
    "gn:country_code":"CD",
    "gn:dem":374,
    "gn:feature_class":"P",
    "gn:feature_code":"PPL",
    "gn:name":"Gale",
    "gn:population":0,
    "gn:timezone":"Africa/Kinshasa",
    "iso:country":"CD",
    "name:ara_x_preferred":[
        "\u0631\u064a\u062d \u0647\u0648\u062c\u0627\u0621"
    ],
    "name:cat_x_preferred":[
        "Temporal"
    ],
    "name:dan_x_preferred":[
        "Kuling"
    ],
    "name:deu_x_preferred":[
        "Starkwind"
    ],
    "name:ita_x_preferred":[
        "Burrasca"
    ],
    "name:lav_x_preferred":[
        "Auka"
    ],
    "name:nno_x_preferred":[
        "Kuling"
    ],
    "name:nor_x_preferred":[
        "Kuling"
    ],
    "name:pol_x_preferred":[
        "Wicher"
    ],
    "name:scn_x_preferred":[
        "Burrasca"
    ],
    "name:spa_x_preferred":[
        "Temporal"
    ],
    "name:swe_x_preferred":[
        "Kuling"
    ],
    "wof:name":"Gale",
    "wof:placetype":"locality"
},
  "geometry": {"coordinates":[20.78385,3.08014],"type":"Point"}
}