{
  "type": "Feature",
  "properties": {
    "gn:admin1_code":"12.0",
    "gn:asciiname":"Nyakabere",
    "gn:country_code":"CD",
    "gn:dem":915,
    "gn:feature_class":"P",
    "gn:feature_code":"PPL",
    "gn:name":"Nyakabere",
    "gn:population":0,
    "gn:timezone":"Africa/Lubumbashi",
    "iso:country":"CD",
    "wof:name":"Nyakabere",
    "wof:placetype":"locality"
},
  "geometry": {"coordinates":[29.14306,-3.045],"type":"Point"}
}