{
  "type": "Feature",
  "properties": {
    "gn:admin1_code":"12.0",
    "gn:asciiname":"Hembe-Bitale",
    "gn:country_code":"CD",
    "gn:dem":1829,
    "gn:feature_class":"P",
    "gn:feature_code":"PPL",
    "gn:name":"Hembe-Bitale",
    "gn:population":0,
    "gn:timezone":"Africa/Lubumbashi",
    "iso:country":"CD",
    "wof:name":"Hembe-Bitale",
    "wof:placetype":"locality"
},
  "geometry": {"coordinates":[28.60121,-2.18515],"type":"Point"}
}