{
  "type": "Feature",
  "properties": {
    "gn:admin1_code":"27.0",
    "gn:asciiname":"Yoko",
    "gn:country_code":"CD",
    "gn:dem":538,
    "gn:feature_class":"P",
    "gn:feature_code":"PPL",
    "gn:name":"Yoko",
    "gn:population":0,
    "gn:timezone":"Africa/Lubumbashi",
    "iso:country":"CD",
    "name:ceb_x_preferred":[
        "Yoko"
    ],
    "name:deu_x_preferred":[
        "Yoko"
    ],
    "name:fin_x_preferred":[
        "Yoko"
    ],
    "name:fra_x_preferred":[
        "Yoko"
    ],
    "name:ita_x_preferred":[
        "Yoko"
    ],
    "name:jpn_x_preferred":[
        "\u30e8\u30fc\u30b3"
    ],
    "name:nld_x_preferred":[
        "Yoko"
    ],
    "name:rus_x_preferred":[
        "\u0419\u043e\u043a\u043e"
    ],
    "name:swe_x_preferred":[
        "Yoko"
    ],
    "wof:name":"Yoko",
    "wof:placetype":"locality"
},
  "geometry": {"coordinates":[23.81667,-2.48333],"type":"Point"}
}