{
  "type": "Feature",
  "properties": {
    "gn:admin1_code":"22.0",
    "gn:asciiname":"Kadelenge",
    "gn:country_code":"CD",
    "gn:dem":1232,
    "gn:feature_class":"P",
    "gn:feature_code":"PPL",
    "gn:name":"Kadelenge",
    "gn:population":0,
    "gn:timezone":"Africa/Lubumbashi",
    "iso:country":"CD",
    "wof:name":"Kadelenge",
    "wof:placetype":"locality"
},
  "geometry": {"coordinates":[24.46667,-10.96667],"type":"Point"}
}