{
  "type": "Feature",
  "properties": {
    "gn:admin1_code":"16.0",
    "gn:asciiname":"Sukune",
    "gn:country_code":"CD",
    "gn:dem":699,
    "gn:feature_class":"P",
    "gn:feature_code":"PPL",
    "gn:name":"Sukune",
    "gn:population":0,
    "gn:timezone":"Africa/Lubumbashi",
    "iso:country":"CD",
    "wof:name":"Sukune",
    "wof:placetype":"locality"
},
  "geometry": {"coordinates":[27.89156,3.87324],"type":"Point"}
}