{
  "type": "Feature",
  "properties": {
    "gn:admin1_code":"27.0",
    "gn:asciiname":"Kitele",
    "gn:country_code":"CD",
    "gn:dem":662,
    "gn:feature_class":"P",
    "gn:feature_code":"PPL",
    "gn:name":"Kitele",
    "gn:population":0,
    "gn:timezone":"Africa/Lubumbashi",
    "iso:country":"CD",
    "name:und_x_variant":[
        "Mininga Kitete",
        "Kitete",
        "Kitele"
    ],
    "wof:name":"Kitele",
    "wof:placetype":"locality"
},
  "geometry": {"coordinates":[24.92033,-4.83707],"type":"Point"}
}