{
  "type": "Feature",
  "properties": {
    "gn:admin1_code":"8.0",
    "gn:asciiname":"Kisala Mbati",
    "gn:country_code":"CD",
    "gn:dem":515,
    "gn:feature_class":"P",
    "gn:feature_code":"PPL",
    "gn:name":"Kisala Mbati",
    "gn:population":0,
    "gn:timezone":"Africa/Kinshasa",
    "iso:country":"CD",
    "name:und_x_variant":[
        "Salamadie"
    ],
    "wof:name":"Kisala Mbati",
    "wof:placetype":"locality"
},
  "geometry": {"coordinates":[15.10215,-4.78453],"type":"Point"}
}