{
  "type": "Feature",
  "properties": {
    "gn:admin1_code":"21.0",
    "gn:asciiname":"Kanda-Kanda",
    "gn:country_code":"CD",
    "gn:dem":832,
    "gn:feature_class":"P",
    "gn:feature_code":"PPL",
    "gn:name":"Kanda-Kanda",
    "gn:population":0,
    "gn:timezone":"Africa/Lubumbashi",
    "iso:country":"CD",
    "wof:name":"Kanda-Kanda",
    "wof:placetype":"locality"
},
  "geometry": {"coordinates":[23.60539,-6.93507],"type":"Point"}
}