{
  "type": "Feature",
  "properties": {
    "gn:admin1_code":"14.0",
    "gn:asciiname":"Mashiri",
    "gn:country_code":"CD",
    "gn:dem":1262,
    "gn:feature_class":"P",
    "gn:feature_code":"PPL",
    "gn:name":"Mashiri",
    "gn:population":0,
    "gn:timezone":"Africa/Lubumbashi",
    "iso:country":"CD",
    "wof:name":"Mashiri",
    "wof:placetype":"locality"
},
  "geometry": {"coordinates":[27.65422,-12.15423],"type":"Point"}
}