{
  "type": "Feature",
  "properties": {
    "gn:admin1_code":"21.0",
    "gn:asciiname":"Tshiamba Tshibuidi",
    "gn:country_code":"CD",
    "gn:dem":934,
    "gn:feature_class":"P",
    "gn:feature_code":"PPL",
    "gn:name":"Tshiamba Tshibuidi",
    "gn:population":0,
    "gn:timezone":"Africa/Lubumbashi",
    "iso:country":"CD",
    "name:und_x_variant":[
        "Tshiambe Tshibuidi"
    ],
    "wof:name":"Tshiamba Tshibuidi",
    "wof:placetype":"locality"
},
  "geometry": {"coordinates":[23.37804,-7.31477],"type":"Point"}
}