{
  "type": "Feature",
  "properties": {
    "gn:admin1_code":"23.0",
    "gn:asciiname":"Kabanga-Nzubu",
    "gn:country_code":"CD",
    "gn:dem":627,
    "gn:feature_class":"P",
    "gn:feature_code":"PPL",
    "gn:name":"Kabanga-Nzubu",
    "gn:population":0,
    "gn:timezone":"Africa/Lubumbashi",
    "iso:country":"CD",
    "wof:name":"Kabanga-Nzubu",
    "wof:placetype":"locality"
},
  "geometry": {"coordinates":[22.25709,-5.44554],"type":"Point"}
}