{
  "type": "Feature",
  "properties": {
    "gn:admin1_code":"18.0",
    "gn:asciiname":"Bena Kabamba",
    "gn:country_code":"CD",
    "gn:dem":585,
    "gn:feature_class":"P",
    "gn:feature_code":"PPL",
    "gn:name":"Bena Kabamba",
    "gn:population":0,
    "gn:timezone":"Africa/Lubumbashi",
    "iso:country":"CD",
    "wof:name":"Bena Kabamba",
    "wof:placetype":"locality"
},
  "geometry": {"coordinates":[22.0704,-4.89107],"type":"Point"}
}