{
  "type": "Feature",
  "properties": {
    "gn:admin1_code":"27.0",
    "gn:asciiname":"Lukangaka",
    "gn:country_code":"CD",
    "gn:dem":552,
    "gn:feature_class":"P",
    "gn:feature_code":"PPL",
    "gn:name":"Lukangaka",
    "gn:population":0,
    "gn:timezone":"Africa/Lubumbashi",
    "iso:country":"CD",
    "wof:name":"Lukangaka",
    "wof:placetype":"locality"
},
  "geometry": {"coordinates":[24.04211,-3.78065],"type":"Point"}
}