{
  "type": "Feature",
  "properties": {
    "gn:admin1_code":"28.0",
    "gn:asciiname":"Konza",
    "gn:country_code":"CD",
    "gn:dem":344,
    "gn:feature_class":"P",
    "gn:feature_code":"PPL",
    "gn:name":"Konza",
    "gn:population":0,
    "gn:timezone":"Africa/Kinshasa",
    "iso:country":"CD",
    "name:ara_x_preferred":[
        "\u0643\u0648\u0646\u0632\u0627"
    ],
    "name:ben_x_preferred":[
        "\u0995\u09cb\u099e\u09cd\u099c\u09be"
    ],
    "name:ceb_x_preferred":[
        "Konza"
    ],
    "name:ell_x_preferred":[
        "\u039a\u03cc\u03bc\u03bd\u03b6\u03b1"
    ],
    "name:fas_x_preferred":[
        "\u06a9\u0648\u0646\u0632\u0627"
    ],
    "name:fra_x_preferred":[
        "Konza"
    ],
    "name:heb_x_preferred":[
        "\u05e7\u05d5\u05e0\u05d6\u05d4"
    ],
    "name:hin_x_preferred":[
        "\u0915\u094b\u0902\u091c\u093c\u093e"
    ],
    "name:hun_x_preferred":[
        "Konza"
    ],
    "name:ind_x_preferred":[
        "Konza"
    ],
    "name:ita_x_preferred":[
        "Konza"
    ],
    "name:jpn_x_preferred":[
        "\u30b3\u30f3\u30b6"
    ],
    "name:kor_x_preferred":[
        "\ucf58\uc790"
    ],
    "name:por_x_preferred":[
        "Konza"
    ],
    "name:rus_x_preferred":[
        "\u041a\u043e\u043d\u0437\u0430"
    ],
    "name:swe_x_preferred":[
        "Konza"
    ],
    "name:tur_x_preferred":[
        "Konza"
    ],
    "name:ukr_x_preferred":[
        "\u041a\u043e\u043d\u0437\u0430"
    ],
    "name:urd_x_preferred":[
        "\u06a9\u0648\u0646\u0632\u0627"
    ],
    "name:vie_x_preferred":[
        "Konza"
    ],
    "name:zho_cn_x_preferred":[
        "\u5b54\u624e"
    ],
    "name:zho_tw_x_preferred":[
        "\u5eb7\u624e"
    ],
    "wof:name":"Konza",
    "wof:placetype":"locality"
},
  "geometry": {"coordinates":[18.75618,2.88862],"type":"Point"}
}