{
  "type": "Feature",
  "properties": {
    "gn:admin1_code":"28.0",
    "gn:asciiname":"Likata",
    "gn:country_code":"CD",
    "gn:dem":333,
    "gn:feature_class":"P",
    "gn:feature_code":"PPL",
    "gn:name":"Likata",
    "gn:population":0,
    "gn:timezone":"Africa/Kinshasa",
    "iso:country":"CD",
    "name:fra_x_preferred":[
        "Likata"
    ],
    "wof:name":"Likata",
    "wof:placetype":"locality"
},
  "geometry": {"coordinates":[19.20655,2.31487],"type":"Point"}
}