{
  "type": "Feature",
  "properties": {
    "gn:admin1_code":"26.0",
    "gn:asciiname":"Kogwa",
    "gn:country_code":"CD",
    "gn:dem":609,
    "gn:feature_class":"P",
    "gn:feature_code":"PPL",
    "gn:name":"Kogwa",
    "gn:population":0,
    "gn:timezone":"Africa/Kinshasa",
    "iso:country":"CD",
    "wof:name":"Kogwa",
    "wof:placetype":"locality"
},
  "geometry": {"coordinates":[20.26094,4.35201],"type":"Point"}
}