{
  "type": "Feature",
  "properties": {
    "gn:admin1_code":"25.0",
    "gn:asciiname":"Mongolo",
    "gn:country_code":"CD",
    "gn:dem":373,
    "gn:feature_class":"P",
    "gn:feature_code":"PPL",
    "gn:name":"Mongolo",
    "gn:population":0,
    "gn:timezone":"Africa/Kinshasa",
    "iso:country":"CD",
    "wof:name":"Mongolo",
    "wof:placetype":"locality"
},
  "geometry": {"coordinates":[20.352,2.25851],"type":"Point"}
}