{
  "type": "Feature",
  "properties": {
    "gn:admin1_code":"24.0",
    "gn:asciiname":"Izo",
    "gn:country_code":"CD",
    "gn:dem":356,
    "gn:feature_class":"P",
    "gn:feature_code":"PPL",
    "gn:name":"Izo",
    "gn:population":0,
    "gn:timezone":"Africa/Kinshasa",
    "iso:country":"CD",
    "wof:name":"Izo",
    "wof:placetype":"locality"
},
  "geometry": {"coordinates":[18.2838,-3.09816],"type":"Point"}
}