{
  "type": "Feature",
  "properties": {
    "gn:admin1_code":"27.0",
    "gn:asciiname":"Bongo Senge",
    "gn:country_code":"CD",
    "gn:dem":454,
    "gn:feature_class":"P",
    "gn:feature_code":"PPL",
    "gn:name":"Bongo Senge",
    "gn:population":0,
    "gn:timezone":"Africa/Lubumbashi",
    "iso:country":"CD",
    "wof:name":"Bongo Senge",
    "wof:placetype":"locality"
},
  "geometry": {"coordinates":[22.39454,-3.40476],"type":"Point"}
}