{
  "type": "Feature",
  "properties": {
    "gn:admin1_code":"8.0",
    "gn:asciiname":"Kikumbi",
    "gn:country_code":"CD",
    "gn:dem":505,
    "gn:feature_class":"P",
    "gn:feature_code":"PPL",
    "gn:name":"Kikumbi",
    "gn:population":0,
    "gn:timezone":"Africa/Kinshasa",
    "iso:country":"CD",
    "wof:name":"Kikumbi",
    "wof:placetype":"locality"
},
  "geometry": {"coordinates":[15.12056,-4.84417],"type":"Point"}
}