{
  "type": "Feature",
  "properties": {
    "gn:admin1_code":"19.0",
    "gn:asciiname":"Shamuhombo",
    "gn:country_code":"CD",
    "gn:dem":1111,
    "gn:feature_class":"P",
    "gn:feature_code":"PPL",
    "gn:name":"Shamuhombo",
    "gn:population":0,
    "gn:timezone":"Africa/Kinshasa",
    "iso:country":"CD",
    "wof:name":"Shamuhombo",
    "wof:placetype":"locality"
},
  "geometry": {"coordinates":[18.94843,-7.80362],"type":"Point"}
}