{
  "type": "Feature",
  "properties": {
    "gn:admin1_code":"4.0",
    "gn:asciiname":"Katengele",
    "gn:country_code":"CD",
    "gn:dem":755,
    "gn:feature_class":"P",
    "gn:feature_code":"PPL",
    "gn:name":"Katengele",
    "gn:population":0,
    "gn:timezone":"Africa/Lubumbashi",
    "iso:country":"CD",
    "wof:name":"Katengele",
    "wof:placetype":"locality"
},
  "geometry": {"coordinates":[23.67965,-6.45387],"type":"Point"}
}