{
  "type": "Feature",
  "properties": {
    "gn:admin1_code":"8.0",
    "gn:asciiname":"Nsaka",
    "gn:country_code":"CD",
    "gn:dem":530,
    "gn:feature_class":"P",
    "gn:feature_code":"PPL",
    "gn:name":"Nsaka",
    "gn:population":0,
    "gn:timezone":"Africa/Kinshasa",
    "iso:country":"CD",
    "wof:name":"Nsaka",
    "wof:placetype":"locality"
},
  "geometry": {"coordinates":[14.89501,-4.86623],"type":"Point"}
}