{
  "type": "Feature",
  "properties": {
    "gn:admin1_code":"26.0",
    "gn:asciiname":"Bogo",
    "gn:country_code":"CD",
    "gn:dem":396,
    "gn:feature_class":"P",
    "gn:feature_code":"PPL",
    "gn:name":"Bogo",
    "gn:population":0,
    "gn:timezone":"Africa/Kinshasa",
    "iso:country":"CD",
    "name:ceb_x_preferred":[
        "Bogo"
    ],
    "name:dan_x_preferred":[
        "Bog\u00f8"
    ],
    "name:deu_x_preferred":[
        "Bogo"
    ],
    "name:fra_x_preferred":[
        "Bogo"
    ],
    "name:ind_x_preferred":[
        "Bogo"
    ],
    "name:nld_x_preferred":[
        "Bogo"
    ],
    "name:pol_x_preferred":[
        "Bogo"
    ],
    "name:swe_x_preferred":[
        "Bogo"
    ],
    "wof:name":"Bogo",
    "wof:placetype":"locality"
},
  "geometry": {"coordinates":[20.77102,3.94351],"type":"Point"}
}