{
  "type": "Feature",
  "properties": {
    "gn:admin1_code":"8.0",
    "gn:asciiname":"Zoyo",
    "gn:country_code":"CD",
    "gn:dem":410,
    "gn:feature_class":"P",
    "gn:feature_code":"PPL",
    "gn:name":"Zoyo",
    "gn:population":0,
    "gn:timezone":"Africa/Kinshasa",
    "iso:country":"CD",
    "wof:name":"Zoyo",
    "wof:placetype":"locality"
},
  "geometry": {"coordinates":[14.63006,-5.56407],"type":"Point"}
}