{
  "type": "Feature",
  "properties": {
    "gn:admin1_code":"30.0",
    "gn:asciiname":"Limenga",
    "gn:country_code":"CD",
    "gn:dem":460,
    "gn:feature_class":"P",
    "gn:feature_code":"PPL",
    "gn:name":"Limenga",
    "gn:population":0,
    "gn:timezone":"Africa/Lubumbashi",
    "iso:country":"CD",
    "name:und_x_variant":[
        "Kalimendo",
        "Limenga"
    ],
    "wof:name":"Limenga",
    "wof:placetype":"locality"
},
  "geometry": {"coordinates":[24.94537,-0.80256],"type":"Point"}
}