{
  "type": "Feature",
  "properties": {
    "gn:admin1_code":"19.0",
    "gn:asciiname":"Shadjandja",
    "gn:country_code":"CD",
    "gn:dem":1065,
    "gn:feature_class":"P",
    "gn:feature_code":"PPL",
    "gn:name":"Shadjandja",
    "gn:population":0,
    "gn:timezone":"Africa/Kinshasa",
    "iso:country":"CD",
    "wof:name":"Shadjandja",
    "wof:placetype":"locality"
},
  "geometry": {"coordinates":[19.19547,-7.66379],"type":"Point"}
}