{
  "type": "Feature",
  "properties": {
    "gn:admin1_code":"27.0",
    "gn:asciiname":"Djoko",
    "gn:country_code":"CD",
    "gn:dem":496,
    "gn:feature_class":"P",
    "gn:feature_code":"PPL",
    "gn:name":"Djoko",
    "gn:population":0,
    "gn:timezone":"Africa/Lubumbashi",
    "iso:country":"CD",
    "wof:name":"Djoko",
    "wof:placetype":"locality"
},
  "geometry": {"coordinates":[22.05,-3.28333],"type":"Point"}
}