{
  "type": "Feature",
  "properties": {
    "gn:admin1_code":"23.0",
    "gn:asciiname":"Kasungu",
    "gn:country_code":"CD",
    "gn:dem":889,
    "gn:feature_class":"P",
    "gn:feature_code":"PPL",
    "gn:name":"Kasungu",
    "gn:population":0,
    "gn:timezone":"Africa/Lubumbashi",
    "iso:country":"CD",
    "name:azb_x_preferred":[
        "\u06a9\u0627\u0633\u0648\u0646\u0642\u0648"
    ],
    "name:ceb_x_preferred":[
        "Kasungu"
    ],
    "name:deu_x_preferred":[
        "Kasungu"
    ],
    "name:fas_x_preferred":[
        "\u06a9\u0627\u0633\u0648\u0646\u06af\u0648"
    ],
    "name:fra_x_preferred":[
        "Kasungu"
    ],
    "name:ita_x_preferred":[
        "Kasungu"
    ],
    "name:kat_x_preferred":[
        "\u10d9\u10d0\u10e1\u10e3\u10dc\u10d2\u10e3"
    ],
    "name:kor_x_preferred":[
        "\uce74\uc22d\uad6c"
    ],
    "name:lit_x_preferred":[
        "Kasungu"
    ],
    "name:nld_x_preferred":[
        "Kasungu"
    ],
    "name:nya_x_preferred":[
        "Kasungu"
    ],
    "name:pol_x_preferred":[
        "Kasungu"
    ],
    "name:por_x_preferred":[
        "Kasungu"
    ],
    "name:ron_x_preferred":[
        "Kasungu"
    ],
    "name:rus_x_preferred":[
        "\u041a\u0430\u0441\u0443\u043d\u0433\u0443"
    ],
    "name:spa_x_preferred":[
        "Kasungu"
    ],
    "name:tur_x_preferred":[
        "Kasungu"
    ],
    "name:zho_x_preferred":[
        "\u5361\u677e\u53e4"
    ],
    "wof:name":"Kasungu",
    "wof:placetype":"locality"
},
  "geometry": {"coordinates":[22.38935,-7.20517],"type":"Point"}
}