{
  "type": "Feature",
  "properties": {
    "gn:admin1_code":"23.0",
    "gn:asciiname":"Kasungu",
    "gn:country_code":"CD",
    "gn:dem":889,
    "gn:feature_class":"P",
    "gn:feature_code":"PPL",
    "gn:name":"Kasungu",
    "gn:population":0,
    "gn:timezone":"Africa/Lubumbashi",
    "iso:country":"CD",
    "wof:name":"Kasungu",
    "wof:placetype":"locality"
},
  "geometry": {"coordinates":[22.38935,-7.20517],"type":"Point"}
}