{
  "type": "Feature",
  "properties": {
    "gn:admin1_code":"18.0",
    "gn:asciiname":"Shakalunga",
    "gn:country_code":"CD",
    "gn:dem":694,
    "gn:feature_class":"P",
    "gn:feature_code":"PPL",
    "gn:name":"Shakalunga",
    "gn:population":0,
    "gn:timezone":"Africa/Lubumbashi",
    "iso:country":"CD",
    "wof:name":"Shakalunga",
    "wof:placetype":"locality"
},
  "geometry": {"coordinates":[20.83346,-7.18492],"type":"Point"}
}