{
  "type": "Feature",
  "properties": {
    "gn:admin1_code":"10.0",
    "gn:asciiname":"Amandanga",
    "gn:country_code":"CD",
    "gn:dem":594,
    "gn:feature_class":"P",
    "gn:feature_code":"PPL",
    "gn:name":"Amandanga",
    "gn:population":0,
    "gn:timezone":"Africa/Lubumbashi",
    "iso:country":"CD",
    "wof:name":"Amandanga",
    "wof:placetype":"locality"
},
  "geometry": {"coordinates":[26.90714,-0.96384],"type":"Point"}
}