{
  "type": "Feature",
  "properties": {
    "gn:admin1_code":"18.0",
    "gn:asciiname":"Tshinkembe",
    "gn:country_code":"CD",
    "gn:dem":830,
    "gn:feature_class":"P",
    "gn:feature_code":"PPL",
    "gn:name":"Tshinkembe",
    "gn:population":0,
    "gn:timezone":"Africa/Lubumbashi",
    "iso:country":"CD",
    "name:und_x_variant":[
        "Tshi Kembe"
    ],
    "wof:name":"Tshinkembe",
    "wof:placetype":"locality"
},
  "geometry": {"coordinates":[21.62323,-7.21564],"type":"Point"}
}