{
  "type": "Feature",
  "properties": {
    "gn:admin1_code":"23.0",
    "gn:asciiname":"Kitende Premiere",
    "gn:country_code":"CD",
    "gn:dem":541,
    "gn:feature_class":"P",
    "gn:feature_code":"PPL",
    "gn:name":"Kitende Premi\u00e8re",
    "gn:population":0,
    "gn:timezone":"Africa/Lubumbashi",
    "iso:country":"CD",
    "wof:name":"Kitende Premiere",
    "wof:placetype":"locality"
},
  "geometry": {"coordinates":[22.35491,-5.98335],"type":"Point"}
}