{
  "type": "Feature",
  "properties": {
    "gn:admin1_code":"8.0",
    "gn:asciiname":"Kinsako",
    "gn:country_code":"CD",
    "gn:dem":537,
    "gn:feature_class":"P",
    "gn:feature_code":"PPL",
    "gn:name":"Kinsako",
    "gn:population":0,
    "gn:timezone":"Africa/Kinshasa",
    "iso:country":"CD",
    "name:und_x_variant":[
        "Kinsoko"
    ],
    "wof:name":"Kinsako",
    "wof:placetype":"locality"
},
  "geometry": {"coordinates":[15.05132,-5.17272],"type":"Point"}
}