{
  "type": "Feature",
  "properties": {
    "gn:admin1_code":"19.0",
    "gn:asciiname":"Kikongo",
    "gn:country_code":"CD",
    "gn:dem":545,
    "gn:feature_class":"P",
    "gn:feature_code":"PPL",
    "gn:name":"Kikongo",
    "gn:population":0,
    "gn:timezone":"Africa/Kinshasa",
    "iso:country":"CD",
    "wof:name":"Kikongo",
    "wof:placetype":"locality"
},
  "geometry": {"coordinates":[17.51419,-4.47498],"type":"Point"}
}