{
  "type": "Feature",
  "properties": {
    "gn:admin1_code":"4.0",
    "gn:asciiname":"Bena-Kabetu",
    "gn:country_code":"CD",
    "gn:dem":571,
    "gn:feature_class":"P",
    "gn:feature_code":"PPL",
    "gn:name":"Bena-Kabetu",
    "gn:population":0,
    "gn:timezone":"Africa/Lubumbashi",
    "iso:country":"CD",
    "wof:name":"Bena-Kabetu",
    "wof:placetype":"locality"
},
  "geometry": {"coordinates":[23.70991,-6.14476],"type":"Point"}
}