{
  "type": "Feature",
  "properties": {
    "gn:admin1_code":"12.0",
    "gn:asciiname":"Yela",
    "gn:country_code":"CD",
    "gn:dem":608,
    "gn:feature_class":"P",
    "gn:feature_code":"PPL",
    "gn:name":"Yela",
    "gn:population":0,
    "gn:timezone":"Africa/Lubumbashi",
    "iso:country":"CD",
    "wof:name":"Yela",
    "wof:placetype":"locality"
},
  "geometry": {"coordinates":[27.38333,-2.43333],"type":"Point"}
}