{
  "type": "Feature",
  "properties": {
    "gn:admin1_code":"13.0",
    "gn:asciiname":"Zali",
    "gn:country_code":"CD",
    "gn:dem":627,
    "gn:feature_class":"P",
    "gn:feature_code":"PPL",
    "gn:name":"Zali",
    "gn:population":0,
    "gn:timezone":"Africa/Lubumbashi",
    "iso:country":"CD",
    "wof:name":"Zali",
    "wof:placetype":"locality"
},
  "geometry": {"coordinates":[25.92289,2.95407],"type":"Point"}
}