{
  "type": "Feature",
  "properties": {
    "gn:admin1_code":"10.0",
    "gn:asciiname":"Fataki",
    "gn:country_code":"CD",
    "gn:dem":758,
    "gn:feature_class":"P",
    "gn:feature_code":"PPL",
    "gn:name":"Fataki",
    "gn:population":0,
    "gn:timezone":"Africa/Lubumbashi",
    "iso:country":"CD",
    "wof:name":"Fataki",
    "wof:placetype":"locality"
},
  "geometry": {"coordinates":[27.76667,-4.86667],"type":"Point"}
}