{
  "type": "Feature",
  "properties": {
    "gn:admin1_code":"22.0",
    "gn:asciiname":"Saimbwanda",
    "gn:country_code":"CD",
    "gn:dem":1054,
    "gn:feature_class":"P",
    "gn:feature_code":"PPL",
    "gn:name":"Saimbwanda",
    "gn:population":0,
    "gn:timezone":"Africa/Lubumbashi",
    "iso:country":"CD",
    "wof:name":"Saimbwanda",
    "wof:placetype":"locality"
},
  "geometry": {"coordinates":[22.28254,-9.8558],"type":"Point"}
}