{
  "type": "Feature",
  "properties": {
    "gn:admin1_code":"19.0",
    "gn:asciiname":"Nzofu",
    "gn:country_code":"CD",
    "gn:dem":730,
    "gn:feature_class":"P",
    "gn:feature_code":"PPL",
    "gn:name":"Nzofu",
    "gn:population":0,
    "gn:timezone":"Africa/Kinshasa",
    "iso:country":"CD",
    "wof:name":"Nzofu",
    "wof:placetype":"locality"
},
  "geometry": {"coordinates":[17.44072,-5.56418],"type":"Point"}
}