{
  "type": "Feature",
  "properties": {
    "gn:admin1_code":"11.0",
    "gn:asciiname":"Katendele",
    "gn:country_code":"CD",
    "gn:dem":1066,
    "gn:feature_class":"P",
    "gn:feature_code":"PPL",
    "gn:name":"Katendele",
    "gn:population":0,
    "gn:timezone":"Africa/Lubumbashi",
    "iso:country":"CD",
    "wof:name":"Katendele",
    "wof:placetype":"locality"
},
  "geometry": {"coordinates":[28.64019,-0.38678],"type":"Point"}
}