{
  "type": "Feature",
  "properties": {
    "gn:admin1_code":"23.0",
    "gn:asciiname":"Mukanzo",
    "gn:country_code":"CD",
    "gn:dem":822,
    "gn:feature_class":"P",
    "gn:feature_code":"PPL",
    "gn:name":"Mukanzo",
    "gn:population":0,
    "gn:timezone":"Africa/Lubumbashi",
    "iso:country":"CD",
    "wof:name":"Mukanzo",
    "wof:placetype":"locality"
},
  "geometry": {"coordinates":[21.84729,-7.2744],"type":"Point"}
}