{
  "type": "Feature",
  "properties": {
    "gn:admin1_code":"27.0",
    "gn:asciiname":"Okanga-Mbala",
    "gn:country_code":"CD",
    "gn:dem":545,
    "gn:feature_class":"P",
    "gn:feature_code":"PPL",
    "gn:name":"Okanga-Mbala",
    "gn:population":0,
    "gn:timezone":"Africa/Lubumbashi",
    "iso:country":"CD",
    "wof:name":"Okanga-Mbala",
    "wof:placetype":"locality"
},
  "geometry": {"coordinates":[23.85,-2.96667],"type":"Point"}
}