{
  "type": "Feature",
  "properties": {
    "gn:admin1_code":"12.0",
    "gn:asciiname":"Bisiege",
    "gn:country_code":"CD",
    "gn:dem":643,
    "gn:feature_class":"P",
    "gn:feature_code":"PPL",
    "gn:name":"Bisiege",
    "gn:population":0,
    "gn:timezone":"Africa/Lubumbashi",
    "iso:country":"CD",
    "wof:name":"Bisiege",
    "wof:placetype":"locality"
},
  "geometry": {"coordinates":[27.43333,-3.91667],"type":"Point"}
}