{
  "type": "Feature",
  "properties": {
    "gn:admin1_code":"13.0",
    "gn:asciiname":"Nemanzi",
    "gn:country_code":"CD",
    "gn:dem":639,
    "gn:feature_class":"P",
    "gn:feature_code":"PPL",
    "gn:name":"Nemanzi",
    "gn:population":0,
    "gn:timezone":"Africa/Lubumbashi",
    "iso:country":"CD",
    "wof:name":"Nemanzi",
    "wof:placetype":"locality"
},
  "geometry": {"coordinates":[26.26043,2.91379],"type":"Point"}
}