{
  "type": "Feature",
  "properties": {
    "gn:admin1_code":"25.0",
    "gn:asciiname":"Mombwandja",
    "gn:country_code":"CD",
    "gn:dem":442,
    "gn:feature_class":"P",
    "gn:feature_code":"PPL",
    "gn:name":"Mombwandja",
    "gn:population":0,
    "gn:timezone":"Africa/Kinshasa",
    "iso:country":"CD",
    "wof:name":"Mombwandja",
    "wof:placetype":"locality"
},
  "geometry": {"coordinates":[22.43333,1.93333],"type":"Point"}
}