{
  "type": "Feature",
  "properties": {
    "gn:admin1_code":"20.0",
    "gn:asciiname":"Kikasi",
    "gn:country_code":"CD",
    "gn:dem":508,
    "gn:feature_class":"P",
    "gn:feature_code":"PPL",
    "gn:name":"Kikasi",
    "gn:population":0,
    "gn:timezone":"Africa/Kinshasa",
    "iso:country":"CD",
    "wof:name":"Kikasi",
    "wof:placetype":"locality"
},
  "geometry": {"coordinates":[17.06932,-4.27055],"type":"Point"}
}