{
  "type": "Feature",
  "properties": {
    "gn:admin1_code":"14.0",
    "gn:asciiname":"Kaundu",
    "gn:country_code":"CD",
    "gn:dem":1069,
    "gn:feature_class":"P",
    "gn:feature_code":"PPL",
    "gn:name":"Kaundu",
    "gn:population":0,
    "gn:timezone":"Africa/Lubumbashi",
    "iso:country":"CD",
    "wof:name":"Kaundu",
    "wof:placetype":"locality"
},
  "geometry": {"coordinates":[27.63333,-8.96667],"type":"Point"}
}