{
  "type": "Feature",
  "properties": {
    "gn:admin1_code":"10.0",
    "gn:asciiname":"Alimasi",
    "gn:country_code":"CD",
    "gn:dem":582,
    "gn:feature_class":"P",
    "gn:feature_code":"PPL",
    "gn:name":"Alimasi",
    "gn:population":0,
    "gn:timezone":"Africa/Lubumbashi",
    "iso:country":"CD",
    "wof:name":"Alimasi",
    "wof:placetype":"locality"
},
  "geometry": {"coordinates":[26.46248,-3.31828],"type":"Point"}
}