{
  "type": "Feature",
  "properties": {
    "gn:admin1_code":"13.0",
    "gn:asciiname":"Pwopode",
    "gn:country_code":"CD",
    "gn:dem":527,
    "gn:feature_class":"P",
    "gn:feature_code":"PPL",
    "gn:name":"Pwopode",
    "gn:population":0,
    "gn:timezone":"Africa/Lubumbashi",
    "iso:country":"CD",
    "wof:name":"Pwopode",
    "wof:placetype":"locality"
},
  "geometry": {"coordinates":[24.88058,3.09684],"type":"Point"}
}