{
  "type": "Feature",
  "properties": {
    "gn:admin1_code":"23.0",
    "gn:asciiname":"Kabwebwe",
    "gn:country_code":"CD",
    "gn:dem":628,
    "gn:feature_class":"P",
    "gn:feature_code":"PPL",
    "gn:name":"Kabwebwe",
    "gn:population":0,
    "gn:timezone":"Africa/Lubumbashi",
    "iso:country":"CD",
    "wof:name":"Kabwebwe",
    "wof:placetype":"locality"
},
  "geometry": {"coordinates":[22.24721,-5.44084],"type":"Point"}
}