{
  "type": "Feature",
  "properties": {
    "gn:admin1_code":"28.0",
    "gn:asciiname":"Bokokole",
    "gn:country_code":"CD",
    "gn:dem":352,
    "gn:feature_class":"P",
    "gn:feature_code":"PPL",
    "gn:name":"Bokokole",
    "gn:population":0,
    "gn:timezone":"Africa/Kinshasa",
    "iso:country":"CD",
    "wof:name":"Bokokole",
    "wof:placetype":"locality"
},
  "geometry": {"coordinates":[19.22604,3.31678],"type":"Point"}
}