{
  "type": "Feature",
  "properties": {
    "gn:admin1_code":"21.0",
    "gn:asciiname":"Kamatanda",
    "gn:country_code":"CD",
    "gn:dem":531,
    "gn:feature_class":"P",
    "gn:feature_code":"PPL",
    "gn:name":"Kamatanda",
    "gn:population":0,
    "gn:timezone":"Africa/Lubumbashi",
    "iso:country":"CD",
    "wof:name":"Kamatanda",
    "wof:placetype":"locality"
},
  "geometry": {"coordinates":[25.93333,-5.16667],"type":"Point"}
}