{
  "type": "Feature",
  "properties": {
    "gn:admin1_code":"14.0",
    "gn:asciiname":"Lunande",
    "gn:country_code":"CD",
    "gn:dem":955,
    "gn:feature_class":"P",
    "gn:feature_code":"PPL",
    "gn:name":"Lunande",
    "gn:population":0,
    "gn:timezone":"Africa/Lubumbashi",
    "iso:country":"CD",
    "wof:name":"Lunande",
    "wof:placetype":"locality"
},
  "geometry": {"coordinates":[27.26667,-9.26667],"type":"Point"}
}