{
  "type": "Feature",
  "properties": {
    "gn:admin1_code":"28.0",
    "gn:asciiname":"Budjinga",
    "gn:country_code":"CD",
    "gn:dem":347,
    "gn:feature_class":"P",
    "gn:feature_code":"PPL",
    "gn:name":"Budjinga",
    "gn:population":0,
    "gn:timezone":"Africa/Kinshasa",
    "iso:country":"CD",
    "wof:name":"Budjinga",
    "wof:placetype":"locality"
},
  "geometry": {"coordinates":[18.68065,2.34509],"type":"Point"}
}