{
  "type": "Feature",
  "properties": {
    "gn:admin1_code":"19.0",
    "gn:asciiname":"Tshishimbi",
    "gn:country_code":"CD",
    "gn:dem":948,
    "gn:feature_class":"P",
    "gn:feature_code":"PPL",
    "gn:name":"Tshishimbi",
    "gn:population":0,
    "gn:timezone":"Africa/Kinshasa",
    "iso:country":"CD",
    "wof:name":"Tshishimbi",
    "wof:placetype":"locality"
},
  "geometry": {"coordinates":[18.38633,-7.92128],"type":"Point"}
}