{
  "type": "Feature",
  "properties": {
    "gn:admin1_code":"24.0",
    "gn:asciiname":"Inunu",
    "gn:country_code":"CD",
    "gn:dem":292,
    "gn:feature_class":"P",
    "gn:feature_code":"PPL",
    "gn:name":"Inunu",
    "gn:population":0,
    "gn:timezone":"Africa/Kinshasa",
    "iso:country":"CD",
    "wof:name":"Inunu",
    "wof:placetype":"locality"
},
  "geometry": {"coordinates":[18.36667000000001,-2.16667],"type":"Point"}
}