{
  "type": "Feature",
  "properties": {
    "gn:admin1_code":"21.0",
    "gn:asciiname":"Katunga",
    "gn:country_code":"CD",
    "gn:dem":774,
    "gn:feature_class":"P",
    "gn:feature_code":"PPL",
    "gn:name":"Katunga",
    "gn:population":0,
    "gn:timezone":"Africa/Lubumbashi",
    "iso:country":"CD",
    "name:nld_x_preferred":[
        "Katunga"
    ],
    "wof:name":"Katunga",
    "wof:placetype":"locality"
},
  "geometry": {"coordinates":[24.74695,-6.08724],"type":"Point"}
}