{
  "type": "Feature",
  "properties": {
    "gn:admin1_code":"19.0",
    "gn:asciiname":"Mwambwambwa",
    "gn:country_code":"CD",
    "gn:dem":1122,
    "gn:feature_class":"P",
    "gn:feature_code":"PPL",
    "gn:name":"Mwambwambwa",
    "gn:population":0,
    "gn:timezone":"Africa/Kinshasa",
    "iso:country":"CD",
    "wof:name":"Mwambwambwa",
    "wof:placetype":"locality"
},
  "geometry": {"coordinates":[19.12124,-7.91839],"type":"Point"}
}