{
  "type": "Feature",
  "properties": {
    "gn:admin1_code":"20.0",
    "gn:asciiname":"Kikwilu-Mbaka",
    "gn:country_code":"CD",
    "gn:dem":395,
    "gn:feature_class":"P",
    "gn:feature_code":"PPL",
    "gn:name":"Kikwilu-Mbaka",
    "gn:population":0,
    "gn:timezone":"Africa/Kinshasa",
    "iso:country":"CD",
    "wof:name":"Kikwilu-Mbaka",
    "wof:placetype":"locality"
},
  "geometry": {"coordinates":[17.17897,-4.26331],"type":"Point"}
}