{
  "type": "Feature",
  "properties": {
    "gn:admin1_code":"24.0",
    "gn:asciiname":"Bokutu",
    "gn:country_code":"CD",
    "gn:dem":312,
    "gn:feature_class":"P",
    "gn:feature_code":"PPL",
    "gn:name":"Bokutu",
    "gn:population":0,
    "gn:timezone":"Africa/Kinshasa",
    "iso:country":"CD",
    "wof:name":"Bokutu",
    "wof:placetype":"locality"
},
  "geometry": {"coordinates":[18.96115,-3.30928],"type":"Point"}
}