{
  "type": "Feature",
  "properties": {
    "gn:admin1_code":"11.0",
    "gn:asciiname":"Igalika",
    "gn:country_code":"CD",
    "gn:dem":1705,
    "gn:feature_class":"P",
    "gn:feature_code":"PPL",
    "gn:name":"Igalika",
    "gn:population":0,
    "gn:timezone":"Africa/Lubumbashi",
    "iso:country":"CD",
    "wof:name":"Igalika",
    "wof:placetype":"locality"
},
  "geometry": {"coordinates":[29.35,-0.36667],"type":"Point"}
}