{
  "type": "Feature",
  "properties": {
    "gn:admin1_code":"30.0",
    "gn:asciiname":"Botopi",
    "gn:country_code":"CD",
    "gn:dem":475,
    "gn:feature_class":"P",
    "gn:feature_code":"PPL",
    "gn:name":"Botopi",
    "gn:population":0,
    "gn:timezone":"Africa/Lubumbashi",
    "iso:country":"CD",
    "wof:name":"Botopi",
    "wof:placetype":"locality"
},
  "geometry": {"coordinates":[25.4255,1.42827],"type":"Point"}
}