{
  "type": "Feature",
  "properties": {
    "gn:admin1_code":"19.0",
    "gn:asciiname":"Kamwesi",
    "gn:country_code":"CD",
    "gn:dem":818,
    "gn:feature_class":"P",
    "gn:feature_code":"PPL",
    "gn:name":"Kamwesi",
    "gn:population":0,
    "gn:timezone":"Africa/Kinshasa",
    "iso:country":"CD",
    "wof:name":"Kamwesi",
    "wof:placetype":"locality"
},
  "geometry": {"coordinates":[17.81105,-7.91981],"type":"Point"}
}