{
  "type": "Feature",
  "properties": {
    "gn:admin1_code":"15.0",
    "gn:asciiname":"Kadia",
    "gn:country_code":"CD",
    "gn:dem":562,
    "gn:feature_class":"P",
    "gn:feature_code":"PPL",
    "gn:name":"Kadia",
    "gn:population":0,
    "gn:timezone":"Africa/Lubumbashi",
    "iso:country":"CD",
    "name:ceb_x_preferred":[
        "Kadia"
    ],
    "name:swe_x_preferred":[
        "Kadia"
    ],
    "wof:name":"Kadia",
    "wof:placetype":"locality"
},
  "geometry": {"coordinates":[26.60253,-8.26442],"type":"Point"}
}