{
  "type": "Feature",
  "properties": {
    "gn:admin1_code":"22.0",
    "gn:asciiname":"Mulaba",
    "gn:country_code":"CD",
    "gn:dem":908,
    "gn:feature_class":"P",
    "gn:feature_code":"PPL",
    "gn:name":"Mulaba",
    "gn:population":0,
    "gn:timezone":"Africa/Lubumbashi",
    "iso:country":"CD",
    "name:und_x_variant":[
        "Muluba",
        "Mulaba"
    ],
    "wof:name":"Mulaba",
    "wof:placetype":"locality"
},
  "geometry": {"coordinates":[22.2747,-8.02917],"type":"Point"}
}