{
  "type": "Feature",
  "properties": {
    "gn:admin1_code":"4.0",
    "gn:asciiname":"Bena-Gandu",
    "gn:country_code":"CD",
    "gn:dem":722,
    "gn:feature_class":"P",
    "gn:feature_code":"PPL",
    "gn:name":"Bena-Gandu",
    "gn:population":0,
    "gn:timezone":"Africa/Lubumbashi",
    "iso:country":"CD",
    "name:und_x_variant":[
        "Gandu",
        "Bena-Gandu"
    ],
    "wof:name":"Bena-Gandu",
    "wof:placetype":"locality"
},
  "geometry": {"coordinates":[23.47379,-6.6063],"type":"Point"}
}