{
  "type": "Feature",
  "properties": {
    "gn:admin1_code":"27.0",
    "gn:asciiname":"Tshendjo",
    "gn:country_code":"CD",
    "gn:dem":532,
    "gn:feature_class":"P",
    "gn:feature_code":"PPL",
    "gn:name":"Tshendjo",
    "gn:population":0,
    "gn:timezone":"Africa/Lubumbashi",
    "iso:country":"CD",
    "wof:name":"Tshendjo",
    "wof:placetype":"locality"
},
  "geometry": {"coordinates":[22.51667,-4.13333],"type":"Point"}
}