{
  "type": "Feature",
  "properties": {
    "gn:admin1_code":"26.0",
    "gn:asciiname":"Bobadi-Moke",
    "gn:country_code":"CD",
    "gn:dem":410,
    "gn:feature_class":"P",
    "gn:feature_code":"PPL",
    "gn:name":"Bobadi-Moke",
    "gn:population":0,
    "gn:timezone":"Africa/Kinshasa",
    "iso:country":"CD",
    "wof:name":"Bobadi-Moke",
    "wof:placetype":"locality"
},
  "geometry": {"coordinates":[20.33415,3.22735],"type":"Point"}
}