{
  "type": "Feature",
  "properties": {
    "gn:admin1_code":"21.0",
    "gn:asciiname":"Kalongo",
    "gn:country_code":"CD",
    "gn:dem":759,
    "gn:feature_class":"P",
    "gn:feature_code":"PPL",
    "gn:name":"Kalongo",
    "gn:population":0,
    "gn:timezone":"Africa/Lubumbashi",
    "iso:country":"CD",
    "wof:name":"Kalongo",
    "wof:placetype":"locality"
},
  "geometry": {"coordinates":[23.64072,-6.76838],"type":"Point"}
}