{
  "type": "Feature",
  "properties": {
    "gn:admin1_code":"22.0",
    "gn:asciiname":"Saiela",
    "gn:country_code":"CD",
    "gn:dem":1073,
    "gn:feature_class":"P",
    "gn:feature_code":"PPL",
    "gn:name":"Saiela",
    "gn:population":0,
    "gn:timezone":"Africa/Lubumbashi",
    "iso:country":"CD",
    "wof:name":"Saiela",
    "wof:placetype":"locality"
},
  "geometry": {"coordinates":[23.68912000000001,-9.34113],"type":"Point"}
}