{
  "type": "Feature",
  "properties": {
    "gn:admin1_code":"29.0",
    "gn:asciiname":"Pofu",
    "gn:country_code":"CD",
    "gn:dem":685,
    "gn:feature_class":"P",
    "gn:feature_code":"PPL",
    "gn:name":"Pofu",
    "gn:population":0,
    "gn:timezone":"Africa/Lubumbashi",
    "iso:country":"CD",
    "name:und_x_variant":[
        "Potu",
        "Pofu"
    ],
    "wof:name":"Pofu",
    "wof:placetype":"locality"
},
  "geometry": {"coordinates":[26.27433,-5.85994],"type":"Point"}
}