{
  "type": "Feature",
  "properties": {
    "gn:admin1_code":"2.0",
    "gn:asciiname":"Bolombo-Bofoku",
    "gn:country_code":"CD",
    "gn:dem":358,
    "gn:feature_class":"P",
    "gn:feature_code":"PPL",
    "gn:name":"Bolombo-Bofoku",
    "gn:population":0,
    "gn:timezone":"Africa/Kinshasa",
    "iso:country":"CD",
    "wof:name":"Bolombo-Bofoku",
    "wof:placetype":"locality"
},
  "geometry": {"coordinates":[19.96667,0.53333],"type":"Point"}
}