{
  "type": "Feature",
  "properties": {
    "gn:admin1_code":"28.0",
    "gn:asciiname":"Boto",
    "gn:country_code":"CD",
    "gn:dem":411,
    "gn:feature_class":"P",
    "gn:feature_code":"PPL",
    "gn:name":"Boto",
    "gn:population":0,
    "gn:timezone":"Africa/Kinshasa",
    "iso:country":"CD",
    "wof:name":"Boto",
    "wof:placetype":"locality"
},
  "geometry": {"coordinates":[20.18871,2.49811],"type":"Point"}
}