{
  "type": "Feature",
  "properties": {
    "gn:admin1_code":"29.0",
    "gn:asciiname":"Kasonkomona",
    "gn:country_code":"CD",
    "gn:dem":1460,
    "gn:feature_class":"P",
    "gn:feature_code":"PPL",
    "gn:name":"Kasonkomona",
    "gn:population":0,
    "gn:timezone":"Africa/Lubumbashi",
    "iso:country":"CD",
    "wof:name":"Kasonkomona",
    "wof:placetype":"locality"
},
  "geometry": {"coordinates":[29.07814,-6.66574],"type":"Point"}
}