{
  "type": "Feature",
  "properties": {
    "gn:admin1_code":"19.0",
    "gn:asciiname":"Shamangwanga",
    "gn:country_code":"CD",
    "gn:dem":900,
    "gn:feature_class":"P",
    "gn:feature_code":"PPL",
    "gn:name":"Shamangwanga",
    "gn:population":0,
    "gn:timezone":"Africa/Kinshasa",
    "iso:country":"CD",
    "wof:name":"Shamangwanga",
    "wof:placetype":"locality"
},
  "geometry": {"coordinates":[18.5743,-6.69979],"type":"Point"}
}