{
  "type": "Feature",
  "properties": {
    "gn:admin1_code":"8.0",
    "gn:asciiname":"Kikeba",
    "gn:country_code":"CD",
    "gn:dem":467,
    "gn:feature_class":"P",
    "gn:feature_code":"PPL",
    "gn:name":"Kikeba",
    "gn:population":0,
    "gn:timezone":"Africa/Kinshasa",
    "iso:country":"CD",
    "wof:name":"Kikeba",
    "wof:placetype":"locality"
},
  "geometry": {"coordinates":[14.95068,-4.788],"type":"Point"}
}