{
  "type": "Feature",
  "properties": {
    "gn:admin1_code":"22.0",
    "gn:asciiname":"Mukenda",
    "gn:country_code":"CD",
    "gn:dem":1120,
    "gn:feature_class":"P",
    "gn:feature_code":"PPL",
    "gn:name":"Mukenda",
    "gn:population":0,
    "gn:timezone":"Africa/Lubumbashi",
    "iso:country":"CD",
    "wof:name":"Mukenda",
    "wof:placetype":"locality"
},
  "geometry": {"coordinates":[24.08409,-10.11195],"type":"Point"}
}