{
  "type": "Feature",
  "properties": {
    "gn:admin1_code":"28.0",
    "gn:asciiname":"Mokodjingo",
    "gn:country_code":"CD",
    "gn:dem":345,
    "gn:feature_class":"P",
    "gn:feature_code":"PPL",
    "gn:name":"Mokodjingo",
    "gn:population":0,
    "gn:timezone":"Africa/Kinshasa",
    "iso:country":"CD",
    "wof:name":"Mokodjingo",
    "wof:placetype":"locality"
},
  "geometry": {"coordinates":[18.76148,2.87151],"type":"Point"}
}