{
  "type": "Feature",
  "properties": {
    "gn:admin1_code":"22.0",
    "gn:asciiname":"Kazembe Kiapanshia",
    "gn:country_code":"CD",
    "gn:dem":1158,
    "gn:feature_class":"P",
    "gn:feature_code":"PPL",
    "gn:name":"Kazembe Kiapanshia",
    "gn:population":0,
    "gn:timezone":"Africa/Lubumbashi",
    "iso:country":"CD",
    "wof:name":"Kazembe Kiapanshia",
    "wof:placetype":"locality"
},
  "geometry": {"coordinates":[25.18333,-10.53333],"type":"Point"}
}