{
  "type": "Feature",
  "properties": {
    "gn:admin1_code":"22.0",
    "gn:asciiname":"Kakenge",
    "gn:country_code":"CD",
    "gn:dem":1070,
    "gn:feature_class":"P",
    "gn:feature_code":"PPL",
    "gn:name":"Kakenge",
    "gn:population":0,
    "gn:timezone":"Africa/Lubumbashi",
    "iso:country":"CD",
    "wof:name":"Kakenge",
    "wof:placetype":"locality"
},
  "geometry": {"coordinates":[22.90932,-9.35635],"type":"Point"}
}