{
  "type": "Feature",
  "properties": {
    "gn:admin1_code":"17.0",
    "gn:asciiname":"Aungba",
    "gn:country_code":"CD",
    "gn:dem":1315,
    "gn:feature_class":"P",
    "gn:feature_code":"PPL",
    "gn:name":"Aungba",
    "gn:population":0,
    "gn:timezone":"Africa/Lubumbashi",
    "iso:country":"CD",
    "wof:name":"Aungba",
    "wof:placetype":"locality"
},
  "geometry": {"coordinates":[30.50626,2.54456],"type":"Point"}
}