{
  "type": "Feature",
  "properties": {
    "gn:admin1_code":"6.0",
    "gn:asciiname":"Masina Sans Fil",
    "gn:country_code":"CD",
    "gn:dem":277,
    "gn:feature_class":"P",
    "gn:feature_code":"PPL",
    "gn:name":"Masina Sans Fil",
    "gn:population":0,
    "gn:timezone":"Africa/Kinshasa",
    "iso:country":"CD",
    "wof:name":"Masina Sans Fil",
    "wof:placetype":"locality"
},
  "geometry": {"coordinates":[15.37022,-4.37518],"type":"Point"}
}