{
  "type": "Feature",
  "properties": {
    "gn:admin1_code":"18.0",
    "gn:asciiname":"Tshinongo",
    "gn:country_code":"CD",
    "gn:dem":498,
    "gn:feature_class":"P",
    "gn:feature_code":"PPL",
    "gn:name":"Tshinongo",
    "gn:population":0,
    "gn:timezone":"Africa/Lubumbashi",
    "iso:country":"CD",
    "wof:name":"Tshinongo",
    "wof:placetype":"locality"
},
  "geometry": {"coordinates":[21.98333,-4.88333],"type":"Point"}
}