{
  "type": "Feature",
  "properties": {
    "gn:admin1_code":"16.0",
    "gn:asciiname":"Nesoro",
    "gn:country_code":"CD",
    "gn:dem":727,
    "gn:feature_class":"P",
    "gn:feature_code":"PPL",
    "gn:name":"Nesoro",
    "gn:population":0,
    "gn:timezone":"Africa/Lubumbashi",
    "iso:country":"CD",
    "wof:name":"Nesoro",
    "wof:placetype":"locality"
},
  "geometry": {"coordinates":[27.47742,2.6878],"type":"Point"}
}