{
  "type": "Feature",
  "properties": {
    "gn:admin1_code":"22.0",
    "gn:asciiname":"Shinsikwa",
    "gn:country_code":"CD",
    "gn:dem":1626,
    "gn:feature_class":"P",
    "gn:feature_code":"PPL",
    "gn:name":"Shinsikwa",
    "gn:population":0,
    "gn:timezone":"Africa/Lubumbashi",
    "iso:country":"CD",
    "wof:name":"Shinsikwa",
    "wof:placetype":"locality"
},
  "geometry": {"coordinates":[26.1688,-10.20103],"type":"Point"}
}