{
  "type": "Feature",
  "properties": {
    "gn:admin1_code":"22.0",
    "gn:asciiname":"Luwawa",
    "gn:country_code":"CD",
    "gn:dem":1045,
    "gn:feature_class":"P",
    "gn:feature_code":"PPL",
    "gn:name":"Luwawa",
    "gn:population":0,
    "gn:timezone":"Africa/Lubumbashi",
    "iso:country":"CD",
    "wof:name":"Luwawa",
    "wof:placetype":"locality"
},
  "geometry": {"coordinates":[22.13806,-9.05661],"type":"Point"}
}