{
  "type": "Feature",
  "properties": {
    "gn:admin1_code":"25.0",
    "gn:asciiname":"Mongiri",
    "gn:country_code":"CD",
    "gn:dem":419,
    "gn:feature_class":"P",
    "gn:feature_code":"PPL",
    "gn:name":"Mongiri",
    "gn:population":0,
    "gn:timezone":"Africa/Kinshasa",
    "iso:country":"CD",
    "name:und_x_variant":[
        "Mongili",
        "Mongiri"
    ],
    "wof:name":"Mongiri",
    "wof:placetype":"locality"
},
  "geometry": {"coordinates":[21.17645,2.98257],"type":"Point"}
}