{
  "type": "Feature",
  "properties": {
    "gn:admin1_code":"16.0",
    "gn:asciiname":"Amuapa",
    "gn:country_code":"CD",
    "gn:dem":766,
    "gn:feature_class":"P",
    "gn:feature_code":"PPL",
    "gn:name":"Amuapa",
    "gn:population":0,
    "gn:timezone":"Africa/Lubumbashi",
    "iso:country":"CD",
    "wof:name":"Amuapa",
    "wof:placetype":"locality"
},
  "geometry": {"coordinates":[27.5304,2.38903],"type":"Point"}
}