{
  "type": "Feature",
  "properties": {
    "gn:admin1_code":"19.0",
    "gn:asciiname":"Kasindji Mutete",
    "gn:country_code":"CD",
    "gn:dem":439,
    "gn:feature_class":"P",
    "gn:feature_code":"PPL",
    "gn:name":"Kasindji Mutete",
    "gn:population":0,
    "gn:timezone":"Africa/Kinshasa",
    "iso:country":"CD",
    "wof:name":"Kasindji Mutete",
    "wof:placetype":"locality"
},
  "geometry": {"coordinates":[16.48049,-5.32586],"type":"Point"}
}