{
  "type": "Feature",
  "properties": {
    "gn:admin1_code":"16.0",
    "gn:asciiname":"Batshuru",
    "gn:country_code":"CD",
    "gn:dem":811,
    "gn:feature_class":"P",
    "gn:feature_code":"PPL",
    "gn:name":"Batshuru",
    "gn:population":0,
    "gn:timezone":"Africa/Lubumbashi",
    "iso:country":"CD",
    "wof:name":"Batshuru",
    "wof:placetype":"locality"
},
  "geometry": {"coordinates":[28.22059,2.5042],"type":"Point"}
}