{
  "type": "Feature",
  "properties": {
    "gn:admin1_code":"20.0",
    "gn:asciiname":"Kintshua",
    "gn:country_code":"CD",
    "gn:dem":594,
    "gn:feature_class":"P",
    "gn:feature_code":"PPL",
    "gn:name":"Kintshua",
    "gn:population":0,
    "gn:timezone":"Africa/Kinshasa",
    "iso:country":"CD",
    "wof:name":"Kintshua",
    "wof:placetype":"locality"
},
  "geometry": {"coordinates":[19.73512,-4.36355],"type":"Point"}
}