{
  "type": "Feature",
  "properties": {
    "gn:admin1_code":"27.0",
    "gn:asciiname":"Lukangi",
    "gn:country_code":"CD",
    "gn:dem":598,
    "gn:feature_class":"P",
    "gn:feature_code":"PPL",
    "gn:name":"Lukangi",
    "gn:population":0,
    "gn:timezone":"Africa/Lubumbashi",
    "iso:country":"CD",
    "wof:name":"Lukangi",
    "wof:placetype":"locality"
},
  "geometry": {"coordinates":[23.93333,-3.51667],"type":"Point"}
}