{
  "type": "Feature",
  "properties": {
    "gn:admin1_code":"8.0",
    "gn:asciiname":"Gombe-Kyani",
    "gn:country_code":"CD",
    "gn:dem":483,
    "gn:feature_class":"P",
    "gn:feature_code":"PPL",
    "gn:name":"Gombe-Kyani",
    "gn:population":0,
    "gn:timezone":"Africa/Kinshasa",
    "iso:country":"CD",
    "name:und_x_variant":[
        "Gombe-Kyale"
    ],
    "wof:name":"Gombe-Kyani",
    "wof:placetype":"locality"
},
  "geometry": {"coordinates":[14.87828,-4.81689],"type":"Point"}
}