{
  "type": "Feature",
  "properties": {
    "gn:admin1_code":"17.0",
    "gn:asciiname":"Angarakini",
    "gn:country_code":"CD",
    "gn:dem":1197,
    "gn:feature_class":"P",
    "gn:feature_code":"PPL",
    "gn:name":"Angarakini",
    "gn:population":0,
    "gn:timezone":"Africa/Lubumbashi",
    "iso:country":"CD",
    "wof:name":"Angarakini",
    "wof:placetype":"locality"
},
  "geometry": {"coordinates":[30.63568,3.07341],"type":"Point"}
}