{
  "type": "Feature",
  "properties": {
    "gn:admin1_code":"10.0",
    "gn:asciiname":"Zumbu",
    "gn:country_code":"CD",
    "gn:dem":578,
    "gn:feature_class":"P",
    "gn:feature_code":"PPL",
    "gn:name":"Zumbu",
    "gn:population":0,
    "gn:timezone":"Africa/Lubumbashi",
    "iso:country":"CD",
    "wof:name":"Zumbu",
    "wof:placetype":"locality"
},
  "geometry": {"coordinates":[25.13333,-4.33333],"type":"Point"}
}