{
  "type": "Feature",
  "properties": {
    "gn:admin1_code":"14.0",
    "gn:asciiname":"Mumpepe",
    "gn:country_code":"CD",
    "gn:dem":1543,
    "gn:feature_class":"P",
    "gn:feature_code":"PPL",
    "gn:name":"Mumpepe",
    "gn:population":0,
    "gn:timezone":"Africa/Lubumbashi",
    "iso:country":"CD",
    "wof:name":"Mumpepe",
    "wof:placetype":"locality"
},
  "geometry": {"coordinates":[27.63167,-10.11732],"type":"Point"}
}