{
  "type": "Feature",
  "properties": {
    "gn:admin1_code":"15.0",
    "gn:asciiname":"Kamwela",
    "gn:country_code":"CD",
    "gn:dem":939,
    "gn:feature_class":"P",
    "gn:feature_code":"PPL",
    "gn:name":"Kamwela",
    "gn:population":0,
    "gn:timezone":"Africa/Lubumbashi",
    "iso:country":"CD",
    "name:und_x_variant":[
        "Kambela",
        "Kamwela"
    ],
    "wof:name":"Kamwela",
    "wof:placetype":"locality"
},
  "geometry": {"coordinates":[24.68858,-9.38808],"type":"Point"}
}