{
  "type": "Feature",
  "properties": {
    "gn:admin1_code":"22.0",
    "gn:asciiname":"Tshilundu",
    "gn:country_code":"CD",
    "gn:dem":927,
    "gn:feature_class":"P",
    "gn:feature_code":"PPL",
    "gn:name":"Tshilundu",
    "gn:population":0,
    "gn:timezone":"Africa/Lubumbashi",
    "iso:country":"CD",
    "wof:name":"Tshilundu",
    "wof:placetype":"locality"
},
  "geometry": {"coordinates":[22.60489,-8.44011],"type":"Point"}
}