{
  "type": "Feature",
  "properties": {
    "gn:admin1_code":"15.0",
    "gn:asciiname":"Kialwe",
    "gn:country_code":"CD",
    "gn:dem":598,
    "gn:feature_class":"P",
    "gn:feature_code":"PPL",
    "gn:name":"Kialwe",
    "gn:population":0,
    "gn:timezone":"Africa/Lubumbashi",
    "iso:country":"CD",
    "wof:name":"Kialwe",
    "wof:placetype":"locality"
},
  "geometry": {"coordinates":[26.35609,-8.88657],"type":"Point"}
}