{
  "type": "Feature",
  "properties": {
    "gn:admin1_code":"8.0",
    "gn:asciiname":"Mawawa",
    "gn:country_code":"CD",
    "gn:dem":442,
    "gn:feature_class":"P",
    "gn:feature_code":"PPL",
    "gn:name":"Mawawa",
    "gn:population":0,
    "gn:timezone":"Africa/Kinshasa",
    "iso:country":"CD",
    "wof:name":"Mawawa",
    "wof:placetype":"locality"
},
  "geometry": {"coordinates":[14.08036,-5.13401],"type":"Point"}
}