{
  "type": "Feature",
  "properties": {
    "gn:admin1_code":"28.0",
    "gn:asciiname":"Bunduka",
    "gn:country_code":"CD",
    "gn:dem":389,
    "gn:feature_class":"P",
    "gn:feature_code":"PPL",
    "gn:name":"Bunduka",
    "gn:population":0,
    "gn:timezone":"Africa/Kinshasa",
    "iso:country":"CD",
    "name:fra_x_preferred":[
        "Bunduka"
    ],
    "wof:name":"Bunduka",
    "wof:placetype":"locality"
},
  "geometry": {"coordinates":[19.29266,2.84628],"type":"Point"}
}