{
  "type": "Feature",
  "properties": {
    "gn:admin1_code":"27.0",
    "gn:asciiname":"Oswe",
    "gn:country_code":"CD",
    "gn:dem":522,
    "gn:feature_class":"P",
    "gn:feature_code":"PPL",
    "gn:name":"Oswe",
    "gn:population":0,
    "gn:timezone":"Africa/Lubumbashi",
    "iso:country":"CD",
    "wof:name":"Oswe",
    "wof:placetype":"locality"
},
  "geometry": {"coordinates":[22.91667,-3.71667],"type":"Point"}
}