{
  "type": "Feature",
  "properties": {
    "gn:admin1_code":"2.0",
    "gn:asciiname":"Likulunkuma",
    "gn:country_code":"CD",
    "gn:dem":355,
    "gn:feature_class":"P",
    "gn:feature_code":"PPL",
    "gn:name":"Likulunkuma",
    "gn:population":0,
    "gn:timezone":"Africa/Kinshasa",
    "iso:country":"CD",
    "wof:name":"Likulunkuma",
    "wof:placetype":"locality"
},
  "geometry": {"coordinates":[20.26667,0.93333],"type":"Point"}
}