{
  "type": "Feature",
  "properties": {
    "gn:admin1_code":"30.0",
    "gn:asciiname":"Bandjwade-Babubuzi",
    "gn:country_code":"CD",
    "gn:dem":416,
    "gn:feature_class":"P",
    "gn:feature_code":"PPL",
    "gn:name":"Bandjwade-Babubuzi",
    "gn:population":0,
    "gn:timezone":"Africa/Lubumbashi",
    "iso:country":"CD",
    "wof:name":"Bandjwade-Babubuzi",
    "wof:placetype":"locality"
},
  "geometry": {"coordinates":[25.25086,0.84423],"type":"Point"}
}