{
  "type": "Feature",
  "properties": {
    "gn:admin1_code":"19.0",
    "gn:asciiname":"Mwatshimbundu",
    "gn:country_code":"CD",
    "gn:dem":1099,
    "gn:feature_class":"P",
    "gn:feature_code":"PPL",
    "gn:name":"Mwatshimbundu",
    "gn:population":0,
    "gn:timezone":"Africa/Kinshasa",
    "iso:country":"CD",
    "wof:name":"Mwatshimbundu",
    "wof:placetype":"locality"
},
  "geometry": {"coordinates":[18.55081,-7.73504],"type":"Point"}
}