{
  "type": "Feature",
  "properties": {
    "gn:admin1_code":"22.0",
    "gn:asciiname":"Kaseka-Tambue",
    "gn:country_code":"CD",
    "gn:dem":1062,
    "gn:feature_class":"P",
    "gn:feature_code":"PPL",
    "gn:name":"Kaseka-Tambue",
    "gn:population":0,
    "gn:timezone":"Africa/Lubumbashi",
    "iso:country":"CD",
    "wof:name":"Kaseka-Tambue",
    "wof:placetype":"locality"
},
  "geometry": {"coordinates":[23.07818,-10.61638],"type":"Point"}
}