{
  "type": "Feature",
  "properties": {
    "gn:admin1_code":"12.0",
    "gn:asciiname":"Kifuko",
    "gn:country_code":"CD",
    "gn:dem":596,
    "gn:feature_class":"P",
    "gn:feature_code":"PPL",
    "gn:name":"Kifuko",
    "gn:population":0,
    "gn:timezone":"Africa/Lubumbashi",
    "iso:country":"CD",
    "wof:name":"Kifuko",
    "wof:placetype":"locality"
},
  "geometry": {"coordinates":[27.18333,-3.15],"type":"Point"}
}