{
  "type": "Feature",
  "properties": {
    "gn:admin1_code":"21.0",
    "gn:asciiname":"Mushia",
    "gn:country_code":"CD",
    "gn:dem":889,
    "gn:feature_class":"P",
    "gn:feature_code":"PPL",
    "gn:name":"Mushia",
    "gn:population":0,
    "gn:timezone":"Africa/Lubumbashi",
    "iso:country":"CD",
    "wof:name":"Mushia",
    "wof:placetype":"locality"
},
  "geometry": {"coordinates":[23.37639,-6.86976],"type":"Point"}
}