{
  "type": "Feature",
  "properties": {
    "gn:admin1_code":"19.0",
    "gn:asciiname":"Mwasamba",
    "gn:country_code":"CD",
    "gn:dem":1057,
    "gn:feature_class":"P",
    "gn:feature_code":"PPL",
    "gn:name":"Mwasamba",
    "gn:population":0,
    "gn:timezone":"Africa/Kinshasa",
    "iso:country":"CD",
    "wof:name":"Mwasamba",
    "wof:placetype":"locality"
},
  "geometry": {"coordinates":[18.68336,-7.49125],"type":"Point"}
}