{
  "type": "Feature",
  "properties": {
    "gn:admin1_code":"23.0",
    "gn:asciiname":"Tshibiaie",
    "gn:country_code":"CD",
    "gn:dem":678,
    "gn:feature_class":"P",
    "gn:feature_code":"PPL",
    "gn:name":"Tshibiaie",
    "gn:population":0,
    "gn:timezone":"Africa/Lubumbashi",
    "iso:country":"CD",
    "name:und_x_variant":[
        "Tshimbiale",
        "Tshibiaie"
    ],
    "wof:name":"Tshibiaie",
    "wof:placetype":"locality"
},
  "geometry": {"coordinates":[22.54104,-5.97891],"type":"Point"}
}