{
  "type": "Feature",
  "properties": {
    "gn:admin1_code":"4.0",
    "gn:asciiname":"Mulumba-Kapuku",
    "gn:country_code":"CD",
    "gn:dem":791,
    "gn:feature_class":"P",
    "gn:feature_code":"PPL",
    "gn:name":"Mulumba-Kapuku",
    "gn:population":0,
    "gn:timezone":"Africa/Lubumbashi",
    "iso:country":"CD",
    "name:und_x_variant":[
        "Mulumba",
        "Mulumbu",
        "Mulumba-Kapuku"
    ],
    "wof:name":"Mulumba-Kapuku",
    "wof:placetype":"locality"
},
  "geometry": {"coordinates":[23.10188,-6.27625],"type":"Point"}
}