{
  "type": "Feature",
  "properties": {
    "gn:admin1_code":"16.0",
    "gn:asciiname":"Gawa",
    "gn:country_code":"CD",
    "gn:dem":910,
    "gn:feature_class":"P",
    "gn:feature_code":"PPL",
    "gn:name":"Gawa",
    "gn:population":0,
    "gn:timezone":"Africa/Lubumbashi",
    "iso:country":"CD",
    "wof:name":"Gawa",
    "wof:placetype":"locality"
},
  "geometry": {"coordinates":[29.67099,3.10737],"type":"Point"}
}