{
  "type": "Feature",
  "properties": {
    "gn:admin1_code":"18.0",
    "gn:asciiname":"Kihombolo",
    "gn:country_code":"CD",
    "gn:dem":548,
    "gn:feature_class":"P",
    "gn:feature_code":"PPL",
    "gn:name":"Kihombolo",
    "gn:population":0,
    "gn:timezone":"Africa/Lubumbashi",
    "iso:country":"CD",
    "wof:name":"Kihombolo",
    "wof:placetype":"locality"
},
  "geometry": {"coordinates":[20.5118,-6.16596],"type":"Point"}
}