{
  "type": "Feature",
  "properties": {
    "gn:admin1_code":"23.0",
    "gn:asciiname":"Tshitadi",
    "gn:country_code":"CD",
    "gn:dem":841,
    "gn:feature_class":"P",
    "gn:feature_code":"PPL",
    "gn:name":"Tshitadi",
    "gn:population":0,
    "gn:timezone":"Africa/Lubumbashi",
    "iso:country":"CD",
    "wof:name":"Tshitadi",
    "wof:placetype":"locality"
},
  "geometry": {"coordinates":[22.29068,-6.78231],"type":"Point"}
}