{
  "type": "Feature",
  "properties": {
    "gn:admin1_code":"30.0",
    "gn:asciiname":"Banangau",
    "gn:country_code":"CD",
    "gn:dem":431,
    "gn:feature_class":"P",
    "gn:feature_code":"PPL",
    "gn:name":"Banangau",
    "gn:population":0,
    "gn:timezone":"Africa/Lubumbashi",
    "iso:country":"CD",
    "name:und_x_variant":[
        "Banangu",
        "Banangau"
    ],
    "wof:name":"Banangau",
    "wof:placetype":"locality"
},
  "geometry": {"coordinates":[25.25,0.36667],"type":"Point"}
}