{
  "type": "Feature",
  "properties": {
    "gn:admin1_code":"10.0",
    "gn:asciiname":"Masisi",
    "gn:country_code":"CD",
    "gn:dem":773,
    "gn:feature_class":"P",
    "gn:feature_code":"PPL",
    "gn:name":"Masisi",
    "gn:population":0,
    "gn:timezone":"Africa/Lubumbashi",
    "iso:country":"CD",
    "name:azb_x_preferred":[
        "\u0645\u0627\u0633\u06cc\u0633\u06cc"
    ],
    "name:fas_x_preferred":[
        "\u0645\u0627\u0633\u06cc\u0633\u06cc"
    ],
    "name:pol_x_preferred":[
        "Masisi"
    ],
    "name:ron_x_preferred":[
        "Masisi"
    ],
    "name:und_x_variant":[
        "Misisi"
    ],
    "wof:name":"Masisi",
    "wof:placetype":"locality"
},
  "geometry": {"coordinates":[28.63144,-4.72497],"type":"Point"}
}