{
  "type": "Feature",
  "properties": {
    "gn:admin1_code":"22.0",
    "gn:asciiname":"Tenge",
    "gn:country_code":"CD",
    "gn:dem":1101,
    "gn:feature_class":"P",
    "gn:feature_code":"PPL",
    "gn:name":"Tenge",
    "gn:population":0,
    "gn:timezone":"Africa/Lubumbashi",
    "iso:country":"CD",
    "wof:name":"Tenge",
    "wof:placetype":"locality"
},
  "geometry": {"coordinates":[23.99246,-9.45985],"type":"Point"}
}