{
  "type": "Feature",
  "properties": {
    "gn:admin1_code":"22.0",
    "gn:asciiname":"Sasoni",
    "gn:country_code":"CD",
    "gn:dem":1019,
    "gn:feature_class":"P",
    "gn:feature_code":"PPL",
    "gn:name":"Sasoni",
    "gn:population":0,
    "gn:timezone":"Africa/Lubumbashi",
    "iso:country":"CD",
    "wof:name":"Sasoni",
    "wof:placetype":"locality"
},
  "geometry": {"coordinates":[23.88333,-9.45],"type":"Point"}
}