{
  "type": "Feature",
  "properties": {
    "gn:admin1_code":"31.0",
    "gn:asciiname":"Yambotengere",
    "gn:country_code":"CD",
    "gn:dem":453,
    "gn:feature_class":"P",
    "gn:feature_code":"PPL",
    "gn:name":"Yambotengere",
    "gn:population":0,
    "gn:timezone":"Africa/Kinshasa",
    "iso:country":"CD",
    "wof:name":"Yambotengere",
    "wof:placetype":"locality"
},
  "geometry": {"coordinates":[21.98333,0.73333],"type":"Point"}
}