{
  "type": "Feature",
  "properties": {
    "gn:admin1_code":"29.0",
    "gn:asciiname":"Loka",
    "gn:country_code":"CD",
    "gn:dem":607,
    "gn:feature_class":"P",
    "gn:feature_code":"PPL",
    "gn:name":"Loka",
    "gn:population":0,
    "gn:timezone":"Africa/Lubumbashi",
    "iso:country":"CD",
    "wof:name":"Loka",
    "wof:placetype":"locality"
},
  "geometry": {"coordinates":[26.6086,-6.0969],"type":"Point"}
}