{
  "type": "Feature",
  "properties": {
    "gn:admin1_code":"25.0",
    "gn:asciiname":"Mongombo-Moke",
    "gn:country_code":"CD",
    "gn:dem":369,
    "gn:feature_class":"P",
    "gn:feature_code":"PPL",
    "gn:name":"Mongombo-Moke",
    "gn:population":0,
    "gn:timezone":"Africa/Kinshasa",
    "iso:country":"CD",
    "wof:name":"Mongombo-Moke",
    "wof:placetype":"locality"
},
  "geometry": {"coordinates":[21.08439,2.48448],"type":"Point"}
}