{
  "type": "Feature",
  "properties": {
    "gn:admin1_code":"18.0",
    "gn:asciiname":"Bualukai",
    "gn:country_code":"CD",
    "gn:dem":654,
    "gn:feature_class":"P",
    "gn:feature_code":"PPL",
    "gn:name":"Bualukai",
    "gn:population":0,
    "gn:timezone":"Africa/Lubumbashi",
    "iso:country":"CD",
    "wof:name":"Bualukai",
    "wof:placetype":"locality"
},
  "geometry": {"coordinates":[21.15703,-7.01487],"type":"Point"}
}