{
  "type": "Feature",
  "properties": {
    "gn:admin1_code":"11.0",
    "gn:asciiname":"Ngoi",
    "gn:country_code":"CD",
    "gn:dem":1675,
    "gn:feature_class":"P",
    "gn:feature_code":"PPL",
    "gn:name":"Ngoi",
    "gn:population":0,
    "gn:timezone":"Africa/Lubumbashi",
    "iso:country":"CD",
    "wof:name":"Ngoi",
    "wof:placetype":"locality"
},
  "geometry": {"coordinates":[28.59583,-1.50528],"type":"Point"}
}