{
  "type": "Feature",
  "properties": {
    "gn:admin1_code":"21.0",
    "gn:asciiname":"Katenta",
    "gn:country_code":"CD",
    "gn:dem":674,
    "gn:feature_class":"P",
    "gn:feature_code":"PPL",
    "gn:name":"Katenta",
    "gn:population":0,
    "gn:timezone":"Africa/Lubumbashi",
    "iso:country":"CD",
    "name:und_x_variant":[
        "Goie Lukamba",
        "Ketenta",
        "Katenta"
    ],
    "wof:name":"Katenta",
    "wof:placetype":"locality"
},
  "geometry": {"coordinates":[25.83921,-5.50455],"type":"Point"}
}