{
  "type": "Feature",
  "properties": {
    "gn:admin1_code":"15.0",
    "gn:asciiname":"Kange",
    "gn:country_code":"CD",
    "gn:dem":668,
    "gn:feature_class":"P",
    "gn:feature_code":"PPL",
    "gn:name":"Kange",
    "gn:population":0,
    "gn:timezone":"Africa/Lubumbashi",
    "iso:country":"CD",
    "name:und_x_variant":[
        "Kenge",
        "Kange"
    ],
    "wof:name":"Kange",
    "wof:placetype":"locality"
},
  "geometry": {"coordinates":[25.88739,-8.07976],"type":"Point"}
}