{
  "type": "Feature",
  "properties": {
    "gn:admin1_code":"10.0",
    "gn:asciiname":"Kalulu",
    "gn:country_code":"CD",
    "gn:dem":663,
    "gn:feature_class":"P",
    "gn:feature_code":"PPL",
    "gn:name":"Kalulu",
    "gn:population":0,
    "gn:timezone":"Africa/Lubumbashi",
    "iso:country":"CD",
    "wof:name":"Kalulu",
    "wof:placetype":"locality"
},
  "geometry": {"coordinates":[26.75629,-3.93285],"type":"Point"}
}