{
  "type": "Feature",
  "properties": {
    "gn:admin1_code":"10.0",
    "gn:asciiname":"Kalulu",
    "gn:country_code":"CD",
    "gn:dem":663,
    "gn:feature_class":"P",
    "gn:feature_code":"PPL",
    "gn:name":"Kalulu",
    "gn:population":0,
    "gn:timezone":"Africa/Lubumbashi",
    "iso:country":"CD",
    "name:deu_x_preferred":[
        "Kalulu"
    ],
    "name:fin_x_preferred":[
        "Kalulu"
    ],
    "name:kor_x_preferred":[
        "\uce74\ub8e8\ub8e8"
    ],
    "name:rus_x_preferred":[
        "\u041a\u0430\u043b\u0443\u043b\u0443"
    ],
    "name:swe_x_preferred":[
        "Kalulu"
    ],
    "name:yor_x_preferred":[
        "Kalulu"
    ],
    "wof:name":"Kalulu",
    "wof:placetype":"locality"
},
  "geometry": {"coordinates":[26.75629,-3.93285],"type":"Point"}
}