{
  "type": "Feature",
  "properties": {
    "gn:admin1_code":"20.0",
    "gn:asciiname":"Bembele-Fioti",
    "gn:country_code":"CD",
    "gn:dem":675,
    "gn:feature_class":"P",
    "gn:feature_code":"PPL",
    "gn:name":"Bembele-Fioti",
    "gn:population":0,
    "gn:timezone":"Africa/Kinshasa",
    "iso:country":"CD",
    "wof:name":"Bembele-Fioti",
    "wof:placetype":"locality"
},
  "geometry": {"coordinates":[19.41667,-4.85],"type":"Point"}
}