{
  "type": "Feature",
  "properties": {
    "gn:admin1_code":"22.0",
    "gn:asciiname":"Kalambalala",
    "gn:country_code":"CD",
    "gn:dem":942,
    "gn:feature_class":"P",
    "gn:feature_code":"PPL",
    "gn:name":"Kalambalala",
    "gn:population":0,
    "gn:timezone":"Africa/Lubumbashi",
    "iso:country":"CD",
    "wof:name":"Kalambalala",
    "wof:placetype":"locality"
},
  "geometry": {"coordinates":[23.30675,-9.72976],"type":"Point"}
}