{
  "type": "Feature",
  "properties": {
    "gn:admin1_code":"19.0",
    "gn:asciiname":"Mwanafunga",
    "gn:country_code":"CD",
    "gn:dem":854,
    "gn:feature_class":"P",
    "gn:feature_code":"PPL",
    "gn:name":"Mwanafunga",
    "gn:population":0,
    "gn:timezone":"Africa/Kinshasa",
    "iso:country":"CD",
    "wof:name":"Mwanafunga",
    "wof:placetype":"locality"
},
  "geometry": {"coordinates":[17.99101,-7.97566],"type":"Point"}
}