{
  "type": "Feature",
  "properties": {
    "gn:admin1_code":"8.0",
    "gn:asciiname":"Kanka-Mawete",
    "gn:country_code":"CD",
    "gn:dem":641,
    "gn:feature_class":"P",
    "gn:feature_code":"PPL",
    "gn:name":"Kanka-Mawete",
    "gn:population":0,
    "gn:timezone":"Africa/Kinshasa",
    "iso:country":"CD",
    "wof:name":"Kanka-Mawete",
    "wof:placetype":"locality"
},
  "geometry": {"coordinates":[14.61667,-5.23333],"type":"Point"}
}