{
  "type": "Feature",
  "properties": {
    "gn:admin1_code":"18.0",
    "gn:asciiname":"Muadiala",
    "gn:country_code":"CD",
    "gn:dem":703,
    "gn:feature_class":"P",
    "gn:feature_code":"PPL",
    "gn:name":"Muadiala",
    "gn:population":0,
    "gn:timezone":"Africa/Lubumbashi",
    "iso:country":"CD",
    "wof:name":"Muadiala",
    "wof:placetype":"locality"
},
  "geometry": {"coordinates":[21.1814,-7.225],"type":"Point"}
}