{
  "type": "Feature",
  "properties": {
    "gn:admin1_code":"16.0",
    "gn:asciiname":"Gombo",
    "gn:country_code":"CD",
    "gn:dem":748,
    "gn:feature_class":"P",
    "gn:feature_code":"PPL",
    "gn:name":"Gombo",
    "gn:population":0,
    "gn:timezone":"Africa/Lubumbashi",
    "iso:country":"CD",
    "wof:name":"Gombo",
    "wof:placetype":"locality"
},
  "geometry": {"coordinates":[27.9406,2.96834],"type":"Point"}
}