{
  "type": "Feature",
  "properties": {
    "gn:admin1_code":"16.0",
    "gn:asciiname":"Bava",
    "gn:country_code":"CD",
    "gn:dem":838,
    "gn:feature_class":"P",
    "gn:feature_code":"PPL",
    "gn:name":"Bava",
    "gn:population":0,
    "gn:timezone":"Africa/Lubumbashi",
    "iso:country":"CD",
    "wof:name":"Bava",
    "wof:placetype":"locality"
},
  "geometry": {"coordinates":[29.76809,3.54915],"type":"Point"}
}