{
  "type": "Feature",
  "properties": {
    "gn:admin1_code":"25.0",
    "gn:asciiname":"Mika",
    "gn:country_code":"CD",
    "gn:dem":411,
    "gn:feature_class":"P",
    "gn:feature_code":"PPL",
    "gn:name":"Mika",
    "gn:population":0,
    "gn:timezone":"Africa/Kinshasa",
    "iso:country":"CD",
    "wof:name":"Mika",
    "wof:placetype":"locality"
},
  "geometry": {"coordinates":[21.50032,2.15704],"type":"Point"}
}