{
  "type": "Feature",
  "properties": {
    "gn:admin1_code":"2.0",
    "gn:asciiname":"Botoma",
    "gn:country_code":"CD",
    "gn:dem":367,
    "gn:feature_class":"P",
    "gn:feature_code":"PPL",
    "gn:name":"Botoma",
    "gn:population":0,
    "gn:timezone":"Africa/Kinshasa",
    "iso:country":"CD",
    "name:und_x_variant":[
        "Tomba",
        "Botoma"
    ],
    "wof:name":"Botoma",
    "wof:placetype":"locality"
},
  "geometry": {"coordinates":[19.58333,0.55],"type":"Point"}
}