{
  "type": "Feature",
  "properties": {
    "gn:admin1_code":"11.0",
    "gn:asciiname":"Kashari",
    "gn:country_code":"CD",
    "gn:dem":2084,
    "gn:feature_class":"P",
    "gn:feature_code":"PPL",
    "gn:name":"Kashari",
    "gn:population":0,
    "gn:timezone":"Africa/Lubumbashi",
    "iso:country":"CD",
    "wof:name":"Kashari",
    "wof:placetype":"locality"
},
  "geometry": {"coordinates":[29.16806,-1.2875],"type":"Point"}
}