{
  "type": "Feature",
  "properties": {
    "gn:admin1_code":"20.0",
    "gn:asciiname":"Bwangongo",
    "gn:country_code":"CD",
    "gn:dem":795,
    "gn:feature_class":"P",
    "gn:feature_code":"PPL",
    "gn:name":"Bwangongo",
    "gn:population":0,
    "gn:timezone":"Africa/Kinshasa",
    "iso:country":"CD",
    "name:und_x_variant":[
        "Bwagongo",
        "Bwangongo"
    ],
    "wof:name":"Bwangongo",
    "wof:placetype":"locality"
},
  "geometry": {"coordinates":[17.83971,-5.58444],"type":"Point"}
}