{
  "type": "Feature",
  "properties": {
    "gn:admin1_code":"20.0",
    "gn:asciiname":"Kikongo-Lusasa",
    "gn:country_code":"CD",
    "gn:dem":669,
    "gn:feature_class":"P",
    "gn:feature_code":"PPL",
    "gn:name":"Kikongo-Lusasa",
    "gn:population":0,
    "gn:timezone":"Africa/Kinshasa",
    "iso:country":"CD",
    "wof:name":"Kikongo-Lusasa",
    "wof:placetype":"locality"
},
  "geometry": {"coordinates":[18.39232,-5.03641],"type":"Point"}
}