{
  "type": "Feature",
  "properties": {
    "gn:admin1_code":"22.0",
    "gn:asciiname":"Safuliela",
    "gn:country_code":"CD",
    "gn:dem":1105,
    "gn:feature_class":"P",
    "gn:feature_code":"PPL",
    "gn:name":"Safuliela",
    "gn:population":0,
    "gn:timezone":"Africa/Lubumbashi",
    "iso:country":"CD",
    "wof:name":"Safuliela",
    "wof:placetype":"locality"
},
  "geometry": {"coordinates":[22.81875,-9.25796],"type":"Point"}
}