{
  "type": "Feature",
  "properties": {
    "gn:admin1_code":"19.0",
    "gn:asciiname":"Kikwasi",
    "gn:country_code":"CD",
    "gn:dem":741,
    "gn:feature_class":"P",
    "gn:feature_code":"PPL",
    "gn:name":"Kikwasi",
    "gn:population":0,
    "gn:timezone":"Africa/Kinshasa",
    "iso:country":"CD",
    "wof:name":"Kikwasi",
    "wof:placetype":"locality"
},
  "geometry": {"coordinates":[17.24589,-5.29305],"type":"Point"}
}