{
  "type": "Feature",
  "properties": {
    "gn:admin1_code":"22.0",
    "gn:asciiname":"Makaka",
    "gn:country_code":"CD",
    "gn:dem":1069,
    "gn:feature_class":"P",
    "gn:feature_code":"PPL",
    "gn:name":"Makaka",
    "gn:population":0,
    "gn:timezone":"Africa/Lubumbashi",
    "iso:country":"CD",
    "wof:name":"Makaka",
    "wof:placetype":"locality"
},
  "geometry": {"coordinates":[23.50701,-10.26541],"type":"Point"}
}