{
  "type": "Feature",
  "properties": {
    "gn:admin1_code":"29.0",
    "gn:asciiname":"Kuumbu",
    "gn:country_code":"CD",
    "gn:dem":920,
    "gn:feature_class":"P",
    "gn:feature_code":"PPL",
    "gn:name":"Kuumbu",
    "gn:population":0,
    "gn:timezone":"Africa/Lubumbashi",
    "iso:country":"CD",
    "wof:name":"Kuumbu",
    "wof:placetype":"locality"
},
  "geometry": {"coordinates":[28.33333,-6.25],"type":"Point"}
}