{
  "type": "Feature",
  "properties": {
    "gn:admin1_code":"0.0",
    "gn:asciiname":"Mwamutshitu",
    "gn:country_code":"CD",
    "gn:dem":964,
    "gn:feature_class":"P",
    "gn:feature_code":"PPL",
    "gn:name":"Mwamutshitu",
    "gn:population":0,
    "gn:timezone":"Africa/Luanda",
    "iso:country":"CD",
    "wof:name":"Mwamutshitu",
    "wof:placetype":"locality"
},
  "geometry": {"coordinates":[22.25,-10.23333],"type":"Point"}
}