{
  "type": "Feature",
  "properties": {
    "gn:admin1_code":"31.0",
    "gn:asciiname":"Momboyo",
    "gn:country_code":"CD",
    "gn:dem":404,
    "gn:feature_class":"P",
    "gn:feature_code":"PPL",
    "gn:name":"Momboyo",
    "gn:population":0,
    "gn:timezone":"Africa/Kinshasa",
    "iso:country":"CD",
    "wof:name":"Momboyo",
    "wof:placetype":"locality"
},
  "geometry": {"coordinates":[21.11667000000001,0.06667],"type":"Point"}
}