{
  "type": "Feature",
  "properties": {
    "gn:admin1_code":"20.0",
    "gn:asciiname":"Mafinga",
    "gn:country_code":"CD",
    "gn:dem":461,
    "gn:feature_class":"P",
    "gn:feature_code":"PPL",
    "gn:name":"Mafinga",
    "gn:population":0,
    "gn:timezone":"Africa/Kinshasa",
    "iso:country":"CD",
    "wof:name":"Mafinga",
    "wof:placetype":"locality"
},
  "geometry": {"coordinates":[18.37294,-5.37927],"type":"Point"}
}