{
  "type": "Feature",
  "properties": {
    "gn:admin1_code":"25.0",
    "gn:asciiname":"Upoto",
    "gn:country_code":"CD",
    "gn:dem":399,
    "gn:feature_class":"P",
    "gn:feature_code":"PPL",
    "gn:name":"Upoto",
    "gn:population":0,
    "gn:timezone":"Africa/Kinshasa",
    "iso:country":"CD",
    "wof:name":"Upoto",
    "wof:placetype":"locality"
},
  "geometry": {"coordinates":[21.49432,2.14082],"type":"Point"}
}