{
  "type": "Feature",
  "properties": {
    "gn:admin1_code":"17.0",
    "gn:asciiname":"Moke",
    "gn:country_code":"CD",
    "gn:dem":843,
    "gn:feature_class":"P",
    "gn:feature_code":"PPL",
    "gn:name":"Moke",
    "gn:population":0,
    "gn:timezone":"Africa/Lubumbashi",
    "iso:country":"CD",
    "name:ceb_x_preferred":[
        "Moke"
    ],
    "name:fra_x_preferred":[
        "Moke"
    ],
    "name:swe_x_preferred":[
        "Moke"
    ],
    "wof:name":"Moke",
    "wof:placetype":"locality"
},
  "geometry": {"coordinates":[28.42603,1.49303],"type":"Point"}
}