{
  "type": "Feature",
  "properties": {
    "gn:admin1_code":"25.0",
    "gn:asciiname":"Ekombe",
    "gn:country_code":"CD",
    "gn:dem":409,
    "gn:feature_class":"P",
    "gn:feature_code":"PPL",
    "gn:name":"Ekombe",
    "gn:population":0,
    "gn:timezone":"Africa/Kinshasa",
    "iso:country":"CD",
    "wof:name":"Ekombe",
    "wof:placetype":"locality"
},
  "geometry": {"coordinates":[21.61007,1.26836],"type":"Point"}
}