{
  "type": "Feature",
  "properties": {
    "gn:admin1_code":"11.0",
    "gn:asciiname":"Mukondoli",
    "gn:country_code":"CD",
    "gn:dem":1318,
    "gn:feature_class":"P",
    "gn:feature_code":"PPL",
    "gn:name":"Mukondoli",
    "gn:population":0,
    "gn:timezone":"Africa/Lubumbashi",
    "iso:country":"CD",
    "wof:name":"Mukondoli",
    "wof:placetype":"locality"
},
  "geometry": {"coordinates":[28.70707,-0.70533],"type":"Point"}
}