{
  "type": "Feature",
  "properties": {
    "gn:admin1_code":"8.0",
    "gn:asciiname":"Boma",
    "gn:country_code":"CD",
    "gn:dem":198,
    "gn:feature_class":"P",
    "gn:feature_code":"PPL",
    "gn:name":"Boma",
    "gn:population":0,
    "gn:timezone":"Africa/Kinshasa",
    "iso:country":"CD",
    "wof:name":"Boma",
    "wof:placetype":"locality"
},
  "geometry": {"coordinates":[14.15509,-4.92742],"type":"Point"}
}