{
  "type": "Feature",
  "properties": {
    "gn:admin1_code":"24.0",
    "gn:asciiname":"Mistandunga",
    "gn:country_code":"CD",
    "gn:dem":307,
    "gn:feature_class":"P",
    "gn:feature_code":"PPL",
    "gn:name":"Mistandunga",
    "gn:population":0,
    "gn:timezone":"Africa/Kinshasa",
    "iso:country":"CD",
    "wof:name":"Mistandunga",
    "wof:placetype":"locality"
},
  "geometry": {"coordinates":[16.36105,-2.07744],"type":"Point"}
}