{
  "type": "Feature",
  "properties": {
    "gn:admin1_code":"8.0",
    "gn:asciiname":"Bukaba",
    "gn:country_code":"CD",
    "gn:dem":667,
    "gn:feature_class":"P",
    "gn:feature_code":"PPL",
    "gn:name":"Bukaba",
    "gn:population":0,
    "gn:timezone":"Africa/Kinshasa",
    "iso:country":"CD",
    "wof:name":"Bukaba",
    "wof:placetype":"locality"
},
  "geometry": {"coordinates":[14.04713,-4.51225],"type":"Point"}
}