{
  "type": "Feature",
  "properties": {
    "gn:admin1_code":"20.0",
    "gn:asciiname":"Ekime",
    "gn:country_code":"CD",
    "gn:dem":629,
    "gn:feature_class":"P",
    "gn:feature_code":"PPL",
    "gn:name":"Ekime",
    "gn:population":0,
    "gn:timezone":"Africa/Kinshasa",
    "iso:country":"CD",
    "wof:name":"Ekime",
    "wof:placetype":"locality"
},
  "geometry": {"coordinates":[19.35428,-5.12955],"type":"Point"}
}