{
  "type": "Feature",
  "properties": {
    "gn:admin1_code":"19.0",
    "gn:asciiname":"Musuku-Dunda",
    "gn:country_code":"CD",
    "gn:dem":883,
    "gn:feature_class":"P",
    "gn:feature_code":"PPL",
    "gn:name":"Musuku-Dunda",
    "gn:population":0,
    "gn:timezone":"Africa/Kinshasa",
    "iso:country":"CD",
    "wof:name":"Musuku-Dunda",
    "wof:placetype":"locality"
},
  "geometry": {"coordinates":[17.52642,-6.02646],"type":"Point"}
}