{
  "type": "Feature",
  "properties": {
    "gn:admin1_code":"15.0",
    "gn:asciiname":"Kikowa",
    "gn:country_code":"CD",
    "gn:dem":780,
    "gn:feature_class":"P",
    "gn:feature_code":"PPL",
    "gn:name":"Kikowa",
    "gn:population":0,
    "gn:timezone":"Africa/Lubumbashi",
    "iso:country":"CD",
    "wof:name":"Kikowa",
    "wof:placetype":"locality"
},
  "geometry": {"coordinates":[25.69011,-8.99847],"type":"Point"}
}