{
  "type": "Feature",
  "properties": {
    "gn:admin1_code":"16.0",
    "gn:asciiname":"Naligonza",
    "gn:country_code":"CD",
    "gn:dem":744,
    "gn:feature_class":"P",
    "gn:feature_code":"PPL",
    "gn:name":"Naligonza",
    "gn:population":0,
    "gn:timezone":"Africa/Lubumbashi",
    "iso:country":"CD",
    "name:und_x_variant":[
        "Nalingonza",
        "Naligonza"
    ],
    "wof:name":"Naligonza",
    "wof:placetype":"locality"
},
  "geometry": {"coordinates":[27.67794,2.95702],"type":"Point"}
}