{
  "type": "Feature",
  "properties": {
    "gn:admin1_code":"24.0",
    "gn:asciiname":"Malebo",
    "gn:country_code":"CD",
    "gn:dem":451,
    "gn:feature_class":"P",
    "gn:feature_code":"PPL",
    "gn:name":"Malebo",
    "gn:population":0,
    "gn:timezone":"Africa/Kinshasa",
    "iso:country":"CD",
    "name:und_x_variant":[
        "Matebo"
    ],
    "wof:name":"Malebo",
    "wof:placetype":"locality"
},
  "geometry": {"coordinates":[16.48326,-2.45439],"type":"Point"}
}