{
  "type": "Feature",
  "properties": {
    "gn:admin1_code":"16.0",
    "gn:asciiname":"Kiasi",
    "gn:country_code":"CD",
    "gn:dem":914,
    "gn:feature_class":"P",
    "gn:feature_code":"PPL",
    "gn:name":"Kiasi",
    "gn:population":0,
    "gn:timezone":"Africa/Lubumbashi",
    "iso:country":"CD",
    "wof:name":"Kiasi",
    "wof:placetype":"locality"
},
  "geometry": {"coordinates":[30.02291,3.12176],"type":"Point"}
}