{
  "type": "Feature",
  "properties": {
    "gn:admin1_code":"13.0",
    "gn:asciiname":"Bangoi",
    "gn:country_code":"CD",
    "gn:dem":592,
    "gn:feature_class":"P",
    "gn:feature_code":"PPL",
    "gn:name":"Bangoi",
    "gn:population":0,
    "gn:timezone":"Africa/Lubumbashi",
    "iso:country":"CD",
    "wof:name":"Bangoi",
    "wof:placetype":"locality"
},
  "geometry": {"coordinates":[25.46147,3.46242],"type":"Point"}
}