{
  "type": "Feature",
  "properties": {
    "gn:admin1_code":"22.0",
    "gn:asciiname":"Kaloya",
    "gn:country_code":"CD",
    "gn:dem":1041,
    "gn:feature_class":"P",
    "gn:feature_code":"PPL",
    "gn:name":"Kaloya",
    "gn:population":0,
    "gn:timezone":"Africa/Lubumbashi",
    "iso:country":"CD",
    "wof:name":"Kaloya",
    "wof:placetype":"locality"
},
  "geometry": {"coordinates":[23.02955,-9.58536],"type":"Point"}
}