{
  "type": "Feature",
  "properties": {
    "gn:admin1_code":"22.0",
    "gn:asciiname":"Samusambo",
    "gn:country_code":"CD",
    "gn:dem":901,
    "gn:feature_class":"P",
    "gn:feature_code":"PPL",
    "gn:name":"Samusambo",
    "gn:population":0,
    "gn:timezone":"Africa/Lubumbashi",
    "iso:country":"CD",
    "name:und_x_variant":[
        "Samusamba",
        "Samuzambu",
        "Samuzambo"
    ],
    "wof:name":"Samusambo",
    "wof:placetype":"locality"
},
  "geometry": {"coordinates":[22.64513,-9.21992],"type":"Point"}
}