{
  "type": "Feature",
  "properties": {
    "gn:admin1_code":"10.0",
    "gn:asciiname":"Lusuna",
    "gn:country_code":"CD",
    "gn:dem":622,
    "gn:feature_class":"P",
    "gn:feature_code":"PPL",
    "gn:name":"Lusuna",
    "gn:population":0,
    "gn:timezone":"Africa/Lubumbashi",
    "iso:country":"CD",
    "wof:name":"Lusuna",
    "wof:placetype":"locality"
},
  "geometry": {"coordinates":[26.78333,-4.15],"type":"Point"}
}