{
  "type": "Feature",
  "properties": {
    "gn:admin1_code":"19.0",
    "gn:asciiname":"Mukila",
    "gn:country_code":"CD",
    "gn:dem":718,
    "gn:feature_class":"P",
    "gn:feature_code":"PPL",
    "gn:name":"Mukila",
    "gn:population":0,
    "gn:timezone":"Africa/Kinshasa",
    "iso:country":"CD",
    "wof:name":"Mukila",
    "wof:placetype":"locality"
},
  "geometry": {"coordinates":[16.32896,-5.37788],"type":"Point"}
}