{
  "type": "Feature",
  "properties": {
    "gn:admin1_code":"13.0",
    "gn:asciiname":"Lingio",
    "gn:country_code":"CD",
    "gn:dem":673,
    "gn:feature_class":"P",
    "gn:feature_code":"PPL",
    "gn:name":"Lingio",
    "gn:population":0,
    "gn:timezone":"Africa/Lubumbashi",
    "iso:country":"CD",
    "wof:name":"Lingio",
    "wof:placetype":"locality"
},
  "geometry": {"coordinates":[27.24045,2.84947],"type":"Point"}
}