{
  "type": "Feature",
  "properties": {
    "gn:admin1_code":"13.0",
    "gn:asciiname":"Mawai",
    "gn:country_code":"CD",
    "gn:dem":398,
    "gn:feature_class":"P",
    "gn:feature_code":"PPL",
    "gn:name":"Mawai",
    "gn:population":0,
    "gn:timezone":"Africa/Lubumbashi",
    "iso:country":"CD",
    "name:msa_x_preferred":[
        "Mawai"
    ],
    "wof:name":"Mawai",
    "wof:placetype":"locality"
},
  "geometry": {"coordinates":[23.87595,2.807],"type":"Point"}
}