{
  "type": "Feature",
  "properties": {
    "gn:admin1_code":"19.0",
    "gn:asciiname":"Kibubu",
    "gn:country_code":"CD",
    "gn:dem":847,
    "gn:feature_class":"P",
    "gn:feature_code":"PPL",
    "gn:name":"Kibubu",
    "gn:population":0,
    "gn:timezone":"Africa/Kinshasa",
    "iso:country":"CD",
    "wof:name":"Kibubu",
    "wof:placetype":"locality"
},
  "geometry": {"coordinates":[17.40443,-6.37809],"type":"Point"}
}