{
  "type": "Feature",
  "properties": {
    "gn:admin1_code":"30.0",
    "gn:asciiname":"Kengesunga",
    "gn:country_code":"CD",
    "gn:dem":461,
    "gn:feature_class":"P",
    "gn:feature_code":"PPL",
    "gn:name":"Kengesunga",
    "gn:population":0,
    "gn:timezone":"Africa/Lubumbashi",
    "iso:country":"CD",
    "wof:name":"Kengesunga",
    "wof:placetype":"locality"
},
  "geometry": {"coordinates":[25.7823,-1.64864],"type":"Point"}
}