{
  "type": "Feature",
  "properties": {
    "gn:admin1_code":"22.0",
    "gn:asciiname":"Nakayembe",
    "gn:country_code":"CD",
    "gn:dem":1036,
    "gn:feature_class":"P",
    "gn:feature_code":"PPL",
    "gn:name":"Nakayembe",
    "gn:population":0,
    "gn:timezone":"Africa/Lubumbashi",
    "iso:country":"CD",
    "wof:name":"Nakayembe",
    "wof:placetype":"locality"
},
  "geometry": {"coordinates":[22.42907,-10.47463],"type":"Point"}
}