{
  "type": "Feature",
  "properties": {
    "gn:admin1_code":"8.0",
    "gn:asciiname":"Diba",
    "gn:country_code":"CD",
    "gn:dem":612,
    "gn:feature_class":"P",
    "gn:feature_code":"PPL",
    "gn:name":"Diba",
    "gn:population":0,
    "gn:timezone":"Africa/Kinshasa",
    "iso:country":"CD",
    "name:cat_x_preferred":[
        "Diba"
    ],
    "name:ceb_x_preferred":[
        "Diba"
    ],
    "name:deu_x_preferred":[
        "Diba"
    ],
    "name:fra_x_preferred":[
        "Diba"
    ],
    "name:swe_x_preferred":[
        "Diba"
    ],
    "wof:name":"Diba",
    "wof:placetype":"locality"
},
  "geometry": {"coordinates":[15.16906,-5.66829],"type":"Point"}
}