{
  "type": "Feature",
  "properties": {
    "gn:admin1_code":"21.0",
    "gn:asciiname":"Kitune",
    "gn:country_code":"CD",
    "gn:dem":839,
    "gn:feature_class":"P",
    "gn:feature_code":"PPL",
    "gn:name":"Kitune",
    "gn:population":0,
    "gn:timezone":"Africa/Lubumbashi",
    "iso:country":"CD",
    "name:und_x_variant":[
        "Kitume",
        "Kitune"
    ],
    "wof:name":"Kitune",
    "wof:placetype":"locality"
},
  "geometry": {"coordinates":[25.0281,-6.26086],"type":"Point"}
}