{
  "type": "Feature",
  "properties": {
    "gn:admin1_code":"19.0",
    "gn:asciiname":"Kinzau",
    "gn:country_code":"CD",
    "gn:dem":835,
    "gn:feature_class":"P",
    "gn:feature_code":"PPL",
    "gn:name":"Kinzau",
    "gn:population":0,
    "gn:timezone":"Africa/Kinshasa",
    "iso:country":"CD",
    "name:por_x_preferred":[
        "Kinzau"
    ],
    "wof:name":"Kinzau",
    "wof:placetype":"locality"
},
  "geometry": {"coordinates":[17.03966,-5.30667],"type":"Point"}
}