{
  "type": "Feature",
  "properties": {
    "gn:admin1_code":"14.0",
    "gn:asciiname":"Kishi",
    "gn:country_code":"CD",
    "gn:dem":1068,
    "gn:feature_class":"P",
    "gn:feature_code":"PPL",
    "gn:name":"Kishi",
    "gn:population":0,
    "gn:timezone":"Africa/Lubumbashi",
    "iso:country":"CD",
    "name:ceb_x_preferred":[
        "Kishi"
    ],
    "name:deu_x_preferred":[
        "Kishi"
    ],
    "name:kor_x_preferred":[
        "\uae30\uc2dc"
    ],
    "name:rus_x_preferred":[
        "\u041a\u0438\u0441\u0438"
    ],
    "name:srp_x_preferred":[
        "\u041a\u0438\u0441\u0438"
    ],
    "name:swe_x_preferred":[
        "Kishi"
    ],
    "wof:name":"Kishi",
    "wof:placetype":"locality"
},
  "geometry": {"coordinates":[27.78726,-10.90854],"type":"Point"}
}