{
  "type": "Feature",
  "properties": {
    "gn:admin1_code":"20.0",
    "gn:asciiname":"Soku",
    "gn:country_code":"CD",
    "gn:dem":365,
    "gn:feature_class":"P",
    "gn:feature_code":"PPL",
    "gn:name":"Soku",
    "gn:population":0,
    "gn:timezone":"Africa/Kinshasa",
    "iso:country":"CD",
    "wof:name":"Soku",
    "wof:placetype":"locality"
},
  "geometry": {"coordinates":[18.59559,-3.78871],"type":"Point"}
}