{
  "type": "Feature",
  "properties": {
    "gn:admin1_code":"17.0",
    "gn:asciiname":"Otsonya",
    "gn:country_code":"CD",
    "gn:dem":1129,
    "gn:feature_class":"P",
    "gn:feature_code":"PPL",
    "gn:name":"Otsonya",
    "gn:population":0,
    "gn:timezone":"Africa/Lubumbashi",
    "iso:country":"CD",
    "wof:name":"Otsonya",
    "wof:placetype":"locality"
},
  "geometry": {"coordinates":[30.48327,2.9188],"type":"Point"}
}