{
  "type": "Feature",
  "properties": {
    "gn:admin1_code":"2.0",
    "gn:asciiname":"Bolongwankoie",
    "gn:country_code":"CD",
    "gn:dem":328,
    "gn:feature_class":"P",
    "gn:feature_code":"PPL",
    "gn:name":"Bolongwankoie",
    "gn:population":0,
    "gn:timezone":"Africa/Kinshasa",
    "iso:country":"CD",
    "wof:name":"Bolongwankoie",
    "wof:placetype":"locality"
},
  "geometry": {"coordinates":[18.48531,-0.30351],"type":"Point"}
}