{
  "type": "Feature",
  "properties": {
    "gn:admin1_code":"12.0",
    "gn:asciiname":"Shandoma",
    "gn:country_code":"CD",
    "gn:dem":1966,
    "gn:feature_class":"P",
    "gn:feature_code":"PPL",
    "gn:name":"Shandoma",
    "gn:population":0,
    "gn:timezone":"Africa/Lubumbashi",
    "iso:country":"CD",
    "wof:name":"Shandoma",
    "wof:placetype":"locality"
},
  "geometry": {"coordinates":[28.8434,-2.55637],"type":"Point"}
}