{
  "type": "Feature",
  "properties": {
    "gn:admin1_code":"19.0",
    "gn:asciiname":"Mwangelu",
    "gn:country_code":"CD",
    "gn:dem":1107,
    "gn:feature_class":"P",
    "gn:feature_code":"PPL",
    "gn:name":"Mwangelu",
    "gn:population":0,
    "gn:timezone":"Africa/Kinshasa",
    "iso:country":"CD",
    "wof:name":"Mwangelu",
    "wof:placetype":"locality"
},
  "geometry": {"coordinates":[18.95232,-7.98887],"type":"Point"}
}