{
  "type": "Feature",
  "properties": {
    "gn:admin1_code":"11.0",
    "gn:asciiname":"Nakatanda",
    "gn:country_code":"CD",
    "gn:dem":1173,
    "gn:feature_class":"P",
    "gn:feature_code":"PPL",
    "gn:name":"Nakatanda",
    "gn:population":0,
    "gn:timezone":"Africa/Lubumbashi",
    "iso:country":"CD",
    "wof:name":"Nakatanda",
    "wof:placetype":"locality"
},
  "geometry": {"coordinates":[28.27061,-1.65391],"type":"Point"}
}