{
  "type": "Feature",
  "properties": {
    "gn:admin1_code":"31.0",
    "gn:asciiname":"Elinga",
    "gn:country_code":"CD",
    "gn:dem":385,
    "gn:feature_class":"P",
    "gn:feature_code":"PPL",
    "gn:name":"Elinga",
    "gn:population":0,
    "gn:timezone":"Africa/Kinshasa",
    "iso:country":"CD",
    "wof:name":"Elinga",
    "wof:placetype":"locality"
},
  "geometry": {"coordinates":[22.10439,-0.63924],"type":"Point"}
}