{
  "type": "Feature",
  "properties": {
    "gn:admin1_code":"30.0",
    "gn:asciiname":"Bobende",
    "gn:country_code":"CD",
    "gn:dem":428,
    "gn:feature_class":"P",
    "gn:feature_code":"PPL",
    "gn:name":"Bobende",
    "gn:population":0,
    "gn:timezone":"Africa/Lubumbashi",
    "iso:country":"CD",
    "wof:name":"Bobende",
    "wof:placetype":"locality"
},
  "geometry": {"coordinates":[25.31679,1.57368],"type":"Point"}
}