{
  "type": "Feature",
  "properties": {
    "gn:admin1_code":"29.0",
    "gn:asciiname":"Genda",
    "gn:country_code":"CD",
    "gn:dem":583,
    "gn:feature_class":"P",
    "gn:feature_code":"PPL",
    "gn:name":"Genda",
    "gn:population":0,
    "gn:timezone":"Africa/Lubumbashi",
    "iso:country":"CD",
    "wof:name":"Genda",
    "wof:placetype":"locality"
},
  "geometry": {"coordinates":[26.70865,-6.49477],"type":"Point"}
}