{
  "type": "Feature",
  "properties": {
    "gn:admin1_code":"14.0",
    "gn:asciiname":"Kipoi",
    "gn:country_code":"CD",
    "gn:dem":1178,
    "gn:feature_class":"P",
    "gn:feature_code":"PPL",
    "gn:name":"Kipoi",
    "gn:population":0,
    "gn:timezone":"Africa/Lubumbashi",
    "iso:country":"CD",
    "name:nld_x_preferred":[
        "Kipoi"
    ],
    "wof:name":"Kipoi",
    "wof:placetype":"locality"
},
  "geometry": {"coordinates":[27.13333,-11.13333],"type":"Point"}
}