{
  "type": "Feature",
  "properties": {
    "gn:admin1_code":"20.0",
    "gn:asciiname":"Bwatundu",
    "gn:country_code":"CD",
    "gn:dem":388,
    "gn:feature_class":"P",
    "gn:feature_code":"PPL",
    "gn:name":"Bwatundu",
    "gn:population":0,
    "gn:timezone":"Africa/Kinshasa",
    "iso:country":"CD",
    "wof:name":"Bwatundu",
    "wof:placetype":"locality"
},
  "geometry": {"coordinates":[18.01603,-4.17414],"type":"Point"}
}