{
  "type": "Feature",
  "properties": {
    "gn:admin1_code":"24.0",
    "gn:asciiname":"Lokori Deuxieme",
    "gn:country_code":"CD",
    "gn:dem":462,
    "gn:feature_class":"P",
    "gn:feature_code":"PPL",
    "gn:name":"Lokori Deuxi\u00e8me",
    "gn:population":0,
    "gn:timezone":"Africa/Kinshasa",
    "iso:country":"CD",
    "name:und_x_variant":[
        "Lokori Deuxi\u00e8me",
        "Lokori II"
    ],
    "wof:name":"Lokori Deuxieme",
    "wof:placetype":"locality"
},
  "geometry": {"coordinates":[20.46531,-3.61394],"type":"Point"}
}