{
  "type": "Feature",
  "properties": {
    "gn:admin1_code":"2.0",
    "gn:asciiname":"Boendjola",
    "gn:country_code":"CD",
    "gn:dem":331,
    "gn:feature_class":"P",
    "gn:feature_code":"PPL",
    "gn:name":"Boendjola",
    "gn:population":0,
    "gn:timezone":"Africa/Kinshasa",
    "iso:country":"CD",
    "wof:name":"Boendjola",
    "wof:placetype":"locality"
},
  "geometry": {"coordinates":[19.51667,-0.18333],"type":"Point"}
}