{
  "type": "Feature",
  "properties": {
    "gn:admin1_code":"19.0",
    "gn:asciiname":"Bungulu",
    "gn:country_code":"CD",
    "gn:dem":1077,
    "gn:feature_class":"P",
    "gn:feature_code":"PPL",
    "gn:name":"Bungulu",
    "gn:population":0,
    "gn:timezone":"Africa/Kinshasa",
    "iso:country":"CD",
    "wof:name":"Bungulu",
    "wof:placetype":"locality"
},
  "geometry": {"coordinates":[18.22862000000001,-7.38364],"type":"Point"}
}