{
  "type": "Feature",
  "properties": {
    "gn:admin1_code":"19.0",
    "gn:asciiname":"Kimvungula",
    "gn:country_code":"CD",
    "gn:dem":701,
    "gn:feature_class":"P",
    "gn:feature_code":"PPL",
    "gn:name":"Kimvungula",
    "gn:population":0,
    "gn:timezone":"Africa/Kinshasa",
    "iso:country":"CD",
    "wof:name":"Kimvungula",
    "wof:placetype":"locality"
},
  "geometry": {"coordinates":[17.45757,-5.17323],"type":"Point"}
}