{
  "type": "Feature",
  "properties": {
    "gn:admin1_code":"8.0",
    "gn:asciiname":"Mbuku-Bula",
    "gn:country_code":"CD",
    "gn:dem":231,
    "gn:feature_class":"P",
    "gn:feature_code":"PPL",
    "gn:name":"Mbuku-Bula",
    "gn:population":0,
    "gn:timezone":"Africa/Kinshasa",
    "iso:country":"CD",
    "wof:name":"Mbuku-Bula",
    "wof:placetype":"locality"
},
  "geometry": {"coordinates":[12.85,-5.15],"type":"Point"}
}