{
  "type": "Feature",
  "properties": {
    "gn:admin1_code":"10.0",
    "gn:asciiname":"Niembo",
    "gn:country_code":"CD",
    "gn:dem":698,
    "gn:feature_class":"P",
    "gn:feature_code":"PPL",
    "gn:name":"Niembo",
    "gn:population":0,
    "gn:timezone":"Africa/Lubumbashi",
    "iso:country":"CD",
    "wof:name":"Niembo",
    "wof:placetype":"locality"
},
  "geometry": {"coordinates":[28.25316,-4.54322],"type":"Point"}
}