{
  "type": "Feature",
  "properties": {
    "gn:admin1_code":"18.0",
    "gn:asciiname":"Muavitombo",
    "gn:country_code":"CD",
    "gn:dem":823,
    "gn:feature_class":"P",
    "gn:feature_code":"PPL",
    "gn:name":"Muavitombo",
    "gn:population":0,
    "gn:timezone":"Africa/Lubumbashi",
    "iso:country":"CD",
    "wof:name":"Muavitombo",
    "wof:placetype":"locality"
},
  "geometry": {"coordinates":[19.93699,-6.44869],"type":"Point"}
}