{
  "type": "Feature",
  "properties": {
    "gn:admin1_code":"10.0",
    "gn:asciiname":"Weta",
    "gn:country_code":"CD",
    "gn:dem":540,
    "gn:feature_class":"P",
    "gn:feature_code":"PPL",
    "gn:name":"Weta",
    "gn:population":0,
    "gn:timezone":"Africa/Lubumbashi",
    "iso:country":"CD",
    "name:und_x_variant":[
        "Wita",
        "Weta"
    ],
    "wof:name":"Weta",
    "wof:placetype":"locality"
},
  "geometry": {"coordinates":[25.07588,-4.14341],"type":"Point"}
}