{
  "type": "Feature",
  "properties": {
    "gn:admin1_code":"10.0",
    "gn:asciiname":"Weta",
    "gn:country_code":"CD",
    "gn:dem":540,
    "gn:feature_class":"P",
    "gn:feature_code":"PPL",
    "gn:name":"Weta",
    "gn:population":0,
    "gn:timezone":"Africa/Lubumbashi",
    "iso:country":"CD",
    "name:ang_x_preferred":[
        "Lopph\u0101ma"
    ],
    "name:cat_x_preferred":[
        "Weta"
    ],
    "name:ces_x_preferred":[
        "Weta"
    ],
    "name:dan_x_preferred":[
        "Weta"
    ],
    "name:epo_x_preferred":[
        "Vetao"
    ],
    "name:fin_x_preferred":[
        "Wetat"
    ],
    "name:fra_x_preferred":[
        "Weta"
    ],
    "name:hun_x_preferred":[
        "Weta"
    ],
    "name:nld_x_preferred":[
        "Weta's"
    ],
    "name:nor_x_preferred":[
        "Wetaer"
    ],
    "name:pnb_x_preferred":[
        "\u0648\u06cc\u0679\u0627"
    ],
    "name:pol_x_preferred":[
        "Weta"
    ],
    "name:por_x_preferred":[
        "Weta"
    ],
    "name:rus_x_preferred":[
        "\u0423\u044d\u0442\u0430"
    ],
    "name:spa_x_preferred":[
        "Weta"
    ],
    "name:swe_x_preferred":[
        "Weta"
    ],
    "name:ukr_x_preferred":[
        "\u0412\u0456\u0442\u0430"
    ],
    "name:und_x_variant":[
        "Wita",
        "Weta"
    ],
    "name:vie_x_preferred":[
        "D\u1ebf Weta"
    ],
    "wof:name":"Weta",
    "wof:placetype":"locality"
},
  "geometry": {"coordinates":[25.07588,-4.14341],"type":"Point"}
}