{
  "type": "Feature",
  "properties": {
    "gn:admin1_code":"19.0",
    "gn:asciiname":"Kakolokoso",
    "gn:country_code":"CD",
    "gn:dem":884,
    "gn:feature_class":"P",
    "gn:feature_code":"PPL",
    "gn:name":"Kakolokoso",
    "gn:population":0,
    "gn:timezone":"Africa/Kinshasa",
    "iso:country":"CD",
    "wof:name":"Kakolokoso",
    "wof:placetype":"locality"
},
  "geometry": {"coordinates":[18.57182,-6.48239],"type":"Point"}
}