{
  "type": "Feature",
  "properties": {
    "gn:admin1_code":"13.0",
    "gn:asciiname":"Ngele",
    "gn:country_code":"CD",
    "gn:dem":519,
    "gn:feature_class":"P",
    "gn:feature_code":"PPL",
    "gn:name":"Ngele",
    "gn:population":0,
    "gn:timezone":"Africa/Lubumbashi",
    "iso:country":"CD",
    "wof:name":"Ngele",
    "wof:placetype":"locality"
},
  "geometry": {"coordinates":[22.82204,4.69763],"type":"Point"}
}