{
  "type": "Feature",
  "properties": {
    "gn:admin1_code":"23.0",
    "gn:asciiname":"Mukundi",
    "gn:country_code":"CD",
    "gn:dem":855,
    "gn:feature_class":"P",
    "gn:feature_code":"PPL",
    "gn:name":"Mukundi",
    "gn:population":0,
    "gn:timezone":"Africa/Lubumbashi",
    "iso:country":"CD",
    "wof:name":"Mukundi",
    "wof:placetype":"locality"
},
  "geometry": {"coordinates":[21.97904,-7.24349],"type":"Point"}
}