{
  "type": "Feature",
  "properties": {
    "gn:admin1_code":"19.0",
    "gn:asciiname":"Kisoso",
    "gn:country_code":"CD",
    "gn:dem":473,
    "gn:feature_class":"P",
    "gn:feature_code":"PPL",
    "gn:name":"Kisoso",
    "gn:population":0,
    "gn:timezone":"Africa/Kinshasa",
    "iso:country":"CD",
    "name:und_x_variant":[
        "Kikoso"
    ],
    "wof:name":"Kisoso",
    "wof:placetype":"locality"
},
  "geometry": {"coordinates":[16.75813,-4.64953],"type":"Point"}
}