{
  "type": "Feature",
  "properties": {
    "gn:admin1_code":"11.0",
    "gn:asciiname":"Makaki",
    "gn:country_code":"CD",
    "gn:dem":782,
    "gn:feature_class":"P",
    "gn:feature_code":"PPL",
    "gn:name":"Makaki",
    "gn:population":0,
    "gn:timezone":"Africa/Lubumbashi",
    "iso:country":"CD",
    "wof:name":"Makaki",
    "wof:placetype":"locality"
},
  "geometry": {"coordinates":[28.1144,-1.62481],"type":"Point"}
}