{
  "type": "Feature",
  "properties": {
    "gn:admin1_code":"22.0",
    "gn:asciiname":"Mwamushinde",
    "gn:country_code":"CD",
    "gn:dem":919,
    "gn:feature_class":"P",
    "gn:feature_code":"PPL",
    "gn:name":"Mwamushinde",
    "gn:population":0,
    "gn:timezone":"Africa/Lubumbashi",
    "iso:country":"CD",
    "wof:name":"Mwamushinde",
    "wof:placetype":"locality"
},
  "geometry": {"coordinates":[23.03455,-10.00816],"type":"Point"}
}