{
  "type": "Feature",
  "properties": {
    "gn:admin1_code":"14.0",
    "gn:asciiname":"Piana",
    "gn:country_code":"CD",
    "gn:dem":1284,
    "gn:feature_class":"P",
    "gn:feature_code":"PPL",
    "gn:name":"Piana",
    "gn:population":0,
    "gn:timezone":"Africa/Lubumbashi",
    "iso:country":"CD",
    "name:ceb_x_preferred":[
        "Piana"
    ],
    "name:deu_x_preferred":[
        "Piana"
    ],
    "name:fra_x_preferred":[
        "Piana"
    ],
    "name:ita_x_preferred":[
        "Piana"
    ],
    "name:nld_x_preferred":[
        "Piana"
    ],
    "name:pol_x_preferred":[
        "Piana"
    ],
    "name:rus_x_preferred":[
        "\u041f\u044c\u044f\u043d\u0430"
    ],
    "name:spa_x_preferred":[
        "Piana"
    ],
    "name:srp_x_preferred":[
        "Pjana"
    ],
    "name:swe_x_preferred":[
        "Piana"
    ],
    "name:ukr_x_preferred":[
        "\u041f'\u044f\u043d\u0430"
    ],
    "wof:name":"Piana",
    "wof:placetype":"locality"
},
  "geometry": {"coordinates":[27.59958,-12.02033],"type":"Point"}
}