{
  "type": "Feature",
  "properties": {
    "gn:admin1_code":"18.0",
    "gn:asciiname":"Luamuela",
    "gn:country_code":"CD",
    "gn:dem":605,
    "gn:feature_class":"P",
    "gn:feature_code":"PPL",
    "gn:name":"Luamuela",
    "gn:population":0,
    "gn:timezone":"Africa/Lubumbashi",
    "iso:country":"CD",
    "wof:name":"Luamuela",
    "wof:placetype":"locality"
},
  "geometry": {"coordinates":[21.02546,-6.62231],"type":"Point"}
}