{
  "type": "Feature",
  "properties": {
    "gn:admin1_code":"13.0",
    "gn:asciiname":"Amaki",
    "gn:country_code":"CD",
    "gn:dem":680,
    "gn:feature_class":"P",
    "gn:feature_code":"PPL",
    "gn:name":"Amaki",
    "gn:population":0,
    "gn:timezone":"Africa/Lubumbashi",
    "iso:country":"CD",
    "wof:name":"Amaki",
    "wof:placetype":"locality"
},
  "geometry": {"coordinates":[26.11667000000001,3.01667],"type":"Point"}
}