{
  "type": "Feature",
  "properties": {
    "gn:admin1_code":"22.0",
    "gn:asciiname":"Safutsheka",
    "gn:country_code":"CD",
    "gn:dem":1091,
    "gn:feature_class":"P",
    "gn:feature_code":"PPL",
    "gn:name":"Safutsheka",
    "gn:population":0,
    "gn:timezone":"Africa/Lubumbashi",
    "iso:country":"CD",
    "wof:name":"Safutsheka",
    "wof:placetype":"locality"
},
  "geometry": {"coordinates":[23.99627000000001,-9.45277],"type":"Point"}
}