{
  "type": "Feature",
  "properties": {
    "gn:admin1_code":"12.0",
    "gn:asciiname":"Fariala",
    "gn:country_code":"CD",
    "gn:dem":825,
    "gn:feature_class":"P",
    "gn:feature_code":"PPL",
    "gn:name":"Fariala",
    "gn:population":0,
    "gn:timezone":"Africa/Lubumbashi",
    "iso:country":"CD",
    "wof:name":"Fariala",
    "wof:placetype":"locality"
},
  "geometry": {"coordinates":[28.79106,-4.99405],"type":"Point"}
}