{
  "type": "Feature",
  "properties": {
    "gn:admin1_code":"22.0",
    "gn:asciiname":"Samueshi",
    "gn:country_code":"CD",
    "gn:dem":944,
    "gn:feature_class":"P",
    "gn:feature_code":"PPL",
    "gn:name":"Samueshi",
    "gn:population":0,
    "gn:timezone":"Africa/Lubumbashi",
    "iso:country":"CD",
    "wof:name":"Samueshi",
    "wof:placetype":"locality"
},
  "geometry": {"coordinates":[23.05754,-10.25124],"type":"Point"}
}