{
  "type": "Feature",
  "properties": {
    "gn:admin1_code":"17.0",
    "gn:asciiname":"Simoni",
    "gn:country_code":"CD",
    "gn:dem":1314,
    "gn:feature_class":"P",
    "gn:feature_code":"PPL",
    "gn:name":"Simoni",
    "gn:population":0,
    "gn:timezone":"Africa/Lubumbashi",
    "iso:country":"CD",
    "name:cos_x_preferred":[
        "Simoni"
    ],
    "name:nld_x_preferred":[
        "Simonis"
    ],
    "name:und_x_variant":[
        "Minia-Simoni"
    ],
    "wof:name":"Simoni",
    "wof:placetype":"locality"
},
  "geometry": {"coordinates":[30.26667,1.83333],"type":"Point"}
}