{
  "type": "Feature",
  "properties": {
    "gn:admin1_code":"14.0",
    "gn:asciiname":"Kimbwi",
    "gn:country_code":"CD",
    "gn:dem":1108,
    "gn:feature_class":"P",
    "gn:feature_code":"PPL",
    "gn:name":"Kimbwi",
    "gn:population":0,
    "gn:timezone":"Africa/Lubumbashi",
    "iso:country":"CD",
    "wof:name":"Kimbwi",
    "wof:placetype":"locality"
},
  "geometry": {"coordinates":[27.58661,-10.84797],"type":"Point"}
}