{
  "type": "Feature",
  "properties": {
    "gn:admin1_code":"10.0",
    "gn:asciiname":"Kitete",
    "gn:country_code":"CD",
    "gn:dem":546,
    "gn:feature_class":"P",
    "gn:feature_code":"PPL",
    "gn:name":"Kitete",
    "gn:population":0,
    "gn:timezone":"Africa/Lubumbashi",
    "iso:country":"CD",
    "wof:name":"Kitete",
    "wof:placetype":"locality"
},
  "geometry": {"coordinates":[25.06076,-4.97558],"type":"Point"}
}