{
  "type": "Feature",
  "properties": {
    "gn:admin1_code":"21.0",
    "gn:asciiname":"Kasambai",
    "gn:country_code":"CD",
    "gn:dem":645,
    "gn:feature_class":"P",
    "gn:feature_code":"PPL",
    "gn:name":"Kasambai",
    "gn:population":0,
    "gn:timezone":"Africa/Lubumbashi",
    "iso:country":"CD",
    "wof:name":"Kasambai",
    "wof:placetype":"locality"
},
  "geometry": {"coordinates":[25.33333,-5.31667],"type":"Point"}
}