{
  "type": "Feature",
  "properties": {
    "gn:admin1_code":"6.0",
    "gn:asciiname":"Ndanu",
    "gn:country_code":"CD",
    "gn:dem":281,
    "gn:feature_class":"P",
    "gn:feature_code":"PPL",
    "gn:name":"Ndanu",
    "gn:population":0,
    "gn:timezone":"Africa/Kinshasa",
    "iso:country":"CD",
    "wof:name":"Ndanu",
    "wof:placetype":"locality"
},
  "geometry": {"coordinates":[15.35776,-4.37866],"type":"Point"}
}