{
  "type": "Feature",
  "properties": {
    "gn:admin1_code":"30.0",
    "gn:asciiname":"Panga",
    "gn:country_code":"CD",
    "gn:dem":460,
    "gn:feature_class":"P",
    "gn:feature_code":"PPL",
    "gn:name":"Panga",
    "gn:population":0,
    "gn:timezone":"Africa/Lubumbashi",
    "iso:country":"CD",
    "name:afr_x_preferred":[
        "Panga"
    ],
    "name:cat_x_preferred":[
        "Pterogymnus laniarius"
    ],
    "name:ceb_x_preferred":[
        "Pterogymnus laniarius"
    ],
    "name:eus_x_preferred":[
        "Hegoafrikako panga"
    ],
    "name:fra_x_preferred":[
        "Pterogymnus laniarius"
    ],
    "name:nld_x_preferred":[
        "Panga"
    ],
    "name:pol_x_preferred":[
        "Pangafer"
    ],
    "name:por_x_preferred":[
        "Panga"
    ],
    "name:slv_x_preferred":[
        "Panga"
    ],
    "name:spa_x_preferred":[
        "Pterogymnus laniarius"
    ],
    "name:swe_x_preferred":[
        "Pangablecka"
    ],
    "name:ukr_x_preferred":[
        "Pterogymnus laniarius"
    ],
    "name:war_x_preferred":[
        "Pterogymnus laniarius"
    ],
    "name:zho_x_preferred":[
        "\u7d05\u88f8\u7ffc\u9bdb"
    ],
    "wof:name":"Panga",
    "wof:placetype":"locality"
},
  "geometry": {"coordinates":[26.39079000000001,1.84756],"type":"Point"}
}