{
  "type": "Feature",
  "properties": {
    "gn:admin1_code":"30.0",
    "gn:asciiname":"Panga",
    "gn:country_code":"CD",
    "gn:dem":460,
    "gn:feature_class":"P",
    "gn:feature_code":"PPL",
    "gn:name":"Panga",
    "gn:population":0,
    "gn:timezone":"Africa/Lubumbashi",
    "iso:country":"CD",
    "wof:name":"Panga",
    "wof:placetype":"locality"
},
  "geometry": {"coordinates":[26.39079000000001,1.84756],"type":"Point"}
}