{
  "type": "Feature",
  "properties": {
    "gn:admin1_code":"22.0",
    "gn:asciiname":"Kambundu",
    "gn:country_code":"CD",
    "gn:dem":998,
    "gn:feature_class":"P",
    "gn:feature_code":"PPL",
    "gn:name":"Kambundu",
    "gn:population":0,
    "gn:timezone":"Africa/Lubumbashi",
    "iso:country":"CD",
    "wof:name":"Kambundu",
    "wof:placetype":"locality"
},
  "geometry": {"coordinates":[22.47783,-8.0599],"type":"Point"}
}