{
  "type": "Feature",
  "properties": {
    "gn:admin1_code":"19.0",
    "gn:asciiname":"Zikalaba",
    "gn:country_code":"CD",
    "gn:dem":717,
    "gn:feature_class":"P",
    "gn:feature_code":"PPL",
    "gn:name":"Zikalaba",
    "gn:population":0,
    "gn:timezone":"Africa/Kinshasa",
    "iso:country":"CD",
    "wof:name":"Zikalaba",
    "wof:placetype":"locality"
},
  "geometry": {"coordinates":[16.39334,-5.17295],"type":"Point"}
}