{
  "type": "Feature",
  "properties": {
    "gn:admin1_code":"21.0",
    "gn:asciiname":"Kalundwe",
    "gn:country_code":"CD",
    "gn:dem":688,
    "gn:feature_class":"P",
    "gn:feature_code":"PPL",
    "gn:name":"Kalundwe",
    "gn:population":0,
    "gn:timezone":"Africa/Lubumbashi",
    "iso:country":"CD",
    "name:und_x_variant":[
        "Kalondwe",
        "Kalundwe",
        "Kalandwa"
    ],
    "wof:name":"Kalundwe",
    "wof:placetype":"locality"
},
  "geometry": {"coordinates":[24.23796,-6.59437],"type":"Point"}
}