{
  "type": "Feature",
  "properties": {
    "gn:admin1_code":"13.0",
    "gn:asciiname":"Makako",
    "gn:country_code":"CD",
    "gn:dem":639,
    "gn:feature_class":"P",
    "gn:feature_code":"PPL",
    "gn:name":"Makako",
    "gn:population":0,
    "gn:timezone":"Africa/Lubumbashi",
    "iso:country":"CD",
    "wof:name":"Makako",
    "wof:placetype":"locality"
},
  "geometry": {"coordinates":[26.25,3.65],"type":"Point"}
}