{
  "type": "Feature",
  "properties": {
    "gn:admin1_code":"14.0",
    "gn:asciiname":"Kombo",
    "gn:country_code":"CD",
    "gn:dem":1200,
    "gn:feature_class":"P",
    "gn:feature_code":"PPL",
    "gn:name":"Kombo",
    "gn:population":0,
    "gn:timezone":"Africa/Lubumbashi",
    "iso:country":"CD",
    "name:cat_x_preferred":[
        "Combo"
    ],
    "name:deu_x_preferred":[
        "Kombo"
    ],
    "wof:name":"Kombo",
    "wof:placetype":"locality"
},
  "geometry": {"coordinates":[27.77445,-12.07078],"type":"Point"}
}