{
  "type": "Feature",
  "properties": {
    "gn:admin1_code":"4.0",
    "gn:asciiname":"Bakwa-Punga",
    "gn:country_code":"CD",
    "gn:dem":812,
    "gn:feature_class":"P",
    "gn:feature_code":"PPL",
    "gn:name":"Bakwa-Punga",
    "gn:population":0,
    "gn:timezone":"Africa/Lubumbashi",
    "iso:country":"CD",
    "name:und_x_variant":[
        "Pungwe",
        "Bakwa-Punga"
    ],
    "wof:name":"Bakwa-Punga",
    "wof:placetype":"locality"
},
  "geometry": {"coordinates":[23.55606,-6.64062],"type":"Point"}
}