{
  "type": "Feature",
  "properties": {
    "gn:admin1_code":"28.0",
    "gn:asciiname":"Bomboka",
    "gn:country_code":"CD",
    "gn:dem":402,
    "gn:feature_class":"P",
    "gn:feature_code":"PPL",
    "gn:name":"Bomboka",
    "gn:population":0,
    "gn:timezone":"Africa/Kinshasa",
    "iso:country":"CD",
    "name:fra_x_preferred":[
        "Bomboka"
    ],
    "wof:name":"Bomboka",
    "wof:placetype":"locality"
},
  "geometry": {"coordinates":[19.01201,2.84115],"type":"Point"}
}