{
  "type": "Feature",
  "properties": {
    "gn:admin1_code":"12.0",
    "gn:asciiname":"Rutemba",
    "gn:country_code":"CD",
    "gn:dem":785,
    "gn:feature_class":"P",
    "gn:feature_code":"PPL",
    "gn:name":"Rutemba",
    "gn:population":0,
    "gn:timezone":"Africa/Lubumbashi",
    "iso:country":"CD",
    "wof:name":"Rutemba",
    "wof:placetype":"locality"
},
  "geometry": {"coordinates":[29.16694,-3.31194],"type":"Point"}
}