{
  "type": "Feature",
  "properties": {
    "gn:admin1_code":"13.0",
    "gn:asciiname":"Kamasidu",
    "gn:country_code":"CD",
    "gn:dem":702,
    "gn:feature_class":"P",
    "gn:feature_code":"PPL",
    "gn:name":"Kamasidu",
    "gn:population":0,
    "gn:timezone":"Africa/Lubumbashi",
    "iso:country":"CD",
    "wof:name":"Kamasidu",
    "wof:placetype":"locality"
},
  "geometry": {"coordinates":[27.24016,3.78437],"type":"Point"}
}