{
  "type": "Feature",
  "properties": {
    "gn:admin1_code":"24.0",
    "gn:asciiname":"Lokoto",
    "gn:country_code":"CD",
    "gn:dem":298,
    "gn:feature_class":"P",
    "gn:feature_code":"PPL",
    "gn:name":"Lokoto",
    "gn:population":0,
    "gn:timezone":"Africa/Kinshasa",
    "iso:country":"CD",
    "wof:name":"Lokoto",
    "wof:placetype":"locality"
},
  "geometry": {"coordinates":[17.77173999999999,-2.39353],"type":"Point"}
}