{
  "type": "Feature",
  "properties": {
    "gn:admin1_code":"28.0",
    "gn:asciiname":"Yu Premiere",
    "gn:country_code":"CD",
    "gn:dem":368,
    "gn:feature_class":"P",
    "gn:feature_code":"PPL",
    "gn:name":"Yu Premi\u00e8re",
    "gn:population":0,
    "gn:timezone":"Africa/Kinshasa",
    "iso:country":"CD",
    "name:und_x_variant":[
        "Yu Premi\u00e8re",
        "Yu I"
    ],
    "wof:name":"Yu Premiere",
    "wof:placetype":"locality"
},
  "geometry": {"coordinates":[18.69446,3.90473],"type":"Point"}
}