{
  "type": "Feature",
  "properties": {
    "gn:admin1_code":"11.0",
    "gn:asciiname":"Kiavikere",
    "gn:country_code":"CD",
    "gn:dem":1421,
    "gn:feature_class":"P",
    "gn:feature_code":"PPL",
    "gn:name":"Kiavikere",
    "gn:population":0,
    "gn:timezone":"Africa/Lubumbashi",
    "iso:country":"CD",
    "wof:name":"Kiavikere",
    "wof:placetype":"locality"
},
  "geometry": {"coordinates":[29.77635,0.41732],"type":"Point"}
}