{
  "type": "Feature",
  "properties": {
    "gn:admin1_code":"15.0",
    "gn:asciiname":"Kimanda",
    "gn:country_code":"CD",
    "gn:dem":902,
    "gn:feature_class":"P",
    "gn:feature_code":"PPL",
    "gn:name":"Kimanda",
    "gn:population":0,
    "gn:timezone":"Africa/Lubumbashi",
    "iso:country":"CD",
    "wof:name":"Kimanda",
    "wof:placetype":"locality"
},
  "geometry": {"coordinates":[24.28514,-7.73153],"type":"Point"}
}