{
  "type": "Feature",
  "properties": {
    "gn:admin1_code":"23.0",
    "gn:asciiname":"Badianana",
    "gn:country_code":"CD",
    "gn:dem":685,
    "gn:feature_class":"P",
    "gn:feature_code":"PPL",
    "gn:name":"Badianana",
    "gn:population":0,
    "gn:timezone":"Africa/Lubumbashi",
    "iso:country":"CD",
    "wof:name":"Badianana",
    "wof:placetype":"locality"
},
  "geometry": {"coordinates":[22.78633,-5.74636],"type":"Point"}
}