{
  "type": "Feature",
  "properties": {
    "gn:admin1_code":"30.0",
    "gn:asciiname":"Likundu Premiere",
    "gn:country_code":"CD",
    "gn:dem":444,
    "gn:feature_class":"P",
    "gn:feature_code":"PPL",
    "gn:name":"Likundu Premi\u00e8re",
    "gn:population":0,
    "gn:timezone":"Africa/Lubumbashi",
    "iso:country":"CD",
    "name:und_x_variant":[
        "Likundu",
        "Likundu I",
        "Likundu Premi\u00e8re"
    ],
    "wof:name":"Likundu Premiere",
    "wof:placetype":"locality"
},
  "geometry": {"coordinates":[24.17207,-0.18929],"type":"Point"}
}