{
  "type": "Feature",
  "properties": {
    "gn:admin1_code":"10.0",
    "gn:asciiname":"Gueso",
    "gn:country_code":"CD",
    "gn:dem":561,
    "gn:feature_class":"P",
    "gn:feature_code":"PPL",
    "gn:name":"Gueso",
    "gn:population":0,
    "gn:timezone":"Africa/Lubumbashi",
    "iso:country":"CD",
    "wof:name":"Gueso",
    "wof:placetype":"locality"
},
  "geometry": {"coordinates":[25.0865,-4.23215],"type":"Point"}
}