{
  "type": "Feature",
  "properties": {
    "gn:gn_country":"CD",
    "gn:gn_fcode":"PPL",
    "gn:gn_pop":50493,
    "gn:population":50493,
    "iso:country":"CD",
    "name:chi_x_preferred":[
        "\u6208\u5df4\u591a\u840a"
    ],
    "name:cze_x_preferred":[
        "Gbadolite"
    ],
    "name:dan_x_preferred":[
        "Gbadolite"
    ],
    "name:dut_x_preferred":[
        "Gbadolite"
    ],
    "name:eng_x_preferred":[
        "Gbadolite"
    ],
    "name:epo_x_preferred":[
        "Gbadolite"
    ],
    "name:est_x_preferred":[
        "Gbadolite"
    ],
    "name:fin_x_preferred":[
        "Gbadolite"
    ],
    "name:fre_x_preferred":[
        "Gbadolite"
    ],
    "name:geo_x_preferred":[
        "\u10d2\u10d1\u10d0\u10d3\u10dd\u10da\u10d8\u10e2\u10d4"
    ],
    "name:ger_x_preferred":[
        "Gbadolite"
    ],
    "name:hrv_x_preferred":[
        "Gbadolite"
    ],
    "name:hun_x_preferred":[
        "Gbadolite"
    ],
    "name:ind_x_preferred":[
        "Gbadolite"
    ],
    "name:ita_x_preferred":[
        "Gbadolite"
    ],
    "name:jpn_x_preferred":[
        "\u30d0\u30c9\u30ea\u30c6"
    ],
    "name:kor_x_preferred":[
        "\uadf8\ubc14\ub3cc\ub9ac\ud14c"
    ],
    "name:nob_x_preferred":[
        "Gbadolite"
    ],
    "name:per_x_preferred":[
        "\u06af\u0628\u0627\u062f\u0648\u0644\u06cc\u062a"
    ],
    "name:pol_x_preferred":[
        "Gbadolite"
    ],
    "name:por_x_preferred":[
        "Gbadolite"
    ],
    "name:rum_x_preferred":[
        "Gbadolite"
    ],
    "name:rus_x_preferred":[
        "\u0413\u0431\u0430\u0434\u043e\u043b\u0438\u0442\u0435"
    ],
    "name:spa_x_preferred":[
        "Gbadolite"
    ],
    "name:swe_x_preferred":[
        "Gbadolite"
    ],
    "name:ukr_x_preferred":[
        "\u0413\u0431\u0430\u0434\u043e\u043b\u0456\u0442\u0435"
    ],
    "name:unk_x_variant":[
        "Badolite"
    ],
    "name:war_x_preferred":[
        "Gbadolite"
    ],
    "name:xmf_x_preferred":[
        "\u10d2\u10d1\u10d0\u10d3\u10dd\u10da\u10d8\u10e2\u10d4"
    ],
    "qs_pg:aaroncc":"CD",
    "qs_pg:gn_country":"CD",
    "qs_pg:gn_fcode":"PPL",
    "qs_pg:gn_pop":50493,
    "qs_pg:name":"Gbadolite",
    "qs_pg:photos_9r":0,
    "qs_pg:photos_sr":0,
    "qs_pg:pop_sr":8,
    "qs_pg:qs_pg_placetype":"locality",
    "wof:name":"Gbadolite",
    "wof:placetype":"locality",
    "wof:population":50493
},
  "geometry": {"coordinates":[21.00284,4.279],"type":"Point"}
}