{
  "type": "Feature",
  "properties": {
    "gn:admin1_code":"17.0",
    "gn:asciiname":"Ale",
    "gn:country_code":"CD",
    "gn:dem":1269,
    "gn:feature_class":"P",
    "gn:feature_code":"PPL",
    "gn:name":"Ale",
    "gn:population":0,
    "gn:timezone":"Africa/Lubumbashi",
    "iso:country":"CD",
    "wof:name":"Ale",
    "wof:placetype":"locality"
},
  "geometry": {"coordinates":[30.79746,3.16534],"type":"Point"}
}