{
  "type": "Feature",
  "properties": {
    "gn:admin1_code":"17.0",
    "gn:asciiname":"Ale",
    "gn:country_code":"CD",
    "gn:dem":1269,
    "gn:feature_class":"P",
    "gn:feature_code":"PPL",
    "gn:name":"Ale",
    "gn:population":0,
    "gn:timezone":"Africa/Lubumbashi",
    "iso:country":"CD",
    "name:afr_x_preferred":[
        "Aal"
    ],
    "name:ara_x_preferred":[
        "\u0645\u0632\u0631"
    ],
    "name:ast_x_preferred":[
        "Ale"
    ],
    "name:bul_x_preferred":[
        "\u0415\u0439\u043b"
    ],
    "name:cat_x_preferred":[
        "Ale"
    ],
    "name:ces_x_preferred":[
        "Ale"
    ],
    "name:dan_x_preferred":[
        "Ale"
    ],
    "name:deu_x_preferred":[
        "Ale"
    ],
    "name:epo_x_preferred":[
        "Elo"
    ],
    "name:est_x_preferred":[
        "Ale"
    ],
    "name:eus_x_preferred":[
        "Ale"
    ],
    "name:fas_x_preferred":[
        "\u0627\u06cc\u0644"
    ],
    "name:fin_x_preferred":[
        "Ale"
    ],
    "name:fra_x_preferred":[
        "Ale"
    ],
    "name:gle_x_preferred":[
        "Leann"
    ],
    "name:heb_x_preferred":[
        "\u05d0\u05d9\u05d9\u05dc"
    ],
    "name:hun_x_preferred":[
        "Ale"
    ],
    "name:ind_x_preferred":[
        "Ale"
    ],
    "name:ita_x_preferred":[
        "Ale"
    ],
    "name:jpn_x_preferred":[
        "\u30a8\u30fc\u30eb"
    ],
    "name:kor_x_preferred":[
        "\uc0c1\uba74\ubc1c\ud6a8\ub9e5\uc8fc"
    ],
    "name:lim_x_preferred":[
        "Ale"
    ],
    "name:lit_x_preferred":[
        "Elis"
    ],
    "name:nep_x_preferred":[
        "\u091c\u093e\u0901\u0921"
    ],
    "name:nld_x_preferred":[
        "Ale"
    ],
    "name:nno_x_preferred":[
        "Ale"
    ],
    "name:nor_x_preferred":[
        "Ale"
    ],
    "name:pol_x_preferred":[
        "Ale"
    ],
    "name:por_x_preferred":[
        "Ale"
    ],
    "name:rus_x_preferred":[
        "\u042d\u043b\u044c"
    ],
    "name:sco_x_preferred":[
        "Yill"
    ],
    "name:slk_x_preferred":[
        "Ale"
    ],
    "name:slv_x_preferred":[
        "Ale"
    ],
    "name:spa_x_preferred":[
        "Ale"
    ],
    "name:swe_x_preferred":[
        "Ale"
    ],
    "name:tam_x_preferred":[
        "\u0b8f\u0bb2\u0bcd"
    ],
    "name:tat_x_preferred":[
        "\u042d\u043b\u044c"
    ],
    "name:tha_x_preferred":[
        "\u0e40\u0e2d\u0e25"
    ],
    "name:tur_x_preferred":[
        "Ale"
    ],
    "name:ukr_x_preferred":[
        "\u0415\u043b\u044c"
    ],
    "name:vie_x_preferred":[
        "Ale"
    ],
    "name:yid_x_preferred":[
        "\u05e2\u05d9\u05dc"
    ],
    "name:zho_x_preferred":[
        "\u7231\u5c14\u5564\u9152"
    ],
    "wof:name":"Ale",
    "wof:placetype":"locality"
},
  "geometry": {"coordinates":[30.79746,3.16534],"type":"Point"}
}