{
  "type": "Feature",
  "properties": {
    "gn:admin1_code":"23.0",
    "gn:asciiname":"Tshisele",
    "gn:country_code":"CD",
    "gn:dem":796,
    "gn:feature_class":"P",
    "gn:feature_code":"PPL",
    "gn:name":"Tshisele",
    "gn:population":0,
    "gn:timezone":"Africa/Lubumbashi",
    "iso:country":"CD",
    "wof:name":"Tshisele",
    "wof:placetype":"locality"
},
  "geometry": {"coordinates":[22.04781,-6.73646],"type":"Point"}
}