{
  "type": "Feature",
  "properties": {
    "gn:admin1_code":"14.0",
    "gn:asciiname":"Kisununu",
    "gn:country_code":"CD",
    "gn:dem":1512,
    "gn:feature_class":"P",
    "gn:feature_code":"PPL",
    "gn:name":"Kisununu",
    "gn:population":0,
    "gn:timezone":"Africa/Lubumbashi",
    "iso:country":"CD",
    "wof:name":"Kisununu",
    "wof:placetype":"locality"
},
  "geometry": {"coordinates":[26.03333,-11.25],"type":"Point"}
}