{
  "type": "Feature",
  "properties": {
    "gn:admin1_code":"10.0",
    "gn:asciiname":"Kitalangulu",
    "gn:country_code":"CD",
    "gn:dem":553,
    "gn:feature_class":"P",
    "gn:feature_code":"PPL",
    "gn:name":"Kitalangulu",
    "gn:population":0,
    "gn:timezone":"Africa/Lubumbashi",
    "iso:country":"CD",
    "name:und_x_variant":[
        "Kitangulu",
        "Kitangula",
        "Kitalangulu"
    ],
    "wof:name":"Kitalangulu",
    "wof:placetype":"locality"
},
  "geometry": {"coordinates":[26.51667,-1.45],"type":"Point"}
}