{
  "type": "Feature",
  "properties": {
    "gn:admin1_code":"30.0",
    "gn:asciiname":"Bafwambako",
    "gn:country_code":"CD",
    "gn:dem":557,
    "gn:feature_class":"P",
    "gn:feature_code":"PPL",
    "gn:name":"Bafwambako",
    "gn:population":0,
    "gn:timezone":"Africa/Lubumbashi",
    "iso:country":"CD",
    "wof:name":"Bafwambako",
    "wof:placetype":"locality"
},
  "geometry": {"coordinates":[27.17146,1.01721],"type":"Point"}
}