{
  "type": "Feature",
  "properties": {
    "gn:admin1_code":"23.0",
    "gn:asciiname":"Muyaya-Kakende",
    "gn:country_code":"CD",
    "gn:dem":796,
    "gn:feature_class":"P",
    "gn:feature_code":"PPL",
    "gn:name":"Muyaya-Kakende",
    "gn:population":0,
    "gn:timezone":"Africa/Lubumbashi",
    "iso:country":"CD",
    "wof:name":"Muyaya-Kakende",
    "wof:placetype":"locality"
},
  "geometry": {"coordinates":[22.88475,-6.1997],"type":"Point"}
}