{
  "type": "Feature",
  "properties": {
    "gn:admin1_code":"21.0",
    "gn:asciiname":"Mulubule",
    "gn:country_code":"CD",
    "gn:dem":638,
    "gn:feature_class":"P",
    "gn:feature_code":"PPL",
    "gn:name":"Mulubule",
    "gn:population":0,
    "gn:timezone":"Africa/Lubumbashi",
    "iso:country":"CD",
    "name:und_x_variant":[
        "Mulebule"
    ],
    "wof:name":"Mulubule",
    "wof:placetype":"locality"
},
  "geometry": {"coordinates":[25.99141,-5.51808],"type":"Point"}
}