{
  "type": "Feature",
  "properties": {
    "gn:admin1_code":"0.0",
    "gn:asciiname":"Kanzenze",
    "gn:cc2":"CD",
    "gn:country_code":"CD",
    "gn:dem":1175,
    "gn:feature_class":"P",
    "gn:feature_code":"PPL",
    "gn:name":"Kanzenze",
    "gn:population":0,
    "gn:timezone":"Africa/Lubumbashi",
    "iso:country":"CD",
    "name:und_x_variant":[
        "Li\u00e8ge Sacr\u00e9-Coeur",
        "Kanzenze"
    ],
    "wof:name":"Kanzenze",
    "wof:placetype":"locality"
},
  "geometry": {"coordinates":[25.20667000000001,-10.52013],"type":"Point"}
}