{
  "type": "Feature",
  "properties": {
    "gn:admin1_code":"10.0",
    "gn:asciiname":"Kayo-Kafioto",
    "gn:country_code":"CD",
    "gn:dem":634,
    "gn:feature_class":"P",
    "gn:feature_code":"PPL",
    "gn:name":"Kayo-Kafioto",
    "gn:population":0,
    "gn:timezone":"Africa/Lubumbashi",
    "iso:country":"CD",
    "wof:name":"Kayo-Kafioto",
    "wof:placetype":"locality"
},
  "geometry": {"coordinates":[26.9516,-4.03784],"type":"Point"}
}