{
  "type": "Feature",
  "properties": {
    "gn:admin1_code":"8.0",
    "gn:asciiname":"Tungila",
    "gn:country_code":"CD",
    "gn:dem":507,
    "gn:feature_class":"P",
    "gn:feature_code":"PPL",
    "gn:name":"Tungila",
    "gn:population":0,
    "gn:timezone":"Africa/Kinshasa",
    "iso:country":"CD",
    "wof:name":"Tungila",
    "wof:placetype":"locality"
},
  "geometry": {"coordinates":[14.89047,-5.59096],"type":"Point"}
}