{
  "type": "Feature",
  "properties": {
    "gn:admin1_code":"31.0",
    "gn:asciiname":"Liangola",
    "gn:country_code":"CD",
    "gn:dem":366,
    "gn:feature_class":"P",
    "gn:feature_code":"PPL",
    "gn:name":"Liangola",
    "gn:population":0,
    "gn:timezone":"Africa/Kinshasa",
    "iso:country":"CD",
    "name:und_x_variant":[
        "Liangela",
        "Liangola"
    ],
    "wof:name":"Liangola",
    "wof:placetype":"locality"
},
  "geometry": {"coordinates":[20.98333,0.13333],"type":"Point"}
}