{
  "type": "Feature",
  "properties": {
    "gn:admin1_code":"30.0",
    "gn:asciiname":"Bigbuli I",
    "gn:country_code":"CD",
    "gn:dem":624,
    "gn:feature_class":"P",
    "gn:feature_code":"PPL",
    "gn:name":"Bigbuli I",
    "gn:population":0,
    "gn:timezone":"Africa/Lubumbashi",
    "iso:country":"CD",
    "wof:name":"Bigbuli I",
    "wof:placetype":"locality"
},
  "geometry": {"coordinates":[27.78333,0.91667],"type":"Point"}
}