{
  "type": "Feature",
  "properties": {
    "gn:admin1_code":"19.0",
    "gn:asciiname":"Kongo-Kandi",
    "gn:country_code":"CD",
    "gn:dem":833,
    "gn:feature_class":"P",
    "gn:feature_code":"PPL",
    "gn:name":"Kongo-Kandi",
    "gn:population":0,
    "gn:timezone":"Africa/Kinshasa",
    "iso:country":"CD",
    "wof:name":"Kongo-Kandi",
    "wof:placetype":"locality"
},
  "geometry": {"coordinates":[17.6996,-5.93594],"type":"Point"}
}