{
  "type": "Feature",
  "properties": {
    "gn:admin1_code":"13.0",
    "gn:asciiname":"Masombo",
    "gn:country_code":"CD",
    "gn:dem":564,
    "gn:feature_class":"P",
    "gn:feature_code":"PPL",
    "gn:name":"Masombo",
    "gn:population":0,
    "gn:timezone":"Africa/Lubumbashi",
    "iso:country":"CD",
    "wof:name":"Masombo",
    "wof:placetype":"locality"
},
  "geometry": {"coordinates":[24.0109,3.93615],"type":"Point"}
}