{
  "type": "Feature",
  "properties": {
    "gn:admin1_code":"16.0",
    "gn:asciiname":"Bangbe",
    "gn:country_code":"CD",
    "gn:dem":729,
    "gn:feature_class":"P",
    "gn:feature_code":"PPL",
    "gn:name":"Bangbe",
    "gn:population":0,
    "gn:timezone":"Africa/Lubumbashi",
    "iso:country":"CD",
    "wof:name":"Bangbe",
    "wof:placetype":"locality"
},
  "geometry": {"coordinates":[28.26263,4.28884],"type":"Point"}
}