{
  "type": "Feature",
  "properties": {
    "gn:admin1_code":"2.0",
    "gn:asciiname":"Bongamba",
    "gn:country_code":"CD",
    "gn:dem":326,
    "gn:feature_class":"P",
    "gn:feature_code":"PPL",
    "gn:name":"Bongamba",
    "gn:population":0,
    "gn:timezone":"Africa/Kinshasa",
    "iso:country":"CD",
    "wof:name":"Bongamba",
    "wof:placetype":"locality"
},
  "geometry": {"coordinates":[18.49148,-0.40665],"type":"Point"}
}