{
  "type": "Feature",
  "properties": {
    "gn:admin1_code":"20.0",
    "gn:asciiname":"Kasanza",
    "gn:country_code":"CD",
    "gn:dem":744,
    "gn:feature_class":"P",
    "gn:feature_code":"PPL",
    "gn:name":"Kasanza",
    "gn:population":0,
    "gn:timezone":"Africa/Kinshasa",
    "iso:country":"CD",
    "wof:name":"Kasanza",
    "wof:placetype":"locality"
},
  "geometry": {"coordinates":[18.77818,-5.96465],"type":"Point"}
}