{
  "type": "Feature",
  "properties": {
    "gn:admin1_code":"29.0",
    "gn:asciiname":"Bugumba",
    "gn:country_code":"CD",
    "gn:dem":982,
    "gn:feature_class":"P",
    "gn:feature_code":"PPL",
    "gn:name":"Bugumba",
    "gn:population":0,
    "gn:timezone":"Africa/Lubumbashi",
    "iso:country":"CD",
    "wof:name":"Bugumba",
    "wof:placetype":"locality"
},
  "geometry": {"coordinates":[29.11667000000001,-5.78333],"type":"Point"}
}