{
  "type": "Feature",
  "properties": {
    "gn:admin1_code":"20.0",
    "gn:asciiname":"Kamafu",
    "gn:country_code":"CD",
    "gn:dem":451,
    "gn:feature_class":"P",
    "gn:feature_code":"PPL",
    "gn:name":"Kamafu",
    "gn:population":0,
    "gn:timezone":"Africa/Kinshasa",
    "iso:country":"CD",
    "wof:name":"Kamafu",
    "wof:placetype":"locality"
},
  "geometry": {"coordinates":[17.91672,-5.35685],"type":"Point"}
}