{
  "type": "Feature",
  "properties": {
    "gn:admin1_code":"24.0",
    "gn:asciiname":"Isoko",
    "gn:country_code":"CD",
    "gn:dem":334,
    "gn:feature_class":"P",
    "gn:feature_code":"PPL",
    "gn:name":"Isoko",
    "gn:population":0,
    "gn:timezone":"Africa/Kinshasa",
    "iso:country":"CD",
    "name:cat_x_preferred":[
        "Isoko"
    ],
    "name:fra_x_preferred":[
        "Isoko"
    ],
    "name:por_x_preferred":[
        "Isoko"
    ],
    "wof:name":"Isoko",
    "wof:placetype":"locality"
},
  "geometry": {"coordinates":[19.56667,-3.43333],"type":"Point"}
}