{
  "type": "Feature",
  "properties": {
    "gn:admin1_code":"8.0",
    "gn:asciiname":"Kimbongo",
    "gn:country_code":"CD",
    "gn:dem":557,
    "gn:feature_class":"P",
    "gn:feature_code":"PPL",
    "gn:name":"Kimbongo",
    "gn:population":0,
    "gn:timezone":"Africa/Kinshasa",
    "iso:country":"CD",
    "wof:name":"Kimbongo",
    "wof:placetype":"locality"
},
  "geometry": {"coordinates":[14.36563,-4.52358],"type":"Point"}
}