{
  "type": "Feature",
  "properties": {
    "gn:admin1_code":"8.0",
    "gn:asciiname":"Manilonde",
    "gn:country_code":"CD",
    "gn:dem":736,
    "gn:feature_class":"P",
    "gn:feature_code":"PPL",
    "gn:name":"Manilonde",
    "gn:population":0,
    "gn:timezone":"Africa/Kinshasa",
    "iso:country":"CD",
    "wof:name":"Manilonde",
    "wof:placetype":"locality"
},
  "geometry": {"coordinates":[14.5525,-5.22979],"type":"Point"}
}