{
  "type": "Feature",
  "properties": {
    "gn:admin1_code":"13.0",
    "gn:asciiname":"Bagno",
    "gn:country_code":"CD",
    "gn:dem":665,
    "gn:feature_class":"P",
    "gn:feature_code":"PPL",
    "gn:name":"Bagno",
    "gn:population":0,
    "gn:timezone":"Africa/Lubumbashi",
    "iso:country":"CD",
    "name:ceb_x_preferred":[
        "Bagno"
    ],
    "name:deu_x_preferred":[
        "Bagno"
    ],
    "name:fra_x_preferred":[
        "Bagno"
    ],
    "name:ita_x_preferred":[
        "Bagno"
    ],
    "name:lit_x_preferred":[
        "Bagnas"
    ],
    "name:pol_x_preferred":[
        "Bagno"
    ],
    "name:rus_x_preferred":[
        "\u0411\u0430\u043d\u044c\u043e"
    ],
    "name:srp_x_preferred":[
        "Bagno"
    ],
    "name:swe_x_preferred":[
        "Bagno"
    ],
    "name:ukr_x_preferred":[
        "\u0411\u0430\u043d\u044c\u043e"
    ],
    "wof:name":"Bagno",
    "wof:placetype":"locality"
},
  "geometry": {"coordinates":[26.58215,2.96321],"type":"Point"}
}