{
  "type": "Feature",
  "properties": {
    "gn:admin1_code":"19.0",
    "gn:asciiname":"Shamundunga",
    "gn:country_code":"CD",
    "gn:dem":881,
    "gn:feature_class":"P",
    "gn:feature_code":"PPL",
    "gn:name":"Shamundunga",
    "gn:population":0,
    "gn:timezone":"Africa/Kinshasa",
    "iso:country":"CD",
    "wof:name":"Shamundunga",
    "wof:placetype":"locality"
},
  "geometry": {"coordinates":[19.67513,-6.70682],"type":"Point"}
}