{
  "type": "Feature",
  "properties": {
    "gn:admin1_code":"8.0",
    "gn:asciiname":"Kumbi",
    "gn:country_code":"CD",
    "gn:dem":598,
    "gn:feature_class":"P",
    "gn:feature_code":"PPL",
    "gn:name":"Kumbi",
    "gn:population":0,
    "gn:timezone":"Africa/Kinshasa",
    "iso:country":"CD",
    "name:und_x_variant":[
        "Nkumbi"
    ],
    "wof:name":"Kumbi",
    "wof:placetype":"locality"
},
  "geometry": {"coordinates":[15.04257,-5.1098],"type":"Point"}
}