{
  "type": "Feature",
  "properties": {
    "gn:admin1_code":"24.0",
    "gn:asciiname":"Bolinda",
    "gn:country_code":"CD",
    "gn:dem":385,
    "gn:feature_class":"P",
    "gn:feature_code":"PPL",
    "gn:name":"Bolinda",
    "gn:population":0,
    "gn:timezone":"Africa/Kinshasa",
    "iso:country":"CD",
    "wof:name":"Bolinda",
    "wof:placetype":"locality"
},
  "geometry": {"coordinates":[19.61321,-2.96133],"type":"Point"}
}