{
  "type": "Feature",
  "properties": {
    "gn:admin1_code":"23.0",
    "gn:asciiname":"Uamba Yamba",
    "gn:country_code":"CD",
    "gn:dem":888,
    "gn:feature_class":"P",
    "gn:feature_code":"PPL",
    "gn:name":"Uamba Yamba",
    "gn:population":0,
    "gn:timezone":"Africa/Lubumbashi",
    "iso:country":"CD",
    "wof:name":"Uamba Yamba",
    "wof:placetype":"locality"
},
  "geometry": {"coordinates":[22.03562,-7.25866],"type":"Point"}
}