{
  "type": "Feature",
  "properties": {
    "gn:admin1_code":"15.0",
    "gn:asciiname":"Sainte Walburge Premiere",
    "gn:country_code":"CD",
    "gn:dem":978,
    "gn:feature_class":"P",
    "gn:feature_code":"PPL",
    "gn:name":"Sainte Walburge Premi\u00e8re",
    "gn:population":0,
    "gn:timezone":"Africa/Lubumbashi",
    "iso:country":"CD",
    "wof:name":"Sainte Walburge Premiere",
    "wof:placetype":"locality"
},
  "geometry": {"coordinates":[24.48286,-7.65419],"type":"Point"}
}