{
  "type": "Feature",
  "properties": {
    "gn:admin1_code":"23.0",
    "gn:asciiname":"Mwena Mbenze",
    "gn:country_code":"CD",
    "gn:dem":1002,
    "gn:feature_class":"P",
    "gn:feature_code":"PPL",
    "gn:name":"Mwena Mbenze",
    "gn:population":0,
    "gn:timezone":"Africa/Lubumbashi",
    "iso:country":"CD",
    "name:und_x_variant":[
        "Muena-Mbenze"
    ],
    "wof:name":"Mwena Mbenze",
    "wof:placetype":"locality"
},
  "geometry": {"coordinates":[22.85338,-7.72978],"type":"Point"}
}