{
  "type": "Feature",
  "properties": {
    "gn:admin1_code":"25.0",
    "gn:asciiname":"Duiapo",
    "gn:country_code":"CD",
    "gn:dem":420,
    "gn:feature_class":"P",
    "gn:feature_code":"PPL",
    "gn:name":"Duiapo",
    "gn:population":0,
    "gn:timezone":"Africa/Kinshasa",
    "iso:country":"CD",
    "wof:name":"Duiapo",
    "wof:placetype":"locality"
},
  "geometry": {"coordinates":[21.20859,2.87714],"type":"Point"}
}