{
  "type": "Feature",
  "properties": {
    "gn:admin1_code":"8.0",
    "gn:asciiname":"Zundu",
    "gn:country_code":"CD",
    "gn:dem":635,
    "gn:feature_class":"P",
    "gn:feature_code":"PPL",
    "gn:name":"Zundu",
    "gn:population":0,
    "gn:timezone":"Africa/Kinshasa",
    "iso:country":"CD",
    "wof:name":"Zundu",
    "wof:placetype":"locality"
},
  "geometry": {"coordinates":[14.82556,-5.15659],"type":"Point"}
}