{
  "type": "Feature",
  "properties": {
    "gn:admin1_code":"15.0",
    "gn:asciiname":"Kila",
    "gn:country_code":"CD",
    "gn:dem":873,
    "gn:feature_class":"P",
    "gn:feature_code":"PPL",
    "gn:name":"Kila",
    "gn:population":0,
    "gn:timezone":"Africa/Lubumbashi",
    "iso:country":"CD",
    "name:ceb_x_preferred":[
        "Kila"
    ],
    "name:nld_x_preferred":[
        "Kila"
    ],
    "name:que_x_preferred":[
        "Kila"
    ],
    "name:rus_x_preferred":[
        "\u041a\u0438\u043b\u0430"
    ],
    "name:swe_x_preferred":[
        "Kila"
    ],
    "name:ukr_x_preferred":[
        "\u041a\u0438\u043b\u0430"
    ],
    "wof:name":"Kila",
    "wof:placetype":"locality"
},
  "geometry": {"coordinates":[25.501,-6.38974],"type":"Point"}
}