{
  "type": "Feature",
  "properties": {
    "gn:admin1_code":"22.0",
    "gn:asciiname":"Tshifwaie",
    "gn:country_code":"CD",
    "gn:dem":1145,
    "gn:feature_class":"P",
    "gn:feature_code":"PPL",
    "gn:name":"Tshifwaie",
    "gn:population":0,
    "gn:timezone":"Africa/Lubumbashi",
    "iso:country":"CD",
    "wof:name":"Tshifwaie",
    "wof:placetype":"locality"
},
  "geometry": {"coordinates":[24.19229,-10.23285],"type":"Point"}
}