{
  "type": "Feature",
  "properties": {
    "gn:admin1_code":"11.0",
    "gn:asciiname":"Lukweti",
    "gn:country_code":"CD",
    "gn:dem":1320,
    "gn:feature_class":"P",
    "gn:feature_code":"PPL",
    "gn:name":"Lukweti",
    "gn:population":0,
    "gn:timezone":"Africa/Lubumbashi",
    "iso:country":"CD",
    "wof:name":"Lukweti",
    "wof:placetype":"locality"
},
  "geometry": {"coordinates":[28.74361,-1.20667],"type":"Point"}
}