{
  "type": "Feature",
  "properties": {
    "gn:admin1_code":"12.0",
    "gn:asciiname":"Kaboke",
    "gn:country_code":"CD",
    "gn:dem":782,
    "gn:feature_class":"P",
    "gn:feature_code":"PPL",
    "gn:name":"Kaboke",
    "gn:population":0,
    "gn:timezone":"Africa/Lubumbashi",
    "iso:country":"CD",
    "wof:name":"Kaboke",
    "wof:placetype":"locality"
},
  "geometry": {"coordinates":[29.09972,-3.84556],"type":"Point"}
}