{
  "type": "Feature",
  "properties": {
    "gn:admin1_code":"17.0",
    "gn:asciiname":"Bukulu",
    "gn:country_code":"CD",
    "gn:dem":932,
    "gn:feature_class":"P",
    "gn:feature_code":"PPL",
    "gn:name":"Bukulu",
    "gn:population":0,
    "gn:timezone":"Africa/Lubumbashi",
    "iso:country":"CD",
    "name:fra_x_preferred":[
        "Bukulu"
    ],
    "wof:name":"Bukulu",
    "wof:placetype":"locality"
},
  "geometry": {"coordinates":[29.75055,1.57569],"type":"Point"}
}