{
  "type": "Feature",
  "properties": {
    "gn:admin1_code":"28.0",
    "gn:asciiname":"Tubute",
    "gn:country_code":"CD",
    "gn:dem":410,
    "gn:feature_class":"P",
    "gn:feature_code":"PPL",
    "gn:name":"Tubute",
    "gn:population":0,
    "gn:timezone":"Africa/Kinshasa",
    "iso:country":"CD",
    "name:fra_x_preferred":[
        "Tubute"
    ],
    "wof:name":"Tubute",
    "wof:placetype":"locality"
},
  "geometry": {"coordinates":[19.61655,2.8108],"type":"Point"}
}