{
  "type": "Feature",
  "properties": {
    "gn:admin1_code":"23.0",
    "gn:asciiname":"Kasombo",
    "gn:country_code":"CD",
    "gn:dem":845,
    "gn:feature_class":"P",
    "gn:feature_code":"PPL",
    "gn:name":"Kasombo",
    "gn:population":0,
    "gn:timezone":"Africa/Lubumbashi",
    "iso:country":"CD",
    "wof:name":"Kasombo",
    "wof:placetype":"locality"
},
  "geometry": {"coordinates":[21.93759,-7.42011],"type":"Point"}
}