{
  "type": "Feature",
  "properties": {
    "gn:admin1_code":"11.0",
    "gn:asciiname":"Sisumba",
    "gn:country_code":"CD",
    "gn:dem":1061,
    "gn:feature_class":"P",
    "gn:feature_code":"PPL",
    "gn:name":"Sisumba",
    "gn:population":0,
    "gn:timezone":"Africa/Lubumbashi",
    "iso:country":"CD",
    "wof:name":"Sisumba",
    "wof:placetype":"locality"
},
  "geometry": {"coordinates":[29.72017,0.25897],"type":"Point"}
}