{
  "type": "Feature",
  "properties": {
    "gn:admin1_code":"21.0",
    "gn:asciiname":"Lukuna",
    "gn:country_code":"CD",
    "gn:dem":746,
    "gn:feature_class":"P",
    "gn:feature_code":"PPL",
    "gn:name":"Lukuna",
    "gn:population":0,
    "gn:timezone":"Africa/Lubumbashi",
    "iso:country":"CD",
    "wof:name":"Lukuna",
    "wof:placetype":"locality"
},
  "geometry": {"coordinates":[23.93796,-6.87703],"type":"Point"}
}