{
  "type": "Feature",
  "properties": {
    "gn:admin1_code":"19.0",
    "gn:asciiname":"Shakamwanga",
    "gn:country_code":"CD",
    "gn:dem":1130,
    "gn:feature_class":"P",
    "gn:feature_code":"PPL",
    "gn:name":"Shakamwanga",
    "gn:population":0,
    "gn:timezone":"Africa/Kinshasa",
    "iso:country":"CD",
    "wof:name":"Shakamwanga",
    "wof:placetype":"locality"
},
  "geometry": {"coordinates":[18.90794,-7.95593],"type":"Point"}
}