{
  "type": "Feature",
  "properties": {
    "gn:admin1_code":"10.0",
    "gn:asciiname":"Etuku",
    "gn:country_code":"CD",
    "gn:dem":532,
    "gn:feature_class":"P",
    "gn:feature_code":"PPL",
    "gn:name":"Etuku",
    "gn:population":0,
    "gn:timezone":"Africa/Lubumbashi",
    "iso:country":"CD",
    "wof:name":"Etuku",
    "wof:placetype":"locality"
},
  "geometry": {"coordinates":[25.05985,-4.09221],"type":"Point"}
}