{
  "type": "Feature",
  "properties": {
    "gn:admin1_code":"19.0",
    "gn:asciiname":"Kana-Rumba",
    "gn:country_code":"CD",
    "gn:dem":438,
    "gn:feature_class":"P",
    "gn:feature_code":"PPL",
    "gn:name":"Kana-Rumba",
    "gn:population":0,
    "gn:timezone":"Africa/Kinshasa",
    "iso:country":"CD",
    "wof:name":"Kana-Rumba",
    "wof:placetype":"locality"
},
  "geometry": {"coordinates":[16.50038,-5.67471],"type":"Point"}
}