{
  "type": "Feature",
  "properties": {
    "gn:admin1_code":"11.0",
    "gn:asciiname":"Kirumba",
    "gn:country_code":"CD",
    "gn:dem":1770,
    "gn:feature_class":"P",
    "gn:feature_code":"PPL",
    "gn:name":"Kirumba",
    "gn:population":0,
    "gn:timezone":"Africa/Lubumbashi",
    "iso:country":"CD",
    "wof:name":"Kirumba",
    "wof:placetype":"locality"
},
  "geometry": {"coordinates":[29.1752,-0.55345],"type":"Point"}
}