{
  "type": "Feature",
  "properties": {
    "gn:admin1_code":"22.0",
    "gn:asciiname":"Wabwenze",
    "gn:country_code":"CD",
    "gn:dem":1005,
    "gn:feature_class":"P",
    "gn:feature_code":"PPL",
    "gn:name":"Wabwenze",
    "gn:population":0,
    "gn:timezone":"Africa/Lubumbashi",
    "iso:country":"CD",
    "wof:name":"Wabwenze",
    "wof:placetype":"locality"
},
  "geometry": {"coordinates":[26.52584,-10.04908],"type":"Point"}
}