{
  "type": "Feature",
  "properties": {
    "gn:admin1_code":"18.0",
    "gn:asciiname":"Tshiwanuanda",
    "gn:country_code":"CD",
    "gn:dem":684,
    "gn:feature_class":"P",
    "gn:feature_code":"PPL",
    "gn:name":"Tshiwanuanda",
    "gn:population":0,
    "gn:timezone":"Africa/Lubumbashi",
    "iso:country":"CD",
    "wof:name":"Tshiwanuanda",
    "wof:placetype":"locality"
},
  "geometry": {"coordinates":[20.3717,-6.58944],"type":"Point"}
}