{
  "type": "Feature",
  "properties": {
    "gn:admin1_code":"19.0",
    "gn:asciiname":"Shamuhunga",
    "gn:country_code":"CD",
    "gn:dem":887,
    "gn:feature_class":"P",
    "gn:feature_code":"PPL",
    "gn:name":"Shamuhunga",
    "gn:population":0,
    "gn:timezone":"Africa/Kinshasa",
    "iso:country":"CD",
    "wof:name":"Shamuhunga",
    "wof:placetype":"locality"
},
  "geometry": {"coordinates":[18.19031,-6.4945],"type":"Point"}
}