{
  "type": "Feature",
  "properties": {
    "gn:admin1_code":"19.0",
    "gn:asciiname":"Manzengele",
    "gn:country_code":"CD",
    "gn:dem":469,
    "gn:feature_class":"P",
    "gn:feature_code":"PPL",
    "gn:name":"Manzengele",
    "gn:population":0,
    "gn:timezone":"Africa/Luanda",
    "iso:country":"CD",
    "wof:name":"Manzengele",
    "wof:placetype":"locality"
},
  "geometry": {"coordinates":[16.7739,-6.67938],"type":"Point"}
}