{
  "type": "Feature",
  "properties": {
    "gn:admin1_code":"10.0",
    "gn:asciiname":"Donga",
    "gn:country_code":"CD",
    "gn:dem":613,
    "gn:feature_class":"P",
    "gn:feature_code":"PPL",
    "gn:name":"Donga",
    "gn:population":0,
    "gn:timezone":"Africa/Lubumbashi",
    "iso:country":"CD",
    "name:ceb_x_preferred":[
        "Donga"
    ],
    "name:deu_x_preferred":[
        "Donga"
    ],
    "name:fas_x_preferred":[
        "\u062f\u0648\u0646\u06af\u0627"
    ],
    "name:fra_x_preferred":[
        "Donga"
    ],
    "name:heb_x_preferred":[
        "\u05d3\u05d5\u05e0\u05d2\u05d4"
    ],
    "name:ita_x_preferred":[
        "Donga"
    ],
    "name:jpn_x_preferred":[
        "\u30c9\u30f3\u30ac"
    ],
    "name:slk_x_preferred":[
        "Donga"
    ],
    "name:swe_x_preferred":[
        "Donga"
    ],
    "wof:name":"Donga",
    "wof:placetype":"locality"
},
  "geometry": {"coordinates":[26.63055,-1.62319],"type":"Point"}
}