{
  "type": "Feature",
  "properties": {
    "gn:admin1_code":"10.0",
    "gn:asciiname":"Donga",
    "gn:country_code":"CD",
    "gn:dem":613,
    "gn:feature_class":"P",
    "gn:feature_code":"PPL",
    "gn:name":"Donga",
    "gn:population":0,
    "gn:timezone":"Africa/Lubumbashi",
    "iso:country":"CD",
    "wof:name":"Donga",
    "wof:placetype":"locality"
},
  "geometry": {"coordinates":[26.63055,-1.62319],"type":"Point"}
}