{
  "type": "Feature",
  "properties": {
    "gn:admin1_code":"12.0",
    "gn:asciiname":"Tshopo",
    "gn:country_code":"CD",
    "gn:dem":1134,
    "gn:feature_class":"P",
    "gn:feature_code":"PPL",
    "gn:name":"Tshopo",
    "gn:population":0,
    "gn:timezone":"Africa/Lubumbashi",
    "iso:country":"CD",
    "wof:name":"Tshopo",
    "wof:placetype":"locality"
},
  "geometry": {"coordinates":[28.28333,-2.93333],"type":"Point"}
}