{
  "type": "Feature",
  "properties": {
    "gn:admin1_code":"19.0",
    "gn:asciiname":"Kapemba",
    "gn:country_code":"CD",
    "gn:dem":1061,
    "gn:feature_class":"P",
    "gn:feature_code":"PPL",
    "gn:name":"Kapemba",
    "gn:population":0,
    "gn:timezone":"Africa/Kinshasa",
    "iso:country":"CD",
    "wof:name":"Kapemba",
    "wof:placetype":"locality"
},
  "geometry": {"coordinates":[18.45409,-7.56178],"type":"Point"}
}