{
  "type": "Feature",
  "properties": {
    "gn:admin1_code":"19.0",
    "gn:asciiname":"Mwa-Mufiya",
    "gn:country_code":"CD",
    "gn:dem":1118,
    "gn:feature_class":"P",
    "gn:feature_code":"PPL",
    "gn:name":"Mwa-Mufiya",
    "gn:population":0,
    "gn:timezone":"Africa/Kinshasa",
    "iso:country":"CD",
    "wof:name":"Mwa-Mufiya",
    "wof:placetype":"locality"
},
  "geometry": {"coordinates":[18.41103,-7.35253],"type":"Point"}
}