{
  "type": "Feature",
  "properties": {
    "gn:admin1_code":"27.0",
    "gn:asciiname":"Wunge",
    "gn:country_code":"CD",
    "gn:dem":672,
    "gn:feature_class":"P",
    "gn:feature_code":"PPL",
    "gn:name":"Wunge",
    "gn:population":0,
    "gn:timezone":"Africa/Lubumbashi",
    "iso:country":"CD",
    "wof:name":"Wunge",
    "wof:placetype":"locality"
},
  "geometry": {"coordinates":[24.48904,-4.39973],"type":"Point"}
}