{
  "type": "Feature",
  "properties": {
    "gn:admin1_code":"15.0",
    "gn:asciiname":"Kalemba",
    "gn:country_code":"CD",
    "gn:dem":617,
    "gn:feature_class":"P",
    "gn:feature_code":"PPL",
    "gn:name":"Kalemba",
    "gn:population":0,
    "gn:timezone":"Africa/Lubumbashi",
    "iso:country":"CD",
    "wof:name":"Kalemba",
    "wof:placetype":"locality"
},
  "geometry": {"coordinates":[27.1357,-7.76328],"type":"Point"}
}