{
  "type": "Feature",
  "properties": {
    "gn:admin1_code":"29.0",
    "gn:asciiname":"Musosa",
    "gn:country_code":"CD",
    "gn:dem":991,
    "gn:feature_class":"P",
    "gn:feature_code":"PPL",
    "gn:name":"Musosa",
    "gn:population":0,
    "gn:timezone":"Africa/Lubumbashi",
    "iso:country":"CD",
    "wof:name":"Musosa",
    "wof:placetype":"locality"
},
  "geometry": {"coordinates":[29.65777000000001,-8.34828],"type":"Point"}
}