{
  "type": "Feature",
  "properties": {
    "gn:admin1_code":"23.0",
    "gn:asciiname":"Kayembe-Kabinda",
    "gn:country_code":"CD",
    "gn:dem":768,
    "gn:feature_class":"P",
    "gn:feature_code":"PPL",
    "gn:name":"Kayembe-Kabinda",
    "gn:population":0,
    "gn:timezone":"Africa/Lubumbashi",
    "iso:country":"CD",
    "wof:name":"Kayembe-Kabinda",
    "wof:placetype":"locality"
},
  "geometry": {"coordinates":[21.99486,-6.38588],"type":"Point"}
}