{
  "type": "Feature",
  "properties": {
    "gn:admin1_code":"23.0",
    "gn:asciiname":"Musangana",
    "gn:country_code":"CD",
    "gn:dem":749,
    "gn:feature_class":"P",
    "gn:feature_code":"PPL",
    "gn:name":"Musangana",
    "gn:population":0,
    "gn:timezone":"Africa/Lubumbashi",
    "iso:country":"CD",
    "wof:name":"Musangana",
    "wof:placetype":"locality"
},
  "geometry": {"coordinates":[22.9083,-5.78629],"type":"Point"}
}