{
  "type": "Feature",
  "properties": {
    "gn:admin1_code":"8.0",
    "gn:asciiname":"Pangala",
    "gn:country_code":"CD",
    "gn:dem":420,
    "gn:feature_class":"P",
    "gn:feature_code":"PPL",
    "gn:name":"Pangala",
    "gn:population":0,
    "gn:timezone":"Africa/Kinshasa",
    "iso:country":"CD",
    "name:und_x_variant":[
        "Pengala"
    ],
    "wof:name":"Pangala",
    "wof:placetype":"locality"
},
  "geometry": {"coordinates":[15.11045,-4.60575],"type":"Point"}
}