{
  "type": "Feature",
  "properties": {
    "gn:admin1_code":"10.0",
    "gn:asciiname":"Kalomo",
    "gn:country_code":"CD",
    "gn:dem":583,
    "gn:feature_class":"P",
    "gn:feature_code":"PPL",
    "gn:name":"Kalomo",
    "gn:population":0,
    "gn:timezone":"Africa/Lubumbashi",
    "iso:country":"CD",
    "name:bul_x_preferred":[
        "\u041a\u0430\u043b\u043e\u043c\u043e"
    ],
    "name:deu_x_preferred":[
        "Kalomo"
    ],
    "name:fra_x_preferred":[
        "Kalomo"
    ],
    "name:ita_x_preferred":[
        "Kalomo"
    ],
    "name:mrj_x_preferred":[
        "\u041a\u0430\u043b\u043e\u043c\u043e"
    ],
    "name:pol_x_preferred":[
        "Kalomo"
    ],
    "name:por_x_preferred":[
        "Kalomo"
    ],
    "name:ron_x_preferred":[
        "Kalomo"
    ],
    "name:spa_x_preferred":[
        "Kalomo"
    ],
    "name:zho_x_preferred":[
        "\u5361\u6d1b\u83ab"
    ],
    "wof:name":"Kalomo",
    "wof:placetype":"locality"
},
  "geometry": {"coordinates":[26.66213,-4.15379],"type":"Point"}
}