{
  "type": "Feature",
  "properties": {
    "gn:admin1_code":"10.0",
    "gn:asciiname":"Mitaku",
    "gn:country_code":"CD",
    "gn:dem":524,
    "gn:feature_class":"P",
    "gn:feature_code":"PPL",
    "gn:name":"Mitaku",
    "gn:population":0,
    "gn:timezone":"Africa/Lubumbashi",
    "iso:country":"CD",
    "wof:name":"Mitaku",
    "wof:placetype":"locality"
},
  "geometry": {"coordinates":[25.93333,-2.58333],"type":"Point"}
}