{
  "type": "Feature",
  "properties": {
    "gn:admin1_code":"19.0",
    "gn:asciiname":"Tambo-Tseke",
    "gn:country_code":"CD",
    "gn:dem":1019,
    "gn:feature_class":"P",
    "gn:feature_code":"PPL",
    "gn:name":"Tambo-Tseke",
    "gn:population":0,
    "gn:timezone":"Africa/Kinshasa",
    "iso:country":"CD",
    "name:und_x_variant":[
        "Tambo Tsheke",
        "Tambo-Tseke"
    ],
    "wof:name":"Tambo-Tseke",
    "wof:placetype":"locality"
},
  "geometry": {"coordinates":[17.79469,-6.98031],"type":"Point"}
}