{
  "type": "Feature",
  "properties": {
    "gn:admin1_code":"23.0",
    "gn:asciiname":"Bombeshi",
    "gn:country_code":"CD",
    "gn:dem":768,
    "gn:feature_class":"P",
    "gn:feature_code":"PPL",
    "gn:name":"Bombeshi",
    "gn:population":0,
    "gn:timezone":"Africa/Lubumbashi",
    "iso:country":"CD",
    "wof:name":"Bombeshi",
    "wof:placetype":"locality"
},
  "geometry": {"coordinates":[22.91585,-5.97576],"type":"Point"}
}