{
  "type": "Feature",
  "properties": {
    "gn:admin1_code":"8.0",
    "gn:asciiname":"Kinkalaba",
    "gn:country_code":"CD",
    "gn:dem":845,
    "gn:feature_class":"P",
    "gn:feature_code":"PPL",
    "gn:name":"Kinkalaba",
    "gn:population":0,
    "gn:timezone":"Africa/Kinshasa",
    "iso:country":"CD",
    "wof:name":"Kinkalaba",
    "wof:placetype":"locality"
},
  "geometry": {"coordinates":[16.10421,-5.63747],"type":"Point"}
}