{
  "type": "Feature",
  "properties": {
    "gn:admin1_code":"13.0",
    "gn:asciiname":"Bombwane",
    "gn:country_code":"CD",
    "gn:dem":581,
    "gn:feature_class":"P",
    "gn:feature_code":"PPL",
    "gn:name":"Bombwane",
    "gn:population":0,
    "gn:timezone":"Africa/Lubumbashi",
    "iso:country":"CD",
    "wof:name":"Bombwane",
    "wof:placetype":"locality"
},
  "geometry": {"coordinates":[25.04476,3.24656],"type":"Point"}
}