{
  "type": "Feature",
  "properties": {
    "gn:admin1_code":"14.0",
    "gn:asciiname":"Kabimbi",
    "gn:country_code":"CD",
    "gn:dem":927,
    "gn:feature_class":"P",
    "gn:feature_code":"PPL",
    "gn:name":"Kabimbi",
    "gn:population":0,
    "gn:timezone":"Africa/Lubumbashi",
    "iso:country":"CD",
    "wof:name":"Kabimbi",
    "wof:placetype":"locality"
},
  "geometry": {"coordinates":[28.63333,-9.88333],"type":"Point"}
}