{
  "type": "Feature",
  "properties": {
    "gn:admin1_code":"8.0",
    "gn:asciiname":"Yungu-Kimpangu",
    "gn:country_code":"CD",
    "gn:dem":724,
    "gn:feature_class":"P",
    "gn:feature_code":"PPL",
    "gn:name":"Yungu-Kimpangu",
    "gn:population":0,
    "gn:timezone":"Africa/Kinshasa",
    "iso:country":"CD",
    "name:und_x_variant":[
        "Yungu",
        "Yunga",
        "Yungu-Kimpangu"
    ],
    "wof:name":"Yungu-Kimpangu",
    "wof:placetype":"locality"
},
  "geometry": {"coordinates":[15.35483,-5.64279],"type":"Point"}
}