{
  "type": "Feature",
  "properties": {
    "gn:admin1_code":"20.0",
    "gn:asciiname":"Mwebale",
    "gn:country_code":"CD",
    "gn:dem":339,
    "gn:feature_class":"P",
    "gn:feature_code":"PPL",
    "gn:name":"Mwebale",
    "gn:population":0,
    "gn:timezone":"Africa/Kinshasa",
    "iso:country":"CD",
    "wof:name":"Mwebale",
    "wof:placetype":"locality"
},
  "geometry": {"coordinates":[17.92944,-3.83233],"type":"Point"}
}