{
  "type": "Feature",
  "properties": {
    "gn:admin1_code":"15.0",
    "gn:asciiname":"Kamola",
    "gn:country_code":"CD",
    "gn:dem":776,
    "gn:feature_class":"P",
    "gn:feature_code":"PPL",
    "gn:name":"Kamola",
    "gn:population":0,
    "gn:timezone":"Africa/Lubumbashi",
    "iso:country":"CD",
    "wof:name":"Kamola",
    "wof:placetype":"locality"
},
  "geometry": {"coordinates":[27.34927,-7.8747],"type":"Point"}
}