{
  "type": "Feature",
  "properties": {
    "gn:admin1_code":"29.0",
    "gn:asciiname":"Tobola",
    "gn:country_code":"CD",
    "gn:dem":571,
    "gn:feature_class":"P",
    "gn:feature_code":"PPL",
    "gn:name":"Tobola",
    "gn:population":0,
    "gn:timezone":"Africa/Lubumbashi",
    "iso:country":"CD",
    "wof:name":"Tobola",
    "wof:placetype":"locality"
},
  "geometry": {"coordinates":[26.97695,-5.45555],"type":"Point"}
}