{
  "type": "Feature",
  "properties": {
    "gn:admin1_code":"21.0",
    "gn:asciiname":"Katonkole",
    "gn:country_code":"CD",
    "gn:dem":870,
    "gn:feature_class":"P",
    "gn:feature_code":"PPL",
    "gn:name":"Katonkole",
    "gn:population":0,
    "gn:timezone":"Africa/Lubumbashi",
    "iso:country":"CD",
    "wof:name":"Katonkole",
    "wof:placetype":"locality"
},
  "geometry": {"coordinates":[25.44035,-6.62136],"type":"Point"}
}