{
  "type": "Feature",
  "properties": {
    "gn:admin1_code":"27.0",
    "gn:asciiname":"Olambo",
    "gn:country_code":"CD",
    "gn:dem":585,
    "gn:feature_class":"P",
    "gn:feature_code":"PPL",
    "gn:name":"Olambo",
    "gn:population":0,
    "gn:timezone":"Africa/Lubumbashi",
    "iso:country":"CD",
    "wof:name":"Olambo",
    "wof:placetype":"locality"
},
  "geometry": {"coordinates":[24.17368,-4.70953],"type":"Point"}
}