{
  "type": "Feature",
  "properties": {
    "gn:admin1_code":"31.0",
    "gn:asciiname":"Bengemba",
    "gn:country_code":"CD",
    "gn:dem":418,
    "gn:feature_class":"P",
    "gn:feature_code":"PPL",
    "gn:name":"Bengemba",
    "gn:population":0,
    "gn:timezone":"Africa/Kinshasa",
    "iso:country":"CD",
    "wof:name":"Bengemba",
    "wof:placetype":"locality"
},
  "geometry": {"coordinates":[23.05,-0.58333],"type":"Point"}
}