{
  "type": "Feature",
  "properties": {
    "gn:admin1_code":"27.0",
    "gn:asciiname":"Oikete",
    "gn:country_code":"CD",
    "gn:dem":424,
    "gn:feature_class":"P",
    "gn:feature_code":"PPL",
    "gn:name":"Oikete",
    "gn:population":0,
    "gn:timezone":"Africa/Lubumbashi",
    "iso:country":"CD",
    "name:und_x_variant":[
        "Dikete",
        "Oikete"
    ],
    "wof:name":"Oikete",
    "wof:placetype":"locality"
},
  "geometry": {"coordinates":[22.83333,-2.51667],"type":"Point"}
}