{
  "type": "Feature",
  "properties": {
    "gn:admin1_code":"22.0",
    "gn:asciiname":"Itasimbila",
    "gn:country_code":"CD",
    "gn:dem":958,
    "gn:feature_class":"P",
    "gn:feature_code":"PPL",
    "gn:name":"Itasimbila",
    "gn:population":0,
    "gn:timezone":"Africa/Lubumbashi",
    "iso:country":"CD",
    "wof:name":"Itasimbila",
    "wof:placetype":"locality"
},
  "geometry": {"coordinates":[23.13564,-10.43828],"type":"Point"}
}