{
  "type": "Feature",
  "properties": {
    "gn:admin1_code":"27.0",
    "gn:asciiname":"Shinga Deuxieme",
    "gn:country_code":"CD",
    "gn:dem":589,
    "gn:feature_class":"P",
    "gn:feature_code":"PPL",
    "gn:name":"Shinga Deuxi\u00e8me",
    "gn:population":0,
    "gn:timezone":"Africa/Lubumbashi",
    "iso:country":"CD",
    "name:und_x_variant":[
        "Shinga",
        "Shinga II",
        "Shinga Deuxi\u00e8me"
    ],
    "wof:name":"Shinga Deuxieme",
    "wof:placetype":"locality"
},
  "geometry": {"coordinates":[24.62797,-3.25559],"type":"Point"}
}