{
  "type": "Feature",
  "properties": {
    "gn:admin1_code":"0.0",
    "gn:asciiname":"Bena-Boyo",
    "gn:country_code":"CD",
    "gn:dem":640,
    "gn:feature_class":"P",
    "gn:feature_code":"PPL",
    "gn:name":"Bena-Boyo",
    "gn:population":0,
    "gn:timezone":"Africa/Lubumbashi",
    "iso:country":"CD",
    "wof:name":"Bena-Boyo",
    "wof:placetype":"locality"
},
  "geometry": {"coordinates":[24.01667,-6.45],"type":"Point"}
}