{
  "type": "Feature",
  "properties": {
    "gn:admin1_code":"10.0",
    "gn:asciiname":"Kiaupansa",
    "gn:country_code":"CD",
    "gn:dem":626,
    "gn:feature_class":"P",
    "gn:feature_code":"PPL",
    "gn:name":"Kiaupansa",
    "gn:population":0,
    "gn:timezone":"Africa/Lubumbashi",
    "iso:country":"CD",
    "wof:name":"Kiaupansa",
    "wof:placetype":"locality"
},
  "geometry": {"coordinates":[26.55736,-3.65327],"type":"Point"}
}