{
  "type": "Feature",
  "properties": {
    "gn:admin1_code":"18.0",
    "gn:asciiname":"Ndeke",
    "gn:country_code":"CD",
    "gn:dem":626,
    "gn:feature_class":"P",
    "gn:feature_code":"PPL",
    "gn:name":"Ndeke",
    "gn:population":0,
    "gn:timezone":"Africa/Lubumbashi",
    "iso:country":"CD",
    "wof:name":"Ndeke",
    "wof:placetype":"locality"
},
  "geometry": {"coordinates":[20.70300000000001,-6.4147],"type":"Point"}
}