{
  "type": "Feature",
  "properties": {
    "gn:admin1_code":"15.0",
    "gn:asciiname":"Kintambo",
    "gn:country_code":"CD",
    "gn:dem":732,
    "gn:feature_class":"P",
    "gn:feature_code":"PPL",
    "gn:name":"Kintambo",
    "gn:population":0,
    "gn:timezone":"Africa/Lubumbashi",
    "iso:country":"CD",
    "name:ceb_x_preferred":[
        "Kintambo"
    ],
    "name:eus_x_preferred":[
        "Kintambo"
    ],
    "name:fra_x_preferred":[
        "Kintambo"
    ],
    "name:lin_x_preferred":[
        "Kint\u00e1mb\u00f3"
    ],
    "name:swe_x_preferred":[
        "Kintambo"
    ],
    "wof:name":"Kintambo",
    "wof:placetype":"locality"
},
  "geometry": {"coordinates":[25.38333,-9.11667],"type":"Point"}
}