{
  "type": "Feature",
  "properties": {
    "gn:admin1_code":"20.0",
    "gn:asciiname":"Mubolu",
    "gn:country_code":"CD",
    "gn:dem":730,
    "gn:feature_class":"P",
    "gn:feature_code":"PPL",
    "gn:name":"Mubolu",
    "gn:population":0,
    "gn:timezone":"Africa/Kinshasa",
    "iso:country":"CD",
    "wof:name":"Mubolu",
    "wof:placetype":"locality"
},
  "geometry": {"coordinates":[19.18072,-5.31152],"type":"Point"}
}