{
  "type": "Feature",
  "properties": {
    "gn:admin1_code":"14.0",
    "gn:asciiname":"Musolo",
    "gn:country_code":"CD",
    "gn:dem":1156,
    "gn:feature_class":"P",
    "gn:feature_code":"PPL",
    "gn:name":"Musolo",
    "gn:population":0,
    "gn:timezone":"Africa/Lubumbashi",
    "iso:country":"CD",
    "wof:name":"Musolo",
    "wof:placetype":"locality"
},
  "geometry": {"coordinates":[29.21614000000001,-12.38253],"type":"Point"}
}