{
  "type": "Feature",
  "properties": {
    "gn:admin1_code":"30.0",
    "gn:asciiname":"Bongandjola",
    "gn:country_code":"CD",
    "gn:dem":427,
    "gn:feature_class":"P",
    "gn:feature_code":"PPL",
    "gn:name":"Bongandjola",
    "gn:population":0,
    "gn:timezone":"Africa/Lubumbashi",
    "iso:country":"CD",
    "wof:name":"Bongandjola",
    "wof:placetype":"locality"
},
  "geometry": {"coordinates":[25.5179,1.75483],"type":"Point"}
}