{
  "type": "Feature",
  "properties": {
    "gn:admin1_code":"23.0",
    "gn:asciiname":"Musasa",
    "gn:country_code":"CD",
    "gn:dem":858,
    "gn:feature_class":"P",
    "gn:feature_code":"PPL",
    "gn:name":"Musasa",
    "gn:population":0,
    "gn:timezone":"Africa/Lubumbashi",
    "iso:country":"CD",
    "name:ceb_x_preferred":[
        "Musasa"
    ],
    "name:swe_x_preferred":[
        "Musasa"
    ],
    "wof:name":"Musasa",
    "wof:placetype":"locality"
},
  "geometry": {"coordinates":[22.34978,-6.77593],"type":"Point"}
}