{
  "type": "Feature",
  "properties": {
    "gn:admin1_code":"30.0",
    "gn:asciiname":"Badumbi",
    "gn:country_code":"CD",
    "gn:dem":441,
    "gn:feature_class":"P",
    "gn:feature_code":"PPL",
    "gn:name":"Badumbi",
    "gn:population":0,
    "gn:timezone":"Africa/Lubumbashi",
    "iso:country":"CD",
    "wof:name":"Badumbi",
    "wof:placetype":"locality"
},
  "geometry": {"coordinates":[25.29886,0.71969],"type":"Point"}
}