{
  "type": "Feature",
  "properties": {
    "gn:admin1_code":"30.0",
    "gn:asciiname":"Yakotambi",
    "gn:country_code":"CD",
    "gn:dem":381,
    "gn:feature_class":"P",
    "gn:feature_code":"PPL",
    "gn:name":"Yakotambi",
    "gn:population":0,
    "gn:timezone":"Africa/Lubumbashi",
    "iso:country":"CD",
    "name:und_x_variant":[
        "Yakobombi",
        "Yakotambi"
    ],
    "wof:name":"Yakotambi",
    "wof:placetype":"locality"
},
  "geometry": {"coordinates":[23.07719,2.00426],"type":"Point"}
}