{
  "type": "Feature",
  "properties": {
    "gn:admin1_code":"17.0",
    "gn:asciiname":"Kiloba",
    "gn:country_code":"CD",
    "gn:dem":1702,
    "gn:feature_class":"P",
    "gn:feature_code":"PPL",
    "gn:name":"Kiloba",
    "gn:population":0,
    "gn:timezone":"Africa/Lubumbashi",
    "iso:country":"CD",
    "wof:name":"Kiloba",
    "wof:placetype":"locality"
},
  "geometry": {"coordinates":[30.57518,2.06808],"type":"Point"}
}