{
  "type": "Feature",
  "properties": {
    "gn:admin1_code":"19.0",
    "gn:asciiname":"Tsutsu",
    "gn:country_code":"CD",
    "gn:dem":529,
    "gn:feature_class":"P",
    "gn:feature_code":"PPL",
    "gn:name":"Tsutsu",
    "gn:population":0,
    "gn:timezone":"Africa/Kinshasa",
    "iso:country":"CD",
    "wof:name":"Tsutsu",
    "wof:placetype":"locality"
},
  "geometry": {"coordinates":[16.8874,-6.14796],"type":"Point"}
}