{
  "type": "Feature",
  "properties": {
    "gn:admin1_code":"12.0",
    "gn:asciiname":"Kamisimbi",
    "gn:country_code":"CD",
    "gn:dem":2205,
    "gn:feature_class":"P",
    "gn:feature_code":"PPL",
    "gn:name":"Kamisimbi",
    "gn:population":0,
    "gn:timezone":"Africa/Lubumbashi",
    "iso:country":"CD",
    "wof:name":"Kamisimbi",
    "wof:placetype":"locality"
},
  "geometry": {"coordinates":[28.80091,-2.57783],"type":"Point"}
}