{
  "type": "Feature",
  "properties": {
    "gn:admin1_code":"22.0",
    "gn:asciiname":"Ngulu",
    "gn:country_code":"CD",
    "gn:dem":975,
    "gn:feature_class":"P",
    "gn:feature_code":"PPL",
    "gn:name":"Ngulu",
    "gn:population":0,
    "gn:timezone":"Africa/Lubumbashi",
    "iso:country":"CD",
    "wof:name":"Ngulu",
    "wof:placetype":"locality"
},
  "geometry": {"coordinates":[23.57733,-8.05806],"type":"Point"}
}