{
  "type": "Feature",
  "properties": {
    "gn:admin1_code":"26.0",
    "gn:asciiname":"Toko",
    "gn:country_code":"CD",
    "gn:dem":390,
    "gn:feature_class":"P",
    "gn:feature_code":"PPL",
    "gn:name":"Toko",
    "gn:population":0,
    "gn:timezone":"Africa/Kinshasa",
    "iso:country":"CD",
    "name:ceb_x_preferred":[
        "Toko"
    ],
    "name:fra_x_preferred":[
        "Toko"
    ],
    "name:mri_x_preferred":[
        "Toko"
    ],
    "wof:name":"Toko",
    "wof:placetype":"locality"
},
  "geometry": {"coordinates":[20.11028,4.81497],"type":"Point"}
}