{
  "type": "Feature",
  "properties": {
    "gn:admin1_code":"10.0",
    "gn:asciiname":"Kapuri",
    "gn:country_code":"CD",
    "gn:dem":641,
    "gn:feature_class":"P",
    "gn:feature_code":"PPL",
    "gn:name":"Kapuri",
    "gn:population":0,
    "gn:timezone":"Africa/Lubumbashi",
    "iso:country":"CD",
    "wof:name":"Kapuri",
    "wof:placetype":"locality"
},
  "geometry": {"coordinates":[26.89575,-3.57521],"type":"Point"}
}