{
  "type": "Feature",
  "properties": {
    "gn:admin1_code":"29.0",
    "gn:asciiname":"Kabianda",
    "gn:country_code":"CD",
    "gn:dem":1068,
    "gn:feature_class":"P",
    "gn:feature_code":"PPL",
    "gn:name":"Kabianda",
    "gn:population":0,
    "gn:timezone":"Africa/Lubumbashi",
    "iso:country":"CD",
    "wof:name":"Kabianda",
    "wof:placetype":"locality"
},
  "geometry": {"coordinates":[29.06667,-5.61667],"type":"Point"}
}