{
  "type": "Feature",
  "properties": {
    "gn:admin1_code":"6.0",
    "gn:asciiname":"Camile",
    "gn:country_code":"CD",
    "gn:dem":370,
    "gn:feature_class":"P",
    "gn:feature_code":"PPL",
    "gn:name":"Camile",
    "gn:population":0,
    "gn:timezone":"Africa/Kinshasa",
    "iso:country":"CD",
    "wof:name":"Camile",
    "wof:placetype":"locality"
},
  "geometry": {"coordinates":[15.18277,-4.39558],"type":"Point"}
}