{
  "type": "Feature",
  "properties": {
    "gn:admin1_code":"21.0",
    "gn:asciiname":"Pongo",
    "gn:country_code":"CD",
    "gn:dem":830,
    "gn:feature_class":"P",
    "gn:feature_code":"PPL",
    "gn:name":"Pongo",
    "gn:population":0,
    "gn:timezone":"Africa/Lubumbashi",
    "iso:country":"CD",
    "name:ceb_x_preferred":[
        "Pongo"
    ],
    "name:deu_x_preferred":[
        "Pongo"
    ],
    "name:fra_x_preferred":[
        "Pongo"
    ],
    "name:ita_x_preferred":[
        "Pongo"
    ],
    "name:swe_x_preferred":[
        "Pongo"
    ],
    "wof:name":"Pongo",
    "wof:placetype":"locality"
},
  "geometry": {"coordinates":[24.59192,-6.51269],"type":"Point"}
}