{
  "type": "Feature",
  "properties": {
    "gn:admin1_code":"18.0",
    "gn:asciiname":"Bushila",
    "gn:country_code":"CD",
    "gn:dem":651,
    "gn:feature_class":"P",
    "gn:feature_code":"PPL",
    "gn:name":"Bushila",
    "gn:population":0,
    "gn:timezone":"Africa/Lubumbashi",
    "iso:country":"CD",
    "wof:name":"Bushila",
    "wof:placetype":"locality"
},
  "geometry": {"coordinates":[21.30309,-6.50752],"type":"Point"}
}