{
  "type": "Feature",
  "properties": {
    "gn:admin1_code":"20.0",
    "gn:asciiname":"Kitobo",
    "gn:country_code":"CD",
    "gn:dem":755,
    "gn:feature_class":"P",
    "gn:feature_code":"PPL",
    "gn:name":"Kitobo",
    "gn:population":0,
    "gn:timezone":"Africa/Kinshasa",
    "iso:country":"CD",
    "wof:name":"Kitobo",
    "wof:placetype":"locality"
},
  "geometry": {"coordinates":[19.08068,-5.74482],"type":"Point"}
}