{
  "type": "Feature",
  "properties": {
    "gn:admin1_code":"8.0",
    "gn:asciiname":"Ntamba",
    "gn:country_code":"CD",
    "gn:dem":510,
    "gn:feature_class":"P",
    "gn:feature_code":"PPL",
    "gn:name":"Ntamba",
    "gn:population":0,
    "gn:timezone":"Africa/Kinshasa",
    "iso:country":"CD",
    "name:hye_x_preferred":[
        "\u0546\u057f\u0561\u0574\u0562\u0561"
    ],
    "name:run_x_preferred":[
        "Ntamba"
    ],
    "wof:name":"Ntamba",
    "wof:placetype":"locality"
},
  "geometry": {"coordinates":[13.88174,-5.02296],"type":"Point"}
}