{
  "type": "Feature",
  "properties": {
    "gn:admin1_code":"11.0",
    "gn:asciiname":"Kangambili",
    "gn:country_code":"CD",
    "gn:dem":679,
    "gn:feature_class":"P",
    "gn:feature_code":"PPL",
    "gn:name":"Kangambili",
    "gn:population":0,
    "gn:timezone":"Africa/Lubumbashi",
    "iso:country":"CD",
    "wof:name":"Kangambili",
    "wof:placetype":"locality"
},
  "geometry": {"coordinates":[28.07236,-1.42253],"type":"Point"}
}