{
  "type": "Feature",
  "properties": {
    "gn:admin1_code":"20.0",
    "gn:asciiname":"Pembe",
    "gn:country_code":"CD",
    "gn:dem":723,
    "gn:feature_class":"P",
    "gn:feature_code":"PPL",
    "gn:name":"Pembe",
    "gn:population":0,
    "gn:timezone":"Africa/Kinshasa",
    "iso:country":"CD",
    "name:bar_x_preferred":[
        "Pembe"
    ],
    "name:mkd_x_preferred":[
        "\u041f\u0435\u043c\u0431\u0435"
    ],
    "wof:name":"Pembe",
    "wof:placetype":"locality"
},
  "geometry": {"coordinates":[19.1964,-5.53605],"type":"Point"}
}