{
  "type": "Feature",
  "properties": {
    "gn:admin1_code":"13.0",
    "gn:asciiname":"Bongalanza",
    "gn:country_code":"CD",
    "gn:dem":574,
    "gn:feature_class":"P",
    "gn:feature_code":"PPL",
    "gn:name":"Bongalanza",
    "gn:population":0,
    "gn:timezone":"Africa/Lubumbashi",
    "iso:country":"CD",
    "wof:name":"Bongalanza",
    "wof:placetype":"locality"
},
  "geometry": {"coordinates":[25.02874,3.23772],"type":"Point"}
}