{
  "type": "Feature",
  "properties": {
    "gn:admin1_code":"30.0",
    "gn:asciiname":"Kikongo",
    "gn:country_code":"CD",
    "gn:dem":456,
    "gn:feature_class":"P",
    "gn:feature_code":"PPL",
    "gn:name":"Kikongo",
    "gn:population":0,
    "gn:timezone":"Africa/Lubumbashi",
    "iso:country":"CD",
    "wof:name":"Kikongo",
    "wof:placetype":"locality"
},
  "geometry": {"coordinates":[25.43382,-0.40789],"type":"Point"}
}