{
  "type": "Feature",
  "properties": {
    "gn:admin1_code":"19.0",
    "gn:asciiname":"Kwakasa",
    "gn:country_code":"CD",
    "gn:dem":837,
    "gn:feature_class":"P",
    "gn:feature_code":"PPL",
    "gn:name":"Kwakasa",
    "gn:population":0,
    "gn:timezone":"Africa/Kinshasa",
    "iso:country":"CD",
    "wof:name":"Kwakasa",
    "wof:placetype":"locality"
},
  "geometry": {"coordinates":[17.69777999999999,-5.93323],"type":"Point"}
}