{
  "type": "Feature",
  "properties": {
    "gn:admin1_code":"13.0",
    "gn:asciiname":"Kende",
    "gn:country_code":"CD",
    "gn:dem":610,
    "gn:feature_class":"P",
    "gn:feature_code":"PPL",
    "gn:name":"Kende",
    "gn:population":0,
    "gn:timezone":"Africa/Lubumbashi",
    "iso:country":"CD",
    "name:deu_x_preferred":[
        "Kende"
    ],
    "name:fra_x_preferred":[
        "Kende"
    ],
    "name:hun_x_preferred":[
        "Kende"
    ],
    "name:nld_x_preferred":[
        "Kende"
    ],
    "name:slv_x_preferred":[
        "Kende"
    ],
    "wof:name":"Kende",
    "wof:placetype":"locality"
},
  "geometry": {"coordinates":[24.73649,4.67951],"type":"Point"}
}