{
  "type": "Feature",
  "properties": {
    "gn:admin1_code":"14.0",
    "gn:asciiname":"Kiona Zini",
    "gn:country_code":"CD",
    "gn:dem":995,
    "gn:feature_class":"P",
    "gn:feature_code":"PPL",
    "gn:name":"Kiona Zini",
    "gn:population":0,
    "gn:timezone":"Africa/Lubumbashi",
    "iso:country":"CD",
    "wof:name":"Kiona Zini",
    "wof:placetype":"locality"
},
  "geometry": {"coordinates":[28.4695,-8.59926],"type":"Point"}
}