{
  "type": "Feature",
  "properties": {
    "gn:admin1_code":"22.0",
    "gn:asciiname":"Sangonda",
    "gn:country_code":"CD",
    "gn:dem":897,
    "gn:feature_class":"P",
    "gn:feature_code":"PPL",
    "gn:name":"Sangonda",
    "gn:population":0,
    "gn:timezone":"Africa/Lubumbashi",
    "iso:country":"CD",
    "wof:name":"Sangonda",
    "wof:placetype":"locality"
},
  "geometry": {"coordinates":[22.86765,-9.66804],"type":"Point"}
}