{
  "type": "Feature",
  "properties": {
    "gn:admin1_code":"20.0",
    "gn:asciiname":"Kingombe",
    "gn:country_code":"CD",
    "gn:dem":528,
    "gn:feature_class":"P",
    "gn:feature_code":"PPL",
    "gn:name":"Kingombe",
    "gn:population":0,
    "gn:timezone":"Africa/Kinshasa",
    "iso:country":"CD",
    "wof:name":"Kingombe",
    "wof:placetype":"locality"
},
  "geometry": {"coordinates":[18.33986,-5.37595],"type":"Point"}
}