{
  "type": "Feature",
  "properties": {
    "gn:admin1_code":"22.0",
    "gn:asciiname":"Mwene-Putu",
    "gn:country_code":"CD",
    "gn:dem":1257,
    "gn:feature_class":"P",
    "gn:feature_code":"PPL",
    "gn:name":"Mwene-Putu",
    "gn:population":0,
    "gn:timezone":"Africa/Lubumbashi",
    "iso:country":"CD",
    "wof:name":"Mwene-Putu",
    "wof:placetype":"locality"
},
  "geometry": {"coordinates":[23.6033,-10.96002],"type":"Point"}
}