{
  "type": "Feature",
  "properties": {
    "gn:admin1_code":"22.0",
    "gn:asciiname":"Mwin Ndej",
    "gn:country_code":"CD",
    "gn:dem":1050,
    "gn:feature_class":"P",
    "gn:feature_code":"PPL",
    "gn:name":"Mwin Ndej",
    "gn:population":0,
    "gn:timezone":"Africa/Lubumbashi",
    "iso:country":"CD",
    "name:und_x_variant":[
        "Mwene-Ndeji"
    ],
    "wof:name":"Mwin Ndej",
    "wof:placetype":"locality"
},
  "geometry": {"coordinates":[23.25444,-8.5835],"type":"Point"}
}