{
  "type": "Feature",
  "properties": {
    "gn:admin1_code":"13.0",
    "gn:asciiname":"Benge",
    "gn:country_code":"CD",
    "gn:dem":415,
    "gn:feature_class":"P",
    "gn:feature_code":"PPL",
    "gn:name":"Benge",
    "gn:population":0,
    "gn:timezone":"Africa/Lubumbashi",
    "iso:country":"CD",
    "wof:name":"Benge",
    "wof:placetype":"locality"
},
  "geometry": {"coordinates":[24.12187,3.08605],"type":"Point"}
}