{
  "type": "Feature",
  "properties": {
    "gn:admin1_code":"22.0",
    "gn:asciiname":"Sangwite",
    "gn:country_code":"CD",
    "gn:dem":971,
    "gn:feature_class":"P",
    "gn:feature_code":"PPL",
    "gn:name":"Sangwite",
    "gn:population":0,
    "gn:timezone":"Africa/Lubumbashi",
    "iso:country":"CD",
    "wof:name":"Sangwite",
    "wof:placetype":"locality"
},
  "geometry": {"coordinates":[23.25389,-10.12434],"type":"Point"}
}