{
  "type": "Feature",
  "properties": {
    "gn:admin1_code":"24.0",
    "gn:asciiname":"Bosenge",
    "gn:country_code":"CD",
    "gn:dem":295,
    "gn:feature_class":"P",
    "gn:feature_code":"PPL",
    "gn:name":"Bosenge",
    "gn:population":0,
    "gn:timezone":"Africa/Kinshasa",
    "iso:country":"CD",
    "wof:name":"Bosenge",
    "wof:placetype":"locality"
},
  "geometry": {"coordinates":[18.23141,-2.45594],"type":"Point"}
}