{
  "type": "Feature",
  "properties": {
    "gn:admin1_code":"20.0",
    "gn:asciiname":"Muta",
    "gn:country_code":"CD",
    "gn:dem":749,
    "gn:feature_class":"P",
    "gn:feature_code":"PPL",
    "gn:name":"Muta",
    "gn:population":0,
    "gn:timezone":"Africa/Kinshasa",
    "iso:country":"CD",
    "name:ceb_x_preferred":[
        "Muta"
    ],
    "name:deu_x_preferred":[
        "Muta"
    ],
    "name:fra_x_preferred":[
        "Muta"
    ],
    "name:hye_x_preferred":[
        "\u0544\u0578\u0582\u057f\u0561"
    ],
    "name:ita_x_preferred":[
        "Muta"
    ],
    "name:rus_x_preferred":[
        "\u041c\u0443\u0442\u0430"
    ],
    "name:swe_x_preferred":[
        "Muta"
    ],
    "wof:name":"Muta",
    "wof:placetype":"locality"
},
  "geometry": {"coordinates":[19.64087,-5.69121],"type":"Point"}
}