{
  "type": "Feature",
  "properties": {
    "gn:admin1_code":"27.0",
    "gn:asciiname":"Soko",
    "gn:country_code":"CD",
    "gn:dem":453,
    "gn:feature_class":"P",
    "gn:feature_code":"PPL",
    "gn:name":"Soko",
    "gn:population":0,
    "gn:timezone":"Africa/Lubumbashi",
    "iso:country":"CD",
    "name:bos_x_preferred":[
        "Soko"
    ],
    "name:ceb_x_preferred":[
        "Soko"
    ],
    "name:fra_x_preferred":[
        "Soko"
    ],
    "name:heb_x_preferred":[
        "\u05e1\u05d5\u05e7\u05d5"
    ],
    "name:mlg_x_preferred":[
        "Soko"
    ],
    "name:nld_x_preferred":[
        "Soko"
    ],
    "name:pol_x_preferred":[
        "Soko"
    ],
    "name:spa_x_preferred":[
        "Soko"
    ],
    "name:swe_x_preferred":[
        "Soko"
    ],
    "wof:name":"Soko",
    "wof:placetype":"locality"
},
  "geometry": {"coordinates":[23.31667,-3.36667],"type":"Point"}
}