{
  "type": "Feature",
  "properties": {
    "gn:admin1_code":"12.0",
    "gn:asciiname":"Ruseko",
    "gn:country_code":"CD",
    "gn:dem":1117,
    "gn:feature_class":"P",
    "gn:feature_code":"PPL",
    "gn:name":"Ruseko",
    "gn:population":0,
    "gn:timezone":"Africa/Lubumbashi",
    "iso:country":"CD",
    "wof:name":"Ruseko",
    "wof:placetype":"locality"
},
  "geometry": {"coordinates":[29.08,-3.06139],"type":"Point"}
}