{
  "type": "Feature",
  "properties": {
    "gn:admin1_code":"16.0",
    "gn:asciiname":"Suru",
    "gn:country_code":"CD",
    "gn:dem":867,
    "gn:feature_class":"P",
    "gn:feature_code":"PPL",
    "gn:name":"Suru",
    "gn:population":0,
    "gn:timezone":"Africa/Lubumbashi",
    "iso:country":"CD",
    "name:ceb_x_preferred":[
        "Suru"
    ],
    "name:hye_x_preferred":[
        "\u054d\u0578\u0582\u057c\u0578\u0582"
    ],
    "name:ind_x_preferred":[
        "Suru"
    ],
    "name:nld_x_preferred":[
        "Suru"
    ],
    "name:rus_x_preferred":[
        "\u0421\u0443\u0440\u0443"
    ],
    "name:swe_x_preferred":[
        "Suru"
    ],
    "name:ukr_x_preferred":[
        "\u0421\u0443\u0440\u0443"
    ],
    "name:und_x_variant":[
        "Surra"
    ],
    "wof:name":"Suru",
    "wof:placetype":"locality"
},
  "geometry": {"coordinates":[30.1171,4.03538],"type":"Point"}
}