{
  "type": "Feature",
  "properties": {
    "gn:admin1_code":"20.0",
    "gn:asciiname":"Ntalamalita",
    "gn:country_code":"CD",
    "gn:dem":361,
    "gn:feature_class":"P",
    "gn:feature_code":"PPL",
    "gn:name":"Ntalamalita",
    "gn:population":0,
    "gn:timezone":"Africa/Kinshasa",
    "iso:country":"CD",
    "wof:name":"Ntalamalita",
    "wof:placetype":"locality"
},
  "geometry": {"coordinates":[18.20799,-3.80027],"type":"Point"}
}