{
  "type": "Feature",
  "properties": {
    "gn:admin1_code":"20.0",
    "gn:asciiname":"Dumbu",
    "gn:country_code":"CD",
    "gn:dem":462,
    "gn:feature_class":"P",
    "gn:feature_code":"PPL",
    "gn:name":"Dumbu",
    "gn:population":0,
    "gn:timezone":"Africa/Kinshasa",
    "iso:country":"CD",
    "name:und_x_variant":[
        "Bela Dumbu",
        "Belo-Dumbu"
    ],
    "wof:name":"Dumbu",
    "wof:placetype":"locality"
},
  "geometry": {"coordinates":[18.36912,-4.36051],"type":"Point"}
}