{
  "type": "Feature",
  "properties": {
    "gn:admin1_code":"30.0",
    "gn:asciiname":"Bongbalangbongo Premiere",
    "gn:country_code":"CD",
    "gn:dem":469,
    "gn:feature_class":"P",
    "gn:feature_code":"PPL",
    "gn:name":"Bongbalangbongo Premi\u00e8re",
    "gn:population":0,
    "gn:timezone":"Africa/Lubumbashi",
    "iso:country":"CD",
    "name:und_x_variant":[
        "Bongbalangbongo Premi\u00e8re",
        "Bongbalangbongo I"
    ],
    "wof:name":"Bongbalangbongo Premiere",
    "wof:placetype":"locality"
},
  "geometry": {"coordinates":[24.37604,1.55846],"type":"Point"}
}