{
  "type": "Feature",
  "properties": {
    "gn:admin1_code":"27.0",
    "gn:asciiname":"Pakima",
    "gn:country_code":"CD",
    "gn:dem":554,
    "gn:feature_class":"P",
    "gn:feature_code":"PPL",
    "gn:name":"Pakima",
    "gn:population":0,
    "gn:timezone":"Africa/Lubumbashi",
    "iso:country":"CD",
    "wof:name":"Pakima",
    "wof:placetype":"locality"
},
  "geometry": {"coordinates":[24.1996,-3.35376],"type":"Point"}
}