{
  "type": "Feature",
  "properties": {
    "gn:admin1_code":"26.0",
    "gn:asciiname":"Boyawambila",
    "gn:country_code":"CD",
    "gn:dem":455,
    "gn:feature_class":"P",
    "gn:feature_code":"PPL",
    "gn:name":"Boyawambila",
    "gn:population":0,
    "gn:timezone":"Africa/Kinshasa",
    "iso:country":"CD",
    "wof:name":"Boyawambila",
    "wof:placetype":"locality"
},
  "geometry": {"coordinates":[20.39199,3.46074],"type":"Point"}
}