{
  "type": "Feature",
  "properties": {
    "gn:admin1_code":"23.0",
    "gn:asciiname":"Kakunda",
    "gn:country_code":"CD",
    "gn:dem":785,
    "gn:feature_class":"P",
    "gn:feature_code":"PPL",
    "gn:name":"Kakunda",
    "gn:population":0,
    "gn:timezone":"Africa/Lubumbashi",
    "iso:country":"CD",
    "name:und_x_variant":[
        "Kakunde",
        "Kakunda"
    ],
    "wof:name":"Kakunda",
    "wof:placetype":"locality"
},
  "geometry": {"coordinates":[22.7879,-6.25107],"type":"Point"}
}