{
  "type": "Feature",
  "properties": {
    "gn:admin1_code":"27.0",
    "gn:asciiname":"Otaka",
    "gn:country_code":"CD",
    "gn:dem":420,
    "gn:feature_class":"P",
    "gn:feature_code":"PPL",
    "gn:name":"Otaka",
    "gn:population":0,
    "gn:timezone":"Africa/Lubumbashi",
    "iso:country":"CD",
    "wof:name":"Otaka",
    "wof:placetype":"locality"
},
  "geometry": {"coordinates":[23.24921,-4.72963],"type":"Point"}
}