{
  "type": "Feature",
  "properties": {
    "gn:admin1_code":"16.0",
    "gn:asciiname":"Mangbukele",
    "gn:country_code":"CD",
    "gn:dem":783,
    "gn:feature_class":"P",
    "gn:feature_code":"PPL",
    "gn:name":"Mangbukele",
    "gn:population":0,
    "gn:timezone":"Africa/Lubumbashi",
    "iso:country":"CD",
    "wof:name":"Mangbukele",
    "wof:placetype":"locality"
},
  "geometry": {"coordinates":[27.61076,2.27881],"type":"Point"}
}