{
  "type": "Feature",
  "properties": {
    "gn:admin1_code":"26.0",
    "gn:asciiname":"Modo",
    "gn:country_code":"CD",
    "gn:dem":402,
    "gn:feature_class":"P",
    "gn:feature_code":"PPL",
    "gn:name":"Modo",
    "gn:population":0,
    "gn:timezone":"Africa/Kinshasa",
    "iso:country":"CD",
    "name:ceb_x_preferred":[
        "Modo"
    ],
    "name:dan_x_preferred":[
        "Modo"
    ],
    "name:deu_x_preferred":[
        "Modo"
    ],
    "name:fra_x_preferred":[
        "Modo"
    ],
    "name:glg_x_preferred":[
        "Modo"
    ],
    "name:ita_x_preferred":[
        "Modo"
    ],
    "name:nld_x_preferred":[
        "Modo"
    ],
    "name:por_x_preferred":[
        "Modo"
    ],
    "name:rus_x_preferred":[
        "\u041c\u043e\u0434\u043e"
    ],
    "name:spa_x_preferred":[
        "Modo"
    ],
    "name:swe_x_preferred":[
        "Modo"
    ],
    "wof:name":"Modo",
    "wof:placetype":"locality"
},
  "geometry": {"coordinates":[22.18005,3.70388],"type":"Point"}
}