{
  "type": "Feature",
  "properties": {
    "gn:admin1_code":"25.0",
    "gn:asciiname":"Yandjeko",
    "gn:country_code":"CD",
    "gn:dem":394,
    "gn:feature_class":"P",
    "gn:feature_code":"PPL",
    "gn:name":"Yandjeko",
    "gn:population":0,
    "gn:timezone":"Africa/Kinshasa",
    "iso:country":"CD",
    "wof:name":"Yandjeko",
    "wof:placetype":"locality"
},
  "geometry": {"coordinates":[22.82981,2.39726],"type":"Point"}
}