{
  "type": "Feature",
  "properties": {
    "gn:admin1_code":"22.0",
    "gn:asciiname":"Tshibuyu",
    "gn:country_code":"CD",
    "gn:dem":918,
    "gn:feature_class":"P",
    "gn:feature_code":"PPL",
    "gn:name":"Tshibuyu",
    "gn:population":0,
    "gn:timezone":"Africa/Lubumbashi",
    "iso:country":"CD",
    "wof:name":"Tshibuyu",
    "wof:placetype":"locality"
},
  "geometry": {"coordinates":[23.06824,-9.83956],"type":"Point"}
}