{
  "type": "Feature",
  "properties": {
    "gn:admin1_code":"8.0",
    "gn:asciiname":"Lula-Nsele",
    "gn:country_code":"CD",
    "gn:dem":567,
    "gn:feature_class":"P",
    "gn:feature_code":"PPL",
    "gn:name":"Lula-Nsele",
    "gn:population":0,
    "gn:timezone":"Africa/Kinshasa",
    "iso:country":"CD",
    "name:und_x_variant":[
        "Lula",
        "Lulu",
        "Lula-Nsele"
    ],
    "wof:name":"Lula-Nsele",
    "wof:placetype":"locality"
},
  "geometry": {"coordinates":[15.53294,-5.3402],"type":"Point"}
}