{
  "type": "Feature",
  "properties": {
    "gn:admin1_code":"23.0",
    "gn:asciiname":"Tshimbalanga",
    "gn:country_code":"CD",
    "gn:dem":781,
    "gn:feature_class":"P",
    "gn:feature_code":"PPL",
    "gn:name":"Tshimbalanga",
    "gn:population":0,
    "gn:timezone":"Africa/Lubumbashi",
    "iso:country":"CD",
    "name:und_x_variant":[
        "Shimbalanga",
        "Tshimbalanga"
    ],
    "wof:name":"Tshimbalanga",
    "wof:placetype":"locality"
},
  "geometry": {"coordinates":[22.85338,-6.079],"type":"Point"}
}