{
  "type": "Feature",
  "properties": {
    "gn:admin1_code":"22.0",
    "gn:asciiname":"Masoji",
    "gn:country_code":"CD",
    "gn:dem":1171,
    "gn:feature_class":"P",
    "gn:feature_code":"PPL",
    "gn:name":"Masoji",
    "gn:population":0,
    "gn:timezone":"Africa/Lubumbashi",
    "iso:country":"CD",
    "wof:name":"Masoji",
    "wof:placetype":"locality"
},
  "geometry": {"coordinates":[24.02539,-10.45082],"type":"Point"}
}