{
  "type": "Feature",
  "properties": {
    "gn:admin1_code":"30.0",
    "gn:asciiname":"Bombo",
    "gn:country_code":"CD",
    "gn:dem":449,
    "gn:feature_class":"P",
    "gn:feature_code":"PPL",
    "gn:name":"Bombo",
    "gn:population":0,
    "gn:timezone":"Africa/Lubumbashi",
    "iso:country":"CD",
    "name:ceb_x_preferred":[
        "Bombo"
    ],
    "name:fra_x_preferred":[
        "Bombo"
    ],
    "name:ita_x_preferred":[
        "Bombo"
    ],
    "name:lug_x_preferred":[
        "Bombo"
    ],
    "name:nld_x_preferred":[
        "Bombo"
    ],
    "name:pol_x_preferred":[
        "Bombo"
    ],
    "name:spa_x_preferred":[
        "Bombo"
    ],
    "name:swe_x_preferred":[
        "Bombo"
    ],
    "wof:name":"Bombo",
    "wof:placetype":"locality"
},
  "geometry": {"coordinates":[25.39165,1.84169],"type":"Point"}
}