{
  "type": "Feature",
  "properties": {
    "gn:admin1_code":"30.0",
    "gn:asciiname":"Bombo",
    "gn:country_code":"CD",
    "gn:dem":449,
    "gn:feature_class":"P",
    "gn:feature_code":"PPL",
    "gn:name":"Bombo",
    "gn:population":0,
    "gn:timezone":"Africa/Lubumbashi",
    "iso:country":"CD",
    "wof:name":"Bombo",
    "wof:placetype":"locality"
},
  "geometry": {"coordinates":[25.39165,1.84169],"type":"Point"}
}