{
  "type": "Feature",
  "properties": {
    "gn:admin1_code":"28.0",
    "gn:asciiname":"Bwalu",
    "gn:country_code":"CD",
    "gn:dem":455,
    "gn:feature_class":"P",
    "gn:feature_code":"PPL",
    "gn:name":"Bwalu",
    "gn:population":0,
    "gn:timezone":"Africa/Kinshasa",
    "iso:country":"CD",
    "name:fra_x_preferred":[
        "Bwalu"
    ],
    "wof:name":"Bwalu",
    "wof:placetype":"locality"
},
  "geometry": {"coordinates":[19.08291,2.74582],"type":"Point"}
}