{
  "type": "Feature",
  "properties": {
    "gn:admin1_code":"16.0",
    "gn:asciiname":"Kagbara",
    "gn:country_code":"CD",
    "gn:dem":856,
    "gn:feature_class":"P",
    "gn:feature_code":"PPL",
    "gn:name":"Kagbara",
    "gn:population":0,
    "gn:timezone":"Africa/Lubumbashi",
    "iso:country":"CD",
    "wof:name":"Kagbara",
    "wof:placetype":"locality"
},
  "geometry": {"coordinates":[29.11828,2.8463],"type":"Point"}
}