{
  "type": "Feature",
  "properties": {
    "gn:admin1_code":"22.0",
    "gn:asciiname":"Tshitembo",
    "gn:country_code":"CD",
    "gn:dem":1024,
    "gn:feature_class":"P",
    "gn:feature_code":"PPL",
    "gn:name":"Tshitembo",
    "gn:population":0,
    "gn:timezone":"Africa/Lubumbashi",
    "iso:country":"CD",
    "wof:name":"Tshitembo",
    "wof:placetype":"locality"
},
  "geometry": {"coordinates":[22.28254,-10.08255],"type":"Point"}
}