{
  "type": "Feature",
  "properties": {
    "gn:admin1_code":"18.0",
    "gn:asciiname":"Kadima",
    "gn:country_code":"CD",
    "gn:dem":589,
    "gn:feature_class":"P",
    "gn:feature_code":"PPL",
    "gn:name":"Kadima",
    "gn:population":0,
    "gn:timezone":"Africa/Lubumbashi",
    "iso:country":"CD",
    "wof:name":"Kadima",
    "wof:placetype":"locality"
},
  "geometry": {"coordinates":[21.04918,-5.58549],"type":"Point"}
}