{
  "type": "Feature",
  "properties": {
    "gn:admin1_code":"23.0",
    "gn:asciiname":"Kawela",
    "gn:country_code":"CD",
    "gn:dem":820,
    "gn:feature_class":"P",
    "gn:feature_code":"PPL",
    "gn:name":"Kawela",
    "gn:population":0,
    "gn:timezone":"Africa/Lubumbashi",
    "iso:country":"CD",
    "wof:name":"Kawela",
    "wof:placetype":"locality"
},
  "geometry": {"coordinates":[22.13453,-6.80088],"type":"Point"}
}