{
  "type": "Feature",
  "properties": {
    "gn:admin1_code":"25.0",
    "gn:asciiname":"Yangombe Deuxieme",
    "gn:country_code":"CD",
    "gn:dem":386,
    "gn:feature_class":"P",
    "gn:feature_code":"PPL",
    "gn:name":"Yangombe Deuxi\u00e8me",
    "gn:population":0,
    "gn:timezone":"Africa/Kinshasa",
    "iso:country":"CD",
    "name:und_x_variant":[
        "Yangombe Deuxi\u00e8me",
        "Yangombe II"
    ],
    "wof:name":"Yangombe Deuxieme",
    "wof:placetype":"locality"
},
  "geometry": {"coordinates":[23.11193,2.14874],"type":"Point"}
}