{
  "type": "Feature",
  "properties": {
    "gn:admin1_code":"28.0",
    "gn:asciiname":"Bogbamili",
    "gn:country_code":"CD",
    "gn:dem":404,
    "gn:feature_class":"P",
    "gn:feature_code":"PPL",
    "gn:name":"Bogbamili",
    "gn:population":0,
    "gn:timezone":"Africa/Kinshasa",
    "iso:country":"CD",
    "wof:name":"Bogbamili",
    "wof:placetype":"locality"
},
  "geometry": {"coordinates":[20.06067,3.26658],"type":"Point"}
}