{
  "type": "Feature",
  "properties": {
    "gn:admin1_code":"14.0",
    "gn:asciiname":"Simama",
    "gn:country_code":"CD",
    "gn:dem":874,
    "gn:feature_class":"P",
    "gn:feature_code":"PPL",
    "gn:name":"Simama",
    "gn:population":0,
    "gn:timezone":"Africa/Lubumbashi",
    "iso:country":"CD",
    "wof:name":"Simama",
    "wof:placetype":"locality"
},
  "geometry": {"coordinates":[27.12144,-9.65609],"type":"Point"}
}