{
  "type": "Feature",
  "properties": {
    "gn:admin1_code":"15.0",
    "gn:asciiname":"Mwala",
    "gn:country_code":"CD",
    "gn:dem":723,
    "gn:feature_class":"P",
    "gn:feature_code":"PPL",
    "gn:name":"Mwala",
    "gn:population":0,
    "gn:timezone":"Africa/Lubumbashi",
    "iso:country":"CD",
    "wof:name":"Mwala",
    "wof:placetype":"locality"
},
  "geometry": {"coordinates":[25.83333,-8.01667],"type":"Point"}
}