{
  "type": "Feature",
  "properties": {
    "gn:admin1_code":"27.0",
    "gn:asciiname":"Lukfuke",
    "gn:country_code":"CD",
    "gn:dem":519,
    "gn:feature_class":"P",
    "gn:feature_code":"PPL",
    "gn:name":"Lukfuke",
    "gn:population":0,
    "gn:timezone":"Africa/Lubumbashi",
    "iso:country":"CD",
    "name:und_x_variant":[
        "Lukfuka",
        "Lukfuke"
    ],
    "wof:name":"Lukfuke",
    "wof:placetype":"locality"
},
  "geometry": {"coordinates":[23.88333,-3.55],"type":"Point"}
}