{
  "type": "Feature",
  "properties": {
    "gn:admin1_code":"27.0",
    "gn:asciiname":"Luhamba",
    "gn:country_code":"CD",
    "gn:dem":526,
    "gn:feature_class":"P",
    "gn:feature_code":"PPL",
    "gn:name":"Luhamba",
    "gn:population":0,
    "gn:timezone":"Africa/Lubumbashi",
    "iso:country":"CD",
    "wof:name":"Luhamba",
    "wof:placetype":"locality"
},
  "geometry": {"coordinates":[24.21667,-2.68333],"type":"Point"}
}