{
  "type": "Feature",
  "properties": {
    "gn:admin1_code":"10.0",
    "gn:asciiname":"Selemani",
    "gn:country_code":"CD",
    "gn:dem":819,
    "gn:feature_class":"P",
    "gn:feature_code":"PPL",
    "gn:name":"Selemani",
    "gn:population":0,
    "gn:timezone":"Africa/Lubumbashi",
    "iso:country":"CD",
    "wof:name":"Selemani",
    "wof:placetype":"locality"
},
  "geometry": {"coordinates":[28.26667,-4.88333],"type":"Point"}
}