{
  "type": "Feature",
  "properties": {
    "gn:admin1_code":"27.0",
    "gn:asciiname":"Vunga",
    "gn:country_code":"CD",
    "gn:dem":611,
    "gn:feature_class":"P",
    "gn:feature_code":"PPL",
    "gn:name":"Vunga",
    "gn:population":0,
    "gn:timezone":"Africa/Lubumbashi",
    "iso:country":"CD",
    "wof:name":"Vunga",
    "wof:placetype":"locality"
},
  "geometry": {"coordinates":[24.48471,-4.37757],"type":"Point"}
}