{
  "type": "Feature",
  "properties": {
    "gn:admin1_code":"19.0",
    "gn:asciiname":"Shamandefu",
    "gn:country_code":"CD",
    "gn:dem":938,
    "gn:feature_class":"P",
    "gn:feature_code":"PPL",
    "gn:name":"Shamandefu",
    "gn:population":0,
    "gn:timezone":"Africa/Kinshasa",
    "iso:country":"CD",
    "wof:name":"Shamandefu",
    "wof:placetype":"locality"
},
  "geometry": {"coordinates":[19.10114,-6.70188],"type":"Point"}
}