{
  "type": "Feature",
  "properties": {
    "gn:admin1_code":"27.0",
    "gn:asciiname":"Usumba",
    "gn:country_code":"CD",
    "gn:dem":623,
    "gn:feature_class":"P",
    "gn:feature_code":"PPL",
    "gn:name":"Usumba",
    "gn:population":0,
    "gn:timezone":"Africa/Lubumbashi",
    "iso:country":"CD",
    "wof:name":"Usumba",
    "wof:placetype":"locality"
},
  "geometry": {"coordinates":[24.29239,-3.18449],"type":"Point"}
}