{
  "type": "Feature",
  "properties": {
    "gn:admin1_code":"16.0",
    "gn:asciiname":"Butuka",
    "gn:country_code":"CD",
    "gn:dem":705,
    "gn:feature_class":"P",
    "gn:feature_code":"PPL",
    "gn:name":"Butuka",
    "gn:population":0,
    "gn:timezone":"Africa/Lubumbashi",
    "iso:country":"CD",
    "wof:name":"Butuka",
    "wof:placetype":"locality"
},
  "geometry": {"coordinates":[27.68022,1.58726],"type":"Point"}
}