{
  "type": "Feature",
  "properties": {
    "gn:admin1_code":"12.0",
    "gn:asciiname":"Rurambo",
    "gn:country_code":"CD",
    "gn:dem":2049,
    "gn:feature_class":"P",
    "gn:feature_code":"PPL",
    "gn:name":"Rurambo",
    "gn:population":0,
    "gn:timezone":"Africa/Lubumbashi",
    "iso:country":"CD",
    "wof:name":"Rurambo",
    "wof:placetype":"locality"
},
  "geometry": {"coordinates":[28.87917,-2.88333],"type":"Point"}
}