{
  "type": "Feature",
  "properties": {
    "gn:admin1_code":"12.0",
    "gn:asciiname":"Kamituga",
    "gn:country_code":"CD",
    "gn:dem":1037,
    "gn:feature_class":"P",
    "gn:feature_code":"PPL",
    "gn:name":"Kamituga",
    "gn:population":0,
    "gn:timezone":"Africa/Lubumbashi",
    "iso:country":"CD",
    "wof:name":"Kamituga",
    "wof:placetype":"locality"
},
  "geometry": {"coordinates":[28.17559,-3.06998],"type":"Point"}
}