{
  "type": "Feature",
  "properties": {
    "gn:admin1_code":"22.0",
    "gn:asciiname":"Samaseka",
    "gn:country_code":"CD",
    "gn:dem":1237,
    "gn:feature_class":"P",
    "gn:feature_code":"PPL",
    "gn:name":"Samaseka",
    "gn:population":0,
    "gn:timezone":"Africa/Lubumbashi",
    "iso:country":"CD",
    "wof:name":"Samaseka",
    "wof:placetype":"locality"
},
  "geometry": {"coordinates":[24.06313,-10.59593],"type":"Point"}
}