{
  "type": "Feature",
  "properties": {
    "gn:admin1_code":"23.0",
    "gn:asciiname":"Mwana Sanga",
    "gn:country_code":"CD",
    "gn:dem":960,
    "gn:feature_class":"P",
    "gn:feature_code":"PPL",
    "gn:name":"Mwana Sanga",
    "gn:population":0,
    "gn:timezone":"Africa/Lubumbashi",
    "iso:country":"CD",
    "wof:name":"Mwana Sanga",
    "wof:placetype":"locality"
},
  "geometry": {"coordinates":[23.11902000000001,-7.22072],"type":"Point"}
}