{
  "type": "Feature",
  "properties": {
    "gn:admin1_code":"18.0",
    "gn:asciiname":"Tshiyamba",
    "gn:country_code":"CD",
    "gn:dem":835,
    "gn:feature_class":"P",
    "gn:feature_code":"PPL",
    "gn:name":"Tshiyamba",
    "gn:population":0,
    "gn:timezone":"Africa/Lubumbashi",
    "iso:country":"CD",
    "wof:name":"Tshiyamba",
    "wof:placetype":"locality"
},
  "geometry": {"coordinates":[21.61908,-7.17083],"type":"Point"}
}