{
  "type": "Feature",
  "properties": {
    "gn:admin1_code":"15.0",
    "gn:asciiname":"Kangi",
    "gn:country_code":"CD",
    "gn:dem":1096,
    "gn:feature_class":"P",
    "gn:feature_code":"PPL",
    "gn:name":"Kangi",
    "gn:population":0,
    "gn:timezone":"Africa/Lubumbashi",
    "iso:country":"CD",
    "wof:name":"Kangi",
    "wof:placetype":"locality"
},
  "geometry": {"coordinates":[24.69177,-8.53108],"type":"Point"}
}