{
  "type": "Feature",
  "properties": {
    "gn:admin1_code":"21.0",
    "gn:asciiname":"Kafumbu",
    "gn:country_code":"CD",
    "gn:dem":692,
    "gn:feature_class":"P",
    "gn:feature_code":"PPL",
    "gn:name":"Kafumbu",
    "gn:population":0,
    "gn:timezone":"Africa/Lubumbashi",
    "iso:country":"CD",
    "wof:name":"Kafumbu",
    "wof:placetype":"locality"
},
  "geometry": {"coordinates":[23.7835,-6.72297],"type":"Point"}
}