{
  "type": "Feature",
  "properties": {
    "gn:admin1_code":"21.0",
    "gn:asciiname":"Kateo",
    "gn:country_code":"CD",
    "gn:dem":898,
    "gn:feature_class":"P",
    "gn:feature_code":"PPL",
    "gn:name":"Kateo",
    "gn:population":0,
    "gn:timezone":"Africa/Lubumbashi",
    "iso:country":"CD",
    "wof:name":"Kateo",
    "wof:placetype":"locality"
},
  "geometry": {"coordinates":[24.48919,-6.17893],"type":"Point"}
}