{
  "type": "Feature",
  "properties": {
    "gn:admin1_code":"22.0",
    "gn:asciiname":"Tshigende",
    "gn:country_code":"CD",
    "gn:dem":929,
    "gn:feature_class":"P",
    "gn:feature_code":"PPL",
    "gn:name":"Tshigende",
    "gn:population":0,
    "gn:timezone":"Africa/Lubumbashi",
    "iso:country":"CD",
    "wof:name":"Tshigende",
    "wof:placetype":"locality"
},
  "geometry": {"coordinates":[22.71635,-9.44865],"type":"Point"}
}