{
  "type": "Feature",
  "properties": {
    "gn:admin1_code":"23.0",
    "gn:asciiname":"Mutombo-Dibwe",
    "gn:country_code":"CD",
    "gn:dem":555,
    "gn:feature_class":"P",
    "gn:feature_code":"PPL",
    "gn:name":"Mutombo-Dibwe",
    "gn:population":0,
    "gn:timezone":"Africa/Lubumbashi",
    "iso:country":"CD",
    "wof:name":"Mutombo-Dibwe",
    "wof:placetype":"locality"
},
  "geometry": {"coordinates":[22.05689,-5.48697],"type":"Point"}
}