{
  "type": "Feature",
  "properties": {
    "gn:admin1_code":"23.0",
    "gn:asciiname":"Mwana-Kabogu",
    "gn:country_code":"CD",
    "gn:dem":778,
    "gn:feature_class":"P",
    "gn:feature_code":"PPL",
    "gn:name":"Mwana-Kabogu",
    "gn:population":0,
    "gn:timezone":"Africa/Lubumbashi",
    "iso:country":"CD",
    "wof:name":"Mwana-Kabogu",
    "wof:placetype":"locality"
},
  "geometry": {"coordinates":[22.34251,-6.49263],"type":"Point"}
}