{
  "type": "Feature",
  "properties": {
    "gn:admin1_code":"15.0",
    "gn:asciiname":"Mafungwe",
    "gn:country_code":"CD",
    "gn:dem":576,
    "gn:feature_class":"P",
    "gn:feature_code":"PPL",
    "gn:name":"Mafungwe",
    "gn:population":0,
    "gn:timezone":"Africa/Lubumbashi",
    "iso:country":"CD",
    "wof:name":"Mafungwe",
    "wof:placetype":"locality"
},
  "geometry": {"coordinates":[26.49471,-8.68639],"type":"Point"}
}