{
  "type": "Feature",
  "properties": {
    "gn:admin1_code":"8.0",
    "gn:asciiname":"Kanga-Kivunda",
    "gn:country_code":"CD",
    "gn:dem":637,
    "gn:feature_class":"P",
    "gn:feature_code":"PPL",
    "gn:name":"Kanga-Kivunda",
    "gn:population":0,
    "gn:timezone":"Africa/Kinshasa",
    "iso:country":"CD",
    "wof:name":"Kanga-Kivunda",
    "wof:placetype":"locality"
},
  "geometry": {"coordinates":[13.99325,-4.61102],"type":"Point"}
}