{
  "type": "Feature",
  "properties": {
    "gn:admin1_code":"16.0",
    "gn:asciiname":"Nabere",
    "gn:country_code":"CD",
    "gn:dem":742,
    "gn:feature_class":"P",
    "gn:feature_code":"PPL",
    "gn:name":"Nabere",
    "gn:population":0,
    "gn:timezone":"Africa/Lubumbashi",
    "iso:country":"CD",
    "wof:name":"Nabere",
    "wof:placetype":"locality"
},
  "geometry": {"coordinates":[27.99502,3.27834],"type":"Point"}
}