{
  "type": "Feature",
  "properties": {
    "gn:admin1_code":"13.0",
    "gn:asciiname":"Bababebole",
    "gn:country_code":"CD",
    "gn:dem":613,
    "gn:feature_class":"P",
    "gn:feature_code":"PPL",
    "gn:name":"Bababebole",
    "gn:population":0,
    "gn:timezone":"Africa/Lubumbashi",
    "iso:country":"CD",
    "wof:name":"Bababebole",
    "wof:placetype":"locality"
},
  "geometry": {"coordinates":[25.75893,3.39103],"type":"Point"}
}