{
  "type": "Feature",
  "properties": {
    "gn:admin1_code":"30.0",
    "gn:asciiname":"Yaboila",
    "gn:country_code":"CD",
    "gn:dem":417,
    "gn:feature_class":"P",
    "gn:feature_code":"PPL",
    "gn:name":"Yaboila",
    "gn:population":0,
    "gn:timezone":"Africa/Lubumbashi",
    "iso:country":"CD",
    "name:und_x_variant":[
        "Yabohila",
        "Yaboili",
        "Yaboila"
    ],
    "name:urd_x_preferred":[
        "\u06cc\u0628\u0648\u06cc\u0627\u0644\u0627"
    ],
    "wof:name":"Yaboila",
    "wof:placetype":"locality"
},
  "geometry": {"coordinates":[23.83749,0.62765],"type":"Point"}
}