{
  "type": "Feature",
  "properties": {
    "gn:admin1_code":"17.0",
    "gn:asciiname":"Sindani",
    "gn:country_code":"CD",
    "gn:dem":925,
    "gn:feature_class":"P",
    "gn:feature_code":"PPL",
    "gn:name":"Sindani",
    "gn:population":0,
    "gn:timezone":"Africa/Lubumbashi",
    "iso:country":"CD",
    "name:fra_x_preferred":[
        "Sindani"
    ],
    "wof:name":"Sindani",
    "wof:placetype":"locality"
},
  "geometry": {"coordinates":[29.83333,1.46667],"type":"Point"}
}