{
  "type": "Feature",
  "properties": {
    "gn:admin1_code":"24.0",
    "gn:asciiname":"Bobeke",
    "gn:country_code":"CD",
    "gn:dem":303,
    "gn:feature_class":"P",
    "gn:feature_code":"PPL",
    "gn:name":"Bobeke",
    "gn:population":0,
    "gn:timezone":"Africa/Kinshasa",
    "iso:country":"CD",
    "wof:name":"Bobeke",
    "wof:placetype":"locality"
},
  "geometry": {"coordinates":[17.74034,-2.33705],"type":"Point"}
}