{
  "type": "Feature",
  "properties": {
    "gn:admin1_code":"20.0",
    "gn:asciiname":"Kanzimba",
    "gn:country_code":"CD",
    "gn:dem":756,
    "gn:feature_class":"P",
    "gn:feature_code":"PPL",
    "gn:name":"Kanzimba",
    "gn:population":0,
    "gn:timezone":"Africa/Kinshasa",
    "iso:country":"CD",
    "wof:name":"Kanzimba",
    "wof:placetype":"locality"
},
  "geometry": {"coordinates":[19.02427,-5.57347],"type":"Point"}
}