{
  "type": "Feature",
  "properties": {
    "gn:admin1_code":"10.0",
    "gn:asciiname":"Kama",
    "gn:country_code":"CD",
    "gn:dem":676,
    "gn:feature_class":"P",
    "gn:feature_code":"PPL",
    "gn:name":"Kama",
    "gn:population":0,
    "gn:timezone":"Africa/Lubumbashi",
    "iso:country":"CD",
    "wof:name":"Kama",
    "wof:placetype":"locality"
},
  "geometry": {"coordinates":[27.52855,-4.04978],"type":"Point"}
}