{
  "type": "Feature",
  "properties": {
    "gn:admin1_code":"10.0",
    "gn:asciiname":"Kama",
    "gn:country_code":"CD",
    "gn:dem":676,
    "gn:feature_class":"P",
    "gn:feature_code":"PPL",
    "gn:name":"Kama",
    "gn:population":0,
    "gn:timezone":"Africa/Lubumbashi",
    "iso:country":"CD",
    "name:bih_x_preferred":[
        "\u0915\u093e\u092e"
    ],
    "name:bul_x_preferred":[
        "\u041a\u0430\u043c\u0430"
    ],
    "name:cat_x_preferred":[
        "Kama"
    ],
    "name:deu_x_preferred":[
        "Kama"
    ],
    "name:est_x_preferred":[
        "Kaama"
    ],
    "name:fra_x_preferred":[
        "Kama"
    ],
    "name:hin_x_preferred":[
        "\u0915\u093e\u092e"
    ],
    "name:hye_x_preferred":[
        "\u053f\u0561\u0574\u0561"
    ],
    "name:ind_x_preferred":[
        "Kama"
    ],
    "name:ita_x_preferred":[
        "Kamaloka"
    ],
    "name:jpn_x_preferred":[
        "\u30ab\u30fc\u30de"
    ],
    "name:kan_x_preferred":[
        "\u0c95\u0cbe\u0cae"
    ],
    "name:kat_x_preferred":[
        "\u10d9\u10d0\u10db\u10d0"
    ],
    "name:lit_x_preferred":[
        "Kama"
    ],
    "name:nld_x_preferred":[
        "Kama"
    ],
    "name:pol_x_preferred":[
        "Kama"
    ],
    "name:por_x_preferred":[
        "Kama"
    ],
    "name:rus_x_preferred":[
        "\u041a\u0430\u043c\u0430"
    ],
    "name:san_x_preferred":[
        "\u0915\u093e\u092e\u0903"
    ],
    "name:sin_x_preferred":[
        "\u0d9a\u0dcf\u0db8"
    ],
    "name:spa_x_preferred":[
        "K\u0101ma"
    ],
    "name:tam_x_preferred":[
        "\u0b95\u0bbe\u0bae\u0bae\u0bcd"
    ],
    "name:tha_x_preferred":[
        "\u0e01\u0e32\u0e21"
    ],
    "name:ukr_x_preferred":[
        "\u041a\u0430\u043c\u0430"
    ],
    "name:urd_x_preferred":[
        "\u06a9\u0627\u0645"
    ],
    "wof:name":"Kama",
    "wof:placetype":"locality"
},
  "geometry": {"coordinates":[27.52855,-4.04978],"type":"Point"}
}