{
  "type": "Feature",
  "properties": {
    "gn:admin1_code":"23.0",
    "gn:asciiname":"Tshinsele",
    "gn:country_code":"CD",
    "gn:dem":632,
    "gn:feature_class":"P",
    "gn:feature_code":"PPL",
    "gn:name":"Tshinsele",
    "gn:population":0,
    "gn:timezone":"Africa/Lubumbashi",
    "iso:country":"CD",
    "wof:name":"Tshinsele",
    "wof:placetype":"locality"
},
  "geometry": {"coordinates":[22.46917,-5.80306],"type":"Point"}
}