{
  "type": "Feature",
  "properties": {
    "gn:admin1_code":"17.0",
    "gn:asciiname":"Elumva",
    "gn:country_code":"CD",
    "gn:dem":1145,
    "gn:feature_class":"P",
    "gn:feature_code":"PPL",
    "gn:name":"Elumva",
    "gn:population":0,
    "gn:timezone":"Africa/Lubumbashi",
    "iso:country":"CD",
    "wof:name":"Elumva",
    "wof:placetype":"locality"
},
  "geometry": {"coordinates":[30.53398,3.21131],"type":"Point"}
}