{
  "type": "Feature",
  "properties": {
    "gn:admin1_code":"12.0",
    "gn:asciiname":"Katonda",
    "gn:country_code":"CD",
    "gn:dem":1467,
    "gn:feature_class":"P",
    "gn:feature_code":"PPL",
    "gn:name":"Katonda",
    "gn:population":0,
    "gn:timezone":"Africa/Lubumbashi",
    "iso:country":"CD",
    "wof:name":"Katonda",
    "wof:placetype":"locality"
},
  "geometry": {"coordinates":[29.05167,-1.99806],"type":"Point"}
}