{
  "type": "Feature",
  "properties": {
    "gn:admin1_code":"10.0",
    "gn:asciiname":"Kamilanga",
    "gn:country_code":"CD",
    "gn:dem":718,
    "gn:feature_class":"P",
    "gn:feature_code":"PPL",
    "gn:name":"Kamilanga",
    "gn:population":0,
    "gn:timezone":"Africa/Lubumbashi",
    "iso:country":"CD",
    "wof:name":"Kamilanga",
    "wof:placetype":"locality"
},
  "geometry": {"coordinates":[26.72836,-3.55575],"type":"Point"}
}