{
  "type": "Feature",
  "properties": {
    "gn:admin1_code":"12.0",
    "gn:asciiname":"Kishombo",
    "gn:country_code":"CD",
    "gn:dem":2540,
    "gn:feature_class":"P",
    "gn:feature_code":"PPL",
    "gn:name":"Kishombo",
    "gn:population":0,
    "gn:timezone":"Africa/Lubumbashi",
    "iso:country":"CD",
    "wof:name":"Kishombo",
    "wof:placetype":"locality"
},
  "geometry": {"coordinates":[28.78083,-3.25333],"type":"Point"}
}