{
  "type": "Feature",
  "properties": {
    "gn:admin1_code":"17.0",
    "gn:asciiname":"Opoku",
    "gn:country_code":"CD",
    "gn:dem":821,
    "gn:feature_class":"P",
    "gn:feature_code":"PPL",
    "gn:name":"Opoku",
    "gn:population":0,
    "gn:timezone":"Africa/Lubumbashi",
    "iso:country":"CD",
    "name:fra_x_preferred":[
        "Opoku"
    ],
    "wof:name":"Opoku",
    "wof:placetype":"locality"
},
  "geometry": {"coordinates":[28.99069,1.83559],"type":"Point"}
}