{
  "type": "Feature",
  "properties": {
    "gn:admin1_code":"8.0",
    "gn:asciiname":"Kombe",
    "gn:country_code":"CD",
    "gn:dem":463,
    "gn:feature_class":"P",
    "gn:feature_code":"PPL",
    "gn:name":"Kombe",
    "gn:population":0,
    "gn:timezone":"Africa/Kinshasa",
    "iso:country":"CD",
    "name:ceb_x_preferred":[
        "Kombe"
    ],
    "name:deu_x_preferred":[
        "Kombe"
    ],
    "name:swe_x_preferred":[
        "Kombe"
    ],
    "name:und_x_variant":[
        "Kiombe",
        "Kombe"
    ],
    "wof:name":"Kombe",
    "wof:placetype":"locality"
},
  "geometry": {"coordinates":[13.72847,-5.14338],"type":"Point"}
}