{
  "type": "Feature",
  "properties": {
    "gn:admin1_code":"8.0",
    "gn:asciiname":"Diadia",
    "gn:country_code":"CD",
    "gn:dem":472,
    "gn:feature_class":"P",
    "gn:feature_code":"PPL",
    "gn:name":"Diadia",
    "gn:population":0,
    "gn:timezone":"Africa/Kinshasa",
    "iso:country":"CD",
    "wof:name":"Diadia",
    "wof:placetype":"locality"
},
  "geometry": {"coordinates":[13.76377,-5.14701],"type":"Point"}
}