{
  "type": "Feature",
  "properties": {
    "gn:admin1_code":"20.0",
    "gn:asciiname":"Muzao",
    "gn:country_code":"CD",
    "gn:dem":794,
    "gn:feature_class":"P",
    "gn:feature_code":"PPL",
    "gn:name":"Muzao",
    "gn:population":0,
    "gn:timezone":"Africa/Kinshasa",
    "iso:country":"CD",
    "wof:name":"Muzao",
    "wof:placetype":"locality"
},
  "geometry": {"coordinates":[18.77152,-5.8193],"type":"Point"}
}