{
  "type": "Feature",
  "properties": {
    "gn:admin1_code":"20.0",
    "gn:asciiname":"Monana Deuxieme",
    "gn:country_code":"CD",
    "gn:dem":394,
    "gn:feature_class":"P",
    "gn:feature_code":"PPL",
    "gn:name":"Monana Deuxi\u00e8me",
    "gn:population":0,
    "gn:timezone":"Africa/Kinshasa",
    "iso:country":"CD",
    "name:und_x_variant":[
        "Monana Deuxi\u00e8me",
        "Monana II"
    ],
    "wof:name":"Monana Deuxieme",
    "wof:placetype":"locality"
},
  "geometry": {"coordinates":[17.7899,-3.93614],"type":"Point"}
}