{
  "type": "Feature",
  "properties": {
    "gn:admin1_code":"29.0",
    "gn:asciiname":"Kiabo",
    "gn:country_code":"CD",
    "gn:dem":686,
    "gn:feature_class":"P",
    "gn:feature_code":"PPL",
    "gn:name":"Kiabo",
    "gn:population":0,
    "gn:timezone":"Africa/Lubumbashi",
    "iso:country":"CD",
    "wof:name":"Kiabo",
    "wof:placetype":"locality"
},
  "geometry": {"coordinates":[27.52839,-6.15166],"type":"Point"}
}