{
  "type": "Feature",
  "properties": {
    "gn:admin1_code":"23.0",
    "gn:asciiname":"Tshilumbaye",
    "gn:country_code":"CD",
    "gn:dem":755,
    "gn:feature_class":"P",
    "gn:feature_code":"PPL",
    "gn:name":"Tshilumbaye",
    "gn:population":0,
    "gn:timezone":"Africa/Lubumbashi",
    "iso:country":"CD",
    "wof:name":"Tshilumbaye",
    "wof:placetype":"locality"
},
  "geometry": {"coordinates":[22.54887,-6.31165],"type":"Point"}
}