{
  "type": "Feature",
  "properties": {
    "gn:admin1_code":"6.0",
    "gn:asciiname":"Matadi-Kibala",
    "gn:country_code":"CD",
    "gn:dem":413,
    "gn:feature_class":"P",
    "gn:feature_code":"PPL",
    "gn:name":"Matadi-Kibala",
    "gn:population":0,
    "gn:timezone":"Africa/Kinshasa",
    "iso:country":"CD",
    "wof:name":"Matadi-Kibala",
    "wof:placetype":"locality"
},
  "geometry": {"coordinates":[15.24444,-4.44472],"type":"Point"}
}