{
  "type": "Feature",
  "properties": {
    "gn:admin1_code":"23.0",
    "gn:asciiname":"Ndaie-Kasansu",
    "gn:country_code":"CD",
    "gn:dem":760,
    "gn:feature_class":"P",
    "gn:feature_code":"PPL",
    "gn:name":"Ndaie-Kasansu",
    "gn:population":0,
    "gn:timezone":"Africa/Lubumbashi",
    "iso:country":"CD",
    "wof:name":"Ndaie-Kasansu",
    "wof:placetype":"locality"
},
  "geometry": {"coordinates":[22.69562,-6.05795],"type":"Point"}
}