{
  "type": "Feature",
  "properties": {
    "gn:admin1_code":"21.0",
    "gn:asciiname":"Kipinda",
    "gn:country_code":"CD",
    "gn:dem":683,
    "gn:feature_class":"P",
    "gn:feature_code":"PPL",
    "gn:name":"Kipinda",
    "gn:population":0,
    "gn:timezone":"Africa/Lubumbashi",
    "iso:country":"CD",
    "wof:name":"Kipinda",
    "wof:placetype":"locality"
},
  "geometry": {"coordinates":[25.65,-5.78333],"type":"Point"}
}