{
  "type": "Feature",
  "properties": {
    "gn:admin1_code":"4.0",
    "gn:asciiname":"Dala",
    "gn:country_code":"CD",
    "gn:dem":633,
    "gn:feature_class":"P",
    "gn:feature_code":"PPL",
    "gn:name":"Dala",
    "gn:population":0,
    "gn:timezone":"Africa/Lubumbashi",
    "iso:country":"CD",
    "name:ceb_x_preferred":[
        "Dala"
    ],
    "name:deu_x_preferred":[
        "Dala"
    ],
    "name:fin_x_preferred":[
        "Dala"
    ],
    "name:fra_x_preferred":[
        "Dala"
    ],
    "name:ita_x_preferred":[
        "Dala"
    ],
    "name:nld_x_preferred":[
        "Dala"
    ],
    "name:swe_x_preferred":[
        "Dala"
    ],
    "wof:name":"Dala",
    "wof:placetype":"locality"
},
  "geometry": {"coordinates":[23.77429,-6.32016],"type":"Point"}
}