{
  "type": "Feature",
  "properties": {
    "gn:admin1_code":"10.0",
    "gn:asciiname":"Madjakala",
    "gn:country_code":"CD",
    "gn:dem":568,
    "gn:feature_class":"P",
    "gn:feature_code":"PPL",
    "gn:name":"Madjakala",
    "gn:population":0,
    "gn:timezone":"Africa/Lubumbashi",
    "iso:country":"CD",
    "wof:name":"Madjakala",
    "wof:placetype":"locality"
},
  "geometry": {"coordinates":[26.85074,-2.50448],"type":"Point"}
}