{
  "type": "Feature",
  "properties": {
    "gn:admin1_code":"2.0",
    "gn:asciiname":"Efondjolo",
    "gn:country_code":"CD",
    "gn:dem":339,
    "gn:feature_class":"P",
    "gn:feature_code":"PPL",
    "gn:name":"Efondjolo",
    "gn:population":0,
    "gn:timezone":"Africa/Kinshasa",
    "iso:country":"CD",
    "wof:name":"Efondjolo",
    "wof:placetype":"locality"
},
  "geometry": {"coordinates":[20.08333,0.36667],"type":"Point"}
}