{
  "type": "Feature",
  "properties": {
    "gn:admin1_code":"22.0",
    "gn:asciiname":"Mwanamadji",
    "gn:country_code":"CD",
    "gn:dem":1120,
    "gn:feature_class":"P",
    "gn:feature_code":"PPL",
    "gn:name":"Mwanamadji",
    "gn:population":0,
    "gn:timezone":"Africa/Lubumbashi",
    "iso:country":"CD",
    "wof:name":"Mwanamadji",
    "wof:placetype":"locality"
},
  "geometry": {"coordinates":[24.99846,-10.34823],"type":"Point"}
}