{
  "type": "Feature",
  "properties": {
    "gn:admin1_code":"15.0",
    "gn:asciiname":"Mwa-Muyombo",
    "gn:country_code":"CD",
    "gn:dem":1069,
    "gn:feature_class":"P",
    "gn:feature_code":"PPL",
    "gn:name":"Mwa-Muyombo",
    "gn:population":0,
    "gn:timezone":"Africa/Lubumbashi",
    "iso:country":"CD",
    "wof:name":"Mwa-Muyombo",
    "wof:placetype":"locality"
},
  "geometry": {"coordinates":[23.80888,-8.03232],"type":"Point"}
}