{
  "type": "Feature",
  "properties": {
    "gn:admin1_code":"27.0",
    "gn:asciiname":"Kingete",
    "gn:country_code":"CD",
    "gn:dem":499,
    "gn:feature_class":"P",
    "gn:feature_code":"PPL",
    "gn:name":"Kingete",
    "gn:population":0,
    "gn:timezone":"Africa/Lubumbashi",
    "iso:country":"CD",
    "wof:name":"Kingete",
    "wof:placetype":"locality"
},
  "geometry": {"coordinates":[23.16667,-3.38333],"type":"Point"}
}