{
  "type": "Feature",
  "properties": {
    "gn:admin1_code":"12.0",
    "gn:asciiname":"Kabara",
    "gn:country_code":"CD",
    "gn:dem":2130,
    "gn:feature_class":"P",
    "gn:feature_code":"PPL",
    "gn:name":"Kabara",
    "gn:population":0,
    "gn:timezone":"Africa/Lubumbashi",
    "iso:country":"CD",
    "wof:name":"Kabara",
    "wof:placetype":"locality"
},
  "geometry": {"coordinates":[28.72917,-3.64306],"type":"Point"}
}