{
  "type": "Feature",
  "properties": {
    "gn:admin1_code":"20.0",
    "gn:asciiname":"Bunga",
    "gn:country_code":"CD",
    "gn:dem":525,
    "gn:feature_class":"P",
    "gn:feature_code":"PPL",
    "gn:name":"Bunga",
    "gn:population":0,
    "gn:timezone":"Africa/Kinshasa",
    "iso:country":"CD",
    "name:ceb_x_preferred":[
        "Bunga"
    ],
    "name:ind_x_preferred":[
        "Bunga"
    ],
    "name:swe_x_preferred":[
        "Bunga"
    ],
    "name:tgl_x_preferred":[
        "Bunga"
    ],
    "wof:name":"Bunga",
    "wof:placetype":"locality"
},
  "geometry": {"coordinates":[18.96648,-5.35461],"type":"Point"}
}