{
  "type": "Feature",
  "properties": {
    "gn:admin1_code":"15.0",
    "gn:asciiname":"Kabula",
    "gn:country_code":"CD",
    "gn:dem":583,
    "gn:feature_class":"P",
    "gn:feature_code":"PPL",
    "gn:name":"Kabula",
    "gn:population":0,
    "gn:timezone":"Africa/Lubumbashi",
    "iso:country":"CD",
    "name:swa_x_preferred":[
        "Kabula"
    ],
    "wof:name":"Kabula",
    "wof:placetype":"locality"
},
  "geometry": {"coordinates":[25.96036,-8.83913],"type":"Point"}
}