{
  "type": "Feature",
  "properties": {
    "gn:admin1_code":"8.0",
    "gn:asciiname":"Kintoto",
    "gn:country_code":"CD",
    "gn:dem":647,
    "gn:feature_class":"P",
    "gn:feature_code":"PPL",
    "gn:name":"Kintoto",
    "gn:population":0,
    "gn:timezone":"Africa/Kinshasa",
    "iso:country":"CD",
    "wof:name":"Kintoto",
    "wof:placetype":"locality"
},
  "geometry": {"coordinates":[15.05086,-5.86665],"type":"Point"}
}