{
  "type": "Feature",
  "properties": {
    "gn:admin1_code":"22.0",
    "gn:asciiname":"Sakapele",
    "gn:country_code":"CD",
    "gn:dem":989,
    "gn:feature_class":"P",
    "gn:feature_code":"PPL",
    "gn:name":"Sakapele",
    "gn:population":0,
    "gn:timezone":"Africa/Lubumbashi",
    "iso:country":"CD",
    "wof:name":"Sakapele",
    "wof:placetype":"locality"
},
  "geometry": {"coordinates":[22.89008,-9.93636],"type":"Point"}
}