{
  "type": "Feature",
  "properties": {
    "gn:admin1_code":"21.0",
    "gn:asciiname":"Bena-Nyambala",
    "gn:country_code":"CD",
    "gn:dem":693,
    "gn:feature_class":"P",
    "gn:feature_code":"PPL",
    "gn:name":"Bena-Nyambala",
    "gn:population":0,
    "gn:timezone":"Africa/Lubumbashi",
    "iso:country":"CD",
    "wof:name":"Bena-Nyambala",
    "wof:placetype":"locality"
},
  "geometry": {"coordinates":[23.76546,-6.76031],"type":"Point"}
}