{
  "type": "Feature",
  "properties": {
    "gn:admin1_code":"16.0",
    "gn:asciiname":"Matubi",
    "gn:country_code":"CD",
    "gn:dem":1079,
    "gn:feature_class":"P",
    "gn:feature_code":"PPL",
    "gn:name":"Matubi",
    "gn:population":0,
    "gn:timezone":"Africa/Lubumbashi",
    "iso:country":"CD",
    "wof:name":"Matubi",
    "wof:placetype":"locality"
},
  "geometry": {"coordinates":[30.11504,2.76692],"type":"Point"}
}