{
  "type": "Feature",
  "properties": {
    "gn:admin1_code":"8.0",
    "gn:asciiname":"Kizuao",
    "gn:country_code":"CD",
    "gn:dem":498,
    "gn:feature_class":"P",
    "gn:feature_code":"PPL",
    "gn:name":"Kizuao",
    "gn:population":0,
    "gn:timezone":"Africa/Kinshasa",
    "iso:country":"CD",
    "wof:name":"Kizuao",
    "wof:placetype":"locality"
},
  "geometry": {"coordinates":[15.50851,-4.73495],"type":"Point"}
}