{
  "type": "Feature",
  "properties": {
    "gn:admin1_code":"23.0",
    "gn:asciiname":"Mwene Bala",
    "gn:country_code":"CD",
    "gn:dem":959,
    "gn:feature_class":"P",
    "gn:feature_code":"PPL",
    "gn:name":"Mwene Bala",
    "gn:population":0,
    "gn:timezone":"Africa/Lubumbashi",
    "iso:country":"CD",
    "wof:name":"Mwene Bala",
    "wof:placetype":"locality"
},
  "geometry": {"coordinates":[22.93183,-7.39382],"type":"Point"}
}