{
  "type": "Feature",
  "properties": {
    "gn:admin1_code":"31.0",
    "gn:asciiname":"Yolongo",
    "gn:country_code":"CD",
    "gn:dem":379,
    "gn:feature_class":"P",
    "gn:feature_code":"PPL",
    "gn:name":"Yolongo",
    "gn:population":0,
    "gn:timezone":"Africa/Kinshasa",
    "iso:country":"CD",
    "wof:name":"Yolongo",
    "wof:placetype":"locality"
},
  "geometry": {"coordinates":[20.90773,-0.7735],"type":"Point"}
}