{
  "type": "Feature",
  "properties": {
    "gn:admin1_code":"29.0",
    "gn:asciiname":"Piana-Nkulu",
    "gn:country_code":"CD",
    "gn:dem":660,
    "gn:feature_class":"P",
    "gn:feature_code":"PPL",
    "gn:name":"Piana-Nkulu",
    "gn:population":0,
    "gn:timezone":"Africa/Lubumbashi",
    "iso:country":"CD",
    "wof:name":"Piana-Nkulu",
    "wof:placetype":"locality"
},
  "geometry": {"coordinates":[26.73764000000001,-5.03966],"type":"Point"}
}