{
  "type": "Feature",
  "properties": {
    "gn:admin1_code":"22.0",
    "gn:asciiname":"Muhembei",
    "gn:country_code":"CD",
    "gn:dem":1104,
    "gn:feature_class":"P",
    "gn:feature_code":"PPL",
    "gn:name":"Muhembei",
    "gn:population":0,
    "gn:timezone":"Africa/Lubumbashi",
    "iso:country":"CD",
    "name:und_x_variant":[
        "Muhembe"
    ],
    "wof:name":"Muhembei",
    "wof:placetype":"locality"
},
  "geometry": {"coordinates":[23.56462,-10.65176],"type":"Point"}
}