{
  "type": "Feature",
  "properties": {
    "gn:admin1_code":"27.0",
    "gn:asciiname":"Sulu",
    "gn:country_code":"CD",
    "gn:dem":645,
    "gn:feature_class":"P",
    "gn:feature_code":"PPL",
    "gn:name":"Sulu",
    "gn:population":0,
    "gn:timezone":"Africa/Lubumbashi",
    "iso:country":"CD",
    "name:ace_x_preferred":[
        "Propinsi Sulu"
    ],
    "name:ara_x_preferred":[
        "\u0633\u0648\u0644\u0648"
    ],
    "name:azb_x_preferred":[
        "\u0633\u0648\u0644\u0648"
    ],
    "name:bcl_x_preferred":[
        "Sulu"
    ],
    "name:ceb_x_preferred":[
        "Sulu"
    ],
    "name:deu_x_preferred":[
        "Provinz Sulu"
    ],
    "name:epo_x_preferred":[
        "Suluo"
    ],
    "name:fas_x_preferred":[
        "\u0633\u0648\u0644\u0648"
    ],
    "name:fin_x_preferred":[
        "Sulu"
    ],
    "name:fra_x_preferred":[
        "Sulu"
    ],
    "name:hin_x_preferred":[
        "\u0938\u0941\u0932\u0941 \u092a\u094d\u0930\u093e\u0928\u094d\u0924"
    ],
    "name:ilo_x_preferred":[
        "Sulu"
    ],
    "name:ind_x_preferred":[
        "Sulu"
    ],
    "name:jpn_x_preferred":[
        "\u30b9\u30fc\u30eb\u30fc\u5dde"
    ],
    "name:kor_x_preferred":[
        "\uc220\ub8e8\uc8fc"
    ],
    "name:lat_x_preferred":[
        "Sulu"
    ],
    "name:mkd_x_preferred":[
        "\u0421\u0443\u043b\u0443"
    ],
    "name:msa_x_preferred":[
        "Sulu"
    ],
    "name:nld_x_preferred":[
        "Sulu"
    ],
    "name:nor_x_preferred":[
        "Sulu"
    ],
    "name:pag_x_preferred":[
        "Sulu"
    ],
    "name:pam_x_preferred":[
        "Sulu"
    ],
    "name:rus_x_preferred":[
        "\u0421\u0443\u043b\u0443"
    ],
    "name:sco_x_preferred":[
        "Sulu"
    ],
    "name:swe_x_preferred":[
        "Sulu"
    ],
    "name:tgl_x_preferred":[
        "Sulu"
    ],
    "name:tha_x_preferred":[
        "\u0e08\u0e31\u0e07\u0e2b\u0e27\u0e31\u0e14\u0e0b\u0e39\u0e25\u0e39"
    ],
    "name:tur_x_preferred":[
        "Sulu"
    ],
    "name:ukr_x_preferred":[
        "\u0421\u0443\u043b\u0443"
    ],
    "name:urd_x_preferred":[
        "\u0633\u0648\u0644\u0648"
    ],
    "name:vie_x_preferred":[
        "Sulu"
    ],
    "name:war_x_preferred":[
        "Sulu"
    ],
    "name:wuu_x_preferred":[
        "\u82cf\u7984\u7701"
    ],
    "name:zho_x_preferred":[
        "\u8607\u797f\u7701"
    ],
    "wof:name":"Sulu",
    "wof:placetype":"locality"
},
  "geometry": {"coordinates":[24.10493,-4.7969],"type":"Point"}
}