{
  "type": "Feature",
  "properties": {
    "gn:admin1_code":"27.0",
    "gn:asciiname":"Sulu",
    "gn:country_code":"CD",
    "gn:dem":645,
    "gn:feature_class":"P",
    "gn:feature_code":"PPL",
    "gn:name":"Sulu",
    "gn:population":0,
    "gn:timezone":"Africa/Lubumbashi",
    "iso:country":"CD",
    "wof:name":"Sulu",
    "wof:placetype":"locality"
},
  "geometry": {"coordinates":[24.10493,-4.7969],"type":"Point"}
}