{
  "type": "Feature",
  "properties": {
    "gn:admin1_code":"27.0",
    "gn:asciiname":"Omehele",
    "gn:country_code":"CD",
    "gn:dem":491,
    "gn:feature_class":"P",
    "gn:feature_code":"PPL",
    "gn:name":"Omehele",
    "gn:population":0,
    "gn:timezone":"Africa/Lubumbashi",
    "iso:country":"CD",
    "name:und_x_variant":[
        "Omehale",
        "Omehele"
    ],
    "wof:name":"Omehele",
    "wof:placetype":"locality"
},
  "geometry": {"coordinates":[23.78333,-3.45],"type":"Point"}
}