{
  "type": "Feature",
  "properties": {
    "gn:admin1_code":"2.0",
    "gn:asciiname":"Likoli",
    "gn:country_code":"CD",
    "gn:dem":330,
    "gn:feature_class":"P",
    "gn:feature_code":"PPL",
    "gn:name":"Likoli",
    "gn:population":0,
    "gn:timezone":"Africa/Kinshasa",
    "iso:country":"CD",
    "wof:name":"Likoli",
    "wof:placetype":"locality"
},
  "geometry": {"coordinates":[19.05,-0.45],"type":"Point"}
}