{
  "type": "Feature",
  "properties": {
    "gn:admin1_code":"30.0",
    "gn:asciiname":"Bafwabuko",
    "gn:country_code":"CD",
    "gn:dem":563,
    "gn:feature_class":"P",
    "gn:feature_code":"PPL",
    "gn:name":"Bafwabuko",
    "gn:population":0,
    "gn:timezone":"Africa/Lubumbashi",
    "iso:country":"CD",
    "wof:name":"Bafwabuko",
    "wof:placetype":"locality"
},
  "geometry": {"coordinates":[27.30539000000001,1.79435],"type":"Point"}
}