{
  "type": "Feature",
  "properties": {
    "gn:admin1_code":"19.0",
    "gn:asciiname":"Ipabo",
    "gn:country_code":"CD",
    "gn:dem":715,
    "gn:feature_class":"P",
    "gn:feature_code":"PPL",
    "gn:name":"Ipabo",
    "gn:population":0,
    "gn:timezone":"Africa/Kinshasa",
    "iso:country":"CD",
    "wof:name":"Ipabo",
    "wof:placetype":"locality"
},
  "geometry": {"coordinates":[17.07201,-5.48654],"type":"Point"}
}