{
  "type": "Feature",
  "properties": {
    "gn:admin1_code":"20.0",
    "gn:asciiname":"Sande",
    "gn:country_code":"CD",
    "gn:dem":817,
    "gn:feature_class":"P",
    "gn:feature_code":"PPL",
    "gn:name":"Sande",
    "gn:population":0,
    "gn:timezone":"Africa/Kinshasa",
    "iso:country":"CD",
    "wof:name":"Sande",
    "wof:placetype":"locality"
},
  "geometry": {"coordinates":[18.73195,-5.81114],"type":"Point"}
}