{
  "type": "Feature",
  "properties": {
    "gn:admin1_code":"19.0",
    "gn:asciiname":"Kinzofu",
    "gn:country_code":"CD",
    "gn:dem":435,
    "gn:feature_class":"P",
    "gn:feature_code":"PPL",
    "gn:name":"Kinzofu",
    "gn:population":0,
    "gn:timezone":"Africa/Luanda",
    "iso:country":"CD",
    "wof:name":"Kinzofu",
    "wof:placetype":"locality"
},
  "geometry": {"coordinates":[16.80885,-6.77118],"type":"Point"}
}