{
  "type": "Feature",
  "properties": {
    "gn:admin1_code":"19.0",
    "gn:asciiname":"Mutshita",
    "gn:country_code":"CD",
    "gn:dem":874,
    "gn:feature_class":"P",
    "gn:feature_code":"PPL",
    "gn:name":"Mutshita",
    "gn:population":0,
    "gn:timezone":"Africa/Kinshasa",
    "iso:country":"CD",
    "wof:name":"Mutshita",
    "wof:placetype":"locality"
},
  "geometry": {"coordinates":[18.35689,-7.93035],"type":"Point"}
}