{
  "type": "Feature",
  "properties": {
    "gn:admin1_code":"16.0",
    "gn:asciiname":"Gilia",
    "gn:country_code":"CD",
    "gn:dem":741,
    "gn:feature_class":"P",
    "gn:feature_code":"PPL",
    "gn:name":"Gilia",
    "gn:population":0,
    "gn:timezone":"Africa/Lubumbashi",
    "iso:country":"CD",
    "name:cat_x_preferred":[
        "Gilia"
    ],
    "name:fin_x_preferred":[
        "Kiurunkukat"
    ],
    "name:fra_x_preferred":[
        "Gilia"
    ],
    "name:nav_x_preferred":[
        "Z\u00e9\u00e9\u02bchaaleeh"
    ],
    "name:pol_x_preferred":[
        "Gilia"
    ],
    "name:por_x_preferred":[
        "Gilia"
    ],
    "name:spa_x_preferred":[
        "Gilia"
    ],
    "name:vie_x_preferred":[
        "Gilia"
    ],
    "wof:name":"Gilia",
    "wof:placetype":"locality"
},
  "geometry": {"coordinates":[27.66932000000001,4.80863],"type":"Point"}
}