{
  "type": "Feature",
  "properties": {
    "gn:admin1_code":"18.0",
    "gn:asciiname":"Kapinga-Muana",
    "gn:country_code":"CD",
    "gn:dem":591,
    "gn:feature_class":"P",
    "gn:feature_code":"PPL",
    "gn:name":"Kapinga-Muana",
    "gn:population":0,
    "gn:timezone":"Africa/Lubumbashi",
    "iso:country":"CD",
    "wof:name":"Kapinga-Muana",
    "wof:placetype":"locality"
},
  "geometry": {"coordinates":[21.35449,-5.4517],"type":"Point"}
}