{
  "type": "Feature",
  "properties": {
    "gn:admin1_code":"16.0",
    "gn:asciiname":"Membo",
    "gn:country_code":"CD",
    "gn:dem":739,
    "gn:feature_class":"P",
    "gn:feature_code":"PPL",
    "gn:name":"Membo",
    "gn:population":0,
    "gn:timezone":"Africa/Lubumbashi",
    "iso:country":"CD",
    "wof:name":"Membo",
    "wof:placetype":"locality"
},
  "geometry": {"coordinates":[27.94405,3.42883],"type":"Point"}
}