{
  "type": "Feature",
  "properties": {
    "gn:admin1_code":"22.0",
    "gn:asciiname":"Goma",
    "gn:country_code":"CD",
    "gn:dem":1190,
    "gn:feature_class":"P",
    "gn:feature_code":"PPL",
    "gn:name":"Goma",
    "gn:population":0,
    "gn:timezone":"Africa/Lubumbashi",
    "iso:country":"CD",
    "wof:name":"Goma",
    "wof:placetype":"locality"
},
  "geometry": {"coordinates":[23.03844,-11.08982],"type":"Point"}
}