{
  "type": "Feature",
  "properties": {
    "gn:admin1_code":"19.0",
    "gn:asciiname":"Dambalongo",
    "gn:country_code":"CD",
    "gn:dem":614,
    "gn:feature_class":"P",
    "gn:feature_code":"PPL",
    "gn:name":"Dambalongo",
    "gn:population":0,
    "gn:timezone":"Africa/Kinshasa",
    "iso:country":"CD",
    "wof:name":"Dambalongo",
    "wof:placetype":"locality"
},
  "geometry": {"coordinates":[17.13045,-6.88261],"type":"Point"}
}