{
  "type": "Feature",
  "properties": {
    "gn:admin1_code":"12.0",
    "gn:asciiname":"Bilole",
    "gn:country_code":"CD",
    "gn:dem":2011,
    "gn:feature_class":"P",
    "gn:feature_code":"PPL",
    "gn:name":"Bilole",
    "gn:population":0,
    "gn:timezone":"Africa/Lubumbashi",
    "iso:country":"CD",
    "wof:name":"Bilole",
    "wof:placetype":"locality"
},
  "geometry": {"coordinates":[28.78444,-3.29472],"type":"Point"}
}