{
  "type": "Feature",
  "properties": {
    "gn:admin1_code":"8.0",
    "gn:asciiname":"Makunga",
    "gn:country_code":"CD",
    "gn:dem":443,
    "gn:feature_class":"P",
    "gn:feature_code":"PPL",
    "gn:name":"Makunga",
    "gn:population":0,
    "gn:timezone":"Africa/Kinshasa",
    "iso:country":"CD",
    "wof:name":"Makunga",
    "wof:placetype":"locality"
},
  "geometry": {"coordinates":[15.37516,-4.79622],"type":"Point"}
}