{
  "type": "Feature",
  "properties": {
    "gn:admin1_code":"15.0",
    "gn:asciiname":"Tumba",
    "gn:country_code":"CD",
    "gn:dem":1118,
    "gn:feature_class":"P",
    "gn:feature_code":"PPL",
    "gn:name":"Tumba",
    "gn:population":0,
    "gn:timezone":"Africa/Lubumbashi",
    "iso:country":"CD",
    "wof:name":"Tumba",
    "wof:placetype":"locality"
},
  "geometry": {"coordinates":[24.98018,-8.77064],"type":"Point"}
}