{
  "type": "Feature",
  "properties": {
    "gn:admin1_code":"19.0",
    "gn:asciiname":"Shamaziamu",
    "gn:country_code":"CD",
    "gn:dem":1130,
    "gn:feature_class":"P",
    "gn:feature_code":"PPL",
    "gn:name":"Shamaziamu",
    "gn:population":0,
    "gn:timezone":"Africa/Kinshasa",
    "iso:country":"CD",
    "wof:name":"Shamaziamu",
    "wof:placetype":"locality"
},
  "geometry": {"coordinates":[18.94887,-7.96941],"type":"Point"}
}