{
  "type": "Feature",
  "properties": {
    "gn:admin1_code":"19.0",
    "gn:asciiname":"Shakatshize",
    "gn:country_code":"CD",
    "gn:dem":941,
    "gn:feature_class":"P",
    "gn:feature_code":"PPL",
    "gn:name":"Shakatshize",
    "gn:population":0,
    "gn:timezone":"Africa/Kinshasa",
    "iso:country":"CD",
    "wof:name":"Shakatshize",
    "wof:placetype":"locality"
},
  "geometry": {"coordinates":[18.88333,-6.95],"type":"Point"}
}