{
  "type": "Feature",
  "properties": {
    "gn:admin1_code":"22.0",
    "gn:asciiname":"Sakanange",
    "gn:country_code":"CD",
    "gn:dem":1364,
    "gn:feature_class":"P",
    "gn:feature_code":"PPL",
    "gn:name":"Sakanange",
    "gn:population":0,
    "gn:timezone":"Africa/Lubumbashi",
    "iso:country":"CD",
    "wof:name":"Sakanange",
    "wof:placetype":"locality"
},
  "geometry": {"coordinates":[25.83333,-10.53333],"type":"Point"}
}