{
  "type": "Feature",
  "properties": {
    "gn:admin1_code":"19.0",
    "gn:asciiname":"Kashieta",
    "gn:country_code":"CD",
    "gn:dem":928,
    "gn:feature_class":"P",
    "gn:feature_code":"PPL",
    "gn:name":"Kashieta",
    "gn:population":0,
    "gn:timezone":"Africa/Kinshasa",
    "iso:country":"CD",
    "wof:name":"Kashieta",
    "wof:placetype":"locality"
},
  "geometry": {"coordinates":[18.77445,-6.58097],"type":"Point"}
}