{
  "type": "Feature",
  "properties": {
    "gn:admin1_code":"16.0",
    "gn:asciiname":"Aola",
    "gn:country_code":"CD",
    "gn:dem":831,
    "gn:feature_class":"P",
    "gn:feature_code":"PPL",
    "gn:name":"Aola",
    "gn:population":0,
    "gn:timezone":"Africa/Lubumbashi",
    "iso:country":"CD",
    "wof:name":"Aola",
    "wof:placetype":"locality"
},
  "geometry": {"coordinates":[29.82846,3.97024],"type":"Point"}
}