{
  "type": "Feature",
  "properties": {
    "gn:admin1_code":"20.0",
    "gn:asciiname":"Saio",
    "gn:country_code":"CD",
    "gn:dem":372,
    "gn:feature_class":"P",
    "gn:feature_code":"PPL",
    "gn:name":"Saio",
    "gn:population":0,
    "gn:timezone":"Africa/Kinshasa",
    "iso:country":"CD",
    "wof:name":"Saio",
    "wof:placetype":"locality"
},
  "geometry": {"coordinates":[18.1859,-3.79349],"type":"Point"}
}