{
  "type": "Feature",
  "properties": {
    "gn:admin1_code":"12.0",
    "gn:asciiname":"Ngandu",
    "gn:country_code":"CD",
    "gn:dem":948,
    "gn:feature_class":"P",
    "gn:feature_code":"PPL",
    "gn:name":"Ngandu",
    "gn:population":0,
    "gn:timezone":"Africa/Lubumbashi",
    "iso:country":"CD",
    "name:und_x_variant":[
        "Gandu",
        "Ngandu"
    ],
    "wof:name":"Ngandu",
    "wof:placetype":"locality"
},
  "geometry": {"coordinates":[28.44547,-2.84308],"type":"Point"}
}