{
  "type": "Feature",
  "properties": {
    "gn:admin1_code":"19.0",
    "gn:asciiname":"Mwatafumu",
    "gn:country_code":"CD",
    "gn:dem":929,
    "gn:feature_class":"P",
    "gn:feature_code":"PPL",
    "gn:name":"Mwatafumu",
    "gn:population":0,
    "gn:timezone":"Africa/Kinshasa",
    "iso:country":"CD",
    "wof:name":"Mwatafumu",
    "wof:placetype":"locality"
},
  "geometry": {"coordinates":[19.5337,-7.0588],"type":"Point"}
}