{
  "type": "Feature",
  "properties": {
    "gn:admin1_code":"14.0",
    "gn:asciiname":"Sonkolo",
    "gn:country_code":"CD",
    "gn:dem":926,
    "gn:feature_class":"P",
    "gn:feature_code":"PPL",
    "gn:name":"Sonkolo",
    "gn:population":0,
    "gn:timezone":"Africa/Lubumbashi",
    "iso:country":"CD",
    "wof:name":"Sonkolo",
    "wof:placetype":"locality"
},
  "geometry": {"coordinates":[27.61888,-9.90696],"type":"Point"}
}