{
  "type": "Feature",
  "properties": {
    "gn:admin1_code":"8.0",
    "gn:asciiname":"Lenge",
    "gn:country_code":"CD",
    "gn:dem":680,
    "gn:feature_class":"P",
    "gn:feature_code":"PPL",
    "gn:name":"Lenge",
    "gn:population":0,
    "gn:timezone":"Africa/Kinshasa",
    "iso:country":"CD",
    "wof:name":"Lenge",
    "wof:placetype":"locality"
},
  "geometry": {"coordinates":[15.30256,-5.62029],"type":"Point"}
}