{
  "type": "Feature",
  "properties": {
    "gn:admin1_code":"30.0",
    "gn:asciiname":"Bafuloko",
    "gn:country_code":"CD",
    "gn:dem":482,
    "gn:feature_class":"P",
    "gn:feature_code":"PPL",
    "gn:name":"Bafuloko",
    "gn:population":0,
    "gn:timezone":"Africa/Lubumbashi",
    "iso:country":"CD",
    "name:und_x_variant":[
        "Kilongalonga"
    ],
    "wof:name":"Bafuloko",
    "wof:placetype":"locality"
},
  "geometry": {"coordinates":[25.75619,-1.41914],"type":"Point"}
}