{
  "type": "Feature",
  "properties": {
    "gn:admin1_code":"19.0",
    "gn:asciiname":"Kajita",
    "gn:country_code":"CD",
    "gn:dem":1123,
    "gn:feature_class":"P",
    "gn:feature_code":"PPL",
    "gn:name":"Kajita",
    "gn:population":0,
    "gn:timezone":"Africa/Kinshasa",
    "iso:country":"CD",
    "wof:name":"Kajita",
    "wof:placetype":"locality"
},
  "geometry": {"coordinates":[18.64725,-7.68693],"type":"Point"}
}