{
  "type": "Feature",
  "properties": {
    "gn:admin1_code":"18.0",
    "gn:asciiname":"Tshilenge",
    "gn:country_code":"CD",
    "gn:dem":569,
    "gn:feature_class":"P",
    "gn:feature_code":"PPL",
    "gn:name":"Tshilenge",
    "gn:population":0,
    "gn:timezone":"Africa/Lubumbashi",
    "iso:country":"CD",
    "name:pol_x_preferred":[
        "Tsilenge"
    ],
    "name:ron_x_preferred":[
        "Tshilenge"
    ],
    "wof:name":"Tshilenge",
    "wof:placetype":"locality"
},
  "geometry": {"coordinates":[21.08014,-6.53438],"type":"Point"}
}