{
  "type": "Feature",
  "properties": {
    "gn:admin1_code":"20.0",
    "gn:asciiname":"Dunda-Vanda",
    "gn:country_code":"CD",
    "gn:dem":461,
    "gn:feature_class":"P",
    "gn:feature_code":"PPL",
    "gn:name":"Dunda-Vanda",
    "gn:population":0,
    "gn:timezone":"Africa/Kinshasa",
    "iso:country":"CD",
    "wof:name":"Dunda-Vanda",
    "wof:placetype":"locality"
},
  "geometry": {"coordinates":[17.71927,-4.54265],"type":"Point"}
}