{
  "type": "Feature",
  "properties": {
    "gn:admin1_code":"27.0",
    "gn:asciiname":"Omayetsha",
    "gn:country_code":"CD",
    "gn:dem":520,
    "gn:feature_class":"P",
    "gn:feature_code":"PPL",
    "gn:name":"Omayetsha",
    "gn:population":0,
    "gn:timezone":"Africa/Lubumbashi",
    "iso:country":"CD",
    "name:und_x_variant":[
        "Onayetsha",
        "Omayetsha"
    ],
    "wof:name":"Omayetsha",
    "wof:placetype":"locality"
},
  "geometry": {"coordinates":[23.62977,-3.699],"type":"Point"}
}