{
  "type": "Feature",
  "properties": {
    "gn:admin1_code":"22.0",
    "gn:asciiname":"Mwene-Kadinga",
    "gn:country_code":"CD",
    "gn:dem":928,
    "gn:feature_class":"P",
    "gn:feature_code":"PPL",
    "gn:name":"Mwene-Kadinga",
    "gn:population":0,
    "gn:timezone":"Africa/Lubumbashi",
    "iso:country":"CD",
    "wof:name":"Mwene-Kadinga",
    "wof:placetype":"locality"
},
  "geometry": {"coordinates":[22.62873,-9.24492],"type":"Point"}
}