{
  "type": "Feature",
  "properties": {
    "gn:admin1_code":"13.0",
    "gn:asciiname":"Baykumbala",
    "gn:country_code":"CD",
    "gn:dem":582,
    "gn:feature_class":"P",
    "gn:feature_code":"PPL",
    "gn:name":"Baykumbala",
    "gn:population":0,
    "gn:timezone":"Africa/Lubumbashi",
    "iso:country":"CD",
    "wof:name":"Baykumbala",
    "wof:placetype":"locality"
},
  "geometry": {"coordinates":[24.16533,4.4067],"type":"Point"}
}