{
  "type": "Feature",
  "properties": {
    "gn:admin1_code":"19.0",
    "gn:asciiname":"Bilembo",
    "gn:country_code":"CD",
    "gn:dem":813,
    "gn:feature_class":"P",
    "gn:feature_code":"PPL",
    "gn:name":"Bilembo",
    "gn:population":0,
    "gn:timezone":"Africa/Kinshasa",
    "iso:country":"CD",
    "wof:name":"Bilembo",
    "wof:placetype":"locality"
},
  "geometry": {"coordinates":[17.66258,-5.87938],"type":"Point"}
}