{
  "type": "Feature",
  "properties": {
    "gn:admin1_code":"22.0",
    "gn:asciiname":"Nakapumba",
    "gn:country_code":"CD",
    "gn:dem":1156,
    "gn:feature_class":"P",
    "gn:feature_code":"PPL",
    "gn:name":"Nakapumba",
    "gn:population":0,
    "gn:timezone":"Africa/Lubumbashi",
    "iso:country":"CD",
    "wof:name":"Nakapumba",
    "wof:placetype":"locality"
},
  "geometry": {"coordinates":[24.01911,-10.22959],"type":"Point"}
}