{
  "type": "Feature",
  "properties": {
    "gn:admin1_code":"13.0",
    "gn:asciiname":"Lumande",
    "gn:country_code":"CD",
    "gn:dem":458,
    "gn:feature_class":"P",
    "gn:feature_code":"PPL",
    "gn:name":"Lumande",
    "gn:population":0,
    "gn:timezone":"Africa/Lubumbashi",
    "iso:country":"CD",
    "wof:name":"Lumande",
    "wof:placetype":"locality"
},
  "geometry": {"coordinates":[22.81602,4.22483],"type":"Point"}
}