{
  "type": "Feature",
  "properties": {
    "gn:admin1_code":"31.0",
    "gn:asciiname":"Isuki",
    "gn:country_code":"CD",
    "gn:dem":403,
    "gn:feature_class":"P",
    "gn:feature_code":"PPL",
    "gn:name":"Isuki",
    "gn:population":0,
    "gn:timezone":"Africa/Kinshasa",
    "iso:country":"CD",
    "wof:name":"Isuki",
    "wof:placetype":"locality"
},
  "geometry": {"coordinates":[23.12123,-0.79824],"type":"Point"}
}