{
  "type": "Feature",
  "properties": {
    "gn:admin1_code":"20.0",
    "gn:asciiname":"Zombo",
    "gn:country_code":"CD",
    "gn:dem":494,
    "gn:feature_class":"P",
    "gn:feature_code":"PPL",
    "gn:name":"Zombo",
    "gn:population":0,
    "gn:timezone":"Africa/Kinshasa",
    "iso:country":"CD",
    "name:ceb_x_preferred":[
        "Zombo"
    ],
    "name:lug_x_preferred":[
        "Zombo"
    ],
    "name:swe_x_preferred":[
        "Zombo"
    ],
    "wof:name":"Zombo",
    "wof:placetype":"locality"
},
  "geometry": {"coordinates":[17.68277999999999,-4.99054],"type":"Point"}
}