{
  "type": "Feature",
  "properties": {
    "gn:admin1_code":"28.0",
    "gn:asciiname":"Ngole",
    "gn:country_code":"CD",
    "gn:dem":413,
    "gn:feature_class":"P",
    "gn:feature_code":"PPL",
    "gn:name":"Ngole",
    "gn:population":0,
    "gn:timezone":"Africa/Kinshasa",
    "iso:country":"CD",
    "name:fra_x_preferred":[
        "Ngole"
    ],
    "wof:name":"Ngole",
    "wof:placetype":"locality"
},
  "geometry": {"coordinates":[19.22036,2.89732],"type":"Point"}
}