{
  "type": "Feature",
  "properties": {
    "gn:admin1_code":"26.0",
    "gn:asciiname":"Wagbodo",
    "gn:country_code":"CD",
    "gn:dem":510,
    "gn:feature_class":"P",
    "gn:feature_code":"PPL",
    "gn:name":"Wagbodo",
    "gn:population":0,
    "gn:timezone":"Africa/Kinshasa",
    "iso:country":"CD",
    "name:und_x_variant":[
        "Wagbolo",
        "Wagaboda",
        "Wagbodo"
    ],
    "wof:name":"Wagbodo",
    "wof:placetype":"locality"
},
  "geometry": {"coordinates":[22.73043,3.7101],"type":"Point"}
}