{
  "type": "Feature",
  "properties": {
    "gn:admin1_code":"8.0",
    "gn:asciiname":"Kinkadi",
    "gn:country_code":"CD",
    "gn:dem":601,
    "gn:feature_class":"P",
    "gn:feature_code":"PPL",
    "gn:name":"Kinkadi",
    "gn:population":0,
    "gn:timezone":"Africa/Kinshasa",
    "iso:country":"CD",
    "wof:name":"Kinkadi",
    "wof:placetype":"locality"
},
  "geometry": {"coordinates":[15.35421,-4.98349],"type":"Point"}
}