{
  "type": "Feature",
  "properties": {
    "gn:admin1_code":"14.0",
    "gn:asciiname":"Dikansa",
    "gn:country_code":"CD",
    "gn:dem":1341,
    "gn:feature_class":"P",
    "gn:feature_code":"PPL",
    "gn:name":"Dikansa",
    "gn:population":0,
    "gn:timezone":"Africa/Lubumbashi",
    "iso:country":"CD",
    "name:und_x_variant":[
        "Dikanza"
    ],
    "wof:name":"Dikansa",
    "wof:placetype":"locality"
},
  "geometry": {"coordinates":[27.03945,-11.54202],"type":"Point"}
}