{
  "type": "Feature",
  "properties": {
    "gn:admin1_code":"25.0",
    "gn:asciiname":"Mongana",
    "gn:country_code":"CD",
    "gn:dem":344,
    "gn:feature_class":"P",
    "gn:feature_code":"PPL",
    "gn:name":"Mongana",
    "gn:population":0,
    "gn:timezone":"Africa/Kinshasa",
    "iso:country":"CD",
    "name:und_x_variant":[
        "Moregana",
        "Mongana"
    ],
    "wof:name":"Mongana",
    "wof:placetype":"locality"
},
  "geometry": {"coordinates":[21.68393,2.10052],"type":"Point"}
}