{
  "type": "Feature",
  "properties": {
    "gn:admin1_code":"15.0",
    "gn:asciiname":"Tshikunda",
    "gn:country_code":"CD",
    "gn:dem":943,
    "gn:feature_class":"P",
    "gn:feature_code":"PPL",
    "gn:name":"Tshikunda",
    "gn:population":0,
    "gn:timezone":"Africa/Lubumbashi",
    "iso:country":"CD",
    "wof:name":"Tshikunda",
    "wof:placetype":"locality"
},
  "geometry": {"coordinates":[23.94529,-8.13654],"type":"Point"}
}