{
  "type": "Feature",
  "properties": {
    "gn:admin1_code":"25.0",
    "gn:asciiname":"Lifanga",
    "gn:country_code":"CD",
    "gn:dem":405,
    "gn:feature_class":"P",
    "gn:feature_code":"PPL",
    "gn:name":"Lifanga",
    "gn:population":0,
    "gn:timezone":"Africa/Kinshasa",
    "iso:country":"CD",
    "wof:name":"Lifanga",
    "wof:placetype":"locality"
},
  "geometry": {"coordinates":[22.44404,1.90509],"type":"Point"}
}