{
  "type": "Feature",
  "properties": {
    "gn:admin1_code":"19.0",
    "gn:asciiname":"Shamandjolo",
    "gn:country_code":"CD",
    "gn:dem":1075,
    "gn:feature_class":"P",
    "gn:feature_code":"PPL",
    "gn:name":"Shamandjolo",
    "gn:population":0,
    "gn:timezone":"Africa/Kinshasa",
    "iso:country":"CD",
    "wof:name":"Shamandjolo",
    "wof:placetype":"locality"
},
  "geometry": {"coordinates":[19.05497,-7.61938],"type":"Point"}
}