{
  "type": "Feature",
  "properties": {
    "gn:admin1_code":"17.0",
    "gn:asciiname":"Adranga",
    "gn:country_code":"CD",
    "gn:dem":1118,
    "gn:feature_class":"P",
    "gn:feature_code":"PPL",
    "gn:name":"Adranga",
    "gn:population":0,
    "gn:timezone":"Africa/Lubumbashi",
    "iso:country":"CD",
    "wof:name":"Adranga",
    "wof:placetype":"locality"
},
  "geometry": {"coordinates":[30.42064,2.90029],"type":"Point"}
}