{
  "type": "Feature",
  "properties": {
    "gn:admin1_code":"14.0",
    "gn:asciiname":"Malembeke",
    "gn:country_code":"CD",
    "gn:dem":1113,
    "gn:feature_class":"P",
    "gn:feature_code":"PPL",
    "gn:name":"Malembeke",
    "gn:population":0,
    "gn:timezone":"Africa/Lubumbashi",
    "iso:country":"CD",
    "wof:name":"Malembeke",
    "wof:placetype":"locality"
},
  "geometry": {"coordinates":[26.56139000000001,-10.62333],"type":"Point"}
}