{
  "type": "Feature",
  "properties": {
    "gn:admin1_code":"8.0",
    "gn:asciiname":"Kondo-Matuba",
    "gn:country_code":"CD",
    "gn:dem":542,
    "gn:feature_class":"P",
    "gn:feature_code":"PPL",
    "gn:name":"Kondo-Matuba",
    "gn:population":0,
    "gn:timezone":"Africa/Kinshasa",
    "iso:country":"CD",
    "wof:name":"Kondo-Matuba",
    "wof:placetype":"locality"
},
  "geometry": {"coordinates":[14.86156,-4.99486],"type":"Point"}
}