{
  "type": "Feature",
  "properties": {
    "gn:admin1_code":"13.0",
    "gn:asciiname":"Diwili",
    "gn:country_code":"CD",
    "gn:dem":550,
    "gn:feature_class":"P",
    "gn:feature_code":"PPL",
    "gn:name":"Diwili",
    "gn:population":0,
    "gn:timezone":"Africa/Lubumbashi",
    "iso:country":"CD",
    "wof:name":"Diwili",
    "wof:placetype":"locality"
},
  "geometry": {"coordinates":[23.9159,3.87479],"type":"Point"}
}