{
  "type": "Feature",
  "properties": {
    "gn:admin1_code":"10.0",
    "gn:asciiname":"Mitimbili",
    "gn:country_code":"CD",
    "gn:dem":690,
    "gn:feature_class":"P",
    "gn:feature_code":"PPL",
    "gn:name":"Mitimbili",
    "gn:population":0,
    "gn:timezone":"Africa/Lubumbashi",
    "iso:country":"CD",
    "wof:name":"Mitimbili",
    "wof:placetype":"locality"
},
  "geometry": {"coordinates":[27.96492000000001,-4.2818],"type":"Point"}
}