{
  "type": "Feature",
  "properties": {
    "gn:admin1_code":"22.0",
    "gn:asciiname":"Sambwania",
    "gn:country_code":"CD",
    "gn:dem":1044,
    "gn:feature_class":"P",
    "gn:feature_code":"PPL",
    "gn:name":"Sambwania",
    "gn:population":0,
    "gn:timezone":"Africa/Lubumbashi",
    "iso:country":"CD",
    "wof:name":"Sambwania",
    "wof:placetype":"locality"
},
  "geometry": {"coordinates":[22.94718,-9.44124],"type":"Point"}
}