{
  "type": "Feature",
  "properties": {
    "gn:admin1_code":"22.0",
    "gn:asciiname":"Bangu",
    "gn:country_code":"CD",
    "gn:dem":1104,
    "gn:feature_class":"P",
    "gn:feature_code":"PPL",
    "gn:name":"Bangu",
    "gn:population":0,
    "gn:timezone":"Africa/Lubumbashi",
    "iso:country":"CD",
    "name:ceb_x_preferred":[
        "Bangu"
    ],
    "name:fra_x_preferred":[
        "Bangu"
    ],
    "name:ita_x_preferred":[
        "Bangu"
    ],
    "name:nld_x_preferred":[
        "Bangu"
    ],
    "name:por_x_preferred":[
        "Bangu"
    ],
    "name:swe_x_preferred":[
        "Bangu"
    ],
    "name:und_x_variant":[
        "Mbangu"
    ],
    "wof:name":"Bangu",
    "wof:placetype":"locality"
},
  "geometry": {"coordinates":[23.71787,-9.09076],"type":"Point"}
}