{
  "type": "Feature",
  "properties": {
    "gn:admin1_code":"16.0",
    "gn:asciiname":"Anakonzi",
    "gn:country_code":"CD",
    "gn:dem":902,
    "gn:feature_class":"P",
    "gn:feature_code":"PPL",
    "gn:name":"Anakonzi",
    "gn:population":0,
    "gn:timezone":"Africa/Lubumbashi",
    "iso:country":"CD",
    "name:und_x_variant":[
        "Amakonzi"
    ],
    "wof:name":"Anakonzi",
    "wof:placetype":"locality"
},
  "geometry": {"coordinates":[29.88182,3.2826],"type":"Point"}
}