{
  "type": "Feature",
  "properties": {
    "gn:admin1_code":"26.0",
    "gn:asciiname":"Badja Premiere",
    "gn:country_code":"CD",
    "gn:dem":439,
    "gn:feature_class":"P",
    "gn:feature_code":"PPL",
    "gn:name":"Badja Premi\u00e8re",
    "gn:population":0,
    "gn:timezone":"Africa/Kinshasa",
    "iso:country":"CD",
    "name:und_x_variant":[
        "Badja Premi\u00e8re",
        "Badja I"
    ],
    "wof:name":"Badja Premiere",
    "wof:placetype":"locality"
},
  "geometry": {"coordinates":[19.99311,4.49279],"type":"Point"}
}