{
  "type": "Feature",
  "properties": {
    "gn:admin1_code":"13.0",
    "gn:asciiname":"Nazamba",
    "gn:country_code":"CD",
    "gn:dem":691,
    "gn:feature_class":"P",
    "gn:feature_code":"PPL",
    "gn:name":"Nazamba",
    "gn:population":0,
    "gn:timezone":"Africa/Lubumbashi",
    "iso:country":"CD",
    "wof:name":"Nazamba",
    "wof:placetype":"locality"
},
  "geometry": {"coordinates":[27.41074,3.05402],"type":"Point"}
}