{
  "type": "Feature",
  "properties": {
    "gn:admin1_code":"16.0",
    "gn:asciiname":"Ebale",
    "gn:country_code":"CD",
    "gn:dem":753,
    "gn:feature_class":"P",
    "gn:feature_code":"PPL",
    "gn:name":"Ebale",
    "gn:population":0,
    "gn:timezone":"Africa/Lubumbashi",
    "iso:country":"CD",
    "wof:name":"Ebale",
    "wof:placetype":"locality"
},
  "geometry": {"coordinates":[27.32671,2.6074],"type":"Point"}
}