{
  "type": "Feature",
  "properties": {
    "gn:admin1_code":"25.0",
    "gn:asciiname":"Yakoi",
    "gn:country_code":"CD",
    "gn:dem":419,
    "gn:feature_class":"P",
    "gn:feature_code":"PPL",
    "gn:name":"Yakoi",
    "gn:population":0,
    "gn:timezone":"Africa/Kinshasa",
    "iso:country":"CD",
    "wof:name":"Yakoi",
    "wof:placetype":"locality"
},
  "geometry": {"coordinates":[22.49456,2.44243],"type":"Point"}
}