{
  "type": "Feature",
  "properties": {
    "gn:admin1_code":"19.0",
    "gn:asciiname":"Bukanga-Tangombe",
    "gn:country_code":"CD",
    "gn:dem":464,
    "gn:feature_class":"P",
    "gn:feature_code":"PPL",
    "gn:name":"Bukanga-Tangombe",
    "gn:population":0,
    "gn:timezone":"Africa/Kinshasa",
    "iso:country":"CD",
    "wof:name":"Bukanga-Tangombe",
    "wof:placetype":"locality"
},
  "geometry": {"coordinates":[17.39196,-4.42028],"type":"Point"}
}