{
  "type": "Feature",
  "properties": {
    "gn:admin1_code":"8.0",
    "gn:asciiname":"Kongo-Botongo",
    "gn:country_code":"CD",
    "gn:dem":570,
    "gn:feature_class":"P",
    "gn:feature_code":"PPL",
    "gn:name":"Kongo-Botongo",
    "gn:population":0,
    "gn:timezone":"Africa/Kinshasa",
    "iso:country":"CD",
    "wof:name":"Kongo-Botongo",
    "wof:placetype":"locality"
},
  "geometry": {"coordinates":[14.48833,-5.10197],"type":"Point"}
}