{
  "type": "Feature",
  "properties": {
    "gn:admin1_code":"19.0",
    "gn:asciiname":"Tshikozi",
    "gn:country_code":"CD",
    "gn:dem":983,
    "gn:feature_class":"P",
    "gn:feature_code":"PPL",
    "gn:name":"Tshikozi",
    "gn:population":0,
    "gn:timezone":"Africa/Kinshasa",
    "iso:country":"CD",
    "wof:name":"Tshikozi",
    "wof:placetype":"locality"
},
  "geometry": {"coordinates":[18.39457,-7.90913],"type":"Point"}
}