{
  "type": "Feature",
  "properties": {
    "gn:admin1_code":"15.0",
    "gn:asciiname":"Tshifumbe",
    "gn:country_code":"CD",
    "gn:dem":928,
    "gn:feature_class":"P",
    "gn:feature_code":"PPL",
    "gn:name":"Tshifumbe",
    "gn:population":0,
    "gn:timezone":"Africa/Lubumbashi",
    "iso:country":"CD",
    "wof:name":"Tshifumbe",
    "wof:placetype":"locality"
},
  "geometry": {"coordinates":[24.2924,-7.9684],"type":"Point"}
}