{
  "type": "Feature",
  "properties": {
    "gn:admin1_code":"19.0",
    "gn:asciiname":"Mwana-Tshikonia",
    "gn:country_code":"CD",
    "gn:dem":908,
    "gn:feature_class":"P",
    "gn:feature_code":"PPL",
    "gn:name":"Mwana-Tshikonia",
    "gn:population":0,
    "gn:timezone":"Africa/Kinshasa",
    "iso:country":"CD",
    "wof:name":"Mwana-Tshikonia",
    "wof:placetype":"locality"
},
  "geometry": {"coordinates":[19.57819,-6.91523],"type":"Point"}
}