{
  "type": "Feature",
  "properties": {
    "gn:admin1_code":"22.0",
    "gn:asciiname":"Tshishidil",
    "gn:country_code":"CD",
    "gn:dem":887,
    "gn:feature_class":"P",
    "gn:feature_code":"PPL",
    "gn:name":"Tshishidil",
    "gn:population":0,
    "gn:timezone":"Africa/Lubumbashi",
    "iso:country":"CD",
    "name:und_x_variant":[
        "Tshishidila"
    ],
    "wof:name":"Tshishidil",
    "wof:placetype":"locality"
},
  "geometry": {"coordinates":[22.64863,-8.30917],"type":"Point"}
}