{
  "type": "Feature",
  "properties": {
    "gn:admin1_code":"15.0",
    "gn:asciiname":"Kalombo",
    "gn:country_code":"CD",
    "gn:dem":991,
    "gn:feature_class":"P",
    "gn:feature_code":"PPL",
    "gn:name":"Kalombo",
    "gn:population":0,
    "gn:timezone":"Africa/Lubumbashi",
    "iso:country":"CD",
    "wof:name":"Kalombo",
    "wof:placetype":"locality"
},
  "geometry": {"coordinates":[25.41667,-8.81667],"type":"Point"}
}