{
  "type": "Feature",
  "properties": {
    "gn:admin1_code":"30.0",
    "gn:asciiname":"Baluka",
    "gn:country_code":"CD",
    "gn:dem":463,
    "gn:feature_class":"P",
    "gn:feature_code":"PPL",
    "gn:name":"Baluka",
    "gn:population":0,
    "gn:timezone":"Africa/Lubumbashi",
    "iso:country":"CD",
    "wof:name":"Baluka",
    "wof:placetype":"locality"
},
  "geometry": {"coordinates":[25.62116,-0.17081],"type":"Point"}
}