{
  "type": "Feature",
  "properties": {
    "gn:admin1_code":"26.0",
    "gn:asciiname":"Banga Deuxieme",
    "gn:country_code":"CD",
    "gn:dem":393,
    "gn:feature_class":"P",
    "gn:feature_code":"PPL",
    "gn:name":"Banga Deuxi\u00e8me",
    "gn:population":0,
    "gn:timezone":"Africa/Kinshasa",
    "iso:country":"CD",
    "name:und_x_variant":[
        "Banga Deuxi\u00e8me",
        "Banga II"
    ],
    "wof:name":"Banga Deuxieme",
    "wof:placetype":"locality"
},
  "geometry": {"coordinates":[19.19401,4.83866],"type":"Point"}
}