{
  "type": "Feature",
  "properties": {
    "gn:admin1_code":"8.0",
    "gn:asciiname":"Kiangu",
    "gn:country_code":"CD",
    "gn:dem":524,
    "gn:feature_class":"P",
    "gn:feature_code":"PPL",
    "gn:name":"Kiangu",
    "gn:population":0,
    "gn:timezone":"Africa/Kinshasa",
    "iso:country":"CD",
    "wof:name":"Kiangu",
    "wof:placetype":"locality"
},
  "geometry": {"coordinates":[14.29081,-4.42642],"type":"Point"}
}