{
  "type": "Feature",
  "properties": {
    "gn:admin1_code":"18.0",
    "gn:asciiname":"Tshibuaka",
    "gn:country_code":"CD",
    "gn:dem":764,
    "gn:feature_class":"P",
    "gn:feature_code":"PPL",
    "gn:name":"Tshibuaka",
    "gn:population":0,
    "gn:timezone":"Africa/Lubumbashi",
    "iso:country":"CD",
    "wof:name":"Tshibuaka",
    "wof:placetype":"locality"
},
  "geometry": {"coordinates":[21.11143,-7.17796],"type":"Point"}
}