{
  "type": "Feature",
  "properties": {
    "gn:admin1_code":"20.0",
    "gn:asciiname":"Tshongopiopio",
    "gn:country_code":"CD",
    "gn:dem":425,
    "gn:feature_class":"P",
    "gn:feature_code":"PPL",
    "gn:name":"Tshongopiopio",
    "gn:population":0,
    "gn:timezone":"Africa/Kinshasa",
    "iso:country":"CD",
    "wof:name":"Tshongopiopio",
    "wof:placetype":"locality"
},
  "geometry": {"coordinates":[19.60362000000001,-4.38287],"type":"Point"}
}