{
  "type": "Feature",
  "properties": {
    "gn:admin1_code":"4.0",
    "gn:asciiname":"Kabeya-Buata",
    "gn:country_code":"CD",
    "gn:dem":621,
    "gn:feature_class":"P",
    "gn:feature_code":"PPL",
    "gn:name":"Kabeya-Buata",
    "gn:population":0,
    "gn:timezone":"Africa/Lubumbashi",
    "iso:country":"CD",
    "wof:name":"Kabeya-Buata",
    "wof:placetype":"locality"
},
  "geometry": {"coordinates":[23.18273,-6.09604],"type":"Point"}
}