{
  "type": "Feature",
  "properties": {
    "gn:admin1_code":"15.0",
    "gn:asciiname":"Umbombo",
    "gn:country_code":"CD",
    "gn:dem":565,
    "gn:feature_class":"P",
    "gn:feature_code":"PPL",
    "gn:name":"Umbombo",
    "gn:population":0,
    "gn:timezone":"Africa/Lubumbashi",
    "iso:country":"CD",
    "wof:name":"Umbombo",
    "wof:placetype":"locality"
},
  "geometry": {"coordinates":[26.51041,-8.37268],"type":"Point"}
}