{
  "type": "Feature",
  "properties": {
    "gn:admin1_code":"0.0",
    "gn:asciiname":"Yambe",
    "gn:country_code":"CD",
    "gn:dem":294,
    "gn:feature_class":"P",
    "gn:feature_code":"PPL",
    "gn:name":"Yambe",
    "gn:population":0,
    "gn:timezone":"Africa/Brazzaville",
    "iso:country":"CD",
    "name:ceb_x_preferred":[
        "Yambe"
    ],
    "name:swe_x_preferred":[
        "Yambe"
    ],
    "wof:name":"Yambe",
    "wof:placetype":"locality"
},
  "geometry": {"coordinates":[17.56667,-0.73333],"type":"Point"}
}