{
  "type": "Feature",
  "properties": {
    "gn:admin1_code":"10.0",
    "gn:asciiname":"Obila",
    "gn:country_code":"CD",
    "gn:dem":649,
    "gn:feature_class":"P",
    "gn:feature_code":"PPL",
    "gn:name":"Obila",
    "gn:population":0,
    "gn:timezone":"Africa/Lubumbashi",
    "iso:country":"CD",
    "name:ceb_x_preferred":[
        "Obila"
    ],
    "name:swe_x_preferred":[
        "Obila"
    ],
    "name:vie_x_preferred":[
        "Obila"
    ],
    "name:war_x_preferred":[
        "Obila"
    ],
    "wof:name":"Obila",
    "wof:placetype":"locality"
},
  "geometry": {"coordinates":[26.40917,-1.40267],"type":"Point"}
}