{
  "type": "Feature",
  "properties": {
    "gn:admin1_code":"22.0",
    "gn:asciiname":"Tshaku",
    "gn:country_code":"CD",
    "gn:dem":1113,
    "gn:feature_class":"P",
    "gn:feature_code":"PPL",
    "gn:name":"Tshaku",
    "gn:population":0,
    "gn:timezone":"Africa/Lubumbashi",
    "iso:country":"CD",
    "wof:name":"Tshaku",
    "wof:placetype":"locality"
},
  "geometry": {"coordinates":[23.55429,-10.40886],"type":"Point"}
}