{
  "type": "Feature",
  "properties": {
    "gn:admin1_code":"27.0",
    "gn:asciiname":"Okala",
    "gn:country_code":"CD",
    "gn:dem":576,
    "gn:feature_class":"P",
    "gn:feature_code":"PPL",
    "gn:name":"Okala",
    "gn:population":0,
    "gn:timezone":"Africa/Lubumbashi",
    "iso:country":"CD",
    "wof:name":"Okala",
    "wof:placetype":"locality"
},
  "geometry": {"coordinates":[22.6412,-2.89387],"type":"Point"}
}