{
  "type": "Feature",
  "properties": {
    "gn:admin1_code":"20.0",
    "gn:asciiname":"Ngiei",
    "gn:country_code":"CD",
    "gn:dem":349,
    "gn:feature_class":"P",
    "gn:feature_code":"PPL",
    "gn:name":"Ngiei",
    "gn:population":0,
    "gn:timezone":"Africa/Kinshasa",
    "iso:country":"CD",
    "name:und_x_variant":[
        "Ngie"
    ],
    "wof:name":"Ngiei",
    "wof:placetype":"locality"
},
  "geometry": {"coordinates":[17.63211,-3.75069],"type":"Point"}
}