{
  "type": "Feature",
  "properties": {
    "gn:admin1_code":"17.0",
    "gn:asciiname":"Goba",
    "gn:country_code":"CD",
    "gn:dem":1815,
    "gn:feature_class":"P",
    "gn:feature_code":"PPL",
    "gn:name":"Goba",
    "gn:population":0,
    "gn:timezone":"Africa/Lubumbashi",
    "iso:country":"CD",
    "name:ben_x_preferred":[
        "\u0997\u09cb\u09ac\u09be"
    ],
    "name:ceb_x_preferred":[
        "Goba"
    ],
    "name:deu_x_preferred":[
        "Goba"
    ],
    "name:ell_x_preferred":[
        "\u0393\u03ba\u03cc\u03bc\u03c0\u03b1"
    ],
    "name:fas_x_preferred":[
        "\u06af\u0648\u0628\u0627"
    ],
    "name:fra_x_preferred":[
        "Goba"
    ],
    "name:heb_x_preferred":[
        "\u05d2\u05d5\u05d1\u05d4"
    ],
    "name:hrv_x_preferred":[
        "Goba"
    ],
    "name:ind_x_preferred":[
        "Goba"
    ],
    "name:ita_x_preferred":[
        "Goba"
    ],
    "name:nld_x_preferred":[
        "Goba"
    ],
    "name:pol_x_preferred":[
        "Goba"
    ],
    "name:por_x_preferred":[
        "Goba"
    ],
    "name:ron_x_preferred":[
        "Goba"
    ],
    "name:rus_x_preferred":[
        "\u0413\u043e\u0431\u0430"
    ],
    "name:spa_x_preferred":[
        "Goba"
    ],
    "name:swe_x_preferred":[
        "Goba"
    ],
    "name:tur_x_preferred":[
        "Goba"
    ],
    "name:urd_x_preferred":[
        "\u06af\u0648\u0628\u0627"
    ],
    "name:vie_x_preferred":[
        "Goba"
    ],
    "wof:name":"Goba",
    "wof:placetype":"locality"
},
  "geometry": {"coordinates":[30.66667,1.81667],"type":"Point"}
}