{
  "type": "Feature",
  "properties": {
    "gn:admin1_code":"17.0",
    "gn:asciiname":"Goba",
    "gn:country_code":"CD",
    "gn:dem":1815,
    "gn:feature_class":"P",
    "gn:feature_code":"PPL",
    "gn:name":"Goba",
    "gn:population":0,
    "gn:timezone":"Africa/Lubumbashi",
    "iso:country":"CD",
    "wof:name":"Goba",
    "wof:placetype":"locality"
},
  "geometry": {"coordinates":[30.66667,1.81667],"type":"Point"}
}