{
  "type": "Feature",
  "properties": {
    "gn:admin1_code":"22.0",
    "gn:asciiname":"Kalula",
    "gn:country_code":"CD",
    "gn:dem":1046,
    "gn:feature_class":"P",
    "gn:feature_code":"PPL",
    "gn:name":"Kalula",
    "gn:population":0,
    "gn:timezone":"Africa/Lubumbashi",
    "iso:country":"CD",
    "wof:name":"Kalula",
    "wof:placetype":"locality"
},
  "geometry": {"coordinates":[23.51248,-10.57653],"type":"Point"}
}