{
  "type": "Feature",
  "properties": {
    "gn:admin1_code":"26.0",
    "gn:asciiname":"Bema",
    "gn:country_code":"CD",
    "gn:dem":431,
    "gn:feature_class":"P",
    "gn:feature_code":"PPL",
    "gn:name":"Bema",
    "gn:population":0,
    "gn:timezone":"Africa/Kinshasa",
    "iso:country":"CD",
    "name:fra_x_preferred":[
        "B\u00eama"
    ],
    "name:ita_x_preferred":[
        "Bimah"
    ],
    "name:nor_x_preferred":[
        "Bima"
    ],
    "name:por_x_preferred":[
        "Bema"
    ],
    "name:rus_x_preferred":[
        "\u0412\u0438\u043c\u0430"
    ],
    "name:slv_x_preferred":[
        "Bema"
    ],
    "name:tur_x_preferred":[
        "Bema"
    ],
    "wof:name":"Bema",
    "wof:placetype":"locality"
},
  "geometry": {"coordinates":[22.5783,3.8935],"type":"Point"}
}