{
  "type": "Feature",
  "properties": {
    "gn:admin1_code":"29.0",
    "gn:asciiname":"Rutuku",
    "gn:country_code":"CD",
    "gn:dem":772,
    "gn:feature_class":"P",
    "gn:feature_code":"PPL",
    "gn:name":"Rutuku",
    "gn:population":0,
    "gn:timezone":"Africa/Lubumbashi",
    "iso:country":"CD",
    "wof:name":"Rutuku",
    "wof:placetype":"locality"
},
  "geometry": {"coordinates":[29.32687,-6.19958],"type":"Point"}
}