{
  "type": "Feature",
  "properties": {
    "gn:admin1_code":"28.0",
    "gn:asciiname":"Furu",
    "gn:country_code":"CD",
    "gn:dem":390,
    "gn:feature_class":"P",
    "gn:feature_code":"PPL",
    "gn:name":"Furu",
    "gn:population":0,
    "gn:timezone":"Africa/Kinshasa",
    "iso:country":"CD",
    "wof:name":"Furu",
    "wof:placetype":"locality"
},
  "geometry": {"coordinates":[20.0531,3.14703],"type":"Point"}
}