{
  "type": "Feature",
  "properties": {
    "gn:admin1_code":"21.0",
    "gn:asciiname":"Lupongo",
    "gn:country_code":"CD",
    "gn:dem":674,
    "gn:feature_class":"P",
    "gn:feature_code":"PPL",
    "gn:name":"Lupongo",
    "gn:population":0,
    "gn:timezone":"Africa/Lubumbashi",
    "iso:country":"CD",
    "wof:name":"Lupongo",
    "wof:placetype":"locality"
},
  "geometry": {"coordinates":[25.76667,-5.48333],"type":"Point"}
}