{
  "type": "Feature",
  "properties": {
    "gn:admin1_code":"30.0",
    "gn:asciiname":"Yaula-Moke",
    "gn:country_code":"CD",
    "gn:dem":422,
    "gn:feature_class":"P",
    "gn:feature_code":"PPL",
    "gn:name":"Yaula-Moke",
    "gn:population":0,
    "gn:timezone":"Africa/Lubumbashi",
    "iso:country":"CD",
    "wof:name":"Yaula-Moke",
    "wof:placetype":"locality"
},
  "geometry": {"coordinates":[24.09165,0.44836],"type":"Point"}
}