{
  "type": "Feature",
  "properties": {
    "gn:admin1_code":"19.0",
    "gn:asciiname":"Kabuita",
    "gn:country_code":"CD",
    "gn:dem":741,
    "gn:feature_class":"P",
    "gn:feature_code":"PPL",
    "gn:name":"Kabuita",
    "gn:population":0,
    "gn:timezone":"Africa/Kinshasa",
    "iso:country":"CD",
    "name:und_x_variant":[
        "Kabwita",
        "Kabuita"
    ],
    "wof:name":"Kabuita",
    "wof:placetype":"locality"
},
  "geometry": {"coordinates":[17.23333,-5.47184],"type":"Point"}
}