{
  "type": "Feature",
  "properties": {
    "gn:admin1_code":"22.0",
    "gn:asciiname":"Tshingamba",
    "gn:country_code":"CD",
    "gn:dem":1008,
    "gn:feature_class":"P",
    "gn:feature_code":"PPL",
    "gn:name":"Tshingamba",
    "gn:population":0,
    "gn:timezone":"Africa/Lubumbashi",
    "iso:country":"CD",
    "wof:name":"Tshingamba",
    "wof:placetype":"locality"
},
  "geometry": {"coordinates":[22.66667,-10.36667],"type":"Point"}
}