{
  "type": "Feature",
  "properties": {
    "gn:admin1_code":"20.0",
    "gn:asciiname":"Fumu",
    "gn:country_code":"CD",
    "gn:dem":564,
    "gn:feature_class":"P",
    "gn:feature_code":"PPL",
    "gn:name":"Fumu",
    "gn:population":0,
    "gn:timezone":"Africa/Kinshasa",
    "iso:country":"CD",
    "wof:name":"Fumu",
    "wof:placetype":"locality"
},
  "geometry": {"coordinates":[17.85533,-4.78218],"type":"Point"}
}