{
  "type": "Feature",
  "properties": {
    "gn:admin1_code":"18.0",
    "gn:asciiname":"Miabo-Kandolo",
    "gn:country_code":"CD",
    "gn:dem":630,
    "gn:feature_class":"P",
    "gn:feature_code":"PPL",
    "gn:name":"Miabo-Kandolo",
    "gn:population":0,
    "gn:timezone":"Africa/Lubumbashi",
    "iso:country":"CD",
    "wof:name":"Miabo-Kandolo",
    "wof:placetype":"locality"
},
  "geometry": {"coordinates":[21.17433,-6.15554],"type":"Point"}
}