{
  "type": "Feature",
  "properties": {
    "gn:admin1_code":"16.0",
    "gn:asciiname":"Bilikpongo",
    "gn:country_code":"CD",
    "gn:dem":744,
    "gn:feature_class":"P",
    "gn:feature_code":"PPL",
    "gn:name":"Bilikpongo",
    "gn:population":0,
    "gn:timezone":"Africa/Lubumbashi",
    "iso:country":"CD",
    "wof:name":"Bilikpongo",
    "wof:placetype":"locality"
},
  "geometry": {"coordinates":[27.46837,2.75307],"type":"Point"}
}