{
  "type": "Feature",
  "properties": {
    "gn:admin1_code":"20.0",
    "gn:asciiname":"Kimbanda",
    "gn:country_code":"CD",
    "gn:dem":353,
    "gn:feature_class":"P",
    "gn:feature_code":"PPL",
    "gn:name":"Kimbanda",
    "gn:population":0,
    "gn:timezone":"Africa/Kinshasa",
    "iso:country":"CD",
    "wof:name":"Kimbanda",
    "wof:placetype":"locality"
},
  "geometry": {"coordinates":[17.98226,-4.0808],"type":"Point"}
}