{
  "type": "Feature",
  "properties": {
    "gn:admin1_code":"20.0",
    "gn:asciiname":"Luswete",
    "gn:country_code":"CD",
    "gn:dem":763,
    "gn:feature_class":"P",
    "gn:feature_code":"PPL",
    "gn:name":"Luswete",
    "gn:population":0,
    "gn:timezone":"Africa/Kinshasa",
    "iso:country":"CD",
    "wof:name":"Luswete",
    "wof:placetype":"locality"
},
  "geometry": {"coordinates":[19.11702,-5.59077],"type":"Point"}
}