{
  "type": "Feature",
  "properties": {
    "gn:admin1_code":"30.0",
    "gn:asciiname":"Bombongo",
    "gn:country_code":"CD",
    "gn:dem":432,
    "gn:feature_class":"P",
    "gn:feature_code":"PPL",
    "gn:name":"Bombongo",
    "gn:population":0,
    "gn:timezone":"Africa/Lubumbashi",
    "iso:country":"CD",
    "wof:name":"Bombongo",
    "wof:placetype":"locality"
},
  "geometry": {"coordinates":[25.34003,1.66494],"type":"Point"}
}