{
  "type": "Feature",
  "properties": {
    "gn:admin1_code":"23.0",
    "gn:asciiname":"Mulume-Mutshi",
    "gn:country_code":"CD",
    "gn:dem":814,
    "gn:feature_class":"P",
    "gn:feature_code":"PPL",
    "gn:name":"Mulume-Mutshi",
    "gn:population":0,
    "gn:timezone":"Africa/Lubumbashi",
    "iso:country":"CD",
    "wof:name":"Mulume-Mutshi",
    "wof:placetype":"locality"
},
  "geometry": {"coordinates":[23.08411,-6.41879],"type":"Point"}
}