{
  "type": "Feature",
  "properties": {
    "gn:admin1_code":"23.0",
    "gn:asciiname":"Beya-Nsamba",
    "gn:country_code":"CD",
    "gn:dem":776,
    "gn:feature_class":"P",
    "gn:feature_code":"PPL",
    "gn:name":"Beya-Nsamba",
    "gn:population":0,
    "gn:timezone":"Africa/Lubumbashi",
    "iso:country":"CD",
    "wof:name":"Beya-Nsamba",
    "wof:placetype":"locality"
},
  "geometry": {"coordinates":[22.96777,-6.12063],"type":"Point"}
}