{
  "type": "Feature",
  "properties": {
    "gn:admin1_code":"10.0",
    "gn:asciiname":"Mweho",
    "gn:country_code":"CD",
    "gn:dem":595,
    "gn:feature_class":"P",
    "gn:feature_code":"PPL",
    "gn:name":"Mweho",
    "gn:population":0,
    "gn:timezone":"Africa/Lubumbashi",
    "iso:country":"CD",
    "name:und_x_variant":[
        "Mweho Pene Kilala",
        "Mweho Kilala",
        "Mweho",
        "Pene-Kilala-Mweho"
    ],
    "wof:name":"Mweho",
    "wof:placetype":"locality"
},
  "geometry": {"coordinates":[26.80127,-4.99176],"type":"Point"}
}