{
  "type": "Feature",
  "properties": {
    "gn:admin1_code":"31.0",
    "gn:asciiname":"Lolingo",
    "gn:country_code":"CD",
    "gn:dem":436,
    "gn:feature_class":"P",
    "gn:feature_code":"PPL",
    "gn:name":"Lolingo",
    "gn:population":0,
    "gn:timezone":"Africa/Kinshasa",
    "iso:country":"CD",
    "wof:name":"Lolingo",
    "wof:placetype":"locality"
},
  "geometry": {"coordinates":[23.73333,-1.38333],"type":"Point"}
}