{
  "type": "Feature",
  "properties": {
    "gn:admin1_code":"14.0",
    "gn:asciiname":"Kibanana",
    "gn:country_code":"CD",
    "gn:dem":928,
    "gn:feature_class":"P",
    "gn:feature_code":"PPL",
    "gn:name":"Kibanana",
    "gn:population":0,
    "gn:timezone":"Africa/Lubumbashi",
    "iso:country":"CD",
    "wof:name":"Kibanana",
    "wof:placetype":"locality"
},
  "geometry": {"coordinates":[28.58333,-9.95],"type":"Point"}
}