{
  "type": "Feature",
  "properties": {
    "gn:admin1_code":"18.0",
    "gn:asciiname":"Buyamba",
    "gn:country_code":"CD",
    "gn:dem":547,
    "gn:feature_class":"P",
    "gn:feature_code":"PPL",
    "gn:name":"Buyamba",
    "gn:population":0,
    "gn:timezone":"Africa/Lubumbashi",
    "iso:country":"CD",
    "wof:name":"Buyamba",
    "wof:placetype":"locality"
},
  "geometry": {"coordinates":[21.33975,-4.72138],"type":"Point"}
}