{
  "type": "Feature",
  "properties": {
    "gn:admin1_code":"21.0",
    "gn:asciiname":"Kapabamba",
    "gn:country_code":"CD",
    "gn:dem":932,
    "gn:feature_class":"P",
    "gn:feature_code":"PPL",
    "gn:name":"Kapabamba",
    "gn:population":0,
    "gn:timezone":"Africa/Lubumbashi",
    "iso:country":"CD",
    "wof:name":"Kapabamba",
    "wof:placetype":"locality"
},
  "geometry": {"coordinates":[23.25281,-7.9528],"type":"Point"}
}