{
  "type": "Feature",
  "properties": {
    "gn:admin1_code":"16.0",
    "gn:asciiname":"Gatanga",
    "gn:country_code":"CD",
    "gn:dem":919,
    "gn:feature_class":"P",
    "gn:feature_code":"PPL",
    "gn:name":"Gatanga",
    "gn:population":0,
    "gn:timezone":"Africa/Lubumbashi",
    "iso:country":"CD",
    "wof:name":"Gatanga",
    "wof:placetype":"locality"
},
  "geometry": {"coordinates":[29.63653,3.16768],"type":"Point"}
}