{
  "type": "Feature",
  "properties": {
    "gn:admin1_code":"22.0",
    "gn:asciiname":"Katala",
    "gn:country_code":"CD",
    "gn:dem":974,
    "gn:feature_class":"P",
    "gn:feature_code":"PPL",
    "gn:name":"Katala",
    "gn:population":0,
    "gn:timezone":"Africa/Lubumbashi",
    "iso:country":"CD",
    "name:rus_x_preferred":[
        "\u041a\u0430\u0442\u0430\u043b\u0430"
    ],
    "name:ukr_x_preferred":[
        "\u041a\u0430\u0442\u0430\u043b\u0430"
    ],
    "wof:name":"Katala",
    "wof:placetype":"locality"
},
  "geometry": {"coordinates":[22.75698,-9.71352],"type":"Point"}
}