{
  "type": "Feature",
  "properties": {
    "gn:admin1_code":"18.0",
    "gn:asciiname":"Mulungu",
    "gn:country_code":"CD",
    "gn:dem":578,
    "gn:feature_class":"P",
    "gn:feature_code":"PPL",
    "gn:name":"Mulungu",
    "gn:population":0,
    "gn:timezone":"Africa/Lubumbashi",
    "iso:country":"CD",
    "name:ita_x_preferred":[
        "Mulungu"
    ],
    "name:lit_x_preferred":[
        "Mulungu"
    ],
    "name:swe_x_preferred":[
        "Mulungu"
    ],
    "wof:name":"Mulungu",
    "wof:placetype":"locality"
},
  "geometry": {"coordinates":[20.79995,-6.30471],"type":"Point"}
}