{
  "type": "Feature",
  "properties": {
    "gn:admin1_code":"19.0",
    "gn:asciiname":"Makua",
    "gn:country_code":"CD",
    "gn:dem":718,
    "gn:feature_class":"P",
    "gn:feature_code":"PPL",
    "gn:name":"Makua",
    "gn:population":0,
    "gn:timezone":"Africa/Kinshasa",
    "iso:country":"CD",
    "name:ceb_x_preferred":[
        "Makua"
    ],
    "name:deu_x_preferred":[
        "Makua"
    ],
    "name:fin_x_preferred":[
        "Makua"
    ],
    "name:fra_x_preferred":[
        "Makua"
    ],
    "wof:name":"Makua",
    "wof:placetype":"locality"
},
  "geometry": {"coordinates":[17.32214,-6.99935],"type":"Point"}
}