{
  "type": "Feature",
  "properties": {
    "gn:admin1_code":"19.0",
    "gn:asciiname":"Fangulu",
    "gn:country_code":"CD",
    "gn:dem":494,
    "gn:feature_class":"P",
    "gn:feature_code":"PPL",
    "gn:name":"Fangulu",
    "gn:population":0,
    "gn:timezone":"Africa/Kinshasa",
    "iso:country":"CD",
    "wof:name":"Fangulu",
    "wof:placetype":"locality"
},
  "geometry": {"coordinates":[16.89661,-4.37263],"type":"Point"}
}