{
  "type": "Feature",
  "properties": {
    "gn:admin1_code":"29.0",
    "gn:asciiname":"Mwale",
    "gn:country_code":"CD",
    "gn:dem":1597,
    "gn:feature_class":"P",
    "gn:feature_code":"PPL",
    "gn:name":"Mwale",
    "gn:population":0,
    "gn:timezone":"Africa/Lubumbashi",
    "iso:country":"CD",
    "wof:name":"Mwale",
    "wof:placetype":"locality"
},
  "geometry": {"coordinates":[29.11667000000001,-6.93333],"type":"Point"}
}