{
  "type": "Feature",
  "properties": {
    "gn:admin1_code":"24.0",
    "gn:asciiname":"Selenge",
    "gn:country_code":"CD",
    "gn:dem":303,
    "gn:feature_class":"P",
    "gn:feature_code":"PPL",
    "gn:name":"Selenge",
    "gn:population":0,
    "gn:timezone":"Africa/Kinshasa",
    "iso:country":"CD",
    "wof:name":"Selenge",
    "wof:placetype":"locality"
},
  "geometry": {"coordinates":[18.18351,-1.95273],"type":"Point"}
}