{
  "type": "Feature",
  "properties": {
    "gn:admin1_code":"29.0",
    "gn:asciiname":"Buki",
    "gn:country_code":"CD",
    "gn:dem":578,
    "gn:feature_class":"P",
    "gn:feature_code":"PPL",
    "gn:name":"Buki",
    "gn:population":0,
    "gn:timezone":"Africa/Lubumbashi",
    "iso:country":"CD",
    "name:bel_x_preferred":[
        "\u0411\u0443\u043a\u0456"
    ],
    "name:ceb_x_preferred":[
        "Buki"
    ],
    "name:deu_x_preferred":[
        "Buki"
    ],
    "name:hye_x_preferred":[
        "\u0532\u0578\u0582\u056f\u056b"
    ],
    "name:lav_x_preferred":[
        "Buki"
    ],
    "name:pol_x_preferred":[
        "Buki"
    ],
    "name:rus_x_preferred":[
        "\u0411\u0443\u043a\u0438"
    ],
    "name:ukr_x_preferred":[
        "\u0411\u0443\u043a\u0438"
    ],
    "wof:name":"Buki",
    "wof:placetype":"locality"
},
  "geometry": {"coordinates":[26.98333,-5.41667],"type":"Point"}
}