{
  "type": "Feature",
  "properties": {
    "gn:admin1_code":"17.0",
    "gn:asciiname":"Djakwa",
    "gn:country_code":"CD",
    "gn:dem":1703,
    "gn:feature_class":"P",
    "gn:feature_code":"PPL",
    "gn:name":"Djakwa",
    "gn:population":0,
    "gn:timezone":"Africa/Lubumbashi",
    "iso:country":"CD",
    "name:und_x_variant":[
        "Djukwa"
    ],
    "wof:name":"Djakwa",
    "wof:placetype":"locality"
},
  "geometry": {"coordinates":[30.59336,2.08518],"type":"Point"}
}