{
  "type": "Feature",
  "properties": {
    "gn:admin1_code":"22.0",
    "gn:asciiname":"Kayombo",
    "gn:country_code":"CD",
    "gn:dem":750,
    "gn:feature_class":"P",
    "gn:feature_code":"PPL",
    "gn:name":"Kayombo",
    "gn:population":0,
    "gn:timezone":"Africa/Lubumbashi",
    "iso:country":"CD",
    "name:und_x_variant":[
        "Kamalesu",
        "Kayombo"
    ],
    "wof:name":"Kayombo",
    "wof:placetype":"locality"
},
  "geometry": {"coordinates":[25.61884,-9.58147],"type":"Point"}
}