{
  "type": "Feature",
  "properties": {
    "gn:admin1_code":"23.0",
    "gn:asciiname":"Kadiata",
    "gn:country_code":"CD",
    "gn:dem":774,
    "gn:feature_class":"P",
    "gn:feature_code":"PPL",
    "gn:name":"Kadiata",
    "gn:population":0,
    "gn:timezone":"Africa/Lubumbashi",
    "iso:country":"CD",
    "wof:name":"Kadiata",
    "wof:placetype":"locality"
},
  "geometry": {"coordinates":[21.73107000000001,-6.7192],"type":"Point"}
}