{
  "type": "Feature",
  "properties": {
    "gn:admin1_code":"21.0",
    "gn:asciiname":"Luana",
    "gn:country_code":"CD",
    "gn:dem":896,
    "gn:feature_class":"P",
    "gn:feature_code":"PPL",
    "gn:name":"Luana",
    "gn:population":0,
    "gn:timezone":"Africa/Lubumbashi",
    "iso:country":"CD",
    "name:ceb_x_preferred":[
        "Luana"
    ],
    "name:deu_x_preferred":[
        "Luana"
    ],
    "name:ita_x_preferred":[
        "Luana"
    ],
    "name:swe_x_preferred":[
        "Luana"
    ],
    "wof:name":"Luana",
    "wof:placetype":"locality"
},
  "geometry": {"coordinates":[23.88437,-7.57348],"type":"Point"}
}