{
  "type": "Feature",
  "properties": {
    "gn:admin1_code":"23.0",
    "gn:asciiname":"Musashi",
    "gn:country_code":"CD",
    "gn:dem":839,
    "gn:feature_class":"P",
    "gn:feature_code":"PPL",
    "gn:name":"Musashi",
    "gn:population":0,
    "gn:timezone":"Africa/Lubumbashi",
    "iso:country":"CD",
    "name:bul_x_preferred":[
        "\u041c\u0443\u0441\u0430\u0448\u0438"
    ],
    "name:deu_x_preferred":[
        "Musashi"
    ],
    "name:epo_x_preferred":[
        "Musa\u015di"
    ],
    "name:fin_x_preferred":[
        "Musashi"
    ],
    "name:fra_x_preferred":[
        "Musashi"
    ],
    "name:hun_x_preferred":[
        "Muszasi"
    ],
    "name:ind_x_preferred":[
        "Musashi"
    ],
    "name:ita_x_preferred":[
        "Musashi"
    ],
    "name:kor_x_preferred":[
        "\ubb34\uc0ac\uc2dc"
    ],
    "name:lit_x_preferred":[
        "Musashi"
    ],
    "name:nld_x_preferred":[
        "Musashi"
    ],
    "name:pol_x_preferred":[
        "Musashi"
    ],
    "name:por_x_preferred":[
        "Musashi"
    ],
    "name:rus_x_preferred":[
        "\u041c\u0443\u0441\u0430\u0441\u0438"
    ],
    "name:spa_x_preferred":[
        "Musashi"
    ],
    "name:swe_x_preferred":[
        "Musashi"
    ],
    "wof:name":"Musashi",
    "wof:placetype":"locality"
},
  "geometry": {"coordinates":[22.16111,-7.24325],"type":"Point"}
}