{
  "type": "Feature",
  "properties": {
    "gn:admin1_code":"23.0",
    "gn:asciiname":"Musashi",
    "gn:country_code":"CD",
    "gn:dem":839,
    "gn:feature_class":"P",
    "gn:feature_code":"PPL",
    "gn:name":"Musashi",
    "gn:population":0,
    "gn:timezone":"Africa/Lubumbashi",
    "iso:country":"CD",
    "wof:name":"Musashi",
    "wof:placetype":"locality"
},
  "geometry": {"coordinates":[22.16111,-7.24325],"type":"Point"}
}