{
  "type": "Feature",
  "properties": {
    "gn:admin1_code":"16.0",
    "gn:asciiname":"Basebaba",
    "gn:country_code":"CD",
    "gn:dem":781,
    "gn:feature_class":"P",
    "gn:feature_code":"PPL",
    "gn:name":"Basebaba",
    "gn:population":0,
    "gn:timezone":"Africa/Lubumbashi",
    "iso:country":"CD",
    "wof:name":"Basebaba",
    "wof:placetype":"locality"
},
  "geometry": {"coordinates":[27.75931,2.18929],"type":"Point"}
}