{
  "type": "Feature",
  "properties": {
    "gn:admin1_code":"30.0",
    "gn:asciiname":"Yalikandja",
    "gn:country_code":"CD",
    "gn:dem":400,
    "gn:feature_class":"P",
    "gn:feature_code":"PPL",
    "gn:name":"Yalikandja",
    "gn:population":0,
    "gn:timezone":"Africa/Lubumbashi",
    "iso:country":"CD",
    "wof:name":"Yalikandja",
    "wof:placetype":"locality"
},
  "geometry": {"coordinates":[23.19273,2.02196],"type":"Point"}
}