{
  "type": "Feature",
  "properties": {
    "gn:admin1_code":"14.0",
    "gn:asciiname":"Mulemena",
    "gn:country_code":"CD",
    "gn:dem":1477,
    "gn:feature_class":"P",
    "gn:feature_code":"PPL",
    "gn:name":"Mulemena",
    "gn:population":0,
    "gn:timezone":"Africa/Lubumbashi",
    "iso:country":"CD",
    "wof:name":"Mulemena",
    "wof:placetype":"locality"
},
  "geometry": {"coordinates":[26.26951,-11.01411],"type":"Point"}
}