{
  "type": "Feature",
  "properties": {
    "gn:admin1_code":"25.0",
    "gn:asciiname":"Yangolu",
    "gn:country_code":"CD",
    "gn:dem":415,
    "gn:feature_class":"P",
    "gn:feature_code":"PPL",
    "gn:name":"Yangolu",
    "gn:population":0,
    "gn:timezone":"Africa/Kinshasa",
    "iso:country":"CD",
    "wof:name":"Yangolu",
    "wof:placetype":"locality"
},
  "geometry": {"coordinates":[22.09866,1.02962],"type":"Point"}
}