{
  "type": "Feature",
  "properties": {
    "gn:admin1_code":"14.0",
    "gn:asciiname":"Gumbo",
    "gn:country_code":"CD",
    "gn:dem":1184,
    "gn:feature_class":"P",
    "gn:feature_code":"PPL",
    "gn:name":"Gumbo",
    "gn:population":0,
    "gn:timezone":"Africa/Lubumbashi",
    "iso:country":"CD",
    "name:ara_x_preferred":[
        "\u062c\u0648\u0645\u0628\u0648"
    ],
    "name:ben_x_preferred":[
        "\u0997\u09be\u09ae\u09cd\u09ac\u09cb"
    ],
    "name:bre_x_preferred":[
        "Gombo"
    ],
    "name:bul_x_preferred":[
        "\u0413\u044a\u043c\u0431\u043e"
    ],
    "name:ces_x_preferred":[
        "Gumbo"
    ],
    "name:dan_x_preferred":[
        "Gumbo"
    ],
    "name:deu_x_preferred":[
        "Gumbo"
    ],
    "name:fas_x_preferred":[
        "\u06af\u0627\u0645\u0628\u0648"
    ],
    "name:fin_x_preferred":[
        "Gumbo"
    ],
    "name:fra_x_preferred":[
        "Gombo"
    ],
    "name:heb_x_preferred":[
        "\u05d2\u05de\u05d1\u05d5"
    ],
    "name:ind_x_preferred":[
        "Gumbo"
    ],
    "name:ita_x_preferred":[
        "Gumbo"
    ],
    "name:jpn_x_preferred":[
        "\u30ac\u30f3\u30dc"
    ],
    "name:lfn_x_preferred":[
        "Gombo"
    ],
    "name:new_x_preferred":[
        "\u0917\u092e\u094d\u092c\u094b"
    ],
    "name:nld_x_preferred":[
        "Gumbo"
    ],
    "name:nor_x_preferred":[
        "Gumbo"
    ],
    "name:pol_x_preferred":[
        "Gumbo"
    ],
    "name:por_x_preferred":[
        "Gumbo"
    ],
    "name:rus_x_preferred":[
        "\u0413\u0430\u043c\u0431\u043e"
    ],
    "name:spa_x_preferred":[
        "Gumbo"
    ],
    "name:swe_x_preferred":[
        "Gumbo"
    ],
    "name:zho_x_preferred":[
        "\u79cb\u8475\u6d53\u6c64"
    ],
    "wof:name":"Gumbo",
    "wof:placetype":"locality"
},
  "geometry": {"coordinates":[28.26667,-12.03333],"type":"Point"}
}