{
  "type": "Feature",
  "properties": {
    "gn:admin1_code":"14.0",
    "gn:asciiname":"Gumbo",
    "gn:country_code":"CD",
    "gn:dem":1184,
    "gn:feature_class":"P",
    "gn:feature_code":"PPL",
    "gn:name":"Gumbo",
    "gn:population":0,
    "gn:timezone":"Africa/Lubumbashi",
    "iso:country":"CD",
    "wof:name":"Gumbo",
    "wof:placetype":"locality"
},
  "geometry": {"coordinates":[28.26667,-12.03333],"type":"Point"}
}