{
  "type": "Feature",
  "properties": {
    "gn:admin1_code":"17.0",
    "gn:asciiname":"Ngaka",
    "gn:country_code":"CD",
    "gn:dem":912,
    "gn:feature_class":"P",
    "gn:feature_code":"PPL",
    "gn:name":"Ngaka",
    "gn:population":0,
    "gn:timezone":"Africa/Lubumbashi",
    "iso:country":"CD",
    "wof:name":"Ngaka",
    "wof:placetype":"locality"
},
  "geometry": {"coordinates":[29.2341,0.80369],"type":"Point"}
}