{
  "type": "Feature",
  "properties": {
    "gn:admin1_code":"18.0",
    "gn:asciiname":"Shakumbila",
    "gn:country_code":"CD",
    "gn:dem":670,
    "gn:feature_class":"P",
    "gn:feature_code":"PPL",
    "gn:name":"Shakumbila",
    "gn:population":0,
    "gn:timezone":"Africa/Lubumbashi",
    "iso:country":"CD",
    "wof:name":"Shakumbila",
    "wof:placetype":"locality"
},
  "geometry": {"coordinates":[20.20463,-6.24483],"type":"Point"}
}