{
  "type": "Feature",
  "properties": {
    "gn:admin1_code":"25.0",
    "gn:asciiname":"Yahamba",
    "gn:country_code":"CD",
    "gn:dem":365,
    "gn:feature_class":"P",
    "gn:feature_code":"PPL",
    "gn:name":"Yahamba",
    "gn:population":0,
    "gn:timezone":"Africa/Kinshasa",
    "iso:country":"CD",
    "wof:name":"Yahamba",
    "wof:placetype":"locality"
},
  "geometry": {"coordinates":[22.17221,2.27681],"type":"Point"}
}