{
  "type": "Feature",
  "properties": {
    "gn:admin1_code":"31.0",
    "gn:asciiname":"Inguo",
    "gn:country_code":"CD",
    "gn:dem":367,
    "gn:feature_class":"P",
    "gn:feature_code":"PPL",
    "gn:name":"Inguo",
    "gn:population":0,
    "gn:timezone":"Africa/Kinshasa",
    "iso:country":"CD",
    "wof:name":"Inguo",
    "wof:placetype":"locality"
},
  "geometry": {"coordinates":[22.15,-0.56667],"type":"Point"}
}