{
  "type": "Feature",
  "properties": {
    "gn:admin1_code":"16.0",
    "gn:asciiname":"Sondo",
    "gn:country_code":"CD",
    "gn:dem":802,
    "gn:feature_class":"P",
    "gn:feature_code":"PPL",
    "gn:name":"Sondo",
    "gn:population":0,
    "gn:timezone":"Africa/Lubumbashi",
    "iso:country":"CD",
    "wof:name":"Sondo",
    "wof:placetype":"locality"
},
  "geometry": {"coordinates":[28.17144,2.31612],"type":"Point"}
}