{
  "type": "Feature",
  "properties": {
    "gn:admin1_code":"28.0",
    "gn:asciiname":"Katako",
    "gn:country_code":"CD",
    "gn:dem":364,
    "gn:feature_class":"P",
    "gn:feature_code":"PPL",
    "gn:name":"Katako",
    "gn:population":0,
    "gn:timezone":"Africa/Kinshasa",
    "iso:country":"CD",
    "wof:name":"Katako",
    "wof:placetype":"locality"
},
  "geometry": {"coordinates":[18.71012,3.95264],"type":"Point"}
}