{
  "type": "Feature",
  "properties": {
    "gn:admin1_code":"16.0",
    "gn:asciiname":"Makpulu",
    "gn:country_code":"CD",
    "gn:dem":730,
    "gn:feature_class":"P",
    "gn:feature_code":"PPL",
    "gn:name":"Makpulu",
    "gn:population":0,
    "gn:timezone":"Africa/Lubumbashi",
    "iso:country":"CD",
    "wof:name":"Makpulu",
    "wof:placetype":"locality"
},
  "geometry": {"coordinates":[27.23703,2.49243],"type":"Point"}
}