{
  "type": "Feature",
  "properties": {
    "gn:admin1_code":"11.0",
    "gn:asciiname":"Katanda",
    "gn:country_code":"CD",
    "gn:dem":968,
    "gn:feature_class":"P",
    "gn:feature_code":"PPL",
    "gn:name":"Katanda",
    "gn:population":0,
    "gn:timezone":"Africa/Lubumbashi",
    "iso:country":"CD",
    "name:che_x_preferred":[
        "\u041a\u0430\u0442\u0430\u043d\u0434\u0430"
    ],
    "name:hye_x_preferred":[
        "\u053f\u0561\u057f\u0561\u0576\u0564\u0561"
    ],
    "name:rus_x_preferred":[
        "\u041a\u0430\u0442\u0430\u043d\u0434\u0430"
    ],
    "name:tat_x_preferred":[
        "\u041a\u0430\u0442\u0430\u043d\u0434\u0430"
    ],
    "name:ukr_x_preferred":[
        "\u041a\u0430\u0442\u0430\u043d\u0434\u0430"
    ],
    "name:und_x_variant":[
        "Katenda",
        "Katanda"
    ],
    "wof:name":"Katanda",
    "wof:placetype":"locality"
},
  "geometry": {"coordinates":[29.36451,-0.82535],"type":"Point"}
}