{
  "type": "Feature",
  "properties": {
    "gn:admin1_code":"23.0",
    "gn:asciiname":"Lukusa-Kasongo",
    "gn:country_code":"CD",
    "gn:dem":615,
    "gn:feature_class":"P",
    "gn:feature_code":"PPL",
    "gn:name":"Lukusa-Kasongo",
    "gn:population":0,
    "gn:timezone":"Africa/Lubumbashi",
    "iso:country":"CD",
    "wof:name":"Lukusa-Kasongo",
    "wof:placetype":"locality"
},
  "geometry": {"coordinates":[22.41356,-5.55013],"type":"Point"}
}