{
  "type": "Feature",
  "properties": {
    "gn:admin1_code":"25.0",
    "gn:asciiname":"Yambangia",
    "gn:country_code":"CD",
    "gn:dem":476,
    "gn:feature_class":"P",
    "gn:feature_code":"PPL",
    "gn:name":"Yambangia",
    "gn:population":0,
    "gn:timezone":"Africa/Kinshasa",
    "iso:country":"CD",
    "wof:name":"Yambangia",
    "wof:placetype":"locality"
},
  "geometry": {"coordinates":[21.74076,2.59315],"type":"Point"}
}