{
  "type": "Feature",
  "properties": {
    "gn:admin1_code":"8.0",
    "gn:asciiname":"Kakala",
    "gn:country_code":"CD",
    "gn:dem":479,
    "gn:feature_class":"P",
    "gn:feature_code":"PPL",
    "gn:name":"Kakala",
    "gn:population":0,
    "gn:timezone":"Africa/Kinshasa",
    "iso:country":"CD",
    "wof:name":"Kakala",
    "wof:placetype":"locality"
},
  "geometry": {"coordinates":[14.25581,-5.25331],"type":"Point"}
}