{
  "type": "Feature",
  "properties": {
    "gn:admin1_code":"8.0",
    "gn:asciiname":"Tshienda",
    "gn:country_code":"CD",
    "gn:dem":6,
    "gn:feature_class":"P",
    "gn:feature_code":"PPL",
    "gn:name":"Tshienda",
    "gn:population":0,
    "gn:timezone":"Africa/Kinshasa",
    "iso:country":"CD",
    "wof:name":"Tshienda",
    "wof:placetype":"locality"
},
  "geometry": {"coordinates":[12.24031,-5.79235],"type":"Point"}
}