{
  "type": "Feature",
  "properties": {
    "gn:admin1_code":"27.0",
    "gn:asciiname":"Djunganumbe",
    "gn:country_code":"CD",
    "gn:dem":654,
    "gn:feature_class":"P",
    "gn:feature_code":"PPL",
    "gn:name":"Djunganumbe",
    "gn:population":0,
    "gn:timezone":"Africa/Lubumbashi",
    "iso:country":"CD",
    "wof:name":"Djunganumbe",
    "wof:placetype":"locality"
},
  "geometry": {"coordinates":[24.52145,-4.52531],"type":"Point"}
}