{
  "type": "Feature",
  "properties": {
    "gn:admin1_code":"12.0",
    "gn:asciiname":"Keisha",
    "gn:country_code":"CD",
    "gn:dem":591,
    "gn:feature_class":"P",
    "gn:feature_code":"PPL",
    "gn:name":"Keisha",
    "gn:population":0,
    "gn:timezone":"Africa/Lubumbashi",
    "iso:country":"CD",
    "name:ita_x_preferred":[
        "Keisha"
    ],
    "wof:name":"Keisha",
    "wof:placetype":"locality"
},
  "geometry": {"coordinates":[27.30391,-2.60888],"type":"Point"}
}