{
  "type": "Feature",
  "properties": {
    "gn:admin1_code":"22.0",
    "gn:asciiname":"Kayongo",
    "gn:country_code":"CD",
    "gn:dem":898,
    "gn:feature_class":"P",
    "gn:feature_code":"PPL",
    "gn:name":"Kayongo",
    "gn:population":0,
    "gn:timezone":"Africa/Lubumbashi",
    "iso:country":"CD",
    "wof:name":"Kayongo",
    "wof:placetype":"locality"
},
  "geometry": {"coordinates":[21.95228,-7.7265],"type":"Point"}
}