{
  "type": "Feature",
  "properties": {
    "gn:admin1_code":"16.0",
    "gn:asciiname":"Ngilinga",
    "gn:country_code":"CD",
    "gn:dem":999,
    "gn:feature_class":"P",
    "gn:feature_code":"PPL",
    "gn:name":"Ngilinga",
    "gn:population":0,
    "gn:timezone":"Africa/Lubumbashi",
    "iso:country":"CD",
    "name:und_x_variant":[
        "Gilinga",
        "Ngilinga"
    ],
    "wof:name":"Ngilinga",
    "wof:placetype":"locality"
},
  "geometry": {"coordinates":[30.15,2.93333],"type":"Point"}
}