{
  "type": "Feature",
  "properties": {
    "gn:admin1_code":"28.0",
    "gn:asciiname":"Kpwole",
    "gn:country_code":"CD",
    "gn:dem":369,
    "gn:feature_class":"P",
    "gn:feature_code":"PPL",
    "gn:name":"Kpwole",
    "gn:population":0,
    "gn:timezone":"Africa/Kinshasa",
    "iso:country":"CD",
    "wof:name":"Kpwole",
    "wof:placetype":"locality"
},
  "geometry": {"coordinates":[18.70383,3.43195],"type":"Point"}
}