{
  "type": "Feature",
  "properties": {
    "gn:admin1_code":"8.0",
    "gn:asciiname":"Songololo",
    "gn:country_code":"CD",
    "gn:dem":566,
    "gn:feature_class":"P",
    "gn:feature_code":"PPL",
    "gn:name":"Songololo",
    "gn:population":0,
    "gn:timezone":"Africa/Kinshasa",
    "iso:country":"CD",
    "name:ceb_x_preferred":[
        "Songololo"
    ],
    "name:fra_x_preferred":[
        "Songololo"
    ],
    "name:ita_x_preferred":[
        "Songololo"
    ],
    "name:kat_x_preferred":[
        "\u10e1\u10dd\u10dc\u10d2\u10dd\u10da\u10dd\u10da\u10dd"
    ],
    "name:ron_x_preferred":[
        "Songololo"
    ],
    "name:rus_x_preferred":[
        "\u0421\u043e\u043d\u0433\u043e\u043b\u043e\u043b\u043e"
    ],
    "name:ukr_x_preferred":[
        "\u0421\u043e\u043d\u0433\u043e\u043b\u043e\u043b\u043e"
    ],
    "name:xmf_x_preferred":[
        "\u10e1\u10dd\u10dc\u10d2\u10dd\u10da\u10dd\u10da\u10dd"
    ],
    "wof:name":"Songololo",
    "wof:placetype":"locality"
},
  "geometry": {"coordinates":[15.01553,-5.06977],"type":"Point"}
}