{
  "type": "Feature",
  "properties": {
    "gn:admin1_code":"8.0",
    "gn:asciiname":"Songololo",
    "gn:country_code":"CD",
    "gn:dem":566,
    "gn:feature_class":"P",
    "gn:feature_code":"PPL",
    "gn:name":"Songololo",
    "gn:population":0,
    "gn:timezone":"Africa/Kinshasa",
    "iso:country":"CD",
    "wof:name":"Songololo",
    "wof:placetype":"locality"
},
  "geometry": {"coordinates":[15.01553,-5.06977],"type":"Point"}
}