{
  "type": "Feature",
  "properties": {
    "gn:admin1_code":"10.0",
    "gn:asciiname":"Olimba",
    "gn:country_code":"CD",
    "gn:dem":619,
    "gn:feature_class":"P",
    "gn:feature_code":"PPL",
    "gn:name":"Olimba",
    "gn:population":0,
    "gn:timezone":"Africa/Lubumbashi",
    "iso:country":"CD",
    "wof:name":"Olimba",
    "wof:placetype":"locality"
},
  "geometry": {"coordinates":[27.02823,-4.39283],"type":"Point"}
}