{
  "type": "Feature",
  "properties": {
    "gn:admin1_code":"19.0",
    "gn:asciiname":"Mosaka",
    "gn:country_code":"CD",
    "gn:dem":641,
    "gn:feature_class":"P",
    "gn:feature_code":"PPL",
    "gn:name":"Mosaka",
    "gn:population":0,
    "gn:timezone":"Africa/Kinshasa",
    "iso:country":"CD",
    "name:und_x_variant":[
        "Saka",
        "Mosaka"
    ],
    "wof:name":"Mosaka",
    "wof:placetype":"locality"
},
  "geometry": {"coordinates":[17.09035,-5.76583],"type":"Point"}
}