{
  "type": "Feature",
  "properties": {
    "gn:admin1_code":"28.0",
    "gn:asciiname":"Isato",
    "gn:country_code":"CD",
    "gn:dem":338,
    "gn:feature_class":"P",
    "gn:feature_code":"PPL",
    "gn:name":"Isato",
    "gn:population":0,
    "gn:timezone":"Africa/Kinshasa",
    "iso:country":"CD",
    "wof:name":"Isato",
    "wof:placetype":"locality"
},
  "geometry": {"coordinates":[18.64945,3.29372],"type":"Point"}
}