{
  "type": "Feature",
  "properties": {
    "gn:admin1_code":"12.0",
    "gn:asciiname":"Fizi",
    "gn:country_code":"CD",
    "gn:dem":1309,
    "gn:feature_class":"P",
    "gn:feature_code":"PPL",
    "gn:name":"Fizi",
    "gn:population":0,
    "gn:timezone":"Africa/Lubumbashi",
    "iso:country":"CD",
    "wof:name":"Fizi",
    "wof:placetype":"locality"
},
  "geometry": {"coordinates":[28.94197,-4.30241],"type":"Point"}
}