{
  "type": "Feature",
  "properties": {
    "gn:admin1_code":"8.0",
    "gn:asciiname":"Dunga",
    "gn:country_code":"CD",
    "gn:dem":564,
    "gn:feature_class":"P",
    "gn:feature_code":"PPL",
    "gn:name":"Dunga",
    "gn:population":0,
    "gn:timezone":"Africa/Kinshasa",
    "iso:country":"CD",
    "name:ara_x_preferred":[
        "\u062f\u0648\u0646\u063a\u0627"
    ],
    "name:azb_x_preferred":[
        "\u062f\u0648\u0646\u0642\u0627"
    ],
    "name:aze_x_preferred":[
        "Dunqa"
    ],
    "name:bel_x_preferred":[
        "\u0414\u0443\u043d\u0433\u0430"
    ],
    "name:ben_x_preferred":[
        "\u09a6\u09c1\u0999\u09cd\u0997\u09be"
    ],
    "name:bul_x_preferred":[
        "\u0414\u0443\u043d\u0433\u0430"
    ],
    "name:ces_x_preferred":[
        "Dunga"
    ],
    "name:cym_x_preferred":[
        "Dunga"
    ],
    "name:dan_x_preferred":[
        "Dunga"
    ],
    "name:deu_x_preferred":[
        "Dunga"
    ],
    "name:est_x_preferred":[
        "Dunga"
    ],
    "name:eus_x_preferred":[
        "Dunga"
    ],
    "name:fas_x_preferred":[
        "\u062f\u0648\u0646\u06af\u0627"
    ],
    "name:fin_x_preferred":[
        "Dunga"
    ],
    "name:fra_x_preferred":[
        "Dunga"
    ],
    "name:fry_x_preferred":[
        "Dunga"
    ],
    "name:heb_x_preferred":[
        "\u05d3\u05d5\u05e0\u05d2\u05d4"
    ],
    "name:hrv_x_preferred":[
        "Dunga"
    ],
    "name:hun_x_preferred":[
        "Dunga"
    ],
    "name:ido_x_preferred":[
        "Dunga"
    ],
    "name:ind_x_preferred":[
        "Dunga"
    ],
    "name:isl_x_preferred":[
        "Dunga"
    ],
    "name:ita_x_preferred":[
        "Dunga"
    ],
    "name:jpn_x_preferred":[
        "\u30c9\u30a5\u30f3\u30ac"
    ],
    "name:kat_x_preferred":[
        "\u10d3\u10e3\u10dc\u10d2\u10d0"
    ],
    "name:lat_x_preferred":[
        "Dunga"
    ],
    "name:lav_x_preferred":[
        "Dunga"
    ],
    "name:lit_x_preferred":[
        "Dunga"
    ],
    "name:mlg_x_preferred":[
        "Dunga"
    ],
    "name:msa_x_preferred":[
        "Dunga"
    ],
    "name:nld_x_preferred":[
        "Dunga"
    ],
    "name:nno_x_preferred":[
        "Carlos Dunga"
    ],
    "name:nor_x_preferred":[
        "Dunga"
    ],
    "name:pol_x_preferred":[
        "Dunga"
    ],
    "name:por_x_preferred":[
        "Dunga"
    ],
    "name:que_x_preferred":[
        "Dunga"
    ],
    "name:ron_x_preferred":[
        "Dunga"
    ],
    "name:rus_x_preferred":[
        "\u0414\u0443\u043d\u0433\u0430"
    ],
    "name:sco_x_preferred":[
        "Dunga"
    ],
    "name:slk_x_preferred":[
        "Dunga"
    ],
    "name:slv_x_preferred":[
        "Dunga"
    ],
    "name:spa_x_preferred":[
        "Dunga"
    ],
    "name:sqi_x_preferred":[
        "Dunga"
    ],
    "name:srp_x_preferred":[
        "\u041a\u0430\u0440\u043b\u043e\u0441 \u0414\u0443\u043d\u0433\u0430"
    ],
    "name:swe_x_preferred":[
        "Dunga"
    ],
    "name:tgk_x_preferred":[
        "\u0414\u0443\u043d\u0433\u0430"
    ],
    "name:tgl_x_preferred":[
        "Dunga"
    ],
    "name:tur_x_preferred":[
        "Dunga"
    ],
    "name:ukr_x_preferred":[
        "\u0414\u0443\u043d\u0433\u0430"
    ],
    "name:vie_x_preferred":[
        "Dunga"
    ],
    "wof:name":"Dunga",
    "wof:placetype":"locality"
},
  "geometry": {"coordinates":[14.02529,-4.66094],"type":"Point"}
}