{
  "type": "Feature",
  "properties": {
    "gn:admin1_code":"8.0",
    "gn:asciiname":"Dunga",
    "gn:country_code":"CD",
    "gn:dem":564,
    "gn:feature_class":"P",
    "gn:feature_code":"PPL",
    "gn:name":"Dunga",
    "gn:population":0,
    "gn:timezone":"Africa/Kinshasa",
    "iso:country":"CD",
    "wof:name":"Dunga",
    "wof:placetype":"locality"
},
  "geometry": {"coordinates":[14.02529,-4.66094],"type":"Point"}
}