{
  "type": "Feature",
  "properties": {
    "gn:admin1_code":"20.0",
    "gn:asciiname":"Utshimba",
    "gn:country_code":"CD",
    "gn:dem":574,
    "gn:feature_class":"P",
    "gn:feature_code":"PPL",
    "gn:name":"Utshimba",
    "gn:population":0,
    "gn:timezone":"Africa/Kinshasa",
    "iso:country":"CD",
    "wof:name":"Utshimba",
    "wof:placetype":"locality"
},
  "geometry": {"coordinates":[19.63954,-6.22321],"type":"Point"}
}