{
  "type": "Feature",
  "properties": {
    "gn:admin1_code":"20.0",
    "gn:asciiname":"Mbele",
    "gn:country_code":"CD",
    "gn:dem":771,
    "gn:feature_class":"P",
    "gn:feature_code":"PPL",
    "gn:name":"Mbele",
    "gn:population":0,
    "gn:timezone":"Africa/Kinshasa",
    "iso:country":"CD",
    "wof:name":"Mbele",
    "wof:placetype":"locality"
},
  "geometry": {"coordinates":[18.94523,-5.84972],"type":"Point"}
}