{
  "type": "Feature",
  "properties": {
    "gn:admin1_code":"23.0",
    "gn:asciiname":"Tshimpanga",
    "gn:country_code":"CD",
    "gn:dem":692,
    "gn:feature_class":"P",
    "gn:feature_code":"PPL",
    "gn:name":"Tshimpanga",
    "gn:population":0,
    "gn:timezone":"Africa/Lubumbashi",
    "iso:country":"CD",
    "wof:name":"Tshimpanga",
    "wof:placetype":"locality"
},
  "geometry": {"coordinates":[21.83376,-5.88417],"type":"Point"}
}