{
  "type": "Feature",
  "properties": {
    "gn:admin1_code":"20.0",
    "gn:asciiname":"Intshueme-Bantsana",
    "gn:country_code":"CD",
    "gn:dem":661,
    "gn:feature_class":"P",
    "gn:feature_code":"PPL",
    "gn:name":"Intshueme-Bantsana",
    "gn:population":0,
    "gn:timezone":"Africa/Kinshasa",
    "iso:country":"CD",
    "wof:name":"Intshueme-Bantsana",
    "wof:placetype":"locality"
},
  "geometry": {"coordinates":[19.51628,-5.0643],"type":"Point"}
}