{
  "type": "Feature",
  "properties": {
    "gn:admin1_code":"29.0",
    "gn:asciiname":"Katamba-Kazadi",
    "gn:country_code":"CD",
    "gn:dem":585,
    "gn:feature_class":"P",
    "gn:feature_code":"PPL",
    "gn:name":"Katamba-Kazadi",
    "gn:population":0,
    "gn:timezone":"Africa/Lubumbashi",
    "iso:country":"CD",
    "wof:name":"Katamba-Kazadi",
    "wof:placetype":"locality"
},
  "geometry": {"coordinates":[26.94621,-7.49937],"type":"Point"}
}