{
  "type": "Feature",
  "properties": {
    "gn:admin1_code":"6.0",
    "gn:asciiname":"Mfu",
    "gn:country_code":"CD",
    "gn:dem":697,
    "gn:feature_class":"P",
    "gn:feature_code":"PPL",
    "gn:name":"Mfu",
    "gn:population":0,
    "gn:timezone":"Africa/Kinshasa",
    "iso:country":"CD",
    "wof:name":"Mfu",
    "wof:placetype":"locality"
},
  "geometry": {"coordinates":[15.76075,-4.39552],"type":"Point"}
}