{
  "type": "Feature",
  "properties": {
    "gn:admin1_code":"31.0",
    "gn:asciiname":"Mange",
    "gn:country_code":"CD",
    "gn:dem":352,
    "gn:feature_class":"P",
    "gn:feature_code":"PPL",
    "gn:name":"Mange",
    "gn:population":0,
    "gn:timezone":"Africa/Kinshasa",
    "iso:country":"CD",
    "wof:name":"Mange",
    "wof:placetype":"locality"
},
  "geometry": {"coordinates":[20.44344,0.86178],"type":"Point"}
}