{
  "type": "Feature",
  "properties": {
    "gn:admin1_code":"11.0",
    "gn:asciiname":"Kuba",
    "gn:country_code":"CD",
    "gn:dem":665,
    "gn:feature_class":"P",
    "gn:feature_code":"PPL",
    "gn:name":"Kuba",
    "gn:population":0,
    "gn:timezone":"Africa/Lubumbashi",
    "iso:country":"CD",
    "wof:name":"Kuba",
    "wof:placetype":"locality"
},
  "geometry": {"coordinates":[27.63109,-1.22665],"type":"Point"}
}