{
  "type": "Feature",
  "properties": {
    "gn:admin1_code":"19.0",
    "gn:asciiname":"Kikawa",
    "gn:country_code":"CD",
    "gn:dem":800,
    "gn:feature_class":"P",
    "gn:feature_code":"PPL",
    "gn:name":"Kikawa",
    "gn:population":0,
    "gn:timezone":"Africa/Kinshasa",
    "iso:country":"CD",
    "wof:name":"Kikawa",
    "wof:placetype":"locality"
},
  "geometry": {"coordinates":[18.34804,-6.06854],"type":"Point"}
}