{
  "type": "Feature",
  "properties": {
    "gn:admin1_code":"13.0",
    "gn:asciiname":"Liwara",
    "gn:country_code":"CD",
    "gn:dem":686,
    "gn:feature_class":"P",
    "gn:feature_code":"PPL",
    "gn:name":"Liwara",
    "gn:population":0,
    "gn:timezone":"Africa/Lubumbashi",
    "iso:country":"CD",
    "wof:name":"Liwara",
    "wof:placetype":"locality"
},
  "geometry": {"coordinates":[27.02433,3.50591],"type":"Point"}
}