{
  "type": "Feature",
  "properties": {
    "gn:admin1_code":"14.0",
    "gn:asciiname":"Mutwale",
    "gn:country_code":"CD",
    "gn:dem":1127,
    "gn:feature_class":"P",
    "gn:feature_code":"PPL",
    "gn:name":"Mutwale",
    "gn:population":0,
    "gn:timezone":"Africa/Lubumbashi",
    "iso:country":"CD",
    "wof:name":"Mutwale",
    "wof:placetype":"locality"
},
  "geometry": {"coordinates":[27.98705,-11.82153],"type":"Point"}
}