{
  "type": "Feature",
  "properties": {
    "gn:admin1_code":"30.0",
    "gn:asciiname":"Yombo",
    "gn:country_code":"CD",
    "gn:dem":466,
    "gn:feature_class":"P",
    "gn:feature_code":"PPL",
    "gn:name":"Yombo",
    "gn:population":0,
    "gn:timezone":"Africa/Lubumbashi",
    "iso:country":"CD",
    "wof:name":"Yombo",
    "wof:placetype":"locality"
},
  "geometry": {"coordinates":[25.28333,-0.81667],"type":"Point"}
}