{
  "type": "Feature",
  "properties": {
    "gn:admin1_code":"30.0",
    "gn:asciiname":"Beikpo",
    "gn:country_code":"CD",
    "gn:dem":458,
    "gn:feature_class":"P",
    "gn:feature_code":"PPL",
    "gn:name":"Beikpo",
    "gn:population":0,
    "gn:timezone":"Africa/Lubumbashi",
    "iso:country":"CD",
    "wof:name":"Beikpo",
    "wof:placetype":"locality"
},
  "geometry": {"coordinates":[25.33727,2.1489],"type":"Point"}
}