{
  "type": "Feature",
  "properties": {
    "gn:admin1_code":"20.0",
    "gn:asciiname":"Mwenga",
    "gn:country_code":"CD",
    "gn:dem":658,
    "gn:feature_class":"P",
    "gn:feature_code":"PPL",
    "gn:name":"Mwenga",
    "gn:population":0,
    "gn:timezone":"Africa/Kinshasa",
    "iso:country":"CD",
    "wof:name":"Mwenga",
    "wof:placetype":"locality"
},
  "geometry": {"coordinates":[18.7682,-5.78057],"type":"Point"}
}