{
  "type": "Feature",
  "properties": {
    "gn:admin1_code":"23.0",
    "gn:asciiname":"Tshikula",
    "gn:country_code":"CD",
    "gn:dem":781,
    "gn:feature_class":"P",
    "gn:feature_code":"PPL",
    "gn:name":"Tshikula",
    "gn:population":0,
    "gn:timezone":"Africa/Lubumbashi",
    "iso:country":"CD",
    "wof:name":"Tshikula",
    "wof:placetype":"locality"
},
  "geometry": {"coordinates":[22.79585,-6.12064],"type":"Point"}
}