{
  "type": "Feature",
  "properties": {
    "gn:admin1_code":"21.0",
    "gn:asciiname":"Senge",
    "gn:country_code":"CD",
    "gn:dem":821,
    "gn:feature_class":"P",
    "gn:feature_code":"PPL",
    "gn:name":"Senge",
    "gn:population":0,
    "gn:timezone":"Africa/Lubumbashi",
    "iso:country":"CD",
    "wof:name":"Senge",
    "wof:placetype":"locality"
},
  "geometry": {"coordinates":[25.17585,-6.31785],"type":"Point"}
}