{
  "type": "Feature",
  "properties": {
    "gn:admin1_code":"20.0",
    "gn:asciiname":"Kingandu",
    "gn:country_code":"CD",
    "gn:dem":754,
    "gn:feature_class":"P",
    "gn:feature_code":"PPL",
    "gn:name":"Kingandu",
    "gn:population":0,
    "gn:timezone":"Africa/Kinshasa",
    "iso:country":"CD",
    "wof:name":"Kingandu",
    "wof:placetype":"locality"
},
  "geometry": {"coordinates":[18.46614,-5.74756],"type":"Point"}
}