{
  "type": "Feature",
  "properties": {
    "gn:admin1_code":"20.0",
    "gn:asciiname":"Kihutu",
    "gn:country_code":"CD",
    "gn:dem":550,
    "gn:feature_class":"P",
    "gn:feature_code":"PPL",
    "gn:name":"Kihutu",
    "gn:population":0,
    "gn:timezone":"Africa/Kinshasa",
    "iso:country":"CD",
    "wof:name":"Kihutu",
    "wof:placetype":"locality"
},
  "geometry": {"coordinates":[18.46297,-4.79179],"type":"Point"}
}