{
  "type": "Feature",
  "properties": {
    "gn:admin1_code":"23.0",
    "gn:asciiname":"Kangombe",
    "gn:country_code":"CD",
    "gn:dem":805,
    "gn:feature_class":"P",
    "gn:feature_code":"PPL",
    "gn:name":"Kangombe",
    "gn:population":0,
    "gn:timezone":"Africa/Lubumbashi",
    "iso:country":"CD",
    "wof:name":"Kangombe",
    "wof:placetype":"locality"
},
  "geometry": {"coordinates":[21.77218,-6.60451],"type":"Point"}
}