{
  "type": "Feature",
  "properties": {
    "gn:admin1_code":"22.0",
    "gn:asciiname":"Mpala-Katiaba",
    "gn:country_code":"CD",
    "gn:dem":1004,
    "gn:feature_class":"P",
    "gn:feature_code":"PPL",
    "gn:name":"Mpala-Katiaba",
    "gn:population":0,
    "gn:timezone":"Africa/Lubumbashi",
    "iso:country":"CD",
    "wof:name":"Mpala-Katiaba",
    "wof:placetype":"locality"
},
  "geometry": {"coordinates":[26.53333,-10.31667],"type":"Point"}
}