{
  "type": "Feature",
  "properties": {
    "gn:admin1_code":"24.0",
    "gn:asciiname":"Gongo-Mosengere",
    "gn:country_code":"CD",
    "gn:dem":316,
    "gn:feature_class":"P",
    "gn:feature_code":"PPL",
    "gn:name":"Gongo-Mosengere",
    "gn:population":0,
    "gn:timezone":"Africa/Kinshasa",
    "iso:country":"CD",
    "name:und_x_variant":[
        "Gongo",
        "Gongo Masengere",
        "Gongo-Mosengere"
    ],
    "wof:name":"Gongo-Mosengere",
    "wof:placetype":"locality"
},
  "geometry": {"coordinates":[17.95,-1.86667],"type":"Point"}
}