{
  "type": "Feature",
  "properties": {
    "gn:admin1_code":"23.0",
    "gn:asciiname":"Kambulu",
    "gn:country_code":"CD",
    "gn:dem":817,
    "gn:feature_class":"P",
    "gn:feature_code":"PPL",
    "gn:name":"Kambulu",
    "gn:population":0,
    "gn:timezone":"Africa/Lubumbashi",
    "iso:country":"CD",
    "wof:name":"Kambulu",
    "wof:placetype":"locality"
},
  "geometry": {"coordinates":[22.0173,-6.98228],"type":"Point"}
}