{
  "type": "Feature",
  "properties": {
    "gn:admin1_code":"23.0",
    "gn:asciiname":"Mwene Sanga",
    "gn:country_code":"CD",
    "gn:dem":878,
    "gn:feature_class":"P",
    "gn:feature_code":"PPL",
    "gn:name":"Mwene Sanga",
    "gn:population":0,
    "gn:timezone":"Africa/Lubumbashi",
    "iso:country":"CD",
    "wof:name":"Mwene Sanga",
    "wof:placetype":"locality"
},
  "geometry": {"coordinates":[23.19777,-7.24877],"type":"Point"}
}