{
  "type": "Feature",
  "properties": {
    "gn:admin1_code":"16.0",
    "gn:asciiname":"Gilima",
    "gn:country_code":"CD",
    "gn:dem":705,
    "gn:feature_class":"P",
    "gn:feature_code":"PPL",
    "gn:name":"Gilima",
    "gn:population":0,
    "gn:timezone":"Africa/Lubumbashi",
    "iso:country":"CD",
    "wof:name":"Gilima",
    "wof:placetype":"locality"
},
  "geometry": {"coordinates":[28.37566,3.90597],"type":"Point"}
}