{
  "type": "Feature",
  "properties": {
    "gn:admin1_code":"20.0",
    "gn:asciiname":"Malono",
    "gn:country_code":"CD",
    "gn:dem":399,
    "gn:feature_class":"P",
    "gn:feature_code":"PPL",
    "gn:name":"Malono",
    "gn:population":0,
    "gn:timezone":"Africa/Kinshasa",
    "iso:country":"CD",
    "wof:name":"Malono",
    "wof:placetype":"locality"
},
  "geometry": {"coordinates":[18.94042,-3.93339],"type":"Point"}
}