{
  "type": "Feature",
  "properties": {
    "gn:admin1_code":"10.0",
    "gn:asciiname":"Siku-Ya-Kufa",
    "gn:country_code":"CD",
    "gn:dem":940,
    "gn:feature_class":"P",
    "gn:feature_code":"PPL",
    "gn:name":"Siku-Ya-Kufa",
    "gn:population":0,
    "gn:timezone":"Africa/Lubumbashi",
    "iso:country":"CD",
    "wof:name":"Siku-Ya-Kufa",
    "wof:placetype":"locality"
},
  "geometry": {"coordinates":[27.87207,-4.97368],"type":"Point"}
}