{
  "type": "Feature",
  "properties": {
    "gn:admin1_code":"21.0",
    "gn:asciiname":"Koshi",
    "gn:country_code":"CD",
    "gn:dem":958,
    "gn:feature_class":"P",
    "gn:feature_code":"PPL",
    "gn:name":"Koshi",
    "gn:population":0,
    "gn:timezone":"Africa/Lubumbashi",
    "iso:country":"CD",
    "name:ceb_x_preferred":[
        "Koshi"
    ],
    "name:deu_x_preferred":[
        "Koshi"
    ],
    "name:fra_x_preferred":[
        "Koshi"
    ],
    "name:nld_x_preferred":[
        "Koshi"
    ],
    "name:swe_x_preferred":[
        "Koshi"
    ],
    "name:uzb_x_preferred":[
        "Koshi"
    ],
    "wof:name":"Koshi",
    "wof:placetype":"locality"
},
  "geometry": {"coordinates":[25.33027,-6.66338],"type":"Point"}
}