{
  "type": "Feature",
  "properties": {
    "gn:admin1_code":"15.0",
    "gn:asciiname":"Kambi",
    "gn:country_code":"CD",
    "gn:dem":942,
    "gn:feature_class":"P",
    "gn:feature_code":"PPL",
    "gn:name":"Kambi",
    "gn:population":0,
    "gn:timezone":"Africa/Lubumbashi",
    "iso:country":"CD",
    "name:ceb_x_preferred":[
        "Kambi"
    ],
    "name:est_x_preferred":[
        "Kambi"
    ],
    "name:swe_x_preferred":[
        "Kambi"
    ],
    "wof:name":"Kambi",
    "wof:placetype":"locality"
},
  "geometry": {"coordinates":[23.93731,-8.05652],"type":"Point"}
}