{
  "type": "Feature",
  "properties": {
    "gn:admin1_code":"26.0",
    "gn:asciiname":"Konia",
    "gn:country_code":"CD",
    "gn:dem":396,
    "gn:feature_class":"P",
    "gn:feature_code":"PPL",
    "gn:name":"Konia",
    "gn:population":0,
    "gn:timezone":"Africa/Kinshasa",
    "iso:country":"CD",
    "wof:name":"Konia",
    "wof:placetype":"locality"
},
  "geometry": {"coordinates":[20.57678,3.85012],"type":"Point"}
}