{
  "type": "Feature",
  "properties": {
    "gn:admin1_code":"19.0",
    "gn:asciiname":"Shapango",
    "gn:country_code":"CD",
    "gn:dem":1072,
    "gn:feature_class":"P",
    "gn:feature_code":"PPL",
    "gn:name":"Shapango",
    "gn:population":0,
    "gn:timezone":"Africa/Kinshasa",
    "iso:country":"CD",
    "wof:name":"Shapango",
    "wof:placetype":"locality"
},
  "geometry": {"coordinates":[18.51798,-7.12371],"type":"Point"}
}