{
  "type": "Feature",
  "properties": {
    "gn:admin1_code":"10.0",
    "gn:asciiname":"Malela-Mukubwa I",
    "gn:country_code":"CD",
    "gn:dem":554,
    "gn:feature_class":"P",
    "gn:feature_code":"PPL",
    "gn:name":"Malela-Mukubwa I",
    "gn:population":0,
    "gn:timezone":"Africa/Lubumbashi",
    "iso:country":"CD",
    "wof:name":"Malela-Mukubwa I",
    "wof:placetype":"locality"
},
  "geometry": {"coordinates":[26.41667,-1.58333],"type":"Point"}
}