{
  "type": "Feature",
  "properties": {
    "gn:admin1_code":"19.0",
    "gn:asciiname":"Banza-Kifulu",
    "gn:country_code":"CD",
    "gn:dem":787,
    "gn:feature_class":"P",
    "gn:feature_code":"PPL",
    "gn:name":"Banza-Kifulu",
    "gn:population":0,
    "gn:timezone":"Africa/Kinshasa",
    "iso:country":"CD",
    "wof:name":"Banza-Kifulu",
    "wof:placetype":"locality"
},
  "geometry": {"coordinates":[18.05958,-5.78727],"type":"Point"}
}