{
  "type": "Feature",
  "properties": {
    "gn:admin1_code":"19.0",
    "gn:asciiname":"Mwa-Mushiko",
    "gn:country_code":"CD",
    "gn:dem":955,
    "gn:feature_class":"P",
    "gn:feature_code":"PPL",
    "gn:name":"Mwa-Mushiko",
    "gn:population":0,
    "gn:timezone":"Africa/Kinshasa",
    "iso:country":"CD",
    "wof:name":"Mwa-Mushiko",
    "wof:placetype":"locality"
},
  "geometry": {"coordinates":[19.49187,-7.18469],"type":"Point"}
}