{
  "type": "Feature",
  "properties": {
    "gn:admin1_code":"8.0",
    "gn:asciiname":"Zamba",
    "gn:country_code":"CD",
    "gn:dem":552,
    "gn:feature_class":"P",
    "gn:feature_code":"PPL",
    "gn:name":"Zamba",
    "gn:population":0,
    "gn:timezone":"Africa/Kinshasa",
    "iso:country":"CD",
    "name:ceb_x_preferred":[
        "Zamba"
    ],
    "name:swe_x_preferred":[
        "Zamba"
    ],
    "wof:name":"Zamba",
    "wof:placetype":"locality"
},
  "geometry": {"coordinates":[15.39313,-5.05789],"type":"Point"}
}