{
  "type": "Feature",
  "properties": {
    "gn:admin1_code":"30.0",
    "gn:asciiname":"Matshitshi",
    "gn:country_code":"CD",
    "gn:dem":750,
    "gn:feature_class":"P",
    "gn:feature_code":"PPL",
    "gn:name":"Matshitshi",
    "gn:population":0,
    "gn:timezone":"Africa/Lubumbashi",
    "iso:country":"CD",
    "name:und_x_variant":[
        "Matsmitsmi"
    ],
    "wof:name":"Matshitshi",
    "wof:placetype":"locality"
},
  "geometry": {"coordinates":[27.73608,-0.2311],"type":"Point"}
}